Workbook

Sheet Cockpit
A1: COCKPIT · ATTERRISSAGE 2026
A2: Point de départ du budget 2027 · réalisé 2024-2025, atterrissage 2026 · commercial + financier, un seul écran
A4: Chiffre d'affaires 2026 | C4: EBITDA 2026 | E4: Marge EBITDA 2026
A5: =Données!B7 | C5: =Données!C7 | E5: =Données!C7/Données!B7
A7: KPI | B7: 2024 réalisé | C7: 2025 réalisé | D7: 2026 atterrissage | E7: YoY 25→26
A8: FINANCE
A9: Chiffre d'affaires (€) | B9: =Données!B5 | C9: =Données!B6 | D9: =Données!B7 | E9: =D9/C9-1
A10: EBITDA (€) | B10: =Données!C5 | C10: =Données!C6 | D10: =Données!C7 | E10: =D10/C10-1
A11: Marge EBITDA % | B11: =Données!C5/Données!B5 | C11: =Données!C6/Données!B6 | D11: =Données!C7/Données!B7 | E11: =D11-C11
A12: COMMERCIAL
A13: Leads | B13: =Données!D5 | C13: =Données!D6 | D13: =Données!D7 | E13: =D13/C13-1
A14: Inscrits | B14: =Données!E5 | C14: =Données!E6 | D14: =Données!E7 | E14: =D14/C14-1
A15: CAC (€/inscrit) | B15: =Données!F5/Données!E5 | C15: =Données!F6/Données!E6 | D15: =Données!F7/Données!E7 | E15: =D15/C15-1
A16: CAC = seul KPI en tension : le coût d'acquisition monte plus vite que le volume. C'est ce qu'on ira traiter dans le budget 2027.
A18: TENSION — base 100 en 2024 : activité (CA) vs dépenses d'acquisition
A19: Année | B19: 2024 | C19: 2025 | D19: 2026
A20: Activité (CA) | B20: =Données!B5/Données!B5*100 | C20: =Données!B6/Données!B5*100 | D20: =Données!B7/Données!B5*100
A21: Dépenses acq. | B21: =Données!F5/Données!F5*100 | C21: =Données!F6/Données!F5*100 | D21: =Données!F7/Données!F5*100
A23: Message : commercial ET financier sur un écran. On progresse (CA/EBITDA), mais le CAC se dégrade -> le budget 2027 doit répondre à ça.

Sheet Données
A1: DONNÉES — agrégats annuels groupe (source : compta produits + socle CRM)
A2: 2024-2025 réalisé · 2026 atterrissage. Bleu = donnée.
A4: Exercice | B4: CA | C4: EBITDA | D4: Leads | E4: Inscrits | F4: Dépense acq.
A5: 2024 | B5: 20064725 | C5: 2648550 | D5: 15305 | E5: 1092 | F5: 358819
A6: 2025 | B6: 21268606 | C6: 2977604 | D6: 16226 | E6: 1159 | F6: 394702
A7: 2026 | B7: 22544725 | C7: 3291530 | D7: 17197 | E7: 1229 | F7: 434174
