Workbook

Sheet Histoire
A1: EDUSERVICES · BUDGET 2027 — l'Acte 1, du chargement au diagnostic
A2: Le fil : on POSE (un seul écran, le cockpit), puis on CREUSE (à la demande). Rien n'est affiché en bloc.
A3: Vocabulaire : 2024-2025 réalisé · 2026 atterrissage (estimé) · 2027 budget (à construire).
A5: # | B5: Ce qu'on FAIT | C5: Ce qu'on AFFICHE | D5: Ce qu'on DIT | E5: Drill / suite
A6: 0 | B6: Chargement compta + CRM | C6: (transition, pas d'écran) | D6: « Deux mondes — finance et commercial — entrent sans friction dans le même modèle. » | E6: → le cockpit
A7: 1 | B7: On POSE l'état + la tension | C7: COCKPIT d'atterrissage 2026 : bandeau CA/EBITDA/Marge + 6 tuiles KPI (finance & commercial) + 1 graphe de tension | D7: « Voilà où on en est : on progresse partout… sauf un point, le coût d'acquisition se dégrade. C'est le départ du budget 2027. » | E7: clic tuile CAC → Diagnostic
A8: 2 | B8: On CREUSE le CAC | C8: DIAGNOSTIC CAC : funnel (taux de passage) + CAC par marque (Tunon 564 €) | D8: « Le CAC n'est pas une fatalité : c'est un taux de conversion. On sait où agir — Tunon en priorité. » | E8: clic marque → funnel campus ; puis → construction 2027
A9: ~ | B9: Pilotage complémentaire | C9: STRUCTURE & MIX : mix initiale/alternance (OPCO) + CA par marque | D9: « Attention : 3 marques sont 100 % financées par l'OPCO — dépendance à surveiller. » | E9: rapport à part (pas dans le flux d'accueil)
A10: → | B10: On construit | C10: (Acte 2 — cadrage, moteur, scénarios) | D10: « Maintenant qu'on sait d'où on part et où ça tire, on construit le budget 2027. » | E10: suite de la démo
A12: Point clé : après le chargement, on n'affiche QUE le cockpit. Le Diagnostic et le Structure&Mix s'ouvrent APRÈS, quand on creuse.

Sheet Cockpit
A1: COCKPIT · ATTERRISSAGE 2026
A2: Point de départ du budget 2027 · réalisé 2024-2025, atterrissage 2026 · commercial + financier, un seul écran
A4: Chiffre d'affaires 2026 | C4: EBITDA 2026 | E4: Marge EBITDA 2026
A5: =Données!B7 | C5: =Données!C7 | E5: =Données!C7/Données!B7
A7: KPI | B7: 2024 réalisé | C7: 2025 réalisé | D7: 2026 atterrissage | E7: YoY 25→26 | F7: sens
A8: FINANCE
A9: Chiffre d'affaires (€) | B9: =Données!B5 | C9: =Données!B6 | D9: =Données!B7 | E9: =D9/C9-1 | F9: bon sens
A10: EBITDA (€) | B10: =Données!C5 | C10: =Données!C6 | D10: =Données!C7 | E10: =D10/C10-1 | F10: bon sens
A11: Marge EBITDA % | B11: =Données!C5/Données!B5 | C11: =Données!C6/Données!B6 | D11: =Données!C7/Données!B7 | E11: =D11-C11 | F11: bon sens
A12: COMMERCIAL
A13: Leads | B13: =Données!D5 | C13: =Données!D6 | D13: =Données!D7 | E13: =D13/C13-1 | F13: bon sens
A14: Inscrits | B14: =Données!E5 | C14: =Données!E6 | D14: =Données!E7 | E14: =D14/C14-1 | F14: bon sens
A15: CAC (€/inscrit) | B15: =Données!F5/Données!E5 | C15: =Données!F6/Données!E6 | D15: =Données!F7/Données!E7 | E15: =D15/C15-1 | F15: à surveiller
A16: CAC = seul KPI en tension : le coût d'acquisition monte plus vite que le volume. C'est ce que le budget 2027 doit corriger.
A18: TENSION — base 100 en 2024
A19: Année | B19: 2024 | C19: 2025 | D19: 2026
A20: Activité (CA) | B20: =Données!B5/Données!B5*100 | C20: =Données!B6/Données!B5*100 | D20: =Données!B7/Données!B5*100
A21: Dépenses acq. | B21: =Données!F5/Données!F5*100 | C21: =Données!F6/Données!F5*100 | D21: =Données!F7/Données!F5*100
A23: L'écart entre les 2 courbes = la dégradation du CAC → ce que le budget 2027 doit corriger. Clic tuile CAC → Diagnostic.

Sheet Diagnostic CAC
A1: DIAGNOSTIC CAC · pourquoi le coût d'acquisition se dégrade · 2026
A2: 1er drill depuis la tuile CAC du cockpit. Le funnel explique COMMENT ; le CAC par marque dit OÙ agir.
A4: Funnel de conversion (groupe)
A5: Étape | B5: Volume | C5: Taux de passage
A6: Leads | B6: 17197
A7: Candidatures | B7: 3720 | C7: =B7/B6
A8: Admis | B8: 2623 | C8: =B8/B7
A9: Inscrits | B9: 1229 | C9: =B9/B8
A10: Global lead → inscrit | C10: =B9/B6
A13: CAC par marque — où le coût dérape
A14: Marque | B14: Dépense acq. | C14: Inscrits | D14: CAC (€/inscrit)
A15: MBway | B15: 166530 | C15: 510 | D15: =B15/C15
A16: ISCOM | B16: 108103 | C16: 338 | D16: =B16/C16
A17: IPAC | B17: 51871 | C17: 130 | D17: =B17/C17
A18: Pigier | B18: 58580 | C18: 164 | D18: =B18/C18
A19: Tunon | B19: 49090 | C19: 87 | D19: =B19/C19 | E19: ◄ 1,7× la moyenne
A21: Le funnel dit COMMENT (taux) ; le CAC par marque dit OÙ agir → Tunon en priorité. Clic marque → funnel du campus.

Sheet Structure & Mix
A1: STRUCTURE & MIX DE FINANCEMENT · 2026
A2: Ce que le CRM ne montre pas : la dépendance à l'alternance (OPCO). Vraie question DAF — risque réglementaire.
A4: Mix scolarité : initiale vs alternance (OPCO), par marque
A5: Marque | B5: Initiale (706) | C5: Alternance (7062) | D5: % alternance
A6: MBway | B6: 1995975 | C6: 7525580 | D6: =C6/(B6+C6)
A7: ISCOM | B7: 1310700 | C7: 4951430 | D7: =C7/(B7+C7)
A8: IPAC | B8: 0 | C8: 2571100 | D8: =C8/(B8+C8) | E8: 100 % OPCO
A9: Pigier | B9: 0 | C9: 2137460 | D9: =C9/(B9+C9) | E9: 100 % OPCO
A10: Tunon | B10: 0 | C10: 1941870 | D10: =C10/(B10+C10) | E10: 100 % OPCO
A13: CA total par marque — concentration
A14: Marque | B14: CA total
A15: MBway | B15: 9567455
A16: ISCOM | B16: 6292550
A17: IPAC | B17: 2582800
A18: Pigier | B18: 2152220
A19: Tunon | B19: 1949700
A21: INSIGHT DAF : groupe massivement financé par l'alternance (OPCO). MBway/ISCOM ~79%, les 3 autres 100%. Dépendance à surveiller.

Sheet Données
A1: DONNÉES — agrégats annuels groupe (compta produits + socle CRM)
A2: 2024-2025 réalisé · 2026 atterrissage. Bleu = donnée.
A4: Exercice | B4: CA | C4: EBITDA | D4: Leads | E4: Inscrits | F4: Dépense acq.
A5: 2024 | B5: 20064725 | C5: 2648550 | D5: 15305 | E5: 1092 | F5: 358819
A6: 2025 | B6: 21268606 | C6: 2977604 | D6: 16226 | E6: 1159 | F6: 394702
A7: 2026 | B7: 22544725 | C7: 3291530 | D7: 17197 | E7: 1229 | F7: 434174
