Workbook

Sheet Lisez-moi
A1: MAQUETTES DE RAPPORTS · Actes 1 & 2 · EDUSERVICES 2027
A2: Rendu cible pour la restitution Tagetik. Chaque rapport indique la vue qui l'alimente et ce qui reste à construire.
A5: RAPPORT | B5: SOURCE / À CONSTRUIRE
A6: Cockpit d'ouverture | B6: V_COCKPIT (cross-source CRM+compta) + 2 drill-through Constitution du CA. Maquette visuelle déjà livrée (artifact).
A7: P&L ① (feuille « P&L ① ») | B7: FST natif 010-EBITDA sur V_PNL. Hiérarchie Compte fournie (MAPPING_COMPTES.csv). Colonne 2027 → P&L ②③④.
A8: Funnel & CAC (feuille) | B8: Matrice multidim sur V_FUNNEL + V_CAC (refaites plates + additives). Un seul rapport. Rien de plus à construire côté SQL.
A10: NAVIGATION (drill-through vs hyperlink)
A11: Cockpit · tuile CA | B11: → drill-through ×2 : Constitution du CA (CRM ‖ Compta)
A12: Cockpit · tuile EBITDA / Marge | B12: → hyperlink : Rapport P&L ① (POV groupe)
A13: Cockpit · tuile CAC | B13: → hyperlink : Rapport Funnel & CAC (POV groupe)
A14: P&L ① · ligne marque | B14: → hyperlink : P&L au POV marque → campus
A15: Funnel & CAC · cellule campus | B15: → hyperlink : funnel du campus
A17: LÉGENDE | B17: Bleu = donnée saisie (image de la vue) · Noir = formule · Vert teal = sous-total / EBITDA · Ochre = point de tension

Sheet Données P&L
A1: DONNÉES · image de la vue V_PNL (VERSION = ACT, réel 2024-2026)
A2: Grain compte × exercice. Sur Tagetik, ces montants viennent de la dimension Compte ; les nœuds SIG et l'EBITDA sont remontés par le FST.
A4: Compte | B4: Libellé | C4: Nœud P&L (FST) | D4: Rôle allocation | E4: 2024 | F4: 2025 | G4: 2026
A5: 706 | B5: Prestations de formation - scolarité (initial) | C5: PRODUITS | D5: PRODUIT | E5: 2942930 | F5: 3119504 | G5: 3306675
A6: 7062 | B6: Prestations de formation - alternance (OPCO) | C6: PRODUITS | D6: PRODUIT | E6: 17023353 | F6: 18044754 | G6: 19127440
A7: 708 | B7: Frais de dossier & droits d'inscription | C7: PRODUITS | D7: PRODUIT | E7: 98442 | F7: 104348 | G7: 110610
A8: 604 | B8: Sous-traitance pédagogique | C8: COUTS_DIRECTS | D8: DIRECT | E8: 618583 | F8: 646928 | G8: 677808
A9: 6063 | B9: Fournitures pédagogiques & petit équipement | C9: COUTS_DIRECTS | D9: DIRECT | E9: 412387 | F9: 431286 | G9: 451874
A10: 621 | B10: Personnel extérieur - vacataires | C10: COUTS_DIRECTS | D10: DIRECT | E10: 1443361 | F10: 1509499 | G10: 1581554
A11: 6231 | B11: Publicité & marketing d'acquisition | C11: COUTS_DIRECTS | D11: DIRECT | E11: 358819 | F11: 394702 | G11: 434174
A12: 6411 | B12: Rémunération enseignants permanents | C12: PERSONNEL | D12: DIRECT | E12: 3505311 | F12: 3665931 | G12: 3840917
A13: 6413 | B13: Rémunération personnel administratif | C13: PERSONNEL | D13: STRUCT_CAMP | E13: 1855752 | F13: 1940786 | G13: 2033426
A14: 6414 | B14: Rémunération direction & siège | C14: PERSONNEL | D14: HOLDING | E14: 1134071 | F14: 1186037 | G14: 1242649
A15: 645 | B15: Charges sociales & prévoyance | C15: PERSONNEL | D15: STRUCT_CAMP | E15: 2886726 | F15: 3019002 | G15: 3163106
A16: 613 | B16: Loyers & charges locatives | C16: STRUCTURE | D16: STRUCT_CAMP | E16: 2165045 | F16: 2264254 | G16: 2372329
... A27: 6811 | B27: Dotations aux amortissements | C27: DOTATIONS | D27: DOTATION | E27: 1203886 | F27: 1276115 | G27: 1352683

Sheet P&L ①
A1: RAPPORT P&L ① · Compte de résultat comparatif
A2: Cible du hyperlink depuis la tuile EBITDA du cockpit · POV = Groupe · réel 2024-2026
A3: SOURCE : FST natif Tagetik (010-EBITDA) sur V_PNL. Ici reproduit par formules SUMIFS sur la feuille « Données P&L ».
A5: en € | B5: 2024 | C5: 2025 | D5: 2026 | E5: Δ 25→26
A6: PRODUITS | B6: =SUMIFS('Données P&L'!$E$5:$E$27,'Données P&L'!$C$5:$C$27,"PRODUITS") | C6: =SUMIFS('Données P&L'!$F$5:$F$27,'Données P&L'!$C$5:$C$27,"PRODUITS") | D6: =SUMIFS('Données P&L'!$G$5:$G$27,'Données P&L'!$C$5:$C$27,"PRODUITS") | E6: =IFERROR((G6-F6)/F6,0)
A7: Coûts directs | B7: =-SUMIFS('Données P&L'!$E$5:$E$27,'Données P&L'!$C$5:$C$27,"COUTS_DIRECTS") | C7: =-SUMIFS('Données P&L'!$F$5:$F$27,'Données P&L'!$C$5:$C$27,"COUTS_DIRECTS") | D7: =-SUMIFS('Données P&L'!$G$5:$G$27,'Données P&L'!$C$5:$C$27,"COUTS_DIRECTS") | E7: =IFERROR((G7-F7)/F7,0)
A8: Personnel | B8: =-SUMIFS('Données P&L'!$E$5:$E$27,'Données P&L'!$C$5:$C$27,"PERSONNEL") | C8: =-SUMIFS('Données P&L'!$F$5:$F$27,'Données P&L'!$C$5:$C$27,"PERSONNEL") | D8: =-SUMIFS('Données P&L'!$G$5:$G$27,'Données P&L'!$C$5:$C$27,"PERSONNEL") | E8: =IFERROR((G8-F8)/F8,0)
A9: Structure | B9: =-SUMIFS('Données P&L'!$E$5:$E$27,'Données P&L'!$C$5:$C$27,"STRUCTURE") | C9: =-SUMIFS('Données P&L'!$F$5:$F$27,'Données P&L'!$C$5:$C$27,"STRUCTURE") | D9: =-SUMIFS('Données P&L'!$G$5:$G$27,'Données P&L'!$C$5:$C$27,"STRUCTURE") | E9: =IFERROR((G9-F9)/F9,0)
A10: Impôts & taxes | B10: =-SUMIFS('Données P&L'!$E$5:$E$27,'Données P&L'!$C$5:$C$27,"IMPOTS_TAXES") | C10: =-SUMIFS('Données P&L'!$F$5:$F$27,'Données P&L'!$C$5:$C$27,"IMPOTS_TAXES") | D10: =-SUMIFS('Données P&L'!$G$5:$G$27,'Données P&L'!$C$5:$C$27,"IMPOTS_TAXES") | E10: =IFERROR((G10-F10)/F10,0)
A11: EBITDA | B11: =B6+SUM(B7:B10) | C11: =C6+SUM(C7:C10) | D11: =D6+SUM(D7:D10) | E11: =IFERROR((G11-F11)/F11,0)
A12: Dotations (D&A) | B12: =-SUMIFS('Données P&L'!$E$5:$E$27,'Données P&L'!$C$5:$C$27,"DOTATIONS") | C12: =-SUMIFS('Données P&L'!$F$5:$F$27,'Données P&L'!$C$5:$C$27,"DOTATIONS") | D12: =-SUMIFS('Données P&L'!$G$5:$G$27,'Données P&L'!$C$5:$C$27,"DOTATIONS") | E12: =IFERROR((G12-F12)/F12,0)
A13: RÉSULTAT D'EXPLOITATION | B13: =B11+B12 | C13: =C11+C12 | D13: =D11+D12 | E13: =IFERROR((G13-F13)/F13,0)
A14: Marge EBITDA % | B14: =B11/B6 | C14: =C11/C6 | D14: =D11/D6 | E14: =G14-F14
A16: Contrôle : EBITDA 2024/25/26 = 2 648 550 / 2 977 604 / 3 291 530 · drill possible : PRODUITS → 2 drill-through Constitution du CA (CRM ‖ Compta).
A17: À reproduire nativement : hiérarchie Compte + FST EBITDA. Colonne 2027 (V01/V02/V03) s'ajoute aux P&L ②③④.

Sheet Données CRM
A1: DONNÉES · image des vues V_FUNNEL + V_CAC (socle CRM)
A2: Grain marque × exercice (mesures additives). Sur Tagetik, maille fine campus/programme/cycle/modalité — les taux, CPL et CAC se calculent dans la matrice.
A4: Exercice | B4: Marque | C4: Leads | D4: Candidats | E4: Admis | F4: Inscrits | G4: Leads payants | H4: Dépense acq. (€)
A5: 2024 | B5: MBWAY | C5: 5736 | D5: 1298 | E5: 920 | F5: 452 | G5: 3326 | H5: 137627
A6: 2024 | B6: ISCOM | C6: 3794 | D6: 857 | E6: 608 | F6: 300 | G6: 2132 | H6: 89342
A7: 2024 | B7: IPAC | C7: 1966 | D7: 393 | E7: 276 | F7: 116 | G7: 1237 | H7: 42867
A8: 2024 | B8: PIGIER | C8: 2492 | D8: 498 | E8: 350 | F8: 146 | G8: 1293 | H8: 48413
A9: 2024 | B9: TUNON | C9: 1317 | D9: 263 | E9: 185 | F9: 78 | G9: 909 | H9: 40570
A10: 2025 | B10: MBWAY | C10: 6079 | D10: 1374 | E10: 973 | F10: 482 | G10: 3487 | H10: 151390
A11: 2025 | B11: ISCOM | C11: 4022 | D11: 909 | E11: 644 | F11: 318 | G11: 2233 | H11: 98275
A12: 2025 | B12: IPAC | C12: 2086 | D12: 416 | E12: 292 | F12: 123 | G12: 1307 | H12: 47155
A13: 2025 | B13: PIGIER | C13: 2642 | D13: 528 | E13: 370 | F13: 154 | G13: 1350 | H13: 53255
A14: 2025 | B14: TUNON | C14: 1397 | D14: 279 | E14: 196 | F14: 82 | G14: 948 | H14: 44627
A15: 2026 | B15: MBWAY | C15: 6444 | D15: 1458 | E15: 1032 | F15: 510 | G15: 3659 | H15: 166530
A16: 2026 | B16: ISCOM | C16: 4263 | D16: 964 | E16: 683 | F16: 338 | G16: 2337 | H16: 108103
... A19: 2026 | B19: TUNON | C19: 1480 | D19: 296 | E19: 207 | F19: 87 | G19: 988 | H19: 49090

Sheet Funnel & CAC
A1: RAPPORT FUNNEL & CAC · le coût d'acquisition, expliqué
A2: Cible du hyperlink depuis la tuile CAC du cockpit · POV = Groupe, drill marque → campus · exercice 2026
A3: SOURCE : matrice multidim sur V_FUNNEL + V_CAC (feuille « Données CRM »). Taux, CPL et CAC = formules (jamais pré-agrégés).
A5: Marque | B5: Leads | C5: → Cand. | D5: % | E5: → Admis | F5: % | G5: → Inscrits | H5: % | I5: Dépense acq. | J5: CPL | K5: CAC (€/inscrit)
A6: Mbway | B6: ='Données CRM'!C15 | C6: ='Données CRM'!D15 | D6: =IFERROR('Données CRM'!D15/'Données CRM'!C15,0) | E6: ='Données CRM'!E15 | F6: =IFERROR('Données CRM'!E15/'Données CRM'!D15,0) | G6: ='Données CRM'!F15 | H6: =IFERROR('Données CRM'!F15/'Données CRM'!E15,0) | I6: ='Données CRM'!H15 | J6: =IFERROR('Données CRM'!H15/'Données CRM'!G15,0) | K6: =IFERROR('Données CRM'!H15/'Données CRM'!F15,0)
A7: Iscom | B7: ='Données CRM'!C16 | C7: ='Données CRM'!D16 | D7: =IFERROR('Données CRM'!D16/'Données CRM'!C16,0) | E7: ='Données CRM'!E16 | F7: =IFERROR('Données CRM'!E16/'Données CRM'!D16,0) | G7: ='Données CRM'!F16 | H7: =IFERROR('Données CRM'!F16/'Données CRM'!E16,0) | I7: ='Données CRM'!H16 | J7: =IFERROR('Données CRM'!H16/'Données CRM'!G16,0) | K7: =IFERROR('Données CRM'!H16/'Données CRM'!F16,0)
A8: Ipac | B8: ='Données CRM'!C17 | C8: ='Données CRM'!D17 | D8: =IFERROR('Données CRM'!D17/'Données CRM'!C17,0) | E8: ='Données CRM'!E17 | F8: =IFERROR('Données CRM'!E17/'Données CRM'!D17,0) | G8: ='Données CRM'!F17 | H8: =IFERROR('Données CRM'!F17/'Données CRM'!E17,0) | I8: ='Données CRM'!H17 | J8: =IFERROR('Données CRM'!H17/'Données CRM'!G17,0) | K8: =IFERROR('Données CRM'!H17/'Données CRM'!F17,0)
A9: Pigier | B9: ='Données CRM'!C18 | C9: ='Données CRM'!D18 | D9: =IFERROR('Données CRM'!D18/'Données CRM'!C18,0) | E9: ='Données CRM'!E18 | F9: =IFERROR('Données CRM'!E18/'Données CRM'!D18,0) | G9: ='Données CRM'!F18 | H9: =IFERROR('Données CRM'!F18/'Données CRM'!E18,0) | I9: ='Données CRM'!H18 | J9: =IFERROR('Données CRM'!H18/'Données CRM'!G18,0) | K9: =IFERROR('Données CRM'!H18/'Données CRM'!F18,0)
A10: Tunon | B10: ='Données CRM'!C19 | C10: ='Données CRM'!D19 | D10: =IFERROR('Données CRM'!D19/'Données CRM'!C19,0) | E10: ='Données CRM'!E19 | F10: =IFERROR('Données CRM'!E19/'Données CRM'!D19,0) | G10: ='Données CRM'!F19 | H10: =IFERROR('Données CRM'!F19/'Données CRM'!E19,0) | I10: ='Données CRM'!H19 | J10: =IFERROR('Données CRM'!H19/'Données CRM'!G19,0) | K10: =IFERROR('Données CRM'!H19/'Données CRM'!F19,0)
A11: GROUPE | B11: =SUM(B6:B10) | C11: =SUM(C6:C10) | D11: =IFERROR(C11/B11,0) | E11: =SUM(E6:E10) | F11: =IFERROR(E11/C11,0) | G11: =SUM(G6:G10) | H11: =IFERROR(G11/E11,0) | I11: =SUM(I6:I10) | J11: =IFERROR(I11/SUM('Données CRM'!G15:G19),0) | K11: =IFERROR(I11/G11,0)
A13: FIL ROUGE : Tunon ≈ 564 €/inscrit contre ~327 € MBway — même funnel, coût très supérieur → c'est LÀ qu'on agira (Acte 6).
A14: Le funnel (taux de passage) explique le CAC : un rapport unique, on ne les sépare pas. Drill cellule campus → funnel du campus (hyperlink POV).
A15: CAC groupe 2026 = 353 € (2024 : 329 · 2025 : 341). Dépense +21 % vs inscrits +12 % → dégradation, déjà vue au cockpit.
