Workbook
Name ALLOC_BRAND_CAMP: Allocation!$C$8
Name ALLOC_CAMP_CLASS: Allocation!$C$9
Name ALLOC_GRP_BRAND: Allocation!$C$6
Name ALLOC_GRP_MARQUE: Allocation!$C$7

Sheet Allocation
N1: =IF($C$6="Chiffre d'affaires","REV_CA",IF($C$6="Nombre de classes","VOL_CLASS","VOL_EFF")) -> VOL_EFF | P1: =IF($C$12="Optimiste","V02",IF($C$12="Prudent","V03","V01")) -> V02 | BF1: SCENARIO | BG1: VERSION | BH1: PERIODE | BI1: EXERCICE | BJ1: ENTITY | BK1: MARQUE | BL1: PROGRAMME | BM1: AN_ETUDE | BN1: MODALITE | BO1: VOL_EFF | BP1: VOL_CLASS | BQ1: CA | BR1: COST_VAC | BS1: COST_PERM | BT1: COST_ODIR | BU1: COST_STRUCT | BV1: COST_MARQUE | BW1: COST_HOLDING | BX1: COST_SIEGE | BY1: COST_VARIABLE | BZ1: COST_STRUCTURE | CA1: COST_COMPLET | CB1: MARGE_COMPLETE | CC1: VOL_NEW | CD1: POOL_VAC | CE1: POOL_PERM | CF1: POOL_ODIR | CG1: POOL_MKT | CH1: POOL_STRUCT | CI1: POOL_HOLDING | CJ1: POOL_FRAIS_MARQUE
D2: Allocation & RENTABILITE - Coût complet du groupe à la classe | N2: =IF($C$7="Chiffre d'affaires","REV_CA",IF($C$7="Nombre de classes","VOL_CLASS","VOL_EFF")) -> REV_CA | BF2: 2027BUD_V1 | BG2: ACT | BH2: 12 | BI2: 2024 | BJ2: IPAC_MTP | BK2: IPAC | BL2: BAC_CCE | BM2: B1 | BN2: ALT | BO2: 36 | BP2: 2 | BQ2: 242640 | BR2: 22035.978 | BS2: 42519.027 | BT2: 26165.051 | BU2: 85770.028 | BV2: 5796.892 | BW2: 33312.214 | BX2: 39109.106 | BY2: 48201.029 | BZ2: 167398.16 | CA2: 215599.19 | CB2: 27040.809 | CC2: 36 | CD2: 66108 | CE2: 127557.21 | CF2: 39731 | CG2: 12543 | CH2: 257310.34 | CI2: 2639292 | CJ2: 499926
N3: =IF($C$8="Chiffre d'affaires","REV_CA",IF($C$8="Nombre de classes","VOL_CLASS","VOL_EFF")) -> VOL_EFF | BF3: 2027BUD_V1 | BG3: ACT | BH3: 12 | BI3: 2024 | BJ3: IPAC_MTP | BK3: IPAC | BL3: BAC_CCE | BM3: B2 | BN3: ALT | BO3: 35 | BP3: 2 | BQ3: 232750 | BR3: 22035.978 | BS3: 42519.027 | BT3: 13243.653 | BU3: 85770.028 | BV3: 5796.892 | BW3: 33312.214 | BX3: 39109.106 | BY3: 35279.631 | BZ3: 167398.16 | CA3: 202677.79 | CB3: 30072.207 | CC3: 0 | CD3: 66108 | CE3: 127557.21 | CF3: 39731 | CG3: 12543 | CH3: 257310.34 | CI3: 2639292 | CJ3: 499926
E4: Scénario | F4: Frais de structure campus | G4: Frais de marque | H4: Holding | I4: Total alloué | N4: =IF($C$9="Chiffre d'affaires","REV_CA",IF($C$9="Nombre de classes","VOL_CLASS","VOL_EFF")) -> VOL_CLASS | BF4: 2027BUD_V1 | BG4: ACT | BH4: 12 | BI4: 2024 | BJ4: IPAC_MTP | BK4: IPAC | BL4: BAC_CCE | BM4: B3 | BN4: ALT | BO4: 34 | BP4: 2 | BQ4: 226100 | BR4: 22035.978 | BS4: 42519.027 | BT4: 12865.255 | BU4: 85770.028 | BV4: 5796.892 | BW4: 33312.214 | BX4: 39109.106 | BY4: 34901.233 | BZ4: 167398.16 | CA4: 202299.39 | CB4: 23800.605 | CC4: 0 | CD4: 66108 | CE4: 127557.21 | CF4: 39731 | CG4: 12543 | CH4: 257310.34 | CI4: 2639292 | CJ4: 499926
B5: Cles d'Allocation | E5: Cadrage | F5: 9045300.6 | G5: 743978.4 | H5: 2975861.6 | I5: 12765141 | BF5: 2027BUD_V1 | BG5: ACT | BH5: 12 | BI5: 2024 | BJ5: IPAC_NAN | BK5: IPAC | BL5: BAC_CCE | BM5: B1 | BN5: ALT | BO5: 44 | BP5: 2 | BQ5: 311960 | BR5: 22035.978 | BS5: 51911.148 | BT5: 34778.025 | BU5: 120276.53 | BV5: 7121.8895 | BW5: 40926.398 | BX5: 48048.287 | BY5: 56814.003 | BZ5: 220235.97 | CA5: 277049.97 | CB5: 34910.028 | CC5: 44 | CD5: 66108 | CE5: 155733.6 | CF5: 49240 | CG5: 17983 | CH5: 360829.96 | CI5: 2639292 | CJ5: 499926
B6: Clé d’allocation siège administratif → marque | C6: Effectif | E6: Optimiste | F6: 8810446.7 | G6: 777795.6 | H6: 2894010 | I6: 12482252 | BF6: 2027BUD_V1 | BG6: ACT | BH6: 12 | BI6: 2024 | BJ6: IPAC_NAN | BK6: IPAC | BL6: BAC_CCE | BM6: B2 | BN6: ALT | BO6: 43 | BP6: 2 | BQ6: 301000 | BR6: 22035.978 | BS6: 51911.148 | BT6: 16413.317 | BU6: 120276.53 | BV6: 7121.8895 | BW6: 40926.398 | BX6: 48048.287 | BY6: 38449.295 | BZ6: 220235.97 | CA6: 258685.26 | CB6: 42314.737 | CC6: 0 | CD6: 66108 | CE6: 155733.6 | CF6: 49240 | CG6: 17983 | CH6: 360829.96 | CI6: 2639292 | CJ6: 499926
B7: Clé d’allocation Pub de marque → marque | C7: Chiffre d'affaires | E7: Prudent | F7: 9361926.3 | G7: 642526.8 | H7: 3092074.3 | I7: 13096527 | BF7: 2027BUD_V1 | BG7: ACT | BH7: 12 | BI7: 2024 | BJ7: IPAC_NAN | BK7: IPAC | BL7: BAC_CCE | BM7: B3 | BN7: ALT | BO7: 42 | BP7: 2 | BQ7: 294000 | BR7: 22035.978 | BS7: 51911.148 | BT7: 16031.608 | BU7: 120276.53 | BV7: 7121.8895 | BW7: 40926.398 | BX7: 48048.287 | BY7: 38067.586 | BZ7: 220235.97 | CA7: 258303.55 | CB7: 35696.445 | CC7: 0 | CD7: 66108 | CE7: 155733.6 | CF7: 49240 | CG7: 17983 | CH7: 360829.96 | CI7: 2639292 | CJ7: 499926
B8: Clé d’allocation Marque → Campus | C8: Effectif | BF8: 2027BUD_V1 | BG8: ACT | BH8: 12 | BI8: 2024 | BJ8: IPAC_REN | BK8: IPAC | BL8: BAC_CCE | BM8: B1 | BN8: ALT | BO8: 36 | BP8: 2 | BQ8: 242640 | BR8: 22035.978 | BS8: 42541.344 | BT8: 25963.051 | BU8: 85815.041 | BV8: 5796.892 | BW8: 33312.214 | BX8: 39109.106 | BY8: 47999.029 | BZ8: 167465.49 | CA8: 215464.52 | CB8: 27175.479 | CC8: 36 | CD8: 66108 | CE8: 127624.16 | CF8: 39731 | CG8: 12341 | CH8: 257445.38 | CI8: 2639292 | CJ8: 499926
B9: Clé d’allocation Campus → Classe | C9: Nombre de classes | BF9: 2027BUD_V1 | BG9: ACT | BH9: 12 | BI9: 2024 | BJ9: IPAC_REN | BK9: IPAC | BL9: BAC_CCE | BM9: B2 | BN9: ALT | BO9: 35 | BP9: 2 | BQ9: 232750 | BR9: 22035.978 | BS9: 42541.344 | BT9: 13243.653 | BU9: 85815.041 | BV9: 5796.892 | BW9: 33312.214 | BX9: 39109.106 | BY9: 35279.631 | BZ9: 167465.49 | CA9: 202745.12 | CB9: 30004.877 | CC9: 0 | CD9: 66108 | CE9: 127624.16 | CF9: 39731 | CG9: 12341 | CH9: 257445.38 | CI9: 2639292 | CJ9: 499926
BF10: 2027BUD_V1 | BG10: ACT | BH10: 12 | BI10: 2024 | BJ10: IPAC_REN | BK10: IPAC | BL10: BAC_CCE | BM10: B3 | BN10: ALT | BO10: 34 | BP10: 2 | BQ10: 226100 | BR10: 22035.978 | BS10: 42541.344 | BT10: 12865.255 | BU10: 85815.041 | BV10: 5796.892 | BW10: 33312.214 | BX10: 39109.106 | BY10: 34901.233 | BZ10: 167465.49 | CA10: 202366.72 | CB10: 23733.275 | CC10: 0 | CD10: 66108 | CE10: 127624.16 | CF10: 39731 | CG10: 12341 | CH10: 257445.38 | CI10: 2639292 | CJ10: 499926
BF11: 2027BUD_V1 | BG11: ACT | BH11: 12 | BI11: 2024 | BJ11: ISCOM_LIL | BK11: ISCOM | BL11: BAC_COM | BM11: B1 | BN11: INIT | BO11: 44 | BP11: 2 | BQ11: 327360 | BR11: 27545 | BS11: 64855.365 | BT11: 27222.12 | BU11: 120992.63 | BV11: 8006.1197 | BW11: 41307.198 | BX11: 49313.318 | BY11: 54767.12 | BZ11: 235161.32 | CA11: 289928.43 | CB11: 37431.565 | CC11: 44 | CD11: 110180 | CE11: 259421.46 | CF11: 82858 | CG11: 20843 | CH11: 604963.16 | CI11: 2639292 | CJ11: 499926
B12: Version budget restituée | C12: Optimiste | D12: ="version "&$P$1&" · "&TEXT(COUNTIF(_CALC_ALLOC!$AS$1:$AS$420,"2027|"&$P$1),"0")&" classes lues sur 60" | BF12: 2027BUD_V1 | BG12: ACT | BH12: 12 | BI12: 2024 | BJ12: ISCOM_LIL | BK12: ISCOM | BL12: BAC_COM | BM12: B2 | BN12: ALT | BO12: 43 | BP12: 2 | BQ12: 294980 | BR12: 22036 | BS12: 51884.292 | BT12: 16418.81 | BU12: 120992.63 | BV12: 8006.1197 | BW12: 41307.198 | BX12: 49313.318 | BY12: 38454.81 | BZ12: 222190.24 | CA12: 260645.05 | CB12: 34334.948 | CC12: 0 | CD12: 110180 | CE12: 259421.46 | CF12: 82858 | CG12: 20843 | CH12: 604963.16 | CI12: 2639292 | CJ12: 499926
BF13: 2027BUD_V1 | BG13: ACT | BH13: 12 | BI13: 2024 | BJ13: ISCOM_LIL | BK13: ISCOM | BL13: BAC_COM | BM13: B3 | BN13: ALT | BO13: 42 | BP13: 2 | BQ13: 288120 | BR13: 22036 | BS13: 51884.292 | BT13: 16037 | BU13: 120992.63 | BV13: 8006.1197 | BW13: 41307.198 | BX13: 49313.318 | BY13: 38073 | BZ13: 222190.24 | CA13: 260263.24 | CB13: 27856.758 | CC13: 0 | CD13: 110180 | CE13: 259421.46 | CF13: 82858 | CG13: 20843 | CH13: 604963.16 | CI13: 2639292 | CJ13: 499926
B14: Maille fine — deplie campus/classe avec les [+] | BF14: 2027BUD_V1 | BG14: ACT | BH14: 12 | BI14: 2024 | BJ14: ISCOM_LIL | BK14: ISCOM | BL14: MAS_COM | BM14: M1 | BN14: ALT | BO14: 44 | BP14: 2 | BQ14: 327360 | BR14: 19281.5 | BS14: 45398.755 | BT14: 27222.12 | BU14: 120992.63 | BV14: 8006.1197 | BW14: 41307.198 | BX14: 49313.318 | BY14: 46503.62 | BZ14: 215704.71 | CA14: 262208.33 | CB14: 65151.675 | CC14: 44 | CD14: 110180 | CE14: 259421.46 | CF14: 82858 | CG14: 20843 | CH14: 604963.16 | CI14: 2639292 | CJ14: 499926
BF15: 2027BUD_V1 | BG15: ACT | BH15: 12 | BI15: 2024 | BJ15: ISCOM_LIL | BK15: ISCOM | BL15: MAS_COM | BM15: M2 | BN15: ALT | BO15: 44 | BP15: 2 | BQ15: 323400 | BR15: 19281.5 | BS15: 45398.755 | BT15: 16800.62 | BU15: 120992.63 | BV15: 8006.1197 | BW15: 41307.198 | BX15: 49313.318 | BY15: 36082.12 | BZ15: 215704.71 | CA15: 251786.83 | CB15: 71613.175 | CC15: 0 | CD15: 110180 | CE15: 259421.46 | CF15: 82858 | CG15: 20843 | CH15: 604963.16 | CI15: 2639292 | CJ15: 499926
BF16: 2027BUD_V1 | BG16: ACT | BH16: 12 | BI16: 2024 | BJ16: ISCOM_PAR | BK16: ISCOM | BL16: BAC_COM | BM16: B1 | BN16: INIT | BO16: 64 | BP16: 3 | BQ16: 543360 | BR16: 41317.75 | BS16: 110892.23 | BT16: 49625.73 | BU16: 202318.32 | BV16: 11584.913 | BW16: 59771.812 | BX16: 71356.724 | BY16: 90943.48 | BZ16: 384567.28 | CA16: 475510.76 | CB16: 67849.239 | CC16: 64 | CD16: 165271 | CE16: 443568.93 | CF16: 120212 | CG16: 50248 | CH16: 1011591.6 | CI16: 2639292 | CJ16: 499926
B17: Marque ▸ Campus ▸ Classe | C17: Effectif | D17: CA | E17: VAC | F17: PERM | G17: ODIR | H17: STRUCT | I17: Frais marque | J17: Holding | K17: Cout complet | L17: Marge complete | M17: Marge % | BF17: 2027BUD_V1 | BG17: ACT | BH17: 12 | BI17: 2024 | BJ17: ISCOM_PAR | BK17: ISCOM | BL17: BAC_COM | BM17: B2 | BN17: ALT | BO17: 62 | BP17: 3 | BQ17: 486080 | BR17: 33054.2 | BS17: 88713.786 | BT17: 23736.1 | BU17: 202318.32 | BV17: 11584.913 | BW17: 59771.812 | BX17: 71356.724 | BY17: 56790.3 | BZ17: 362388.83 | CA17: 419179.13 | CB17: 66900.866 | CC17: 0 | CD17: 165271 | CE17: 443568.93 | CF17: 120212 | CG17: 50248 | CH17: 1011591.6 | CI17: 2639292 | CJ17: 499926
B18: MBway | C18: =SUMIFS(_CALC_ALLOC!$G$1:$G$420,_CALC_ALLOC!$AS$1:$AS$420,"2027|"&$P$1,_CALC_ALLOC!$C$1:$C$420,$V18) -> 0 | D18: =SUMIFS(_CALC_ALLOC!$I$1:$I$420,_CALC_ALLOC!$AS$1:$AS$420,"2027|"&$P$1,_CALC_ALLOC!$C$1:$C$420,$V18) -> 0 | E18: =SUMIFS(_CALC_ALLOC!$AI$1:$AI$420,_CALC_ALLOC!$AS$1:$AS$420,"2027|"&$P$1,_CALC_ALLOC!$C$1:$C$420,$V18) -> 0 | F18: =SUMIFS(_CALC_ALLOC!$AJ$1:$AJ$420,_CALC_ALLOC!$AS$1:$AS$420,"2027|"&$P$1,_CALC_ALLOC!$C$1:$C$420,$V18) -> 0 | G18: =SUMIFS(_CALC_ALLOC!$AK$1:$AK$420,_CALC_ALLOC!$AS$1:$AS$420,"2027|"&$P$1,_CALC_ALLOC!$C$1:$C$420,$V18) -> 0 | H18: =SUMIFS(_CALC_ALLOC!$AL$1:$AL$420,_CALC_ALLOC!$AS$1:$AS$420,"2027|"&$P$1,_CALC_ALLOC!$C$1:$C$420,$V18) -> 0 | I18: =SUMIFS(_CALC_ALLOC!$AR$1:$AR$420,_CALC_ALLOC!$AS$1:$AS$420,"2027|"&$P$1,_CALC_ALLOC!$C$1:$C$420,$V18) -> 0 | J18: =SUMIFS(_CALC_ALLOC!$AM$1:$AM$420,_CALC_ALLOC!$AS$1:$AS$420,"2027|"&$P$1,_CALC_ALLOC!$C$1:$C$420,$V18) -> 0 | K18: =E18+F18+G18+H18+I18+J18 -> 0 | L18: =SUMIFS(_CALC_ALLOC!$AN$1:$AN$420,_CALC_ALLOC!$AS$1:$AS$420,"2027|"&$P$1,_CALC_ALLOC!$C$1:$C$420,$V18) -> 0 | M18: =IF(D18=0,0,L18/D18) -> 0 | T18: MBWAY | V18: MBWAY | Z18: 1 | BF18: 2027BUD_V1 | BG18: ACT | BH18: 12 | BI18: 2024 | BJ18: ISCOM_PAR | BK18: ISCOM | BL18: BAC_COM | BM18: B3 | BN18: ALT | BO18: 61 | BP18: 3 | BQ18: 478240 | BR18: 33054.2 | BS18: 88713.786 | BT18: 23353.225 | BU18: 202318.32 | BV18: 11584.913 | BW18: 59771.812 | BX18: 71356.724 | BY18: 56407.425 | BZ18: 362388.83 | CA18: 418796.26 | CB18: 59443.741 | CC18: 0 | CD18: 165271 | CE18: 443568.93 | CF18: 120212 | CG18: 50248 | CH18: 1011591.6 | CI18: 2639292 | CJ18: 499926
B19: Paris | C19: =SUMIFS(_CALC_ALLOC!$G$1:$G$420,_CALC_ALLOC!$AS$1:$AS$420,"2027|"&$P$1,_CALC_ALLOC!$B$1:$B$420,$U19) -> 0 | D19: =SUMIFS(_CALC_ALLOC!$I$1:$I$420,_CALC_ALLOC!$AS$1:$AS$420,"2027|"&$P$1,_CALC_ALLOC!$B$1:$B$420,$U19) -> 0 | E19: =SUMIFS(_CALC_ALLOC!$AI$1:$AI$420,_CALC_ALLOC!$AS$1:$AS$420,"2027|"&$P$1,_CALC_ALLOC!$B$1:$B$420,$U19) -> 0 | F19: =SUMIFS(_CALC_ALLOC!$AJ$1:$AJ$420,_CALC_ALLOC!$AS$1:$AS$420,"2027|"&$P$1,_CALC_ALLOC!$B$1:$B$420,$U19) -> 0 | G19: =SUMIFS(_CALC_ALLOC!$AK$1:$AK$420,_CALC_ALLOC!$AS$1:$AS$420,"2027|"&$P$1,_CALC_ALLOC!$B$1:$B$420,$U19) -> 0 | H19: =SUMIFS(_CALC_ALLOC!$AL$1:$AL$420,_CALC_ALLOC!$AS$1:$AS$420,"2027|"&$P$1,_CALC_ALLOC!$B$1:$B$420,$U19) -> 0 | I19: =SUMIFS(_CALC_ALLOC!$AR$1:$AR$420,_CALC_ALLOC!$AS$1:$AS$420,"2027|"&$P$1,_CALC_ALLOC!$B$1:$B$420,$U19) -> 0 | J19: =SUMIFS(_CALC_ALLOC!$AM$1:$AM$420,_CALC_ALLOC!$AS$1:$AS$420,"2027|"&$P$1,_CALC_ALLOC!$B$1:$B$420,$U19) -> 0 | K19: =E19+F19+G19+H19+I19+J19 -> 0 | L19: =SUMIFS(_CALC_ALLOC!$AN$1:$AN$420,_CALC_ALLOC!$AS$1:$AS$420,"2027|"&$P$1,_CALC_ALLOC!$B$1:$B$420,$U19) -> 0 | M19: =IF(D19=0,0,L19/D19) -> 0 | T19: MBWAY_PAR | U19: MBWAY_PAR | V19: MBWAY | Z19: 2 | BF19: 2027BUD_V1 | BG19: ACT | BH19: 12 | BI19: 2024 | BJ19: ISCOM_PAR | BK19: ISCOM | BL19: MAS_COM | BM19: M1 | BN19: ALT | BO19: 64 | BP19: 3 | BQ19: 543360 | BR19: 28922.425 | BS19: 77624.563 | BT19: 49625.73 | BU19: 202318.32 | BV19: 11584.913 | BW19: 59771.812 | BX19: 71356.724 | BY19: 78548.155 | BZ19: 351299.61 | CA19: 429847.77 | CB19: 113512.23 | CC19: 64 | CD19: 165271 | CE19: 443568.93 | CF19: 120212 | CG19: 50248 | CH19: 1011591.6 | CI19: 2639292 | CJ19: 499926
B20: Bachelor Management, 1re année, initial | C20: =SUMIFS(_CALC_ALLOC!$G$1:$G$420,_CALC_ALLOC!$AS$1:$AS$420,"2027|"&$P$1,_CALC_ALLOC!$B$1:$B$420,$U20,_CALC_ALLOC!$D$1:$D$420,$W20,_CALC_ALLOC!$E$1:$E$420,$X20,_CALC_ALLOC!$F$1:$F$420,$Y20) -> 0 | D20: =SUMIFS(_CALC_ALLOC!$I$1:$I$420,_CALC_ALLOC!$AS$1:$AS$420,"2027|"&$P$1,_CALC_ALLOC!$B$1:$B$420,$U20,_CALC_ALLOC!$D$1:$D$420,$W20,_CALC_ALLOC!$E$1:$E$420,$X20,_CALC_ALLOC!$F$1:$F$420,$Y20) -> 0 | E20: =SUMIFS(_CALC_ALLOC!$AI$1:$AI$420,_CALC_ALLOC!$AS$1:$AS$420,"2027|"&$P$1,_CALC_ALLOC!$B$1:$B$420,$U20,_CALC_ALLOC!$D$1:$D$420,$W20,_CALC_ALLOC!$E$1:$E$420,$X20,_CALC_ALLOC!$F$1:$F$420,$Y20) -> 0 | F20: =SUMIFS(_CALC_ALLOC!$AJ$1:$AJ$420,_CALC_ALLOC!$AS$1:$AS$420,"2027|"&$P$1,_CALC_ALLOC!$B$1:$B$420,$U20,_CALC_ALLOC!$D$1:$D$420,$W20,_CALC_ALLOC!$E$1:$E$420,$X20,_CALC_ALLOC!$F$1:$F$420,$Y20) -> 0 | G20: =SUMIFS(_CALC_ALLOC!$AK$1:$AK$420,_CALC_ALLOC!$AS$1:$AS$420,"2027|"&$P$1,_CALC_ALLOC!$B$1:$B$420,$U20,_CALC_ALLOC!$D$1:$D$420,$W20,_CALC_ALLOC!$E$1:$E$420,$X20,_CALC_ALLOC!$F$1:$F$420,$Y20) -> 0 | H20: =SUMIFS(_CALC_ALLOC!$AL$1:$AL$420,_CALC_ALLOC!$AS$1:$AS$420,"2027|"&$P$1,_CALC_ALLOC!$B$1:$B$420,$U20,_CALC_ALLOC!$D$1:$D$420,$W20,_CALC_ALLOC!$E$1:$E$420,$X20,_CALC_ALLOC!$F$1:$F$420,$Y20) -> 0 | I20: =SUMIFS(_CALC_ALLOC!$AR$1:$AR$420,_CALC_ALLOC!$AS$1:$AS$420,"2027|"&$P$1,_CALC_ALLOC!$B$1:$B$420,$U20,_CALC_ALLOC!$D$1:$D$420,$W20,_CALC_ALLOC!$E$1:$E$420,$X20,_CALC_ALLOC!$F$1:$F$420,$Y20) -> 0 | J20: =SUMIFS(_CALC_ALLOC!$AM$1:$AM$420,_CALC_ALLOC!$AS$1:$AS$420,"2027|"&$P$1,_CALC_ALLOC!$B$1:$B$420,$U20,_CALC_ALLOC!$D$1:$D$420,$W20,_CALC_ALLOC!$E$1:$E$420,$X20,_CALC_ALLOC!$F$1:$F$420,$Y20) -> 0 | K20: =E20+F20+G20+H20+I20+J20 -> 0 | L20: =SUMIFS(_CALC_ALLOC!$AN$1:$AN$420,_CALC_ALLOC!$AS$1:$AS$420,"2027|"&$P$1,_CALC_ALLOC!$B$1:$B$420,$U20,_CALC_ALLOC!$D$1:$D$420,$W20,_CALC_ALLOC!$E$1:$E$420,$X20,_CALC_ALLOC!$F$1:$F$420,$Y20) -> 0 | M20: =IF(D20=0,0,L20/D20) -> 0 | T20: MBWAY_PAR|BAC_MGT|B1|INIT | U20: MBWAY_PAR | V20: MBWAY | W20: BAC_MGT | X20: B1 | Y20: INIT | Z20: 3 | BF20: 2027BUD_V1 | BG20: ACT | BH20: 12 | BI20: 2024 | BJ20: ISCOM_PAR | BK20: ISCOM | BL20: MAS_COM | BM20: M2 | BN20: ALT | BO20: 63 | BP20: 3 | BQ20: 529200 | BR20: 28922.425 | BS20: 77624.563 | BT20: 24118.855 | BU20: 202318.32 | BV20: 11584.913 | BW20: 59771.812 | BX20: 71356.724 | BY20: 53041.28 | BZ20: 351299.61 | CA20: 404340.89 | CB20: 124859.11 | CC20: 0 | CD20: 165271 | CE20: 443568.93 | CF20: 120212 | CG20: 50248 | CH20: 1011591.6 | CI20: 2639292 | CJ20: 499926
B21: Bachelor Management, 2e année, alternance | C21: =SUMIFS(_CALC_ALLOC!$G$1:$G$420,_CALC_ALLOC!$AS$1:$AS$420,"2027|"&$P$1,_CALC_ALLOC!$B$1:$B$420,$U21,_CALC_ALLOC!$D$1:$D$420,$W21,_CALC_ALLOC!$E$1:$E$420,$X21,_CALC_ALLOC!$F$1:$F$420,$Y21) -> 0 | D21: =SUMIFS(_CALC_ALLOC!$I$1:$I$420,_CALC_ALLOC!$AS$1:$AS$420,"2027|"&$P$1,_CALC_ALLOC!$B$1:$B$420,$U21,_CALC_ALLOC!$D$1:$D$420,$W21,_CALC_ALLOC!$E$1:$E$420,$X21,_CALC_ALLOC!$F$1:$F$420,$Y21) -> 0 | E21: =SUMIFS(_CALC_ALLOC!$AI$1:$AI$420,_CALC_ALLOC!$AS$1:$AS$420,"2027|"&$P$1,_CALC_ALLOC!$B$1:$B$420,$U21,_CALC_ALLOC!$D$1:$D$420,$W21,_CALC_ALLOC!$E$1:$E$420,$X21,_CALC_ALLOC!$F$1:$F$420,$Y21) -> 0 | F21: =SUMIFS(_CALC_ALLOC!$AJ$1:$AJ$420,_CALC_ALLOC!$AS$1:$AS$420,"2027|"&$P$1,_CALC_ALLOC!$B$1:$B$420,$U21,_CALC_ALLOC!$D$1:$D$420,$W21,_CALC_ALLOC!$E$1:$E$420,$X21,_CALC_ALLOC!$F$1:$F$420,$Y21) -> 0 | G21: =SUMIFS(_CALC_ALLOC!$AK$1:$AK$420,_CALC_ALLOC!$AS$1:$AS$420,"2027|"&$P$1,_CALC_ALLOC!$B$1:$B$420,$U21,_CALC_ALLOC!$D$1:$D$420,$W21,_CALC_ALLOC!$E$1:$E$420,$X21,_CALC_ALLOC!$F$1:$F$420,$Y21) -> 0 | H21: =SUMIFS(_CALC_ALLOC!$AL$1:$AL$420,_CALC_ALLOC!$AS$1:$AS$420,"2027|"&$P$1,_CALC_ALLOC!$B$1:$B$420,$U21,_CALC_ALLOC!$D$1:$D$420,$W21,_CALC_ALLOC!$E$1:$E$420,$X21,_CALC_ALLOC!$F$1:$F$420,$Y21) -> 0 | I21: =SUMIFS(_CALC_ALLOC!$AR$1:$AR$420,_CALC_ALLOC!$AS$1:$AS$420,"2027|"&$P$1,_CALC_ALLOC!$B$1:$B$420,$U21,_CALC_ALLOC!$D$1:$D$420,$W21,_CALC_ALLOC!$E$1:$E$420,$X21,_CALC_ALLOC!$F$1:$F$420,$Y21) -> 0 | J21: =SUMIFS(_CALC_ALLOC!$AM$1:$AM$420,_CALC_ALLOC!$AS$1:$AS$420,"2027|"&$P$1,_CALC_ALLOC!$B$1:$B$420,$U21,_CALC_ALLOC!$D$1:$D$420,$W21,_CALC_ALLOC!$E$1:$E$420,$X21,_CALC_ALLOC!$F$1:$F$420,$Y21) -> 0 | K21: =E21+F21+G21+H21+I21+J21 -> 0 | L21: =SUMIFS(_CALC_ALLOC!$AN$1:$AN$420,_CALC_ALLOC!$AS$1:$AS$420,"2027|"&$P$1,_CALC_ALLOC!$B$1:$B$420,$U21,_CALC_ALLOC!$D$1:$D$420,$W21,_CALC_ALLOC!$E$1:$E$420,$X21,_CALC_ALLOC!$F$1:$F$420,$Y21) -> 0 | M21: =IF(D21=0,0,L21/D21) -> 0 | T21: MBWAY_PAR|BAC_MGT|B2|ALT | U21: MBWAY_PAR | V21: MBWAY | W21: BAC_MGT | X21: B2 | Y21: ALT | Z21: 3 | BF21: 2027BUD_V1 | BG21: ACT | BH21: 12 | BI21: 2024 | BJ21: ISCOM_TLS | BK21: ISCOM | BL21: BAC_COM | BM21: B1 | BN21: INIT | BO21: 42 | BP21: 2 | BQ21: 306180 | BR21: 27545 | BS21: 61223.45 | BT21: 25118.694 | BU21: 110126.31 | BV21: 7600.2884 | BW21: 39213.331 | BX21: 46813.62 | BY21: 52663.694 | BZ21: 218163.38 | CA21: 270827.08 | CB21: 35352.922 | CC21: 42 | CD21: 110180 | CE21: 244893.8 | CF21: 78443 | CG21: 18251 | CH21: 550631.57 | CI21: 2639292 | CJ21: 499926
B22: Bachelor Management, 3e année, alternance | C22: =SUMIFS(_CALC_ALLOC!$G$1:$G$420,_CALC_ALLOC!$AS$1:$AS$420,"2027|"&$P$1,_CALC_ALLOC!$B$1:$B$420,$U22,_CALC_ALLOC!$D$1:$D$420,$W22,_CALC_ALLOC!$E$1:$E$420,$X22,_CALC_ALLOC!$F$1:$F$420,$Y22) -> 0 | D22: =SUMIFS(_CALC_ALLOC!$I$1:$I$420,_CALC_ALLOC!$AS$1:$AS$420,"2027|"&$P$1,_CALC_ALLOC!$B$1:$B$420,$U22,_CALC_ALLOC!$D$1:$D$420,$W22,_CALC_ALLOC!$E$1:$E$420,$X22,_CALC_ALLOC!$F$1:$F$420,$Y22) -> 0 | E22: =SUMIFS(_CALC_ALLOC!$AI$1:$AI$420,_CALC_ALLOC!$AS$1:$AS$420,"2027|"&$P$1,_CALC_ALLOC!$B$1:$B$420,$U22,_CALC_ALLOC!$D$1:$D$420,$W22,_CALC_ALLOC!$E$1:$E$420,$X22,_CALC_ALLOC!$F$1:$F$420,$Y22) -> 0 | F22: =SUMIFS(_CALC_ALLOC!$AJ$1:$AJ$420,_CALC_ALLOC!$AS$1:$AS$420,"2027|"&$P$1,_CALC_ALLOC!$B$1:$B$420,$U22,_CALC_ALLOC!$D$1:$D$420,$W22,_CALC_ALLOC!$E$1:$E$420,$X22,_CALC_ALLOC!$F$1:$F$420,$Y22) -> 0 | G22: =SUMIFS(_CALC_ALLOC!$AK$1:$AK$420,_CALC_ALLOC!$AS$1:$AS$420,"2027|"&$P$1,_CALC_ALLOC!$B$1:$B$420,$U22,_CALC_ALLOC!$D$1:$D$420,$W22,_CALC_ALLOC!$E$1:$E$420,$X22,_CALC_ALLOC!$F$1:$F$420,$Y22) -> 0 | H22: =SUMIFS(_CALC_ALLOC!$AL$1:$AL$420,_CALC_ALLOC!$AS$1:$AS$420,"2027|"&$P$1,_CALC_ALLOC!$B$1:$B$420,$U22,_CALC_ALLOC!$D$1:$D$420,$W22,_CALC_ALLOC!$E$1:$E$420,$X22,_CALC_ALLOC!$F$1:$F$420,$Y22) -> 0 | I22: =SUMIFS(_CALC_ALLOC!$AR$1:$AR$420,_CALC_ALLOC!$AS$1:$AS$420,"2027|"&$P$1,_CALC_ALLOC!$B$1:$B$420,$U22,_CALC_ALLOC!$D$1:$D$420,$W22,_CALC_ALLOC!$E$1:$E$420,$X22,_CALC_ALLOC!$F$1:$F$420,$Y22) -> 0 | J22: =SUMIFS(_CALC_ALLOC!$AM$1:$AM$420,_CALC_ALLOC!$AS$1:$AS$420,"2027|"&$P$1,_CALC_ALLOC!$B$1:$B$420,$U22,_CALC_ALLOC!$D$1:$D$420,$W22,_CALC_ALLOC!$E$1:$E$420,$X22,_CALC_ALLOC!$F$1:$F$420,$Y22) -> 0 | K22: =E22+F22+G22+H22+I22+J22 -> 0 | L22: =SUMIFS(_CALC_ALLOC!$AN$1:$AN$420,_CALC_ALLOC!$AS$1:$AS$420,"2027|"&$P$1,_CALC_ALLOC!$B$1:$B$420,$U22,_CALC_ALLOC!$D$1:$D$420,$W22,_CALC_ALLOC!$E$1:$E$420,$X22,_CALC_ALLOC!$F$1:$F$420,$Y22) -> 0 | M22: =IF(D22=0,0,L22/D22) -> 0 | T22: MBWAY_PAR|BAC_MGT|B3|ALT | U22: MBWAY_PAR | V22: MBWAY | W22: BAC_MGT | X22: B3 | Y22: ALT | Z22: 3 | BF22: 2027BUD_V1 | BG22: ACT | BH22: 12 | BI22: 2024 | BJ22: ISCOM_TLS | BK22: ISCOM | BL22: BAC_COM | BM22: B2 | BN22: ALT | BO22: 41 | BP22: 2 | BQ22: 275520 | BR22: 22036 | BS22: 48978.76 | BT22: 15612.432 | BU22: 110126.31 | BV22: 7600.2884 | BW22: 39213.331 | BX22: 46813.62 | BY22: 37648.432 | BZ22: 205918.69 | CA22: 243567.13 | CB22: 31952.875 | CC22: 0 | CD22: 110180 | CE22: 244893.8 | CF22: 78443 | CG22: 18251 | CH22: 550631.57 | CI22: 2639292 | CJ22: 499926
B23: Mastère Management, 1re année, alternance | C23: =SUMIFS(_CALC_ALLOC!$G$1:$G$420,_CALC_ALLOC!$AS$1:$AS$420,"2027|"&$P$1,_CALC_ALLOC!$B$1:$B$420,$U23,_CALC_ALLOC!$D$1:$D$420,$W23,_CALC_ALLOC!$E$1:$E$420,$X23,_CALC_ALLOC!$F$1:$F$420,$Y23) -> 0 | D23: =SUMIFS(_CALC_ALLOC!$I$1:$I$420,_CALC_ALLOC!$AS$1:$AS$420,"2027|"&$P$1,_CALC_ALLOC!$B$1:$B$420,$U23,_CALC_ALLOC!$D$1:$D$420,$W23,_CALC_ALLOC!$E$1:$E$420,$X23,_CALC_ALLOC!$F$1:$F$420,$Y23) -> 0 | E23: =SUMIFS(_CALC_ALLOC!$AI$1:$AI$420,_CALC_ALLOC!$AS$1:$AS$420,"2027|"&$P$1,_CALC_ALLOC!$B$1:$B$420,$U23,_CALC_ALLOC!$D$1:$D$420,$W23,_CALC_ALLOC!$E$1:$E$420,$X23,_CALC_ALLOC!$F$1:$F$420,$Y23) -> 0 | F23: =SUMIFS(_CALC_ALLOC!$AJ$1:$AJ$420,_CALC_ALLOC!$AS$1:$AS$420,"2027|"&$P$1,_CALC_ALLOC!$B$1:$B$420,$U23,_CALC_ALLOC!$D$1:$D$420,$W23,_CALC_ALLOC!$E$1:$E$420,$X23,_CALC_ALLOC!$F$1:$F$420,$Y23) -> 0 | G23: =SUMIFS(_CALC_ALLOC!$AK$1:$AK$420,_CALC_ALLOC!$AS$1:$AS$420,"2027|"&$P$1,_CALC_ALLOC!$B$1:$B$420,$U23,_CALC_ALLOC!$D$1:$D$420,$W23,_CALC_ALLOC!$E$1:$E$420,$X23,_CALC_ALLOC!$F$1:$F$420,$Y23) -> 0 | H23: =SUMIFS(_CALC_ALLOC!$AL$1:$AL$420,_CALC_ALLOC!$AS$1:$AS$420,"2027|"&$P$1,_CALC_ALLOC!$B$1:$B$420,$U23,_CALC_ALLOC!$D$1:$D$420,$W23,_CALC_ALLOC!$E$1:$E$420,$X23,_CALC_ALLOC!$F$1:$F$420,$Y23) -> 0 | I23: =SUMIFS(_CALC_ALLOC!$AR$1:$AR$420,_CALC_ALLOC!$AS$1:$AS$420,"2027|"&$P$1,_CALC_ALLOC!$B$1:$B$420,$U23,_CALC_ALLOC!$D$1:$D$420,$W23,_CALC_ALLOC!$E$1:$E$420,$X23,_CALC_ALLOC!$F$1:$F$420,$Y23) -> 0 | J23: =SUMIFS(_CALC_ALLOC!$AM$1:$AM$420,_CALC_ALLOC!$AS$1:$AS$420,"2027|"&$P$1,_CALC_ALLOC!$B$1:$B$420,$U23,_CALC_ALLOC!$D$1:$D$420,$W23,_CALC_ALLOC!$E$1:$E$420,$X23,_CALC_ALLOC!$F$1:$F$420,$Y23) -> 0 | K23: =E23+F23+G23+H23+I23+J23 -> 0 | L23: =SUMIFS(_CALC_ALLOC!$AN$1:$AN$420,_CALC_ALLOC!$AS$1:$AS$420,"2027|"&$P$1,_CALC_ALLOC!$B$1:$B$420,$U23,_CALC_ALLOC!$D$1:$D$420,$W23,_CALC_ALLOC!$E$1:$E$420,$X23,_CALC_ALLOC!$F$1:$F$420,$Y23) -> 0 | M23: =IF(D23=0,0,L23/D23) -> 0 | T23: MBWAY_PAR|MAS_MGT|M1|ALT | U23: MBWAY_PAR | V23: MBWAY | W23: MAS_MGT | X23: M1 | Y23: ALT | Z23: 3 | BF23: 2027BUD_V1 | BG23: ACT | BH23: 12 | BI23: 2024 | BJ23: ISCOM_TLS | BK23: ISCOM | BL23: BAC_COM | BM23: B3 | BN23: ALT | BO23: 40 | BP23: 2 | BQ23: 268800 | BR23: 22036 | BS23: 48978.76 | BT23: 15231.591 | BU23: 110126.31 | BV23: 7600.2884 | BW23: 39213.331 | BX23: 46813.62 | BY23: 37267.591 | BZ23: 205918.69 | CA23: 243186.28 | CB23: 25613.715 | CC23: 0 | CD23: 110180 | CE23: 244893.8 | CF23: 78443 | CG23: 18251 | CH23: 550631.57 | CI23: 2639292 | CJ23: 499926
B24: Mastère Management, 2e année, alternance | C24: =SUMIFS(_CALC_ALLOC!$G$1:$G$420,_CALC_ALLOC!$AS$1:$AS$420,"2027|"&$P$1,_CALC_ALLOC!$B$1:$B$420,$U24,_CALC_ALLOC!$D$1:$D$420,$W24,_CALC_ALLOC!$E$1:$E$420,$X24,_CALC_ALLOC!$F$1:$F$420,$Y24) -> 0 | D24: =SUMIFS(_CALC_ALLOC!$I$1:$I$420,_CALC_ALLOC!$AS$1:$AS$420,"2027|"&$P$1,_CALC_ALLOC!$B$1:$B$420,$U24,_CALC_ALLOC!$D$1:$D$420,$W24,_CALC_ALLOC!$E$1:$E$420,$X24,_CALC_ALLOC!$F$1:$F$420,$Y24) -> 0 | E24: =SUMIFS(_CALC_ALLOC!$AI$1:$AI$420,_CALC_ALLOC!$AS$1:$AS$420,"2027|"&$P$1,_CALC_ALLOC!$B$1:$B$420,$U24,_CALC_ALLOC!$D$1:$D$420,$W24,_CALC_ALLOC!$E$1:$E$420,$X24,_CALC_ALLOC!$F$1:$F$420,$Y24) -> 0 | F24: =SUMIFS(_CALC_ALLOC!$AJ$1:$AJ$420,_CALC_ALLOC!$AS$1:$AS$420,"2027|"&$P$1,_CALC_ALLOC!$B$1:$B$420,$U24,_CALC_ALLOC!$D$1:$D$420,$W24,_CALC_ALLOC!$E$1:$E$420,$X24,_CALC_ALLOC!$F$1:$F$420,$Y24) -> 0 | G24: =SUMIFS(_CALC_ALLOC!$AK$1:$AK$420,_CALC_ALLOC!$AS$1:$AS$420,"2027|"&$P$1,_CALC_ALLOC!$B$1:$B$420,$U24,_CALC_ALLOC!$D$1:$D$420,$W24,_CALC_ALLOC!$E$1:$E$420,$X24,_CALC_ALLOC!$F$1:$F$420,$Y24) -> 0 | H24: =SUMIFS(_CALC_ALLOC!$AL$1:$AL$420,_CALC_ALLOC!$AS$1:$AS$420,"2027|"&$P$1,_CALC_ALLOC!$B$1:$B$420,$U24,_CALC_ALLOC!$D$1:$D$420,$W24,_CALC_ALLOC!$E$1:$E$420,$X24,_CALC_ALLOC!$F$1:$F$420,$Y24) -> 0 | I24: =SUMIFS(_CALC_ALLOC!$AR$1:$AR$420,_CALC_ALLOC!$AS$1:$AS$420,"2027|"&$P$1,_CALC_ALLOC!$B$1:$B$420,$U24,_CALC_ALLOC!$D$1:$D$420,$W24,_CALC_ALLOC!$E$1:$E$420,$X24,_CALC_ALLOC!$F$1:$F$420,$Y24) -> 0 | J24: =SUMIFS(_CALC_ALLOC!$AM$1:$AM$420,_CALC_ALLOC!$AS$1:$AS$420,"2027|"&$P$1,_CALC_ALLOC!$B$1:$B$420,$U24,_CALC_ALLOC!$D$1:$D$420,$W24,_CALC_ALLOC!$E$1:$E$420,$X24,_CALC_ALLOC!$F$1:$F$420,$Y24) -> 0 | K24: =E24+F24+G24+H24+I24+J24 -> 0 | L24: =SUMIFS(_CALC_ALLOC!$AN$1:$AN$420,_CALC_ALLOC!$AS$1:$AS$420,"2027|"&$P$1,_CALC_ALLOC!$B$1:$B$420,$U24,_CALC_ALLOC!$D$1:$D$420,$W24,_CALC_ALLOC!$E$1:$E$420,$X24,_CALC_ALLOC!$F$1:$F$420,$Y24) -> 0 | M24: =IF(D24=0,0,L24/D24) -> 0 | T24: MBWAY_PAR|MAS_MGT|M2|ALT | U24: MBWAY_PAR | V24: MBWAY | W24: MAS_MGT | X24: M2 | Y24: ALT | Z24: 3 | BF24: 2027BUD_V1 | BG24: ACT | BH24: 12 | BI24: 2024 | BJ24: ISCOM_TLS | BK24: ISCOM | BL24: MAS_COM | BM24: M1 | BN24: ALT | BO24: 42 | BP24: 2 | BQ24: 306180 | BR24: 19281.5 | BS24: 42856.415 | BT24: 25118.694 | BU24: 110126.31 | BV24: 7600.2884 | BW24: 39213.331 | BX24: 46813.62 | BY24: 44400.194 | BZ24: 199796.35 | CA24: 244196.54 | CB24: 61983.457 | CC24: 42 | CD24: 110180 | CE24: 244893.8 | CF24: 78443 | CG24: 18251 | CH24: 550631.57 | CI24: 2639292 | CJ24: 499926
B25: Lyon | C25: =SUMIFS(_CALC_ALLOC!$G$1:$G$420,_CALC_ALLOC!$AS$1:$AS$420,"2027|"&$P$1,_CALC_ALLOC!$B$1:$B$420,$U25) -> 0 | D25: =SUMIFS(_CALC_ALLOC!$I$1:$I$420,_CALC_ALLOC!$AS$1:$AS$420,"2027|"&$P$1,_CALC_ALLOC!$B$1:$B$420,$U25) -> 0 | E25: =SUMIFS(_CALC_ALLOC!$AI$1:$AI$420,_CALC_ALLOC!$AS$1:$AS$420,"2027|"&$P$1,_CALC_ALLOC!$B$1:$B$420,$U25) -> 0 | F25: =SUMIFS(_CALC_ALLOC!$AJ$1:$AJ$420,_CALC_ALLOC!$AS$1:$AS$420,"2027|"&$P$1,_CALC_ALLOC!$B$1:$B$420,$U25) -> 0 | G25: =SUMIFS(_CALC_ALLOC!$AK$1:$AK$420,_CALC_ALLOC!$AS$1:$AS$420,"2027|"&$P$1,_CALC_ALLOC!$B$1:$B$420,$U25) -> 0 | H25: =SUMIFS(_CALC_ALLOC!$AL$1:$AL$420,_CALC_ALLOC!$AS$1:$AS$420,"2027|"&$P$1,_CALC_ALLOC!$B$1:$B$420,$U25) -> 0 | I25: =SUMIFS(_CALC_ALLOC!$AR$1:$AR$420,_CALC_ALLOC!$AS$1:$AS$420,"2027|"&$P$1,_CALC_ALLOC!$B$1:$B$420,$U25) -> 0 | J25: =SUMIFS(_CALC_ALLOC!$AM$1:$AM$420,_CALC_ALLOC!$AS$1:$AS$420,"2027|"&$P$1,_CALC_ALLOC!$B$1:$B$420,$U25) -> 0 | K25: =E25+F25+G25+H25+I25+J25 -> 0 | L25: =SUMIFS(_CALC_ALLOC!$AN$1:$AN$420,_CALC_ALLOC!$AS$1:$AS$420,"2027|"&$P$1,_CALC_ALLOC!$B$1:$B$420,$U25) -> 0 | M25: =IF(D25=0,0,L25/D25) -> 0 | T25: MBWAY_LYO | U25: MBWAY_LYO | V25: MBWAY | Z25: 2 | BF25: 2027BUD_V1 | BG25: ACT | BH25: 12 | BI25: 2024 | BJ25: ISCOM_TLS | BK25: ISCOM | BL25: MAS_COM | BM25: M2 | BN25: ALT | BO25: 41 | BP25: 2 | BQ25: 295200 | BR25: 19281.5 | BS25: 42856.415 | BT25: 15612.432 | BU25: 110126.31 | BV25: 7600.2884 | BW25: 39213.331 | BX25: 46813.62 | BY25: 34893.932 | BZ25: 199796.35 | CA25: 234690.28 | CB25: 60509.72 | CC25: 0 | CD25: 110180 | CE25: 244893.8 | CF25: 78443 | CG25: 18251 | CH25: 550631.57 | CI25: 2639292 | CJ25: 499926
B26: Bachelor Management, 1re année, initial | C26: =SUMIFS(_CALC_ALLOC!$G$1:$G$420,_CALC_ALLOC!$AS$1:$AS$420,"2027|"&$P$1,_CALC_ALLOC!$B$1:$B$420,$U26,_CALC_ALLOC!$D$1:$D$420,$W26,_CALC_ALLOC!$E$1:$E$420,$X26,_CALC_ALLOC!$F$1:$F$420,$Y26) -> 0 | D26: =SUMIFS(_CALC_ALLOC!$I$1:$I$420,_CALC_ALLOC!$AS$1:$AS$420,"2027|"&$P$1,_CALC_ALLOC!$B$1:$B$420,$U26,_CALC_ALLOC!$D$1:$D$420,$W26,_CALC_ALLOC!$E$1:$E$420,$X26,_CALC_ALLOC!$F$1:$F$420,$Y26) -> 0 | E26: =SUMIFS(_CALC_ALLOC!$AI$1:$AI$420,_CALC_ALLOC!$AS$1:$AS$420,"2027|"&$P$1,_CALC_ALLOC!$B$1:$B$420,$U26,_CALC_ALLOC!$D$1:$D$420,$W26,_CALC_ALLOC!$E$1:$E$420,$X26,_CALC_ALLOC!$F$1:$F$420,$Y26) -> 0 | F26: =SUMIFS(_CALC_ALLOC!$AJ$1:$AJ$420,_CALC_ALLOC!$AS$1:$AS$420,"2027|"&$P$1,_CALC_ALLOC!$B$1:$B$420,$U26,_CALC_ALLOC!$D$1:$D$420,$W26,_CALC_ALLOC!$E$1:$E$420,$X26,_CALC_ALLOC!$F$1:$F$420,$Y26) -> 0 | G26: =SUMIFS(_CALC_ALLOC!$AK$1:$AK$420,_CALC_ALLOC!$AS$1:$AS$420,"2027|"&$P$1,_CALC_ALLOC!$B$1:$B$420,$U26,_CALC_ALLOC!$D$1:$D$420,$W26,_CALC_ALLOC!$E$1:$E$420,$X26,_CALC_ALLOC!$F$1:$F$420,$Y26) -> 0 | H26: =SUMIFS(_CALC_ALLOC!$AL$1:$AL$420,_CALC_ALLOC!$AS$1:$AS$420,"2027|"&$P$1,_CALC_ALLOC!$B$1:$B$420,$U26,_CALC_ALLOC!$D$1:$D$420,$W26,_CALC_ALLOC!$E$1:$E$420,$X26,_CALC_ALLOC!$F$1:$F$420,$Y26) -> 0 | I26: =SUMIFS(_CALC_ALLOC!$AR$1:$AR$420,_CALC_ALLOC!$AS$1:$AS$420,"2027|"&$P$1,_CALC_ALLOC!$B$1:$B$420,$U26,_CALC_ALLOC!$D$1:$D$420,$W26,_CALC_ALLOC!$E$1:$E$420,$X26,_CALC_ALLOC!$F$1:$F$420,$Y26) -> 0 | J26: =SUMIFS(_CALC_ALLOC!$AM$1:$AM$420,_CALC_ALLOC!$AS$1:$AS$420,"2027|"&$P$1,_CALC_ALLOC!$B$1:$B$420,$U26,_CALC_ALLOC!$D$1:$D$420,$W26,_CALC_ALLOC!$E$1:$E$420,$X26,_CALC_ALLOC!$F$1:$F$420,$Y26) -> 0 | K26: =E26+F26+G26+H26+I26+J26 -> 0 | L26: =SUMIFS(_CALC_ALLOC!$AN$1:$AN$420,_CALC_ALLOC!$AS$1:$AS$420,"2027|"&$P$1,_CALC_ALLOC!$B$1:$B$420,$U26,_CALC_ALLOC!$D$1:$D$420,$W26,_CALC_ALLOC!$E$1:$E$420,$X26,_CALC_ALLOC!$F$1:$F$420,$Y26) -> 0 | M26: =IF(D26=0,0,L26/D26) -> 0 | T26: MBWAY_LYO|BAC_MGT|B1|INIT | U26: MBWAY_LYO | V26: MBWAY | W26: BAC_MGT | X26: B1 | Y26: INIT | Z26: 3 | BF26: 2027BUD_V1 | BG26: ACT | BH26: 12 | BI26: 2024 | BJ26: MBWAY_BOR | BK26: MBWAY | BL26: BAC_MGT | BM26: B1 | BN26: INIT | BO26: 45 | BP26: 2 | BQ26: 331425 | BR26: 27545 | BS26: 64185.895 | BT26: 27515.708 | BU26: 121392.64 | BV26: 8229.0045 | BW26: 42068.694 | BX26: 50297.698 | BY26: 55060.708 | BZ26: 235876.23 | CA26: 290936.94 | CB26: 40488.063 | CC26: 45 | CD26: 110180 | CE26: 256743.58 | CF26: 84556 | CG26: 20597 | CH26: 606963.18 | CI26: 2639292 | CJ26: 499926
B27: Bachelor Management, 2e année, alternance | C27: =SUMIFS(_CALC_ALLOC!$G$1:$G$420,_CALC_ALLOC!$AS$1:$AS$420,"2027|"&$P$1,_CALC_ALLOC!$B$1:$B$420,$U27,_CALC_ALLOC!$D$1:$D$420,$W27,_CALC_ALLOC!$E$1:$E$420,$X27,_CALC_ALLOC!$F$1:$F$420,$Y27) -> 0 | D27: =SUMIFS(_CALC_ALLOC!$I$1:$I$420,_CALC_ALLOC!$AS$1:$AS$420,"2027|"&$P$1,_CALC_ALLOC!$B$1:$B$420,$U27,_CALC_ALLOC!$D$1:$D$420,$W27,_CALC_ALLOC!$E$1:$E$420,$X27,_CALC_ALLOC!$F$1:$F$420,$Y27) -> 0 | E27: =SUMIFS(_CALC_ALLOC!$AI$1:$AI$420,_CALC_ALLOC!$AS$1:$AS$420,"2027|"&$P$1,_CALC_ALLOC!$B$1:$B$420,$U27,_CALC_ALLOC!$D$1:$D$420,$W27,_CALC_ALLOC!$E$1:$E$420,$X27,_CALC_ALLOC!$F$1:$F$420,$Y27) -> 0 | F27: =SUMIFS(_CALC_ALLOC!$AJ$1:$AJ$420,_CALC_ALLOC!$AS$1:$AS$420,"2027|"&$P$1,_CALC_ALLOC!$B$1:$B$420,$U27,_CALC_ALLOC!$D$1:$D$420,$W27,_CALC_ALLOC!$E$1:$E$420,$X27,_CALC_ALLOC!$F$1:$F$420,$Y27) -> 0 | G27: =SUMIFS(_CALC_ALLOC!$AK$1:$AK$420,_CALC_ALLOC!$AS$1:$AS$420,"2027|"&$P$1,_CALC_ALLOC!$B$1:$B$420,$U27,_CALC_ALLOC!$D$1:$D$420,$W27,_CALC_ALLOC!$E$1:$E$420,$X27,_CALC_ALLOC!$F$1:$F$420,$Y27) -> 0 | H27: =SUMIFS(_CALC_ALLOC!$AL$1:$AL$420,_CALC_ALLOC!$AS$1:$AS$420,"2027|"&$P$1,_CALC_ALLOC!$B$1:$B$420,$U27,_CALC_ALLOC!$D$1:$D$420,$W27,_CALC_ALLOC!$E$1:$E$420,$X27,_CALC_ALLOC!$F$1:$F$420,$Y27) -> 0 | I27: =SUMIFS(_CALC_ALLOC!$AR$1:$AR$420,_CALC_ALLOC!$AS$1:$AS$420,"2027|"&$P$1,_CALC_ALLOC!$B$1:$B$420,$U27,_CALC_ALLOC!$D$1:$D$420,$W27,_CALC_ALLOC!$E$1:$E$420,$X27,_CALC_ALLOC!$F$1:$F$420,$Y27) -> 0 | J27: =SUMIFS(_CALC_ALLOC!$AM$1:$AM$420,_CALC_ALLOC!$AS$1:$AS$420,"2027|"&$P$1,_CALC_ALLOC!$B$1:$B$420,$U27,_CALC_ALLOC!$D$1:$D$420,$W27,_CALC_ALLOC!$E$1:$E$420,$X27,_CALC_ALLOC!$F$1:$F$420,$Y27) -> 0 | K27: =E27+F27+G27+H27+I27+J27 -> 0 | L27: =SUMIFS(_CALC_ALLOC!$AN$1:$AN$420,_CALC_ALLOC!$AS$1:$AS$420,"2027|"&$P$1,_CALC_ALLOC!$B$1:$B$420,$U27,_CALC_ALLOC!$D$1:$D$420,$W27,_CALC_ALLOC!$E$1:$E$420,$X27,_CALC_ALLOC!$F$1:$F$420,$Y27) -> 0 | M27: =IF(D27=0,0,L27/D27) -> 0 | T27: MBWAY_LYO|BAC_MGT|B2|ALT | U27: MBWAY_LYO | V27: MBWAY | W27: BAC_MGT | X27: B2 | Y27: ALT | Z27: 3 | BF27: 2027BUD_V1 | BG27: ACT | BH27: 12 | BI27: 2024 | BJ27: MBWAY_BOR | BK27: MBWAY | BL27: BAC_MGT | BM27: B2 | BN27: ALT | BO27: 44 | BP27: 2 | BQ27: 298760 | BR27: 22036 | BS27: 51348.716 | BT27: 16834.677 | BU27: 121392.64 | BV27: 8229.0045 | BW27: 42068.694 | BX27: 50297.698 | BY27: 38870.677 | BZ27: 223039.05 | CA27: 261909.73 | CB27: 36850.273 | CC27: 0 | CD27: 110180 | CE27: 256743.58 | CF27: 84556 | CG27: 20597 | CH27: 606963.18 | CI27: 2639292 | CJ27: 499926
B28: Bachelor Management, 3e année, alternance | C28: =SUMIFS(_CALC_ALLOC!$G$1:$G$420,_CALC_ALLOC!$AS$1:$AS$420,"2027|"&$P$1,_CALC_ALLOC!$B$1:$B$420,$U28,_CALC_ALLOC!$D$1:$D$420,$W28,_CALC_ALLOC!$E$1:$E$420,$X28,_CALC_ALLOC!$F$1:$F$420,$Y28) -> 0 | D28: =SUMIFS(_CALC_ALLOC!$I$1:$I$420,_CALC_ALLOC!$AS$1:$AS$420,"2027|"&$P$1,_CALC_ALLOC!$B$1:$B$420,$U28,_CALC_ALLOC!$D$1:$D$420,$W28,_CALC_ALLOC!$E$1:$E$420,$X28,_CALC_ALLOC!$F$1:$F$420,$Y28) -> 0 | E28: =SUMIFS(_CALC_ALLOC!$AI$1:$AI$420,_CALC_ALLOC!$AS$1:$AS$420,"2027|"&$P$1,_CALC_ALLOC!$B$1:$B$420,$U28,_CALC_ALLOC!$D$1:$D$420,$W28,_CALC_ALLOC!$E$1:$E$420,$X28,_CALC_ALLOC!$F$1:$F$420,$Y28) -> 0 | F28: =SUMIFS(_CALC_ALLOC!$AJ$1:$AJ$420,_CALC_ALLOC!$AS$1:$AS$420,"2027|"&$P$1,_CALC_ALLOC!$B$1:$B$420,$U28,_CALC_ALLOC!$D$1:$D$420,$W28,_CALC_ALLOC!$E$1:$E$420,$X28,_CALC_ALLOC!$F$1:$F$420,$Y28) -> 0 | G28: =SUMIFS(_CALC_ALLOC!$AK$1:$AK$420,_CALC_ALLOC!$AS$1:$AS$420,"2027|"&$P$1,_CALC_ALLOC!$B$1:$B$420,$U28,_CALC_ALLOC!$D$1:$D$420,$W28,_CALC_ALLOC!$E$1:$E$420,$X28,_CALC_ALLOC!$F$1:$F$420,$Y28) -> 0 | H28: =SUMIFS(_CALC_ALLOC!$AL$1:$AL$420,_CALC_ALLOC!$AS$1:$AS$420,"2027|"&$P$1,_CALC_ALLOC!$B$1:$B$420,$U28,_CALC_ALLOC!$D$1:$D$420,$W28,_CALC_ALLOC!$E$1:$E$420,$X28,_CALC_ALLOC!$F$1:$F$420,$Y28) -> 0 | I28: =SUMIFS(_CALC_ALLOC!$AR$1:$AR$420,_CALC_ALLOC!$AS$1:$AS$420,"2027|"&$P$1,_CALC_ALLOC!$B$1:$B$420,$U28,_CALC_ALLOC!$D$1:$D$420,$W28,_CALC_ALLOC!$E$1:$E$420,$X28,_CALC_ALLOC!$F$1:$F$420,$Y28) -> 0 | J28: =SUMIFS(_CALC_ALLOC!$AM$1:$AM$420,_CALC_ALLOC!$AS$1:$AS$420,"2027|"&$P$1,_CALC_ALLOC!$B$1:$B$420,$U28,_CALC_ALLOC!$D$1:$D$420,$W28,_CALC_ALLOC!$E$1:$E$420,$X28,_CALC_ALLOC!$F$1:$F$420,$Y28) -> 0 | K28: =E28+F28+G28+H28+I28+J28 -> 0 | L28: =SUMIFS(_CALC_ALLOC!$AN$1:$AN$420,_CALC_ALLOC!$AS$1:$AS$420,"2027|"&$P$1,_CALC_ALLOC!$B$1:$B$420,$U28,_CALC_ALLOC!$D$1:$D$420,$W28,_CALC_ALLOC!$E$1:$E$420,$X28,_CALC_ALLOC!$F$1:$F$420,$Y28) -> 0 | M28: =IF(D28=0,0,L28/D28) -> 0 | T28: MBWAY_LYO|BAC_MGT|B3|ALT | U28: MBWAY_LYO | V28: MBWAY | W28: BAC_MGT | X28: B3 | Y28: ALT | Z28: 3 | BF28: 2027BUD_V1 | BG28: ACT | BH28: 12 | BI28: 2024 | BJ28: MBWAY_BOR | BK28: MBWAY | BL28: BAC_MGT | BM28: B3 | BN28: ALT | BO28: 43 | BP28: 2 | BQ28: 291970 | BR28: 22036 | BS28: 51348.716 | BT28: 16452.061 | BU28: 121392.64 | BV28: 8229.0045 | BW28: 42068.694 | BX28: 50297.698 | BY28: 38488.061 | BZ28: 223039.05 | CA28: 261527.11 | CB28: 30442.889 | CC28: 0 | CD28: 110180 | CE28: 256743.58 | CF28: 84556 | CG28: 20597 | CH28: 606963.18 | CI28: 2639292 | CJ28: 499926
B29: Mastère Management, 1re année, alternance | C29: =SUMIFS(_CALC_ALLOC!$G$1:$G$420,_CALC_ALLOC!$AS$1:$AS$420,"2027|"&$P$1,_CALC_ALLOC!$B$1:$B$420,$U29,_CALC_ALLOC!$D$1:$D$420,$W29,_CALC_ALLOC!$E$1:$E$420,$X29,_CALC_ALLOC!$F$1:$F$420,$Y29) -> 0 | D29: =SUMIFS(_CALC_ALLOC!$I$1:$I$420,_CALC_ALLOC!$AS$1:$AS$420,"2027|"&$P$1,_CALC_ALLOC!$B$1:$B$420,$U29,_CALC_ALLOC!$D$1:$D$420,$W29,_CALC_ALLOC!$E$1:$E$420,$X29,_CALC_ALLOC!$F$1:$F$420,$Y29) -> 0 | E29: =SUMIFS(_CALC_ALLOC!$AI$1:$AI$420,_CALC_ALLOC!$AS$1:$AS$420,"2027|"&$P$1,_CALC_ALLOC!$B$1:$B$420,$U29,_CALC_ALLOC!$D$1:$D$420,$W29,_CALC_ALLOC!$E$1:$E$420,$X29,_CALC_ALLOC!$F$1:$F$420,$Y29) -> 0 | F29: =SUMIFS(_CALC_ALLOC!$AJ$1:$AJ$420,_CALC_ALLOC!$AS$1:$AS$420,"2027|"&$P$1,_CALC_ALLOC!$B$1:$B$420,$U29,_CALC_ALLOC!$D$1:$D$420,$W29,_CALC_ALLOC!$E$1:$E$420,$X29,_CALC_ALLOC!$F$1:$F$420,$Y29) -> 0 | G29: =SUMIFS(_CALC_ALLOC!$AK$1:$AK$420,_CALC_ALLOC!$AS$1:$AS$420,"2027|"&$P$1,_CALC_ALLOC!$B$1:$B$420,$U29,_CALC_ALLOC!$D$1:$D$420,$W29,_CALC_ALLOC!$E$1:$E$420,$X29,_CALC_ALLOC!$F$1:$F$420,$Y29) -> 0 | H29: =SUMIFS(_CALC_ALLOC!$AL$1:$AL$420,_CALC_ALLOC!$AS$1:$AS$420,"2027|"&$P$1,_CALC_ALLOC!$B$1:$B$420,$U29,_CALC_ALLOC!$D$1:$D$420,$W29,_CALC_ALLOC!$E$1:$E$420,$X29,_CALC_ALLOC!$F$1:$F$420,$Y29) -> 0 | I29: =SUMIFS(_CALC_ALLOC!$AR$1:$AR$420,_CALC_ALLOC!$AS$1:$AS$420,"2027|"&$P$1,_CALC_ALLOC!$B$1:$B$420,$U29,_CALC_ALLOC!$D$1:$D$420,$W29,_CALC_ALLOC!$E$1:$E$420,$X29,_CALC_ALLOC!$F$1:$F$420,$Y29) -> 0 | J29: =SUMIFS(_CALC_ALLOC!$AM$1:$AM$420,_CALC_ALLOC!$AS$1:$AS$420,"2027|"&$P$1,_CALC_ALLOC!$B$1:$B$420,$U29,_CALC_ALLOC!$D$1:$D$420,$W29,_CALC_ALLOC!$E$1:$E$420,$X29,_CALC_ALLOC!$F$1:$F$420,$Y29) -> 0 | K29: =E29+F29+G29+H29+I29+J29 -> 0 | L29: =SUMIFS(_CALC_ALLOC!$AN$1:$AN$420,_CALC_ALLOC!$AS$1:$AS$420,"2027|"&$P$1,_CALC_ALLOC!$B$1:$B$420,$U29,_CALC_ALLOC!$D$1:$D$420,$W29,_CALC_ALLOC!$E$1:$E$420,$X29,_CALC_ALLOC!$F$1:$F$420,$Y29) -> 0 | M29: =IF(D29=0,0,L29/D29) -> 0 | T29: MBWAY_LYO|MAS_MGT|M1|ALT | U29: MBWAY_LYO | V29: MBWAY | W29: MAS_MGT | X29: M1 | Y29: ALT | Z29: 3 | BF29: 2027BUD_V1 | BG29: ACT | BH29: 12 | BI29: 2024 | BJ29: MBWAY_BOR | BK29: MBWAY | BL29: MAS_MGT | BM29: M1 | BN29: ALT | BO29: 45 | BP29: 2 | BQ29: 331425 | BR29: 19281.5 | BS29: 44930.126 | BT29: 27515.708 | BU29: 121392.64 | BV29: 8229.0045 | BW29: 42068.694 | BX29: 50297.698 | BY29: 46797.208 | BZ29: 216620.46 | CA29: 263417.67 | CB29: 68007.331 | CC29: 45 | CD29: 110180 | CE29: 256743.58 | CF29: 84556 | CG29: 20597 | CH29: 606963.18 | CI29: 2639292 | CJ29: 499926
B30: Mastère Management, 2e année, alternance | C30: =SUMIFS(_CALC_ALLOC!$G$1:$G$420,_CALC_ALLOC!$AS$1:$AS$420,"2027|"&$P$1,_CALC_ALLOC!$B$1:$B$420,$U30,_CALC_ALLOC!$D$1:$D$420,$W30,_CALC_ALLOC!$E$1:$E$420,$X30,_CALC_ALLOC!$F$1:$F$420,$Y30) -> 0 | D30: =SUMIFS(_CALC_ALLOC!$I$1:$I$420,_CALC_ALLOC!$AS$1:$AS$420,"2027|"&$P$1,_CALC_ALLOC!$B$1:$B$420,$U30,_CALC_ALLOC!$D$1:$D$420,$W30,_CALC_ALLOC!$E$1:$E$420,$X30,_CALC_ALLOC!$F$1:$F$420,$Y30) -> 0 | E30: =SUMIFS(_CALC_ALLOC!$AI$1:$AI$420,_CALC_ALLOC!$AS$1:$AS$420,"2027|"&$P$1,_CALC_ALLOC!$B$1:$B$420,$U30,_CALC_ALLOC!$D$1:$D$420,$W30,_CALC_ALLOC!$E$1:$E$420,$X30,_CALC_ALLOC!$F$1:$F$420,$Y30) -> 0 | F30: =SUMIFS(_CALC_ALLOC!$AJ$1:$AJ$420,_CALC_ALLOC!$AS$1:$AS$420,"2027|"&$P$1,_CALC_ALLOC!$B$1:$B$420,$U30,_CALC_ALLOC!$D$1:$D$420,$W30,_CALC_ALLOC!$E$1:$E$420,$X30,_CALC_ALLOC!$F$1:$F$420,$Y30) -> 0 | G30: =SUMIFS(_CALC_ALLOC!$AK$1:$AK$420,_CALC_ALLOC!$AS$1:$AS$420,"2027|"&$P$1,_CALC_ALLOC!$B$1:$B$420,$U30,_CALC_ALLOC!$D$1:$D$420,$W30,_CALC_ALLOC!$E$1:$E$420,$X30,_CALC_ALLOC!$F$1:$F$420,$Y30) -> 0 | H30: =SUMIFS(_CALC_ALLOC!$AL$1:$AL$420,_CALC_ALLOC!$AS$1:$AS$420,"2027|"&$P$1,_CALC_ALLOC!$B$1:$B$420,$U30,_CALC_ALLOC!$D$1:$D$420,$W30,_CALC_ALLOC!$E$1:$E$420,$X30,_CALC_ALLOC!$F$1:$F$420,$Y30) -> 0 | I30: =SUMIFS(_CALC_ALLOC!$AR$1:$AR$420,_CALC_ALLOC!$AS$1:$AS$420,"2027|"&$P$1,_CALC_ALLOC!$B$1:$B$420,$U30,_CALC_ALLOC!$D$1:$D$420,$W30,_CALC_ALLOC!$E$1:$E$420,$X30,_CALC_ALLOC!$F$1:$F$420,$Y30) -> 0 | J30: =SUMIFS(_CALC_ALLOC!$AM$1:$AM$420,_CALC_ALLOC!$AS$1:$AS$420,"2027|"&$P$1,_CALC_ALLOC!$B$1:$B$420,$U30,_CALC_ALLOC!$D$1:$D$420,$W30,_CALC_ALLOC!$E$1:$E$420,$X30,_CALC_ALLOC!$F$1:$F$420,$Y30) -> 0 | K30: =E30+F30+G30+H30+I30+J30 -> 0 | L30: =SUMIFS(_CALC_ALLOC!$AN$1:$AN$420,_CALC_ALLOC!$AS$1:$AS$420,"2027|"&$P$1,_CALC_ALLOC!$B$1:$B$420,$U30,_CALC_ALLOC!$D$1:$D$420,$W30,_CALC_ALLOC!$E$1:$E$420,$X30,_CALC_ALLOC!$F$1:$F$420,$Y30) -> 0 | M30: =IF(D30=0,0,L30/D30) -> 0 | T30: MBWAY_LYO|MAS_MGT|M2|ALT | U30: MBWAY_LYO | V30: MBWAY | W30: MAS_MGT | X30: M2 | Y30: ALT | Z30: 3 | BF30: 2027BUD_V1 | BG30: ACT | BH30: 12 | BI30: 2024 | BJ30: MBWAY_BOR | BK30: MBWAY | BL30: MAS_MGT | BM30: M2 | BN30: ALT | BO30: 44 | BP30: 2 | BQ30: 320100 | BR30: 19281.5 | BS30: 44930.126 | BT30: 16834.677 | BU30: 121392.64 | BV30: 8229.0045 | BW30: 42068.694 | BX30: 50297.698 | BY30: 36116.177 | BZ30: 216620.46 | CA30: 252736.64 | CB30: 67363.362 | CC30: 0 | CD30: 110180 | CE30: 256743.58 | CF30: 84556 | CG30: 20597 | CH30: 606963.18 | CI30: 2639292 | CJ30: 499926
B31: Nantes | C31: =SUMIFS(_CALC_ALLOC!$G$1:$G$420,_CALC_ALLOC!$AS$1:$AS$420,"2027|"&$P$1,_CALC_ALLOC!$B$1:$B$420,$U31) -> 0 | D31: =SUMIFS(_CALC_ALLOC!$I$1:$I$420,_CALC_ALLOC!$AS$1:$AS$420,"2027|"&$P$1,_CALC_ALLOC!$B$1:$B$420,$U31) -> 0 | E31: =SUMIFS(_CALC_ALLOC!$AI$1:$AI$420,_CALC_ALLOC!$AS$1:$AS$420,"2027|"&$P$1,_CALC_ALLOC!$B$1:$B$420,$U31) -> 0 | F31: =SUMIFS(_CALC_ALLOC!$AJ$1:$AJ$420,_CALC_ALLOC!$AS$1:$AS$420,"2027|"&$P$1,_CALC_ALLOC!$B$1:$B$420,$U31) -> 0 | G31: =SUMIFS(_CALC_ALLOC!$AK$1:$AK$420,_CALC_ALLOC!$AS$1:$AS$420,"2027|"&$P$1,_CALC_ALLOC!$B$1:$B$420,$U31) -> 0 | H31: =SUMIFS(_CALC_ALLOC!$AL$1:$AL$420,_CALC_ALLOC!$AS$1:$AS$420,"2027|"&$P$1,_CALC_ALLOC!$B$1:$B$420,$U31) -> 0 | I31: =SUMIFS(_CALC_ALLOC!$AR$1:$AR$420,_CALC_ALLOC!$AS$1:$AS$420,"2027|"&$P$1,_CALC_ALLOC!$B$1:$B$420,$U31) -> 0 | J31: =SUMIFS(_CALC_ALLOC!$AM$1:$AM$420,_CALC_ALLOC!$AS$1:$AS$420,"2027|"&$P$1,_CALC_ALLOC!$B$1:$B$420,$U31) -> 0 | K31: =E31+F31+G31+H31+I31+J31 -> 0 | L31: =SUMIFS(_CALC_ALLOC!$AN$1:$AN$420,_CALC_ALLOC!$AS$1:$AS$420,"2027|"&$P$1,_CALC_ALLOC!$B$1:$B$420,$U31) -> 0 | M31: =IF(D31=0,0,L31/D31) -> 0 | T31: MBWAY_NAN | U31: MBWAY_NAN | V31: MBWAY | Z31: 2 | BF31: 2027BUD_V1 | BG31: ACT | BH31: 12 | BI31: 2024 | BJ31: MBWAY_LYO | BK31: MBWAY | BL31: BAC_MGT | BM31: B1 | BN31: INIT | BO31: 59 | BP31: 3 | BQ31: 469935 | BR31: 41317.711 | BS31: 106414.01 | BT31: 39727.824 | BU31: 201383.22 | BV31: 12416.529 | BW31: 63476.349 | BX31: 75892.878 | BY31: 81045.535 | BZ31: 383690.11 | CA31: 464735.64 | CB31: 5199.3554 | CC31: 59 | CD31: 143235 | CE31: 368902.58 | CF31: 110025 | CG31: 34532 | CH31: 872661.51 | CI31: 2639292 | CJ31: 499926
B32: Bachelor Management, 1re année, initial | C32: =SUMIFS(_CALC_ALLOC!$G$1:$G$420,_CALC_ALLOC!$AS$1:$AS$420,"2027|"&$P$1,_CALC_ALLOC!$B$1:$B$420,$U32,_CALC_ALLOC!$D$1:$D$420,$W32,_CALC_ALLOC!$E$1:$E$420,$X32,_CALC_ALLOC!$F$1:$F$420,$Y32) -> 0 | D32: =SUMIFS(_CALC_ALLOC!$I$1:$I$420,_CALC_ALLOC!$AS$1:$AS$420,"2027|"&$P$1,_CALC_ALLOC!$B$1:$B$420,$U32,_CALC_ALLOC!$D$1:$D$420,$W32,_CALC_ALLOC!$E$1:$E$420,$X32,_CALC_ALLOC!$F$1:$F$420,$Y32) -> 0 | E32: =SUMIFS(_CALC_ALLOC!$AI$1:$AI$420,_CALC_ALLOC!$AS$1:$AS$420,"2027|"&$P$1,_CALC_ALLOC!$B$1:$B$420,$U32,_CALC_ALLOC!$D$1:$D$420,$W32,_CALC_ALLOC!$E$1:$E$420,$X32,_CALC_ALLOC!$F$1:$F$420,$Y32) -> 0 | F32: =SUMIFS(_CALC_ALLOC!$AJ$1:$AJ$420,_CALC_ALLOC!$AS$1:$AS$420,"2027|"&$P$1,_CALC_ALLOC!$B$1:$B$420,$U32,_CALC_ALLOC!$D$1:$D$420,$W32,_CALC_ALLOC!$E$1:$E$420,$X32,_CALC_ALLOC!$F$1:$F$420,$Y32) -> 0 | G32: =SUMIFS(_CALC_ALLOC!$AK$1:$AK$420,_CALC_ALLOC!$AS$1:$AS$420,"2027|"&$P$1,_CALC_ALLOC!$B$1:$B$420,$U32,_CALC_ALLOC!$D$1:$D$420,$W32,_CALC_ALLOC!$E$1:$E$420,$X32,_CALC_ALLOC!$F$1:$F$420,$Y32) -> 0 | H32: =SUMIFS(_CALC_ALLOC!$AL$1:$AL$420,_CALC_ALLOC!$AS$1:$AS$420,"2027|"&$P$1,_CALC_ALLOC!$B$1:$B$420,$U32,_CALC_ALLOC!$D$1:$D$420,$W32,_CALC_ALLOC!$E$1:$E$420,$X32,_CALC_ALLOC!$F$1:$F$420,$Y32) -> 0 | I32: =SUMIFS(_CALC_ALLOC!$AR$1:$AR$420,_CALC_ALLOC!$AS$1:$AS$420,"2027|"&$P$1,_CALC_ALLOC!$B$1:$B$420,$U32,_CALC_ALLOC!$D$1:$D$420,$W32,_CALC_ALLOC!$E$1:$E$420,$X32,_CALC_ALLOC!$F$1:$F$420,$Y32) -> 0 | J32: =SUMIFS(_CALC_ALLOC!$AM$1:$AM$420,_CALC_ALLOC!$AS$1:$AS$420,"2027|"&$P$1,_CALC_ALLOC!$B$1:$B$420,$U32,_CALC_ALLOC!$D$1:$D$420,$W32,_CALC_ALLOC!$E$1:$E$420,$X32,_CALC_ALLOC!$F$1:$F$420,$Y32) -> 0 | K32: =E32+F32+G32+H32+I32+J32 -> 0 | L32: =SUMIFS(_CALC_ALLOC!$AN$1:$AN$420,_CALC_ALLOC!$AS$1:$AS$420,"2027|"&$P$1,_CALC_ALLOC!$B$1:$B$420,$U32,_CALC_ALLOC!$D$1:$D$420,$W32,_CALC_ALLOC!$E$1:$E$420,$X32,_CALC_ALLOC!$F$1:$F$420,$Y32) -> 0 | M32: =IF(D32=0,0,L32/D32) -> 0 | T32: MBWAY_NAN|BAC_MGT|B1|INIT | U32: MBWAY_NAN | V32: MBWAY | W32: BAC_MGT | X32: B1 | Y32: INIT | Z32: 3 | BF32: 2027BUD_V1 | BG32: ACT | BH32: 12 | BI32: 2024 | BJ32: MBWAY_LYO | BK32: MBWAY | BL32: BAC_MGT | BM32: B2 | BN32: ALT | BO32: 57 | BP32: 2 | BQ32: 418950 | BR32: 22036.132 | BS32: 56754.186 | BT32: 21700.341 | BU32: 134255.48 | BV32: 8277.6861 | BW32: 42317.566 | BX32: 50595.252 | BY32: 43736.473 | BZ32: 241604.92 | CA32: 285341.39 | CB32: 133608.61 | CC32: 0 | CD32: 143235 | CE32: 368902.58 | CF32: 110025 | CG32: 34532 | CH32: 872661.51 | CI32: 2639292 | CJ32: 499926
B33: Bachelor Management, 2e année, alternance | C33: =SUMIFS(_CALC_ALLOC!$G$1:$G$420,_CALC_ALLOC!$AS$1:$AS$420,"2027|"&$P$1,_CALC_ALLOC!$B$1:$B$420,$U33,_CALC_ALLOC!$D$1:$D$420,$W33,_CALC_ALLOC!$E$1:$E$420,$X33,_CALC_ALLOC!$F$1:$F$420,$Y33) -> 0 | D33: =SUMIFS(_CALC_ALLOC!$I$1:$I$420,_CALC_ALLOC!$AS$1:$AS$420,"2027|"&$P$1,_CALC_ALLOC!$B$1:$B$420,$U33,_CALC_ALLOC!$D$1:$D$420,$W33,_CALC_ALLOC!$E$1:$E$420,$X33,_CALC_ALLOC!$F$1:$F$420,$Y33) -> 0 | E33: =SUMIFS(_CALC_ALLOC!$AI$1:$AI$420,_CALC_ALLOC!$AS$1:$AS$420,"2027|"&$P$1,_CALC_ALLOC!$B$1:$B$420,$U33,_CALC_ALLOC!$D$1:$D$420,$W33,_CALC_ALLOC!$E$1:$E$420,$X33,_CALC_ALLOC!$F$1:$F$420,$Y33) -> 0 | F33: =SUMIFS(_CALC_ALLOC!$AJ$1:$AJ$420,_CALC_ALLOC!$AS$1:$AS$420,"2027|"&$P$1,_CALC_ALLOC!$B$1:$B$420,$U33,_CALC_ALLOC!$D$1:$D$420,$W33,_CALC_ALLOC!$E$1:$E$420,$X33,_CALC_ALLOC!$F$1:$F$420,$Y33) -> 0 | G33: =SUMIFS(_CALC_ALLOC!$AK$1:$AK$420,_CALC_ALLOC!$AS$1:$AS$420,"2027|"&$P$1,_CALC_ALLOC!$B$1:$B$420,$U33,_CALC_ALLOC!$D$1:$D$420,$W33,_CALC_ALLOC!$E$1:$E$420,$X33,_CALC_ALLOC!$F$1:$F$420,$Y33) -> 0 | H33: =SUMIFS(_CALC_ALLOC!$AL$1:$AL$420,_CALC_ALLOC!$AS$1:$AS$420,"2027|"&$P$1,_CALC_ALLOC!$B$1:$B$420,$U33,_CALC_ALLOC!$D$1:$D$420,$W33,_CALC_ALLOC!$E$1:$E$420,$X33,_CALC_ALLOC!$F$1:$F$420,$Y33) -> 0 | I33: =SUMIFS(_CALC_ALLOC!$AR$1:$AR$420,_CALC_ALLOC!$AS$1:$AS$420,"2027|"&$P$1,_CALC_ALLOC!$B$1:$B$420,$U33,_CALC_ALLOC!$D$1:$D$420,$W33,_CALC_ALLOC!$E$1:$E$420,$X33,_CALC_ALLOC!$F$1:$F$420,$Y33) -> 0 | J33: =SUMIFS(_CALC_ALLOC!$AM$1:$AM$420,_CALC_ALLOC!$AS$1:$AS$420,"2027|"&$P$1,_CALC_ALLOC!$B$1:$B$420,$U33,_CALC_ALLOC!$D$1:$D$420,$W33,_CALC_ALLOC!$E$1:$E$420,$X33,_CALC_ALLOC!$F$1:$F$420,$Y33) -> 0 | K33: =E33+F33+G33+H33+I33+J33 -> 0 | L33: =SUMIFS(_CALC_ALLOC!$AN$1:$AN$420,_CALC_ALLOC!$AS$1:$AS$420,"2027|"&$P$1,_CALC_ALLOC!$B$1:$B$420,$U33,_CALC_ALLOC!$D$1:$D$420,$W33,_CALC_ALLOC!$E$1:$E$420,$X33,_CALC_ALLOC!$F$1:$F$420,$Y33) -> 0 | M33: =IF(D33=0,0,L33/D33) -> 0 | T33: MBWAY_NAN|BAC_MGT|B2|ALT | U33: MBWAY_NAN | V33: MBWAY | W33: BAC_MGT | X33: B2 | Y33: ALT | Z33: 3 | BF33: 2027BUD_V1 | BG33: ACT | BH33: 12 | BI33: 2024 | BJ33: MBWAY_LYO | BK33: MBWAY | BL33: BAC_MGT | BM33: B3 | BN33: ALT | BO33: 56 | BP33: 2 | BQ33: 411600 | BR33: 22036.132 | BS33: 56754.186 | BT33: 21319.654 | BU33: 134255.48 | BV33: 8277.6861 | BW33: 42317.566 | BX33: 50595.252 | BY33: 43355.786 | BZ33: 241604.92 | CA33: 284960.71 | CB33: 126639.29 | CC33: 0 | CD33: 143235 | CE33: 368902.58 | CF33: 110025 | CG33: 34532 | CH33: 872661.51 | CI33: 2639292 | CJ33: 499926
B34: Bachelor Management, 3e année, alternance | C34: =SUMIFS(_CALC_ALLOC!$G$1:$G$420,_CALC_ALLOC!$AS$1:$AS$420,"2027|"&$P$1,_CALC_ALLOC!$B$1:$B$420,$U34,_CALC_ALLOC!$D$1:$D$420,$W34,_CALC_ALLOC!$E$1:$E$420,$X34,_CALC_ALLOC!$F$1:$F$420,$Y34) -> 0 | D34: =SUMIFS(_CALC_ALLOC!$I$1:$I$420,_CALC_ALLOC!$AS$1:$AS$420,"2027|"&$P$1,_CALC_ALLOC!$B$1:$B$420,$U34,_CALC_ALLOC!$D$1:$D$420,$W34,_CALC_ALLOC!$E$1:$E$420,$X34,_CALC_ALLOC!$F$1:$F$420,$Y34) -> 0 | E34: =SUMIFS(_CALC_ALLOC!$AI$1:$AI$420,_CALC_ALLOC!$AS$1:$AS$420,"2027|"&$P$1,_CALC_ALLOC!$B$1:$B$420,$U34,_CALC_ALLOC!$D$1:$D$420,$W34,_CALC_ALLOC!$E$1:$E$420,$X34,_CALC_ALLOC!$F$1:$F$420,$Y34) -> 0 | F34: =SUMIFS(_CALC_ALLOC!$AJ$1:$AJ$420,_CALC_ALLOC!$AS$1:$AS$420,"2027|"&$P$1,_CALC_ALLOC!$B$1:$B$420,$U34,_CALC_ALLOC!$D$1:$D$420,$W34,_CALC_ALLOC!$E$1:$E$420,$X34,_CALC_ALLOC!$F$1:$F$420,$Y34) -> 0 | G34: =SUMIFS(_CALC_ALLOC!$AK$1:$AK$420,_CALC_ALLOC!$AS$1:$AS$420,"2027|"&$P$1,_CALC_ALLOC!$B$1:$B$420,$U34,_CALC_ALLOC!$D$1:$D$420,$W34,_CALC_ALLOC!$E$1:$E$420,$X34,_CALC_ALLOC!$F$1:$F$420,$Y34) -> 0 | H34: =SUMIFS(_CALC_ALLOC!$AL$1:$AL$420,_CALC_ALLOC!$AS$1:$AS$420,"2027|"&$P$1,_CALC_ALLOC!$B$1:$B$420,$U34,_CALC_ALLOC!$D$1:$D$420,$W34,_CALC_ALLOC!$E$1:$E$420,$X34,_CALC_ALLOC!$F$1:$F$420,$Y34) -> 0 | I34: =SUMIFS(_CALC_ALLOC!$AR$1:$AR$420,_CALC_ALLOC!$AS$1:$AS$420,"2027|"&$P$1,_CALC_ALLOC!$B$1:$B$420,$U34,_CALC_ALLOC!$D$1:$D$420,$W34,_CALC_ALLOC!$E$1:$E$420,$X34,_CALC_ALLOC!$F$1:$F$420,$Y34) -> 0 | J34: =SUMIFS(_CALC_ALLOC!$AM$1:$AM$420,_CALC_ALLOC!$AS$1:$AS$420,"2027|"&$P$1,_CALC_ALLOC!$B$1:$B$420,$U34,_CALC_ALLOC!$D$1:$D$420,$W34,_CALC_ALLOC!$E$1:$E$420,$X34,_CALC_ALLOC!$F$1:$F$420,$Y34) -> 0 | K34: =E34+F34+G34+H34+I34+J34 -> 0 | L34: =SUMIFS(_CALC_ALLOC!$AN$1:$AN$420,_CALC_ALLOC!$AS$1:$AS$420,"2027|"&$P$1,_CALC_ALLOC!$B$1:$B$420,$U34,_CALC_ALLOC!$D$1:$D$420,$W34,_CALC_ALLOC!$E$1:$E$420,$X34,_CALC_ALLOC!$F$1:$F$420,$Y34) -> 0 | M34: =IF(D34=0,0,L34/D34) -> 0 | T34: MBWAY_NAN|BAC_MGT|B3|ALT | U34: MBWAY_NAN | V34: MBWAY | W34: BAC_MGT | X34: B3 | Y34: ALT | Z34: 3 | BF34: 2027BUD_V1 | BG34: ACT | BH34: 12 | BI34: 2024 | BJ34: MBWAY_LYO | BK34: MBWAY | BL34: MAS_MGT | BM34: M1 | BN34: ALT | BO34: 59 | BP34: 3 | BQ34: 469935 | BR34: 28922.441 | BS34: 74489.916 | BT34: 39727.824 | BU34: 201383.22 | BV34: 12416.529 | BW34: 63476.349 | BX34: 75892.878 | BY34: 68650.265 | BZ34: 351766.02 | CA34: 420416.28 | CB34: 49518.717 | CC34: 59 | CD34: 143235 | CE34: 368902.58 | CF34: 110025 | CG34: 34532 | CH34: 872661.51 | CI34: 2639292 | CJ34: 499926
B35: Mastère Management, 1re année, alternance | C35: =SUMIFS(_CALC_ALLOC!$G$1:$G$420,_CALC_ALLOC!$AS$1:$AS$420,"2027|"&$P$1,_CALC_ALLOC!$B$1:$B$420,$U35,_CALC_ALLOC!$D$1:$D$420,$W35,_CALC_ALLOC!$E$1:$E$420,$X35,_CALC_ALLOC!$F$1:$F$420,$Y35) -> 0 | D35: =SUMIFS(_CALC_ALLOC!$I$1:$I$420,_CALC_ALLOC!$AS$1:$AS$420,"2027|"&$P$1,_CALC_ALLOC!$B$1:$B$420,$U35,_CALC_ALLOC!$D$1:$D$420,$W35,_CALC_ALLOC!$E$1:$E$420,$X35,_CALC_ALLOC!$F$1:$F$420,$Y35) -> 0 | E35: =SUMIFS(_CALC_ALLOC!$AI$1:$AI$420,_CALC_ALLOC!$AS$1:$AS$420,"2027|"&$P$1,_CALC_ALLOC!$B$1:$B$420,$U35,_CALC_ALLOC!$D$1:$D$420,$W35,_CALC_ALLOC!$E$1:$E$420,$X35,_CALC_ALLOC!$F$1:$F$420,$Y35) -> 0 | F35: =SUMIFS(_CALC_ALLOC!$AJ$1:$AJ$420,_CALC_ALLOC!$AS$1:$AS$420,"2027|"&$P$1,_CALC_ALLOC!$B$1:$B$420,$U35,_CALC_ALLOC!$D$1:$D$420,$W35,_CALC_ALLOC!$E$1:$E$420,$X35,_CALC_ALLOC!$F$1:$F$420,$Y35) -> 0 | G35: =SUMIFS(_CALC_ALLOC!$AK$1:$AK$420,_CALC_ALLOC!$AS$1:$AS$420,"2027|"&$P$1,_CALC_ALLOC!$B$1:$B$420,$U35,_CALC_ALLOC!$D$1:$D$420,$W35,_CALC_ALLOC!$E$1:$E$420,$X35,_CALC_ALLOC!$F$1:$F$420,$Y35) -> 0 | H35: =SUMIFS(_CALC_ALLOC!$AL$1:$AL$420,_CALC_ALLOC!$AS$1:$AS$420,"2027|"&$P$1,_CALC_ALLOC!$B$1:$B$420,$U35,_CALC_ALLOC!$D$1:$D$420,$W35,_CALC_ALLOC!$E$1:$E$420,$X35,_CALC_ALLOC!$F$1:$F$420,$Y35) -> 0 | I35: =SUMIFS(_CALC_ALLOC!$AR$1:$AR$420,_CALC_ALLOC!$AS$1:$AS$420,"2027|"&$P$1,_CALC_ALLOC!$B$1:$B$420,$U35,_CALC_ALLOC!$D$1:$D$420,$W35,_CALC_ALLOC!$E$1:$E$420,$X35,_CALC_ALLOC!$F$1:$F$420,$Y35) -> 0 | J35: =SUMIFS(_CALC_ALLOC!$AM$1:$AM$420,_CALC_ALLOC!$AS$1:$AS$420,"2027|"&$P$1,_CALC_ALLOC!$B$1:$B$420,$U35,_CALC_ALLOC!$D$1:$D$420,$W35,_CALC_ALLOC!$E$1:$E$420,$X35,_CALC_ALLOC!$F$1:$F$420,$Y35) -> 0 | K35: =E35+F35+G35+H35+I35+J35 -> 0 | L35: =SUMIFS(_CALC_ALLOC!$AN$1:$AN$420,_CALC_ALLOC!$AS$1:$AS$420,"2027|"&$P$1,_CALC_ALLOC!$B$1:$B$420,$U35,_CALC_ALLOC!$D$1:$D$420,$W35,_CALC_ALLOC!$E$1:$E$420,$X35,_CALC_ALLOC!$F$1:$F$420,$Y35) -> 0 | M35: =IF(D35=0,0,L35/D35) -> 0 | T35: MBWAY_NAN|MAS_MGT|M1|ALT | U35: MBWAY_NAN | V35: MBWAY | W35: MAS_MGT | X35: M1 | Y35: ALT | Z35: 3 | BF35: 2027BUD_V1 | BG35: ACT | BH35: 12 | BI35: 2024 | BJ35: MBWAY_LYO | BK35: MBWAY | BL35: MAS_MGT | BM35: M2 | BN35: ALT | BO35: 58 | BP35: 3 | BQ35: 456750 | BR35: 28922.441 | BS35: 74489.916 | BT35: 22081.137 | BU35: 201383.22 | BV35: 12416.529 | BW35: 63476.349 | BX35: 75892.878 | BY35: 51003.578 | BZ35: 351766.02 | CA35: 402769.6 | CB35: 53980.404 | CC35: 0 | CD35: 143235 | CE35: 368902.58 | CF35: 110025 | CG35: 34532 | CH35: 872661.51 | CI35: 2639292 | CJ35: 499926
B36: Mastère Management, 2e année, alternance | C36: =SUMIFS(_CALC_ALLOC!$G$1:$G$420,_CALC_ALLOC!$AS$1:$AS$420,"2027|"&$P$1,_CALC_ALLOC!$B$1:$B$420,$U36,_CALC_ALLOC!$D$1:$D$420,$W36,_CALC_ALLOC!$E$1:$E$420,$X36,_CALC_ALLOC!$F$1:$F$420,$Y36) -> 0 | D36: =SUMIFS(_CALC_ALLOC!$I$1:$I$420,_CALC_ALLOC!$AS$1:$AS$420,"2027|"&$P$1,_CALC_ALLOC!$B$1:$B$420,$U36,_CALC_ALLOC!$D$1:$D$420,$W36,_CALC_ALLOC!$E$1:$E$420,$X36,_CALC_ALLOC!$F$1:$F$420,$Y36) -> 0 | E36: =SUMIFS(_CALC_ALLOC!$AI$1:$AI$420,_CALC_ALLOC!$AS$1:$AS$420,"2027|"&$P$1,_CALC_ALLOC!$B$1:$B$420,$U36,_CALC_ALLOC!$D$1:$D$420,$W36,_CALC_ALLOC!$E$1:$E$420,$X36,_CALC_ALLOC!$F$1:$F$420,$Y36) -> 0 | F36: =SUMIFS(_CALC_ALLOC!$AJ$1:$AJ$420,_CALC_ALLOC!$AS$1:$AS$420,"2027|"&$P$1,_CALC_ALLOC!$B$1:$B$420,$U36,_CALC_ALLOC!$D$1:$D$420,$W36,_CALC_ALLOC!$E$1:$E$420,$X36,_CALC_ALLOC!$F$1:$F$420,$Y36) -> 0 | G36: =SUMIFS(_CALC_ALLOC!$AK$1:$AK$420,_CALC_ALLOC!$AS$1:$AS$420,"2027|"&$P$1,_CALC_ALLOC!$B$1:$B$420,$U36,_CALC_ALLOC!$D$1:$D$420,$W36,_CALC_ALLOC!$E$1:$E$420,$X36,_CALC_ALLOC!$F$1:$F$420,$Y36) -> 0 | H36: =SUMIFS(_CALC_ALLOC!$AL$1:$AL$420,_CALC_ALLOC!$AS$1:$AS$420,"2027|"&$P$1,_CALC_ALLOC!$B$1:$B$420,$U36,_CALC_ALLOC!$D$1:$D$420,$W36,_CALC_ALLOC!$E$1:$E$420,$X36,_CALC_ALLOC!$F$1:$F$420,$Y36) -> 0 | I36: =SUMIFS(_CALC_ALLOC!$AR$1:$AR$420,_CALC_ALLOC!$AS$1:$AS$420,"2027|"&$P$1,_CALC_ALLOC!$B$1:$B$420,$U36,_CALC_ALLOC!$D$1:$D$420,$W36,_CALC_ALLOC!$E$1:$E$420,$X36,_CALC_ALLOC!$F$1:$F$420,$Y36) -> 0 | J36: =SUMIFS(_CALC_ALLOC!$AM$1:$AM$420,_CALC_ALLOC!$AS$1:$AS$420,"2027|"&$P$1,_CALC_ALLOC!$B$1:$B$420,$U36,_CALC_ALLOC!$D$1:$D$420,$W36,_CALC_ALLOC!$E$1:$E$420,$X36,_CALC_ALLOC!$F$1:$F$420,$Y36) -> 0 | K36: =E36+F36+G36+H36+I36+J36 -> 0 | L36: =SUMIFS(_CALC_ALLOC!$AN$1:$AN$420,_CALC_ALLOC!$AS$1:$AS$420,"2027|"&$P$1,_CALC_ALLOC!$B$1:$B$420,$U36,_CALC_ALLOC!$D$1:$D$420,$W36,_CALC_ALLOC!$E$1:$E$420,$X36,_CALC_ALLOC!$F$1:$F$420,$Y36) -> 0 | M36: =IF(D36=0,0,L36/D36) -> 0 | T36: MBWAY_NAN|MAS_MGT|M2|ALT | U36: MBWAY_NAN | V36: MBWAY | W36: MAS_MGT | X36: M2 | Y36: ALT | Z36: 3 | BF36: 2027BUD_V1 | BG36: ACT | BH36: 12 | BI36: 2024 | BJ36: MBWAY_NAN | BK36: MBWAY | BL36: BAC_MGT | BM36: B1 | BN36: INIT | BO36: 53 | BP36: 2 | BQ36: 402270 | BR36: 28130.937 | BS36: 67425.875 | BT36: 33226.027 | BU36: 123506.23 | BV36: 8129.6605 | BW36: 41560.823 | BX36: 49690.483 | BY36: 61356.964 | BZ36: 240622.59 | CA36: 301979.55 | CB36: 100290.45 | CC36: 53 | CD36: 132216 | CE36: 316903.04 | CF36: 99837 | CG36: 26060 | CH36: 741040.34 | CI36: 2639292 | CJ36: 499926
B37: Bordeaux | C37: =SUMIFS(_CALC_ALLOC!$G$1:$G$420,_CALC_ALLOC!$AS$1:$AS$420,"2027|"&$P$1,_CALC_ALLOC!$B$1:$B$420,$U37) -> 0 | D37: =SUMIFS(_CALC_ALLOC!$I$1:$I$420,_CALC_ALLOC!$AS$1:$AS$420,"2027|"&$P$1,_CALC_ALLOC!$B$1:$B$420,$U37) -> 0 | E37: =SUMIFS(_CALC_ALLOC!$AI$1:$AI$420,_CALC_ALLOC!$AS$1:$AS$420,"2027|"&$P$1,_CALC_ALLOC!$B$1:$B$420,$U37) -> 0 | F37: =SUMIFS(_CALC_ALLOC!$AJ$1:$AJ$420,_CALC_ALLOC!$AS$1:$AS$420,"2027|"&$P$1,_CALC_ALLOC!$B$1:$B$420,$U37) -> 0 | G37: =SUMIFS(_CALC_ALLOC!$AK$1:$AK$420,_CALC_ALLOC!$AS$1:$AS$420,"2027|"&$P$1,_CALC_ALLOC!$B$1:$B$420,$U37) -> 0 | H37: =SUMIFS(_CALC_ALLOC!$AL$1:$AL$420,_CALC_ALLOC!$AS$1:$AS$420,"2027|"&$P$1,_CALC_ALLOC!$B$1:$B$420,$U37) -> 0 | I37: =SUMIFS(_CALC_ALLOC!$AR$1:$AR$420,_CALC_ALLOC!$AS$1:$AS$420,"2027|"&$P$1,_CALC_ALLOC!$B$1:$B$420,$U37) -> 0 | J37: =SUMIFS(_CALC_ALLOC!$AM$1:$AM$420,_CALC_ALLOC!$AS$1:$AS$420,"2027|"&$P$1,_CALC_ALLOC!$B$1:$B$420,$U37) -> 0 | K37: =E37+F37+G37+H37+I37+J37 -> 0 | L37: =SUMIFS(_CALC_ALLOC!$AN$1:$AN$420,_CALC_ALLOC!$AS$1:$AS$420,"2027|"&$P$1,_CALC_ALLOC!$B$1:$B$420,$U37) -> 0 | M37: =IF(D37=0,0,L37/D37) -> 0 | T37: MBWAY_BOR | U37: MBWAY_BOR | V37: MBWAY | Z37: 2 | BF37: 2027BUD_V1 | BG37: ACT | BH37: 12 | BI37: 2024 | BJ37: MBWAY_NAN | BK37: MBWAY | BL37: BAC_MGT | BM37: B2 | BN37: ALT | BO37: 52 | BP37: 2 | BQ37: 364000 | BR37: 22504.75 | BS37: 53940.7 | BT37: 19814.949 | BU37: 123506.23 | BV37: 8129.6605 | BW37: 41560.823 | BX37: 49690.483 | BY37: 42319.699 | BZ37: 227137.41 | CA37: 269457.11 | CB37: 94542.889 | CC37: 0 | CD37: 132216 | CE37: 316903.04 | CF37: 99837 | CG37: 26060 | CH37: 741040.34 | CI37: 2639292 | CJ37: 499926
B38: Bachelor Management, 1re année, initial | C38: =SUMIFS(_CALC_ALLOC!$G$1:$G$420,_CALC_ALLOC!$AS$1:$AS$420,"2027|"&$P$1,_CALC_ALLOC!$B$1:$B$420,$U38,_CALC_ALLOC!$D$1:$D$420,$W38,_CALC_ALLOC!$E$1:$E$420,$X38,_CALC_ALLOC!$F$1:$F$420,$Y38) -> 0 | D38: =SUMIFS(_CALC_ALLOC!$I$1:$I$420,_CALC_ALLOC!$AS$1:$AS$420,"2027|"&$P$1,_CALC_ALLOC!$B$1:$B$420,$U38,_CALC_ALLOC!$D$1:$D$420,$W38,_CALC_ALLOC!$E$1:$E$420,$X38,_CALC_ALLOC!$F$1:$F$420,$Y38) -> 0 | E38: =SUMIFS(_CALC_ALLOC!$AI$1:$AI$420,_CALC_ALLOC!$AS$1:$AS$420,"2027|"&$P$1,_CALC_ALLOC!$B$1:$B$420,$U38,_CALC_ALLOC!$D$1:$D$420,$W38,_CALC_ALLOC!$E$1:$E$420,$X38,_CALC_ALLOC!$F$1:$F$420,$Y38) -> 0 | F38: =SUMIFS(_CALC_ALLOC!$AJ$1:$AJ$420,_CALC_ALLOC!$AS$1:$AS$420,"2027|"&$P$1,_CALC_ALLOC!$B$1:$B$420,$U38,_CALC_ALLOC!$D$1:$D$420,$W38,_CALC_ALLOC!$E$1:$E$420,$X38,_CALC_ALLOC!$F$1:$F$420,$Y38) -> 0 | G38: =SUMIFS(_CALC_ALLOC!$AK$1:$AK$420,_CALC_ALLOC!$AS$1:$AS$420,"2027|"&$P$1,_CALC_ALLOC!$B$1:$B$420,$U38,_CALC_ALLOC!$D$1:$D$420,$W38,_CALC_ALLOC!$E$1:$E$420,$X38,_CALC_ALLOC!$F$1:$F$420,$Y38) -> 0 | H38: =SUMIFS(_CALC_ALLOC!$AL$1:$AL$420,_CALC_ALLOC!$AS$1:$AS$420,"2027|"&$P$1,_CALC_ALLOC!$B$1:$B$420,$U38,_CALC_ALLOC!$D$1:$D$420,$W38,_CALC_ALLOC!$E$1:$E$420,$X38,_CALC_ALLOC!$F$1:$F$420,$Y38) -> 0 | I38: =SUMIFS(_CALC_ALLOC!$AR$1:$AR$420,_CALC_ALLOC!$AS$1:$AS$420,"2027|"&$P$1,_CALC_ALLOC!$B$1:$B$420,$U38,_CALC_ALLOC!$D$1:$D$420,$W38,_CALC_ALLOC!$E$1:$E$420,$X38,_CALC_ALLOC!$F$1:$F$420,$Y38) -> 0 | J38: =SUMIFS(_CALC_ALLOC!$AM$1:$AM$420,_CALC_ALLOC!$AS$1:$AS$420,"2027|"&$P$1,_CALC_ALLOC!$B$1:$B$420,$U38,_CALC_ALLOC!$D$1:$D$420,$W38,_CALC_ALLOC!$E$1:$E$420,$X38,_CALC_ALLOC!$F$1:$F$420,$Y38) -> 0 | K38: =E38+F38+G38+H38+I38+J38 -> 0 | L38: =SUMIFS(_CALC_ALLOC!$AN$1:$AN$420,_CALC_ALLOC!$AS$1:$AS$420,"2027|"&$P$1,_CALC_ALLOC!$B$1:$B$420,$U38,_CALC_ALLOC!$D$1:$D$420,$W38,_CALC_ALLOC!$E$1:$E$420,$X38,_CALC_ALLOC!$F$1:$F$420,$Y38) -> 0 | M38: =IF(D38=0,0,L38/D38) -> 0 | T38: MBWAY_BOR|BAC_MGT|B1|INIT | U38: MBWAY_BOR | V38: MBWAY | W38: BAC_MGT | X38: B1 | Y38: INIT | Z38: 3 | BF38: 2027BUD_V1 | BG38: ACT | BH38: 12 | BI38: 2024 | BJ38: MBWAY_NAN | BK38: MBWAY | BL38: BAC_MGT | BM38: B3 | BN38: ALT | BO38: 51 | BP38: 2 | BQ38: 357000 | BR38: 22504.75 | BS38: 53940.7 | BT38: 19433.871 | BU38: 123506.23 | BV38: 8129.6605 | BW38: 41560.823 | BX38: 49690.483 | BY38: 41938.621 | BZ38: 227137.41 | CA38: 269076.03 | CB38: 87923.966 | CC38: 0 | CD38: 132216 | CE38: 316903.04 | CF38: 99837 | CG38: 26060 | CH38: 741040.34 | CI38: 2639292 | CJ38: 499926
B39: Bachelor Management, 2e année, alternance | C39: =SUMIFS(_CALC_ALLOC!$G$1:$G$420,_CALC_ALLOC!$AS$1:$AS$420,"2027|"&$P$1,_CALC_ALLOC!$B$1:$B$420,$U39,_CALC_ALLOC!$D$1:$D$420,$W39,_CALC_ALLOC!$E$1:$E$420,$X39,_CALC_ALLOC!$F$1:$F$420,$Y39) -> 0 | D39: =SUMIFS(_CALC_ALLOC!$I$1:$I$420,_CALC_ALLOC!$AS$1:$AS$420,"2027|"&$P$1,_CALC_ALLOC!$B$1:$B$420,$U39,_CALC_ALLOC!$D$1:$D$420,$W39,_CALC_ALLOC!$E$1:$E$420,$X39,_CALC_ALLOC!$F$1:$F$420,$Y39) -> 0 | E39: =SUMIFS(_CALC_ALLOC!$AI$1:$AI$420,_CALC_ALLOC!$AS$1:$AS$420,"2027|"&$P$1,_CALC_ALLOC!$B$1:$B$420,$U39,_CALC_ALLOC!$D$1:$D$420,$W39,_CALC_ALLOC!$E$1:$E$420,$X39,_CALC_ALLOC!$F$1:$F$420,$Y39) -> 0 | F39: =SUMIFS(_CALC_ALLOC!$AJ$1:$AJ$420,_CALC_ALLOC!$AS$1:$AS$420,"2027|"&$P$1,_CALC_ALLOC!$B$1:$B$420,$U39,_CALC_ALLOC!$D$1:$D$420,$W39,_CALC_ALLOC!$E$1:$E$420,$X39,_CALC_ALLOC!$F$1:$F$420,$Y39) -> 0 | G39: =SUMIFS(_CALC_ALLOC!$AK$1:$AK$420,_CALC_ALLOC!$AS$1:$AS$420,"2027|"&$P$1,_CALC_ALLOC!$B$1:$B$420,$U39,_CALC_ALLOC!$D$1:$D$420,$W39,_CALC_ALLOC!$E$1:$E$420,$X39,_CALC_ALLOC!$F$1:$F$420,$Y39) -> 0 | H39: =SUMIFS(_CALC_ALLOC!$AL$1:$AL$420,_CALC_ALLOC!$AS$1:$AS$420,"2027|"&$P$1,_CALC_ALLOC!$B$1:$B$420,$U39,_CALC_ALLOC!$D$1:$D$420,$W39,_CALC_ALLOC!$E$1:$E$420,$X39,_CALC_ALLOC!$F$1:$F$420,$Y39) -> 0 | I39: =SUMIFS(_CALC_ALLOC!$AR$1:$AR$420,_CALC_ALLOC!$AS$1:$AS$420,"2027|"&$P$1,_CALC_ALLOC!$B$1:$B$420,$U39,_CALC_ALLOC!$D$1:$D$420,$W39,_CALC_ALLOC!$E$1:$E$420,$X39,_CALC_ALLOC!$F$1:$F$420,$Y39) -> 0 | J39: =SUMIFS(_CALC_ALLOC!$AM$1:$AM$420,_CALC_ALLOC!$AS$1:$AS$420,"2027|"&$P$1,_CALC_ALLOC!$B$1:$B$420,$U39,_CALC_ALLOC!$D$1:$D$420,$W39,_CALC_ALLOC!$E$1:$E$420,$X39,_CALC_ALLOC!$F$1:$F$420,$Y39) -> 0 | K39: =E39+F39+G39+H39+I39+J39 -> 0 | L39: =SUMIFS(_CALC_ALLOC!$AN$1:$AN$420,_CALC_ALLOC!$AS$1:$AS$420,"2027|"&$P$1,_CALC_ALLOC!$B$1:$B$420,$U39,_CALC_ALLOC!$D$1:$D$420,$W39,_CALC_ALLOC!$E$1:$E$420,$X39,_CALC_ALLOC!$F$1:$F$420,$Y39) -> 0 | M39: =IF(D39=0,0,L39/D39) -> 0 | T39: MBWAY_BOR|BAC_MGT|B2|ALT | U39: MBWAY_BOR | V39: MBWAY | W39: BAC_MGT | X39: B2 | Y39: ALT | Z39: 3 | BF39: 2027BUD_V1 | BG39: ACT | BH39: 12 | BI39: 2024 | BJ39: MBWAY_NAN | BK39: MBWAY | BL39: MAS_MGT | BM39: M1 | BN39: ALT | BO39: 53 | BP39: 3 | BQ39: 402270 | BR39: 29537.583 | BS39: 70797.407 | BT39: 33226.027 | BU39: 185260.08 | BV39: 12194.539 | BW39: 62341.483 | BX39: 74536.023 | BY39: 62763.61 | BZ39: 330593.51 | CA39: 393357.12 | CB39: 8912.8754 | CC39: 53 | CD39: 132216 | CE39: 316903.04 | CF39: 99837 | CG39: 26060 | CH39: 741040.34 | CI39: 2639292 | CJ39: 499926
B40: Bachelor Management, 3e année, alternance | C40: =SUMIFS(_CALC_ALLOC!$G$1:$G$420,_CALC_ALLOC!$AS$1:$AS$420,"2027|"&$P$1,_CALC_ALLOC!$B$1:$B$420,$U40,_CALC_ALLOC!$D$1:$D$420,$W40,_CALC_ALLOC!$E$1:$E$420,$X40,_CALC_ALLOC!$F$1:$F$420,$Y40) -> 0 | D40: =SUMIFS(_CALC_ALLOC!$I$1:$I$420,_CALC_ALLOC!$AS$1:$AS$420,"2027|"&$P$1,_CALC_ALLOC!$B$1:$B$420,$U40,_CALC_ALLOC!$D$1:$D$420,$W40,_CALC_ALLOC!$E$1:$E$420,$X40,_CALC_ALLOC!$F$1:$F$420,$Y40) -> 0 | E40: =SUMIFS(_CALC_ALLOC!$AI$1:$AI$420,_CALC_ALLOC!$AS$1:$AS$420,"2027|"&$P$1,_CALC_ALLOC!$B$1:$B$420,$U40,_CALC_ALLOC!$D$1:$D$420,$W40,_CALC_ALLOC!$E$1:$E$420,$X40,_CALC_ALLOC!$F$1:$F$420,$Y40) -> 0 | F40: =SUMIFS(_CALC_ALLOC!$AJ$1:$AJ$420,_CALC_ALLOC!$AS$1:$AS$420,"2027|"&$P$1,_CALC_ALLOC!$B$1:$B$420,$U40,_CALC_ALLOC!$D$1:$D$420,$W40,_CALC_ALLOC!$E$1:$E$420,$X40,_CALC_ALLOC!$F$1:$F$420,$Y40) -> 0 | G40: =SUMIFS(_CALC_ALLOC!$AK$1:$AK$420,_CALC_ALLOC!$AS$1:$AS$420,"2027|"&$P$1,_CALC_ALLOC!$B$1:$B$420,$U40,_CALC_ALLOC!$D$1:$D$420,$W40,_CALC_ALLOC!$E$1:$E$420,$X40,_CALC_ALLOC!$F$1:$F$420,$Y40) -> 0 | H40: =SUMIFS(_CALC_ALLOC!$AL$1:$AL$420,_CALC_ALLOC!$AS$1:$AS$420,"2027|"&$P$1,_CALC_ALLOC!$B$1:$B$420,$U40,_CALC_ALLOC!$D$1:$D$420,$W40,_CALC_ALLOC!$E$1:$E$420,$X40,_CALC_ALLOC!$F$1:$F$420,$Y40) -> 0 | I40: =SUMIFS(_CALC_ALLOC!$AR$1:$AR$420,_CALC_ALLOC!$AS$1:$AS$420,"2027|"&$P$1,_CALC_ALLOC!$B$1:$B$420,$U40,_CALC_ALLOC!$D$1:$D$420,$W40,_CALC_ALLOC!$E$1:$E$420,$X40,_CALC_ALLOC!$F$1:$F$420,$Y40) -> 0 | J40: =SUMIFS(_CALC_ALLOC!$AM$1:$AM$420,_CALC_ALLOC!$AS$1:$AS$420,"2027|"&$P$1,_CALC_ALLOC!$B$1:$B$420,$U40,_CALC_ALLOC!$D$1:$D$420,$W40,_CALC_ALLOC!$E$1:$E$420,$X40,_CALC_ALLOC!$F$1:$F$420,$Y40) -> 0 | K40: =E40+F40+G40+H40+I40+J40 -> 0 | L40: =SUMIFS(_CALC_ALLOC!$AN$1:$AN$420,_CALC_ALLOC!$AS$1:$AS$420,"2027|"&$P$1,_CALC_ALLOC!$B$1:$B$420,$U40,_CALC_ALLOC!$D$1:$D$420,$W40,_CALC_ALLOC!$E$1:$E$420,$X40,_CALC_ALLOC!$F$1:$F$420,$Y40) -> 0 | M40: =IF(D40=0,0,L40/D40) -> 0 | T40: MBWAY_BOR|BAC_MGT|B3|ALT | U40: MBWAY_BOR | V40: MBWAY | W40: BAC_MGT | X40: B3 | Y40: ALT | Z40: 3 | BF40: 2027BUD_V1 | BG40: ACT | BH40: 12 | BI40: 2024 | BJ40: MBWAY_NAN | BK40: MBWAY | BL40: MAS_MGT | BM40: M2 | BN40: ALT | BO40: 53 | BP40: 3 | BQ40: 397500 | BR40: 29537.583 | BS40: 70797.407 | BT40: 20196.027 | BU40: 185260.08 | BV40: 12194.539 | BW40: 62341.483 | BX40: 74536.023 | BY40: 49733.61 | BZ40: 330593.51 | CA40: 380327.12 | CB40: 17172.875 | CC40: 0 | CD40: 132216 | CE40: 316903.04 | CF40: 99837 | CG40: 26060 | CH40: 741040.34 | CI40: 2639292 | CJ40: 499926
B41: Mastère Management, 1re année, alternance | C41: =SUMIFS(_CALC_ALLOC!$G$1:$G$420,_CALC_ALLOC!$AS$1:$AS$420,"2027|"&$P$1,_CALC_ALLOC!$B$1:$B$420,$U41,_CALC_ALLOC!$D$1:$D$420,$W41,_CALC_ALLOC!$E$1:$E$420,$X41,_CALC_ALLOC!$F$1:$F$420,$Y41) -> 0 | D41: =SUMIFS(_CALC_ALLOC!$I$1:$I$420,_CALC_ALLOC!$AS$1:$AS$420,"2027|"&$P$1,_CALC_ALLOC!$B$1:$B$420,$U41,_CALC_ALLOC!$D$1:$D$420,$W41,_CALC_ALLOC!$E$1:$E$420,$X41,_CALC_ALLOC!$F$1:$F$420,$Y41) -> 0 | E41: =SUMIFS(_CALC_ALLOC!$AI$1:$AI$420,_CALC_ALLOC!$AS$1:$AS$420,"2027|"&$P$1,_CALC_ALLOC!$B$1:$B$420,$U41,_CALC_ALLOC!$D$1:$D$420,$W41,_CALC_ALLOC!$E$1:$E$420,$X41,_CALC_ALLOC!$F$1:$F$420,$Y41) -> 0 | F41: =SUMIFS(_CALC_ALLOC!$AJ$1:$AJ$420,_CALC_ALLOC!$AS$1:$AS$420,"2027|"&$P$1,_CALC_ALLOC!$B$1:$B$420,$U41,_CALC_ALLOC!$D$1:$D$420,$W41,_CALC_ALLOC!$E$1:$E$420,$X41,_CALC_ALLOC!$F$1:$F$420,$Y41) -> 0 | G41: =SUMIFS(_CALC_ALLOC!$AK$1:$AK$420,_CALC_ALLOC!$AS$1:$AS$420,"2027|"&$P$1,_CALC_ALLOC!$B$1:$B$420,$U41,_CALC_ALLOC!$D$1:$D$420,$W41,_CALC_ALLOC!$E$1:$E$420,$X41,_CALC_ALLOC!$F$1:$F$420,$Y41) -> 0 | H41: =SUMIFS(_CALC_ALLOC!$AL$1:$AL$420,_CALC_ALLOC!$AS$1:$AS$420,"2027|"&$P$1,_CALC_ALLOC!$B$1:$B$420,$U41,_CALC_ALLOC!$D$1:$D$420,$W41,_CALC_ALLOC!$E$1:$E$420,$X41,_CALC_ALLOC!$F$1:$F$420,$Y41) -> 0 | I41: =SUMIFS(_CALC_ALLOC!$AR$1:$AR$420,_CALC_ALLOC!$AS$1:$AS$420,"2027|"&$P$1,_CALC_ALLOC!$B$1:$B$420,$U41,_CALC_ALLOC!$D$1:$D$420,$W41,_CALC_ALLOC!$E$1:$E$420,$X41,_CALC_ALLOC!$F$1:$F$420,$Y41) -> 0 | J41: =SUMIFS(_CALC_ALLOC!$AM$1:$AM$420,_CALC_ALLOC!$AS$1:$AS$420,"2027|"&$P$1,_CALC_ALLOC!$B$1:$B$420,$U41,_CALC_ALLOC!$D$1:$D$420,$W41,_CALC_ALLOC!$E$1:$E$420,$X41,_CALC_ALLOC!$F$1:$F$420,$Y41) -> 0 | K41: =E41+F41+G41+H41+I41+J41 -> 0 | L41: =SUMIFS(_CALC_ALLOC!$AN$1:$AN$420,_CALC_ALLOC!$AS$1:$AS$420,"2027|"&$P$1,_CALC_ALLOC!$B$1:$B$420,$U41,_CALC_ALLOC!$D$1:$D$420,$W41,_CALC_ALLOC!$E$1:$E$420,$X41,_CALC_ALLOC!$F$1:$F$420,$Y41) -> 0 | M41: =IF(D41=0,0,L41/D41) -> 0 | T41: MBWAY_BOR|MAS_MGT|M1|ALT | U41: MBWAY_BOR | V41: MBWAY | W41: MAS_MGT | X41: M1 | Y41: ALT | Z41: 3 | BF41: 2027BUD_V1 | BG41: ACT | BH41: 12 | BI41: 2024 | BJ41: MBWAY_PAR | BK41: MBWAY | BL41: BAC_MGT | BM41: B1 | BN41: INIT | BO41: 69 | BP41: 3 | BQ41: 585810 | BR41: 41317.75 | BS41: 115398.44 | BT41: 54544.507 | BU41: 221608.66 | BV41: 12659.991 | BW41: 64720.986 | BX41: 77380.977 | BY41: 95862.257 | BZ41: 414388.08 | CA41: 510250.34 | CB41: 75559.665 | CC41: 69 | CD41: 165271 | CE41: 461593.76 | CF41: 129720 | CG41: 56438 | CH41: 1108043.3 | CI41: 2639292 | CJ41: 499926
B42: Mastère Management, 2e année, alternance | C42: =SUMIFS(_CALC_ALLOC!$G$1:$G$420,_CALC_ALLOC!$AS$1:$AS$420,"2027|"&$P$1,_CALC_ALLOC!$B$1:$B$420,$U42,_CALC_ALLOC!$D$1:$D$420,$W42,_CALC_ALLOC!$E$1:$E$420,$X42,_CALC_ALLOC!$F$1:$F$420,$Y42) -> 0 | D42: =SUMIFS(_CALC_ALLOC!$I$1:$I$420,_CALC_ALLOC!$AS$1:$AS$420,"2027|"&$P$1,_CALC_ALLOC!$B$1:$B$420,$U42,_CALC_ALLOC!$D$1:$D$420,$W42,_CALC_ALLOC!$E$1:$E$420,$X42,_CALC_ALLOC!$F$1:$F$420,$Y42) -> 0 | E42: =SUMIFS(_CALC_ALLOC!$AI$1:$AI$420,_CALC_ALLOC!$AS$1:$AS$420,"2027|"&$P$1,_CALC_ALLOC!$B$1:$B$420,$U42,_CALC_ALLOC!$D$1:$D$420,$W42,_CALC_ALLOC!$E$1:$E$420,$X42,_CALC_ALLOC!$F$1:$F$420,$Y42) -> 0 | F42: =SUMIFS(_CALC_ALLOC!$AJ$1:$AJ$420,_CALC_ALLOC!$AS$1:$AS$420,"2027|"&$P$1,_CALC_ALLOC!$B$1:$B$420,$U42,_CALC_ALLOC!$D$1:$D$420,$W42,_CALC_ALLOC!$E$1:$E$420,$X42,_CALC_ALLOC!$F$1:$F$420,$Y42) -> 0 | G42: =SUMIFS(_CALC_ALLOC!$AK$1:$AK$420,_CALC_ALLOC!$AS$1:$AS$420,"2027|"&$P$1,_CALC_ALLOC!$B$1:$B$420,$U42,_CALC_ALLOC!$D$1:$D$420,$W42,_CALC_ALLOC!$E$1:$E$420,$X42,_CALC_ALLOC!$F$1:$F$420,$Y42) -> 0 | H42: =SUMIFS(_CALC_ALLOC!$AL$1:$AL$420,_CALC_ALLOC!$AS$1:$AS$420,"2027|"&$P$1,_CALC_ALLOC!$B$1:$B$420,$U42,_CALC_ALLOC!$D$1:$D$420,$W42,_CALC_ALLOC!$E$1:$E$420,$X42,_CALC_ALLOC!$F$1:$F$420,$Y42) -> 0 | I42: =SUMIFS(_CALC_ALLOC!$AR$1:$AR$420,_CALC_ALLOC!$AS$1:$AS$420,"2027|"&$P$1,_CALC_ALLOC!$B$1:$B$420,$U42,_CALC_ALLOC!$D$1:$D$420,$W42,_CALC_ALLOC!$E$1:$E$420,$X42,_CALC_ALLOC!$F$1:$F$420,$Y42) -> 0 | J42: =SUMIFS(_CALC_ALLOC!$AM$1:$AM$420,_CALC_ALLOC!$AS$1:$AS$420,"2027|"&$P$1,_CALC_ALLOC!$B$1:$B$420,$U42,_CALC_ALLOC!$D$1:$D$420,$W42,_CALC_ALLOC!$E$1:$E$420,$X42,_CALC_ALLOC!$F$1:$F$420,$Y42) -> 0 | K42: =E42+F42+G42+H42+I42+J42 -> 0 | L42: =SUMIFS(_CALC_ALLOC!$AN$1:$AN$420,_CALC_ALLOC!$AS$1:$AS$420,"2027|"&$P$1,_CALC_ALLOC!$B$1:$B$420,$U42,_CALC_ALLOC!$D$1:$D$420,$W42,_CALC_ALLOC!$E$1:$E$420,$X42,_CALC_ALLOC!$F$1:$F$420,$Y42) -> 0 | M42: =IF(D42=0,0,L42/D42) -> 0 | T42: MBWAY_BOR|MAS_MGT|M2|ALT | U42: MBWAY_BOR | V42: MBWAY | W42: MAS_MGT | X42: M2 | Y42: ALT | Z42: 3 | BF42: 2027BUD_V1 | BG42: ACT | BH42: 12 | BI42: 2024 | BJ42: MBWAY_PAR | BK42: MBWAY | BL42: BAC_MGT | BM42: B2 | BN42: ALT | BO42: 68 | BP42: 3 | BQ42: 533120 | BR42: 33054.2 | BS42: 92318.752 | BT42: 25944 | BU42: 221608.66 | BV42: 12659.991 | BW42: 64720.986 | BX42: 77380.977 | BY42: 58998.2 | BZ42: 391308.39 | CA42: 450306.59 | CB42: 82813.409 | CC42: 0 | CD42: 165271 | CE42: 461593.76 | CF42: 129720 | CG42: 56438 | CH42: 1108043.3 | CI42: 2639292 | CJ42: 499926
B43: ISCOM | C43: =SUMIFS(_CALC_ALLOC!$G$1:$G$420,_CALC_ALLOC!$AS$1:$AS$420,"2027|"&$P$1,_CALC_ALLOC!$C$1:$C$420,$V43) -> 0 | D43: =SUMIFS(_CALC_ALLOC!$I$1:$I$420,_CALC_ALLOC!$AS$1:$AS$420,"2027|"&$P$1,_CALC_ALLOC!$C$1:$C$420,$V43) -> 0 | E43: =SUMIFS(_CALC_ALLOC!$AI$1:$AI$420,_CALC_ALLOC!$AS$1:$AS$420,"2027|"&$P$1,_CALC_ALLOC!$C$1:$C$420,$V43) -> 0 | F43: =SUMIFS(_CALC_ALLOC!$AJ$1:$AJ$420,_CALC_ALLOC!$AS$1:$AS$420,"2027|"&$P$1,_CALC_ALLOC!$C$1:$C$420,$V43) -> 0 | G43: =SUMIFS(_CALC_ALLOC!$AK$1:$AK$420,_CALC_ALLOC!$AS$1:$AS$420,"2027|"&$P$1,_CALC_ALLOC!$C$1:$C$420,$V43) -> 0 | H43: =SUMIFS(_CALC_ALLOC!$AL$1:$AL$420,_CALC_ALLOC!$AS$1:$AS$420,"2027|"&$P$1,_CALC_ALLOC!$C$1:$C$420,$V43) -> 0 | I43: =SUMIFS(_CALC_ALLOC!$AR$1:$AR$420,_CALC_ALLOC!$AS$1:$AS$420,"2027|"&$P$1,_CALC_ALLOC!$C$1:$C$420,$V43) -> 0 | J43: =SUMIFS(_CALC_ALLOC!$AM$1:$AM$420,_CALC_ALLOC!$AS$1:$AS$420,"2027|"&$P$1,_CALC_ALLOC!$C$1:$C$420,$V43) -> 0 | K43: =E43+F43+G43+H43+I43+J43 -> 0 | L43: =SUMIFS(_CALC_ALLOC!$AN$1:$AN$420,_CALC_ALLOC!$AS$1:$AS$420,"2027|"&$P$1,_CALC_ALLOC!$C$1:$C$420,$V43) -> 0 | M43: =IF(D43=0,0,L43/D43) -> 0 | T43: ISCOM | V43: ISCOM | Z43: 1 | BF43: 2027BUD_V1 | BG43: ACT | BH43: 12 | BI43: 2024 | BJ43: MBWAY_PAR | BK43: MBWAY | BL43: BAC_MGT | BM43: B3 | BN43: ALT | BO43: 66 | BP43: 3 | BQ43: 517440 | BR43: 33054.2 | BS43: 92318.752 | BT43: 25180.857 | BU43: 221608.66 | BV43: 12659.991 | BW43: 64720.986 | BX43: 77380.977 | BY43: 58235.057 | BZ43: 391308.39 | CA43: 449543.45 | CB43: 67896.552 | CC43: 0 | CD43: 165271 | CE43: 461593.76 | CF43: 129720 | CG43: 56438 | CH43: 1108043.3 | CI43: 2639292 | CJ43: 499926
B44: Paris | C44: =SUMIFS(_CALC_ALLOC!$G$1:$G$420,_CALC_ALLOC!$AS$1:$AS$420,"2027|"&$P$1,_CALC_ALLOC!$B$1:$B$420,$U44) -> 0 | D44: =SUMIFS(_CALC_ALLOC!$I$1:$I$420,_CALC_ALLOC!$AS$1:$AS$420,"2027|"&$P$1,_CALC_ALLOC!$B$1:$B$420,$U44) -> 0 | E44: =SUMIFS(_CALC_ALLOC!$AI$1:$AI$420,_CALC_ALLOC!$AS$1:$AS$420,"2027|"&$P$1,_CALC_ALLOC!$B$1:$B$420,$U44) -> 0 | F44: =SUMIFS(_CALC_ALLOC!$AJ$1:$AJ$420,_CALC_ALLOC!$AS$1:$AS$420,"2027|"&$P$1,_CALC_ALLOC!$B$1:$B$420,$U44) -> 0 | G44: =SUMIFS(_CALC_ALLOC!$AK$1:$AK$420,_CALC_ALLOC!$AS$1:$AS$420,"2027|"&$P$1,_CALC_ALLOC!$B$1:$B$420,$U44) -> 0 | H44: =SUMIFS(_CALC_ALLOC!$AL$1:$AL$420,_CALC_ALLOC!$AS$1:$AS$420,"2027|"&$P$1,_CALC_ALLOC!$B$1:$B$420,$U44) -> 0 | I44: =SUMIFS(_CALC_ALLOC!$AR$1:$AR$420,_CALC_ALLOC!$AS$1:$AS$420,"2027|"&$P$1,_CALC_ALLOC!$B$1:$B$420,$U44) -> 0 | J44: =SUMIFS(_CALC_ALLOC!$AM$1:$AM$420,_CALC_ALLOC!$AS$1:$AS$420,"2027|"&$P$1,_CALC_ALLOC!$B$1:$B$420,$U44) -> 0 | K44: =E44+F44+G44+H44+I44+J44 -> 0 | L44: =SUMIFS(_CALC_ALLOC!$AN$1:$AN$420,_CALC_ALLOC!$AS$1:$AS$420,"2027|"&$P$1,_CALC_ALLOC!$B$1:$B$420,$U44) -> 0 | M44: =IF(D44=0,0,L44/D44) -> 0 | T44: ISCOM_PAR | U44: ISCOM_PAR | V44: ISCOM | Z44: 2 | BF44: 2027BUD_V1 | BG44: ACT | BH44: 12 | BI44: 2024 | BJ44: MBWAY_PAR | BK44: MBWAY | BL44: MAS_MGT | BM44: M1 | BN44: ALT | BO44: 69 | BP44: 3 | BQ44: 585810 | BR44: 28922.425 | BS44: 80778.908 | BT44: 54544.507 | BU44: 221608.66 | BV44: 12659.991 | BW44: 64720.986 | BX44: 77380.977 | BY44: 83466.932 | BZ44: 379768.55 | CA44: 463235.48 | CB44: 122574.52 | CC44: 69 | CD44: 165271 | CE44: 461593.76 | CF44: 129720 | CG44: 56438 | CH44: 1108043.3 | CI44: 2639292 | CJ44: 499926
B45: Bachelor Communication, 1re année, initial | C45: =SUMIFS(_CALC_ALLOC!$G$1:$G$420,_CALC_ALLOC!$AS$1:$AS$420,"2027|"&$P$1,_CALC_ALLOC!$B$1:$B$420,$U45,_CALC_ALLOC!$D$1:$D$420,$W45,_CALC_ALLOC!$E$1:$E$420,$X45,_CALC_ALLOC!$F$1:$F$420,$Y45) -> 0 | D45: =SUMIFS(_CALC_ALLOC!$I$1:$I$420,_CALC_ALLOC!$AS$1:$AS$420,"2027|"&$P$1,_CALC_ALLOC!$B$1:$B$420,$U45,_CALC_ALLOC!$D$1:$D$420,$W45,_CALC_ALLOC!$E$1:$E$420,$X45,_CALC_ALLOC!$F$1:$F$420,$Y45) -> 0 | E45: =SUMIFS(_CALC_ALLOC!$AI$1:$AI$420,_CALC_ALLOC!$AS$1:$AS$420,"2027|"&$P$1,_CALC_ALLOC!$B$1:$B$420,$U45,_CALC_ALLOC!$D$1:$D$420,$W45,_CALC_ALLOC!$E$1:$E$420,$X45,_CALC_ALLOC!$F$1:$F$420,$Y45) -> 0 | F45: =SUMIFS(_CALC_ALLOC!$AJ$1:$AJ$420,_CALC_ALLOC!$AS$1:$AS$420,"2027|"&$P$1,_CALC_ALLOC!$B$1:$B$420,$U45,_CALC_ALLOC!$D$1:$D$420,$W45,_CALC_ALLOC!$E$1:$E$420,$X45,_CALC_ALLOC!$F$1:$F$420,$Y45) -> 0 | G45: =SUMIFS(_CALC_ALLOC!$AK$1:$AK$420,_CALC_ALLOC!$AS$1:$AS$420,"2027|"&$P$1,_CALC_ALLOC!$B$1:$B$420,$U45,_CALC_ALLOC!$D$1:$D$420,$W45,_CALC_ALLOC!$E$1:$E$420,$X45,_CALC_ALLOC!$F$1:$F$420,$Y45) -> 0 | H45: =SUMIFS(_CALC_ALLOC!$AL$1:$AL$420,_CALC_ALLOC!$AS$1:$AS$420,"2027|"&$P$1,_CALC_ALLOC!$B$1:$B$420,$U45,_CALC_ALLOC!$D$1:$D$420,$W45,_CALC_ALLOC!$E$1:$E$420,$X45,_CALC_ALLOC!$F$1:$F$420,$Y45) -> 0 | I45: =SUMIFS(_CALC_ALLOC!$AR$1:$AR$420,_CALC_ALLOC!$AS$1:$AS$420,"2027|"&$P$1,_CALC_ALLOC!$B$1:$B$420,$U45,_CALC_ALLOC!$D$1:$D$420,$W45,_CALC_ALLOC!$E$1:$E$420,$X45,_CALC_ALLOC!$F$1:$F$420,$Y45) -> 0 | J45: =SUMIFS(_CALC_ALLOC!$AM$1:$AM$420,_CALC_ALLOC!$AS$1:$AS$420,"2027|"&$P$1,_CALC_ALLOC!$B$1:$B$420,$U45,_CALC_ALLOC!$D$1:$D$420,$W45,_CALC_ALLOC!$E$1:$E$420,$X45,_CALC_ALLOC!$F$1:$F$420,$Y45) -> 0 | K45: =E45+F45+G45+H45+I45+J45 -> 0 | L45: =SUMIFS(_CALC_ALLOC!$AN$1:$AN$420,_CALC_ALLOC!$AS$1:$AS$420,"2027|"&$P$1,_CALC_ALLOC!$B$1:$B$420,$U45,_CALC_ALLOC!$D$1:$D$420,$W45,_CALC_ALLOC!$E$1:$E$420,$X45,_CALC_ALLOC!$F$1:$F$420,$Y45) -> 0 | M45: =IF(D45=0,0,L45/D45) -> 0 | T45: ISCOM_PAR|BAC_COM|B1|INIT | U45: ISCOM_PAR | V45: ISCOM | W45: BAC_COM | X45: B1 | Y45: INIT | Z45: 3 | BF45: 2027BUD_V1 | BG45: ACT | BH45: 12 | BI45: 2024 | BJ45: MBWAY_PAR | BK45: MBWAY | BL45: MAS_MGT | BM45: M2 | BN45: ALT | BO45: 68 | BP45: 3 | BQ45: 571200 | BR45: 28922.425 | BS45: 80778.908 | BT45: 25944 | BU45: 221608.66 | BV45: 12659.991 | BW45: 64720.986 | BX45: 77380.977 | BY45: 54866.425 | BZ45: 379768.55 | CA45: 434634.97 | CB45: 136565.03 | CC45: 0 | CD45: 165271 | CE45: 461593.76 | CF45: 129720 | CG45: 56438 | CH45: 1108043.3 | CI45: 2639292 | CJ45: 499926
B46: Bachelor Communication, 2e année, alternance | C46: =SUMIFS(_CALC_ALLOC!$G$1:$G$420,_CALC_ALLOC!$AS$1:$AS$420,"2027|"&$P$1,_CALC_ALLOC!$B$1:$B$420,$U46,_CALC_ALLOC!$D$1:$D$420,$W46,_CALC_ALLOC!$E$1:$E$420,$X46,_CALC_ALLOC!$F$1:$F$420,$Y46) -> 0 | D46: =SUMIFS(_CALC_ALLOC!$I$1:$I$420,_CALC_ALLOC!$AS$1:$AS$420,"2027|"&$P$1,_CALC_ALLOC!$B$1:$B$420,$U46,_CALC_ALLOC!$D$1:$D$420,$W46,_CALC_ALLOC!$E$1:$E$420,$X46,_CALC_ALLOC!$F$1:$F$420,$Y46) -> 0 | E46: =SUMIFS(_CALC_ALLOC!$AI$1:$AI$420,_CALC_ALLOC!$AS$1:$AS$420,"2027|"&$P$1,_CALC_ALLOC!$B$1:$B$420,$U46,_CALC_ALLOC!$D$1:$D$420,$W46,_CALC_ALLOC!$E$1:$E$420,$X46,_CALC_ALLOC!$F$1:$F$420,$Y46) -> 0 | F46: =SUMIFS(_CALC_ALLOC!$AJ$1:$AJ$420,_CALC_ALLOC!$AS$1:$AS$420,"2027|"&$P$1,_CALC_ALLOC!$B$1:$B$420,$U46,_CALC_ALLOC!$D$1:$D$420,$W46,_CALC_ALLOC!$E$1:$E$420,$X46,_CALC_ALLOC!$F$1:$F$420,$Y46) -> 0 | G46: =SUMIFS(_CALC_ALLOC!$AK$1:$AK$420,_CALC_ALLOC!$AS$1:$AS$420,"2027|"&$P$1,_CALC_ALLOC!$B$1:$B$420,$U46,_CALC_ALLOC!$D$1:$D$420,$W46,_CALC_ALLOC!$E$1:$E$420,$X46,_CALC_ALLOC!$F$1:$F$420,$Y46) -> 0 | H46: =SUMIFS(_CALC_ALLOC!$AL$1:$AL$420,_CALC_ALLOC!$AS$1:$AS$420,"2027|"&$P$1,_CALC_ALLOC!$B$1:$B$420,$U46,_CALC_ALLOC!$D$1:$D$420,$W46,_CALC_ALLOC!$E$1:$E$420,$X46,_CALC_ALLOC!$F$1:$F$420,$Y46) -> 0 | I46: =SUMIFS(_CALC_ALLOC!$AR$1:$AR$420,_CALC_ALLOC!$AS$1:$AS$420,"2027|"&$P$1,_CALC_ALLOC!$B$1:$B$420,$U46,_CALC_ALLOC!$D$1:$D$420,$W46,_CALC_ALLOC!$E$1:$E$420,$X46,_CALC_ALLOC!$F$1:$F$420,$Y46) -> 0 | J46: =SUMIFS(_CALC_ALLOC!$AM$1:$AM$420,_CALC_ALLOC!$AS$1:$AS$420,"2027|"&$P$1,_CALC_ALLOC!$B$1:$B$420,$U46,_CALC_ALLOC!$D$1:$D$420,$W46,_CALC_ALLOC!$E$1:$E$420,$X46,_CALC_ALLOC!$F$1:$F$420,$Y46) -> 0 | K46: =E46+F46+G46+H46+I46+J46 -> 0 | L46: =SUMIFS(_CALC_ALLOC!$AN$1:$AN$420,_CALC_ALLOC!$AS$1:$AS$420,"2027|"&$P$1,_CALC_ALLOC!$B$1:$B$420,$U46,_CALC_ALLOC!$D$1:$D$420,$W46,_CALC_ALLOC!$E$1:$E$420,$X46,_CALC_ALLOC!$F$1:$F$420,$Y46) -> 0 | M46: =IF(D46=0,0,L46/D46) -> 0 | T46: ISCOM_PAR|BAC_COM|B2|ALT | U46: ISCOM_PAR | V46: ISCOM | W46: BAC_COM | X46: B2 | Y46: ALT | Z46: 3 | BF46: 2027BUD_V1 | BG46: ACT | BH46: 12 | BI46: 2024 | BJ46: PIGIER_BOR | BK46: PIGIER | BL46: BTS_GES | BM46: BTS1 | BN46: ALT | BO46: 32 | BP46: 2 | BQ46: 189120 | BR46: 21725.557 | BS46: 40999.742 | BT46: 18968.772 | BU46: 63370.352 | BV46: 5105.8972 | BW46: 29695.45 | BX46: 34801.347 | BY46: 40694.329 | BZ46: 139171.44 | CA46: 179865.77 | CB46: 9254.2297 | CC46: 32 | CD46: 88144 | CE46: 166342.4 | CF46: 48220 | CG46: 18155 | CH46: 316851.76 | CI46: 2639292 | CJ46: 499926
B47: Bachelor Communication, 3e année, alternance | C47: =SUMIFS(_CALC_ALLOC!$G$1:$G$420,_CALC_ALLOC!$AS$1:$AS$420,"2027|"&$P$1,_CALC_ALLOC!$B$1:$B$420,$U47,_CALC_ALLOC!$D$1:$D$420,$W47,_CALC_ALLOC!$E$1:$E$420,$X47,_CALC_ALLOC!$F$1:$F$420,$Y47) -> 0 | D47: =SUMIFS(_CALC_ALLOC!$I$1:$I$420,_CALC_ALLOC!$AS$1:$AS$420,"2027|"&$P$1,_CALC_ALLOC!$B$1:$B$420,$U47,_CALC_ALLOC!$D$1:$D$420,$W47,_CALC_ALLOC!$E$1:$E$420,$X47,_CALC_ALLOC!$F$1:$F$420,$Y47) -> 0 | E47: =SUMIFS(_CALC_ALLOC!$AI$1:$AI$420,_CALC_ALLOC!$AS$1:$AS$420,"2027|"&$P$1,_CALC_ALLOC!$B$1:$B$420,$U47,_CALC_ALLOC!$D$1:$D$420,$W47,_CALC_ALLOC!$E$1:$E$420,$X47,_CALC_ALLOC!$F$1:$F$420,$Y47) -> 0 | F47: =SUMIFS(_CALC_ALLOC!$AJ$1:$AJ$420,_CALC_ALLOC!$AS$1:$AS$420,"2027|"&$P$1,_CALC_ALLOC!$B$1:$B$420,$U47,_CALC_ALLOC!$D$1:$D$420,$W47,_CALC_ALLOC!$E$1:$E$420,$X47,_CALC_ALLOC!$F$1:$F$420,$Y47) -> 0 | G47: =SUMIFS(_CALC_ALLOC!$AK$1:$AK$420,_CALC_ALLOC!$AS$1:$AS$420,"2027|"&$P$1,_CALC_ALLOC!$B$1:$B$420,$U47,_CALC_ALLOC!$D$1:$D$420,$W47,_CALC_ALLOC!$E$1:$E$420,$X47,_CALC_ALLOC!$F$1:$F$420,$Y47) -> 0 | H47: =SUMIFS(_CALC_ALLOC!$AL$1:$AL$420,_CALC_ALLOC!$AS$1:$AS$420,"2027|"&$P$1,_CALC_ALLOC!$B$1:$B$420,$U47,_CALC_ALLOC!$D$1:$D$420,$W47,_CALC_ALLOC!$E$1:$E$420,$X47,_CALC_ALLOC!$F$1:$F$420,$Y47) -> 0 | I47: =SUMIFS(_CALC_ALLOC!$AR$1:$AR$420,_CALC_ALLOC!$AS$1:$AS$420,"2027|"&$P$1,_CALC_ALLOC!$B$1:$B$420,$U47,_CALC_ALLOC!$D$1:$D$420,$W47,_CALC_ALLOC!$E$1:$E$420,$X47,_CALC_ALLOC!$F$1:$F$420,$Y47) -> 0 | J47: =SUMIFS(_CALC_ALLOC!$AM$1:$AM$420,_CALC_ALLOC!$AS$1:$AS$420,"2027|"&$P$1,_CALC_ALLOC!$B$1:$B$420,$U47,_CALC_ALLOC!$D$1:$D$420,$W47,_CALC_ALLOC!$E$1:$E$420,$X47,_CALC_ALLOC!$F$1:$F$420,$Y47) -> 0 | K47: =E47+F47+G47+H47+I47+J47 -> 0 | L47: =SUMIFS(_CALC_ALLOC!$AN$1:$AN$420,_CALC_ALLOC!$AS$1:$AS$420,"2027|"&$P$1,_CALC_ALLOC!$B$1:$B$420,$U47,_CALC_ALLOC!$D$1:$D$420,$W47,_CALC_ALLOC!$E$1:$E$420,$X47,_CALC_ALLOC!$F$1:$F$420,$Y47) -> 0 | M47: =IF(D47=0,0,L47/D47) -> 0 | T47: ISCOM_PAR|BAC_COM|B3|ALT | U47: ISCOM_PAR | V47: ISCOM | W47: BAC_COM | X47: B3 | Y47: ALT | Z47: 3 | BF47: 2027BUD_V1 | BG47: ACT | BH47: 12 | BI47: 2024 | BJ47: PIGIER_BOR | BK47: PIGIER | BL47: BTS_GES | BM47: BTS2 | BN47: ALT | BO47: 31 | BP47: 2 | BQ47: 180420 | BR47: 21725.557 | BS47: 40999.742 | BT47: 9582.1337 | BU47: 63370.352 | BV47: 5105.8972 | BW47: 29695.45 | BX47: 34801.347 | BY47: 31307.691 | BZ47: 139171.44 | CA47: 170479.13 | CB47: 9940.8681 | CC47: 0 | CD47: 88144 | CE47: 166342.4 | CF47: 48220 | CG47: 18155 | CH47: 316851.76 | CI47: 2639292 | CJ47: 499926
B48: Mastère Communication, 1re année, alternance | C48: =SUMIFS(_CALC_ALLOC!$G$1:$G$420,_CALC_ALLOC!$AS$1:$AS$420,"2027|"&$P$1,_CALC_ALLOC!$B$1:$B$420,$U48,_CALC_ALLOC!$D$1:$D$420,$W48,_CALC_ALLOC!$E$1:$E$420,$X48,_CALC_ALLOC!$F$1:$F$420,$Y48) -> 0 | D48: =SUMIFS(_CALC_ALLOC!$I$1:$I$420,_CALC_ALLOC!$AS$1:$AS$420,"2027|"&$P$1,_CALC_ALLOC!$B$1:$B$420,$U48,_CALC_ALLOC!$D$1:$D$420,$W48,_CALC_ALLOC!$E$1:$E$420,$X48,_CALC_ALLOC!$F$1:$F$420,$Y48) -> 0 | E48: =SUMIFS(_CALC_ALLOC!$AI$1:$AI$420,_CALC_ALLOC!$AS$1:$AS$420,"2027|"&$P$1,_CALC_ALLOC!$B$1:$B$420,$U48,_CALC_ALLOC!$D$1:$D$420,$W48,_CALC_ALLOC!$E$1:$E$420,$X48,_CALC_ALLOC!$F$1:$F$420,$Y48) -> 0 | F48: =SUMIFS(_CALC_ALLOC!$AJ$1:$AJ$420,_CALC_ALLOC!$AS$1:$AS$420,"2027|"&$P$1,_CALC_ALLOC!$B$1:$B$420,$U48,_CALC_ALLOC!$D$1:$D$420,$W48,_CALC_ALLOC!$E$1:$E$420,$X48,_CALC_ALLOC!$F$1:$F$420,$Y48) -> 0 | G48: =SUMIFS(_CALC_ALLOC!$AK$1:$AK$420,_CALC_ALLOC!$AS$1:$AS$420,"2027|"&$P$1,_CALC_ALLOC!$B$1:$B$420,$U48,_CALC_ALLOC!$D$1:$D$420,$W48,_CALC_ALLOC!$E$1:$E$420,$X48,_CALC_ALLOC!$F$1:$F$420,$Y48) -> 0 | H48: =SUMIFS(_CALC_ALLOC!$AL$1:$AL$420,_CALC_ALLOC!$AS$1:$AS$420,"2027|"&$P$1,_CALC_ALLOC!$B$1:$B$420,$U48,_CALC_ALLOC!$D$1:$D$420,$W48,_CALC_ALLOC!$E$1:$E$420,$X48,_CALC_ALLOC!$F$1:$F$420,$Y48) -> 0 | I48: =SUMIFS(_CALC_ALLOC!$AR$1:$AR$420,_CALC_ALLOC!$AS$1:$AS$420,"2027|"&$P$1,_CALC_ALLOC!$B$1:$B$420,$U48,_CALC_ALLOC!$D$1:$D$420,$W48,_CALC_ALLOC!$E$1:$E$420,$X48,_CALC_ALLOC!$F$1:$F$420,$Y48) -> 0 | J48: =SUMIFS(_CALC_ALLOC!$AM$1:$AM$420,_CALC_ALLOC!$AS$1:$AS$420,"2027|"&$P$1,_CALC_ALLOC!$B$1:$B$420,$U48,_CALC_ALLOC!$D$1:$D$420,$W48,_CALC_ALLOC!$E$1:$E$420,$X48,_CALC_ALLOC!$F$1:$F$420,$Y48) -> 0 | K48: =E48+F48+G48+H48+I48+J48 -> 0 | L48: =SUMIFS(_CALC_ALLOC!$AN$1:$AN$420,_CALC_ALLOC!$AS$1:$AS$420,"2027|"&$P$1,_CALC_ALLOC!$B$1:$B$420,$U48,_CALC_ALLOC!$D$1:$D$420,$W48,_CALC_ALLOC!$E$1:$E$420,$X48,_CALC_ALLOC!$F$1:$F$420,$Y48) -> 0 | M48: =IF(D48=0,0,L48/D48) -> 0 | T48: ISCOM_PAR|MAS_COM|M1|ALT | U48: ISCOM_PAR | V48: ISCOM | W48: MAS_COM | X48: M1 | Y48: ALT | Z48: 3 | BF48: 2027BUD_V1 | BG48: ACT | BH48: 12 | BI48: 2024 | BJ48: PIGIER_BOR | BK48: PIGIER | BL48: BAC_RH | BM48: B1 | BN48: ALT | BO48: 32 | BP48: 2 | BQ48: 220160 | BR48: 14897.57 | BS48: 28114.194 | BT48: 18968.772 | BU48: 63370.352 | BV48: 5105.8972 | BW48: 29695.45 | BX48: 34801.347 | BY48: 33866.342 | BZ48: 126285.89 | CA48: 160152.24 | CB48: 60007.764 | CC48: 32 | CD48: 88144 | CE48: 166342.4 | CF48: 48220 | CG48: 18155 | CH48: 316851.76 | CI48: 2639292 | CJ48: 499926
B49: Mastère Communication, 2e année, alternance | C49: =SUMIFS(_CALC_ALLOC!$G$1:$G$420,_CALC_ALLOC!$AS$1:$AS$420,"2027|"&$P$1,_CALC_ALLOC!$B$1:$B$420,$U49,_CALC_ALLOC!$D$1:$D$420,$W49,_CALC_ALLOC!$E$1:$E$420,$X49,_CALC_ALLOC!$F$1:$F$420,$Y49) -> 0 | D49: =SUMIFS(_CALC_ALLOC!$I$1:$I$420,_CALC_ALLOC!$AS$1:$AS$420,"2027|"&$P$1,_CALC_ALLOC!$B$1:$B$420,$U49,_CALC_ALLOC!$D$1:$D$420,$W49,_CALC_ALLOC!$E$1:$E$420,$X49,_CALC_ALLOC!$F$1:$F$420,$Y49) -> 0 | E49: =SUMIFS(_CALC_ALLOC!$AI$1:$AI$420,_CALC_ALLOC!$AS$1:$AS$420,"2027|"&$P$1,_CALC_ALLOC!$B$1:$B$420,$U49,_CALC_ALLOC!$D$1:$D$420,$W49,_CALC_ALLOC!$E$1:$E$420,$X49,_CALC_ALLOC!$F$1:$F$420,$Y49) -> 0 | F49: =SUMIFS(_CALC_ALLOC!$AJ$1:$AJ$420,_CALC_ALLOC!$AS$1:$AS$420,"2027|"&$P$1,_CALC_ALLOC!$B$1:$B$420,$U49,_CALC_ALLOC!$D$1:$D$420,$W49,_CALC_ALLOC!$E$1:$E$420,$X49,_CALC_ALLOC!$F$1:$F$420,$Y49) -> 0 | G49: =SUMIFS(_CALC_ALLOC!$AK$1:$AK$420,_CALC_ALLOC!$AS$1:$AS$420,"2027|"&$P$1,_CALC_ALLOC!$B$1:$B$420,$U49,_CALC_ALLOC!$D$1:$D$420,$W49,_CALC_ALLOC!$E$1:$E$420,$X49,_CALC_ALLOC!$F$1:$F$420,$Y49) -> 0 | H49: =SUMIFS(_CALC_ALLOC!$AL$1:$AL$420,_CALC_ALLOC!$AS$1:$AS$420,"2027|"&$P$1,_CALC_ALLOC!$B$1:$B$420,$U49,_CALC_ALLOC!$D$1:$D$420,$W49,_CALC_ALLOC!$E$1:$E$420,$X49,_CALC_ALLOC!$F$1:$F$420,$Y49) -> 0 | I49: =SUMIFS(_CALC_ALLOC!$AR$1:$AR$420,_CALC_ALLOC!$AS$1:$AS$420,"2027|"&$P$1,_CALC_ALLOC!$B$1:$B$420,$U49,_CALC_ALLOC!$D$1:$D$420,$W49,_CALC_ALLOC!$E$1:$E$420,$X49,_CALC_ALLOC!$F$1:$F$420,$Y49) -> 0 | J49: =SUMIFS(_CALC_ALLOC!$AM$1:$AM$420,_CALC_ALLOC!$AS$1:$AS$420,"2027|"&$P$1,_CALC_ALLOC!$B$1:$B$420,$U49,_CALC_ALLOC!$D$1:$D$420,$W49,_CALC_ALLOC!$E$1:$E$420,$X49,_CALC_ALLOC!$F$1:$F$420,$Y49) -> 0 | K49: =E49+F49+G49+H49+I49+J49 -> 0 | L49: =SUMIFS(_CALC_ALLOC!$AN$1:$AN$420,_CALC_ALLOC!$AS$1:$AS$420,"2027|"&$P$1,_CALC_ALLOC!$B$1:$B$420,$U49,_CALC_ALLOC!$D$1:$D$420,$W49,_CALC_ALLOC!$E$1:$E$420,$X49,_CALC_ALLOC!$F$1:$F$420,$Y49) -> 0 | M49: =IF(D49=0,0,L49/D49) -> 0 | T49: ISCOM_PAR|MAS_COM|M2|ALT | U49: ISCOM_PAR | V49: ISCOM | W49: MAS_COM | X49: M2 | Y49: ALT | Z49: 3 | BF49: 2027BUD_V1 | BG49: ACT | BH49: 12 | BI49: 2024 | BJ49: PIGIER_BOR | BK49: PIGIER | BL49: BAC_RH | BM49: B2 | BN49: ALT | BO49: 31 | BP49: 2 | BQ49: 210490 | BR49: 14897.57 | BS49: 28114.194 | BT49: 9582.1337 | BU49: 63370.352 | BV49: 5105.8972 | BW49: 29695.45 | BX49: 34801.347 | BY49: 24479.704 | BZ49: 126285.89 | CA49: 150765.6 | CB49: 59724.403 | CC49: 0 | CD49: 88144 | CE49: 166342.4 | CF49: 48220 | CG49: 18155 | CH49: 316851.76 | CI49: 2639292 | CJ49: 499926
B50: Lille | C50: =SUMIFS(_CALC_ALLOC!$G$1:$G$420,_CALC_ALLOC!$AS$1:$AS$420,"2027|"&$P$1,_CALC_ALLOC!$B$1:$B$420,$U50) -> 0 | D50: =SUMIFS(_CALC_ALLOC!$I$1:$I$420,_CALC_ALLOC!$AS$1:$AS$420,"2027|"&$P$1,_CALC_ALLOC!$B$1:$B$420,$U50) -> 0 | E50: =SUMIFS(_CALC_ALLOC!$AI$1:$AI$420,_CALC_ALLOC!$AS$1:$AS$420,"2027|"&$P$1,_CALC_ALLOC!$B$1:$B$420,$U50) -> 0 | F50: =SUMIFS(_CALC_ALLOC!$AJ$1:$AJ$420,_CALC_ALLOC!$AS$1:$AS$420,"2027|"&$P$1,_CALC_ALLOC!$B$1:$B$420,$U50) -> 0 | G50: =SUMIFS(_CALC_ALLOC!$AK$1:$AK$420,_CALC_ALLOC!$AS$1:$AS$420,"2027|"&$P$1,_CALC_ALLOC!$B$1:$B$420,$U50) -> 0 | H50: =SUMIFS(_CALC_ALLOC!$AL$1:$AL$420,_CALC_ALLOC!$AS$1:$AS$420,"2027|"&$P$1,_CALC_ALLOC!$B$1:$B$420,$U50) -> 0 | I50: =SUMIFS(_CALC_ALLOC!$AR$1:$AR$420,_CALC_ALLOC!$AS$1:$AS$420,"2027|"&$P$1,_CALC_ALLOC!$B$1:$B$420,$U50) -> 0 | J50: =SUMIFS(_CALC_ALLOC!$AM$1:$AM$420,_CALC_ALLOC!$AS$1:$AS$420,"2027|"&$P$1,_CALC_ALLOC!$B$1:$B$420,$U50) -> 0 | K50: =E50+F50+G50+H50+I50+J50 -> 0 | L50: =SUMIFS(_CALC_ALLOC!$AN$1:$AN$420,_CALC_ALLOC!$AS$1:$AS$420,"2027|"&$P$1,_CALC_ALLOC!$B$1:$B$420,$U50) -> 0 | M50: =IF(D50=0,0,L50/D50) -> 0 | T50: ISCOM_LIL | U50: ISCOM_LIL | V50: ISCOM | Z50: 2 | BF50: 2027BUD_V1 | BG50: ACT | BH50: 12 | BI50: 2024 | BJ50: PIGIER_BOR | BK50: PIGIER | BL50: BAC_RH | BM50: B3 | BN50: ALT | BO50: 30 | BP50: 2 | BQ50: 203700 | BR50: 14897.57 | BS50: 28114.194 | BT50: 9273.0435 | BU50: 63370.352 | BV50: 5105.8972 | BW50: 29695.45 | BX50: 34801.347 | BY50: 24170.614 | BZ50: 126285.89 | CA50: 150456.51 | CB50: 53243.493 | CC50: 0 | CD50: 88144 | CE50: 166342.4 | CF50: 48220 | CG50: 18155 | CH50: 316851.76 | CI50: 2639292 | CJ50: 499926
B51: Bachelor Communication, 1re année, initial | C51: =SUMIFS(_CALC_ALLOC!$G$1:$G$420,_CALC_ALLOC!$AS$1:$AS$420,"2027|"&$P$1,_CALC_ALLOC!$B$1:$B$420,$U51,_CALC_ALLOC!$D$1:$D$420,$W51,_CALC_ALLOC!$E$1:$E$420,$X51,_CALC_ALLOC!$F$1:$F$420,$Y51) -> 0 | D51: =SUMIFS(_CALC_ALLOC!$I$1:$I$420,_CALC_ALLOC!$AS$1:$AS$420,"2027|"&$P$1,_CALC_ALLOC!$B$1:$B$420,$U51,_CALC_ALLOC!$D$1:$D$420,$W51,_CALC_ALLOC!$E$1:$E$420,$X51,_CALC_ALLOC!$F$1:$F$420,$Y51) -> 0 | E51: =SUMIFS(_CALC_ALLOC!$AI$1:$AI$420,_CALC_ALLOC!$AS$1:$AS$420,"2027|"&$P$1,_CALC_ALLOC!$B$1:$B$420,$U51,_CALC_ALLOC!$D$1:$D$420,$W51,_CALC_ALLOC!$E$1:$E$420,$X51,_CALC_ALLOC!$F$1:$F$420,$Y51) -> 0 | F51: =SUMIFS(_CALC_ALLOC!$AJ$1:$AJ$420,_CALC_ALLOC!$AS$1:$AS$420,"2027|"&$P$1,_CALC_ALLOC!$B$1:$B$420,$U51,_CALC_ALLOC!$D$1:$D$420,$W51,_CALC_ALLOC!$E$1:$E$420,$X51,_CALC_ALLOC!$F$1:$F$420,$Y51) -> 0 | G51: =SUMIFS(_CALC_ALLOC!$AK$1:$AK$420,_CALC_ALLOC!$AS$1:$AS$420,"2027|"&$P$1,_CALC_ALLOC!$B$1:$B$420,$U51,_CALC_ALLOC!$D$1:$D$420,$W51,_CALC_ALLOC!$E$1:$E$420,$X51,_CALC_ALLOC!$F$1:$F$420,$Y51) -> 0 | H51: =SUMIFS(_CALC_ALLOC!$AL$1:$AL$420,_CALC_ALLOC!$AS$1:$AS$420,"2027|"&$P$1,_CALC_ALLOC!$B$1:$B$420,$U51,_CALC_ALLOC!$D$1:$D$420,$W51,_CALC_ALLOC!$E$1:$E$420,$X51,_CALC_ALLOC!$F$1:$F$420,$Y51) -> 0 | I51: =SUMIFS(_CALC_ALLOC!$AR$1:$AR$420,_CALC_ALLOC!$AS$1:$AS$420,"2027|"&$P$1,_CALC_ALLOC!$B$1:$B$420,$U51,_CALC_ALLOC!$D$1:$D$420,$W51,_CALC_ALLOC!$E$1:$E$420,$X51,_CALC_ALLOC!$F$1:$F$420,$Y51) -> 0 | J51: =SUMIFS(_CALC_ALLOC!$AM$1:$AM$420,_CALC_ALLOC!$AS$1:$AS$420,"2027|"&$P$1,_CALC_ALLOC!$B$1:$B$420,$U51,_CALC_ALLOC!$D$1:$D$420,$W51,_CALC_ALLOC!$E$1:$E$420,$X51,_CALC_ALLOC!$F$1:$F$420,$Y51) -> 0 | K51: =E51+F51+G51+H51+I51+J51 -> 0 | L51: =SUMIFS(_CALC_ALLOC!$AN$1:$AN$420,_CALC_ALLOC!$AS$1:$AS$420,"2027|"&$P$1,_CALC_ALLOC!$B$1:$B$420,$U51,_CALC_ALLOC!$D$1:$D$420,$W51,_CALC_ALLOC!$E$1:$E$420,$X51,_CALC_ALLOC!$F$1:$F$420,$Y51) -> 0 | M51: =IF(D51=0,0,L51/D51) -> 0 | T51: ISCOM_LIL|BAC_COM|B1|INIT | U51: ISCOM_LIL | V51: ISCOM | W51: BAC_COM | X51: B1 | Y51: INIT | Z51: 3 | BF51: 2027BUD_V1 | BG51: ACT | BH51: 12 | BI51: 2024 | BJ51: PIGIER_LYO | BK51: PIGIER | BL51: BAC_RH | BM51: B3 | BN51: ALT | BO51: 39 | BP51: 2 | BQ51: 286650 | BR51: 14897.57 | BS51: 37284.458 | BT51: 11991.768 | BU51: 98210.434 | BV51: 6578.7616 | BW51: 38261.5 | BX51: 44840.262 | BY51: 26889.338 | BZ51: 180335.15 | CA51: 207224.49 | CB51: 79425.508 | CC51: 0 | CD51: 88144 | CE51: 220599.82 | CF51: 61804 | CG51: 30258 | CH51: 491052.17 | CI51: 2639292 | CJ51: 499926
B52: Bachelor Communication, 2e année, alternance | C52: =SUMIFS(_CALC_ALLOC!$G$1:$G$420,_CALC_ALLOC!$AS$1:$AS$420,"2027|"&$P$1,_CALC_ALLOC!$B$1:$B$420,$U52,_CALC_ALLOC!$D$1:$D$420,$W52,_CALC_ALLOC!$E$1:$E$420,$X52,_CALC_ALLOC!$F$1:$F$420,$Y52) -> 0 | D52: =SUMIFS(_CALC_ALLOC!$I$1:$I$420,_CALC_ALLOC!$AS$1:$AS$420,"2027|"&$P$1,_CALC_ALLOC!$B$1:$B$420,$U52,_CALC_ALLOC!$D$1:$D$420,$W52,_CALC_ALLOC!$E$1:$E$420,$X52,_CALC_ALLOC!$F$1:$F$420,$Y52) -> 0 | E52: =SUMIFS(_CALC_ALLOC!$AI$1:$AI$420,_CALC_ALLOC!$AS$1:$AS$420,"2027|"&$P$1,_CALC_ALLOC!$B$1:$B$420,$U52,_CALC_ALLOC!$D$1:$D$420,$W52,_CALC_ALLOC!$E$1:$E$420,$X52,_CALC_ALLOC!$F$1:$F$420,$Y52) -> 0 | F52: =SUMIFS(_CALC_ALLOC!$AJ$1:$AJ$420,_CALC_ALLOC!$AS$1:$AS$420,"2027|"&$P$1,_CALC_ALLOC!$B$1:$B$420,$U52,_CALC_ALLOC!$D$1:$D$420,$W52,_CALC_ALLOC!$E$1:$E$420,$X52,_CALC_ALLOC!$F$1:$F$420,$Y52) -> 0 | G52: =SUMIFS(_CALC_ALLOC!$AK$1:$AK$420,_CALC_ALLOC!$AS$1:$AS$420,"2027|"&$P$1,_CALC_ALLOC!$B$1:$B$420,$U52,_CALC_ALLOC!$D$1:$D$420,$W52,_CALC_ALLOC!$E$1:$E$420,$X52,_CALC_ALLOC!$F$1:$F$420,$Y52) -> 0 | H52: =SUMIFS(_CALC_ALLOC!$AL$1:$AL$420,_CALC_ALLOC!$AS$1:$AS$420,"2027|"&$P$1,_CALC_ALLOC!$B$1:$B$420,$U52,_CALC_ALLOC!$D$1:$D$420,$W52,_CALC_ALLOC!$E$1:$E$420,$X52,_CALC_ALLOC!$F$1:$F$420,$Y52) -> 0 | I52: =SUMIFS(_CALC_ALLOC!$AR$1:$AR$420,_CALC_ALLOC!$AS$1:$AS$420,"2027|"&$P$1,_CALC_ALLOC!$B$1:$B$420,$U52,_CALC_ALLOC!$D$1:$D$420,$W52,_CALC_ALLOC!$E$1:$E$420,$X52,_CALC_ALLOC!$F$1:$F$420,$Y52) -> 0 | J52: =SUMIFS(_CALC_ALLOC!$AM$1:$AM$420,_CALC_ALLOC!$AS$1:$AS$420,"2027|"&$P$1,_CALC_ALLOC!$B$1:$B$420,$U52,_CALC_ALLOC!$D$1:$D$420,$W52,_CALC_ALLOC!$E$1:$E$420,$X52,_CALC_ALLOC!$F$1:$F$420,$Y52) -> 0 | K52: =E52+F52+G52+H52+I52+J52 -> 0 | L52: =SUMIFS(_CALC_ALLOC!$AN$1:$AN$420,_CALC_ALLOC!$AS$1:$AS$420,"2027|"&$P$1,_CALC_ALLOC!$B$1:$B$420,$U52,_CALC_ALLOC!$D$1:$D$420,$W52,_CALC_ALLOC!$E$1:$E$420,$X52,_CALC_ALLOC!$F$1:$F$420,$Y52) -> 0 | M52: =IF(D52=0,0,L52/D52) -> 0 | T52: ISCOM_LIL|BAC_COM|B2|ALT | U52: ISCOM_LIL | V52: ISCOM | W52: BAC_COM | X52: B2 | Y52: ALT | Z52: 3 | BF52: 2027BUD_V1 | BG52: ACT | BH52: 12 | BI52: 2024 | BJ52: PIGIER_LYO | BK52: PIGIER | BL52: BTS_GES | BM52: BTS1 | BN52: ALT | BO52: 41 | BP52: 2 | BQ52: 261990 | BR52: 21725.557 | BS52: 54373.002 | BT52: 27735.78 | BU52: 98210.434 | BV52: 6578.7616 | BW52: 38261.5 | BX52: 44840.262 | BY52: 49461.337 | BZ52: 197423.7 | CA52: 246885.03 | CB52: 15104.965 | CC52: 41 | CD52: 88144 | CE52: 220599.82 | CF52: 61804 | CG52: 30258 | CH52: 491052.17 | CI52: 2639292 | CJ52: 499926
B53: Bachelor Communication, 3e année, alternance | C53: =SUMIFS(_CALC_ALLOC!$G$1:$G$420,_CALC_ALLOC!$AS$1:$AS$420,"2027|"&$P$1,_CALC_ALLOC!$B$1:$B$420,$U53,_CALC_ALLOC!$D$1:$D$420,$W53,_CALC_ALLOC!$E$1:$E$420,$X53,_CALC_ALLOC!$F$1:$F$420,$Y53) -> 0 | D53: =SUMIFS(_CALC_ALLOC!$I$1:$I$420,_CALC_ALLOC!$AS$1:$AS$420,"2027|"&$P$1,_CALC_ALLOC!$B$1:$B$420,$U53,_CALC_ALLOC!$D$1:$D$420,$W53,_CALC_ALLOC!$E$1:$E$420,$X53,_CALC_ALLOC!$F$1:$F$420,$Y53) -> 0 | E53: =SUMIFS(_CALC_ALLOC!$AI$1:$AI$420,_CALC_ALLOC!$AS$1:$AS$420,"2027|"&$P$1,_CALC_ALLOC!$B$1:$B$420,$U53,_CALC_ALLOC!$D$1:$D$420,$W53,_CALC_ALLOC!$E$1:$E$420,$X53,_CALC_ALLOC!$F$1:$F$420,$Y53) -> 0 | F53: =SUMIFS(_CALC_ALLOC!$AJ$1:$AJ$420,_CALC_ALLOC!$AS$1:$AS$420,"2027|"&$P$1,_CALC_ALLOC!$B$1:$B$420,$U53,_CALC_ALLOC!$D$1:$D$420,$W53,_CALC_ALLOC!$E$1:$E$420,$X53,_CALC_ALLOC!$F$1:$F$420,$Y53) -> 0 | G53: =SUMIFS(_CALC_ALLOC!$AK$1:$AK$420,_CALC_ALLOC!$AS$1:$AS$420,"2027|"&$P$1,_CALC_ALLOC!$B$1:$B$420,$U53,_CALC_ALLOC!$D$1:$D$420,$W53,_CALC_ALLOC!$E$1:$E$420,$X53,_CALC_ALLOC!$F$1:$F$420,$Y53) -> 0 | H53: =SUMIFS(_CALC_ALLOC!$AL$1:$AL$420,_CALC_ALLOC!$AS$1:$AS$420,"2027|"&$P$1,_CALC_ALLOC!$B$1:$B$420,$U53,_CALC_ALLOC!$D$1:$D$420,$W53,_CALC_ALLOC!$E$1:$E$420,$X53,_CALC_ALLOC!$F$1:$F$420,$Y53) -> 0 | I53: =SUMIFS(_CALC_ALLOC!$AR$1:$AR$420,_CALC_ALLOC!$AS$1:$AS$420,"2027|"&$P$1,_CALC_ALLOC!$B$1:$B$420,$U53,_CALC_ALLOC!$D$1:$D$420,$W53,_CALC_ALLOC!$E$1:$E$420,$X53,_CALC_ALLOC!$F$1:$F$420,$Y53) -> 0 | J53: =SUMIFS(_CALC_ALLOC!$AM$1:$AM$420,_CALC_ALLOC!$AS$1:$AS$420,"2027|"&$P$1,_CALC_ALLOC!$B$1:$B$420,$U53,_CALC_ALLOC!$D$1:$D$420,$W53,_CALC_ALLOC!$E$1:$E$420,$X53,_CALC_ALLOC!$F$1:$F$420,$Y53) -> 0 | K53: =E53+F53+G53+H53+I53+J53 -> 0 | L53: =SUMIFS(_CALC_ALLOC!$AN$1:$AN$420,_CALC_ALLOC!$AS$1:$AS$420,"2027|"&$P$1,_CALC_ALLOC!$B$1:$B$420,$U53,_CALC_ALLOC!$D$1:$D$420,$W53,_CALC_ALLOC!$E$1:$E$420,$X53,_CALC_ALLOC!$F$1:$F$420,$Y53) -> 0 | M53: =IF(D53=0,0,L53/D53) -> 0 | T53: ISCOM_LIL|BAC_COM|B3|ALT | U53: ISCOM_LIL | V53: ISCOM | W53: BAC_COM | X53: B3 | Y53: ALT | Z53: 3 | BF53: 2027BUD_V1 | BG53: ACT | BH53: 12 | BI53: 2024 | BJ53: PIGIER_LYO | BK53: PIGIER | BL53: BTS_GES | BM53: BTS2 | BN53: ALT | BO53: 40 | BP53: 2 | BQ53: 252000 | BR53: 21725.557 | BS53: 54373.002 | BT53: 12299.243 | BU53: 98210.434 | BV53: 6578.7616 | BW53: 38261.5 | BX53: 44840.262 | BY53: 34024.8 | BZ53: 197423.7 | CA53: 231448.5 | CB53: 20551.502 | CC53: 0 | CD53: 88144 | CE53: 220599.82 | CF53: 61804 | CG53: 30258 | CH53: 491052.17 | CI53: 2639292 | CJ53: 499926
B54: Mastère Communication, 1re année, alternance | C54: =SUMIFS(_CALC_ALLOC!$G$1:$G$420,_CALC_ALLOC!$AS$1:$AS$420,"2027|"&$P$1,_CALC_ALLOC!$B$1:$B$420,$U54,_CALC_ALLOC!$D$1:$D$420,$W54,_CALC_ALLOC!$E$1:$E$420,$X54,_CALC_ALLOC!$F$1:$F$420,$Y54) -> 0 | D54: =SUMIFS(_CALC_ALLOC!$I$1:$I$420,_CALC_ALLOC!$AS$1:$AS$420,"2027|"&$P$1,_CALC_ALLOC!$B$1:$B$420,$U54,_CALC_ALLOC!$D$1:$D$420,$W54,_CALC_ALLOC!$E$1:$E$420,$X54,_CALC_ALLOC!$F$1:$F$420,$Y54) -> 0 | E54: =SUMIFS(_CALC_ALLOC!$AI$1:$AI$420,_CALC_ALLOC!$AS$1:$AS$420,"2027|"&$P$1,_CALC_ALLOC!$B$1:$B$420,$U54,_CALC_ALLOC!$D$1:$D$420,$W54,_CALC_ALLOC!$E$1:$E$420,$X54,_CALC_ALLOC!$F$1:$F$420,$Y54) -> 0 | F54: =SUMIFS(_CALC_ALLOC!$AJ$1:$AJ$420,_CALC_ALLOC!$AS$1:$AS$420,"2027|"&$P$1,_CALC_ALLOC!$B$1:$B$420,$U54,_CALC_ALLOC!$D$1:$D$420,$W54,_CALC_ALLOC!$E$1:$E$420,$X54,_CALC_ALLOC!$F$1:$F$420,$Y54) -> 0 | G54: =SUMIFS(_CALC_ALLOC!$AK$1:$AK$420,_CALC_ALLOC!$AS$1:$AS$420,"2027|"&$P$1,_CALC_ALLOC!$B$1:$B$420,$U54,_CALC_ALLOC!$D$1:$D$420,$W54,_CALC_ALLOC!$E$1:$E$420,$X54,_CALC_ALLOC!$F$1:$F$420,$Y54) -> 0 | H54: =SUMIFS(_CALC_ALLOC!$AL$1:$AL$420,_CALC_ALLOC!$AS$1:$AS$420,"2027|"&$P$1,_CALC_ALLOC!$B$1:$B$420,$U54,_CALC_ALLOC!$D$1:$D$420,$W54,_CALC_ALLOC!$E$1:$E$420,$X54,_CALC_ALLOC!$F$1:$F$420,$Y54) -> 0 | I54: =SUMIFS(_CALC_ALLOC!$AR$1:$AR$420,_CALC_ALLOC!$AS$1:$AS$420,"2027|"&$P$1,_CALC_ALLOC!$B$1:$B$420,$U54,_CALC_ALLOC!$D$1:$D$420,$W54,_CALC_ALLOC!$E$1:$E$420,$X54,_CALC_ALLOC!$F$1:$F$420,$Y54) -> 0 | J54: =SUMIFS(_CALC_ALLOC!$AM$1:$AM$420,_CALC_ALLOC!$AS$1:$AS$420,"2027|"&$P$1,_CALC_ALLOC!$B$1:$B$420,$U54,_CALC_ALLOC!$D$1:$D$420,$W54,_CALC_ALLOC!$E$1:$E$420,$X54,_CALC_ALLOC!$F$1:$F$420,$Y54) -> 0 | K54: =E54+F54+G54+H54+I54+J54 -> 0 | L54: =SUMIFS(_CALC_ALLOC!$AN$1:$AN$420,_CALC_ALLOC!$AS$1:$AS$420,"2027|"&$P$1,_CALC_ALLOC!$B$1:$B$420,$U54,_CALC_ALLOC!$D$1:$D$420,$W54,_CALC_ALLOC!$E$1:$E$420,$X54,_CALC_ALLOC!$F$1:$F$420,$Y54) -> 0 | M54: =IF(D54=0,0,L54/D54) -> 0 | T54: ISCOM_LIL|MAS_COM|M1|ALT | U54: ISCOM_LIL | V54: ISCOM | W54: MAS_COM | X54: M1 | Y54: ALT | Z54: 3 | BF54: 2027BUD_V1 | BG54: ACT | BH54: 12 | BI54: 2024 | BJ54: PIGIER_LYO | BK54: PIGIER | BL54: BAC_RH | BM54: B1 | BN54: ALT | BO54: 41 | BP54: 2 | BQ54: 305040 | BR54: 14897.57 | BS54: 37284.458 | BT54: 27735.78 | BU54: 98210.434 | BV54: 6578.7616 | BW54: 38261.5 | BX54: 44840.262 | BY54: 42633.35 | BZ54: 180335.15 | CA54: 222968.5 | CB54: 82071.496 | CC54: 41 | CD54: 88144 | CE54: 220599.82 | CF54: 61804 | CG54: 30258 | CH54: 491052.17 | CI54: 2639292 | CJ54: 499926
B55: Mastère Communication, 2e année, alternance | C55: =SUMIFS(_CALC_ALLOC!$G$1:$G$420,_CALC_ALLOC!$AS$1:$AS$420,"2027|"&$P$1,_CALC_ALLOC!$B$1:$B$420,$U55,_CALC_ALLOC!$D$1:$D$420,$W55,_CALC_ALLOC!$E$1:$E$420,$X55,_CALC_ALLOC!$F$1:$F$420,$Y55) -> 0 | D55: =SUMIFS(_CALC_ALLOC!$I$1:$I$420,_CALC_ALLOC!$AS$1:$AS$420,"2027|"&$P$1,_CALC_ALLOC!$B$1:$B$420,$U55,_CALC_ALLOC!$D$1:$D$420,$W55,_CALC_ALLOC!$E$1:$E$420,$X55,_CALC_ALLOC!$F$1:$F$420,$Y55) -> 0 | E55: =SUMIFS(_CALC_ALLOC!$AI$1:$AI$420,_CALC_ALLOC!$AS$1:$AS$420,"2027|"&$P$1,_CALC_ALLOC!$B$1:$B$420,$U55,_CALC_ALLOC!$D$1:$D$420,$W55,_CALC_ALLOC!$E$1:$E$420,$X55,_CALC_ALLOC!$F$1:$F$420,$Y55) -> 0 | F55: =SUMIFS(_CALC_ALLOC!$AJ$1:$AJ$420,_CALC_ALLOC!$AS$1:$AS$420,"2027|"&$P$1,_CALC_ALLOC!$B$1:$B$420,$U55,_CALC_ALLOC!$D$1:$D$420,$W55,_CALC_ALLOC!$E$1:$E$420,$X55,_CALC_ALLOC!$F$1:$F$420,$Y55) -> 0 | G55: =SUMIFS(_CALC_ALLOC!$AK$1:$AK$420,_CALC_ALLOC!$AS$1:$AS$420,"2027|"&$P$1,_CALC_ALLOC!$B$1:$B$420,$U55,_CALC_ALLOC!$D$1:$D$420,$W55,_CALC_ALLOC!$E$1:$E$420,$X55,_CALC_ALLOC!$F$1:$F$420,$Y55) -> 0 | H55: =SUMIFS(_CALC_ALLOC!$AL$1:$AL$420,_CALC_ALLOC!$AS$1:$AS$420,"2027|"&$P$1,_CALC_ALLOC!$B$1:$B$420,$U55,_CALC_ALLOC!$D$1:$D$420,$W55,_CALC_ALLOC!$E$1:$E$420,$X55,_CALC_ALLOC!$F$1:$F$420,$Y55) -> 0 | I55: =SUMIFS(_CALC_ALLOC!$AR$1:$AR$420,_CALC_ALLOC!$AS$1:$AS$420,"2027|"&$P$1,_CALC_ALLOC!$B$1:$B$420,$U55,_CALC_ALLOC!$D$1:$D$420,$W55,_CALC_ALLOC!$E$1:$E$420,$X55,_CALC_ALLOC!$F$1:$F$420,$Y55) -> 0 | J55: =SUMIFS(_CALC_ALLOC!$AM$1:$AM$420,_CALC_ALLOC!$AS$1:$AS$420,"2027|"&$P$1,_CALC_ALLOC!$B$1:$B$420,$U55,_CALC_ALLOC!$D$1:$D$420,$W55,_CALC_ALLOC!$E$1:$E$420,$X55,_CALC_ALLOC!$F$1:$F$420,$Y55) -> 0 | K55: =E55+F55+G55+H55+I55+J55 -> 0 | L55: =SUMIFS(_CALC_ALLOC!$AN$1:$AN$420,_CALC_ALLOC!$AS$1:$AS$420,"2027|"&$P$1,_CALC_ALLOC!$B$1:$B$420,$U55,_CALC_ALLOC!$D$1:$D$420,$W55,_CALC_ALLOC!$E$1:$E$420,$X55,_CALC_ALLOC!$F$1:$F$420,$Y55) -> 0 | M55: =IF(D55=0,0,L55/D55) -> 0 | T55: ISCOM_LIL|MAS_COM|M2|ALT | U55: ISCOM_LIL | V55: ISCOM | W55: MAS_COM | X55: M2 | Y55: ALT | Z55: 3 | BF55: 2027BUD_V1 | BG55: ACT | BH55: 12 | BI55: 2024 | BJ55: PIGIER_LYO | BK55: PIGIER | BL55: BAC_RH | BM55: B2 | BN55: ALT | BO55: 40 | BP55: 2 | BQ55: 294000 | BR55: 14897.57 | BS55: 37284.458 | BT55: 12299.243 | BU55: 98210.434 | BV55: 6578.7616 | BW55: 38261.5 | BX55: 44840.262 | BY55: 27196.813 | BZ55: 180335.15 | CA55: 207531.97 | CB55: 86468.033 | CC55: 0 | CD55: 88144 | CE55: 220599.82 | CF55: 61804 | CG55: 30258 | CH55: 491052.17 | CI55: 2639292 | CJ55: 499926
B56: Toulouse | C56: =SUMIFS(_CALC_ALLOC!$G$1:$G$420,_CALC_ALLOC!$AS$1:$AS$420,"2027|"&$P$1,_CALC_ALLOC!$B$1:$B$420,$U56) -> 0 | D56: =SUMIFS(_CALC_ALLOC!$I$1:$I$420,_CALC_ALLOC!$AS$1:$AS$420,"2027|"&$P$1,_CALC_ALLOC!$B$1:$B$420,$U56) -> 0 | E56: =SUMIFS(_CALC_ALLOC!$AI$1:$AI$420,_CALC_ALLOC!$AS$1:$AS$420,"2027|"&$P$1,_CALC_ALLOC!$B$1:$B$420,$U56) -> 0 | F56: =SUMIFS(_CALC_ALLOC!$AJ$1:$AJ$420,_CALC_ALLOC!$AS$1:$AS$420,"2027|"&$P$1,_CALC_ALLOC!$B$1:$B$420,$U56) -> 0 | G56: =SUMIFS(_CALC_ALLOC!$AK$1:$AK$420,_CALC_ALLOC!$AS$1:$AS$420,"2027|"&$P$1,_CALC_ALLOC!$B$1:$B$420,$U56) -> 0 | H56: =SUMIFS(_CALC_ALLOC!$AL$1:$AL$420,_CALC_ALLOC!$AS$1:$AS$420,"2027|"&$P$1,_CALC_ALLOC!$B$1:$B$420,$U56) -> 0 | I56: =SUMIFS(_CALC_ALLOC!$AR$1:$AR$420,_CALC_ALLOC!$AS$1:$AS$420,"2027|"&$P$1,_CALC_ALLOC!$B$1:$B$420,$U56) -> 0 | J56: =SUMIFS(_CALC_ALLOC!$AM$1:$AM$420,_CALC_ALLOC!$AS$1:$AS$420,"2027|"&$P$1,_CALC_ALLOC!$B$1:$B$420,$U56) -> 0 | K56: =E56+F56+G56+H56+I56+J56 -> 0 | L56: =SUMIFS(_CALC_ALLOC!$AN$1:$AN$420,_CALC_ALLOC!$AS$1:$AS$420,"2027|"&$P$1,_CALC_ALLOC!$B$1:$B$420,$U56) -> 0 | M56: =IF(D56=0,0,L56/D56) -> 0 | T56: ISCOM_TLS | U56: ISCOM_TLS | V56: ISCOM | Z56: 2 | BF56: 2027BUD_V1 | BG56: ACT | BH56: 12 | BI56: 2024 | BJ56: TUNON_LYO | BK56: TUNON | BL56: BAC_TOU | BM56: B1 | BN56: ALT | BO56: 36 | BP56: 2 | BQ56: 267840 | BR56: 22035.978 | BS56: 53952.793 | BT56: 29200.051 | BU56: 108834.58 | BV56: 6503.9605 | BW56: 33312.15 | BX56: 39816.11 | BY56: 51236.029 | BZ56: 202603.49 | CA56: 253839.52 | CB56: 14000.483 | CC56: 36 | CD56: 66108 | CE56: 161858.54 | CF56: 39731 | CG56: 15578 | CH56: 326504.08 | CI56: 2639292 | CJ56: 499926
B57: Bachelor Communication, 1re année, initial | C57: =SUMIFS(_CALC_ALLOC!$G$1:$G$420,_CALC_ALLOC!$AS$1:$AS$420,"2027|"&$P$1,_CALC_ALLOC!$B$1:$B$420,$U57,_CALC_ALLOC!$D$1:$D$420,$W57,_CALC_ALLOC!$E$1:$E$420,$X57,_CALC_ALLOC!$F$1:$F$420,$Y57) -> 0 | D57: =SUMIFS(_CALC_ALLOC!$I$1:$I$420,_CALC_ALLOC!$AS$1:$AS$420,"2027|"&$P$1,_CALC_ALLOC!$B$1:$B$420,$U57,_CALC_ALLOC!$D$1:$D$420,$W57,_CALC_ALLOC!$E$1:$E$420,$X57,_CALC_ALLOC!$F$1:$F$420,$Y57) -> 0 | E57: =SUMIFS(_CALC_ALLOC!$AI$1:$AI$420,_CALC_ALLOC!$AS$1:$AS$420,"2027|"&$P$1,_CALC_ALLOC!$B$1:$B$420,$U57,_CALC_ALLOC!$D$1:$D$420,$W57,_CALC_ALLOC!$E$1:$E$420,$X57,_CALC_ALLOC!$F$1:$F$420,$Y57) -> 0 | F57: =SUMIFS(_CALC_ALLOC!$AJ$1:$AJ$420,_CALC_ALLOC!$AS$1:$AS$420,"2027|"&$P$1,_CALC_ALLOC!$B$1:$B$420,$U57,_CALC_ALLOC!$D$1:$D$420,$W57,_CALC_ALLOC!$E$1:$E$420,$X57,_CALC_ALLOC!$F$1:$F$420,$Y57) -> 0 | G57: =SUMIFS(_CALC_ALLOC!$AK$1:$AK$420,_CALC_ALLOC!$AS$1:$AS$420,"2027|"&$P$1,_CALC_ALLOC!$B$1:$B$420,$U57,_CALC_ALLOC!$D$1:$D$420,$W57,_CALC_ALLOC!$E$1:$E$420,$X57,_CALC_ALLOC!$F$1:$F$420,$Y57) -> 0 | H57: =SUMIFS(_CALC_ALLOC!$AL$1:$AL$420,_CALC_ALLOC!$AS$1:$AS$420,"2027|"&$P$1,_CALC_ALLOC!$B$1:$B$420,$U57,_CALC_ALLOC!$D$1:$D$420,$W57,_CALC_ALLOC!$E$1:$E$420,$X57,_CALC_ALLOC!$F$1:$F$420,$Y57) -> 0 | I57: =SUMIFS(_CALC_ALLOC!$AR$1:$AR$420,_CALC_ALLOC!$AS$1:$AS$420,"2027|"&$P$1,_CALC_ALLOC!$B$1:$B$420,$U57,_CALC_ALLOC!$D$1:$D$420,$W57,_CALC_ALLOC!$E$1:$E$420,$X57,_CALC_ALLOC!$F$1:$F$420,$Y57) -> 0 | J57: =SUMIFS(_CALC_ALLOC!$AM$1:$AM$420,_CALC_ALLOC!$AS$1:$AS$420,"2027|"&$P$1,_CALC_ALLOC!$B$1:$B$420,$U57,_CALC_ALLOC!$D$1:$D$420,$W57,_CALC_ALLOC!$E$1:$E$420,$X57,_CALC_ALLOC!$F$1:$F$420,$Y57) -> 0 | K57: =E57+F57+G57+H57+I57+J57 -> 0 | L57: =SUMIFS(_CALC_ALLOC!$AN$1:$AN$420,_CALC_ALLOC!$AS$1:$AS$420,"2027|"&$P$1,_CALC_ALLOC!$B$1:$B$420,$U57,_CALC_ALLOC!$D$1:$D$420,$W57,_CALC_ALLOC!$E$1:$E$420,$X57,_CALC_ALLOC!$F$1:$F$420,$Y57) -> 0 | M57: =IF(D57=0,0,L57/D57) -> 0 | T57: ISCOM_TLS|BAC_COM|B1|INIT | U57: ISCOM_TLS | V57: ISCOM | W57: BAC_COM | X57: B1 | Y57: INIT | Z57: 3 | BF57: 2027BUD_V1 | BG57: ACT | BH57: 12 | BI57: 2024 | BJ57: TUNON_LYO | BK57: TUNON | BL57: BAC_TOU | BM57: B2 | BN57: ALT | BO57: 35 | BP57: 2 | BQ57: 257250 | BR57: 22035.978 | BS57: 53952.793 | BT57: 13243.653 | BU57: 108834.58 | BV57: 6503.9605 | BW57: 33312.15 | BX57: 39816.11 | BY57: 35279.631 | BZ57: 202603.49 | CA57: 237883.12 | CB57: 19366.881 | CC57: 0 | CD57: 66108 | CE57: 161858.54 | CF57: 39731 | CG57: 15578 | CH57: 326504.08 | CI57: 2639292 | CJ57: 499926
B58: Bachelor Communication, 2e année, alternance | C58: =SUMIFS(_CALC_ALLOC!$G$1:$G$420,_CALC_ALLOC!$AS$1:$AS$420,"2027|"&$P$1,_CALC_ALLOC!$B$1:$B$420,$U58,_CALC_ALLOC!$D$1:$D$420,$W58,_CALC_ALLOC!$E$1:$E$420,$X58,_CALC_ALLOC!$F$1:$F$420,$Y58) -> 0 | D58: =SUMIFS(_CALC_ALLOC!$I$1:$I$420,_CALC_ALLOC!$AS$1:$AS$420,"2027|"&$P$1,_CALC_ALLOC!$B$1:$B$420,$U58,_CALC_ALLOC!$D$1:$D$420,$W58,_CALC_ALLOC!$E$1:$E$420,$X58,_CALC_ALLOC!$F$1:$F$420,$Y58) -> 0 | E58: =SUMIFS(_CALC_ALLOC!$AI$1:$AI$420,_CALC_ALLOC!$AS$1:$AS$420,"2027|"&$P$1,_CALC_ALLOC!$B$1:$B$420,$U58,_CALC_ALLOC!$D$1:$D$420,$W58,_CALC_ALLOC!$E$1:$E$420,$X58,_CALC_ALLOC!$F$1:$F$420,$Y58) -> 0 | F58: =SUMIFS(_CALC_ALLOC!$AJ$1:$AJ$420,_CALC_ALLOC!$AS$1:$AS$420,"2027|"&$P$1,_CALC_ALLOC!$B$1:$B$420,$U58,_CALC_ALLOC!$D$1:$D$420,$W58,_CALC_ALLOC!$E$1:$E$420,$X58,_CALC_ALLOC!$F$1:$F$420,$Y58) -> 0 | G58: =SUMIFS(_CALC_ALLOC!$AK$1:$AK$420,_CALC_ALLOC!$AS$1:$AS$420,"2027|"&$P$1,_CALC_ALLOC!$B$1:$B$420,$U58,_CALC_ALLOC!$D$1:$D$420,$W58,_CALC_ALLOC!$E$1:$E$420,$X58,_CALC_ALLOC!$F$1:$F$420,$Y58) -> 0 | H58: =SUMIFS(_CALC_ALLOC!$AL$1:$AL$420,_CALC_ALLOC!$AS$1:$AS$420,"2027|"&$P$1,_CALC_ALLOC!$B$1:$B$420,$U58,_CALC_ALLOC!$D$1:$D$420,$W58,_CALC_ALLOC!$E$1:$E$420,$X58,_CALC_ALLOC!$F$1:$F$420,$Y58) -> 0 | I58: =SUMIFS(_CALC_ALLOC!$AR$1:$AR$420,_CALC_ALLOC!$AS$1:$AS$420,"2027|"&$P$1,_CALC_ALLOC!$B$1:$B$420,$U58,_CALC_ALLOC!$D$1:$D$420,$W58,_CALC_ALLOC!$E$1:$E$420,$X58,_CALC_ALLOC!$F$1:$F$420,$Y58) -> 0 | J58: =SUMIFS(_CALC_ALLOC!$AM$1:$AM$420,_CALC_ALLOC!$AS$1:$AS$420,"2027|"&$P$1,_CALC_ALLOC!$B$1:$B$420,$U58,_CALC_ALLOC!$D$1:$D$420,$W58,_CALC_ALLOC!$E$1:$E$420,$X58,_CALC_ALLOC!$F$1:$F$420,$Y58) -> 0 | K58: =E58+F58+G58+H58+I58+J58 -> 0 | L58: =SUMIFS(_CALC_ALLOC!$AN$1:$AN$420,_CALC_ALLOC!$AS$1:$AS$420,"2027|"&$P$1,_CALC_ALLOC!$B$1:$B$420,$U58,_CALC_ALLOC!$D$1:$D$420,$W58,_CALC_ALLOC!$E$1:$E$420,$X58,_CALC_ALLOC!$F$1:$F$420,$Y58) -> 0 | M58: =IF(D58=0,0,L58/D58) -> 0 | T58: ISCOM_TLS|BAC_COM|B2|ALT | U58: ISCOM_TLS | V58: ISCOM | W58: BAC_COM | X58: B2 | Y58: ALT | Z58: 3 | BF58: 2027BUD_V1 | BG58: ACT | BH58: 12 | BI58: 2024 | BJ58: TUNON_LYO | BK58: TUNON | BL58: BAC_TOU | BM58: B3 | BN58: ALT | BO58: 34 | BP58: 2 | BQ58: 249900 | BR58: 22035.978 | BS58: 53952.793 | BT58: 12865.255 | BU58: 108834.58 | BV58: 6503.9605 | BW58: 33312.15 | BX58: 39816.11 | BY58: 34901.233 | BZ58: 202603.49 | CA58: 237504.72 | CB58: 12395.279 | CC58: 0 | CD58: 66108 | CE58: 161858.54 | CF58: 39731 | CG58: 15578 | CH58: 326504.08 | CI58: 2639292 | CJ58: 499926
B59: Bachelor Communication, 3e année, alternance | C59: =SUMIFS(_CALC_ALLOC!$G$1:$G$420,_CALC_ALLOC!$AS$1:$AS$420,"2027|"&$P$1,_CALC_ALLOC!$B$1:$B$420,$U59,_CALC_ALLOC!$D$1:$D$420,$W59,_CALC_ALLOC!$E$1:$E$420,$X59,_CALC_ALLOC!$F$1:$F$420,$Y59) -> 0 | D59: =SUMIFS(_CALC_ALLOC!$I$1:$I$420,_CALC_ALLOC!$AS$1:$AS$420,"2027|"&$P$1,_CALC_ALLOC!$B$1:$B$420,$U59,_CALC_ALLOC!$D$1:$D$420,$W59,_CALC_ALLOC!$E$1:$E$420,$X59,_CALC_ALLOC!$F$1:$F$420,$Y59) -> 0 | E59: =SUMIFS(_CALC_ALLOC!$AI$1:$AI$420,_CALC_ALLOC!$AS$1:$AS$420,"2027|"&$P$1,_CALC_ALLOC!$B$1:$B$420,$U59,_CALC_ALLOC!$D$1:$D$420,$W59,_CALC_ALLOC!$E$1:$E$420,$X59,_CALC_ALLOC!$F$1:$F$420,$Y59) -> 0 | F59: =SUMIFS(_CALC_ALLOC!$AJ$1:$AJ$420,_CALC_ALLOC!$AS$1:$AS$420,"2027|"&$P$1,_CALC_ALLOC!$B$1:$B$420,$U59,_CALC_ALLOC!$D$1:$D$420,$W59,_CALC_ALLOC!$E$1:$E$420,$X59,_CALC_ALLOC!$F$1:$F$420,$Y59) -> 0 | G59: =SUMIFS(_CALC_ALLOC!$AK$1:$AK$420,_CALC_ALLOC!$AS$1:$AS$420,"2027|"&$P$1,_CALC_ALLOC!$B$1:$B$420,$U59,_CALC_ALLOC!$D$1:$D$420,$W59,_CALC_ALLOC!$E$1:$E$420,$X59,_CALC_ALLOC!$F$1:$F$420,$Y59) -> 0 | H59: =SUMIFS(_CALC_ALLOC!$AL$1:$AL$420,_CALC_ALLOC!$AS$1:$AS$420,"2027|"&$P$1,_CALC_ALLOC!$B$1:$B$420,$U59,_CALC_ALLOC!$D$1:$D$420,$W59,_CALC_ALLOC!$E$1:$E$420,$X59,_CALC_ALLOC!$F$1:$F$420,$Y59) -> 0 | I59: =SUMIFS(_CALC_ALLOC!$AR$1:$AR$420,_CALC_ALLOC!$AS$1:$AS$420,"2027|"&$P$1,_CALC_ALLOC!$B$1:$B$420,$U59,_CALC_ALLOC!$D$1:$D$420,$W59,_CALC_ALLOC!$E$1:$E$420,$X59,_CALC_ALLOC!$F$1:$F$420,$Y59) -> 0 | J59: =SUMIFS(_CALC_ALLOC!$AM$1:$AM$420,_CALC_ALLOC!$AS$1:$AS$420,"2027|"&$P$1,_CALC_ALLOC!$B$1:$B$420,$U59,_CALC_ALLOC!$D$1:$D$420,$W59,_CALC_ALLOC!$E$1:$E$420,$X59,_CALC_ALLOC!$F$1:$F$420,$Y59) -> 0 | K59: =E59+F59+G59+H59+I59+J59 -> 0 | L59: =SUMIFS(_CALC_ALLOC!$AN$1:$AN$420,_CALC_ALLOC!$AS$1:$AS$420,"2027|"&$P$1,_CALC_ALLOC!$B$1:$B$420,$U59,_CALC_ALLOC!$D$1:$D$420,$W59,_CALC_ALLOC!$E$1:$E$420,$X59,_CALC_ALLOC!$F$1:$F$420,$Y59) -> 0 | M59: =IF(D59=0,0,L59/D59) -> 0 | T59: ISCOM_TLS|BAC_COM|B3|ALT | U59: ISCOM_TLS | V59: ISCOM | W59: BAC_COM | X59: B3 | Y59: ALT | Z59: 3 | BF59: 2027BUD_V1 | BG59: ACT | BH59: 12 | BI59: 2024 | BJ59: TUNON_PAR | BK59: TUNON | BL59: BAC_TOU | BM59: B1 | BN59: ALT | BO59: 42 | BP59: 2 | BQ59: 333060 | BR59: 22035.978 | BS59: 64380.832 | BT59: 40993.639 | BU59: 144344.22 | BV59: 7618.9207 | BW59: 39022.781 | BX59: 46641.702 | BY59: 63029.617 | BZ59: 255366.75 | CA59: 318396.37 | CB59: 14663.633 | CC59: 42 | CD59: 66108 | CE59: 193142.69 | CF59: 46862 | CG59: 24992 | CH59: 433033.08 | CI59: 2639292 | CJ59: 499926
B60: Mastère Communication, 1re année, alternance | C60: =SUMIFS(_CALC_ALLOC!$G$1:$G$420,_CALC_ALLOC!$AS$1:$AS$420,"2027|"&$P$1,_CALC_ALLOC!$B$1:$B$420,$U60,_CALC_ALLOC!$D$1:$D$420,$W60,_CALC_ALLOC!$E$1:$E$420,$X60,_CALC_ALLOC!$F$1:$F$420,$Y60) -> 0 | D60: =SUMIFS(_CALC_ALLOC!$I$1:$I$420,_CALC_ALLOC!$AS$1:$AS$420,"2027|"&$P$1,_CALC_ALLOC!$B$1:$B$420,$U60,_CALC_ALLOC!$D$1:$D$420,$W60,_CALC_ALLOC!$E$1:$E$420,$X60,_CALC_ALLOC!$F$1:$F$420,$Y60) -> 0 | E60: =SUMIFS(_CALC_ALLOC!$AI$1:$AI$420,_CALC_ALLOC!$AS$1:$AS$420,"2027|"&$P$1,_CALC_ALLOC!$B$1:$B$420,$U60,_CALC_ALLOC!$D$1:$D$420,$W60,_CALC_ALLOC!$E$1:$E$420,$X60,_CALC_ALLOC!$F$1:$F$420,$Y60) -> 0 | F60: =SUMIFS(_CALC_ALLOC!$AJ$1:$AJ$420,_CALC_ALLOC!$AS$1:$AS$420,"2027|"&$P$1,_CALC_ALLOC!$B$1:$B$420,$U60,_CALC_ALLOC!$D$1:$D$420,$W60,_CALC_ALLOC!$E$1:$E$420,$X60,_CALC_ALLOC!$F$1:$F$420,$Y60) -> 0 | G60: =SUMIFS(_CALC_ALLOC!$AK$1:$AK$420,_CALC_ALLOC!$AS$1:$AS$420,"2027|"&$P$1,_CALC_ALLOC!$B$1:$B$420,$U60,_CALC_ALLOC!$D$1:$D$420,$W60,_CALC_ALLOC!$E$1:$E$420,$X60,_CALC_ALLOC!$F$1:$F$420,$Y60) -> 0 | H60: =SUMIFS(_CALC_ALLOC!$AL$1:$AL$420,_CALC_ALLOC!$AS$1:$AS$420,"2027|"&$P$1,_CALC_ALLOC!$B$1:$B$420,$U60,_CALC_ALLOC!$D$1:$D$420,$W60,_CALC_ALLOC!$E$1:$E$420,$X60,_CALC_ALLOC!$F$1:$F$420,$Y60) -> 0 | I60: =SUMIFS(_CALC_ALLOC!$AR$1:$AR$420,_CALC_ALLOC!$AS$1:$AS$420,"2027|"&$P$1,_CALC_ALLOC!$B$1:$B$420,$U60,_CALC_ALLOC!$D$1:$D$420,$W60,_CALC_ALLOC!$E$1:$E$420,$X60,_CALC_ALLOC!$F$1:$F$420,$Y60) -> 0 | J60: =SUMIFS(_CALC_ALLOC!$AM$1:$AM$420,_CALC_ALLOC!$AS$1:$AS$420,"2027|"&$P$1,_CALC_ALLOC!$B$1:$B$420,$U60,_CALC_ALLOC!$D$1:$D$420,$W60,_CALC_ALLOC!$E$1:$E$420,$X60,_CALC_ALLOC!$F$1:$F$420,$Y60) -> 0 | K60: =E60+F60+G60+H60+I60+J60 -> 0 | L60: =SUMIFS(_CALC_ALLOC!$AN$1:$AN$420,_CALC_ALLOC!$AS$1:$AS$420,"2027|"&$P$1,_CALC_ALLOC!$B$1:$B$420,$U60,_CALC_ALLOC!$D$1:$D$420,$W60,_CALC_ALLOC!$E$1:$E$420,$X60,_CALC_ALLOC!$F$1:$F$420,$Y60) -> 0 | M60: =IF(D60=0,0,L60/D60) -> 0 | T60: ISCOM_TLS|MAS_COM|M1|ALT | U60: ISCOM_TLS | V60: ISCOM | W60: MAS_COM | X60: M1 | Y60: ALT | Z60: 3 | BF60: 2027BUD_V1 | BG60: ACT | BH60: 12 | BI60: 2024 | BJ60: TUNON_PAR | BK60: TUNON | BL60: BAC_TOU | BM60: B2 | BN60: ALT | BO60: 41 | BP60: 2 | BQ60: 321440 | BR60: 22035.978 | BS60: 64380.832 | BT60: 15620.651 | BU60: 144344.22 | BV60: 7618.9207 | BW60: 39022.781 | BX60: 46641.702 | BY60: 37656.629 | BZ60: 255366.75 | CA60: 293023.38 | CB60: 28416.621 | CC60: 0 | CD60: 66108 | CE60: 193142.69 | CF60: 46862 | CG60: 24992 | CH60: 433033.08 | CI60: 2639292 | CJ60: 499926
B61: Mastère Communication, 2e année, alternance | C61: =SUMIFS(_CALC_ALLOC!$G$1:$G$420,_CALC_ALLOC!$AS$1:$AS$420,"2027|"&$P$1,_CALC_ALLOC!$B$1:$B$420,$U61,_CALC_ALLOC!$D$1:$D$420,$W61,_CALC_ALLOC!$E$1:$E$420,$X61,_CALC_ALLOC!$F$1:$F$420,$Y61) -> 0 | D61: =SUMIFS(_CALC_ALLOC!$I$1:$I$420,_CALC_ALLOC!$AS$1:$AS$420,"2027|"&$P$1,_CALC_ALLOC!$B$1:$B$420,$U61,_CALC_ALLOC!$D$1:$D$420,$W61,_CALC_ALLOC!$E$1:$E$420,$X61,_CALC_ALLOC!$F$1:$F$420,$Y61) -> 0 | E61: =SUMIFS(_CALC_ALLOC!$AI$1:$AI$420,_CALC_ALLOC!$AS$1:$AS$420,"2027|"&$P$1,_CALC_ALLOC!$B$1:$B$420,$U61,_CALC_ALLOC!$D$1:$D$420,$W61,_CALC_ALLOC!$E$1:$E$420,$X61,_CALC_ALLOC!$F$1:$F$420,$Y61) -> 0 | F61: =SUMIFS(_CALC_ALLOC!$AJ$1:$AJ$420,_CALC_ALLOC!$AS$1:$AS$420,"2027|"&$P$1,_CALC_ALLOC!$B$1:$B$420,$U61,_CALC_ALLOC!$D$1:$D$420,$W61,_CALC_ALLOC!$E$1:$E$420,$X61,_CALC_ALLOC!$F$1:$F$420,$Y61) -> 0 | G61: =SUMIFS(_CALC_ALLOC!$AK$1:$AK$420,_CALC_ALLOC!$AS$1:$AS$420,"2027|"&$P$1,_CALC_ALLOC!$B$1:$B$420,$U61,_CALC_ALLOC!$D$1:$D$420,$W61,_CALC_ALLOC!$E$1:$E$420,$X61,_CALC_ALLOC!$F$1:$F$420,$Y61) -> 0 | H61: =SUMIFS(_CALC_ALLOC!$AL$1:$AL$420,_CALC_ALLOC!$AS$1:$AS$420,"2027|"&$P$1,_CALC_ALLOC!$B$1:$B$420,$U61,_CALC_ALLOC!$D$1:$D$420,$W61,_CALC_ALLOC!$E$1:$E$420,$X61,_CALC_ALLOC!$F$1:$F$420,$Y61) -> 0 | I61: =SUMIFS(_CALC_ALLOC!$AR$1:$AR$420,_CALC_ALLOC!$AS$1:$AS$420,"2027|"&$P$1,_CALC_ALLOC!$B$1:$B$420,$U61,_CALC_ALLOC!$D$1:$D$420,$W61,_CALC_ALLOC!$E$1:$E$420,$X61,_CALC_ALLOC!$F$1:$F$420,$Y61) -> 0 | J61: =SUMIFS(_CALC_ALLOC!$AM$1:$AM$420,_CALC_ALLOC!$AS$1:$AS$420,"2027|"&$P$1,_CALC_ALLOC!$B$1:$B$420,$U61,_CALC_ALLOC!$D$1:$D$420,$W61,_CALC_ALLOC!$E$1:$E$420,$X61,_CALC_ALLOC!$F$1:$F$420,$Y61) -> 0 | K61: =E61+F61+G61+H61+I61+J61 -> 0 | L61: =SUMIFS(_CALC_ALLOC!$AN$1:$AN$420,_CALC_ALLOC!$AS$1:$AS$420,"2027|"&$P$1,_CALC_ALLOC!$B$1:$B$420,$U61,_CALC_ALLOC!$D$1:$D$420,$W61,_CALC_ALLOC!$E$1:$E$420,$X61,_CALC_ALLOC!$F$1:$F$420,$Y61) -> 0 | M61: =IF(D61=0,0,L61/D61) -> 0 | T61: ISCOM_TLS|MAS_COM|M2|ALT | U61: ISCOM_TLS | V61: ISCOM | W61: MAS_COM | X61: M2 | Y61: ALT | Z61: 3 | BF61: 2027BUD_V1 | BG61: ACT | BH61: 12 | BI61: 2024 | BJ61: TUNON_PAR | BK61: TUNON | BL61: BAC_TOU | BM61: B3 | BN61: ALT | BO61: 40 | BP61: 2 | BQ61: 313600 | BR61: 22035.978 | BS61: 64380.832 | BT61: 15239.663 | BU61: 144344.22 | BV61: 7618.9207 | BW61: 39022.781 | BX61: 46641.702 | BY61: 37275.641 | BZ61: 255366.75 | CA61: 292642.39 | CB61: 20957.609 | CC61: 0 | CD61: 66108 | CE61: 193142.69 | CF61: 46862 | CG61: 24992 | CH61: 433033.08 | CI61: 2639292 | CJ61: 499926
B62: Ipac Bachelor Factory | C62: =SUMIFS(_CALC_ALLOC!$G$1:$G$420,_CALC_ALLOC!$AS$1:$AS$420,"2027|"&$P$1,_CALC_ALLOC!$C$1:$C$420,$V62) -> 0 | D62: =SUMIFS(_CALC_ALLOC!$I$1:$I$420,_CALC_ALLOC!$AS$1:$AS$420,"2027|"&$P$1,_CALC_ALLOC!$C$1:$C$420,$V62) -> 0 | E62: =SUMIFS(_CALC_ALLOC!$AI$1:$AI$420,_CALC_ALLOC!$AS$1:$AS$420,"2027|"&$P$1,_CALC_ALLOC!$C$1:$C$420,$V62) -> 0 | F62: =SUMIFS(_CALC_ALLOC!$AJ$1:$AJ$420,_CALC_ALLOC!$AS$1:$AS$420,"2027|"&$P$1,_CALC_ALLOC!$C$1:$C$420,$V62) -> 0 | G62: =SUMIFS(_CALC_ALLOC!$AK$1:$AK$420,_CALC_ALLOC!$AS$1:$AS$420,"2027|"&$P$1,_CALC_ALLOC!$C$1:$C$420,$V62) -> 0 | H62: =SUMIFS(_CALC_ALLOC!$AL$1:$AL$420,_CALC_ALLOC!$AS$1:$AS$420,"2027|"&$P$1,_CALC_ALLOC!$C$1:$C$420,$V62) -> 0 | I62: =SUMIFS(_CALC_ALLOC!$AR$1:$AR$420,_CALC_ALLOC!$AS$1:$AS$420,"2027|"&$P$1,_CALC_ALLOC!$C$1:$C$420,$V62) -> 0 | J62: =SUMIFS(_CALC_ALLOC!$AM$1:$AM$420,_CALC_ALLOC!$AS$1:$AS$420,"2027|"&$P$1,_CALC_ALLOC!$C$1:$C$420,$V62) -> 0 | K62: =E62+F62+G62+H62+I62+J62 -> 0 | L62: =SUMIFS(_CALC_ALLOC!$AN$1:$AN$420,_CALC_ALLOC!$AS$1:$AS$420,"2027|"&$P$1,_CALC_ALLOC!$C$1:$C$420,$V62) -> 0 | M62: =IF(D62=0,0,L62/D62) -> 0 | T62: IPAC | V62: IPAC | Z62: 1 | BF62: 2027BUD_V1 | BG62: ACT | BH62: 12 | BI62: 2025 | BJ62: IPAC_MTP | BK62: IPAC | BL62: BAC_CCE | BM62: B1 | BN62: ALT | BO62: 38 | BP62: 2 | BQ62: 256120 | BR62: 23045.644 | BS62: 44060.963 | BT62: 28022.995 | BU62: 88880.908 | BV62: 6722.1864 | BW62: 34820.295 | BX62: 41542.481 | BY62: 51068.638 | BZ62: 174484.35 | CA62: 225552.99 | CB62: 30567.01 | CC62: 38 | CD62: 69137 | CE62: 132183.02 | CF62: 41552 | CG62: 13798 | CH62: 266642.99 | CI62: 2760232 | CJ62: 580167
B63: Nantes | C63: =SUMIFS(_CALC_ALLOC!$G$1:$G$420,_CALC_ALLOC!$AS$1:$AS$420,"2027|"&$P$1,_CALC_ALLOC!$B$1:$B$420,$U63) -> 0 | D63: =SUMIFS(_CALC_ALLOC!$I$1:$I$420,_CALC_ALLOC!$AS$1:$AS$420,"2027|"&$P$1,_CALC_ALLOC!$B$1:$B$420,$U63) -> 0 | E63: =SUMIFS(_CALC_ALLOC!$AI$1:$AI$420,_CALC_ALLOC!$AS$1:$AS$420,"2027|"&$P$1,_CALC_ALLOC!$B$1:$B$420,$U63) -> 0 | F63: =SUMIFS(_CALC_ALLOC!$AJ$1:$AJ$420,_CALC_ALLOC!$AS$1:$AS$420,"2027|"&$P$1,_CALC_ALLOC!$B$1:$B$420,$U63) -> 0 | G63: =SUMIFS(_CALC_ALLOC!$AK$1:$AK$420,_CALC_ALLOC!$AS$1:$AS$420,"2027|"&$P$1,_CALC_ALLOC!$B$1:$B$420,$U63) -> 0 | H63: =SUMIFS(_CALC_ALLOC!$AL$1:$AL$420,_CALC_ALLOC!$AS$1:$AS$420,"2027|"&$P$1,_CALC_ALLOC!$B$1:$B$420,$U63) -> 0 | I63: =SUMIFS(_CALC_ALLOC!$AR$1:$AR$420,_CALC_ALLOC!$AS$1:$AS$420,"2027|"&$P$1,_CALC_ALLOC!$B$1:$B$420,$U63) -> 0 | J63: =SUMIFS(_CALC_ALLOC!$AM$1:$AM$420,_CALC_ALLOC!$AS$1:$AS$420,"2027|"&$P$1,_CALC_ALLOC!$B$1:$B$420,$U63) -> 0 | K63: =E63+F63+G63+H63+I63+J63 -> 0 | L63: =SUMIFS(_CALC_ALLOC!$AN$1:$AN$420,_CALC_ALLOC!$AS$1:$AS$420,"2027|"&$P$1,_CALC_ALLOC!$B$1:$B$420,$U63) -> 0 | M63: =IF(D63=0,0,L63/D63) -> 0 | T63: IPAC_NAN | U63: IPAC_NAN | V63: IPAC | Z63: 2 | BF63: 2027BUD_V1 | BG63: ACT | BH63: 12 | BI63: 2025 | BJ63: IPAC_MTP | BK63: IPAC | BL63: BAC_CCE | BM63: B2 | BN63: ALT | BO63: 37 | BP63: 2 | BQ63: 246050 | BR63: 23045.644 | BS63: 44060.963 | BT63: 13850.653 | BU63: 88880.908 | BV63: 6722.1864 | BW63: 34820.295 | BX63: 41542.481 | BY63: 36896.296 | BZ63: 174484.35 | CA63: 211380.65 | CB63: 34669.352 | CC63: 0 | CD63: 69137 | CE63: 132183.02 | CF63: 41552 | CG63: 13798 | CH63: 266642.99 | CI63: 2760232 | CJ63: 580167
B64: Bachelor Commerce, 1re année, alternance | C64: =SUMIFS(_CALC_ALLOC!$G$1:$G$420,_CALC_ALLOC!$AS$1:$AS$420,"2027|"&$P$1,_CALC_ALLOC!$B$1:$B$420,$U64,_CALC_ALLOC!$D$1:$D$420,$W64,_CALC_ALLOC!$E$1:$E$420,$X64,_CALC_ALLOC!$F$1:$F$420,$Y64) -> 0 | D64: =SUMIFS(_CALC_ALLOC!$I$1:$I$420,_CALC_ALLOC!$AS$1:$AS$420,"2027|"&$P$1,_CALC_ALLOC!$B$1:$B$420,$U64,_CALC_ALLOC!$D$1:$D$420,$W64,_CALC_ALLOC!$E$1:$E$420,$X64,_CALC_ALLOC!$F$1:$F$420,$Y64) -> 0 | E64: =SUMIFS(_CALC_ALLOC!$AI$1:$AI$420,_CALC_ALLOC!$AS$1:$AS$420,"2027|"&$P$1,_CALC_ALLOC!$B$1:$B$420,$U64,_CALC_ALLOC!$D$1:$D$420,$W64,_CALC_ALLOC!$E$1:$E$420,$X64,_CALC_ALLOC!$F$1:$F$420,$Y64) -> 0 | F64: =SUMIFS(_CALC_ALLOC!$AJ$1:$AJ$420,_CALC_ALLOC!$AS$1:$AS$420,"2027|"&$P$1,_CALC_ALLOC!$B$1:$B$420,$U64,_CALC_ALLOC!$D$1:$D$420,$W64,_CALC_ALLOC!$E$1:$E$420,$X64,_CALC_ALLOC!$F$1:$F$420,$Y64) -> 0 | G64: =SUMIFS(_CALC_ALLOC!$AK$1:$AK$420,_CALC_ALLOC!$AS$1:$AS$420,"2027|"&$P$1,_CALC_ALLOC!$B$1:$B$420,$U64,_CALC_ALLOC!$D$1:$D$420,$W64,_CALC_ALLOC!$E$1:$E$420,$X64,_CALC_ALLOC!$F$1:$F$420,$Y64) -> 0 | H64: =SUMIFS(_CALC_ALLOC!$AL$1:$AL$420,_CALC_ALLOC!$AS$1:$AS$420,"2027|"&$P$1,_CALC_ALLOC!$B$1:$B$420,$U64,_CALC_ALLOC!$D$1:$D$420,$W64,_CALC_ALLOC!$E$1:$E$420,$X64,_CALC_ALLOC!$F$1:$F$420,$Y64) -> 0 | I64: =SUMIFS(_CALC_ALLOC!$AR$1:$AR$420,_CALC_ALLOC!$AS$1:$AS$420,"2027|"&$P$1,_CALC_ALLOC!$B$1:$B$420,$U64,_CALC_ALLOC!$D$1:$D$420,$W64,_CALC_ALLOC!$E$1:$E$420,$X64,_CALC_ALLOC!$F$1:$F$420,$Y64) -> 0 | J64: =SUMIFS(_CALC_ALLOC!$AM$1:$AM$420,_CALC_ALLOC!$AS$1:$AS$420,"2027|"&$P$1,_CALC_ALLOC!$B$1:$B$420,$U64,_CALC_ALLOC!$D$1:$D$420,$W64,_CALC_ALLOC!$E$1:$E$420,$X64,_CALC_ALLOC!$F$1:$F$420,$Y64) -> 0 | K64: =E64+F64+G64+H64+I64+J64 -> 0 | L64: =SUMIFS(_CALC_ALLOC!$AN$1:$AN$420,_CALC_ALLOC!$AS$1:$AS$420,"2027|"&$P$1,_CALC_ALLOC!$B$1:$B$420,$U64,_CALC_ALLOC!$D$1:$D$420,$W64,_CALC_ALLOC!$E$1:$E$420,$X64,_CALC_ALLOC!$F$1:$F$420,$Y64) -> 0 | M64: =IF(D64=0,0,L64/D64) -> 0 | T64: IPAC_NAN|BAC_CCE|B1|ALT | U64: IPAC_NAN | V64: IPAC | W64: BAC_CCE | X64: B1 | Y64: ALT | Z64: 3 | BF64: 2027BUD_V1 | BG64: ACT | BH64: 12 | BI64: 2025 | BJ64: IPAC_MTP | BK64: IPAC | BL64: BAC_CCE | BM64: B3 | BN64: ALT | BO64: 36 | BP64: 2 | BQ64: 239400 | BR64: 23045.644 | BS64: 44060.963 | BT64: 13476.311 | BU64: 88880.908 | BV64: 6722.1864 | BW64: 34820.295 | BX64: 41542.481 | BY64: 36521.954 | BZ64: 174484.35 | CA64: 211006.31 | CB64: 28393.694 | CC64: 0 | CD64: 69137 | CE64: 132183.02 | CF64: 41552 | CG64: 13798 | CH64: 266642.99 | CI64: 2760232 | CJ64: 580167
B65: Bachelor Commerce, 2e année, alternance | C65: =SUMIFS(_CALC_ALLOC!$G$1:$G$420,_CALC_ALLOC!$AS$1:$AS$420,"2027|"&$P$1,_CALC_ALLOC!$B$1:$B$420,$U65,_CALC_ALLOC!$D$1:$D$420,$W65,_CALC_ALLOC!$E$1:$E$420,$X65,_CALC_ALLOC!$F$1:$F$420,$Y65) -> 0 | D65: =SUMIFS(_CALC_ALLOC!$I$1:$I$420,_CALC_ALLOC!$AS$1:$AS$420,"2027|"&$P$1,_CALC_ALLOC!$B$1:$B$420,$U65,_CALC_ALLOC!$D$1:$D$420,$W65,_CALC_ALLOC!$E$1:$E$420,$X65,_CALC_ALLOC!$F$1:$F$420,$Y65) -> 0 | E65: =SUMIFS(_CALC_ALLOC!$AI$1:$AI$420,_CALC_ALLOC!$AS$1:$AS$420,"2027|"&$P$1,_CALC_ALLOC!$B$1:$B$420,$U65,_CALC_ALLOC!$D$1:$D$420,$W65,_CALC_ALLOC!$E$1:$E$420,$X65,_CALC_ALLOC!$F$1:$F$420,$Y65) -> 0 | F65: =SUMIFS(_CALC_ALLOC!$AJ$1:$AJ$420,_CALC_ALLOC!$AS$1:$AS$420,"2027|"&$P$1,_CALC_ALLOC!$B$1:$B$420,$U65,_CALC_ALLOC!$D$1:$D$420,$W65,_CALC_ALLOC!$E$1:$E$420,$X65,_CALC_ALLOC!$F$1:$F$420,$Y65) -> 0 | G65: =SUMIFS(_CALC_ALLOC!$AK$1:$AK$420,_CALC_ALLOC!$AS$1:$AS$420,"2027|"&$P$1,_CALC_ALLOC!$B$1:$B$420,$U65,_CALC_ALLOC!$D$1:$D$420,$W65,_CALC_ALLOC!$E$1:$E$420,$X65,_CALC_ALLOC!$F$1:$F$420,$Y65) -> 0 | H65: =SUMIFS(_CALC_ALLOC!$AL$1:$AL$420,_CALC_ALLOC!$AS$1:$AS$420,"2027|"&$P$1,_CALC_ALLOC!$B$1:$B$420,$U65,_CALC_ALLOC!$D$1:$D$420,$W65,_CALC_ALLOC!$E$1:$E$420,$X65,_CALC_ALLOC!$F$1:$F$420,$Y65) -> 0 | I65: =SUMIFS(_CALC_ALLOC!$AR$1:$AR$420,_CALC_ALLOC!$AS$1:$AS$420,"2027|"&$P$1,_CALC_ALLOC!$B$1:$B$420,$U65,_CALC_ALLOC!$D$1:$D$420,$W65,_CALC_ALLOC!$E$1:$E$420,$X65,_CALC_ALLOC!$F$1:$F$420,$Y65) -> 0 | J65: =SUMIFS(_CALC_ALLOC!$AM$1:$AM$420,_CALC_ALLOC!$AS$1:$AS$420,"2027|"&$P$1,_CALC_ALLOC!$B$1:$B$420,$U65,_CALC_ALLOC!$D$1:$D$420,$W65,_CALC_ALLOC!$E$1:$E$420,$X65,_CALC_ALLOC!$F$1:$F$420,$Y65) -> 0 | K65: =E65+F65+G65+H65+I65+J65 -> 0 | L65: =SUMIFS(_CALC_ALLOC!$AN$1:$AN$420,_CALC_ALLOC!$AS$1:$AS$420,"2027|"&$P$1,_CALC_ALLOC!$B$1:$B$420,$U65,_CALC_ALLOC!$D$1:$D$420,$W65,_CALC_ALLOC!$E$1:$E$420,$X65,_CALC_ALLOC!$F$1:$F$420,$Y65) -> 0 | M65: =IF(D65=0,0,L65/D65) -> 0 | T65: IPAC_NAN|BAC_CCE|B2|ALT | U65: IPAC_NAN | V65: IPAC | W65: BAC_CCE | X65: B2 | Y65: ALT | Z65: 3 | BF65: 2027BUD_V1 | BG65: ACT | BH65: 12 | BI65: 2025 | BJ65: IPAC_NAN | BK65: IPAC | BL65: BAC_CCE | BM65: B1 | BN65: ALT | BO65: 47 | BP65: 2 | BQ65: 333230 | BR65: 23045.644 | BS65: 53637.103 | BT65: 37578.054 | BU65: 124275.61 | BV65: 8236.2095 | BW65: 42662.793 | BX65: 50899.002 | BY65: 60623.698 | BZ65: 228811.72 | CA65: 289435.42 | CB65: 43794.585 | CC65: 47 | CD65: 69137 | CE65: 160911.47 | CF65: 51495 | CG65: 19782 | CH65: 372827.21 | CI65: 2760232 | CJ65: 580167
B66: Bachelor Commerce, 3e année, alternance | C66: =SUMIFS(_CALC_ALLOC!$G$1:$G$420,_CALC_ALLOC!$AS$1:$AS$420,"2027|"&$P$1,_CALC_ALLOC!$B$1:$B$420,$U66,_CALC_ALLOC!$D$1:$D$420,$W66,_CALC_ALLOC!$E$1:$E$420,$X66,_CALC_ALLOC!$F$1:$F$420,$Y66) -> 0 | D66: =SUMIFS(_CALC_ALLOC!$I$1:$I$420,_CALC_ALLOC!$AS$1:$AS$420,"2027|"&$P$1,_CALC_ALLOC!$B$1:$B$420,$U66,_CALC_ALLOC!$D$1:$D$420,$W66,_CALC_ALLOC!$E$1:$E$420,$X66,_CALC_ALLOC!$F$1:$F$420,$Y66) -> 0 | E66: =SUMIFS(_CALC_ALLOC!$AI$1:$AI$420,_CALC_ALLOC!$AS$1:$AS$420,"2027|"&$P$1,_CALC_ALLOC!$B$1:$B$420,$U66,_CALC_ALLOC!$D$1:$D$420,$W66,_CALC_ALLOC!$E$1:$E$420,$X66,_CALC_ALLOC!$F$1:$F$420,$Y66) -> 0 | F66: =SUMIFS(_CALC_ALLOC!$AJ$1:$AJ$420,_CALC_ALLOC!$AS$1:$AS$420,"2027|"&$P$1,_CALC_ALLOC!$B$1:$B$420,$U66,_CALC_ALLOC!$D$1:$D$420,$W66,_CALC_ALLOC!$E$1:$E$420,$X66,_CALC_ALLOC!$F$1:$F$420,$Y66) -> 0 | G66: =SUMIFS(_CALC_ALLOC!$AK$1:$AK$420,_CALC_ALLOC!$AS$1:$AS$420,"2027|"&$P$1,_CALC_ALLOC!$B$1:$B$420,$U66,_CALC_ALLOC!$D$1:$D$420,$W66,_CALC_ALLOC!$E$1:$E$420,$X66,_CALC_ALLOC!$F$1:$F$420,$Y66) -> 0 | H66: =SUMIFS(_CALC_ALLOC!$AL$1:$AL$420,_CALC_ALLOC!$AS$1:$AS$420,"2027|"&$P$1,_CALC_ALLOC!$B$1:$B$420,$U66,_CALC_ALLOC!$D$1:$D$420,$W66,_CALC_ALLOC!$E$1:$E$420,$X66,_CALC_ALLOC!$F$1:$F$420,$Y66) -> 0 | I66: =SUMIFS(_CALC_ALLOC!$AR$1:$AR$420,_CALC_ALLOC!$AS$1:$AS$420,"2027|"&$P$1,_CALC_ALLOC!$B$1:$B$420,$U66,_CALC_ALLOC!$D$1:$D$420,$W66,_CALC_ALLOC!$E$1:$E$420,$X66,_CALC_ALLOC!$F$1:$F$420,$Y66) -> 0 | J66: =SUMIFS(_CALC_ALLOC!$AM$1:$AM$420,_CALC_ALLOC!$AS$1:$AS$420,"2027|"&$P$1,_CALC_ALLOC!$B$1:$B$420,$U66,_CALC_ALLOC!$D$1:$D$420,$W66,_CALC_ALLOC!$E$1:$E$420,$X66,_CALC_ALLOC!$F$1:$F$420,$Y66) -> 0 | K66: =E66+F66+G66+H66+I66+J66 -> 0 | L66: =SUMIFS(_CALC_ALLOC!$AN$1:$AN$420,_CALC_ALLOC!$AS$1:$AS$420,"2027|"&$P$1,_CALC_ALLOC!$B$1:$B$420,$U66,_CALC_ALLOC!$D$1:$D$420,$W66,_CALC_ALLOC!$E$1:$E$420,$X66,_CALC_ALLOC!$F$1:$F$420,$Y66) -> 0 | M66: =IF(D66=0,0,L66/D66) -> 0 | T66: IPAC_NAN|BAC_CCE|B3|ALT | U66: IPAC_NAN | V66: IPAC | W66: BAC_CCE | X66: B3 | Y66: ALT | Z66: 3 | BF66: 2027BUD_V1 | BG66: ACT | BH66: 12 | BI66: 2025 | BJ66: IPAC_NAN | BK66: IPAC | BL66: BAC_CCE | BM66: B2 | BN66: ALT | BO66: 45 | BP66: 2 | BQ66: 315000 | BR66: 23045.644 | BS66: 53637.103 | BT66: 17038.769 | BU66: 124275.61 | BV66: 8236.2095 | BW66: 42662.793 | BX66: 50899.002 | BY66: 40084.412 | BZ66: 228811.72 | CA66: 268896.13 | CB66: 46103.87 | CC66: 0 | CD66: 69137 | CE66: 160911.47 | CF66: 51495 | CG66: 19782 | CH66: 372827.21 | CI66: 2760232 | CJ66: 580167
B67: Rennes | C67: =SUMIFS(_CALC_ALLOC!$G$1:$G$420,_CALC_ALLOC!$AS$1:$AS$420,"2027|"&$P$1,_CALC_ALLOC!$B$1:$B$420,$U67) -> 0 | D67: =SUMIFS(_CALC_ALLOC!$I$1:$I$420,_CALC_ALLOC!$AS$1:$AS$420,"2027|"&$P$1,_CALC_ALLOC!$B$1:$B$420,$U67) -> 0 | E67: =SUMIFS(_CALC_ALLOC!$AI$1:$AI$420,_CALC_ALLOC!$AS$1:$AS$420,"2027|"&$P$1,_CALC_ALLOC!$B$1:$B$420,$U67) -> 0 | F67: =SUMIFS(_CALC_ALLOC!$AJ$1:$AJ$420,_CALC_ALLOC!$AS$1:$AS$420,"2027|"&$P$1,_CALC_ALLOC!$B$1:$B$420,$U67) -> 0 | G67: =SUMIFS(_CALC_ALLOC!$AK$1:$AK$420,_CALC_ALLOC!$AS$1:$AS$420,"2027|"&$P$1,_CALC_ALLOC!$B$1:$B$420,$U67) -> 0 | H67: =SUMIFS(_CALC_ALLOC!$AL$1:$AL$420,_CALC_ALLOC!$AS$1:$AS$420,"2027|"&$P$1,_CALC_ALLOC!$B$1:$B$420,$U67) -> 0 | I67: =SUMIFS(_CALC_ALLOC!$AR$1:$AR$420,_CALC_ALLOC!$AS$1:$AS$420,"2027|"&$P$1,_CALC_ALLOC!$B$1:$B$420,$U67) -> 0 | J67: =SUMIFS(_CALC_ALLOC!$AM$1:$AM$420,_CALC_ALLOC!$AS$1:$AS$420,"2027|"&$P$1,_CALC_ALLOC!$B$1:$B$420,$U67) -> 0 | K67: =E67+F67+G67+H67+I67+J67 -> 0 | L67: =SUMIFS(_CALC_ALLOC!$AN$1:$AN$420,_CALC_ALLOC!$AS$1:$AS$420,"2027|"&$P$1,_CALC_ALLOC!$B$1:$B$420,$U67) -> 0 | M67: =IF(D67=0,0,L67/D67) -> 0 | T67: IPAC_REN | U67: IPAC_REN | V67: IPAC | Z67: 2 | BF67: 2027BUD_V1 | BG67: ACT | BH67: 12 | BI67: 2025 | BJ67: IPAC_NAN | BK67: IPAC | BL67: BAC_CCE | BM67: B3 | BN67: ALT | BO67: 44 | BP67: 2 | BQ67: 308000 | BR67: 23045.644 | BS67: 53637.103 | BT67: 16660.126 | BU67: 124275.61 | BV67: 8236.2095 | BW67: 42662.793 | BX67: 50899.002 | BY67: 39705.769 | BZ67: 228811.72 | CA67: 268517.49 | CB67: 39482.513 | CC67: 0 | CD67: 69137 | CE67: 160911.47 | CF67: 51495 | CG67: 19782 | CH67: 372827.21 | CI67: 2760232 | CJ67: 580167
B68: Bachelor Commerce, 1re année, alternance | C68: =SUMIFS(_CALC_ALLOC!$G$1:$G$420,_CALC_ALLOC!$AS$1:$AS$420,"2027|"&$P$1,_CALC_ALLOC!$B$1:$B$420,$U68,_CALC_ALLOC!$D$1:$D$420,$W68,_CALC_ALLOC!$E$1:$E$420,$X68,_CALC_ALLOC!$F$1:$F$420,$Y68) -> 0 | D68: =SUMIFS(_CALC_ALLOC!$I$1:$I$420,_CALC_ALLOC!$AS$1:$AS$420,"2027|"&$P$1,_CALC_ALLOC!$B$1:$B$420,$U68,_CALC_ALLOC!$D$1:$D$420,$W68,_CALC_ALLOC!$E$1:$E$420,$X68,_CALC_ALLOC!$F$1:$F$420,$Y68) -> 0 | E68: =SUMIFS(_CALC_ALLOC!$AI$1:$AI$420,_CALC_ALLOC!$AS$1:$AS$420,"2027|"&$P$1,_CALC_ALLOC!$B$1:$B$420,$U68,_CALC_ALLOC!$D$1:$D$420,$W68,_CALC_ALLOC!$E$1:$E$420,$X68,_CALC_ALLOC!$F$1:$F$420,$Y68) -> 0 | F68: =SUMIFS(_CALC_ALLOC!$AJ$1:$AJ$420,_CALC_ALLOC!$AS$1:$AS$420,"2027|"&$P$1,_CALC_ALLOC!$B$1:$B$420,$U68,_CALC_ALLOC!$D$1:$D$420,$W68,_CALC_ALLOC!$E$1:$E$420,$X68,_CALC_ALLOC!$F$1:$F$420,$Y68) -> 0 | G68: =SUMIFS(_CALC_ALLOC!$AK$1:$AK$420,_CALC_ALLOC!$AS$1:$AS$420,"2027|"&$P$1,_CALC_ALLOC!$B$1:$B$420,$U68,_CALC_ALLOC!$D$1:$D$420,$W68,_CALC_ALLOC!$E$1:$E$420,$X68,_CALC_ALLOC!$F$1:$F$420,$Y68) -> 0 | H68: =SUMIFS(_CALC_ALLOC!$AL$1:$AL$420,_CALC_ALLOC!$AS$1:$AS$420,"2027|"&$P$1,_CALC_ALLOC!$B$1:$B$420,$U68,_CALC_ALLOC!$D$1:$D$420,$W68,_CALC_ALLOC!$E$1:$E$420,$X68,_CALC_ALLOC!$F$1:$F$420,$Y68) -> 0 | I68: =SUMIFS(_CALC_ALLOC!$AR$1:$AR$420,_CALC_ALLOC!$AS$1:$AS$420,"2027|"&$P$1,_CALC_ALLOC!$B$1:$B$420,$U68,_CALC_ALLOC!$D$1:$D$420,$W68,_CALC_ALLOC!$E$1:$E$420,$X68,_CALC_ALLOC!$F$1:$F$420,$Y68) -> 0 | J68: =SUMIFS(_CALC_ALLOC!$AM$1:$AM$420,_CALC_ALLOC!$AS$1:$AS$420,"2027|"&$P$1,_CALC_ALLOC!$B$1:$B$420,$U68,_CALC_ALLOC!$D$1:$D$420,$W68,_CALC_ALLOC!$E$1:$E$420,$X68,_CALC_ALLOC!$F$1:$F$420,$Y68) -> 0 | K68: =E68+F68+G68+H68+I68+J68 -> 0 | L68: =SUMIFS(_CALC_ALLOC!$AN$1:$AN$420,_CALC_ALLOC!$AS$1:$AS$420,"2027|"&$P$1,_CALC_ALLOC!$B$1:$B$420,$U68,_CALC_ALLOC!$D$1:$D$420,$W68,_CALC_ALLOC!$E$1:$E$420,$X68,_CALC_ALLOC!$F$1:$F$420,$Y68) -> 0 | M68: =IF(D68=0,0,L68/D68) -> 0 | T68: IPAC_REN|BAC_CCE|B1|ALT | U68: IPAC_REN | V68: IPAC | W68: BAC_CCE | X68: B1 | Y68: ALT | Z68: 3 | BF68: 2027BUD_V1 | BG68: ACT | BH68: 12 | BI68: 2025 | BJ68: IPAC_REN | BK68: IPAC | BL68: BAC_CCE | BM68: B1 | BN68: ALT | BO68: 38 | BP68: 2 | BQ68: 256120 | BR68: 23045.644 | BS68: 44085.599 | BT68: 27799.995 | BU68: 88930.611 | BV68: 6722.1864 | BW68: 34820.295 | BX68: 41542.481 | BY68: 50845.638 | BZ68: 174558.69 | CA68: 225404.33 | CB68: 30715.67 | CC68: 38 | CD68: 69137 | CE68: 132256.93 | CF68: 41552 | CG68: 13575 | CH68: 266792.1 | CI68: 2760232 | CJ68: 580167
B69: Bachelor Commerce, 2e année, alternance | C69: =SUMIFS(_CALC_ALLOC!$G$1:$G$420,_CALC_ALLOC!$AS$1:$AS$420,"2027|"&$P$1,_CALC_ALLOC!$B$1:$B$420,$U69,_CALC_ALLOC!$D$1:$D$420,$W69,_CALC_ALLOC!$E$1:$E$420,$X69,_CALC_ALLOC!$F$1:$F$420,$Y69) -> 0 | D69: =SUMIFS(_CALC_ALLOC!$I$1:$I$420,_CALC_ALLOC!$AS$1:$AS$420,"2027|"&$P$1,_CALC_ALLOC!$B$1:$B$420,$U69,_CALC_ALLOC!$D$1:$D$420,$W69,_CALC_ALLOC!$E$1:$E$420,$X69,_CALC_ALLOC!$F$1:$F$420,$Y69) -> 0 | E69: =SUMIFS(_CALC_ALLOC!$AI$1:$AI$420,_CALC_ALLOC!$AS$1:$AS$420,"2027|"&$P$1,_CALC_ALLOC!$B$1:$B$420,$U69,_CALC_ALLOC!$D$1:$D$420,$W69,_CALC_ALLOC!$E$1:$E$420,$X69,_CALC_ALLOC!$F$1:$F$420,$Y69) -> 0 | F69: =SUMIFS(_CALC_ALLOC!$AJ$1:$AJ$420,_CALC_ALLOC!$AS$1:$AS$420,"2027|"&$P$1,_CALC_ALLOC!$B$1:$B$420,$U69,_CALC_ALLOC!$D$1:$D$420,$W69,_CALC_ALLOC!$E$1:$E$420,$X69,_CALC_ALLOC!$F$1:$F$420,$Y69) -> 0 | G69: =SUMIFS(_CALC_ALLOC!$AK$1:$AK$420,_CALC_ALLOC!$AS$1:$AS$420,"2027|"&$P$1,_CALC_ALLOC!$B$1:$B$420,$U69,_CALC_ALLOC!$D$1:$D$420,$W69,_CALC_ALLOC!$E$1:$E$420,$X69,_CALC_ALLOC!$F$1:$F$420,$Y69) -> 0 | H69: =SUMIFS(_CALC_ALLOC!$AL$1:$AL$420,_CALC_ALLOC!$AS$1:$AS$420,"2027|"&$P$1,_CALC_ALLOC!$B$1:$B$420,$U69,_CALC_ALLOC!$D$1:$D$420,$W69,_CALC_ALLOC!$E$1:$E$420,$X69,_CALC_ALLOC!$F$1:$F$420,$Y69) -> 0 | I69: =SUMIFS(_CALC_ALLOC!$AR$1:$AR$420,_CALC_ALLOC!$AS$1:$AS$420,"2027|"&$P$1,_CALC_ALLOC!$B$1:$B$420,$U69,_CALC_ALLOC!$D$1:$D$420,$W69,_CALC_ALLOC!$E$1:$E$420,$X69,_CALC_ALLOC!$F$1:$F$420,$Y69) -> 0 | J69: =SUMIFS(_CALC_ALLOC!$AM$1:$AM$420,_CALC_ALLOC!$AS$1:$AS$420,"2027|"&$P$1,_CALC_ALLOC!$B$1:$B$420,$U69,_CALC_ALLOC!$D$1:$D$420,$W69,_CALC_ALLOC!$E$1:$E$420,$X69,_CALC_ALLOC!$F$1:$F$420,$Y69) -> 0 | K69: =E69+F69+G69+H69+I69+J69 -> 0 | L69: =SUMIFS(_CALC_ALLOC!$AN$1:$AN$420,_CALC_ALLOC!$AS$1:$AS$420,"2027|"&$P$1,_CALC_ALLOC!$B$1:$B$420,$U69,_CALC_ALLOC!$D$1:$D$420,$W69,_CALC_ALLOC!$E$1:$E$420,$X69,_CALC_ALLOC!$F$1:$F$420,$Y69) -> 0 | M69: =IF(D69=0,0,L69/D69) -> 0 | T69: IPAC_REN|BAC_CCE|B2|ALT | U69: IPAC_REN | V69: IPAC | W69: BAC_CCE | X69: B2 | Y69: ALT | Z69: 3 | BF69: 2027BUD_V1 | BG69: ACT | BH69: 12 | BI69: 2025 | BJ69: IPAC_REN | BK69: IPAC | BL69: BAC_CCE | BM69: B2 | BN69: ALT | BO69: 37 | BP69: 2 | BQ69: 246050 | BR69: 23045.644 | BS69: 44085.599 | BT69: 13850.653 | BU69: 88930.611 | BV69: 6722.1864 | BW69: 34820.295 | BX69: 41542.481 | BY69: 36896.296 | BZ69: 174558.69 | CA69: 211454.99 | CB69: 34595.012 | CC69: 0 | CD69: 69137 | CE69: 132256.93 | CF69: 41552 | CG69: 13575 | CH69: 266792.1 | CI69: 2760232 | CJ69: 580167
B70: Bachelor Commerce, 3e année, alternance | C70: =SUMIFS(_CALC_ALLOC!$G$1:$G$420,_CALC_ALLOC!$AS$1:$AS$420,"2027|"&$P$1,_CALC_ALLOC!$B$1:$B$420,$U70,_CALC_ALLOC!$D$1:$D$420,$W70,_CALC_ALLOC!$E$1:$E$420,$X70,_CALC_ALLOC!$F$1:$F$420,$Y70) -> 0 | D70: =SUMIFS(_CALC_ALLOC!$I$1:$I$420,_CALC_ALLOC!$AS$1:$AS$420,"2027|"&$P$1,_CALC_ALLOC!$B$1:$B$420,$U70,_CALC_ALLOC!$D$1:$D$420,$W70,_CALC_ALLOC!$E$1:$E$420,$X70,_CALC_ALLOC!$F$1:$F$420,$Y70) -> 0 | E70: =SUMIFS(_CALC_ALLOC!$AI$1:$AI$420,_CALC_ALLOC!$AS$1:$AS$420,"2027|"&$P$1,_CALC_ALLOC!$B$1:$B$420,$U70,_CALC_ALLOC!$D$1:$D$420,$W70,_CALC_ALLOC!$E$1:$E$420,$X70,_CALC_ALLOC!$F$1:$F$420,$Y70) -> 0 | F70: =SUMIFS(_CALC_ALLOC!$AJ$1:$AJ$420,_CALC_ALLOC!$AS$1:$AS$420,"2027|"&$P$1,_CALC_ALLOC!$B$1:$B$420,$U70,_CALC_ALLOC!$D$1:$D$420,$W70,_CALC_ALLOC!$E$1:$E$420,$X70,_CALC_ALLOC!$F$1:$F$420,$Y70) -> 0 | G70: =SUMIFS(_CALC_ALLOC!$AK$1:$AK$420,_CALC_ALLOC!$AS$1:$AS$420,"2027|"&$P$1,_CALC_ALLOC!$B$1:$B$420,$U70,_CALC_ALLOC!$D$1:$D$420,$W70,_CALC_ALLOC!$E$1:$E$420,$X70,_CALC_ALLOC!$F$1:$F$420,$Y70) -> 0 | H70: =SUMIFS(_CALC_ALLOC!$AL$1:$AL$420,_CALC_ALLOC!$AS$1:$AS$420,"2027|"&$P$1,_CALC_ALLOC!$B$1:$B$420,$U70,_CALC_ALLOC!$D$1:$D$420,$W70,_CALC_ALLOC!$E$1:$E$420,$X70,_CALC_ALLOC!$F$1:$F$420,$Y70) -> 0 | I70: =SUMIFS(_CALC_ALLOC!$AR$1:$AR$420,_CALC_ALLOC!$AS$1:$AS$420,"2027|"&$P$1,_CALC_ALLOC!$B$1:$B$420,$U70,_CALC_ALLOC!$D$1:$D$420,$W70,_CALC_ALLOC!$E$1:$E$420,$X70,_CALC_ALLOC!$F$1:$F$420,$Y70) -> 0 | J70: =SUMIFS(_CALC_ALLOC!$AM$1:$AM$420,_CALC_ALLOC!$AS$1:$AS$420,"2027|"&$P$1,_CALC_ALLOC!$B$1:$B$420,$U70,_CALC_ALLOC!$D$1:$D$420,$W70,_CALC_ALLOC!$E$1:$E$420,$X70,_CALC_ALLOC!$F$1:$F$420,$Y70) -> 0 | K70: =E70+F70+G70+H70+I70+J70 -> 0 | L70: =SUMIFS(_CALC_ALLOC!$AN$1:$AN$420,_CALC_ALLOC!$AS$1:$AS$420,"2027|"&$P$1,_CALC_ALLOC!$B$1:$B$420,$U70,_CALC_ALLOC!$D$1:$D$420,$W70,_CALC_ALLOC!$E$1:$E$420,$X70,_CALC_ALLOC!$F$1:$F$420,$Y70) -> 0 | M70: =IF(D70=0,0,L70/D70) -> 0 | T70: IPAC_REN|BAC_CCE|B3|ALT | U70: IPAC_REN | V70: IPAC | W70: BAC_CCE | X70: B3 | Y70: ALT | Z70: 3 | BF70: 2027BUD_V1 | BG70: ACT | BH70: 12 | BI70: 2025 | BJ70: IPAC_REN | BK70: IPAC | BL70: BAC_CCE | BM70: B3 | BN70: ALT | BO70: 36 | BP70: 2 | BQ70: 239400 | BR70: 23045.644 | BS70: 44085.599 | BT70: 13476.311 | BU70: 88930.611 | BV70: 6722.1864 | BW70: 34820.295 | BX70: 41542.481 | BY70: 36521.954 | BZ70: 174558.69 | CA70: 211080.65 | CB70: 28319.354 | CC70: 0 | CD70: 69137 | CE70: 132256.93 | CF70: 41552 | CG70: 13575 | CH70: 266792.1 | CI70: 2760232 | CJ70: 580167
B71: Montpellier | C71: =SUMIFS(_CALC_ALLOC!$G$1:$G$420,_CALC_ALLOC!$AS$1:$AS$420,"2027|"&$P$1,_CALC_ALLOC!$B$1:$B$420,$U71) -> 0 | D71: =SUMIFS(_CALC_ALLOC!$I$1:$I$420,_CALC_ALLOC!$AS$1:$AS$420,"2027|"&$P$1,_CALC_ALLOC!$B$1:$B$420,$U71) -> 0 | E71: =SUMIFS(_CALC_ALLOC!$AI$1:$AI$420,_CALC_ALLOC!$AS$1:$AS$420,"2027|"&$P$1,_CALC_ALLOC!$B$1:$B$420,$U71) -> 0 | F71: =SUMIFS(_CALC_ALLOC!$AJ$1:$AJ$420,_CALC_ALLOC!$AS$1:$AS$420,"2027|"&$P$1,_CALC_ALLOC!$B$1:$B$420,$U71) -> 0 | G71: =SUMIFS(_CALC_ALLOC!$AK$1:$AK$420,_CALC_ALLOC!$AS$1:$AS$420,"2027|"&$P$1,_CALC_ALLOC!$B$1:$B$420,$U71) -> 0 | H71: =SUMIFS(_CALC_ALLOC!$AL$1:$AL$420,_CALC_ALLOC!$AS$1:$AS$420,"2027|"&$P$1,_CALC_ALLOC!$B$1:$B$420,$U71) -> 0 | I71: =SUMIFS(_CALC_ALLOC!$AR$1:$AR$420,_CALC_ALLOC!$AS$1:$AS$420,"2027|"&$P$1,_CALC_ALLOC!$B$1:$B$420,$U71) -> 0 | J71: =SUMIFS(_CALC_ALLOC!$AM$1:$AM$420,_CALC_ALLOC!$AS$1:$AS$420,"2027|"&$P$1,_CALC_ALLOC!$B$1:$B$420,$U71) -> 0 | K71: =E71+F71+G71+H71+I71+J71 -> 0 | L71: =SUMIFS(_CALC_ALLOC!$AN$1:$AN$420,_CALC_ALLOC!$AS$1:$AS$420,"2027|"&$P$1,_CALC_ALLOC!$B$1:$B$420,$U71) -> 0 | M71: =IF(D71=0,0,L71/D71) -> 0 | T71: IPAC_MTP | U71: IPAC_MTP | V71: IPAC | Z71: 2 | BF71: 2027BUD_V1 | BG71: ACT | BH71: 12 | BI71: 2025 | BJ71: ISCOM_LIL | BK71: ISCOM | BL71: BAC_COM | BM71: B1 | BN71: INIT | BO71: 47 | BP71: 2 | BQ71: 349680 | BR71: 28807.25 | BS71: 67642.553 | BT71: 29248.572 | BU71: 126191.86 | BV71: 9272.2577 | BW71: 43102.006 | BX71: 52374.264 | BY71: 58055.822 | BZ71: 246208.68 | CA71: 304264.5 | CB71: 45415.497 | CC71: 47 | CD71: 115229 | CE71: 270570.21 | CF71: 86655 | CG71: 22927 | CH71: 630959.32 | CI71: 2760232 | CJ71: 580167
B72: Bachelor Commerce, 1re année, alternance | C72: =SUMIFS(_CALC_ALLOC!$G$1:$G$420,_CALC_ALLOC!$AS$1:$AS$420,"2027|"&$P$1,_CALC_ALLOC!$B$1:$B$420,$U72,_CALC_ALLOC!$D$1:$D$420,$W72,_CALC_ALLOC!$E$1:$E$420,$X72,_CALC_ALLOC!$F$1:$F$420,$Y72) -> 0 | D72: =SUMIFS(_CALC_ALLOC!$I$1:$I$420,_CALC_ALLOC!$AS$1:$AS$420,"2027|"&$P$1,_CALC_ALLOC!$B$1:$B$420,$U72,_CALC_ALLOC!$D$1:$D$420,$W72,_CALC_ALLOC!$E$1:$E$420,$X72,_CALC_ALLOC!$F$1:$F$420,$Y72) -> 0 | E72: =SUMIFS(_CALC_ALLOC!$AI$1:$AI$420,_CALC_ALLOC!$AS$1:$AS$420,"2027|"&$P$1,_CALC_ALLOC!$B$1:$B$420,$U72,_CALC_ALLOC!$D$1:$D$420,$W72,_CALC_ALLOC!$E$1:$E$420,$X72,_CALC_ALLOC!$F$1:$F$420,$Y72) -> 0 | F72: =SUMIFS(_CALC_ALLOC!$AJ$1:$AJ$420,_CALC_ALLOC!$AS$1:$AS$420,"2027|"&$P$1,_CALC_ALLOC!$B$1:$B$420,$U72,_CALC_ALLOC!$D$1:$D$420,$W72,_CALC_ALLOC!$E$1:$E$420,$X72,_CALC_ALLOC!$F$1:$F$420,$Y72) -> 0 | G72: =SUMIFS(_CALC_ALLOC!$AK$1:$AK$420,_CALC_ALLOC!$AS$1:$AS$420,"2027|"&$P$1,_CALC_ALLOC!$B$1:$B$420,$U72,_CALC_ALLOC!$D$1:$D$420,$W72,_CALC_ALLOC!$E$1:$E$420,$X72,_CALC_ALLOC!$F$1:$F$420,$Y72) -> 0 | H72: =SUMIFS(_CALC_ALLOC!$AL$1:$AL$420,_CALC_ALLOC!$AS$1:$AS$420,"2027|"&$P$1,_CALC_ALLOC!$B$1:$B$420,$U72,_CALC_ALLOC!$D$1:$D$420,$W72,_CALC_ALLOC!$E$1:$E$420,$X72,_CALC_ALLOC!$F$1:$F$420,$Y72) -> 0 | I72: =SUMIFS(_CALC_ALLOC!$AR$1:$AR$420,_CALC_ALLOC!$AS$1:$AS$420,"2027|"&$P$1,_CALC_ALLOC!$B$1:$B$420,$U72,_CALC_ALLOC!$D$1:$D$420,$W72,_CALC_ALLOC!$E$1:$E$420,$X72,_CALC_ALLOC!$F$1:$F$420,$Y72) -> 0 | J72: =SUMIFS(_CALC_ALLOC!$AM$1:$AM$420,_CALC_ALLOC!$AS$1:$AS$420,"2027|"&$P$1,_CALC_ALLOC!$B$1:$B$420,$U72,_CALC_ALLOC!$D$1:$D$420,$W72,_CALC_ALLOC!$E$1:$E$420,$X72,_CALC_ALLOC!$F$1:$F$420,$Y72) -> 0 | K72: =E72+F72+G72+H72+I72+J72 -> 0 | L72: =SUMIFS(_CALC_ALLOC!$AN$1:$AN$420,_CALC_ALLOC!$AS$1:$AS$420,"2027|"&$P$1,_CALC_ALLOC!$B$1:$B$420,$U72,_CALC_ALLOC!$D$1:$D$420,$W72,_CALC_ALLOC!$E$1:$E$420,$X72,_CALC_ALLOC!$F$1:$F$420,$Y72) -> 0 | M72: =IF(D72=0,0,L72/D72) -> 0 | T72: IPAC_MTP|BAC_CCE|B1|ALT | U72: IPAC_MTP | V72: IPAC | W72: BAC_CCE | X72: B1 | Y72: ALT | Z72: 3 | BF72: 2027BUD_V1 | BG72: ACT | BH72: 12 | BI72: 2025 | BJ72: ISCOM_LIL | BK72: ISCOM | BL72: BAC_COM | BM72: B2 | BN72: ALT | BO72: 45 | BP72: 2 | BQ72: 308700 | BR72: 23045.8 | BS72: 54114.042 | BT72: 17028.227 | BU72: 126191.86 | BV72: 9272.2577 | BW72: 43102.006 | BX72: 52374.264 | BY72: 40074.027 | BZ72: 232680.17 | CA72: 272754.2 | CB72: 35945.803 | CC72: 0 | CD72: 115229 | CE72: 270570.21 | CF72: 86655 | CG72: 22927 | CH72: 630959.32 | CI72: 2760232 | CJ72: 580167
B73: Bachelor Commerce, 2e année, alternance | C73: =SUMIFS(_CALC_ALLOC!$G$1:$G$420,_CALC_ALLOC!$AS$1:$AS$420,"2027|"&$P$1,_CALC_ALLOC!$B$1:$B$420,$U73,_CALC_ALLOC!$D$1:$D$420,$W73,_CALC_ALLOC!$E$1:$E$420,$X73,_CALC_ALLOC!$F$1:$F$420,$Y73) -> 0 | D73: =SUMIFS(_CALC_ALLOC!$I$1:$I$420,_CALC_ALLOC!$AS$1:$AS$420,"2027|"&$P$1,_CALC_ALLOC!$B$1:$B$420,$U73,_CALC_ALLOC!$D$1:$D$420,$W73,_CALC_ALLOC!$E$1:$E$420,$X73,_CALC_ALLOC!$F$1:$F$420,$Y73) -> 0 | E73: =SUMIFS(_CALC_ALLOC!$AI$1:$AI$420,_CALC_ALLOC!$AS$1:$AS$420,"2027|"&$P$1,_CALC_ALLOC!$B$1:$B$420,$U73,_CALC_ALLOC!$D$1:$D$420,$W73,_CALC_ALLOC!$E$1:$E$420,$X73,_CALC_ALLOC!$F$1:$F$420,$Y73) -> 0 | F73: =SUMIFS(_CALC_ALLOC!$AJ$1:$AJ$420,_CALC_ALLOC!$AS$1:$AS$420,"2027|"&$P$1,_CALC_ALLOC!$B$1:$B$420,$U73,_CALC_ALLOC!$D$1:$D$420,$W73,_CALC_ALLOC!$E$1:$E$420,$X73,_CALC_ALLOC!$F$1:$F$420,$Y73) -> 0 | G73: =SUMIFS(_CALC_ALLOC!$AK$1:$AK$420,_CALC_ALLOC!$AS$1:$AS$420,"2027|"&$P$1,_CALC_ALLOC!$B$1:$B$420,$U73,_CALC_ALLOC!$D$1:$D$420,$W73,_CALC_ALLOC!$E$1:$E$420,$X73,_CALC_ALLOC!$F$1:$F$420,$Y73) -> 0 | H73: =SUMIFS(_CALC_ALLOC!$AL$1:$AL$420,_CALC_ALLOC!$AS$1:$AS$420,"2027|"&$P$1,_CALC_ALLOC!$B$1:$B$420,$U73,_CALC_ALLOC!$D$1:$D$420,$W73,_CALC_ALLOC!$E$1:$E$420,$X73,_CALC_ALLOC!$F$1:$F$420,$Y73) -> 0 | I73: =SUMIFS(_CALC_ALLOC!$AR$1:$AR$420,_CALC_ALLOC!$AS$1:$AS$420,"2027|"&$P$1,_CALC_ALLOC!$B$1:$B$420,$U73,_CALC_ALLOC!$D$1:$D$420,$W73,_CALC_ALLOC!$E$1:$E$420,$X73,_CALC_ALLOC!$F$1:$F$420,$Y73) -> 0 | J73: =SUMIFS(_CALC_ALLOC!$AM$1:$AM$420,_CALC_ALLOC!$AS$1:$AS$420,"2027|"&$P$1,_CALC_ALLOC!$B$1:$B$420,$U73,_CALC_ALLOC!$D$1:$D$420,$W73,_CALC_ALLOC!$E$1:$E$420,$X73,_CALC_ALLOC!$F$1:$F$420,$Y73) -> 0 | K73: =E73+F73+G73+H73+I73+J73 -> 0 | L73: =SUMIFS(_CALC_ALLOC!$AN$1:$AN$420,_CALC_ALLOC!$AS$1:$AS$420,"2027|"&$P$1,_CALC_ALLOC!$B$1:$B$420,$U73,_CALC_ALLOC!$D$1:$D$420,$W73,_CALC_ALLOC!$E$1:$E$420,$X73,_CALC_ALLOC!$F$1:$F$420,$Y73) -> 0 | M73: =IF(D73=0,0,L73/D73) -> 0 | T73: IPAC_MTP|BAC_CCE|B2|ALT | U73: IPAC_MTP | V73: IPAC | W73: BAC_CCE | X73: B2 | Y73: ALT | Z73: 3 | BF73: 2027BUD_V1 | BG73: ACT | BH73: 12 | BI73: 2025 | BJ73: ISCOM_LIL | BK73: ISCOM | BL73: BAC_COM | BM73: B3 | BN73: ALT | BO73: 44 | BP73: 2 | BQ73: 301840 | BR73: 23045.8 | BS73: 54114.042 | BT73: 16649.805 | BU73: 126191.86 | BV73: 9272.2577 | BW73: 43102.006 | BX73: 52374.264 | BY73: 39695.605 | BZ73: 232680.17 | CA73: 272375.78 | CB73: 29464.225 | CC73: 0 | CD73: 115229 | CE73: 270570.21 | CF73: 86655 | CG73: 22927 | CH73: 630959.32 | CI73: 2760232 | CJ73: 580167
B74: Bachelor Commerce, 3e année, alternance | C74: =SUMIFS(_CALC_ALLOC!$G$1:$G$420,_CALC_ALLOC!$AS$1:$AS$420,"2027|"&$P$1,_CALC_ALLOC!$B$1:$B$420,$U74,_CALC_ALLOC!$D$1:$D$420,$W74,_CALC_ALLOC!$E$1:$E$420,$X74,_CALC_ALLOC!$F$1:$F$420,$Y74) -> 0 | D74: =SUMIFS(_CALC_ALLOC!$I$1:$I$420,_CALC_ALLOC!$AS$1:$AS$420,"2027|"&$P$1,_CALC_ALLOC!$B$1:$B$420,$U74,_CALC_ALLOC!$D$1:$D$420,$W74,_CALC_ALLOC!$E$1:$E$420,$X74,_CALC_ALLOC!$F$1:$F$420,$Y74) -> 0 | E74: =SUMIFS(_CALC_ALLOC!$AI$1:$AI$420,_CALC_ALLOC!$AS$1:$AS$420,"2027|"&$P$1,_CALC_ALLOC!$B$1:$B$420,$U74,_CALC_ALLOC!$D$1:$D$420,$W74,_CALC_ALLOC!$E$1:$E$420,$X74,_CALC_ALLOC!$F$1:$F$420,$Y74) -> 0 | F74: =SUMIFS(_CALC_ALLOC!$AJ$1:$AJ$420,_CALC_ALLOC!$AS$1:$AS$420,"2027|"&$P$1,_CALC_ALLOC!$B$1:$B$420,$U74,_CALC_ALLOC!$D$1:$D$420,$W74,_CALC_ALLOC!$E$1:$E$420,$X74,_CALC_ALLOC!$F$1:$F$420,$Y74) -> 0 | G74: =SUMIFS(_CALC_ALLOC!$AK$1:$AK$420,_CALC_ALLOC!$AS$1:$AS$420,"2027|"&$P$1,_CALC_ALLOC!$B$1:$B$420,$U74,_CALC_ALLOC!$D$1:$D$420,$W74,_CALC_ALLOC!$E$1:$E$420,$X74,_CALC_ALLOC!$F$1:$F$420,$Y74) -> 0 | H74: =SUMIFS(_CALC_ALLOC!$AL$1:$AL$420,_CALC_ALLOC!$AS$1:$AS$420,"2027|"&$P$1,_CALC_ALLOC!$B$1:$B$420,$U74,_CALC_ALLOC!$D$1:$D$420,$W74,_CALC_ALLOC!$E$1:$E$420,$X74,_CALC_ALLOC!$F$1:$F$420,$Y74) -> 0 | I74: =SUMIFS(_CALC_ALLOC!$AR$1:$AR$420,_CALC_ALLOC!$AS$1:$AS$420,"2027|"&$P$1,_CALC_ALLOC!$B$1:$B$420,$U74,_CALC_ALLOC!$D$1:$D$420,$W74,_CALC_ALLOC!$E$1:$E$420,$X74,_CALC_ALLOC!$F$1:$F$420,$Y74) -> 0 | J74: =SUMIFS(_CALC_ALLOC!$AM$1:$AM$420,_CALC_ALLOC!$AS$1:$AS$420,"2027|"&$P$1,_CALC_ALLOC!$B$1:$B$420,$U74,_CALC_ALLOC!$D$1:$D$420,$W74,_CALC_ALLOC!$E$1:$E$420,$X74,_CALC_ALLOC!$F$1:$F$420,$Y74) -> 0 | K74: =E74+F74+G74+H74+I74+J74 -> 0 | L74: =SUMIFS(_CALC_ALLOC!$AN$1:$AN$420,_CALC_ALLOC!$AS$1:$AS$420,"2027|"&$P$1,_CALC_ALLOC!$B$1:$B$420,$U74,_CALC_ALLOC!$D$1:$D$420,$W74,_CALC_ALLOC!$E$1:$E$420,$X74,_CALC_ALLOC!$F$1:$F$420,$Y74) -> 0 | M74: =IF(D74=0,0,L74/D74) -> 0 | T74: IPAC_MTP|BAC_CCE|B3|ALT | U74: IPAC_MTP | V74: IPAC | W74: BAC_CCE | X74: B3 | Y74: ALT | Z74: 3 | BF74: 2027BUD_V1 | BG74: ACT | BH74: 12 | BI74: 2025 | BJ74: ISCOM_LIL | BK74: ISCOM | BL74: MAS_COM | BM74: M1 | BN74: ALT | BO74: 47 | BP74: 2 | BQ74: 349680 | BR74: 20165.075 | BS74: 47349.787 | BT74: 29248.572 | BU74: 126191.86 | BV74: 9272.2577 | BW74: 43102.006 | BX74: 52374.264 | BY74: 49413.647 | BZ74: 225915.91 | CA74: 275329.56 | CB74: 74350.438 | CC74: 47 | CD74: 115229 | CE74: 270570.21 | CF74: 86655 | CG74: 22927 | CH74: 630959.32 | CI74: 2760232 | CJ74: 580167
B75: Pigier | C75: =SUMIFS(_CALC_ALLOC!$G$1:$G$420,_CALC_ALLOC!$AS$1:$AS$420,"2027|"&$P$1,_CALC_ALLOC!$C$1:$C$420,$V75) -> 0 | D75: =SUMIFS(_CALC_ALLOC!$I$1:$I$420,_CALC_ALLOC!$AS$1:$AS$420,"2027|"&$P$1,_CALC_ALLOC!$C$1:$C$420,$V75) -> 0 | E75: =SUMIFS(_CALC_ALLOC!$AI$1:$AI$420,_CALC_ALLOC!$AS$1:$AS$420,"2027|"&$P$1,_CALC_ALLOC!$C$1:$C$420,$V75) -> 0 | F75: =SUMIFS(_CALC_ALLOC!$AJ$1:$AJ$420,_CALC_ALLOC!$AS$1:$AS$420,"2027|"&$P$1,_CALC_ALLOC!$C$1:$C$420,$V75) -> 0 | G75: =SUMIFS(_CALC_ALLOC!$AK$1:$AK$420,_CALC_ALLOC!$AS$1:$AS$420,"2027|"&$P$1,_CALC_ALLOC!$C$1:$C$420,$V75) -> 0 | H75: =SUMIFS(_CALC_ALLOC!$AL$1:$AL$420,_CALC_ALLOC!$AS$1:$AS$420,"2027|"&$P$1,_CALC_ALLOC!$C$1:$C$420,$V75) -> 0 | I75: =SUMIFS(_CALC_ALLOC!$AR$1:$AR$420,_CALC_ALLOC!$AS$1:$AS$420,"2027|"&$P$1,_CALC_ALLOC!$C$1:$C$420,$V75) -> 0 | J75: =SUMIFS(_CALC_ALLOC!$AM$1:$AM$420,_CALC_ALLOC!$AS$1:$AS$420,"2027|"&$P$1,_CALC_ALLOC!$C$1:$C$420,$V75) -> 0 | K75: =E75+F75+G75+H75+I75+J75 -> 0 | L75: =SUMIFS(_CALC_ALLOC!$AN$1:$AN$420,_CALC_ALLOC!$AS$1:$AS$420,"2027|"&$P$1,_CALC_ALLOC!$C$1:$C$420,$V75) -> 0 | M75: =IF(D75=0,0,L75/D75) -> 0 | T75: PIGIER | V75: PIGIER | Z75: 1 | BF75: 2027BUD_V1 | BG75: ACT | BH75: 12 | BI75: 2025 | BJ75: ISCOM_LIL | BK75: ISCOM | BL75: MAS_COM | BM75: M2 | BN75: ALT | BO75: 46 | BP75: 2 | BQ75: 338100 | BR75: 20165.075 | BS75: 47349.787 | BT75: 17406.65 | BU75: 126191.86 | BV75: 9272.2577 | BW75: 43102.006 | BX75: 52374.264 | BY75: 37571.725 | BZ75: 225915.91 | CA75: 263487.64 | CB75: 74612.36 | CC75: 0 | CD75: 115229 | CE75: 270570.21 | CF75: 86655 | CG75: 22927 | CH75: 630959.32 | CI75: 2760232 | CJ75: 580167
B76: Lyon | C76: =SUMIFS(_CALC_ALLOC!$G$1:$G$420,_CALC_ALLOC!$AS$1:$AS$420,"2027|"&$P$1,_CALC_ALLOC!$B$1:$B$420,$U76) -> 0 | D76: =SUMIFS(_CALC_ALLOC!$I$1:$I$420,_CALC_ALLOC!$AS$1:$AS$420,"2027|"&$P$1,_CALC_ALLOC!$B$1:$B$420,$U76) -> 0 | E76: =SUMIFS(_CALC_ALLOC!$AI$1:$AI$420,_CALC_ALLOC!$AS$1:$AS$420,"2027|"&$P$1,_CALC_ALLOC!$B$1:$B$420,$U76) -> 0 | F76: =SUMIFS(_CALC_ALLOC!$AJ$1:$AJ$420,_CALC_ALLOC!$AS$1:$AS$420,"2027|"&$P$1,_CALC_ALLOC!$B$1:$B$420,$U76) -> 0 | G76: =SUMIFS(_CALC_ALLOC!$AK$1:$AK$420,_CALC_ALLOC!$AS$1:$AS$420,"2027|"&$P$1,_CALC_ALLOC!$B$1:$B$420,$U76) -> 0 | H76: =SUMIFS(_CALC_ALLOC!$AL$1:$AL$420,_CALC_ALLOC!$AS$1:$AS$420,"2027|"&$P$1,_CALC_ALLOC!$B$1:$B$420,$U76) -> 0 | I76: =SUMIFS(_CALC_ALLOC!$AR$1:$AR$420,_CALC_ALLOC!$AS$1:$AS$420,"2027|"&$P$1,_CALC_ALLOC!$B$1:$B$420,$U76) -> 0 | J76: =SUMIFS(_CALC_ALLOC!$AM$1:$AM$420,_CALC_ALLOC!$AS$1:$AS$420,"2027|"&$P$1,_CALC_ALLOC!$B$1:$B$420,$U76) -> 0 | K76: =E76+F76+G76+H76+I76+J76 -> 0 | L76: =SUMIFS(_CALC_ALLOC!$AN$1:$AN$420,_CALC_ALLOC!$AS$1:$AS$420,"2027|"&$P$1,_CALC_ALLOC!$B$1:$B$420,$U76) -> 0 | M76: =IF(D76=0,0,L76/D76) -> 0 | T76: PIGIER_LYO | U76: PIGIER_LYO | V76: PIGIER | Z76: 2 | BF76: 2027BUD_V1 | BG76: ACT | BH76: 12 | BI76: 2025 | BJ76: ISCOM_PAR | BK76: ISCOM | BL76: BAC_COM | BM76: B1 | BN76: INIT | BO76: 68 | BP76: 3 | BQ76: 577320 | BR76: 43211 | BS76: 116748.28 | BT76: 53231.586 | BU76: 213002.64 | BV76: 13523.733 | BW76: 62864.949 | BX76: 76388.682 | BY76: 96442.586 | BZ76: 406139.6 | CA76: 502582.19 | CB76: 74737.81 | CC76: 68 | CD76: 172844 | CE76: 466993.12 | CF76: 125720 | CG76: 55272 | CH76: 1065013.2 | CI76: 2760232 | CJ76: 580167
B77: Bachelor Ressources humaines, 1re année, alternance | C77: =SUMIFS(_CALC_ALLOC!$G$1:$G$420,_CALC_ALLOC!$AS$1:$AS$420,"2027|"&$P$1,_CALC_ALLOC!$B$1:$B$420,$U77,_CALC_ALLOC!$D$1:$D$420,$W77,_CALC_ALLOC!$E$1:$E$420,$X77,_CALC_ALLOC!$F$1:$F$420,$Y77) -> 0 | D77: =SUMIFS(_CALC_ALLOC!$I$1:$I$420,_CALC_ALLOC!$AS$1:$AS$420,"2027|"&$P$1,_CALC_ALLOC!$B$1:$B$420,$U77,_CALC_ALLOC!$D$1:$D$420,$W77,_CALC_ALLOC!$E$1:$E$420,$X77,_CALC_ALLOC!$F$1:$F$420,$Y77) -> 0 | E77: =SUMIFS(_CALC_ALLOC!$AI$1:$AI$420,_CALC_ALLOC!$AS$1:$AS$420,"2027|"&$P$1,_CALC_ALLOC!$B$1:$B$420,$U77,_CALC_ALLOC!$D$1:$D$420,$W77,_CALC_ALLOC!$E$1:$E$420,$X77,_CALC_ALLOC!$F$1:$F$420,$Y77) -> 0 | F77: =SUMIFS(_CALC_ALLOC!$AJ$1:$AJ$420,_CALC_ALLOC!$AS$1:$AS$420,"2027|"&$P$1,_CALC_ALLOC!$B$1:$B$420,$U77,_CALC_ALLOC!$D$1:$D$420,$W77,_CALC_ALLOC!$E$1:$E$420,$X77,_CALC_ALLOC!$F$1:$F$420,$Y77) -> 0 | G77: =SUMIFS(_CALC_ALLOC!$AK$1:$AK$420,_CALC_ALLOC!$AS$1:$AS$420,"2027|"&$P$1,_CALC_ALLOC!$B$1:$B$420,$U77,_CALC_ALLOC!$D$1:$D$420,$W77,_CALC_ALLOC!$E$1:$E$420,$X77,_CALC_ALLOC!$F$1:$F$420,$Y77) -> 0 | H77: =SUMIFS(_CALC_ALLOC!$AL$1:$AL$420,_CALC_ALLOC!$AS$1:$AS$420,"2027|"&$P$1,_CALC_ALLOC!$B$1:$B$420,$U77,_CALC_ALLOC!$D$1:$D$420,$W77,_CALC_ALLOC!$E$1:$E$420,$X77,_CALC_ALLOC!$F$1:$F$420,$Y77) -> 0 | I77: =SUMIFS(_CALC_ALLOC!$AR$1:$AR$420,_CALC_ALLOC!$AS$1:$AS$420,"2027|"&$P$1,_CALC_ALLOC!$B$1:$B$420,$U77,_CALC_ALLOC!$D$1:$D$420,$W77,_CALC_ALLOC!$E$1:$E$420,$X77,_CALC_ALLOC!$F$1:$F$420,$Y77) -> 0 | J77: =SUMIFS(_CALC_ALLOC!$AM$1:$AM$420,_CALC_ALLOC!$AS$1:$AS$420,"2027|"&$P$1,_CALC_ALLOC!$B$1:$B$420,$U77,_CALC_ALLOC!$D$1:$D$420,$W77,_CALC_ALLOC!$E$1:$E$420,$X77,_CALC_ALLOC!$F$1:$F$420,$Y77) -> 0 | K77: =E77+F77+G77+H77+I77+J77 -> 0 | L77: =SUMIFS(_CALC_ALLOC!$AN$1:$AN$420,_CALC_ALLOC!$AS$1:$AS$420,"2027|"&$P$1,_CALC_ALLOC!$B$1:$B$420,$U77,_CALC_ALLOC!$D$1:$D$420,$W77,_CALC_ALLOC!$E$1:$E$420,$X77,_CALC_ALLOC!$F$1:$F$420,$Y77) -> 0 | M77: =IF(D77=0,0,L77/D77) -> 0 | T77: PIGIER_LYO|BAC_RH|B1|ALT | U77: PIGIER_LYO | V77: PIGIER | W77: BAC_RH | X77: B1 | Y77: ALT | Z77: 3 | BF77: 2027BUD_V1 | BG77: ACT | BH77: 12 | BI77: 2025 | BJ77: ISCOM_PAR | BK77: ISCOM | BL77: BAC_COM | BM77: B2 | BN77: ALT | BO77: 66 | BP77: 3 | BQ77: 517440 | BR77: 34568.8 | BS77: 93398.624 | BT77: 24842.775 | BU77: 213002.64 | BV77: 13523.733 | BW77: 62864.949 | BX77: 76388.682 | BY77: 59411.575 | BZ77: 382789.95 | CA77: 442201.52 | CB77: 75238.478 | CC77: 0 | CD77: 172844 | CE77: 466993.12 | CF77: 125720 | CG77: 55272 | CH77: 1065013.2 | CI77: 2760232 | CJ77: 580167
B78: Bachelor Ressources humaines, 2e année, alternance | C78: =SUMIFS(_CALC_ALLOC!$G$1:$G$420,_CALC_ALLOC!$AS$1:$AS$420,"2027|"&$P$1,_CALC_ALLOC!$B$1:$B$420,$U78,_CALC_ALLOC!$D$1:$D$420,$W78,_CALC_ALLOC!$E$1:$E$420,$X78,_CALC_ALLOC!$F$1:$F$420,$Y78) -> 0 | D78: =SUMIFS(_CALC_ALLOC!$I$1:$I$420,_CALC_ALLOC!$AS$1:$AS$420,"2027|"&$P$1,_CALC_ALLOC!$B$1:$B$420,$U78,_CALC_ALLOC!$D$1:$D$420,$W78,_CALC_ALLOC!$E$1:$E$420,$X78,_CALC_ALLOC!$F$1:$F$420,$Y78) -> 0 | E78: =SUMIFS(_CALC_ALLOC!$AI$1:$AI$420,_CALC_ALLOC!$AS$1:$AS$420,"2027|"&$P$1,_CALC_ALLOC!$B$1:$B$420,$U78,_CALC_ALLOC!$D$1:$D$420,$W78,_CALC_ALLOC!$E$1:$E$420,$X78,_CALC_ALLOC!$F$1:$F$420,$Y78) -> 0 | F78: =SUMIFS(_CALC_ALLOC!$AJ$1:$AJ$420,_CALC_ALLOC!$AS$1:$AS$420,"2027|"&$P$1,_CALC_ALLOC!$B$1:$B$420,$U78,_CALC_ALLOC!$D$1:$D$420,$W78,_CALC_ALLOC!$E$1:$E$420,$X78,_CALC_ALLOC!$F$1:$F$420,$Y78) -> 0 | G78: =SUMIFS(_CALC_ALLOC!$AK$1:$AK$420,_CALC_ALLOC!$AS$1:$AS$420,"2027|"&$P$1,_CALC_ALLOC!$B$1:$B$420,$U78,_CALC_ALLOC!$D$1:$D$420,$W78,_CALC_ALLOC!$E$1:$E$420,$X78,_CALC_ALLOC!$F$1:$F$420,$Y78) -> 0 | H78: =SUMIFS(_CALC_ALLOC!$AL$1:$AL$420,_CALC_ALLOC!$AS$1:$AS$420,"2027|"&$P$1,_CALC_ALLOC!$B$1:$B$420,$U78,_CALC_ALLOC!$D$1:$D$420,$W78,_CALC_ALLOC!$E$1:$E$420,$X78,_CALC_ALLOC!$F$1:$F$420,$Y78) -> 0 | I78: =SUMIFS(_CALC_ALLOC!$AR$1:$AR$420,_CALC_ALLOC!$AS$1:$AS$420,"2027|"&$P$1,_CALC_ALLOC!$B$1:$B$420,$U78,_CALC_ALLOC!$D$1:$D$420,$W78,_CALC_ALLOC!$E$1:$E$420,$X78,_CALC_ALLOC!$F$1:$F$420,$Y78) -> 0 | J78: =SUMIFS(_CALC_ALLOC!$AM$1:$AM$420,_CALC_ALLOC!$AS$1:$AS$420,"2027|"&$P$1,_CALC_ALLOC!$B$1:$B$420,$U78,_CALC_ALLOC!$D$1:$D$420,$W78,_CALC_ALLOC!$E$1:$E$420,$X78,_CALC_ALLOC!$F$1:$F$420,$Y78) -> 0 | K78: =E78+F78+G78+H78+I78+J78 -> 0 | L78: =SUMIFS(_CALC_ALLOC!$AN$1:$AN$420,_CALC_ALLOC!$AS$1:$AS$420,"2027|"&$P$1,_CALC_ALLOC!$B$1:$B$420,$U78,_CALC_ALLOC!$D$1:$D$420,$W78,_CALC_ALLOC!$E$1:$E$420,$X78,_CALC_ALLOC!$F$1:$F$420,$Y78) -> 0 | M78: =IF(D78=0,0,L78/D78) -> 0 | T78: PIGIER_LYO|BAC_RH|B2|ALT | U78: PIGIER_LYO | V78: PIGIER | W78: BAC_RH | X78: B2 | Y78: ALT | Z78: 3 | BF78: 2027BUD_V1 | BG78: ACT | BH78: 12 | BI78: 2025 | BJ78: ISCOM_PAR | BK78: ISCOM | BL78: BAC_COM | BM78: B3 | BN78: ALT | BO78: 65 | BP78: 3 | BQ78: 509600 | BR78: 34568.8 | BS78: 93398.624 | BT78: 24466.369 | BU78: 213002.64 | BV78: 13523.733 | BW78: 62864.949 | BX78: 76388.682 | BY78: 59035.169 | BZ78: 382789.95 | CA78: 441825.12 | CB78: 67774.883 | CC78: 0 | CD78: 172844 | CE78: 466993.12 | CF78: 125720 | CG78: 55272 | CH78: 1065013.2 | CI78: 2760232 | CJ78: 580167
B79: Bachelor Ressources humaines, 3e année, alternance | C79: =SUMIFS(_CALC_ALLOC!$G$1:$G$420,_CALC_ALLOC!$AS$1:$AS$420,"2027|"&$P$1,_CALC_ALLOC!$B$1:$B$420,$U79,_CALC_ALLOC!$D$1:$D$420,$W79,_CALC_ALLOC!$E$1:$E$420,$X79,_CALC_ALLOC!$F$1:$F$420,$Y79) -> 0 | D79: =SUMIFS(_CALC_ALLOC!$I$1:$I$420,_CALC_ALLOC!$AS$1:$AS$420,"2027|"&$P$1,_CALC_ALLOC!$B$1:$B$420,$U79,_CALC_ALLOC!$D$1:$D$420,$W79,_CALC_ALLOC!$E$1:$E$420,$X79,_CALC_ALLOC!$F$1:$F$420,$Y79) -> 0 | E79: =SUMIFS(_CALC_ALLOC!$AI$1:$AI$420,_CALC_ALLOC!$AS$1:$AS$420,"2027|"&$P$1,_CALC_ALLOC!$B$1:$B$420,$U79,_CALC_ALLOC!$D$1:$D$420,$W79,_CALC_ALLOC!$E$1:$E$420,$X79,_CALC_ALLOC!$F$1:$F$420,$Y79) -> 0 | F79: =SUMIFS(_CALC_ALLOC!$AJ$1:$AJ$420,_CALC_ALLOC!$AS$1:$AS$420,"2027|"&$P$1,_CALC_ALLOC!$B$1:$B$420,$U79,_CALC_ALLOC!$D$1:$D$420,$W79,_CALC_ALLOC!$E$1:$E$420,$X79,_CALC_ALLOC!$F$1:$F$420,$Y79) -> 0 | G79: =SUMIFS(_CALC_ALLOC!$AK$1:$AK$420,_CALC_ALLOC!$AS$1:$AS$420,"2027|"&$P$1,_CALC_ALLOC!$B$1:$B$420,$U79,_CALC_ALLOC!$D$1:$D$420,$W79,_CALC_ALLOC!$E$1:$E$420,$X79,_CALC_ALLOC!$F$1:$F$420,$Y79) -> 0 | H79: =SUMIFS(_CALC_ALLOC!$AL$1:$AL$420,_CALC_ALLOC!$AS$1:$AS$420,"2027|"&$P$1,_CALC_ALLOC!$B$1:$B$420,$U79,_CALC_ALLOC!$D$1:$D$420,$W79,_CALC_ALLOC!$E$1:$E$420,$X79,_CALC_ALLOC!$F$1:$F$420,$Y79) -> 0 | I79: =SUMIFS(_CALC_ALLOC!$AR$1:$AR$420,_CALC_ALLOC!$AS$1:$AS$420,"2027|"&$P$1,_CALC_ALLOC!$B$1:$B$420,$U79,_CALC_ALLOC!$D$1:$D$420,$W79,_CALC_ALLOC!$E$1:$E$420,$X79,_CALC_ALLOC!$F$1:$F$420,$Y79) -> 0 | J79: =SUMIFS(_CALC_ALLOC!$AM$1:$AM$420,_CALC_ALLOC!$AS$1:$AS$420,"2027|"&$P$1,_CALC_ALLOC!$B$1:$B$420,$U79,_CALC_ALLOC!$D$1:$D$420,$W79,_CALC_ALLOC!$E$1:$E$420,$X79,_CALC_ALLOC!$F$1:$F$420,$Y79) -> 0 | K79: =E79+F79+G79+H79+I79+J79 -> 0 | L79: =SUMIFS(_CALC_ALLOC!$AN$1:$AN$420,_CALC_ALLOC!$AS$1:$AS$420,"2027|"&$P$1,_CALC_ALLOC!$B$1:$B$420,$U79,_CALC_ALLOC!$D$1:$D$420,$W79,_CALC_ALLOC!$E$1:$E$420,$X79,_CALC_ALLOC!$F$1:$F$420,$Y79) -> 0 | M79: =IF(D79=0,0,L79/D79) -> 0 | T79: PIGIER_LYO|BAC_RH|B3|ALT | U79: PIGIER_LYO | V79: PIGIER | W79: BAC_RH | X79: B3 | Y79: ALT | Z79: 3 | BF79: 2027BUD_V1 | BG79: ACT | BH79: 12 | BI79: 2025 | BJ79: ISCOM_PAR | BK79: ISCOM | BL79: MAS_COM | BM79: M1 | BN79: ALT | BO79: 68 | BP79: 3 | BQ79: 577320 | BR79: 30247.7 | BS79: 81723.796 | BT79: 53231.586 | BU79: 213002.64 | BV79: 13523.733 | BW79: 62864.949 | BX79: 76388.682 | BY79: 83479.286 | BZ79: 371115.12 | CA79: 454594.41 | CB79: 122725.59 | CC79: 68 | CD79: 172844 | CE79: 466993.12 | CF79: 125720 | CG79: 55272 | CH79: 1065013.2 | CI79: 2760232 | CJ79: 580167
B80: BTS Gestion, 1re année, alternance | C80: =SUMIFS(_CALC_ALLOC!$G$1:$G$420,_CALC_ALLOC!$AS$1:$AS$420,"2027|"&$P$1,_CALC_ALLOC!$B$1:$B$420,$U80,_CALC_ALLOC!$D$1:$D$420,$W80,_CALC_ALLOC!$E$1:$E$420,$X80,_CALC_ALLOC!$F$1:$F$420,$Y80) -> 0 | D80: =SUMIFS(_CALC_ALLOC!$I$1:$I$420,_CALC_ALLOC!$AS$1:$AS$420,"2027|"&$P$1,_CALC_ALLOC!$B$1:$B$420,$U80,_CALC_ALLOC!$D$1:$D$420,$W80,_CALC_ALLOC!$E$1:$E$420,$X80,_CALC_ALLOC!$F$1:$F$420,$Y80) -> 0 | E80: =SUMIFS(_CALC_ALLOC!$AI$1:$AI$420,_CALC_ALLOC!$AS$1:$AS$420,"2027|"&$P$1,_CALC_ALLOC!$B$1:$B$420,$U80,_CALC_ALLOC!$D$1:$D$420,$W80,_CALC_ALLOC!$E$1:$E$420,$X80,_CALC_ALLOC!$F$1:$F$420,$Y80) -> 0 | F80: =SUMIFS(_CALC_ALLOC!$AJ$1:$AJ$420,_CALC_ALLOC!$AS$1:$AS$420,"2027|"&$P$1,_CALC_ALLOC!$B$1:$B$420,$U80,_CALC_ALLOC!$D$1:$D$420,$W80,_CALC_ALLOC!$E$1:$E$420,$X80,_CALC_ALLOC!$F$1:$F$420,$Y80) -> 0 | G80: =SUMIFS(_CALC_ALLOC!$AK$1:$AK$420,_CALC_ALLOC!$AS$1:$AS$420,"2027|"&$P$1,_CALC_ALLOC!$B$1:$B$420,$U80,_CALC_ALLOC!$D$1:$D$420,$W80,_CALC_ALLOC!$E$1:$E$420,$X80,_CALC_ALLOC!$F$1:$F$420,$Y80) -> 0 | H80: =SUMIFS(_CALC_ALLOC!$AL$1:$AL$420,_CALC_ALLOC!$AS$1:$AS$420,"2027|"&$P$1,_CALC_ALLOC!$B$1:$B$420,$U80,_CALC_ALLOC!$D$1:$D$420,$W80,_CALC_ALLOC!$E$1:$E$420,$X80,_CALC_ALLOC!$F$1:$F$420,$Y80) -> 0 | I80: =SUMIFS(_CALC_ALLOC!$AR$1:$AR$420,_CALC_ALLOC!$AS$1:$AS$420,"2027|"&$P$1,_CALC_ALLOC!$B$1:$B$420,$U80,_CALC_ALLOC!$D$1:$D$420,$W80,_CALC_ALLOC!$E$1:$E$420,$X80,_CALC_ALLOC!$F$1:$F$420,$Y80) -> 0 | J80: =SUMIFS(_CALC_ALLOC!$AM$1:$AM$420,_CALC_ALLOC!$AS$1:$AS$420,"2027|"&$P$1,_CALC_ALLOC!$B$1:$B$420,$U80,_CALC_ALLOC!$D$1:$D$420,$W80,_CALC_ALLOC!$E$1:$E$420,$X80,_CALC_ALLOC!$F$1:$F$420,$Y80) -> 0 | K80: =E80+F80+G80+H80+I80+J80 -> 0 | L80: =SUMIFS(_CALC_ALLOC!$AN$1:$AN$420,_CALC_ALLOC!$AS$1:$AS$420,"2027|"&$P$1,_CALC_ALLOC!$B$1:$B$420,$U80,_CALC_ALLOC!$D$1:$D$420,$W80,_CALC_ALLOC!$E$1:$E$420,$X80,_CALC_ALLOC!$F$1:$F$420,$Y80) -> 0 | M80: =IF(D80=0,0,L80/D80) -> 0 | T80: PIGIER_LYO|BTS_GES|BTS1|ALT | U80: PIGIER_LYO | V80: PIGIER | W80: BTS_GES | X80: BTS1 | Y80: ALT | Z80: 3 | BF80: 2027BUD_V1 | BG80: ACT | BH80: 12 | BI80: 2025 | BJ80: ISCOM_PAR | BK80: ISCOM | BL80: MAS_COM | BM80: M2 | BN80: ALT | BO80: 67 | BP80: 3 | BQ80: 562800 | BR80: 30247.7 | BS80: 81723.796 | BT80: 25219.181 | BU80: 213002.64 | BV80: 13523.733 | BW80: 62864.949 | BX80: 76388.682 | BY80: 55466.881 | BZ80: 371115.12 | CA80: 426582 | CB80: 136218 | CC80: 0 | CD80: 172844 | CE80: 466993.12 | CF80: 125720 | CG80: 55272 | CH80: 1065013.2 | CI80: 2760232 | CJ80: 580167
B81: BTS Gestion, 2e année, alternance | C81: =SUMIFS(_CALC_ALLOC!$G$1:$G$420,_CALC_ALLOC!$AS$1:$AS$420,"2027|"&$P$1,_CALC_ALLOC!$B$1:$B$420,$U81,_CALC_ALLOC!$D$1:$D$420,$W81,_CALC_ALLOC!$E$1:$E$420,$X81,_CALC_ALLOC!$F$1:$F$420,$Y81) -> 0 | D81: =SUMIFS(_CALC_ALLOC!$I$1:$I$420,_CALC_ALLOC!$AS$1:$AS$420,"2027|"&$P$1,_CALC_ALLOC!$B$1:$B$420,$U81,_CALC_ALLOC!$D$1:$D$420,$W81,_CALC_ALLOC!$E$1:$E$420,$X81,_CALC_ALLOC!$F$1:$F$420,$Y81) -> 0 | E81: =SUMIFS(_CALC_ALLOC!$AI$1:$AI$420,_CALC_ALLOC!$AS$1:$AS$420,"2027|"&$P$1,_CALC_ALLOC!$B$1:$B$420,$U81,_CALC_ALLOC!$D$1:$D$420,$W81,_CALC_ALLOC!$E$1:$E$420,$X81,_CALC_ALLOC!$F$1:$F$420,$Y81) -> 0 | F81: =SUMIFS(_CALC_ALLOC!$AJ$1:$AJ$420,_CALC_ALLOC!$AS$1:$AS$420,"2027|"&$P$1,_CALC_ALLOC!$B$1:$B$420,$U81,_CALC_ALLOC!$D$1:$D$420,$W81,_CALC_ALLOC!$E$1:$E$420,$X81,_CALC_ALLOC!$F$1:$F$420,$Y81) -> 0 | G81: =SUMIFS(_CALC_ALLOC!$AK$1:$AK$420,_CALC_ALLOC!$AS$1:$AS$420,"2027|"&$P$1,_CALC_ALLOC!$B$1:$B$420,$U81,_CALC_ALLOC!$D$1:$D$420,$W81,_CALC_ALLOC!$E$1:$E$420,$X81,_CALC_ALLOC!$F$1:$F$420,$Y81) -> 0 | H81: =SUMIFS(_CALC_ALLOC!$AL$1:$AL$420,_CALC_ALLOC!$AS$1:$AS$420,"2027|"&$P$1,_CALC_ALLOC!$B$1:$B$420,$U81,_CALC_ALLOC!$D$1:$D$420,$W81,_CALC_ALLOC!$E$1:$E$420,$X81,_CALC_ALLOC!$F$1:$F$420,$Y81) -> 0 | I81: =SUMIFS(_CALC_ALLOC!$AR$1:$AR$420,_CALC_ALLOC!$AS$1:$AS$420,"2027|"&$P$1,_CALC_ALLOC!$B$1:$B$420,$U81,_CALC_ALLOC!$D$1:$D$420,$W81,_CALC_ALLOC!$E$1:$E$420,$X81,_CALC_ALLOC!$F$1:$F$420,$Y81) -> 0 | J81: =SUMIFS(_CALC_ALLOC!$AM$1:$AM$420,_CALC_ALLOC!$AS$1:$AS$420,"2027|"&$P$1,_CALC_ALLOC!$B$1:$B$420,$U81,_CALC_ALLOC!$D$1:$D$420,$W81,_CALC_ALLOC!$E$1:$E$420,$X81,_CALC_ALLOC!$F$1:$F$420,$Y81) -> 0 | K81: =E81+F81+G81+H81+I81+J81 -> 0 | L81: =SUMIFS(_CALC_ALLOC!$AN$1:$AN$420,_CALC_ALLOC!$AS$1:$AS$420,"2027|"&$P$1,_CALC_ALLOC!$B$1:$B$420,$U81,_CALC_ALLOC!$D$1:$D$420,$W81,_CALC_ALLOC!$E$1:$E$420,$X81,_CALC_ALLOC!$F$1:$F$420,$Y81) -> 0 | M81: =IF(D81=0,0,L81/D81) -> 0 | T81: PIGIER_LYO|BTS_GES|BTS2|ALT | U81: PIGIER_LYO | V81: PIGIER | W81: BTS_GES | X81: BTS2 | Y81: ALT | Z81: 3 | BF81: 2027BUD_V1 | BG81: ACT | BH81: 12 | BI81: 2025 | BJ81: ISCOM_TLS | BK81: ISCOM | BL81: BAC_COM | BM81: B1 | BN81: INIT | BO81: 44 | BP81: 2 | BQ81: 320760 | BR81: 28807.25 | BS81: 63305.21 | BT81: 26749.387 | BU81: 113871.44 | BV81: 8745.8858 | BW81: 40655.171 | BX81: 49401.057 | BY81: 55556.637 | BZ81: 226577.7 | CA81: 282134.34 | CB81: 38625.66 | CC81: 44 | CD81: 115229 | CE81: 253220.84 | CF81: 82038 | CG81: 20076 | CH81: 569357.18 | CI81: 2760232 | CJ81: 580167
B82: Bordeaux | C82: =SUMIFS(_CALC_ALLOC!$G$1:$G$420,_CALC_ALLOC!$AS$1:$AS$420,"2027|"&$P$1,_CALC_ALLOC!$B$1:$B$420,$U82) -> 0 | D82: =SUMIFS(_CALC_ALLOC!$I$1:$I$420,_CALC_ALLOC!$AS$1:$AS$420,"2027|"&$P$1,_CALC_ALLOC!$B$1:$B$420,$U82) -> 0 | E82: =SUMIFS(_CALC_ALLOC!$AI$1:$AI$420,_CALC_ALLOC!$AS$1:$AS$420,"2027|"&$P$1,_CALC_ALLOC!$B$1:$B$420,$U82) -> 0 | F82: =SUMIFS(_CALC_ALLOC!$AJ$1:$AJ$420,_CALC_ALLOC!$AS$1:$AS$420,"2027|"&$P$1,_CALC_ALLOC!$B$1:$B$420,$U82) -> 0 | G82: =SUMIFS(_CALC_ALLOC!$AK$1:$AK$420,_CALC_ALLOC!$AS$1:$AS$420,"2027|"&$P$1,_CALC_ALLOC!$B$1:$B$420,$U82) -> 0 | H82: =SUMIFS(_CALC_ALLOC!$AL$1:$AL$420,_CALC_ALLOC!$AS$1:$AS$420,"2027|"&$P$1,_CALC_ALLOC!$B$1:$B$420,$U82) -> 0 | I82: =SUMIFS(_CALC_ALLOC!$AR$1:$AR$420,_CALC_ALLOC!$AS$1:$AS$420,"2027|"&$P$1,_CALC_ALLOC!$B$1:$B$420,$U82) -> 0 | J82: =SUMIFS(_CALC_ALLOC!$AM$1:$AM$420,_CALC_ALLOC!$AS$1:$AS$420,"2027|"&$P$1,_CALC_ALLOC!$B$1:$B$420,$U82) -> 0 | K82: =E82+F82+G82+H82+I82+J82 -> 0 | L82: =SUMIFS(_CALC_ALLOC!$AN$1:$AN$420,_CALC_ALLOC!$AS$1:$AS$420,"2027|"&$P$1,_CALC_ALLOC!$B$1:$B$420,$U82) -> 0 | M82: =IF(D82=0,0,L82/D82) -> 0 | T82: PIGIER_BOR | U82: PIGIER_BOR | V82: PIGIER | Z82: 2 | BF82: 2027BUD_V1 | BG82: ACT | BH82: 12 | BI82: 2025 | BJ82: ISCOM_TLS | BK82: ISCOM | BL82: BAC_COM | BM82: B2 | BN82: ALT | BO82: 43 | BP82: 2 | BQ82: 288960 | BR82: 23045.8 | BS82: 50644.168 | BT82: 16331.633 | BU82: 113871.44 | BV82: 8745.8858 | BW82: 40655.171 | BX82: 49401.057 | BY82: 39377.433 | BZ82: 213916.66 | CA82: 253294.09 | CB82: 35665.906 | CC82: 0 | CD82: 115229 | CE82: 253220.84 | CF82: 82038 | CG82: 20076 | CH82: 569357.18 | CI82: 2760232 | CJ82: 580167
B83: Bachelor Ressources humaines, 1re année, alternance | C83: =SUMIFS(_CALC_ALLOC!$G$1:$G$420,_CALC_ALLOC!$AS$1:$AS$420,"2027|"&$P$1,_CALC_ALLOC!$B$1:$B$420,$U83,_CALC_ALLOC!$D$1:$D$420,$W83,_CALC_ALLOC!$E$1:$E$420,$X83,_CALC_ALLOC!$F$1:$F$420,$Y83) -> 0 | D83: =SUMIFS(_CALC_ALLOC!$I$1:$I$420,_CALC_ALLOC!$AS$1:$AS$420,"2027|"&$P$1,_CALC_ALLOC!$B$1:$B$420,$U83,_CALC_ALLOC!$D$1:$D$420,$W83,_CALC_ALLOC!$E$1:$E$420,$X83,_CALC_ALLOC!$F$1:$F$420,$Y83) -> 0 | E83: =SUMIFS(_CALC_ALLOC!$AI$1:$AI$420,_CALC_ALLOC!$AS$1:$AS$420,"2027|"&$P$1,_CALC_ALLOC!$B$1:$B$420,$U83,_CALC_ALLOC!$D$1:$D$420,$W83,_CALC_ALLOC!$E$1:$E$420,$X83,_CALC_ALLOC!$F$1:$F$420,$Y83) -> 0 | F83: =SUMIFS(_CALC_ALLOC!$AJ$1:$AJ$420,_CALC_ALLOC!$AS$1:$AS$420,"2027|"&$P$1,_CALC_ALLOC!$B$1:$B$420,$U83,_CALC_ALLOC!$D$1:$D$420,$W83,_CALC_ALLOC!$E$1:$E$420,$X83,_CALC_ALLOC!$F$1:$F$420,$Y83) -> 0 | G83: =SUMIFS(_CALC_ALLOC!$AK$1:$AK$420,_CALC_ALLOC!$AS$1:$AS$420,"2027|"&$P$1,_CALC_ALLOC!$B$1:$B$420,$U83,_CALC_ALLOC!$D$1:$D$420,$W83,_CALC_ALLOC!$E$1:$E$420,$X83,_CALC_ALLOC!$F$1:$F$420,$Y83) -> 0 | H83: =SUMIFS(_CALC_ALLOC!$AL$1:$AL$420,_CALC_ALLOC!$AS$1:$AS$420,"2027|"&$P$1,_CALC_ALLOC!$B$1:$B$420,$U83,_CALC_ALLOC!$D$1:$D$420,$W83,_CALC_ALLOC!$E$1:$E$420,$X83,_CALC_ALLOC!$F$1:$F$420,$Y83) -> 0 | I83: =SUMIFS(_CALC_ALLOC!$AR$1:$AR$420,_CALC_ALLOC!$AS$1:$AS$420,"2027|"&$P$1,_CALC_ALLOC!$B$1:$B$420,$U83,_CALC_ALLOC!$D$1:$D$420,$W83,_CALC_ALLOC!$E$1:$E$420,$X83,_CALC_ALLOC!$F$1:$F$420,$Y83) -> 0 | J83: =SUMIFS(_CALC_ALLOC!$AM$1:$AM$420,_CALC_ALLOC!$AS$1:$AS$420,"2027|"&$P$1,_CALC_ALLOC!$B$1:$B$420,$U83,_CALC_ALLOC!$D$1:$D$420,$W83,_CALC_ALLOC!$E$1:$E$420,$X83,_CALC_ALLOC!$F$1:$F$420,$Y83) -> 0 | K83: =E83+F83+G83+H83+I83+J83 -> 0 | L83: =SUMIFS(_CALC_ALLOC!$AN$1:$AN$420,_CALC_ALLOC!$AS$1:$AS$420,"2027|"&$P$1,_CALC_ALLOC!$B$1:$B$420,$U83,_CALC_ALLOC!$D$1:$D$420,$W83,_CALC_ALLOC!$E$1:$E$420,$X83,_CALC_ALLOC!$F$1:$F$420,$Y83) -> 0 | M83: =IF(D83=0,0,L83/D83) -> 0 | T83: PIGIER_BOR|BAC_RH|B1|ALT | U83: PIGIER_BOR | V83: PIGIER | W83: BAC_RH | X83: B1 | Y83: ALT | Z83: 3 | BF83: 2027BUD_V1 | BG83: ACT | BH83: 12 | BI83: 2025 | BJ83: ISCOM_TLS | BK83: ISCOM | BL83: BAC_COM | BM83: B3 | BN83: ALT | BO83: 42 | BP83: 2 | BQ83: 282240 | BR83: 23045.8 | BS83: 50644.168 | BT83: 15951.797 | BU83: 113871.44 | BV83: 8745.8858 | BW83: 40655.171 | BX83: 49401.057 | BY83: 38997.597 | BZ83: 213916.66 | CA83: 252914.26 | CB83: 29325.742 | CC83: 0 | CD83: 115229 | CE83: 253220.84 | CF83: 82038 | CG83: 20076 | CH83: 569357.18 | CI83: 2760232 | CJ83: 580167
B84: Bachelor Ressources humaines, 2e année, alternance | C84: =SUMIFS(_CALC_ALLOC!$G$1:$G$420,_CALC_ALLOC!$AS$1:$AS$420,"2027|"&$P$1,_CALC_ALLOC!$B$1:$B$420,$U84,_CALC_ALLOC!$D$1:$D$420,$W84,_CALC_ALLOC!$E$1:$E$420,$X84,_CALC_ALLOC!$F$1:$F$420,$Y84) -> 0 | D84: =SUMIFS(_CALC_ALLOC!$I$1:$I$420,_CALC_ALLOC!$AS$1:$AS$420,"2027|"&$P$1,_CALC_ALLOC!$B$1:$B$420,$U84,_CALC_ALLOC!$D$1:$D$420,$W84,_CALC_ALLOC!$E$1:$E$420,$X84,_CALC_ALLOC!$F$1:$F$420,$Y84) -> 0 | E84: =SUMIFS(_CALC_ALLOC!$AI$1:$AI$420,_CALC_ALLOC!$AS$1:$AS$420,"2027|"&$P$1,_CALC_ALLOC!$B$1:$B$420,$U84,_CALC_ALLOC!$D$1:$D$420,$W84,_CALC_ALLOC!$E$1:$E$420,$X84,_CALC_ALLOC!$F$1:$F$420,$Y84) -> 0 | F84: =SUMIFS(_CALC_ALLOC!$AJ$1:$AJ$420,_CALC_ALLOC!$AS$1:$AS$420,"2027|"&$P$1,_CALC_ALLOC!$B$1:$B$420,$U84,_CALC_ALLOC!$D$1:$D$420,$W84,_CALC_ALLOC!$E$1:$E$420,$X84,_CALC_ALLOC!$F$1:$F$420,$Y84) -> 0 | G84: =SUMIFS(_CALC_ALLOC!$AK$1:$AK$420,_CALC_ALLOC!$AS$1:$AS$420,"2027|"&$P$1,_CALC_ALLOC!$B$1:$B$420,$U84,_CALC_ALLOC!$D$1:$D$420,$W84,_CALC_ALLOC!$E$1:$E$420,$X84,_CALC_ALLOC!$F$1:$F$420,$Y84) -> 0 | H84: =SUMIFS(_CALC_ALLOC!$AL$1:$AL$420,_CALC_ALLOC!$AS$1:$AS$420,"2027|"&$P$1,_CALC_ALLOC!$B$1:$B$420,$U84,_CALC_ALLOC!$D$1:$D$420,$W84,_CALC_ALLOC!$E$1:$E$420,$X84,_CALC_ALLOC!$F$1:$F$420,$Y84) -> 0 | I84: =SUMIFS(_CALC_ALLOC!$AR$1:$AR$420,_CALC_ALLOC!$AS$1:$AS$420,"2027|"&$P$1,_CALC_ALLOC!$B$1:$B$420,$U84,_CALC_ALLOC!$D$1:$D$420,$W84,_CALC_ALLOC!$E$1:$E$420,$X84,_CALC_ALLOC!$F$1:$F$420,$Y84) -> 0 | J84: =SUMIFS(_CALC_ALLOC!$AM$1:$AM$420,_CALC_ALLOC!$AS$1:$AS$420,"2027|"&$P$1,_CALC_ALLOC!$B$1:$B$420,$U84,_CALC_ALLOC!$D$1:$D$420,$W84,_CALC_ALLOC!$E$1:$E$420,$X84,_CALC_ALLOC!$F$1:$F$420,$Y84) -> 0 | K84: =E84+F84+G84+H84+I84+J84 -> 0 | L84: =SUMIFS(_CALC_ALLOC!$AN$1:$AN$420,_CALC_ALLOC!$AS$1:$AS$420,"2027|"&$P$1,_CALC_ALLOC!$B$1:$B$420,$U84,_CALC_ALLOC!$D$1:$D$420,$W84,_CALC_ALLOC!$E$1:$E$420,$X84,_CALC_ALLOC!$F$1:$F$420,$Y84) -> 0 | M84: =IF(D84=0,0,L84/D84) -> 0 | T84: PIGIER_BOR|BAC_RH|B2|ALT | U84: PIGIER_BOR | V84: PIGIER | W84: BAC_RH | X84: B2 | Y84: ALT | Z84: 3 | BF84: 2027BUD_V1 | BG84: ACT | BH84: 12 | BI84: 2025 | BJ84: ISCOM_TLS | BK84: ISCOM | BL84: MAS_COM | BM84: M1 | BN84: ALT | BO84: 44 | BP84: 2 | BQ84: 320760 | BR84: 20165.075 | BS84: 44313.647 | BT84: 26749.387 | BU84: 113871.44 | BV84: 8745.8858 | BW84: 40655.171 | BX84: 49401.057 | BY84: 46914.462 | BZ84: 207586.14 | CA84: 254500.6 | CB84: 66259.398 | CC84: 44 | CD84: 115229 | CE84: 253220.84 | CF84: 82038 | CG84: 20076 | CH84: 569357.18 | CI84: 2760232 | CJ84: 580167
B85: Bachelor Ressources humaines, 3e année, alternance | C85: =SUMIFS(_CALC_ALLOC!$G$1:$G$420,_CALC_ALLOC!$AS$1:$AS$420,"2027|"&$P$1,_CALC_ALLOC!$B$1:$B$420,$U85,_CALC_ALLOC!$D$1:$D$420,$W85,_CALC_ALLOC!$E$1:$E$420,$X85,_CALC_ALLOC!$F$1:$F$420,$Y85) -> 0 | D85: =SUMIFS(_CALC_ALLOC!$I$1:$I$420,_CALC_ALLOC!$AS$1:$AS$420,"2027|"&$P$1,_CALC_ALLOC!$B$1:$B$420,$U85,_CALC_ALLOC!$D$1:$D$420,$W85,_CALC_ALLOC!$E$1:$E$420,$X85,_CALC_ALLOC!$F$1:$F$420,$Y85) -> 0 | E85: =SUMIFS(_CALC_ALLOC!$AI$1:$AI$420,_CALC_ALLOC!$AS$1:$AS$420,"2027|"&$P$1,_CALC_ALLOC!$B$1:$B$420,$U85,_CALC_ALLOC!$D$1:$D$420,$W85,_CALC_ALLOC!$E$1:$E$420,$X85,_CALC_ALLOC!$F$1:$F$420,$Y85) -> 0 | F85: =SUMIFS(_CALC_ALLOC!$AJ$1:$AJ$420,_CALC_ALLOC!$AS$1:$AS$420,"2027|"&$P$1,_CALC_ALLOC!$B$1:$B$420,$U85,_CALC_ALLOC!$D$1:$D$420,$W85,_CALC_ALLOC!$E$1:$E$420,$X85,_CALC_ALLOC!$F$1:$F$420,$Y85) -> 0 | G85: =SUMIFS(_CALC_ALLOC!$AK$1:$AK$420,_CALC_ALLOC!$AS$1:$AS$420,"2027|"&$P$1,_CALC_ALLOC!$B$1:$B$420,$U85,_CALC_ALLOC!$D$1:$D$420,$W85,_CALC_ALLOC!$E$1:$E$420,$X85,_CALC_ALLOC!$F$1:$F$420,$Y85) -> 0 | H85: =SUMIFS(_CALC_ALLOC!$AL$1:$AL$420,_CALC_ALLOC!$AS$1:$AS$420,"2027|"&$P$1,_CALC_ALLOC!$B$1:$B$420,$U85,_CALC_ALLOC!$D$1:$D$420,$W85,_CALC_ALLOC!$E$1:$E$420,$X85,_CALC_ALLOC!$F$1:$F$420,$Y85) -> 0 | I85: =SUMIFS(_CALC_ALLOC!$AR$1:$AR$420,_CALC_ALLOC!$AS$1:$AS$420,"2027|"&$P$1,_CALC_ALLOC!$B$1:$B$420,$U85,_CALC_ALLOC!$D$1:$D$420,$W85,_CALC_ALLOC!$E$1:$E$420,$X85,_CALC_ALLOC!$F$1:$F$420,$Y85) -> 0 | J85: =SUMIFS(_CALC_ALLOC!$AM$1:$AM$420,_CALC_ALLOC!$AS$1:$AS$420,"2027|"&$P$1,_CALC_ALLOC!$B$1:$B$420,$U85,_CALC_ALLOC!$D$1:$D$420,$W85,_CALC_ALLOC!$E$1:$E$420,$X85,_CALC_ALLOC!$F$1:$F$420,$Y85) -> 0 | K85: =E85+F85+G85+H85+I85+J85 -> 0 | L85: =SUMIFS(_CALC_ALLOC!$AN$1:$AN$420,_CALC_ALLOC!$AS$1:$AS$420,"2027|"&$P$1,_CALC_ALLOC!$B$1:$B$420,$U85,_CALC_ALLOC!$D$1:$D$420,$W85,_CALC_ALLOC!$E$1:$E$420,$X85,_CALC_ALLOC!$F$1:$F$420,$Y85) -> 0 | M85: =IF(D85=0,0,L85/D85) -> 0 | T85: PIGIER_BOR|BAC_RH|B3|ALT | U85: PIGIER_BOR | V85: PIGIER | W85: BAC_RH | X85: B3 | Y85: ALT | Z85: 3 | BF85: 2027BUD_V1 | BG85: ACT | BH85: 12 | BI85: 2025 | BJ85: ISCOM_TLS | BK85: ISCOM | BL85: MAS_COM | BM85: M2 | BN85: ALT | BO85: 43 | BP85: 2 | BQ85: 309600 | BR85: 20165.075 | BS85: 44313.647 | BT85: 16331.633 | BU85: 113871.44 | BV85: 8745.8858 | BW85: 40655.171 | BX85: 49401.057 | BY85: 36496.708 | BZ85: 207586.14 | CA85: 244082.85 | CB85: 65517.152 | CC85: 0 | CD85: 115229 | CE85: 253220.84 | CF85: 82038 | CG85: 20076 | CH85: 569357.18 | CI85: 2760232 | CJ85: 580167
B86: BTS Gestion, 1re année, alternance | C86: =SUMIFS(_CALC_ALLOC!$G$1:$G$420,_CALC_ALLOC!$AS$1:$AS$420,"2027|"&$P$1,_CALC_ALLOC!$B$1:$B$420,$U86,_CALC_ALLOC!$D$1:$D$420,$W86,_CALC_ALLOC!$E$1:$E$420,$X86,_CALC_ALLOC!$F$1:$F$420,$Y86) -> 0 | D86: =SUMIFS(_CALC_ALLOC!$I$1:$I$420,_CALC_ALLOC!$AS$1:$AS$420,"2027|"&$P$1,_CALC_ALLOC!$B$1:$B$420,$U86,_CALC_ALLOC!$D$1:$D$420,$W86,_CALC_ALLOC!$E$1:$E$420,$X86,_CALC_ALLOC!$F$1:$F$420,$Y86) -> 0 | E86: =SUMIFS(_CALC_ALLOC!$AI$1:$AI$420,_CALC_ALLOC!$AS$1:$AS$420,"2027|"&$P$1,_CALC_ALLOC!$B$1:$B$420,$U86,_CALC_ALLOC!$D$1:$D$420,$W86,_CALC_ALLOC!$E$1:$E$420,$X86,_CALC_ALLOC!$F$1:$F$420,$Y86) -> 0 | F86: =SUMIFS(_CALC_ALLOC!$AJ$1:$AJ$420,_CALC_ALLOC!$AS$1:$AS$420,"2027|"&$P$1,_CALC_ALLOC!$B$1:$B$420,$U86,_CALC_ALLOC!$D$1:$D$420,$W86,_CALC_ALLOC!$E$1:$E$420,$X86,_CALC_ALLOC!$F$1:$F$420,$Y86) -> 0 | G86: =SUMIFS(_CALC_ALLOC!$AK$1:$AK$420,_CALC_ALLOC!$AS$1:$AS$420,"2027|"&$P$1,_CALC_ALLOC!$B$1:$B$420,$U86,_CALC_ALLOC!$D$1:$D$420,$W86,_CALC_ALLOC!$E$1:$E$420,$X86,_CALC_ALLOC!$F$1:$F$420,$Y86) -> 0 | H86: =SUMIFS(_CALC_ALLOC!$AL$1:$AL$420,_CALC_ALLOC!$AS$1:$AS$420,"2027|"&$P$1,_CALC_ALLOC!$B$1:$B$420,$U86,_CALC_ALLOC!$D$1:$D$420,$W86,_CALC_ALLOC!$E$1:$E$420,$X86,_CALC_ALLOC!$F$1:$F$420,$Y86) -> 0 | I86: =SUMIFS(_CALC_ALLOC!$AR$1:$AR$420,_CALC_ALLOC!$AS$1:$AS$420,"2027|"&$P$1,_CALC_ALLOC!$B$1:$B$420,$U86,_CALC_ALLOC!$D$1:$D$420,$W86,_CALC_ALLOC!$E$1:$E$420,$X86,_CALC_ALLOC!$F$1:$F$420,$Y86) -> 0 | J86: =SUMIFS(_CALC_ALLOC!$AM$1:$AM$420,_CALC_ALLOC!$AS$1:$AS$420,"2027|"&$P$1,_CALC_ALLOC!$B$1:$B$420,$U86,_CALC_ALLOC!$D$1:$D$420,$W86,_CALC_ALLOC!$E$1:$E$420,$X86,_CALC_ALLOC!$F$1:$F$420,$Y86) -> 0 | K86: =E86+F86+G86+H86+I86+J86 -> 0 | L86: =SUMIFS(_CALC_ALLOC!$AN$1:$AN$420,_CALC_ALLOC!$AS$1:$AS$420,"2027|"&$P$1,_CALC_ALLOC!$B$1:$B$420,$U86,_CALC_ALLOC!$D$1:$D$420,$W86,_CALC_ALLOC!$E$1:$E$420,$X86,_CALC_ALLOC!$F$1:$F$420,$Y86) -> 0 | M86: =IF(D86=0,0,L86/D86) -> 0 | T86: PIGIER_BOR|BTS_GES|BTS1|ALT | U86: PIGIER_BOR | V86: PIGIER | W86: BTS_GES | X86: BTS1 | Y86: ALT | Z86: 3 | BF86: 2027BUD_V1 | BG86: ACT | BH86: 12 | BI86: 2025 | BJ86: MBWAY_BOR | BK86: MBWAY | BL86: BAC_MGT | BM86: B1 | BN86: INIT | BO86: 48 | BP86: 2 | BQ86: 353520 | BR86: 28807.25 | BS86: 66982.25 | BT86: 29467.969 | BU86: 126681.16 | BV86: 9559.8896 | BW86: 44043.135 | BX86: 53603.024 | BY86: 58275.219 | BZ86: 247266.43 | CA86: 305541.65 | CB86: 47978.351 | CC86: 48 | CD86: 115229 | CE86: 267929 | CF86: 88430 | CG86: 22657 | CH86: 633405.78 | CI86: 2760232 | CJ86: 580167
B87: BTS Gestion, 2e année, alternance | C87: =SUMIFS(_CALC_ALLOC!$G$1:$G$420,_CALC_ALLOC!$AS$1:$AS$420,"2027|"&$P$1,_CALC_ALLOC!$B$1:$B$420,$U87,_CALC_ALLOC!$D$1:$D$420,$W87,_CALC_ALLOC!$E$1:$E$420,$X87,_CALC_ALLOC!$F$1:$F$420,$Y87) -> 0 | D87: =SUMIFS(_CALC_ALLOC!$I$1:$I$420,_CALC_ALLOC!$AS$1:$AS$420,"2027|"&$P$1,_CALC_ALLOC!$B$1:$B$420,$U87,_CALC_ALLOC!$D$1:$D$420,$W87,_CALC_ALLOC!$E$1:$E$420,$X87,_CALC_ALLOC!$F$1:$F$420,$Y87) -> 0 | E87: =SUMIFS(_CALC_ALLOC!$AI$1:$AI$420,_CALC_ALLOC!$AS$1:$AS$420,"2027|"&$P$1,_CALC_ALLOC!$B$1:$B$420,$U87,_CALC_ALLOC!$D$1:$D$420,$W87,_CALC_ALLOC!$E$1:$E$420,$X87,_CALC_ALLOC!$F$1:$F$420,$Y87) -> 0 | F87: =SUMIFS(_CALC_ALLOC!$AJ$1:$AJ$420,_CALC_ALLOC!$AS$1:$AS$420,"2027|"&$P$1,_CALC_ALLOC!$B$1:$B$420,$U87,_CALC_ALLOC!$D$1:$D$420,$W87,_CALC_ALLOC!$E$1:$E$420,$X87,_CALC_ALLOC!$F$1:$F$420,$Y87) -> 0 | G87: =SUMIFS(_CALC_ALLOC!$AK$1:$AK$420,_CALC_ALLOC!$AS$1:$AS$420,"2027|"&$P$1,_CALC_ALLOC!$B$1:$B$420,$U87,_CALC_ALLOC!$D$1:$D$420,$W87,_CALC_ALLOC!$E$1:$E$420,$X87,_CALC_ALLOC!$F$1:$F$420,$Y87) -> 0 | H87: =SUMIFS(_CALC_ALLOC!$AL$1:$AL$420,_CALC_ALLOC!$AS$1:$AS$420,"2027|"&$P$1,_CALC_ALLOC!$B$1:$B$420,$U87,_CALC_ALLOC!$D$1:$D$420,$W87,_CALC_ALLOC!$E$1:$E$420,$X87,_CALC_ALLOC!$F$1:$F$420,$Y87) -> 0 | I87: =SUMIFS(_CALC_ALLOC!$AR$1:$AR$420,_CALC_ALLOC!$AS$1:$AS$420,"2027|"&$P$1,_CALC_ALLOC!$B$1:$B$420,$U87,_CALC_ALLOC!$D$1:$D$420,$W87,_CALC_ALLOC!$E$1:$E$420,$X87,_CALC_ALLOC!$F$1:$F$420,$Y87) -> 0 | J87: =SUMIFS(_CALC_ALLOC!$AM$1:$AM$420,_CALC_ALLOC!$AS$1:$AS$420,"2027|"&$P$1,_CALC_ALLOC!$B$1:$B$420,$U87,_CALC_ALLOC!$D$1:$D$420,$W87,_CALC_ALLOC!$E$1:$E$420,$X87,_CALC_ALLOC!$F$1:$F$420,$Y87) -> 0 | K87: =E87+F87+G87+H87+I87+J87 -> 0 | L87: =SUMIFS(_CALC_ALLOC!$AN$1:$AN$420,_CALC_ALLOC!$AS$1:$AS$420,"2027|"&$P$1,_CALC_ALLOC!$B$1:$B$420,$U87,_CALC_ALLOC!$D$1:$D$420,$W87,_CALC_ALLOC!$E$1:$E$420,$X87,_CALC_ALLOC!$F$1:$F$420,$Y87) -> 0 | M87: =IF(D87=0,0,L87/D87) -> 0 | T87: PIGIER_BOR|BTS_GES|BTS2|ALT | U87: PIGIER_BOR | V87: PIGIER | W87: BTS_GES | X87: BTS2 | Y87: ALT | Z87: 3 | BF87: 2027BUD_V1 | BG87: ACT | BH87: 12 | BI87: 2025 | BJ87: MBWAY_BOR | BK87: MBWAY | BL87: BAC_MGT | BM87: B2 | BN87: ALT | BO87: 46 | BP87: 2 | BQ87: 312340 | BR87: 23045.8 | BS87: 53585.8 | BT87: 17383.658 | BU87: 126681.16 | BV87: 9559.8896 | BW87: 44043.135 | BX87: 53603.024 | BY87: 40429.458 | BZ87: 233869.98 | CA87: 274299.44 | CB87: 38040.562 | CC87: 0 | CD87: 115229 | CE87: 267929 | CF87: 88430 | CG87: 22657 | CH87: 633405.78 | CI87: 2760232 | CJ87: 580167
B88: Tunon | C88: =SUMIFS(_CALC_ALLOC!$G$1:$G$420,_CALC_ALLOC!$AS$1:$AS$420,"2027|"&$P$1,_CALC_ALLOC!$C$1:$C$420,$V88) -> 0 | D88: =SUMIFS(_CALC_ALLOC!$I$1:$I$420,_CALC_ALLOC!$AS$1:$AS$420,"2027|"&$P$1,_CALC_ALLOC!$C$1:$C$420,$V88) -> 0 | E88: =SUMIFS(_CALC_ALLOC!$AI$1:$AI$420,_CALC_ALLOC!$AS$1:$AS$420,"2027|"&$P$1,_CALC_ALLOC!$C$1:$C$420,$V88) -> 0 | F88: =SUMIFS(_CALC_ALLOC!$AJ$1:$AJ$420,_CALC_ALLOC!$AS$1:$AS$420,"2027|"&$P$1,_CALC_ALLOC!$C$1:$C$420,$V88) -> 0 | G88: =SUMIFS(_CALC_ALLOC!$AK$1:$AK$420,_CALC_ALLOC!$AS$1:$AS$420,"2027|"&$P$1,_CALC_ALLOC!$C$1:$C$420,$V88) -> 0 | H88: =SUMIFS(_CALC_ALLOC!$AL$1:$AL$420,_CALC_ALLOC!$AS$1:$AS$420,"2027|"&$P$1,_CALC_ALLOC!$C$1:$C$420,$V88) -> 0 | I88: =SUMIFS(_CALC_ALLOC!$AR$1:$AR$420,_CALC_ALLOC!$AS$1:$AS$420,"2027|"&$P$1,_CALC_ALLOC!$C$1:$C$420,$V88) -> 0 | J88: =SUMIFS(_CALC_ALLOC!$AM$1:$AM$420,_CALC_ALLOC!$AS$1:$AS$420,"2027|"&$P$1,_CALC_ALLOC!$C$1:$C$420,$V88) -> 0 | K88: =E88+F88+G88+H88+I88+J88 -> 0 | L88: =SUMIFS(_CALC_ALLOC!$AN$1:$AN$420,_CALC_ALLOC!$AS$1:$AS$420,"2027|"&$P$1,_CALC_ALLOC!$C$1:$C$420,$V88) -> 0 | M88: =IF(D88=0,0,L88/D88) -> 0 | T88: TUNON | V88: TUNON | Z88: 1 | BF88: 2027BUD_V1 | BG88: ACT | BH88: 12 | BI88: 2025 | BJ88: MBWAY_BOR | BK88: MBWAY | BL88: BAC_MGT | BM88: B3 | BN88: ALT | BO88: 45 | BP88: 2 | BQ88: 305550 | BR88: 23045.8 | BS88: 53585.8 | BT88: 17005.708 | BU88: 126681.16 | BV88: 9559.8896 | BW88: 44043.135 | BX88: 53603.024 | BY88: 40051.508 | BZ88: 233869.98 | CA88: 273921.49 | CB88: 31628.512 | CC88: 0 | CD88: 115229 | CE88: 267929 | CF88: 88430 | CG88: 22657 | CH88: 633405.78 | CI88: 2760232 | CJ88: 580167
B89: Paris | C89: =SUMIFS(_CALC_ALLOC!$G$1:$G$420,_CALC_ALLOC!$AS$1:$AS$420,"2027|"&$P$1,_CALC_ALLOC!$B$1:$B$420,$U89) -> 0 | D89: =SUMIFS(_CALC_ALLOC!$I$1:$I$420,_CALC_ALLOC!$AS$1:$AS$420,"2027|"&$P$1,_CALC_ALLOC!$B$1:$B$420,$U89) -> 0 | E89: =SUMIFS(_CALC_ALLOC!$AI$1:$AI$420,_CALC_ALLOC!$AS$1:$AS$420,"2027|"&$P$1,_CALC_ALLOC!$B$1:$B$420,$U89) -> 0 | F89: =SUMIFS(_CALC_ALLOC!$AJ$1:$AJ$420,_CALC_ALLOC!$AS$1:$AS$420,"2027|"&$P$1,_CALC_ALLOC!$B$1:$B$420,$U89) -> 0 | G89: =SUMIFS(_CALC_ALLOC!$AK$1:$AK$420,_CALC_ALLOC!$AS$1:$AS$420,"2027|"&$P$1,_CALC_ALLOC!$B$1:$B$420,$U89) -> 0 | H89: =SUMIFS(_CALC_ALLOC!$AL$1:$AL$420,_CALC_ALLOC!$AS$1:$AS$420,"2027|"&$P$1,_CALC_ALLOC!$B$1:$B$420,$U89) -> 0 | I89: =SUMIFS(_CALC_ALLOC!$AR$1:$AR$420,_CALC_ALLOC!$AS$1:$AS$420,"2027|"&$P$1,_CALC_ALLOC!$B$1:$B$420,$U89) -> 0 | J89: =SUMIFS(_CALC_ALLOC!$AM$1:$AM$420,_CALC_ALLOC!$AS$1:$AS$420,"2027|"&$P$1,_CALC_ALLOC!$B$1:$B$420,$U89) -> 0 | K89: =E89+F89+G89+H89+I89+J89 -> 0 | L89: =SUMIFS(_CALC_ALLOC!$AN$1:$AN$420,_CALC_ALLOC!$AS$1:$AS$420,"2027|"&$P$1,_CALC_ALLOC!$B$1:$B$420,$U89) -> 0 | M89: =IF(D89=0,0,L89/D89) -> 0 | T89: TUNON_PAR | U89: TUNON_PAR | V89: TUNON | Z89: 2 | BF89: 2027BUD_V1 | BG89: ACT | BH89: 12 | BI89: 2025 | BJ89: MBWAY_BOR | BK89: MBWAY | BL89: MAS_MGT | BM89: M1 | BN89: ALT | BO89: 48 | BP89: 2 | BQ89: 353520 | BR89: 20165.075 | BS89: 46887.575 | BT89: 29467.969 | BU89: 126681.16 | BV89: 9559.8896 | BW89: 44043.135 | BX89: 53603.024 | BY89: 49633.044 | BZ89: 227171.76 | CA89: 276804.8 | CB89: 76715.201 | CC89: 48 | CD89: 115229 | CE89: 267929 | CF89: 88430 | CG89: 22657 | CH89: 633405.78 | CI89: 2760232 | CJ89: 580167
B90: Bachelor Tourisme, 1re année, alternance | C90: =SUMIFS(_CALC_ALLOC!$G$1:$G$420,_CALC_ALLOC!$AS$1:$AS$420,"2027|"&$P$1,_CALC_ALLOC!$B$1:$B$420,$U90,_CALC_ALLOC!$D$1:$D$420,$W90,_CALC_ALLOC!$E$1:$E$420,$X90,_CALC_ALLOC!$F$1:$F$420,$Y90) -> 0 | D90: =SUMIFS(_CALC_ALLOC!$I$1:$I$420,_CALC_ALLOC!$AS$1:$AS$420,"2027|"&$P$1,_CALC_ALLOC!$B$1:$B$420,$U90,_CALC_ALLOC!$D$1:$D$420,$W90,_CALC_ALLOC!$E$1:$E$420,$X90,_CALC_ALLOC!$F$1:$F$420,$Y90) -> 0 | E90: =SUMIFS(_CALC_ALLOC!$AI$1:$AI$420,_CALC_ALLOC!$AS$1:$AS$420,"2027|"&$P$1,_CALC_ALLOC!$B$1:$B$420,$U90,_CALC_ALLOC!$D$1:$D$420,$W90,_CALC_ALLOC!$E$1:$E$420,$X90,_CALC_ALLOC!$F$1:$F$420,$Y90) -> 0 | F90: =SUMIFS(_CALC_ALLOC!$AJ$1:$AJ$420,_CALC_ALLOC!$AS$1:$AS$420,"2027|"&$P$1,_CALC_ALLOC!$B$1:$B$420,$U90,_CALC_ALLOC!$D$1:$D$420,$W90,_CALC_ALLOC!$E$1:$E$420,$X90,_CALC_ALLOC!$F$1:$F$420,$Y90) -> 0 | G90: =SUMIFS(_CALC_ALLOC!$AK$1:$AK$420,_CALC_ALLOC!$AS$1:$AS$420,"2027|"&$P$1,_CALC_ALLOC!$B$1:$B$420,$U90,_CALC_ALLOC!$D$1:$D$420,$W90,_CALC_ALLOC!$E$1:$E$420,$X90,_CALC_ALLOC!$F$1:$F$420,$Y90) -> 0 | H90: =SUMIFS(_CALC_ALLOC!$AL$1:$AL$420,_CALC_ALLOC!$AS$1:$AS$420,"2027|"&$P$1,_CALC_ALLOC!$B$1:$B$420,$U90,_CALC_ALLOC!$D$1:$D$420,$W90,_CALC_ALLOC!$E$1:$E$420,$X90,_CALC_ALLOC!$F$1:$F$420,$Y90) -> 0 | I90: =SUMIFS(_CALC_ALLOC!$AR$1:$AR$420,_CALC_ALLOC!$AS$1:$AS$420,"2027|"&$P$1,_CALC_ALLOC!$B$1:$B$420,$U90,_CALC_ALLOC!$D$1:$D$420,$W90,_CALC_ALLOC!$E$1:$E$420,$X90,_CALC_ALLOC!$F$1:$F$420,$Y90) -> 0 | J90: =SUMIFS(_CALC_ALLOC!$AM$1:$AM$420,_CALC_ALLOC!$AS$1:$AS$420,"2027|"&$P$1,_CALC_ALLOC!$B$1:$B$420,$U90,_CALC_ALLOC!$D$1:$D$420,$W90,_CALC_ALLOC!$E$1:$E$420,$X90,_CALC_ALLOC!$F$1:$F$420,$Y90) -> 0 | K90: =E90+F90+G90+H90+I90+J90 -> 0 | L90: =SUMIFS(_CALC_ALLOC!$AN$1:$AN$420,_CALC_ALLOC!$AS$1:$AS$420,"2027|"&$P$1,_CALC_ALLOC!$B$1:$B$420,$U90,_CALC_ALLOC!$D$1:$D$420,$W90,_CALC_ALLOC!$E$1:$E$420,$X90,_CALC_ALLOC!$F$1:$F$420,$Y90) -> 0 | M90: =IF(D90=0,0,L90/D90) -> 0 | T90: TUNON_PAR|BAC_TOU|B1|ALT | U90: TUNON_PAR | V90: TUNON | W90: BAC_TOU | X90: B1 | Y90: ALT | Z90: 3 | BF90: 2027BUD_V1 | BG90: ACT | BH90: 12 | BI90: 2025 | BJ90: MBWAY_BOR | BK90: MBWAY | BL90: MAS_MGT | BM90: M2 | BN90: ALT | BO90: 47 | BP90: 2 | BQ90: 341925 | BR90: 20165.075 | BS90: 46887.575 | BT90: 17761.519 | BU90: 126681.16 | BV90: 9559.8896 | BW90: 44043.135 | BX90: 53603.024 | BY90: 37926.594 | BZ90: 227171.76 | CA90: 265098.35 | CB90: 76826.65 | CC90: 0 | CD90: 115229 | CE90: 267929 | CF90: 88430 | CG90: 22657 | CH90: 633405.78 | CI90: 2760232 | CJ90: 580167
B91: Bachelor Tourisme, 2e année, alternance | C91: =SUMIFS(_CALC_ALLOC!$G$1:$G$420,_CALC_ALLOC!$AS$1:$AS$420,"2027|"&$P$1,_CALC_ALLOC!$B$1:$B$420,$U91,_CALC_ALLOC!$D$1:$D$420,$W91,_CALC_ALLOC!$E$1:$E$420,$X91,_CALC_ALLOC!$F$1:$F$420,$Y91) -> 0 | D91: =SUMIFS(_CALC_ALLOC!$I$1:$I$420,_CALC_ALLOC!$AS$1:$AS$420,"2027|"&$P$1,_CALC_ALLOC!$B$1:$B$420,$U91,_CALC_ALLOC!$D$1:$D$420,$W91,_CALC_ALLOC!$E$1:$E$420,$X91,_CALC_ALLOC!$F$1:$F$420,$Y91) -> 0 | E91: =SUMIFS(_CALC_ALLOC!$AI$1:$AI$420,_CALC_ALLOC!$AS$1:$AS$420,"2027|"&$P$1,_CALC_ALLOC!$B$1:$B$420,$U91,_CALC_ALLOC!$D$1:$D$420,$W91,_CALC_ALLOC!$E$1:$E$420,$X91,_CALC_ALLOC!$F$1:$F$420,$Y91) -> 0 | F91: =SUMIFS(_CALC_ALLOC!$AJ$1:$AJ$420,_CALC_ALLOC!$AS$1:$AS$420,"2027|"&$P$1,_CALC_ALLOC!$B$1:$B$420,$U91,_CALC_ALLOC!$D$1:$D$420,$W91,_CALC_ALLOC!$E$1:$E$420,$X91,_CALC_ALLOC!$F$1:$F$420,$Y91) -> 0 | G91: =SUMIFS(_CALC_ALLOC!$AK$1:$AK$420,_CALC_ALLOC!$AS$1:$AS$420,"2027|"&$P$1,_CALC_ALLOC!$B$1:$B$420,$U91,_CALC_ALLOC!$D$1:$D$420,$W91,_CALC_ALLOC!$E$1:$E$420,$X91,_CALC_ALLOC!$F$1:$F$420,$Y91) -> 0 | H91: =SUMIFS(_CALC_ALLOC!$AL$1:$AL$420,_CALC_ALLOC!$AS$1:$AS$420,"2027|"&$P$1,_CALC_ALLOC!$B$1:$B$420,$U91,_CALC_ALLOC!$D$1:$D$420,$W91,_CALC_ALLOC!$E$1:$E$420,$X91,_CALC_ALLOC!$F$1:$F$420,$Y91) -> 0 | I91: =SUMIFS(_CALC_ALLOC!$AR$1:$AR$420,_CALC_ALLOC!$AS$1:$AS$420,"2027|"&$P$1,_CALC_ALLOC!$B$1:$B$420,$U91,_CALC_ALLOC!$D$1:$D$420,$W91,_CALC_ALLOC!$E$1:$E$420,$X91,_CALC_ALLOC!$F$1:$F$420,$Y91) -> 0 | J91: =SUMIFS(_CALC_ALLOC!$AM$1:$AM$420,_CALC_ALLOC!$AS$1:$AS$420,"2027|"&$P$1,_CALC_ALLOC!$B$1:$B$420,$U91,_CALC_ALLOC!$D$1:$D$420,$W91,_CALC_ALLOC!$E$1:$E$420,$X91,_CALC_ALLOC!$F$1:$F$420,$Y91) -> 0 | K91: =E91+F91+G91+H91+I91+J91 -> 0 | L91: =SUMIFS(_CALC_ALLOC!$AN$1:$AN$420,_CALC_ALLOC!$AS$1:$AS$420,"2027|"&$P$1,_CALC_ALLOC!$B$1:$B$420,$U91,_CALC_ALLOC!$D$1:$D$420,$W91,_CALC_ALLOC!$E$1:$E$420,$X91,_CALC_ALLOC!$F$1:$F$420,$Y91) -> 0 | M91: =IF(D91=0,0,L91/D91) -> 0 | T91: TUNON_PAR|BAC_TOU|B2|ALT | U91: TUNON_PAR | V91: TUNON | W91: BAC_TOU | X91: B2 | Y91: ALT | Z91: 3 | BF91: 2027BUD_V1 | BG91: ACT | BH91: 12 | BI91: 2025 | BJ91: MBWAY_LYO | BK91: MBWAY | BL91: BAC_MGT | BM91: B1 | BN91: INIT | BO91: 62 | BP91: 3 | BQ91: 493830 | BR91: 43210.881 | BS91: 110109.71 | BT91: 42460.069 | BU91: 208376.72 | BV91: 14330.378 | BW91: 66021.133 | BX91: 80351.511 | BY91: 85670.95 | BZ91: 398837.93 | CA91: 484508.88 | CB91: 9321.1176 | CC91: 62 | CD91: 149798 | CE91: 381714.36 | CF91: 115067 | CG91: 37985 | CH91: 902966.67 | CI91: 2760232 | CJ91: 580167
B92: Bachelor Tourisme, 3e année, alternance | C92: =SUMIFS(_CALC_ALLOC!$G$1:$G$420,_CALC_ALLOC!$AS$1:$AS$420,"2027|"&$P$1,_CALC_ALLOC!$B$1:$B$420,$U92,_CALC_ALLOC!$D$1:$D$420,$W92,_CALC_ALLOC!$E$1:$E$420,$X92,_CALC_ALLOC!$F$1:$F$420,$Y92) -> 0 | D92: =SUMIFS(_CALC_ALLOC!$I$1:$I$420,_CALC_ALLOC!$AS$1:$AS$420,"2027|"&$P$1,_CALC_ALLOC!$B$1:$B$420,$U92,_CALC_ALLOC!$D$1:$D$420,$W92,_CALC_ALLOC!$E$1:$E$420,$X92,_CALC_ALLOC!$F$1:$F$420,$Y92) -> 0 | E92: =SUMIFS(_CALC_ALLOC!$AI$1:$AI$420,_CALC_ALLOC!$AS$1:$AS$420,"2027|"&$P$1,_CALC_ALLOC!$B$1:$B$420,$U92,_CALC_ALLOC!$D$1:$D$420,$W92,_CALC_ALLOC!$E$1:$E$420,$X92,_CALC_ALLOC!$F$1:$F$420,$Y92) -> 0 | F92: =SUMIFS(_CALC_ALLOC!$AJ$1:$AJ$420,_CALC_ALLOC!$AS$1:$AS$420,"2027|"&$P$1,_CALC_ALLOC!$B$1:$B$420,$U92,_CALC_ALLOC!$D$1:$D$420,$W92,_CALC_ALLOC!$E$1:$E$420,$X92,_CALC_ALLOC!$F$1:$F$420,$Y92) -> 0 | G92: =SUMIFS(_CALC_ALLOC!$AK$1:$AK$420,_CALC_ALLOC!$AS$1:$AS$420,"2027|"&$P$1,_CALC_ALLOC!$B$1:$B$420,$U92,_CALC_ALLOC!$D$1:$D$420,$W92,_CALC_ALLOC!$E$1:$E$420,$X92,_CALC_ALLOC!$F$1:$F$420,$Y92) -> 0 | H92: =SUMIFS(_CALC_ALLOC!$AL$1:$AL$420,_CALC_ALLOC!$AS$1:$AS$420,"2027|"&$P$1,_CALC_ALLOC!$B$1:$B$420,$U92,_CALC_ALLOC!$D$1:$D$420,$W92,_CALC_ALLOC!$E$1:$E$420,$X92,_CALC_ALLOC!$F$1:$F$420,$Y92) -> 0 | I92: =SUMIFS(_CALC_ALLOC!$AR$1:$AR$420,_CALC_ALLOC!$AS$1:$AS$420,"2027|"&$P$1,_CALC_ALLOC!$B$1:$B$420,$U92,_CALC_ALLOC!$D$1:$D$420,$W92,_CALC_ALLOC!$E$1:$E$420,$X92,_CALC_ALLOC!$F$1:$F$420,$Y92) -> 0 | J92: =SUMIFS(_CALC_ALLOC!$AM$1:$AM$420,_CALC_ALLOC!$AS$1:$AS$420,"2027|"&$P$1,_CALC_ALLOC!$B$1:$B$420,$U92,_CALC_ALLOC!$D$1:$D$420,$W92,_CALC_ALLOC!$E$1:$E$420,$X92,_CALC_ALLOC!$F$1:$F$420,$Y92) -> 0 | K92: =E92+F92+G92+H92+I92+J92 -> 0 | L92: =SUMIFS(_CALC_ALLOC!$AN$1:$AN$420,_CALC_ALLOC!$AS$1:$AS$420,"2027|"&$P$1,_CALC_ALLOC!$B$1:$B$420,$U92,_CALC_ALLOC!$D$1:$D$420,$W92,_CALC_ALLOC!$E$1:$E$420,$X92,_CALC_ALLOC!$F$1:$F$420,$Y92) -> 0 | M92: =IF(D92=0,0,L92/D92) -> 0 | T92: TUNON_PAR|BAC_TOU|B3|ALT | U92: TUNON_PAR | V92: TUNON | W92: BAC_TOU | X92: B3 | Y92: ALT | Z92: 3 | BF92: 2027BUD_V1 | BG92: ACT | BH92: 12 | BI92: 2025 | BJ92: MBWAY_LYO | BK92: MBWAY | BL92: BAC_MGT | BM92: B2 | BN92: ALT | BO92: 60 | BP92: 2 | BQ92: 441000 | BR92: 23045.823 | BS92: 58725.227 | BT92: 22710.544 | BU92: 138917.81 | BV92: 9553.585 | BW92: 44014.089 | BX92: 53567.674 | BY92: 45756.367 | BZ92: 251210.71 | CA92: 296967.08 | CB92: 144032.92 | CC92: 0 | CD92: 149798 | CE92: 381714.36 | CF92: 115067 | CG92: 37985 | CH92: 902966.67 | CI92: 2760232 | CJ92: 580167
B93: Lyon | C93: =SUMIFS(_CALC_ALLOC!$G$1:$G$420,_CALC_ALLOC!$AS$1:$AS$420,"2027|"&$P$1,_CALC_ALLOC!$B$1:$B$420,$U93) -> 0 | D93: =SUMIFS(_CALC_ALLOC!$I$1:$I$420,_CALC_ALLOC!$AS$1:$AS$420,"2027|"&$P$1,_CALC_ALLOC!$B$1:$B$420,$U93) -> 0 | E93: =SUMIFS(_CALC_ALLOC!$AI$1:$AI$420,_CALC_ALLOC!$AS$1:$AS$420,"2027|"&$P$1,_CALC_ALLOC!$B$1:$B$420,$U93) -> 0 | F93: =SUMIFS(_CALC_ALLOC!$AJ$1:$AJ$420,_CALC_ALLOC!$AS$1:$AS$420,"2027|"&$P$1,_CALC_ALLOC!$B$1:$B$420,$U93) -> 0 | G93: =SUMIFS(_CALC_ALLOC!$AK$1:$AK$420,_CALC_ALLOC!$AS$1:$AS$420,"2027|"&$P$1,_CALC_ALLOC!$B$1:$B$420,$U93) -> 0 | H93: =SUMIFS(_CALC_ALLOC!$AL$1:$AL$420,_CALC_ALLOC!$AS$1:$AS$420,"2027|"&$P$1,_CALC_ALLOC!$B$1:$B$420,$U93) -> 0 | I93: =SUMIFS(_CALC_ALLOC!$AR$1:$AR$420,_CALC_ALLOC!$AS$1:$AS$420,"2027|"&$P$1,_CALC_ALLOC!$B$1:$B$420,$U93) -> 0 | J93: =SUMIFS(_CALC_ALLOC!$AM$1:$AM$420,_CALC_ALLOC!$AS$1:$AS$420,"2027|"&$P$1,_CALC_ALLOC!$B$1:$B$420,$U93) -> 0 | K93: =E93+F93+G93+H93+I93+J93 -> 0 | L93: =SUMIFS(_CALC_ALLOC!$AN$1:$AN$420,_CALC_ALLOC!$AS$1:$AS$420,"2027|"&$P$1,_CALC_ALLOC!$B$1:$B$420,$U93) -> 0 | M93: =IF(D93=0,0,L93/D93) -> 0 | T93: TUNON_LYO | U93: TUNON_LYO | V93: TUNON | Z93: 2 | BF93: 2027BUD_V1 | BG93: ACT | BH93: 12 | BI93: 2025 | BJ93: MBWAY_LYO | BK93: MBWAY | BL93: BAC_MGT | BM93: B3 | BN93: ALT | BO93: 59 | BP93: 2 | BQ93: 433650 | BR93: 23045.823 | BS93: 58725.227 | BT93: 22331.973 | BU93: 138917.81 | BV93: 9553.585 | BW93: 44014.089 | BX93: 53567.674 | BY93: 45377.796 | BZ93: 251210.71 | CA93: 296588.51 | CB93: 137061.49 | CC93: 0 | CD93: 149798 | CE93: 381714.36 | CF93: 115067 | CG93: 37985 | CH93: 902966.67 | CI93: 2760232 | CJ93: 580167
B94: Bachelor Tourisme, 1re année, alternance | C94: =SUMIFS(_CALC_ALLOC!$G$1:$G$420,_CALC_ALLOC!$AS$1:$AS$420,"2027|"&$P$1,_CALC_ALLOC!$B$1:$B$420,$U94,_CALC_ALLOC!$D$1:$D$420,$W94,_CALC_ALLOC!$E$1:$E$420,$X94,_CALC_ALLOC!$F$1:$F$420,$Y94) -> 0 | D94: =SUMIFS(_CALC_ALLOC!$I$1:$I$420,_CALC_ALLOC!$AS$1:$AS$420,"2027|"&$P$1,_CALC_ALLOC!$B$1:$B$420,$U94,_CALC_ALLOC!$D$1:$D$420,$W94,_CALC_ALLOC!$E$1:$E$420,$X94,_CALC_ALLOC!$F$1:$F$420,$Y94) -> 0 | E94: =SUMIFS(_CALC_ALLOC!$AI$1:$AI$420,_CALC_ALLOC!$AS$1:$AS$420,"2027|"&$P$1,_CALC_ALLOC!$B$1:$B$420,$U94,_CALC_ALLOC!$D$1:$D$420,$W94,_CALC_ALLOC!$E$1:$E$420,$X94,_CALC_ALLOC!$F$1:$F$420,$Y94) -> 0 | F94: =SUMIFS(_CALC_ALLOC!$AJ$1:$AJ$420,_CALC_ALLOC!$AS$1:$AS$420,"2027|"&$P$1,_CALC_ALLOC!$B$1:$B$420,$U94,_CALC_ALLOC!$D$1:$D$420,$W94,_CALC_ALLOC!$E$1:$E$420,$X94,_CALC_ALLOC!$F$1:$F$420,$Y94) -> 0 | G94: =SUMIFS(_CALC_ALLOC!$AK$1:$AK$420,_CALC_ALLOC!$AS$1:$AS$420,"2027|"&$P$1,_CALC_ALLOC!$B$1:$B$420,$U94,_CALC_ALLOC!$D$1:$D$420,$W94,_CALC_ALLOC!$E$1:$E$420,$X94,_CALC_ALLOC!$F$1:$F$420,$Y94) -> 0 | H94: =SUMIFS(_CALC_ALLOC!$AL$1:$AL$420,_CALC_ALLOC!$AS$1:$AS$420,"2027|"&$P$1,_CALC_ALLOC!$B$1:$B$420,$U94,_CALC_ALLOC!$D$1:$D$420,$W94,_CALC_ALLOC!$E$1:$E$420,$X94,_CALC_ALLOC!$F$1:$F$420,$Y94) -> 0 | I94: =SUMIFS(_CALC_ALLOC!$AR$1:$AR$420,_CALC_ALLOC!$AS$1:$AS$420,"2027|"&$P$1,_CALC_ALLOC!$B$1:$B$420,$U94,_CALC_ALLOC!$D$1:$D$420,$W94,_CALC_ALLOC!$E$1:$E$420,$X94,_CALC_ALLOC!$F$1:$F$420,$Y94) -> 0 | J94: =SUMIFS(_CALC_ALLOC!$AM$1:$AM$420,_CALC_ALLOC!$AS$1:$AS$420,"2027|"&$P$1,_CALC_ALLOC!$B$1:$B$420,$U94,_CALC_ALLOC!$D$1:$D$420,$W94,_CALC_ALLOC!$E$1:$E$420,$X94,_CALC_ALLOC!$F$1:$F$420,$Y94) -> 0 | K94: =E94+F94+G94+H94+I94+J94 -> 0 | L94: =SUMIFS(_CALC_ALLOC!$AN$1:$AN$420,_CALC_ALLOC!$AS$1:$AS$420,"2027|"&$P$1,_CALC_ALLOC!$B$1:$B$420,$U94,_CALC_ALLOC!$D$1:$D$420,$W94,_CALC_ALLOC!$E$1:$E$420,$X94,_CALC_ALLOC!$F$1:$F$420,$Y94) -> 0 | M94: =IF(D94=0,0,L94/D94) -> 0 | T94: TUNON_LYO|BAC_TOU|B1|ALT | U94: TUNON_LYO | V94: TUNON | W94: BAC_TOU | X94: B1 | Y94: ALT | Z94: 3 | BF94: 2027BUD_V1 | BG94: ACT | BH94: 12 | BI94: 2025 | BJ94: MBWAY_LYO | BK94: MBWAY | BL94: MAS_MGT | BM94: M1 | BN94: ALT | BO94: 62 | BP94: 3 | BQ94: 493830 | BR94: 30247.662 | BS94: 77076.909 | BT94: 42460.069 | BU94: 208376.72 | BV94: 14330.378 | BW94: 66021.133 | BX94: 80351.511 | BY94: 72707.731 | BZ94: 365805.13 | CA94: 438512.87 | CB94: 55317.134 | CC94: 62 | CD94: 149798 | CE94: 381714.36 | CF94: 115067 | CG94: 37985 | CH94: 902966.67 | CI94: 2760232 | CJ94: 580167
B95: Bachelor Tourisme, 2e année, alternance | C95: =SUMIFS(_CALC_ALLOC!$G$1:$G$420,_CALC_ALLOC!$AS$1:$AS$420,"2027|"&$P$1,_CALC_ALLOC!$B$1:$B$420,$U95,_CALC_ALLOC!$D$1:$D$420,$W95,_CALC_ALLOC!$E$1:$E$420,$X95,_CALC_ALLOC!$F$1:$F$420,$Y95) -> 0 | D95: =SUMIFS(_CALC_ALLOC!$I$1:$I$420,_CALC_ALLOC!$AS$1:$AS$420,"2027|"&$P$1,_CALC_ALLOC!$B$1:$B$420,$U95,_CALC_ALLOC!$D$1:$D$420,$W95,_CALC_ALLOC!$E$1:$E$420,$X95,_CALC_ALLOC!$F$1:$F$420,$Y95) -> 0 | E95: =SUMIFS(_CALC_ALLOC!$AI$1:$AI$420,_CALC_ALLOC!$AS$1:$AS$420,"2027|"&$P$1,_CALC_ALLOC!$B$1:$B$420,$U95,_CALC_ALLOC!$D$1:$D$420,$W95,_CALC_ALLOC!$E$1:$E$420,$X95,_CALC_ALLOC!$F$1:$F$420,$Y95) -> 0 | F95: =SUMIFS(_CALC_ALLOC!$AJ$1:$AJ$420,_CALC_ALLOC!$AS$1:$AS$420,"2027|"&$P$1,_CALC_ALLOC!$B$1:$B$420,$U95,_CALC_ALLOC!$D$1:$D$420,$W95,_CALC_ALLOC!$E$1:$E$420,$X95,_CALC_ALLOC!$F$1:$F$420,$Y95) -> 0 | G95: =SUMIFS(_CALC_ALLOC!$AK$1:$AK$420,_CALC_ALLOC!$AS$1:$AS$420,"2027|"&$P$1,_CALC_ALLOC!$B$1:$B$420,$U95,_CALC_ALLOC!$D$1:$D$420,$W95,_CALC_ALLOC!$E$1:$E$420,$X95,_CALC_ALLOC!$F$1:$F$420,$Y95) -> 0 | H95: =SUMIFS(_CALC_ALLOC!$AL$1:$AL$420,_CALC_ALLOC!$AS$1:$AS$420,"2027|"&$P$1,_CALC_ALLOC!$B$1:$B$420,$U95,_CALC_ALLOC!$D$1:$D$420,$W95,_CALC_ALLOC!$E$1:$E$420,$X95,_CALC_ALLOC!$F$1:$F$420,$Y95) -> 0 | I95: =SUMIFS(_CALC_ALLOC!$AR$1:$AR$420,_CALC_ALLOC!$AS$1:$AS$420,"2027|"&$P$1,_CALC_ALLOC!$B$1:$B$420,$U95,_CALC_ALLOC!$D$1:$D$420,$W95,_CALC_ALLOC!$E$1:$E$420,$X95,_CALC_ALLOC!$F$1:$F$420,$Y95) -> 0 | J95: =SUMIFS(_CALC_ALLOC!$AM$1:$AM$420,_CALC_ALLOC!$AS$1:$AS$420,"2027|"&$P$1,_CALC_ALLOC!$B$1:$B$420,$U95,_CALC_ALLOC!$D$1:$D$420,$W95,_CALC_ALLOC!$E$1:$E$420,$X95,_CALC_ALLOC!$F$1:$F$420,$Y95) -> 0 | K95: =E95+F95+G95+H95+I95+J95 -> 0 | L95: =SUMIFS(_CALC_ALLOC!$AN$1:$AN$420,_CALC_ALLOC!$AS$1:$AS$420,"2027|"&$P$1,_CALC_ALLOC!$B$1:$B$420,$U95,_CALC_ALLOC!$D$1:$D$420,$W95,_CALC_ALLOC!$E$1:$E$420,$X95,_CALC_ALLOC!$F$1:$F$420,$Y95) -> 0 | M95: =IF(D95=0,0,L95/D95) -> 0 | T95: TUNON_LYO|BAC_TOU|B2|ALT | U95: TUNON_LYO | V95: TUNON | W95: BAC_TOU | X95: B2 | Y95: ALT | Z95: 3 | BF95: 2027BUD_V1 | BG95: ACT | BH95: 12 | BI95: 2025 | BJ95: MBWAY_LYO | BK95: MBWAY | BL95: MAS_MGT | BM95: M2 | BN95: ALT | BO95: 61 | BP95: 3 | BQ95: 480375 | BR95: 30247.662 | BS95: 77076.909 | BT95: 23088.999 | BU95: 208376.72 | BV95: 14330.378 | BW95: 66021.133 | BX95: 80351.511 | BY95: 53336.661 | BZ95: 365805.13 | CA95: 419141.8 | CB95: 61233.205 | CC95: 0 | CD95: 149798 | CE95: 381714.36 | CF95: 115067 | CG95: 37985 | CH95: 902966.67 | CI95: 2760232 | CJ95: 580167
B96: Bachelor Tourisme, 3e année, alternance | C96: =SUMIFS(_CALC_ALLOC!$G$1:$G$420,_CALC_ALLOC!$AS$1:$AS$420,"2027|"&$P$1,_CALC_ALLOC!$B$1:$B$420,$U96,_CALC_ALLOC!$D$1:$D$420,$W96,_CALC_ALLOC!$E$1:$E$420,$X96,_CALC_ALLOC!$F$1:$F$420,$Y96) -> 0 | D96: =SUMIFS(_CALC_ALLOC!$I$1:$I$420,_CALC_ALLOC!$AS$1:$AS$420,"2027|"&$P$1,_CALC_ALLOC!$B$1:$B$420,$U96,_CALC_ALLOC!$D$1:$D$420,$W96,_CALC_ALLOC!$E$1:$E$420,$X96,_CALC_ALLOC!$F$1:$F$420,$Y96) -> 0 | E96: =SUMIFS(_CALC_ALLOC!$AI$1:$AI$420,_CALC_ALLOC!$AS$1:$AS$420,"2027|"&$P$1,_CALC_ALLOC!$B$1:$B$420,$U96,_CALC_ALLOC!$D$1:$D$420,$W96,_CALC_ALLOC!$E$1:$E$420,$X96,_CALC_ALLOC!$F$1:$F$420,$Y96) -> 0 | F96: =SUMIFS(_CALC_ALLOC!$AJ$1:$AJ$420,_CALC_ALLOC!$AS$1:$AS$420,"2027|"&$P$1,_CALC_ALLOC!$B$1:$B$420,$U96,_CALC_ALLOC!$D$1:$D$420,$W96,_CALC_ALLOC!$E$1:$E$420,$X96,_CALC_ALLOC!$F$1:$F$420,$Y96) -> 0 | G96: =SUMIFS(_CALC_ALLOC!$AK$1:$AK$420,_CALC_ALLOC!$AS$1:$AS$420,"2027|"&$P$1,_CALC_ALLOC!$B$1:$B$420,$U96,_CALC_ALLOC!$D$1:$D$420,$W96,_CALC_ALLOC!$E$1:$E$420,$X96,_CALC_ALLOC!$F$1:$F$420,$Y96) -> 0 | H96: =SUMIFS(_CALC_ALLOC!$AL$1:$AL$420,_CALC_ALLOC!$AS$1:$AS$420,"2027|"&$P$1,_CALC_ALLOC!$B$1:$B$420,$U96,_CALC_ALLOC!$D$1:$D$420,$W96,_CALC_ALLOC!$E$1:$E$420,$X96,_CALC_ALLOC!$F$1:$F$420,$Y96) -> 0 | I96: =SUMIFS(_CALC_ALLOC!$AR$1:$AR$420,_CALC_ALLOC!$AS$1:$AS$420,"2027|"&$P$1,_CALC_ALLOC!$B$1:$B$420,$U96,_CALC_ALLOC!$D$1:$D$420,$W96,_CALC_ALLOC!$E$1:$E$420,$X96,_CALC_ALLOC!$F$1:$F$420,$Y96) -> 0 | J96: =SUMIFS(_CALC_ALLOC!$AM$1:$AM$420,_CALC_ALLOC!$AS$1:$AS$420,"2027|"&$P$1,_CALC_ALLOC!$B$1:$B$420,$U96,_CALC_ALLOC!$D$1:$D$420,$W96,_CALC_ALLOC!$E$1:$E$420,$X96,_CALC_ALLOC!$F$1:$F$420,$Y96) -> 0 | K96: =E96+F96+G96+H96+I96+J96 -> 0 | L96: =SUMIFS(_CALC_ALLOC!$AN$1:$AN$420,_CALC_ALLOC!$AS$1:$AS$420,"2027|"&$P$1,_CALC_ALLOC!$B$1:$B$420,$U96,_CALC_ALLOC!$D$1:$D$420,$W96,_CALC_ALLOC!$E$1:$E$420,$X96,_CALC_ALLOC!$F$1:$F$420,$Y96) -> 0 | M96: =IF(D96=0,0,L96/D96) -> 0 | T96: TUNON_LYO|BAC_TOU|B3|ALT | U96: TUNON_LYO | V96: TUNON | W96: BAC_TOU | X96: B3 | Y96: ALT | Z96: 3 | BF96: 2027BUD_V1 | BG96: ACT | BH96: 12 | BI96: 2025 | BJ96: MBWAY_NAN | BK96: MBWAY | BL96: BAC_MGT | BM96: B1 | BN96: INIT | BO96: 57 | BP96: 2 | BQ96: 432630 | BR96: 29420.08 | BS96: 70856.809 | BT96: 35664.476 | BU96: 129791.15 | BV96: 9498.5749 | BW96: 43760.653 | BX96: 53259.228 | BY96: 65084.556 | BZ96: 253907.19 | CA96: 318991.74 | CB96: 113638.26 | CC96: 57 | CD96: 138275 | CE96: 333028.5 | CF96: 104412 | CG96: 28666 | CH96: 778750.02 | CI96: 2760232 | CJ96: 580167
B97: GROUPE | C97: =SUMIFS(_CALC_ALLOC!$G$1:$G$420,_CALC_ALLOC!$AS$1:$AS$420,"2027|"&$P$1) -> 3473.67 | D97: =SUMIFS(_CALC_ALLOC!$I$1:$I$420,_CALC_ALLOC!$AS$1:$AS$420,"2027|"&$P$1) -> 26814168 | E97: =SUMIFS(_CALC_ALLOC!$AI$1:$AI$420,_CALC_ALLOC!$AS$1:$AS$420,"2027|"&$P$1) -> 1780848.6 | F97: =SUMIFS(_CALC_ALLOC!$AJ$1:$AJ$420,_CALC_ALLOC!$AS$1:$AS$420,"2027|"&$P$1) -> 4035428 | G97: =SUMIFS(_CALC_ALLOC!$AK$1:$AK$420,_CALC_ALLOC!$AS$1:$AS$420,"2027|"&$P$1) -> 1771335.5 | H97: =SUMIFS(_CALC_ALLOC!$AL$1:$AL$420,_CALC_ALLOC!$AS$1:$AS$420,"2027|"&$P$1) -> 8810446.7 | I97: =SUMIFS(_CALC_ALLOC!$AR$1:$AR$420,_CALC_ALLOC!$AS$1:$AS$420,"2027|"&$P$1) -> 777795.6 | J97: =SUMIFS(_CALC_ALLOC!$AM$1:$AM$420,_CALC_ALLOC!$AS$1:$AS$420,"2027|"&$P$1) -> 2894010 | K97: =E97+F97+G97+H97+I97+J97 -> 20069864 | L97: =SUMIFS(_CALC_ALLOC!$AN$1:$AN$420,_CALC_ALLOC!$AS$1:$AS$420,"2027|"&$P$1) -> 6744304.1 | M97: =IF(D97=0,0,L97/D97) -> 0.25152017 | T97: GROUPE | Z97: 0 | BF97: 2027BUD_V1 | BG97: ACT | BH97: 12 | BI97: 2025 | BJ97: MBWAY_NAN | BK97: MBWAY | BL97: BAC_MGT | BM97: B2 | BN97: ALT | BO97: 55 | BP97: 2 | BQ97: 385000 | BR97: 23536.064 | BS97: 56685.447 | BT97: 20582.946 | BU97: 129791.15 | BV97: 9498.5749 | BW97: 43760.653 | BX97: 53259.228 | BY97: 44119.011 | BZ97: 239735.83 | CA97: 283854.84 | CB97: 101145.16 | CC97: 0 | CD97: 138275 | CE97: 333028.5 | CF97: 104412 | CG97: 28666 | CH97: 778750.02 | CI97: 2760232 | CJ97: 580167
BF98: 2027BUD_V1 | BG98: ACT | BH98: 12 | BI98: 2025 | BJ98: MBWAY_NAN | BK98: MBWAY | BL98: BAC_MGT | BM98: B3 | BN98: ALT | BO98: 54 | BP98: 2 | BQ98: 378000 | BR98: 23536.064 | BS98: 56685.447 | BT98: 20208.734 | BU98: 129791.15 | BV98: 9498.5749 | BW98: 43760.653 | BX98: 53259.228 | BY98: 43744.798 | BZ98: 239735.83 | CA98: 283480.62 | CB98: 94519.376 | CC98: 0 | CD98: 138275 | CE98: 333028.5 | CF98: 104412 | CG98: 28666 | CH98: 778750.02 | CI98: 2760232 | CJ98: 580167
BF99: 2027BUD_V1 | BG99: ACT | BH99: 12 | BI99: 2025 | BJ99: MBWAY_NAN | BK99: MBWAY | BL99: MAS_MGT | BM99: M1 | BN99: ALT | BO99: 57 | BP99: 3 | BQ99: 432630 | BR99: 30891.188 | BS99: 74399.899 | BT99: 35664.476 | BU99: 194687.51 | BV99: 14247.919 | BW99: 65641.242 | BX99: 79889.162 | BY99: 66555.664 | BZ99: 348976.57 | CA99: 415532.23 | CB99: 17097.77 | CC99: 57 | CD99: 138275 | CE99: 333028.5 | CF99: 104412 | CG99: 28666 | CH99: 778750.02 | CI99: 2760232 | CJ99: 580167
BF100: 2027BUD_V1 | BG100: ACT | BH100: 12 | BI100: 2025 | BJ100: MBWAY_NAN | BK100: MBWAY | BL100: MAS_MGT | BM100: M2 | BN100: ALT | BO100: 56 | BP100: 3 | BQ100: 420000 | BR100: 30891.188 | BS100: 74399.899 | BT100: 20957.159 | BU100: 194687.51 | BV100: 14247.919 | BW100: 65641.242 | BX100: 79889.162 | BY100: 51848.347 | BZ100: 348976.57 | CA100: 400824.91 | CB100: 19175.087 | CC100: 0 | CD100: 138275 | CE100: 333028.5 | CF100: 104412 | CG100: 28666 | CH100: 778750.02 | CI100: 2760232 | CJ100: 580167
...

Sheet _CALC_ALLOC
A1: EXERCICE | B1: ENTITY | C1: MARQUE | D1: PROG | E1: AN | F1: MOD | G1: VOL_EFF | H1: VOL_CLASS | I1: CA | J1: VOL_NEW | K1: HRS | L1: E_EFF | M1: E_CLS | N1: E_CA | O1: E_HRS | P1: E_NEW | Q1: M_EFF | R1: M_CLS | S1: M_CA | T1: G_EFF | U1: G_CLS | V1: G_CA | W1: VAC | X1: PERM | Y1: ODIR | Z1: MKT | AA1: STRUCT_CAMP | AB1: SIEGE | AC1: D3C | AD1: D3E | AE1: D2E | AF1: D2M | AG1: D1M | AH1: D1G | AI1: COST_VAC | AJ1: COST_PERM | AK1: COST_ODIR | AL1: COST_STRUCT | AM1: COST_SIEGE | AN1: MARGE | AO1: FRAIS_MARQUE_TOT | AP1: D1M_K4 | AQ1: D1G_K4 | AR1: COST_MARQUE | AS1: EXVER | AT1: ■ VIOLET = colonne branchee sur une saisie (cad / Pilotage / 3_Allocation) -> a recabler cote Tagetik
A2: =IF(Allocation!BI2="","",Allocation!BI2) -> 2024 | B2: =IF(Allocation!BJ2="","",Allocation!BJ2) -> IPAC_MTP | C2: =IF(Allocation!BK2="","",Allocation!BK2) -> IPAC | D2: =IF(Allocation!BL2="","",Allocation!BL2) -> BAC_CCE | E2: =IF(Allocation!BM2="","",Allocation!BM2) -> B1 | F2: =IF(Allocation!BN2="","",Allocation!BN2) -> ALT | G2: =IF(Allocation!BO2="","",Allocation!BO2) -> 36 | H2: =IF(Allocation!BP2="","",Allocation!BP2) -> 2 | I2: =IF(Allocation!BQ2="","",Allocation!BQ2) -> 242640 | J2: =IF(Allocation!CC2="","",Allocation!CC2) -> 36 | K2: =IF($A2="","",$H2*IF(AND(LEFT($D2,3)="BAC",$F2="INIT"),600,IF(LEFT($D2,3)="BAC",480,IF(AND(LEFT($D2,3)="MAS",$F2="INIT"),520,IF(LEFT($D2,3)="MAS",420,IF($F2="INIT",1000,700)))))) -> 960 | L2: =IF($A2="","",SUMIFS($G$1:$G$349,$AS$1:$AS$349,$AS2,$B$1:$B$349,$B2)) -> 105 | M2: =IF($A2="","",SUMIFS($H$1:$H$349,$AS$1:$AS$349,$AS2,$B$1:$B$349,$B2)) -> 6 | N2: =IF($A2="","",SUMIFS($I$1:$I$349,$AS$1:$AS$349,$AS2,$B$1:$B$349,$B2)) -> 701490 | O2: =IF($A2="","",SUMIFS($K$1:$K$349,$AS$1:$AS$349,$AS2,$B$1:$B$349,$B2)) -> 2880 | P2: =IF($A2="","",SUMIFS($J$1:$J$349,$AS$1:$AS$349,$AS2,$B$1:$B$349,$B2)) -> 36 | Q2: =IF($A2="","",SUMIFS($G$1:$G$349,$AS$1:$AS$349,$AS2,$C$1:$C$349,$C2)) -> 339 | R2: =IF($A2="","",SUMIFS($H$1:$H$349,$AS$1:$AS$349,$AS2,$C$1:$C$349,$C2)) -> 18 | S2: =IF($A2="","",SUMIFS($I$1:$I$349,$AS$1:$AS$349,$AS2,$C$1:$C$349,$C2)) -> 2309940 | T2: =IF($A2="","",SUMIFS($G$1:$G$349,$AS$1:$AS$349,$AS2)) -> 2773 | U2: =IF($A2="","",SUMIFS($H$1:$H$349,$AS$1:$AS$349,$AS2)) -> 135 | V2: =IF($A2="","",SUMIFS($I$1:$I$349,$AS$1:$AS$349,$AS2)) -> 20567210 | W2: =IF($A2="","",Allocation!CD2) -> 66108 | X2: =IF($A2="","",Allocation!CE2) -> 127557.21 | Y2: =IF($A2="","",Allocation!CF2) -> 39731 | Z2: =IF($A2="","",Allocation!CG2) -> 12543 | AA2: =IF($A2="","",Allocation!CH2) -> 257310.34 | AB2: =IF($A2="","",Allocation!CI2) -> 2639292 | AC2: =IF($A2="","",IF(Allocation!$N$4="VOL_EFF",$G2,IF(Allocation!$N$4="VOL_CLASS",$H2,$I2))) -> 2 | AD2: =IF($A2="","",IF(Allocation!$N$4="VOL_EFF",$L2,IF(Allocation!$N$4="VOL_CLASS",$M2,$N2))) -> 6 | AE2: =IF($A2="","",IF(Allocation!$N$3="VOL_EFF",$L2,IF(Allocation!$N$3="VOL_CLASS",$M2,$N2))) -> 105 | AF2: =IF($A2="","",IF(Allocation!$N$3="VOL_EFF",$Q2,IF(Allocation!$N$3="VOL_CLASS",$R2,$S2))) -> 339 | AG2: =IF($A2="","",IF(Allocation!$N$1="VOL_EFF",$Q2,IF(Allocation!$N$1="VOL_CLASS",$R2,$S2))) -> 339 | AH2: =IF($A2="","",IF(Allocation!$N$1="VOL_EFF",$T2,IF(Allocation!$N$1="VOL_CLASS",$U2,$V2))) -> 2773 | AI2: =IF($A2="","",$W2*IFERROR($K2/$O2,0)) -> 22036 | AJ2: =IF($A2="","",$X2*IFERROR($K2/$O2,0)) -> 42519.07 | AK2: =IF($A2="","",$Y2*IFERROR($G2/$L2,0)+$Z2*IFERROR($J2/$P2,0)) -> 26165.057 | AL2: =IF($A2="","",$AA2*IFERROR($AC2/$AD2,0)) -> 85770.113 | AM2: =IF($A2="","",$AB2*IFERROR($AG2/$AH2,0)*IFERROR($AE2/$AF2,0)*IFERROR($AC2/$AD2,0)) -> 33312.376 | AN2: =IF($A2="","",$I2-($AI2+$AJ2+$AK2+$AL2+$AM2+$AR2)) -> 27040.435 | AO2: =IF($A2="","",Allocation!CJ2) -> 499926 | AP2: =IF($A2="","",IF(Allocation!$N$2="VOL_EFF",$Q2,IF(Allocation!$N$2="VOL_CLASS",$R2,$S2))) -> 2309940 | AQ2: =IF($A2="","",IF(Allocation!$N$2="VOL_EFF",$T2,IF(Allocation!$N$2="VOL_CLASS",$U2,$V2))) -> 20567210 | AR2: =IF($A2="","",$AO2*IFERROR($AP2/$AQ2,0)*IFERROR($AE2/$AF2,0)*IFERROR($AC2/$AD2,0)) -> 5796.9478 | AS2: =IF($A2="","",$A2&"|"&Allocation!BG2) -> 2024|ACT
