Workbook
Name ALLOC_BRAND_CAMP: ALLOC!$C$8
Name ALLOC_CAMP_CLASS: ALLOC!$C$9
Name ALLOC_GRP_BRAND: ALLOC!$C$6
Name ALLOC_GRP_MARQUE: ALLOC!$C$7
Name BUD_REF_CAP: PIL!$K$15:$K$28
Name HYP_ACQ_BUD_V01: cad!$C$23
Name HYP_ACQ_BUD_V02: cad!$D$23
Name HYP_ACQ_BUD_V03: cad!$E$23
Name HYP_BRAND_BUD_V01: cad!$C$24
Name HYP_BRAND_BUD_V02: cad!$D$24
Name HYP_BRAND_BUD_V03: cad!$E$24
Name HYP_CAP_RETENU: PIL!$J$15:$J$28
Name HYP_CONV_ADM_V01: cad!$C$27
Name HYP_CONV_ADM_V02: cad!$D$27
Name HYP_CONV_ADM_V03: cad!$E$27
Name HYP_CONV_LEAD_V01: cad!$C$26
Name HYP_CONV_LEAD_V02: cad!$D$26
Name HYP_CONV_LEAD_V03: cad!$E$26
Name HYP_FEE_V01: cad!$C$39
Name HYP_FEE_V02: cad!$D$39
Name HYP_FEE_V03: cad!$E$39
Name HYP_FTE_PERM_V01: cad!$C$34
Name HYP_FTE_PERM_V02: cad!$D$34
Name HYP_FTE_PERM_V03: cad!$E$34
Name HYP_INFL_EXT_V01: cad!$C$32
Name HYP_INFL_EXT_V02: cad!$D$32
Name HYP_INFL_EXT_V03: cad!$E$32
Name HYP_PASSAGE_V01: cad!$C$28
Name HYP_PASSAGE_V02: cad!$D$28
Name HYP_PASSAGE_V03: cad!$E$28
Name HYP_PRICE_COEF_IPAC: cad!$J$14
Name HYP_PRICE_COEF_ISCOM: cad!$J$13
Name HYP_PRICE_COEF_MBWAY: cad!$J$12
Name HYP_PRICE_COEF_PIGIER: cad!$J$15
Name HYP_PRICE_COEF_TUNON: cad!$J$16
Name HYP_PRICE_V01: cad!$C$25
Name HYP_PRICE_V02: cad!$D$25
Name HYP_PRICE_V03: cad!$E$25
Name HYP_PRODUCTIVITY_V01: cad!$C$35
Name HYP_PRODUCTIVITY_V02: cad!$D$35
Name HYP_PRODUCTIVITY_V03: cad!$E$35
Name HYP_SALARY_V01: cad!$C$33
Name HYP_SALARY_V02: cad!$D$33
Name HYP_SALARY_V03: cad!$E$33
Name HYP_STRUCT_COST_V01: cad!$C$36
Name HYP_STRUCT_COST_V02: cad!$D$36
Name HYP_STRUCT_COST_V03: cad!$E$36
Name SCENARIO_ACTIF: cad!$C$5
Name SCENARIO_CODE: cad!$P$1
Name TEC_EBITDA: cad!$F$6
Name TEC_PL: cad!$F$5

Sheet _TGK_HIDDEN
A1: Template00 | B1: =cad!A65546 -> 0
A2: Template01 | B2: =Allocation2!A65536 -> 0
A3: Template02 | B3: =Campagne!A65536 -> 0
A4: Template03 | B4: =Moteur!A65536 -> 0
A5: Template04 | B5: =Compta!A65536 -> 0
A6: Template05 | B6: =PNL!A65536 -> 0
A7: Template06 | B7: =PIL!A65538 -> 0
A10: Template09 | B10: =ALLOC!B65537 -> 0

Sheet cad
P1: =IF(cad!$C$5="Optimiste","V02",IF(cad!$C$5="Prudent","V03","V01")) -> V01
B2: POSTE DE COMMANDE CFO — Cadrage CA & EBITDA 2027
B5: Scenario actif : | C5: 1000 | E5: Croissance CA cible : | F5: 0.05
E6: Marge EBITDA cible : | F6: 0.15
B8: Reconciliation — Reference · Cible · Construit (scenario actif) | I8: Coeff prix par marque (decision)
B10: Indicateur | C10: Reference | D10: Cible | E10: Construit | F10: Ecart | G10: Ecart % | I10: Marque | J10: Coeff prix
C11: 2026
B12: Chiffre d'affaires | C12: 22544725 | D12: =C12*(1+cad!$F$5) -> 23671961 | E12: =SUMIFS(Moteur!$R$1:$R$175,Moteur!$B$1:$B$175,cad!$P$1) -> 0 | F12: =E12-D12 -> -23671961 | G12: =IFERROR(E12/D12-1,0) -> -1 | I12: MBway | J12: 1.2
B13: EBITDA | C13: 3291530 | D13: =D12*cad!$F$6 -> 3550794.2 | E13: =SUMIFS(_CALC_PNL!$T$1:$T$1347,_CALC_PNL!$D$1:$D$1347,cad!$P$1,_CALC_PNL!$C$1:$C$1347,"2027") -> 0 | F13: =E13-D13 -> -3550794.2 | G13: =IFERROR(E13/D13-1,0) -> -1 | I13: ISCOM | J13: 1.15
B14: Marge EBITDA % | C14: =IFERROR(C13/C12,0) -> 0.14600001 | D14: =cad!$F$6 -> 0.15 | E14: =IFERROR(E13/E12,0) -> 0 | F14: =E14-D14 -> -0.15 | I14: Ipac Bachelor Factory | J14: 0.95
B15: Effectif | C15: 1000 | E15: =SUMIFS(Moteur!$P$1:$P$175,Moteur!$B$1:$B$175,cad!$P$1) -> 0 | F15: =E15-#REF! -> #REF! | G15: =IFERROR(E15/#REF!-1,0) -> 0 | I15: Pigier | J15: 0.9
I16: Tunon | J16: 1.05
B19: Leviers de CROISSANCE / REVENUS
B21: Paramètre | C21: =C22 -> Cadrage | D21: =D22 -> Optimiste | E21: =E22 -> Prudent | F21: ACTIF (scenario)
C22: Cadrage | D22: Optimiste | E22: Prudent
B23: Variation du budget d'acquisition → leads payants | C23: 0.08 | D23: 0.15 | E23: -0.05 | F23: #N/A
B24: Variation du budget de marque → socle organique | C24: 0.1 | D24: 0.2 | E24: -0.05 | F24: #N/A
B25: Hausse tarifaire (prix) | C25: 0.002855 | D25: 0.035 | E25: 0.02 | F25: #N/A
B26: Gain du taux de conversion Lead → Candidature | C26: 0.01 | D26: 0.03 | E26: 0 | F26: #N/A
B27: Gain du taux de conversion Admis → Inscrit | C27: 0.01 | D27: 0.025 | E27: 0 | F27: #N/A
B28: Amélioration du taux de passage | C28: 0.005 | D28: 0.015 | E28: -0.01 | F28: #N/A
B30: Leviers de COUTS
B32: Inflation des charges externes | C32: 0.02 | D32: 0.015 | E32: 0.03 | F32: =INDEX(C32:E32,MATCH(cad!$C$5,$C$22:$E$22,0)) -> #N/A
B33: Politique salariale sur la masse permanente | C33: 0.025 | D33: 0.02 | E33: 0.03 | F33: =INDEX(C33:E33,MATCH(cad!$C$5,$C$22:$E$22,0)) -> #N/A
B34: Variation des effectifs permanents | C34: 0.04 | D34: 0.03 | E34: 0.05 | F34: =INDEX(C34:E34,MATCH(cad!$C$5,$C$22:$E$22,0)) -> #N/A
B35: Effort de productivité sur les achats et la structure | C35: 0.018697 | D35: 0.03 | E35: 0 | F35: =INDEX(C35:E35,MATCH(cad!$C$5,$C$22:$E$22,0)) -> #N/A
B36: Variation des coûts de structure (loyers, IT, siège…) | C36: 0 | D36: -0.03 | E36: 0.04 | F36: =INDEX(C36:E36,MATCH(cad!$C$5,$C$22:$E$22,0)) -> #N/A
B38: Constante — frais de dossier (decision)
B39: Frais de dossier par nouvel inscrit | C39: 90 | D39: 90 | E39: 90 | F39: =INDEX(C39:E39,MATCH(cad!$C$5,$C$22:$E$22,0)) -> #N/A

Sheet PIL
B2: PILOTAGE · Cockpit de decision CFO — Budget 2027
B6: CA 2027 | D6: EBITDA (après siège) | F6: Marge EBITDA | H6: Effectif | J6: Croissance CA vs 2026
B7: =E49 -> 0 | D7: =H49 -> 0 | F7: =I49 -> 0 | H7: =D49 -> 0 | J7: =IFERROR(E49/cad!$C$12-1,0) -> -1
B12: 1 · Cap strategique par campus (marque x ville) — arbitrage du budget d'acquisition
U13: à masquer | V13: à masquer | W13: à masquer
A14: Campus | B14: Marque | C14: Ville | D14: CAC marginal | E14: Croiss. leads | F14: Intensité mkt | G14: Cap Eff | H14: Cap mom. | I14: Cap pot. | J14: Cap retenu | K14: Budget acq réf. | L14: Entity | U14: CAP_EFF (live) | V14: CAP_MOM (live) | W14: CAP_POT (live)
A15: MBWAY_PAR | B15: MBway | C15: Paris | D15: 1475 | E15: 0.110736 | F15: 0.021757 | G15: 0.81 | H15: 1.06 | I15: 0.86 | J15: 1 | K15: 68291 | L15: MBWAY_PAR
A16: MBWAY_LYO | B16: MBway | C16: Lyon | D16: 1102 | E16: 0.118872 | F16: 0.016735 | G16: 1.09 | H16: 1.14 | I16: 1.12 | J16: 1 | K16: 41783
A17: MBWAY_NAN | B17: MBway | C17: Nantes | D17: 964 | E17: 0.123795 | F17: 0.01461 | G17: 1.25 | H17: 1.18 | I17: 1.29 | J17: 1 | K17: 31533
A18: MBWAY_BOR | B18: MBway | C18: Bordeaux | D18: 890 | E18: 0.126095 | F18: 0.014052 | G18: 1.35 | H18: 1.21 | I18: 1.34 | J18: 1 | K18: 24923
A19: ISCOM_PAR | B19: ISCOM | C19: Paris | D19: 1540 | E19: 0.077745 | F19: 0.020903 | G19: 0.78 | H19: 0.74 | I19: 0.9 | J19: 1 | K19: 60800
A20: ISCOM_LIL | B20: ISCOM | C20: Lille | D20: 979 | E20: 0.081545 | F20: 0.014363 | G20: 1.23 | H20: 0.78 | I20: 1.31 | J20: 1 | K20: 25220
A21: ISCOM_TLS | B21: ISCOM | C21: Toulouse | D21: 919 | E21: 0.082117 | F21: 0.013565 | G21: 1.31 | H21: 0.79 | I21: 1.39 | J21: 1 | K21: 22083
A22: IPAC_NAN | B22: Ipac | C22: Nantes | D22: 1216 | E22: 0.137885 | F22: 0.021344 | G22: 0.99 | H22: 1.32 | I22: 0.88 | J22: 1 | K22: 21760
A23: IPAC_REN | B23: Ipac | C23: Rennes | D23: 1041 | E23: 0.144781 | F23: 0.019104 | G23: 1.16 | H23: 1.39 | I23: 0.98 | J23: 1 | K23: 14933
A24: IPAC_MTP | B24: Ipac | C24: Montpellier | D24: 1034 | E24: 0.144781 | F24: 0.019418 | G24: 1.16 | H24: 1.39 | I24: 0.97 | J24: 1 | K24: 15178
A25: PIGIER_LYO | B25: Pigier | C25: Lyon | D25: 1705 | E25: 0.085003 | F25: 0.02928 | G25: 0.71 | H25: 0.81 | I25: 0.64 | J25: 1 | K25: 36612
A26: PIGIER_BOR | B26: Pigier | C26: Bordeaux | D26: 1368 | E26: 0.087533 | F26: 0.02436 | G26: 0.88 | H26: 0.84 | I26: 0.77 | J26: 1 | K26: 21968
A27: TUNON_PAR | B27: Tunon | C27: Paris | D27: 2193 | E27: 0.069519 | F27: 0.027841 | G27: 0.55 | H27: 0.67 | I27: 0.68 | J27: 1 | K27: 30240
A28: TUNON_LYO | B28: Tunon | C28: Lyon | D28: 1625 | E28: 0.072555 | F28: 0.021828 | G28: 0.74 | H28: 0.69 | I28: 0.86 | J28: 1 | K28: 18850
B30: 2 · Synthese par campus (resultats budget, live)
A32: Campus | B32: Marque | C32: Ville | D32: Effectif | E32: CA 2027 | F32: Prix moy. | G32: Part CA | H32: EBITDA campus | I32: Mrg EBITDA | J32: EBITDA/etud. | K32: Rejoue | L32: CAC marg.
A33: MBWAY_PAR | B33: MBway | C33: Paris | D33: =SUMIFS(Moteur!$P$1:$P$175,Moteur!$D$1:$D$175,$A33,Moteur!$B$1:$B$175,cad!$P$1) -> 0 | E33: =SUMIFS(Moteur!$R$1:$R$175,Moteur!$D$1:$D$175,$A33,Moteur!$B$1:$B$175,cad!$P$1) -> 0 | F33: =IFERROR(E33/D33,0) -> 0 | G33: =IFERROR(E33/SUM($E$33:$E$46),0) -> 0 | H33: =SUMIFS(_CALC_PNL!$T$1:$T$1347,_CALC_PNL!$A$1:$A$1347,$A33,_CALC_PNL!$D$1:$D$1347,cad!$P$1,_CALC_PNL!$C$1:$C$1347,"2027") -> 0 | I33: =IFERROR(H33/E33,0) -> 0 | J33: =IFERROR(H33/D33,0) -> 0 | K33: =SUMIFS(PIL!$K$15:$K$28,PIL!$A$15:$A$28,$A33)*SUMIFS(PIL!$J$15:$J$28,PIL!$A$15:$A$28,$A33)*(SUM(PIL!$K$15:$K$28)/SUMPRODUCT(PIL!$K$15:$K$28,PIL!$J$15:$J$28)) -> 68291 | L33: =SUMIFS(PIL!$D$15:$D$28,PIL!$A$15:$A$28,$A33) -> 1475
A34: MBWAY_LYO | B34: MBway | C34: Lyon | D34: =SUMIFS(Moteur!$P$1:$P$175,Moteur!$D$1:$D$175,$A34,Moteur!$B$1:$B$175,cad!$P$1) -> 0 | E34: =SUMIFS(Moteur!$R$1:$R$175,Moteur!$D$1:$D$175,$A34,Moteur!$B$1:$B$175,cad!$P$1) -> 0 | F34: =IFERROR(E34/D34,0) -> 0 | G34: =IFERROR(E34/SUM($E$33:$E$46),0) -> 0 | H34: =SUMIFS(_CALC_PNL!$T$1:$T$1347,_CALC_PNL!$A$1:$A$1347,$A34,_CALC_PNL!$D$1:$D$1347,cad!$P$1,_CALC_PNL!$C$1:$C$1347,"2027") -> 0 | I34: =IFERROR(H34/E34,0) -> 0 | J34: =IFERROR(H34/D34,0) -> 0 | K34: =SUMIFS(PIL!$K$15:$K$28,PIL!$A$15:$A$28,$A34)*SUMIFS(PIL!$J$15:$J$28,PIL!$A$15:$A$28,$A34)*(SUM(PIL!$K$15:$K$28)/SUMPRODUCT(PIL!$K$15:$K$28,PIL!$J$15:$J$28)) -> 41783 | L34: =SUMIFS(PIL!$D$15:$D$28,PIL!$A$15:$A$28,$A34) -> 1102
A35: MBWAY_NAN | B35: MBway | C35: Nantes | D35: =SUMIFS(Moteur!$P$1:$P$175,Moteur!$D$1:$D$175,$A35,Moteur!$B$1:$B$175,cad!$P$1) -> 0 | E35: =SUMIFS(Moteur!$R$1:$R$175,Moteur!$D$1:$D$175,$A35,Moteur!$B$1:$B$175,cad!$P$1) -> 0 | F35: =IFERROR(E35/D35,0) -> 0 | G35: =IFERROR(E35/SUM($E$33:$E$46),0) -> 0 | H35: =SUMIFS(_CALC_PNL!$T$1:$T$1347,_CALC_PNL!$A$1:$A$1347,$A35,_CALC_PNL!$D$1:$D$1347,cad!$P$1,_CALC_PNL!$C$1:$C$1347,"2027") -> 0 | I35: =IFERROR(H35/E35,0) -> 0 | J35: =IFERROR(H35/D35,0) -> 0 | K35: =SUMIFS(PIL!$K$15:$K$28,PIL!$A$15:$A$28,$A35)*SUMIFS(PIL!$J$15:$J$28,PIL!$A$15:$A$28,$A35)*(SUM(PIL!$K$15:$K$28)/SUMPRODUCT(PIL!$K$15:$K$28,PIL!$J$15:$J$28)) -> 31533 | L35: =SUMIFS(PIL!$D$15:$D$28,PIL!$A$15:$A$28,$A35) -> 964
A36: MBWAY_BOR | B36: MBway | C36: Bordeaux | D36: =SUMIFS(Moteur!$P$1:$P$175,Moteur!$D$1:$D$175,$A36,Moteur!$B$1:$B$175,cad!$P$1) -> 0 | E36: =SUMIFS(Moteur!$R$1:$R$175,Moteur!$D$1:$D$175,$A36,Moteur!$B$1:$B$175,cad!$P$1) -> 0 | F36: =IFERROR(E36/D36,0) -> 0 | G36: =IFERROR(E36/SUM($E$33:$E$46),0) -> 0 | H36: =SUMIFS(_CALC_PNL!$T$1:$T$1347,_CALC_PNL!$A$1:$A$1347,$A36,_CALC_PNL!$D$1:$D$1347,cad!$P$1,_CALC_PNL!$C$1:$C$1347,"2027") -> 0 | I36: =IFERROR(H36/E36,0) -> 0 | J36: =IFERROR(H36/D36,0) -> 0 | K36: =SUMIFS(PIL!$K$15:$K$28,PIL!$A$15:$A$28,$A36)*SUMIFS(PIL!$J$15:$J$28,PIL!$A$15:$A$28,$A36)*(SUM(PIL!$K$15:$K$28)/SUMPRODUCT(PIL!$K$15:$K$28,PIL!$J$15:$J$28)) -> 24923 | L36: =SUMIFS(PIL!$D$15:$D$28,PIL!$A$15:$A$28,$A36) -> 890
A37: ISCOM_PAR | B37: ISCOM | C37: Paris | D37: =SUMIFS(Moteur!$P$1:$P$175,Moteur!$D$1:$D$175,$A37,Moteur!$B$1:$B$175,cad!$P$1) -> 0 | E37: =SUMIFS(Moteur!$R$1:$R$175,Moteur!$D$1:$D$175,$A37,Moteur!$B$1:$B$175,cad!$P$1) -> 0 | F37: =IFERROR(E37/D37,0) -> 0 | G37: =IFERROR(E37/SUM($E$33:$E$46),0) -> 0 | H37: =SUMIFS(_CALC_PNL!$T$1:$T$1347,_CALC_PNL!$A$1:$A$1347,$A37,_CALC_PNL!$D$1:$D$1347,cad!$P$1,_CALC_PNL!$C$1:$C$1347,"2027") -> 0 | I37: =IFERROR(H37/E37,0) -> 0 | J37: =IFERROR(H37/D37,0) -> 0 | K37: =SUMIFS(PIL!$K$15:$K$28,PIL!$A$15:$A$28,$A37)*SUMIFS(PIL!$J$15:$J$28,PIL!$A$15:$A$28,$A37)*(SUM(PIL!$K$15:$K$28)/SUMPRODUCT(PIL!$K$15:$K$28,PIL!$J$15:$J$28)) -> 60800 | L37: =SUMIFS(PIL!$D$15:$D$28,PIL!$A$15:$A$28,$A37) -> 1540
A38: ISCOM_LIL | B38: ISCOM | C38: Lille | D38: =SUMIFS(Moteur!$P$1:$P$175,Moteur!$D$1:$D$175,$A38,Moteur!$B$1:$B$175,cad!$P$1) -> 0 | E38: =SUMIFS(Moteur!$R$1:$R$175,Moteur!$D$1:$D$175,$A38,Moteur!$B$1:$B$175,cad!$P$1) -> 0 | F38: =IFERROR(E38/D38,0) -> 0 | G38: =IFERROR(E38/SUM($E$33:$E$46),0) -> 0 | H38: =SUMIFS(_CALC_PNL!$T$1:$T$1347,_CALC_PNL!$A$1:$A$1347,$A38,_CALC_PNL!$D$1:$D$1347,cad!$P$1,_CALC_PNL!$C$1:$C$1347,"2027") -> 0 | I38: =IFERROR(H38/E38,0) -> 0 | J38: =IFERROR(H38/D38,0) -> 0 | K38: =SUMIFS(PIL!$K$15:$K$28,PIL!$A$15:$A$28,$A38)*SUMIFS(PIL!$J$15:$J$28,PIL!$A$15:$A$28,$A38)*(SUM(PIL!$K$15:$K$28)/SUMPRODUCT(PIL!$K$15:$K$28,PIL!$J$15:$J$28)) -> 25220 | L38: =SUMIFS(PIL!$D$15:$D$28,PIL!$A$15:$A$28,$A38) -> 979
A39: ISCOM_TLS | B39: ISCOM | C39: Toulouse | D39: =SUMIFS(Moteur!$P$1:$P$175,Moteur!$D$1:$D$175,$A39,Moteur!$B$1:$B$175,cad!$P$1) -> 0 | E39: =SUMIFS(Moteur!$R$1:$R$175,Moteur!$D$1:$D$175,$A39,Moteur!$B$1:$B$175,cad!$P$1) -> 0 | F39: =IFERROR(E39/D39,0) -> 0 | G39: =IFERROR(E39/SUM($E$33:$E$46),0) -> 0 | H39: =SUMIFS(_CALC_PNL!$T$1:$T$1347,_CALC_PNL!$A$1:$A$1347,$A39,_CALC_PNL!$D$1:$D$1347,cad!$P$1,_CALC_PNL!$C$1:$C$1347,"2027") -> 0 | I39: =IFERROR(H39/E39,0) -> 0 | J39: =IFERROR(H39/D39,0) -> 0 | K39: =SUMIFS(PIL!$K$15:$K$28,PIL!$A$15:$A$28,$A39)*SUMIFS(PIL!$J$15:$J$28,PIL!$A$15:$A$28,$A39)*(SUM(PIL!$K$15:$K$28)/SUMPRODUCT(PIL!$K$15:$K$28,PIL!$J$15:$J$28)) -> 22083 | L39: =SUMIFS(PIL!$D$15:$D$28,PIL!$A$15:$A$28,$A39) -> 919
A40: IPAC_NAN | B40: Ipac | C40: Nantes | D40: =SUMIFS(Moteur!$P$1:$P$175,Moteur!$D$1:$D$175,$A40,Moteur!$B$1:$B$175,cad!$P$1) -> 0 | E40: =SUMIFS(Moteur!$R$1:$R$175,Moteur!$D$1:$D$175,$A40,Moteur!$B$1:$B$175,cad!$P$1) -> 0 | F40: =IFERROR(E40/D40,0) -> 0 | G40: =IFERROR(E40/SUM($E$33:$E$46),0) -> 0 | H40: =SUMIFS(_CALC_PNL!$T$1:$T$1347,_CALC_PNL!$A$1:$A$1347,$A40,_CALC_PNL!$D$1:$D$1347,cad!$P$1,_CALC_PNL!$C$1:$C$1347,"2027") -> 0 | I40: =IFERROR(H40/E40,0) -> 0 | J40: =IFERROR(H40/D40,0) -> 0 | K40: =SUMIFS(PIL!$K$15:$K$28,PIL!$A$15:$A$28,$A40)*SUMIFS(PIL!$J$15:$J$28,PIL!$A$15:$A$28,$A40)*(SUM(PIL!$K$15:$K$28)/SUMPRODUCT(PIL!$K$15:$K$28,PIL!$J$15:$J$28)) -> 21760 | L40: =SUMIFS(PIL!$D$15:$D$28,PIL!$A$15:$A$28,$A40) -> 1216
A41: IPAC_REN | B41: Ipac | C41: Rennes | D41: =SUMIFS(Moteur!$P$1:$P$175,Moteur!$D$1:$D$175,$A41,Moteur!$B$1:$B$175,cad!$P$1) -> 0 | E41: =SUMIFS(Moteur!$R$1:$R$175,Moteur!$D$1:$D$175,$A41,Moteur!$B$1:$B$175,cad!$P$1) -> 0 | F41: =IFERROR(E41/D41,0) -> 0 | G41: =IFERROR(E41/SUM($E$33:$E$46),0) -> 0 | H41: =SUMIFS(_CALC_PNL!$T$1:$T$1347,_CALC_PNL!$A$1:$A$1347,$A41,_CALC_PNL!$D$1:$D$1347,cad!$P$1,_CALC_PNL!$C$1:$C$1347,"2027") -> 0 | I41: =IFERROR(H41/E41,0) -> 0 | J41: =IFERROR(H41/D41,0) -> 0 | K41: =SUMIFS(PIL!$K$15:$K$28,PIL!$A$15:$A$28,$A41)*SUMIFS(PIL!$J$15:$J$28,PIL!$A$15:$A$28,$A41)*(SUM(PIL!$K$15:$K$28)/SUMPRODUCT(PIL!$K$15:$K$28,PIL!$J$15:$J$28)) -> 14933 | L41: =SUMIFS(PIL!$D$15:$D$28,PIL!$A$15:$A$28,$A41) -> 1041
A42: IPAC_MTP | B42: Ipac | C42: Montpellier | D42: =SUMIFS(Moteur!$P$1:$P$175,Moteur!$D$1:$D$175,$A42,Moteur!$B$1:$B$175,cad!$P$1) -> 0 | E42: =SUMIFS(Moteur!$R$1:$R$175,Moteur!$D$1:$D$175,$A42,Moteur!$B$1:$B$175,cad!$P$1) -> 0 | F42: =IFERROR(E42/D42,0) -> 0 | G42: =IFERROR(E42/SUM($E$33:$E$46),0) -> 0 | H42: =SUMIFS(_CALC_PNL!$T$1:$T$1347,_CALC_PNL!$A$1:$A$1347,$A42,_CALC_PNL!$D$1:$D$1347,cad!$P$1,_CALC_PNL!$C$1:$C$1347,"2027") -> 0 | I42: =IFERROR(H42/E42,0) -> 0 | J42: =IFERROR(H42/D42,0) -> 0 | K42: =SUMIFS(PIL!$K$15:$K$28,PIL!$A$15:$A$28,$A42)*SUMIFS(PIL!$J$15:$J$28,PIL!$A$15:$A$28,$A42)*(SUM(PIL!$K$15:$K$28)/SUMPRODUCT(PIL!$K$15:$K$28,PIL!$J$15:$J$28)) -> 15178 | L42: =SUMIFS(PIL!$D$15:$D$28,PIL!$A$15:$A$28,$A42) -> 1034
A43: PIGIER_LYO | B43: Pigier | C43: Lyon | D43: =SUMIFS(Moteur!$P$1:$P$175,Moteur!$D$1:$D$175,$A43,Moteur!$B$1:$B$175,cad!$P$1) -> 0 | E43: =SUMIFS(Moteur!$R$1:$R$175,Moteur!$D$1:$D$175,$A43,Moteur!$B$1:$B$175,cad!$P$1) -> 0 | F43: =IFERROR(E43/D43,0) -> 0 | G43: =IFERROR(E43/SUM($E$33:$E$46),0) -> 0 | H43: =SUMIFS(_CALC_PNL!$T$1:$T$1347,_CALC_PNL!$A$1:$A$1347,$A43,_CALC_PNL!$D$1:$D$1347,cad!$P$1,_CALC_PNL!$C$1:$C$1347,"2027") -> 0 | I43: =IFERROR(H43/E43,0) -> 0 | J43: =IFERROR(H43/D43,0) -> 0 | K43: =SUMIFS(PIL!$K$15:$K$28,PIL!$A$15:$A$28,$A43)*SUMIFS(PIL!$J$15:$J$28,PIL!$A$15:$A$28,$A43)*(SUM(PIL!$K$15:$K$28)/SUMPRODUCT(PIL!$K$15:$K$28,PIL!$J$15:$J$28)) -> 36612 | L43: =SUMIFS(PIL!$D$15:$D$28,PIL!$A$15:$A$28,$A43) -> 1705
A44: PIGIER_BOR | B44: Pigier | C44: Bordeaux | D44: =SUMIFS(Moteur!$P$1:$P$175,Moteur!$D$1:$D$175,$A44,Moteur!$B$1:$B$175,cad!$P$1) -> 0 | E44: =SUMIFS(Moteur!$R$1:$R$175,Moteur!$D$1:$D$175,$A44,Moteur!$B$1:$B$175,cad!$P$1) -> 0 | F44: =IFERROR(E44/D44,0) -> 0 | G44: =IFERROR(E44/SUM($E$33:$E$46),0) -> 0 | H44: =SUMIFS(_CALC_PNL!$T$1:$T$1347,_CALC_PNL!$A$1:$A$1347,$A44,_CALC_PNL!$D$1:$D$1347,cad!$P$1,_CALC_PNL!$C$1:$C$1347,"2027") -> 0 | I44: =IFERROR(H44/E44,0) -> 0 | J44: =IFERROR(H44/D44,0) -> 0 | K44: =SUMIFS(PIL!$K$15:$K$28,PIL!$A$15:$A$28,$A44)*SUMIFS(PIL!$J$15:$J$28,PIL!$A$15:$A$28,$A44)*(SUM(PIL!$K$15:$K$28)/SUMPRODUCT(PIL!$K$15:$K$28,PIL!$J$15:$J$28)) -> 21968 | L44: =SUMIFS(PIL!$D$15:$D$28,PIL!$A$15:$A$28,$A44) -> 1368
... A46: TUNON_LYO | B46: Tunon | C46: Lyon | D46: =SUMIFS(Moteur!$P$1:$P$175,Moteur!$D$1:$D$175,$A46,Moteur!$B$1:$B$175,cad!$P$1) -> 0 | E46: =SUMIFS(Moteur!$R$1:$R$175,Moteur!$D$1:$D$175,$A46,Moteur!$B$1:$B$175,cad!$P$1) -> 0 | F46: =IFERROR(E46/D46,0) -> 0 | G46: =IFERROR(E46/SUM($E$33:$E$46),0) -> 0 | H46: =SUMIFS(_CALC_PNL!$T$1:$T$1347,_CALC_PNL!$A$1:$A$1347,$A46,_CALC_PNL!$D$1:$D$1347,cad!$P$1,_CALC_PNL!$C$1:$C$1347,"2027") -> 0 | I46: =IFERROR(H46/E46,0) -> 0 | J46: =IFERROR(H46/D46,0) -> 0 | K46: =SUMIFS(PIL!$K$15:$K$28,PIL!$A$15:$A$28,$A46)*SUMIFS(PIL!$J$15:$J$28,PIL!$A$15:$A$28,$A46)*(SUM(PIL!$K$15:$K$28)/SUMPRODUCT(PIL!$K$15:$K$28,PIL!$J$15:$J$28)) -> 18850 | L46: =SUMIFS(PIL!$D$15:$D$28,PIL!$A$15:$A$28,$A46) -> 1625
A47: Sous-total campus | D47: =SUM(D33:D46) -> 0 | E47: =SUM(E33:E46) -> 0 | F47: =IFERROR(E47/D47,0) -> 0 | G47: =SUM(G33:G46) -> 0 | H47: =SUM(H33:H46) -> 0 | I47: =IFERROR(H47/E47,0) -> 0 | J47: =IFERROR(H47/D47,0) -> 0 | K47: =SUM(K33:K46) -> 434174
A48: Siege / holding (GRP) | H48: =SUMIFS(_CALC_PNL!$T$1:$T$1347,_CALC_PNL!$A$1:$A$1347,"GRP",_CALC_PNL!$D$1:$D$1347,cad!$P$1,_CALC_PNL!$C$1:$C$1347,"2027") -> 0
A49: GROUPE 2027 V01 | D49: =D47 -> 0 | E49: =E47 -> 0 | F49: =IFERROR(E49/D49,0) -> 0 | G49: =SUM(G33:G46) -> 0 | H49: =H47+H48 -> 0 | I49: =IFERROR(H49/E49,0) -> 0 | J49: =IFERROR(H49/D49,0) -> 0 | K49: =SUM(K33:K46) -> 434174

Sheet ALLOC
N1: =IF($C$6="Chiffre d'affaires","REV_CA",IF($C$6="Nombre de classes","VOL_CLASS","VOL_EFF")) -> REV_CA
B2: 3 · Allocation222 & RENTABILITE — cout complet du groupe a la classe | N2: =IF($C$7="Chiffre d'affaires","REV_CA",IF($C$7="Nombre de classes","VOL_CLASS","VOL_EFF")) -> REV_CA
N3: =IF($C$8="Chiffre d'affaires","REV_CA",IF($C$8="Nombre de classes","VOL_CLASS","VOL_EFF")) -> VOL_EFF
N4: =IF($C$9="Chiffre d'affaires","REV_CA",IF($C$9="Nombre de classes","VOL_CLASS","VOL_EFF")) -> VOL_CLASS
B5: Cles d'Allocation222 (saisie)
B6: Siège administratif → marque | C6: Chiffre d'affaires
B7: Publicité de marque → marque | C7: Chiffre d'affaires
B8: Marque → campus | C8: Effectif
B9: Campus → classe | C9: Nombre de classes
B14: Maille fine — deplie campus/classe avec les [+]
B17: Marque ▸ Campus ▸ Classe | C17: Effectif | D17: CA | E17: VAC | F17: PERM | G17: ODIR | H17: STRUCT | I17: Frais marque | J17: Holding | K17: Cout complet | L17: Marge complete | M17: Marge %
B18: MBway | C18: =SUMIFS(_CALC_ALLOC!$G$1:$G$349,_CALC_ALLOC!$A$1:$A$349,"2026",_CALC_ALLOC!$C$1:$C$349,"MBWAY") -> #VALUE! | D18: =SUMIFS(_CALC_ALLOC!$I$1:$I$349,_CALC_ALLOC!$A$1:$A$349,"2026",_CALC_ALLOC!$C$1:$C$349,"MBWAY") -> 0 | E18: =SUMIFS(_CALC_ALLOC!$AI$1:$AI$349,_CALC_ALLOC!$A$1:$A$349,"2026",_CALC_ALLOC!$C$1:$C$349,"MBWAY") -> 0 | F18: =SUMIFS(_CALC_ALLOC!$AJ$1:$AJ$349,_CALC_ALLOC!$A$1:$A$349,"2026",_CALC_ALLOC!$C$1:$C$349,"MBWAY") -> 0 | G18: =SUMIFS(_CALC_ALLOC!$AK$1:$AK$349,_CALC_ALLOC!$A$1:$A$349,"2026",_CALC_ALLOC!$C$1:$C$349,"MBWAY") -> 0 | H18: =SUMIFS(_CALC_ALLOC!$AL$1:$AL$349,_CALC_ALLOC!$A$1:$A$349,"2026",_CALC_ALLOC!$C$1:$C$349,"MBWAY") -> 0 | I18: =SUMIFS(_CALC_ALLOC!$AR$1:$AR$349,_CALC_ALLOC!$A$1:$A$349,"2026",_CALC_ALLOC!$C$1:$C$349,"MBWAY") -> 0 | J18: =SUMIFS(_CALC_ALLOC!$AM$1:$AM$349,_CALC_ALLOC!$A$1:$A$349,"2026",_CALC_ALLOC!$C$1:$C$349,"MBWAY") -> 0 | K18: =E18+F18+G18+H18+I18+J18 -> 0 | L18: =SUMIFS(_CALC_ALLOC!$AN$1:$AN$349,_CALC_ALLOC!$A$1:$A$349,"2026",_CALC_ALLOC!$C$1:$C$349,"MBWAY") -> 0 | M18: =IFERROR(L18/D18,0) -> 0
B19: Paris (MBWAY_PAR) | C19: =SUMIFS(_CALC_ALLOC!$G$1:$G$349,_CALC_ALLOC!$A$1:$A$349,"2026",_CALC_ALLOC!$B$1:$B$349,"MBWAY_PAR") -> 0 | D19: =SUMIFS(_CALC_ALLOC!$I$1:$I$349,_CALC_ALLOC!$A$1:$A$349,"2026",_CALC_ALLOC!$B$1:$B$349,"MBWAY_PAR") -> 0 | E19: =SUMIFS(_CALC_ALLOC!$AI$1:$AI$349,_CALC_ALLOC!$A$1:$A$349,"2026",_CALC_ALLOC!$B$1:$B$349,"MBWAY_PAR") -> 0 | F19: =SUMIFS(_CALC_ALLOC!$AJ$1:$AJ$349,_CALC_ALLOC!$A$1:$A$349,"2026",_CALC_ALLOC!$B$1:$B$349,"MBWAY_PAR") -> 0 | G19: =SUMIFS(_CALC_ALLOC!$AK$1:$AK$349,_CALC_ALLOC!$A$1:$A$349,"2026",_CALC_ALLOC!$B$1:$B$349,"MBWAY_PAR") -> 0 | H19: =SUMIFS(_CALC_ALLOC!$AL$1:$AL$349,_CALC_ALLOC!$A$1:$A$349,"2026",_CALC_ALLOC!$B$1:$B$349,"MBWAY_PAR") -> 0 | I19: =SUMIFS(_CALC_ALLOC!$AR$1:$AR$349,_CALC_ALLOC!$A$1:$A$349,"2026",_CALC_ALLOC!$B$1:$B$349,"MBWAY_PAR") -> 0 | J19: =SUMIFS(_CALC_ALLOC!$AM$1:$AM$349,_CALC_ALLOC!$A$1:$A$349,"2026",_CALC_ALLOC!$B$1:$B$349,"MBWAY_PAR") -> 0 | K19: =E19+F19+G19+H19+I19+J19 -> 0 | L19: =SUMIFS(_CALC_ALLOC!$AN$1:$AN$349,_CALC_ALLOC!$A$1:$A$349,"2026",_CALC_ALLOC!$B$1:$B$349,"MBWAY_PAR") -> 0 | M19: =IFERROR(L19/D19,0) -> 0
B20: BAC_MGT B1 INIT | C20: =SUMIFS(_CALC_ALLOC!$G$1:$G$349,_CALC_ALLOC!$A$1:$A$349,"2026",_CALC_ALLOC!$B$1:$B$349,"MBWAY_PAR",_CALC_ALLOC!$D$1:$D$349,"BAC_MGT",_CALC_ALLOC!$E$1:$E$349,"B1",_CALC_ALLOC!$F$1:$F$349,"INIT") -> 0 | D20: =SUMIFS(_CALC_ALLOC!$I$1:$I$349,_CALC_ALLOC!$A$1:$A$349,"2026",_CALC_ALLOC!$B$1:$B$349,"MBWAY_PAR",_CALC_ALLOC!$D$1:$D$349,"BAC_MGT",_CALC_ALLOC!$E$1:$E$349,"B1",_CALC_ALLOC!$F$1:$F$349,"INIT") -> 0 | E20: =SUMIFS(_CALC_ALLOC!$AI$1:$AI$349,_CALC_ALLOC!$A$1:$A$349,"2026",_CALC_ALLOC!$B$1:$B$349,"MBWAY_PAR",_CALC_ALLOC!$D$1:$D$349,"BAC_MGT",_CALC_ALLOC!$E$1:$E$349,"B1",_CALC_ALLOC!$F$1:$F$349,"INIT") -> 0 | F20: =SUMIFS(_CALC_ALLOC!$AJ$1:$AJ$349,_CALC_ALLOC!$A$1:$A$349,"2026",_CALC_ALLOC!$B$1:$B$349,"MBWAY_PAR",_CALC_ALLOC!$D$1:$D$349,"BAC_MGT",_CALC_ALLOC!$E$1:$E$349,"B1",_CALC_ALLOC!$F$1:$F$349,"INIT") -> 0 | G20: =SUMIFS(_CALC_ALLOC!$AK$1:$AK$349,_CALC_ALLOC!$A$1:$A$349,"2026",_CALC_ALLOC!$B$1:$B$349,"MBWAY_PAR",_CALC_ALLOC!$D$1:$D$349,"BAC_MGT",_CALC_ALLOC!$E$1:$E$349,"B1",_CALC_ALLOC!$F$1:$F$349,"INIT") -> 0 | H20: =SUMIFS(_CALC_ALLOC!$AL$1:$AL$349,_CALC_ALLOC!$A$1:$A$349,"2026",_CALC_ALLOC!$B$1:$B$349,"MBWAY_PAR",_CALC_ALLOC!$D$1:$D$349,"BAC_MGT",_CALC_ALLOC!$E$1:$E$349,"B1",_CALC_ALLOC!$F$1:$F$349,"INIT") -> 0 | I20: =SUMIFS(_CALC_ALLOC!$AR$1:$AR$349,_CALC_ALLOC!$A$1:$A$349,"2026",_CALC_ALLOC!$B$1:$B$349,"MBWAY_PAR",_CALC_ALLOC!$D$1:$D$349,"BAC_MGT",_CALC_ALLOC!$E$1:$E$349,"B1",_CALC_ALLOC!$F$1:$F$349,"INIT") -> 0 | J20: =SUMIFS(_CALC_ALLOC!$AM$1:$AM$349,_CALC_ALLOC!$A$1:$A$349,"2026",_CALC_ALLOC!$B$1:$B$349,"MBWAY_PAR",_CALC_ALLOC!$D$1:$D$349,"BAC_MGT",_CALC_ALLOC!$E$1:$E$349,"B1",_CALC_ALLOC!$F$1:$F$349,"INIT") -> 0 | K20: =E20+F20+G20+H20+I20+J20 -> 0 | L20: =SUMIFS(_CALC_ALLOC!$AN$1:$AN$349,_CALC_ALLOC!$A$1:$A$349,"2026",_CALC_ALLOC!$B$1:$B$349,"MBWAY_PAR",_CALC_ALLOC!$D$1:$D$349,"BAC_MGT",_CALC_ALLOC!$E$1:$E$349,"B1",_CALC_ALLOC!$F$1:$F$349,"INIT") -> 0 | M20: =IFERROR(L20/D20,0) -> 0
B21: BAC_MGT B2 ALT | C21: =SUMIFS(_CALC_ALLOC!$G$1:$G$349,_CALC_ALLOC!$A$1:$A$349,"2026",_CALC_ALLOC!$B$1:$B$349,"MBWAY_PAR",_CALC_ALLOC!$D$1:$D$349,"BAC_MGT",_CALC_ALLOC!$E$1:$E$349,"B2",_CALC_ALLOC!$F$1:$F$349,"ALT") -> 0 | D21: =SUMIFS(_CALC_ALLOC!$I$1:$I$349,_CALC_ALLOC!$A$1:$A$349,"2026",_CALC_ALLOC!$B$1:$B$349,"MBWAY_PAR",_CALC_ALLOC!$D$1:$D$349,"BAC_MGT",_CALC_ALLOC!$E$1:$E$349,"B2",_CALC_ALLOC!$F$1:$F$349,"ALT") -> 0 | E21: =SUMIFS(_CALC_ALLOC!$AI$1:$AI$349,_CALC_ALLOC!$A$1:$A$349,"2026",_CALC_ALLOC!$B$1:$B$349,"MBWAY_PAR",_CALC_ALLOC!$D$1:$D$349,"BAC_MGT",_CALC_ALLOC!$E$1:$E$349,"B2",_CALC_ALLOC!$F$1:$F$349,"ALT") -> 0 | F21: =SUMIFS(_CALC_ALLOC!$AJ$1:$AJ$349,_CALC_ALLOC!$A$1:$A$349,"2026",_CALC_ALLOC!$B$1:$B$349,"MBWAY_PAR",_CALC_ALLOC!$D$1:$D$349,"BAC_MGT",_CALC_ALLOC!$E$1:$E$349,"B2",_CALC_ALLOC!$F$1:$F$349,"ALT") -> 0 | G21: =SUMIFS(_CALC_ALLOC!$AK$1:$AK$349,_CALC_ALLOC!$A$1:$A$349,"2026",_CALC_ALLOC!$B$1:$B$349,"MBWAY_PAR",_CALC_ALLOC!$D$1:$D$349,"BAC_MGT",_CALC_ALLOC!$E$1:$E$349,"B2",_CALC_ALLOC!$F$1:$F$349,"ALT") -> 0 | H21: =SUMIFS(_CALC_ALLOC!$AL$1:$AL$349,_CALC_ALLOC!$A$1:$A$349,"2026",_CALC_ALLOC!$B$1:$B$349,"MBWAY_PAR",_CALC_ALLOC!$D$1:$D$349,"BAC_MGT",_CALC_ALLOC!$E$1:$E$349,"B2",_CALC_ALLOC!$F$1:$F$349,"ALT") -> 0 | I21: =SUMIFS(_CALC_ALLOC!$AR$1:$AR$349,_CALC_ALLOC!$A$1:$A$349,"2026",_CALC_ALLOC!$B$1:$B$349,"MBWAY_PAR",_CALC_ALLOC!$D$1:$D$349,"BAC_MGT",_CALC_ALLOC!$E$1:$E$349,"B2",_CALC_ALLOC!$F$1:$F$349,"ALT") -> 0 | J21: =SUMIFS(_CALC_ALLOC!$AM$1:$AM$349,_CALC_ALLOC!$A$1:$A$349,"2026",_CALC_ALLOC!$B$1:$B$349,"MBWAY_PAR",_CALC_ALLOC!$D$1:$D$349,"BAC_MGT",_CALC_ALLOC!$E$1:$E$349,"B2",_CALC_ALLOC!$F$1:$F$349,"ALT") -> 0 | K21: =E21+F21+G21+H21+I21+J21 -> 0 | L21: =SUMIFS(_CALC_ALLOC!$AN$1:$AN$349,_CALC_ALLOC!$A$1:$A$349,"2026",_CALC_ALLOC!$B$1:$B$349,"MBWAY_PAR",_CALC_ALLOC!$D$1:$D$349,"BAC_MGT",_CALC_ALLOC!$E$1:$E$349,"B2",_CALC_ALLOC!$F$1:$F$349,"ALT") -> 0 | M21: =IFERROR(L21/D21,0) -> 0
B22: BAC_MGT B3 ALT | C22: =SUMIFS(_CALC_ALLOC!$G$1:$G$349,_CALC_ALLOC!$A$1:$A$349,"2026",_CALC_ALLOC!$B$1:$B$349,"MBWAY_PAR",_CALC_ALLOC!$D$1:$D$349,"BAC_MGT",_CALC_ALLOC!$E$1:$E$349,"B3",_CALC_ALLOC!$F$1:$F$349,"ALT") -> 0 | D22: =SUMIFS(_CALC_ALLOC!$I$1:$I$349,_CALC_ALLOC!$A$1:$A$349,"2026",_CALC_ALLOC!$B$1:$B$349,"MBWAY_PAR",_CALC_ALLOC!$D$1:$D$349,"BAC_MGT",_CALC_ALLOC!$E$1:$E$349,"B3",_CALC_ALLOC!$F$1:$F$349,"ALT") -> 0 | E22: =SUMIFS(_CALC_ALLOC!$AI$1:$AI$349,_CALC_ALLOC!$A$1:$A$349,"2026",_CALC_ALLOC!$B$1:$B$349,"MBWAY_PAR",_CALC_ALLOC!$D$1:$D$349,"BAC_MGT",_CALC_ALLOC!$E$1:$E$349,"B3",_CALC_ALLOC!$F$1:$F$349,"ALT") -> 0 | F22: =SUMIFS(_CALC_ALLOC!$AJ$1:$AJ$349,_CALC_ALLOC!$A$1:$A$349,"2026",_CALC_ALLOC!$B$1:$B$349,"MBWAY_PAR",_CALC_ALLOC!$D$1:$D$349,"BAC_MGT",_CALC_ALLOC!$E$1:$E$349,"B3",_CALC_ALLOC!$F$1:$F$349,"ALT") -> 0 | G22: =SUMIFS(_CALC_ALLOC!$AK$1:$AK$349,_CALC_ALLOC!$A$1:$A$349,"2026",_CALC_ALLOC!$B$1:$B$349,"MBWAY_PAR",_CALC_ALLOC!$D$1:$D$349,"BAC_MGT",_CALC_ALLOC!$E$1:$E$349,"B3",_CALC_ALLOC!$F$1:$F$349,"ALT") -> 0 | H22: =SUMIFS(_CALC_ALLOC!$AL$1:$AL$349,_CALC_ALLOC!$A$1:$A$349,"2026",_CALC_ALLOC!$B$1:$B$349,"MBWAY_PAR",_CALC_ALLOC!$D$1:$D$349,"BAC_MGT",_CALC_ALLOC!$E$1:$E$349,"B3",_CALC_ALLOC!$F$1:$F$349,"ALT") -> 0 | I22: =SUMIFS(_CALC_ALLOC!$AR$1:$AR$349,_CALC_ALLOC!$A$1:$A$349,"2026",_CALC_ALLOC!$B$1:$B$349,"MBWAY_PAR",_CALC_ALLOC!$D$1:$D$349,"BAC_MGT",_CALC_ALLOC!$E$1:$E$349,"B3",_CALC_ALLOC!$F$1:$F$349,"ALT") -> 0 | J22: =SUMIFS(_CALC_ALLOC!$AM$1:$AM$349,_CALC_ALLOC!$A$1:$A$349,"2026",_CALC_ALLOC!$B$1:$B$349,"MBWAY_PAR",_CALC_ALLOC!$D$1:$D$349,"BAC_MGT",_CALC_ALLOC!$E$1:$E$349,"B3",_CALC_ALLOC!$F$1:$F$349,"ALT") -> 0 | K22: =E22+F22+G22+H22+I22+J22 -> 0 | L22: =SUMIFS(_CALC_ALLOC!$AN$1:$AN$349,_CALC_ALLOC!$A$1:$A$349,"2026",_CALC_ALLOC!$B$1:$B$349,"MBWAY_PAR",_CALC_ALLOC!$D$1:$D$349,"BAC_MGT",_CALC_ALLOC!$E$1:$E$349,"B3",_CALC_ALLOC!$F$1:$F$349,"ALT") -> 0 | M22: =IFERROR(L22/D22,0) -> 0
B23: MAS_MGT M1 ALT | C23: =SUMIFS(_CALC_ALLOC!$G$1:$G$349,_CALC_ALLOC!$A$1:$A$349,"2026",_CALC_ALLOC!$B$1:$B$349,"MBWAY_PAR",_CALC_ALLOC!$D$1:$D$349,"MAS_MGT",_CALC_ALLOC!$E$1:$E$349,"M1",_CALC_ALLOC!$F$1:$F$349,"ALT") -> 0 | D23: =SUMIFS(_CALC_ALLOC!$I$1:$I$349,_CALC_ALLOC!$A$1:$A$349,"2026",_CALC_ALLOC!$B$1:$B$349,"MBWAY_PAR",_CALC_ALLOC!$D$1:$D$349,"MAS_MGT",_CALC_ALLOC!$E$1:$E$349,"M1",_CALC_ALLOC!$F$1:$F$349,"ALT") -> 0 | E23: =SUMIFS(_CALC_ALLOC!$AI$1:$AI$349,_CALC_ALLOC!$A$1:$A$349,"2026",_CALC_ALLOC!$B$1:$B$349,"MBWAY_PAR",_CALC_ALLOC!$D$1:$D$349,"MAS_MGT",_CALC_ALLOC!$E$1:$E$349,"M1",_CALC_ALLOC!$F$1:$F$349,"ALT") -> 0 | F23: =SUMIFS(_CALC_ALLOC!$AJ$1:$AJ$349,_CALC_ALLOC!$A$1:$A$349,"2026",_CALC_ALLOC!$B$1:$B$349,"MBWAY_PAR",_CALC_ALLOC!$D$1:$D$349,"MAS_MGT",_CALC_ALLOC!$E$1:$E$349,"M1",_CALC_ALLOC!$F$1:$F$349,"ALT") -> 0 | G23: =SUMIFS(_CALC_ALLOC!$AK$1:$AK$349,_CALC_ALLOC!$A$1:$A$349,"2026",_CALC_ALLOC!$B$1:$B$349,"MBWAY_PAR",_CALC_ALLOC!$D$1:$D$349,"MAS_MGT",_CALC_ALLOC!$E$1:$E$349,"M1",_CALC_ALLOC!$F$1:$F$349,"ALT") -> 0 | H23: =SUMIFS(_CALC_ALLOC!$AL$1:$AL$349,_CALC_ALLOC!$A$1:$A$349,"2026",_CALC_ALLOC!$B$1:$B$349,"MBWAY_PAR",_CALC_ALLOC!$D$1:$D$349,"MAS_MGT",_CALC_ALLOC!$E$1:$E$349,"M1",_CALC_ALLOC!$F$1:$F$349,"ALT") -> 0 | I23: =SUMIFS(_CALC_ALLOC!$AR$1:$AR$349,_CALC_ALLOC!$A$1:$A$349,"2026",_CALC_ALLOC!$B$1:$B$349,"MBWAY_PAR",_CALC_ALLOC!$D$1:$D$349,"MAS_MGT",_CALC_ALLOC!$E$1:$E$349,"M1",_CALC_ALLOC!$F$1:$F$349,"ALT") -> 0 | J23: =SUMIFS(_CALC_ALLOC!$AM$1:$AM$349,_CALC_ALLOC!$A$1:$A$349,"2026",_CALC_ALLOC!$B$1:$B$349,"MBWAY_PAR",_CALC_ALLOC!$D$1:$D$349,"MAS_MGT",_CALC_ALLOC!$E$1:$E$349,"M1",_CALC_ALLOC!$F$1:$F$349,"ALT") -> 0 | K23: =E23+F23+G23+H23+I23+J23 -> 0 | L23: =SUMIFS(_CALC_ALLOC!$AN$1:$AN$349,_CALC_ALLOC!$A$1:$A$349,"2026",_CALC_ALLOC!$B$1:$B$349,"MBWAY_PAR",_CALC_ALLOC!$D$1:$D$349,"MAS_MGT",_CALC_ALLOC!$E$1:$E$349,"M1",_CALC_ALLOC!$F$1:$F$349,"ALT") -> 0 | M23: =IFERROR(L23/D23,0) -> 0
B24: MAS_MGT M2 ALT | C24: =SUMIFS(_CALC_ALLOC!$G$1:$G$349,_CALC_ALLOC!$A$1:$A$349,"2026",_CALC_ALLOC!$B$1:$B$349,"MBWAY_PAR",_CALC_ALLOC!$D$1:$D$349,"MAS_MGT",_CALC_ALLOC!$E$1:$E$349,"M2",_CALC_ALLOC!$F$1:$F$349,"ALT") -> 0 | D24: =SUMIFS(_CALC_ALLOC!$I$1:$I$349,_CALC_ALLOC!$A$1:$A$349,"2026",_CALC_ALLOC!$B$1:$B$349,"MBWAY_PAR",_CALC_ALLOC!$D$1:$D$349,"MAS_MGT",_CALC_ALLOC!$E$1:$E$349,"M2",_CALC_ALLOC!$F$1:$F$349,"ALT") -> 0 | E24: =SUMIFS(_CALC_ALLOC!$AI$1:$AI$349,_CALC_ALLOC!$A$1:$A$349,"2026",_CALC_ALLOC!$B$1:$B$349,"MBWAY_PAR",_CALC_ALLOC!$D$1:$D$349,"MAS_MGT",_CALC_ALLOC!$E$1:$E$349,"M2",_CALC_ALLOC!$F$1:$F$349,"ALT") -> 0 | F24: =SUMIFS(_CALC_ALLOC!$AJ$1:$AJ$349,_CALC_ALLOC!$A$1:$A$349,"2026",_CALC_ALLOC!$B$1:$B$349,"MBWAY_PAR",_CALC_ALLOC!$D$1:$D$349,"MAS_MGT",_CALC_ALLOC!$E$1:$E$349,"M2",_CALC_ALLOC!$F$1:$F$349,"ALT") -> 0 | G24: =SUMIFS(_CALC_ALLOC!$AK$1:$AK$349,_CALC_ALLOC!$A$1:$A$349,"2026",_CALC_ALLOC!$B$1:$B$349,"MBWAY_PAR",_CALC_ALLOC!$D$1:$D$349,"MAS_MGT",_CALC_ALLOC!$E$1:$E$349,"M2",_CALC_ALLOC!$F$1:$F$349,"ALT") -> 0 | H24: =SUMIFS(_CALC_ALLOC!$AL$1:$AL$349,_CALC_ALLOC!$A$1:$A$349,"2026",_CALC_ALLOC!$B$1:$B$349,"MBWAY_PAR",_CALC_ALLOC!$D$1:$D$349,"MAS_MGT",_CALC_ALLOC!$E$1:$E$349,"M2",_CALC_ALLOC!$F$1:$F$349,"ALT") -> 0 | I24: =SUMIFS(_CALC_ALLOC!$AR$1:$AR$349,_CALC_ALLOC!$A$1:$A$349,"2026",_CALC_ALLOC!$B$1:$B$349,"MBWAY_PAR",_CALC_ALLOC!$D$1:$D$349,"MAS_MGT",_CALC_ALLOC!$E$1:$E$349,"M2",_CALC_ALLOC!$F$1:$F$349,"ALT") -> 0 | J24: =SUMIFS(_CALC_ALLOC!$AM$1:$AM$349,_CALC_ALLOC!$A$1:$A$349,"2026",_CALC_ALLOC!$B$1:$B$349,"MBWAY_PAR",_CALC_ALLOC!$D$1:$D$349,"MAS_MGT",_CALC_ALLOC!$E$1:$E$349,"M2",_CALC_ALLOC!$F$1:$F$349,"ALT") -> 0 | K24: =E24+F24+G24+H24+I24+J24 -> 0 | L24: =SUMIFS(_CALC_ALLOC!$AN$1:$AN$349,_CALC_ALLOC!$A$1:$A$349,"2026",_CALC_ALLOC!$B$1:$B$349,"MBWAY_PAR",_CALC_ALLOC!$D$1:$D$349,"MAS_MGT",_CALC_ALLOC!$E$1:$E$349,"M2",_CALC_ALLOC!$F$1:$F$349,"ALT") -> 0 | M24: =IFERROR(L24/D24,0) -> 0
B25: Lyon (MBWAY_LYO) | C25: =SUMIFS(_CALC_ALLOC!$G$1:$G$349,_CALC_ALLOC!$A$1:$A$349,"2026",_CALC_ALLOC!$B$1:$B$349,"MBWAY_LYO") -> 0 | D25: =SUMIFS(_CALC_ALLOC!$I$1:$I$349,_CALC_ALLOC!$A$1:$A$349,"2026",_CALC_ALLOC!$B$1:$B$349,"MBWAY_LYO") -> 0 | E25: =SUMIFS(_CALC_ALLOC!$AI$1:$AI$349,_CALC_ALLOC!$A$1:$A$349,"2026",_CALC_ALLOC!$B$1:$B$349,"MBWAY_LYO") -> 0 | F25: =SUMIFS(_CALC_ALLOC!$AJ$1:$AJ$349,_CALC_ALLOC!$A$1:$A$349,"2026",_CALC_ALLOC!$B$1:$B$349,"MBWAY_LYO") -> 0 | G25: =SUMIFS(_CALC_ALLOC!$AK$1:$AK$349,_CALC_ALLOC!$A$1:$A$349,"2026",_CALC_ALLOC!$B$1:$B$349,"MBWAY_LYO") -> 0 | H25: =SUMIFS(_CALC_ALLOC!$AL$1:$AL$349,_CALC_ALLOC!$A$1:$A$349,"2026",_CALC_ALLOC!$B$1:$B$349,"MBWAY_LYO") -> 0 | I25: =SUMIFS(_CALC_ALLOC!$AR$1:$AR$349,_CALC_ALLOC!$A$1:$A$349,"2026",_CALC_ALLOC!$B$1:$B$349,"MBWAY_LYO") -> 0 | J25: =SUMIFS(_CALC_ALLOC!$AM$1:$AM$349,_CALC_ALLOC!$A$1:$A$349,"2026",_CALC_ALLOC!$B$1:$B$349,"MBWAY_LYO") -> 0 | K25: =E25+F25+G25+H25+I25+J25 -> 0 | L25: =SUMIFS(_CALC_ALLOC!$AN$1:$AN$349,_CALC_ALLOC!$A$1:$A$349,"2026",_CALC_ALLOC!$B$1:$B$349,"MBWAY_LYO") -> 0 | M25: =IFERROR(L25/D25,0) -> 0
B26: BAC_MGT B1 INIT | C26: =SUMIFS(_CALC_ALLOC!$G$1:$G$349,_CALC_ALLOC!$A$1:$A$349,"2026",_CALC_ALLOC!$B$1:$B$349,"MBWAY_LYO",_CALC_ALLOC!$D$1:$D$349,"BAC_MGT",_CALC_ALLOC!$E$1:$E$349,"B1",_CALC_ALLOC!$F$1:$F$349,"INIT") -> 0 | D26: =SUMIFS(_CALC_ALLOC!$I$1:$I$349,_CALC_ALLOC!$A$1:$A$349,"2026",_CALC_ALLOC!$B$1:$B$349,"MBWAY_LYO",_CALC_ALLOC!$D$1:$D$349,"BAC_MGT",_CALC_ALLOC!$E$1:$E$349,"B1",_CALC_ALLOC!$F$1:$F$349,"INIT") -> 0 | E26: =SUMIFS(_CALC_ALLOC!$AI$1:$AI$349,_CALC_ALLOC!$A$1:$A$349,"2026",_CALC_ALLOC!$B$1:$B$349,"MBWAY_LYO",_CALC_ALLOC!$D$1:$D$349,"BAC_MGT",_CALC_ALLOC!$E$1:$E$349,"B1",_CALC_ALLOC!$F$1:$F$349,"INIT") -> 0 | F26: =SUMIFS(_CALC_ALLOC!$AJ$1:$AJ$349,_CALC_ALLOC!$A$1:$A$349,"2026",_CALC_ALLOC!$B$1:$B$349,"MBWAY_LYO",_CALC_ALLOC!$D$1:$D$349,"BAC_MGT",_CALC_ALLOC!$E$1:$E$349,"B1",_CALC_ALLOC!$F$1:$F$349,"INIT") -> 0 | G26: =SUMIFS(_CALC_ALLOC!$AK$1:$AK$349,_CALC_ALLOC!$A$1:$A$349,"2026",_CALC_ALLOC!$B$1:$B$349,"MBWAY_LYO",_CALC_ALLOC!$D$1:$D$349,"BAC_MGT",_CALC_ALLOC!$E$1:$E$349,"B1",_CALC_ALLOC!$F$1:$F$349,"INIT") -> 0 | H26: =SUMIFS(_CALC_ALLOC!$AL$1:$AL$349,_CALC_ALLOC!$A$1:$A$349,"2026",_CALC_ALLOC!$B$1:$B$349,"MBWAY_LYO",_CALC_ALLOC!$D$1:$D$349,"BAC_MGT",_CALC_ALLOC!$E$1:$E$349,"B1",_CALC_ALLOC!$F$1:$F$349,"INIT") -> 0 | I26: =SUMIFS(_CALC_ALLOC!$AR$1:$AR$349,_CALC_ALLOC!$A$1:$A$349,"2026",_CALC_ALLOC!$B$1:$B$349,"MBWAY_LYO",_CALC_ALLOC!$D$1:$D$349,"BAC_MGT",_CALC_ALLOC!$E$1:$E$349,"B1",_CALC_ALLOC!$F$1:$F$349,"INIT") -> 0 | J26: =SUMIFS(_CALC_ALLOC!$AM$1:$AM$349,_CALC_ALLOC!$A$1:$A$349,"2026",_CALC_ALLOC!$B$1:$B$349,"MBWAY_LYO",_CALC_ALLOC!$D$1:$D$349,"BAC_MGT",_CALC_ALLOC!$E$1:$E$349,"B1",_CALC_ALLOC!$F$1:$F$349,"INIT") -> 0 | K26: =E26+F26+G26+H26+I26+J26 -> 0 | L26: =SUMIFS(_CALC_ALLOC!$AN$1:$AN$349,_CALC_ALLOC!$A$1:$A$349,"2026",_CALC_ALLOC!$B$1:$B$349,"MBWAY_LYO",_CALC_ALLOC!$D$1:$D$349,"BAC_MGT",_CALC_ALLOC!$E$1:$E$349,"B1",_CALC_ALLOC!$F$1:$F$349,"INIT") -> 0 | M26: =IFERROR(L26/D26,0) -> 0
B27: BAC_MGT B2 ALT | C27: =SUMIFS(_CALC_ALLOC!$G$1:$G$349,_CALC_ALLOC!$A$1:$A$349,"2026",_CALC_ALLOC!$B$1:$B$349,"MBWAY_LYO",_CALC_ALLOC!$D$1:$D$349,"BAC_MGT",_CALC_ALLOC!$E$1:$E$349,"B2",_CALC_ALLOC!$F$1:$F$349,"ALT") -> 0 | D27: =SUMIFS(_CALC_ALLOC!$I$1:$I$349,_CALC_ALLOC!$A$1:$A$349,"2026",_CALC_ALLOC!$B$1:$B$349,"MBWAY_LYO",_CALC_ALLOC!$D$1:$D$349,"BAC_MGT",_CALC_ALLOC!$E$1:$E$349,"B2",_CALC_ALLOC!$F$1:$F$349,"ALT") -> 0 | E27: =SUMIFS(_CALC_ALLOC!$AI$1:$AI$349,_CALC_ALLOC!$A$1:$A$349,"2026",_CALC_ALLOC!$B$1:$B$349,"MBWAY_LYO",_CALC_ALLOC!$D$1:$D$349,"BAC_MGT",_CALC_ALLOC!$E$1:$E$349,"B2",_CALC_ALLOC!$F$1:$F$349,"ALT") -> 0 | F27: =SUMIFS(_CALC_ALLOC!$AJ$1:$AJ$349,_CALC_ALLOC!$A$1:$A$349,"2026",_CALC_ALLOC!$B$1:$B$349,"MBWAY_LYO",_CALC_ALLOC!$D$1:$D$349,"BAC_MGT",_CALC_ALLOC!$E$1:$E$349,"B2",_CALC_ALLOC!$F$1:$F$349,"ALT") -> 0 | G27: =SUMIFS(_CALC_ALLOC!$AK$1:$AK$349,_CALC_ALLOC!$A$1:$A$349,"2026",_CALC_ALLOC!$B$1:$B$349,"MBWAY_LYO",_CALC_ALLOC!$D$1:$D$349,"BAC_MGT",_CALC_ALLOC!$E$1:$E$349,"B2",_CALC_ALLOC!$F$1:$F$349,"ALT") -> 0 | H27: =SUMIFS(_CALC_ALLOC!$AL$1:$AL$349,_CALC_ALLOC!$A$1:$A$349,"2026",_CALC_ALLOC!$B$1:$B$349,"MBWAY_LYO",_CALC_ALLOC!$D$1:$D$349,"BAC_MGT",_CALC_ALLOC!$E$1:$E$349,"B2",_CALC_ALLOC!$F$1:$F$349,"ALT") -> 0 | I27: =SUMIFS(_CALC_ALLOC!$AR$1:$AR$349,_CALC_ALLOC!$A$1:$A$349,"2026",_CALC_ALLOC!$B$1:$B$349,"MBWAY_LYO",_CALC_ALLOC!$D$1:$D$349,"BAC_MGT",_CALC_ALLOC!$E$1:$E$349,"B2",_CALC_ALLOC!$F$1:$F$349,"ALT") -> 0 | J27: =SUMIFS(_CALC_ALLOC!$AM$1:$AM$349,_CALC_ALLOC!$A$1:$A$349,"2026",_CALC_ALLOC!$B$1:$B$349,"MBWAY_LYO",_CALC_ALLOC!$D$1:$D$349,"BAC_MGT",_CALC_ALLOC!$E$1:$E$349,"B2",_CALC_ALLOC!$F$1:$F$349,"ALT") -> 0 | K27: =E27+F27+G27+H27+I27+J27 -> 0 | L27: =SUMIFS(_CALC_ALLOC!$AN$1:$AN$349,_CALC_ALLOC!$A$1:$A$349,"2026",_CALC_ALLOC!$B$1:$B$349,"MBWAY_LYO",_CALC_ALLOC!$D$1:$D$349,"BAC_MGT",_CALC_ALLOC!$E$1:$E$349,"B2",_CALC_ALLOC!$F$1:$F$349,"ALT") -> 0 | M27: =IFERROR(L27/D27,0) -> 0
B28: BAC_MGT B3 ALT | C28: =SUMIFS(_CALC_ALLOC!$G$1:$G$349,_CALC_ALLOC!$A$1:$A$349,"2026",_CALC_ALLOC!$B$1:$B$349,"MBWAY_LYO",_CALC_ALLOC!$D$1:$D$349,"BAC_MGT",_CALC_ALLOC!$E$1:$E$349,"B3",_CALC_ALLOC!$F$1:$F$349,"ALT") -> 0 | D28: =SUMIFS(_CALC_ALLOC!$I$1:$I$349,_CALC_ALLOC!$A$1:$A$349,"2026",_CALC_ALLOC!$B$1:$B$349,"MBWAY_LYO",_CALC_ALLOC!$D$1:$D$349,"BAC_MGT",_CALC_ALLOC!$E$1:$E$349,"B3",_CALC_ALLOC!$F$1:$F$349,"ALT") -> 0 | E28: =SUMIFS(_CALC_ALLOC!$AI$1:$AI$349,_CALC_ALLOC!$A$1:$A$349,"2026",_CALC_ALLOC!$B$1:$B$349,"MBWAY_LYO",_CALC_ALLOC!$D$1:$D$349,"BAC_MGT",_CALC_ALLOC!$E$1:$E$349,"B3",_CALC_ALLOC!$F$1:$F$349,"ALT") -> 0 | F28: =SUMIFS(_CALC_ALLOC!$AJ$1:$AJ$349,_CALC_ALLOC!$A$1:$A$349,"2026",_CALC_ALLOC!$B$1:$B$349,"MBWAY_LYO",_CALC_ALLOC!$D$1:$D$349,"BAC_MGT",_CALC_ALLOC!$E$1:$E$349,"B3",_CALC_ALLOC!$F$1:$F$349,"ALT") -> 0 | G28: =SUMIFS(_CALC_ALLOC!$AK$1:$AK$349,_CALC_ALLOC!$A$1:$A$349,"2026",_CALC_ALLOC!$B$1:$B$349,"MBWAY_LYO",_CALC_ALLOC!$D$1:$D$349,"BAC_MGT",_CALC_ALLOC!$E$1:$E$349,"B3",_CALC_ALLOC!$F$1:$F$349,"ALT") -> 0 | H28: =SUMIFS(_CALC_ALLOC!$AL$1:$AL$349,_CALC_ALLOC!$A$1:$A$349,"2026",_CALC_ALLOC!$B$1:$B$349,"MBWAY_LYO",_CALC_ALLOC!$D$1:$D$349,"BAC_MGT",_CALC_ALLOC!$E$1:$E$349,"B3",_CALC_ALLOC!$F$1:$F$349,"ALT") -> 0 | I28: =SUMIFS(_CALC_ALLOC!$AR$1:$AR$349,_CALC_ALLOC!$A$1:$A$349,"2026",_CALC_ALLOC!$B$1:$B$349,"MBWAY_LYO",_CALC_ALLOC!$D$1:$D$349,"BAC_MGT",_CALC_ALLOC!$E$1:$E$349,"B3",_CALC_ALLOC!$F$1:$F$349,"ALT") -> 0 | J28: =SUMIFS(_CALC_ALLOC!$AM$1:$AM$349,_CALC_ALLOC!$A$1:$A$349,"2026",_CALC_ALLOC!$B$1:$B$349,"MBWAY_LYO",_CALC_ALLOC!$D$1:$D$349,"BAC_MGT",_CALC_ALLOC!$E$1:$E$349,"B3",_CALC_ALLOC!$F$1:$F$349,"ALT") -> 0 | K28: =E28+F28+G28+H28+I28+J28 -> 0 | L28: =SUMIFS(_CALC_ALLOC!$AN$1:$AN$349,_CALC_ALLOC!$A$1:$A$349,"2026",_CALC_ALLOC!$B$1:$B$349,"MBWAY_LYO",_CALC_ALLOC!$D$1:$D$349,"BAC_MGT",_CALC_ALLOC!$E$1:$E$349,"B3",_CALC_ALLOC!$F$1:$F$349,"ALT") -> 0 | M28: =IFERROR(L28/D28,0) -> 0
B29: MAS_MGT M1 ALT | C29: =SUMIFS(_CALC_ALLOC!$G$1:$G$349,_CALC_ALLOC!$A$1:$A$349,"2026",_CALC_ALLOC!$B$1:$B$349,"MBWAY_LYO",_CALC_ALLOC!$D$1:$D$349,"MAS_MGT",_CALC_ALLOC!$E$1:$E$349,"M1",_CALC_ALLOC!$F$1:$F$349,"ALT") -> 0 | D29: =SUMIFS(_CALC_ALLOC!$I$1:$I$349,_CALC_ALLOC!$A$1:$A$349,"2026",_CALC_ALLOC!$B$1:$B$349,"MBWAY_LYO",_CALC_ALLOC!$D$1:$D$349,"MAS_MGT",_CALC_ALLOC!$E$1:$E$349,"M1",_CALC_ALLOC!$F$1:$F$349,"ALT") -> 0 | E29: =SUMIFS(_CALC_ALLOC!$AI$1:$AI$349,_CALC_ALLOC!$A$1:$A$349,"2026",_CALC_ALLOC!$B$1:$B$349,"MBWAY_LYO",_CALC_ALLOC!$D$1:$D$349,"MAS_MGT",_CALC_ALLOC!$E$1:$E$349,"M1",_CALC_ALLOC!$F$1:$F$349,"ALT") -> 0 | F29: =SUMIFS(_CALC_ALLOC!$AJ$1:$AJ$349,_CALC_ALLOC!$A$1:$A$349,"2026",_CALC_ALLOC!$B$1:$B$349,"MBWAY_LYO",_CALC_ALLOC!$D$1:$D$349,"MAS_MGT",_CALC_ALLOC!$E$1:$E$349,"M1",_CALC_ALLOC!$F$1:$F$349,"ALT") -> 0 | G29: =SUMIFS(_CALC_ALLOC!$AK$1:$AK$349,_CALC_ALLOC!$A$1:$A$349,"2026",_CALC_ALLOC!$B$1:$B$349,"MBWAY_LYO",_CALC_ALLOC!$D$1:$D$349,"MAS_MGT",_CALC_ALLOC!$E$1:$E$349,"M1",_CALC_ALLOC!$F$1:$F$349,"ALT") -> 0 | H29: =SUMIFS(_CALC_ALLOC!$AL$1:$AL$349,_CALC_ALLOC!$A$1:$A$349,"2026",_CALC_ALLOC!$B$1:$B$349,"MBWAY_LYO",_CALC_ALLOC!$D$1:$D$349,"MAS_MGT",_CALC_ALLOC!$E$1:$E$349,"M1",_CALC_ALLOC!$F$1:$F$349,"ALT") -> 0 | I29: =SUMIFS(_CALC_ALLOC!$AR$1:$AR$349,_CALC_ALLOC!$A$1:$A$349,"2026",_CALC_ALLOC!$B$1:$B$349,"MBWAY_LYO",_CALC_ALLOC!$D$1:$D$349,"MAS_MGT",_CALC_ALLOC!$E$1:$E$349,"M1",_CALC_ALLOC!$F$1:$F$349,"ALT") -> 0 | J29: =SUMIFS(_CALC_ALLOC!$AM$1:$AM$349,_CALC_ALLOC!$A$1:$A$349,"2026",_CALC_ALLOC!$B$1:$B$349,"MBWAY_LYO",_CALC_ALLOC!$D$1:$D$349,"MAS_MGT",_CALC_ALLOC!$E$1:$E$349,"M1",_CALC_ALLOC!$F$1:$F$349,"ALT") -> 0 | K29: =E29+F29+G29+H29+I29+J29 -> 0 | L29: =SUMIFS(_CALC_ALLOC!$AN$1:$AN$349,_CALC_ALLOC!$A$1:$A$349,"2026",_CALC_ALLOC!$B$1:$B$349,"MBWAY_LYO",_CALC_ALLOC!$D$1:$D$349,"MAS_MGT",_CALC_ALLOC!$E$1:$E$349,"M1",_CALC_ALLOC!$F$1:$F$349,"ALT") -> 0 | M29: =IFERROR(L29/D29,0) -> 0
B30: MAS_MGT M2 ALT | C30: =SUMIFS(_CALC_ALLOC!$G$1:$G$349,_CALC_ALLOC!$A$1:$A$349,"2026",_CALC_ALLOC!$B$1:$B$349,"MBWAY_LYO",_CALC_ALLOC!$D$1:$D$349,"MAS_MGT",_CALC_ALLOC!$E$1:$E$349,"M2",_CALC_ALLOC!$F$1:$F$349,"ALT") -> 0 | D30: =SUMIFS(_CALC_ALLOC!$I$1:$I$349,_CALC_ALLOC!$A$1:$A$349,"2026",_CALC_ALLOC!$B$1:$B$349,"MBWAY_LYO",_CALC_ALLOC!$D$1:$D$349,"MAS_MGT",_CALC_ALLOC!$E$1:$E$349,"M2",_CALC_ALLOC!$F$1:$F$349,"ALT") -> 0 | E30: =SUMIFS(_CALC_ALLOC!$AI$1:$AI$349,_CALC_ALLOC!$A$1:$A$349,"2026",_CALC_ALLOC!$B$1:$B$349,"MBWAY_LYO",_CALC_ALLOC!$D$1:$D$349,"MAS_MGT",_CALC_ALLOC!$E$1:$E$349,"M2",_CALC_ALLOC!$F$1:$F$349,"ALT") -> 0 | F30: =SUMIFS(_CALC_ALLOC!$AJ$1:$AJ$349,_CALC_ALLOC!$A$1:$A$349,"2026",_CALC_ALLOC!$B$1:$B$349,"MBWAY_LYO",_CALC_ALLOC!$D$1:$D$349,"MAS_MGT",_CALC_ALLOC!$E$1:$E$349,"M2",_CALC_ALLOC!$F$1:$F$349,"ALT") -> 0 | G30: =SUMIFS(_CALC_ALLOC!$AK$1:$AK$349,_CALC_ALLOC!$A$1:$A$349,"2026",_CALC_ALLOC!$B$1:$B$349,"MBWAY_LYO",_CALC_ALLOC!$D$1:$D$349,"MAS_MGT",_CALC_ALLOC!$E$1:$E$349,"M2",_CALC_ALLOC!$F$1:$F$349,"ALT") -> 0 | H30: =SUMIFS(_CALC_ALLOC!$AL$1:$AL$349,_CALC_ALLOC!$A$1:$A$349,"2026",_CALC_ALLOC!$B$1:$B$349,"MBWAY_LYO",_CALC_ALLOC!$D$1:$D$349,"MAS_MGT",_CALC_ALLOC!$E$1:$E$349,"M2",_CALC_ALLOC!$F$1:$F$349,"ALT") -> 0 | I30: =SUMIFS(_CALC_ALLOC!$AR$1:$AR$349,_CALC_ALLOC!$A$1:$A$349,"2026",_CALC_ALLOC!$B$1:$B$349,"MBWAY_LYO",_CALC_ALLOC!$D$1:$D$349,"MAS_MGT",_CALC_ALLOC!$E$1:$E$349,"M2",_CALC_ALLOC!$F$1:$F$349,"ALT") -> 0 | J30: =SUMIFS(_CALC_ALLOC!$AM$1:$AM$349,_CALC_ALLOC!$A$1:$A$349,"2026",_CALC_ALLOC!$B$1:$B$349,"MBWAY_LYO",_CALC_ALLOC!$D$1:$D$349,"MAS_MGT",_CALC_ALLOC!$E$1:$E$349,"M2",_CALC_ALLOC!$F$1:$F$349,"ALT") -> 0 | K30: =E30+F30+G30+H30+I30+J30 -> 0 | L30: =SUMIFS(_CALC_ALLOC!$AN$1:$AN$349,_CALC_ALLOC!$A$1:$A$349,"2026",_CALC_ALLOC!$B$1:$B$349,"MBWAY_LYO",_CALC_ALLOC!$D$1:$D$349,"MAS_MGT",_CALC_ALLOC!$E$1:$E$349,"M2",_CALC_ALLOC!$F$1:$F$349,"ALT") -> 0 | M30: =IFERROR(L30/D30,0) -> 0
B31: Nantes (MBWAY_NAN) | C31: =SUMIFS(_CALC_ALLOC!$G$1:$G$349,_CALC_ALLOC!$A$1:$A$349,"2026",_CALC_ALLOC!$B$1:$B$349,"MBWAY_NAN") -> 0 | D31: =SUMIFS(_CALC_ALLOC!$I$1:$I$349,_CALC_ALLOC!$A$1:$A$349,"2026",_CALC_ALLOC!$B$1:$B$349,"MBWAY_NAN") -> 0 | E31: =SUMIFS(_CALC_ALLOC!$AI$1:$AI$349,_CALC_ALLOC!$A$1:$A$349,"2026",_CALC_ALLOC!$B$1:$B$349,"MBWAY_NAN") -> 0 | F31: =SUMIFS(_CALC_ALLOC!$AJ$1:$AJ$349,_CALC_ALLOC!$A$1:$A$349,"2026",_CALC_ALLOC!$B$1:$B$349,"MBWAY_NAN") -> 0 | G31: =SUMIFS(_CALC_ALLOC!$AK$1:$AK$349,_CALC_ALLOC!$A$1:$A$349,"2026",_CALC_ALLOC!$B$1:$B$349,"MBWAY_NAN") -> 0 | H31: =SUMIFS(_CALC_ALLOC!$AL$1:$AL$349,_CALC_ALLOC!$A$1:$A$349,"2026",_CALC_ALLOC!$B$1:$B$349,"MBWAY_NAN") -> 0 | I31: =SUMIFS(_CALC_ALLOC!$AR$1:$AR$349,_CALC_ALLOC!$A$1:$A$349,"2026",_CALC_ALLOC!$B$1:$B$349,"MBWAY_NAN") -> 0 | J31: =SUMIFS(_CALC_ALLOC!$AM$1:$AM$349,_CALC_ALLOC!$A$1:$A$349,"2026",_CALC_ALLOC!$B$1:$B$349,"MBWAY_NAN") -> 0 | K31: =E31+F31+G31+H31+I31+J31 -> 0 | L31: =SUMIFS(_CALC_ALLOC!$AN$1:$AN$349,_CALC_ALLOC!$A$1:$A$349,"2026",_CALC_ALLOC!$B$1:$B$349,"MBWAY_NAN") -> 0 | M31: =IFERROR(L31/D31,0) -> 0
B32: BAC_MGT B1 INIT | C32: =SUMIFS(_CALC_ALLOC!$G$1:$G$349,_CALC_ALLOC!$A$1:$A$349,"2026",_CALC_ALLOC!$B$1:$B$349,"MBWAY_NAN",_CALC_ALLOC!$D$1:$D$349,"BAC_MGT",_CALC_ALLOC!$E$1:$E$349,"B1",_CALC_ALLOC!$F$1:$F$349,"INIT") -> 0 | D32: =SUMIFS(_CALC_ALLOC!$I$1:$I$349,_CALC_ALLOC!$A$1:$A$349,"2026",_CALC_ALLOC!$B$1:$B$349,"MBWAY_NAN",_CALC_ALLOC!$D$1:$D$349,"BAC_MGT",_CALC_ALLOC!$E$1:$E$349,"B1",_CALC_ALLOC!$F$1:$F$349,"INIT") -> 0 | E32: =SUMIFS(_CALC_ALLOC!$AI$1:$AI$349,_CALC_ALLOC!$A$1:$A$349,"2026",_CALC_ALLOC!$B$1:$B$349,"MBWAY_NAN",_CALC_ALLOC!$D$1:$D$349,"BAC_MGT",_CALC_ALLOC!$E$1:$E$349,"B1",_CALC_ALLOC!$F$1:$F$349,"INIT") -> 0 | F32: =SUMIFS(_CALC_ALLOC!$AJ$1:$AJ$349,_CALC_ALLOC!$A$1:$A$349,"2026",_CALC_ALLOC!$B$1:$B$349,"MBWAY_NAN",_CALC_ALLOC!$D$1:$D$349,"BAC_MGT",_CALC_ALLOC!$E$1:$E$349,"B1",_CALC_ALLOC!$F$1:$F$349,"INIT") -> 0 | G32: =SUMIFS(_CALC_ALLOC!$AK$1:$AK$349,_CALC_ALLOC!$A$1:$A$349,"2026",_CALC_ALLOC!$B$1:$B$349,"MBWAY_NAN",_CALC_ALLOC!$D$1:$D$349,"BAC_MGT",_CALC_ALLOC!$E$1:$E$349,"B1",_CALC_ALLOC!$F$1:$F$349,"INIT") -> 0 | H32: =SUMIFS(_CALC_ALLOC!$AL$1:$AL$349,_CALC_ALLOC!$A$1:$A$349,"2026",_CALC_ALLOC!$B$1:$B$349,"MBWAY_NAN",_CALC_ALLOC!$D$1:$D$349,"BAC_MGT",_CALC_ALLOC!$E$1:$E$349,"B1",_CALC_ALLOC!$F$1:$F$349,"INIT") -> 0 | I32: =SUMIFS(_CALC_ALLOC!$AR$1:$AR$349,_CALC_ALLOC!$A$1:$A$349,"2026",_CALC_ALLOC!$B$1:$B$349,"MBWAY_NAN",_CALC_ALLOC!$D$1:$D$349,"BAC_MGT",_CALC_ALLOC!$E$1:$E$349,"B1",_CALC_ALLOC!$F$1:$F$349,"INIT") -> 0 | J32: =SUMIFS(_CALC_ALLOC!$AM$1:$AM$349,_CALC_ALLOC!$A$1:$A$349,"2026",_CALC_ALLOC!$B$1:$B$349,"MBWAY_NAN",_CALC_ALLOC!$D$1:$D$349,"BAC_MGT",_CALC_ALLOC!$E$1:$E$349,"B1",_CALC_ALLOC!$F$1:$F$349,"INIT") -> 0 | K32: =E32+F32+G32+H32+I32+J32 -> 0 | L32: =SUMIFS(_CALC_ALLOC!$AN$1:$AN$349,_CALC_ALLOC!$A$1:$A$349,"2026",_CALC_ALLOC!$B$1:$B$349,"MBWAY_NAN",_CALC_ALLOC!$D$1:$D$349,"BAC_MGT",_CALC_ALLOC!$E$1:$E$349,"B1",_CALC_ALLOC!$F$1:$F$349,"INIT") -> 0 | M32: =IFERROR(L32/D32,0) -> 0
B33: BAC_MGT B2 ALT | C33: =SUMIFS(_CALC_ALLOC!$G$1:$G$349,_CALC_ALLOC!$A$1:$A$349,"2026",_CALC_ALLOC!$B$1:$B$349,"MBWAY_NAN",_CALC_ALLOC!$D$1:$D$349,"BAC_MGT",_CALC_ALLOC!$E$1:$E$349,"B2",_CALC_ALLOC!$F$1:$F$349,"ALT") -> 0 | D33: =SUMIFS(_CALC_ALLOC!$I$1:$I$349,_CALC_ALLOC!$A$1:$A$349,"2026",_CALC_ALLOC!$B$1:$B$349,"MBWAY_NAN",_CALC_ALLOC!$D$1:$D$349,"BAC_MGT",_CALC_ALLOC!$E$1:$E$349,"B2",_CALC_ALLOC!$F$1:$F$349,"ALT") -> 0 | E33: =SUMIFS(_CALC_ALLOC!$AI$1:$AI$349,_CALC_ALLOC!$A$1:$A$349,"2026",_CALC_ALLOC!$B$1:$B$349,"MBWAY_NAN",_CALC_ALLOC!$D$1:$D$349,"BAC_MGT",_CALC_ALLOC!$E$1:$E$349,"B2",_CALC_ALLOC!$F$1:$F$349,"ALT") -> 0 | F33: =SUMIFS(_CALC_ALLOC!$AJ$1:$AJ$349,_CALC_ALLOC!$A$1:$A$349,"2026",_CALC_ALLOC!$B$1:$B$349,"MBWAY_NAN",_CALC_ALLOC!$D$1:$D$349,"BAC_MGT",_CALC_ALLOC!$E$1:$E$349,"B2",_CALC_ALLOC!$F$1:$F$349,"ALT") -> 0 | G33: =SUMIFS(_CALC_ALLOC!$AK$1:$AK$349,_CALC_ALLOC!$A$1:$A$349,"2026",_CALC_ALLOC!$B$1:$B$349,"MBWAY_NAN",_CALC_ALLOC!$D$1:$D$349,"BAC_MGT",_CALC_ALLOC!$E$1:$E$349,"B2",_CALC_ALLOC!$F$1:$F$349,"ALT") -> 0 | H33: =SUMIFS(_CALC_ALLOC!$AL$1:$AL$349,_CALC_ALLOC!$A$1:$A$349,"2026",_CALC_ALLOC!$B$1:$B$349,"MBWAY_NAN",_CALC_ALLOC!$D$1:$D$349,"BAC_MGT",_CALC_ALLOC!$E$1:$E$349,"B2",_CALC_ALLOC!$F$1:$F$349,"ALT") -> 0 | I33: =SUMIFS(_CALC_ALLOC!$AR$1:$AR$349,_CALC_ALLOC!$A$1:$A$349,"2026",_CALC_ALLOC!$B$1:$B$349,"MBWAY_NAN",_CALC_ALLOC!$D$1:$D$349,"BAC_MGT",_CALC_ALLOC!$E$1:$E$349,"B2",_CALC_ALLOC!$F$1:$F$349,"ALT") -> 0 | J33: =SUMIFS(_CALC_ALLOC!$AM$1:$AM$349,_CALC_ALLOC!$A$1:$A$349,"2026",_CALC_ALLOC!$B$1:$B$349,"MBWAY_NAN",_CALC_ALLOC!$D$1:$D$349,"BAC_MGT",_CALC_ALLOC!$E$1:$E$349,"B2",_CALC_ALLOC!$F$1:$F$349,"ALT") -> 0 | K33: =E33+F33+G33+H33+I33+J33 -> 0 | L33: =SUMIFS(_CALC_ALLOC!$AN$1:$AN$349,_CALC_ALLOC!$A$1:$A$349,"2026",_CALC_ALLOC!$B$1:$B$349,"MBWAY_NAN",_CALC_ALLOC!$D$1:$D$349,"BAC_MGT",_CALC_ALLOC!$E$1:$E$349,"B2",_CALC_ALLOC!$F$1:$F$349,"ALT") -> 0 | M33: =IFERROR(L33/D33,0) -> 0
B34: BAC_MGT B3 ALT | C34: =SUMIFS(_CALC_ALLOC!$G$1:$G$349,_CALC_ALLOC!$A$1:$A$349,"2026",_CALC_ALLOC!$B$1:$B$349,"MBWAY_NAN",_CALC_ALLOC!$D$1:$D$349,"BAC_MGT",_CALC_ALLOC!$E$1:$E$349,"B3",_CALC_ALLOC!$F$1:$F$349,"ALT") -> 0 | D34: =SUMIFS(_CALC_ALLOC!$I$1:$I$349,_CALC_ALLOC!$A$1:$A$349,"2026",_CALC_ALLOC!$B$1:$B$349,"MBWAY_NAN",_CALC_ALLOC!$D$1:$D$349,"BAC_MGT",_CALC_ALLOC!$E$1:$E$349,"B3",_CALC_ALLOC!$F$1:$F$349,"ALT") -> 0 | E34: =SUMIFS(_CALC_ALLOC!$AI$1:$AI$349,_CALC_ALLOC!$A$1:$A$349,"2026",_CALC_ALLOC!$B$1:$B$349,"MBWAY_NAN",_CALC_ALLOC!$D$1:$D$349,"BAC_MGT",_CALC_ALLOC!$E$1:$E$349,"B3",_CALC_ALLOC!$F$1:$F$349,"ALT") -> 0 | F34: =SUMIFS(_CALC_ALLOC!$AJ$1:$AJ$349,_CALC_ALLOC!$A$1:$A$349,"2026",_CALC_ALLOC!$B$1:$B$349,"MBWAY_NAN",_CALC_ALLOC!$D$1:$D$349,"BAC_MGT",_CALC_ALLOC!$E$1:$E$349,"B3",_CALC_ALLOC!$F$1:$F$349,"ALT") -> 0 | G34: =SUMIFS(_CALC_ALLOC!$AK$1:$AK$349,_CALC_ALLOC!$A$1:$A$349,"2026",_CALC_ALLOC!$B$1:$B$349,"MBWAY_NAN",_CALC_ALLOC!$D$1:$D$349,"BAC_MGT",_CALC_ALLOC!$E$1:$E$349,"B3",_CALC_ALLOC!$F$1:$F$349,"ALT") -> 0 | H34: =SUMIFS(_CALC_ALLOC!$AL$1:$AL$349,_CALC_ALLOC!$A$1:$A$349,"2026",_CALC_ALLOC!$B$1:$B$349,"MBWAY_NAN",_CALC_ALLOC!$D$1:$D$349,"BAC_MGT",_CALC_ALLOC!$E$1:$E$349,"B3",_CALC_ALLOC!$F$1:$F$349,"ALT") -> 0 | I34: =SUMIFS(_CALC_ALLOC!$AR$1:$AR$349,_CALC_ALLOC!$A$1:$A$349,"2026",_CALC_ALLOC!$B$1:$B$349,"MBWAY_NAN",_CALC_ALLOC!$D$1:$D$349,"BAC_MGT",_CALC_ALLOC!$E$1:$E$349,"B3",_CALC_ALLOC!$F$1:$F$349,"ALT") -> 0 | J34: =SUMIFS(_CALC_ALLOC!$AM$1:$AM$349,_CALC_ALLOC!$A$1:$A$349,"2026",_CALC_ALLOC!$B$1:$B$349,"MBWAY_NAN",_CALC_ALLOC!$D$1:$D$349,"BAC_MGT",_CALC_ALLOC!$E$1:$E$349,"B3",_CALC_ALLOC!$F$1:$F$349,"ALT") -> 0 | K34: =E34+F34+G34+H34+I34+J34 -> 0 | L34: =SUMIFS(_CALC_ALLOC!$AN$1:$AN$349,_CALC_ALLOC!$A$1:$A$349,"2026",_CALC_ALLOC!$B$1:$B$349,"MBWAY_NAN",_CALC_ALLOC!$D$1:$D$349,"BAC_MGT",_CALC_ALLOC!$E$1:$E$349,"B3",_CALC_ALLOC!$F$1:$F$349,"ALT") -> 0 | M34: =IFERROR(L34/D34,0) -> 0
B35: MAS_MGT M1 ALT | C35: =SUMIFS(_CALC_ALLOC!$G$1:$G$349,_CALC_ALLOC!$A$1:$A$349,"2026",_CALC_ALLOC!$B$1:$B$349,"MBWAY_NAN",_CALC_ALLOC!$D$1:$D$349,"MAS_MGT",_CALC_ALLOC!$E$1:$E$349,"M1",_CALC_ALLOC!$F$1:$F$349,"ALT") -> 0 | D35: =SUMIFS(_CALC_ALLOC!$I$1:$I$349,_CALC_ALLOC!$A$1:$A$349,"2026",_CALC_ALLOC!$B$1:$B$349,"MBWAY_NAN",_CALC_ALLOC!$D$1:$D$349,"MAS_MGT",_CALC_ALLOC!$E$1:$E$349,"M1",_CALC_ALLOC!$F$1:$F$349,"ALT") -> 0 | E35: =SUMIFS(_CALC_ALLOC!$AI$1:$AI$349,_CALC_ALLOC!$A$1:$A$349,"2026",_CALC_ALLOC!$B$1:$B$349,"MBWAY_NAN",_CALC_ALLOC!$D$1:$D$349,"MAS_MGT",_CALC_ALLOC!$E$1:$E$349,"M1",_CALC_ALLOC!$F$1:$F$349,"ALT") -> 0 | F35: =SUMIFS(_CALC_ALLOC!$AJ$1:$AJ$349,_CALC_ALLOC!$A$1:$A$349,"2026",_CALC_ALLOC!$B$1:$B$349,"MBWAY_NAN",_CALC_ALLOC!$D$1:$D$349,"MAS_MGT",_CALC_ALLOC!$E$1:$E$349,"M1",_CALC_ALLOC!$F$1:$F$349,"ALT") -> 0 | G35: =SUMIFS(_CALC_ALLOC!$AK$1:$AK$349,_CALC_ALLOC!$A$1:$A$349,"2026",_CALC_ALLOC!$B$1:$B$349,"MBWAY_NAN",_CALC_ALLOC!$D$1:$D$349,"MAS_MGT",_CALC_ALLOC!$E$1:$E$349,"M1",_CALC_ALLOC!$F$1:$F$349,"ALT") -> 0 | H35: =SUMIFS(_CALC_ALLOC!$AL$1:$AL$349,_CALC_ALLOC!$A$1:$A$349,"2026",_CALC_ALLOC!$B$1:$B$349,"MBWAY_NAN",_CALC_ALLOC!$D$1:$D$349,"MAS_MGT",_CALC_ALLOC!$E$1:$E$349,"M1",_CALC_ALLOC!$F$1:$F$349,"ALT") -> 0 | I35: =SUMIFS(_CALC_ALLOC!$AR$1:$AR$349,_CALC_ALLOC!$A$1:$A$349,"2026",_CALC_ALLOC!$B$1:$B$349,"MBWAY_NAN",_CALC_ALLOC!$D$1:$D$349,"MAS_MGT",_CALC_ALLOC!$E$1:$E$349,"M1",_CALC_ALLOC!$F$1:$F$349,"ALT") -> 0 | J35: =SUMIFS(_CALC_ALLOC!$AM$1:$AM$349,_CALC_ALLOC!$A$1:$A$349,"2026",_CALC_ALLOC!$B$1:$B$349,"MBWAY_NAN",_CALC_ALLOC!$D$1:$D$349,"MAS_MGT",_CALC_ALLOC!$E$1:$E$349,"M1",_CALC_ALLOC!$F$1:$F$349,"ALT") -> 0 | K35: =E35+F35+G35+H35+I35+J35 -> 0 | L35: =SUMIFS(_CALC_ALLOC!$AN$1:$AN$349,_CALC_ALLOC!$A$1:$A$349,"2026",_CALC_ALLOC!$B$1:$B$349,"MBWAY_NAN",_CALC_ALLOC!$D$1:$D$349,"MAS_MGT",_CALC_ALLOC!$E$1:$E$349,"M1",_CALC_ALLOC!$F$1:$F$349,"ALT") -> 0 | M35: =IFERROR(L35/D35,0) -> 0
B36: MAS_MGT M2 ALT | C36: =SUMIFS(_CALC_ALLOC!$G$1:$G$349,_CALC_ALLOC!$A$1:$A$349,"2026",_CALC_ALLOC!$B$1:$B$349,"MBWAY_NAN",_CALC_ALLOC!$D$1:$D$349,"MAS_MGT",_CALC_ALLOC!$E$1:$E$349,"M2",_CALC_ALLOC!$F$1:$F$349,"ALT") -> 0 | D36: =SUMIFS(_CALC_ALLOC!$I$1:$I$349,_CALC_ALLOC!$A$1:$A$349,"2026",_CALC_ALLOC!$B$1:$B$349,"MBWAY_NAN",_CALC_ALLOC!$D$1:$D$349,"MAS_MGT",_CALC_ALLOC!$E$1:$E$349,"M2",_CALC_ALLOC!$F$1:$F$349,"ALT") -> 0 | E36: =SUMIFS(_CALC_ALLOC!$AI$1:$AI$349,_CALC_ALLOC!$A$1:$A$349,"2026",_CALC_ALLOC!$B$1:$B$349,"MBWAY_NAN",_CALC_ALLOC!$D$1:$D$349,"MAS_MGT",_CALC_ALLOC!$E$1:$E$349,"M2",_CALC_ALLOC!$F$1:$F$349,"ALT") -> 0 | F36: =SUMIFS(_CALC_ALLOC!$AJ$1:$AJ$349,_CALC_ALLOC!$A$1:$A$349,"2026",_CALC_ALLOC!$B$1:$B$349,"MBWAY_NAN",_CALC_ALLOC!$D$1:$D$349,"MAS_MGT",_CALC_ALLOC!$E$1:$E$349,"M2",_CALC_ALLOC!$F$1:$F$349,"ALT") -> 0 | G36: =SUMIFS(_CALC_ALLOC!$AK$1:$AK$349,_CALC_ALLOC!$A$1:$A$349,"2026",_CALC_ALLOC!$B$1:$B$349,"MBWAY_NAN",_CALC_ALLOC!$D$1:$D$349,"MAS_MGT",_CALC_ALLOC!$E$1:$E$349,"M2",_CALC_ALLOC!$F$1:$F$349,"ALT") -> 0 | H36: =SUMIFS(_CALC_ALLOC!$AL$1:$AL$349,_CALC_ALLOC!$A$1:$A$349,"2026",_CALC_ALLOC!$B$1:$B$349,"MBWAY_NAN",_CALC_ALLOC!$D$1:$D$349,"MAS_MGT",_CALC_ALLOC!$E$1:$E$349,"M2",_CALC_ALLOC!$F$1:$F$349,"ALT") -> 0 | I36: =SUMIFS(_CALC_ALLOC!$AR$1:$AR$349,_CALC_ALLOC!$A$1:$A$349,"2026",_CALC_ALLOC!$B$1:$B$349,"MBWAY_NAN",_CALC_ALLOC!$D$1:$D$349,"MAS_MGT",_CALC_ALLOC!$E$1:$E$349,"M2",_CALC_ALLOC!$F$1:$F$349,"ALT") -> 0 | J36: =SUMIFS(_CALC_ALLOC!$AM$1:$AM$349,_CALC_ALLOC!$A$1:$A$349,"2026",_CALC_ALLOC!$B$1:$B$349,"MBWAY_NAN",_CALC_ALLOC!$D$1:$D$349,"MAS_MGT",_CALC_ALLOC!$E$1:$E$349,"M2",_CALC_ALLOC!$F$1:$F$349,"ALT") -> 0 | K36: =E36+F36+G36+H36+I36+J36 -> 0 | L36: =SUMIFS(_CALC_ALLOC!$AN$1:$AN$349,_CALC_ALLOC!$A$1:$A$349,"2026",_CALC_ALLOC!$B$1:$B$349,"MBWAY_NAN",_CALC_ALLOC!$D$1:$D$349,"MAS_MGT",_CALC_ALLOC!$E$1:$E$349,"M2",_CALC_ALLOC!$F$1:$F$349,"ALT") -> 0 | M36: =IFERROR(L36/D36,0) -> 0
B37: Bordeaux (MBWAY_BOR) | C37: =SUMIFS(_CALC_ALLOC!$G$1:$G$349,_CALC_ALLOC!$A$1:$A$349,"2026",_CALC_ALLOC!$B$1:$B$349,"MBWAY_BOR") -> 0 | D37: =SUMIFS(_CALC_ALLOC!$I$1:$I$349,_CALC_ALLOC!$A$1:$A$349,"2026",_CALC_ALLOC!$B$1:$B$349,"MBWAY_BOR") -> 0 | E37: =SUMIFS(_CALC_ALLOC!$AI$1:$AI$349,_CALC_ALLOC!$A$1:$A$349,"2026",_CALC_ALLOC!$B$1:$B$349,"MBWAY_BOR") -> 0 | F37: =SUMIFS(_CALC_ALLOC!$AJ$1:$AJ$349,_CALC_ALLOC!$A$1:$A$349,"2026",_CALC_ALLOC!$B$1:$B$349,"MBWAY_BOR") -> 0 | G37: =SUMIFS(_CALC_ALLOC!$AK$1:$AK$349,_CALC_ALLOC!$A$1:$A$349,"2026",_CALC_ALLOC!$B$1:$B$349,"MBWAY_BOR") -> 0 | H37: =SUMIFS(_CALC_ALLOC!$AL$1:$AL$349,_CALC_ALLOC!$A$1:$A$349,"2026",_CALC_ALLOC!$B$1:$B$349,"MBWAY_BOR") -> 0 | I37: =SUMIFS(_CALC_ALLOC!$AR$1:$AR$349,_CALC_ALLOC!$A$1:$A$349,"2026",_CALC_ALLOC!$B$1:$B$349,"MBWAY_BOR") -> 0 | J37: =SUMIFS(_CALC_ALLOC!$AM$1:$AM$349,_CALC_ALLOC!$A$1:$A$349,"2026",_CALC_ALLOC!$B$1:$B$349,"MBWAY_BOR") -> 0 | K37: =E37+F37+G37+H37+I37+J37 -> 0 | L37: =SUMIFS(_CALC_ALLOC!$AN$1:$AN$349,_CALC_ALLOC!$A$1:$A$349,"2026",_CALC_ALLOC!$B$1:$B$349,"MBWAY_BOR") -> 0 | M37: =IFERROR(L37/D37,0) -> 0
B38: BAC_MGT B1 INIT | C38: =SUMIFS(_CALC_ALLOC!$G$1:$G$349,_CALC_ALLOC!$A$1:$A$349,"2026",_CALC_ALLOC!$B$1:$B$349,"MBWAY_BOR",_CALC_ALLOC!$D$1:$D$349,"BAC_MGT",_CALC_ALLOC!$E$1:$E$349,"B1",_CALC_ALLOC!$F$1:$F$349,"INIT") -> 0 | D38: =SUMIFS(_CALC_ALLOC!$I$1:$I$349,_CALC_ALLOC!$A$1:$A$349,"2026",_CALC_ALLOC!$B$1:$B$349,"MBWAY_BOR",_CALC_ALLOC!$D$1:$D$349,"BAC_MGT",_CALC_ALLOC!$E$1:$E$349,"B1",_CALC_ALLOC!$F$1:$F$349,"INIT") -> 0 | E38: =SUMIFS(_CALC_ALLOC!$AI$1:$AI$349,_CALC_ALLOC!$A$1:$A$349,"2026",_CALC_ALLOC!$B$1:$B$349,"MBWAY_BOR",_CALC_ALLOC!$D$1:$D$349,"BAC_MGT",_CALC_ALLOC!$E$1:$E$349,"B1",_CALC_ALLOC!$F$1:$F$349,"INIT") -> 0 | F38: =SUMIFS(_CALC_ALLOC!$AJ$1:$AJ$349,_CALC_ALLOC!$A$1:$A$349,"2026",_CALC_ALLOC!$B$1:$B$349,"MBWAY_BOR",_CALC_ALLOC!$D$1:$D$349,"BAC_MGT",_CALC_ALLOC!$E$1:$E$349,"B1",_CALC_ALLOC!$F$1:$F$349,"INIT") -> 0 | G38: =SUMIFS(_CALC_ALLOC!$AK$1:$AK$349,_CALC_ALLOC!$A$1:$A$349,"2026",_CALC_ALLOC!$B$1:$B$349,"MBWAY_BOR",_CALC_ALLOC!$D$1:$D$349,"BAC_MGT",_CALC_ALLOC!$E$1:$E$349,"B1",_CALC_ALLOC!$F$1:$F$349,"INIT") -> 0 | H38: =SUMIFS(_CALC_ALLOC!$AL$1:$AL$349,_CALC_ALLOC!$A$1:$A$349,"2026",_CALC_ALLOC!$B$1:$B$349,"MBWAY_BOR",_CALC_ALLOC!$D$1:$D$349,"BAC_MGT",_CALC_ALLOC!$E$1:$E$349,"B1",_CALC_ALLOC!$F$1:$F$349,"INIT") -> 0 | I38: =SUMIFS(_CALC_ALLOC!$AR$1:$AR$349,_CALC_ALLOC!$A$1:$A$349,"2026",_CALC_ALLOC!$B$1:$B$349,"MBWAY_BOR",_CALC_ALLOC!$D$1:$D$349,"BAC_MGT",_CALC_ALLOC!$E$1:$E$349,"B1",_CALC_ALLOC!$F$1:$F$349,"INIT") -> 0 | J38: =SUMIFS(_CALC_ALLOC!$AM$1:$AM$349,_CALC_ALLOC!$A$1:$A$349,"2026",_CALC_ALLOC!$B$1:$B$349,"MBWAY_BOR",_CALC_ALLOC!$D$1:$D$349,"BAC_MGT",_CALC_ALLOC!$E$1:$E$349,"B1",_CALC_ALLOC!$F$1:$F$349,"INIT") -> 0 | K38: =E38+F38+G38+H38+I38+J38 -> 0 | L38: =SUMIFS(_CALC_ALLOC!$AN$1:$AN$349,_CALC_ALLOC!$A$1:$A$349,"2026",_CALC_ALLOC!$B$1:$B$349,"MBWAY_BOR",_CALC_ALLOC!$D$1:$D$349,"BAC_MGT",_CALC_ALLOC!$E$1:$E$349,"B1",_CALC_ALLOC!$F$1:$F$349,"INIT") -> 0 | M38: =IFERROR(L38/D38,0) -> 0
B39: BAC_MGT B2 ALT | C39: =SUMIFS(_CALC_ALLOC!$G$1:$G$349,_CALC_ALLOC!$A$1:$A$349,"2026",_CALC_ALLOC!$B$1:$B$349,"MBWAY_BOR",_CALC_ALLOC!$D$1:$D$349,"BAC_MGT",_CALC_ALLOC!$E$1:$E$349,"B2",_CALC_ALLOC!$F$1:$F$349,"ALT") -> 0 | D39: =SUMIFS(_CALC_ALLOC!$I$1:$I$349,_CALC_ALLOC!$A$1:$A$349,"2026",_CALC_ALLOC!$B$1:$B$349,"MBWAY_BOR",_CALC_ALLOC!$D$1:$D$349,"BAC_MGT",_CALC_ALLOC!$E$1:$E$349,"B2",_CALC_ALLOC!$F$1:$F$349,"ALT") -> 0 | E39: =SUMIFS(_CALC_ALLOC!$AI$1:$AI$349,_CALC_ALLOC!$A$1:$A$349,"2026",_CALC_ALLOC!$B$1:$B$349,"MBWAY_BOR",_CALC_ALLOC!$D$1:$D$349,"BAC_MGT",_CALC_ALLOC!$E$1:$E$349,"B2",_CALC_ALLOC!$F$1:$F$349,"ALT") -> 0 | F39: =SUMIFS(_CALC_ALLOC!$AJ$1:$AJ$349,_CALC_ALLOC!$A$1:$A$349,"2026",_CALC_ALLOC!$B$1:$B$349,"MBWAY_BOR",_CALC_ALLOC!$D$1:$D$349,"BAC_MGT",_CALC_ALLOC!$E$1:$E$349,"B2",_CALC_ALLOC!$F$1:$F$349,"ALT") -> 0 | G39: =SUMIFS(_CALC_ALLOC!$AK$1:$AK$349,_CALC_ALLOC!$A$1:$A$349,"2026",_CALC_ALLOC!$B$1:$B$349,"MBWAY_BOR",_CALC_ALLOC!$D$1:$D$349,"BAC_MGT",_CALC_ALLOC!$E$1:$E$349,"B2",_CALC_ALLOC!$F$1:$F$349,"ALT") -> 0 | H39: =SUMIFS(_CALC_ALLOC!$AL$1:$AL$349,_CALC_ALLOC!$A$1:$A$349,"2026",_CALC_ALLOC!$B$1:$B$349,"MBWAY_BOR",_CALC_ALLOC!$D$1:$D$349,"BAC_MGT",_CALC_ALLOC!$E$1:$E$349,"B2",_CALC_ALLOC!$F$1:$F$349,"ALT") -> 0 | I39: =SUMIFS(_CALC_ALLOC!$AR$1:$AR$349,_CALC_ALLOC!$A$1:$A$349,"2026",_CALC_ALLOC!$B$1:$B$349,"MBWAY_BOR",_CALC_ALLOC!$D$1:$D$349,"BAC_MGT",_CALC_ALLOC!$E$1:$E$349,"B2",_CALC_ALLOC!$F$1:$F$349,"ALT") -> 0 | J39: =SUMIFS(_CALC_ALLOC!$AM$1:$AM$349,_CALC_ALLOC!$A$1:$A$349,"2026",_CALC_ALLOC!$B$1:$B$349,"MBWAY_BOR",_CALC_ALLOC!$D$1:$D$349,"BAC_MGT",_CALC_ALLOC!$E$1:$E$349,"B2",_CALC_ALLOC!$F$1:$F$349,"ALT") -> 0 | K39: =E39+F39+G39+H39+I39+J39 -> 0 | L39: =SUMIFS(_CALC_ALLOC!$AN$1:$AN$349,_CALC_ALLOC!$A$1:$A$349,"2026",_CALC_ALLOC!$B$1:$B$349,"MBWAY_BOR",_CALC_ALLOC!$D$1:$D$349,"BAC_MGT",_CALC_ALLOC!$E$1:$E$349,"B2",_CALC_ALLOC!$F$1:$F$349,"ALT") -> 0 | M39: =IFERROR(L39/D39,0) -> 0
B40: BAC_MGT B3 ALT | C40: =SUMIFS(_CALC_ALLOC!$G$1:$G$349,_CALC_ALLOC!$A$1:$A$349,"2026",_CALC_ALLOC!$B$1:$B$349,"MBWAY_BOR",_CALC_ALLOC!$D$1:$D$349,"BAC_MGT",_CALC_ALLOC!$E$1:$E$349,"B3",_CALC_ALLOC!$F$1:$F$349,"ALT") -> 0 | D40: =SUMIFS(_CALC_ALLOC!$I$1:$I$349,_CALC_ALLOC!$A$1:$A$349,"2026",_CALC_ALLOC!$B$1:$B$349,"MBWAY_BOR",_CALC_ALLOC!$D$1:$D$349,"BAC_MGT",_CALC_ALLOC!$E$1:$E$349,"B3",_CALC_ALLOC!$F$1:$F$349,"ALT") -> 0 | E40: =SUMIFS(_CALC_ALLOC!$AI$1:$AI$349,_CALC_ALLOC!$A$1:$A$349,"2026",_CALC_ALLOC!$B$1:$B$349,"MBWAY_BOR",_CALC_ALLOC!$D$1:$D$349,"BAC_MGT",_CALC_ALLOC!$E$1:$E$349,"B3",_CALC_ALLOC!$F$1:$F$349,"ALT") -> 0 | F40: =SUMIFS(_CALC_ALLOC!$AJ$1:$AJ$349,_CALC_ALLOC!$A$1:$A$349,"2026",_CALC_ALLOC!$B$1:$B$349,"MBWAY_BOR",_CALC_ALLOC!$D$1:$D$349,"BAC_MGT",_CALC_ALLOC!$E$1:$E$349,"B3",_CALC_ALLOC!$F$1:$F$349,"ALT") -> 0 | G40: =SUMIFS(_CALC_ALLOC!$AK$1:$AK$349,_CALC_ALLOC!$A$1:$A$349,"2026",_CALC_ALLOC!$B$1:$B$349,"MBWAY_BOR",_CALC_ALLOC!$D$1:$D$349,"BAC_MGT",_CALC_ALLOC!$E$1:$E$349,"B3",_CALC_ALLOC!$F$1:$F$349,"ALT") -> 0 | H40: =SUMIFS(_CALC_ALLOC!$AL$1:$AL$349,_CALC_ALLOC!$A$1:$A$349,"2026",_CALC_ALLOC!$B$1:$B$349,"MBWAY_BOR",_CALC_ALLOC!$D$1:$D$349,"BAC_MGT",_CALC_ALLOC!$E$1:$E$349,"B3",_CALC_ALLOC!$F$1:$F$349,"ALT") -> 0 | I40: =SUMIFS(_CALC_ALLOC!$AR$1:$AR$349,_CALC_ALLOC!$A$1:$A$349,"2026",_CALC_ALLOC!$B$1:$B$349,"MBWAY_BOR",_CALC_ALLOC!$D$1:$D$349,"BAC_MGT",_CALC_ALLOC!$E$1:$E$349,"B3",_CALC_ALLOC!$F$1:$F$349,"ALT") -> 0 | J40: =SUMIFS(_CALC_ALLOC!$AM$1:$AM$349,_CALC_ALLOC!$A$1:$A$349,"2026",_CALC_ALLOC!$B$1:$B$349,"MBWAY_BOR",_CALC_ALLOC!$D$1:$D$349,"BAC_MGT",_CALC_ALLOC!$E$1:$E$349,"B3",_CALC_ALLOC!$F$1:$F$349,"ALT") -> 0 | K40: =E40+F40+G40+H40+I40+J40 -> 0 | L40: =SUMIFS(_CALC_ALLOC!$AN$1:$AN$349,_CALC_ALLOC!$A$1:$A$349,"2026",_CALC_ALLOC!$B$1:$B$349,"MBWAY_BOR",_CALC_ALLOC!$D$1:$D$349,"BAC_MGT",_CALC_ALLOC!$E$1:$E$349,"B3",_CALC_ALLOC!$F$1:$F$349,"ALT") -> 0 | M40: =IFERROR(L40/D40,0) -> 0
B41: MAS_MGT M1 ALT | C41: =SUMIFS(_CALC_ALLOC!$G$1:$G$349,_CALC_ALLOC!$A$1:$A$349,"2026",_CALC_ALLOC!$B$1:$B$349,"MBWAY_BOR",_CALC_ALLOC!$D$1:$D$349,"MAS_MGT",_CALC_ALLOC!$E$1:$E$349,"M1",_CALC_ALLOC!$F$1:$F$349,"ALT") -> 0 | D41: =SUMIFS(_CALC_ALLOC!$I$1:$I$349,_CALC_ALLOC!$A$1:$A$349,"2026",_CALC_ALLOC!$B$1:$B$349,"MBWAY_BOR",_CALC_ALLOC!$D$1:$D$349,"MAS_MGT",_CALC_ALLOC!$E$1:$E$349,"M1",_CALC_ALLOC!$F$1:$F$349,"ALT") -> 0 | E41: =SUMIFS(_CALC_ALLOC!$AI$1:$AI$349,_CALC_ALLOC!$A$1:$A$349,"2026",_CALC_ALLOC!$B$1:$B$349,"MBWAY_BOR",_CALC_ALLOC!$D$1:$D$349,"MAS_MGT",_CALC_ALLOC!$E$1:$E$349,"M1",_CALC_ALLOC!$F$1:$F$349,"ALT") -> 0 | F41: =SUMIFS(_CALC_ALLOC!$AJ$1:$AJ$349,_CALC_ALLOC!$A$1:$A$349,"2026",_CALC_ALLOC!$B$1:$B$349,"MBWAY_BOR",_CALC_ALLOC!$D$1:$D$349,"MAS_MGT",_CALC_ALLOC!$E$1:$E$349,"M1",_CALC_ALLOC!$F$1:$F$349,"ALT") -> 0 | G41: =SUMIFS(_CALC_ALLOC!$AK$1:$AK$349,_CALC_ALLOC!$A$1:$A$349,"2026",_CALC_ALLOC!$B$1:$B$349,"MBWAY_BOR",_CALC_ALLOC!$D$1:$D$349,"MAS_MGT",_CALC_ALLOC!$E$1:$E$349,"M1",_CALC_ALLOC!$F$1:$F$349,"ALT") -> 0 | H41: =SUMIFS(_CALC_ALLOC!$AL$1:$AL$349,_CALC_ALLOC!$A$1:$A$349,"2026",_CALC_ALLOC!$B$1:$B$349,"MBWAY_BOR",_CALC_ALLOC!$D$1:$D$349,"MAS_MGT",_CALC_ALLOC!$E$1:$E$349,"M1",_CALC_ALLOC!$F$1:$F$349,"ALT") -> 0 | I41: =SUMIFS(_CALC_ALLOC!$AR$1:$AR$349,_CALC_ALLOC!$A$1:$A$349,"2026",_CALC_ALLOC!$B$1:$B$349,"MBWAY_BOR",_CALC_ALLOC!$D$1:$D$349,"MAS_MGT",_CALC_ALLOC!$E$1:$E$349,"M1",_CALC_ALLOC!$F$1:$F$349,"ALT") -> 0 | J41: =SUMIFS(_CALC_ALLOC!$AM$1:$AM$349,_CALC_ALLOC!$A$1:$A$349,"2026",_CALC_ALLOC!$B$1:$B$349,"MBWAY_BOR",_CALC_ALLOC!$D$1:$D$349,"MAS_MGT",_CALC_ALLOC!$E$1:$E$349,"M1",_CALC_ALLOC!$F$1:$F$349,"ALT") -> 0 | K41: =E41+F41+G41+H41+I41+J41 -> 0 | L41: =SUMIFS(_CALC_ALLOC!$AN$1:$AN$349,_CALC_ALLOC!$A$1:$A$349,"2026",_CALC_ALLOC!$B$1:$B$349,"MBWAY_BOR",_CALC_ALLOC!$D$1:$D$349,"MAS_MGT",_CALC_ALLOC!$E$1:$E$349,"M1",_CALC_ALLOC!$F$1:$F$349,"ALT") -> 0 | M41: =IFERROR(L41/D41,0) -> 0
B42: MAS_MGT M2 ALT | C42: =SUMIFS(_CALC_ALLOC!$G$1:$G$349,_CALC_ALLOC!$A$1:$A$349,"2026",_CALC_ALLOC!$B$1:$B$349,"MBWAY_BOR",_CALC_ALLOC!$D$1:$D$349,"MAS_MGT",_CALC_ALLOC!$E$1:$E$349,"M2",_CALC_ALLOC!$F$1:$F$349,"ALT") -> 0 | D42: =SUMIFS(_CALC_ALLOC!$I$1:$I$349,_CALC_ALLOC!$A$1:$A$349,"2026",_CALC_ALLOC!$B$1:$B$349,"MBWAY_BOR",_CALC_ALLOC!$D$1:$D$349,"MAS_MGT",_CALC_ALLOC!$E$1:$E$349,"M2",_CALC_ALLOC!$F$1:$F$349,"ALT") -> 0 | E42: =SUMIFS(_CALC_ALLOC!$AI$1:$AI$349,_CALC_ALLOC!$A$1:$A$349,"2026",_CALC_ALLOC!$B$1:$B$349,"MBWAY_BOR",_CALC_ALLOC!$D$1:$D$349,"MAS_MGT",_CALC_ALLOC!$E$1:$E$349,"M2",_CALC_ALLOC!$F$1:$F$349,"ALT") -> 0 | F42: =SUMIFS(_CALC_ALLOC!$AJ$1:$AJ$349,_CALC_ALLOC!$A$1:$A$349,"2026",_CALC_ALLOC!$B$1:$B$349,"MBWAY_BOR",_CALC_ALLOC!$D$1:$D$349,"MAS_MGT",_CALC_ALLOC!$E$1:$E$349,"M2",_CALC_ALLOC!$F$1:$F$349,"ALT") -> 0 | G42: =SUMIFS(_CALC_ALLOC!$AK$1:$AK$349,_CALC_ALLOC!$A$1:$A$349,"2026",_CALC_ALLOC!$B$1:$B$349,"MBWAY_BOR",_CALC_ALLOC!$D$1:$D$349,"MAS_MGT",_CALC_ALLOC!$E$1:$E$349,"M2",_CALC_ALLOC!$F$1:$F$349,"ALT") -> 0 | H42: =SUMIFS(_CALC_ALLOC!$AL$1:$AL$349,_CALC_ALLOC!$A$1:$A$349,"2026",_CALC_ALLOC!$B$1:$B$349,"MBWAY_BOR",_CALC_ALLOC!$D$1:$D$349,"MAS_MGT",_CALC_ALLOC!$E$1:$E$349,"M2",_CALC_ALLOC!$F$1:$F$349,"ALT") -> 0 | I42: =SUMIFS(_CALC_ALLOC!$AR$1:$AR$349,_CALC_ALLOC!$A$1:$A$349,"2026",_CALC_ALLOC!$B$1:$B$349,"MBWAY_BOR",_CALC_ALLOC!$D$1:$D$349,"MAS_MGT",_CALC_ALLOC!$E$1:$E$349,"M2",_CALC_ALLOC!$F$1:$F$349,"ALT") -> 0 | J42: =SUMIFS(_CALC_ALLOC!$AM$1:$AM$349,_CALC_ALLOC!$A$1:$A$349,"2026",_CALC_ALLOC!$B$1:$B$349,"MBWAY_BOR",_CALC_ALLOC!$D$1:$D$349,"MAS_MGT",_CALC_ALLOC!$E$1:$E$349,"M2",_CALC_ALLOC!$F$1:$F$349,"ALT") -> 0 | K42: =E42+F42+G42+H42+I42+J42 -> 0 | L42: =SUMIFS(_CALC_ALLOC!$AN$1:$AN$349,_CALC_ALLOC!$A$1:$A$349,"2026",_CALC_ALLOC!$B$1:$B$349,"MBWAY_BOR",_CALC_ALLOC!$D$1:$D$349,"MAS_MGT",_CALC_ALLOC!$E$1:$E$349,"M2",_CALC_ALLOC!$F$1:$F$349,"ALT") -> 0 | M42: =IFERROR(L42/D42,0) -> 0
B43: ISCOM | C43: =SUMIFS(_CALC_ALLOC!$G$1:$G$349,_CALC_ALLOC!$A$1:$A$349,"2026",_CALC_ALLOC!$C$1:$C$349,"ISCOM") -> 0 | D43: =SUMIFS(_CALC_ALLOC!$I$1:$I$349,_CALC_ALLOC!$A$1:$A$349,"2026",_CALC_ALLOC!$C$1:$C$349,"ISCOM") -> 0 | E43: =SUMIFS(_CALC_ALLOC!$AI$1:$AI$349,_CALC_ALLOC!$A$1:$A$349,"2026",_CALC_ALLOC!$C$1:$C$349,"ISCOM") -> 0 | F43: =SUMIFS(_CALC_ALLOC!$AJ$1:$AJ$349,_CALC_ALLOC!$A$1:$A$349,"2026",_CALC_ALLOC!$C$1:$C$349,"ISCOM") -> 0 | G43: =SUMIFS(_CALC_ALLOC!$AK$1:$AK$349,_CALC_ALLOC!$A$1:$A$349,"2026",_CALC_ALLOC!$C$1:$C$349,"ISCOM") -> 0 | H43: =SUMIFS(_CALC_ALLOC!$AL$1:$AL$349,_CALC_ALLOC!$A$1:$A$349,"2026",_CALC_ALLOC!$C$1:$C$349,"ISCOM") -> 0 | I43: =SUMIFS(_CALC_ALLOC!$AR$1:$AR$349,_CALC_ALLOC!$A$1:$A$349,"2026",_CALC_ALLOC!$C$1:$C$349,"ISCOM") -> 0 | J43: =SUMIFS(_CALC_ALLOC!$AM$1:$AM$349,_CALC_ALLOC!$A$1:$A$349,"2026",_CALC_ALLOC!$C$1:$C$349,"ISCOM") -> 0 | K43: =E43+F43+G43+H43+I43+J43 -> 0 | L43: =SUMIFS(_CALC_ALLOC!$AN$1:$AN$349,_CALC_ALLOC!$A$1:$A$349,"2026",_CALC_ALLOC!$C$1:$C$349,"ISCOM") -> 0 | M43: =IFERROR(L43/D43,0) -> 0
B44: Paris (ISCOM_PAR) | C44: =SUMIFS(_CALC_ALLOC!$G$1:$G$349,_CALC_ALLOC!$A$1:$A$349,"2026",_CALC_ALLOC!$B$1:$B$349,"ISCOM_PAR") -> 0 | D44: =SUMIFS(_CALC_ALLOC!$I$1:$I$349,_CALC_ALLOC!$A$1:$A$349,"2026",_CALC_ALLOC!$B$1:$B$349,"ISCOM_PAR") -> 0 | E44: =SUMIFS(_CALC_ALLOC!$AI$1:$AI$349,_CALC_ALLOC!$A$1:$A$349,"2026",_CALC_ALLOC!$B$1:$B$349,"ISCOM_PAR") -> 0 | F44: =SUMIFS(_CALC_ALLOC!$AJ$1:$AJ$349,_CALC_ALLOC!$A$1:$A$349,"2026",_CALC_ALLOC!$B$1:$B$349,"ISCOM_PAR") -> 0 | G44: =SUMIFS(_CALC_ALLOC!$AK$1:$AK$349,_CALC_ALLOC!$A$1:$A$349,"2026",_CALC_ALLOC!$B$1:$B$349,"ISCOM_PAR") -> 0 | H44: =SUMIFS(_CALC_ALLOC!$AL$1:$AL$349,_CALC_ALLOC!$A$1:$A$349,"2026",_CALC_ALLOC!$B$1:$B$349,"ISCOM_PAR") -> 0 | I44: =SUMIFS(_CALC_ALLOC!$AR$1:$AR$349,_CALC_ALLOC!$A$1:$A$349,"2026",_CALC_ALLOC!$B$1:$B$349,"ISCOM_PAR") -> 0 | J44: =SUMIFS(_CALC_ALLOC!$AM$1:$AM$349,_CALC_ALLOC!$A$1:$A$349,"2026",_CALC_ALLOC!$B$1:$B$349,"ISCOM_PAR") -> 0 | K44: =E44+F44+G44+H44+I44+J44 -> 0 | L44: =SUMIFS(_CALC_ALLOC!$AN$1:$AN$349,_CALC_ALLOC!$A$1:$A$349,"2026",_CALC_ALLOC!$B$1:$B$349,"ISCOM_PAR") -> 0 | M44: =IFERROR(L44/D44,0) -> 0
B45: BAC_COM B1 INIT | C45: =SUMIFS(_CALC_ALLOC!$G$1:$G$349,_CALC_ALLOC!$A$1:$A$349,"2026",_CALC_ALLOC!$B$1:$B$349,"ISCOM_PAR",_CALC_ALLOC!$D$1:$D$349,"BAC_COM",_CALC_ALLOC!$E$1:$E$349,"B1",_CALC_ALLOC!$F$1:$F$349,"INIT") -> 0 | D45: =SUMIFS(_CALC_ALLOC!$I$1:$I$349,_CALC_ALLOC!$A$1:$A$349,"2026",_CALC_ALLOC!$B$1:$B$349,"ISCOM_PAR",_CALC_ALLOC!$D$1:$D$349,"BAC_COM",_CALC_ALLOC!$E$1:$E$349,"B1",_CALC_ALLOC!$F$1:$F$349,"INIT") -> 0 | E45: =SUMIFS(_CALC_ALLOC!$AI$1:$AI$349,_CALC_ALLOC!$A$1:$A$349,"2026",_CALC_ALLOC!$B$1:$B$349,"ISCOM_PAR",_CALC_ALLOC!$D$1:$D$349,"BAC_COM",_CALC_ALLOC!$E$1:$E$349,"B1",_CALC_ALLOC!$F$1:$F$349,"INIT") -> 0 | F45: =SUMIFS(_CALC_ALLOC!$AJ$1:$AJ$349,_CALC_ALLOC!$A$1:$A$349,"2026",_CALC_ALLOC!$B$1:$B$349,"ISCOM_PAR",_CALC_ALLOC!$D$1:$D$349,"BAC_COM",_CALC_ALLOC!$E$1:$E$349,"B1",_CALC_ALLOC!$F$1:$F$349,"INIT") -> 0 | G45: =SUMIFS(_CALC_ALLOC!$AK$1:$AK$349,_CALC_ALLOC!$A$1:$A$349,"2026",_CALC_ALLOC!$B$1:$B$349,"ISCOM_PAR",_CALC_ALLOC!$D$1:$D$349,"BAC_COM",_CALC_ALLOC!$E$1:$E$349,"B1",_CALC_ALLOC!$F$1:$F$349,"INIT") -> 0 | H45: =SUMIFS(_CALC_ALLOC!$AL$1:$AL$349,_CALC_ALLOC!$A$1:$A$349,"2026",_CALC_ALLOC!$B$1:$B$349,"ISCOM_PAR",_CALC_ALLOC!$D$1:$D$349,"BAC_COM",_CALC_ALLOC!$E$1:$E$349,"B1",_CALC_ALLOC!$F$1:$F$349,"INIT") -> 0 | I45: =SUMIFS(_CALC_ALLOC!$AR$1:$AR$349,_CALC_ALLOC!$A$1:$A$349,"2026",_CALC_ALLOC!$B$1:$B$349,"ISCOM_PAR",_CALC_ALLOC!$D$1:$D$349,"BAC_COM",_CALC_ALLOC!$E$1:$E$349,"B1",_CALC_ALLOC!$F$1:$F$349,"INIT") -> 0 | J45: =SUMIFS(_CALC_ALLOC!$AM$1:$AM$349,_CALC_ALLOC!$A$1:$A$349,"2026",_CALC_ALLOC!$B$1:$B$349,"ISCOM_PAR",_CALC_ALLOC!$D$1:$D$349,"BAC_COM",_CALC_ALLOC!$E$1:$E$349,"B1",_CALC_ALLOC!$F$1:$F$349,"INIT") -> 0 | K45: =E45+F45+G45+H45+I45+J45 -> 0 | L45: =SUMIFS(_CALC_ALLOC!$AN$1:$AN$349,_CALC_ALLOC!$A$1:$A$349,"2026",_CALC_ALLOC!$B$1:$B$349,"ISCOM_PAR",_CALC_ALLOC!$D$1:$D$349,"BAC_COM",_CALC_ALLOC!$E$1:$E$349,"B1",_CALC_ALLOC!$F$1:$F$349,"INIT") -> 0 | M45: =IFERROR(L45/D45,0) -> 0
B46: BAC_COM B2 ALT | C46: =SUMIFS(_CALC_ALLOC!$G$1:$G$349,_CALC_ALLOC!$A$1:$A$349,"2026",_CALC_ALLOC!$B$1:$B$349,"ISCOM_PAR",_CALC_ALLOC!$D$1:$D$349,"BAC_COM",_CALC_ALLOC!$E$1:$E$349,"B2",_CALC_ALLOC!$F$1:$F$349,"ALT") -> 0 | D46: =SUMIFS(_CALC_ALLOC!$I$1:$I$349,_CALC_ALLOC!$A$1:$A$349,"2026",_CALC_ALLOC!$B$1:$B$349,"ISCOM_PAR",_CALC_ALLOC!$D$1:$D$349,"BAC_COM",_CALC_ALLOC!$E$1:$E$349,"B2",_CALC_ALLOC!$F$1:$F$349,"ALT") -> 0 | E46: =SUMIFS(_CALC_ALLOC!$AI$1:$AI$349,_CALC_ALLOC!$A$1:$A$349,"2026",_CALC_ALLOC!$B$1:$B$349,"ISCOM_PAR",_CALC_ALLOC!$D$1:$D$349,"BAC_COM",_CALC_ALLOC!$E$1:$E$349,"B2",_CALC_ALLOC!$F$1:$F$349,"ALT") -> 0 | F46: =SUMIFS(_CALC_ALLOC!$AJ$1:$AJ$349,_CALC_ALLOC!$A$1:$A$349,"2026",_CALC_ALLOC!$B$1:$B$349,"ISCOM_PAR",_CALC_ALLOC!$D$1:$D$349,"BAC_COM",_CALC_ALLOC!$E$1:$E$349,"B2",_CALC_ALLOC!$F$1:$F$349,"ALT") -> 0 | G46: =SUMIFS(_CALC_ALLOC!$AK$1:$AK$349,_CALC_ALLOC!$A$1:$A$349,"2026",_CALC_ALLOC!$B$1:$B$349,"ISCOM_PAR",_CALC_ALLOC!$D$1:$D$349,"BAC_COM",_CALC_ALLOC!$E$1:$E$349,"B2",_CALC_ALLOC!$F$1:$F$349,"ALT") -> 0 | H46: =SUMIFS(_CALC_ALLOC!$AL$1:$AL$349,_CALC_ALLOC!$A$1:$A$349,"2026",_CALC_ALLOC!$B$1:$B$349,"ISCOM_PAR",_CALC_ALLOC!$D$1:$D$349,"BAC_COM",_CALC_ALLOC!$E$1:$E$349,"B2",_CALC_ALLOC!$F$1:$F$349,"ALT") -> 0 | I46: =SUMIFS(_CALC_ALLOC!$AR$1:$AR$349,_CALC_ALLOC!$A$1:$A$349,"2026",_CALC_ALLOC!$B$1:$B$349,"ISCOM_PAR",_CALC_ALLOC!$D$1:$D$349,"BAC_COM",_CALC_ALLOC!$E$1:$E$349,"B2",_CALC_ALLOC!$F$1:$F$349,"ALT") -> 0 | J46: =SUMIFS(_CALC_ALLOC!$AM$1:$AM$349,_CALC_ALLOC!$A$1:$A$349,"2026",_CALC_ALLOC!$B$1:$B$349,"ISCOM_PAR",_CALC_ALLOC!$D$1:$D$349,"BAC_COM",_CALC_ALLOC!$E$1:$E$349,"B2",_CALC_ALLOC!$F$1:$F$349,"ALT") -> 0 | K46: =E46+F46+G46+H46+I46+J46 -> 0 | L46: =SUMIFS(_CALC_ALLOC!$AN$1:$AN$349,_CALC_ALLOC!$A$1:$A$349,"2026",_CALC_ALLOC!$B$1:$B$349,"ISCOM_PAR",_CALC_ALLOC!$D$1:$D$349,"BAC_COM",_CALC_ALLOC!$E$1:$E$349,"B2",_CALC_ALLOC!$F$1:$F$349,"ALT") -> 0 | M46: =IFERROR(L46/D46,0) -> 0
B47: BAC_COM B3 ALT | C47: =SUMIFS(_CALC_ALLOC!$G$1:$G$349,_CALC_ALLOC!$A$1:$A$349,"2026",_CALC_ALLOC!$B$1:$B$349,"ISCOM_PAR",_CALC_ALLOC!$D$1:$D$349,"BAC_COM",_CALC_ALLOC!$E$1:$E$349,"B3",_CALC_ALLOC!$F$1:$F$349,"ALT") -> 0 | D47: =SUMIFS(_CALC_ALLOC!$I$1:$I$349,_CALC_ALLOC!$A$1:$A$349,"2026",_CALC_ALLOC!$B$1:$B$349,"ISCOM_PAR",_CALC_ALLOC!$D$1:$D$349,"BAC_COM",_CALC_ALLOC!$E$1:$E$349,"B3",_CALC_ALLOC!$F$1:$F$349,"ALT") -> 0 | E47: =SUMIFS(_CALC_ALLOC!$AI$1:$AI$349,_CALC_ALLOC!$A$1:$A$349,"2026",_CALC_ALLOC!$B$1:$B$349,"ISCOM_PAR",_CALC_ALLOC!$D$1:$D$349,"BAC_COM",_CALC_ALLOC!$E$1:$E$349,"B3",_CALC_ALLOC!$F$1:$F$349,"ALT") -> 0 | F47: =SUMIFS(_CALC_ALLOC!$AJ$1:$AJ$349,_CALC_ALLOC!$A$1:$A$349,"2026",_CALC_ALLOC!$B$1:$B$349,"ISCOM_PAR",_CALC_ALLOC!$D$1:$D$349,"BAC_COM",_CALC_ALLOC!$E$1:$E$349,"B3",_CALC_ALLOC!$F$1:$F$349,"ALT") -> 0 | G47: =SUMIFS(_CALC_ALLOC!$AK$1:$AK$349,_CALC_ALLOC!$A$1:$A$349,"2026",_CALC_ALLOC!$B$1:$B$349,"ISCOM_PAR",_CALC_ALLOC!$D$1:$D$349,"BAC_COM",_CALC_ALLOC!$E$1:$E$349,"B3",_CALC_ALLOC!$F$1:$F$349,"ALT") -> 0 | H47: =SUMIFS(_CALC_ALLOC!$AL$1:$AL$349,_CALC_ALLOC!$A$1:$A$349,"2026",_CALC_ALLOC!$B$1:$B$349,"ISCOM_PAR",_CALC_ALLOC!$D$1:$D$349,"BAC_COM",_CALC_ALLOC!$E$1:$E$349,"B3",_CALC_ALLOC!$F$1:$F$349,"ALT") -> 0 | I47: =SUMIFS(_CALC_ALLOC!$AR$1:$AR$349,_CALC_ALLOC!$A$1:$A$349,"2026",_CALC_ALLOC!$B$1:$B$349,"ISCOM_PAR",_CALC_ALLOC!$D$1:$D$349,"BAC_COM",_CALC_ALLOC!$E$1:$E$349,"B3",_CALC_ALLOC!$F$1:$F$349,"ALT") -> 0 | J47: =SUMIFS(_CALC_ALLOC!$AM$1:$AM$349,_CALC_ALLOC!$A$1:$A$349,"2026",_CALC_ALLOC!$B$1:$B$349,"ISCOM_PAR",_CALC_ALLOC!$D$1:$D$349,"BAC_COM",_CALC_ALLOC!$E$1:$E$349,"B3",_CALC_ALLOC!$F$1:$F$349,"ALT") -> 0 | K47: =E47+F47+G47+H47+I47+J47 -> 0 | L47: =SUMIFS(_CALC_ALLOC!$AN$1:$AN$349,_CALC_ALLOC!$A$1:$A$349,"2026",_CALC_ALLOC!$B$1:$B$349,"ISCOM_PAR",_CALC_ALLOC!$D$1:$D$349,"BAC_COM",_CALC_ALLOC!$E$1:$E$349,"B3",_CALC_ALLOC!$F$1:$F$349,"ALT") -> 0 | M47: =IFERROR(L47/D47,0) -> 0
B48: MAS_COM M1 ALT | C48: =SUMIFS(_CALC_ALLOC!$G$1:$G$349,_CALC_ALLOC!$A$1:$A$349,"2026",_CALC_ALLOC!$B$1:$B$349,"ISCOM_PAR",_CALC_ALLOC!$D$1:$D$349,"MAS_COM",_CALC_ALLOC!$E$1:$E$349,"M1",_CALC_ALLOC!$F$1:$F$349,"ALT") -> 0 | D48: =SUMIFS(_CALC_ALLOC!$I$1:$I$349,_CALC_ALLOC!$A$1:$A$349,"2026",_CALC_ALLOC!$B$1:$B$349,"ISCOM_PAR",_CALC_ALLOC!$D$1:$D$349,"MAS_COM",_CALC_ALLOC!$E$1:$E$349,"M1",_CALC_ALLOC!$F$1:$F$349,"ALT") -> 0 | E48: =SUMIFS(_CALC_ALLOC!$AI$1:$AI$349,_CALC_ALLOC!$A$1:$A$349,"2026",_CALC_ALLOC!$B$1:$B$349,"ISCOM_PAR",_CALC_ALLOC!$D$1:$D$349,"MAS_COM",_CALC_ALLOC!$E$1:$E$349,"M1",_CALC_ALLOC!$F$1:$F$349,"ALT") -> 0 | F48: =SUMIFS(_CALC_ALLOC!$AJ$1:$AJ$349,_CALC_ALLOC!$A$1:$A$349,"2026",_CALC_ALLOC!$B$1:$B$349,"ISCOM_PAR",_CALC_ALLOC!$D$1:$D$349,"MAS_COM",_CALC_ALLOC!$E$1:$E$349,"M1",_CALC_ALLOC!$F$1:$F$349,"ALT") -> 0 | G48: =SUMIFS(_CALC_ALLOC!$AK$1:$AK$349,_CALC_ALLOC!$A$1:$A$349,"2026",_CALC_ALLOC!$B$1:$B$349,"ISCOM_PAR",_CALC_ALLOC!$D$1:$D$349,"MAS_COM",_CALC_ALLOC!$E$1:$E$349,"M1",_CALC_ALLOC!$F$1:$F$349,"ALT") -> 0 | H48: =SUMIFS(_CALC_ALLOC!$AL$1:$AL$349,_CALC_ALLOC!$A$1:$A$349,"2026",_CALC_ALLOC!$B$1:$B$349,"ISCOM_PAR",_CALC_ALLOC!$D$1:$D$349,"MAS_COM",_CALC_ALLOC!$E$1:$E$349,"M1",_CALC_ALLOC!$F$1:$F$349,"ALT") -> 0 | I48: =SUMIFS(_CALC_ALLOC!$AR$1:$AR$349,_CALC_ALLOC!$A$1:$A$349,"2026",_CALC_ALLOC!$B$1:$B$349,"ISCOM_PAR",_CALC_ALLOC!$D$1:$D$349,"MAS_COM",_CALC_ALLOC!$E$1:$E$349,"M1",_CALC_ALLOC!$F$1:$F$349,"ALT") -> 0 | J48: =SUMIFS(_CALC_ALLOC!$AM$1:$AM$349,_CALC_ALLOC!$A$1:$A$349,"2026",_CALC_ALLOC!$B$1:$B$349,"ISCOM_PAR",_CALC_ALLOC!$D$1:$D$349,"MAS_COM",_CALC_ALLOC!$E$1:$E$349,"M1",_CALC_ALLOC!$F$1:$F$349,"ALT") -> 0 | K48: =E48+F48+G48+H48+I48+J48 -> 0 | L48: =SUMIFS(_CALC_ALLOC!$AN$1:$AN$349,_CALC_ALLOC!$A$1:$A$349,"2026",_CALC_ALLOC!$B$1:$B$349,"ISCOM_PAR",_CALC_ALLOC!$D$1:$D$349,"MAS_COM",_CALC_ALLOC!$E$1:$E$349,"M1",_CALC_ALLOC!$F$1:$F$349,"ALT") -> 0 | M48: =IFERROR(L48/D48,0) -> 0
B49: MAS_COM M2 ALT | C49: =SUMIFS(_CALC_ALLOC!$G$1:$G$349,_CALC_ALLOC!$A$1:$A$349,"2026",_CALC_ALLOC!$B$1:$B$349,"ISCOM_PAR",_CALC_ALLOC!$D$1:$D$349,"MAS_COM",_CALC_ALLOC!$E$1:$E$349,"M2",_CALC_ALLOC!$F$1:$F$349,"ALT") -> 0 | D49: =SUMIFS(_CALC_ALLOC!$I$1:$I$349,_CALC_ALLOC!$A$1:$A$349,"2026",_CALC_ALLOC!$B$1:$B$349,"ISCOM_PAR",_CALC_ALLOC!$D$1:$D$349,"MAS_COM",_CALC_ALLOC!$E$1:$E$349,"M2",_CALC_ALLOC!$F$1:$F$349,"ALT") -> 0 | E49: =SUMIFS(_CALC_ALLOC!$AI$1:$AI$349,_CALC_ALLOC!$A$1:$A$349,"2026",_CALC_ALLOC!$B$1:$B$349,"ISCOM_PAR",_CALC_ALLOC!$D$1:$D$349,"MAS_COM",_CALC_ALLOC!$E$1:$E$349,"M2",_CALC_ALLOC!$F$1:$F$349,"ALT") -> 0 | F49: =SUMIFS(_CALC_ALLOC!$AJ$1:$AJ$349,_CALC_ALLOC!$A$1:$A$349,"2026",_CALC_ALLOC!$B$1:$B$349,"ISCOM_PAR",_CALC_ALLOC!$D$1:$D$349,"MAS_COM",_CALC_ALLOC!$E$1:$E$349,"M2",_CALC_ALLOC!$F$1:$F$349,"ALT") -> 0 | G49: =SUMIFS(_CALC_ALLOC!$AK$1:$AK$349,_CALC_ALLOC!$A$1:$A$349,"2026",_CALC_ALLOC!$B$1:$B$349,"ISCOM_PAR",_CALC_ALLOC!$D$1:$D$349,"MAS_COM",_CALC_ALLOC!$E$1:$E$349,"M2",_CALC_ALLOC!$F$1:$F$349,"ALT") -> 0 | H49: =SUMIFS(_CALC_ALLOC!$AL$1:$AL$349,_CALC_ALLOC!$A$1:$A$349,"2026",_CALC_ALLOC!$B$1:$B$349,"ISCOM_PAR",_CALC_ALLOC!$D$1:$D$349,"MAS_COM",_CALC_ALLOC!$E$1:$E$349,"M2",_CALC_ALLOC!$F$1:$F$349,"ALT") -> 0 | I49: =SUMIFS(_CALC_ALLOC!$AR$1:$AR$349,_CALC_ALLOC!$A$1:$A$349,"2026",_CALC_ALLOC!$B$1:$B$349,"ISCOM_PAR",_CALC_ALLOC!$D$1:$D$349,"MAS_COM",_CALC_ALLOC!$E$1:$E$349,"M2",_CALC_ALLOC!$F$1:$F$349,"ALT") -> 0 | J49: =SUMIFS(_CALC_ALLOC!$AM$1:$AM$349,_CALC_ALLOC!$A$1:$A$349,"2026",_CALC_ALLOC!$B$1:$B$349,"ISCOM_PAR",_CALC_ALLOC!$D$1:$D$349,"MAS_COM",_CALC_ALLOC!$E$1:$E$349,"M2",_CALC_ALLOC!$F$1:$F$349,"ALT") -> 0 | K49: =E49+F49+G49+H49+I49+J49 -> 0 | L49: =SUMIFS(_CALC_ALLOC!$AN$1:$AN$349,_CALC_ALLOC!$A$1:$A$349,"2026",_CALC_ALLOC!$B$1:$B$349,"ISCOM_PAR",_CALC_ALLOC!$D$1:$D$349,"MAS_COM",_CALC_ALLOC!$E$1:$E$349,"M2",_CALC_ALLOC!$F$1:$F$349,"ALT") -> 0 | M49: =IFERROR(L49/D49,0) -> 0
B50: Lille (ISCOM_LIL) | C50: =SUMIFS(_CALC_ALLOC!$G$1:$G$349,_CALC_ALLOC!$A$1:$A$349,"2026",_CALC_ALLOC!$B$1:$B$349,"ISCOM_LIL") -> 0 | D50: =SUMIFS(_CALC_ALLOC!$I$1:$I$349,_CALC_ALLOC!$A$1:$A$349,"2026",_CALC_ALLOC!$B$1:$B$349,"ISCOM_LIL") -> 0 | E50: =SUMIFS(_CALC_ALLOC!$AI$1:$AI$349,_CALC_ALLOC!$A$1:$A$349,"2026",_CALC_ALLOC!$B$1:$B$349,"ISCOM_LIL") -> 0 | F50: =SUMIFS(_CALC_ALLOC!$AJ$1:$AJ$349,_CALC_ALLOC!$A$1:$A$349,"2026",_CALC_ALLOC!$B$1:$B$349,"ISCOM_LIL") -> 0 | G50: =SUMIFS(_CALC_ALLOC!$AK$1:$AK$349,_CALC_ALLOC!$A$1:$A$349,"2026",_CALC_ALLOC!$B$1:$B$349,"ISCOM_LIL") -> 0 | H50: =SUMIFS(_CALC_ALLOC!$AL$1:$AL$349,_CALC_ALLOC!$A$1:$A$349,"2026",_CALC_ALLOC!$B$1:$B$349,"ISCOM_LIL") -> 0 | I50: =SUMIFS(_CALC_ALLOC!$AR$1:$AR$349,_CALC_ALLOC!$A$1:$A$349,"2026",_CALC_ALLOC!$B$1:$B$349,"ISCOM_LIL") -> 0 | J50: =SUMIFS(_CALC_ALLOC!$AM$1:$AM$349,_CALC_ALLOC!$A$1:$A$349,"2026",_CALC_ALLOC!$B$1:$B$349,"ISCOM_LIL") -> 0 | K50: =E50+F50+G50+H50+I50+J50 -> 0 | L50: =SUMIFS(_CALC_ALLOC!$AN$1:$AN$349,_CALC_ALLOC!$A$1:$A$349,"2026",_CALC_ALLOC!$B$1:$B$349,"ISCOM_LIL") -> 0 | M50: =IFERROR(L50/D50,0) -> 0
B51: BAC_COM B1 INIT | C51: =SUMIFS(_CALC_ALLOC!$G$1:$G$349,_CALC_ALLOC!$A$1:$A$349,"2026",_CALC_ALLOC!$B$1:$B$349,"ISCOM_LIL",_CALC_ALLOC!$D$1:$D$349,"BAC_COM",_CALC_ALLOC!$E$1:$E$349,"B1",_CALC_ALLOC!$F$1:$F$349,"INIT") -> 0 | D51: =SUMIFS(_CALC_ALLOC!$I$1:$I$349,_CALC_ALLOC!$A$1:$A$349,"2026",_CALC_ALLOC!$B$1:$B$349,"ISCOM_LIL",_CALC_ALLOC!$D$1:$D$349,"BAC_COM",_CALC_ALLOC!$E$1:$E$349,"B1",_CALC_ALLOC!$F$1:$F$349,"INIT") -> 0 | E51: =SUMIFS(_CALC_ALLOC!$AI$1:$AI$349,_CALC_ALLOC!$A$1:$A$349,"2026",_CALC_ALLOC!$B$1:$B$349,"ISCOM_LIL",_CALC_ALLOC!$D$1:$D$349,"BAC_COM",_CALC_ALLOC!$E$1:$E$349,"B1",_CALC_ALLOC!$F$1:$F$349,"INIT") -> 0 | F51: =SUMIFS(_CALC_ALLOC!$AJ$1:$AJ$349,_CALC_ALLOC!$A$1:$A$349,"2026",_CALC_ALLOC!$B$1:$B$349,"ISCOM_LIL",_CALC_ALLOC!$D$1:$D$349,"BAC_COM",_CALC_ALLOC!$E$1:$E$349,"B1",_CALC_ALLOC!$F$1:$F$349,"INIT") -> 0 | G51: =SUMIFS(_CALC_ALLOC!$AK$1:$AK$349,_CALC_ALLOC!$A$1:$A$349,"2026",_CALC_ALLOC!$B$1:$B$349,"ISCOM_LIL",_CALC_ALLOC!$D$1:$D$349,"BAC_COM",_CALC_ALLOC!$E$1:$E$349,"B1",_CALC_ALLOC!$F$1:$F$349,"INIT") -> 0 | H51: =SUMIFS(_CALC_ALLOC!$AL$1:$AL$349,_CALC_ALLOC!$A$1:$A$349,"2026",_CALC_ALLOC!$B$1:$B$349,"ISCOM_LIL",_CALC_ALLOC!$D$1:$D$349,"BAC_COM",_CALC_ALLOC!$E$1:$E$349,"B1",_CALC_ALLOC!$F$1:$F$349,"INIT") -> 0 | I51: =SUMIFS(_CALC_ALLOC!$AR$1:$AR$349,_CALC_ALLOC!$A$1:$A$349,"2026",_CALC_ALLOC!$B$1:$B$349,"ISCOM_LIL",_CALC_ALLOC!$D$1:$D$349,"BAC_COM",_CALC_ALLOC!$E$1:$E$349,"B1",_CALC_ALLOC!$F$1:$F$349,"INIT") -> 0 | J51: =SUMIFS(_CALC_ALLOC!$AM$1:$AM$349,_CALC_ALLOC!$A$1:$A$349,"2026",_CALC_ALLOC!$B$1:$B$349,"ISCOM_LIL",_CALC_ALLOC!$D$1:$D$349,"BAC_COM",_CALC_ALLOC!$E$1:$E$349,"B1",_CALC_ALLOC!$F$1:$F$349,"INIT") -> 0 | K51: =E51+F51+G51+H51+I51+J51 -> 0 | L51: =SUMIFS(_CALC_ALLOC!$AN$1:$AN$349,_CALC_ALLOC!$A$1:$A$349,"2026",_CALC_ALLOC!$B$1:$B$349,"ISCOM_LIL",_CALC_ALLOC!$D$1:$D$349,"BAC_COM",_CALC_ALLOC!$E$1:$E$349,"B1",_CALC_ALLOC!$F$1:$F$349,"INIT") -> 0 | M51: =IFERROR(L51/D51,0) -> 0
B52: BAC_COM B2 ALT | C52: =SUMIFS(_CALC_ALLOC!$G$1:$G$349,_CALC_ALLOC!$A$1:$A$349,"2026",_CALC_ALLOC!$B$1:$B$349,"ISCOM_LIL",_CALC_ALLOC!$D$1:$D$349,"BAC_COM",_CALC_ALLOC!$E$1:$E$349,"B2",_CALC_ALLOC!$F$1:$F$349,"ALT") -> 0 | D52: =SUMIFS(_CALC_ALLOC!$I$1:$I$349,_CALC_ALLOC!$A$1:$A$349,"2026",_CALC_ALLOC!$B$1:$B$349,"ISCOM_LIL",_CALC_ALLOC!$D$1:$D$349,"BAC_COM",_CALC_ALLOC!$E$1:$E$349,"B2",_CALC_ALLOC!$F$1:$F$349,"ALT") -> 0 | E52: =SUMIFS(_CALC_ALLOC!$AI$1:$AI$349,_CALC_ALLOC!$A$1:$A$349,"2026",_CALC_ALLOC!$B$1:$B$349,"ISCOM_LIL",_CALC_ALLOC!$D$1:$D$349,"BAC_COM",_CALC_ALLOC!$E$1:$E$349,"B2",_CALC_ALLOC!$F$1:$F$349,"ALT") -> 0 | F52: =SUMIFS(_CALC_ALLOC!$AJ$1:$AJ$349,_CALC_ALLOC!$A$1:$A$349,"2026",_CALC_ALLOC!$B$1:$B$349,"ISCOM_LIL",_CALC_ALLOC!$D$1:$D$349,"BAC_COM",_CALC_ALLOC!$E$1:$E$349,"B2",_CALC_ALLOC!$F$1:$F$349,"ALT") -> 0 | G52: =SUMIFS(_CALC_ALLOC!$AK$1:$AK$349,_CALC_ALLOC!$A$1:$A$349,"2026",_CALC_ALLOC!$B$1:$B$349,"ISCOM_LIL",_CALC_ALLOC!$D$1:$D$349,"BAC_COM",_CALC_ALLOC!$E$1:$E$349,"B2",_CALC_ALLOC!$F$1:$F$349,"ALT") -> 0 | H52: =SUMIFS(_CALC_ALLOC!$AL$1:$AL$349,_CALC_ALLOC!$A$1:$A$349,"2026",_CALC_ALLOC!$B$1:$B$349,"ISCOM_LIL",_CALC_ALLOC!$D$1:$D$349,"BAC_COM",_CALC_ALLOC!$E$1:$E$349,"B2",_CALC_ALLOC!$F$1:$F$349,"ALT") -> 0 | I52: =SUMIFS(_CALC_ALLOC!$AR$1:$AR$349,_CALC_ALLOC!$A$1:$A$349,"2026",_CALC_ALLOC!$B$1:$B$349,"ISCOM_LIL",_CALC_ALLOC!$D$1:$D$349,"BAC_COM",_CALC_ALLOC!$E$1:$E$349,"B2",_CALC_ALLOC!$F$1:$F$349,"ALT") -> 0 | J52: =SUMIFS(_CALC_ALLOC!$AM$1:$AM$349,_CALC_ALLOC!$A$1:$A$349,"2026",_CALC_ALLOC!$B$1:$B$349,"ISCOM_LIL",_CALC_ALLOC!$D$1:$D$349,"BAC_COM",_CALC_ALLOC!$E$1:$E$349,"B2",_CALC_ALLOC!$F$1:$F$349,"ALT") -> 0 | K52: =E52+F52+G52+H52+I52+J52 -> 0 | L52: =SUMIFS(_CALC_ALLOC!$AN$1:$AN$349,_CALC_ALLOC!$A$1:$A$349,"2026",_CALC_ALLOC!$B$1:$B$349,"ISCOM_LIL",_CALC_ALLOC!$D$1:$D$349,"BAC_COM",_CALC_ALLOC!$E$1:$E$349,"B2",_CALC_ALLOC!$F$1:$F$349,"ALT") -> 0 | M52: =IFERROR(L52/D52,0) -> 0
B53: BAC_COM B3 ALT | C53: =SUMIFS(_CALC_ALLOC!$G$1:$G$349,_CALC_ALLOC!$A$1:$A$349,"2026",_CALC_ALLOC!$B$1:$B$349,"ISCOM_LIL",_CALC_ALLOC!$D$1:$D$349,"BAC_COM",_CALC_ALLOC!$E$1:$E$349,"B3",_CALC_ALLOC!$F$1:$F$349,"ALT") -> 0 | D53: =SUMIFS(_CALC_ALLOC!$I$1:$I$349,_CALC_ALLOC!$A$1:$A$349,"2026",_CALC_ALLOC!$B$1:$B$349,"ISCOM_LIL",_CALC_ALLOC!$D$1:$D$349,"BAC_COM",_CALC_ALLOC!$E$1:$E$349,"B3",_CALC_ALLOC!$F$1:$F$349,"ALT") -> 0 | E53: =SUMIFS(_CALC_ALLOC!$AI$1:$AI$349,_CALC_ALLOC!$A$1:$A$349,"2026",_CALC_ALLOC!$B$1:$B$349,"ISCOM_LIL",_CALC_ALLOC!$D$1:$D$349,"BAC_COM",_CALC_ALLOC!$E$1:$E$349,"B3",_CALC_ALLOC!$F$1:$F$349,"ALT") -> 0 | F53: =SUMIFS(_CALC_ALLOC!$AJ$1:$AJ$349,_CALC_ALLOC!$A$1:$A$349,"2026",_CALC_ALLOC!$B$1:$B$349,"ISCOM_LIL",_CALC_ALLOC!$D$1:$D$349,"BAC_COM",_CALC_ALLOC!$E$1:$E$349,"B3",_CALC_ALLOC!$F$1:$F$349,"ALT") -> 0 | G53: =SUMIFS(_CALC_ALLOC!$AK$1:$AK$349,_CALC_ALLOC!$A$1:$A$349,"2026",_CALC_ALLOC!$B$1:$B$349,"ISCOM_LIL",_CALC_ALLOC!$D$1:$D$349,"BAC_COM",_CALC_ALLOC!$E$1:$E$349,"B3",_CALC_ALLOC!$F$1:$F$349,"ALT") -> 0 | H53: =SUMIFS(_CALC_ALLOC!$AL$1:$AL$349,_CALC_ALLOC!$A$1:$A$349,"2026",_CALC_ALLOC!$B$1:$B$349,"ISCOM_LIL",_CALC_ALLOC!$D$1:$D$349,"BAC_COM",_CALC_ALLOC!$E$1:$E$349,"B3",_CALC_ALLOC!$F$1:$F$349,"ALT") -> 0 | I53: =SUMIFS(_CALC_ALLOC!$AR$1:$AR$349,_CALC_ALLOC!$A$1:$A$349,"2026",_CALC_ALLOC!$B$1:$B$349,"ISCOM_LIL",_CALC_ALLOC!$D$1:$D$349,"BAC_COM",_CALC_ALLOC!$E$1:$E$349,"B3",_CALC_ALLOC!$F$1:$F$349,"ALT") -> 0 | J53: =SUMIFS(_CALC_ALLOC!$AM$1:$AM$349,_CALC_ALLOC!$A$1:$A$349,"2026",_CALC_ALLOC!$B$1:$B$349,"ISCOM_LIL",_CALC_ALLOC!$D$1:$D$349,"BAC_COM",_CALC_ALLOC!$E$1:$E$349,"B3",_CALC_ALLOC!$F$1:$F$349,"ALT") -> 0 | K53: =E53+F53+G53+H53+I53+J53 -> 0 | L53: =SUMIFS(_CALC_ALLOC!$AN$1:$AN$349,_CALC_ALLOC!$A$1:$A$349,"2026",_CALC_ALLOC!$B$1:$B$349,"ISCOM_LIL",_CALC_ALLOC!$D$1:$D$349,"BAC_COM",_CALC_ALLOC!$E$1:$E$349,"B3",_CALC_ALLOC!$F$1:$F$349,"ALT") -> 0 | M53: =IFERROR(L53/D53,0) -> 0
B54: MAS_COM M1 ALT | C54: =SUMIFS(_CALC_ALLOC!$G$1:$G$349,_CALC_ALLOC!$A$1:$A$349,"2026",_CALC_ALLOC!$B$1:$B$349,"ISCOM_LIL",_CALC_ALLOC!$D$1:$D$349,"MAS_COM",_CALC_ALLOC!$E$1:$E$349,"M1",_CALC_ALLOC!$F$1:$F$349,"ALT") -> 0 | D54: =SUMIFS(_CALC_ALLOC!$I$1:$I$349,_CALC_ALLOC!$A$1:$A$349,"2026",_CALC_ALLOC!$B$1:$B$349,"ISCOM_LIL",_CALC_ALLOC!$D$1:$D$349,"MAS_COM",_CALC_ALLOC!$E$1:$E$349,"M1",_CALC_ALLOC!$F$1:$F$349,"ALT") -> 0 | E54: =SUMIFS(_CALC_ALLOC!$AI$1:$AI$349,_CALC_ALLOC!$A$1:$A$349,"2026",_CALC_ALLOC!$B$1:$B$349,"ISCOM_LIL",_CALC_ALLOC!$D$1:$D$349,"MAS_COM",_CALC_ALLOC!$E$1:$E$349,"M1",_CALC_ALLOC!$F$1:$F$349,"ALT") -> 0 | F54: =SUMIFS(_CALC_ALLOC!$AJ$1:$AJ$349,_CALC_ALLOC!$A$1:$A$349,"2026",_CALC_ALLOC!$B$1:$B$349,"ISCOM_LIL",_CALC_ALLOC!$D$1:$D$349,"MAS_COM",_CALC_ALLOC!$E$1:$E$349,"M1",_CALC_ALLOC!$F$1:$F$349,"ALT") -> 0 | G54: =SUMIFS(_CALC_ALLOC!$AK$1:$AK$349,_CALC_ALLOC!$A$1:$A$349,"2026",_CALC_ALLOC!$B$1:$B$349,"ISCOM_LIL",_CALC_ALLOC!$D$1:$D$349,"MAS_COM",_CALC_ALLOC!$E$1:$E$349,"M1",_CALC_ALLOC!$F$1:$F$349,"ALT") -> 0 | H54: =SUMIFS(_CALC_ALLOC!$AL$1:$AL$349,_CALC_ALLOC!$A$1:$A$349,"2026",_CALC_ALLOC!$B$1:$B$349,"ISCOM_LIL",_CALC_ALLOC!$D$1:$D$349,"MAS_COM",_CALC_ALLOC!$E$1:$E$349,"M1",_CALC_ALLOC!$F$1:$F$349,"ALT") -> 0 | I54: =SUMIFS(_CALC_ALLOC!$AR$1:$AR$349,_CALC_ALLOC!$A$1:$A$349,"2026",_CALC_ALLOC!$B$1:$B$349,"ISCOM_LIL",_CALC_ALLOC!$D$1:$D$349,"MAS_COM",_CALC_ALLOC!$E$1:$E$349,"M1",_CALC_ALLOC!$F$1:$F$349,"ALT") -> 0 | J54: =SUMIFS(_CALC_ALLOC!$AM$1:$AM$349,_CALC_ALLOC!$A$1:$A$349,"2026",_CALC_ALLOC!$B$1:$B$349,"ISCOM_LIL",_CALC_ALLOC!$D$1:$D$349,"MAS_COM",_CALC_ALLOC!$E$1:$E$349,"M1",_CALC_ALLOC!$F$1:$F$349,"ALT") -> 0 | K54: =E54+F54+G54+H54+I54+J54 -> 0 | L54: =SUMIFS(_CALC_ALLOC!$AN$1:$AN$349,_CALC_ALLOC!$A$1:$A$349,"2026",_CALC_ALLOC!$B$1:$B$349,"ISCOM_LIL",_CALC_ALLOC!$D$1:$D$349,"MAS_COM",_CALC_ALLOC!$E$1:$E$349,"M1",_CALC_ALLOC!$F$1:$F$349,"ALT") -> 0 | M54: =IFERROR(L54/D54,0) -> 0
B55: MAS_COM M2 ALT | C55: =SUMIFS(_CALC_ALLOC!$G$1:$G$349,_CALC_ALLOC!$A$1:$A$349,"2026",_CALC_ALLOC!$B$1:$B$349,"ISCOM_LIL",_CALC_ALLOC!$D$1:$D$349,"MAS_COM",_CALC_ALLOC!$E$1:$E$349,"M2",_CALC_ALLOC!$F$1:$F$349,"ALT") -> 0 | D55: =SUMIFS(_CALC_ALLOC!$I$1:$I$349,_CALC_ALLOC!$A$1:$A$349,"2026",_CALC_ALLOC!$B$1:$B$349,"ISCOM_LIL",_CALC_ALLOC!$D$1:$D$349,"MAS_COM",_CALC_ALLOC!$E$1:$E$349,"M2",_CALC_ALLOC!$F$1:$F$349,"ALT") -> 0 | E55: =SUMIFS(_CALC_ALLOC!$AI$1:$AI$349,_CALC_ALLOC!$A$1:$A$349,"2026",_CALC_ALLOC!$B$1:$B$349,"ISCOM_LIL",_CALC_ALLOC!$D$1:$D$349,"MAS_COM",_CALC_ALLOC!$E$1:$E$349,"M2",_CALC_ALLOC!$F$1:$F$349,"ALT") -> 0 | F55: =SUMIFS(_CALC_ALLOC!$AJ$1:$AJ$349,_CALC_ALLOC!$A$1:$A$349,"2026",_CALC_ALLOC!$B$1:$B$349,"ISCOM_LIL",_CALC_ALLOC!$D$1:$D$349,"MAS_COM",_CALC_ALLOC!$E$1:$E$349,"M2",_CALC_ALLOC!$F$1:$F$349,"ALT") -> 0 | G55: =SUMIFS(_CALC_ALLOC!$AK$1:$AK$349,_CALC_ALLOC!$A$1:$A$349,"2026",_CALC_ALLOC!$B$1:$B$349,"ISCOM_LIL",_CALC_ALLOC!$D$1:$D$349,"MAS_COM",_CALC_ALLOC!$E$1:$E$349,"M2",_CALC_ALLOC!$F$1:$F$349,"ALT") -> 0 | H55: =SUMIFS(_CALC_ALLOC!$AL$1:$AL$349,_CALC_ALLOC!$A$1:$A$349,"2026",_CALC_ALLOC!$B$1:$B$349,"ISCOM_LIL",_CALC_ALLOC!$D$1:$D$349,"MAS_COM",_CALC_ALLOC!$E$1:$E$349,"M2",_CALC_ALLOC!$F$1:$F$349,"ALT") -> 0 | I55: =SUMIFS(_CALC_ALLOC!$AR$1:$AR$349,_CALC_ALLOC!$A$1:$A$349,"2026",_CALC_ALLOC!$B$1:$B$349,"ISCOM_LIL",_CALC_ALLOC!$D$1:$D$349,"MAS_COM",_CALC_ALLOC!$E$1:$E$349,"M2",_CALC_ALLOC!$F$1:$F$349,"ALT") -> 0 | J55: =SUMIFS(_CALC_ALLOC!$AM$1:$AM$349,_CALC_ALLOC!$A$1:$A$349,"2026",_CALC_ALLOC!$B$1:$B$349,"ISCOM_LIL",_CALC_ALLOC!$D$1:$D$349,"MAS_COM",_CALC_ALLOC!$E$1:$E$349,"M2",_CALC_ALLOC!$F$1:$F$349,"ALT") -> 0 | K55: =E55+F55+G55+H55+I55+J55 -> 0 | L55: =SUMIFS(_CALC_ALLOC!$AN$1:$AN$349,_CALC_ALLOC!$A$1:$A$349,"2026",_CALC_ALLOC!$B$1:$B$349,"ISCOM_LIL",_CALC_ALLOC!$D$1:$D$349,"MAS_COM",_CALC_ALLOC!$E$1:$E$349,"M2",_CALC_ALLOC!$F$1:$F$349,"ALT") -> 0 | M55: =IFERROR(L55/D55,0) -> 0
B56: Toulouse (ISCOM_TLS) | C56: =SUMIFS(_CALC_ALLOC!$G$1:$G$349,_CALC_ALLOC!$A$1:$A$349,"2026",_CALC_ALLOC!$B$1:$B$349,"ISCOM_TLS") -> 0 | D56: =SUMIFS(_CALC_ALLOC!$I$1:$I$349,_CALC_ALLOC!$A$1:$A$349,"2026",_CALC_ALLOC!$B$1:$B$349,"ISCOM_TLS") -> 0 | E56: =SUMIFS(_CALC_ALLOC!$AI$1:$AI$349,_CALC_ALLOC!$A$1:$A$349,"2026",_CALC_ALLOC!$B$1:$B$349,"ISCOM_TLS") -> 0 | F56: =SUMIFS(_CALC_ALLOC!$AJ$1:$AJ$349,_CALC_ALLOC!$A$1:$A$349,"2026",_CALC_ALLOC!$B$1:$B$349,"ISCOM_TLS") -> 0 | G56: =SUMIFS(_CALC_ALLOC!$AK$1:$AK$349,_CALC_ALLOC!$A$1:$A$349,"2026",_CALC_ALLOC!$B$1:$B$349,"ISCOM_TLS") -> 0 | H56: =SUMIFS(_CALC_ALLOC!$AL$1:$AL$349,_CALC_ALLOC!$A$1:$A$349,"2026",_CALC_ALLOC!$B$1:$B$349,"ISCOM_TLS") -> 0 | I56: =SUMIFS(_CALC_ALLOC!$AR$1:$AR$349,_CALC_ALLOC!$A$1:$A$349,"2026",_CALC_ALLOC!$B$1:$B$349,"ISCOM_TLS") -> 0 | J56: =SUMIFS(_CALC_ALLOC!$AM$1:$AM$349,_CALC_ALLOC!$A$1:$A$349,"2026",_CALC_ALLOC!$B$1:$B$349,"ISCOM_TLS") -> 0 | K56: =E56+F56+G56+H56+I56+J56 -> 0 | L56: =SUMIFS(_CALC_ALLOC!$AN$1:$AN$349,_CALC_ALLOC!$A$1:$A$349,"2026",_CALC_ALLOC!$B$1:$B$349,"ISCOM_TLS") -> 0 | M56: =IFERROR(L56/D56,0) -> 0
B57: BAC_COM B1 INIT | C57: =SUMIFS(_CALC_ALLOC!$G$1:$G$349,_CALC_ALLOC!$A$1:$A$349,"2026",_CALC_ALLOC!$B$1:$B$349,"ISCOM_TLS",_CALC_ALLOC!$D$1:$D$349,"BAC_COM",_CALC_ALLOC!$E$1:$E$349,"B1",_CALC_ALLOC!$F$1:$F$349,"INIT") -> 0 | D57: =SUMIFS(_CALC_ALLOC!$I$1:$I$349,_CALC_ALLOC!$A$1:$A$349,"2026",_CALC_ALLOC!$B$1:$B$349,"ISCOM_TLS",_CALC_ALLOC!$D$1:$D$349,"BAC_COM",_CALC_ALLOC!$E$1:$E$349,"B1",_CALC_ALLOC!$F$1:$F$349,"INIT") -> 0 | E57: =SUMIFS(_CALC_ALLOC!$AI$1:$AI$349,_CALC_ALLOC!$A$1:$A$349,"2026",_CALC_ALLOC!$B$1:$B$349,"ISCOM_TLS",_CALC_ALLOC!$D$1:$D$349,"BAC_COM",_CALC_ALLOC!$E$1:$E$349,"B1",_CALC_ALLOC!$F$1:$F$349,"INIT") -> 0 | F57: =SUMIFS(_CALC_ALLOC!$AJ$1:$AJ$349,_CALC_ALLOC!$A$1:$A$349,"2026",_CALC_ALLOC!$B$1:$B$349,"ISCOM_TLS",_CALC_ALLOC!$D$1:$D$349,"BAC_COM",_CALC_ALLOC!$E$1:$E$349,"B1",_CALC_ALLOC!$F$1:$F$349,"INIT") -> 0 | G57: =SUMIFS(_CALC_ALLOC!$AK$1:$AK$349,_CALC_ALLOC!$A$1:$A$349,"2026",_CALC_ALLOC!$B$1:$B$349,"ISCOM_TLS",_CALC_ALLOC!$D$1:$D$349,"BAC_COM",_CALC_ALLOC!$E$1:$E$349,"B1",_CALC_ALLOC!$F$1:$F$349,"INIT") -> 0 | H57: =SUMIFS(_CALC_ALLOC!$AL$1:$AL$349,_CALC_ALLOC!$A$1:$A$349,"2026",_CALC_ALLOC!$B$1:$B$349,"ISCOM_TLS",_CALC_ALLOC!$D$1:$D$349,"BAC_COM",_CALC_ALLOC!$E$1:$E$349,"B1",_CALC_ALLOC!$F$1:$F$349,"INIT") -> 0 | I57: =SUMIFS(_CALC_ALLOC!$AR$1:$AR$349,_CALC_ALLOC!$A$1:$A$349,"2026",_CALC_ALLOC!$B$1:$B$349,"ISCOM_TLS",_CALC_ALLOC!$D$1:$D$349,"BAC_COM",_CALC_ALLOC!$E$1:$E$349,"B1",_CALC_ALLOC!$F$1:$F$349,"INIT") -> 0 | J57: =SUMIFS(_CALC_ALLOC!$AM$1:$AM$349,_CALC_ALLOC!$A$1:$A$349,"2026",_CALC_ALLOC!$B$1:$B$349,"ISCOM_TLS",_CALC_ALLOC!$D$1:$D$349,"BAC_COM",_CALC_ALLOC!$E$1:$E$349,"B1",_CALC_ALLOC!$F$1:$F$349,"INIT") -> 0 | K57: =E57+F57+G57+H57+I57+J57 -> 0 | L57: =SUMIFS(_CALC_ALLOC!$AN$1:$AN$349,_CALC_ALLOC!$A$1:$A$349,"2026",_CALC_ALLOC!$B$1:$B$349,"ISCOM_TLS",_CALC_ALLOC!$D$1:$D$349,"BAC_COM",_CALC_ALLOC!$E$1:$E$349,"B1",_CALC_ALLOC!$F$1:$F$349,"INIT") -> 0 | M57: =IFERROR(L57/D57,0) -> 0
B58: BAC_COM B2 ALT | C58: =SUMIFS(_CALC_ALLOC!$G$1:$G$349,_CALC_ALLOC!$A$1:$A$349,"2026",_CALC_ALLOC!$B$1:$B$349,"ISCOM_TLS",_CALC_ALLOC!$D$1:$D$349,"BAC_COM",_CALC_ALLOC!$E$1:$E$349,"B2",_CALC_ALLOC!$F$1:$F$349,"ALT") -> 0 | D58: =SUMIFS(_CALC_ALLOC!$I$1:$I$349,_CALC_ALLOC!$A$1:$A$349,"2026",_CALC_ALLOC!$B$1:$B$349,"ISCOM_TLS",_CALC_ALLOC!$D$1:$D$349,"BAC_COM",_CALC_ALLOC!$E$1:$E$349,"B2",_CALC_ALLOC!$F$1:$F$349,"ALT") -> 0 | E58: =SUMIFS(_CALC_ALLOC!$AI$1:$AI$349,_CALC_ALLOC!$A$1:$A$349,"2026",_CALC_ALLOC!$B$1:$B$349,"ISCOM_TLS",_CALC_ALLOC!$D$1:$D$349,"BAC_COM",_CALC_ALLOC!$E$1:$E$349,"B2",_CALC_ALLOC!$F$1:$F$349,"ALT") -> 0 | F58: =SUMIFS(_CALC_ALLOC!$AJ$1:$AJ$349,_CALC_ALLOC!$A$1:$A$349,"2026",_CALC_ALLOC!$B$1:$B$349,"ISCOM_TLS",_CALC_ALLOC!$D$1:$D$349,"BAC_COM",_CALC_ALLOC!$E$1:$E$349,"B2",_CALC_ALLOC!$F$1:$F$349,"ALT") -> 0 | G58: =SUMIFS(_CALC_ALLOC!$AK$1:$AK$349,_CALC_ALLOC!$A$1:$A$349,"2026",_CALC_ALLOC!$B$1:$B$349,"ISCOM_TLS",_CALC_ALLOC!$D$1:$D$349,"BAC_COM",_CALC_ALLOC!$E$1:$E$349,"B2",_CALC_ALLOC!$F$1:$F$349,"ALT") -> 0 | H58: =SUMIFS(_CALC_ALLOC!$AL$1:$AL$349,_CALC_ALLOC!$A$1:$A$349,"2026",_CALC_ALLOC!$B$1:$B$349,"ISCOM_TLS",_CALC_ALLOC!$D$1:$D$349,"BAC_COM",_CALC_ALLOC!$E$1:$E$349,"B2",_CALC_ALLOC!$F$1:$F$349,"ALT") -> 0 | I58: =SUMIFS(_CALC_ALLOC!$AR$1:$AR$349,_CALC_ALLOC!$A$1:$A$349,"2026",_CALC_ALLOC!$B$1:$B$349,"ISCOM_TLS",_CALC_ALLOC!$D$1:$D$349,"BAC_COM",_CALC_ALLOC!$E$1:$E$349,"B2",_CALC_ALLOC!$F$1:$F$349,"ALT") -> 0 | J58: =SUMIFS(_CALC_ALLOC!$AM$1:$AM$349,_CALC_ALLOC!$A$1:$A$349,"2026",_CALC_ALLOC!$B$1:$B$349,"ISCOM_TLS",_CALC_ALLOC!$D$1:$D$349,"BAC_COM",_CALC_ALLOC!$E$1:$E$349,"B2",_CALC_ALLOC!$F$1:$F$349,"ALT") -> 0 | K58: =E58+F58+G58+H58+I58+J58 -> 0 | L58: =SUMIFS(_CALC_ALLOC!$AN$1:$AN$349,_CALC_ALLOC!$A$1:$A$349,"2026",_CALC_ALLOC!$B$1:$B$349,"ISCOM_TLS",_CALC_ALLOC!$D$1:$D$349,"BAC_COM",_CALC_ALLOC!$E$1:$E$349,"B2",_CALC_ALLOC!$F$1:$F$349,"ALT") -> 0 | M58: =IFERROR(L58/D58,0) -> 0
B59: BAC_COM B3 ALT | C59: =SUMIFS(_CALC_ALLOC!$G$1:$G$349,_CALC_ALLOC!$A$1:$A$349,"2026",_CALC_ALLOC!$B$1:$B$349,"ISCOM_TLS",_CALC_ALLOC!$D$1:$D$349,"BAC_COM",_CALC_ALLOC!$E$1:$E$349,"B3",_CALC_ALLOC!$F$1:$F$349,"ALT") -> 0 | D59: =SUMIFS(_CALC_ALLOC!$I$1:$I$349,_CALC_ALLOC!$A$1:$A$349,"2026",_CALC_ALLOC!$B$1:$B$349,"ISCOM_TLS",_CALC_ALLOC!$D$1:$D$349,"BAC_COM",_CALC_ALLOC!$E$1:$E$349,"B3",_CALC_ALLOC!$F$1:$F$349,"ALT") -> 0 | E59: =SUMIFS(_CALC_ALLOC!$AI$1:$AI$349,_CALC_ALLOC!$A$1:$A$349,"2026",_CALC_ALLOC!$B$1:$B$349,"ISCOM_TLS",_CALC_ALLOC!$D$1:$D$349,"BAC_COM",_CALC_ALLOC!$E$1:$E$349,"B3",_CALC_ALLOC!$F$1:$F$349,"ALT") -> 0 | F59: =SUMIFS(_CALC_ALLOC!$AJ$1:$AJ$349,_CALC_ALLOC!$A$1:$A$349,"2026",_CALC_ALLOC!$B$1:$B$349,"ISCOM_TLS",_CALC_ALLOC!$D$1:$D$349,"BAC_COM",_CALC_ALLOC!$E$1:$E$349,"B3",_CALC_ALLOC!$F$1:$F$349,"ALT") -> 0 | G59: =SUMIFS(_CALC_ALLOC!$AK$1:$AK$349,_CALC_ALLOC!$A$1:$A$349,"2026",_CALC_ALLOC!$B$1:$B$349,"ISCOM_TLS",_CALC_ALLOC!$D$1:$D$349,"BAC_COM",_CALC_ALLOC!$E$1:$E$349,"B3",_CALC_ALLOC!$F$1:$F$349,"ALT") -> 0 | H59: =SUMIFS(_CALC_ALLOC!$AL$1:$AL$349,_CALC_ALLOC!$A$1:$A$349,"2026",_CALC_ALLOC!$B$1:$B$349,"ISCOM_TLS",_CALC_ALLOC!$D$1:$D$349,"BAC_COM",_CALC_ALLOC!$E$1:$E$349,"B3",_CALC_ALLOC!$F$1:$F$349,"ALT") -> 0 | I59: =SUMIFS(_CALC_ALLOC!$AR$1:$AR$349,_CALC_ALLOC!$A$1:$A$349,"2026",_CALC_ALLOC!$B$1:$B$349,"ISCOM_TLS",_CALC_ALLOC!$D$1:$D$349,"BAC_COM",_CALC_ALLOC!$E$1:$E$349,"B3",_CALC_ALLOC!$F$1:$F$349,"ALT") -> 0 | J59: =SUMIFS(_CALC_ALLOC!$AM$1:$AM$349,_CALC_ALLOC!$A$1:$A$349,"2026",_CALC_ALLOC!$B$1:$B$349,"ISCOM_TLS",_CALC_ALLOC!$D$1:$D$349,"BAC_COM",_CALC_ALLOC!$E$1:$E$349,"B3",_CALC_ALLOC!$F$1:$F$349,"ALT") -> 0 | K59: =E59+F59+G59+H59+I59+J59 -> 0 | L59: =SUMIFS(_CALC_ALLOC!$AN$1:$AN$349,_CALC_ALLOC!$A$1:$A$349,"2026",_CALC_ALLOC!$B$1:$B$349,"ISCOM_TLS",_CALC_ALLOC!$D$1:$D$349,"BAC_COM",_CALC_ALLOC!$E$1:$E$349,"B3",_CALC_ALLOC!$F$1:$F$349,"ALT") -> 0 | M59: =IFERROR(L59/D59,0) -> 0
B60: MAS_COM M1 ALT | C60: =SUMIFS(_CALC_ALLOC!$G$1:$G$349,_CALC_ALLOC!$A$1:$A$349,"2026",_CALC_ALLOC!$B$1:$B$349,"ISCOM_TLS",_CALC_ALLOC!$D$1:$D$349,"MAS_COM",_CALC_ALLOC!$E$1:$E$349,"M1",_CALC_ALLOC!$F$1:$F$349,"ALT") -> 0 | D60: =SUMIFS(_CALC_ALLOC!$I$1:$I$349,_CALC_ALLOC!$A$1:$A$349,"2026",_CALC_ALLOC!$B$1:$B$349,"ISCOM_TLS",_CALC_ALLOC!$D$1:$D$349,"MAS_COM",_CALC_ALLOC!$E$1:$E$349,"M1",_CALC_ALLOC!$F$1:$F$349,"ALT") -> 0 | E60: =SUMIFS(_CALC_ALLOC!$AI$1:$AI$349,_CALC_ALLOC!$A$1:$A$349,"2026",_CALC_ALLOC!$B$1:$B$349,"ISCOM_TLS",_CALC_ALLOC!$D$1:$D$349,"MAS_COM",_CALC_ALLOC!$E$1:$E$349,"M1",_CALC_ALLOC!$F$1:$F$349,"ALT") -> 0 | F60: =SUMIFS(_CALC_ALLOC!$AJ$1:$AJ$349,_CALC_ALLOC!$A$1:$A$349,"2026",_CALC_ALLOC!$B$1:$B$349,"ISCOM_TLS",_CALC_ALLOC!$D$1:$D$349,"MAS_COM",_CALC_ALLOC!$E$1:$E$349,"M1",_CALC_ALLOC!$F$1:$F$349,"ALT") -> 0 | G60: =SUMIFS(_CALC_ALLOC!$AK$1:$AK$349,_CALC_ALLOC!$A$1:$A$349,"2026",_CALC_ALLOC!$B$1:$B$349,"ISCOM_TLS",_CALC_ALLOC!$D$1:$D$349,"MAS_COM",_CALC_ALLOC!$E$1:$E$349,"M1",_CALC_ALLOC!$F$1:$F$349,"ALT") -> 0 | H60: =SUMIFS(_CALC_ALLOC!$AL$1:$AL$349,_CALC_ALLOC!$A$1:$A$349,"2026",_CALC_ALLOC!$B$1:$B$349,"ISCOM_TLS",_CALC_ALLOC!$D$1:$D$349,"MAS_COM",_CALC_ALLOC!$E$1:$E$349,"M1",_CALC_ALLOC!$F$1:$F$349,"ALT") -> 0 | I60: =SUMIFS(_CALC_ALLOC!$AR$1:$AR$349,_CALC_ALLOC!$A$1:$A$349,"2026",_CALC_ALLOC!$B$1:$B$349,"ISCOM_TLS",_CALC_ALLOC!$D$1:$D$349,"MAS_COM",_CALC_ALLOC!$E$1:$E$349,"M1",_CALC_ALLOC!$F$1:$F$349,"ALT") -> 0 | J60: =SUMIFS(_CALC_ALLOC!$AM$1:$AM$349,_CALC_ALLOC!$A$1:$A$349,"2026",_CALC_ALLOC!$B$1:$B$349,"ISCOM_TLS",_CALC_ALLOC!$D$1:$D$349,"MAS_COM",_CALC_ALLOC!$E$1:$E$349,"M1",_CALC_ALLOC!$F$1:$F$349,"ALT") -> 0 | K60: =E60+F60+G60+H60+I60+J60 -> 0 | L60: =SUMIFS(_CALC_ALLOC!$AN$1:$AN$349,_CALC_ALLOC!$A$1:$A$349,"2026",_CALC_ALLOC!$B$1:$B$349,"ISCOM_TLS",_CALC_ALLOC!$D$1:$D$349,"MAS_COM",_CALC_ALLOC!$E$1:$E$349,"M1",_CALC_ALLOC!$F$1:$F$349,"ALT") -> 0 | M60: =IFERROR(L60/D60,0) -> 0
B61: MAS_COM M2 ALT | C61: =SUMIFS(_CALC_ALLOC!$G$1:$G$349,_CALC_ALLOC!$A$1:$A$349,"2026",_CALC_ALLOC!$B$1:$B$349,"ISCOM_TLS",_CALC_ALLOC!$D$1:$D$349,"MAS_COM",_CALC_ALLOC!$E$1:$E$349,"M2",_CALC_ALLOC!$F$1:$F$349,"ALT") -> 0 | D61: =SUMIFS(_CALC_ALLOC!$I$1:$I$349,_CALC_ALLOC!$A$1:$A$349,"2026",_CALC_ALLOC!$B$1:$B$349,"ISCOM_TLS",_CALC_ALLOC!$D$1:$D$349,"MAS_COM",_CALC_ALLOC!$E$1:$E$349,"M2",_CALC_ALLOC!$F$1:$F$349,"ALT") -> 0 | E61: =SUMIFS(_CALC_ALLOC!$AI$1:$AI$349,_CALC_ALLOC!$A$1:$A$349,"2026",_CALC_ALLOC!$B$1:$B$349,"ISCOM_TLS",_CALC_ALLOC!$D$1:$D$349,"MAS_COM",_CALC_ALLOC!$E$1:$E$349,"M2",_CALC_ALLOC!$F$1:$F$349,"ALT") -> 0 | F61: =SUMIFS(_CALC_ALLOC!$AJ$1:$AJ$349,_CALC_ALLOC!$A$1:$A$349,"2026",_CALC_ALLOC!$B$1:$B$349,"ISCOM_TLS",_CALC_ALLOC!$D$1:$D$349,"MAS_COM",_CALC_ALLOC!$E$1:$E$349,"M2",_CALC_ALLOC!$F$1:$F$349,"ALT") -> 0 | G61: =SUMIFS(_CALC_ALLOC!$AK$1:$AK$349,_CALC_ALLOC!$A$1:$A$349,"2026",_CALC_ALLOC!$B$1:$B$349,"ISCOM_TLS",_CALC_ALLOC!$D$1:$D$349,"MAS_COM",_CALC_ALLOC!$E$1:$E$349,"M2",_CALC_ALLOC!$F$1:$F$349,"ALT") -> 0 | H61: =SUMIFS(_CALC_ALLOC!$AL$1:$AL$349,_CALC_ALLOC!$A$1:$A$349,"2026",_CALC_ALLOC!$B$1:$B$349,"ISCOM_TLS",_CALC_ALLOC!$D$1:$D$349,"MAS_COM",_CALC_ALLOC!$E$1:$E$349,"M2",_CALC_ALLOC!$F$1:$F$349,"ALT") -> 0 | I61: =SUMIFS(_CALC_ALLOC!$AR$1:$AR$349,_CALC_ALLOC!$A$1:$A$349,"2026",_CALC_ALLOC!$B$1:$B$349,"ISCOM_TLS",_CALC_ALLOC!$D$1:$D$349,"MAS_COM",_CALC_ALLOC!$E$1:$E$349,"M2",_CALC_ALLOC!$F$1:$F$349,"ALT") -> 0 | J61: =SUMIFS(_CALC_ALLOC!$AM$1:$AM$349,_CALC_ALLOC!$A$1:$A$349,"2026",_CALC_ALLOC!$B$1:$B$349,"ISCOM_TLS",_CALC_ALLOC!$D$1:$D$349,"MAS_COM",_CALC_ALLOC!$E$1:$E$349,"M2",_CALC_ALLOC!$F$1:$F$349,"ALT") -> 0 | K61: =E61+F61+G61+H61+I61+J61 -> 0 | L61: =SUMIFS(_CALC_ALLOC!$AN$1:$AN$349,_CALC_ALLOC!$A$1:$A$349,"2026",_CALC_ALLOC!$B$1:$B$349,"ISCOM_TLS",_CALC_ALLOC!$D$1:$D$349,"MAS_COM",_CALC_ALLOC!$E$1:$E$349,"M2",_CALC_ALLOC!$F$1:$F$349,"ALT") -> 0 | M61: =IFERROR(L61/D61,0) -> 0
B62: Ipac | C62: =SUMIFS(_CALC_ALLOC!$G$1:$G$349,_CALC_ALLOC!$A$1:$A$349,"2026",_CALC_ALLOC!$C$1:$C$349,"IPAC") -> 0 | D62: =SUMIFS(_CALC_ALLOC!$I$1:$I$349,_CALC_ALLOC!$A$1:$A$349,"2026",_CALC_ALLOC!$C$1:$C$349,"IPAC") -> 0 | E62: =SUMIFS(_CALC_ALLOC!$AI$1:$AI$349,_CALC_ALLOC!$A$1:$A$349,"2026",_CALC_ALLOC!$C$1:$C$349,"IPAC") -> 0 | F62: =SUMIFS(_CALC_ALLOC!$AJ$1:$AJ$349,_CALC_ALLOC!$A$1:$A$349,"2026",_CALC_ALLOC!$C$1:$C$349,"IPAC") -> 0 | G62: =SUMIFS(_CALC_ALLOC!$AK$1:$AK$349,_CALC_ALLOC!$A$1:$A$349,"2026",_CALC_ALLOC!$C$1:$C$349,"IPAC") -> 0 | H62: =SUMIFS(_CALC_ALLOC!$AL$1:$AL$349,_CALC_ALLOC!$A$1:$A$349,"2026",_CALC_ALLOC!$C$1:$C$349,"IPAC") -> 0 | I62: =SUMIFS(_CALC_ALLOC!$AR$1:$AR$349,_CALC_ALLOC!$A$1:$A$349,"2026",_CALC_ALLOC!$C$1:$C$349,"IPAC") -> 0 | J62: =SUMIFS(_CALC_ALLOC!$AM$1:$AM$349,_CALC_ALLOC!$A$1:$A$349,"2026",_CALC_ALLOC!$C$1:$C$349,"IPAC") -> 0 | K62: =E62+F62+G62+H62+I62+J62 -> 0 | L62: =SUMIFS(_CALC_ALLOC!$AN$1:$AN$349,_CALC_ALLOC!$A$1:$A$349,"2026",_CALC_ALLOC!$C$1:$C$349,"IPAC") -> 0 | M62: =IFERROR(L62/D62,0) -> 0
B63: Nantes (IPAC_NAN) | C63: =SUMIFS(_CALC_ALLOC!$G$1:$G$349,_CALC_ALLOC!$A$1:$A$349,"2026",_CALC_ALLOC!$B$1:$B$349,"IPAC_NAN") -> 0 | D63: =SUMIFS(_CALC_ALLOC!$I$1:$I$349,_CALC_ALLOC!$A$1:$A$349,"2026",_CALC_ALLOC!$B$1:$B$349,"IPAC_NAN") -> 0 | E63: =SUMIFS(_CALC_ALLOC!$AI$1:$AI$349,_CALC_ALLOC!$A$1:$A$349,"2026",_CALC_ALLOC!$B$1:$B$349,"IPAC_NAN") -> 0 | F63: =SUMIFS(_CALC_ALLOC!$AJ$1:$AJ$349,_CALC_ALLOC!$A$1:$A$349,"2026",_CALC_ALLOC!$B$1:$B$349,"IPAC_NAN") -> 0 | G63: =SUMIFS(_CALC_ALLOC!$AK$1:$AK$349,_CALC_ALLOC!$A$1:$A$349,"2026",_CALC_ALLOC!$B$1:$B$349,"IPAC_NAN") -> 0 | H63: =SUMIFS(_CALC_ALLOC!$AL$1:$AL$349,_CALC_ALLOC!$A$1:$A$349,"2026",_CALC_ALLOC!$B$1:$B$349,"IPAC_NAN") -> 0 | I63: =SUMIFS(_CALC_ALLOC!$AR$1:$AR$349,_CALC_ALLOC!$A$1:$A$349,"2026",_CALC_ALLOC!$B$1:$B$349,"IPAC_NAN") -> 0 | J63: =SUMIFS(_CALC_ALLOC!$AM$1:$AM$349,_CALC_ALLOC!$A$1:$A$349,"2026",_CALC_ALLOC!$B$1:$B$349,"IPAC_NAN") -> 0 | K63: =E63+F63+G63+H63+I63+J63 -> 0 | L63: =SUMIFS(_CALC_ALLOC!$AN$1:$AN$349,_CALC_ALLOC!$A$1:$A$349,"2026",_CALC_ALLOC!$B$1:$B$349,"IPAC_NAN") -> 0 | M63: =IFERROR(L63/D63,0) -> 0
B64: BAC_CCE B1 ALT | C64: =SUMIFS(_CALC_ALLOC!$G$1:$G$349,_CALC_ALLOC!$A$1:$A$349,"2026",_CALC_ALLOC!$B$1:$B$349,"IPAC_NAN",_CALC_ALLOC!$D$1:$D$349,"BAC_CCE",_CALC_ALLOC!$E$1:$E$349,"B1",_CALC_ALLOC!$F$1:$F$349,"ALT") -> 0 | D64: =SUMIFS(_CALC_ALLOC!$I$1:$I$349,_CALC_ALLOC!$A$1:$A$349,"2026",_CALC_ALLOC!$B$1:$B$349,"IPAC_NAN",_CALC_ALLOC!$D$1:$D$349,"BAC_CCE",_CALC_ALLOC!$E$1:$E$349,"B1",_CALC_ALLOC!$F$1:$F$349,"ALT") -> 0 | E64: =SUMIFS(_CALC_ALLOC!$AI$1:$AI$349,_CALC_ALLOC!$A$1:$A$349,"2026",_CALC_ALLOC!$B$1:$B$349,"IPAC_NAN",_CALC_ALLOC!$D$1:$D$349,"BAC_CCE",_CALC_ALLOC!$E$1:$E$349,"B1",_CALC_ALLOC!$F$1:$F$349,"ALT") -> 0 | F64: =SUMIFS(_CALC_ALLOC!$AJ$1:$AJ$349,_CALC_ALLOC!$A$1:$A$349,"2026",_CALC_ALLOC!$B$1:$B$349,"IPAC_NAN",_CALC_ALLOC!$D$1:$D$349,"BAC_CCE",_CALC_ALLOC!$E$1:$E$349,"B1",_CALC_ALLOC!$F$1:$F$349,"ALT") -> 0 | G64: =SUMIFS(_CALC_ALLOC!$AK$1:$AK$349,_CALC_ALLOC!$A$1:$A$349,"2026",_CALC_ALLOC!$B$1:$B$349,"IPAC_NAN",_CALC_ALLOC!$D$1:$D$349,"BAC_CCE",_CALC_ALLOC!$E$1:$E$349,"B1",_CALC_ALLOC!$F$1:$F$349,"ALT") -> 0 | H64: =SUMIFS(_CALC_ALLOC!$AL$1:$AL$349,_CALC_ALLOC!$A$1:$A$349,"2026",_CALC_ALLOC!$B$1:$B$349,"IPAC_NAN",_CALC_ALLOC!$D$1:$D$349,"BAC_CCE",_CALC_ALLOC!$E$1:$E$349,"B1",_CALC_ALLOC!$F$1:$F$349,"ALT") -> 0 | I64: =SUMIFS(_CALC_ALLOC!$AR$1:$AR$349,_CALC_ALLOC!$A$1:$A$349,"2026",_CALC_ALLOC!$B$1:$B$349,"IPAC_NAN",_CALC_ALLOC!$D$1:$D$349,"BAC_CCE",_CALC_ALLOC!$E$1:$E$349,"B1",_CALC_ALLOC!$F$1:$F$349,"ALT") -> 0 | J64: =SUMIFS(_CALC_ALLOC!$AM$1:$AM$349,_CALC_ALLOC!$A$1:$A$349,"2026",_CALC_ALLOC!$B$1:$B$349,"IPAC_NAN",_CALC_ALLOC!$D$1:$D$349,"BAC_CCE",_CALC_ALLOC!$E$1:$E$349,"B1",_CALC_ALLOC!$F$1:$F$349,"ALT") -> 0 | K64: =E64+F64+G64+H64+I64+J64 -> 0 | L64: =SUMIFS(_CALC_ALLOC!$AN$1:$AN$349,_CALC_ALLOC!$A$1:$A$349,"2026",_CALC_ALLOC!$B$1:$B$349,"IPAC_NAN",_CALC_ALLOC!$D$1:$D$349,"BAC_CCE",_CALC_ALLOC!$E$1:$E$349,"B1",_CALC_ALLOC!$F$1:$F$349,"ALT") -> 0 | M64: =IFERROR(L64/D64,0) -> 0
B65: BAC_CCE B2 ALT | C65: =SUMIFS(_CALC_ALLOC!$G$1:$G$349,_CALC_ALLOC!$A$1:$A$349,"2026",_CALC_ALLOC!$B$1:$B$349,"IPAC_NAN",_CALC_ALLOC!$D$1:$D$349,"BAC_CCE",_CALC_ALLOC!$E$1:$E$349,"B2",_CALC_ALLOC!$F$1:$F$349,"ALT") -> 0 | D65: =SUMIFS(_CALC_ALLOC!$I$1:$I$349,_CALC_ALLOC!$A$1:$A$349,"2026",_CALC_ALLOC!$B$1:$B$349,"IPAC_NAN",_CALC_ALLOC!$D$1:$D$349,"BAC_CCE",_CALC_ALLOC!$E$1:$E$349,"B2",_CALC_ALLOC!$F$1:$F$349,"ALT") -> 0 | E65: =SUMIFS(_CALC_ALLOC!$AI$1:$AI$349,_CALC_ALLOC!$A$1:$A$349,"2026",_CALC_ALLOC!$B$1:$B$349,"IPAC_NAN",_CALC_ALLOC!$D$1:$D$349,"BAC_CCE",_CALC_ALLOC!$E$1:$E$349,"B2",_CALC_ALLOC!$F$1:$F$349,"ALT") -> 0 | F65: =SUMIFS(_CALC_ALLOC!$AJ$1:$AJ$349,_CALC_ALLOC!$A$1:$A$349,"2026",_CALC_ALLOC!$B$1:$B$349,"IPAC_NAN",_CALC_ALLOC!$D$1:$D$349,"BAC_CCE",_CALC_ALLOC!$E$1:$E$349,"B2",_CALC_ALLOC!$F$1:$F$349,"ALT") -> 0 | G65: =SUMIFS(_CALC_ALLOC!$AK$1:$AK$349,_CALC_ALLOC!$A$1:$A$349,"2026",_CALC_ALLOC!$B$1:$B$349,"IPAC_NAN",_CALC_ALLOC!$D$1:$D$349,"BAC_CCE",_CALC_ALLOC!$E$1:$E$349,"B2",_CALC_ALLOC!$F$1:$F$349,"ALT") -> 0 | H65: =SUMIFS(_CALC_ALLOC!$AL$1:$AL$349,_CALC_ALLOC!$A$1:$A$349,"2026",_CALC_ALLOC!$B$1:$B$349,"IPAC_NAN",_CALC_ALLOC!$D$1:$D$349,"BAC_CCE",_CALC_ALLOC!$E$1:$E$349,"B2",_CALC_ALLOC!$F$1:$F$349,"ALT") -> 0 | I65: =SUMIFS(_CALC_ALLOC!$AR$1:$AR$349,_CALC_ALLOC!$A$1:$A$349,"2026",_CALC_ALLOC!$B$1:$B$349,"IPAC_NAN",_CALC_ALLOC!$D$1:$D$349,"BAC_CCE",_CALC_ALLOC!$E$1:$E$349,"B2",_CALC_ALLOC!$F$1:$F$349,"ALT") -> 0 | J65: =SUMIFS(_CALC_ALLOC!$AM$1:$AM$349,_CALC_ALLOC!$A$1:$A$349,"2026",_CALC_ALLOC!$B$1:$B$349,"IPAC_NAN",_CALC_ALLOC!$D$1:$D$349,"BAC_CCE",_CALC_ALLOC!$E$1:$E$349,"B2",_CALC_ALLOC!$F$1:$F$349,"ALT") -> 0 | K65: =E65+F65+G65+H65+I65+J65 -> 0 | L65: =SUMIFS(_CALC_ALLOC!$AN$1:$AN$349,_CALC_ALLOC!$A$1:$A$349,"2026",_CALC_ALLOC!$B$1:$B$349,"IPAC_NAN",_CALC_ALLOC!$D$1:$D$349,"BAC_CCE",_CALC_ALLOC!$E$1:$E$349,"B2",_CALC_ALLOC!$F$1:$F$349,"ALT") -> 0 | M65: =IFERROR(L65/D65,0) -> 0
B66: BAC_CCE B3 ALT | C66: =SUMIFS(_CALC_ALLOC!$G$1:$G$349,_CALC_ALLOC!$A$1:$A$349,"2026",_CALC_ALLOC!$B$1:$B$349,"IPAC_NAN",_CALC_ALLOC!$D$1:$D$349,"BAC_CCE",_CALC_ALLOC!$E$1:$E$349,"B3",_CALC_ALLOC!$F$1:$F$349,"ALT") -> 0 | D66: =SUMIFS(_CALC_ALLOC!$I$1:$I$349,_CALC_ALLOC!$A$1:$A$349,"2026",_CALC_ALLOC!$B$1:$B$349,"IPAC_NAN",_CALC_ALLOC!$D$1:$D$349,"BAC_CCE",_CALC_ALLOC!$E$1:$E$349,"B3",_CALC_ALLOC!$F$1:$F$349,"ALT") -> 0 | E66: =SUMIFS(_CALC_ALLOC!$AI$1:$AI$349,_CALC_ALLOC!$A$1:$A$349,"2026",_CALC_ALLOC!$B$1:$B$349,"IPAC_NAN",_CALC_ALLOC!$D$1:$D$349,"BAC_CCE",_CALC_ALLOC!$E$1:$E$349,"B3",_CALC_ALLOC!$F$1:$F$349,"ALT") -> 0 | F66: =SUMIFS(_CALC_ALLOC!$AJ$1:$AJ$349,_CALC_ALLOC!$A$1:$A$349,"2026",_CALC_ALLOC!$B$1:$B$349,"IPAC_NAN",_CALC_ALLOC!$D$1:$D$349,"BAC_CCE",_CALC_ALLOC!$E$1:$E$349,"B3",_CALC_ALLOC!$F$1:$F$349,"ALT") -> 0 | G66: =SUMIFS(_CALC_ALLOC!$AK$1:$AK$349,_CALC_ALLOC!$A$1:$A$349,"2026",_CALC_ALLOC!$B$1:$B$349,"IPAC_NAN",_CALC_ALLOC!$D$1:$D$349,"BAC_CCE",_CALC_ALLOC!$E$1:$E$349,"B3",_CALC_ALLOC!$F$1:$F$349,"ALT") -> 0 | H66: =SUMIFS(_CALC_ALLOC!$AL$1:$AL$349,_CALC_ALLOC!$A$1:$A$349,"2026",_CALC_ALLOC!$B$1:$B$349,"IPAC_NAN",_CALC_ALLOC!$D$1:$D$349,"BAC_CCE",_CALC_ALLOC!$E$1:$E$349,"B3",_CALC_ALLOC!$F$1:$F$349,"ALT") -> 0 | I66: =SUMIFS(_CALC_ALLOC!$AR$1:$AR$349,_CALC_ALLOC!$A$1:$A$349,"2026",_CALC_ALLOC!$B$1:$B$349,"IPAC_NAN",_CALC_ALLOC!$D$1:$D$349,"BAC_CCE",_CALC_ALLOC!$E$1:$E$349,"B3",_CALC_ALLOC!$F$1:$F$349,"ALT") -> 0 | J66: =SUMIFS(_CALC_ALLOC!$AM$1:$AM$349,_CALC_ALLOC!$A$1:$A$349,"2026",_CALC_ALLOC!$B$1:$B$349,"IPAC_NAN",_CALC_ALLOC!$D$1:$D$349,"BAC_CCE",_CALC_ALLOC!$E$1:$E$349,"B3",_CALC_ALLOC!$F$1:$F$349,"ALT") -> 0 | K66: =E66+F66+G66+H66+I66+J66 -> 0 | L66: =SUMIFS(_CALC_ALLOC!$AN$1:$AN$349,_CALC_ALLOC!$A$1:$A$349,"2026",_CALC_ALLOC!$B$1:$B$349,"IPAC_NAN",_CALC_ALLOC!$D$1:$D$349,"BAC_CCE",_CALC_ALLOC!$E$1:$E$349,"B3",_CALC_ALLOC!$F$1:$F$349,"ALT") -> 0 | M66: =IFERROR(L66/D66,0) -> 0
B67: Rennes (IPAC_REN) | C67: =SUMIFS(_CALC_ALLOC!$G$1:$G$349,_CALC_ALLOC!$A$1:$A$349,"2026",_CALC_ALLOC!$B$1:$B$349,"IPAC_REN") -> 0 | D67: =SUMIFS(_CALC_ALLOC!$I$1:$I$349,_CALC_ALLOC!$A$1:$A$349,"2026",_CALC_ALLOC!$B$1:$B$349,"IPAC_REN") -> 0 | E67: =SUMIFS(_CALC_ALLOC!$AI$1:$AI$349,_CALC_ALLOC!$A$1:$A$349,"2026",_CALC_ALLOC!$B$1:$B$349,"IPAC_REN") -> 0 | F67: =SUMIFS(_CALC_ALLOC!$AJ$1:$AJ$349,_CALC_ALLOC!$A$1:$A$349,"2026",_CALC_ALLOC!$B$1:$B$349,"IPAC_REN") -> 0 | G67: =SUMIFS(_CALC_ALLOC!$AK$1:$AK$349,_CALC_ALLOC!$A$1:$A$349,"2026",_CALC_ALLOC!$B$1:$B$349,"IPAC_REN") -> 0 | H67: =SUMIFS(_CALC_ALLOC!$AL$1:$AL$349,_CALC_ALLOC!$A$1:$A$349,"2026",_CALC_ALLOC!$B$1:$B$349,"IPAC_REN") -> 0 | I67: =SUMIFS(_CALC_ALLOC!$AR$1:$AR$349,_CALC_ALLOC!$A$1:$A$349,"2026",_CALC_ALLOC!$B$1:$B$349,"IPAC_REN") -> 0 | J67: =SUMIFS(_CALC_ALLOC!$AM$1:$AM$349,_CALC_ALLOC!$A$1:$A$349,"2026",_CALC_ALLOC!$B$1:$B$349,"IPAC_REN") -> 0 | K67: =E67+F67+G67+H67+I67+J67 -> 0 | L67: =SUMIFS(_CALC_ALLOC!$AN$1:$AN$349,_CALC_ALLOC!$A$1:$A$349,"2026",_CALC_ALLOC!$B$1:$B$349,"IPAC_REN") -> 0 | M67: =IFERROR(L67/D67,0) -> 0
B68: BAC_CCE B1 ALT | C68: =SUMIFS(_CALC_ALLOC!$G$1:$G$349,_CALC_ALLOC!$A$1:$A$349,"2026",_CALC_ALLOC!$B$1:$B$349,"IPAC_REN",_CALC_ALLOC!$D$1:$D$349,"BAC_CCE",_CALC_ALLOC!$E$1:$E$349,"B1",_CALC_ALLOC!$F$1:$F$349,"ALT") -> 0 | D68: =SUMIFS(_CALC_ALLOC!$I$1:$I$349,_CALC_ALLOC!$A$1:$A$349,"2026",_CALC_ALLOC!$B$1:$B$349,"IPAC_REN",_CALC_ALLOC!$D$1:$D$349,"BAC_CCE",_CALC_ALLOC!$E$1:$E$349,"B1",_CALC_ALLOC!$F$1:$F$349,"ALT") -> 0 | E68: =SUMIFS(_CALC_ALLOC!$AI$1:$AI$349,_CALC_ALLOC!$A$1:$A$349,"2026",_CALC_ALLOC!$B$1:$B$349,"IPAC_REN",_CALC_ALLOC!$D$1:$D$349,"BAC_CCE",_CALC_ALLOC!$E$1:$E$349,"B1",_CALC_ALLOC!$F$1:$F$349,"ALT") -> 0 | F68: =SUMIFS(_CALC_ALLOC!$AJ$1:$AJ$349,_CALC_ALLOC!$A$1:$A$349,"2026",_CALC_ALLOC!$B$1:$B$349,"IPAC_REN",_CALC_ALLOC!$D$1:$D$349,"BAC_CCE",_CALC_ALLOC!$E$1:$E$349,"B1",_CALC_ALLOC!$F$1:$F$349,"ALT") -> 0 | G68: =SUMIFS(_CALC_ALLOC!$AK$1:$AK$349,_CALC_ALLOC!$A$1:$A$349,"2026",_CALC_ALLOC!$B$1:$B$349,"IPAC_REN",_CALC_ALLOC!$D$1:$D$349,"BAC_CCE",_CALC_ALLOC!$E$1:$E$349,"B1",_CALC_ALLOC!$F$1:$F$349,"ALT") -> 0 | H68: =SUMIFS(_CALC_ALLOC!$AL$1:$AL$349,_CALC_ALLOC!$A$1:$A$349,"2026",_CALC_ALLOC!$B$1:$B$349,"IPAC_REN",_CALC_ALLOC!$D$1:$D$349,"BAC_CCE",_CALC_ALLOC!$E$1:$E$349,"B1",_CALC_ALLOC!$F$1:$F$349,"ALT") -> 0 | I68: =SUMIFS(_CALC_ALLOC!$AR$1:$AR$349,_CALC_ALLOC!$A$1:$A$349,"2026",_CALC_ALLOC!$B$1:$B$349,"IPAC_REN",_CALC_ALLOC!$D$1:$D$349,"BAC_CCE",_CALC_ALLOC!$E$1:$E$349,"B1",_CALC_ALLOC!$F$1:$F$349,"ALT") -> 0 | J68: =SUMIFS(_CALC_ALLOC!$AM$1:$AM$349,_CALC_ALLOC!$A$1:$A$349,"2026",_CALC_ALLOC!$B$1:$B$349,"IPAC_REN",_CALC_ALLOC!$D$1:$D$349,"BAC_CCE",_CALC_ALLOC!$E$1:$E$349,"B1",_CALC_ALLOC!$F$1:$F$349,"ALT") -> 0 | K68: =E68+F68+G68+H68+I68+J68 -> 0 | L68: =SUMIFS(_CALC_ALLOC!$AN$1:$AN$349,_CALC_ALLOC!$A$1:$A$349,"2026",_CALC_ALLOC!$B$1:$B$349,"IPAC_REN",_CALC_ALLOC!$D$1:$D$349,"BAC_CCE",_CALC_ALLOC!$E$1:$E$349,"B1",_CALC_ALLOC!$F$1:$F$349,"ALT") -> 0 | M68: =IFERROR(L68/D68,0) -> 0
B69: BAC_CCE B2 ALT | C69: =SUMIFS(_CALC_ALLOC!$G$1:$G$349,_CALC_ALLOC!$A$1:$A$349,"2026",_CALC_ALLOC!$B$1:$B$349,"IPAC_REN",_CALC_ALLOC!$D$1:$D$349,"BAC_CCE",_CALC_ALLOC!$E$1:$E$349,"B2",_CALC_ALLOC!$F$1:$F$349,"ALT") -> 0 | D69: =SUMIFS(_CALC_ALLOC!$I$1:$I$349,_CALC_ALLOC!$A$1:$A$349,"2026",_CALC_ALLOC!$B$1:$B$349,"IPAC_REN",_CALC_ALLOC!$D$1:$D$349,"BAC_CCE",_CALC_ALLOC!$E$1:$E$349,"B2",_CALC_ALLOC!$F$1:$F$349,"ALT") -> 0 | E69: =SUMIFS(_CALC_ALLOC!$AI$1:$AI$349,_CALC_ALLOC!$A$1:$A$349,"2026",_CALC_ALLOC!$B$1:$B$349,"IPAC_REN",_CALC_ALLOC!$D$1:$D$349,"BAC_CCE",_CALC_ALLOC!$E$1:$E$349,"B2",_CALC_ALLOC!$F$1:$F$349,"ALT") -> 0 | F69: =SUMIFS(_CALC_ALLOC!$AJ$1:$AJ$349,_CALC_ALLOC!$A$1:$A$349,"2026",_CALC_ALLOC!$B$1:$B$349,"IPAC_REN",_CALC_ALLOC!$D$1:$D$349,"BAC_CCE",_CALC_ALLOC!$E$1:$E$349,"B2",_CALC_ALLOC!$F$1:$F$349,"ALT") -> 0 | G69: =SUMIFS(_CALC_ALLOC!$AK$1:$AK$349,_CALC_ALLOC!$A$1:$A$349,"2026",_CALC_ALLOC!$B$1:$B$349,"IPAC_REN",_CALC_ALLOC!$D$1:$D$349,"BAC_CCE",_CALC_ALLOC!$E$1:$E$349,"B2",_CALC_ALLOC!$F$1:$F$349,"ALT") -> 0 | H69: =SUMIFS(_CALC_ALLOC!$AL$1:$AL$349,_CALC_ALLOC!$A$1:$A$349,"2026",_CALC_ALLOC!$B$1:$B$349,"IPAC_REN",_CALC_ALLOC!$D$1:$D$349,"BAC_CCE",_CALC_ALLOC!$E$1:$E$349,"B2",_CALC_ALLOC!$F$1:$F$349,"ALT") -> 0 | I69: =SUMIFS(_CALC_ALLOC!$AR$1:$AR$349,_CALC_ALLOC!$A$1:$A$349,"2026",_CALC_ALLOC!$B$1:$B$349,"IPAC_REN",_CALC_ALLOC!$D$1:$D$349,"BAC_CCE",_CALC_ALLOC!$E$1:$E$349,"B2",_CALC_ALLOC!$F$1:$F$349,"ALT") -> 0 | J69: =SUMIFS(_CALC_ALLOC!$AM$1:$AM$349,_CALC_ALLOC!$A$1:$A$349,"2026",_CALC_ALLOC!$B$1:$B$349,"IPAC_REN",_CALC_ALLOC!$D$1:$D$349,"BAC_CCE",_CALC_ALLOC!$E$1:$E$349,"B2",_CALC_ALLOC!$F$1:$F$349,"ALT") -> 0 | K69: =E69+F69+G69+H69+I69+J69 -> 0 | L69: =SUMIFS(_CALC_ALLOC!$AN$1:$AN$349,_CALC_ALLOC!$A$1:$A$349,"2026",_CALC_ALLOC!$B$1:$B$349,"IPAC_REN",_CALC_ALLOC!$D$1:$D$349,"BAC_CCE",_CALC_ALLOC!$E$1:$E$349,"B2",_CALC_ALLOC!$F$1:$F$349,"ALT") -> 0 | M69: =IFERROR(L69/D69,0) -> 0
B70: BAC_CCE B3 ALT | C70: =SUMIFS(_CALC_ALLOC!$G$1:$G$349,_CALC_ALLOC!$A$1:$A$349,"2026",_CALC_ALLOC!$B$1:$B$349,"IPAC_REN",_CALC_ALLOC!$D$1:$D$349,"BAC_CCE",_CALC_ALLOC!$E$1:$E$349,"B3",_CALC_ALLOC!$F$1:$F$349,"ALT") -> 0 | D70: =SUMIFS(_CALC_ALLOC!$I$1:$I$349,_CALC_ALLOC!$A$1:$A$349,"2026",_CALC_ALLOC!$B$1:$B$349,"IPAC_REN",_CALC_ALLOC!$D$1:$D$349,"BAC_CCE",_CALC_ALLOC!$E$1:$E$349,"B3",_CALC_ALLOC!$F$1:$F$349,"ALT") -> 0 | E70: =SUMIFS(_CALC_ALLOC!$AI$1:$AI$349,_CALC_ALLOC!$A$1:$A$349,"2026",_CALC_ALLOC!$B$1:$B$349,"IPAC_REN",_CALC_ALLOC!$D$1:$D$349,"BAC_CCE",_CALC_ALLOC!$E$1:$E$349,"B3",_CALC_ALLOC!$F$1:$F$349,"ALT") -> 0 | F70: =SUMIFS(_CALC_ALLOC!$AJ$1:$AJ$349,_CALC_ALLOC!$A$1:$A$349,"2026",_CALC_ALLOC!$B$1:$B$349,"IPAC_REN",_CALC_ALLOC!$D$1:$D$349,"BAC_CCE",_CALC_ALLOC!$E$1:$E$349,"B3",_CALC_ALLOC!$F$1:$F$349,"ALT") -> 0 | G70: =SUMIFS(_CALC_ALLOC!$AK$1:$AK$349,_CALC_ALLOC!$A$1:$A$349,"2026",_CALC_ALLOC!$B$1:$B$349,"IPAC_REN",_CALC_ALLOC!$D$1:$D$349,"BAC_CCE",_CALC_ALLOC!$E$1:$E$349,"B3",_CALC_ALLOC!$F$1:$F$349,"ALT") -> 0 | H70: =SUMIFS(_CALC_ALLOC!$AL$1:$AL$349,_CALC_ALLOC!$A$1:$A$349,"2026",_CALC_ALLOC!$B$1:$B$349,"IPAC_REN",_CALC_ALLOC!$D$1:$D$349,"BAC_CCE",_CALC_ALLOC!$E$1:$E$349,"B3",_CALC_ALLOC!$F$1:$F$349,"ALT") -> 0 | I70: =SUMIFS(_CALC_ALLOC!$AR$1:$AR$349,_CALC_ALLOC!$A$1:$A$349,"2026",_CALC_ALLOC!$B$1:$B$349,"IPAC_REN",_CALC_ALLOC!$D$1:$D$349,"BAC_CCE",_CALC_ALLOC!$E$1:$E$349,"B3",_CALC_ALLOC!$F$1:$F$349,"ALT") -> 0 | J70: =SUMIFS(_CALC_ALLOC!$AM$1:$AM$349,_CALC_ALLOC!$A$1:$A$349,"2026",_CALC_ALLOC!$B$1:$B$349,"IPAC_REN",_CALC_ALLOC!$D$1:$D$349,"BAC_CCE",_CALC_ALLOC!$E$1:$E$349,"B3",_CALC_ALLOC!$F$1:$F$349,"ALT") -> 0 | K70: =E70+F70+G70+H70+I70+J70 -> 0 | L70: =SUMIFS(_CALC_ALLOC!$AN$1:$AN$349,_CALC_ALLOC!$A$1:$A$349,"2026",_CALC_ALLOC!$B$1:$B$349,"IPAC_REN",_CALC_ALLOC!$D$1:$D$349,"BAC_CCE",_CALC_ALLOC!$E$1:$E$349,"B3",_CALC_ALLOC!$F$1:$F$349,"ALT") -> 0 | M70: =IFERROR(L70/D70,0) -> 0
B71: Montpellier (IPAC_MTP) | C71: =SUMIFS(_CALC_ALLOC!$G$1:$G$349,_CALC_ALLOC!$A$1:$A$349,"2026",_CALC_ALLOC!$B$1:$B$349,"IPAC_MTP") -> 0 | D71: =SUMIFS(_CALC_ALLOC!$I$1:$I$349,_CALC_ALLOC!$A$1:$A$349,"2026",_CALC_ALLOC!$B$1:$B$349,"IPAC_MTP") -> 0 | E71: =SUMIFS(_CALC_ALLOC!$AI$1:$AI$349,_CALC_ALLOC!$A$1:$A$349,"2026",_CALC_ALLOC!$B$1:$B$349,"IPAC_MTP") -> 0 | F71: =SUMIFS(_CALC_ALLOC!$AJ$1:$AJ$349,_CALC_ALLOC!$A$1:$A$349,"2026",_CALC_ALLOC!$B$1:$B$349,"IPAC_MTP") -> 0 | G71: =SUMIFS(_CALC_ALLOC!$AK$1:$AK$349,_CALC_ALLOC!$A$1:$A$349,"2026",_CALC_ALLOC!$B$1:$B$349,"IPAC_MTP") -> 0 | H71: =SUMIFS(_CALC_ALLOC!$AL$1:$AL$349,_CALC_ALLOC!$A$1:$A$349,"2026",_CALC_ALLOC!$B$1:$B$349,"IPAC_MTP") -> 0 | I71: =SUMIFS(_CALC_ALLOC!$AR$1:$AR$349,_CALC_ALLOC!$A$1:$A$349,"2026",_CALC_ALLOC!$B$1:$B$349,"IPAC_MTP") -> 0 | J71: =SUMIFS(_CALC_ALLOC!$AM$1:$AM$349,_CALC_ALLOC!$A$1:$A$349,"2026",_CALC_ALLOC!$B$1:$B$349,"IPAC_MTP") -> 0 | K71: =E71+F71+G71+H71+I71+J71 -> 0 | L71: =SUMIFS(_CALC_ALLOC!$AN$1:$AN$349,_CALC_ALLOC!$A$1:$A$349,"2026",_CALC_ALLOC!$B$1:$B$349,"IPAC_MTP") -> 0 | M71: =IFERROR(L71/D71,0) -> 0
B72: BAC_CCE B1 ALT | C72: =SUMIFS(_CALC_ALLOC!$G$1:$G$349,_CALC_ALLOC!$A$1:$A$349,"2026",_CALC_ALLOC!$B$1:$B$349,"IPAC_MTP",_CALC_ALLOC!$D$1:$D$349,"BAC_CCE",_CALC_ALLOC!$E$1:$E$349,"B1",_CALC_ALLOC!$F$1:$F$349,"ALT") -> 0 | D72: =SUMIFS(_CALC_ALLOC!$I$1:$I$349,_CALC_ALLOC!$A$1:$A$349,"2026",_CALC_ALLOC!$B$1:$B$349,"IPAC_MTP",_CALC_ALLOC!$D$1:$D$349,"BAC_CCE",_CALC_ALLOC!$E$1:$E$349,"B1",_CALC_ALLOC!$F$1:$F$349,"ALT") -> 0 | E72: =SUMIFS(_CALC_ALLOC!$AI$1:$AI$349,_CALC_ALLOC!$A$1:$A$349,"2026",_CALC_ALLOC!$B$1:$B$349,"IPAC_MTP",_CALC_ALLOC!$D$1:$D$349,"BAC_CCE",_CALC_ALLOC!$E$1:$E$349,"B1",_CALC_ALLOC!$F$1:$F$349,"ALT") -> 0 | F72: =SUMIFS(_CALC_ALLOC!$AJ$1:$AJ$349,_CALC_ALLOC!$A$1:$A$349,"2026",_CALC_ALLOC!$B$1:$B$349,"IPAC_MTP",_CALC_ALLOC!$D$1:$D$349,"BAC_CCE",_CALC_ALLOC!$E$1:$E$349,"B1",_CALC_ALLOC!$F$1:$F$349,"ALT") -> 0 | G72: =SUMIFS(_CALC_ALLOC!$AK$1:$AK$349,_CALC_ALLOC!$A$1:$A$349,"2026",_CALC_ALLOC!$B$1:$B$349,"IPAC_MTP",_CALC_ALLOC!$D$1:$D$349,"BAC_CCE",_CALC_ALLOC!$E$1:$E$349,"B1",_CALC_ALLOC!$F$1:$F$349,"ALT") -> 0 | H72: =SUMIFS(_CALC_ALLOC!$AL$1:$AL$349,_CALC_ALLOC!$A$1:$A$349,"2026",_CALC_ALLOC!$B$1:$B$349,"IPAC_MTP",_CALC_ALLOC!$D$1:$D$349,"BAC_CCE",_CALC_ALLOC!$E$1:$E$349,"B1",_CALC_ALLOC!$F$1:$F$349,"ALT") -> 0 | I72: =SUMIFS(_CALC_ALLOC!$AR$1:$AR$349,_CALC_ALLOC!$A$1:$A$349,"2026",_CALC_ALLOC!$B$1:$B$349,"IPAC_MTP",_CALC_ALLOC!$D$1:$D$349,"BAC_CCE",_CALC_ALLOC!$E$1:$E$349,"B1",_CALC_ALLOC!$F$1:$F$349,"ALT") -> 0 | J72: =SUMIFS(_CALC_ALLOC!$AM$1:$AM$349,_CALC_ALLOC!$A$1:$A$349,"2026",_CALC_ALLOC!$B$1:$B$349,"IPAC_MTP",_CALC_ALLOC!$D$1:$D$349,"BAC_CCE",_CALC_ALLOC!$E$1:$E$349,"B1",_CALC_ALLOC!$F$1:$F$349,"ALT") -> 0 | K72: =E72+F72+G72+H72+I72+J72 -> 0 | L72: =SUMIFS(_CALC_ALLOC!$AN$1:$AN$349,_CALC_ALLOC!$A$1:$A$349,"2026",_CALC_ALLOC!$B$1:$B$349,"IPAC_MTP",_CALC_ALLOC!$D$1:$D$349,"BAC_CCE",_CALC_ALLOC!$E$1:$E$349,"B1",_CALC_ALLOC!$F$1:$F$349,"ALT") -> 0 | M72: =IFERROR(L72/D72,0) -> 0
B73: BAC_CCE B2 ALT | C73: =SUMIFS(_CALC_ALLOC!$G$1:$G$349,_CALC_ALLOC!$A$1:$A$349,"2026",_CALC_ALLOC!$B$1:$B$349,"IPAC_MTP",_CALC_ALLOC!$D$1:$D$349,"BAC_CCE",_CALC_ALLOC!$E$1:$E$349,"B2",_CALC_ALLOC!$F$1:$F$349,"ALT") -> 0 | D73: =SUMIFS(_CALC_ALLOC!$I$1:$I$349,_CALC_ALLOC!$A$1:$A$349,"2026",_CALC_ALLOC!$B$1:$B$349,"IPAC_MTP",_CALC_ALLOC!$D$1:$D$349,"BAC_CCE",_CALC_ALLOC!$E$1:$E$349,"B2",_CALC_ALLOC!$F$1:$F$349,"ALT") -> 0 | E73: =SUMIFS(_CALC_ALLOC!$AI$1:$AI$349,_CALC_ALLOC!$A$1:$A$349,"2026",_CALC_ALLOC!$B$1:$B$349,"IPAC_MTP",_CALC_ALLOC!$D$1:$D$349,"BAC_CCE",_CALC_ALLOC!$E$1:$E$349,"B2",_CALC_ALLOC!$F$1:$F$349,"ALT") -> 0 | F73: =SUMIFS(_CALC_ALLOC!$AJ$1:$AJ$349,_CALC_ALLOC!$A$1:$A$349,"2026",_CALC_ALLOC!$B$1:$B$349,"IPAC_MTP",_CALC_ALLOC!$D$1:$D$349,"BAC_CCE",_CALC_ALLOC!$E$1:$E$349,"B2",_CALC_ALLOC!$F$1:$F$349,"ALT") -> 0 | G73: =SUMIFS(_CALC_ALLOC!$AK$1:$AK$349,_CALC_ALLOC!$A$1:$A$349,"2026",_CALC_ALLOC!$B$1:$B$349,"IPAC_MTP",_CALC_ALLOC!$D$1:$D$349,"BAC_CCE",_CALC_ALLOC!$E$1:$E$349,"B2",_CALC_ALLOC!$F$1:$F$349,"ALT") -> 0 | H73: =SUMIFS(_CALC_ALLOC!$AL$1:$AL$349,_CALC_ALLOC!$A$1:$A$349,"2026",_CALC_ALLOC!$B$1:$B$349,"IPAC_MTP",_CALC_ALLOC!$D$1:$D$349,"BAC_CCE",_CALC_ALLOC!$E$1:$E$349,"B2",_CALC_ALLOC!$F$1:$F$349,"ALT") -> 0 | I73: =SUMIFS(_CALC_ALLOC!$AR$1:$AR$349,_CALC_ALLOC!$A$1:$A$349,"2026",_CALC_ALLOC!$B$1:$B$349,"IPAC_MTP",_CALC_ALLOC!$D$1:$D$349,"BAC_CCE",_CALC_ALLOC!$E$1:$E$349,"B2",_CALC_ALLOC!$F$1:$F$349,"ALT") -> 0 | J73: =SUMIFS(_CALC_ALLOC!$AM$1:$AM$349,_CALC_ALLOC!$A$1:$A$349,"2026",_CALC_ALLOC!$B$1:$B$349,"IPAC_MTP",_CALC_ALLOC!$D$1:$D$349,"BAC_CCE",_CALC_ALLOC!$E$1:$E$349,"B2",_CALC_ALLOC!$F$1:$F$349,"ALT") -> 0 | K73: =E73+F73+G73+H73+I73+J73 -> 0 | L73: =SUMIFS(_CALC_ALLOC!$AN$1:$AN$349,_CALC_ALLOC!$A$1:$A$349,"2026",_CALC_ALLOC!$B$1:$B$349,"IPAC_MTP",_CALC_ALLOC!$D$1:$D$349,"BAC_CCE",_CALC_ALLOC!$E$1:$E$349,"B2",_CALC_ALLOC!$F$1:$F$349,"ALT") -> 0 | M73: =IFERROR(L73/D73,0) -> 0
B74: BAC_CCE B3 ALT | C74: =SUMIFS(_CALC_ALLOC!$G$1:$G$349,_CALC_ALLOC!$A$1:$A$349,"2026",_CALC_ALLOC!$B$1:$B$349,"IPAC_MTP",_CALC_ALLOC!$D$1:$D$349,"BAC_CCE",_CALC_ALLOC!$E$1:$E$349,"B3",_CALC_ALLOC!$F$1:$F$349,"ALT") -> 0 | D74: =SUMIFS(_CALC_ALLOC!$I$1:$I$349,_CALC_ALLOC!$A$1:$A$349,"2026",_CALC_ALLOC!$B$1:$B$349,"IPAC_MTP",_CALC_ALLOC!$D$1:$D$349,"BAC_CCE",_CALC_ALLOC!$E$1:$E$349,"B3",_CALC_ALLOC!$F$1:$F$349,"ALT") -> 0 | E74: =SUMIFS(_CALC_ALLOC!$AI$1:$AI$349,_CALC_ALLOC!$A$1:$A$349,"2026",_CALC_ALLOC!$B$1:$B$349,"IPAC_MTP",_CALC_ALLOC!$D$1:$D$349,"BAC_CCE",_CALC_ALLOC!$E$1:$E$349,"B3",_CALC_ALLOC!$F$1:$F$349,"ALT") -> 0 | F74: =SUMIFS(_CALC_ALLOC!$AJ$1:$AJ$349,_CALC_ALLOC!$A$1:$A$349,"2026",_CALC_ALLOC!$B$1:$B$349,"IPAC_MTP",_CALC_ALLOC!$D$1:$D$349,"BAC_CCE",_CALC_ALLOC!$E$1:$E$349,"B3",_CALC_ALLOC!$F$1:$F$349,"ALT") -> 0 | G74: =SUMIFS(_CALC_ALLOC!$AK$1:$AK$349,_CALC_ALLOC!$A$1:$A$349,"2026",_CALC_ALLOC!$B$1:$B$349,"IPAC_MTP",_CALC_ALLOC!$D$1:$D$349,"BAC_CCE",_CALC_ALLOC!$E$1:$E$349,"B3",_CALC_ALLOC!$F$1:$F$349,"ALT") -> 0 | H74: =SUMIFS(_CALC_ALLOC!$AL$1:$AL$349,_CALC_ALLOC!$A$1:$A$349,"2026",_CALC_ALLOC!$B$1:$B$349,"IPAC_MTP",_CALC_ALLOC!$D$1:$D$349,"BAC_CCE",_CALC_ALLOC!$E$1:$E$349,"B3",_CALC_ALLOC!$F$1:$F$349,"ALT") -> 0 | I74: =SUMIFS(_CALC_ALLOC!$AR$1:$AR$349,_CALC_ALLOC!$A$1:$A$349,"2026",_CALC_ALLOC!$B$1:$B$349,"IPAC_MTP",_CALC_ALLOC!$D$1:$D$349,"BAC_CCE",_CALC_ALLOC!$E$1:$E$349,"B3",_CALC_ALLOC!$F$1:$F$349,"ALT") -> 0 | J74: =SUMIFS(_CALC_ALLOC!$AM$1:$AM$349,_CALC_ALLOC!$A$1:$A$349,"2026",_CALC_ALLOC!$B$1:$B$349,"IPAC_MTP",_CALC_ALLOC!$D$1:$D$349,"BAC_CCE",_CALC_ALLOC!$E$1:$E$349,"B3",_CALC_ALLOC!$F$1:$F$349,"ALT") -> 0 | K74: =E74+F74+G74+H74+I74+J74 -> 0 | L74: =SUMIFS(_CALC_ALLOC!$AN$1:$AN$349,_CALC_ALLOC!$A$1:$A$349,"2026",_CALC_ALLOC!$B$1:$B$349,"IPAC_MTP",_CALC_ALLOC!$D$1:$D$349,"BAC_CCE",_CALC_ALLOC!$E$1:$E$349,"B3",_CALC_ALLOC!$F$1:$F$349,"ALT") -> 0 | M74: =IFERROR(L74/D74,0) -> 0
B75: Pigier | C75: =SUMIFS(_CALC_ALLOC!$G$1:$G$349,_CALC_ALLOC!$A$1:$A$349,"2026",_CALC_ALLOC!$C$1:$C$349,"PIGIER") -> 0 | D75: =SUMIFS(_CALC_ALLOC!$I$1:$I$349,_CALC_ALLOC!$A$1:$A$349,"2026",_CALC_ALLOC!$C$1:$C$349,"PIGIER") -> 0 | E75: =SUMIFS(_CALC_ALLOC!$AI$1:$AI$349,_CALC_ALLOC!$A$1:$A$349,"2026",_CALC_ALLOC!$C$1:$C$349,"PIGIER") -> 0 | F75: =SUMIFS(_CALC_ALLOC!$AJ$1:$AJ$349,_CALC_ALLOC!$A$1:$A$349,"2026",_CALC_ALLOC!$C$1:$C$349,"PIGIER") -> 0 | G75: =SUMIFS(_CALC_ALLOC!$AK$1:$AK$349,_CALC_ALLOC!$A$1:$A$349,"2026",_CALC_ALLOC!$C$1:$C$349,"PIGIER") -> 0 | H75: =SUMIFS(_CALC_ALLOC!$AL$1:$AL$349,_CALC_ALLOC!$A$1:$A$349,"2026",_CALC_ALLOC!$C$1:$C$349,"PIGIER") -> 0 | I75: =SUMIFS(_CALC_ALLOC!$AR$1:$AR$349,_CALC_ALLOC!$A$1:$A$349,"2026",_CALC_ALLOC!$C$1:$C$349,"PIGIER") -> 0 | J75: =SUMIFS(_CALC_ALLOC!$AM$1:$AM$349,_CALC_ALLOC!$A$1:$A$349,"2026",_CALC_ALLOC!$C$1:$C$349,"PIGIER") -> 0 | K75: =E75+F75+G75+H75+I75+J75 -> 0 | L75: =SUMIFS(_CALC_ALLOC!$AN$1:$AN$349,_CALC_ALLOC!$A$1:$A$349,"2026",_CALC_ALLOC!$C$1:$C$349,"PIGIER") -> 0 | M75: =IFERROR(L75/D75,0) -> 0
B76: Lyon (PIGIER_LYO) | C76: =SUMIFS(_CALC_ALLOC!$G$1:$G$349,_CALC_ALLOC!$A$1:$A$349,"2026",_CALC_ALLOC!$B$1:$B$349,"PIGIER_LYO") -> 0 | D76: =SUMIFS(_CALC_ALLOC!$I$1:$I$349,_CALC_ALLOC!$A$1:$A$349,"2026",_CALC_ALLOC!$B$1:$B$349,"PIGIER_LYO") -> 0 | E76: =SUMIFS(_CALC_ALLOC!$AI$1:$AI$349,_CALC_ALLOC!$A$1:$A$349,"2026",_CALC_ALLOC!$B$1:$B$349,"PIGIER_LYO") -> 0 | F76: =SUMIFS(_CALC_ALLOC!$AJ$1:$AJ$349,_CALC_ALLOC!$A$1:$A$349,"2026",_CALC_ALLOC!$B$1:$B$349,"PIGIER_LYO") -> 0 | G76: =SUMIFS(_CALC_ALLOC!$AK$1:$AK$349,_CALC_ALLOC!$A$1:$A$349,"2026",_CALC_ALLOC!$B$1:$B$349,"PIGIER_LYO") -> 0 | H76: =SUMIFS(_CALC_ALLOC!$AL$1:$AL$349,_CALC_ALLOC!$A$1:$A$349,"2026",_CALC_ALLOC!$B$1:$B$349,"PIGIER_LYO") -> 0 | I76: =SUMIFS(_CALC_ALLOC!$AR$1:$AR$349,_CALC_ALLOC!$A$1:$A$349,"2026",_CALC_ALLOC!$B$1:$B$349,"PIGIER_LYO") -> 0 | J76: =SUMIFS(_CALC_ALLOC!$AM$1:$AM$349,_CALC_ALLOC!$A$1:$A$349,"2026",_CALC_ALLOC!$B$1:$B$349,"PIGIER_LYO") -> 0 | K76: =E76+F76+G76+H76+I76+J76 -> 0 | L76: =SUMIFS(_CALC_ALLOC!$AN$1:$AN$349,_CALC_ALLOC!$A$1:$A$349,"2026",_CALC_ALLOC!$B$1:$B$349,"PIGIER_LYO") -> 0 | M76: =IFERROR(L76/D76,0) -> 0
B77: BTS_GES BTS1 ALT | C77: =SUMIFS(_CALC_ALLOC!$G$1:$G$349,_CALC_ALLOC!$A$1:$A$349,"2026",_CALC_ALLOC!$B$1:$B$349,"PIGIER_LYO",_CALC_ALLOC!$D$1:$D$349,"BTS_GES",_CALC_ALLOC!$E$1:$E$349,"BTS1",_CALC_ALLOC!$F$1:$F$349,"ALT") -> 0 | D77: =SUMIFS(_CALC_ALLOC!$I$1:$I$349,_CALC_ALLOC!$A$1:$A$349,"2026",_CALC_ALLOC!$B$1:$B$349,"PIGIER_LYO",_CALC_ALLOC!$D$1:$D$349,"BTS_GES",_CALC_ALLOC!$E$1:$E$349,"BTS1",_CALC_ALLOC!$F$1:$F$349,"ALT") -> 0 | E77: =SUMIFS(_CALC_ALLOC!$AI$1:$AI$349,_CALC_ALLOC!$A$1:$A$349,"2026",_CALC_ALLOC!$B$1:$B$349,"PIGIER_LYO",_CALC_ALLOC!$D$1:$D$349,"BTS_GES",_CALC_ALLOC!$E$1:$E$349,"BTS1",_CALC_ALLOC!$F$1:$F$349,"ALT") -> 0 | F77: =SUMIFS(_CALC_ALLOC!$AJ$1:$AJ$349,_CALC_ALLOC!$A$1:$A$349,"2026",_CALC_ALLOC!$B$1:$B$349,"PIGIER_LYO",_CALC_ALLOC!$D$1:$D$349,"BTS_GES",_CALC_ALLOC!$E$1:$E$349,"BTS1",_CALC_ALLOC!$F$1:$F$349,"ALT") -> 0 | G77: =SUMIFS(_CALC_ALLOC!$AK$1:$AK$349,_CALC_ALLOC!$A$1:$A$349,"2026",_CALC_ALLOC!$B$1:$B$349,"PIGIER_LYO",_CALC_ALLOC!$D$1:$D$349,"BTS_GES",_CALC_ALLOC!$E$1:$E$349,"BTS1",_CALC_ALLOC!$F$1:$F$349,"ALT") -> 0 | H77: =SUMIFS(_CALC_ALLOC!$AL$1:$AL$349,_CALC_ALLOC!$A$1:$A$349,"2026",_CALC_ALLOC!$B$1:$B$349,"PIGIER_LYO",_CALC_ALLOC!$D$1:$D$349,"BTS_GES",_CALC_ALLOC!$E$1:$E$349,"BTS1",_CALC_ALLOC!$F$1:$F$349,"ALT") -> 0 | I77: =SUMIFS(_CALC_ALLOC!$AR$1:$AR$349,_CALC_ALLOC!$A$1:$A$349,"2026",_CALC_ALLOC!$B$1:$B$349,"PIGIER_LYO",_CALC_ALLOC!$D$1:$D$349,"BTS_GES",_CALC_ALLOC!$E$1:$E$349,"BTS1",_CALC_ALLOC!$F$1:$F$349,"ALT") -> 0 | J77: =SUMIFS(_CALC_ALLOC!$AM$1:$AM$349,_CALC_ALLOC!$A$1:$A$349,"2026",_CALC_ALLOC!$B$1:$B$349,"PIGIER_LYO",_CALC_ALLOC!$D$1:$D$349,"BTS_GES",_CALC_ALLOC!$E$1:$E$349,"BTS1",_CALC_ALLOC!$F$1:$F$349,"ALT") -> 0 | K77: =E77+F77+G77+H77+I77+J77 -> 0 | L77: =SUMIFS(_CALC_ALLOC!$AN$1:$AN$349,_CALC_ALLOC!$A$1:$A$349,"2026",_CALC_ALLOC!$B$1:$B$349,"PIGIER_LYO",_CALC_ALLOC!$D$1:$D$349,"BTS_GES",_CALC_ALLOC!$E$1:$E$349,"BTS1",_CALC_ALLOC!$F$1:$F$349,"ALT") -> 0 | M77: =IFERROR(L77/D77,0) -> 0
B78: BTS_GES BTS2 ALT | C78: =SUMIFS(_CALC_ALLOC!$G$1:$G$349,_CALC_ALLOC!$A$1:$A$349,"2026",_CALC_ALLOC!$B$1:$B$349,"PIGIER_LYO",_CALC_ALLOC!$D$1:$D$349,"BTS_GES",_CALC_ALLOC!$E$1:$E$349,"BTS2",_CALC_ALLOC!$F$1:$F$349,"ALT") -> 0 | D78: =SUMIFS(_CALC_ALLOC!$I$1:$I$349,_CALC_ALLOC!$A$1:$A$349,"2026",_CALC_ALLOC!$B$1:$B$349,"PIGIER_LYO",_CALC_ALLOC!$D$1:$D$349,"BTS_GES",_CALC_ALLOC!$E$1:$E$349,"BTS2",_CALC_ALLOC!$F$1:$F$349,"ALT") -> 0 | E78: =SUMIFS(_CALC_ALLOC!$AI$1:$AI$349,_CALC_ALLOC!$A$1:$A$349,"2026",_CALC_ALLOC!$B$1:$B$349,"PIGIER_LYO",_CALC_ALLOC!$D$1:$D$349,"BTS_GES",_CALC_ALLOC!$E$1:$E$349,"BTS2",_CALC_ALLOC!$F$1:$F$349,"ALT") -> 0 | F78: =SUMIFS(_CALC_ALLOC!$AJ$1:$AJ$349,_CALC_ALLOC!$A$1:$A$349,"2026",_CALC_ALLOC!$B$1:$B$349,"PIGIER_LYO",_CALC_ALLOC!$D$1:$D$349,"BTS_GES",_CALC_ALLOC!$E$1:$E$349,"BTS2",_CALC_ALLOC!$F$1:$F$349,"ALT") -> 0 | G78: =SUMIFS(_CALC_ALLOC!$AK$1:$AK$349,_CALC_ALLOC!$A$1:$A$349,"2026",_CALC_ALLOC!$B$1:$B$349,"PIGIER_LYO",_CALC_ALLOC!$D$1:$D$349,"BTS_GES",_CALC_ALLOC!$E$1:$E$349,"BTS2",_CALC_ALLOC!$F$1:$F$349,"ALT") -> 0 | H78: =SUMIFS(_CALC_ALLOC!$AL$1:$AL$349,_CALC_ALLOC!$A$1:$A$349,"2026",_CALC_ALLOC!$B$1:$B$349,"PIGIER_LYO",_CALC_ALLOC!$D$1:$D$349,"BTS_GES",_CALC_ALLOC!$E$1:$E$349,"BTS2",_CALC_ALLOC!$F$1:$F$349,"ALT") -> 0 | I78: =SUMIFS(_CALC_ALLOC!$AR$1:$AR$349,_CALC_ALLOC!$A$1:$A$349,"2026",_CALC_ALLOC!$B$1:$B$349,"PIGIER_LYO",_CALC_ALLOC!$D$1:$D$349,"BTS_GES",_CALC_ALLOC!$E$1:$E$349,"BTS2",_CALC_ALLOC!$F$1:$F$349,"ALT") -> 0 | J78: =SUMIFS(_CALC_ALLOC!$AM$1:$AM$349,_CALC_ALLOC!$A$1:$A$349,"2026",_CALC_ALLOC!$B$1:$B$349,"PIGIER_LYO",_CALC_ALLOC!$D$1:$D$349,"BTS_GES",_CALC_ALLOC!$E$1:$E$349,"BTS2",_CALC_ALLOC!$F$1:$F$349,"ALT") -> 0 | K78: =E78+F78+G78+H78+I78+J78 -> 0 | L78: =SUMIFS(_CALC_ALLOC!$AN$1:$AN$349,_CALC_ALLOC!$A$1:$A$349,"2026",_CALC_ALLOC!$B$1:$B$349,"PIGIER_LYO",_CALC_ALLOC!$D$1:$D$349,"BTS_GES",_CALC_ALLOC!$E$1:$E$349,"BTS2",_CALC_ALLOC!$F$1:$F$349,"ALT") -> 0 | M78: =IFERROR(L78/D78,0) -> 0
B79: BAC_RH B1 ALT | C79: =SUMIFS(_CALC_ALLOC!$G$1:$G$349,_CALC_ALLOC!$A$1:$A$349,"2026",_CALC_ALLOC!$B$1:$B$349,"PIGIER_LYO",_CALC_ALLOC!$D$1:$D$349,"BAC_RH",_CALC_ALLOC!$E$1:$E$349,"B1",_CALC_ALLOC!$F$1:$F$349,"ALT") -> 0 | D79: =SUMIFS(_CALC_ALLOC!$I$1:$I$349,_CALC_ALLOC!$A$1:$A$349,"2026",_CALC_ALLOC!$B$1:$B$349,"PIGIER_LYO",_CALC_ALLOC!$D$1:$D$349,"BAC_RH",_CALC_ALLOC!$E$1:$E$349,"B1",_CALC_ALLOC!$F$1:$F$349,"ALT") -> 0 | E79: =SUMIFS(_CALC_ALLOC!$AI$1:$AI$349,_CALC_ALLOC!$A$1:$A$349,"2026",_CALC_ALLOC!$B$1:$B$349,"PIGIER_LYO",_CALC_ALLOC!$D$1:$D$349,"BAC_RH",_CALC_ALLOC!$E$1:$E$349,"B1",_CALC_ALLOC!$F$1:$F$349,"ALT") -> 0 | F79: =SUMIFS(_CALC_ALLOC!$AJ$1:$AJ$349,_CALC_ALLOC!$A$1:$A$349,"2026",_CALC_ALLOC!$B$1:$B$349,"PIGIER_LYO",_CALC_ALLOC!$D$1:$D$349,"BAC_RH",_CALC_ALLOC!$E$1:$E$349,"B1",_CALC_ALLOC!$F$1:$F$349,"ALT") -> 0 | G79: =SUMIFS(_CALC_ALLOC!$AK$1:$AK$349,_CALC_ALLOC!$A$1:$A$349,"2026",_CALC_ALLOC!$B$1:$B$349,"PIGIER_LYO",_CALC_ALLOC!$D$1:$D$349,"BAC_RH",_CALC_ALLOC!$E$1:$E$349,"B1",_CALC_ALLOC!$F$1:$F$349,"ALT") -> 0 | H79: =SUMIFS(_CALC_ALLOC!$AL$1:$AL$349,_CALC_ALLOC!$A$1:$A$349,"2026",_CALC_ALLOC!$B$1:$B$349,"PIGIER_LYO",_CALC_ALLOC!$D$1:$D$349,"BAC_RH",_CALC_ALLOC!$E$1:$E$349,"B1",_CALC_ALLOC!$F$1:$F$349,"ALT") -> 0 | I79: =SUMIFS(_CALC_ALLOC!$AR$1:$AR$349,_CALC_ALLOC!$A$1:$A$349,"2026",_CALC_ALLOC!$B$1:$B$349,"PIGIER_LYO",_CALC_ALLOC!$D$1:$D$349,"BAC_RH",_CALC_ALLOC!$E$1:$E$349,"B1",_CALC_ALLOC!$F$1:$F$349,"ALT") -> 0 | J79: =SUMIFS(_CALC_ALLOC!$AM$1:$AM$349,_CALC_ALLOC!$A$1:$A$349,"2026",_CALC_ALLOC!$B$1:$B$349,"PIGIER_LYO",_CALC_ALLOC!$D$1:$D$349,"BAC_RH",_CALC_ALLOC!$E$1:$E$349,"B1",_CALC_ALLOC!$F$1:$F$349,"ALT") -> 0 | K79: =E79+F79+G79+H79+I79+J79 -> 0 | L79: =SUMIFS(_CALC_ALLOC!$AN$1:$AN$349,_CALC_ALLOC!$A$1:$A$349,"2026",_CALC_ALLOC!$B$1:$B$349,"PIGIER_LYO",_CALC_ALLOC!$D$1:$D$349,"BAC_RH",_CALC_ALLOC!$E$1:$E$349,"B1",_CALC_ALLOC!$F$1:$F$349,"ALT") -> 0 | M79: =IFERROR(L79/D79,0) -> 0
B80: BAC_RH B3 ALT | C80: =SUMIFS(_CALC_ALLOC!$G$1:$G$349,_CALC_ALLOC!$A$1:$A$349,"2026",_CALC_ALLOC!$B$1:$B$349,"PIGIER_LYO",_CALC_ALLOC!$D$1:$D$349,"BAC_RH",_CALC_ALLOC!$E$1:$E$349,"B3",_CALC_ALLOC!$F$1:$F$349,"ALT") -> 0 | D80: =SUMIFS(_CALC_ALLOC!$I$1:$I$349,_CALC_ALLOC!$A$1:$A$349,"2026",_CALC_ALLOC!$B$1:$B$349,"PIGIER_LYO",_CALC_ALLOC!$D$1:$D$349,"BAC_RH",_CALC_ALLOC!$E$1:$E$349,"B3",_CALC_ALLOC!$F$1:$F$349,"ALT") -> 0 | E80: =SUMIFS(_CALC_ALLOC!$AI$1:$AI$349,_CALC_ALLOC!$A$1:$A$349,"2026",_CALC_ALLOC!$B$1:$B$349,"PIGIER_LYO",_CALC_ALLOC!$D$1:$D$349,"BAC_RH",_CALC_ALLOC!$E$1:$E$349,"B3",_CALC_ALLOC!$F$1:$F$349,"ALT") -> 0 | F80: =SUMIFS(_CALC_ALLOC!$AJ$1:$AJ$349,_CALC_ALLOC!$A$1:$A$349,"2026",_CALC_ALLOC!$B$1:$B$349,"PIGIER_LYO",_CALC_ALLOC!$D$1:$D$349,"BAC_RH",_CALC_ALLOC!$E$1:$E$349,"B3",_CALC_ALLOC!$F$1:$F$349,"ALT") -> 0 | G80: =SUMIFS(_CALC_ALLOC!$AK$1:$AK$349,_CALC_ALLOC!$A$1:$A$349,"2026",_CALC_ALLOC!$B$1:$B$349,"PIGIER_LYO",_CALC_ALLOC!$D$1:$D$349,"BAC_RH",_CALC_ALLOC!$E$1:$E$349,"B3",_CALC_ALLOC!$F$1:$F$349,"ALT") -> 0 | H80: =SUMIFS(_CALC_ALLOC!$AL$1:$AL$349,_CALC_ALLOC!$A$1:$A$349,"2026",_CALC_ALLOC!$B$1:$B$349,"PIGIER_LYO",_CALC_ALLOC!$D$1:$D$349,"BAC_RH",_CALC_ALLOC!$E$1:$E$349,"B3",_CALC_ALLOC!$F$1:$F$349,"ALT") -> 0 | I80: =SUMIFS(_CALC_ALLOC!$AR$1:$AR$349,_CALC_ALLOC!$A$1:$A$349,"2026",_CALC_ALLOC!$B$1:$B$349,"PIGIER_LYO",_CALC_ALLOC!$D$1:$D$349,"BAC_RH",_CALC_ALLOC!$E$1:$E$349,"B3",_CALC_ALLOC!$F$1:$F$349,"ALT") -> 0 | J80: =SUMIFS(_CALC_ALLOC!$AM$1:$AM$349,_CALC_ALLOC!$A$1:$A$349,"2026",_CALC_ALLOC!$B$1:$B$349,"PIGIER_LYO",_CALC_ALLOC!$D$1:$D$349,"BAC_RH",_CALC_ALLOC!$E$1:$E$349,"B3",_CALC_ALLOC!$F$1:$F$349,"ALT") -> 0 | K80: =E80+F80+G80+H80+I80+J80 -> 0 | L80: =SUMIFS(_CALC_ALLOC!$AN$1:$AN$349,_CALC_ALLOC!$A$1:$A$349,"2026",_CALC_ALLOC!$B$1:$B$349,"PIGIER_LYO",_CALC_ALLOC!$D$1:$D$349,"BAC_RH",_CALC_ALLOC!$E$1:$E$349,"B3",_CALC_ALLOC!$F$1:$F$349,"ALT") -> 0 | M80: =IFERROR(L80/D80,0) -> 0
B81: Bordeaux (PIGIER_BOR) | C81: =SUMIFS(_CALC_ALLOC!$G$1:$G$349,_CALC_ALLOC!$A$1:$A$349,"2026",_CALC_ALLOC!$B$1:$B$349,"PIGIER_BOR") -> 0 | D81: =SUMIFS(_CALC_ALLOC!$I$1:$I$349,_CALC_ALLOC!$A$1:$A$349,"2026",_CALC_ALLOC!$B$1:$B$349,"PIGIER_BOR") -> 0 | E81: =SUMIFS(_CALC_ALLOC!$AI$1:$AI$349,_CALC_ALLOC!$A$1:$A$349,"2026",_CALC_ALLOC!$B$1:$B$349,"PIGIER_BOR") -> 0 | F81: =SUMIFS(_CALC_ALLOC!$AJ$1:$AJ$349,_CALC_ALLOC!$A$1:$A$349,"2026",_CALC_ALLOC!$B$1:$B$349,"PIGIER_BOR") -> 0 | G81: =SUMIFS(_CALC_ALLOC!$AK$1:$AK$349,_CALC_ALLOC!$A$1:$A$349,"2026",_CALC_ALLOC!$B$1:$B$349,"PIGIER_BOR") -> 0 | H81: =SUMIFS(_CALC_ALLOC!$AL$1:$AL$349,_CALC_ALLOC!$A$1:$A$349,"2026",_CALC_ALLOC!$B$1:$B$349,"PIGIER_BOR") -> 0 | I81: =SUMIFS(_CALC_ALLOC!$AR$1:$AR$349,_CALC_ALLOC!$A$1:$A$349,"2026",_CALC_ALLOC!$B$1:$B$349,"PIGIER_BOR") -> 0 | J81: =SUMIFS(_CALC_ALLOC!$AM$1:$AM$349,_CALC_ALLOC!$A$1:$A$349,"2026",_CALC_ALLOC!$B$1:$B$349,"PIGIER_BOR") -> 0 | K81: =E81+F81+G81+H81+I81+J81 -> 0 | L81: =SUMIFS(_CALC_ALLOC!$AN$1:$AN$349,_CALC_ALLOC!$A$1:$A$349,"2026",_CALC_ALLOC!$B$1:$B$349,"PIGIER_BOR") -> 0 | M81: =IFERROR(L81/D81,0) -> 0
B82: BTS_GES BTS1 ALT | C82: =SUMIFS(_CALC_ALLOC!$G$1:$G$349,_CALC_ALLOC!$A$1:$A$349,"2026",_CALC_ALLOC!$B$1:$B$349,"PIGIER_BOR",_CALC_ALLOC!$D$1:$D$349,"BTS_GES",_CALC_ALLOC!$E$1:$E$349,"BTS1",_CALC_ALLOC!$F$1:$F$349,"ALT") -> 0 | D82: =SUMIFS(_CALC_ALLOC!$I$1:$I$349,_CALC_ALLOC!$A$1:$A$349,"2026",_CALC_ALLOC!$B$1:$B$349,"PIGIER_BOR",_CALC_ALLOC!$D$1:$D$349,"BTS_GES",_CALC_ALLOC!$E$1:$E$349,"BTS1",_CALC_ALLOC!$F$1:$F$349,"ALT") -> 0 | E82: =SUMIFS(_CALC_ALLOC!$AI$1:$AI$349,_CALC_ALLOC!$A$1:$A$349,"2026",_CALC_ALLOC!$B$1:$B$349,"PIGIER_BOR",_CALC_ALLOC!$D$1:$D$349,"BTS_GES",_CALC_ALLOC!$E$1:$E$349,"BTS1",_CALC_ALLOC!$F$1:$F$349,"ALT") -> 0 | F82: =SUMIFS(_CALC_ALLOC!$AJ$1:$AJ$349,_CALC_ALLOC!$A$1:$A$349,"2026",_CALC_ALLOC!$B$1:$B$349,"PIGIER_BOR",_CALC_ALLOC!$D$1:$D$349,"BTS_GES",_CALC_ALLOC!$E$1:$E$349,"BTS1",_CALC_ALLOC!$F$1:$F$349,"ALT") -> 0 | G82: =SUMIFS(_CALC_ALLOC!$AK$1:$AK$349,_CALC_ALLOC!$A$1:$A$349,"2026",_CALC_ALLOC!$B$1:$B$349,"PIGIER_BOR",_CALC_ALLOC!$D$1:$D$349,"BTS_GES",_CALC_ALLOC!$E$1:$E$349,"BTS1",_CALC_ALLOC!$F$1:$F$349,"ALT") -> 0 | H82: =SUMIFS(_CALC_ALLOC!$AL$1:$AL$349,_CALC_ALLOC!$A$1:$A$349,"2026",_CALC_ALLOC!$B$1:$B$349,"PIGIER_BOR",_CALC_ALLOC!$D$1:$D$349,"BTS_GES",_CALC_ALLOC!$E$1:$E$349,"BTS1",_CALC_ALLOC!$F$1:$F$349,"ALT") -> 0 | I82: =SUMIFS(_CALC_ALLOC!$AR$1:$AR$349,_CALC_ALLOC!$A$1:$A$349,"2026",_CALC_ALLOC!$B$1:$B$349,"PIGIER_BOR",_CALC_ALLOC!$D$1:$D$349,"BTS_GES",_CALC_ALLOC!$E$1:$E$349,"BTS1",_CALC_ALLOC!$F$1:$F$349,"ALT") -> 0 | J82: =SUMIFS(_CALC_ALLOC!$AM$1:$AM$349,_CALC_ALLOC!$A$1:$A$349,"2026",_CALC_ALLOC!$B$1:$B$349,"PIGIER_BOR",_CALC_ALLOC!$D$1:$D$349,"BTS_GES",_CALC_ALLOC!$E$1:$E$349,"BTS1",_CALC_ALLOC!$F$1:$F$349,"ALT") -> 0 | K82: =E82+F82+G82+H82+I82+J82 -> 0 | L82: =SUMIFS(_CALC_ALLOC!$AN$1:$AN$349,_CALC_ALLOC!$A$1:$A$349,"2026",_CALC_ALLOC!$B$1:$B$349,"PIGIER_BOR",_CALC_ALLOC!$D$1:$D$349,"BTS_GES",_CALC_ALLOC!$E$1:$E$349,"BTS1",_CALC_ALLOC!$F$1:$F$349,"ALT") -> 0 | M82: =IFERROR(L82/D82,0) -> 0
B83: BTS_GES BTS2 ALT | C83: =SUMIFS(_CALC_ALLOC!$G$1:$G$349,_CALC_ALLOC!$A$1:$A$349,"2026",_CALC_ALLOC!$B$1:$B$349,"PIGIER_BOR",_CALC_ALLOC!$D$1:$D$349,"BTS_GES",_CALC_ALLOC!$E$1:$E$349,"BTS2",_CALC_ALLOC!$F$1:$F$349,"ALT") -> 0 | D83: =SUMIFS(_CALC_ALLOC!$I$1:$I$349,_CALC_ALLOC!$A$1:$A$349,"2026",_CALC_ALLOC!$B$1:$B$349,"PIGIER_BOR",_CALC_ALLOC!$D$1:$D$349,"BTS_GES",_CALC_ALLOC!$E$1:$E$349,"BTS2",_CALC_ALLOC!$F$1:$F$349,"ALT") -> 0 | E83: =SUMIFS(_CALC_ALLOC!$AI$1:$AI$349,_CALC_ALLOC!$A$1:$A$349,"2026",_CALC_ALLOC!$B$1:$B$349,"PIGIER_BOR",_CALC_ALLOC!$D$1:$D$349,"BTS_GES",_CALC_ALLOC!$E$1:$E$349,"BTS2",_CALC_ALLOC!$F$1:$F$349,"ALT") -> 0 | F83: =SUMIFS(_CALC_ALLOC!$AJ$1:$AJ$349,_CALC_ALLOC!$A$1:$A$349,"2026",_CALC_ALLOC!$B$1:$B$349,"PIGIER_BOR",_CALC_ALLOC!$D$1:$D$349,"BTS_GES",_CALC_ALLOC!$E$1:$E$349,"BTS2",_CALC_ALLOC!$F$1:$F$349,"ALT") -> 0 | G83: =SUMIFS(_CALC_ALLOC!$AK$1:$AK$349,_CALC_ALLOC!$A$1:$A$349,"2026",_CALC_ALLOC!$B$1:$B$349,"PIGIER_BOR",_CALC_ALLOC!$D$1:$D$349,"BTS_GES",_CALC_ALLOC!$E$1:$E$349,"BTS2",_CALC_ALLOC!$F$1:$F$349,"ALT") -> 0 | H83: =SUMIFS(_CALC_ALLOC!$AL$1:$AL$349,_CALC_ALLOC!$A$1:$A$349,"2026",_CALC_ALLOC!$B$1:$B$349,"PIGIER_BOR",_CALC_ALLOC!$D$1:$D$349,"BTS_GES",_CALC_ALLOC!$E$1:$E$349,"BTS2",_CALC_ALLOC!$F$1:$F$349,"ALT") -> 0 | I83: =SUMIFS(_CALC_ALLOC!$AR$1:$AR$349,_CALC_ALLOC!$A$1:$A$349,"2026",_CALC_ALLOC!$B$1:$B$349,"PIGIER_BOR",_CALC_ALLOC!$D$1:$D$349,"BTS_GES",_CALC_ALLOC!$E$1:$E$349,"BTS2",_CALC_ALLOC!$F$1:$F$349,"ALT") -> 0 | J83: =SUMIFS(_CALC_ALLOC!$AM$1:$AM$349,_CALC_ALLOC!$A$1:$A$349,"2026",_CALC_ALLOC!$B$1:$B$349,"PIGIER_BOR",_CALC_ALLOC!$D$1:$D$349,"BTS_GES",_CALC_ALLOC!$E$1:$E$349,"BTS2",_CALC_ALLOC!$F$1:$F$349,"ALT") -> 0 | K83: =E83+F83+G83+H83+I83+J83 -> 0 | L83: =SUMIFS(_CALC_ALLOC!$AN$1:$AN$349,_CALC_ALLOC!$A$1:$A$349,"2026",_CALC_ALLOC!$B$1:$B$349,"PIGIER_BOR",_CALC_ALLOC!$D$1:$D$349,"BTS_GES",_CALC_ALLOC!$E$1:$E$349,"BTS2",_CALC_ALLOC!$F$1:$F$349,"ALT") -> 0 | M83: =IFERROR(L83/D83,0) -> 0
B84: BAC_RH B1 ALT | C84: =SUMIFS(_CALC_ALLOC!$G$1:$G$349,_CALC_ALLOC!$A$1:$A$349,"2026",_CALC_ALLOC!$B$1:$B$349,"PIGIER_BOR",_CALC_ALLOC!$D$1:$D$349,"BAC_RH",_CALC_ALLOC!$E$1:$E$349,"B1",_CALC_ALLOC!$F$1:$F$349,"ALT") -> 0 | D84: =SUMIFS(_CALC_ALLOC!$I$1:$I$349,_CALC_ALLOC!$A$1:$A$349,"2026",_CALC_ALLOC!$B$1:$B$349,"PIGIER_BOR",_CALC_ALLOC!$D$1:$D$349,"BAC_RH",_CALC_ALLOC!$E$1:$E$349,"B1",_CALC_ALLOC!$F$1:$F$349,"ALT") -> 0 | E84: =SUMIFS(_CALC_ALLOC!$AI$1:$AI$349,_CALC_ALLOC!$A$1:$A$349,"2026",_CALC_ALLOC!$B$1:$B$349,"PIGIER_BOR",_CALC_ALLOC!$D$1:$D$349,"BAC_RH",_CALC_ALLOC!$E$1:$E$349,"B1",_CALC_ALLOC!$F$1:$F$349,"ALT") -> 0 | F84: =SUMIFS(_CALC_ALLOC!$AJ$1:$AJ$349,_CALC_ALLOC!$A$1:$A$349,"2026",_CALC_ALLOC!$B$1:$B$349,"PIGIER_BOR",_CALC_ALLOC!$D$1:$D$349,"BAC_RH",_CALC_ALLOC!$E$1:$E$349,"B1",_CALC_ALLOC!$F$1:$F$349,"ALT") -> 0 | G84: =SUMIFS(_CALC_ALLOC!$AK$1:$AK$349,_CALC_ALLOC!$A$1:$A$349,"2026",_CALC_ALLOC!$B$1:$B$349,"PIGIER_BOR",_CALC_ALLOC!$D$1:$D$349,"BAC_RH",_CALC_ALLOC!$E$1:$E$349,"B1",_CALC_ALLOC!$F$1:$F$349,"ALT") -> 0 | H84: =SUMIFS(_CALC_ALLOC!$AL$1:$AL$349,_CALC_ALLOC!$A$1:$A$349,"2026",_CALC_ALLOC!$B$1:$B$349,"PIGIER_BOR",_CALC_ALLOC!$D$1:$D$349,"BAC_RH",_CALC_ALLOC!$E$1:$E$349,"B1",_CALC_ALLOC!$F$1:$F$349,"ALT") -> 0 | I84: =SUMIFS(_CALC_ALLOC!$AR$1:$AR$349,_CALC_ALLOC!$A$1:$A$349,"2026",_CALC_ALLOC!$B$1:$B$349,"PIGIER_BOR",_CALC_ALLOC!$D$1:$D$349,"BAC_RH",_CALC_ALLOC!$E$1:$E$349,"B1",_CALC_ALLOC!$F$1:$F$349,"ALT") -> 0 | J84: =SUMIFS(_CALC_ALLOC!$AM$1:$AM$349,_CALC_ALLOC!$A$1:$A$349,"2026",_CALC_ALLOC!$B$1:$B$349,"PIGIER_BOR",_CALC_ALLOC!$D$1:$D$349,"BAC_RH",_CALC_ALLOC!$E$1:$E$349,"B1",_CALC_ALLOC!$F$1:$F$349,"ALT") -> 0 | K84: =E84+F84+G84+H84+I84+J84 -> 0 | L84: =SUMIFS(_CALC_ALLOC!$AN$1:$AN$349,_CALC_ALLOC!$A$1:$A$349,"2026",_CALC_ALLOC!$B$1:$B$349,"PIGIER_BOR",_CALC_ALLOC!$D$1:$D$349,"BAC_RH",_CALC_ALLOC!$E$1:$E$349,"B1",_CALC_ALLOC!$F$1:$F$349,"ALT") -> 0 | M84: =IFERROR(L84/D84,0) -> 0
B85: BAC_RH B3 ALT | C85: =SUMIFS(_CALC_ALLOC!$G$1:$G$349,_CALC_ALLOC!$A$1:$A$349,"2026",_CALC_ALLOC!$B$1:$B$349,"PIGIER_BOR",_CALC_ALLOC!$D$1:$D$349,"BAC_RH",_CALC_ALLOC!$E$1:$E$349,"B3",_CALC_ALLOC!$F$1:$F$349,"ALT") -> 0 | D85: =SUMIFS(_CALC_ALLOC!$I$1:$I$349,_CALC_ALLOC!$A$1:$A$349,"2026",_CALC_ALLOC!$B$1:$B$349,"PIGIER_BOR",_CALC_ALLOC!$D$1:$D$349,"BAC_RH",_CALC_ALLOC!$E$1:$E$349,"B3",_CALC_ALLOC!$F$1:$F$349,"ALT") -> 0 | E85: =SUMIFS(_CALC_ALLOC!$AI$1:$AI$349,_CALC_ALLOC!$A$1:$A$349,"2026",_CALC_ALLOC!$B$1:$B$349,"PIGIER_BOR",_CALC_ALLOC!$D$1:$D$349,"BAC_RH",_CALC_ALLOC!$E$1:$E$349,"B3",_CALC_ALLOC!$F$1:$F$349,"ALT") -> 0 | F85: =SUMIFS(_CALC_ALLOC!$AJ$1:$AJ$349,_CALC_ALLOC!$A$1:$A$349,"2026",_CALC_ALLOC!$B$1:$B$349,"PIGIER_BOR",_CALC_ALLOC!$D$1:$D$349,"BAC_RH",_CALC_ALLOC!$E$1:$E$349,"B3",_CALC_ALLOC!$F$1:$F$349,"ALT") -> 0 | G85: =SUMIFS(_CALC_ALLOC!$AK$1:$AK$349,_CALC_ALLOC!$A$1:$A$349,"2026",_CALC_ALLOC!$B$1:$B$349,"PIGIER_BOR",_CALC_ALLOC!$D$1:$D$349,"BAC_RH",_CALC_ALLOC!$E$1:$E$349,"B3",_CALC_ALLOC!$F$1:$F$349,"ALT") -> 0 | H85: =SUMIFS(_CALC_ALLOC!$AL$1:$AL$349,_CALC_ALLOC!$A$1:$A$349,"2026",_CALC_ALLOC!$B$1:$B$349,"PIGIER_BOR",_CALC_ALLOC!$D$1:$D$349,"BAC_RH",_CALC_ALLOC!$E$1:$E$349,"B3",_CALC_ALLOC!$F$1:$F$349,"ALT") -> 0 | I85: =SUMIFS(_CALC_ALLOC!$AR$1:$AR$349,_CALC_ALLOC!$A$1:$A$349,"2026",_CALC_ALLOC!$B$1:$B$349,"PIGIER_BOR",_CALC_ALLOC!$D$1:$D$349,"BAC_RH",_CALC_ALLOC!$E$1:$E$349,"B3",_CALC_ALLOC!$F$1:$F$349,"ALT") -> 0 | J85: =SUMIFS(_CALC_ALLOC!$AM$1:$AM$349,_CALC_ALLOC!$A$1:$A$349,"2026",_CALC_ALLOC!$B$1:$B$349,"PIGIER_BOR",_CALC_ALLOC!$D$1:$D$349,"BAC_RH",_CALC_ALLOC!$E$1:$E$349,"B3",_CALC_ALLOC!$F$1:$F$349,"ALT") -> 0 | K85: =E85+F85+G85+H85+I85+J85 -> 0 | L85: =SUMIFS(_CALC_ALLOC!$AN$1:$AN$349,_CALC_ALLOC!$A$1:$A$349,"2026",_CALC_ALLOC!$B$1:$B$349,"PIGIER_BOR",_CALC_ALLOC!$D$1:$D$349,"BAC_RH",_CALC_ALLOC!$E$1:$E$349,"B3",_CALC_ALLOC!$F$1:$F$349,"ALT") -> 0 | M85: =IFERROR(L85/D85,0) -> 0
B86: Tunon | C86: =SUMIFS(_CALC_ALLOC!$G$1:$G$349,_CALC_ALLOC!$A$1:$A$349,"2026",_CALC_ALLOC!$C$1:$C$349,"TUNON") -> 0 | D86: =SUMIFS(_CALC_ALLOC!$I$1:$I$349,_CALC_ALLOC!$A$1:$A$349,"2026",_CALC_ALLOC!$C$1:$C$349,"TUNON") -> 0 | E86: =SUMIFS(_CALC_ALLOC!$AI$1:$AI$349,_CALC_ALLOC!$A$1:$A$349,"2026",_CALC_ALLOC!$C$1:$C$349,"TUNON") -> 0 | F86: =SUMIFS(_CALC_ALLOC!$AJ$1:$AJ$349,_CALC_ALLOC!$A$1:$A$349,"2026",_CALC_ALLOC!$C$1:$C$349,"TUNON") -> 0 | G86: =SUMIFS(_CALC_ALLOC!$AK$1:$AK$349,_CALC_ALLOC!$A$1:$A$349,"2026",_CALC_ALLOC!$C$1:$C$349,"TUNON") -> 0 | H86: =SUMIFS(_CALC_ALLOC!$AL$1:$AL$349,_CALC_ALLOC!$A$1:$A$349,"2026",_CALC_ALLOC!$C$1:$C$349,"TUNON") -> 0 | I86: =SUMIFS(_CALC_ALLOC!$AR$1:$AR$349,_CALC_ALLOC!$A$1:$A$349,"2026",_CALC_ALLOC!$C$1:$C$349,"TUNON") -> 0 | J86: =SUMIFS(_CALC_ALLOC!$AM$1:$AM$349,_CALC_ALLOC!$A$1:$A$349,"2026",_CALC_ALLOC!$C$1:$C$349,"TUNON") -> 0 | K86: =E86+F86+G86+H86+I86+J86 -> 0 | L86: =SUMIFS(_CALC_ALLOC!$AN$1:$AN$349,_CALC_ALLOC!$A$1:$A$349,"2026",_CALC_ALLOC!$C$1:$C$349,"TUNON") -> 0 | M86: =IFERROR(L86/D86,0) -> 0
B87: Paris (TUNON_PAR) | C87: =SUMIFS(_CALC_ALLOC!$G$1:$G$349,_CALC_ALLOC!$A$1:$A$349,"2026",_CALC_ALLOC!$B$1:$B$349,"TUNON_PAR") -> 0 | D87: =SUMIFS(_CALC_ALLOC!$I$1:$I$349,_CALC_ALLOC!$A$1:$A$349,"2026",_CALC_ALLOC!$B$1:$B$349,"TUNON_PAR") -> 0 | E87: =SUMIFS(_CALC_ALLOC!$AI$1:$AI$349,_CALC_ALLOC!$A$1:$A$349,"2026",_CALC_ALLOC!$B$1:$B$349,"TUNON_PAR") -> 0 | F87: =SUMIFS(_CALC_ALLOC!$AJ$1:$AJ$349,_CALC_ALLOC!$A$1:$A$349,"2026",_CALC_ALLOC!$B$1:$B$349,"TUNON_PAR") -> 0 | G87: =SUMIFS(_CALC_ALLOC!$AK$1:$AK$349,_CALC_ALLOC!$A$1:$A$349,"2026",_CALC_ALLOC!$B$1:$B$349,"TUNON_PAR") -> 0 | H87: =SUMIFS(_CALC_ALLOC!$AL$1:$AL$349,_CALC_ALLOC!$A$1:$A$349,"2026",_CALC_ALLOC!$B$1:$B$349,"TUNON_PAR") -> 0 | I87: =SUMIFS(_CALC_ALLOC!$AR$1:$AR$349,_CALC_ALLOC!$A$1:$A$349,"2026",_CALC_ALLOC!$B$1:$B$349,"TUNON_PAR") -> 0 | J87: =SUMIFS(_CALC_ALLOC!$AM$1:$AM$349,_CALC_ALLOC!$A$1:$A$349,"2026",_CALC_ALLOC!$B$1:$B$349,"TUNON_PAR") -> 0 | K87: =E87+F87+G87+H87+I87+J87 -> 0 | L87: =SUMIFS(_CALC_ALLOC!$AN$1:$AN$349,_CALC_ALLOC!$A$1:$A$349,"2026",_CALC_ALLOC!$B$1:$B$349,"TUNON_PAR") -> 0 | M87: =IFERROR(L87/D87,0) -> 0
B88: BAC_TOU B1 ALT | C88: =SUMIFS(_CALC_ALLOC!$G$1:$G$349,_CALC_ALLOC!$A$1:$A$349,"2026",_CALC_ALLOC!$B$1:$B$349,"TUNON_PAR",_CALC_ALLOC!$D$1:$D$349,"BAC_TOU",_CALC_ALLOC!$E$1:$E$349,"B1",_CALC_ALLOC!$F$1:$F$349,"ALT") -> 0 | D88: =SUMIFS(_CALC_ALLOC!$I$1:$I$349,_CALC_ALLOC!$A$1:$A$349,"2026",_CALC_ALLOC!$B$1:$B$349,"TUNON_PAR",_CALC_ALLOC!$D$1:$D$349,"BAC_TOU",_CALC_ALLOC!$E$1:$E$349,"B1",_CALC_ALLOC!$F$1:$F$349,"ALT") -> 0 | E88: =SUMIFS(_CALC_ALLOC!$AI$1:$AI$349,_CALC_ALLOC!$A$1:$A$349,"2026",_CALC_ALLOC!$B$1:$B$349,"TUNON_PAR",_CALC_ALLOC!$D$1:$D$349,"BAC_TOU",_CALC_ALLOC!$E$1:$E$349,"B1",_CALC_ALLOC!$F$1:$F$349,"ALT") -> 0 | F88: =SUMIFS(_CALC_ALLOC!$AJ$1:$AJ$349,_CALC_ALLOC!$A$1:$A$349,"2026",_CALC_ALLOC!$B$1:$B$349,"TUNON_PAR",_CALC_ALLOC!$D$1:$D$349,"BAC_TOU",_CALC_ALLOC!$E$1:$E$349,"B1",_CALC_ALLOC!$F$1:$F$349,"ALT") -> 0 | G88: =SUMIFS(_CALC_ALLOC!$AK$1:$AK$349,_CALC_ALLOC!$A$1:$A$349,"2026",_CALC_ALLOC!$B$1:$B$349,"TUNON_PAR",_CALC_ALLOC!$D$1:$D$349,"BAC_TOU",_CALC_ALLOC!$E$1:$E$349,"B1",_CALC_ALLOC!$F$1:$F$349,"ALT") -> 0 | H88: =SUMIFS(_CALC_ALLOC!$AL$1:$AL$349,_CALC_ALLOC!$A$1:$A$349,"2026",_CALC_ALLOC!$B$1:$B$349,"TUNON_PAR",_CALC_ALLOC!$D$1:$D$349,"BAC_TOU",_CALC_ALLOC!$E$1:$E$349,"B1",_CALC_ALLOC!$F$1:$F$349,"ALT") -> 0 | I88: =SUMIFS(_CALC_ALLOC!$AR$1:$AR$349,_CALC_ALLOC!$A$1:$A$349,"2026",_CALC_ALLOC!$B$1:$B$349,"TUNON_PAR",_CALC_ALLOC!$D$1:$D$349,"BAC_TOU",_CALC_ALLOC!$E$1:$E$349,"B1",_CALC_ALLOC!$F$1:$F$349,"ALT") -> 0 | J88: =SUMIFS(_CALC_ALLOC!$AM$1:$AM$349,_CALC_ALLOC!$A$1:$A$349,"2026",_CALC_ALLOC!$B$1:$B$349,"TUNON_PAR",_CALC_ALLOC!$D$1:$D$349,"BAC_TOU",_CALC_ALLOC!$E$1:$E$349,"B1",_CALC_ALLOC!$F$1:$F$349,"ALT") -> 0 | K88: =E88+F88+G88+H88+I88+J88 -> 0 | L88: =SUMIFS(_CALC_ALLOC!$AN$1:$AN$349,_CALC_ALLOC!$A$1:$A$349,"2026",_CALC_ALLOC!$B$1:$B$349,"TUNON_PAR",_CALC_ALLOC!$D$1:$D$349,"BAC_TOU",_CALC_ALLOC!$E$1:$E$349,"B1",_CALC_ALLOC!$F$1:$F$349,"ALT") -> 0 | M88: =IFERROR(L88/D88,0) -> 0
B89: BAC_TOU B2 ALT | C89: =SUMIFS(_CALC_ALLOC!$G$1:$G$349,_CALC_ALLOC!$A$1:$A$349,"2026",_CALC_ALLOC!$B$1:$B$349,"TUNON_PAR",_CALC_ALLOC!$D$1:$D$349,"BAC_TOU",_CALC_ALLOC!$E$1:$E$349,"B2",_CALC_ALLOC!$F$1:$F$349,"ALT") -> 0 | D89: =SUMIFS(_CALC_ALLOC!$I$1:$I$349,_CALC_ALLOC!$A$1:$A$349,"2026",_CALC_ALLOC!$B$1:$B$349,"TUNON_PAR",_CALC_ALLOC!$D$1:$D$349,"BAC_TOU",_CALC_ALLOC!$E$1:$E$349,"B2",_CALC_ALLOC!$F$1:$F$349,"ALT") -> 0 | E89: =SUMIFS(_CALC_ALLOC!$AI$1:$AI$349,_CALC_ALLOC!$A$1:$A$349,"2026",_CALC_ALLOC!$B$1:$B$349,"TUNON_PAR",_CALC_ALLOC!$D$1:$D$349,"BAC_TOU",_CALC_ALLOC!$E$1:$E$349,"B2",_CALC_ALLOC!$F$1:$F$349,"ALT") -> 0 | F89: =SUMIFS(_CALC_ALLOC!$AJ$1:$AJ$349,_CALC_ALLOC!$A$1:$A$349,"2026",_CALC_ALLOC!$B$1:$B$349,"TUNON_PAR",_CALC_ALLOC!$D$1:$D$349,"BAC_TOU",_CALC_ALLOC!$E$1:$E$349,"B2",_CALC_ALLOC!$F$1:$F$349,"ALT") -> 0 | G89: =SUMIFS(_CALC_ALLOC!$AK$1:$AK$349,_CALC_ALLOC!$A$1:$A$349,"2026",_CALC_ALLOC!$B$1:$B$349,"TUNON_PAR",_CALC_ALLOC!$D$1:$D$349,"BAC_TOU",_CALC_ALLOC!$E$1:$E$349,"B2",_CALC_ALLOC!$F$1:$F$349,"ALT") -> 0 | H89: =SUMIFS(_CALC_ALLOC!$AL$1:$AL$349,_CALC_ALLOC!$A$1:$A$349,"2026",_CALC_ALLOC!$B$1:$B$349,"TUNON_PAR",_CALC_ALLOC!$D$1:$D$349,"BAC_TOU",_CALC_ALLOC!$E$1:$E$349,"B2",_CALC_ALLOC!$F$1:$F$349,"ALT") -> 0 | I89: =SUMIFS(_CALC_ALLOC!$AR$1:$AR$349,_CALC_ALLOC!$A$1:$A$349,"2026",_CALC_ALLOC!$B$1:$B$349,"TUNON_PAR",_CALC_ALLOC!$D$1:$D$349,"BAC_TOU",_CALC_ALLOC!$E$1:$E$349,"B2",_CALC_ALLOC!$F$1:$F$349,"ALT") -> 0 | J89: =SUMIFS(_CALC_ALLOC!$AM$1:$AM$349,_CALC_ALLOC!$A$1:$A$349,"2026",_CALC_ALLOC!$B$1:$B$349,"TUNON_PAR",_CALC_ALLOC!$D$1:$D$349,"BAC_TOU",_CALC_ALLOC!$E$1:$E$349,"B2",_CALC_ALLOC!$F$1:$F$349,"ALT") -> 0 | K89: =E89+F89+G89+H89+I89+J89 -> 0 | L89: =SUMIFS(_CALC_ALLOC!$AN$1:$AN$349,_CALC_ALLOC!$A$1:$A$349,"2026",_CALC_ALLOC!$B$1:$B$349,"TUNON_PAR",_CALC_ALLOC!$D$1:$D$349,"BAC_TOU",_CALC_ALLOC!$E$1:$E$349,"B2",_CALC_ALLOC!$F$1:$F$349,"ALT") -> 0 | M89: =IFERROR(L89/D89,0) -> 0
B90: BAC_TOU B3 ALT | C90: =SUMIFS(_CALC_ALLOC!$G$1:$G$349,_CALC_ALLOC!$A$1:$A$349,"2026",_CALC_ALLOC!$B$1:$B$349,"TUNON_PAR",_CALC_ALLOC!$D$1:$D$349,"BAC_TOU",_CALC_ALLOC!$E$1:$E$349,"B3",_CALC_ALLOC!$F$1:$F$349,"ALT") -> 0 | D90: =SUMIFS(_CALC_ALLOC!$I$1:$I$349,_CALC_ALLOC!$A$1:$A$349,"2026",_CALC_ALLOC!$B$1:$B$349,"TUNON_PAR",_CALC_ALLOC!$D$1:$D$349,"BAC_TOU",_CALC_ALLOC!$E$1:$E$349,"B3",_CALC_ALLOC!$F$1:$F$349,"ALT") -> 0 | E90: =SUMIFS(_CALC_ALLOC!$AI$1:$AI$349,_CALC_ALLOC!$A$1:$A$349,"2026",_CALC_ALLOC!$B$1:$B$349,"TUNON_PAR",_CALC_ALLOC!$D$1:$D$349,"BAC_TOU",_CALC_ALLOC!$E$1:$E$349,"B3",_CALC_ALLOC!$F$1:$F$349,"ALT") -> 0 | F90: =SUMIFS(_CALC_ALLOC!$AJ$1:$AJ$349,_CALC_ALLOC!$A$1:$A$349,"2026",_CALC_ALLOC!$B$1:$B$349,"TUNON_PAR",_CALC_ALLOC!$D$1:$D$349,"BAC_TOU",_CALC_ALLOC!$E$1:$E$349,"B3",_CALC_ALLOC!$F$1:$F$349,"ALT") -> 0 | G90: =SUMIFS(_CALC_ALLOC!$AK$1:$AK$349,_CALC_ALLOC!$A$1:$A$349,"2026",_CALC_ALLOC!$B$1:$B$349,"TUNON_PAR",_CALC_ALLOC!$D$1:$D$349,"BAC_TOU",_CALC_ALLOC!$E$1:$E$349,"B3",_CALC_ALLOC!$F$1:$F$349,"ALT") -> 0 | H90: =SUMIFS(_CALC_ALLOC!$AL$1:$AL$349,_CALC_ALLOC!$A$1:$A$349,"2026",_CALC_ALLOC!$B$1:$B$349,"TUNON_PAR",_CALC_ALLOC!$D$1:$D$349,"BAC_TOU",_CALC_ALLOC!$E$1:$E$349,"B3",_CALC_ALLOC!$F$1:$F$349,"ALT") -> 0 | I90: =SUMIFS(_CALC_ALLOC!$AR$1:$AR$349,_CALC_ALLOC!$A$1:$A$349,"2026",_CALC_ALLOC!$B$1:$B$349,"TUNON_PAR",_CALC_ALLOC!$D$1:$D$349,"BAC_TOU",_CALC_ALLOC!$E$1:$E$349,"B3",_CALC_ALLOC!$F$1:$F$349,"ALT") -> 0 | J90: =SUMIFS(_CALC_ALLOC!$AM$1:$AM$349,_CALC_ALLOC!$A$1:$A$349,"2026",_CALC_ALLOC!$B$1:$B$349,"TUNON_PAR",_CALC_ALLOC!$D$1:$D$349,"BAC_TOU",_CALC_ALLOC!$E$1:$E$349,"B3",_CALC_ALLOC!$F$1:$F$349,"ALT") -> 0 | K90: =E90+F90+G90+H90+I90+J90 -> 0 | L90: =SUMIFS(_CALC_ALLOC!$AN$1:$AN$349,_CALC_ALLOC!$A$1:$A$349,"2026",_CALC_ALLOC!$B$1:$B$349,"TUNON_PAR",_CALC_ALLOC!$D$1:$D$349,"BAC_TOU",_CALC_ALLOC!$E$1:$E$349,"B3",_CALC_ALLOC!$F$1:$F$349,"ALT") -> 0 | M90: =IFERROR(L90/D90,0) -> 0
B91: Lyon (TUNON_LYO) | C91: =SUMIFS(_CALC_ALLOC!$G$1:$G$349,_CALC_ALLOC!$A$1:$A$349,"2026",_CALC_ALLOC!$B$1:$B$349,"TUNON_LYO") -> 0 | D91: =SUMIFS(_CALC_ALLOC!$I$1:$I$349,_CALC_ALLOC!$A$1:$A$349,"2026",_CALC_ALLOC!$B$1:$B$349,"TUNON_LYO") -> 0 | E91: =SUMIFS(_CALC_ALLOC!$AI$1:$AI$349,_CALC_ALLOC!$A$1:$A$349,"2026",_CALC_ALLOC!$B$1:$B$349,"TUNON_LYO") -> 0 | F91: =SUMIFS(_CALC_ALLOC!$AJ$1:$AJ$349,_CALC_ALLOC!$A$1:$A$349,"2026",_CALC_ALLOC!$B$1:$B$349,"TUNON_LYO") -> 0 | G91: =SUMIFS(_CALC_ALLOC!$AK$1:$AK$349,_CALC_ALLOC!$A$1:$A$349,"2026",_CALC_ALLOC!$B$1:$B$349,"TUNON_LYO") -> 0 | H91: =SUMIFS(_CALC_ALLOC!$AL$1:$AL$349,_CALC_ALLOC!$A$1:$A$349,"2026",_CALC_ALLOC!$B$1:$B$349,"TUNON_LYO") -> 0 | I91: =SUMIFS(_CALC_ALLOC!$AR$1:$AR$349,_CALC_ALLOC!$A$1:$A$349,"2026",_CALC_ALLOC!$B$1:$B$349,"TUNON_LYO") -> 0 | J91: =SUMIFS(_CALC_ALLOC!$AM$1:$AM$349,_CALC_ALLOC!$A$1:$A$349,"2026",_CALC_ALLOC!$B$1:$B$349,"TUNON_LYO") -> 0 | K91: =E91+F91+G91+H91+I91+J91 -> 0 | L91: =SUMIFS(_CALC_ALLOC!$AN$1:$AN$349,_CALC_ALLOC!$A$1:$A$349,"2026",_CALC_ALLOC!$B$1:$B$349,"TUNON_LYO") -> 0 | M91: =IFERROR(L91/D91,0) -> 0
B92: BAC_TOU B1 ALT | C92: =SUMIFS(_CALC_ALLOC!$G$1:$G$349,_CALC_ALLOC!$A$1:$A$349,"2026",_CALC_ALLOC!$B$1:$B$349,"TUNON_LYO",_CALC_ALLOC!$D$1:$D$349,"BAC_TOU",_CALC_ALLOC!$E$1:$E$349,"B1",_CALC_ALLOC!$F$1:$F$349,"ALT") -> 0 | D92: =SUMIFS(_CALC_ALLOC!$I$1:$I$349,_CALC_ALLOC!$A$1:$A$349,"2026",_CALC_ALLOC!$B$1:$B$349,"TUNON_LYO",_CALC_ALLOC!$D$1:$D$349,"BAC_TOU",_CALC_ALLOC!$E$1:$E$349,"B1",_CALC_ALLOC!$F$1:$F$349,"ALT") -> 0 | E92: =SUMIFS(_CALC_ALLOC!$AI$1:$AI$349,_CALC_ALLOC!$A$1:$A$349,"2026",_CALC_ALLOC!$B$1:$B$349,"TUNON_LYO",_CALC_ALLOC!$D$1:$D$349,"BAC_TOU",_CALC_ALLOC!$E$1:$E$349,"B1",_CALC_ALLOC!$F$1:$F$349,"ALT") -> 0 | F92: =SUMIFS(_CALC_ALLOC!$AJ$1:$AJ$349,_CALC_ALLOC!$A$1:$A$349,"2026",_CALC_ALLOC!$B$1:$B$349,"TUNON_LYO",_CALC_ALLOC!$D$1:$D$349,"BAC_TOU",_CALC_ALLOC!$E$1:$E$349,"B1",_CALC_ALLOC!$F$1:$F$349,"ALT") -> 0 | G92: =SUMIFS(_CALC_ALLOC!$AK$1:$AK$349,_CALC_ALLOC!$A$1:$A$349,"2026",_CALC_ALLOC!$B$1:$B$349,"TUNON_LYO",_CALC_ALLOC!$D$1:$D$349,"BAC_TOU",_CALC_ALLOC!$E$1:$E$349,"B1",_CALC_ALLOC!$F$1:$F$349,"ALT") -> 0 | H92: =SUMIFS(_CALC_ALLOC!$AL$1:$AL$349,_CALC_ALLOC!$A$1:$A$349,"2026",_CALC_ALLOC!$B$1:$B$349,"TUNON_LYO",_CALC_ALLOC!$D$1:$D$349,"BAC_TOU",_CALC_ALLOC!$E$1:$E$349,"B1",_CALC_ALLOC!$F$1:$F$349,"ALT") -> 0 | I92: =SUMIFS(_CALC_ALLOC!$AR$1:$AR$349,_CALC_ALLOC!$A$1:$A$349,"2026",_CALC_ALLOC!$B$1:$B$349,"TUNON_LYO",_CALC_ALLOC!$D$1:$D$349,"BAC_TOU",_CALC_ALLOC!$E$1:$E$349,"B1",_CALC_ALLOC!$F$1:$F$349,"ALT") -> 0 | J92: =SUMIFS(_CALC_ALLOC!$AM$1:$AM$349,_CALC_ALLOC!$A$1:$A$349,"2026",_CALC_ALLOC!$B$1:$B$349,"TUNON_LYO",_CALC_ALLOC!$D$1:$D$349,"BAC_TOU",_CALC_ALLOC!$E$1:$E$349,"B1",_CALC_ALLOC!$F$1:$F$349,"ALT") -> 0 | K92: =E92+F92+G92+H92+I92+J92 -> 0 | L92: =SUMIFS(_CALC_ALLOC!$AN$1:$AN$349,_CALC_ALLOC!$A$1:$A$349,"2026",_CALC_ALLOC!$B$1:$B$349,"TUNON_LYO",_CALC_ALLOC!$D$1:$D$349,"BAC_TOU",_CALC_ALLOC!$E$1:$E$349,"B1",_CALC_ALLOC!$F$1:$F$349,"ALT") -> 0 | M92: =IFERROR(L92/D92,0) -> 0
B93: BAC_TOU B2 ALT | C93: =SUMIFS(_CALC_ALLOC!$G$1:$G$349,_CALC_ALLOC!$A$1:$A$349,"2026",_CALC_ALLOC!$B$1:$B$349,"TUNON_LYO",_CALC_ALLOC!$D$1:$D$349,"BAC_TOU",_CALC_ALLOC!$E$1:$E$349,"B2",_CALC_ALLOC!$F$1:$F$349,"ALT") -> 0 | D93: =SUMIFS(_CALC_ALLOC!$I$1:$I$349,_CALC_ALLOC!$A$1:$A$349,"2026",_CALC_ALLOC!$B$1:$B$349,"TUNON_LYO",_CALC_ALLOC!$D$1:$D$349,"BAC_TOU",_CALC_ALLOC!$E$1:$E$349,"B2",_CALC_ALLOC!$F$1:$F$349,"ALT") -> 0 | E93: =SUMIFS(_CALC_ALLOC!$AI$1:$AI$349,_CALC_ALLOC!$A$1:$A$349,"2026",_CALC_ALLOC!$B$1:$B$349,"TUNON_LYO",_CALC_ALLOC!$D$1:$D$349,"BAC_TOU",_CALC_ALLOC!$E$1:$E$349,"B2",_CALC_ALLOC!$F$1:$F$349,"ALT") -> 0 | F93: =SUMIFS(_CALC_ALLOC!$AJ$1:$AJ$349,_CALC_ALLOC!$A$1:$A$349,"2026",_CALC_ALLOC!$B$1:$B$349,"TUNON_LYO",_CALC_ALLOC!$D$1:$D$349,"BAC_TOU",_CALC_ALLOC!$E$1:$E$349,"B2",_CALC_ALLOC!$F$1:$F$349,"ALT") -> 0 | G93: =SUMIFS(_CALC_ALLOC!$AK$1:$AK$349,_CALC_ALLOC!$A$1:$A$349,"2026",_CALC_ALLOC!$B$1:$B$349,"TUNON_LYO",_CALC_ALLOC!$D$1:$D$349,"BAC_TOU",_CALC_ALLOC!$E$1:$E$349,"B2",_CALC_ALLOC!$F$1:$F$349,"ALT") -> 0 | H93: =SUMIFS(_CALC_ALLOC!$AL$1:$AL$349,_CALC_ALLOC!$A$1:$A$349,"2026",_CALC_ALLOC!$B$1:$B$349,"TUNON_LYO",_CALC_ALLOC!$D$1:$D$349,"BAC_TOU",_CALC_ALLOC!$E$1:$E$349,"B2",_CALC_ALLOC!$F$1:$F$349,"ALT") -> 0 | I93: =SUMIFS(_CALC_ALLOC!$AR$1:$AR$349,_CALC_ALLOC!$A$1:$A$349,"2026",_CALC_ALLOC!$B$1:$B$349,"TUNON_LYO",_CALC_ALLOC!$D$1:$D$349,"BAC_TOU",_CALC_ALLOC!$E$1:$E$349,"B2",_CALC_ALLOC!$F$1:$F$349,"ALT") -> 0 | J93: =SUMIFS(_CALC_ALLOC!$AM$1:$AM$349,_CALC_ALLOC!$A$1:$A$349,"2026",_CALC_ALLOC!$B$1:$B$349,"TUNON_LYO",_CALC_ALLOC!$D$1:$D$349,"BAC_TOU",_CALC_ALLOC!$E$1:$E$349,"B2",_CALC_ALLOC!$F$1:$F$349,"ALT") -> 0 | K93: =E93+F93+G93+H93+I93+J93 -> 0 | L93: =SUMIFS(_CALC_ALLOC!$AN$1:$AN$349,_CALC_ALLOC!$A$1:$A$349,"2026",_CALC_ALLOC!$B$1:$B$349,"TUNON_LYO",_CALC_ALLOC!$D$1:$D$349,"BAC_TOU",_CALC_ALLOC!$E$1:$E$349,"B2",_CALC_ALLOC!$F$1:$F$349,"ALT") -> 0 | M93: =IFERROR(L93/D93,0) -> 0
B94: BAC_TOU B3 ALT | C94: =SUMIFS(_CALC_ALLOC!$G$1:$G$349,_CALC_ALLOC!$A$1:$A$349,"2026",_CALC_ALLOC!$B$1:$B$349,"TUNON_LYO",_CALC_ALLOC!$D$1:$D$349,"BAC_TOU",_CALC_ALLOC!$E$1:$E$349,"B3",_CALC_ALLOC!$F$1:$F$349,"ALT") -> 0 | D94: =SUMIFS(_CALC_ALLOC!$I$1:$I$349,_CALC_ALLOC!$A$1:$A$349,"2026",_CALC_ALLOC!$B$1:$B$349,"TUNON_LYO",_CALC_ALLOC!$D$1:$D$349,"BAC_TOU",_CALC_ALLOC!$E$1:$E$349,"B3",_CALC_ALLOC!$F$1:$F$349,"ALT") -> 0 | E94: =SUMIFS(_CALC_ALLOC!$AI$1:$AI$349,_CALC_ALLOC!$A$1:$A$349,"2026",_CALC_ALLOC!$B$1:$B$349,"TUNON_LYO",_CALC_ALLOC!$D$1:$D$349,"BAC_TOU",_CALC_ALLOC!$E$1:$E$349,"B3",_CALC_ALLOC!$F$1:$F$349,"ALT") -> 0 | F94: =SUMIFS(_CALC_ALLOC!$AJ$1:$AJ$349,_CALC_ALLOC!$A$1:$A$349,"2026",_CALC_ALLOC!$B$1:$B$349,"TUNON_LYO",_CALC_ALLOC!$D$1:$D$349,"BAC_TOU",_CALC_ALLOC!$E$1:$E$349,"B3",_CALC_ALLOC!$F$1:$F$349,"ALT") -> 0 | G94: =SUMIFS(_CALC_ALLOC!$AK$1:$AK$349,_CALC_ALLOC!$A$1:$A$349,"2026",_CALC_ALLOC!$B$1:$B$349,"TUNON_LYO",_CALC_ALLOC!$D$1:$D$349,"BAC_TOU",_CALC_ALLOC!$E$1:$E$349,"B3",_CALC_ALLOC!$F$1:$F$349,"ALT") -> 0 | H94: =SUMIFS(_CALC_ALLOC!$AL$1:$AL$349,_CALC_ALLOC!$A$1:$A$349,"2026",_CALC_ALLOC!$B$1:$B$349,"TUNON_LYO",_CALC_ALLOC!$D$1:$D$349,"BAC_TOU",_CALC_ALLOC!$E$1:$E$349,"B3",_CALC_ALLOC!$F$1:$F$349,"ALT") -> 0 | I94: =SUMIFS(_CALC_ALLOC!$AR$1:$AR$349,_CALC_ALLOC!$A$1:$A$349,"2026",_CALC_ALLOC!$B$1:$B$349,"TUNON_LYO",_CALC_ALLOC!$D$1:$D$349,"BAC_TOU",_CALC_ALLOC!$E$1:$E$349,"B3",_CALC_ALLOC!$F$1:$F$349,"ALT") -> 0 | J94: =SUMIFS(_CALC_ALLOC!$AM$1:$AM$349,_CALC_ALLOC!$A$1:$A$349,"2026",_CALC_ALLOC!$B$1:$B$349,"TUNON_LYO",_CALC_ALLOC!$D$1:$D$349,"BAC_TOU",_CALC_ALLOC!$E$1:$E$349,"B3",_CALC_ALLOC!$F$1:$F$349,"ALT") -> 0 | K94: =E94+F94+G94+H94+I94+J94 -> 0 | L94: =SUMIFS(_CALC_ALLOC!$AN$1:$AN$349,_CALC_ALLOC!$A$1:$A$349,"2026",_CALC_ALLOC!$B$1:$B$349,"TUNON_LYO",_CALC_ALLOC!$D$1:$D$349,"BAC_TOU",_CALC_ALLOC!$E$1:$E$349,"B3",_CALC_ALLOC!$F$1:$F$349,"ALT") -> 0 | M94: =IFERROR(L94/D94,0) -> 0
B95: GROUPE | C95: =SUMIFS(_CALC_ALLOC!$G$1:$G$349,_CALC_ALLOC!$A$1:$A$349,"2026") -> 0 | D95: =SUMIFS(_CALC_ALLOC!$I$1:$I$349,_CALC_ALLOC!$A$1:$A$349,"2026") -> 0 | E95: =SUMIFS(_CALC_ALLOC!$AI$1:$AI$349,_CALC_ALLOC!$A$1:$A$349,"2026") -> 0 | F95: =SUMIFS(_CALC_ALLOC!$AJ$1:$AJ$349,_CALC_ALLOC!$A$1:$A$349,"2026") -> 0 | G95: =SUMIFS(_CALC_ALLOC!$AK$1:$AK$349,_CALC_ALLOC!$A$1:$A$349,"2026") -> 0 | H95: =SUMIFS(_CALC_ALLOC!$AL$1:$AL$349,_CALC_ALLOC!$A$1:$A$349,"2026") -> 0 | I95: =SUMIFS(_CALC_ALLOC!$AR$1:$AR$349,_CALC_ALLOC!$A$1:$A$349,"2026") -> 0 | J95: =SUMIFS(_CALC_ALLOC!$AM$1:$AM$349,_CALC_ALLOC!$A$1:$A$349,"2026") -> 0 | K95: =E95+F95+G95+H95+I95+J95 -> 0 | L95: =SUMIFS(_CALC_ALLOC!$AN$1:$AN$349,_CALC_ALLOC!$A$1:$A$349,"2026") -> 0 | M95: =IFERROR(L95/D95,0) -> 0

Sheet Allocation2
A1: SCENARIO | B1: VERSION | C1: PERIODE | D1: EXERCICE | E1: ENTITY | F1: MARQUE | G1: PROGRAMME | H1: AN_ETUDE | I1: MODALITE | J1: VOL_EFF | K1: VOL_CLASS | L1: CA | M1: COST_VAC | N1: COST_PERM | O1: COST_ODIR | P1: COST_STRUCT | Q1: COST_MARQUE | R1: COST_HOLDING | S1: COST_SIEGE | T1: COST_VARIABLE | U1: COST_STRUCTURE | V1: COST_COMPLET | W1: MARGE_COMPLETE | X1: VOL_NEW | Y1: POOL_VAC | Z1: POOL_PERM | AA1: POOL_ODIR | AB1: POOL_MKT | AC1: POOL_STRUCT | AD1: POOL_HOLDING | AE1: POOL_FRAIS_MARQUE

Sheet Campagne
A1: SCENARIO | B1: PERIODE | C1: ENTITY | D1: ORG_REF | E1: PAID_REF | F1: LEAD_REF | G1: SPEND_ACQ_REF | H1: SPEND_BRAND_REF | I1: PART_ORG | J1: CPL | K1: REND_ACQ | L1: CONVERSION | M1: REND_BRAND | N1: CAC_MARGINAL
A2: 1000 | B2: 1000 | C2: 1000 | D2: 1000 | E2: 1000 | F2: 1000 | G2: 1000 | H2: 1000 | I2: 1000 | J2: 1000 | K2: 1000 | L2: 1000 | M2: 1000 | N2: 1000

Sheet Moteur
A1: SCENARIO | B1: VERSION | C1: PERIODE | D1: ENTITY | E1: MARQUE | F1: PROGRAMME | G1: AN_ETUDE | H1: MODALITE | I1: EXERCICE | J1: NOUVEAUX | K1: EFFECTIF | L1: PRIX | M1: CA | O1: NOUVEAUX (live) | P1: EFFECTIF (live) | Q1: PRIX (live) | R1: 🟢 CA (live) | S1: Δ CA vs Tagetik
A2: 1000 | B2: 1000 | C2: 1000 | D2: 1000 | E2: 1000 | F2: 1000 | G2: 1000 | H2: 1000 | I2: 1000 | J2: 1000 | K2: 1000 | L2: 1000 | M2: 1000 | O2: =IF(D2="","",_CALC_MOTEUR!AE2) -> 0 | P2: =IF(D2="","",_CALC_MOTEUR!AF2) -> 0 | Q2: =IF(D2="","",_CALC_MOTEUR!AG2) -> 0 | R2: =IF(D2="","",_CALC_MOTEUR!AH2) -> 0 | S2: =IF(D2="","",R2-M2) -> -1000
O3: =IF(D3="","",_CALC_MOTEUR!AE3) | P3: =IF(D3="","",_CALC_MOTEUR!AF3) | Q3: =IF(D3="","",_CALC_MOTEUR!AG3) | R3: =IF(D3="","",_CALC_MOTEUR!AH3) | S3: =IF(D3="","",R3-M3)
O4: =IF(D4="","",_CALC_MOTEUR!AE4) | P4: =IF(D4="","",_CALC_MOTEUR!AF4) | Q4: =IF(D4="","",_CALC_MOTEUR!AG4) | R4: =IF(D4="","",_CALC_MOTEUR!AH4) | S4: =IF(D4="","",R4-M4)
O5: =IF(D5="","",_CALC_MOTEUR!AE5) | P5: =IF(D5="","",_CALC_MOTEUR!AF5) | Q5: =IF(D5="","",_CALC_MOTEUR!AG5) | R5: =IF(D5="","",_CALC_MOTEUR!AH5) | S5: =IF(D5="","",R5-M5)
O6: =IF(D6="","",_CALC_MOTEUR!AE6) | P6: =IF(D6="","",_CALC_MOTEUR!AF6) | Q6: =IF(D6="","",_CALC_MOTEUR!AG6) | R6: =IF(D6="","",_CALC_MOTEUR!AH6) | S6: =IF(D6="","",R6-M6)
O7: =IF(D7="","",_CALC_MOTEUR!AE7) | P7: =IF(D7="","",_CALC_MOTEUR!AF7) | Q7: =IF(D7="","",_CALC_MOTEUR!AG7) | R7: =IF(D7="","",_CALC_MOTEUR!AH7) | S7: =IF(D7="","",R7-M7)
O8: =IF(D8="","",_CALC_MOTEUR!AE8) | P8: =IF(D8="","",_CALC_MOTEUR!AF8) | Q8: =IF(D8="","",_CALC_MOTEUR!AG8) | R8: =IF(D8="","",_CALC_MOTEUR!AH8) | S8: =IF(D8="","",R8-M8)
O9: =IF(D9="","",_CALC_MOTEUR!AE9) | P9: =IF(D9="","",_CALC_MOTEUR!AF9) | Q9: =IF(D9="","",_CALC_MOTEUR!AG9) | R9: =IF(D9="","",_CALC_MOTEUR!AH9) | S9: =IF(D9="","",R9-M9)
O10: =IF(D10="","",_CALC_MOTEUR!AE10) | P10: =IF(D10="","",_CALC_MOTEUR!AF10) | Q10: =IF(D10="","",_CALC_MOTEUR!AG10) | R10: =IF(D10="","",_CALC_MOTEUR!AH10) | S10: =IF(D10="","",R10-M10)
O11: =IF(D11="","",_CALC_MOTEUR!AE11) | P11: =IF(D11="","",_CALC_MOTEUR!AF11) | Q11: =IF(D11="","",_CALC_MOTEUR!AG11) | R11: =IF(D11="","",_CALC_MOTEUR!AH11) | S11: =IF(D11="","",R11-M11)
O12: =IF(D12="","",_CALC_MOTEUR!AE12) | P12: =IF(D12="","",_CALC_MOTEUR!AF12) | Q12: =IF(D12="","",_CALC_MOTEUR!AG12) | R12: =IF(D12="","",_CALC_MOTEUR!AH12) | S12: =IF(D12="","",R12-M12)
O13: =IF(D13="","",_CALC_MOTEUR!AE13) | P13: =IF(D13="","",_CALC_MOTEUR!AF13) | Q13: =IF(D13="","",_CALC_MOTEUR!AG13) | R13: =IF(D13="","",_CALC_MOTEUR!AH13) | S13: =IF(D13="","",R13-M13)
O14: =IF(D14="","",_CALC_MOTEUR!AE14) | P14: =IF(D14="","",_CALC_MOTEUR!AF14) | Q14: =IF(D14="","",_CALC_MOTEUR!AG14) | R14: =IF(D14="","",_CALC_MOTEUR!AH14) | S14: =IF(D14="","",R14-M14)
... O175: =IF(D175="","",_CALC_MOTEUR!AE175) | P175: =IF(D175="","",_CALC_MOTEUR!AF175) | Q175: =IF(D175="","",_CALC_MOTEUR!AG175) | R175: =IF(D175="","",_CALC_MOTEUR!AH175) | S175: =IF(D175="","",R175-M175)

Sheet Compta
A1: Entity | B1: Account | C1: EXERCICE | D1: Scenario | E1: Period | F1: Amount
A2: 1000 | B2: 1000 | C2: 1000 | D2: 1000 | E2: 1000 | F2: 1000

Sheet PNL
A1: ENTITY | B1: ACCOUNT | C1: EXERCICE | D1: VERSION | E1: SCENARIO | F1: PERIOD | G1: AMOUNT | H1: 🟢 AMOUNT (live) | I1: Δ vs Tagetik
A2: 1000 | B2: 1000 | C2: 1000 | D2: 1000 | E2: 1000 | F2: 1000 | G2: 1000 | H2: =IF(PNL!A2="","",_CALC_PNL!P2) -> 1000 | I2: =IF(PNL!A2="","",IF(_CALC_PNL!E2=1,H2-G2,""))
H3: =IF(PNL!A3="","",_CALC_PNL!P3) | I3: =IF(PNL!A3="","",IF(_CALC_PNL!E3=1,H3-G3,""))
H4: =IF(PNL!A4="","",_CALC_PNL!P4) | I4: =IF(PNL!A4="","",IF(_CALC_PNL!E4=1,H4-G4,""))
H5: =IF(PNL!A5="","",_CALC_PNL!P5) | I5: =IF(PNL!A5="","",IF(_CALC_PNL!E5=1,H5-G5,""))
H6: =IF(PNL!A6="","",_CALC_PNL!P6) | I6: =IF(PNL!A6="","",IF(_CALC_PNL!E6=1,H6-G6,""))
H7: =IF(PNL!A7="","",_CALC_PNL!P7) | I7: =IF(PNL!A7="","",IF(_CALC_PNL!E7=1,H7-G7,""))
H8: =IF(PNL!A8="","",_CALC_PNL!P8) | I8: =IF(PNL!A8="","",IF(_CALC_PNL!E8=1,H8-G8,""))
H9: =IF(PNL!A9="","",_CALC_PNL!P9) | I9: =IF(PNL!A9="","",IF(_CALC_PNL!E9=1,H9-G9,""))
H10: =IF(PNL!A10="","",_CALC_PNL!P10) | I10: =IF(PNL!A10="","",IF(_CALC_PNL!E10=1,H10-G10,""))
H11: =IF(PNL!A11="","",_CALC_PNL!P11) | I11: =IF(PNL!A11="","",IF(_CALC_PNL!E11=1,H11-G11,""))
H12: =IF(PNL!A12="","",_CALC_PNL!P12) | I12: =IF(PNL!A12="","",IF(_CALC_PNL!E12=1,H12-G12,""))
H13: =IF(PNL!A13="","",_CALC_PNL!P13) | I13: =IF(PNL!A13="","",IF(_CALC_PNL!E13=1,H13-G13,""))
H14: =IF(PNL!A14="","",_CALC_PNL!P14) | I14: =IF(PNL!A14="","",IF(_CALC_PNL!E14=1,H14-G14,""))
... H1347: =IF(PNL!A1347="","",_CALC_PNL!P1347) | I1347: =IF(PNL!A1347="","",IF(_CALC_PNL!E1347=1,H1347-G1347,""))

Sheet Allocation

Sheet _CALC_MOTEUR
A1: KENT | B1: KVER | C1: KPROG | D1: KAN | E1: KMOD | F1: KMARQ | G1: VOL_LEAD | H1: VOL_EFF_INF | I1: REV_STUD | J1: RLC | K1: RCA | L1: YLD | M1: PASSAGE | N1: IS_ENTRY | O1: ORG_REF | P1: PAID_REF | Q1: LEAD_REF | R1: REND_ACQ | S1: REND_BRAND | T1: REJOUE | U1: BUD_REF | V1: ACQ | W1: BRAND | X1: PRICE | Y1: GLC | Z1: GCV | AA1: PASS | AB1: FEE | AC1: PRICE_COEF | AD1: NOUV_CALC | AE1: NOUVEAUX | AF1: EFFECTIF | AG1: PRIX | AH1: CA | AJ1: ■ VIOLET = colonne branchee sur une saisie (cad / Pilotage / 3_Allocation2) -> a recabler cote Tagetik
A2: =IF(Moteur!D2="","",Moteur!D2) -> 1000 | B2: =IF(Moteur!B2="","",Moteur!B2) -> 1000 | C2: =IF(Moteur!F2="","",Moteur!F2) -> 1000 | D2: =IF(Moteur!G2="","",Moteur!G2) -> 1000 | E2: =IF(Moteur!H2="","",Moteur!H2) -> 1000 | F2: =IF(Moteur!E2="","",Moteur!E2) -> 1000 | G2: =IF($A2="","",SUMIFS([1]Allocation22!$H$1:$H$175,[1]Allocation22!$C$1:$C$175,$A2,[1]Allocation22!$D$1:$D$175,$C2,[1]Allocation22!$E$1:$E$175,$D2,[1]Allocation22!$F$1:$F$175,$E2,[1]Allocation22!$G$1:$G$175,"2026")) -> #VALUE! | H2: =IF($A2="","",SUMIFS(Allocation2!$N$1:$N$175,Allocation2!$C$1:$C$175,$A2,Allocation2!$D$1:$D$175,$C2,Allocation2!$E$1:$E$175,$D2,Allocation2!$F$1:$F$175,$E2,Allocation2!$G$1:$G$175,"2026")) -> 0 | I2: =IF($A2="","",SUMIFS(Allocation2!$P$1:$P$175,Allocation2!$C$1:$C$175,$A2,Allocation2!$D$1:$D$175,$C2,Allocation2!$E$1:$E$175,$D2,Allocation2!$F$1:$F$175,$E2,Allocation2!$G$1:$G$175,"2026")) -> 0 | J2: =IF($A2="","",SUMIFS(Allocation2!$W$1:$W$175,Allocation2!$C$1:$C$175,$A2,Allocation2!$D$1:$D$175,$C2,Allocation2!$E$1:$E$175,$D2,Allocation2!$F$1:$F$175,$E2,Allocation2!$G$1:$G$175,"2026")) -> 0 | K2: =IF($A2="","",SUMIFS(Allocation2!$X$1:$X$175,Allocation2!$C$1:$C$175,$A2,Allocation2!$D$1:$D$175,$C2,Allocation2!$E$1:$E$175,$D2,Allocation2!$F$1:$F$175,$E2,Allocation2!$G$1:$G$175,"2026")) -> 0 | L2: =IF($A2="","",SUMIFS(Allocation2!$Y$1:$Y$175,Allocation2!$C$1:$C$175,$A2,Allocation2!$D$1:$D$175,$C2,Allocation2!$E$1:$E$175,$D2,Allocation2!$F$1:$F$175,$E2,Allocation2!$G$1:$G$175,"2026")) -> 0 | M2: =IF($A2="","",SUMIFS(Allocation2!$V$1:$V$175,Allocation2!$C$1:$C$175,$A2,Allocation2!$D$1:$D$175,$C2,Allocation2!$E$1:$E$175,$D2,Allocation2!$F$1:$F$175,$E2,Allocation2!$G$1:$G$175,"2026")) -> 0 | N2: =IF($A2="","",IF(OR($D2="B1",$D2="M1",$D2="BTS1"),1,0)) -> 0 | O2: =IF($A2="","",SUMIFS(Campagne!$D$1:$D$15,Campagne!$C$1:$C$15,$A2)) -> 1000 | P2: =IF($A2="","",SUMIFS(Campagne!$E$1:$E$15,Campagne!$C$1:$C$15,$A2)) -> 1000 | Q2: =IF($A2="","",SUMIFS(Campagne!$F$1:$F$15,Campagne!$C$1:$C$15,$A2)) -> 1000 | R2: =IF($A2="","",SUMIFS(Campagne!$K$1:$K$15,Campagne!$C$1:$C$15,$A2)) -> 1000 | S2: =IF($A2="","",SUMIFS(Campagne!$M$1:$M$15,Campagne!$C$1:$C$15,$A2)) -> 1000 | T2: =IF($A2="","",SUMIFS(PIL!$K$15:$K$28,PIL!$A$15:$A$28,$A2)*SUMIFS(PIL!$J$15:$J$28,PIL!$A$15:$A$28,$A2)*(SUM(PIL!$K$15:$K$28)/SUMPRODUCT(PIL!$K$15:$K$28,PIL!$J$15:$J$28))) -> 0 | U2: =IF($A2="","",SUMIFS(PIL!$K$15:$K$28,PIL!$A$15:$A$28,$A2)) -> 0 | V2: =IF($A2="","",IF($B2="V01",cad!$C$23,IF($B2="V02",cad!$D$23,cad!$E$23))) -> -0.05 | W2: =IF($A2="","",IF($B2="V01",cad!$C$24,IF($B2="V02",cad!$D$24,cad!$E$24))) -> -0.05 | X2: =IF($A2="","",IF($B2="V01",cad!$C$25,IF($B2="V02",cad!$D$25,cad!$E$25))) -> 0.02 | Y2: =IF($A2="","",IF($B2="V01",cad!$C$26,IF($B2="V02",cad!$D$26,cad!$E$26))) -> 0 | Z2: =IF($A2="","",IF($B2="V01",cad!$C$27,IF($B2="V02",cad!$D$27,cad!$E$27))) -> 0 | AA2: =IF($A2="","",IF($B2="V01",cad!$C$28,IF($B2="V02",cad!$D$28,cad!$E$28))) -> -0.01 | AB2: =IF($A2="","",IF($B2="V01",cad!$C$39,IF($B2="V02",cad!$D$39,cad!$E$39))) -> 90 | AC2: =IF($A2="","",IF($F2="MBWAY",cad!$J$12,IF($F2="ISCOM",cad!$J$13,IF($F2="IPAC",cad!$J$14,IF($F2="PIGIER",cad!$J$15,cad!$J$16))))) -> 1.05 | AD2: =IF($A2="","",($O2*(1+$W2)^$S2+$P2*IFERROR((($T2/$U2)*(1+$V2))^$R2,0))*IFERROR($G2/$Q2,0)*($J2+$Y2)*$K2*($L2+$Z2)) -> 0 | AE2: =IF($A2="","",IF($N2=1,$AD2,0)) -> 0 | AF2: =IF($A2="","",IF($N2=1,$AD2,$H2*($M2+$AA2))) -> 0 | AG2: =IF($A2="","",$I2*(1+$X2*$AC2)) -> 0 | AH2: =IF($A2="","",$AF2*$AG2+$AE2*$AB2) -> 0
A3: =IF(Moteur!D3="","",Moteur!D3) | B3: =IF(Moteur!B3="","",Moteur!B3) | C3: =IF(Moteur!F3="","",Moteur!F3) | D3: =IF(Moteur!G3="","",Moteur!G3) | E3: =IF(Moteur!H3="","",Moteur!H3) | F3: =IF(Moteur!E3="","",Moteur!E3) | G3: =IF($A3="","",SUMIFS(Allocation2!$H$1:$H$175,Allocation2!$C$1:$C$175,$A3,Allocation2!$D$1:$D$175,$C3,Allocation2!$E$1:$E$175,$D3,Allocation2!$F$1:$F$175,$E3,Allocation2!$G$1:$G$175,"2026")) | H3: =IF($A3="","",SUMIFS(Allocation2!$N$1:$N$175,Allocation2!$C$1:$C$175,$A3,Allocation2!$D$1:$D$175,$C3,Allocation2!$E$1:$E$175,$D3,Allocation2!$F$1:$F$175,$E3,Allocation2!$G$1:$G$175,"2026")) | I3: =IF($A3="","",SUMIFS(Allocation2!$P$1:$P$175,Allocation2!$C$1:$C$175,$A3,Allocation2!$D$1:$D$175,$C3,Allocation2!$E$1:$E$175,$D3,Allocation2!$F$1:$F$175,$E3,Allocation2!$G$1:$G$175,"2026")) | J3: =IF($A3="","",SUMIFS(Allocation2!$W$1:$W$175,Allocation2!$C$1:$C$175,$A3,Allocation2!$D$1:$D$175,$C3,Allocation2!$E$1:$E$175,$D3,Allocation2!$F$1:$F$175,$E3,Allocation2!$G$1:$G$175,"2026")) | K3: =IF($A3="","",SUMIFS(Allocation2!$X$1:$X$175,Allocation2!$C$1:$C$175,$A3,Allocation2!$D$1:$D$175,$C3,Allocation2!$E$1:$E$175,$D3,Allocation2!$F$1:$F$175,$E3,Allocation2!$G$1:$G$175,"2026")) | L3: =IF($A3="","",SUMIFS(Allocation2!$Y$1:$Y$175,Allocation2!$C$1:$C$175,$A3,Allocation2!$D$1:$D$175,$C3,Allocation2!$E$1:$E$175,$D3,Allocation2!$F$1:$F$175,$E3,Allocation2!$G$1:$G$175,"2026")) | M3: =IF($A3="","",SUMIFS(Allocation2!$V$1:$V$175,Allocation2!$C$1:$C$175,$A3,Allocation2!$D$1:$D$175,$C3,Allocation2!$E$1:$E$175,$D3,Allocation2!$F$1:$F$175,$E3,Allocation2!$G$1:$G$175,"2026")) | N3: =IF($A3="","",IF(OR($D3="B1",$D3="M1",$D3="BTS1"),1,0)) | O3: =IF($A3="","",SUMIFS(Campagne!$D$1:$D$15,Campagne!$C$1:$C$15,$A3)) | P3: =IF($A3="","",SUMIFS(Campagne!$E$1:$E$15,Campagne!$C$1:$C$15,$A3)) | Q3: =IF($A3="","",SUMIFS(Campagne!$F$1:$F$15,Campagne!$C$1:$C$15,$A3)) | R3: =IF($A3="","",SUMIFS(Campagne!$K$1:$K$15,Campagne!$C$1:$C$15,$A3)) | S3: =IF($A3="","",SUMIFS(Campagne!$M$1:$M$15,Campagne!$C$1:$C$15,$A3)) | T3: =IF($A3="","",SUMIFS(PIL!$K$15:$K$28,PIL!$A$15:$A$28,$A3)*SUMIFS(PIL!$J$15:$J$28,PIL!$A$15:$A$28,$A3)*(SUM(PIL!$K$15:$K$28)/SUMPRODUCT(PIL!$K$15:$K$28,PIL!$J$15:$J$28))) | U3: =IF($A3="","",SUMIFS(PIL!$K$15:$K$28,PIL!$A$15:$A$28,$A3)) | V3: =IF($A3="","",IF($B3="V01",cad!$C$23,IF($B3="V02",cad!$D$23,cad!$E$23))) | W3: =IF($A3="","",IF($B3="V01",cad!$C$24,IF($B3="V02",cad!$D$24,cad!$E$24))) | X3: =IF($A3="","",IF($B3="V01",cad!$C$25,IF($B3="V02",cad!$D$25,cad!$E$25))) | Y3: =IF($A3="","",IF($B3="V01",cad!$C$26,IF($B3="V02",cad!$D$26,cad!$E$26))) | Z3: =IF($A3="","",IF($B3="V01",cad!$C$27,IF($B3="V02",cad!$D$27,cad!$E$27))) | AA3: =IF($A3="","",IF($B3="V01",cad!$C$28,IF($B3="V02",cad!$D$28,cad!$E$28))) | AB3: =IF($A3="","",IF($B3="V01",cad!$C$39,IF($B3="V02",cad!$D$39,cad!$E$39))) | AC3: =IF($A3="","",IF($F3="MBWAY",cad!$J$12,IF($F3="ISCOM",cad!$J$13,IF($F3="IPAC",cad!$J$14,IF($F3="PIGIER",cad!$J$15,cad!$J$16))))) | AD3: =IF($A3="","",($O3*(1+$W3)^$S3+$P3*IFERROR((($T3/$U3)*(1+$V3))^$R3,0))*IFERROR($G3/$Q3,0)*($J3+$Y3)*$K3*($L3+$Z3)) | AE3: =IF($A3="","",IF($N3=1,$AD3,0)) | AF3: =IF($A3="","",IF($N3=1,$AD3,$H3*($M3+$AA3))) | AG3: =IF($A3="","",$I3*(1+$X3*$AC3)) | AH3: =IF($A3="","",$AF3*$AG3+$AE3*$AB3)
A4: =IF(Moteur!D4="","",Moteur!D4) | B4: =IF(Moteur!B4="","",Moteur!B4) | C4: =IF(Moteur!F4="","",Moteur!F4) | D4: =IF(Moteur!G4="","",Moteur!G4) | E4: =IF(Moteur!H4="","",Moteur!H4) | F4: =IF(Moteur!E4="","",Moteur!E4) | G4: =IF($A4="","",SUMIFS(Allocation2!$H$1:$H$175,Allocation2!$C$1:$C$175,$A4,Allocation2!$D$1:$D$175,$C4,Allocation2!$E$1:$E$175,$D4,Allocation2!$F$1:$F$175,$E4,Allocation2!$G$1:$G$175,"2026")) | H4: =IF($A4="","",SUMIFS(Allocation2!$N$1:$N$175,Allocation2!$C$1:$C$175,$A4,Allocation2!$D$1:$D$175,$C4,Allocation2!$E$1:$E$175,$D4,Allocation2!$F$1:$F$175,$E4,Allocation2!$G$1:$G$175,"2026")) | I4: =IF($A4="","",SUMIFS(Allocation2!$P$1:$P$175,Allocation2!$C$1:$C$175,$A4,Allocation2!$D$1:$D$175,$C4,Allocation2!$E$1:$E$175,$D4,Allocation2!$F$1:$F$175,$E4,Allocation2!$G$1:$G$175,"2026")) | J4: =IF($A4="","",SUMIFS(Allocation2!$W$1:$W$175,Allocation2!$C$1:$C$175,$A4,Allocation2!$D$1:$D$175,$C4,Allocation2!$E$1:$E$175,$D4,Allocation2!$F$1:$F$175,$E4,Allocation2!$G$1:$G$175,"2026")) | K4: =IF($A4="","",SUMIFS(Allocation2!$X$1:$X$175,Allocation2!$C$1:$C$175,$A4,Allocation2!$D$1:$D$175,$C4,Allocation2!$E$1:$E$175,$D4,Allocation2!$F$1:$F$175,$E4,Allocation2!$G$1:$G$175,"2026")) | L4: =IF($A4="","",SUMIFS(Allocation2!$Y$1:$Y$175,Allocation2!$C$1:$C$175,$A4,Allocation2!$D$1:$D$175,$C4,Allocation2!$E$1:$E$175,$D4,Allocation2!$F$1:$F$175,$E4,Allocation2!$G$1:$G$175,"2026")) | M4: =IF($A4="","",SUMIFS(Allocation2!$V$1:$V$175,Allocation2!$C$1:$C$175,$A4,Allocation2!$D$1:$D$175,$C4,Allocation2!$E$1:$E$175,$D4,Allocation2!$F$1:$F$175,$E4,Allocation2!$G$1:$G$175,"2026")) | N4: =IF($A4="","",IF(OR($D4="B1",$D4="M1",$D4="BTS1"),1,0)) | O4: =IF($A4="","",SUMIFS(Campagne!$D$1:$D$15,Campagne!$C$1:$C$15,$A4)) | P4: =IF($A4="","",SUMIFS(Campagne!$E$1:$E$15,Campagne!$C$1:$C$15,$A4)) | Q4: =IF($A4="","",SUMIFS(Campagne!$F$1:$F$15,Campagne!$C$1:$C$15,$A4)) | R4: =IF($A4="","",SUMIFS(Campagne!$K$1:$K$15,Campagne!$C$1:$C$15,$A4)) | S4: =IF($A4="","",SUMIFS(Campagne!$M$1:$M$15,Campagne!$C$1:$C$15,$A4)) | T4: =IF($A4="","",SUMIFS(PIL!$K$15:$K$28,PIL!$A$15:$A$28,$A4)*SUMIFS(PIL!$J$15:$J$28,PIL!$A$15:$A$28,$A4)*(SUM(PIL!$K$15:$K$28)/SUMPRODUCT(PIL!$K$15:$K$28,PIL!$J$15:$J$28))) | U4: =IF($A4="","",SUMIFS(PIL!$K$15:$K$28,PIL!$A$15:$A$28,$A4)) | V4: =IF($A4="","",IF($B4="V01",cad!$C$23,IF($B4="V02",cad!$D$23,cad!$E$23))) | W4: =IF($A4="","",IF($B4="V01",cad!$C$24,IF($B4="V02",cad!$D$24,cad!$E$24))) | X4: =IF($A4="","",IF($B4="V01",cad!$C$25,IF($B4="V02",cad!$D$25,cad!$E$25))) | Y4: =IF($A4="","",IF($B4="V01",cad!$C$26,IF($B4="V02",cad!$D$26,cad!$E$26))) | Z4: =IF($A4="","",IF($B4="V01",cad!$C$27,IF($B4="V02",cad!$D$27,cad!$E$27))) | AA4: =IF($A4="","",IF($B4="V01",cad!$C$28,IF($B4="V02",cad!$D$28,cad!$E$28))) | AB4: =IF($A4="","",IF($B4="V01",cad!$C$39,IF($B4="V02",cad!$D$39,cad!$E$39))) | AC4: =IF($A4="","",IF($F4="MBWAY",cad!$J$12,IF($F4="ISCOM",cad!$J$13,IF($F4="IPAC",cad!$J$14,IF($F4="PIGIER",cad!$J$15,cad!$J$16))))) | AD4: =IF($A4="","",($O4*(1+$W4)^$S4+$P4*IFERROR((($T4/$U4)*(1+$V4))^$R4,0))*IFERROR($G4/$Q4,0)*($J4+$Y4)*$K4*($L4+$Z4)) | AE4: =IF($A4="","",IF($N4=1,$AD4,0)) | AF4: =IF($A4="","",IF($N4=1,$AD4,$H4*($M4+$AA4))) | AG4: =IF($A4="","",$I4*(1+$X4*$AC4)) | AH4: =IF($A4="","",$AF4*$AG4+$AE4*$AB4)
A5: =IF(Moteur!D5="","",Moteur!D5) | B5: =IF(Moteur!B5="","",Moteur!B5) | C5: =IF(Moteur!F5="","",Moteur!F5) | D5: =IF(Moteur!G5="","",Moteur!G5) | E5: =IF(Moteur!H5="","",Moteur!H5) | F5: =IF(Moteur!E5="","",Moteur!E5) | G5: =IF($A5="","",SUMIFS(Allocation2!$H$1:$H$175,Allocation2!$C$1:$C$175,$A5,Allocation2!$D$1:$D$175,$C5,Allocation2!$E$1:$E$175,$D5,Allocation2!$F$1:$F$175,$E5,Allocation2!$G$1:$G$175,"2026")) | H5: =IF($A5="","",SUMIFS(Allocation2!$N$1:$N$175,Allocation2!$C$1:$C$175,$A5,Allocation2!$D$1:$D$175,$C5,Allocation2!$E$1:$E$175,$D5,Allocation2!$F$1:$F$175,$E5,Allocation2!$G$1:$G$175,"2026")) | I5: =IF($A5="","",SUMIFS(Allocation2!$P$1:$P$175,Allocation2!$C$1:$C$175,$A5,Allocation2!$D$1:$D$175,$C5,Allocation2!$E$1:$E$175,$D5,Allocation2!$F$1:$F$175,$E5,Allocation2!$G$1:$G$175,"2026")) | J5: =IF($A5="","",SUMIFS(Allocation2!$W$1:$W$175,Allocation2!$C$1:$C$175,$A5,Allocation2!$D$1:$D$175,$C5,Allocation2!$E$1:$E$175,$D5,Allocation2!$F$1:$F$175,$E5,Allocation2!$G$1:$G$175,"2026")) | K5: =IF($A5="","",SUMIFS(Allocation2!$X$1:$X$175,Allocation2!$C$1:$C$175,$A5,Allocation2!$D$1:$D$175,$C5,Allocation2!$E$1:$E$175,$D5,Allocation2!$F$1:$F$175,$E5,Allocation2!$G$1:$G$175,"2026")) | L5: =IF($A5="","",SUMIFS(Allocation2!$Y$1:$Y$175,Allocation2!$C$1:$C$175,$A5,Allocation2!$D$1:$D$175,$C5,Allocation2!$E$1:$E$175,$D5,Allocation2!$F$1:$F$175,$E5,Allocation2!$G$1:$G$175,"2026")) | M5: =IF($A5="","",SUMIFS(Allocation2!$V$1:$V$175,Allocation2!$C$1:$C$175,$A5,Allocation2!$D$1:$D$175,$C5,Allocation2!$E$1:$E$175,$D5,Allocation2!$F$1:$F$175,$E5,Allocation2!$G$1:$G$175,"2026")) | N5: =IF($A5="","",IF(OR($D5="B1",$D5="M1",$D5="BTS1"),1,0)) | O5: =IF($A5="","",SUMIFS(Campagne!$D$1:$D$15,Campagne!$C$1:$C$15,$A5)) | P5: =IF($A5="","",SUMIFS(Campagne!$E$1:$E$15,Campagne!$C$1:$C$15,$A5)) | Q5: =IF($A5="","",SUMIFS(Campagne!$F$1:$F$15,Campagne!$C$1:$C$15,$A5)) | R5: =IF($A5="","",SUMIFS(Campagne!$K$1:$K$15,Campagne!$C$1:$C$15,$A5)) | S5: =IF($A5="","",SUMIFS(Campagne!$M$1:$M$15,Campagne!$C$1:$C$15,$A5)) | T5: =IF($A5="","",SUMIFS(PIL!$K$15:$K$28,PIL!$A$15:$A$28,$A5)*SUMIFS(PIL!$J$15:$J$28,PIL!$A$15:$A$28,$A5)*(SUM(PIL!$K$15:$K$28)/SUMPRODUCT(PIL!$K$15:$K$28,PIL!$J$15:$J$28))) | U5: =IF($A5="","",SUMIFS(PIL!$K$15:$K$28,PIL!$A$15:$A$28,$A5)) | V5: =IF($A5="","",IF($B5="V01",cad!$C$23,IF($B5="V02",cad!$D$23,cad!$E$23))) | W5: =IF($A5="","",IF($B5="V01",cad!$C$24,IF($B5="V02",cad!$D$24,cad!$E$24))) | X5: =IF($A5="","",IF($B5="V01",cad!$C$25,IF($B5="V02",cad!$D$25,cad!$E$25))) | Y5: =IF($A5="","",IF($B5="V01",cad!$C$26,IF($B5="V02",cad!$D$26,cad!$E$26))) | Z5: =IF($A5="","",IF($B5="V01",cad!$C$27,IF($B5="V02",cad!$D$27,cad!$E$27))) | AA5: =IF($A5="","",IF($B5="V01",cad!$C$28,IF($B5="V02",cad!$D$28,cad!$E$28))) | AB5: =IF($A5="","",IF($B5="V01",cad!$C$39,IF($B5="V02",cad!$D$39,cad!$E$39))) | AC5: =IF($A5="","",IF($F5="MBWAY",cad!$J$12,IF($F5="ISCOM",cad!$J$13,IF($F5="IPAC",cad!$J$14,IF($F5="PIGIER",cad!$J$15,cad!$J$16))))) | AD5: =IF($A5="","",($O5*(1+$W5)^$S5+$P5*IFERROR((($T5/$U5)*(1+$V5))^$R5,0))*IFERROR($G5/$Q5,0)*($J5+$Y5)*$K5*($L5+$Z5)) | AE5: =IF($A5="","",IF($N5=1,$AD5,0)) | AF5: =IF($A5="","",IF($N5=1,$AD5,$H5*($M5+$AA5))) | AG5: =IF($A5="","",$I5*(1+$X5*$AC5)) | AH5: =IF($A5="","",$AF5*$AG5+$AE5*$AB5)
A6: =IF(Moteur!D6="","",Moteur!D6) | B6: =IF(Moteur!B6="","",Moteur!B6) | C6: =IF(Moteur!F6="","",Moteur!F6) | D6: =IF(Moteur!G6="","",Moteur!G6) | E6: =IF(Moteur!H6="","",Moteur!H6) | F6: =IF(Moteur!E6="","",Moteur!E6) | G6: =IF($A6="","",SUMIFS(Allocation2!$H$1:$H$175,Allocation2!$C$1:$C$175,$A6,Allocation2!$D$1:$D$175,$C6,Allocation2!$E$1:$E$175,$D6,Allocation2!$F$1:$F$175,$E6,Allocation2!$G$1:$G$175,"2026")) | H6: =IF($A6="","",SUMIFS(Allocation2!$N$1:$N$175,Allocation2!$C$1:$C$175,$A6,Allocation2!$D$1:$D$175,$C6,Allocation2!$E$1:$E$175,$D6,Allocation2!$F$1:$F$175,$E6,Allocation2!$G$1:$G$175,"2026")) | I6: =IF($A6="","",SUMIFS(Allocation2!$P$1:$P$175,Allocation2!$C$1:$C$175,$A6,Allocation2!$D$1:$D$175,$C6,Allocation2!$E$1:$E$175,$D6,Allocation2!$F$1:$F$175,$E6,Allocation2!$G$1:$G$175,"2026")) | J6: =IF($A6="","",SUMIFS(Allocation2!$W$1:$W$175,Allocation2!$C$1:$C$175,$A6,Allocation2!$D$1:$D$175,$C6,Allocation2!$E$1:$E$175,$D6,Allocation2!$F$1:$F$175,$E6,Allocation2!$G$1:$G$175,"2026")) | K6: =IF($A6="","",SUMIFS(Allocation2!$X$1:$X$175,Allocation2!$C$1:$C$175,$A6,Allocation2!$D$1:$D$175,$C6,Allocation2!$E$1:$E$175,$D6,Allocation2!$F$1:$F$175,$E6,Allocation2!$G$1:$G$175,"2026")) | L6: =IF($A6="","",SUMIFS(Allocation2!$Y$1:$Y$175,Allocation2!$C$1:$C$175,$A6,Allocation2!$D$1:$D$175,$C6,Allocation2!$E$1:$E$175,$D6,Allocation2!$F$1:$F$175,$E6,Allocation2!$G$1:$G$175,"2026")) | M6: =IF($A6="","",SUMIFS(Allocation2!$V$1:$V$175,Allocation2!$C$1:$C$175,$A6,Allocation2!$D$1:$D$175,$C6,Allocation2!$E$1:$E$175,$D6,Allocation2!$F$1:$F$175,$E6,Allocation2!$G$1:$G$175,"2026")) | N6: =IF($A6="","",IF(OR($D6="B1",$D6="M1",$D6="BTS1"),1,0)) | O6: =IF($A6="","",SUMIFS(Campagne!$D$1:$D$15,Campagne!$C$1:$C$15,$A6)) | P6: =IF($A6="","",SUMIFS(Campagne!$E$1:$E$15,Campagne!$C$1:$C$15,$A6)) | Q6: =IF($A6="","",SUMIFS(Campagne!$F$1:$F$15,Campagne!$C$1:$C$15,$A6)) | R6: =IF($A6="","",SUMIFS(Campagne!$K$1:$K$15,Campagne!$C$1:$C$15,$A6)) | S6: =IF($A6="","",SUMIFS(Campagne!$M$1:$M$15,Campagne!$C$1:$C$15,$A6)) | T6: =IF($A6="","",SUMIFS(PIL!$K$15:$K$28,PIL!$A$15:$A$28,$A6)*SUMIFS(PIL!$J$15:$J$28,PIL!$A$15:$A$28,$A6)*(SUM(PIL!$K$15:$K$28)/SUMPRODUCT(PIL!$K$15:$K$28,PIL!$J$15:$J$28))) | U6: =IF($A6="","",SUMIFS(PIL!$K$15:$K$28,PIL!$A$15:$A$28,$A6)) | V6: =IF($A6="","",IF($B6="V01",cad!$C$23,IF($B6="V02",cad!$D$23,cad!$E$23))) | W6: =IF($A6="","",IF($B6="V01",cad!$C$24,IF($B6="V02",cad!$D$24,cad!$E$24))) | X6: =IF($A6="","",IF($B6="V01",cad!$C$25,IF($B6="V02",cad!$D$25,cad!$E$25))) | Y6: =IF($A6="","",IF($B6="V01",cad!$C$26,IF($B6="V02",cad!$D$26,cad!$E$26))) | Z6: =IF($A6="","",IF($B6="V01",cad!$C$27,IF($B6="V02",cad!$D$27,cad!$E$27))) | AA6: =IF($A6="","",IF($B6="V01",cad!$C$28,IF($B6="V02",cad!$D$28,cad!$E$28))) | AB6: =IF($A6="","",IF($B6="V01",cad!$C$39,IF($B6="V02",cad!$D$39,cad!$E$39))) | AC6: =IF($A6="","",IF($F6="MBWAY",cad!$J$12,IF($F6="ISCOM",cad!$J$13,IF($F6="IPAC",cad!$J$14,IF($F6="PIGIER",cad!$J$15,cad!$J$16))))) | AD6: =IF($A6="","",($O6*(1+$W6)^$S6+$P6*IFERROR((($T6/$U6)*(1+$V6))^$R6,0))*IFERROR($G6/$Q6,0)*($J6+$Y6)*$K6*($L6+$Z6)) | AE6: =IF($A6="","",IF($N6=1,$AD6,0)) | AF6: =IF($A6="","",IF($N6=1,$AD6,$H6*($M6+$AA6))) | AG6: =IF($A6="","",$I6*(1+$X6*$AC6)) | AH6: =IF($A6="","",$AF6*$AG6+$AE6*$AB6)
A7: =IF(Moteur!D7="","",Moteur!D7) | B7: =IF(Moteur!B7="","",Moteur!B7) | C7: =IF(Moteur!F7="","",Moteur!F7) | D7: =IF(Moteur!G7="","",Moteur!G7) | E7: =IF(Moteur!H7="","",Moteur!H7) | F7: =IF(Moteur!E7="","",Moteur!E7) | G7: =IF($A7="","",SUMIFS(Allocation2!$H$1:$H$175,Allocation2!$C$1:$C$175,$A7,Allocation2!$D$1:$D$175,$C7,Allocation2!$E$1:$E$175,$D7,Allocation2!$F$1:$F$175,$E7,Allocation2!$G$1:$G$175,"2026")) | H7: =IF($A7="","",SUMIFS(Allocation2!$N$1:$N$175,Allocation2!$C$1:$C$175,$A7,Allocation2!$D$1:$D$175,$C7,Allocation2!$E$1:$E$175,$D7,Allocation2!$F$1:$F$175,$E7,Allocation2!$G$1:$G$175,"2026")) | I7: =IF($A7="","",SUMIFS(Allocation2!$P$1:$P$175,Allocation2!$C$1:$C$175,$A7,Allocation2!$D$1:$D$175,$C7,Allocation2!$E$1:$E$175,$D7,Allocation2!$F$1:$F$175,$E7,Allocation2!$G$1:$G$175,"2026")) | J7: =IF($A7="","",SUMIFS(Allocation2!$W$1:$W$175,Allocation2!$C$1:$C$175,$A7,Allocation2!$D$1:$D$175,$C7,Allocation2!$E$1:$E$175,$D7,Allocation2!$F$1:$F$175,$E7,Allocation2!$G$1:$G$175,"2026")) | K7: =IF($A7="","",SUMIFS(Allocation2!$X$1:$X$175,Allocation2!$C$1:$C$175,$A7,Allocation2!$D$1:$D$175,$C7,Allocation2!$E$1:$E$175,$D7,Allocation2!$F$1:$F$175,$E7,Allocation2!$G$1:$G$175,"2026")) | L7: =IF($A7="","",SUMIFS(Allocation2!$Y$1:$Y$175,Allocation2!$C$1:$C$175,$A7,Allocation2!$D$1:$D$175,$C7,Allocation2!$E$1:$E$175,$D7,Allocation2!$F$1:$F$175,$E7,Allocation2!$G$1:$G$175,"2026")) | M7: =IF($A7="","",SUMIFS(Allocation2!$V$1:$V$175,Allocation2!$C$1:$C$175,$A7,Allocation2!$D$1:$D$175,$C7,Allocation2!$E$1:$E$175,$D7,Allocation2!$F$1:$F$175,$E7,Allocation2!$G$1:$G$175,"2026")) | N7: =IF($A7="","",IF(OR($D7="B1",$D7="M1",$D7="BTS1"),1,0)) | O7: =IF($A7="","",SUMIFS(Campagne!$D$1:$D$15,Campagne!$C$1:$C$15,$A7)) | P7: =IF($A7="","",SUMIFS(Campagne!$E$1:$E$15,Campagne!$C$1:$C$15,$A7)) | Q7: =IF($A7="","",SUMIFS(Campagne!$F$1:$F$15,Campagne!$C$1:$C$15,$A7)) | R7: =IF($A7="","",SUMIFS(Campagne!$K$1:$K$15,Campagne!$C$1:$C$15,$A7)) | S7: =IF($A7="","",SUMIFS(Campagne!$M$1:$M$15,Campagne!$C$1:$C$15,$A7)) | T7: =IF($A7="","",SUMIFS(PIL!$K$15:$K$28,PIL!$A$15:$A$28,$A7)*SUMIFS(PIL!$J$15:$J$28,PIL!$A$15:$A$28,$A7)*(SUM(PIL!$K$15:$K$28)/SUMPRODUCT(PIL!$K$15:$K$28,PIL!$J$15:$J$28))) | U7: =IF($A7="","",SUMIFS(PIL!$K$15:$K$28,PIL!$A$15:$A$28,$A7)) | V7: =IF($A7="","",IF($B7="V01",cad!$C$23,IF($B7="V02",cad!$D$23,cad!$E$23))) | W7: =IF($A7="","",IF($B7="V01",cad!$C$24,IF($B7="V02",cad!$D$24,cad!$E$24))) | X7: =IF($A7="","",IF($B7="V01",cad!$C$25,IF($B7="V02",cad!$D$25,cad!$E$25))) | Y7: =IF($A7="","",IF($B7="V01",cad!$C$26,IF($B7="V02",cad!$D$26,cad!$E$26))) | Z7: =IF($A7="","",IF($B7="V01",cad!$C$27,IF($B7="V02",cad!$D$27,cad!$E$27))) | AA7: =IF($A7="","",IF($B7="V01",cad!$C$28,IF($B7="V02",cad!$D$28,cad!$E$28))) | AB7: =IF($A7="","",IF($B7="V01",cad!$C$39,IF($B7="V02",cad!$D$39,cad!$E$39))) | AC7: =IF($A7="","",IF($F7="MBWAY",cad!$J$12,IF($F7="ISCOM",cad!$J$13,IF($F7="IPAC",cad!$J$14,IF($F7="PIGIER",cad!$J$15,cad!$J$16))))) | AD7: =IF($A7="","",($O7*(1+$W7)^$S7+$P7*IFERROR((($T7/$U7)*(1+$V7))^$R7,0))*IFERROR($G7/$Q7,0)*($J7+$Y7)*$K7*($L7+$Z7)) | AE7: =IF($A7="","",IF($N7=1,$AD7,0)) | AF7: =IF($A7="","",IF($N7=1,$AD7,$H7*($M7+$AA7))) | AG7: =IF($A7="","",$I7*(1+$X7*$AC7)) | AH7: =IF($A7="","",$AF7*$AG7+$AE7*$AB7)
A8: =IF(Moteur!D8="","",Moteur!D8) | B8: =IF(Moteur!B8="","",Moteur!B8) | C8: =IF(Moteur!F8="","",Moteur!F8) | D8: =IF(Moteur!G8="","",Moteur!G8) | E8: =IF(Moteur!H8="","",Moteur!H8) | F8: =IF(Moteur!E8="","",Moteur!E8) | G8: =IF($A8="","",SUMIFS(Allocation2!$H$1:$H$175,Allocation2!$C$1:$C$175,$A8,Allocation2!$D$1:$D$175,$C8,Allocation2!$E$1:$E$175,$D8,Allocation2!$F$1:$F$175,$E8,Allocation2!$G$1:$G$175,"2026")) | H8: =IF($A8="","",SUMIFS(Allocation2!$N$1:$N$175,Allocation2!$C$1:$C$175,$A8,Allocation2!$D$1:$D$175,$C8,Allocation2!$E$1:$E$175,$D8,Allocation2!$F$1:$F$175,$E8,Allocation2!$G$1:$G$175,"2026")) | I8: =IF($A8="","",SUMIFS(Allocation2!$P$1:$P$175,Allocation2!$C$1:$C$175,$A8,Allocation2!$D$1:$D$175,$C8,Allocation2!$E$1:$E$175,$D8,Allocation2!$F$1:$F$175,$E8,Allocation2!$G$1:$G$175,"2026")) | J8: =IF($A8="","",SUMIFS(Allocation2!$W$1:$W$175,Allocation2!$C$1:$C$175,$A8,Allocation2!$D$1:$D$175,$C8,Allocation2!$E$1:$E$175,$D8,Allocation2!$F$1:$F$175,$E8,Allocation2!$G$1:$G$175,"2026")) | K8: =IF($A8="","",SUMIFS(Allocation2!$X$1:$X$175,Allocation2!$C$1:$C$175,$A8,Allocation2!$D$1:$D$175,$C8,Allocation2!$E$1:$E$175,$D8,Allocation2!$F$1:$F$175,$E8,Allocation2!$G$1:$G$175,"2026")) | L8: =IF($A8="","",SUMIFS(Allocation2!$Y$1:$Y$175,Allocation2!$C$1:$C$175,$A8,Allocation2!$D$1:$D$175,$C8,Allocation2!$E$1:$E$175,$D8,Allocation2!$F$1:$F$175,$E8,Allocation2!$G$1:$G$175,"2026")) | M8: =IF($A8="","",SUMIFS(Allocation2!$V$1:$V$175,Allocation2!$C$1:$C$175,$A8,Allocation2!$D$1:$D$175,$C8,Allocation2!$E$1:$E$175,$D8,Allocation2!$F$1:$F$175,$E8,Allocation2!$G$1:$G$175,"2026")) | N8: =IF($A8="","",IF(OR($D8="B1",$D8="M1",$D8="BTS1"),1,0)) | O8: =IF($A8="","",SUMIFS(Campagne!$D$1:$D$15,Campagne!$C$1:$C$15,$A8)) | P8: =IF($A8="","",SUMIFS(Campagne!$E$1:$E$15,Campagne!$C$1:$C$15,$A8)) | Q8: =IF($A8="","",SUMIFS(Campagne!$F$1:$F$15,Campagne!$C$1:$C$15,$A8)) | R8: =IF($A8="","",SUMIFS(Campagne!$K$1:$K$15,Campagne!$C$1:$C$15,$A8)) | S8: =IF($A8="","",SUMIFS(Campagne!$M$1:$M$15,Campagne!$C$1:$C$15,$A8)) | T8: =IF($A8="","",SUMIFS(PIL!$K$15:$K$28,PIL!$A$15:$A$28,$A8)*SUMIFS(PIL!$J$15:$J$28,PIL!$A$15:$A$28,$A8)*(SUM(PIL!$K$15:$K$28)/SUMPRODUCT(PIL!$K$15:$K$28,PIL!$J$15:$J$28))) | U8: =IF($A8="","",SUMIFS(PIL!$K$15:$K$28,PIL!$A$15:$A$28,$A8)) | V8: =IF($A8="","",IF($B8="V01",cad!$C$23,IF($B8="V02",cad!$D$23,cad!$E$23))) | W8: =IF($A8="","",IF($B8="V01",cad!$C$24,IF($B8="V02",cad!$D$24,cad!$E$24))) | X8: =IF($A8="","",IF($B8="V01",cad!$C$25,IF($B8="V02",cad!$D$25,cad!$E$25))) | Y8: =IF($A8="","",IF($B8="V01",cad!$C$26,IF($B8="V02",cad!$D$26,cad!$E$26))) | Z8: =IF($A8="","",IF($B8="V01",cad!$C$27,IF($B8="V02",cad!$D$27,cad!$E$27))) | AA8: =IF($A8="","",IF($B8="V01",cad!$C$28,IF($B8="V02",cad!$D$28,cad!$E$28))) | AB8: =IF($A8="","",IF($B8="V01",cad!$C$39,IF($B8="V02",cad!$D$39,cad!$E$39))) | AC8: =IF($A8="","",IF($F8="MBWAY",cad!$J$12,IF($F8="ISCOM",cad!$J$13,IF($F8="IPAC",cad!$J$14,IF($F8="PIGIER",cad!$J$15,cad!$J$16))))) | AD8: =IF($A8="","",($O8*(1+$W8)^$S8+$P8*IFERROR((($T8/$U8)*(1+$V8))^$R8,0))*IFERROR($G8/$Q8,0)*($J8+$Y8)*$K8*($L8+$Z8)) | AE8: =IF($A8="","",IF($N8=1,$AD8,0)) | AF8: =IF($A8="","",IF($N8=1,$AD8,$H8*($M8+$AA8))) | AG8: =IF($A8="","",$I8*(1+$X8*$AC8)) | AH8: =IF($A8="","",$AF8*$AG8+$AE8*$AB8)
A9: =IF(Moteur!D9="","",Moteur!D9) | B9: =IF(Moteur!B9="","",Moteur!B9) | C9: =IF(Moteur!F9="","",Moteur!F9) | D9: =IF(Moteur!G9="","",Moteur!G9) | E9: =IF(Moteur!H9="","",Moteur!H9) | F9: =IF(Moteur!E9="","",Moteur!E9) | G9: =IF($A9="","",SUMIFS(Allocation2!$H$1:$H$175,Allocation2!$C$1:$C$175,$A9,Allocation2!$D$1:$D$175,$C9,Allocation2!$E$1:$E$175,$D9,Allocation2!$F$1:$F$175,$E9,Allocation2!$G$1:$G$175,"2026")) | H9: =IF($A9="","",SUMIFS(Allocation2!$N$1:$N$175,Allocation2!$C$1:$C$175,$A9,Allocation2!$D$1:$D$175,$C9,Allocation2!$E$1:$E$175,$D9,Allocation2!$F$1:$F$175,$E9,Allocation2!$G$1:$G$175,"2026")) | I9: =IF($A9="","",SUMIFS(Allocation2!$P$1:$P$175,Allocation2!$C$1:$C$175,$A9,Allocation2!$D$1:$D$175,$C9,Allocation2!$E$1:$E$175,$D9,Allocation2!$F$1:$F$175,$E9,Allocation2!$G$1:$G$175,"2026")) | J9: =IF($A9="","",SUMIFS(Allocation2!$W$1:$W$175,Allocation2!$C$1:$C$175,$A9,Allocation2!$D$1:$D$175,$C9,Allocation2!$E$1:$E$175,$D9,Allocation2!$F$1:$F$175,$E9,Allocation2!$G$1:$G$175,"2026")) | K9: =IF($A9="","",SUMIFS(Allocation2!$X$1:$X$175,Allocation2!$C$1:$C$175,$A9,Allocation2!$D$1:$D$175,$C9,Allocation2!$E$1:$E$175,$D9,Allocation2!$F$1:$F$175,$E9,Allocation2!$G$1:$G$175,"2026")) | L9: =IF($A9="","",SUMIFS(Allocation2!$Y$1:$Y$175,Allocation2!$C$1:$C$175,$A9,Allocation2!$D$1:$D$175,$C9,Allocation2!$E$1:$E$175,$D9,Allocation2!$F$1:$F$175,$E9,Allocation2!$G$1:$G$175,"2026")) | M9: =IF($A9="","",SUMIFS(Allocation2!$V$1:$V$175,Allocation2!$C$1:$C$175,$A9,Allocation2!$D$1:$D$175,$C9,Allocation2!$E$1:$E$175,$D9,Allocation2!$F$1:$F$175,$E9,Allocation2!$G$1:$G$175,"2026")) | N9: =IF($A9="","",IF(OR($D9="B1",$D9="M1",$D9="BTS1"),1,0)) | O9: =IF($A9="","",SUMIFS(Campagne!$D$1:$D$15,Campagne!$C$1:$C$15,$A9)) | P9: =IF($A9="","",SUMIFS(Campagne!$E$1:$E$15,Campagne!$C$1:$C$15,$A9)) | Q9: =IF($A9="","",SUMIFS(Campagne!$F$1:$F$15,Campagne!$C$1:$C$15,$A9)) | R9: =IF($A9="","",SUMIFS(Campagne!$K$1:$K$15,Campagne!$C$1:$C$15,$A9)) | S9: =IF($A9="","",SUMIFS(Campagne!$M$1:$M$15,Campagne!$C$1:$C$15,$A9)) | T9: =IF($A9="","",SUMIFS(PIL!$K$15:$K$28,PIL!$A$15:$A$28,$A9)*SUMIFS(PIL!$J$15:$J$28,PIL!$A$15:$A$28,$A9)*(SUM(PIL!$K$15:$K$28)/SUMPRODUCT(PIL!$K$15:$K$28,PIL!$J$15:$J$28))) | U9: =IF($A9="","",SUMIFS(PIL!$K$15:$K$28,PIL!$A$15:$A$28,$A9)) | V9: =IF($A9="","",IF($B9="V01",cad!$C$23,IF($B9="V02",cad!$D$23,cad!$E$23))) | W9: =IF($A9="","",IF($B9="V01",cad!$C$24,IF($B9="V02",cad!$D$24,cad!$E$24))) | X9: =IF($A9="","",IF($B9="V01",cad!$C$25,IF($B9="V02",cad!$D$25,cad!$E$25))) | Y9: =IF($A9="","",IF($B9="V01",cad!$C$26,IF($B9="V02",cad!$D$26,cad!$E$26))) | Z9: =IF($A9="","",IF($B9="V01",cad!$C$27,IF($B9="V02",cad!$D$27,cad!$E$27))) | AA9: =IF($A9="","",IF($B9="V01",cad!$C$28,IF($B9="V02",cad!$D$28,cad!$E$28))) | AB9: =IF($A9="","",IF($B9="V01",cad!$C$39,IF($B9="V02",cad!$D$39,cad!$E$39))) | AC9: =IF($A9="","",IF($F9="MBWAY",cad!$J$12,IF($F9="ISCOM",cad!$J$13,IF($F9="IPAC",cad!$J$14,IF($F9="PIGIER",cad!$J$15,cad!$J$16))))) | AD9: =IF($A9="","",($O9*(1+$W9)^$S9+$P9*IFERROR((($T9/$U9)*(1+$V9))^$R9,0))*IFERROR($G9/$Q9,0)*($J9+$Y9)*$K9*($L9+$Z9)) | AE9: =IF($A9="","",IF($N9=1,$AD9,0)) | AF9: =IF($A9="","",IF($N9=1,$AD9,$H9*($M9+$AA9))) | AG9: =IF($A9="","",$I9*(1+$X9*$AC9)) | AH9: =IF($A9="","",$AF9*$AG9+$AE9*$AB9)
A10: =IF(Moteur!D10="","",Moteur!D10) | B10: =IF(Moteur!B10="","",Moteur!B10) | C10: =IF(Moteur!F10="","",Moteur!F10) | D10: =IF(Moteur!G10="","",Moteur!G10) | E10: =IF(Moteur!H10="","",Moteur!H10) | F10: =IF(Moteur!E10="","",Moteur!E10) | G10: =IF($A10="","",SUMIFS(Allocation2!$H$1:$H$175,Allocation2!$C$1:$C$175,$A10,Allocation2!$D$1:$D$175,$C10,Allocation2!$E$1:$E$175,$D10,Allocation2!$F$1:$F$175,$E10,Allocation2!$G$1:$G$175,"2026")) | H10: =IF($A10="","",SUMIFS(Allocation2!$N$1:$N$175,Allocation2!$C$1:$C$175,$A10,Allocation2!$D$1:$D$175,$C10,Allocation2!$E$1:$E$175,$D10,Allocation2!$F$1:$F$175,$E10,Allocation2!$G$1:$G$175,"2026")) | I10: =IF($A10="","",SUMIFS(Allocation2!$P$1:$P$175,Allocation2!$C$1:$C$175,$A10,Allocation2!$D$1:$D$175,$C10,Allocation2!$E$1:$E$175,$D10,Allocation2!$F$1:$F$175,$E10,Allocation2!$G$1:$G$175,"2026")) | J10: =IF($A10="","",SUMIFS(Allocation2!$W$1:$W$175,Allocation2!$C$1:$C$175,$A10,Allocation2!$D$1:$D$175,$C10,Allocation2!$E$1:$E$175,$D10,Allocation2!$F$1:$F$175,$E10,Allocation2!$G$1:$G$175,"2026")) | K10: =IF($A10="","",SUMIFS(Allocation2!$X$1:$X$175,Allocation2!$C$1:$C$175,$A10,Allocation2!$D$1:$D$175,$C10,Allocation2!$E$1:$E$175,$D10,Allocation2!$F$1:$F$175,$E10,Allocation2!$G$1:$G$175,"2026")) | L10: =IF($A10="","",SUMIFS(Allocation2!$Y$1:$Y$175,Allocation2!$C$1:$C$175,$A10,Allocation2!$D$1:$D$175,$C10,Allocation2!$E$1:$E$175,$D10,Allocation2!$F$1:$F$175,$E10,Allocation2!$G$1:$G$175,"2026")) | M10: =IF($A10="","",SUMIFS(Allocation2!$V$1:$V$175,Allocation2!$C$1:$C$175,$A10,Allocation2!$D$1:$D$175,$C10,Allocation2!$E$1:$E$175,$D10,Allocation2!$F$1:$F$175,$E10,Allocation2!$G$1:$G$175,"2026")) | N10: =IF($A10="","",IF(OR($D10="B1",$D10="M1",$D10="BTS1"),1,0)) | O10: =IF($A10="","",SUMIFS(Campagne!$D$1:$D$15,Campagne!$C$1:$C$15,$A10)) | P10: =IF($A10="","",SUMIFS(Campagne!$E$1:$E$15,Campagne!$C$1:$C$15,$A10)) | Q10: =IF($A10="","",SUMIFS(Campagne!$F$1:$F$15,Campagne!$C$1:$C$15,$A10)) | R10: =IF($A10="","",SUMIFS(Campagne!$K$1:$K$15,Campagne!$C$1:$C$15,$A10)) | S10: =IF($A10="","",SUMIFS(Campagne!$M$1:$M$15,Campagne!$C$1:$C$15,$A10)) | T10: =IF($A10="","",SUMIFS(PIL!$K$15:$K$28,PIL!$A$15:$A$28,$A10)*SUMIFS(PIL!$J$15:$J$28,PIL!$A$15:$A$28,$A10)*(SUM(PIL!$K$15:$K$28)/SUMPRODUCT(PIL!$K$15:$K$28,PIL!$J$15:$J$28))) | U10: =IF($A10="","",SUMIFS(PIL!$K$15:$K$28,PIL!$A$15:$A$28,$A10)) | V10: =IF($A10="","",IF($B10="V01",cad!$C$23,IF($B10="V02",cad!$D$23,cad!$E$23))) | W10: =IF($A10="","",IF($B10="V01",cad!$C$24,IF($B10="V02",cad!$D$24,cad!$E$24))) | X10: =IF($A10="","",IF($B10="V01",cad!$C$25,IF($B10="V02",cad!$D$25,cad!$E$25))) | Y10: =IF($A10="","",IF($B10="V01",cad!$C$26,IF($B10="V02",cad!$D$26,cad!$E$26))) | Z10: =IF($A10="","",IF($B10="V01",cad!$C$27,IF($B10="V02",cad!$D$27,cad!$E$27))) | AA10: =IF($A10="","",IF($B10="V01",cad!$C$28,IF($B10="V02",cad!$D$28,cad!$E$28))) | AB10: =IF($A10="","",IF($B10="V01",cad!$C$39,IF($B10="V02",cad!$D$39,cad!$E$39))) | AC10: =IF($A10="","",IF($F10="MBWAY",cad!$J$12,IF($F10="ISCOM",cad!$J$13,IF($F10="IPAC",cad!$J$14,IF($F10="PIGIER",cad!$J$15,cad!$J$16))))) | AD10: =IF($A10="","",($O10*(1+$W10)^$S10+$P10*IFERROR((($T10/$U10)*(1+$V10))^$R10,0))*IFERROR($G10/$Q10,0)*($J10+$Y10)*$K10*($L10+$Z10)) | AE10: =IF($A10="","",IF($N10=1,$AD10,0)) | AF10: =IF($A10="","",IF($N10=1,$AD10,$H10*($M10+$AA10))) | AG10: =IF($A10="","",$I10*(1+$X10*$AC10)) | AH10: =IF($A10="","",$AF10*$AG10+$AE10*$AB10)
A11: =IF(Moteur!D11="","",Moteur!D11) | B11: =IF(Moteur!B11="","",Moteur!B11) | C11: =IF(Moteur!F11="","",Moteur!F11) | D11: =IF(Moteur!G11="","",Moteur!G11) | E11: =IF(Moteur!H11="","",Moteur!H11) | F11: =IF(Moteur!E11="","",Moteur!E11) | G11: =IF($A11="","",SUMIFS(Allocation2!$H$1:$H$175,Allocation2!$C$1:$C$175,$A11,Allocation2!$D$1:$D$175,$C11,Allocation2!$E$1:$E$175,$D11,Allocation2!$F$1:$F$175,$E11,Allocation2!$G$1:$G$175,"2026")) | H11: =IF($A11="","",SUMIFS(Allocation2!$N$1:$N$175,Allocation2!$C$1:$C$175,$A11,Allocation2!$D$1:$D$175,$C11,Allocation2!$E$1:$E$175,$D11,Allocation2!$F$1:$F$175,$E11,Allocation2!$G$1:$G$175,"2026")) | I11: =IF($A11="","",SUMIFS(Allocation2!$P$1:$P$175,Allocation2!$C$1:$C$175,$A11,Allocation2!$D$1:$D$175,$C11,Allocation2!$E$1:$E$175,$D11,Allocation2!$F$1:$F$175,$E11,Allocation2!$G$1:$G$175,"2026")) | J11: =IF($A11="","",SUMIFS(Allocation2!$W$1:$W$175,Allocation2!$C$1:$C$175,$A11,Allocation2!$D$1:$D$175,$C11,Allocation2!$E$1:$E$175,$D11,Allocation2!$F$1:$F$175,$E11,Allocation2!$G$1:$G$175,"2026")) | K11: =IF($A11="","",SUMIFS(Allocation2!$X$1:$X$175,Allocation2!$C$1:$C$175,$A11,Allocation2!$D$1:$D$175,$C11,Allocation2!$E$1:$E$175,$D11,Allocation2!$F$1:$F$175,$E11,Allocation2!$G$1:$G$175,"2026")) | L11: =IF($A11="","",SUMIFS(Allocation2!$Y$1:$Y$175,Allocation2!$C$1:$C$175,$A11,Allocation2!$D$1:$D$175,$C11,Allocation2!$E$1:$E$175,$D11,Allocation2!$F$1:$F$175,$E11,Allocation2!$G$1:$G$175,"2026")) | M11: =IF($A11="","",SUMIFS(Allocation2!$V$1:$V$175,Allocation2!$C$1:$C$175,$A11,Allocation2!$D$1:$D$175,$C11,Allocation2!$E$1:$E$175,$D11,Allocation2!$F$1:$F$175,$E11,Allocation2!$G$1:$G$175,"2026")) | N11: =IF($A11="","",IF(OR($D11="B1",$D11="M1",$D11="BTS1"),1,0)) | O11: =IF($A11="","",SUMIFS(Campagne!$D$1:$D$15,Campagne!$C$1:$C$15,$A11)) | P11: =IF($A11="","",SUMIFS(Campagne!$E$1:$E$15,Campagne!$C$1:$C$15,$A11)) | Q11: =IF($A11="","",SUMIFS(Campagne!$F$1:$F$15,Campagne!$C$1:$C$15,$A11)) | R11: =IF($A11="","",SUMIFS(Campagne!$K$1:$K$15,Campagne!$C$1:$C$15,$A11)) | S11: =IF($A11="","",SUMIFS(Campagne!$M$1:$M$15,Campagne!$C$1:$C$15,$A11)) | T11: =IF($A11="","",SUMIFS(PIL!$K$15:$K$28,PIL!$A$15:$A$28,$A11)*SUMIFS(PIL!$J$15:$J$28,PIL!$A$15:$A$28,$A11)*(SUM(PIL!$K$15:$K$28)/SUMPRODUCT(PIL!$K$15:$K$28,PIL!$J$15:$J$28))) | U11: =IF($A11="","",SUMIFS(PIL!$K$15:$K$28,PIL!$A$15:$A$28,$A11)) | V11: =IF($A11="","",IF($B11="V01",cad!$C$23,IF($B11="V02",cad!$D$23,cad!$E$23))) | W11: =IF($A11="","",IF($B11="V01",cad!$C$24,IF($B11="V02",cad!$D$24,cad!$E$24))) | X11: =IF($A11="","",IF($B11="V01",cad!$C$25,IF($B11="V02",cad!$D$25,cad!$E$25))) | Y11: =IF($A11="","",IF($B11="V01",cad!$C$26,IF($B11="V02",cad!$D$26,cad!$E$26))) | Z11: =IF($A11="","",IF($B11="V01",cad!$C$27,IF($B11="V02",cad!$D$27,cad!$E$27))) | AA11: =IF($A11="","",IF($B11="V01",cad!$C$28,IF($B11="V02",cad!$D$28,cad!$E$28))) | AB11: =IF($A11="","",IF($B11="V01",cad!$C$39,IF($B11="V02",cad!$D$39,cad!$E$39))) | AC11: =IF($A11="","",IF($F11="MBWAY",cad!$J$12,IF($F11="ISCOM",cad!$J$13,IF($F11="IPAC",cad!$J$14,IF($F11="PIGIER",cad!$J$15,cad!$J$16))))) | AD11: =IF($A11="","",($O11*(1+$W11)^$S11+$P11*IFERROR((($T11/$U11)*(1+$V11))^$R11,0))*IFERROR($G11/$Q11,0)*($J11+$Y11)*$K11*($L11+$Z11)) | AE11: =IF($A11="","",IF($N11=1,$AD11,0)) | AF11: =IF($A11="","",IF($N11=1,$AD11,$H11*($M11+$AA11))) | AG11: =IF($A11="","",$I11*(1+$X11*$AC11)) | AH11: =IF($A11="","",$AF11*$AG11+$AE11*$AB11)
A12: =IF(Moteur!D12="","",Moteur!D12) | B12: =IF(Moteur!B12="","",Moteur!B12) | C12: =IF(Moteur!F12="","",Moteur!F12) | D12: =IF(Moteur!G12="","",Moteur!G12) | E12: =IF(Moteur!H12="","",Moteur!H12) | F12: =IF(Moteur!E12="","",Moteur!E12) | G12: =IF($A12="","",SUMIFS(Allocation2!$H$1:$H$175,Allocation2!$C$1:$C$175,$A12,Allocation2!$D$1:$D$175,$C12,Allocation2!$E$1:$E$175,$D12,Allocation2!$F$1:$F$175,$E12,Allocation2!$G$1:$G$175,"2026")) | H12: =IF($A12="","",SUMIFS(Allocation2!$N$1:$N$175,Allocation2!$C$1:$C$175,$A12,Allocation2!$D$1:$D$175,$C12,Allocation2!$E$1:$E$175,$D12,Allocation2!$F$1:$F$175,$E12,Allocation2!$G$1:$G$175,"2026")) | I12: =IF($A12="","",SUMIFS(Allocation2!$P$1:$P$175,Allocation2!$C$1:$C$175,$A12,Allocation2!$D$1:$D$175,$C12,Allocation2!$E$1:$E$175,$D12,Allocation2!$F$1:$F$175,$E12,Allocation2!$G$1:$G$175,"2026")) | J12: =IF($A12="","",SUMIFS(Allocation2!$W$1:$W$175,Allocation2!$C$1:$C$175,$A12,Allocation2!$D$1:$D$175,$C12,Allocation2!$E$1:$E$175,$D12,Allocation2!$F$1:$F$175,$E12,Allocation2!$G$1:$G$175,"2026")) | K12: =IF($A12="","",SUMIFS(Allocation2!$X$1:$X$175,Allocation2!$C$1:$C$175,$A12,Allocation2!$D$1:$D$175,$C12,Allocation2!$E$1:$E$175,$D12,Allocation2!$F$1:$F$175,$E12,Allocation2!$G$1:$G$175,"2026")) | L12: =IF($A12="","",SUMIFS(Allocation2!$Y$1:$Y$175,Allocation2!$C$1:$C$175,$A12,Allocation2!$D$1:$D$175,$C12,Allocation2!$E$1:$E$175,$D12,Allocation2!$F$1:$F$175,$E12,Allocation2!$G$1:$G$175,"2026")) | M12: =IF($A12="","",SUMIFS(Allocation2!$V$1:$V$175,Allocation2!$C$1:$C$175,$A12,Allocation2!$D$1:$D$175,$C12,Allocation2!$E$1:$E$175,$D12,Allocation2!$F$1:$F$175,$E12,Allocation2!$G$1:$G$175,"2026")) | N12: =IF($A12="","",IF(OR($D12="B1",$D12="M1",$D12="BTS1"),1,0)) | O12: =IF($A12="","",SUMIFS(Campagne!$D$1:$D$15,Campagne!$C$1:$C$15,$A12)) | P12: =IF($A12="","",SUMIFS(Campagne!$E$1:$E$15,Campagne!$C$1:$C$15,$A12)) | Q12: =IF($A12="","",SUMIFS(Campagne!$F$1:$F$15,Campagne!$C$1:$C$15,$A12)) | R12: =IF($A12="","",SUMIFS(Campagne!$K$1:$K$15,Campagne!$C$1:$C$15,$A12)) | S12: =IF($A12="","",SUMIFS(Campagne!$M$1:$M$15,Campagne!$C$1:$C$15,$A12)) | T12: =IF($A12="","",SUMIFS(PIL!$K$15:$K$28,PIL!$A$15:$A$28,$A12)*SUMIFS(PIL!$J$15:$J$28,PIL!$A$15:$A$28,$A12)*(SUM(PIL!$K$15:$K$28)/SUMPRODUCT(PIL!$K$15:$K$28,PIL!$J$15:$J$28))) | U12: =IF($A12="","",SUMIFS(PIL!$K$15:$K$28,PIL!$A$15:$A$28,$A12)) | V12: =IF($A12="","",IF($B12="V01",cad!$C$23,IF($B12="V02",cad!$D$23,cad!$E$23))) | W12: =IF($A12="","",IF($B12="V01",cad!$C$24,IF($B12="V02",cad!$D$24,cad!$E$24))) | X12: =IF($A12="","",IF($B12="V01",cad!$C$25,IF($B12="V02",cad!$D$25,cad!$E$25))) | Y12: =IF($A12="","",IF($B12="V01",cad!$C$26,IF($B12="V02",cad!$D$26,cad!$E$26))) | Z12: =IF($A12="","",IF($B12="V01",cad!$C$27,IF($B12="V02",cad!$D$27,cad!$E$27))) | AA12: =IF($A12="","",IF($B12="V01",cad!$C$28,IF($B12="V02",cad!$D$28,cad!$E$28))) | AB12: =IF($A12="","",IF($B12="V01",cad!$C$39,IF($B12="V02",cad!$D$39,cad!$E$39))) | AC12: =IF($A12="","",IF($F12="MBWAY",cad!$J$12,IF($F12="ISCOM",cad!$J$13,IF($F12="IPAC",cad!$J$14,IF($F12="PIGIER",cad!$J$15,cad!$J$16))))) | AD12: =IF($A12="","",($O12*(1+$W12)^$S12+$P12*IFERROR((($T12/$U12)*(1+$V12))^$R12,0))*IFERROR($G12/$Q12,0)*($J12+$Y12)*$K12*($L12+$Z12)) | AE12: =IF($A12="","",IF($N12=1,$AD12,0)) | AF12: =IF($A12="","",IF($N12=1,$AD12,$H12*($M12+$AA12))) | AG12: =IF($A12="","",$I12*(1+$X12*$AC12)) | AH12: =IF($A12="","",$AF12*$AG12+$AE12*$AB12)
