Workbook
Name BUD_REF_CAP: Pilotage!$K$19:$K$32
Name HYP_ACQ_BUD_V01: Cadrage!$C$22
Name HYP_ACQ_BUD_V02: Cadrage!$D$22
Name HYP_ACQ_BUD_V03: Cadrage!$E$22
Name HYP_BRAND_BUD_V01: Cadrage!$C$23
Name HYP_BRAND_BUD_V02: Cadrage!$D$23
Name HYP_BRAND_BUD_V03: Cadrage!$E$23
Name HYP_CAP_RETENU: Pilotage!$J$19:$J$32
Name HYP_CONV_ADM_V01: Cadrage!$C$26
Name HYP_CONV_ADM_V02: Cadrage!$D$26
Name HYP_CONV_ADM_V03: Cadrage!$E$26
Name HYP_CONV_LEAD_V01: Cadrage!$C$25
Name HYP_CONV_LEAD_V02: Cadrage!$D$25
Name HYP_CONV_LEAD_V03: Cadrage!$E$25
Name HYP_FEE_V01: Cadrage!$C$39
Name HYP_FEE_V02: Cadrage!$D$39
Name HYP_FEE_V03: Cadrage!$E$39
Name HYP_FTE_PERM_V01: Cadrage!$C$33
Name HYP_FTE_PERM_V02: Cadrage!$D$33
Name HYP_FTE_PERM_V03: Cadrage!$E$33
Name HYP_INFL_EXT_V01: Cadrage!$C$31
Name HYP_INFL_EXT_V02: Cadrage!$D$31
Name HYP_INFL_EXT_V03: Cadrage!$E$31
Name HYP_PASSAGE_V01: Cadrage!$C$27
Name HYP_PASSAGE_V02: Cadrage!$D$27
Name HYP_PASSAGE_V03: Cadrage!$E$27
Name HYP_PRICE_COEF_IPAC: Cadrage!$K$13
Name HYP_PRICE_COEF_ISCOM: Cadrage!$K$12
Name HYP_PRICE_COEF_MBWAY: Cadrage!$K$11
Name HYP_PRICE_COEF_PIGIER: Cadrage!$K$14
Name HYP_PRICE_COEF_TUNON: Cadrage!$K$15
Name HYP_PRICE_V01: Cadrage!$C$24
Name HYP_PRICE_V02: Cadrage!$D$24
Name HYP_PRICE_V03: Cadrage!$E$24
Name HYP_PRODUCTIVITY_V01: Cadrage!$C$34
Name HYP_PRODUCTIVITY_V02: Cadrage!$D$34
Name HYP_PRODUCTIVITY_V03: Cadrage!$E$34
Name HYP_SALARY_V01: Cadrage!$C$32
Name HYP_SALARY_V02: Cadrage!$D$32
Name HYP_SALARY_V03: Cadrage!$E$32
Name HYP_STRUCT_COST_V01: Cadrage!$C$35
Name HYP_STRUCT_COST_V02: Cadrage!$D$35
Name HYP_STRUCT_COST_V03: Cadrage!$E$35
Name SCENARIO_ACTIF: Cadrage!$C$4
Name SCENARIO_CODE: Cadrage!$P$1
Name TEC_EBITDA: Cadrage!$F$5
Name TEC_PL: Cadrage!$F$4

Sheet Cadrage
O1: code scénario -> | P1: =IF($C$4="Cadrage","V01",IF($C$4="Optimiste","V02","V03"))
C2: POSTE DE COMMANDE CFO — Cadrage CA & EBITDA 2027
B4: Scenario actif : | C4: Cadrage | E4: Objectif EBITDA (amél. vs 2026) : | F4: 0.065
E5: (marge : constat — plus une saisie) | F5: 0.15
B7: Reconciliation — Reference · Cible · Construit (scenario actif) | J7: Coeff prix par marque (decision)
B9: Indicateur | C9: Reference | D9: Objectif | E9: Construit | F9: Ecart | G9: Ecart % | J9: Marque | K9: Coeff prix
C10: Forecast 2026
B11: Chiffre d'affaires | C11: 23098985 | D11: — | E11: =SUMIFS(Moteur!$R$1:$R$200,Moteur!$B$1:$B$200,Cadrage!$P$1) | F11: =E11-C11 | G11: =IFERROR(E11/C11-1,0) | J11: MBway | K11: 1.2
B12: EBITDA | C12: 3845790 | D12: =C12*(1+Cadrage!$F$4) | E12: =SUMIFS(_CALC_PNL!$T$1:$T$1347,_CALC_PNL!$D$1:$D$1347,Cadrage!$P$1,_CALC_PNL!$C$1:$C$1347,"2027") | F12: =E12-D12 | G12: =IFERROR(E12/D12-1,0) | J12: ISCOM | K12: 1.15
B13: Marge EBITDA % | C13: =IFERROR(C12/C11, 0) | D13: — | E13: =IFERROR(E12/E11,0) | F13: =E13-C13 | G13: =IFERROR(E13-C13,0) | J13: Ipac Bachelor Factory | K13: 0.95
B14: Effectif | C14: 3114 | E14: =SUMIFS(Moteur!$P$1:$P$200,Moteur!$B$1:$B$200,Cadrage!$P$1) | F14: =E14-C14 | G14: =IFERROR(E14/C14-1,0) | J14: Pigier | K14: 0.9
J15: Tunon | K15: 1.05
B18: Leviers de CROISSANCE / REVENUS
B20: Paramètre | C20: =C21 | D20: =D21 | E20: =E21 | F20: ACTIF (scenario)
C21: Cadrage | D21: Optimiste | E21: Prudent
B22: Variation du budget d'acquisition → leads payants | C22: 0.08 | D22: 0.15 | E22: -0.05 | F22: =INDEX(C22:E22,MATCH(Cadrage!$C$4,$C$21:$E$21,0))
B23: Variation du budget de marque → socle organique | C23: 0.1 | D23: 0.15 | E23: -0.05 | F23: =INDEX(C23:E23,MATCH(Cadrage!$C$4,$C$21:$E$21,0))
B24: Hausse tarifaire (prix) | C24: 0.0029 | D24: 0.035 | E24: 0.02 | F24: =INDEX(C24:E24,MATCH(Cadrage!$C$4,$C$21:$E$21,0))
B25: Gain du taux de conversion Lead → Candidature | C25: 0.01 | D25: 0.03 | E25: -0.01 | F25: =INDEX(C25:E25,MATCH(Cadrage!$C$4,$C$21:$E$21,0))
B26: Gain du taux de conversion Admis → Inscrit | C26: 0.01 | D26: 0.025 | E26: -0.01 | F26: =INDEX(C26:E26,MATCH(Cadrage!$C$4,$C$21:$E$21,0))
B27: Amélioration du taux de passage | C27: 0.005 | D27: 0.015 | E27: -0.01 | F27: =INDEX(C27:E27,MATCH(Cadrage!$C$4,$C$21:$E$21,0))
B29: Leviers de COUTS
B31: Inflation des charges externes | C31: 0.02 | D31: 0.015 | E31: 0.03 | F31: =INDEX(C31:E31,MATCH(Cadrage!$C$4,$C$21:$E$21,0))
B32: Politique salariale sur la masse permanente | C32: 0.025 | D32: 0.02 | E32: 0.03 | F32: =INDEX(C32:E32,MATCH(Cadrage!$C$4,$C$21:$E$21,0))
B33: Variation des effectifs permanents | C33: 0.04 | D33: 0.03 | E33: 0.05 | F33: =INDEX(C33:E33,MATCH(Cadrage!$C$4,$C$21:$E$21,0))
B34: Effort de productivité sur les achats et la structure | C34: 0.0185 | D34: 0.03 | F34: =INDEX(C34:E34,MATCH(Cadrage!$C$4,$C$21:$E$21,0))
B35: Variation des coûts de structure (loyers, IT, siège…) | D35: -0.03 | E35: 0.04 | F35: =INDEX(C35:E35,MATCH(Cadrage!$C$4,$C$21:$E$21,0))
B37: Constante — frais de dossier (decision)
B39: Frais de dossier par nouvel inscrit | C39: 90 | D39: 90 | E39: 90 | F39: =INDEX(C39:E39,MATCH(Cadrage!$C$4,$C$21:$E$21,0))

Sheet Pilotage
O1: code scénario -> | P1: =IF($E$6="Cadrage","V01",IF($E$6="Optimiste","V02","V03"))
G2: PILOTAGE · Cockpit de decision CFO — Budget 2027
B6: Scenario actif : | E6: Cadrage
B9: CA 2027 | D9: EBITDA (apres siege) | F9: Marge EBITDA | H9: Effectif | J9: Croissance CA vs 2026
B10: =E55 | D10: =H55 | F10: =I55 | H10: =D55 | J10: =IFERROR(E55/Cadrage!$C$11-1,0)
B12: ="EBITDA vs objectif Cadrage : "&IF(D10>=Cadrage!$D$12,"🟢 tenu (+"&TEXT(D10-Cadrage!$D$12,"#,##0")&" €)","🔴 à combler ("&TEXT(D10-Cadrage!$D$12,"#,##0")&" €)")
A15: COLumn to hide
B16: 1 · Cap strategique par campus (marque x ville) — arbitrage du budget d'acquisition
U17: à masquer | V17: à masquer | W17: à masquer
A18: Campus | B18: Marque | C18: Ville | D18: CAC marginal | E18: Croiss. leads | F18: Intensité mkt | G18: Cap Eff | H18: Cap mom. | I18: Cap pot. | J18: Cap retenu | K18: Budget acq réf. | L18: Entity | U18: CAP_EFF (live) | V18: CAP_MOM (live) | W18: CAP_POT (live)
A19: MBWAY_PAR | B19: MBway | C19: Paris | D19: 1475.0125 | E19: 0.11073637 | F19: 0.021756763 | G19: 0.8149808 | H19: 1.0597054 | I19: 0.86473065 | J19: 1 | K19: 68291 | L19: MBWAY_PAR
A20: MBWAY_LYO | B20: MBway | C20: Lyon | D20: 1101.595 | E20: 0.11887172 | F20: 0.016735257 | G20: 1.0912421 | H20: 1.1375577 | I20: 1.1241979 | J20: 1 | K20: 41783 | L20: MBWAY_LYO
A21: MBWAY_NAN | B21: MBway | C21: Nantes | D21: 963.56901 | E21: 0.1237954 | F21: 0.014610109 | G21: 1.2475566 | H21: 1.1846754 | I21: 1.2877207 | J21: 1 | K21: 31533 | L21: MBWAY_NAN
A22: MBWAY_BOR | B22: MBway | C22: Bordeaux | D22: 889.58534 | E22: 0.12609457 | F22: 0.01405213 | G22: 1.3513114 | H22: 1.2066776 | I22: 1.3388532 | J22: 1 | K22: 24923 | L22: MBWAY_BOR
A23: ISCOM_PAR | B23: ISCOM | C23: Paris | D23: 1540.3212 | E23: 0.077744807 | F23: 0.020902665 | G23: 0.78042607 | H23: 0.74398855 | I23: 0.90006419 | J23: 1 | K23: 60800 | L23: ISCOM_PAR
A24: ISCOM_LIL | B24: ISCOM | C24: Lille | D24: 978.58254 | E24: 0.081545064 | F24: 0.014363413 | G24: 1.2284164 | H24: 0.78035559 | I24: 1.3098377 | J24: 1 | K24: 25220 | L24: ISCOM_LIL
A25: ISCOM_TLS | B25: ISCOM | C25: Toulouse | D25: 919.03491 | E25: 0.082116788 | F25: 0.013564662 | G25: 1.30801 | H25: 0.78582677 | I25: 1.386967 | J25: 1 | K25: 22083 | L25: ISCOM_TLS
A26: IPAC_NAN | B26: Ipac | C26: Nantes | D26: 1216.283 | E26: 0.13788487 | F26: 0.021343795 | G26: 0.98834472 | H26: 1.3195064 | I26: 0.88146178 | J26: 1 | K26: 21760 | L26: IPAC_NAN
A27: IPAC_REN | B27: Ipac | C27: Rennes | D27: 1040.5484 | E27: 0.14478114 | F27: 0.019104458 | G27: 1.1552628 | H27: 1.3855011 | I27: 0.98478271 | J27: 1 | K27: 14933 | L27: IPAC_REN
A28: IPAC_MTP | B28: Ipac | C28: Montpellier | D28: 1033.9757 | E28: 0.14478114 | F28: 0.019417898 | G28: 1.1626065 | H28: 1.3855011 | I28: 0.96888656 | J28: 1 | K28: 15178 | L28: IPAC_MTP
A29: PIGIER_LYO | B29: Pigier | C29: Lyon | D29: 1704.9638 | E29: 0.085003455 | F29: 0.029279527 | G29: 0.70506298 | H29: 0.81345109 | I29: 0.64255614 | J29: 1 | K29: 36612 | L29: PIGIER_LYO
A30: PIGIER_BOR | B30: Pigier | C30: Bordeaux | D30: 1368.0761 | E30: 0.087533156 | F30: 0.024360438 | G30: 0.87868421 | H30: 0.83765937 | I30: 0.77230713 | J30: 1 | K30: 21968 | L30: PIGIER_BOR
... A32: TUNON_LYO | B32: Tunon | C32: Lyon | D32: 1624.6613 | E32: 0.072555205 | F32: 0.021828498 | G32: 0.7399123 | H32: 0.69432601 | I32: 0.86188889 | J32: 1 | K32: 18850 | L32: TUNON_LYO
B36: 2 · Synthese par campus (resultats budget, live)
A38: Campus | B38: Marque | C38: Ville | D38: Effectif | E38: CA 2027 | F38: Prix moy. | G38: Part CA | H38: EBITDA campus | I38: Mrg EBITDA | J38: EBITDA/etud. | K38: Rejoue | L38: CAC marg.
A39: MBWAY_PAR | B39: MBway | C39: Paris | D39: =SUMIFS(Moteur!$P$1:$P$200,Moteur!$D$1:$D$200,$A39,Moteur!$B$1:$B$200,$P$1) | E39: =SUMIFS(Moteur!$R$1:$R$200,Moteur!$D$1:$D$200,$A39,Moteur!$B$1:$B$200,$P$1) | F39: =IFERROR(E39/D39,0) | G39: =IFERROR(E39/SUM($E$39:$E$52),0) | H39: =SUMIFS(_CALC_PNL!$T$1:$T$1347,_CALC_PNL!$A$1:$A$1347,$A39,_CALC_PNL!$D$1:$D$1347,$P$1,_CALC_PNL!$C$1:$C$1347,"2027") | I39: =IFERROR(H39/E39,0) | J39: =IFERROR(H39/D39,0) | K39: =SUMIFS(Pilotage!$K$19:$K$32,Pilotage!$A$19:$A$32,$A39)*SUMIFS(Pilotage!$J$19:$J$32,Pilotage!$A$19:$A$32,$A39)*(SUM(Pilotage!$K$19:$K$32)/SUMPRODUCT(Pilotage!$K$19:$K$32,Pilotage!$J$19:$J$32)) | L39: =SUMIFS(Pilotage!$D$19:$D$32,Pilotage!$A$19:$A$32,$A39)
A40: MBWAY_LYO | B40: MBway | C40: Lyon | D40: =SUMIFS(Moteur!$P$1:$P$200,Moteur!$D$1:$D$200,$A40,Moteur!$B$1:$B$200,$P$1) | E40: =SUMIFS(Moteur!$R$1:$R$200,Moteur!$D$1:$D$200,$A40,Moteur!$B$1:$B$200,$P$1) | F40: =IFERROR(E40/D40,0) | G40: =IFERROR(E40/SUM($E$39:$E$52),0) | H40: =SUMIFS(_CALC_PNL!$T$1:$T$1347,_CALC_PNL!$A$1:$A$1347,$A40,_CALC_PNL!$D$1:$D$1347,$P$1,_CALC_PNL!$C$1:$C$1347,"2027") | I40: =IFERROR(H40/E40,0) | J40: =IFERROR(H40/D40,0) | K40: =SUMIFS(Pilotage!$K$19:$K$32,Pilotage!$A$19:$A$32,$A40)*SUMIFS(Pilotage!$J$19:$J$32,Pilotage!$A$19:$A$32,$A40)*(SUM(Pilotage!$K$19:$K$32)/SUMPRODUCT(Pilotage!$K$19:$K$32,Pilotage!$J$19:$J$32)) | L40: =SUMIFS(Pilotage!$D$19:$D$32,Pilotage!$A$19:$A$32,$A40)
A41: MBWAY_NAN | B41: MBway | C41: Nantes | D41: =SUMIFS(Moteur!$P$1:$P$200,Moteur!$D$1:$D$200,$A41,Moteur!$B$1:$B$200,$P$1) | E41: =SUMIFS(Moteur!$R$1:$R$200,Moteur!$D$1:$D$200,$A41,Moteur!$B$1:$B$200,$P$1) | F41: =IFERROR(E41/D41,0) | G41: =IFERROR(E41/SUM($E$39:$E$52),0) | H41: =SUMIFS(_CALC_PNL!$T$1:$T$1347,_CALC_PNL!$A$1:$A$1347,$A41,_CALC_PNL!$D$1:$D$1347,$P$1,_CALC_PNL!$C$1:$C$1347,"2027") | I41: =IFERROR(H41/E41,0) | J41: =IFERROR(H41/D41,0) | K41: =SUMIFS(Pilotage!$K$19:$K$32,Pilotage!$A$19:$A$32,$A41)*SUMIFS(Pilotage!$J$19:$J$32,Pilotage!$A$19:$A$32,$A41)*(SUM(Pilotage!$K$19:$K$32)/SUMPRODUCT(Pilotage!$K$19:$K$32,Pilotage!$J$19:$J$32)) | L41: =SUMIFS(Pilotage!$D$19:$D$32,Pilotage!$A$19:$A$32,$A41)
A42: MBWAY_BOR | B42: MBway | C42: Bordeaux | D42: =SUMIFS(Moteur!$P$1:$P$200,Moteur!$D$1:$D$200,$A42,Moteur!$B$1:$B$200,$P$1) | E42: =SUMIFS(Moteur!$R$1:$R$200,Moteur!$D$1:$D$200,$A42,Moteur!$B$1:$B$200,$P$1) | F42: =IFERROR(E42/D42,0) | G42: =IFERROR(E42/SUM($E$39:$E$52),0) | H42: =SUMIFS(_CALC_PNL!$T$1:$T$1347,_CALC_PNL!$A$1:$A$1347,$A42,_CALC_PNL!$D$1:$D$1347,$P$1,_CALC_PNL!$C$1:$C$1347,"2027") | I42: =IFERROR(H42/E42,0) | J42: =IFERROR(H42/D42,0) | K42: =SUMIFS(Pilotage!$K$19:$K$32,Pilotage!$A$19:$A$32,$A42)*SUMIFS(Pilotage!$J$19:$J$32,Pilotage!$A$19:$A$32,$A42)*(SUM(Pilotage!$K$19:$K$32)/SUMPRODUCT(Pilotage!$K$19:$K$32,Pilotage!$J$19:$J$32)) | L42: =SUMIFS(Pilotage!$D$19:$D$32,Pilotage!$A$19:$A$32,$A42)
A43: ISCOM_PAR | B43: ISCOM | C43: Paris | D43: =SUMIFS(Moteur!$P$1:$P$200,Moteur!$D$1:$D$200,$A43,Moteur!$B$1:$B$200,$P$1) | E43: =SUMIFS(Moteur!$R$1:$R$200,Moteur!$D$1:$D$200,$A43,Moteur!$B$1:$B$200,$P$1) | F43: =IFERROR(E43/D43,0) | G43: =IFERROR(E43/SUM($E$39:$E$52),0) | H43: =SUMIFS(_CALC_PNL!$T$1:$T$1347,_CALC_PNL!$A$1:$A$1347,$A43,_CALC_PNL!$D$1:$D$1347,$P$1,_CALC_PNL!$C$1:$C$1347,"2027") | I43: =IFERROR(H43/E43,0) | J43: =IFERROR(H43/D43,0) | K43: =SUMIFS(Pilotage!$K$19:$K$32,Pilotage!$A$19:$A$32,$A43)*SUMIFS(Pilotage!$J$19:$J$32,Pilotage!$A$19:$A$32,$A43)*(SUM(Pilotage!$K$19:$K$32)/SUMPRODUCT(Pilotage!$K$19:$K$32,Pilotage!$J$19:$J$32)) | L43: =SUMIFS(Pilotage!$D$19:$D$32,Pilotage!$A$19:$A$32,$A43)
A44: ISCOM_LIL | B44: ISCOM | C44: Lille | D44: =SUMIFS(Moteur!$P$1:$P$200,Moteur!$D$1:$D$200,$A44,Moteur!$B$1:$B$200,$P$1) | E44: =SUMIFS(Moteur!$R$1:$R$200,Moteur!$D$1:$D$200,$A44,Moteur!$B$1:$B$200,$P$1) | F44: =IFERROR(E44/D44,0) | G44: =IFERROR(E44/SUM($E$39:$E$52),0) | H44: =SUMIFS(_CALC_PNL!$T$1:$T$1347,_CALC_PNL!$A$1:$A$1347,$A44,_CALC_PNL!$D$1:$D$1347,$P$1,_CALC_PNL!$C$1:$C$1347,"2027") | I44: =IFERROR(H44/E44,0) | J44: =IFERROR(H44/D44,0) | K44: =SUMIFS(Pilotage!$K$19:$K$32,Pilotage!$A$19:$A$32,$A44)*SUMIFS(Pilotage!$J$19:$J$32,Pilotage!$A$19:$A$32,$A44)*(SUM(Pilotage!$K$19:$K$32)/SUMPRODUCT(Pilotage!$K$19:$K$32,Pilotage!$J$19:$J$32)) | L44: =SUMIFS(Pilotage!$D$19:$D$32,Pilotage!$A$19:$A$32,$A44)
A45: ISCOM_TLS | B45: ISCOM | C45: Toulouse | D45: =SUMIFS(Moteur!$P$1:$P$200,Moteur!$D$1:$D$200,$A45,Moteur!$B$1:$B$200,$P$1) | E45: =SUMIFS(Moteur!$R$1:$R$200,Moteur!$D$1:$D$200,$A45,Moteur!$B$1:$B$200,$P$1) | F45: =IFERROR(E45/D45,0) | G45: =IFERROR(E45/SUM($E$39:$E$52),0) | H45: =SUMIFS(_CALC_PNL!$T$1:$T$1347,_CALC_PNL!$A$1:$A$1347,$A45,_CALC_PNL!$D$1:$D$1347,$P$1,_CALC_PNL!$C$1:$C$1347,"2027") | I45: =IFERROR(H45/E45,0) | J45: =IFERROR(H45/D45,0) | K45: =SUMIFS(Pilotage!$K$19:$K$32,Pilotage!$A$19:$A$32,$A45)*SUMIFS(Pilotage!$J$19:$J$32,Pilotage!$A$19:$A$32,$A45)*(SUM(Pilotage!$K$19:$K$32)/SUMPRODUCT(Pilotage!$K$19:$K$32,Pilotage!$J$19:$J$32)) | L45: =SUMIFS(Pilotage!$D$19:$D$32,Pilotage!$A$19:$A$32,$A45)
A46: IPAC_NAN | B46: Ipac | C46: Nantes | D46: =SUMIFS(Moteur!$P$1:$P$200,Moteur!$D$1:$D$200,$A46,Moteur!$B$1:$B$200,$P$1) | E46: =SUMIFS(Moteur!$R$1:$R$200,Moteur!$D$1:$D$200,$A46,Moteur!$B$1:$B$200,$P$1) | F46: =IFERROR(E46/D46,0) | G46: =IFERROR(E46/SUM($E$39:$E$52),0) | H46: =SUMIFS(_CALC_PNL!$T$1:$T$1347,_CALC_PNL!$A$1:$A$1347,$A46,_CALC_PNL!$D$1:$D$1347,$P$1,_CALC_PNL!$C$1:$C$1347,"2027") | I46: =IFERROR(H46/E46,0) | J46: =IFERROR(H46/D46,0) | K46: =SUMIFS(Pilotage!$K$19:$K$32,Pilotage!$A$19:$A$32,$A46)*SUMIFS(Pilotage!$J$19:$J$32,Pilotage!$A$19:$A$32,$A46)*(SUM(Pilotage!$K$19:$K$32)/SUMPRODUCT(Pilotage!$K$19:$K$32,Pilotage!$J$19:$J$32)) | L46: =SUMIFS(Pilotage!$D$19:$D$32,Pilotage!$A$19:$A$32,$A46)
A47: IPAC_REN | B47: Ipac | C47: Rennes | D47: =SUMIFS(Moteur!$P$1:$P$200,Moteur!$D$1:$D$200,$A47,Moteur!$B$1:$B$200,$P$1) | E47: =SUMIFS(Moteur!$R$1:$R$200,Moteur!$D$1:$D$200,$A47,Moteur!$B$1:$B$200,$P$1) | F47: =IFERROR(E47/D47,0) | G47: =IFERROR(E47/SUM($E$39:$E$52),0) | H47: =SUMIFS(_CALC_PNL!$T$1:$T$1347,_CALC_PNL!$A$1:$A$1347,$A47,_CALC_PNL!$D$1:$D$1347,$P$1,_CALC_PNL!$C$1:$C$1347,"2027") | I47: =IFERROR(H47/E47,0) | J47: =IFERROR(H47/D47,0) | K47: =SUMIFS(Pilotage!$K$19:$K$32,Pilotage!$A$19:$A$32,$A47)*SUMIFS(Pilotage!$J$19:$J$32,Pilotage!$A$19:$A$32,$A47)*(SUM(Pilotage!$K$19:$K$32)/SUMPRODUCT(Pilotage!$K$19:$K$32,Pilotage!$J$19:$J$32)) | L47: =SUMIFS(Pilotage!$D$19:$D$32,Pilotage!$A$19:$A$32,$A47)
A48: IPAC_MTP | B48: Ipac | C48: Montpellier | D48: =SUMIFS(Moteur!$P$1:$P$200,Moteur!$D$1:$D$200,$A48,Moteur!$B$1:$B$200,$P$1) | E48: =SUMIFS(Moteur!$R$1:$R$200,Moteur!$D$1:$D$200,$A48,Moteur!$B$1:$B$200,$P$1) | F48: =IFERROR(E48/D48,0) | G48: =IFERROR(E48/SUM($E$39:$E$52),0) | H48: =SUMIFS(_CALC_PNL!$T$1:$T$1347,_CALC_PNL!$A$1:$A$1347,$A48,_CALC_PNL!$D$1:$D$1347,$P$1,_CALC_PNL!$C$1:$C$1347,"2027") | I48: =IFERROR(H48/E48,0) | J48: =IFERROR(H48/D48,0) | K48: =SUMIFS(Pilotage!$K$19:$K$32,Pilotage!$A$19:$A$32,$A48)*SUMIFS(Pilotage!$J$19:$J$32,Pilotage!$A$19:$A$32,$A48)*(SUM(Pilotage!$K$19:$K$32)/SUMPRODUCT(Pilotage!$K$19:$K$32,Pilotage!$J$19:$J$32)) | L48: =SUMIFS(Pilotage!$D$19:$D$32,Pilotage!$A$19:$A$32,$A48)
A49: PIGIER_LYO | B49: Pigier | C49: Lyon | D49: =SUMIFS(Moteur!$P$1:$P$200,Moteur!$D$1:$D$200,$A49,Moteur!$B$1:$B$200,$P$1) | E49: =SUMIFS(Moteur!$R$1:$R$200,Moteur!$D$1:$D$200,$A49,Moteur!$B$1:$B$200,$P$1) | F49: =IFERROR(E49/D49,0) | G49: =IFERROR(E49/SUM($E$39:$E$52),0) | H49: =SUMIFS(_CALC_PNL!$T$1:$T$1347,_CALC_PNL!$A$1:$A$1347,$A49,_CALC_PNL!$D$1:$D$1347,$P$1,_CALC_PNL!$C$1:$C$1347,"2027") | I49: =IFERROR(H49/E49,0) | J49: =IFERROR(H49/D49,0) | K49: =SUMIFS(Pilotage!$K$19:$K$32,Pilotage!$A$19:$A$32,$A49)*SUMIFS(Pilotage!$J$19:$J$32,Pilotage!$A$19:$A$32,$A49)*(SUM(Pilotage!$K$19:$K$32)/SUMPRODUCT(Pilotage!$K$19:$K$32,Pilotage!$J$19:$J$32)) | L49: =SUMIFS(Pilotage!$D$19:$D$32,Pilotage!$A$19:$A$32,$A49)
A50: PIGIER_BOR | B50: Pigier | C50: Bordeaux | D50: =SUMIFS(Moteur!$P$1:$P$200,Moteur!$D$1:$D$200,$A50,Moteur!$B$1:$B$200,$P$1) | E50: =SUMIFS(Moteur!$R$1:$R$200,Moteur!$D$1:$D$200,$A50,Moteur!$B$1:$B$200,$P$1) | F50: =IFERROR(E50/D50,0) | G50: =IFERROR(E50/SUM($E$39:$E$52),0) | H50: =SUMIFS(_CALC_PNL!$T$1:$T$1347,_CALC_PNL!$A$1:$A$1347,$A50,_CALC_PNL!$D$1:$D$1347,$P$1,_CALC_PNL!$C$1:$C$1347,"2027") | I50: =IFERROR(H50/E50,0) | J50: =IFERROR(H50/D50,0) | K50: =SUMIFS(Pilotage!$K$19:$K$32,Pilotage!$A$19:$A$32,$A50)*SUMIFS(Pilotage!$J$19:$J$32,Pilotage!$A$19:$A$32,$A50)*(SUM(Pilotage!$K$19:$K$32)/SUMPRODUCT(Pilotage!$K$19:$K$32,Pilotage!$J$19:$J$32)) | L50: =SUMIFS(Pilotage!$D$19:$D$32,Pilotage!$A$19:$A$32,$A50)
... A52: TUNON_LYO | B52: Tunon | C52: Lyon | D52: =SUMIFS(Moteur!$P$1:$P$200,Moteur!$D$1:$D$200,$A52,Moteur!$B$1:$B$200,$P$1) | E52: =SUMIFS(Moteur!$R$1:$R$200,Moteur!$D$1:$D$200,$A52,Moteur!$B$1:$B$200,$P$1) | F52: =IFERROR(E52/D52,0) | G52: =IFERROR(E52/SUM($E$39:$E$52),0) | H52: =SUMIFS(_CALC_PNL!$T$1:$T$1347,_CALC_PNL!$A$1:$A$1347,$A52,_CALC_PNL!$D$1:$D$1347,$P$1,_CALC_PNL!$C$1:$C$1347,"2027") | I52: =IFERROR(H52/E52,0) | J52: =IFERROR(H52/D52,0) | K52: =SUMIFS(Pilotage!$K$19:$K$32,Pilotage!$A$19:$A$32,$A52)*SUMIFS(Pilotage!$J$19:$J$32,Pilotage!$A$19:$A$32,$A52)*(SUM(Pilotage!$K$19:$K$32)/SUMPRODUCT(Pilotage!$K$19:$K$32,Pilotage!$J$19:$J$32)) | L52: =SUMIFS(Pilotage!$D$19:$D$32,Pilotage!$A$19:$A$32,$A52)
A53: Sous-total campus | B53: Sous-total campus | D53: =SUM(D39:D52) | E53: =SUM(E39:E52) | F53: =IFERROR(E53/D53,0) | G53: =SUM(G39:G52) | H53: =SUM(H39:H52) | I53: =IFERROR(H53/E53,0) | J53: =IFERROR(H53/D53,0) | K53: =SUM(K39:K52)
A54: Siege / holding (GRP) | B54: Siege / holding (GRP) | H54: =SUMIFS(_CALC_PNL!$T$1:$T$1347,_CALC_PNL!$A$1:$A$1347,"GRP",_CALC_PNL!$D$1:$D$1347,$P$1,_CALC_PNL!$C$1:$C$1347,"2027")
A55: GROUPE 2027 V01 | B55: GROUPE 2027 V01 | D55: =D53 | E55: =E53 | F55: =IFERROR(E55/D55,0) | G55: =SUM(G39:G52) | H55: =H53+H54 | I55: =IFERROR(H55/E55,0) | J55: =IFERROR(H55/D55,0) | K55: =SUM(K39:K52)

Sheet Socle
A1: SCENARIO | B1: PERIODE | C1: ENTITY | D1: PROGRAMME | E1: AN_ETUDE | F1: MODALITE | G1: EXERCICE | H1: VOL_LEAD | I1: VOL_CAND | J1: VOL_ADMIS | K1: VOL_NEW | L1: VOL_REINS | M1: VOL_EFF | N1: VOL_EFF_INF | O1: VOL_CLASS | P1: REV_STUD | Q1: REV_FRAIS_INS | R1: VOL_LEAD_ORG | S1: VOL_LEAD_PAY | T1: DEPENSE_ACQ | U1: DEPENSE_MARQUE | V1: TX_PASSAGE | W1: TX_LEAD_CAND | X1: TX_CAND_ADMIS | Y1: TX_YIELD_ADMIS_INSC | Z1: VOL_LEAD_TOTAL | AA1: PART_ORG | AB1: CPL | AC1: CA
A2: 2027BUD_V1 | B2: 12 | C2: MBWAY_PAR | D2: BAC_MGT | E2: B1 | F2: INIT | G2: 2026 | H2: 646 | I2: 181 | J2: 130 | K2: 78 | L2: 0 | M2: 78 | N2: 0 | O2: 3 | P2: 8400 | Q2: 90 | R2: 232 | S2: 414 | T2: 22326 | U2: 21185 | V2: 0 | W2: 0.28018576 | X2: 0.71823204 | Y2: 0.6 | Z2: 646 | AA2: 0.35913313 | AB2: 53.927536 | AC2: 662220
A3: 2027BUD_V1 | B3: 12 | C3: MBWAY_PAR | D3: BAC_MGT | E3: B2 | F3: ALT | G3: 2026 | H3: 0 | I3: 0 | J3: 0 | K3: 0 | L3: 76 | M3: 76 | N3: 78 | O3: 3 | P3: 7840 | Q3: 90 | R3: 0 | S3: 0 | T3: 0 | U3: 0 | V3: 0.97435897 | W3: 0 | X3: 0 | Y3: 0 | Z3: 0 | AA3: 0 | AB3: 0 | AC3: 595840
A4: 2027BUD_V1 | B4: 12 | C4: MBWAY_PAR | D4: BAC_MGT | E4: B3 | F4: ALT | G4: 2026 | H4: 0 | I4: 0 | J4: 0 | K4: 0 | L4: 74 | M4: 74 | N4: 76 | O4: 3 | P4: 7840 | Q4: 90 | R4: 0 | S4: 0 | T4: 0 | U4: 0 | V4: 0.97368421 | W4: 0 | X4: 0 | Y4: 0 | Z4: 0 | AA4: 0 | AB4: 0 | AC4: 580160
A5: 2027BUD_V1 | B5: 12 | C5: MBWAY_PAR | D5: MAS_MGT | E5: M1 | F5: ALT | G5: 2026 | H5: 1330 | I5: 266 | J5: 186 | K5: 78 | L5: 0 | M5: 78 | N5: 0 | O5: 3 | P5: 8400 | Q5: 90 | R5: 479 | S5: 851 | T5: 45965 | U5: 43615 | V5: 0 | W5: 0.2 | X5: 0.69924812 | Y5: 0.41935484 | Z5: 1330 | AA5: 0.36015038 | AB5: 54.012926 | AC5: 662220
A6: 2027BUD_V1 | B6: 12 | C6: MBWAY_PAR | D6: MAS_MGT | E6: M2 | F6: ALT | G6: 2026 | H6: 0 | I6: 0 | J6: 0 | K6: 0 | L6: 76 | M6: 76 | N6: 78 | O6: 3 | P6: 8400 | Q6: 90 | R6: 0 | S6: 0 | T6: 0 | U6: 0 | V6: 0.97435897 | W6: 0 | X6: 0 | Y6: 0 | Z6: 0 | AA6: 0 | AB6: 0 | AC6: 638400
A7: 2027BUD_V1 | B7: 12 | C7: MBWAY_LYO | D7: BAC_MGT | E7: B1 | F7: INIT | G7: 2026 | H7: 546 | I7: 153 | J7: 110 | K7: 66 | L7: 0 | M7: 66 | N7: 0 | O7: 3 | P7: 7875 | Q7: 90 | R7: 235 | S7: 311 | T7: 13694 | U7: 21386 | V7: 0 | W7: 0.28021978 | X7: 0.71895425 | Y7: 0.6 | Z7: 546 | AA7: 0.43040293 | AB7: 44.032154 | AC7: 525690
A8: 2027BUD_V1 | B8: 12 | C8: MBWAY_LYO | D8: BAC_MGT | E8: B2 | F8: ALT | G8: 2026 | H8: 0 | I8: 0 | J8: 0 | K8: 0 | L8: 64 | M8: 64 | N8: 66 | O8: 2 | P8: 7350 | Q8: 90 | R8: 0 | S8: 0 | T8: 0 | U8: 0 | V8: 0.96969697 | W8: 0 | X8: 0 | Y8: 0 | Z8: 0 | AA8: 0 | AB8: 0 | AC8: 470400
A9: 2027BUD_V1 | B9: 12 | C9: MBWAY_LYO | D9: BAC_MGT | E9: B3 | F9: ALT | G9: 2026 | H9: 0 | I9: 0 | J9: 0 | K9: 0 | L9: 63 | M9: 63 | N9: 64 | O9: 2 | P9: 7350 | Q9: 90 | R9: 0 | S9: 0 | T9: 0 | U9: 0 | V9: 0.984375 | W9: 0 | X9: 0 | Y9: 0 | Z9: 0 | AA9: 0 | AB9: 0 | AC9: 463050
A10: 2027BUD_V1 | B10: 12 | C10: MBWAY_LYO | D10: MAS_MGT | E10: M1 | F10: ALT | G10: 2026 | H10: 1120 | I10: 224 | J10: 157 | K10: 66 | L10: 0 | M10: 66 | N10: 0 | O10: 3 | P10: 7875 | Q10: 90 | R10: 481 | S10: 639 | T10: 28089 | U10: 43869 | V10: 0 | W10: 0.2 | X10: 0.70089286 | Y10: 0.42038217 | Z10: 1120 | AA10: 0.42946429 | AB10: 43.957746 | AC10: 525690
A11: 2027BUD_V1 | B11: 12 | C11: MBWAY_LYO | D11: MAS_MGT | E11: M2 | F11: ALT | G11: 2026 | H11: 0 | I11: 0 | J11: 0 | K11: 0 | L11: 65 | M11: 65 | N11: 66 | O11: 3 | P11: 7875 | Q11: 90 | R11: 0 | S11: 0 | T11: 0 | U11: 0 | V11: 0.98484848 | W11: 0 | X11: 0 | Y11: 0 | Z11: 0 | AA11: 0 | AB11: 0 | AC11: 511875
A12: 2027BUD_V1 | B12: 12 | C12: MBWAY_NAN | D12: BAC_MGT | E12: B1 | F12: INIT | G12: 2026 | H12: 496 | I12: 139 | J12: 100 | K12: 60 | L12: 0 | M12: 60 | N12: 0 | O12: 2 | P12: 7500 | Q12: 90 | R12: 238 | S12: 258 | T12: 10317 | U12: 21708 | V12: 0 | W12: 0.28024193 | X12: 0.71942446 | Y12: 0.6 | Z12: 496 | AA12: 0.47983871 | AB12: 39.988372 | AC12: 455400
A13: 2027BUD_V1 | B13: 12 | C13: MBWAY_NAN | D13: BAC_MGT | E13: B2 | F13: ALT | G13: 2026 | H13: 0 | I13: 0 | J13: 0 | K13: 0 | L13: 58 | M13: 58 | N13: 60 | O13: 2 | P13: 7000 | Q13: 90 | R13: 0 | S13: 0 | T13: 0 | U13: 0 | V13: 0.96666667 | W13: 0 | X13: 0 | Y13: 0 | Z13: 0 | AA13: 0 | AB13: 0 | AC13: 406000
... A181: 2027BUD_V1 | B181: 12 | C181: PIGIER_LYO | D181: BAC_RH | E181: B3 | F181: ALT | G181: 2026 | H181: 0 | I181: 0 | J181: 0 | K181: 0 | L181: 44 | M181: 44 | N181: 45 | O181: 2 | P181: 7350 | Q181: 90 | R181: 0 | S181: 0 | T181: 0 | U181: 0 | V181: 0.97777778 | W181: 0 | X181: 0 | Y181: 0 | Z181: 0 | AA181: 0 | AB181: 0 | AC181: 323400

Sheet Campagne
A1: SCENARIO | B1: PERIODE | C1: ENTITY | D1: ORG_REF | E1: PAID_REF | F1: LEAD_REF | G1: SPEND_ACQ_REF | H1: SPEND_BRAND_REF | I1: PART_ORG | J1: CPL | K1: REND_ACQ | L1: CONVERSION | M1: REND_BRAND | N1: CAC_MARGINAL
A2: 2027BUD_V1 | B2: 12 | C2: MBWAY_PAR | D2: 711 | E2: 1265 | F2: 1976 | G2: 68291 | H2: 64800 | I2: 0.35981781 | J2: 53.98498 | K2: 0.46359595 | L2: 0.078947368 | M2: 0.30805412 | N2: 1475.0124
A3: 2027BUD_V1 | B3: 12 | C3: MBWAY_LYO | D3: 716 | E3: 950 | F3: 1666 | G3: 41783 | H3: 65255 | I3: 0.42977191 | J3: 43.982105 | K3: 0.50391241 | L3: 0.079231693 | M3: 0.32659376 | N3: 1101.5952
A4: 2027BUD_V1 | B4: 12 | C4: MBWAY_NAN | D4: 728 | E4: 788 | F4: 1516 | G4: 31533 | H4: 66349 | I4: 0.48021108 | J4: 40.016497 | K4: 0.52465564 | L4: 0.079155673 | M4: 0.34345059 | N4: 963.56869
A5: 2027BUD_V1 | B5: 12 | C5: MBWAY_BOR | D5: 630 | E5: 656 | F5: 1286 | G5: 24923 | H5: 57418 | I5: 0.48989113 | J5: 37.992378 | K5: 0.53845529 | L5: 0.079315708 | M5: 0.34824917 | N5: 889.58535
A6: 2027BUD_V1 | B6: 12 | C6: ISCOM_PAR | D6: 690 | E6: 1126 | F6: 1816 | G6: 60800 | H6: 62886 | I6: 0.37995595 | J6: 53.996448 | K6: 0.44208627 | L6: 0.079295154 | M6: 0.31719351 | N6: 1540.322
A7: 2027BUD_V1 | B7: 12 | C7: ISCOM_LIL | D7: 630 | E7: 630 | F7: 1260 | G7: 25220 | H7: 57418 | I7: 0.5 | J7: 40.031746 | K7: 0.51584831 | L7: 0.079302141 | M7: 0.34838058 | N7: 978.58287
A8: 2027BUD_V1 | B8: 12 | C8: ISCOM_TLS | D8: 605 | E8: 581 | F8: 1186 | G8: 22083 | H8: 55139 | I8: 0.51011804 | J8: 38.008606 | K8: 0.52180337 | L8: 0.07925801 | M8: 0.35585226 | N8: 919.03467
A9: 2027BUD_V1 | B9: 12 | C9: IPAC_NAN | D9: 306 | E9: 544 | F9: 850 | G9: 21760 | H9: 27889 | I9: 0.36 | J9: 40 | K9: 0.55908079 | L9: 0.058823529 | M9: 0.30491226 | N9: 1216.2822
A10: 2027BUD_V1 | B10: 12 | C10: IPAC_REN | D10: 265 | E10: 415 | F10: 680 | G10: 14933 | H10: 24152 | I10: 0.38970588 | J10: 35.983133 | K10: 0.58787656 | L10: 0.058823529 | M10: 0.31735415 | N10: 1040.5471
A11: 2027BUD_V1 | B11: 12 | C11: IPAC_MTP | D11: 258 | E11: 422 | F11: 680 | G11: 15178 | H11: 23514 | I11: 0.37941177 | J11: 35.966825 | K11: 0.59134489 | L11: 0.058823529 | M11: 0.31527519 | N11: 1033.9753
A12: 2027BUD_V1 | B12: 12 | C12: PIGIER_LYO | D12: 738 | E12: 832 | F12: 1570 | G12: 36612 | H12: 67261 | I12: 0.47006369 | J12: 44.004808 | K12: 0.44045026 | L12: 0.058598726 | M12: 0.34304578 | N12: 1704.9635
A13: 2027BUD_V1 | B13: 12 | C13: PIGIER_BOR | D13: 652 | E13: 578 | F13: 1230 | G13: 21968 | H13: 59423 | I13: 0.5300813 | J13: 38.00692 | K13: 0.47459663 | L13: 0.058536585 | M13: 0.35757396 | N13: 1368.0773
... A15: 2027BUD_V1 | B15: 12 | C15: TUNON_LYO | D15: 252 | E15: 428 | F15: 680 | G15: 18850 | H15: 22967 | I15: 0.37058823 | J15: 44.042056 | K15: 0.46084356 | L15: 0.058823529 | M15: 0.31798625 | N15: 1624.6618

Sheet Moteur
A1: SCENARIO | B1: VERSION | C1: PERIODE | D1: ENTITY | E1: MARQUE | F1: PROGRAMME | G1: AN_ETUDE | H1: MODALITE | I1: EXERCICE | J1: NOUVEAUX | K1: EFFECTIF | L1: PRIX | M1: CA | O1: NOUVEAUX (live) | P1: EFFECTIF (live) | Q1: PRIX (live) | R1: 🟢 CA (live) | S1: Δ CA vs Tagetik
A2: 2027BUD_V1 | B2: V01 | C2: 12 | D2: MBWAY_PAR | E2: MBWAY | F2: BAC_MGT | G2: B1 | H2: INIT | I2: 2027 | J2: 84.920594 | K2: 84.920594 | L2: 8429.232 | M2: 723458.24 | O2: =IF(D2="","",_CALC_MOTEUR!AE2) | P2: =IF(D2="","",_CALC_MOTEUR!AF2) | Q2: =IF(D2="","",_CALC_MOTEUR!AG2) | R2: =IF(D2="","",_CALC_MOTEUR!AH2) | S2: =IF(D2="","",R2-M2)
A3: 2027BUD_V1 | B3: V02 | C3: 12 | D3: MBWAY_PAR | E3: MBWAY | F3: BAC_MGT | G3: B1 | H3: INIT | I3: 2027 | J3: 95.228067 | K3: 95.228067 | L3: 8752.8 | M3: 842082.75 | O3: =IF(D3="","",_CALC_MOTEUR!AE3) | P3: =IF(D3="","",_CALC_MOTEUR!AF3) | Q3: =IF(D3="","",_CALC_MOTEUR!AG3) | R3: =IF(D3="","",_CALC_MOTEUR!AH3) | S3: =IF(D3="","",R3-M3)
A4: 2027BUD_V1 | B4: V03 | C4: 12 | D4: MBWAY_PAR | E4: MBWAY | F4: BAC_MGT | G4: B1 | H4: INIT | I4: 2027 | J4: 72.43266 | K4: 72.43266 | L4: 8601.6 | M4: 629555.71 | O4: =IF(D4="","",_CALC_MOTEUR!AE4) | P4: =IF(D4="","",_CALC_MOTEUR!AF4) | Q4: =IF(D4="","",_CALC_MOTEUR!AG4) | R4: =IF(D4="","",_CALC_MOTEUR!AH4) | S4: =IF(D4="","",R4-M4)
A5: 2027BUD_V1 | B5: V01 | C5: 12 | D5: MBWAY_PAR | E5: MBWAY | F5: BAC_MGT | G5: B2 | H5: ALT | I5: 2027 | J5: 0 | K5: 76.39 | L5: 7867.2832 | M5: 600981.76 | O5: =IF(D5="","",_CALC_MOTEUR!AE5) | P5: =IF(D5="","",_CALC_MOTEUR!AF5) | Q5: =IF(D5="","",_CALC_MOTEUR!AG5) | R5: =IF(D5="","",_CALC_MOTEUR!AH5) | S5: =IF(D5="","",R5-M5)
A6: 2027BUD_V1 | B6: V02 | C6: 12 | D6: MBWAY_PAR | E6: MBWAY | F6: BAC_MGT | G6: B2 | H6: ALT | I6: 2027 | J6: 0 | K6: 77.17 | L6: 8169.28 | M6: 630423.34 | O6: =IF(D6="","",_CALC_MOTEUR!AE6) | P6: =IF(D6="","",_CALC_MOTEUR!AF6) | Q6: =IF(D6="","",_CALC_MOTEUR!AG6) | R6: =IF(D6="","",_CALC_MOTEUR!AH6) | S6: =IF(D6="","",R6-M6)
A7: 2027BUD_V1 | B7: V03 | C7: 12 | D7: MBWAY_PAR | E7: MBWAY | F7: BAC_MGT | G7: B2 | H7: ALT | I7: 2027 | J7: 0 | K7: 75.22 | L7: 8028.16 | M7: 603878.2 | O7: =IF(D7="","",_CALC_MOTEUR!AE7) | P7: =IF(D7="","",_CALC_MOTEUR!AF7) | Q7: =IF(D7="","",_CALC_MOTEUR!AG7) | R7: =IF(D7="","",_CALC_MOTEUR!AH7) | S7: =IF(D7="","",R7-M7)
A8: 2027BUD_V1 | B8: V01 | C8: 12 | D8: MBWAY_PAR | E8: MBWAY | F8: BAC_MGT | G8: B3 | H8: ALT | I8: 2027 | J8: 0 | K8: 74.38 | L8: 7867.2832 | M8: 585168.52 | O8: =IF(D8="","",_CALC_MOTEUR!AE8) | P8: =IF(D8="","",_CALC_MOTEUR!AF8) | Q8: =IF(D8="","",_CALC_MOTEUR!AG8) | R8: =IF(D8="","",_CALC_MOTEUR!AH8) | S8: =IF(D8="","",R8-M8)
A9: 2027BUD_V1 | B9: V02 | C9: 12 | D9: MBWAY_PAR | E9: MBWAY | F9: BAC_MGT | G9: B3 | H9: ALT | I9: 2027 | J9: 0 | K9: 75.14 | L9: 8169.28 | M9: 613839.7 | O9: =IF(D9="","",_CALC_MOTEUR!AE9) | P9: =IF(D9="","",_CALC_MOTEUR!AF9) | Q9: =IF(D9="","",_CALC_MOTEUR!AG9) | R9: =IF(D9="","",_CALC_MOTEUR!AH9) | S9: =IF(D9="","",R9-M9)
A10: 2027BUD_V1 | B10: V03 | C10: 12 | D10: MBWAY_PAR | E10: MBWAY | F10: BAC_MGT | G10: B3 | H10: ALT | I10: 2027 | J10: 0 | K10: 73.24 | L10: 8028.16 | M10: 587982.44 | O10: =IF(D10="","",_CALC_MOTEUR!AE10) | P10: =IF(D10="","",_CALC_MOTEUR!AF10) | Q10: =IF(D10="","",_CALC_MOTEUR!AG10) | R10: =IF(D10="","",_CALC_MOTEUR!AH10) | S10: =IF(D10="","",R10-M10)
A11: 2027BUD_V1 | B11: V01 | C11: 12 | D11: MBWAY_PAR | E11: MBWAY | F11: MAS_MGT | G11: M1 | H11: ALT | I11: 2027 | J11: 86.701858 | K11: 86.701858 | L11: 8429.232 | M11: 738633.24 | O11: =IF(D11="","",_CALC_MOTEUR!AE11) | P11: =IF(D11="","",_CALC_MOTEUR!AF11) | Q11: =IF(D11="","",_CALC_MOTEUR!AG11) | R11: =IF(D11="","",_CALC_MOTEUR!AH11) | S11: =IF(D11="","",R11-M11)
A12: 2027BUD_V1 | B12: V02 | C12: 12 | D12: MBWAY_PAR | E12: MBWAY | F12: MAS_MGT | G12: M1 | H12: ALT | I12: 2027 | J12: 100.62514 | K12: 100.62514 | L12: 8752.8 | M12: 889808 | O12: =IF(D12="","",_CALC_MOTEUR!AE12) | P12: =IF(D12="","",_CALC_MOTEUR!AF12) | Q12: =IF(D12="","",_CALC_MOTEUR!AG12) | R12: =IF(D12="","",_CALC_MOTEUR!AH12) | S12: =IF(D12="","",R12-M12)
A13: 2027BUD_V1 | B13: V03 | C13: 12 | D13: MBWAY_PAR | E13: MBWAY | F13: MAS_MGT | G13: M1 | H13: ALT | I13: 2027 | J13: 70.836836 | K13: 70.836836 | L13: 8601.6 | M13: 615685.44 | O13: =IF(D13="","",_CALC_MOTEUR!AE13) | P13: =IF(D13="","",_CALC_MOTEUR!AF13) | Q13: =IF(D13="","",_CALC_MOTEUR!AG13) | R13: =IF(D13="","",_CALC_MOTEUR!AH13) | S13: =IF(D13="","",R13-M13)
... A181: 2027BUD_V1 | B181: V03 | C181: 12 | D181: TUNON_LYO | E181: TUNON | F181: BAC_TOU | G181: B3 | H181: ALT | I181: 2027 | J181: 0 | K181: 37.61 | L181: 7504.35 | M181: 282238.6 | O181: =IF(D181="","",_CALC_MOTEUR!AE181) | P181: =IF(D181="","",_CALC_MOTEUR!AF181) | Q181: =IF(D181="","",_CALC_MOTEUR!AG181) | R181: =IF(D181="","",_CALC_MOTEUR!AH181) | S181: =IF(D181="","",R181-M181)
O182: =IF(D182="","",_CALC_MOTEUR!AE182) | P182: =IF(D182="","",_CALC_MOTEUR!AF182) | Q182: =IF(D182="","",_CALC_MOTEUR!AG182) | R182: =IF(D182="","",_CALC_MOTEUR!AH182) | S182: =IF(D182="","",R182-M182)
O183: =IF(D183="","",_CALC_MOTEUR!AE183) | P183: =IF(D183="","",_CALC_MOTEUR!AF183) | Q183: =IF(D183="","",_CALC_MOTEUR!AG183) | R183: =IF(D183="","",_CALC_MOTEUR!AH183) | S183: =IF(D183="","",R183-M183)
O184: =IF(D184="","",_CALC_MOTEUR!AE184) | P184: =IF(D184="","",_CALC_MOTEUR!AF184) | Q184: =IF(D184="","",_CALC_MOTEUR!AG184) | R184: =IF(D184="","",_CALC_MOTEUR!AH184) | S184: =IF(D184="","",R184-M184)
O185: =IF(D185="","",_CALC_MOTEUR!AE185) | P185: =IF(D185="","",_CALC_MOTEUR!AF185) | Q185: =IF(D185="","",_CALC_MOTEUR!AG185) | R185: =IF(D185="","",_CALC_MOTEUR!AH185) | S185: =IF(D185="","",R185-M185)
O186: =IF(D186="","",_CALC_MOTEUR!AE186) | P186: =IF(D186="","",_CALC_MOTEUR!AF186) | Q186: =IF(D186="","",_CALC_MOTEUR!AG186) | R186: =IF(D186="","",_CALC_MOTEUR!AH186) | S186: =IF(D186="","",R186-M186)
O187: =IF(D187="","",_CALC_MOTEUR!AE187) | P187: =IF(D187="","",_CALC_MOTEUR!AF187) | Q187: =IF(D187="","",_CALC_MOTEUR!AG187) | R187: =IF(D187="","",_CALC_MOTEUR!AH187) | S187: =IF(D187="","",R187-M187)
O188: =IF(D188="","",_CALC_MOTEUR!AE188) | P188: =IF(D188="","",_CALC_MOTEUR!AF188) | Q188: =IF(D188="","",_CALC_MOTEUR!AG188) | R188: =IF(D188="","",_CALC_MOTEUR!AH188) | S188: =IF(D188="","",R188-M188)
O189: =IF(D189="","",_CALC_MOTEUR!AE189) | P189: =IF(D189="","",_CALC_MOTEUR!AF189) | Q189: =IF(D189="","",_CALC_MOTEUR!AG189) | R189: =IF(D189="","",_CALC_MOTEUR!AH189) | S189: =IF(D189="","",R189-M189)
O190: =IF(D190="","",_CALC_MOTEUR!AE190) | P190: =IF(D190="","",_CALC_MOTEUR!AF190) | Q190: =IF(D190="","",_CALC_MOTEUR!AG190) | R190: =IF(D190="","",_CALC_MOTEUR!AH190) | S190: =IF(D190="","",R190-M190)
O191: =IF(D191="","",_CALC_MOTEUR!AE191) | P191: =IF(D191="","",_CALC_MOTEUR!AF191) | Q191: =IF(D191="","",_CALC_MOTEUR!AG191) | R191: =IF(D191="","",_CALC_MOTEUR!AH191) | S191: =IF(D191="","",R191-M191)
O192: =IF(D192="","",_CALC_MOTEUR!AE192) | P192: =IF(D192="","",_CALC_MOTEUR!AF192) | Q192: =IF(D192="","",_CALC_MOTEUR!AG192) | R192: =IF(D192="","",_CALC_MOTEUR!AH192) | S192: =IF(D192="","",R192-M192)
O193: =IF(D193="","",_CALC_MOTEUR!AE193) | P193: =IF(D193="","",_CALC_MOTEUR!AF193) | Q193: =IF(D193="","",_CALC_MOTEUR!AG193) | R193: =IF(D193="","",_CALC_MOTEUR!AH193) | S193: =IF(D193="","",R193-M193)
... O207: =IF(D207="","",_CALC_MOTEUR!AE207) | P207: =IF(D207="","",_CALC_MOTEUR!AF207) | Q207: =IF(D207="","",_CALC_MOTEUR!AG207) | R207: =IF(D207="","",_CALC_MOTEUR!AH207) | S207: =IF(D207="","",R207-M207)

Sheet Comptabilité
A1: Entity | B1: Account | C1: EXERCICE | D1: Scenario | E1: Period | F1: Amount
A2: MBWAY_PAR | B2: 7062 | C2: 2024 | D2: 2027BUD_V1 | E2: 12 | F2: 2197935
A3: MBWAY_LYO | B3: 7062 | C3: 2024 | D3: 2027BUD_V1 | E3: 12 | F3: 1748910
A4: MBWAY_NAN | B4: 7062 | C4: 2024 | D4: 2027BUD_V1 | E4: 12 | F4: 1510769
A5: MBWAY_BOR | B5: 7062 | C5: 2024 | D5: 2027BUD_V1 | E5: 12 | F5: 1240125
A6: ISCOM_PAR | B6: 7062 | C6: 2024 | D6: 2027BUD_V1 | E6: 12 | F6: 2038946
A7: ISCOM_LIL | B7: 7062 | C7: 2024 | D7: 2027BUD_V1 | E7: 12 | F7: 1227617
A8: ISCOM_TLS | B8: 7062 | C8: 2024 | D8: 2027BUD_V1 | E8: 12 | F8: 1140192
A9: IPAC_NAN | B9: 7062 | C9: 2024 | D9: 2027BUD_V1 | E9: 12 | F9: 903346
A10: IPAC_REN | B10: 7062 | C10: 2024 | D10: 2027BUD_V1 | E10: 12 | F10: 692462
A11: IPAC_MTP | B11: 7062 | C11: 2024 | D11: 2027BUD_V1 | E11: 12 | F11: 692462
A12: TUNON_PAR | B12: 7062 | C12: 2024 | D12: 2027BUD_V1 | E12: 12 | F12: 962905
A13: TUNON_LYO | B13: 7062 | C13: 2024 | D13: 2027BUD_V1 | E13: 12 | F13: 765352
... A675: PIGIER_LYO | B675: 7062 | C675: 2026 | D675: 2027BUD_V1 | E675: 12 | F675: 1565550

Sheet PNL
A1: ENTITY | B1: ACCOUNT | C1: EXERCICE | D1: VERSION | E1: SCENARIO | F1: PERIOD | G1: AMOUNT | H1: 🟢 AMOUNT (live) | I1: Δ vs Tagetik
A2: MBWAY_PAR | B2: 7062 | C2: 2024 | D2: ACT | E2: 2027BUD_V1 | F2: 12 | G2: 2197935 | H2: =IF(PNL!A2="","",_CALC_PNL!P2) | I2: =IF(PNL!A2="","",IF(_CALC_PNL!E2=1,H2-G2,""))
A3: MBWAY_LYO | B3: 7062 | C3: 2024 | D3: ACT | E3: 2027BUD_V1 | F3: 12 | G3: 1748910 | H3: =IF(PNL!A3="","",_CALC_PNL!P3) | I3: =IF(PNL!A3="","",IF(_CALC_PNL!E3=1,H3-G3,""))
A4: MBWAY_NAN | B4: 7062 | C4: 2024 | D4: ACT | E4: 2027BUD_V1 | F4: 12 | G4: 1510769 | H4: =IF(PNL!A4="","",_CALC_PNL!P4) | I4: =IF(PNL!A4="","",IF(_CALC_PNL!E4=1,H4-G4,""))
A5: MBWAY_BOR | B5: 7062 | C5: 2024 | D5: ACT | E5: 2027BUD_V1 | F5: 12 | G5: 1240125 | H5: =IF(PNL!A5="","",_CALC_PNL!P5) | I5: =IF(PNL!A5="","",IF(_CALC_PNL!E5=1,H5-G5,""))
A6: ISCOM_PAR | B6: 7062 | C6: 2024 | D6: ACT | E6: 2027BUD_V1 | F6: 12 | G6: 2038946 | H6: =IF(PNL!A6="","",_CALC_PNL!P6) | I6: =IF(PNL!A6="","",IF(_CALC_PNL!E6=1,H6-G6,""))
A7: ISCOM_LIL | B7: 7062 | C7: 2024 | D7: ACT | E7: 2027BUD_V1 | F7: 12 | G7: 1227617 | H7: =IF(PNL!A7="","",_CALC_PNL!P7) | I7: =IF(PNL!A7="","",IF(_CALC_PNL!E7=1,H7-G7,""))
A8: ISCOM_TLS | B8: 7062 | C8: 2024 | D8: ACT | E8: 2027BUD_V1 | F8: 12 | G8: 1140192 | H8: =IF(PNL!A8="","",_CALC_PNL!P8) | I8: =IF(PNL!A8="","",IF(_CALC_PNL!E8=1,H8-G8,""))
A9: IPAC_NAN | B9: 7062 | C9: 2024 | D9: ACT | E9: 2027BUD_V1 | F9: 12 | G9: 903346 | H9: =IF(PNL!A9="","",_CALC_PNL!P9) | I9: =IF(PNL!A9="","",IF(_CALC_PNL!E9=1,H9-G9,""))
A10: IPAC_REN | B10: 7062 | C10: 2024 | D10: ACT | E10: 2027BUD_V1 | F10: 12 | G10: 692462 | H10: =IF(PNL!A10="","",_CALC_PNL!P10) | I10: =IF(PNL!A10="","",IF(_CALC_PNL!E10=1,H10-G10,""))
A11: IPAC_MTP | B11: 7062 | C11: 2024 | D11: ACT | E11: 2027BUD_V1 | F11: 12 | G11: 692462 | H11: =IF(PNL!A11="","",_CALC_PNL!P11) | I11: =IF(PNL!A11="","",IF(_CALC_PNL!E11=1,H11-G11,""))
A12: TUNON_PAR | B12: 7062 | C12: 2024 | D12: ACT | E12: 2027BUD_V1 | F12: 12 | G12: 962905 | H12: =IF(PNL!A12="","",_CALC_PNL!P12) | I12: =IF(PNL!A12="","",IF(_CALC_PNL!E12=1,H12-G12,""))
A13: TUNON_LYO | B13: 7062 | C13: 2024 | D13: ACT | E13: 2027BUD_V1 | F13: 12 | G13: 765352 | H13: =IF(PNL!A13="","",_CALC_PNL!P13) | I13: =IF(PNL!A13="","",IF(_CALC_PNL!E13=1,H13-G13,""))
... A1347: IPAC_REN | B1347: 6413 | C1347: 2027 | D1347: V03 | E1347: 2027BUD_V1 | F1347: 12 | G1347: 62869.758 | H1347: =IF(PNL!A1347="","",_CALC_PNL!P1347) | I1347: =IF(PNL!A1347="","",IF(_CALC_PNL!E1347=1,H1347-G1347,""))

Sheet _CALC_MOTEUR
A1: KENT | B1: KVER | C1: KPROG | D1: KAN | E1: KMOD | F1: KMARQ | G1: VOL_LEAD | H1: VOL_EFF_INF | I1: REV_STUD | J1: RLC | K1: RCA | L1: YLD | M1: PASSAGE | N1: IS_ENTRY | O1: ORG_REF | P1: PAID_REF | Q1: LEAD_REF | R1: REND_ACQ | S1: REND_BRAND | T1: REJOUE | U1: BUD_REF | V1: ACQ | W1: BRAND | X1: PRICE | Y1: GLC | Z1: GCV | AA1: PASS | AB1: FEE | AC1: PRICE_COEF | AD1: NOUV_CALC | AE1: NOUVEAUX | AF1: EFFECTIF | AG1: PRIX | AH1: CA | AJ1: ■ VIOLET = colonne branchee sur une saisie (cad / Pilotage / 3_Allocation) -> a recabler cote Tagetik
A2: =IF(Moteur!D2="","",Moteur!D2) | B2: =IF(Moteur!B2="","",Moteur!B2) | C2: =IF(Moteur!F2="","",Moteur!F2) | D2: =IF(Moteur!G2="","",Moteur!G2) | E2: =IF(Moteur!H2="","",Moteur!H2) | F2: =IF(Moteur!E2="","",Moteur!E2) | G2: =IF($A2="","",SUMIFS(Socle!$H$1:$H$379,Socle!$C$1:$C$379,$A2,Socle!$D$1:$D$379,$C2,Socle!$E$1:$E$379,$D2,Socle!$F$1:$F$379,$E2,Socle!$G$1:$G$379,"2026")) | H2: =IF($A2="","",SUMIFS(Socle!$N$1:$N$379,Socle!$C$1:$C$379,$A2,Socle!$D$1:$D$379,$C2,Socle!$E$1:$E$379,$D2,Socle!$F$1:$F$379,$E2,Socle!$G$1:$G$379,"2026")) | I2: =IF($A2="","",SUMIFS(Socle!$P$1:$P$379,Socle!$C$1:$C$379,$A2,Socle!$D$1:$D$379,$C2,Socle!$E$1:$E$379,$D2,Socle!$F$1:$F$379,$E2,Socle!$G$1:$G$379,"2026")) | J2: =IF($A2="","",SUMIFS(Socle!$W$1:$W$379,Socle!$C$1:$C$379,$A2,Socle!$D$1:$D$379,$C2,Socle!$E$1:$E$379,$D2,Socle!$F$1:$F$379,$E2,Socle!$G$1:$G$379,"2026")) | K2: =IF($A2="","",SUMIFS(Socle!$X$1:$X$379,Socle!$C$1:$C$379,$A2,Socle!$D$1:$D$379,$C2,Socle!$E$1:$E$379,$D2,Socle!$F$1:$F$379,$E2,Socle!$G$1:$G$379,"2026")) | L2: =IF($A2="","",SUMIFS(Socle!$Y$1:$Y$379,Socle!$C$1:$C$379,$A2,Socle!$D$1:$D$379,$C2,Socle!$E$1:$E$379,$D2,Socle!$F$1:$F$379,$E2,Socle!$G$1:$G$379,"2026")) | M2: =IF($A2="","",SUMIFS(Socle!$V$1:$V$379,Socle!$C$1:$C$379,$A2,Socle!$D$1:$D$379,$C2,Socle!$E$1:$E$379,$D2,Socle!$F$1:$F$379,$E2,Socle!$G$1:$G$379,"2026")) | N2: =IF($A2="","",IF(OR($D2="B1",$D2="M1",$D2="BTS1"),1,0)) | O2: =IF($A2="","",SUMIFS(Campagne!$D$1:$D$28,Campagne!$C$1:$C$28,$A2)) | P2: =IF($A2="","",SUMIFS(Campagne!$E$1:$E$28,Campagne!$C$1:$C$28,$A2)) | Q2: =IF($A2="","",SUMIFS(Campagne!$F$1:$F$28,Campagne!$C$1:$C$28,$A2)) | R2: =IF($A2="","",SUMIFS(Campagne!$K$1:$K$28,Campagne!$C$1:$C$28,$A2)) | S2: =IF($A2="","",SUMIFS(Campagne!$M$1:$M$28,Campagne!$C$1:$C$28,$A2)) | T2: =IF($A2="","",SUMIFS(Pilotage!$K$19:$K$32,Pilotage!$A$19:$A$32,$A2)*SUMIFS(Pilotage!$J$19:$J$32,Pilotage!$A$19:$A$32,$A2)*(SUM(Pilotage!$K$19:$K$32)/SUMPRODUCT(Pilotage!$K$19:$K$32,Pilotage!$J$19:$J$32))) | U2: =IF($A2="","",SUMIFS(Pilotage!$K$19:$K$32,Pilotage!$A$19:$A$32,$A2)) | V2: =IF($A2="","",IF($B2="V01",Cadrage!$C$22,IF($B2="V02",Cadrage!$D$22,Cadrage!$E$22))) | W2: =IF($A2="","",IF($B2="V01",Cadrage!$C$23,IF($B2="V02",Cadrage!$D$23,Cadrage!$E$23))) | X2: =IF($A2="","",IF($B2="V01",Cadrage!$C$24,IF($B2="V02",Cadrage!$D$24,Cadrage!$E$24))) | Y2: =IF($A2="","",IF($B2="V01",Cadrage!$C$25,IF($B2="V02",Cadrage!$D$25,Cadrage!$E$25))) | Z2: =IF($A2="","",IF($B2="V01",Cadrage!$C$26,IF($B2="V02",Cadrage!$D$26,Cadrage!$E$26))) | AA2: =IF($A2="","",IF($B2="V01",Cadrage!$C$27,IF($B2="V02",Cadrage!$D$27,Cadrage!$E$27))) | AB2: =IF($A2="","",IF($B2="V01",Cadrage!$C$39,IF($B2="V02",Cadrage!$D$39,Cadrage!$E$39))) | AC2: =IF($A2="","",IF($F2="MBWAY",Cadrage!$K$11,IF($F2="ISCOM",Cadrage!$K$12,IF($F2="IPAC",Cadrage!$K$13,IF($F2="PIGIER",Cadrage!$K$14,Cadrage!$K$15))))) | AD2: =IF($A2="","",($O2*(1+$W2)^$S2+$P2*IFERROR((($T2/$U2)*(1+$V2))^$R2,0))*IFERROR($G2/$Q2,0)*($J2+$Y2)*$K2*($L2+$Z2)) | AE2: =IF($A2="","",IF($N2=1,$AD2,0)) | AF2: =IF($A2="","",IF($N2=1,$AD2,$H2*($M2+$AA2))) | AG2: =IF($A2="","",$I2*(1+$X2*$AC2)) | AH2: =IF($A2="","",$AF2*$AG2+$AE2*$AB2)
A3: =IF(Moteur!D3="","",Moteur!D3) | B3: =IF(Moteur!B3="","",Moteur!B3) | C3: =IF(Moteur!F3="","",Moteur!F3) | D3: =IF(Moteur!G3="","",Moteur!G3) | E3: =IF(Moteur!H3="","",Moteur!H3) | F3: =IF(Moteur!E3="","",Moteur!E3) | G3: =IF($A3="","",SUMIFS(Socle!$H$1:$H$379,Socle!$C$1:$C$379,$A3,Socle!$D$1:$D$379,$C3,Socle!$E$1:$E$379,$D3,Socle!$F$1:$F$379,$E3,Socle!$G$1:$G$379,"2026")) | H3: =IF($A3="","",SUMIFS(Socle!$N$1:$N$379,Socle!$C$1:$C$379,$A3,Socle!$D$1:$D$379,$C3,Socle!$E$1:$E$379,$D3,Socle!$F$1:$F$379,$E3,Socle!$G$1:$G$379,"2026")) | I3: =IF($A3="","",SUMIFS(Socle!$P$1:$P$379,Socle!$C$1:$C$379,$A3,Socle!$D$1:$D$379,$C3,Socle!$E$1:$E$379,$D3,Socle!$F$1:$F$379,$E3,Socle!$G$1:$G$379,"2026")) | J3: =IF($A3="","",SUMIFS(Socle!$W$1:$W$379,Socle!$C$1:$C$379,$A3,Socle!$D$1:$D$379,$C3,Socle!$E$1:$E$379,$D3,Socle!$F$1:$F$379,$E3,Socle!$G$1:$G$379,"2026")) | K3: =IF($A3="","",SUMIFS(Socle!$X$1:$X$379,Socle!$C$1:$C$379,$A3,Socle!$D$1:$D$379,$C3,Socle!$E$1:$E$379,$D3,Socle!$F$1:$F$379,$E3,Socle!$G$1:$G$379,"2026")) | L3: =IF($A3="","",SUMIFS(Socle!$Y$1:$Y$379,Socle!$C$1:$C$379,$A3,Socle!$D$1:$D$379,$C3,Socle!$E$1:$E$379,$D3,Socle!$F$1:$F$379,$E3,Socle!$G$1:$G$379,"2026")) | M3: =IF($A3="","",SUMIFS(Socle!$V$1:$V$379,Socle!$C$1:$C$379,$A3,Socle!$D$1:$D$379,$C3,Socle!$E$1:$E$379,$D3,Socle!$F$1:$F$379,$E3,Socle!$G$1:$G$379,"2026")) | N3: =IF($A3="","",IF(OR($D3="B1",$D3="M1",$D3="BTS1"),1,0)) | O3: =IF($A3="","",SUMIFS(Campagne!$D$1:$D$28,Campagne!$C$1:$C$28,$A3)) | P3: =IF($A3="","",SUMIFS(Campagne!$E$1:$E$28,Campagne!$C$1:$C$28,$A3)) | Q3: =IF($A3="","",SUMIFS(Campagne!$F$1:$F$28,Campagne!$C$1:$C$28,$A3)) | R3: =IF($A3="","",SUMIFS(Campagne!$K$1:$K$28,Campagne!$C$1:$C$28,$A3)) | S3: =IF($A3="","",SUMIFS(Campagne!$M$1:$M$28,Campagne!$C$1:$C$28,$A3)) | T3: =IF($A3="","",SUMIFS(Pilotage!$K$19:$K$32,Pilotage!$A$19:$A$32,$A3)*SUMIFS(Pilotage!$J$19:$J$32,Pilotage!$A$19:$A$32,$A3)*(SUM(Pilotage!$K$19:$K$32)/SUMPRODUCT(Pilotage!$K$19:$K$32,Pilotage!$J$19:$J$32))) | U3: =IF($A3="","",SUMIFS(Pilotage!$K$19:$K$32,Pilotage!$A$19:$A$32,$A3)) | V3: =IF($A3="","",IF($B3="V01",Cadrage!$C$22,IF($B3="V02",Cadrage!$D$22,Cadrage!$E$22))) | W3: =IF($A3="","",IF($B3="V01",Cadrage!$C$23,IF($B3="V02",Cadrage!$D$23,Cadrage!$E$23))) | X3: =IF($A3="","",IF($B3="V01",Cadrage!$C$24,IF($B3="V02",Cadrage!$D$24,Cadrage!$E$24))) | Y3: =IF($A3="","",IF($B3="V01",Cadrage!$C$25,IF($B3="V02",Cadrage!$D$25,Cadrage!$E$25))) | Z3: =IF($A3="","",IF($B3="V01",Cadrage!$C$26,IF($B3="V02",Cadrage!$D$26,Cadrage!$E$26))) | AA3: =IF($A3="","",IF($B3="V01",Cadrage!$C$27,IF($B3="V02",Cadrage!$D$27,Cadrage!$E$27))) | AB3: =IF($A3="","",IF($B3="V01",Cadrage!$C$39,IF($B3="V02",Cadrage!$D$39,Cadrage!$E$39))) | AC3: =IF($A3="","",IF($F3="MBWAY",Cadrage!$K$11,IF($F3="ISCOM",Cadrage!$K$12,IF($F3="IPAC",Cadrage!$K$13,IF($F3="PIGIER",Cadrage!$K$14,Cadrage!$K$15))))) | AD3: =IF($A3="","",($O3*(1+$W3)^$S3+$P3*IFERROR((($T3/$U3)*(1+$V3))^$R3,0))*IFERROR($G3/$Q3,0)*($J3+$Y3)*$K3*($L3+$Z3)) | AE3: =IF($A3="","",IF($N3=1,$AD3,0)) | AF3: =IF($A3="","",IF($N3=1,$AD3,$H3*($M3+$AA3))) | AG3: =IF($A3="","",$I3*(1+$X3*$AC3)) | AH3: =IF($A3="","",$AF3*$AG3+$AE3*$AB3)
A4: =IF(Moteur!D4="","",Moteur!D4) | B4: =IF(Moteur!B4="","",Moteur!B4) | C4: =IF(Moteur!F4="","",Moteur!F4) | D4: =IF(Moteur!G4="","",Moteur!G4) | E4: =IF(Moteur!H4="","",Moteur!H4) | F4: =IF(Moteur!E4="","",Moteur!E4) | G4: =IF($A4="","",SUMIFS(Socle!$H$1:$H$379,Socle!$C$1:$C$379,$A4,Socle!$D$1:$D$379,$C4,Socle!$E$1:$E$379,$D4,Socle!$F$1:$F$379,$E4,Socle!$G$1:$G$379,"2026")) | H4: =IF($A4="","",SUMIFS(Socle!$N$1:$N$379,Socle!$C$1:$C$379,$A4,Socle!$D$1:$D$379,$C4,Socle!$E$1:$E$379,$D4,Socle!$F$1:$F$379,$E4,Socle!$G$1:$G$379,"2026")) | I4: =IF($A4="","",SUMIFS(Socle!$P$1:$P$379,Socle!$C$1:$C$379,$A4,Socle!$D$1:$D$379,$C4,Socle!$E$1:$E$379,$D4,Socle!$F$1:$F$379,$E4,Socle!$G$1:$G$379,"2026")) | J4: =IF($A4="","",SUMIFS(Socle!$W$1:$W$379,Socle!$C$1:$C$379,$A4,Socle!$D$1:$D$379,$C4,Socle!$E$1:$E$379,$D4,Socle!$F$1:$F$379,$E4,Socle!$G$1:$G$379,"2026")) | K4: =IF($A4="","",SUMIFS(Socle!$X$1:$X$379,Socle!$C$1:$C$379,$A4,Socle!$D$1:$D$379,$C4,Socle!$E$1:$E$379,$D4,Socle!$F$1:$F$379,$E4,Socle!$G$1:$G$379,"2026")) | L4: =IF($A4="","",SUMIFS(Socle!$Y$1:$Y$379,Socle!$C$1:$C$379,$A4,Socle!$D$1:$D$379,$C4,Socle!$E$1:$E$379,$D4,Socle!$F$1:$F$379,$E4,Socle!$G$1:$G$379,"2026")) | M4: =IF($A4="","",SUMIFS(Socle!$V$1:$V$379,Socle!$C$1:$C$379,$A4,Socle!$D$1:$D$379,$C4,Socle!$E$1:$E$379,$D4,Socle!$F$1:$F$379,$E4,Socle!$G$1:$G$379,"2026")) | N4: =IF($A4="","",IF(OR($D4="B1",$D4="M1",$D4="BTS1"),1,0)) | O4: =IF($A4="","",SUMIFS(Campagne!$D$1:$D$28,Campagne!$C$1:$C$28,$A4)) | P4: =IF($A4="","",SUMIFS(Campagne!$E$1:$E$28,Campagne!$C$1:$C$28,$A4)) | Q4: =IF($A4="","",SUMIFS(Campagne!$F$1:$F$28,Campagne!$C$1:$C$28,$A4)) | R4: =IF($A4="","",SUMIFS(Campagne!$K$1:$K$28,Campagne!$C$1:$C$28,$A4)) | S4: =IF($A4="","",SUMIFS(Campagne!$M$1:$M$28,Campagne!$C$1:$C$28,$A4)) | T4: =IF($A4="","",SUMIFS(Pilotage!$K$19:$K$32,Pilotage!$A$19:$A$32,$A4)*SUMIFS(Pilotage!$J$19:$J$32,Pilotage!$A$19:$A$32,$A4)*(SUM(Pilotage!$K$19:$K$32)/SUMPRODUCT(Pilotage!$K$19:$K$32,Pilotage!$J$19:$J$32))) | U4: =IF($A4="","",SUMIFS(Pilotage!$K$19:$K$32,Pilotage!$A$19:$A$32,$A4)) | V4: =IF($A4="","",IF($B4="V01",Cadrage!$C$22,IF($B4="V02",Cadrage!$D$22,Cadrage!$E$22))) | W4: =IF($A4="","",IF($B4="V01",Cadrage!$C$23,IF($B4="V02",Cadrage!$D$23,Cadrage!$E$23))) | X4: =IF($A4="","",IF($B4="V01",Cadrage!$C$24,IF($B4="V02",Cadrage!$D$24,Cadrage!$E$24))) | Y4: =IF($A4="","",IF($B4="V01",Cadrage!$C$25,IF($B4="V02",Cadrage!$D$25,Cadrage!$E$25))) | Z4: =IF($A4="","",IF($B4="V01",Cadrage!$C$26,IF($B4="V02",Cadrage!$D$26,Cadrage!$E$26))) | AA4: =IF($A4="","",IF($B4="V01",Cadrage!$C$27,IF($B4="V02",Cadrage!$D$27,Cadrage!$E$27))) | AB4: =IF($A4="","",IF($B4="V01",Cadrage!$C$39,IF($B4="V02",Cadrage!$D$39,Cadrage!$E$39))) | AC4: =IF($A4="","",IF($F4="MBWAY",Cadrage!$K$11,IF($F4="ISCOM",Cadrage!$K$12,IF($F4="IPAC",Cadrage!$K$13,IF($F4="PIGIER",Cadrage!$K$14,Cadrage!$K$15))))) | AD4: =IF($A4="","",($O4*(1+$W4)^$S4+$P4*IFERROR((($T4/$U4)*(1+$V4))^$R4,0))*IFERROR($G4/$Q4,0)*($J4+$Y4)*$K4*($L4+$Z4)) | AE4: =IF($A4="","",IF($N4=1,$AD4,0)) | AF4: =IF($A4="","",IF($N4=1,$AD4,$H4*($M4+$AA4))) | AG4: =IF($A4="","",$I4*(1+$X4*$AC4)) | AH4: =IF($A4="","",$AF4*$AG4+$AE4*$AB4)
A5: =IF(Moteur!D5="","",Moteur!D5) | B5: =IF(Moteur!B5="","",Moteur!B5) | C5: =IF(Moteur!F5="","",Moteur!F5) | D5: =IF(Moteur!G5="","",Moteur!G5) | E5: =IF(Moteur!H5="","",Moteur!H5) | F5: =IF(Moteur!E5="","",Moteur!E5) | G5: =IF($A5="","",SUMIFS(Socle!$H$1:$H$379,Socle!$C$1:$C$379,$A5,Socle!$D$1:$D$379,$C5,Socle!$E$1:$E$379,$D5,Socle!$F$1:$F$379,$E5,Socle!$G$1:$G$379,"2026")) | H5: =IF($A5="","",SUMIFS(Socle!$N$1:$N$379,Socle!$C$1:$C$379,$A5,Socle!$D$1:$D$379,$C5,Socle!$E$1:$E$379,$D5,Socle!$F$1:$F$379,$E5,Socle!$G$1:$G$379,"2026")) | I5: =IF($A5="","",SUMIFS(Socle!$P$1:$P$379,Socle!$C$1:$C$379,$A5,Socle!$D$1:$D$379,$C5,Socle!$E$1:$E$379,$D5,Socle!$F$1:$F$379,$E5,Socle!$G$1:$G$379,"2026")) | J5: =IF($A5="","",SUMIFS(Socle!$W$1:$W$379,Socle!$C$1:$C$379,$A5,Socle!$D$1:$D$379,$C5,Socle!$E$1:$E$379,$D5,Socle!$F$1:$F$379,$E5,Socle!$G$1:$G$379,"2026")) | K5: =IF($A5="","",SUMIFS(Socle!$X$1:$X$379,Socle!$C$1:$C$379,$A5,Socle!$D$1:$D$379,$C5,Socle!$E$1:$E$379,$D5,Socle!$F$1:$F$379,$E5,Socle!$G$1:$G$379,"2026")) | L5: =IF($A5="","",SUMIFS(Socle!$Y$1:$Y$379,Socle!$C$1:$C$379,$A5,Socle!$D$1:$D$379,$C5,Socle!$E$1:$E$379,$D5,Socle!$F$1:$F$379,$E5,Socle!$G$1:$G$379,"2026")) | M5: =IF($A5="","",SUMIFS(Socle!$V$1:$V$379,Socle!$C$1:$C$379,$A5,Socle!$D$1:$D$379,$C5,Socle!$E$1:$E$379,$D5,Socle!$F$1:$F$379,$E5,Socle!$G$1:$G$379,"2026")) | N5: =IF($A5="","",IF(OR($D5="B1",$D5="M1",$D5="BTS1"),1,0)) | O5: =IF($A5="","",SUMIFS(Campagne!$D$1:$D$28,Campagne!$C$1:$C$28,$A5)) | P5: =IF($A5="","",SUMIFS(Campagne!$E$1:$E$28,Campagne!$C$1:$C$28,$A5)) | Q5: =IF($A5="","",SUMIFS(Campagne!$F$1:$F$28,Campagne!$C$1:$C$28,$A5)) | R5: =IF($A5="","",SUMIFS(Campagne!$K$1:$K$28,Campagne!$C$1:$C$28,$A5)) | S5: =IF($A5="","",SUMIFS(Campagne!$M$1:$M$28,Campagne!$C$1:$C$28,$A5)) | T5: =IF($A5="","",SUMIFS(Pilotage!$K$19:$K$32,Pilotage!$A$19:$A$32,$A5)*SUMIFS(Pilotage!$J$19:$J$32,Pilotage!$A$19:$A$32,$A5)*(SUM(Pilotage!$K$19:$K$32)/SUMPRODUCT(Pilotage!$K$19:$K$32,Pilotage!$J$19:$J$32))) | U5: =IF($A5="","",SUMIFS(Pilotage!$K$19:$K$32,Pilotage!$A$19:$A$32,$A5)) | V5: =IF($A5="","",IF($B5="V01",Cadrage!$C$22,IF($B5="V02",Cadrage!$D$22,Cadrage!$E$22))) | W5: =IF($A5="","",IF($B5="V01",Cadrage!$C$23,IF($B5="V02",Cadrage!$D$23,Cadrage!$E$23))) | X5: =IF($A5="","",IF($B5="V01",Cadrage!$C$24,IF($B5="V02",Cadrage!$D$24,Cadrage!$E$24))) | Y5: =IF($A5="","",IF($B5="V01",Cadrage!$C$25,IF($B5="V02",Cadrage!$D$25,Cadrage!$E$25))) | Z5: =IF($A5="","",IF($B5="V01",Cadrage!$C$26,IF($B5="V02",Cadrage!$D$26,Cadrage!$E$26))) | AA5: =IF($A5="","",IF($B5="V01",Cadrage!$C$27,IF($B5="V02",Cadrage!$D$27,Cadrage!$E$27))) | AB5: =IF($A5="","",IF($B5="V01",Cadrage!$C$39,IF($B5="V02",Cadrage!$D$39,Cadrage!$E$39))) | AC5: =IF($A5="","",IF($F5="MBWAY",Cadrage!$K$11,IF($F5="ISCOM",Cadrage!$K$12,IF($F5="IPAC",Cadrage!$K$13,IF($F5="PIGIER",Cadrage!$K$14,Cadrage!$K$15))))) | AD5: =IF($A5="","",($O5*(1+$W5)^$S5+$P5*IFERROR((($T5/$U5)*(1+$V5))^$R5,0))*IFERROR($G5/$Q5,0)*($J5+$Y5)*$K5*($L5+$Z5)) | AE5: =IF($A5="","",IF($N5=1,$AD5,0)) | AF5: =IF($A5="","",IF($N5=1,$AD5,$H5*($M5+$AA5))) | AG5: =IF($A5="","",$I5*(1+$X5*$AC5)) | AH5: =IF($A5="","",$AF5*$AG5+$AE5*$AB5)
A6: =IF(Moteur!D6="","",Moteur!D6) | B6: =IF(Moteur!B6="","",Moteur!B6) | C6: =IF(Moteur!F6="","",Moteur!F6) | D6: =IF(Moteur!G6="","",Moteur!G6) | E6: =IF(Moteur!H6="","",Moteur!H6) | F6: =IF(Moteur!E6="","",Moteur!E6) | G6: =IF($A6="","",SUMIFS(Socle!$H$1:$H$379,Socle!$C$1:$C$379,$A6,Socle!$D$1:$D$379,$C6,Socle!$E$1:$E$379,$D6,Socle!$F$1:$F$379,$E6,Socle!$G$1:$G$379,"2026")) | H6: =IF($A6="","",SUMIFS(Socle!$N$1:$N$379,Socle!$C$1:$C$379,$A6,Socle!$D$1:$D$379,$C6,Socle!$E$1:$E$379,$D6,Socle!$F$1:$F$379,$E6,Socle!$G$1:$G$379,"2026")) | I6: =IF($A6="","",SUMIFS(Socle!$P$1:$P$379,Socle!$C$1:$C$379,$A6,Socle!$D$1:$D$379,$C6,Socle!$E$1:$E$379,$D6,Socle!$F$1:$F$379,$E6,Socle!$G$1:$G$379,"2026")) | J6: =IF($A6="","",SUMIFS(Socle!$W$1:$W$379,Socle!$C$1:$C$379,$A6,Socle!$D$1:$D$379,$C6,Socle!$E$1:$E$379,$D6,Socle!$F$1:$F$379,$E6,Socle!$G$1:$G$379,"2026")) | K6: =IF($A6="","",SUMIFS(Socle!$X$1:$X$379,Socle!$C$1:$C$379,$A6,Socle!$D$1:$D$379,$C6,Socle!$E$1:$E$379,$D6,Socle!$F$1:$F$379,$E6,Socle!$G$1:$G$379,"2026")) | L6: =IF($A6="","",SUMIFS(Socle!$Y$1:$Y$379,Socle!$C$1:$C$379,$A6,Socle!$D$1:$D$379,$C6,Socle!$E$1:$E$379,$D6,Socle!$F$1:$F$379,$E6,Socle!$G$1:$G$379,"2026")) | M6: =IF($A6="","",SUMIFS(Socle!$V$1:$V$379,Socle!$C$1:$C$379,$A6,Socle!$D$1:$D$379,$C6,Socle!$E$1:$E$379,$D6,Socle!$F$1:$F$379,$E6,Socle!$G$1:$G$379,"2026")) | N6: =IF($A6="","",IF(OR($D6="B1",$D6="M1",$D6="BTS1"),1,0)) | O6: =IF($A6="","",SUMIFS(Campagne!$D$1:$D$28,Campagne!$C$1:$C$28,$A6)) | P6: =IF($A6="","",SUMIFS(Campagne!$E$1:$E$28,Campagne!$C$1:$C$28,$A6)) | Q6: =IF($A6="","",SUMIFS(Campagne!$F$1:$F$28,Campagne!$C$1:$C$28,$A6)) | R6: =IF($A6="","",SUMIFS(Campagne!$K$1:$K$28,Campagne!$C$1:$C$28,$A6)) | S6: =IF($A6="","",SUMIFS(Campagne!$M$1:$M$28,Campagne!$C$1:$C$28,$A6)) | T6: =IF($A6="","",SUMIFS(Pilotage!$K$19:$K$32,Pilotage!$A$19:$A$32,$A6)*SUMIFS(Pilotage!$J$19:$J$32,Pilotage!$A$19:$A$32,$A6)*(SUM(Pilotage!$K$19:$K$32)/SUMPRODUCT(Pilotage!$K$19:$K$32,Pilotage!$J$19:$J$32))) | U6: =IF($A6="","",SUMIFS(Pilotage!$K$19:$K$32,Pilotage!$A$19:$A$32,$A6)) | V6: =IF($A6="","",IF($B6="V01",Cadrage!$C$22,IF($B6="V02",Cadrage!$D$22,Cadrage!$E$22))) | W6: =IF($A6="","",IF($B6="V01",Cadrage!$C$23,IF($B6="V02",Cadrage!$D$23,Cadrage!$E$23))) | X6: =IF($A6="","",IF($B6="V01",Cadrage!$C$24,IF($B6="V02",Cadrage!$D$24,Cadrage!$E$24))) | Y6: =IF($A6="","",IF($B6="V01",Cadrage!$C$25,IF($B6="V02",Cadrage!$D$25,Cadrage!$E$25))) | Z6: =IF($A6="","",IF($B6="V01",Cadrage!$C$26,IF($B6="V02",Cadrage!$D$26,Cadrage!$E$26))) | AA6: =IF($A6="","",IF($B6="V01",Cadrage!$C$27,IF($B6="V02",Cadrage!$D$27,Cadrage!$E$27))) | AB6: =IF($A6="","",IF($B6="V01",Cadrage!$C$39,IF($B6="V02",Cadrage!$D$39,Cadrage!$E$39))) | AC6: =IF($A6="","",IF($F6="MBWAY",Cadrage!$K$11,IF($F6="ISCOM",Cadrage!$K$12,IF($F6="IPAC",Cadrage!$K$13,IF($F6="PIGIER",Cadrage!$K$14,Cadrage!$K$15))))) | AD6: =IF($A6="","",($O6*(1+$W6)^$S6+$P6*IFERROR((($T6/$U6)*(1+$V6))^$R6,0))*IFERROR($G6/$Q6,0)*($J6+$Y6)*$K6*($L6+$Z6)) | AE6: =IF($A6="","",IF($N6=1,$AD6,0)) | AF6: =IF($A6="","",IF($N6=1,$AD6,$H6*($M6+$AA6))) | AG6: =IF($A6="","",$I6*(1+$X6*$AC6)) | AH6: =IF($A6="","",$AF6*$AG6+$AE6*$AB6)
A7: =IF(Moteur!D7="","",Moteur!D7) | B7: =IF(Moteur!B7="","",Moteur!B7) | C7: =IF(Moteur!F7="","",Moteur!F7) | D7: =IF(Moteur!G7="","",Moteur!G7) | E7: =IF(Moteur!H7="","",Moteur!H7) | F7: =IF(Moteur!E7="","",Moteur!E7) | G7: =IF($A7="","",SUMIFS(Socle!$H$1:$H$379,Socle!$C$1:$C$379,$A7,Socle!$D$1:$D$379,$C7,Socle!$E$1:$E$379,$D7,Socle!$F$1:$F$379,$E7,Socle!$G$1:$G$379,"2026")) | H7: =IF($A7="","",SUMIFS(Socle!$N$1:$N$379,Socle!$C$1:$C$379,$A7,Socle!$D$1:$D$379,$C7,Socle!$E$1:$E$379,$D7,Socle!$F$1:$F$379,$E7,Socle!$G$1:$G$379,"2026")) | I7: =IF($A7="","",SUMIFS(Socle!$P$1:$P$379,Socle!$C$1:$C$379,$A7,Socle!$D$1:$D$379,$C7,Socle!$E$1:$E$379,$D7,Socle!$F$1:$F$379,$E7,Socle!$G$1:$G$379,"2026")) | J7: =IF($A7="","",SUMIFS(Socle!$W$1:$W$379,Socle!$C$1:$C$379,$A7,Socle!$D$1:$D$379,$C7,Socle!$E$1:$E$379,$D7,Socle!$F$1:$F$379,$E7,Socle!$G$1:$G$379,"2026")) | K7: =IF($A7="","",SUMIFS(Socle!$X$1:$X$379,Socle!$C$1:$C$379,$A7,Socle!$D$1:$D$379,$C7,Socle!$E$1:$E$379,$D7,Socle!$F$1:$F$379,$E7,Socle!$G$1:$G$379,"2026")) | L7: =IF($A7="","",SUMIFS(Socle!$Y$1:$Y$379,Socle!$C$1:$C$379,$A7,Socle!$D$1:$D$379,$C7,Socle!$E$1:$E$379,$D7,Socle!$F$1:$F$379,$E7,Socle!$G$1:$G$379,"2026")) | M7: =IF($A7="","",SUMIFS(Socle!$V$1:$V$379,Socle!$C$1:$C$379,$A7,Socle!$D$1:$D$379,$C7,Socle!$E$1:$E$379,$D7,Socle!$F$1:$F$379,$E7,Socle!$G$1:$G$379,"2026")) | N7: =IF($A7="","",IF(OR($D7="B1",$D7="M1",$D7="BTS1"),1,0)) | O7: =IF($A7="","",SUMIFS(Campagne!$D$1:$D$28,Campagne!$C$1:$C$28,$A7)) | P7: =IF($A7="","",SUMIFS(Campagne!$E$1:$E$28,Campagne!$C$1:$C$28,$A7)) | Q7: =IF($A7="","",SUMIFS(Campagne!$F$1:$F$28,Campagne!$C$1:$C$28,$A7)) | R7: =IF($A7="","",SUMIFS(Campagne!$K$1:$K$28,Campagne!$C$1:$C$28,$A7)) | S7: =IF($A7="","",SUMIFS(Campagne!$M$1:$M$28,Campagne!$C$1:$C$28,$A7)) | T7: =IF($A7="","",SUMIFS(Pilotage!$K$19:$K$32,Pilotage!$A$19:$A$32,$A7)*SUMIFS(Pilotage!$J$19:$J$32,Pilotage!$A$19:$A$32,$A7)*(SUM(Pilotage!$K$19:$K$32)/SUMPRODUCT(Pilotage!$K$19:$K$32,Pilotage!$J$19:$J$32))) | U7: =IF($A7="","",SUMIFS(Pilotage!$K$19:$K$32,Pilotage!$A$19:$A$32,$A7)) | V7: =IF($A7="","",IF($B7="V01",Cadrage!$C$22,IF($B7="V02",Cadrage!$D$22,Cadrage!$E$22))) | W7: =IF($A7="","",IF($B7="V01",Cadrage!$C$23,IF($B7="V02",Cadrage!$D$23,Cadrage!$E$23))) | X7: =IF($A7="","",IF($B7="V01",Cadrage!$C$24,IF($B7="V02",Cadrage!$D$24,Cadrage!$E$24))) | Y7: =IF($A7="","",IF($B7="V01",Cadrage!$C$25,IF($B7="V02",Cadrage!$D$25,Cadrage!$E$25))) | Z7: =IF($A7="","",IF($B7="V01",Cadrage!$C$26,IF($B7="V02",Cadrage!$D$26,Cadrage!$E$26))) | AA7: =IF($A7="","",IF($B7="V01",Cadrage!$C$27,IF($B7="V02",Cadrage!$D$27,Cadrage!$E$27))) | AB7: =IF($A7="","",IF($B7="V01",Cadrage!$C$39,IF($B7="V02",Cadrage!$D$39,Cadrage!$E$39))) | AC7: =IF($A7="","",IF($F7="MBWAY",Cadrage!$K$11,IF($F7="ISCOM",Cadrage!$K$12,IF($F7="IPAC",Cadrage!$K$13,IF($F7="PIGIER",Cadrage!$K$14,Cadrage!$K$15))))) | AD7: =IF($A7="","",($O7*(1+$W7)^$S7+$P7*IFERROR((($T7/$U7)*(1+$V7))^$R7,0))*IFERROR($G7/$Q7,0)*($J7+$Y7)*$K7*($L7+$Z7)) | AE7: =IF($A7="","",IF($N7=1,$AD7,0)) | AF7: =IF($A7="","",IF($N7=1,$AD7,$H7*($M7+$AA7))) | AG7: =IF($A7="","",$I7*(1+$X7*$AC7)) | AH7: =IF($A7="","",$AF7*$AG7+$AE7*$AB7)
A8: =IF(Moteur!D8="","",Moteur!D8) | B8: =IF(Moteur!B8="","",Moteur!B8) | C8: =IF(Moteur!F8="","",Moteur!F8) | D8: =IF(Moteur!G8="","",Moteur!G8) | E8: =IF(Moteur!H8="","",Moteur!H8) | F8: =IF(Moteur!E8="","",Moteur!E8) | G8: =IF($A8="","",SUMIFS(Socle!$H$1:$H$379,Socle!$C$1:$C$379,$A8,Socle!$D$1:$D$379,$C8,Socle!$E$1:$E$379,$D8,Socle!$F$1:$F$379,$E8,Socle!$G$1:$G$379,"2026")) | H8: =IF($A8="","",SUMIFS(Socle!$N$1:$N$379,Socle!$C$1:$C$379,$A8,Socle!$D$1:$D$379,$C8,Socle!$E$1:$E$379,$D8,Socle!$F$1:$F$379,$E8,Socle!$G$1:$G$379,"2026")) | I8: =IF($A8="","",SUMIFS(Socle!$P$1:$P$379,Socle!$C$1:$C$379,$A8,Socle!$D$1:$D$379,$C8,Socle!$E$1:$E$379,$D8,Socle!$F$1:$F$379,$E8,Socle!$G$1:$G$379,"2026")) | J8: =IF($A8="","",SUMIFS(Socle!$W$1:$W$379,Socle!$C$1:$C$379,$A8,Socle!$D$1:$D$379,$C8,Socle!$E$1:$E$379,$D8,Socle!$F$1:$F$379,$E8,Socle!$G$1:$G$379,"2026")) | K8: =IF($A8="","",SUMIFS(Socle!$X$1:$X$379,Socle!$C$1:$C$379,$A8,Socle!$D$1:$D$379,$C8,Socle!$E$1:$E$379,$D8,Socle!$F$1:$F$379,$E8,Socle!$G$1:$G$379,"2026")) | L8: =IF($A8="","",SUMIFS(Socle!$Y$1:$Y$379,Socle!$C$1:$C$379,$A8,Socle!$D$1:$D$379,$C8,Socle!$E$1:$E$379,$D8,Socle!$F$1:$F$379,$E8,Socle!$G$1:$G$379,"2026")) | M8: =IF($A8="","",SUMIFS(Socle!$V$1:$V$379,Socle!$C$1:$C$379,$A8,Socle!$D$1:$D$379,$C8,Socle!$E$1:$E$379,$D8,Socle!$F$1:$F$379,$E8,Socle!$G$1:$G$379,"2026")) | N8: =IF($A8="","",IF(OR($D8="B1",$D8="M1",$D8="BTS1"),1,0)) | O8: =IF($A8="","",SUMIFS(Campagne!$D$1:$D$28,Campagne!$C$1:$C$28,$A8)) | P8: =IF($A8="","",SUMIFS(Campagne!$E$1:$E$28,Campagne!$C$1:$C$28,$A8)) | Q8: =IF($A8="","",SUMIFS(Campagne!$F$1:$F$28,Campagne!$C$1:$C$28,$A8)) | R8: =IF($A8="","",SUMIFS(Campagne!$K$1:$K$28,Campagne!$C$1:$C$28,$A8)) | S8: =IF($A8="","",SUMIFS(Campagne!$M$1:$M$28,Campagne!$C$1:$C$28,$A8)) | T8: =IF($A8="","",SUMIFS(Pilotage!$K$19:$K$32,Pilotage!$A$19:$A$32,$A8)*SUMIFS(Pilotage!$J$19:$J$32,Pilotage!$A$19:$A$32,$A8)*(SUM(Pilotage!$K$19:$K$32)/SUMPRODUCT(Pilotage!$K$19:$K$32,Pilotage!$J$19:$J$32))) | U8: =IF($A8="","",SUMIFS(Pilotage!$K$19:$K$32,Pilotage!$A$19:$A$32,$A8)) | V8: =IF($A8="","",IF($B8="V01",Cadrage!$C$22,IF($B8="V02",Cadrage!$D$22,Cadrage!$E$22))) | W8: =IF($A8="","",IF($B8="V01",Cadrage!$C$23,IF($B8="V02",Cadrage!$D$23,Cadrage!$E$23))) | X8: =IF($A8="","",IF($B8="V01",Cadrage!$C$24,IF($B8="V02",Cadrage!$D$24,Cadrage!$E$24))) | Y8: =IF($A8="","",IF($B8="V01",Cadrage!$C$25,IF($B8="V02",Cadrage!$D$25,Cadrage!$E$25))) | Z8: =IF($A8="","",IF($B8="V01",Cadrage!$C$26,IF($B8="V02",Cadrage!$D$26,Cadrage!$E$26))) | AA8: =IF($A8="","",IF($B8="V01",Cadrage!$C$27,IF($B8="V02",Cadrage!$D$27,Cadrage!$E$27))) | AB8: =IF($A8="","",IF($B8="V01",Cadrage!$C$39,IF($B8="V02",Cadrage!$D$39,Cadrage!$E$39))) | AC8: =IF($A8="","",IF($F8="MBWAY",Cadrage!$K$11,IF($F8="ISCOM",Cadrage!$K$12,IF($F8="IPAC",Cadrage!$K$13,IF($F8="PIGIER",Cadrage!$K$14,Cadrage!$K$15))))) | AD8: =IF($A8="","",($O8*(1+$W8)^$S8+$P8*IFERROR((($T8/$U8)*(1+$V8))^$R8,0))*IFERROR($G8/$Q8,0)*($J8+$Y8)*$K8*($L8+$Z8)) | AE8: =IF($A8="","",IF($N8=1,$AD8,0)) | AF8: =IF($A8="","",IF($N8=1,$AD8,$H8*($M8+$AA8))) | AG8: =IF($A8="","",$I8*(1+$X8*$AC8)) | AH8: =IF($A8="","",$AF8*$AG8+$AE8*$AB8)
A9: =IF(Moteur!D9="","",Moteur!D9) | B9: =IF(Moteur!B9="","",Moteur!B9) | C9: =IF(Moteur!F9="","",Moteur!F9) | D9: =IF(Moteur!G9="","",Moteur!G9) | E9: =IF(Moteur!H9="","",Moteur!H9) | F9: =IF(Moteur!E9="","",Moteur!E9) | G9: =IF($A9="","",SUMIFS(Socle!$H$1:$H$379,Socle!$C$1:$C$379,$A9,Socle!$D$1:$D$379,$C9,Socle!$E$1:$E$379,$D9,Socle!$F$1:$F$379,$E9,Socle!$G$1:$G$379,"2026")) | H9: =IF($A9="","",SUMIFS(Socle!$N$1:$N$379,Socle!$C$1:$C$379,$A9,Socle!$D$1:$D$379,$C9,Socle!$E$1:$E$379,$D9,Socle!$F$1:$F$379,$E9,Socle!$G$1:$G$379,"2026")) | I9: =IF($A9="","",SUMIFS(Socle!$P$1:$P$379,Socle!$C$1:$C$379,$A9,Socle!$D$1:$D$379,$C9,Socle!$E$1:$E$379,$D9,Socle!$F$1:$F$379,$E9,Socle!$G$1:$G$379,"2026")) | J9: =IF($A9="","",SUMIFS(Socle!$W$1:$W$379,Socle!$C$1:$C$379,$A9,Socle!$D$1:$D$379,$C9,Socle!$E$1:$E$379,$D9,Socle!$F$1:$F$379,$E9,Socle!$G$1:$G$379,"2026")) | K9: =IF($A9="","",SUMIFS(Socle!$X$1:$X$379,Socle!$C$1:$C$379,$A9,Socle!$D$1:$D$379,$C9,Socle!$E$1:$E$379,$D9,Socle!$F$1:$F$379,$E9,Socle!$G$1:$G$379,"2026")) | L9: =IF($A9="","",SUMIFS(Socle!$Y$1:$Y$379,Socle!$C$1:$C$379,$A9,Socle!$D$1:$D$379,$C9,Socle!$E$1:$E$379,$D9,Socle!$F$1:$F$379,$E9,Socle!$G$1:$G$379,"2026")) | M9: =IF($A9="","",SUMIFS(Socle!$V$1:$V$379,Socle!$C$1:$C$379,$A9,Socle!$D$1:$D$379,$C9,Socle!$E$1:$E$379,$D9,Socle!$F$1:$F$379,$E9,Socle!$G$1:$G$379,"2026")) | N9: =IF($A9="","",IF(OR($D9="B1",$D9="M1",$D9="BTS1"),1,0)) | O9: =IF($A9="","",SUMIFS(Campagne!$D$1:$D$28,Campagne!$C$1:$C$28,$A9)) | P9: =IF($A9="","",SUMIFS(Campagne!$E$1:$E$28,Campagne!$C$1:$C$28,$A9)) | Q9: =IF($A9="","",SUMIFS(Campagne!$F$1:$F$28,Campagne!$C$1:$C$28,$A9)) | R9: =IF($A9="","",SUMIFS(Campagne!$K$1:$K$28,Campagne!$C$1:$C$28,$A9)) | S9: =IF($A9="","",SUMIFS(Campagne!$M$1:$M$28,Campagne!$C$1:$C$28,$A9)) | T9: =IF($A9="","",SUMIFS(Pilotage!$K$19:$K$32,Pilotage!$A$19:$A$32,$A9)*SUMIFS(Pilotage!$J$19:$J$32,Pilotage!$A$19:$A$32,$A9)*(SUM(Pilotage!$K$19:$K$32)/SUMPRODUCT(Pilotage!$K$19:$K$32,Pilotage!$J$19:$J$32))) | U9: =IF($A9="","",SUMIFS(Pilotage!$K$19:$K$32,Pilotage!$A$19:$A$32,$A9)) | V9: =IF($A9="","",IF($B9="V01",Cadrage!$C$22,IF($B9="V02",Cadrage!$D$22,Cadrage!$E$22))) | W9: =IF($A9="","",IF($B9="V01",Cadrage!$C$23,IF($B9="V02",Cadrage!$D$23,Cadrage!$E$23))) | X9: =IF($A9="","",IF($B9="V01",Cadrage!$C$24,IF($B9="V02",Cadrage!$D$24,Cadrage!$E$24))) | Y9: =IF($A9="","",IF($B9="V01",Cadrage!$C$25,IF($B9="V02",Cadrage!$D$25,Cadrage!$E$25))) | Z9: =IF($A9="","",IF($B9="V01",Cadrage!$C$26,IF($B9="V02",Cadrage!$D$26,Cadrage!$E$26))) | AA9: =IF($A9="","",IF($B9="V01",Cadrage!$C$27,IF($B9="V02",Cadrage!$D$27,Cadrage!$E$27))) | AB9: =IF($A9="","",IF($B9="V01",Cadrage!$C$39,IF($B9="V02",Cadrage!$D$39,Cadrage!$E$39))) | AC9: =IF($A9="","",IF($F9="MBWAY",Cadrage!$K$11,IF($F9="ISCOM",Cadrage!$K$12,IF($F9="IPAC",Cadrage!$K$13,IF($F9="PIGIER",Cadrage!$K$14,Cadrage!$K$15))))) | AD9: =IF($A9="","",($O9*(1+$W9)^$S9+$P9*IFERROR((($T9/$U9)*(1+$V9))^$R9,0))*IFERROR($G9/$Q9,0)*($J9+$Y9)*$K9*($L9+$Z9)) | AE9: =IF($A9="","",IF($N9=1,$AD9,0)) | AF9: =IF($A9="","",IF($N9=1,$AD9,$H9*($M9+$AA9))) | AG9: =IF($A9="","",$I9*(1+$X9*$AC9)) | AH9: =IF($A9="","",$AF9*$AG9+$AE9*$AB9)
A10: =IF(Moteur!D10="","",Moteur!D10) | B10: =IF(Moteur!B10="","",Moteur!B10) | C10: =IF(Moteur!F10="","",Moteur!F10) | D10: =IF(Moteur!G10="","",Moteur!G10) | E10: =IF(Moteur!H10="","",Moteur!H10) | F10: =IF(Moteur!E10="","",Moteur!E10) | G10: =IF($A10="","",SUMIFS(Socle!$H$1:$H$379,Socle!$C$1:$C$379,$A10,Socle!$D$1:$D$379,$C10,Socle!$E$1:$E$379,$D10,Socle!$F$1:$F$379,$E10,Socle!$G$1:$G$379,"2026")) | H10: =IF($A10="","",SUMIFS(Socle!$N$1:$N$379,Socle!$C$1:$C$379,$A10,Socle!$D$1:$D$379,$C10,Socle!$E$1:$E$379,$D10,Socle!$F$1:$F$379,$E10,Socle!$G$1:$G$379,"2026")) | I10: =IF($A10="","",SUMIFS(Socle!$P$1:$P$379,Socle!$C$1:$C$379,$A10,Socle!$D$1:$D$379,$C10,Socle!$E$1:$E$379,$D10,Socle!$F$1:$F$379,$E10,Socle!$G$1:$G$379,"2026")) | J10: =IF($A10="","",SUMIFS(Socle!$W$1:$W$379,Socle!$C$1:$C$379,$A10,Socle!$D$1:$D$379,$C10,Socle!$E$1:$E$379,$D10,Socle!$F$1:$F$379,$E10,Socle!$G$1:$G$379,"2026")) | K10: =IF($A10="","",SUMIFS(Socle!$X$1:$X$379,Socle!$C$1:$C$379,$A10,Socle!$D$1:$D$379,$C10,Socle!$E$1:$E$379,$D10,Socle!$F$1:$F$379,$E10,Socle!$G$1:$G$379,"2026")) | L10: =IF($A10="","",SUMIFS(Socle!$Y$1:$Y$379,Socle!$C$1:$C$379,$A10,Socle!$D$1:$D$379,$C10,Socle!$E$1:$E$379,$D10,Socle!$F$1:$F$379,$E10,Socle!$G$1:$G$379,"2026")) | M10: =IF($A10="","",SUMIFS(Socle!$V$1:$V$379,Socle!$C$1:$C$379,$A10,Socle!$D$1:$D$379,$C10,Socle!$E$1:$E$379,$D10,Socle!$F$1:$F$379,$E10,Socle!$G$1:$G$379,"2026")) | N10: =IF($A10="","",IF(OR($D10="B1",$D10="M1",$D10="BTS1"),1,0)) | O10: =IF($A10="","",SUMIFS(Campagne!$D$1:$D$28,Campagne!$C$1:$C$28,$A10)) | P10: =IF($A10="","",SUMIFS(Campagne!$E$1:$E$28,Campagne!$C$1:$C$28,$A10)) | Q10: =IF($A10="","",SUMIFS(Campagne!$F$1:$F$28,Campagne!$C$1:$C$28,$A10)) | R10: =IF($A10="","",SUMIFS(Campagne!$K$1:$K$28,Campagne!$C$1:$C$28,$A10)) | S10: =IF($A10="","",SUMIFS(Campagne!$M$1:$M$28,Campagne!$C$1:$C$28,$A10)) | T10: =IF($A10="","",SUMIFS(Pilotage!$K$19:$K$32,Pilotage!$A$19:$A$32,$A10)*SUMIFS(Pilotage!$J$19:$J$32,Pilotage!$A$19:$A$32,$A10)*(SUM(Pilotage!$K$19:$K$32)/SUMPRODUCT(Pilotage!$K$19:$K$32,Pilotage!$J$19:$J$32))) | U10: =IF($A10="","",SUMIFS(Pilotage!$K$19:$K$32,Pilotage!$A$19:$A$32,$A10)) | V10: =IF($A10="","",IF($B10="V01",Cadrage!$C$22,IF($B10="V02",Cadrage!$D$22,Cadrage!$E$22))) | W10: =IF($A10="","",IF($B10="V01",Cadrage!$C$23,IF($B10="V02",Cadrage!$D$23,Cadrage!$E$23))) | X10: =IF($A10="","",IF($B10="V01",Cadrage!$C$24,IF($B10="V02",Cadrage!$D$24,Cadrage!$E$24))) | Y10: =IF($A10="","",IF($B10="V01",Cadrage!$C$25,IF($B10="V02",Cadrage!$D$25,Cadrage!$E$25))) | Z10: =IF($A10="","",IF($B10="V01",Cadrage!$C$26,IF($B10="V02",Cadrage!$D$26,Cadrage!$E$26))) | AA10: =IF($A10="","",IF($B10="V01",Cadrage!$C$27,IF($B10="V02",Cadrage!$D$27,Cadrage!$E$27))) | AB10: =IF($A10="","",IF($B10="V01",Cadrage!$C$39,IF($B10="V02",Cadrage!$D$39,Cadrage!$E$39))) | AC10: =IF($A10="","",IF($F10="MBWAY",Cadrage!$K$11,IF($F10="ISCOM",Cadrage!$K$12,IF($F10="IPAC",Cadrage!$K$13,IF($F10="PIGIER",Cadrage!$K$14,Cadrage!$K$15))))) | AD10: =IF($A10="","",($O10*(1+$W10)^$S10+$P10*IFERROR((($T10/$U10)*(1+$V10))^$R10,0))*IFERROR($G10/$Q10,0)*($J10+$Y10)*$K10*($L10+$Z10)) | AE10: =IF($A10="","",IF($N10=1,$AD10,0)) | AF10: =IF($A10="","",IF($N10=1,$AD10,$H10*($M10+$AA10))) | AG10: =IF($A10="","",$I10*(1+$X10*$AC10)) | AH10: =IF($A10="","",$AF10*$AG10+$AE10*$AB10)
A11: =IF(Moteur!D11="","",Moteur!D11) | B11: =IF(Moteur!B11="","",Moteur!B11) | C11: =IF(Moteur!F11="","",Moteur!F11) | D11: =IF(Moteur!G11="","",Moteur!G11) | E11: =IF(Moteur!H11="","",Moteur!H11) | F11: =IF(Moteur!E11="","",Moteur!E11) | G11: =IF($A11="","",SUMIFS(Socle!$H$1:$H$379,Socle!$C$1:$C$379,$A11,Socle!$D$1:$D$379,$C11,Socle!$E$1:$E$379,$D11,Socle!$F$1:$F$379,$E11,Socle!$G$1:$G$379,"2026")) | H11: =IF($A11="","",SUMIFS(Socle!$N$1:$N$379,Socle!$C$1:$C$379,$A11,Socle!$D$1:$D$379,$C11,Socle!$E$1:$E$379,$D11,Socle!$F$1:$F$379,$E11,Socle!$G$1:$G$379,"2026")) | I11: =IF($A11="","",SUMIFS(Socle!$P$1:$P$379,Socle!$C$1:$C$379,$A11,Socle!$D$1:$D$379,$C11,Socle!$E$1:$E$379,$D11,Socle!$F$1:$F$379,$E11,Socle!$G$1:$G$379,"2026")) | J11: =IF($A11="","",SUMIFS(Socle!$W$1:$W$379,Socle!$C$1:$C$379,$A11,Socle!$D$1:$D$379,$C11,Socle!$E$1:$E$379,$D11,Socle!$F$1:$F$379,$E11,Socle!$G$1:$G$379,"2026")) | K11: =IF($A11="","",SUMIFS(Socle!$X$1:$X$379,Socle!$C$1:$C$379,$A11,Socle!$D$1:$D$379,$C11,Socle!$E$1:$E$379,$D11,Socle!$F$1:$F$379,$E11,Socle!$G$1:$G$379,"2026")) | L11: =IF($A11="","",SUMIFS(Socle!$Y$1:$Y$379,Socle!$C$1:$C$379,$A11,Socle!$D$1:$D$379,$C11,Socle!$E$1:$E$379,$D11,Socle!$F$1:$F$379,$E11,Socle!$G$1:$G$379,"2026")) | M11: =IF($A11="","",SUMIFS(Socle!$V$1:$V$379,Socle!$C$1:$C$379,$A11,Socle!$D$1:$D$379,$C11,Socle!$E$1:$E$379,$D11,Socle!$F$1:$F$379,$E11,Socle!$G$1:$G$379,"2026")) | N11: =IF($A11="","",IF(OR($D11="B1",$D11="M1",$D11="BTS1"),1,0)) | O11: =IF($A11="","",SUMIFS(Campagne!$D$1:$D$28,Campagne!$C$1:$C$28,$A11)) | P11: =IF($A11="","",SUMIFS(Campagne!$E$1:$E$28,Campagne!$C$1:$C$28,$A11)) | Q11: =IF($A11="","",SUMIFS(Campagne!$F$1:$F$28,Campagne!$C$1:$C$28,$A11)) | R11: =IF($A11="","",SUMIFS(Campagne!$K$1:$K$28,Campagne!$C$1:$C$28,$A11)) | S11: =IF($A11="","",SUMIFS(Campagne!$M$1:$M$28,Campagne!$C$1:$C$28,$A11)) | T11: =IF($A11="","",SUMIFS(Pilotage!$K$19:$K$32,Pilotage!$A$19:$A$32,$A11)*SUMIFS(Pilotage!$J$19:$J$32,Pilotage!$A$19:$A$32,$A11)*(SUM(Pilotage!$K$19:$K$32)/SUMPRODUCT(Pilotage!$K$19:$K$32,Pilotage!$J$19:$J$32))) | U11: =IF($A11="","",SUMIFS(Pilotage!$K$19:$K$32,Pilotage!$A$19:$A$32,$A11)) | V11: =IF($A11="","",IF($B11="V01",Cadrage!$C$22,IF($B11="V02",Cadrage!$D$22,Cadrage!$E$22))) | W11: =IF($A11="","",IF($B11="V01",Cadrage!$C$23,IF($B11="V02",Cadrage!$D$23,Cadrage!$E$23))) | X11: =IF($A11="","",IF($B11="V01",Cadrage!$C$24,IF($B11="V02",Cadrage!$D$24,Cadrage!$E$24))) | Y11: =IF($A11="","",IF($B11="V01",Cadrage!$C$25,IF($B11="V02",Cadrage!$D$25,Cadrage!$E$25))) | Z11: =IF($A11="","",IF($B11="V01",Cadrage!$C$26,IF($B11="V02",Cadrage!$D$26,Cadrage!$E$26))) | AA11: =IF($A11="","",IF($B11="V01",Cadrage!$C$27,IF($B11="V02",Cadrage!$D$27,Cadrage!$E$27))) | AB11: =IF($A11="","",IF($B11="V01",Cadrage!$C$39,IF($B11="V02",Cadrage!$D$39,Cadrage!$E$39))) | AC11: =IF($A11="","",IF($F11="MBWAY",Cadrage!$K$11,IF($F11="ISCOM",Cadrage!$K$12,IF($F11="IPAC",Cadrage!$K$13,IF($F11="PIGIER",Cadrage!$K$14,Cadrage!$K$15))))) | AD11: =IF($A11="","",($O11*(1+$W11)^$S11+$P11*IFERROR((($T11/$U11)*(1+$V11))^$R11,0))*IFERROR($G11/$Q11,0)*($J11+$Y11)*$K11*($L11+$Z11)) | AE11: =IF($A11="","",IF($N11=1,$AD11,0)) | AF11: =IF($A11="","",IF($N11=1,$AD11,$H11*($M11+$AA11))) | AG11: =IF($A11="","",$I11*(1+$X11*$AC11)) | AH11: =IF($A11="","",$AF11*$AG11+$AE11*$AB11)
A12: =IF(Moteur!D12="","",Moteur!D12) | B12: =IF(Moteur!B12="","",Moteur!B12) | C12: =IF(Moteur!F12="","",Moteur!F12) | D12: =IF(Moteur!G12="","",Moteur!G12) | E12: =IF(Moteur!H12="","",Moteur!H12) | F12: =IF(Moteur!E12="","",Moteur!E12) | G12: =IF($A12="","",SUMIFS(Socle!$H$1:$H$379,Socle!$C$1:$C$379,$A12,Socle!$D$1:$D$379,$C12,Socle!$E$1:$E$379,$D12,Socle!$F$1:$F$379,$E12,Socle!$G$1:$G$379,"2026")) | H12: =IF($A12="","",SUMIFS(Socle!$N$1:$N$379,Socle!$C$1:$C$379,$A12,Socle!$D$1:$D$379,$C12,Socle!$E$1:$E$379,$D12,Socle!$F$1:$F$379,$E12,Socle!$G$1:$G$379,"2026")) | I12: =IF($A12="","",SUMIFS(Socle!$P$1:$P$379,Socle!$C$1:$C$379,$A12,Socle!$D$1:$D$379,$C12,Socle!$E$1:$E$379,$D12,Socle!$F$1:$F$379,$E12,Socle!$G$1:$G$379,"2026")) | J12: =IF($A12="","",SUMIFS(Socle!$W$1:$W$379,Socle!$C$1:$C$379,$A12,Socle!$D$1:$D$379,$C12,Socle!$E$1:$E$379,$D12,Socle!$F$1:$F$379,$E12,Socle!$G$1:$G$379,"2026")) | K12: =IF($A12="","",SUMIFS(Socle!$X$1:$X$379,Socle!$C$1:$C$379,$A12,Socle!$D$1:$D$379,$C12,Socle!$E$1:$E$379,$D12,Socle!$F$1:$F$379,$E12,Socle!$G$1:$G$379,"2026")) | L12: =IF($A12="","",SUMIFS(Socle!$Y$1:$Y$379,Socle!$C$1:$C$379,$A12,Socle!$D$1:$D$379,$C12,Socle!$E$1:$E$379,$D12,Socle!$F$1:$F$379,$E12,Socle!$G$1:$G$379,"2026")) | M12: =IF($A12="","",SUMIFS(Socle!$V$1:$V$379,Socle!$C$1:$C$379,$A12,Socle!$D$1:$D$379,$C12,Socle!$E$1:$E$379,$D12,Socle!$F$1:$F$379,$E12,Socle!$G$1:$G$379,"2026")) | N12: =IF($A12="","",IF(OR($D12="B1",$D12="M1",$D12="BTS1"),1,0)) | O12: =IF($A12="","",SUMIFS(Campagne!$D$1:$D$28,Campagne!$C$1:$C$28,$A12)) | P12: =IF($A12="","",SUMIFS(Campagne!$E$1:$E$28,Campagne!$C$1:$C$28,$A12)) | Q12: =IF($A12="","",SUMIFS(Campagne!$F$1:$F$28,Campagne!$C$1:$C$28,$A12)) | R12: =IF($A12="","",SUMIFS(Campagne!$K$1:$K$28,Campagne!$C$1:$C$28,$A12)) | S12: =IF($A12="","",SUMIFS(Campagne!$M$1:$M$28,Campagne!$C$1:$C$28,$A12)) | T12: =IF($A12="","",SUMIFS(Pilotage!$K$19:$K$32,Pilotage!$A$19:$A$32,$A12)*SUMIFS(Pilotage!$J$19:$J$32,Pilotage!$A$19:$A$32,$A12)*(SUM(Pilotage!$K$19:$K$32)/SUMPRODUCT(Pilotage!$K$19:$K$32,Pilotage!$J$19:$J$32))) | U12: =IF($A12="","",SUMIFS(Pilotage!$K$19:$K$32,Pilotage!$A$19:$A$32,$A12)) | V12: =IF($A12="","",IF($B12="V01",Cadrage!$C$22,IF($B12="V02",Cadrage!$D$22,Cadrage!$E$22))) | W12: =IF($A12="","",IF($B12="V01",Cadrage!$C$23,IF($B12="V02",Cadrage!$D$23,Cadrage!$E$23))) | X12: =IF($A12="","",IF($B12="V01",Cadrage!$C$24,IF($B12="V02",Cadrage!$D$24,Cadrage!$E$24))) | Y12: =IF($A12="","",IF($B12="V01",Cadrage!$C$25,IF($B12="V02",Cadrage!$D$25,Cadrage!$E$25))) | Z12: =IF($A12="","",IF($B12="V01",Cadrage!$C$26,IF($B12="V02",Cadrage!$D$26,Cadrage!$E$26))) | AA12: =IF($A12="","",IF($B12="V01",Cadrage!$C$27,IF($B12="V02",Cadrage!$D$27,Cadrage!$E$27))) | AB12: =IF($A12="","",IF($B12="V01",Cadrage!$C$39,IF($B12="V02",Cadrage!$D$39,Cadrage!$E$39))) | AC12: =IF($A12="","",IF($F12="MBWAY",Cadrage!$K$11,IF($F12="ISCOM",Cadrage!$K$12,IF($F12="IPAC",Cadrage!$K$13,IF($F12="PIGIER",Cadrage!$K$14,Cadrage!$K$15))))) | AD12: =IF($A12="","",($O12*(1+$W12)^$S12+$P12*IFERROR((($T12/$U12)*(1+$V12))^$R12,0))*IFERROR($G12/$Q12,0)*($J12+$Y12)*$K12*($L12+$Z12)) | AE12: =IF($A12="","",IF($N12=1,$AD12,0)) | AF12: =IF($A12="","",IF($N12=1,$AD12,$H12*($M12+$AA12))) | AG12: =IF($A12="","",$I12*(1+$X12*$AC12)) | AH12: =IF($A12="","",$AF12*$AG12+$AE12*$AB12)
A13: =IF(Moteur!D13="","",Moteur!D13) | B13: =IF(Moteur!B13="","",Moteur!B13) | C13: =IF(Moteur!F13="","",Moteur!F13) | D13: =IF(Moteur!G13="","",Moteur!G13) | E13: =IF(Moteur!H13="","",Moteur!H13) | F13: =IF(Moteur!E13="","",Moteur!E13) | G13: =IF($A13="","",SUMIFS(Socle!$H$1:$H$379,Socle!$C$1:$C$379,$A13,Socle!$D$1:$D$379,$C13,Socle!$E$1:$E$379,$D13,Socle!$F$1:$F$379,$E13,Socle!$G$1:$G$379,"2026")) | H13: =IF($A13="","",SUMIFS(Socle!$N$1:$N$379,Socle!$C$1:$C$379,$A13,Socle!$D$1:$D$379,$C13,Socle!$E$1:$E$379,$D13,Socle!$F$1:$F$379,$E13,Socle!$G$1:$G$379,"2026")) | I13: =IF($A13="","",SUMIFS(Socle!$P$1:$P$379,Socle!$C$1:$C$379,$A13,Socle!$D$1:$D$379,$C13,Socle!$E$1:$E$379,$D13,Socle!$F$1:$F$379,$E13,Socle!$G$1:$G$379,"2026")) | J13: =IF($A13="","",SUMIFS(Socle!$W$1:$W$379,Socle!$C$1:$C$379,$A13,Socle!$D$1:$D$379,$C13,Socle!$E$1:$E$379,$D13,Socle!$F$1:$F$379,$E13,Socle!$G$1:$G$379,"2026")) | K13: =IF($A13="","",SUMIFS(Socle!$X$1:$X$379,Socle!$C$1:$C$379,$A13,Socle!$D$1:$D$379,$C13,Socle!$E$1:$E$379,$D13,Socle!$F$1:$F$379,$E13,Socle!$G$1:$G$379,"2026")) | L13: =IF($A13="","",SUMIFS(Socle!$Y$1:$Y$379,Socle!$C$1:$C$379,$A13,Socle!$D$1:$D$379,$C13,Socle!$E$1:$E$379,$D13,Socle!$F$1:$F$379,$E13,Socle!$G$1:$G$379,"2026")) | M13: =IF($A13="","",SUMIFS(Socle!$V$1:$V$379,Socle!$C$1:$C$379,$A13,Socle!$D$1:$D$379,$C13,Socle!$E$1:$E$379,$D13,Socle!$F$1:$F$379,$E13,Socle!$G$1:$G$379,"2026")) | N13: =IF($A13="","",IF(OR($D13="B1",$D13="M1",$D13="BTS1"),1,0)) | O13: =IF($A13="","",SUMIFS(Campagne!$D$1:$D$28,Campagne!$C$1:$C$28,$A13)) | P13: =IF($A13="","",SUMIFS(Campagne!$E$1:$E$28,Campagne!$C$1:$C$28,$A13)) | Q13: =IF($A13="","",SUMIFS(Campagne!$F$1:$F$28,Campagne!$C$1:$C$28,$A13)) | R13: =IF($A13="","",SUMIFS(Campagne!$K$1:$K$28,Campagne!$C$1:$C$28,$A13)) | S13: =IF($A13="","",SUMIFS(Campagne!$M$1:$M$28,Campagne!$C$1:$C$28,$A13)) | T13: =IF($A13="","",SUMIFS(Pilotage!$K$19:$K$32,Pilotage!$A$19:$A$32,$A13)*SUMIFS(Pilotage!$J$19:$J$32,Pilotage!$A$19:$A$32,$A13)*(SUM(Pilotage!$K$19:$K$32)/SUMPRODUCT(Pilotage!$K$19:$K$32,Pilotage!$J$19:$J$32))) | U13: =IF($A13="","",SUMIFS(Pilotage!$K$19:$K$32,Pilotage!$A$19:$A$32,$A13)) | V13: =IF($A13="","",IF($B13="V01",Cadrage!$C$22,IF($B13="V02",Cadrage!$D$22,Cadrage!$E$22))) | W13: =IF($A13="","",IF($B13="V01",Cadrage!$C$23,IF($B13="V02",Cadrage!$D$23,Cadrage!$E$23))) | X13: =IF($A13="","",IF($B13="V01",Cadrage!$C$24,IF($B13="V02",Cadrage!$D$24,Cadrage!$E$24))) | Y13: =IF($A13="","",IF($B13="V01",Cadrage!$C$25,IF($B13="V02",Cadrage!$D$25,Cadrage!$E$25))) | Z13: =IF($A13="","",IF($B13="V01",Cadrage!$C$26,IF($B13="V02",Cadrage!$D$26,Cadrage!$E$26))) | AA13: =IF($A13="","",IF($B13="V01",Cadrage!$C$27,IF($B13="V02",Cadrage!$D$27,Cadrage!$E$27))) | AB13: =IF($A13="","",IF($B13="V01",Cadrage!$C$39,IF($B13="V02",Cadrage!$D$39,Cadrage!$E$39))) | AC13: =IF($A13="","",IF($F13="MBWAY",Cadrage!$K$11,IF($F13="ISCOM",Cadrage!$K$12,IF($F13="IPAC",Cadrage!$K$13,IF($F13="PIGIER",Cadrage!$K$14,Cadrage!$K$15))))) | AD13: =IF($A13="","",($O13*(1+$W13)^$S13+$P13*IFERROR((($T13/$U13)*(1+$V13))^$R13,0))*IFERROR($G13/$Q13,0)*($J13+$Y13)*$K13*($L13+$Z13)) | AE13: =IF($A13="","",IF($N13=1,$AD13,0)) | AF13: =IF($A13="","",IF($N13=1,$AD13,$H13*($M13+$AA13))) | AG13: =IF($A13="","",$I13*(1+$X13*$AC13)) | AH13: =IF($A13="","",$AF13*$AG13+$AE13*$AB13)
... A190: =IF(Moteur!D190="","",Moteur!D190) | B190: =IF(Moteur!B190="","",Moteur!B190) | C190: =IF(Moteur!F190="","",Moteur!F190) | D190: =IF(Moteur!G190="","",Moteur!G190) | E190: =IF(Moteur!H190="","",Moteur!H190) | F190: =IF(Moteur!E190="","",Moteur!E190) | G190: =IF($A190="","",SUMIFS(Socle!$H$1:$H$379,Socle!$C$1:$C$379,$A190,Socle!$D$1:$D$379,$C190,Socle!$E$1:$E$379,$D190,Socle!$F$1:$F$379,$E190,Socle!$G$1:$G$379,"2026")) | H190: =IF($A190="","",SUMIFS(Socle!$N$1:$N$379,Socle!$C$1:$C$379,$A190,Socle!$D$1:$D$379,$C190,Socle!$E$1:$E$379,$D190,Socle!$F$1:$F$379,$E190,Socle!$G$1:$G$379,"2026")) | I190: =IF($A190="","",SUMIFS(Socle!$P$1:$P$379,Socle!$C$1:$C$379,$A190,Socle!$D$1:$D$379,$C190,Socle!$E$1:$E$379,$D190,Socle!$F$1:$F$379,$E190,Socle!$G$1:$G$379,"2026")) | J190: =IF($A190="","",SUMIFS(Socle!$W$1:$W$379,Socle!$C$1:$C$379,$A190,Socle!$D$1:$D$379,$C190,Socle!$E$1:$E$379,$D190,Socle!$F$1:$F$379,$E190,Socle!$G$1:$G$379,"2026")) | K190: =IF($A190="","",SUMIFS(Socle!$X$1:$X$379,Socle!$C$1:$C$379,$A190,Socle!$D$1:$D$379,$C190,Socle!$E$1:$E$379,$D190,Socle!$F$1:$F$379,$E190,Socle!$G$1:$G$379,"2026")) | L190: =IF($A190="","",SUMIFS(Socle!$Y$1:$Y$379,Socle!$C$1:$C$379,$A190,Socle!$D$1:$D$379,$C190,Socle!$E$1:$E$379,$D190,Socle!$F$1:$F$379,$E190,Socle!$G$1:$G$379,"2026")) | M190: =IF($A190="","",SUMIFS(Socle!$V$1:$V$379,Socle!$C$1:$C$379,$A190,Socle!$D$1:$D$379,$C190,Socle!$E$1:$E$379,$D190,Socle!$F$1:$F$379,$E190,Socle!$G$1:$G$379,"2026")) | N190: =IF($A190="","",IF(OR($D190="B1",$D190="M1",$D190="BTS1"),1,0)) | O190: =IF($A190="","",SUMIFS(Campagne!$D$1:$D$28,Campagne!$C$1:$C$28,$A190)) | P190: =IF($A190="","",SUMIFS(Campagne!$E$1:$E$28,Campagne!$C$1:$C$28,$A190)) | Q190: =IF($A190="","",SUMIFS(Campagne!$F$1:$F$28,Campagne!$C$1:$C$28,$A190)) | R190: =IF($A190="","",SUMIFS(Campagne!$K$1:$K$28,Campagne!$C$1:$C$28,$A190)) | S190: =IF($A190="","",SUMIFS(Campagne!$M$1:$M$28,Campagne!$C$1:$C$28,$A190)) | T190: =IF($A190="","",SUMIFS(Pilotage!$K$19:$K$32,Pilotage!$A$19:$A$32,$A190)*SUMIFS(Pilotage!$J$19:$J$32,Pilotage!$A$19:$A$32,$A190)*(SUM(Pilotage!$K$19:$K$32)/SUMPRODUCT(Pilotage!$K$19:$K$32,Pilotage!$J$19:$J$32))) | U190: =IF($A190="","",SUMIFS(Pilotage!$K$19:$K$32,Pilotage!$A$19:$A$32,$A190)) | V190: =IF($A190="","",IF($B190="V01",Cadrage!$C$22,IF($B190="V02",Cadrage!$D$22,Cadrage!$E$22))) | W190: =IF($A190="","",IF($B190="V01",Cadrage!$C$23,IF($B190="V02",Cadrage!$D$23,Cadrage!$E$23))) | X190: =IF($A190="","",IF($B190="V01",Cadrage!$C$24,IF($B190="V02",Cadrage!$D$24,Cadrage!$E$24))) | Y190: =IF($A190="","",IF($B190="V01",Cadrage!$C$25,IF($B190="V02",Cadrage!$D$25,Cadrage!$E$25))) | Z190: =IF($A190="","",IF($B190="V01",Cadrage!$C$26,IF($B190="V02",Cadrage!$D$26,Cadrage!$E$26))) | AA190: =IF($A190="","",IF($B190="V01",Cadrage!$C$27,IF($B190="V02",Cadrage!$D$27,Cadrage!$E$27))) | AB190: =IF($A190="","",IF($B190="V01",Cadrage!$C$39,IF($B190="V02",Cadrage!$D$39,Cadrage!$E$39))) | AC190: =IF($A190="","",IF($F190="MBWAY",Cadrage!$K$11,IF($F190="ISCOM",Cadrage!$K$12,IF($F190="IPAC",Cadrage!$K$13,IF($F190="PIGIER",Cadrage!$K$14,Cadrage!$K$15))))) | AD190: =IF($A190="","",($O190*(1+$W190)^$S190+$P190*IFERROR((($T190/$U190)*(1+$V190))^$R190,0))*IFERROR($G190/$Q190,0)*($J190+$Y190)*$K190*($L190+$Z190)) | AE190: =IF($A190="","",IF($N190=1,$AD190,0)) | AF190: =IF($A190="","",IF($N190=1,$AD190,$H190*($M190+$AA190))) | AG190: =IF($A190="","",$I190*(1+$X190*$AC190)) | AH190: =IF($A190="","",$AF190*$AG190+$AE190*$AB190)

Sheet _CALC_PNL
A1: ENT | B1: ACC | C1: EX | D1: VER | E1: ISBUD | F1: CPT26 | G1: ACQ | H1: BRAND | I1: INFL | J1: SAL | K1: FTE | L1: PROD | M1: STRUCT | N1: CAF | O1: FAC | P1: AMT_LIVE | R1: =SUMIFS(Comptabilité!$F$1:$F$675,Comptabilité!$B$1:$B$675,"7062",Comptabilité!$C$1:$C$675,"2026")+SUMIFS(Comptabilité!$F$1:$F$675,Comptabilité!$B$1:$B$675,"706",Comptabilité!$C$1:$C$675,"2026")+SUMIFS(Comptabilité!$F$1:$F$675,Comptabilité!$B$1:$B$675,"708",Comptabilité!$C$1:$C$675,"2026") | T1: EBITDA_SIGNED | V1: ■ VIOLET = colonne branchee sur une saisie (cad / Pilotage / 3_Allocation) -> a recabler cote Tagetik
A2: =IF(PNL!A2="","",PNL!A2) | B2: =IF(PNL!B2="","",PNL!B2) | C2: =IF(PNL!C2="","",PNL!C2) | D2: =IF(PNL!D2="","",PNL!D2) | E2: =IF($A2="","",IF(AND($C2="2027",OR($D2="V01",$D2="V02",$D2="V03")),1,0)) | F2: =IF($A2="","",IF($E2=1,SUMIFS(Comptabilité!$F$1:$F$675,Comptabilité!$A$1:$A$675,$A2,Comptabilité!$B$1:$B$675,$B2,Comptabilité!$C$1:$C$675,"2026"),0)) | G2: =IF($A2="","",IF($D2="V01",Cadrage!$C$22,IF($D2="V02",Cadrage!$D$22,Cadrage!$E$22))) | H2: =IF($A2="","",IF($D2="V01",Cadrage!$C$23,IF($D2="V02",Cadrage!$D$23,Cadrage!$E$23))) | I2: =IF($A2="","",IF($D2="V01",Cadrage!$C$31,IF($D2="V02",Cadrage!$D$31,Cadrage!$E$31))) | J2: =IF($A2="","",IF($D2="V01",Cadrage!$C$32,IF($D2="V02",Cadrage!$D$32,Cadrage!$E$32))) | K2: =IF($A2="","",IF($D2="V01",Cadrage!$C$33,IF($D2="V02",Cadrage!$D$33,Cadrage!$E$33))) | L2: =IF($A2="","",IF($D2="V01",Cadrage!$C$34,IF($D2="V02",Cadrage!$D$34,Cadrage!$E$34))) | M2: =IF($A2="","",IF($D2="V01",Cadrage!$C$35,IF($D2="V02",Cadrage!$D$35,Cadrage!$E$35))) | N2: =IF($A2="","",IF($D2="V01",$R$2,IF($D2="V02",$R$3,$R$4))) | O2: =IF($A2="","",IF(OR($B2="7062",$B2="706",$B2="708"),$N2,IF($B2="6231",1+$G2,IF($B2="6236",1+$H2,IF(OR($B2="621",$B2="604",$B2="6063"),$N2*(1-$L2),IF(OR($B2="6411",$B2="6413",$B2="6414",$B2="645"),(1+$J2)*(1+$K2),IF(OR($B2="613",$B2="615",$B2="616",$B2="6226",$B2="625",$B2="626",$B2="6281"),(1+$I2)*(1-$L2)*(1+$M2),IF(OR($B2="6331",$B2="63511",$B2="6333"),(1+$I2)*(1-$L2),IF($B2="6811",1+$I2,1))))))))) | P2: =IF($A2="","",IF($E2=1,$F2*$O2,PNL!G2)) | R2: =SUMIFS(Moteur!$R$1:$R$200,Moteur!$B$1:$B$200,"V01")/$R$1 | T2: =IF($A2="","",IF($E2=1,IF(OR($B2="7062",$B2="706",$B2="708"),$P2,IF(AND(LEFT($B2,1)="6",$B2<>"6811"),-$P2,0)),0))
A3: =IF(PNL!A3="","",PNL!A3) | B3: =IF(PNL!B3="","",PNL!B3) | C3: =IF(PNL!C3="","",PNL!C3) | D3: =IF(PNL!D3="","",PNL!D3) | E3: =IF($A3="","",IF(AND($C3="2027",OR($D3="V01",$D3="V02",$D3="V03")),1,0)) | F3: =IF($A3="","",IF($E3=1,SUMIFS(Comptabilité!$F$1:$F$675,Comptabilité!$A$1:$A$675,$A3,Comptabilité!$B$1:$B$675,$B3,Comptabilité!$C$1:$C$675,"2026"),0)) | G3: =IF($A3="","",IF($D3="V01",Cadrage!$C$22,IF($D3="V02",Cadrage!$D$22,Cadrage!$E$22))) | H3: =IF($A3="","",IF($D3="V01",Cadrage!$C$23,IF($D3="V02",Cadrage!$D$23,Cadrage!$E$23))) | I3: =IF($A3="","",IF($D3="V01",Cadrage!$C$31,IF($D3="V02",Cadrage!$D$31,Cadrage!$E$31))) | J3: =IF($A3="","",IF($D3="V01",Cadrage!$C$32,IF($D3="V02",Cadrage!$D$32,Cadrage!$E$32))) | K3: =IF($A3="","",IF($D3="V01",Cadrage!$C$33,IF($D3="V02",Cadrage!$D$33,Cadrage!$E$33))) | L3: =IF($A3="","",IF($D3="V01",Cadrage!$C$34,IF($D3="V02",Cadrage!$D$34,Cadrage!$E$34))) | M3: =IF($A3="","",IF($D3="V01",Cadrage!$C$35,IF($D3="V02",Cadrage!$D$35,Cadrage!$E$35))) | N3: =IF($A3="","",IF($D3="V01",$R$2,IF($D3="V02",$R$3,$R$4))) | O3: =IF($A3="","",IF(OR($B3="7062",$B3="706",$B3="708"),$N3,IF($B3="6231",1+$G3,IF($B3="6236",1+$H3,IF(OR($B3="621",$B3="604",$B3="6063"),$N3*(1-$L3),IF(OR($B3="6411",$B3="6413",$B3="6414",$B3="645"),(1+$J3)*(1+$K3),IF(OR($B3="613",$B3="615",$B3="616",$B3="6226",$B3="625",$B3="626",$B3="6281"),(1+$I3)*(1-$L3)*(1+$M3),IF(OR($B3="6331",$B3="63511",$B3="6333"),(1+$I3)*(1-$L3),IF($B3="6811",1+$I3,1))))))))) | P3: =IF($A3="","",IF($E3=1,$F3*$O3,PNL!G3)) | R3: =SUMIFS(Moteur!$R$1:$R$200,Moteur!$B$1:$B$200,"V02")/$R$1 | T3: =IF($A3="","",IF($E3=1,IF(OR($B3="7062",$B3="706",$B3="708"),$P3,IF(AND(LEFT($B3,1)="6",$B3<>"6811"),-$P3,0)),0))
A4: =IF(PNL!A4="","",PNL!A4) | B4: =IF(PNL!B4="","",PNL!B4) | C4: =IF(PNL!C4="","",PNL!C4) | D4: =IF(PNL!D4="","",PNL!D4) | E4: =IF($A4="","",IF(AND($C4="2027",OR($D4="V01",$D4="V02",$D4="V03")),1,0)) | F4: =IF($A4="","",IF($E4=1,SUMIFS(Comptabilité!$F$1:$F$675,Comptabilité!$A$1:$A$675,$A4,Comptabilité!$B$1:$B$675,$B4,Comptabilité!$C$1:$C$675,"2026"),0)) | G4: =IF($A4="","",IF($D4="V01",Cadrage!$C$22,IF($D4="V02",Cadrage!$D$22,Cadrage!$E$22))) | H4: =IF($A4="","",IF($D4="V01",Cadrage!$C$23,IF($D4="V02",Cadrage!$D$23,Cadrage!$E$23))) | I4: =IF($A4="","",IF($D4="V01",Cadrage!$C$31,IF($D4="V02",Cadrage!$D$31,Cadrage!$E$31))) | J4: =IF($A4="","",IF($D4="V01",Cadrage!$C$32,IF($D4="V02",Cadrage!$D$32,Cadrage!$E$32))) | K4: =IF($A4="","",IF($D4="V01",Cadrage!$C$33,IF($D4="V02",Cadrage!$D$33,Cadrage!$E$33))) | L4: =IF($A4="","",IF($D4="V01",Cadrage!$C$34,IF($D4="V02",Cadrage!$D$34,Cadrage!$E$34))) | M4: =IF($A4="","",IF($D4="V01",Cadrage!$C$35,IF($D4="V02",Cadrage!$D$35,Cadrage!$E$35))) | N4: =IF($A4="","",IF($D4="V01",$R$2,IF($D4="V02",$R$3,$R$4))) | O4: =IF($A4="","",IF(OR($B4="7062",$B4="706",$B4="708"),$N4,IF($B4="6231",1+$G4,IF($B4="6236",1+$H4,IF(OR($B4="621",$B4="604",$B4="6063"),$N4*(1-$L4),IF(OR($B4="6411",$B4="6413",$B4="6414",$B4="645"),(1+$J4)*(1+$K4),IF(OR($B4="613",$B4="615",$B4="616",$B4="6226",$B4="625",$B4="626",$B4="6281"),(1+$I4)*(1-$L4)*(1+$M4),IF(OR($B4="6331",$B4="63511",$B4="6333"),(1+$I4)*(1-$L4),IF($B4="6811",1+$I4,1))))))))) | P4: =IF($A4="","",IF($E4=1,$F4*$O4,PNL!G4)) | R4: =SUMIFS(Moteur!$R$1:$R$200,Moteur!$B$1:$B$200,"V03")/$R$1 | T4: =IF($A4="","",IF($E4=1,IF(OR($B4="7062",$B4="706",$B4="708"),$P4,IF(AND(LEFT($B4,1)="6",$B4<>"6811"),-$P4,0)),0))
A5: =IF(PNL!A5="","",PNL!A5) | B5: =IF(PNL!B5="","",PNL!B5) | C5: =IF(PNL!C5="","",PNL!C5) | D5: =IF(PNL!D5="","",PNL!D5) | E5: =IF($A5="","",IF(AND($C5="2027",OR($D5="V01",$D5="V02",$D5="V03")),1,0)) | F5: =IF($A5="","",IF($E5=1,SUMIFS(Comptabilité!$F$1:$F$675,Comptabilité!$A$1:$A$675,$A5,Comptabilité!$B$1:$B$675,$B5,Comptabilité!$C$1:$C$675,"2026"),0)) | G5: =IF($A5="","",IF($D5="V01",Cadrage!$C$22,IF($D5="V02",Cadrage!$D$22,Cadrage!$E$22))) | H5: =IF($A5="","",IF($D5="V01",Cadrage!$C$23,IF($D5="V02",Cadrage!$D$23,Cadrage!$E$23))) | I5: =IF($A5="","",IF($D5="V01",Cadrage!$C$31,IF($D5="V02",Cadrage!$D$31,Cadrage!$E$31))) | J5: =IF($A5="","",IF($D5="V01",Cadrage!$C$32,IF($D5="V02",Cadrage!$D$32,Cadrage!$E$32))) | K5: =IF($A5="","",IF($D5="V01",Cadrage!$C$33,IF($D5="V02",Cadrage!$D$33,Cadrage!$E$33))) | L5: =IF($A5="","",IF($D5="V01",Cadrage!$C$34,IF($D5="V02",Cadrage!$D$34,Cadrage!$E$34))) | M5: =IF($A5="","",IF($D5="V01",Cadrage!$C$35,IF($D5="V02",Cadrage!$D$35,Cadrage!$E$35))) | N5: =IF($A5="","",IF($D5="V01",$R$2,IF($D5="V02",$R$3,$R$4))) | O5: =IF($A5="","",IF(OR($B5="7062",$B5="706",$B5="708"),$N5,IF($B5="6231",1+$G5,IF($B5="6236",1+$H5,IF(OR($B5="621",$B5="604",$B5="6063"),$N5*(1-$L5),IF(OR($B5="6411",$B5="6413",$B5="6414",$B5="645"),(1+$J5)*(1+$K5),IF(OR($B5="613",$B5="615",$B5="616",$B5="6226",$B5="625",$B5="626",$B5="6281"),(1+$I5)*(1-$L5)*(1+$M5),IF(OR($B5="6331",$B5="63511",$B5="6333"),(1+$I5)*(1-$L5),IF($B5="6811",1+$I5,1))))))))) | P5: =IF($A5="","",IF($E5=1,$F5*$O5,PNL!G5)) | T5: =IF($A5="","",IF($E5=1,IF(OR($B5="7062",$B5="706",$B5="708"),$P5,IF(AND(LEFT($B5,1)="6",$B5<>"6811"),-$P5,0)),0))
A6: =IF(PNL!A6="","",PNL!A6) | B6: =IF(PNL!B6="","",PNL!B6) | C6: =IF(PNL!C6="","",PNL!C6) | D6: =IF(PNL!D6="","",PNL!D6) | E6: =IF($A6="","",IF(AND($C6="2027",OR($D6="V01",$D6="V02",$D6="V03")),1,0)) | F6: =IF($A6="","",IF($E6=1,SUMIFS(Comptabilité!$F$1:$F$675,Comptabilité!$A$1:$A$675,$A6,Comptabilité!$B$1:$B$675,$B6,Comptabilité!$C$1:$C$675,"2026"),0)) | G6: =IF($A6="","",IF($D6="V01",Cadrage!$C$22,IF($D6="V02",Cadrage!$D$22,Cadrage!$E$22))) | H6: =IF($A6="","",IF($D6="V01",Cadrage!$C$23,IF($D6="V02",Cadrage!$D$23,Cadrage!$E$23))) | I6: =IF($A6="","",IF($D6="V01",Cadrage!$C$31,IF($D6="V02",Cadrage!$D$31,Cadrage!$E$31))) | J6: =IF($A6="","",IF($D6="V01",Cadrage!$C$32,IF($D6="V02",Cadrage!$D$32,Cadrage!$E$32))) | K6: =IF($A6="","",IF($D6="V01",Cadrage!$C$33,IF($D6="V02",Cadrage!$D$33,Cadrage!$E$33))) | L6: =IF($A6="","",IF($D6="V01",Cadrage!$C$34,IF($D6="V02",Cadrage!$D$34,Cadrage!$E$34))) | M6: =IF($A6="","",IF($D6="V01",Cadrage!$C$35,IF($D6="V02",Cadrage!$D$35,Cadrage!$E$35))) | N6: =IF($A6="","",IF($D6="V01",$R$2,IF($D6="V02",$R$3,$R$4))) | O6: =IF($A6="","",IF(OR($B6="7062",$B6="706",$B6="708"),$N6,IF($B6="6231",1+$G6,IF($B6="6236",1+$H6,IF(OR($B6="621",$B6="604",$B6="6063"),$N6*(1-$L6),IF(OR($B6="6411",$B6="6413",$B6="6414",$B6="645"),(1+$J6)*(1+$K6),IF(OR($B6="613",$B6="615",$B6="616",$B6="6226",$B6="625",$B6="626",$B6="6281"),(1+$I6)*(1-$L6)*(1+$M6),IF(OR($B6="6331",$B6="63511",$B6="6333"),(1+$I6)*(1-$L6),IF($B6="6811",1+$I6,1))))))))) | P6: =IF($A6="","",IF($E6=1,$F6*$O6,PNL!G6)) | T6: =IF($A6="","",IF($E6=1,IF(OR($B6="7062",$B6="706",$B6="708"),$P6,IF(AND(LEFT($B6,1)="6",$B6<>"6811"),-$P6,0)),0))
A7: =IF(PNL!A7="","",PNL!A7) | B7: =IF(PNL!B7="","",PNL!B7) | C7: =IF(PNL!C7="","",PNL!C7) | D7: =IF(PNL!D7="","",PNL!D7) | E7: =IF($A7="","",IF(AND($C7="2027",OR($D7="V01",$D7="V02",$D7="V03")),1,0)) | F7: =IF($A7="","",IF($E7=1,SUMIFS(Comptabilité!$F$1:$F$675,Comptabilité!$A$1:$A$675,$A7,Comptabilité!$B$1:$B$675,$B7,Comptabilité!$C$1:$C$675,"2026"),0)) | G7: =IF($A7="","",IF($D7="V01",Cadrage!$C$22,IF($D7="V02",Cadrage!$D$22,Cadrage!$E$22))) | H7: =IF($A7="","",IF($D7="V01",Cadrage!$C$23,IF($D7="V02",Cadrage!$D$23,Cadrage!$E$23))) | I7: =IF($A7="","",IF($D7="V01",Cadrage!$C$31,IF($D7="V02",Cadrage!$D$31,Cadrage!$E$31))) | J7: =IF($A7="","",IF($D7="V01",Cadrage!$C$32,IF($D7="V02",Cadrage!$D$32,Cadrage!$E$32))) | K7: =IF($A7="","",IF($D7="V01",Cadrage!$C$33,IF($D7="V02",Cadrage!$D$33,Cadrage!$E$33))) | L7: =IF($A7="","",IF($D7="V01",Cadrage!$C$34,IF($D7="V02",Cadrage!$D$34,Cadrage!$E$34))) | M7: =IF($A7="","",IF($D7="V01",Cadrage!$C$35,IF($D7="V02",Cadrage!$D$35,Cadrage!$E$35))) | N7: =IF($A7="","",IF($D7="V01",$R$2,IF($D7="V02",$R$3,$R$4))) | O7: =IF($A7="","",IF(OR($B7="7062",$B7="706",$B7="708"),$N7,IF($B7="6231",1+$G7,IF($B7="6236",1+$H7,IF(OR($B7="621",$B7="604",$B7="6063"),$N7*(1-$L7),IF(OR($B7="6411",$B7="6413",$B7="6414",$B7="645"),(1+$J7)*(1+$K7),IF(OR($B7="613",$B7="615",$B7="616",$B7="6226",$B7="625",$B7="626",$B7="6281"),(1+$I7)*(1-$L7)*(1+$M7),IF(OR($B7="6331",$B7="63511",$B7="6333"),(1+$I7)*(1-$L7),IF($B7="6811",1+$I7,1))))))))) | P7: =IF($A7="","",IF($E7=1,$F7*$O7,PNL!G7)) | T7: =IF($A7="","",IF($E7=1,IF(OR($B7="7062",$B7="706",$B7="708"),$P7,IF(AND(LEFT($B7,1)="6",$B7<>"6811"),-$P7,0)),0))
A8: =IF(PNL!A8="","",PNL!A8) | B8: =IF(PNL!B8="","",PNL!B8) | C8: =IF(PNL!C8="","",PNL!C8) | D8: =IF(PNL!D8="","",PNL!D8) | E8: =IF($A8="","",IF(AND($C8="2027",OR($D8="V01",$D8="V02",$D8="V03")),1,0)) | F8: =IF($A8="","",IF($E8=1,SUMIFS(Comptabilité!$F$1:$F$675,Comptabilité!$A$1:$A$675,$A8,Comptabilité!$B$1:$B$675,$B8,Comptabilité!$C$1:$C$675,"2026"),0)) | G8: =IF($A8="","",IF($D8="V01",Cadrage!$C$22,IF($D8="V02",Cadrage!$D$22,Cadrage!$E$22))) | H8: =IF($A8="","",IF($D8="V01",Cadrage!$C$23,IF($D8="V02",Cadrage!$D$23,Cadrage!$E$23))) | I8: =IF($A8="","",IF($D8="V01",Cadrage!$C$31,IF($D8="V02",Cadrage!$D$31,Cadrage!$E$31))) | J8: =IF($A8="","",IF($D8="V01",Cadrage!$C$32,IF($D8="V02",Cadrage!$D$32,Cadrage!$E$32))) | K8: =IF($A8="","",IF($D8="V01",Cadrage!$C$33,IF($D8="V02",Cadrage!$D$33,Cadrage!$E$33))) | L8: =IF($A8="","",IF($D8="V01",Cadrage!$C$34,IF($D8="V02",Cadrage!$D$34,Cadrage!$E$34))) | M8: =IF($A8="","",IF($D8="V01",Cadrage!$C$35,IF($D8="V02",Cadrage!$D$35,Cadrage!$E$35))) | N8: =IF($A8="","",IF($D8="V01",$R$2,IF($D8="V02",$R$3,$R$4))) | O8: =IF($A8="","",IF(OR($B8="7062",$B8="706",$B8="708"),$N8,IF($B8="6231",1+$G8,IF($B8="6236",1+$H8,IF(OR($B8="621",$B8="604",$B8="6063"),$N8*(1-$L8),IF(OR($B8="6411",$B8="6413",$B8="6414",$B8="645"),(1+$J8)*(1+$K8),IF(OR($B8="613",$B8="615",$B8="616",$B8="6226",$B8="625",$B8="626",$B8="6281"),(1+$I8)*(1-$L8)*(1+$M8),IF(OR($B8="6331",$B8="63511",$B8="6333"),(1+$I8)*(1-$L8),IF($B8="6811",1+$I8,1))))))))) | P8: =IF($A8="","",IF($E8=1,$F8*$O8,PNL!G8)) | T8: =IF($A8="","",IF($E8=1,IF(OR($B8="7062",$B8="706",$B8="708"),$P8,IF(AND(LEFT($B8,1)="6",$B8<>"6811"),-$P8,0)),0))
A9: =IF(PNL!A9="","",PNL!A9) | B9: =IF(PNL!B9="","",PNL!B9) | C9: =IF(PNL!C9="","",PNL!C9) | D9: =IF(PNL!D9="","",PNL!D9) | E9: =IF($A9="","",IF(AND($C9="2027",OR($D9="V01",$D9="V02",$D9="V03")),1,0)) | F9: =IF($A9="","",IF($E9=1,SUMIFS(Comptabilité!$F$1:$F$675,Comptabilité!$A$1:$A$675,$A9,Comptabilité!$B$1:$B$675,$B9,Comptabilité!$C$1:$C$675,"2026"),0)) | G9: =IF($A9="","",IF($D9="V01",Cadrage!$C$22,IF($D9="V02",Cadrage!$D$22,Cadrage!$E$22))) | H9: =IF($A9="","",IF($D9="V01",Cadrage!$C$23,IF($D9="V02",Cadrage!$D$23,Cadrage!$E$23))) | I9: =IF($A9="","",IF($D9="V01",Cadrage!$C$31,IF($D9="V02",Cadrage!$D$31,Cadrage!$E$31))) | J9: =IF($A9="","",IF($D9="V01",Cadrage!$C$32,IF($D9="V02",Cadrage!$D$32,Cadrage!$E$32))) | K9: =IF($A9="","",IF($D9="V01",Cadrage!$C$33,IF($D9="V02",Cadrage!$D$33,Cadrage!$E$33))) | L9: =IF($A9="","",IF($D9="V01",Cadrage!$C$34,IF($D9="V02",Cadrage!$D$34,Cadrage!$E$34))) | M9: =IF($A9="","",IF($D9="V01",Cadrage!$C$35,IF($D9="V02",Cadrage!$D$35,Cadrage!$E$35))) | N9: =IF($A9="","",IF($D9="V01",$R$2,IF($D9="V02",$R$3,$R$4))) | O9: =IF($A9="","",IF(OR($B9="7062",$B9="706",$B9="708"),$N9,IF($B9="6231",1+$G9,IF($B9="6236",1+$H9,IF(OR($B9="621",$B9="604",$B9="6063"),$N9*(1-$L9),IF(OR($B9="6411",$B9="6413",$B9="6414",$B9="645"),(1+$J9)*(1+$K9),IF(OR($B9="613",$B9="615",$B9="616",$B9="6226",$B9="625",$B9="626",$B9="6281"),(1+$I9)*(1-$L9)*(1+$M9),IF(OR($B9="6331",$B9="63511",$B9="6333"),(1+$I9)*(1-$L9),IF($B9="6811",1+$I9,1))))))))) | P9: =IF($A9="","",IF($E9=1,$F9*$O9,PNL!G9)) | T9: =IF($A9="","",IF($E9=1,IF(OR($B9="7062",$B9="706",$B9="708"),$P9,IF(AND(LEFT($B9,1)="6",$B9<>"6811"),-$P9,0)),0))
A10: =IF(PNL!A10="","",PNL!A10) | B10: =IF(PNL!B10="","",PNL!B10) | C10: =IF(PNL!C10="","",PNL!C10) | D10: =IF(PNL!D10="","",PNL!D10) | E10: =IF($A10="","",IF(AND($C10="2027",OR($D10="V01",$D10="V02",$D10="V03")),1,0)) | F10: =IF($A10="","",IF($E10=1,SUMIFS(Comptabilité!$F$1:$F$675,Comptabilité!$A$1:$A$675,$A10,Comptabilité!$B$1:$B$675,$B10,Comptabilité!$C$1:$C$675,"2026"),0)) | G10: =IF($A10="","",IF($D10="V01",Cadrage!$C$22,IF($D10="V02",Cadrage!$D$22,Cadrage!$E$22))) | H10: =IF($A10="","",IF($D10="V01",Cadrage!$C$23,IF($D10="V02",Cadrage!$D$23,Cadrage!$E$23))) | I10: =IF($A10="","",IF($D10="V01",Cadrage!$C$31,IF($D10="V02",Cadrage!$D$31,Cadrage!$E$31))) | J10: =IF($A10="","",IF($D10="V01",Cadrage!$C$32,IF($D10="V02",Cadrage!$D$32,Cadrage!$E$32))) | K10: =IF($A10="","",IF($D10="V01",Cadrage!$C$33,IF($D10="V02",Cadrage!$D$33,Cadrage!$E$33))) | L10: =IF($A10="","",IF($D10="V01",Cadrage!$C$34,IF($D10="V02",Cadrage!$D$34,Cadrage!$E$34))) | M10: =IF($A10="","",IF($D10="V01",Cadrage!$C$35,IF($D10="V02",Cadrage!$D$35,Cadrage!$E$35))) | N10: =IF($A10="","",IF($D10="V01",$R$2,IF($D10="V02",$R$3,$R$4))) | O10: =IF($A10="","",IF(OR($B10="7062",$B10="706",$B10="708"),$N10,IF($B10="6231",1+$G10,IF($B10="6236",1+$H10,IF(OR($B10="621",$B10="604",$B10="6063"),$N10*(1-$L10),IF(OR($B10="6411",$B10="6413",$B10="6414",$B10="645"),(1+$J10)*(1+$K10),IF(OR($B10="613",$B10="615",$B10="616",$B10="6226",$B10="625",$B10="626",$B10="6281"),(1+$I10)*(1-$L10)*(1+$M10),IF(OR($B10="6331",$B10="63511",$B10="6333"),(1+$I10)*(1-$L10),IF($B10="6811",1+$I10,1))))))))) | P10: =IF($A10="","",IF($E10=1,$F10*$O10,PNL!G10)) | T10: =IF($A10="","",IF($E10=1,IF(OR($B10="7062",$B10="706",$B10="708"),$P10,IF(AND(LEFT($B10,1)="6",$B10<>"6811"),-$P10,0)),0))
A11: =IF(PNL!A11="","",PNL!A11) | B11: =IF(PNL!B11="","",PNL!B11) | C11: =IF(PNL!C11="","",PNL!C11) | D11: =IF(PNL!D11="","",PNL!D11) | E11: =IF($A11="","",IF(AND($C11="2027",OR($D11="V01",$D11="V02",$D11="V03")),1,0)) | F11: =IF($A11="","",IF($E11=1,SUMIFS(Comptabilité!$F$1:$F$675,Comptabilité!$A$1:$A$675,$A11,Comptabilité!$B$1:$B$675,$B11,Comptabilité!$C$1:$C$675,"2026"),0)) | G11: =IF($A11="","",IF($D11="V01",Cadrage!$C$22,IF($D11="V02",Cadrage!$D$22,Cadrage!$E$22))) | H11: =IF($A11="","",IF($D11="V01",Cadrage!$C$23,IF($D11="V02",Cadrage!$D$23,Cadrage!$E$23))) | I11: =IF($A11="","",IF($D11="V01",Cadrage!$C$31,IF($D11="V02",Cadrage!$D$31,Cadrage!$E$31))) | J11: =IF($A11="","",IF($D11="V01",Cadrage!$C$32,IF($D11="V02",Cadrage!$D$32,Cadrage!$E$32))) | K11: =IF($A11="","",IF($D11="V01",Cadrage!$C$33,IF($D11="V02",Cadrage!$D$33,Cadrage!$E$33))) | L11: =IF($A11="","",IF($D11="V01",Cadrage!$C$34,IF($D11="V02",Cadrage!$D$34,Cadrage!$E$34))) | M11: =IF($A11="","",IF($D11="V01",Cadrage!$C$35,IF($D11="V02",Cadrage!$D$35,Cadrage!$E$35))) | N11: =IF($A11="","",IF($D11="V01",$R$2,IF($D11="V02",$R$3,$R$4))) | O11: =IF($A11="","",IF(OR($B11="7062",$B11="706",$B11="708"),$N11,IF($B11="6231",1+$G11,IF($B11="6236",1+$H11,IF(OR($B11="621",$B11="604",$B11="6063"),$N11*(1-$L11),IF(OR($B11="6411",$B11="6413",$B11="6414",$B11="645"),(1+$J11)*(1+$K11),IF(OR($B11="613",$B11="615",$B11="616",$B11="6226",$B11="625",$B11="626",$B11="6281"),(1+$I11)*(1-$L11)*(1+$M11),IF(OR($B11="6331",$B11="63511",$B11="6333"),(1+$I11)*(1-$L11),IF($B11="6811",1+$I11,1))))))))) | P11: =IF($A11="","",IF($E11=1,$F11*$O11,PNL!G11)) | T11: =IF($A11="","",IF($E11=1,IF(OR($B11="7062",$B11="706",$B11="708"),$P11,IF(AND(LEFT($B11,1)="6",$B11<>"6811"),-$P11,0)),0))
A12: =IF(PNL!A12="","",PNL!A12) | B12: =IF(PNL!B12="","",PNL!B12) | C12: =IF(PNL!C12="","",PNL!C12) | D12: =IF(PNL!D12="","",PNL!D12) | E12: =IF($A12="","",IF(AND($C12="2027",OR($D12="V01",$D12="V02",$D12="V03")),1,0)) | F12: =IF($A12="","",IF($E12=1,SUMIFS(Comptabilité!$F$1:$F$675,Comptabilité!$A$1:$A$675,$A12,Comptabilité!$B$1:$B$675,$B12,Comptabilité!$C$1:$C$675,"2026"),0)) | G12: =IF($A12="","",IF($D12="V01",Cadrage!$C$22,IF($D12="V02",Cadrage!$D$22,Cadrage!$E$22))) | H12: =IF($A12="","",IF($D12="V01",Cadrage!$C$23,IF($D12="V02",Cadrage!$D$23,Cadrage!$E$23))) | I12: =IF($A12="","",IF($D12="V01",Cadrage!$C$31,IF($D12="V02",Cadrage!$D$31,Cadrage!$E$31))) | J12: =IF($A12="","",IF($D12="V01",Cadrage!$C$32,IF($D12="V02",Cadrage!$D$32,Cadrage!$E$32))) | K12: =IF($A12="","",IF($D12="V01",Cadrage!$C$33,IF($D12="V02",Cadrage!$D$33,Cadrage!$E$33))) | L12: =IF($A12="","",IF($D12="V01",Cadrage!$C$34,IF($D12="V02",Cadrage!$D$34,Cadrage!$E$34))) | M12: =IF($A12="","",IF($D12="V01",Cadrage!$C$35,IF($D12="V02",Cadrage!$D$35,Cadrage!$E$35))) | N12: =IF($A12="","",IF($D12="V01",$R$2,IF($D12="V02",$R$3,$R$4))) | O12: =IF($A12="","",IF(OR($B12="7062",$B12="706",$B12="708"),$N12,IF($B12="6231",1+$G12,IF($B12="6236",1+$H12,IF(OR($B12="621",$B12="604",$B12="6063"),$N12*(1-$L12),IF(OR($B12="6411",$B12="6413",$B12="6414",$B12="645"),(1+$J12)*(1+$K12),IF(OR($B12="613",$B12="615",$B12="616",$B12="6226",$B12="625",$B12="626",$B12="6281"),(1+$I12)*(1-$L12)*(1+$M12),IF(OR($B12="6331",$B12="63511",$B12="6333"),(1+$I12)*(1-$L12),IF($B12="6811",1+$I12,1))))))))) | P12: =IF($A12="","",IF($E12=1,$F12*$O12,PNL!G12)) | T12: =IF($A12="","",IF($E12=1,IF(OR($B12="7062",$B12="706",$B12="708"),$P12,IF(AND(LEFT($B12,1)="6",$B12<>"6811"),-$P12,0)),0))
A13: =IF(PNL!A13="","",PNL!A13) | B13: =IF(PNL!B13="","",PNL!B13) | C13: =IF(PNL!C13="","",PNL!C13) | D13: =IF(PNL!D13="","",PNL!D13) | E13: =IF($A13="","",IF(AND($C13="2027",OR($D13="V01",$D13="V02",$D13="V03")),1,0)) | F13: =IF($A13="","",IF($E13=1,SUMIFS(Comptabilité!$F$1:$F$675,Comptabilité!$A$1:$A$675,$A13,Comptabilité!$B$1:$B$675,$B13,Comptabilité!$C$1:$C$675,"2026"),0)) | G13: =IF($A13="","",IF($D13="V01",Cadrage!$C$22,IF($D13="V02",Cadrage!$D$22,Cadrage!$E$22))) | H13: =IF($A13="","",IF($D13="V01",Cadrage!$C$23,IF($D13="V02",Cadrage!$D$23,Cadrage!$E$23))) | I13: =IF($A13="","",IF($D13="V01",Cadrage!$C$31,IF($D13="V02",Cadrage!$D$31,Cadrage!$E$31))) | J13: =IF($A13="","",IF($D13="V01",Cadrage!$C$32,IF($D13="V02",Cadrage!$D$32,Cadrage!$E$32))) | K13: =IF($A13="","",IF($D13="V01",Cadrage!$C$33,IF($D13="V02",Cadrage!$D$33,Cadrage!$E$33))) | L13: =IF($A13="","",IF($D13="V01",Cadrage!$C$34,IF($D13="V02",Cadrage!$D$34,Cadrage!$E$34))) | M13: =IF($A13="","",IF($D13="V01",Cadrage!$C$35,IF($D13="V02",Cadrage!$D$35,Cadrage!$E$35))) | N13: =IF($A13="","",IF($D13="V01",$R$2,IF($D13="V02",$R$3,$R$4))) | O13: =IF($A13="","",IF(OR($B13="7062",$B13="706",$B13="708"),$N13,IF($B13="6231",1+$G13,IF($B13="6236",1+$H13,IF(OR($B13="621",$B13="604",$B13="6063"),$N13*(1-$L13),IF(OR($B13="6411",$B13="6413",$B13="6414",$B13="645"),(1+$J13)*(1+$K13),IF(OR($B13="613",$B13="615",$B13="616",$B13="6226",$B13="625",$B13="626",$B13="6281"),(1+$I13)*(1-$L13)*(1+$M13),IF(OR($B13="6331",$B13="63511",$B13="6333"),(1+$I13)*(1-$L13),IF($B13="6811",1+$I13,1))))))))) | P13: =IF($A13="","",IF($E13=1,$F13*$O13,PNL!G13)) | T13: =IF($A13="","",IF($E13=1,IF(OR($B13="7062",$B13="706",$B13="708"),$P13,IF(AND(LEFT($B13,1)="6",$B13<>"6811"),-$P13,0)),0))
A14: =IF(PNL!A14="","",PNL!A14) | B14: =IF(PNL!B14="","",PNL!B14) | C14: =IF(PNL!C14="","",PNL!C14) | D14: =IF(PNL!D14="","",PNL!D14) | E14: =IF($A14="","",IF(AND($C14="2027",OR($D14="V01",$D14="V02",$D14="V03")),1,0)) | F14: =IF($A14="","",IF($E14=1,SUMIFS(Comptabilité!$F$1:$F$675,Comptabilité!$A$1:$A$675,$A14,Comptabilité!$B$1:$B$675,$B14,Comptabilité!$C$1:$C$675,"2026"),0)) | G14: =IF($A14="","",IF($D14="V01",Cadrage!$C$22,IF($D14="V02",Cadrage!$D$22,Cadrage!$E$22))) | H14: =IF($A14="","",IF($D14="V01",Cadrage!$C$23,IF($D14="V02",Cadrage!$D$23,Cadrage!$E$23))) | I14: =IF($A14="","",IF($D14="V01",Cadrage!$C$31,IF($D14="V02",Cadrage!$D$31,Cadrage!$E$31))) | J14: =IF($A14="","",IF($D14="V01",Cadrage!$C$32,IF($D14="V02",Cadrage!$D$32,Cadrage!$E$32))) | K14: =IF($A14="","",IF($D14="V01",Cadrage!$C$33,IF($D14="V02",Cadrage!$D$33,Cadrage!$E$33))) | L14: =IF($A14="","",IF($D14="V01",Cadrage!$C$34,IF($D14="V02",Cadrage!$D$34,Cadrage!$E$34))) | M14: =IF($A14="","",IF($D14="V01",Cadrage!$C$35,IF($D14="V02",Cadrage!$D$35,Cadrage!$E$35))) | N14: =IF($A14="","",IF($D14="V01",$R$2,IF($D14="V02",$R$3,$R$4))) | O14: =IF($A14="","",IF(OR($B14="7062",$B14="706",$B14="708"),$N14,IF($B14="6231",1+$G14,IF($B14="6236",1+$H14,IF(OR($B14="621",$B14="604",$B14="6063"),$N14*(1-$L14),IF(OR($B14="6411",$B14="6413",$B14="6414",$B14="645"),(1+$J14)*(1+$K14),IF(OR($B14="613",$B14="615",$B14="616",$B14="6226",$B14="625",$B14="626",$B14="6281"),(1+$I14)*(1-$L14)*(1+$M14),IF(OR($B14="6331",$B14="63511",$B14="6333"),(1+$I14)*(1-$L14),IF($B14="6811",1+$I14,1))))))))) | P14: =IF($A14="","",IF($E14=1,$F14*$O14,PNL!G14)) | T14: =IF($A14="","",IF($E14=1,IF(OR($B14="7062",$B14="706",$B14="708"),$P14,IF(AND(LEFT($B14,1)="6",$B14<>"6811"),-$P14,0)),0))
A15: =IF(PNL!A15="","",PNL!A15) | B15: =IF(PNL!B15="","",PNL!B15) | C15: =IF(PNL!C15="","",PNL!C15) | D15: =IF(PNL!D15="","",PNL!D15) | E15: =IF($A15="","",IF(AND($C15="2027",OR($D15="V01",$D15="V02",$D15="V03")),1,0)) | F15: =IF($A15="","",IF($E15=1,SUMIFS(Comptabilité!$F$1:$F$675,Comptabilité!$A$1:$A$675,$A15,Comptabilité!$B$1:$B$675,$B15,Comptabilité!$C$1:$C$675,"2026"),0)) | G15: =IF($A15="","",IF($D15="V01",Cadrage!$C$22,IF($D15="V02",Cadrage!$D$22,Cadrage!$E$22))) | H15: =IF($A15="","",IF($D15="V01",Cadrage!$C$23,IF($D15="V02",Cadrage!$D$23,Cadrage!$E$23))) | I15: =IF($A15="","",IF($D15="V01",Cadrage!$C$31,IF($D15="V02",Cadrage!$D$31,Cadrage!$E$31))) | J15: =IF($A15="","",IF($D15="V01",Cadrage!$C$32,IF($D15="V02",Cadrage!$D$32,Cadrage!$E$32))) | K15: =IF($A15="","",IF($D15="V01",Cadrage!$C$33,IF($D15="V02",Cadrage!$D$33,Cadrage!$E$33))) | L15: =IF($A15="","",IF($D15="V01",Cadrage!$C$34,IF($D15="V02",Cadrage!$D$34,Cadrage!$E$34))) | M15: =IF($A15="","",IF($D15="V01",Cadrage!$C$35,IF($D15="V02",Cadrage!$D$35,Cadrage!$E$35))) | N15: =IF($A15="","",IF($D15="V01",$R$2,IF($D15="V02",$R$3,$R$4))) | O15: =IF($A15="","",IF(OR($B15="7062",$B15="706",$B15="708"),$N15,IF($B15="6231",1+$G15,IF($B15="6236",1+$H15,IF(OR($B15="621",$B15="604",$B15="6063"),$N15*(1-$L15),IF(OR($B15="6411",$B15="6413",$B15="6414",$B15="645"),(1+$J15)*(1+$K15),IF(OR($B15="613",$B15="615",$B15="616",$B15="6226",$B15="625",$B15="626",$B15="6281"),(1+$I15)*(1-$L15)*(1+$M15),IF(OR($B15="6331",$B15="63511",$B15="6333"),(1+$I15)*(1-$L15),IF($B15="6811",1+$I15,1))))))))) | P15: =IF($A15="","",IF($E15=1,$F15*$O15,PNL!G15)) | T15: =IF($A15="","",IF($E15=1,IF(OR($B15="7062",$B15="706",$B15="708"),$P15,IF(AND(LEFT($B15,1)="6",$B15<>"6811"),-$P15,0)),0))
A16: =IF(PNL!A16="","",PNL!A16) | B16: =IF(PNL!B16="","",PNL!B16) | C16: =IF(PNL!C16="","",PNL!C16) | D16: =IF(PNL!D16="","",PNL!D16) | E16: =IF($A16="","",IF(AND($C16="2027",OR($D16="V01",$D16="V02",$D16="V03")),1,0)) | F16: =IF($A16="","",IF($E16=1,SUMIFS(Comptabilité!$F$1:$F$675,Comptabilité!$A$1:$A$675,$A16,Comptabilité!$B$1:$B$675,$B16,Comptabilité!$C$1:$C$675,"2026"),0)) | G16: =IF($A16="","",IF($D16="V01",Cadrage!$C$22,IF($D16="V02",Cadrage!$D$22,Cadrage!$E$22))) | H16: =IF($A16="","",IF($D16="V01",Cadrage!$C$23,IF($D16="V02",Cadrage!$D$23,Cadrage!$E$23))) | I16: =IF($A16="","",IF($D16="V01",Cadrage!$C$31,IF($D16="V02",Cadrage!$D$31,Cadrage!$E$31))) | J16: =IF($A16="","",IF($D16="V01",Cadrage!$C$32,IF($D16="V02",Cadrage!$D$32,Cadrage!$E$32))) | K16: =IF($A16="","",IF($D16="V01",Cadrage!$C$33,IF($D16="V02",Cadrage!$D$33,Cadrage!$E$33))) | L16: =IF($A16="","",IF($D16="V01",Cadrage!$C$34,IF($D16="V02",Cadrage!$D$34,Cadrage!$E$34))) | M16: =IF($A16="","",IF($D16="V01",Cadrage!$C$35,IF($D16="V02",Cadrage!$D$35,Cadrage!$E$35))) | N16: =IF($A16="","",IF($D16="V01",$R$2,IF($D16="V02",$R$3,$R$4))) | O16: =IF($A16="","",IF(OR($B16="7062",$B16="706",$B16="708"),$N16,IF($B16="6231",1+$G16,IF($B16="6236",1+$H16,IF(OR($B16="621",$B16="604",$B16="6063"),$N16*(1-$L16),IF(OR($B16="6411",$B16="6413",$B16="6414",$B16="645"),(1+$J16)*(1+$K16),IF(OR($B16="613",$B16="615",$B16="616",$B16="6226",$B16="625",$B16="626",$B16="6281"),(1+$I16)*(1-$L16)*(1+$M16),IF(OR($B16="6331",$B16="63511",$B16="6333"),(1+$I16)*(1-$L16),IF($B16="6811",1+$I16,1))))))))) | P16: =IF($A16="","",IF($E16=1,$F16*$O16,PNL!G16)) | T16: =IF($A16="","",IF($E16=1,IF(OR($B16="7062",$B16="706",$B16="708"),$P16,IF(AND(LEFT($B16,1)="6",$B16<>"6811"),-$P16,0)),0))
... A1347: =IF(PNL!A1347="","",PNL!A1347) | B1347: =IF(PNL!B1347="","",PNL!B1347) | C1347: =IF(PNL!C1347="","",PNL!C1347) | D1347: =IF(PNL!D1347="","",PNL!D1347) | E1347: =IF($A1347="","",IF(AND($C1347="2027",OR($D1347="V01",$D1347="V02",$D1347="V03")),1,0)) | F1347: =IF($A1347="","",IF($E1347=1,SUMIFS(Comptabilité!$F$1:$F$675,Comptabilité!$A$1:$A$675,$A1347,Comptabilité!$B$1:$B$675,$B1347,Comptabilité!$C$1:$C$675,"2026"),0)) | G1347: =IF($A1347="","",IF($D1347="V01",Cadrage!$C$22,IF($D1347="V02",Cadrage!$D$22,Cadrage!$E$22))) | H1347: =IF($A1347="","",IF($D1347="V01",Cadrage!$C$23,IF($D1347="V02",Cadrage!$D$23,Cadrage!$E$23))) | I1347: =IF($A1347="","",IF($D1347="V01",Cadrage!$C$31,IF($D1347="V02",Cadrage!$D$31,Cadrage!$E$31))) | J1347: =IF($A1347="","",IF($D1347="V01",Cadrage!$C$32,IF($D1347="V02",Cadrage!$D$32,Cadrage!$E$32))) | K1347: =IF($A1347="","",IF($D1347="V01",Cadrage!$C$33,IF($D1347="V02",Cadrage!$D$33,Cadrage!$E$33))) | L1347: =IF($A1347="","",IF($D1347="V01",Cadrage!$C$34,IF($D1347="V02",Cadrage!$D$34,Cadrage!$E$34))) | M1347: =IF($A1347="","",IF($D1347="V01",Cadrage!$C$35,IF($D1347="V02",Cadrage!$D$35,Cadrage!$E$35))) | N1347: =IF($A1347="","",IF($D1347="V01",$R$2,IF($D1347="V02",$R$3,$R$4))) | O1347: =IF($A1347="","",IF(OR($B1347="7062",$B1347="706",$B1347="708"),$N1347,IF($B1347="6231",1+$G1347,IF($B1347="6236",1+$H1347,IF(OR($B1347="621",$B1347="604",$B1347="6063"),$N1347*(1-$L1347),IF(OR($B1347="6411",$B1347="6413",$B1347="6414",$B1347="645"),(1+$J1347)*(1+$K1347),IF(OR($B1347="613",$B1347="615",$B1347="616",$B1347="6226",$B1347="625",$B1347="626",$B1347="6281"),(1+$I1347)*(1-$L1347)*(1+$M1347),IF(OR($B1347="6331",$B1347="63511",$B1347="6333"),(1+$I1347)*(1-$L1347),IF($B1347="6811",1+$I1347,1))))))))) | P1347: =IF($A1347="","",IF($E1347=1,$F1347*$O1347,PNL!G1347)) | T1347: =IF($A1347="","",IF($E1347=1,IF(OR($B1347="7062",$B1347="706",$B1347="708"),$P1347,IF(AND(LEFT($B1347,1)="6",$B1347<>"6811"),-$P1347,0)),0))
A1348: =IF(PNL!A1348="","",PNL!A1348) | B1348: =IF(PNL!B1348="","",PNL!B1348) | C1348: =IF(PNL!C1348="","",PNL!C1348) | D1348: =IF(PNL!D1348="","",PNL!D1348) | E1348: =IF($A1348="","",IF(AND($C1348="2027",OR($D1348="V01",$D1348="V02",$D1348="V03")),1,0)) | F1348: =IF($A1348="","",IF($E1348=1,SUMIFS(Comptabilité!$F$1:$F$675,Comptabilité!$A$1:$A$675,$A1348,Comptabilité!$B$1:$B$675,$B1348,Comptabilité!$C$1:$C$675,"2026"),0)) | G1348: =IF($A1348="","",IF($D1348="V01",Cadrage!$C$22,IF($D1348="V02",Cadrage!$D$22,Cadrage!$E$22))) | H1348: =IF($A1348="","",IF($D1348="V01",Cadrage!$C$23,IF($D1348="V02",Cadrage!$D$23,Cadrage!$E$23))) | I1348: =IF($A1348="","",IF($D1348="V01",Cadrage!$C$31,IF($D1348="V02",Cadrage!$D$31,Cadrage!$E$31))) | J1348: =IF($A1348="","",IF($D1348="V01",Cadrage!$C$32,IF($D1348="V02",Cadrage!$D$32,Cadrage!$E$32))) | K1348: =IF($A1348="","",IF($D1348="V01",Cadrage!$C$33,IF($D1348="V02",Cadrage!$D$33,Cadrage!$E$33))) | L1348: =IF($A1348="","",IF($D1348="V01",Cadrage!$C$34,IF($D1348="V02",Cadrage!$D$34,Cadrage!$E$34))) | M1348: =IF($A1348="","",IF($D1348="V01",Cadrage!$C$35,IF($D1348="V02",Cadrage!$D$35,Cadrage!$E$35))) | N1348: =IF($A1348="","",IF($D1348="V01",$R$2,IF($D1348="V02",$R$3,$R$4))) | O1348: =IF($A1348="","",IF(OR($B1348="7062",$B1348="706",$B1348="708"),$N1348,IF($B1348="6231",1+$G1348,IF($B1348="6236",1+$H1348,IF(OR($B1348="621",$B1348="604",$B1348="6063"),$N1348*(1-$L1348),IF(OR($B1348="6411",$B1348="6413",$B1348="6414",$B1348="645"),(1+$J1348)*(1+$K1348),IF(OR($B1348="613",$B1348="615",$B1348="616",$B1348="6226",$B1348="625",$B1348="626",$B1348="6281"),(1+$I1348)*(1-$L1348)*(1+$M1348),IF(OR($B1348="6331",$B1348="63511",$B1348="6333"),(1+$I1348)*(1-$L1348),IF($B1348="6811",1+$I1348,1))))))))) | P1348: =IF($A1348="","",IF($E1348=1,$F1348*$O1348,PNL!G1348))
A1349: =IF(PNL!A1349="","",PNL!A1349) | B1349: =IF(PNL!B1349="","",PNL!B1349) | C1349: =IF(PNL!C1349="","",PNL!C1349) | D1349: =IF(PNL!D1349="","",PNL!D1349) | E1349: =IF($A1349="","",IF(AND($C1349="2027",OR($D1349="V01",$D1349="V02",$D1349="V03")),1,0)) | F1349: =IF($A1349="","",IF($E1349=1,SUMIFS(Comptabilité!$F$1:$F$675,Comptabilité!$A$1:$A$675,$A1349,Comptabilité!$B$1:$B$675,$B1349,Comptabilité!$C$1:$C$675,"2026"),0)) | G1349: =IF($A1349="","",IF($D1349="V01",Cadrage!$C$22,IF($D1349="V02",Cadrage!$D$22,Cadrage!$E$22))) | H1349: =IF($A1349="","",IF($D1349="V01",Cadrage!$C$23,IF($D1349="V02",Cadrage!$D$23,Cadrage!$E$23))) | I1349: =IF($A1349="","",IF($D1349="V01",Cadrage!$C$31,IF($D1349="V02",Cadrage!$D$31,Cadrage!$E$31))) | J1349: =IF($A1349="","",IF($D1349="V01",Cadrage!$C$32,IF($D1349="V02",Cadrage!$D$32,Cadrage!$E$32))) | K1349: =IF($A1349="","",IF($D1349="V01",Cadrage!$C$33,IF($D1349="V02",Cadrage!$D$33,Cadrage!$E$33))) | L1349: =IF($A1349="","",IF($D1349="V01",Cadrage!$C$34,IF($D1349="V02",Cadrage!$D$34,Cadrage!$E$34))) | M1349: =IF($A1349="","",IF($D1349="V01",Cadrage!$C$35,IF($D1349="V02",Cadrage!$D$35,Cadrage!$E$35))) | N1349: =IF($A1349="","",IF($D1349="V01",$R$2,IF($D1349="V02",$R$3,$R$4))) | O1349: =IF($A1349="","",IF(OR($B1349="7062",$B1349="706",$B1349="708"),$N1349,IF($B1349="6231",1+$G1349,IF($B1349="6236",1+$H1349,IF(OR($B1349="621",$B1349="604",$B1349="6063"),$N1349*(1-$L1349),IF(OR($B1349="6411",$B1349="6413",$B1349="6414",$B1349="645"),(1+$J1349)*(1+$K1349),IF(OR($B1349="613",$B1349="615",$B1349="616",$B1349="6226",$B1349="625",$B1349="626",$B1349="6281"),(1+$I1349)*(1-$L1349)*(1+$M1349),IF(OR($B1349="6331",$B1349="63511",$B1349="6333"),(1+$I1349)*(1-$L1349),IF($B1349="6811",1+$I1349,1))))))))) | P1349: =IF($A1349="","",IF($E1349=1,$F1349*$O1349,PNL!G1349))
A1350: =IF(PNL!A1350="","",PNL!A1350) | B1350: =IF(PNL!B1350="","",PNL!B1350) | C1350: =IF(PNL!C1350="","",PNL!C1350) | D1350: =IF(PNL!D1350="","",PNL!D1350) | E1350: =IF($A1350="","",IF(AND($C1350="2027",OR($D1350="V01",$D1350="V02",$D1350="V03")),1,0)) | F1350: =IF($A1350="","",IF($E1350=1,SUMIFS(Comptabilité!$F$1:$F$675,Comptabilité!$A$1:$A$675,$A1350,Comptabilité!$B$1:$B$675,$B1350,Comptabilité!$C$1:$C$675,"2026"),0)) | G1350: =IF($A1350="","",IF($D1350="V01",Cadrage!$C$22,IF($D1350="V02",Cadrage!$D$22,Cadrage!$E$22))) | H1350: =IF($A1350="","",IF($D1350="V01",Cadrage!$C$23,IF($D1350="V02",Cadrage!$D$23,Cadrage!$E$23))) | I1350: =IF($A1350="","",IF($D1350="V01",Cadrage!$C$31,IF($D1350="V02",Cadrage!$D$31,Cadrage!$E$31))) | J1350: =IF($A1350="","",IF($D1350="V01",Cadrage!$C$32,IF($D1350="V02",Cadrage!$D$32,Cadrage!$E$32))) | K1350: =IF($A1350="","",IF($D1350="V01",Cadrage!$C$33,IF($D1350="V02",Cadrage!$D$33,Cadrage!$E$33))) | L1350: =IF($A1350="","",IF($D1350="V01",Cadrage!$C$34,IF($D1350="V02",Cadrage!$D$34,Cadrage!$E$34))) | M1350: =IF($A1350="","",IF($D1350="V01",Cadrage!$C$35,IF($D1350="V02",Cadrage!$D$35,Cadrage!$E$35))) | N1350: =IF($A1350="","",IF($D1350="V01",$R$2,IF($D1350="V02",$R$3,$R$4))) | O1350: =IF($A1350="","",IF(OR($B1350="7062",$B1350="706",$B1350="708"),$N1350,IF($B1350="6231",1+$G1350,IF($B1350="6236",1+$H1350,IF(OR($B1350="621",$B1350="604",$B1350="6063"),$N1350*(1-$L1350),IF(OR($B1350="6411",$B1350="6413",$B1350="6414",$B1350="645"),(1+$J1350)*(1+$K1350),IF(OR($B1350="613",$B1350="615",$B1350="616",$B1350="6226",$B1350="625",$B1350="626",$B1350="6281"),(1+$I1350)*(1-$L1350)*(1+$M1350),IF(OR($B1350="6331",$B1350="63511",$B1350="6333"),(1+$I1350)*(1-$L1350),IF($B1350="6811",1+$I1350,1))))))))) | P1350: =IF($A1350="","",IF($E1350=1,$F1350*$O1350,PNL!G1350))
A1351: =IF(PNL!A1351="","",PNL!A1351) | B1351: =IF(PNL!B1351="","",PNL!B1351) | C1351: =IF(PNL!C1351="","",PNL!C1351) | D1351: =IF(PNL!D1351="","",PNL!D1351) | E1351: =IF($A1351="","",IF(AND($C1351="2027",OR($D1351="V01",$D1351="V02",$D1351="V03")),1,0)) | F1351: =IF($A1351="","",IF($E1351=1,SUMIFS(Comptabilité!$F$1:$F$675,Comptabilité!$A$1:$A$675,$A1351,Comptabilité!$B$1:$B$675,$B1351,Comptabilité!$C$1:$C$675,"2026"),0)) | G1351: =IF($A1351="","",IF($D1351="V01",Cadrage!$C$22,IF($D1351="V02",Cadrage!$D$22,Cadrage!$E$22))) | H1351: =IF($A1351="","",IF($D1351="V01",Cadrage!$C$23,IF($D1351="V02",Cadrage!$D$23,Cadrage!$E$23))) | I1351: =IF($A1351="","",IF($D1351="V01",Cadrage!$C$31,IF($D1351="V02",Cadrage!$D$31,Cadrage!$E$31))) | J1351: =IF($A1351="","",IF($D1351="V01",Cadrage!$C$32,IF($D1351="V02",Cadrage!$D$32,Cadrage!$E$32))) | K1351: =IF($A1351="","",IF($D1351="V01",Cadrage!$C$33,IF($D1351="V02",Cadrage!$D$33,Cadrage!$E$33))) | L1351: =IF($A1351="","",IF($D1351="V01",Cadrage!$C$34,IF($D1351="V02",Cadrage!$D$34,Cadrage!$E$34))) | M1351: =IF($A1351="","",IF($D1351="V01",Cadrage!$C$35,IF($D1351="V02",Cadrage!$D$35,Cadrage!$E$35))) | N1351: =IF($A1351="","",IF($D1351="V01",$R$2,IF($D1351="V02",$R$3,$R$4))) | O1351: =IF($A1351="","",IF(OR($B1351="7062",$B1351="706",$B1351="708"),$N1351,IF($B1351="6231",1+$G1351,IF($B1351="6236",1+$H1351,IF(OR($B1351="621",$B1351="604",$B1351="6063"),$N1351*(1-$L1351),IF(OR($B1351="6411",$B1351="6413",$B1351="6414",$B1351="645"),(1+$J1351)*(1+$K1351),IF(OR($B1351="613",$B1351="615",$B1351="616",$B1351="6226",$B1351="625",$B1351="626",$B1351="6281"),(1+$I1351)*(1-$L1351)*(1+$M1351),IF(OR($B1351="6331",$B1351="63511",$B1351="6333"),(1+$I1351)*(1-$L1351),IF($B1351="6811",1+$I1351,1))))))))) | P1351: =IF($A1351="","",IF($E1351=1,$F1351*$O1351,PNL!G1351))
A1352: =IF(PNL!A1352="","",PNL!A1352) | B1352: =IF(PNL!B1352="","",PNL!B1352) | C1352: =IF(PNL!C1352="","",PNL!C1352) | D1352: =IF(PNL!D1352="","",PNL!D1352) | E1352: =IF($A1352="","",IF(AND($C1352="2027",OR($D1352="V01",$D1352="V02",$D1352="V03")),1,0)) | F1352: =IF($A1352="","",IF($E1352=1,SUMIFS(Comptabilité!$F$1:$F$675,Comptabilité!$A$1:$A$675,$A1352,Comptabilité!$B$1:$B$675,$B1352,Comptabilité!$C$1:$C$675,"2026"),0)) | G1352: =IF($A1352="","",IF($D1352="V01",Cadrage!$C$22,IF($D1352="V02",Cadrage!$D$22,Cadrage!$E$22))) | H1352: =IF($A1352="","",IF($D1352="V01",Cadrage!$C$23,IF($D1352="V02",Cadrage!$D$23,Cadrage!$E$23))) | I1352: =IF($A1352="","",IF($D1352="V01",Cadrage!$C$31,IF($D1352="V02",Cadrage!$D$31,Cadrage!$E$31))) | J1352: =IF($A1352="","",IF($D1352="V01",Cadrage!$C$32,IF($D1352="V02",Cadrage!$D$32,Cadrage!$E$32))) | K1352: =IF($A1352="","",IF($D1352="V01",Cadrage!$C$33,IF($D1352="V02",Cadrage!$D$33,Cadrage!$E$33))) | L1352: =IF($A1352="","",IF($D1352="V01",Cadrage!$C$34,IF($D1352="V02",Cadrage!$D$34,Cadrage!$E$34))) | M1352: =IF($A1352="","",IF($D1352="V01",Cadrage!$C$35,IF($D1352="V02",Cadrage!$D$35,Cadrage!$E$35))) | N1352: =IF($A1352="","",IF($D1352="V01",$R$2,IF($D1352="V02",$R$3,$R$4))) | O1352: =IF($A1352="","",IF(OR($B1352="7062",$B1352="706",$B1352="708"),$N1352,IF($B1352="6231",1+$G1352,IF($B1352="6236",1+$H1352,IF(OR($B1352="621",$B1352="604",$B1352="6063"),$N1352*(1-$L1352),IF(OR($B1352="6411",$B1352="6413",$B1352="6414",$B1352="645"),(1+$J1352)*(1+$K1352),IF(OR($B1352="613",$B1352="615",$B1352="616",$B1352="6226",$B1352="625",$B1352="626",$B1352="6281"),(1+$I1352)*(1-$L1352)*(1+$M1352),IF(OR($B1352="6331",$B1352="63511",$B1352="6333"),(1+$I1352)*(1-$L1352),IF($B1352="6811",1+$I1352,1))))))))) | P1352: =IF($A1352="","",IF($E1352=1,$F1352*$O1352,PNL!G1352))
A1353: =IF(PNL!A1353="","",PNL!A1353) | B1353: =IF(PNL!B1353="","",PNL!B1353) | C1353: =IF(PNL!C1353="","",PNL!C1353) | D1353: =IF(PNL!D1353="","",PNL!D1353) | E1353: =IF($A1353="","",IF(AND($C1353="2027",OR($D1353="V01",$D1353="V02",$D1353="V03")),1,0)) | F1353: =IF($A1353="","",IF($E1353=1,SUMIFS(Comptabilité!$F$1:$F$675,Comptabilité!$A$1:$A$675,$A1353,Comptabilité!$B$1:$B$675,$B1353,Comptabilité!$C$1:$C$675,"2026"),0)) | G1353: =IF($A1353="","",IF($D1353="V01",Cadrage!$C$22,IF($D1353="V02",Cadrage!$D$22,Cadrage!$E$22))) | H1353: =IF($A1353="","",IF($D1353="V01",Cadrage!$C$23,IF($D1353="V02",Cadrage!$D$23,Cadrage!$E$23))) | I1353: =IF($A1353="","",IF($D1353="V01",Cadrage!$C$31,IF($D1353="V02",Cadrage!$D$31,Cadrage!$E$31))) | J1353: =IF($A1353="","",IF($D1353="V01",Cadrage!$C$32,IF($D1353="V02",Cadrage!$D$32,Cadrage!$E$32))) | K1353: =IF($A1353="","",IF($D1353="V01",Cadrage!$C$33,IF($D1353="V02",Cadrage!$D$33,Cadrage!$E$33))) | L1353: =IF($A1353="","",IF($D1353="V01",Cadrage!$C$34,IF($D1353="V02",Cadrage!$D$34,Cadrage!$E$34))) | M1353: =IF($A1353="","",IF($D1353="V01",Cadrage!$C$35,IF($D1353="V02",Cadrage!$D$35,Cadrage!$E$35))) | N1353: =IF($A1353="","",IF($D1353="V01",$R$2,IF($D1353="V02",$R$3,$R$4))) | O1353: =IF($A1353="","",IF(OR($B1353="7062",$B1353="706",$B1353="708"),$N1353,IF($B1353="6231",1+$G1353,IF($B1353="6236",1+$H1353,IF(OR($B1353="621",$B1353="604",$B1353="6063"),$N1353*(1-$L1353),IF(OR($B1353="6411",$B1353="6413",$B1353="6414",$B1353="645"),(1+$J1353)*(1+$K1353),IF(OR($B1353="613",$B1353="615",$B1353="616",$B1353="6226",$B1353="625",$B1353="626",$B1353="6281"),(1+$I1353)*(1-$L1353)*(1+$M1353),IF(OR($B1353="6331",$B1353="63511",$B1353="6333"),(1+$I1353)*(1-$L1353),IF($B1353="6811",1+$I1353,1))))))))) | P1353: =IF($A1353="","",IF($E1353=1,$F1353*$O1353,PNL!G1353))
A1354: =IF(PNL!A1354="","",PNL!A1354) | B1354: =IF(PNL!B1354="","",PNL!B1354) | C1354: =IF(PNL!C1354="","",PNL!C1354) | D1354: =IF(PNL!D1354="","",PNL!D1354) | E1354: =IF($A1354="","",IF(AND($C1354="2027",OR($D1354="V01",$D1354="V02",$D1354="V03")),1,0)) | F1354: =IF($A1354="","",IF($E1354=1,SUMIFS(Comptabilité!$F$1:$F$675,Comptabilité!$A$1:$A$675,$A1354,Comptabilité!$B$1:$B$675,$B1354,Comptabilité!$C$1:$C$675,"2026"),0)) | G1354: =IF($A1354="","",IF($D1354="V01",Cadrage!$C$22,IF($D1354="V02",Cadrage!$D$22,Cadrage!$E$22))) | H1354: =IF($A1354="","",IF($D1354="V01",Cadrage!$C$23,IF($D1354="V02",Cadrage!$D$23,Cadrage!$E$23))) | I1354: =IF($A1354="","",IF($D1354="V01",Cadrage!$C$31,IF($D1354="V02",Cadrage!$D$31,Cadrage!$E$31))) | J1354: =IF($A1354="","",IF($D1354="V01",Cadrage!$C$32,IF($D1354="V02",Cadrage!$D$32,Cadrage!$E$32))) | K1354: =IF($A1354="","",IF($D1354="V01",Cadrage!$C$33,IF($D1354="V02",Cadrage!$D$33,Cadrage!$E$33))) | L1354: =IF($A1354="","",IF($D1354="V01",Cadrage!$C$34,IF($D1354="V02",Cadrage!$D$34,Cadrage!$E$34))) | M1354: =IF($A1354="","",IF($D1354="V01",Cadrage!$C$35,IF($D1354="V02",Cadrage!$D$35,Cadrage!$E$35))) | N1354: =IF($A1354="","",IF($D1354="V01",$R$2,IF($D1354="V02",$R$3,$R$4))) | O1354: =IF($A1354="","",IF(OR($B1354="7062",$B1354="706",$B1354="708"),$N1354,IF($B1354="6231",1+$G1354,IF($B1354="6236",1+$H1354,IF(OR($B1354="621",$B1354="604",$B1354="6063"),$N1354*(1-$L1354),IF(OR($B1354="6411",$B1354="6413",$B1354="6414",$B1354="645"),(1+$J1354)*(1+$K1354),IF(OR($B1354="613",$B1354="615",$B1354="616",$B1354="6226",$B1354="625",$B1354="626",$B1354="6281"),(1+$I1354)*(1-$L1354)*(1+$M1354),IF(OR($B1354="6331",$B1354="63511",$B1354="6333"),(1+$I1354)*(1-$L1354),IF($B1354="6811",1+$I1354,1))))))))) | P1354: =IF($A1354="","",IF($E1354=1,$F1354*$O1354,PNL!G1354))
A1355: =IF(PNL!A1355="","",PNL!A1355) | B1355: =IF(PNL!B1355="","",PNL!B1355) | C1355: =IF(PNL!C1355="","",PNL!C1355) | D1355: =IF(PNL!D1355="","",PNL!D1355) | E1355: =IF($A1355="","",IF(AND($C1355="2027",OR($D1355="V01",$D1355="V02",$D1355="V03")),1,0)) | F1355: =IF($A1355="","",IF($E1355=1,SUMIFS(Comptabilité!$F$1:$F$675,Comptabilité!$A$1:$A$675,$A1355,Comptabilité!$B$1:$B$675,$B1355,Comptabilité!$C$1:$C$675,"2026"),0)) | G1355: =IF($A1355="","",IF($D1355="V01",Cadrage!$C$22,IF($D1355="V02",Cadrage!$D$22,Cadrage!$E$22))) | H1355: =IF($A1355="","",IF($D1355="V01",Cadrage!$C$23,IF($D1355="V02",Cadrage!$D$23,Cadrage!$E$23))) | I1355: =IF($A1355="","",IF($D1355="V01",Cadrage!$C$31,IF($D1355="V02",Cadrage!$D$31,Cadrage!$E$31))) | J1355: =IF($A1355="","",IF($D1355="V01",Cadrage!$C$32,IF($D1355="V02",Cadrage!$D$32,Cadrage!$E$32))) | K1355: =IF($A1355="","",IF($D1355="V01",Cadrage!$C$33,IF($D1355="V02",Cadrage!$D$33,Cadrage!$E$33))) | L1355: =IF($A1355="","",IF($D1355="V01",Cadrage!$C$34,IF($D1355="V02",Cadrage!$D$34,Cadrage!$E$34))) | M1355: =IF($A1355="","",IF($D1355="V01",Cadrage!$C$35,IF($D1355="V02",Cadrage!$D$35,Cadrage!$E$35))) | N1355: =IF($A1355="","",IF($D1355="V01",$R$2,IF($D1355="V02",$R$3,$R$4))) | O1355: =IF($A1355="","",IF(OR($B1355="7062",$B1355="706",$B1355="708"),$N1355,IF($B1355="6231",1+$G1355,IF($B1355="6236",1+$H1355,IF(OR($B1355="621",$B1355="604",$B1355="6063"),$N1355*(1-$L1355),IF(OR($B1355="6411",$B1355="6413",$B1355="6414",$B1355="645"),(1+$J1355)*(1+$K1355),IF(OR($B1355="613",$B1355="615",$B1355="616",$B1355="6226",$B1355="625",$B1355="626",$B1355="6281"),(1+$I1355)*(1-$L1355)*(1+$M1355),IF(OR($B1355="6331",$B1355="63511",$B1355="6333"),(1+$I1355)*(1-$L1355),IF($B1355="6811",1+$I1355,1))))))))) | P1355: =IF($A1355="","",IF($E1355=1,$F1355*$O1355,PNL!G1355))
A1356: =IF(PNL!A1356="","",PNL!A1356) | B1356: =IF(PNL!B1356="","",PNL!B1356) | C1356: =IF(PNL!C1356="","",PNL!C1356) | D1356: =IF(PNL!D1356="","",PNL!D1356) | E1356: =IF($A1356="","",IF(AND($C1356="2027",OR($D1356="V01",$D1356="V02",$D1356="V03")),1,0)) | F1356: =IF($A1356="","",IF($E1356=1,SUMIFS(Comptabilité!$F$1:$F$675,Comptabilité!$A$1:$A$675,$A1356,Comptabilité!$B$1:$B$675,$B1356,Comptabilité!$C$1:$C$675,"2026"),0)) | G1356: =IF($A1356="","",IF($D1356="V01",Cadrage!$C$22,IF($D1356="V02",Cadrage!$D$22,Cadrage!$E$22))) | H1356: =IF($A1356="","",IF($D1356="V01",Cadrage!$C$23,IF($D1356="V02",Cadrage!$D$23,Cadrage!$E$23))) | I1356: =IF($A1356="","",IF($D1356="V01",Cadrage!$C$31,IF($D1356="V02",Cadrage!$D$31,Cadrage!$E$31))) | J1356: =IF($A1356="","",IF($D1356="V01",Cadrage!$C$32,IF($D1356="V02",Cadrage!$D$32,Cadrage!$E$32))) | K1356: =IF($A1356="","",IF($D1356="V01",Cadrage!$C$33,IF($D1356="V02",Cadrage!$D$33,Cadrage!$E$33))) | L1356: =IF($A1356="","",IF($D1356="V01",Cadrage!$C$34,IF($D1356="V02",Cadrage!$D$34,Cadrage!$E$34))) | M1356: =IF($A1356="","",IF($D1356="V01",Cadrage!$C$35,IF($D1356="V02",Cadrage!$D$35,Cadrage!$E$35))) | N1356: =IF($A1356="","",IF($D1356="V01",$R$2,IF($D1356="V02",$R$3,$R$4))) | O1356: =IF($A1356="","",IF(OR($B1356="7062",$B1356="706",$B1356="708"),$N1356,IF($B1356="6231",1+$G1356,IF($B1356="6236",1+$H1356,IF(OR($B1356="621",$B1356="604",$B1356="6063"),$N1356*(1-$L1356),IF(OR($B1356="6411",$B1356="6413",$B1356="6414",$B1356="645"),(1+$J1356)*(1+$K1356),IF(OR($B1356="613",$B1356="615",$B1356="616",$B1356="6226",$B1356="625",$B1356="626",$B1356="6281"),(1+$I1356)*(1-$L1356)*(1+$M1356),IF(OR($B1356="6331",$B1356="63511",$B1356="6333"),(1+$I1356)*(1-$L1356),IF($B1356="6811",1+$I1356,1))))))))) | P1356: =IF($A1356="","",IF($E1356=1,$F1356*$O1356,PNL!G1356))
A1357: =IF(PNL!A1357="","",PNL!A1357) | B1357: =IF(PNL!B1357="","",PNL!B1357) | C1357: =IF(PNL!C1357="","",PNL!C1357) | D1357: =IF(PNL!D1357="","",PNL!D1357) | E1357: =IF($A1357="","",IF(AND($C1357="2027",OR($D1357="V01",$D1357="V02",$D1357="V03")),1,0)) | F1357: =IF($A1357="","",IF($E1357=1,SUMIFS(Comptabilité!$F$1:$F$675,Comptabilité!$A$1:$A$675,$A1357,Comptabilité!$B$1:$B$675,$B1357,Comptabilité!$C$1:$C$675,"2026"),0)) | G1357: =IF($A1357="","",IF($D1357="V01",Cadrage!$C$22,IF($D1357="V02",Cadrage!$D$22,Cadrage!$E$22))) | H1357: =IF($A1357="","",IF($D1357="V01",Cadrage!$C$23,IF($D1357="V02",Cadrage!$D$23,Cadrage!$E$23))) | I1357: =IF($A1357="","",IF($D1357="V01",Cadrage!$C$31,IF($D1357="V02",Cadrage!$D$31,Cadrage!$E$31))) | J1357: =IF($A1357="","",IF($D1357="V01",Cadrage!$C$32,IF($D1357="V02",Cadrage!$D$32,Cadrage!$E$32))) | K1357: =IF($A1357="","",IF($D1357="V01",Cadrage!$C$33,IF($D1357="V02",Cadrage!$D$33,Cadrage!$E$33))) | L1357: =IF($A1357="","",IF($D1357="V01",Cadrage!$C$34,IF($D1357="V02",Cadrage!$D$34,Cadrage!$E$34))) | M1357: =IF($A1357="","",IF($D1357="V01",Cadrage!$C$35,IF($D1357="V02",Cadrage!$D$35,Cadrage!$E$35))) | N1357: =IF($A1357="","",IF($D1357="V01",$R$2,IF($D1357="V02",$R$3,$R$4))) | O1357: =IF($A1357="","",IF(OR($B1357="7062",$B1357="706",$B1357="708"),$N1357,IF($B1357="6231",1+$G1357,IF($B1357="6236",1+$H1357,IF(OR($B1357="621",$B1357="604",$B1357="6063"),$N1357*(1-$L1357),IF(OR($B1357="6411",$B1357="6413",$B1357="6414",$B1357="645"),(1+$J1357)*(1+$K1357),IF(OR($B1357="613",$B1357="615",$B1357="616",$B1357="6226",$B1357="625",$B1357="626",$B1357="6281"),(1+$I1357)*(1-$L1357)*(1+$M1357),IF(OR($B1357="6331",$B1357="63511",$B1357="6333"),(1+$I1357)*(1-$L1357),IF($B1357="6811",1+$I1357,1))))))))) | P1357: =IF($A1357="","",IF($E1357=1,$F1357*$O1357,PNL!G1357))
A1358: =IF(PNL!A1358="","",PNL!A1358) | B1358: =IF(PNL!B1358="","",PNL!B1358) | C1358: =IF(PNL!C1358="","",PNL!C1358) | D1358: =IF(PNL!D1358="","",PNL!D1358) | E1358: =IF($A1358="","",IF(AND($C1358="2027",OR($D1358="V01",$D1358="V02",$D1358="V03")),1,0)) | F1358: =IF($A1358="","",IF($E1358=1,SUMIFS(Comptabilité!$F$1:$F$675,Comptabilité!$A$1:$A$675,$A1358,Comptabilité!$B$1:$B$675,$B1358,Comptabilité!$C$1:$C$675,"2026"),0)) | G1358: =IF($A1358="","",IF($D1358="V01",Cadrage!$C$22,IF($D1358="V02",Cadrage!$D$22,Cadrage!$E$22))) | H1358: =IF($A1358="","",IF($D1358="V01",Cadrage!$C$23,IF($D1358="V02",Cadrage!$D$23,Cadrage!$E$23))) | I1358: =IF($A1358="","",IF($D1358="V01",Cadrage!$C$31,IF($D1358="V02",Cadrage!$D$31,Cadrage!$E$31))) | J1358: =IF($A1358="","",IF($D1358="V01",Cadrage!$C$32,IF($D1358="V02",Cadrage!$D$32,Cadrage!$E$32))) | K1358: =IF($A1358="","",IF($D1358="V01",Cadrage!$C$33,IF($D1358="V02",Cadrage!$D$33,Cadrage!$E$33))) | L1358: =IF($A1358="","",IF($D1358="V01",Cadrage!$C$34,IF($D1358="V02",Cadrage!$D$34,Cadrage!$E$34))) | M1358: =IF($A1358="","",IF($D1358="V01",Cadrage!$C$35,IF($D1358="V02",Cadrage!$D$35,Cadrage!$E$35))) | N1358: =IF($A1358="","",IF($D1358="V01",$R$2,IF($D1358="V02",$R$3,$R$4))) | O1358: =IF($A1358="","",IF(OR($B1358="7062",$B1358="706",$B1358="708"),$N1358,IF($B1358="6231",1+$G1358,IF($B1358="6236",1+$H1358,IF(OR($B1358="621",$B1358="604",$B1358="6063"),$N1358*(1-$L1358),IF(OR($B1358="6411",$B1358="6413",$B1358="6414",$B1358="645"),(1+$J1358)*(1+$K1358),IF(OR($B1358="613",$B1358="615",$B1358="616",$B1358="6226",$B1358="625",$B1358="626",$B1358="6281"),(1+$I1358)*(1-$L1358)*(1+$M1358),IF(OR($B1358="6331",$B1358="63511",$B1358="6333"),(1+$I1358)*(1-$L1358),IF($B1358="6811",1+$I1358,1))))))))) | P1358: =IF($A1358="","",IF($E1358=1,$F1358*$O1358,PNL!G1358))
A1359: =IF(PNL!A1359="","",PNL!A1359) | B1359: =IF(PNL!B1359="","",PNL!B1359) | C1359: =IF(PNL!C1359="","",PNL!C1359) | D1359: =IF(PNL!D1359="","",PNL!D1359) | E1359: =IF($A1359="","",IF(AND($C1359="2027",OR($D1359="V01",$D1359="V02",$D1359="V03")),1,0)) | F1359: =IF($A1359="","",IF($E1359=1,SUMIFS(Comptabilité!$F$1:$F$675,Comptabilité!$A$1:$A$675,$A1359,Comptabilité!$B$1:$B$675,$B1359,Comptabilité!$C$1:$C$675,"2026"),0)) | G1359: =IF($A1359="","",IF($D1359="V01",Cadrage!$C$22,IF($D1359="V02",Cadrage!$D$22,Cadrage!$E$22))) | H1359: =IF($A1359="","",IF($D1359="V01",Cadrage!$C$23,IF($D1359="V02",Cadrage!$D$23,Cadrage!$E$23))) | I1359: =IF($A1359="","",IF($D1359="V01",Cadrage!$C$31,IF($D1359="V02",Cadrage!$D$31,Cadrage!$E$31))) | J1359: =IF($A1359="","",IF($D1359="V01",Cadrage!$C$32,IF($D1359="V02",Cadrage!$D$32,Cadrage!$E$32))) | K1359: =IF($A1359="","",IF($D1359="V01",Cadrage!$C$33,IF($D1359="V02",Cadrage!$D$33,Cadrage!$E$33))) | L1359: =IF($A1359="","",IF($D1359="V01",Cadrage!$C$34,IF($D1359="V02",Cadrage!$D$34,Cadrage!$E$34))) | M1359: =IF($A1359="","",IF($D1359="V01",Cadrage!$C$35,IF($D1359="V02",Cadrage!$D$35,Cadrage!$E$35))) | N1359: =IF($A1359="","",IF($D1359="V01",$R$2,IF($D1359="V02",$R$3,$R$4))) | O1359: =IF($A1359="","",IF(OR($B1359="7062",$B1359="706",$B1359="708"),$N1359,IF($B1359="6231",1+$G1359,IF($B1359="6236",1+$H1359,IF(OR($B1359="621",$B1359="604",$B1359="6063"),$N1359*(1-$L1359),IF(OR($B1359="6411",$B1359="6413",$B1359="6414",$B1359="645"),(1+$J1359)*(1+$K1359),IF(OR($B1359="613",$B1359="615",$B1359="616",$B1359="6226",$B1359="625",$B1359="626",$B1359="6281"),(1+$I1359)*(1-$L1359)*(1+$M1359),IF(OR($B1359="6331",$B1359="63511",$B1359="6333"),(1+$I1359)*(1-$L1359),IF($B1359="6811",1+$I1359,1))))))))) | P1359: =IF($A1359="","",IF($E1359=1,$F1359*$O1359,PNL!G1359))
... A1435: =IF(PNL!A1435="","",PNL!A1435) | B1435: =IF(PNL!B1435="","",PNL!B1435) | C1435: =IF(PNL!C1435="","",PNL!C1435) | D1435: =IF(PNL!D1435="","",PNL!D1435) | E1435: =IF($A1435="","",IF(AND($C1435="2027",OR($D1435="V01",$D1435="V02",$D1435="V03")),1,0)) | F1435: =IF($A1435="","",IF($E1435=1,SUMIFS(Comptabilité!$F$1:$F$675,Comptabilité!$A$1:$A$675,$A1435,Comptabilité!$B$1:$B$675,$B1435,Comptabilité!$C$1:$C$675,"2026"),0)) | G1435: =IF($A1435="","",IF($D1435="V01",Cadrage!$C$22,IF($D1435="V02",Cadrage!$D$22,Cadrage!$E$22))) | H1435: =IF($A1435="","",IF($D1435="V01",Cadrage!$C$23,IF($D1435="V02",Cadrage!$D$23,Cadrage!$E$23))) | I1435: =IF($A1435="","",IF($D1435="V01",Cadrage!$C$31,IF($D1435="V02",Cadrage!$D$31,Cadrage!$E$31))) | J1435: =IF($A1435="","",IF($D1435="V01",Cadrage!$C$32,IF($D1435="V02",Cadrage!$D$32,Cadrage!$E$32))) | K1435: =IF($A1435="","",IF($D1435="V01",Cadrage!$C$33,IF($D1435="V02",Cadrage!$D$33,Cadrage!$E$33))) | L1435: =IF($A1435="","",IF($D1435="V01",Cadrage!$C$34,IF($D1435="V02",Cadrage!$D$34,Cadrage!$E$34))) | M1435: =IF($A1435="","",IF($D1435="V01",Cadrage!$C$35,IF($D1435="V02",Cadrage!$D$35,Cadrage!$E$35))) | N1435: =IF($A1435="","",IF($D1435="V01",$R$2,IF($D1435="V02",$R$3,$R$4))) | O1435: =IF($A1435="","",IF(OR($B1435="7062",$B1435="706",$B1435="708"),$N1435,IF($B1435="6231",1+$G1435,IF($B1435="6236",1+$H1435,IF(OR($B1435="621",$B1435="604",$B1435="6063"),$N1435*(1-$L1435),IF(OR($B1435="6411",$B1435="6413",$B1435="6414",$B1435="645"),(1+$J1435)*(1+$K1435),IF(OR($B1435="613",$B1435="615",$B1435="616",$B1435="6226",$B1435="625",$B1435="626",$B1435="6281"),(1+$I1435)*(1-$L1435)*(1+$M1435),IF(OR($B1435="6331",$B1435="63511",$B1435="6333"),(1+$I1435)*(1-$L1435),IF($B1435="6811",1+$I1435,1))))))))) | P1435: =IF($A1435="","",IF($E1435=1,$F1435*$O1435,PNL!G1435))
