Workbook
Name BUD_REF_CAP: Pilotage!$K$19:$K$32
Name HYP_ACQ_BUD_V01: Cadrage!$C$23
Name HYP_ACQ_BUD_V02: Cadrage!$D$23
Name HYP_ACQ_BUD_V03: Cadrage!$E$23
Name HYP_BRAND_BUD_V01: Cadrage!$C$24
Name HYP_BRAND_BUD_V02: Cadrage!$D$24
Name HYP_BRAND_BUD_V03: Cadrage!$E$24
Name HYP_CAP_RETENU: Pilotage!$J$19:$J$32
Name HYP_CONV_ADM_V01: Cadrage!$C$27
Name HYP_CONV_ADM_V02: Cadrage!$D$27
Name HYP_CONV_ADM_V03: Cadrage!$E$27
Name HYP_CONV_LEAD_V01: Cadrage!$C$26
Name HYP_CONV_LEAD_V02: Cadrage!$D$26
Name HYP_CONV_LEAD_V03: Cadrage!$E$26
Name HYP_FEE_V01: Cadrage!$C$42
Name HYP_FEE_V02: Cadrage!$D$42
Name HYP_FEE_V03: Cadrage!$E$42
Name HYP_FTE_PERM_V01: Cadrage!$C$34
Name HYP_FTE_PERM_V02: Cadrage!$D$34
Name HYP_FTE_PERM_V03: Cadrage!$E$34
Name HYP_INFL_EXT_V01: Cadrage!$C$32
Name HYP_INFL_EXT_V02: Cadrage!$D$32
Name HYP_INFL_EXT_V03: Cadrage!$E$32
Name HYP_PASSAGE_V01: Cadrage!$C$28
Name HYP_PASSAGE_V02: Cadrage!#REF!
Name HYP_PASSAGE_V03: Cadrage!$D$28
Name HYP_PRICE_COEF_IPAC: Cadrage!#REF!
Name HYP_PRICE_COEF_ISCOM: Cadrage!$K$35
Name HYP_PRICE_COEF_MBWAY: Cadrage!$K$34
Name HYP_PRICE_COEF_PIGIER: Cadrage!$K$36
Name HYP_PRICE_COEF_TUNON: Cadrage!#REF!
Name HYP_PRICE_V01: Cadrage!$C$25
Name HYP_PRICE_V02: Cadrage!$D$25
Name HYP_PRICE_V03: Cadrage!$E$25
Name HYP_PRODUCTIVITY_V01: Cadrage!$C$35
Name HYP_PRODUCTIVITY_V02: Cadrage!$D$35
Name HYP_PRODUCTIVITY_V03: Cadrage!$E$35
Name HYP_SALARY_V01: Cadrage!$C$33
Name HYP_SALARY_V02: Cadrage!$D$33
Name HYP_SALARY_V03: Cadrage!$E$33
Name HYP_STRUCT_COST_V01: Cadrage!#REF!
Name HYP_STRUCT_COST_V02: Cadrage!#REF!
Name HYP_STRUCT_COST_V03: Cadrage!#REF!
Name SCENARIO_ACTIF: Cadrage!$C$5
Name SCENARIO_CODE: Cadrage!$P$1
Name TEC_EBITDA: Cadrage!$F$6
Name TEC_PL: Cadrage!#REF!

Sheet _TGK_HIDDEN
A1: Template00 | B1: =Cadrage!A65545 -> 0
A2: Template01 | B2: =Socle!A65536 -> 0
A3: Template02 | B3: =Campagne!A65536 -> 0
A4: Template03 | B4: =Moteur!A65536 -> 0
A5: Template04 | B5: =Comptabilité!A65536 -> 0
A6: Template05 | B6: =PNL!A65536 -> 0
A7: Template06 | B7: =Pilotage!A65544 -> 0

Sheet Cadrage
P1: =IF($C$5="Cadrage","V01",IF($C$5="Optimiste","V02","V03")) -> V01
C2: Hypothèses & scénarios 2027
B5: Scenario actif : | C5: Cadrage | D5: Objectif d'EBITDA | F5: 0.065
B7: OBJECTIF 2027 | D7: CE QUE LES LEVIERS PRODUISENT | F7: RESTE À TROUVER
B8: =C13*(1+F5) -> 4095766.4 | D8: =D13 -> 4111503.6 | F8: =$B$8-D8 -> -15737.279
B9: ="+"&TEXT($F$5,"0,00%")&" sur "&TEXT(C13,"# ##0 €")&" en 2026, soit "&TEXT($B$8-C13,"+# ##0 €")&" à trouver" -> +007% sur 3845 790 € en 2026, soit +249 976 € à trouver | D9: ="scénario « "&$C$5&" » · marge "&TEXT(D14,"0,0%") -> scénario « Cadrage » · marge 17% | F9: objectif moins construit · se ferme à chaque levier
B10: ① RÉCONCILIATION | F10: de 2026 au scénario construit
B11: Indicateur | C11: Référence 2026 | D11: Construit 2027 | E11: Écart | F11: Écart % | W11: EXERCICE | X11: CA | Y11: EBITDA | Z11: MARGE EBITDA
B12: Chiffre d'affaires | C12: 23098985 | D12: =_xlfn.SUMIFS(Moteur!$R$1:$R$200,Moteur!$B$1:$B$200,Cadrage!$P$1) -> 24231704 | E12: =D12-C12 -> 1132718.5 | F12: =_xlfn.IFERROR(D12/C12-1,0) -> 0.04903759 | W12: 2024 | X12: 20567210 | Y12: 3151035 | Z12: 0.1532
B13: EBITDA | C13: 3845790 | D13: =_xlfn.SUMIFS(_CALC_PNL!$T$1:$T$1347,_CALC_PNL!$D$1:$D$1347,Cadrage!$P$1,_CALC_PNL!$C$1:$C$1347,"2027") -> 4111503.6 | E13: =D13-C13 -> 265713.63 | F13: =_xlfn.IFERROR(D13/C13-1,0) -> 0.06909208 | W13: 2025 | X13: 21758770 | Y13: 3467768 | Z13: 0.1594
B14: Marge EBITDA % | C14: =_xlfn.IFERROR(C13/C12,0) -> 0.16649173 | D14: =_xlfn.IFERROR(D13/D12,0) -> 0.16967456 | E14: =D14-C14 -> 0.0031828285 | W14: 2026 | X14: 23098985 | Y14: 3845790 | Z14: 0.1665
B15: Effectif | C15: 3114 | D15: =_xlfn.SUMIFS(Moteur!$P$1:$P$200,Moteur!$B$1:$B$200,Cadrage!$P$1) -> 3253.6168 | E15: =D15-C15 -> 139.61681 | F15: =_xlfn.IFERROR(D15/C15-1,0) -> 0.044835198 | W15: 2027 | X15: =D12 -> 24231704 | Y15: =D13 -> 4111503.6 | Z15: =D14 -> 0.16967456
B18: ② LES DOUZE LEVIERS
B19: Levier | C19: Cadrage | D19: Optimiste | E19: Prudent | F19: RETENU
B21: CROISSANCE · ce qui fait le chiffre d'affaires
C22: Cadrage | D22: Optimiste | E22: Prudent
B23: Variation du budget d'acquisition → leads payants | C23: 0.08 | D23: 0.15 | E23: -0.05 | F23: =INDEX(C23:E23,MATCH(Cadrage!$C$5,$C$22:$E$22,0)) -> 0.08
B24: Variation du budget de marque → socle organique | C24: 0.1 | D24: 0.15 | E24: -0.05 | F24: =INDEX(C24:E24,MATCH(Cadrage!$C$5,$C$22:$E$22,0)) -> 0.1
B25: Hausse tarifaire (prix) | C25: 0.0029 | D25: 0.035 | E25: 0.02 | F25: =INDEX(C25:E25,MATCH(Cadrage!$C$5,$C$22:$E$22,0)) -> 0.0029
B26: Gain du taux de conversion Lead → Candidature | C26: 0.01 | D26: 0.03 | E26: -0.01 | F26: =INDEX(C26:E26,MATCH(Cadrage!$C$5,$C$22:$E$22,0)) -> 0.01
B27: Gain du taux de conversion Admis → Inscrit | C27: 0.01 | D27: 0.025 | E27: -0.01 | F27: =INDEX(C27:E27,MATCH(Cadrage!$C$5,$C$22:$E$22,0)) -> 0.01
B28: Amélioration du taux de passage | C28: 0.005 | D28: 0.015 | E28: -0.01 | F28: =INDEX(C28:E28,MATCH(Cadrage!$C$5,$C$22:$E$22,0)) -> 0.005
B32: COÛTS · ce qui fait la marge | J32: ③ COEFFICIENTS DE PRIX
B34: Inflation des charges externes | C34: 0.02 | D34: 0.015 | E34: 0.03 | F34: =INDEX(C34:E34,MATCH(Cadrage!$C$5,$C$22:$E$22,0)) -> 0.02 | J34: MBway | K34: 1.2
B35: Politique salariale sur la masse permanente | C35: 0.025 | D35: 0.02 | E35: 0.03 | F35: =INDEX(C35:E35,MATCH(Cadrage!$C$5,$C$22:$E$22,0)) -> 0.025 | J35: ISCOM | K35: 1.15
B36: Variation des effectifs permanents | C36: 0.04 | D36: 0.03 | E36: 0.05 | F36: =INDEX(C36:E36,MATCH(Cadrage!$C$5,$C$22:$E$22,0)) -> 0.04 | J36: Ipac Bachelor Factory | K36: 0.95
B37: Effort de productivité sur les achats et la structure | C37: 0.0185 | D37: 0.03 | F37: =INDEX(C37:E37,MATCH(Cadrage!$C$5,$C$22:$E$22,0)) -> 0.0185 | J37: Pigier | K37: 0.9
B38: Variation des coûts de structure (loyers, IT, siège…) | D38: -0.03 | E38: 0.04 | F38: =INDEX(C38:E38,MATCH(Cadrage!$C$5,$C$22:$E$22,0)) -> 0 | J38: Tunon | K38: 1.05
B40: CONSTANTE · hors scénario, saisie directe
B42: Frais de dossier par nouvel inscrit | C42: 90 | D42: 90 | E42: 90 | F42: =INDEX(C42:E42,MATCH(Cadrage!$C$5,$C$22:$E$22,0)) -> 90

Sheet Pilotage
O1: code scénario -> | P1: =IF($E$6="Cadrage","V01",IF($E$6="Optimiste","V02","V03")) -> V01
G2: PILOTAGE · Cockpit de decision CFO · Budget 2027
B6: Scenario actif : | E6: Cadrage
B9: CA 2027 | D9: EBITDA (apres siege) | F9: Marge EBITDA | H9: Effectif | J9: Croissance CA vs 2026
B10: =E55 -> 24231704 | D10: =H55 -> 4111503.6 | F10: =I55 -> 0.16967456 | H10: =D55 -> 3253.6168 | J10: =_xlfn.IFERROR(E55/Cadrage!$C$12-1,0) -> 0.04903759
B11: ="contre "&TEXT(Cadrage!$C$12,"#,##0 €")&" en 2026" -> contre 23.098.985 € en 2026 | D11: ="contre "&TEXT(Cadrage!$C$13,"#,##0 €")&" en 2026" -> contre 3.845.790 € en 2026 | F11: ="contre "&TEXT(Cadrage!$C$14,"0.0%")&" en 2026" -> contre 16,6% en 2026 | H11: ="contre "&TEXT(Cadrage!$C$15,"#,##0")&" en 2026" -> contre 3.114 en 2026 | J11: vs 2026
B16: 1 · Cap strategique par campus (marque x campus) - arbitrage du budget d'acquisition
U17: à masquer | V17: à masquer | W17: à masquer
A18: Campus | B18: Marque | C18: Ville | D18: CAC marginal | E18: Croiss. leads | F18: Intensité mkt | G18: Cap Eff | H18: Cap mom. | I18: Cap pot. | J18: Cap retenu | K18: Budget acq réf. | L18: Entity | U18: CAP_EFF (live) | V18: CAP_MOM (live) | W18: CAP_POT (live)
A19: =$L19 -> IPAC_MTP | B19: =IF(LEFT($L19,5)="MBWAY","MBway",IF(LEFT($L19,5)="ISCOM","ISCOM",IF(LEFT($L19,4)="IPAC","Ipac",IF(LEFT($L19,6)="PIGIER","Pigier",IF(LEFT($L19,5)="TUNON","Tunon",""))))) -> Ipac | C19: =IF(RIGHT($L19,3)="PAR","Paris",IF(RIGHT($L19,3)="LYO","Lyon",IF(RIGHT($L19,3)="NAN","Nantes",IF(RIGHT($L19,3)="BOR","Bordeaux",IF(RIGHT($L19,3)="LIL","Lille",IF(RIGHT($L19,3)="TLS","Toulouse",IF(RIGHT($L19,3)="REN","Rennes",IF(RIGHT($L19,3)="MTP","Montpellier","")))))))) -> Montpellier | D19: 1033.9846 | E19: 0.144781 | F19: 0.019417 | G19: 1.1626041 | H19: 1.385517 | I19: 0.94434 | J19: 1 | K19: 15178 | L19: IPAC_MTP
A20: =$L20 -> IPAC_NAN | B20: =IF(LEFT($L20,5)="MBWAY","MBway",IF(LEFT($L20,5)="ISCOM","ISCOM",IF(LEFT($L20,4)="IPAC","Ipac",IF(LEFT($L20,6)="PIGIER","Pigier",IF(LEFT($L20,5)="TUNON","Tunon",""))))) -> Ipac | C20: =IF(RIGHT($L20,3)="PAR","Paris",IF(RIGHT($L20,3)="LYO","Lyon",IF(RIGHT($L20,3)="NAN","Nantes",IF(RIGHT($L20,3)="BOR","Bordeaux",IF(RIGHT($L20,3)="LIL","Lille",IF(RIGHT($L20,3)="TLS","Toulouse",IF(RIGHT($L20,3)="REN","Rennes",IF(RIGHT($L20,3)="MTP","Montpellier","")))))))) -> Nantes | D20: 1216.2931 | E20: 0.137884 | F20: 0.021343 | G20: 0.98834297 | H20: 1.319514 | I20: 0.85913 | J20: 1 | K20: 21760 | L20: IPAC_NAN
A21: =$L21 -> IPAC_REN | B21: =IF(LEFT($L21,5)="MBWAY","MBway",IF(LEFT($L21,5)="ISCOM","ISCOM",IF(LEFT($L21,4)="IPAC","Ipac",IF(LEFT($L21,6)="PIGIER","Pigier",IF(LEFT($L21,5)="TUNON","Tunon",""))))) -> Ipac | C21: =IF(RIGHT($L21,3)="PAR","Paris",IF(RIGHT($L21,3)="LYO","Lyon",IF(RIGHT($L21,3)="NAN","Nantes",IF(RIGHT($L21,3)="BOR","Bordeaux",IF(RIGHT($L21,3)="LIL","Lille",IF(RIGHT($L21,3)="TLS","Toulouse",IF(RIGHT($L21,3)="REN","Rennes",IF(RIGHT($L21,3)="MTP","Montpellier","")))))))) -> Rennes | D21: 1040.5564 | E21: 0.144781 | F21: 0.019104 | G21: 1.1552615 | H21: 1.385517 | I21: 0.959834 | J21: 1 | K21: 14933 | L21: IPAC_REN
A22: =$L22 -> ISCOM_LIL | B22: =IF(LEFT($L22,5)="MBWAY","MBway",IF(LEFT($L22,5)="ISCOM","ISCOM",IF(LEFT($L22,4)="IPAC","Ipac",IF(LEFT($L22,6)="PIGIER","Pigier",IF(LEFT($L22,5)="TUNON","Tunon",""))))) -> ISCOM | C22: =IF(RIGHT($L22,3)="PAR","Paris",IF(RIGHT($L22,3)="LYO","Lyon",IF(RIGHT($L22,3)="NAN","Nantes",IF(RIGHT($L22,3)="BOR","Bordeaux",IF(RIGHT($L22,3)="LIL","Lille",IF(RIGHT($L22,3)="TLS","Toulouse",IF(RIGHT($L22,3)="REN","Rennes",IF(RIGHT($L22,3)="MTP","Montpellier","")))))))) -> Lille | D22: 978.58461 | E22: 0.081545 | F22: 0.014363 | G22: 1.2284219 | H22: 0.780364 | I22: 1.276654 | J22: 1 | K22: 25220 | L22: ISCOM_LIL
A23: =$L23 -> ISCOM_PAR | B23: =IF(LEFT($L23,5)="MBWAY","MBway",IF(LEFT($L23,5)="ISCOM","ISCOM",IF(LEFT($L23,4)="IPAC","Ipac",IF(LEFT($L23,6)="PIGIER","Pigier",IF(LEFT($L23,5)="TUNON","Tunon",""))))) -> ISCOM | C23: =IF(RIGHT($L23,3)="PAR","Paris",IF(RIGHT($L23,3)="LYO","Lyon",IF(RIGHT($L23,3)="NAN","Nantes",IF(RIGHT($L23,3)="BOR","Bordeaux",IF(RIGHT($L23,3)="LIL","Lille",IF(RIGHT($L23,3)="TLS","Toulouse",IF(RIGHT($L23,3)="REN","Rennes",IF(RIGHT($L23,3)="MTP","Montpellier","")))))))) -> Paris | D23: 1540.325 | E23: 0.077744 | F23: 0.020902 | G23: 0.78042932 | H23: 0.74399 | I23: 0.877261 | J23: 1 | K23: 60800 | L23: ISCOM_PAR
A24: =$L24 -> ISCOM_TLS | B24: =IF(LEFT($L24,5)="MBWAY","MBway",IF(LEFT($L24,5)="ISCOM","ISCOM",IF(LEFT($L24,4)="IPAC","Ipac",IF(LEFT($L24,6)="PIGIER","Pigier",IF(LEFT($L24,5)="TUNON","Tunon",""))))) -> ISCOM | C24: =IF(RIGHT($L24,3)="PAR","Paris",IF(RIGHT($L24,3)="LYO","Lyon",IF(RIGHT($L24,3)="NAN","Nantes",IF(RIGHT($L24,3)="BOR","Bordeaux",IF(RIGHT($L24,3)="LIL","Lille",IF(RIGHT($L24,3)="TLS","Toulouse",IF(RIGHT($L24,3)="REN","Rennes",IF(RIGHT($L24,3)="MTP","Montpellier","")))))))) -> Toulouse | D24: 919.03477 | E24: 0.082116 | F24: 0.013564 | G24: 1.3080188 | H24: 0.785829 | I24: 1.351829 | J24: 1 | K24: 22083 | L24: ISCOM_TLS
A25: =$L25 -> MBWAY_BOR | B25: =IF(LEFT($L25,5)="MBWAY","MBway",IF(LEFT($L25,5)="ISCOM","ISCOM",IF(LEFT($L25,4)="IPAC","Ipac",IF(LEFT($L25,6)="PIGIER","Pigier",IF(LEFT($L25,5)="TUNON","Tunon",""))))) -> MBway | C25: =IF(RIGHT($L25,3)="PAR","Paris",IF(RIGHT($L25,3)="LYO","Lyon",IF(RIGHT($L25,3)="NAN","Nantes",IF(RIGHT($L25,3)="BOR","Bordeaux",IF(RIGHT($L25,3)="LIL","Lille",IF(RIGHT($L25,3)="TLS","Toulouse",IF(RIGHT($L25,3)="REN","Rennes",IF(RIGHT($L25,3)="MTP","Montpellier","")))))))) -> Bordeaux | D25: 889.59329 | E25: 0.126094 | F25: 0.014052 | G25: 1.3513083 | H25: 1.206687 | I25: 1.304934 | J25: 1 | K25: 24923 | L25: MBWAY_BOR
A26: =$L26 -> MBWAY_LYO | B26: =IF(LEFT($L26,5)="MBWAY","MBway",IF(LEFT($L26,5)="ISCOM","ISCOM",IF(LEFT($L26,4)="IPAC","Ipac",IF(LEFT($L26,6)="PIGIER","Pigier",IF(LEFT($L26,5)="TUNON","Tunon",""))))) -> MBway | C26: =IF(RIGHT($L26,3)="PAR","Paris",IF(RIGHT($L26,3)="LYO","Lyon",IF(RIGHT($L26,3)="NAN","Nantes",IF(RIGHT($L26,3)="BOR","Bordeaux",IF(RIGHT($L26,3)="LIL","Lille",IF(RIGHT($L26,3)="TLS","Toulouse",IF(RIGHT($L26,3)="REN","Rennes",IF(RIGHT($L26,3)="MTP","Montpellier","")))))))) -> Lyon | D26: 1101.6048 | E26: 0.118871 | F26: 0.016735 | G26: 1.0912396 | H26: 1.137565 | I26: 1.095717 | J26: 1 | K26: 41783 | L26: MBWAY_LYO
A27: =$L27 -> MBWAY_NAN | B27: =IF(LEFT($L27,5)="MBWAY","MBway",IF(LEFT($L27,5)="ISCOM","ISCOM",IF(LEFT($L27,4)="IPAC","Ipac",IF(LEFT($L27,6)="PIGIER","Pigier",IF(LEFT($L27,5)="TUNON","Tunon",""))))) -> MBway | C27: =IF(RIGHT($L27,3)="PAR","Paris",IF(RIGHT($L27,3)="LYO","Lyon",IF(RIGHT($L27,3)="NAN","Nantes",IF(RIGHT($L27,3)="BOR","Bordeaux",IF(RIGHT($L27,3)="LIL","Lille",IF(RIGHT($L27,3)="TLS","Toulouse",IF(RIGHT($L27,3)="REN","Rennes",IF(RIGHT($L27,3)="MTP","Montpellier","")))))))) -> Nantes | D27: 963.57687 | E27: 0.123795 | F27: 0.01461 | G27: 1.2475546 | H27: 1.184686 | I27: 1.255097 | J27: 1 | K27: 31533 | L27: MBWAY_NAN
A28: =$L28 -> MBWAY_PAR | B28: =IF(LEFT($L28,5)="MBWAY","MBway",IF(LEFT($L28,5)="ISCOM","ISCOM",IF(LEFT($L28,4)="IPAC","Ipac",IF(LEFT($L28,6)="PIGIER","Pigier",IF(LEFT($L28,5)="TUNON","Tunon",""))))) -> MBway | C28: =IF(RIGHT($L28,3)="PAR","Paris",IF(RIGHT($L28,3)="LYO","Lyon",IF(RIGHT($L28,3)="NAN","Nantes",IF(RIGHT($L28,3)="BOR","Bordeaux",IF(RIGHT($L28,3)="LIL","Lille",IF(RIGHT($L28,3)="TLS","Toulouse",IF(RIGHT($L28,3)="REN","Rennes",IF(RIGHT($L28,3)="MTP","Montpellier","")))))))) -> Paris | D28: 1475.0192 | E28: 0.110736 | F28: 0.021756 | G28: 0.81498244 | H28: 1.059715 | I28: 0.842823 | J28: 1 | K28: 68291 | L28: MBWAY_PAR
A29: =$L29 -> PIGIER_BOR | B29: =IF(LEFT($L29,5)="MBWAY","MBway",IF(LEFT($L29,5)="ISCOM","ISCOM",IF(LEFT($L29,4)="IPAC","Ipac",IF(LEFT($L29,6)="PIGIER","Pigier",IF(LEFT($L29,5)="TUNON","Tunon",""))))) -> Pigier | C29: =IF(RIGHT($L29,3)="PAR","Paris",IF(RIGHT($L29,3)="LYO","Lyon",IF(RIGHT($L29,3)="NAN","Nantes",IF(RIGHT($L29,3)="BOR","Bordeaux",IF(RIGHT($L29,3)="LIL","Lille",IF(RIGHT($L29,3)="TLS","Toulouse",IF(RIGHT($L29,3)="REN","Rennes",IF(RIGHT($L29,3)="MTP","Montpellier","")))))))) -> Bordeaux | D29: 1368.091 | E29: 0.087533 | F29: 0.019395 | G29: 0.87868042 | H29: 0.837668 | I29: 0.945444 | J29: 1 | K29: 21968 | L29: PIGIER_BOR
A30: =$L30 -> PIGIER_LYO | B30: =IF(LEFT($L30,5)="MBWAY","MBway",IF(LEFT($L30,5)="ISCOM","ISCOM",IF(LEFT($L30,4)="IPAC","Ipac",IF(LEFT($L30,6)="PIGIER","Pigier",IF(LEFT($L30,5)="TUNON","Tunon",""))))) -> Pigier | C30: =IF(RIGHT($L30,3)="PAR","Paris",IF(RIGHT($L30,3)="LYO","Lyon",IF(RIGHT($L30,3)="NAN","Nantes",IF(RIGHT($L30,3)="BOR","Bordeaux",IF(RIGHT($L30,3)="LIL","Lille",IF(RIGHT($L30,3)="TLS","Toulouse",IF(RIGHT($L30,3)="REN","Rennes",IF(RIGHT($L30,3)="MTP","Montpellier","")))))))) -> Lyon | D30: 1704.9846 | E30: 0.085003 | F30: 0.023262 | G30: 0.70505903 | H30: 0.813456 | I30: 0.788252 | J30: 1 | K30: 36612 | L30: PIGIER_LYO
... A32: =$L32 -> TUNON_PAR | B32: =IF(LEFT($L32,5)="MBWAY","MBway",IF(LEFT($L32,5)="ISCOM","ISCOM",IF(LEFT($L32,4)="IPAC","Ipac",IF(LEFT($L32,6)="PIGIER","Pigier",IF(LEFT($L32,5)="TUNON","Tunon",""))))) -> Tunon | C32: =IF(RIGHT($L32,3)="PAR","Paris",IF(RIGHT($L32,3)="LYO","Lyon",IF(RIGHT($L32,3)="NAN","Nantes",IF(RIGHT($L32,3)="BOR","Bordeaux",IF(RIGHT($L32,3)="LIL","Lille",IF(RIGHT($L32,3)="TLS","Toulouse",IF(RIGHT($L32,3)="REN","Rennes",IF(RIGHT($L32,3)="MTP","Montpellier","")))))))) -> Paris | D32: 2192.8927 | E32: 0.069518 | F32: 0.027841 | G32: 0.54818677 | H32: 0.665269 | I32: 0.658626 | J32: 1 | K32: 30240 | L32: TUNON_PAR
B36: 2 · Synthese par campus (resultats budget, live)
A38: Campus | B38: Marque | C38: Ville | D38: Effectif | E38: CA 2027 | F38: Prix moy. | G38: Part CA | H38: EBITDA campus | I38: Mrg EBITDA | J38: EBITDA/etud. | K38: Rejoue | L38: CAC marg.
A39: =A19 -> IPAC_MTP | B39: =B19 -> Ipac | C39: =C19 -> Montpellier | D39: =_xlfn.SUMIFS(Moteur!$P$1:$P$200,Moteur!$D$1:$D$200,$A39,Moteur!$B$1:$B$200,$P$1) -> 122.1326 | E39: =_xlfn.SUMIFS(Moteur!$R$1:$R$200,Moteur!$D$1:$D$200,$A39,Moteur!$B$1:$B$200,$P$1) -> 818445.73 | F39: =_xlfn.IFERROR(E39/D39,0) -> 6701.2881 | G39: =_xlfn.IFERROR(E39/SUM($E$39:$E$52),0) -> 0.033775823 | H39: =_xlfn.SUMIFS(_CALC_PNL!$T$1:$T$1347,_CALC_PNL!$A$1:$A$1347,$A39,_CALC_PNL!$D$1:$D$1347,$P$1,_CALC_PNL!$C$1:$C$1347,"2027") -> 254308.3 | I39: =_xlfn.IFERROR(H39/E39,0) -> 0.31072103 | J39: =_xlfn.IFERROR(H39/D39,0) -> 2082.2312 | K39: =_xlfn.SUMIFS(Pilotage!$K$19:$K$32,Pilotage!$A$19:$A$32,$A39)*_xlfn.SUMIFS(Pilotage!$J$19:$J$32,Pilotage!$A$19:$A$32,$A39)*(SUM(Pilotage!$K$19:$K$32)/SUMPRODUCT(Pilotage!$K$19:$K$32,Pilotage!$J$19:$J$32)) -> 15178 | L39: =_xlfn.SUMIFS(Pilotage!$D$19:$D$32,Pilotage!$A$19:$A$32,$A39) -> 1033.9846
A40: =A20 -> IPAC_NAN | B40: =B20 -> Ipac | C40: =C20 -> Nantes | D40: =_xlfn.SUMIFS(Moteur!$P$1:$P$200,Moteur!$D$1:$D$200,$A40,Moteur!$B$1:$B$200,$P$1) -> 151.32252 | E40: =_xlfn.SUMIFS(Moteur!$R$1:$R$200,Moteur!$D$1:$D$200,$A40,Moteur!$B$1:$B$200,$P$1) -> 1067200.8 | F40: =_xlfn.IFERROR(E40/D40,0) -> 7052.4917 | G40: =_xlfn.IFERROR(E40/SUM($E$39:$E$52),0) -> 0.044041509 | H40: =_xlfn.SUMIFS(_CALC_PNL!$T$1:$T$1347,_CALC_PNL!$A$1:$A$1347,$A40,_CALC_PNL!$D$1:$D$1347,$P$1,_CALC_PNL!$C$1:$C$1347,"2027") -> 331184.51 | I40: =_xlfn.IFERROR(H40/E40,0) -> 0.31033008 | J40: =_xlfn.IFERROR(H40/D40,0) -> 2188.6003 | K40: =_xlfn.SUMIFS(Pilotage!$K$19:$K$32,Pilotage!$A$19:$A$32,$A40)*_xlfn.SUMIFS(Pilotage!$J$19:$J$32,Pilotage!$A$19:$A$32,$A40)*(SUM(Pilotage!$K$19:$K$32)/SUMPRODUCT(Pilotage!$K$19:$K$32,Pilotage!$J$19:$J$32)) -> 21760 | L40: =_xlfn.SUMIFS(Pilotage!$D$19:$D$32,Pilotage!$A$19:$A$32,$A40) -> 1216.2931
A41: =A21 -> IPAC_REN | B41: =B21 -> Ipac | C41: =C21 -> Rennes | D41: =_xlfn.SUMIFS(Moteur!$P$1:$P$200,Moteur!$D$1:$D$200,$A41,Moteur!$B$1:$B$200,$P$1) -> 122.12158 | E41: =_xlfn.SUMIFS(Moteur!$R$1:$R$200,Moteur!$D$1:$D$200,$A41,Moteur!$B$1:$B$200,$P$1) -> 818371.29 | F41: =_xlfn.IFERROR(E41/D41,0) -> 6701.2829 | G41: =_xlfn.IFERROR(E41/SUM($E$39:$E$52),0) -> 0.033772751 | H41: =_xlfn.SUMIFS(_CALC_PNL!$T$1:$T$1347,_CALC_PNL!$A$1:$A$1347,$A41,_CALC_PNL!$D$1:$D$1347,$P$1,_CALC_PNL!$C$1:$C$1347,"2027") -> 254316.41 | I41: =_xlfn.IFERROR(H41/E41,0) -> 0.3107592 | J41: =_xlfn.IFERROR(H41/D41,0) -> 2082.4853 | K41: =_xlfn.SUMIFS(Pilotage!$K$19:$K$32,Pilotage!$A$19:$A$32,$A41)*_xlfn.SUMIFS(Pilotage!$J$19:$J$32,Pilotage!$A$19:$A$32,$A41)*(SUM(Pilotage!$K$19:$K$32)/SUMPRODUCT(Pilotage!$K$19:$K$32,Pilotage!$J$19:$J$32)) -> 14933 | L41: =_xlfn.SUMIFS(Pilotage!$D$19:$D$32,Pilotage!$A$19:$A$32,$A41) -> 1040.5564
A42: =A22 -> ISCOM_LIL | B42: =B22 -> ISCOM | C42: =C22 -> Lille | D42: =_xlfn.SUMIFS(Moteur!$P$1:$P$200,Moteur!$D$1:$D$200,$A42,Moteur!$B$1:$B$200,$P$1) -> 255.08663 | E42: =_xlfn.SUMIFS(Moteur!$R$1:$R$200,Moteur!$D$1:$D$200,$A42,Moteur!$B$1:$B$200,$P$1) -> 1844124.5 | F42: =_xlfn.IFERROR(E42/D42,0) -> 7229.4049 | G42: =_xlfn.IFERROR(E42/SUM($E$39:$E$52),0) -> 0.076103793 | H42: =_xlfn.SUMIFS(_CALC_PNL!$T$1:$T$1347,_CALC_PNL!$A$1:$A$1347,$A42,_CALC_PNL!$D$1:$D$1347,$P$1,_CALC_PNL!$C$1:$C$1347,"2027") -> 602778.74 | I42: =_xlfn.IFERROR(H42/E42,0) -> 0.32686444 | J42: =_xlfn.IFERROR(H42/D42,0) -> 2363.0354 | K42: =_xlfn.SUMIFS(Pilotage!$K$19:$K$32,Pilotage!$A$19:$A$32,$A42)*_xlfn.SUMIFS(Pilotage!$J$19:$J$32,Pilotage!$A$19:$A$32,$A42)*(SUM(Pilotage!$K$19:$K$32)/SUMPRODUCT(Pilotage!$K$19:$K$32,Pilotage!$J$19:$J$32)) -> 25220 | L42: =_xlfn.SUMIFS(Pilotage!$D$19:$D$32,Pilotage!$A$19:$A$32,$A42) -> 978.58461
A43: =A23 -> ISCOM_PAR | B43: =B23 -> ISCOM | C43: =C23 -> Paris | D43: =_xlfn.SUMIFS(Moteur!$P$1:$P$200,Moteur!$D$1:$D$200,$A43,Moteur!$B$1:$B$200,$P$1) -> 369.35233 | E43: =_xlfn.SUMIFS(Moteur!$R$1:$R$200,Moteur!$D$1:$D$200,$A43,Moteur!$B$1:$B$200,$P$1) -> 3048653.5 | F43: =_xlfn.IFERROR(E43/D43,0) -> 8254.0524 | G43: =_xlfn.IFERROR(E43/SUM($E$39:$E$52),0) -> 0.12581259 | H43: =_xlfn.SUMIFS(_CALC_PNL!$T$1:$T$1347,_CALC_PNL!$A$1:$A$1347,$A43,_CALC_PNL!$D$1:$D$1347,$P$1,_CALC_PNL!$C$1:$C$1347,"2027") -> 985765.87 | I43: =_xlfn.IFERROR(H43/E43,0) -> 0.32334468 | J43: =_xlfn.IFERROR(H43/D43,0) -> 2668.9039 | K43: =_xlfn.SUMIFS(Pilotage!$K$19:$K$32,Pilotage!$A$19:$A$32,$A43)*_xlfn.SUMIFS(Pilotage!$J$19:$J$32,Pilotage!$A$19:$A$32,$A43)*(SUM(Pilotage!$K$19:$K$32)/SUMPRODUCT(Pilotage!$K$19:$K$32,Pilotage!$J$19:$J$32)) -> 60800 | L43: =_xlfn.SUMIFS(Pilotage!$D$19:$D$32,Pilotage!$A$19:$A$32,$A43) -> 1540.325
A44: =A24 -> ISCOM_TLS | B44: =B24 -> ISCOM | C44: =C24 -> Toulouse | D44: =_xlfn.SUMIFS(Moteur!$P$1:$P$200,Moteur!$D$1:$D$200,$A44,Moteur!$B$1:$B$200,$P$1) -> 241.48135 | E44: =_xlfn.SUMIFS(Moteur!$R$1:$R$200,Moteur!$D$1:$D$200,$A44,Moteur!$B$1:$B$200,$P$1) -> 1709754.8 | F44: =_xlfn.IFERROR(E44/D44,0) -> 7080.2771 | G44: =_xlfn.IFERROR(E44/SUM($E$39:$E$52),0) -> 0.070558591 | H44: =_xlfn.SUMIFS(_CALC_PNL!$T$1:$T$1347,_CALC_PNL!$A$1:$A$1347,$A44,_CALC_PNL!$D$1:$D$1347,$P$1,_CALC_PNL!$C$1:$C$1347,"2027") -> 560009.03 | I44: =_xlfn.IFERROR(H44/E44,0) -> 0.32753762 | J44: =_xlfn.IFERROR(H44/D44,0) -> 2319.0571 | K44: =_xlfn.SUMIFS(Pilotage!$K$19:$K$32,Pilotage!$A$19:$A$32,$A44)*_xlfn.SUMIFS(Pilotage!$J$19:$J$32,Pilotage!$A$19:$A$32,$A44)*(SUM(Pilotage!$K$19:$K$32)/SUMPRODUCT(Pilotage!$K$19:$K$32,Pilotage!$J$19:$J$32)) -> 22083 | L44: =_xlfn.SUMIFS(Pilotage!$D$19:$D$32,Pilotage!$A$19:$A$32,$A44) -> 919.03477
A45: =A25 -> MBWAY_BOR | B45: =B25 -> MBway | C45: =C25 -> Bordeaux | D45: =_xlfn.SUMIFS(Moteur!$P$1:$P$200,Moteur!$D$1:$D$200,$A45,Moteur!$B$1:$B$200,$P$1) -> 260.41179 | E45: =_xlfn.SUMIFS(Moteur!$R$1:$R$200,Moteur!$D$1:$D$200,$A45,Moteur!$B$1:$B$200,$P$1) -> 1863775.7 | F45: =_xlfn.IFERROR(E45/D45,0) -> 7157.0326 | G45: =_xlfn.IFERROR(E45/SUM($E$39:$E$52),0) -> 0.076914761 | H45: =_xlfn.SUMIFS(_CALC_PNL!$T$1:$T$1347,_CALC_PNL!$A$1:$A$1347,$A45,_CALC_PNL!$D$1:$D$1347,$P$1,_CALC_PNL!$C$1:$C$1347,"2027") -> 625402.3 | I45: =_xlfn.IFERROR(H45/E45,0) -> 0.33555664 | J45: =_xlfn.IFERROR(H45/D45,0) -> 2401.5898 | K45: =_xlfn.SUMIFS(Pilotage!$K$19:$K$32,Pilotage!$A$19:$A$32,$A45)*_xlfn.SUMIFS(Pilotage!$J$19:$J$32,Pilotage!$A$19:$A$32,$A45)*(SUM(Pilotage!$K$19:$K$32)/SUMPRODUCT(Pilotage!$K$19:$K$32,Pilotage!$J$19:$J$32)) -> 24923 | L45: =_xlfn.SUMIFS(Pilotage!$D$19:$D$32,Pilotage!$A$19:$A$32,$A45) -> 889.59329
A46: =A26 -> MBWAY_LYO | B46: =B26 -> MBway | C46: =C26 -> Lyon | D46: =_xlfn.SUMIFS(Moteur!$P$1:$P$200,Moteur!$D$1:$D$200,$A46,Moteur!$B$1:$B$200,$P$1) -> 338.49824 | E46: =_xlfn.SUMIFS(Moteur!$R$1:$R$200,Moteur!$D$1:$D$200,$A46,Moteur!$B$1:$B$200,$P$1) -> 2620797.3 | F46: =_xlfn.IFERROR(E46/D46,0) -> 7742.4254 | G46: =_xlfn.IFERROR(E46/SUM($E$39:$E$52),0) -> 0.10815572 | H46: =_xlfn.SUMIFS(_CALC_PNL!$T$1:$T$1347,_CALC_PNL!$A$1:$A$1347,$A46,_CALC_PNL!$D$1:$D$1347,$P$1,_CALC_PNL!$C$1:$C$1347,"2027") -> 876442.71 | I46: =_xlfn.IFERROR(H46/E46,0) -> 0.33441835 | J46: =_xlfn.IFERROR(H46/D46,0) -> 2589.2091 | K46: =_xlfn.SUMIFS(Pilotage!$K$19:$K$32,Pilotage!$A$19:$A$32,$A46)*_xlfn.SUMIFS(Pilotage!$J$19:$J$32,Pilotage!$A$19:$A$32,$A46)*(SUM(Pilotage!$K$19:$K$32)/SUMPRODUCT(Pilotage!$K$19:$K$32,Pilotage!$J$19:$J$32)) -> 41783 | L46: =_xlfn.SUMIFS(Pilotage!$D$19:$D$32,Pilotage!$A$19:$A$32,$A46) -> 1101.6048
A47: =A27 -> MBWAY_NAN | B47: =B27 -> MBway | C47: =C27 -> Nantes | D47: =_xlfn.SUMIFS(Moteur!$P$1:$P$200,Moteur!$D$1:$D$200,$A47,Moteur!$B$1:$B$200,$P$1) -> 307.34298 | E47: =_xlfn.SUMIFS(Moteur!$R$1:$R$200,Moteur!$D$1:$D$200,$A47,Moteur!$B$1:$B$200,$P$1) -> 2267018.6 | F47: =_xlfn.IFERROR(E47/D47,0) -> 7376.1849 | G47: =_xlfn.IFERROR(E47/SUM($E$39:$E$52),0) -> 0.093555892 | H47: =_xlfn.SUMIFS(_CALC_PNL!$T$1:$T$1347,_CALC_PNL!$A$1:$A$1347,$A47,_CALC_PNL!$D$1:$D$1347,$P$1,_CALC_PNL!$C$1:$C$1347,"2027") -> 763702.73 | I47: =_xlfn.IFERROR(H47/E47,0) -> 0.33687537 | J47: =_xlfn.IFERROR(H47/D47,0) -> 2484.855 | K47: =_xlfn.SUMIFS(Pilotage!$K$19:$K$32,Pilotage!$A$19:$A$32,$A47)*_xlfn.SUMIFS(Pilotage!$J$19:$J$32,Pilotage!$A$19:$A$32,$A47)*(SUM(Pilotage!$K$19:$K$32)/SUMPRODUCT(Pilotage!$K$19:$K$32,Pilotage!$J$19:$J$32)) -> 31533 | L47: =_xlfn.SUMIFS(Pilotage!$D$19:$D$32,Pilotage!$A$19:$A$32,$A47) -> 963.57687
A48: =A28 -> MBWAY_PAR | B48: =B28 -> MBway | C48: =C28 -> Paris | D48: =_xlfn.SUMIFS(Moteur!$P$1:$P$200,Moteur!$D$1:$D$200,$A48,Moteur!$B$1:$B$200,$P$1) -> 398.78245 | E48: =_xlfn.SUMIFS(Moteur!$R$1:$R$200,Moteur!$D$1:$D$200,$A48,Moteur!$B$1:$B$200,$P$1) -> 3292150.8 | F48: =_xlfn.IFERROR(E48/D48,0) -> 8255.5057 | G48: =_xlfn.IFERROR(E48/SUM($E$39:$E$52),0) -> 0.1358613 | H48: =_xlfn.SUMIFS(_CALC_PNL!$T$1:$T$1347,_CALC_PNL!$A$1:$A$1347,$A48,_CALC_PNL!$D$1:$D$1347,$P$1,_CALC_PNL!$C$1:$C$1347,"2027") -> 1096393.8 | I48: =_xlfn.IFERROR(H48/E48,0) -> 0.33303268 | J48: =_xlfn.IFERROR(H48/D48,0) -> 2749.3532 | K48: =_xlfn.SUMIFS(Pilotage!$K$19:$K$32,Pilotage!$A$19:$A$32,$A48)*_xlfn.SUMIFS(Pilotage!$J$19:$J$32,Pilotage!$A$19:$A$32,$A48)*(SUM(Pilotage!$K$19:$K$32)/SUMPRODUCT(Pilotage!$K$19:$K$32,Pilotage!$J$19:$J$32)) -> 68291 | L48: =_xlfn.SUMIFS(Pilotage!$D$19:$D$32,Pilotage!$A$19:$A$32,$A48) -> 1475.0192
A49: =A29 -> PIGIER_BOR | B49: =B29 -> Pigier | C49: =C29 -> Bordeaux | D49: =_xlfn.SUMIFS(Moteur!$P$1:$P$200,Moteur!$D$1:$D$200,$A49,Moteur!$B$1:$B$200,$P$1) -> 184.71663 | E49: =_xlfn.SUMIFS(Moteur!$R$1:$R$200,Moteur!$D$1:$D$200,$A49,Moteur!$B$1:$B$200,$P$1) -> 1191512.5 | F49: =_xlfn.IFERROR(E49/D49,0) -> 6450.4887 | G49: =_xlfn.IFERROR(E49/SUM($E$39:$E$52),0) -> 0.049171637 | H49: =_xlfn.SUMIFS(_CALC_PNL!$T$1:$T$1347,_CALC_PNL!$A$1:$A$1347,$A49,_CALC_PNL!$D$1:$D$1347,$P$1,_CALC_PNL!$C$1:$C$1347,"2027") -> 455099.2 | I49: =_xlfn.IFERROR(H49/E49,0) -> 0.38195082 | J49: =_xlfn.IFERROR(H49/D49,0) -> 2463.7695 | K49: =_xlfn.SUMIFS(Pilotage!$K$19:$K$32,Pilotage!$A$19:$A$32,$A49)*_xlfn.SUMIFS(Pilotage!$J$19:$J$32,Pilotage!$A$19:$A$32,$A49)*(SUM(Pilotage!$K$19:$K$32)/SUMPRODUCT(Pilotage!$K$19:$K$32,Pilotage!$J$19:$J$32)) -> 21968 | L49: =_xlfn.SUMIFS(Pilotage!$D$19:$D$32,Pilotage!$A$19:$A$32,$A49) -> 1368.091
A50: =A30 -> PIGIER_LYO | B50: =B30 -> Pigier | C50: =C30 -> Lyon | D50: =_xlfn.SUMIFS(Moteur!$P$1:$P$200,Moteur!$D$1:$D$200,$A50,Moteur!$B$1:$B$200,$P$1) -> 236.94751 | E50: =_xlfn.SUMIFS(Moteur!$R$1:$R$200,Moteur!$D$1:$D$200,$A50,Moteur!$B$1:$B$200,$P$1) -> 1653869.9 | F50: =_xlfn.IFERROR(E50/D50,0) -> 6979.8999 | G50: =_xlfn.IFERROR(E50/SUM($E$39:$E$52),0) -> 0.068252317 | H50: =_xlfn.SUMIFS(_CALC_PNL!$T$1:$T$1347,_CALC_PNL!$A$1:$A$1347,$A50,_CALC_PNL!$D$1:$D$1347,$P$1,_CALC_PNL!$C$1:$C$1347,"2027") -> 626670.52 | I50: =_xlfn.IFERROR(H50/E50,0) -> 0.37891162 | J50: =_xlfn.IFERROR(H50/D50,0) -> 2644.7652 | K50: =_xlfn.SUMIFS(Pilotage!$K$19:$K$32,Pilotage!$A$19:$A$32,$A50)*_xlfn.SUMIFS(Pilotage!$J$19:$J$32,Pilotage!$A$19:$A$32,$A50)*(SUM(Pilotage!$K$19:$K$32)/SUMPRODUCT(Pilotage!$K$19:$K$32,Pilotage!$J$19:$J$32)) -> 36612 | L50: =_xlfn.SUMIFS(Pilotage!$D$19:$D$32,Pilotage!$A$19:$A$32,$A50) -> 1704.9846
... A52: =A32 -> TUNON_PAR | B52: =B32 -> Tunon | C52: =C32 -> Paris | D52: =_xlfn.SUMIFS(Moteur!$P$1:$P$200,Moteur!$D$1:$D$200,$A52,Moteur!$B$1:$B$200,$P$1) -> 143.56031 | E52: =_xlfn.SUMIFS(Moteur!$R$1:$R$200,Moteur!$D$1:$D$200,$A52,Moteur!$B$1:$B$200,$P$1) -> 1133628.6 | F52: =_xlfn.IFERROR(E52/D52,0) -> 7896.5321 | G52: =_xlfn.IFERROR(E52/SUM($E$39:$E$52),0) -> 0.046782868 | H52: =_xlfn.SUMIFS(_CALC_PNL!$T$1:$T$1347,_CALC_PNL!$A$1:$A$1347,$A52,_CALC_PNL!$D$1:$D$1347,$P$1,_CALC_PNL!$C$1:$C$1347,"2027") -> 220510.28 | I52: =_xlfn.IFERROR(H52/E52,0) -> 0.19451722 | J52: =_xlfn.IFERROR(H52/D52,0) -> 1536.0115 | K52: =_xlfn.SUMIFS(Pilotage!$K$19:$K$32,Pilotage!$A$19:$A$32,$A52)*_xlfn.SUMIFS(Pilotage!$J$19:$J$32,Pilotage!$A$19:$A$32,$A52)*(SUM(Pilotage!$K$19:$K$32)/SUMPRODUCT(Pilotage!$K$19:$K$32,Pilotage!$J$19:$J$32)) -> 30240 | L52: =_xlfn.SUMIFS(Pilotage!$D$19:$D$32,Pilotage!$A$19:$A$32,$A52) -> 2192.8927
A53: Sous-total campus | B53: Sous-total campus | D53: =SUM(D39:D52) -> 3253.6168 | E53: =SUM(E39:E52) -> 24231704 | F53: =_xlfn.IFERROR(E53/D53,0) -> 7447.6206 | G53: =SUM(G39:G52) -> 1 | H53: =SUM(H39:H52) -> 7831343.6 | I53: =_xlfn.IFERROR(H53/E53,0) -> 0.32318585 | J53: =_xlfn.IFERROR(H53/D53,0) -> 2406.9656 | K53: =SUM(K39:K52) -> 434174
A54: Siege / holding (GRP) | B54: Siege / holding (GRP) | H54: =_xlfn.SUMIFS(_CALC_PNL!$T$1:$T$1347,_CALC_PNL!$A$1:$A$1347,"GRP",_CALC_PNL!$D$1:$D$1347,$P$1,_CALC_PNL!$C$1:$C$1347,"2027") -> -3719840
A55: GROUPE 2027 V01 | B55: GROUPE 2027 V01 | D55: =D53 -> 3253.6168 | E55: =E53 -> 24231704 | F55: =_xlfn.IFERROR(E55/D55,0) -> 7447.6206 | G55: =SUM(G39:G52) -> 1 | H55: =H53+H54 -> 4111503.6 | I55: =_xlfn.IFERROR(H55/E55,0) -> 0.16967456 | J55: =_xlfn.IFERROR(H55/D55,0) -> 1263.6717 | K55: =SUM(K39:K52) -> 434174

Sheet Socle
A1: SCENARIO | B1: PERIODE | C1: ENTITY | D1: PROGRAMME | E1: AN_ETUDE | F1: MODALITE | G1: EXERCICE | H1: VOL_LEAD | I1: VOL_CAND | J1: VOL_ADMIS | K1: VOL_NEW | L1: VOL_REINS | M1: VOL_EFF | N1: VOL_EFF_INF | O1: VOL_CLASS | P1: REV_STUD | Q1: REV_FRAIS_INS | R1: VOL_LEAD_ORG | S1: VOL_LEAD_PAY | T1: DEPENSE_ACQ | U1: DEPENSE_MARQUE | V1: TX_PASSAGE | W1: TX_LEAD_CAND | X1: TX_CAND_ADMIS | Y1: TX_YIELD_ADMIS_INSC | Z1: VOL_LEAD_TOTAL | AA1: PART_ORG | AB1: CPL | AC1: CA
A2: 2027BUD_V1 | B2: 12 | C2: IPAC_MTP | D2: BAC_CCE | E2: B1 | F2: ALT | G2: 2026 | H2: 680 | I2: 136 | J2: 95 | K2: 40 | L2: 0 | M2: 40 | N2: 0 | O2: 2 | P2: 6650 | Q2: 90 | R2: 258 | S2: 422 | T2: 15178 | U2: 23514 | V2: 0 | W2: 0.2 | X2: 0.69852941 | Y2: 0.42105263 | Z2: 680 | AA2: 0.37941177 | AB2: 35.966825 | AC2: 269600
A3: 2027BUD_V1 | B3: 12 | C3: IPAC_MTP | D3: BAC_CCE | E3: B2 | F3: ALT | G3: 2026 | H3: 0 | I3: 0 | J3: 0 | K3: 0 | L3: 39 | M3: 39 | N3: 40 | O3: 2 | P3: 6650 | Q3: 90 | R3: 0 | S3: 0 | T3: 0 | U3: 0 | V3: 0.975 | W3: 0 | X3: 0 | Y3: 0 | Z3: 0 | AA3: 0 | AB3: 0 | AC3: 259350
A4: 2027BUD_V1 | B4: 12 | C4: IPAC_MTP | D4: BAC_CCE | E4: B3 | F4: ALT | G4: 2026 | H4: 0 | I4: 0 | J4: 0 | K4: 0 | L4: 38 | M4: 38 | N4: 39 | O4: 2 | P4: 6650 | Q4: 90 | R4: 0 | S4: 0 | T4: 0 | U4: 0 | V4: 0.97435897 | W4: 0 | X4: 0 | Y4: 0 | Z4: 0 | AA4: 0 | AB4: 0 | AC4: 252700
A5: 2027BUD_V1 | B5: 12 | C5: IPAC_MTP | D5: BAC_CCE | E5: B1 | F5: ALT | G5: 2025 | H5: 642 | I5: 128 | J5: 90 | K5: 38 | L5: 0 | M5: 38 | N5: 0 | O5: 2 | P5: 6650 | Q5: 90 | R5: 237 | S5: 399 | T5: 13798 | U5: 17870 | V5: 0 | W5: 0.19937695 | X5: 0.703125 | Y5: 0.42222222 | Z5: 636 | AA5: 0.37264151 | AB5: 34.581454 | AC5: 256120
A6: 2027BUD_V1 | B6: 12 | C6: IPAC_MTP | D6: BAC_CCE | E6: B2 | F6: ALT | G6: 2025 | H6: 0 | I6: 0 | J6: 0 | K6: 0 | L6: 37 | M6: 37 | N6: 38 | O6: 2 | P6: 6650 | Q6: 90 | R6: 0 | S6: 0 | T6: 0 | U6: 0 | V6: 0.97368421 | W6: 0 | X6: 0 | Y6: 0 | Z6: 0 | AA6: 0 | AB6: 0 | AC6: 246050
A7: 2027BUD_V1 | B7: 12 | C7: IPAC_MTP | D7: BAC_CCE | E7: B3 | F7: ALT | G7: 2025 | H7: 0 | I7: 0 | J7: 0 | K7: 0 | L7: 36 | M7: 36 | N7: 37 | O7: 2 | P7: 6650 | Q7: 90 | R7: 0 | S7: 0 | T7: 0 | U7: 0 | V7: 0.97297297 | W7: 0 | X7: 0 | Y7: 0 | Z7: 0 | AA7: 0 | AB7: 0 | AC7: 239400
A8: 2027BUD_V1 | B8: 12 | C8: IPAC_MTP | D8: BAC_CCE | E8: B1 | F8: ALT | G8: 2024 | H8: 605 | I8: 121 | J8: 85 | K8: 36 | L8: 0 | M8: 36 | N8: 0 | O8: 2 | P8: 6650 | Q8: 90 | R8: 217 | S8: 377 | T8: 12543 | U8: 13581 | V8: 0 | W8: 0.2 | X8: 0.70247934 | Y8: 0.42352941 | Z8: 594 | AA8: 0.36531987 | AB8: 33.270557 | AC8: 242640
A9: 2027BUD_V1 | B9: 12 | C9: IPAC_MTP | D9: BAC_CCE | E9: B2 | F9: ALT | G9: 2024 | H9: 0 | I9: 0 | J9: 0 | K9: 0 | L9: 35 | M9: 35 | N9: 36 | O9: 2 | P9: 6650 | Q9: 90 | R9: 0 | S9: 0 | T9: 0 | U9: 0 | V9: 0.97222222 | W9: 0 | X9: 0 | Y9: 0 | Z9: 0 | AA9: 0 | AB9: 0 | AC9: 232750
A10: 2027BUD_V1 | B10: 12 | C10: IPAC_MTP | D10: BAC_CCE | E10: B3 | F10: ALT | G10: 2024 | H10: 0 | I10: 0 | J10: 0 | K10: 0 | L10: 34 | M10: 34 | N10: 35 | O10: 2 | P10: 6650 | Q10: 90 | R10: 0 | S10: 0 | T10: 0 | U10: 0 | V10: 0.97142857 | W10: 0 | X10: 0 | Y10: 0 | Z10: 0 | AA10: 0 | AB10: 0 | AC10: 226100
A11: 2027BUD_V1 | B11: 12 | C11: IPAC_NAN | D11: BAC_CCE | E11: B1 | F11: ALT | G11: 2024 | H11: 756 | I11: 151 | J11: 106 | K11: 44 | L11: 0 | M11: 44 | N11: 0 | O11: 2 | P11: 7000 | Q11: 90 | R11: 258 | S11: 489 | T11: 17983 | U11: 15937 | V11: 0 | W11: 0.19973545 | X11: 0.70198675 | Y11: 0.41509434 | Z11: 747 | AA11: 0.34538153 | AB11: 36.775051 | AC11: 311960
A12: 2027BUD_V1 | B12: 12 | C12: IPAC_NAN | D12: BAC_CCE | E12: B2 | F12: ALT | G12: 2024 | H12: 0 | I12: 0 | J12: 0 | K12: 0 | L12: 43 | M12: 43 | N12: 44 | O12: 2 | P12: 7000 | Q12: 90 | R12: 0 | S12: 0 | T12: 0 | U12: 0 | V12: 0.97727273 | W12: 0 | X12: 0 | Y12: 0 | Z12: 0 | AA12: 0 | AB12: 0 | AC12: 301000
A13: 2027BUD_V1 | B13: 12 | C13: IPAC_NAN | D13: BAC_CCE | E13: B3 | F13: ALT | G13: 2024 | H13: 0 | I13: 0 | J13: 0 | K13: 0 | L13: 42 | M13: 42 | N13: 43 | O13: 2 | P13: 7000 | Q13: 90 | R13: 0 | S13: 0 | T13: 0 | U13: 0 | V13: 0.97674419 | W13: 0 | X13: 0 | Y13: 0 | Z13: 0 | AA13: 0 | AB13: 0 | AC13: 294000
... A181: 2027BUD_V1 | B181: 12 | C181: TUNON_PAR | D181: BAC_TOU | E181: B3 | F181: ALT | G181: 2026 | H181: 0 | I181: 0 | J181: 0 | K181: 0 | L181: 45 | M181: 45 | N181: 46 | O181: 2 | P181: 7840 | Q181: 90 | R181: 0 | S181: 0 | T181: 0 | U181: 0 | V181: 0.97826087 | W181: 0 | X181: 0 | Y181: 0 | Z181: 0 | AA181: 0 | AB181: 0 | AC181: 352800

Sheet Campagne
A1: SCENARIO | B1: PERIODE | C1: ENTITY | D1: ORG_REF | E1: PAID_REF | F1: LEAD_REF | G1: SPEND_ACQ_REF | H1: SPEND_BRAND_REF | I1: PART_ORG | J1: CPL | K1: REND_ACQ | L1: CONVERSION | M1: REND_BRAND | N1: CAC_MARGINAL
A2: 2027BUD_V1 | B2: 12 | C2: IPAC_MTP | D2: 258 | E2: 422 | F2: 680 | G2: 15178 | H2: 23514 | I2: 0.379411 | J2: 35.966824 | K2: 0.59134489 | L2: 0.058823 | M2: 0.31527519 | N2: 1033.9846
A3: 2027BUD_V1 | B3: 12 | C3: IPAC_NAN | D3: 306 | E3: 544 | F3: 850 | G3: 21760 | H3: 27889 | I3: 0.36 | J3: 40 | K3: 0.55908079 | L3: 0.058823 | M3: 0.30491226 | N3: 1216.2931
A4: 2027BUD_V1 | B4: 12 | C4: IPAC_REN | D4: 265 | E4: 415 | F4: 680 | G4: 14933 | H4: 24152 | I4: 0.389705 | J4: 35.983132 | K4: 0.58787656 | L4: 0.058823 | M4: 0.31735415 | N4: 1040.5564
A5: 2027BUD_V1 | B5: 12 | C5: ISCOM_LIL | D5: 630 | E5: 630 | F5: 1260 | G5: 25220 | H5: 57418 | I5: 0.5 | J5: 40.031746 | K5: 0.51584831 | L5: 0.079302 | M5: 0.34838058 | N5: 978.58461
A6: 2027BUD_V1 | B6: 12 | C6: ISCOM_PAR | D6: 690 | E6: 1126 | F6: 1816 | G6: 60800 | H6: 62886 | I6: 0.379955 | J6: 53.996447 | K6: 0.44208627 | L6: 0.079295 | M6: 0.31719351 | N6: 1540.325
A7: 2027BUD_V1 | B7: 12 | C7: ISCOM_TLS | D7: 605 | E7: 581 | F7: 1186 | G7: 22083 | H7: 55139 | I7: 0.510118 | J7: 38.008605 | K7: 0.52180337 | L7: 0.079258 | M7: 0.35585226 | N7: 919.03477
A8: 2027BUD_V1 | B8: 12 | C8: MBWAY_BOR | D8: 630 | E8: 656 | F8: 1286 | G8: 24923 | H8: 57418 | I8: 0.489891 | J8: 37.992378 | K8: 0.53845529 | L8: 0.079315 | M8: 0.34824917 | N8: 889.59329
A9: 2027BUD_V1 | B9: 12 | C9: MBWAY_LYO | D9: 716 | E9: 950 | F9: 1666 | G9: 41783 | H9: 65255 | I9: 0.429771 | J9: 43.982105 | K9: 0.50391241 | L9: 0.079231 | M9: 0.32659376 | N9: 1101.6048
A10: 2027BUD_V1 | B10: 12 | C10: MBWAY_NAN | D10: 728 | E10: 788 | F10: 1516 | G10: 31533 | H10: 66349 | I10: 0.480211 | J10: 40.016497 | K10: 0.52465564 | L10: 0.079155 | M10: 0.34345059 | N10: 963.57687
A11: 2027BUD_V1 | B11: 12 | C11: MBWAY_PAR | D11: 711 | E11: 1265 | F11: 1976 | G11: 68291 | H11: 64800 | I11: 0.359817 | J11: 53.98498 | K11: 0.46359595 | L11: 0.078947 | M11: 0.30805412 | N11: 1475.0192
A12: 2027BUD_V1 | B12: 12 | C12: PIGIER_BOR | D12: 652 | E12: 578 | F12: 1230 | G12: 21968 | H12: 59423 | I12: 0.530081 | J12: 38.00692 | K12: 0.47459663 | L12: 0.058536 | M12: 0.35757396 | N12: 1368.091
A13: 2027BUD_V1 | B13: 12 | C13: PIGIER_LYO | D13: 738 | E13: 832 | F13: 1570 | G13: 36612 | H13: 67261 | I13: 0.470063 | J13: 44.004807 | K13: 0.44045026 | L13: 0.058598 | M13: 0.34304578 | N13: 1704.9846
... A15: 2027BUD_V1 | B15: 12 | C15: TUNON_PAR | D15: 240 | E15: 560 | F15: 800 | G15: 30240 | H15: 21873 | I15: 0.3 | J15: 54 | K15: 0.41914907 | L15: 0.05875 | M15: 0.27988845 | N15: 2192.8927

Sheet Moteur
A1: SCENARIO | B1: VERSION | C1: PERIODE | D1: ENTITY | E1: MARQUE | F1: PROGRAMME | G1: AN_ETUDE | H1: MODALITE | I1: EXERCICE | J1: NOUVEAUX | K1: EFFECTIF | L1: PRIX | M1: CA | O1: NOUVEAUX (live) | P1: EFFECTIF (live) | Q1: PRIX (live) | R1: 🟢 CA (live) | S1: Δ CA vs Tagetik
A2: 2027BUD_V1 | B2: V01 | C2: 12 | D2: MBWAY_PAR | E2: MBWAY | F2: BAC_MGT | G2: B1 | H2: INIT | I2: 2027 | J2: 84.920597 | K2: 84.920597 | L2: 8429.232 | M2: 723458.27 | O2: =IF(D2="","",_CALC_MOTEUR!AE2) -> 84.920594 | P2: =IF(D2="","",_CALC_MOTEUR!AF2) -> 84.920594 | Q2: =IF(D2="","",_CALC_MOTEUR!AG2) -> 8429.232 | R2: =IF(D2="","",_CALC_MOTEUR!AH2) -> 723458.24 | S2: =IF(D2="","",R2-M2) -> -0.024558644
A3: 2027BUD_V1 | B3: V01 | C3: 12 | D3: MBWAY_PAR | E3: MBWAY | F3: BAC_MGT | G3: B2 | H3: ALT | I3: 2027 | J3: 0 | K3: 76.39 | L3: 7867.2832 | M3: 600981.76 | O3: =IF(D3="","",_CALC_MOTEUR!AE3) -> 0 | P3: =IF(D3="","",_CALC_MOTEUR!AF3) -> 76.39 | Q3: =IF(D3="","",_CALC_MOTEUR!AG3) -> 7867.2832 | R3: =IF(D3="","",_CALC_MOTEUR!AH3) -> 600981.76 | S3: =IF(D3="","",R3-M3) -> -0.00022028398
A4: 2027BUD_V1 | B4: V01 | C4: 12 | D4: MBWAY_PAR | E4: MBWAY | F4: BAC_MGT | G4: B3 | H4: ALT | I4: 2027 | J4: 0 | K4: 74.38 | L4: 7867.2832 | M4: 585168.52 | O4: =IF(D4="","",_CALC_MOTEUR!AE4) -> 0 | P4: =IF(D4="","",_CALC_MOTEUR!AF4) -> 74.38 | Q4: =IF(D4="","",_CALC_MOTEUR!AG4) -> 7867.2832 | R4: =IF(D4="","",_CALC_MOTEUR!AH4) -> 585168.52 | S4: =IF(D4="","",R4-M4) -> 0.00028322195
A5: 2027BUD_V1 | B5: V01 | C5: 12 | D5: MBWAY_PAR | E5: MBWAY | F5: MAS_MGT | G5: M1 | H5: ALT | I5: 2027 | J5: 86.70186 | K5: 86.70186 | L5: 8429.232 | M5: 738633.26 | O5: =IF(D5="","",_CALC_MOTEUR!AE5) -> 86.701858 | P5: =IF(D5="","",_CALC_MOTEUR!AF5) -> 86.701858 | Q5: =IF(D5="","",_CALC_MOTEUR!AG5) -> 8429.232 | R5: =IF(D5="","",_CALC_MOTEUR!AH5) -> 738633.24 | S5: =IF(D5="","",R5-M5) -> -0.019111536
A6: 2027BUD_V1 | B6: V01 | C6: 12 | D6: MBWAY_PAR | E6: MBWAY | F6: MAS_MGT | G6: M2 | H6: ALT | I6: 2027 | J6: 0 | K6: 76.39 | L6: 8429.232 | M6: 643909.03 | O6: =IF(D6="","",_CALC_MOTEUR!AE6) -> 0 | P6: =IF(D6="","",_CALC_MOTEUR!AF6) -> 76.39 | Q6: =IF(D6="","",_CALC_MOTEUR!AG6) -> 8429.232 | R6: =IF(D6="","",_CALC_MOTEUR!AH6) -> 643909.03 | S6: =IF(D6="","",R6-M6) -> -0.00023601903
A7: 2027BUD_V1 | B7: V01 | C7: 12 | D7: MBWAY_LYO | E7: MBWAY | F7: BAC_MGT | G7: B1 | H7: INIT | I7: 2027 | J7: 72.005855 | K7: 72.005855 | L7: 7902.405 | M7: 575499.96 | O7: =IF(D7="","",_CALC_MOTEUR!AE7) -> 72.005873 | P7: =IF(D7="","",_CALC_MOTEUR!AF7) -> 72.005873 | Q7: =IF(D7="","",_CALC_MOTEUR!AG7) -> 7902.405 | R7: =IF(D7="","",_CALC_MOTEUR!AH7) -> 575500.1 | S7: =IF(D7="","",R7-M7) -> 0.14050092
A8: 2027BUD_V1 | B8: V01 | C8: 12 | D8: MBWAY_LYO | E8: MBWAY | F8: BAC_MGT | G8: B2 | H8: ALT | I8: 2027 | J8: 0 | K8: 64.33 | L8: 7375.578 | M8: 474470.93 | O8: =IF(D8="","",_CALC_MOTEUR!AE8) -> 0 | P8: =IF(D8="","",_CALC_MOTEUR!AF8) -> 64.33 | Q8: =IF(D8="","",_CALC_MOTEUR!AG8) -> 7375.578 | R8: =IF(D8="","",_CALC_MOTEUR!AH8) -> 474470.93 | S8: =IF(D8="","",R8-M8) -> 0.00014751201
A9: 2027BUD_V1 | B9: V01 | C9: 12 | D9: MBWAY_LYO | E9: MBWAY | F9: BAC_MGT | G9: B3 | H9: ALT | I9: 2027 | J9: 0 | K9: 63.32 | L9: 7375.578 | M9: 467021.6 | O9: =IF(D9="","",_CALC_MOTEUR!AE9) -> 0 | P9: =IF(D9="","",_CALC_MOTEUR!AF9) -> 63.32 | Q9: =IF(D9="","",_CALC_MOTEUR!AG9) -> 7375.578 | R9: =IF(D9="","",_CALC_MOTEUR!AH9) -> 467021.6 | S9: =IF(D9="","",R9-M9) -> 0
A10: 2027BUD_V1 | B10: V01 | C10: 12 | D10: MBWAY_LYO | E10: MBWAY | F10: MAS_MGT | G10: M1 | H10: ALT | I10: 2027 | J10: 73.512347 | K10: 73.512347 | L10: 7902.405 | M10: 587540.45 | O10: =IF(D10="","",_CALC_MOTEUR!AE10) -> 73.512365 | P10: =IF(D10="","",_CALC_MOTEUR!AF10) -> 73.512365 | Q10: =IF(D10="","",_CALC_MOTEUR!AG10) -> 7902.405 | R10: =IF(D10="","",_CALC_MOTEUR!AH10) -> 587540.59 | S10: =IF(D10="","",R10-M10) -> 0.14475602
A11: 2027BUD_V1 | B11: V01 | C11: 12 | D11: MBWAY_LYO | E11: MBWAY | F11: MAS_MGT | G11: M2 | H11: ALT | I11: 2027 | J11: 0 | K11: 65.33 | L11: 7902.405 | M11: 516264.12 | O11: =IF(D11="","",_CALC_MOTEUR!AE11) -> 0 | P11: =IF(D11="","",_CALC_MOTEUR!AF11) -> 65.33 | Q11: =IF(D11="","",_CALC_MOTEUR!AG11) -> 7902.405 | R11: =IF(D11="","",_CALC_MOTEUR!AH11) -> 516264.12 | S11: =IF(D11="","",R11-M11) -> 7.9024001e-05
A12: 2027BUD_V1 | B12: V01 | C12: 12 | D12: MBWAY_NAN | E12: MBWAY | F12: BAC_MGT | G12: B1 | H12: INIT | I12: 2027 | J12: 65.539302 | K12: 65.539302 | L12: 7526.1 | M12: 499153.88 | O12: =IF(D12="","",_CALC_MOTEUR!AE12) -> 65.539313 | P12: =IF(D12="","",_CALC_MOTEUR!AF12) -> 65.539313 | Q12: =IF(D12="","",_CALC_MOTEUR!AG12) -> 7526.1 | R12: =IF(D12="","",_CALC_MOTEUR!AH12) -> 499153.96 | S12: =IF(D12="","",R12-M12) -> 0.080706865
A13: 2027BUD_V1 | B13: V01 | C13: 12 | D13: MBWAY_NAN | E13: MBWAY | F13: BAC_MGT | G13: B2 | H13: ALT | I13: 2027 | J13: 0 | K13: 58.3 | L13: 7024.36 | M13: 409520.19 | O13: =IF(D13="","",_CALC_MOTEUR!AE13) -> 0 | P13: =IF(D13="","",_CALC_MOTEUR!AF13) -> 58.3 | Q13: =IF(D13="","",_CALC_MOTEUR!AG13) -> 7024.36 | R13: =IF(D13="","",_CALC_MOTEUR!AH13) -> 409520.19 | S13: =IF(D13="","",R13-M13) -> 0.00014048698
... A181: 2027BUD_V1 | B181: V03 | C181: 12 | D181: PIGIER_LYO | E181: PIGIER | F181: BAC_RH | G181: B3 | H181: ALT | I181: 2027 | J181: 0 | K181: 43.55 | L181: 7482.3 | M181: 325854.16 | O181: =IF(D181="","",_CALC_MOTEUR!AE181) -> 0 | P181: =IF(D181="","",_CALC_MOTEUR!AF181) -> 43.55 | Q181: =IF(D181="","",_CALC_MOTEUR!AG181) -> 7482.3 | R181: =IF(D181="","",_CALC_MOTEUR!AH181) -> 325854.17 | S181: =IF(D181="","",R181-M181) -> 7.4823038e-05
O182: =IF(D182="","",_CALC_MOTEUR!AE182) | P182: =IF(D182="","",_CALC_MOTEUR!AF182) | Q182: =IF(D182="","",_CALC_MOTEUR!AG182) | R182: =IF(D182="","",_CALC_MOTEUR!AH182) | S182: =IF(D182="","",R182-M182)
O183: =IF(D183="","",_CALC_MOTEUR!AE183) | P183: =IF(D183="","",_CALC_MOTEUR!AF183) | Q183: =IF(D183="","",_CALC_MOTEUR!AG183) | R183: =IF(D183="","",_CALC_MOTEUR!AH183) | S183: =IF(D183="","",R183-M183)
O184: =IF(D184="","",_CALC_MOTEUR!AE184) | P184: =IF(D184="","",_CALC_MOTEUR!AF184) | Q184: =IF(D184="","",_CALC_MOTEUR!AG184) | R184: =IF(D184="","",_CALC_MOTEUR!AH184) | S184: =IF(D184="","",R184-M184)
O185: =IF(D185="","",_CALC_MOTEUR!AE185) | P185: =IF(D185="","",_CALC_MOTEUR!AF185) | Q185: =IF(D185="","",_CALC_MOTEUR!AG185) | R185: =IF(D185="","",_CALC_MOTEUR!AH185) | S185: =IF(D185="","",R185-M185)
O186: =IF(D186="","",_CALC_MOTEUR!AE186) | P186: =IF(D186="","",_CALC_MOTEUR!AF186) | Q186: =IF(D186="","",_CALC_MOTEUR!AG186) | R186: =IF(D186="","",_CALC_MOTEUR!AH186) | S186: =IF(D186="","",R186-M186)
O187: =IF(D187="","",_CALC_MOTEUR!AE187) | P187: =IF(D187="","",_CALC_MOTEUR!AF187) | Q187: =IF(D187="","",_CALC_MOTEUR!AG187) | R187: =IF(D187="","",_CALC_MOTEUR!AH187) | S187: =IF(D187="","",R187-M187)
O188: =IF(D188="","",_CALC_MOTEUR!AE188) | P188: =IF(D188="","",_CALC_MOTEUR!AF188) | Q188: =IF(D188="","",_CALC_MOTEUR!AG188) | R188: =IF(D188="","",_CALC_MOTEUR!AH188) | S188: =IF(D188="","",R188-M188)
O189: =IF(D189="","",_CALC_MOTEUR!AE189) | P189: =IF(D189="","",_CALC_MOTEUR!AF189) | Q189: =IF(D189="","",_CALC_MOTEUR!AG189) | R189: =IF(D189="","",_CALC_MOTEUR!AH189) | S189: =IF(D189="","",R189-M189)
O190: =IF(D190="","",_CALC_MOTEUR!AE190) | P190: =IF(D190="","",_CALC_MOTEUR!AF190) | Q190: =IF(D190="","",_CALC_MOTEUR!AG190) | R190: =IF(D190="","",_CALC_MOTEUR!AH190) | S190: =IF(D190="","",R190-M190)
O191: =IF(D191="","",_CALC_MOTEUR!AE191) | P191: =IF(D191="","",_CALC_MOTEUR!AF191) | Q191: =IF(D191="","",_CALC_MOTEUR!AG191) | R191: =IF(D191="","",_CALC_MOTEUR!AH191) | S191: =IF(D191="","",R191-M191)
O192: =IF(D192="","",_CALC_MOTEUR!AE192) | P192: =IF(D192="","",_CALC_MOTEUR!AF192) | Q192: =IF(D192="","",_CALC_MOTEUR!AG192) | R192: =IF(D192="","",_CALC_MOTEUR!AH192) | S192: =IF(D192="","",R192-M192)
O193: =IF(D193="","",_CALC_MOTEUR!AE193) | P193: =IF(D193="","",_CALC_MOTEUR!AF193) | Q193: =IF(D193="","",_CALC_MOTEUR!AG193) | R193: =IF(D193="","",_CALC_MOTEUR!AH193) | S193: =IF(D193="","",R193-M193)
... O207: =IF(D207="","",_CALC_MOTEUR!AE207) | P207: =IF(D207="","",_CALC_MOTEUR!AF207) | Q207: =IF(D207="","",_CALC_MOTEUR!AG207) | R207: =IF(D207="","",_CALC_MOTEUR!AH207) | S207: =IF(D207="","",R207-M207)

Sheet Comptabilité
A1: Entity | B1: Account | C1: EXERCICE | D1: Scenario | E1: Period | F1: Amount
A2: MBWAY_PAR | B2: 7062 | C2: 2024 | D2: 2027BUD_V1 | E2: 12 | F2: 2201360
A3: MBWAY_LYO | B3: 7062 | C3: 2024 | D3: 2027BUD_V1 | E3: 12 | F3: 1751925
A4: MBWAY_NAN | B4: 7062 | C4: 2024 | D4: 2027BUD_V1 | E4: 12 | F4: 1516000
A5: MBWAY_BOR | B5: 7062 | C5: 2024 | D5: 2027BUD_V1 | E5: 12 | F5: 1238205
A6: ISCOM_PAR | B6: 7062 | C6: 2024 | D6: 2027BUD_V1 | E6: 12 | F6: 2031120
A7: ISCOM_LIL | B7: 7062 | C7: 2024 | D7: 2027BUD_V1 | E7: 12 | F7: 1229900
A8: ISCOM_TLS | B8: 7062 | C8: 2024 | D8: 2027BUD_V1 | E8: 12 | F8: 1141920
A9: IPAC_NAN | B9: 7062 | C9: 2024 | D9: 2027BUD_V1 | E9: 12 | F9: 903000
A10: IPAC_REN | B10: 7062 | C10: 2024 | D10: 2027BUD_V1 | E10: 12 | F10: 698250
A11: IPAC_MTP | B11: 7062 | C11: 2024 | D11: 2027BUD_V1 | E11: 12 | F11: 698250
A12: TUNON_PAR | B12: 7062 | C12: 2024 | D12: 2027BUD_V1 | E12: 12 | F12: 964320
A13: TUNON_LYO | B13: 7062 | C13: 2024 | D13: 2027BUD_V1 | E13: 12 | F13: 771750
... A673: PIGIER_LYO | B673: 7062 | C673: 2026 | D673: 2027BUD_V1 | E673: 12 | F673: 1565550

Sheet PNL
A1: ENTITY | B1: ACCOUNT | C1: EXERCICE | D1: VERSION | E1: SCENARIO | F1: PERIOD | G1: AMOUNT | H1: 🟢 AMOUNT (live) | I1: Δ vs Tagetik
A2: MBWAY_PAR | B2: 7062 | C2: 2024 | D2: ACT | E2: 2027BUD_V1 | F2: 12 | G2: 2201360 | H2: =IF(PNL!A2="","",_CALC_PNL!P2) -> 2201360 | I2: =IF(PNL!A2="","",IF(_CALC_PNL!E2=1,H2-G2,""))
A3: MBWAY_LYO | B3: 7062 | C3: 2024 | D3: ACT | E3: 2027BUD_V1 | F3: 12 | G3: 1751925 | H3: =IF(PNL!A3="","",_CALC_PNL!P3) -> 1751925 | I3: =IF(PNL!A3="","",IF(_CALC_PNL!E3=1,H3-G3,""))
A4: MBWAY_NAN | B4: 7062 | C4: 2024 | D4: ACT | E4: 2027BUD_V1 | F4: 12 | G4: 1516000 | H4: =IF(PNL!A4="","",_CALC_PNL!P4) -> 1516000 | I4: =IF(PNL!A4="","",IF(_CALC_PNL!E4=1,H4-G4,""))
A5: MBWAY_BOR | B5: 7062 | C5: 2024 | D5: ACT | E5: 2027BUD_V1 | F5: 12 | G5: 1238205 | H5: =IF(PNL!A5="","",_CALC_PNL!P5) -> 1238205 | I5: =IF(PNL!A5="","",IF(_CALC_PNL!E5=1,H5-G5,""))
A6: ISCOM_PAR | B6: 7062 | C6: 2024 | D6: ACT | E6: 2027BUD_V1 | F6: 12 | G6: 2031120 | H6: =IF(PNL!A6="","",_CALC_PNL!P6) -> 2031120 | I6: =IF(PNL!A6="","",IF(_CALC_PNL!E6=1,H6-G6,""))
A7: ISCOM_LIL | B7: 7062 | C7: 2024 | D7: ACT | E7: 2027BUD_V1 | F7: 12 | G7: 1229900 | H7: =IF(PNL!A7="","",_CALC_PNL!P7) -> 1229900 | I7: =IF(PNL!A7="","",IF(_CALC_PNL!E7=1,H7-G7,""))
A8: ISCOM_TLS | B8: 7062 | C8: 2024 | D8: ACT | E8: 2027BUD_V1 | F8: 12 | G8: 1141920 | H8: =IF(PNL!A8="","",_CALC_PNL!P8) -> 1141920 | I8: =IF(PNL!A8="","",IF(_CALC_PNL!E8=1,H8-G8,""))
A9: IPAC_NAN | B9: 7062 | C9: 2024 | D9: ACT | E9: 2027BUD_V1 | F9: 12 | G9: 903000 | H9: =IF(PNL!A9="","",_CALC_PNL!P9) -> 903000 | I9: =IF(PNL!A9="","",IF(_CALC_PNL!E9=1,H9-G9,""))
A10: IPAC_REN | B10: 7062 | C10: 2024 | D10: ACT | E10: 2027BUD_V1 | F10: 12 | G10: 698250 | H10: =IF(PNL!A10="","",_CALC_PNL!P10) -> 698250 | I10: =IF(PNL!A10="","",IF(_CALC_PNL!E10=1,H10-G10,""))
A11: IPAC_MTP | B11: 7062 | C11: 2024 | D11: ACT | E11: 2027BUD_V1 | F11: 12 | G11: 698250 | H11: =IF(PNL!A11="","",_CALC_PNL!P11) -> 698250 | I11: =IF(PNL!A11="","",IF(_CALC_PNL!E11=1,H11-G11,""))
A12: TUNON_PAR | B12: 7062 | C12: 2024 | D12: ACT | E12: 2027BUD_V1 | F12: 12 | G12: 964320 | H12: =IF(PNL!A12="","",_CALC_PNL!P12) -> 964320 | I12: =IF(PNL!A12="","",IF(_CALC_PNL!E12=1,H12-G12,""))
A13: TUNON_LYO | B13: 7062 | C13: 2024 | D13: ACT | E13: 2027BUD_V1 | F13: 12 | G13: 771750 | H13: =IF(PNL!A13="","",_CALC_PNL!P13) -> 771750 | I13: =IF(PNL!A13="","",IF(_CALC_PNL!E13=1,H13-G13,""))
... A1345: TUNON_PAR | B1345: 708 | C1345: 2027 | D1345: V03 | E1345: 2027BUD_V1 | F1345: 12 | G1345: 4148.0311 | H1345: =IF(PNL!A1345="","",_CALC_PNL!P1345) -> 4148.0314 | I1345: =IF(PNL!A1345="","",IF(_CALC_PNL!E1345=1,H1345-G1345,"")) -> 0.00033472774
H1346: =IF(PNL!A1346="","",_CALC_PNL!P1346) | I1346: =IF(PNL!A1346="","",IF(_CALC_PNL!E1346=1,H1346-G1346,""))
H1347: =IF(PNL!A1347="","",_CALC_PNL!P1347) | I1347: =IF(PNL!A1347="","",IF(_CALC_PNL!E1347=1,H1347-G1347,""))

Sheet _CALC_MOTEUR
A1: KENT | B1: KVER | C1: KPROG | D1: KAN | E1: KMOD | F1: KMARQ | G1: VOL_LEAD | H1: VOL_EFF_INF | I1: REV_STUD | J1: RLC | K1: RCA | L1: YLD | M1: PASSAGE | N1: IS_ENTRY | O1: ORG_REF | P1: PAID_REF | Q1: LEAD_REF | R1: REND_ACQ | S1: REND_BRAND | T1: REJOUE | U1: BUD_REF | V1: ACQ | W1: BRAND | X1: PRICE | Y1: GLC | Z1: GCV | AA1: PASS | AB1: FEE | AC1: PRICE_COEF | AD1: NOUV_CALC | AE1: NOUVEAUX | AF1: EFFECTIF | AG1: PRIX | AH1: CA | AJ1: ■ VIOLET = colonne branchee sur une saisie (cad / Pilotage / 3_Allocation) -> a recabler cote Tagetik
A2: =IF(Moteur!D2="","",Moteur!D2) -> MBWAY_PAR | B2: =IF(Moteur!B2="","",Moteur!B2) -> V01 | C2: =IF(Moteur!F2="","",Moteur!F2) -> BAC_MGT | D2: =IF(Moteur!G2="","",Moteur!G2) -> B1 | E2: =IF(Moteur!H2="","",Moteur!H2) -> INIT | F2: =IF(Moteur!E2="","",Moteur!E2) -> MBWAY | G2: =IF($A2="","",_xlfn.SUMIFS(Socle!$H$1:$H$658,Socle!$C$1:$C$658,$A2,Socle!$D$1:$D$658,$C2,Socle!$E$1:$E$658,$D2,Socle!$F$1:$F$658,$E2,Socle!$G$1:$G$658,"2026")) -> 646 | H2: =IF($A2="","",_xlfn.SUMIFS(Socle!$N$1:$N$658,Socle!$C$1:$C$658,$A2,Socle!$D$1:$D$658,$C2,Socle!$E$1:$E$658,$D2,Socle!$F$1:$F$658,$E2,Socle!$G$1:$G$658,"2026")) -> 0 | I2: =IF($A2="","",_xlfn.SUMIFS(Socle!$P$1:$P$658,Socle!$C$1:$C$658,$A2,Socle!$D$1:$D$658,$C2,Socle!$E$1:$E$658,$D2,Socle!$F$1:$F$658,$E2,Socle!$G$1:$G$658,"2026")) -> 8400 | J2: =IF($A2="","",_xlfn.SUMIFS(Socle!$W$1:$W$658,Socle!$C$1:$C$658,$A2,Socle!$D$1:$D$658,$C2,Socle!$E$1:$E$658,$D2,Socle!$F$1:$F$658,$E2,Socle!$G$1:$G$658,"2026")) -> 0.28018576 | K2: =IF($A2="","",_xlfn.SUMIFS(Socle!$X$1:$X$658,Socle!$C$1:$C$658,$A2,Socle!$D$1:$D$658,$C2,Socle!$E$1:$E$658,$D2,Socle!$F$1:$F$658,$E2,Socle!$G$1:$G$658,"2026")) -> 0.71823204 | L2: =IF($A2="","",_xlfn.SUMIFS(Socle!$Y$1:$Y$658,Socle!$C$1:$C$658,$A2,Socle!$D$1:$D$658,$C2,Socle!$E$1:$E$658,$D2,Socle!$F$1:$F$658,$E2,Socle!$G$1:$G$658,"2026")) -> 0.6 | M2: =IF($A2="","",_xlfn.SUMIFS(Socle!$V$1:$V$658,Socle!$C$1:$C$658,$A2,Socle!$D$1:$D$658,$C2,Socle!$E$1:$E$658,$D2,Socle!$F$1:$F$658,$E2,Socle!$G$1:$G$658,"2026")) -> 0 | N2: =IF($A2="","",IF(OR($D2="B1",$D2="M1",$D2="BTS1"),1,0)) -> 1 | O2: =IF($A2="","",_xlfn.SUMIFS(Campagne!$D$1:$D$141,Campagne!$C$1:$C$141,$A2)) -> 711 | P2: =IF($A2="","",_xlfn.SUMIFS(Campagne!$E$1:$E$141,Campagne!$C$1:$C$141,$A2)) -> 1265 | Q2: =IF($A2="","",_xlfn.SUMIFS(Campagne!$F$1:$F$141,Campagne!$C$1:$C$141,$A2)) -> 1976 | R2: =IF($A2="","",_xlfn.SUMIFS(Campagne!$K$1:$K$141,Campagne!$C$1:$C$141,$A2)) -> 0.46359595 | S2: =IF($A2="","",_xlfn.SUMIFS(Campagne!$M$1:$M$141,Campagne!$C$1:$C$141,$A2)) -> 0.30805412 | T2: =IF($A2="","",_xlfn.SUMIFS(Pilotage!$K$19:$K$32,Pilotage!$A$19:$A$32,$A2)*_xlfn.SUMIFS(Pilotage!$J$19:$J$32,Pilotage!$A$19:$A$32,$A2)*(SUM(Pilotage!$K$19:$K$32)/SUMPRODUCT(Pilotage!$K$19:$K$32,Pilotage!$J$19:$J$32))) -> 68291 | U2: =IF($A2="","",_xlfn.SUMIFS(Pilotage!$K$19:$K$32,Pilotage!$A$19:$A$32,$A2)) -> 68291 | V2: =IF($A2="","",IF($B2="V01",Cadrage!$C$23,IF($B2="V02",Cadrage!$D$23,Cadrage!$E$23))) -> 0.08 | W2: =IF($A2="","",IF($B2="V01",Cadrage!$C$24,IF($B2="V02",Cadrage!$D$24,Cadrage!$E$24))) -> 0.1 | X2: =IF($A2="","",IF($B2="V01",Cadrage!$C$25,IF($B2="V02",Cadrage!$D$25,Cadrage!$E$25))) -> 0.0029 | Y2: =IF($A2="","",IF($B2="V01",Cadrage!$C$26,IF($B2="V02",Cadrage!$D$26,Cadrage!$E$26))) -> 0.01 | Z2: =IF($A2="","",IF($B2="V01",Cadrage!$C$27,IF($B2="V02",Cadrage!$D$27,Cadrage!$E$27))) -> 0.01 | AA2: =IF($A2="","",IF($B2="V01",Cadrage!$C$28,IF($B2="V02",Cadrage!$D$28,Cadrage!$E$28))) -> 0.005 | AB2: =IF($A2="","",IF($B2="V01",Cadrage!$C$42,IF($B2="V02",Cadrage!$D$42,Cadrage!$E$42))) -> 90 | AC2: =IF($A2="","",IF($F2="MBWAY",Cadrage!$K$34,IF($F2="ISCOM",Cadrage!$K$35,IF($F2="IPAC",Cadrage!$K$36,IF($F2="PIGIER",Cadrage!$K$37,Cadrage!$K$38))))) -> 1.2 | AD2: =IF($A2="","",($O2*(1+$W2)^$S2+$P2*_xlfn.IFERROR((($T2/$U2)*(1+$V2))^$R2,0))*_xlfn.IFERROR($G2/$Q2,0)*($J2+$Y2)*$K2*($L2+$Z2)) -> 84.920594 | AE2: =IF($A2="","",IF($N2=1,$AD2,0)) -> 84.920594 | AF2: =IF($A2="","",IF($N2=1,$AD2,$H2*($M2+$AA2))) -> 84.920594 | AG2: =IF($A2="","",$I2*(1+$X2*$AC2)) -> 8429.232 | AH2: =IF($A2="","",$AF2*$AG2+$AE2*$AB2) -> 723458.24
A3: =IF(Moteur!D3="","",Moteur!D3) -> MBWAY_PAR | B3: =IF(Moteur!B3="","",Moteur!B3) -> V01 | C3: =IF(Moteur!F3="","",Moteur!F3) -> BAC_MGT | D3: =IF(Moteur!G3="","",Moteur!G3) -> B2 | E3: =IF(Moteur!H3="","",Moteur!H3) -> ALT | F3: =IF(Moteur!E3="","",Moteur!E3) -> MBWAY | G3: =IF($A3="","",_xlfn.SUMIFS(Socle!$H$1:$H$658,Socle!$C$1:$C$658,$A3,Socle!$D$1:$D$658,$C3,Socle!$E$1:$E$658,$D3,Socle!$F$1:$F$658,$E3,Socle!$G$1:$G$658,"2026")) -> 0 | H3: =IF($A3="","",_xlfn.SUMIFS(Socle!$N$1:$N$658,Socle!$C$1:$C$658,$A3,Socle!$D$1:$D$658,$C3,Socle!$E$1:$E$658,$D3,Socle!$F$1:$F$658,$E3,Socle!$G$1:$G$658,"2026")) -> 78 | I3: =IF($A3="","",_xlfn.SUMIFS(Socle!$P$1:$P$658,Socle!$C$1:$C$658,$A3,Socle!$D$1:$D$658,$C3,Socle!$E$1:$E$658,$D3,Socle!$F$1:$F$658,$E3,Socle!$G$1:$G$658,"2026")) -> 7840 | J3: =IF($A3="","",_xlfn.SUMIFS(Socle!$W$1:$W$658,Socle!$C$1:$C$658,$A3,Socle!$D$1:$D$658,$C3,Socle!$E$1:$E$658,$D3,Socle!$F$1:$F$658,$E3,Socle!$G$1:$G$658,"2026")) -> 0 | K3: =IF($A3="","",_xlfn.SUMIFS(Socle!$X$1:$X$658,Socle!$C$1:$C$658,$A3,Socle!$D$1:$D$658,$C3,Socle!$E$1:$E$658,$D3,Socle!$F$1:$F$658,$E3,Socle!$G$1:$G$658,"2026")) -> 0 | L3: =IF($A3="","",_xlfn.SUMIFS(Socle!$Y$1:$Y$658,Socle!$C$1:$C$658,$A3,Socle!$D$1:$D$658,$C3,Socle!$E$1:$E$658,$D3,Socle!$F$1:$F$658,$E3,Socle!$G$1:$G$658,"2026")) -> 0 | M3: =IF($A3="","",_xlfn.SUMIFS(Socle!$V$1:$V$658,Socle!$C$1:$C$658,$A3,Socle!$D$1:$D$658,$C3,Socle!$E$1:$E$658,$D3,Socle!$F$1:$F$658,$E3,Socle!$G$1:$G$658,"2026")) -> 0.97435897 | N3: =IF($A3="","",IF(OR($D3="B1",$D3="M1",$D3="BTS1"),1,0)) -> 0 | O3: =IF($A3="","",_xlfn.SUMIFS(Campagne!$D$1:$D$141,Campagne!$C$1:$C$141,$A3)) -> 711 | P3: =IF($A3="","",_xlfn.SUMIFS(Campagne!$E$1:$E$141,Campagne!$C$1:$C$141,$A3)) -> 1265 | Q3: =IF($A3="","",_xlfn.SUMIFS(Campagne!$F$1:$F$141,Campagne!$C$1:$C$141,$A3)) -> 1976 | R3: =IF($A3="","",_xlfn.SUMIFS(Campagne!$K$1:$K$141,Campagne!$C$1:$C$141,$A3)) -> 0.46359595 | S3: =IF($A3="","",_xlfn.SUMIFS(Campagne!$M$1:$M$141,Campagne!$C$1:$C$141,$A3)) -> 0.30805412 | T3: =IF($A3="","",_xlfn.SUMIFS(Pilotage!$K$19:$K$32,Pilotage!$A$19:$A$32,$A3)*_xlfn.SUMIFS(Pilotage!$J$19:$J$32,Pilotage!$A$19:$A$32,$A3)*(SUM(Pilotage!$K$19:$K$32)/SUMPRODUCT(Pilotage!$K$19:$K$32,Pilotage!$J$19:$J$32))) -> 68291 | U3: =IF($A3="","",_xlfn.SUMIFS(Pilotage!$K$19:$K$32,Pilotage!$A$19:$A$32,$A3)) -> 68291 | V3: =IF($A3="","",IF($B3="V01",Cadrage!$C$23,IF($B3="V02",Cadrage!$D$23,Cadrage!$E$23))) -> 0.08 | W3: =IF($A3="","",IF($B3="V01",Cadrage!$C$24,IF($B3="V02",Cadrage!$D$24,Cadrage!$E$24))) -> 0.1 | X3: =IF($A3="","",IF($B3="V01",Cadrage!$C$25,IF($B3="V02",Cadrage!$D$25,Cadrage!$E$25))) -> 0.0029 | Y3: =IF($A3="","",IF($B3="V01",Cadrage!$C$26,IF($B3="V02",Cadrage!$D$26,Cadrage!$E$26))) -> 0.01 | Z3: =IF($A3="","",IF($B3="V01",Cadrage!$C$27,IF($B3="V02",Cadrage!$D$27,Cadrage!$E$27))) -> 0.01 | AA3: =IF($A3="","",IF($B3="V01",Cadrage!$C$28,IF($B3="V02",Cadrage!$D$28,Cadrage!$E$28))) -> 0.005 | AB3: =IF($A3="","",IF($B3="V01",Cadrage!$C$42,IF($B3="V02",Cadrage!$D$42,Cadrage!$E$42))) -> 90 | AC3: =IF($A3="","",IF($F3="MBWAY",Cadrage!$K$34,IF($F3="ISCOM",Cadrage!$K$35,IF($F3="IPAC",Cadrage!$K$36,IF($F3="PIGIER",Cadrage!$K$37,Cadrage!$K$38))))) -> 1.2 | AD3: =IF($A3="","",($O3*(1+$W3)^$S3+$P3*_xlfn.IFERROR((($T3/$U3)*(1+$V3))^$R3,0))*_xlfn.IFERROR($G3/$Q3,0)*($J3+$Y3)*$K3*($L3+$Z3)) -> 0 | AE3: =IF($A3="","",IF($N3=1,$AD3,0)) -> 0 | AF3: =IF($A3="","",IF($N3=1,$AD3,$H3*($M3+$AA3))) -> 76.39 | AG3: =IF($A3="","",$I3*(1+$X3*$AC3)) -> 7867.2832 | AH3: =IF($A3="","",$AF3*$AG3+$AE3*$AB3) -> 600981.76
A4: =IF(Moteur!D4="","",Moteur!D4) -> MBWAY_PAR | B4: =IF(Moteur!B4="","",Moteur!B4) -> V01 | C4: =IF(Moteur!F4="","",Moteur!F4) -> BAC_MGT | D4: =IF(Moteur!G4="","",Moteur!G4) -> B3 | E4: =IF(Moteur!H4="","",Moteur!H4) -> ALT | F4: =IF(Moteur!E4="","",Moteur!E4) -> MBWAY | G4: =IF($A4="","",_xlfn.SUMIFS(Socle!$H$1:$H$658,Socle!$C$1:$C$658,$A4,Socle!$D$1:$D$658,$C4,Socle!$E$1:$E$658,$D4,Socle!$F$1:$F$658,$E4,Socle!$G$1:$G$658,"2026")) -> 0 | H4: =IF($A4="","",_xlfn.SUMIFS(Socle!$N$1:$N$658,Socle!$C$1:$C$658,$A4,Socle!$D$1:$D$658,$C4,Socle!$E$1:$E$658,$D4,Socle!$F$1:$F$658,$E4,Socle!$G$1:$G$658,"2026")) -> 76 | I4: =IF($A4="","",_xlfn.SUMIFS(Socle!$P$1:$P$658,Socle!$C$1:$C$658,$A4,Socle!$D$1:$D$658,$C4,Socle!$E$1:$E$658,$D4,Socle!$F$1:$F$658,$E4,Socle!$G$1:$G$658,"2026")) -> 7840 | J4: =IF($A4="","",_xlfn.SUMIFS(Socle!$W$1:$W$658,Socle!$C$1:$C$658,$A4,Socle!$D$1:$D$658,$C4,Socle!$E$1:$E$658,$D4,Socle!$F$1:$F$658,$E4,Socle!$G$1:$G$658,"2026")) -> 0 | K4: =IF($A4="","",_xlfn.SUMIFS(Socle!$X$1:$X$658,Socle!$C$1:$C$658,$A4,Socle!$D$1:$D$658,$C4,Socle!$E$1:$E$658,$D4,Socle!$F$1:$F$658,$E4,Socle!$G$1:$G$658,"2026")) -> 0 | L4: =IF($A4="","",_xlfn.SUMIFS(Socle!$Y$1:$Y$658,Socle!$C$1:$C$658,$A4,Socle!$D$1:$D$658,$C4,Socle!$E$1:$E$658,$D4,Socle!$F$1:$F$658,$E4,Socle!$G$1:$G$658,"2026")) -> 0 | M4: =IF($A4="","",_xlfn.SUMIFS(Socle!$V$1:$V$658,Socle!$C$1:$C$658,$A4,Socle!$D$1:$D$658,$C4,Socle!$E$1:$E$658,$D4,Socle!$F$1:$F$658,$E4,Socle!$G$1:$G$658,"2026")) -> 0.97368421 | N4: =IF($A4="","",IF(OR($D4="B1",$D4="M1",$D4="BTS1"),1,0)) -> 0 | O4: =IF($A4="","",_xlfn.SUMIFS(Campagne!$D$1:$D$141,Campagne!$C$1:$C$141,$A4)) -> 711 | P4: =IF($A4="","",_xlfn.SUMIFS(Campagne!$E$1:$E$141,Campagne!$C$1:$C$141,$A4)) -> 1265 | Q4: =IF($A4="","",_xlfn.SUMIFS(Campagne!$F$1:$F$141,Campagne!$C$1:$C$141,$A4)) -> 1976 | R4: =IF($A4="","",_xlfn.SUMIFS(Campagne!$K$1:$K$141,Campagne!$C$1:$C$141,$A4)) -> 0.46359595 | S4: =IF($A4="","",_xlfn.SUMIFS(Campagne!$M$1:$M$141,Campagne!$C$1:$C$141,$A4)) -> 0.30805412 | T4: =IF($A4="","",_xlfn.SUMIFS(Pilotage!$K$19:$K$32,Pilotage!$A$19:$A$32,$A4)*_xlfn.SUMIFS(Pilotage!$J$19:$J$32,Pilotage!$A$19:$A$32,$A4)*(SUM(Pilotage!$K$19:$K$32)/SUMPRODUCT(Pilotage!$K$19:$K$32,Pilotage!$J$19:$J$32))) -> 68291 | U4: =IF($A4="","",_xlfn.SUMIFS(Pilotage!$K$19:$K$32,Pilotage!$A$19:$A$32,$A4)) -> 68291 | V4: =IF($A4="","",IF($B4="V01",Cadrage!$C$23,IF($B4="V02",Cadrage!$D$23,Cadrage!$E$23))) -> 0.08 | W4: =IF($A4="","",IF($B4="V01",Cadrage!$C$24,IF($B4="V02",Cadrage!$D$24,Cadrage!$E$24))) -> 0.1 | X4: =IF($A4="","",IF($B4="V01",Cadrage!$C$25,IF($B4="V02",Cadrage!$D$25,Cadrage!$E$25))) -> 0.0029 | Y4: =IF($A4="","",IF($B4="V01",Cadrage!$C$26,IF($B4="V02",Cadrage!$D$26,Cadrage!$E$26))) -> 0.01 | Z4: =IF($A4="","",IF($B4="V01",Cadrage!$C$27,IF($B4="V02",Cadrage!$D$27,Cadrage!$E$27))) -> 0.01 | AA4: =IF($A4="","",IF($B4="V01",Cadrage!$C$28,IF($B4="V02",Cadrage!$D$28,Cadrage!$E$28))) -> 0.005 | AB4: =IF($A4="","",IF($B4="V01",Cadrage!$C$42,IF($B4="V02",Cadrage!$D$42,Cadrage!$E$42))) -> 90 | AC4: =IF($A4="","",IF($F4="MBWAY",Cadrage!$K$34,IF($F4="ISCOM",Cadrage!$K$35,IF($F4="IPAC",Cadrage!$K$36,IF($F4="PIGIER",Cadrage!$K$37,Cadrage!$K$38))))) -> 1.2 | AD4: =IF($A4="","",($O4*(1+$W4)^$S4+$P4*_xlfn.IFERROR((($T4/$U4)*(1+$V4))^$R4,0))*_xlfn.IFERROR($G4/$Q4,0)*($J4+$Y4)*$K4*($L4+$Z4)) -> 0 | AE4: =IF($A4="","",IF($N4=1,$AD4,0)) -> 0 | AF4: =IF($A4="","",IF($N4=1,$AD4,$H4*($M4+$AA4))) -> 74.38 | AG4: =IF($A4="","",$I4*(1+$X4*$AC4)) -> 7867.2832 | AH4: =IF($A4="","",$AF4*$AG4+$AE4*$AB4) -> 585168.52
A5: =IF(Moteur!D5="","",Moteur!D5) -> MBWAY_PAR | B5: =IF(Moteur!B5="","",Moteur!B5) -> V01 | C5: =IF(Moteur!F5="","",Moteur!F5) -> MAS_MGT | D5: =IF(Moteur!G5="","",Moteur!G5) -> M1 | E5: =IF(Moteur!H5="","",Moteur!H5) -> ALT | F5: =IF(Moteur!E5="","",Moteur!E5) -> MBWAY | G5: =IF($A5="","",_xlfn.SUMIFS(Socle!$H$1:$H$658,Socle!$C$1:$C$658,$A5,Socle!$D$1:$D$658,$C5,Socle!$E$1:$E$658,$D5,Socle!$F$1:$F$658,$E5,Socle!$G$1:$G$658,"2026")) -> 1330 | H5: =IF($A5="","",_xlfn.SUMIFS(Socle!$N$1:$N$658,Socle!$C$1:$C$658,$A5,Socle!$D$1:$D$658,$C5,Socle!$E$1:$E$658,$D5,Socle!$F$1:$F$658,$E5,Socle!$G$1:$G$658,"2026")) -> 0 | I5: =IF($A5="","",_xlfn.SUMIFS(Socle!$P$1:$P$658,Socle!$C$1:$C$658,$A5,Socle!$D$1:$D$658,$C5,Socle!$E$1:$E$658,$D5,Socle!$F$1:$F$658,$E5,Socle!$G$1:$G$658,"2026")) -> 8400 | J5: =IF($A5="","",_xlfn.SUMIFS(Socle!$W$1:$W$658,Socle!$C$1:$C$658,$A5,Socle!$D$1:$D$658,$C5,Socle!$E$1:$E$658,$D5,Socle!$F$1:$F$658,$E5,Socle!$G$1:$G$658,"2026")) -> 0.2 | K5: =IF($A5="","",_xlfn.SUMIFS(Socle!$X$1:$X$658,Socle!$C$1:$C$658,$A5,Socle!$D$1:$D$658,$C5,Socle!$E$1:$E$658,$D5,Socle!$F$1:$F$658,$E5,Socle!$G$1:$G$658,"2026")) -> 0.69924812 | L5: =IF($A5="","",_xlfn.SUMIFS(Socle!$Y$1:$Y$658,Socle!$C$1:$C$658,$A5,Socle!$D$1:$D$658,$C5,Socle!$E$1:$E$658,$D5,Socle!$F$1:$F$658,$E5,Socle!$G$1:$G$658,"2026")) -> 0.41935484 | M5: =IF($A5="","",_xlfn.SUMIFS(Socle!$V$1:$V$658,Socle!$C$1:$C$658,$A5,Socle!$D$1:$D$658,$C5,Socle!$E$1:$E$658,$D5,Socle!$F$1:$F$658,$E5,Socle!$G$1:$G$658,"2026")) -> 0 | N5: =IF($A5="","",IF(OR($D5="B1",$D5="M1",$D5="BTS1"),1,0)) -> 1 | O5: =IF($A5="","",_xlfn.SUMIFS(Campagne!$D$1:$D$141,Campagne!$C$1:$C$141,$A5)) -> 711 | P5: =IF($A5="","",_xlfn.SUMIFS(Campagne!$E$1:$E$141,Campagne!$C$1:$C$141,$A5)) -> 1265 | Q5: =IF($A5="","",_xlfn.SUMIFS(Campagne!$F$1:$F$141,Campagne!$C$1:$C$141,$A5)) -> 1976 | R5: =IF($A5="","",_xlfn.SUMIFS(Campagne!$K$1:$K$141,Campagne!$C$1:$C$141,$A5)) -> 0.46359595 | S5: =IF($A5="","",_xlfn.SUMIFS(Campagne!$M$1:$M$141,Campagne!$C$1:$C$141,$A5)) -> 0.30805412 | T5: =IF($A5="","",_xlfn.SUMIFS(Pilotage!$K$19:$K$32,Pilotage!$A$19:$A$32,$A5)*_xlfn.SUMIFS(Pilotage!$J$19:$J$32,Pilotage!$A$19:$A$32,$A5)*(SUM(Pilotage!$K$19:$K$32)/SUMPRODUCT(Pilotage!$K$19:$K$32,Pilotage!$J$19:$J$32))) -> 68291 | U5: =IF($A5="","",_xlfn.SUMIFS(Pilotage!$K$19:$K$32,Pilotage!$A$19:$A$32,$A5)) -> 68291 | V5: =IF($A5="","",IF($B5="V01",Cadrage!$C$23,IF($B5="V02",Cadrage!$D$23,Cadrage!$E$23))) -> 0.08 | W5: =IF($A5="","",IF($B5="V01",Cadrage!$C$24,IF($B5="V02",Cadrage!$D$24,Cadrage!$E$24))) -> 0.1 | X5: =IF($A5="","",IF($B5="V01",Cadrage!$C$25,IF($B5="V02",Cadrage!$D$25,Cadrage!$E$25))) -> 0.0029 | Y5: =IF($A5="","",IF($B5="V01",Cadrage!$C$26,IF($B5="V02",Cadrage!$D$26,Cadrage!$E$26))) -> 0.01 | Z5: =IF($A5="","",IF($B5="V01",Cadrage!$C$27,IF($B5="V02",Cadrage!$D$27,Cadrage!$E$27))) -> 0.01 | AA5: =IF($A5="","",IF($B5="V01",Cadrage!$C$28,IF($B5="V02",Cadrage!$D$28,Cadrage!$E$28))) -> 0.005 | AB5: =IF($A5="","",IF($B5="V01",Cadrage!$C$42,IF($B5="V02",Cadrage!$D$42,Cadrage!$E$42))) -> 90 | AC5: =IF($A5="","",IF($F5="MBWAY",Cadrage!$K$34,IF($F5="ISCOM",Cadrage!$K$35,IF($F5="IPAC",Cadrage!$K$36,IF($F5="PIGIER",Cadrage!$K$37,Cadrage!$K$38))))) -> 1.2 | AD5: =IF($A5="","",($O5*(1+$W5)^$S5+$P5*_xlfn.IFERROR((($T5/$U5)*(1+$V5))^$R5,0))*_xlfn.IFERROR($G5/$Q5,0)*($J5+$Y5)*$K5*($L5+$Z5)) -> 86.701858 | AE5: =IF($A5="","",IF($N5=1,$AD5,0)) -> 86.701858 | AF5: =IF($A5="","",IF($N5=1,$AD5,$H5*($M5+$AA5))) -> 86.701858 | AG5: =IF($A5="","",$I5*(1+$X5*$AC5)) -> 8429.232 | AH5: =IF($A5="","",$AF5*$AG5+$AE5*$AB5) -> 738633.24
A6: =IF(Moteur!D6="","",Moteur!D6) -> MBWAY_PAR | B6: =IF(Moteur!B6="","",Moteur!B6) -> V01 | C6: =IF(Moteur!F6="","",Moteur!F6) -> MAS_MGT | D6: =IF(Moteur!G6="","",Moteur!G6) -> M2 | E6: =IF(Moteur!H6="","",Moteur!H6) -> ALT | F6: =IF(Moteur!E6="","",Moteur!E6) -> MBWAY | G6: =IF($A6="","",_xlfn.SUMIFS(Socle!$H$1:$H$658,Socle!$C$1:$C$658,$A6,Socle!$D$1:$D$658,$C6,Socle!$E$1:$E$658,$D6,Socle!$F$1:$F$658,$E6,Socle!$G$1:$G$658,"2026")) -> 0 | H6: =IF($A6="","",_xlfn.SUMIFS(Socle!$N$1:$N$658,Socle!$C$1:$C$658,$A6,Socle!$D$1:$D$658,$C6,Socle!$E$1:$E$658,$D6,Socle!$F$1:$F$658,$E6,Socle!$G$1:$G$658,"2026")) -> 78 | I6: =IF($A6="","",_xlfn.SUMIFS(Socle!$P$1:$P$658,Socle!$C$1:$C$658,$A6,Socle!$D$1:$D$658,$C6,Socle!$E$1:$E$658,$D6,Socle!$F$1:$F$658,$E6,Socle!$G$1:$G$658,"2026")) -> 8400 | J6: =IF($A6="","",_xlfn.SUMIFS(Socle!$W$1:$W$658,Socle!$C$1:$C$658,$A6,Socle!$D$1:$D$658,$C6,Socle!$E$1:$E$658,$D6,Socle!$F$1:$F$658,$E6,Socle!$G$1:$G$658,"2026")) -> 0 | K6: =IF($A6="","",_xlfn.SUMIFS(Socle!$X$1:$X$658,Socle!$C$1:$C$658,$A6,Socle!$D$1:$D$658,$C6,Socle!$E$1:$E$658,$D6,Socle!$F$1:$F$658,$E6,Socle!$G$1:$G$658,"2026")) -> 0 | L6: =IF($A6="","",_xlfn.SUMIFS(Socle!$Y$1:$Y$658,Socle!$C$1:$C$658,$A6,Socle!$D$1:$D$658,$C6,Socle!$E$1:$E$658,$D6,Socle!$F$1:$F$658,$E6,Socle!$G$1:$G$658,"2026")) -> 0 | M6: =IF($A6="","",_xlfn.SUMIFS(Socle!$V$1:$V$658,Socle!$C$1:$C$658,$A6,Socle!$D$1:$D$658,$C6,Socle!$E$1:$E$658,$D6,Socle!$F$1:$F$658,$E6,Socle!$G$1:$G$658,"2026")) -> 0.97435897 | N6: =IF($A6="","",IF(OR($D6="B1",$D6="M1",$D6="BTS1"),1,0)) -> 0 | O6: =IF($A6="","",_xlfn.SUMIFS(Campagne!$D$1:$D$141,Campagne!$C$1:$C$141,$A6)) -> 711 | P6: =IF($A6="","",_xlfn.SUMIFS(Campagne!$E$1:$E$141,Campagne!$C$1:$C$141,$A6)) -> 1265 | Q6: =IF($A6="","",_xlfn.SUMIFS(Campagne!$F$1:$F$141,Campagne!$C$1:$C$141,$A6)) -> 1976 | R6: =IF($A6="","",_xlfn.SUMIFS(Campagne!$K$1:$K$141,Campagne!$C$1:$C$141,$A6)) -> 0.46359595 | S6: =IF($A6="","",_xlfn.SUMIFS(Campagne!$M$1:$M$141,Campagne!$C$1:$C$141,$A6)) -> 0.30805412 | T6: =IF($A6="","",_xlfn.SUMIFS(Pilotage!$K$19:$K$32,Pilotage!$A$19:$A$32,$A6)*_xlfn.SUMIFS(Pilotage!$J$19:$J$32,Pilotage!$A$19:$A$32,$A6)*(SUM(Pilotage!$K$19:$K$32)/SUMPRODUCT(Pilotage!$K$19:$K$32,Pilotage!$J$19:$J$32))) -> 68291 | U6: =IF($A6="","",_xlfn.SUMIFS(Pilotage!$K$19:$K$32,Pilotage!$A$19:$A$32,$A6)) -> 68291 | V6: =IF($A6="","",IF($B6="V01",Cadrage!$C$23,IF($B6="V02",Cadrage!$D$23,Cadrage!$E$23))) -> 0.08 | W6: =IF($A6="","",IF($B6="V01",Cadrage!$C$24,IF($B6="V02",Cadrage!$D$24,Cadrage!$E$24))) -> 0.1 | X6: =IF($A6="","",IF($B6="V01",Cadrage!$C$25,IF($B6="V02",Cadrage!$D$25,Cadrage!$E$25))) -> 0.0029 | Y6: =IF($A6="","",IF($B6="V01",Cadrage!$C$26,IF($B6="V02",Cadrage!$D$26,Cadrage!$E$26))) -> 0.01 | Z6: =IF($A6="","",IF($B6="V01",Cadrage!$C$27,IF($B6="V02",Cadrage!$D$27,Cadrage!$E$27))) -> 0.01 | AA6: =IF($A6="","",IF($B6="V01",Cadrage!$C$28,IF($B6="V02",Cadrage!$D$28,Cadrage!$E$28))) -> 0.005 | AB6: =IF($A6="","",IF($B6="V01",Cadrage!$C$42,IF($B6="V02",Cadrage!$D$42,Cadrage!$E$42))) -> 90 | AC6: =IF($A6="","",IF($F6="MBWAY",Cadrage!$K$34,IF($F6="ISCOM",Cadrage!$K$35,IF($F6="IPAC",Cadrage!$K$36,IF($F6="PIGIER",Cadrage!$K$37,Cadrage!$K$38))))) -> 1.2 | AD6: =IF($A6="","",($O6*(1+$W6)^$S6+$P6*_xlfn.IFERROR((($T6/$U6)*(1+$V6))^$R6,0))*_xlfn.IFERROR($G6/$Q6,0)*($J6+$Y6)*$K6*($L6+$Z6)) -> 0 | AE6: =IF($A6="","",IF($N6=1,$AD6,0)) -> 0 | AF6: =IF($A6="","",IF($N6=1,$AD6,$H6*($M6+$AA6))) -> 76.39 | AG6: =IF($A6="","",$I6*(1+$X6*$AC6)) -> 8429.232 | AH6: =IF($A6="","",$AF6*$AG6+$AE6*$AB6) -> 643909.03
A7: =IF(Moteur!D7="","",Moteur!D7) -> MBWAY_LYO | B7: =IF(Moteur!B7="","",Moteur!B7) -> V01 | C7: =IF(Moteur!F7="","",Moteur!F7) -> BAC_MGT | D7: =IF(Moteur!G7="","",Moteur!G7) -> B1 | E7: =IF(Moteur!H7="","",Moteur!H7) -> INIT | F7: =IF(Moteur!E7="","",Moteur!E7) -> MBWAY | G7: =IF($A7="","",_xlfn.SUMIFS(Socle!$H$1:$H$658,Socle!$C$1:$C$658,$A7,Socle!$D$1:$D$658,$C7,Socle!$E$1:$E$658,$D7,Socle!$F$1:$F$658,$E7,Socle!$G$1:$G$658,"2026")) -> 546 | H7: =IF($A7="","",_xlfn.SUMIFS(Socle!$N$1:$N$658,Socle!$C$1:$C$658,$A7,Socle!$D$1:$D$658,$C7,Socle!$E$1:$E$658,$D7,Socle!$F$1:$F$658,$E7,Socle!$G$1:$G$658,"2026")) -> 0 | I7: =IF($A7="","",_xlfn.SUMIFS(Socle!$P$1:$P$658,Socle!$C$1:$C$658,$A7,Socle!$D$1:$D$658,$C7,Socle!$E$1:$E$658,$D7,Socle!$F$1:$F$658,$E7,Socle!$G$1:$G$658,"2026")) -> 7875 | J7: =IF($A7="","",_xlfn.SUMIFS(Socle!$W$1:$W$658,Socle!$C$1:$C$658,$A7,Socle!$D$1:$D$658,$C7,Socle!$E$1:$E$658,$D7,Socle!$F$1:$F$658,$E7,Socle!$G$1:$G$658,"2026")) -> 0.28021978 | K7: =IF($A7="","",_xlfn.SUMIFS(Socle!$X$1:$X$658,Socle!$C$1:$C$658,$A7,Socle!$D$1:$D$658,$C7,Socle!$E$1:$E$658,$D7,Socle!$F$1:$F$658,$E7,Socle!$G$1:$G$658,"2026")) -> 0.71895425 | L7: =IF($A7="","",_xlfn.SUMIFS(Socle!$Y$1:$Y$658,Socle!$C$1:$C$658,$A7,Socle!$D$1:$D$658,$C7,Socle!$E$1:$E$658,$D7,Socle!$F$1:$F$658,$E7,Socle!$G$1:$G$658,"2026")) -> 0.6 | M7: =IF($A7="","",_xlfn.SUMIFS(Socle!$V$1:$V$658,Socle!$C$1:$C$658,$A7,Socle!$D$1:$D$658,$C7,Socle!$E$1:$E$658,$D7,Socle!$F$1:$F$658,$E7,Socle!$G$1:$G$658,"2026")) -> 0 | N7: =IF($A7="","",IF(OR($D7="B1",$D7="M1",$D7="BTS1"),1,0)) -> 1 | O7: =IF($A7="","",_xlfn.SUMIFS(Campagne!$D$1:$D$141,Campagne!$C$1:$C$141,$A7)) -> 716 | P7: =IF($A7="","",_xlfn.SUMIFS(Campagne!$E$1:$E$141,Campagne!$C$1:$C$141,$A7)) -> 950 | Q7: =IF($A7="","",_xlfn.SUMIFS(Campagne!$F$1:$F$141,Campagne!$C$1:$C$141,$A7)) -> 1666 | R7: =IF($A7="","",_xlfn.SUMIFS(Campagne!$K$1:$K$141,Campagne!$C$1:$C$141,$A7)) -> 0.50391241 | S7: =IF($A7="","",_xlfn.SUMIFS(Campagne!$M$1:$M$141,Campagne!$C$1:$C$141,$A7)) -> 0.32659376 | T7: =IF($A7="","",_xlfn.SUMIFS(Pilotage!$K$19:$K$32,Pilotage!$A$19:$A$32,$A7)*_xlfn.SUMIFS(Pilotage!$J$19:$J$32,Pilotage!$A$19:$A$32,$A7)*(SUM(Pilotage!$K$19:$K$32)/SUMPRODUCT(Pilotage!$K$19:$K$32,Pilotage!$J$19:$J$32))) -> 41783 | U7: =IF($A7="","",_xlfn.SUMIFS(Pilotage!$K$19:$K$32,Pilotage!$A$19:$A$32,$A7)) -> 41783 | V7: =IF($A7="","",IF($B7="V01",Cadrage!$C$23,IF($B7="V02",Cadrage!$D$23,Cadrage!$E$23))) -> 0.08 | W7: =IF($A7="","",IF($B7="V01",Cadrage!$C$24,IF($B7="V02",Cadrage!$D$24,Cadrage!$E$24))) -> 0.1 | X7: =IF($A7="","",IF($B7="V01",Cadrage!$C$25,IF($B7="V02",Cadrage!$D$25,Cadrage!$E$25))) -> 0.0029 | Y7: =IF($A7="","",IF($B7="V01",Cadrage!$C$26,IF($B7="V02",Cadrage!$D$26,Cadrage!$E$26))) -> 0.01 | Z7: =IF($A7="","",IF($B7="V01",Cadrage!$C$27,IF($B7="V02",Cadrage!$D$27,Cadrage!$E$27))) -> 0.01 | AA7: =IF($A7="","",IF($B7="V01",Cadrage!$C$28,IF($B7="V02",Cadrage!$D$28,Cadrage!$E$28))) -> 0.005 | AB7: =IF($A7="","",IF($B7="V01",Cadrage!$C$42,IF($B7="V02",Cadrage!$D$42,Cadrage!$E$42))) -> 90 | AC7: =IF($A7="","",IF($F7="MBWAY",Cadrage!$K$34,IF($F7="ISCOM",Cadrage!$K$35,IF($F7="IPAC",Cadrage!$K$36,IF($F7="PIGIER",Cadrage!$K$37,Cadrage!$K$38))))) -> 1.2 | AD7: =IF($A7="","",($O7*(1+$W7)^$S7+$P7*_xlfn.IFERROR((($T7/$U7)*(1+$V7))^$R7,0))*_xlfn.IFERROR($G7/$Q7,0)*($J7+$Y7)*$K7*($L7+$Z7)) -> 72.005873 | AE7: =IF($A7="","",IF($N7=1,$AD7,0)) -> 72.005873 | AF7: =IF($A7="","",IF($N7=1,$AD7,$H7*($M7+$AA7))) -> 72.005873 | AG7: =IF($A7="","",$I7*(1+$X7*$AC7)) -> 7902.405 | AH7: =IF($A7="","",$AF7*$AG7+$AE7*$AB7) -> 575500.1
A8: =IF(Moteur!D8="","",Moteur!D8) -> MBWAY_LYO | B8: =IF(Moteur!B8="","",Moteur!B8) -> V01 | C8: =IF(Moteur!F8="","",Moteur!F8) -> BAC_MGT | D8: =IF(Moteur!G8="","",Moteur!G8) -> B2 | E8: =IF(Moteur!H8="","",Moteur!H8) -> ALT | F8: =IF(Moteur!E8="","",Moteur!E8) -> MBWAY | G8: =IF($A8="","",_xlfn.SUMIFS(Socle!$H$1:$H$658,Socle!$C$1:$C$658,$A8,Socle!$D$1:$D$658,$C8,Socle!$E$1:$E$658,$D8,Socle!$F$1:$F$658,$E8,Socle!$G$1:$G$658,"2026")) -> 0 | H8: =IF($A8="","",_xlfn.SUMIFS(Socle!$N$1:$N$658,Socle!$C$1:$C$658,$A8,Socle!$D$1:$D$658,$C8,Socle!$E$1:$E$658,$D8,Socle!$F$1:$F$658,$E8,Socle!$G$1:$G$658,"2026")) -> 66 | I8: =IF($A8="","",_xlfn.SUMIFS(Socle!$P$1:$P$658,Socle!$C$1:$C$658,$A8,Socle!$D$1:$D$658,$C8,Socle!$E$1:$E$658,$D8,Socle!$F$1:$F$658,$E8,Socle!$G$1:$G$658,"2026")) -> 7350 | J8: =IF($A8="","",_xlfn.SUMIFS(Socle!$W$1:$W$658,Socle!$C$1:$C$658,$A8,Socle!$D$1:$D$658,$C8,Socle!$E$1:$E$658,$D8,Socle!$F$1:$F$658,$E8,Socle!$G$1:$G$658,"2026")) -> 0 | K8: =IF($A8="","",_xlfn.SUMIFS(Socle!$X$1:$X$658,Socle!$C$1:$C$658,$A8,Socle!$D$1:$D$658,$C8,Socle!$E$1:$E$658,$D8,Socle!$F$1:$F$658,$E8,Socle!$G$1:$G$658,"2026")) -> 0 | L8: =IF($A8="","",_xlfn.SUMIFS(Socle!$Y$1:$Y$658,Socle!$C$1:$C$658,$A8,Socle!$D$1:$D$658,$C8,Socle!$E$1:$E$658,$D8,Socle!$F$1:$F$658,$E8,Socle!$G$1:$G$658,"2026")) -> 0 | M8: =IF($A8="","",_xlfn.SUMIFS(Socle!$V$1:$V$658,Socle!$C$1:$C$658,$A8,Socle!$D$1:$D$658,$C8,Socle!$E$1:$E$658,$D8,Socle!$F$1:$F$658,$E8,Socle!$G$1:$G$658,"2026")) -> 0.96969697 | N8: =IF($A8="","",IF(OR($D8="B1",$D8="M1",$D8="BTS1"),1,0)) -> 0 | O8: =IF($A8="","",_xlfn.SUMIFS(Campagne!$D$1:$D$141,Campagne!$C$1:$C$141,$A8)) -> 716 | P8: =IF($A8="","",_xlfn.SUMIFS(Campagne!$E$1:$E$141,Campagne!$C$1:$C$141,$A8)) -> 950 | Q8: =IF($A8="","",_xlfn.SUMIFS(Campagne!$F$1:$F$141,Campagne!$C$1:$C$141,$A8)) -> 1666 | R8: =IF($A8="","",_xlfn.SUMIFS(Campagne!$K$1:$K$141,Campagne!$C$1:$C$141,$A8)) -> 0.50391241 | S8: =IF($A8="","",_xlfn.SUMIFS(Campagne!$M$1:$M$141,Campagne!$C$1:$C$141,$A8)) -> 0.32659376 | T8: =IF($A8="","",_xlfn.SUMIFS(Pilotage!$K$19:$K$32,Pilotage!$A$19:$A$32,$A8)*_xlfn.SUMIFS(Pilotage!$J$19:$J$32,Pilotage!$A$19:$A$32,$A8)*(SUM(Pilotage!$K$19:$K$32)/SUMPRODUCT(Pilotage!$K$19:$K$32,Pilotage!$J$19:$J$32))) -> 41783 | U8: =IF($A8="","",_xlfn.SUMIFS(Pilotage!$K$19:$K$32,Pilotage!$A$19:$A$32,$A8)) -> 41783 | V8: =IF($A8="","",IF($B8="V01",Cadrage!$C$23,IF($B8="V02",Cadrage!$D$23,Cadrage!$E$23))) -> 0.08 | W8: =IF($A8="","",IF($B8="V01",Cadrage!$C$24,IF($B8="V02",Cadrage!$D$24,Cadrage!$E$24))) -> 0.1 | X8: =IF($A8="","",IF($B8="V01",Cadrage!$C$25,IF($B8="V02",Cadrage!$D$25,Cadrage!$E$25))) -> 0.0029 | Y8: =IF($A8="","",IF($B8="V01",Cadrage!$C$26,IF($B8="V02",Cadrage!$D$26,Cadrage!$E$26))) -> 0.01 | Z8: =IF($A8="","",IF($B8="V01",Cadrage!$C$27,IF($B8="V02",Cadrage!$D$27,Cadrage!$E$27))) -> 0.01 | AA8: =IF($A8="","",IF($B8="V01",Cadrage!$C$28,IF($B8="V02",Cadrage!$D$28,Cadrage!$E$28))) -> 0.005 | AB8: =IF($A8="","",IF($B8="V01",Cadrage!$C$42,IF($B8="V02",Cadrage!$D$42,Cadrage!$E$42))) -> 90 | AC8: =IF($A8="","",IF($F8="MBWAY",Cadrage!$K$34,IF($F8="ISCOM",Cadrage!$K$35,IF($F8="IPAC",Cadrage!$K$36,IF($F8="PIGIER",Cadrage!$K$37,Cadrage!$K$38))))) -> 1.2 | AD8: =IF($A8="","",($O8*(1+$W8)^$S8+$P8*_xlfn.IFERROR((($T8/$U8)*(1+$V8))^$R8,0))*_xlfn.IFERROR($G8/$Q8,0)*($J8+$Y8)*$K8*($L8+$Z8)) -> 0 | AE8: =IF($A8="","",IF($N8=1,$AD8,0)) -> 0 | AF8: =IF($A8="","",IF($N8=1,$AD8,$H8*($M8+$AA8))) -> 64.33 | AG8: =IF($A8="","",$I8*(1+$X8*$AC8)) -> 7375.578 | AH8: =IF($A8="","",$AF8*$AG8+$AE8*$AB8) -> 474470.93
A9: =IF(Moteur!D9="","",Moteur!D9) -> MBWAY_LYO | B9: =IF(Moteur!B9="","",Moteur!B9) -> V01 | C9: =IF(Moteur!F9="","",Moteur!F9) -> BAC_MGT | D9: =IF(Moteur!G9="","",Moteur!G9) -> B3 | E9: =IF(Moteur!H9="","",Moteur!H9) -> ALT | F9: =IF(Moteur!E9="","",Moteur!E9) -> MBWAY | G9: =IF($A9="","",_xlfn.SUMIFS(Socle!$H$1:$H$658,Socle!$C$1:$C$658,$A9,Socle!$D$1:$D$658,$C9,Socle!$E$1:$E$658,$D9,Socle!$F$1:$F$658,$E9,Socle!$G$1:$G$658,"2026")) -> 0 | H9: =IF($A9="","",_xlfn.SUMIFS(Socle!$N$1:$N$658,Socle!$C$1:$C$658,$A9,Socle!$D$1:$D$658,$C9,Socle!$E$1:$E$658,$D9,Socle!$F$1:$F$658,$E9,Socle!$G$1:$G$658,"2026")) -> 64 | I9: =IF($A9="","",_xlfn.SUMIFS(Socle!$P$1:$P$658,Socle!$C$1:$C$658,$A9,Socle!$D$1:$D$658,$C9,Socle!$E$1:$E$658,$D9,Socle!$F$1:$F$658,$E9,Socle!$G$1:$G$658,"2026")) -> 7350 | J9: =IF($A9="","",_xlfn.SUMIFS(Socle!$W$1:$W$658,Socle!$C$1:$C$658,$A9,Socle!$D$1:$D$658,$C9,Socle!$E$1:$E$658,$D9,Socle!$F$1:$F$658,$E9,Socle!$G$1:$G$658,"2026")) -> 0 | K9: =IF($A9="","",_xlfn.SUMIFS(Socle!$X$1:$X$658,Socle!$C$1:$C$658,$A9,Socle!$D$1:$D$658,$C9,Socle!$E$1:$E$658,$D9,Socle!$F$1:$F$658,$E9,Socle!$G$1:$G$658,"2026")) -> 0 | L9: =IF($A9="","",_xlfn.SUMIFS(Socle!$Y$1:$Y$658,Socle!$C$1:$C$658,$A9,Socle!$D$1:$D$658,$C9,Socle!$E$1:$E$658,$D9,Socle!$F$1:$F$658,$E9,Socle!$G$1:$G$658,"2026")) -> 0 | M9: =IF($A9="","",_xlfn.SUMIFS(Socle!$V$1:$V$658,Socle!$C$1:$C$658,$A9,Socle!$D$1:$D$658,$C9,Socle!$E$1:$E$658,$D9,Socle!$F$1:$F$658,$E9,Socle!$G$1:$G$658,"2026")) -> 0.984375 | N9: =IF($A9="","",IF(OR($D9="B1",$D9="M1",$D9="BTS1"),1,0)) -> 0 | O9: =IF($A9="","",_xlfn.SUMIFS(Campagne!$D$1:$D$141,Campagne!$C$1:$C$141,$A9)) -> 716 | P9: =IF($A9="","",_xlfn.SUMIFS(Campagne!$E$1:$E$141,Campagne!$C$1:$C$141,$A9)) -> 950 | Q9: =IF($A9="","",_xlfn.SUMIFS(Campagne!$F$1:$F$141,Campagne!$C$1:$C$141,$A9)) -> 1666 | R9: =IF($A9="","",_xlfn.SUMIFS(Campagne!$K$1:$K$141,Campagne!$C$1:$C$141,$A9)) -> 0.50391241 | S9: =IF($A9="","",_xlfn.SUMIFS(Campagne!$M$1:$M$141,Campagne!$C$1:$C$141,$A9)) -> 0.32659376 | T9: =IF($A9="","",_xlfn.SUMIFS(Pilotage!$K$19:$K$32,Pilotage!$A$19:$A$32,$A9)*_xlfn.SUMIFS(Pilotage!$J$19:$J$32,Pilotage!$A$19:$A$32,$A9)*(SUM(Pilotage!$K$19:$K$32)/SUMPRODUCT(Pilotage!$K$19:$K$32,Pilotage!$J$19:$J$32))) -> 41783 | U9: =IF($A9="","",_xlfn.SUMIFS(Pilotage!$K$19:$K$32,Pilotage!$A$19:$A$32,$A9)) -> 41783 | V9: =IF($A9="","",IF($B9="V01",Cadrage!$C$23,IF($B9="V02",Cadrage!$D$23,Cadrage!$E$23))) -> 0.08 | W9: =IF($A9="","",IF($B9="V01",Cadrage!$C$24,IF($B9="V02",Cadrage!$D$24,Cadrage!$E$24))) -> 0.1 | X9: =IF($A9="","",IF($B9="V01",Cadrage!$C$25,IF($B9="V02",Cadrage!$D$25,Cadrage!$E$25))) -> 0.0029 | Y9: =IF($A9="","",IF($B9="V01",Cadrage!$C$26,IF($B9="V02",Cadrage!$D$26,Cadrage!$E$26))) -> 0.01 | Z9: =IF($A9="","",IF($B9="V01",Cadrage!$C$27,IF($B9="V02",Cadrage!$D$27,Cadrage!$E$27))) -> 0.01 | AA9: =IF($A9="","",IF($B9="V01",Cadrage!$C$28,IF($B9="V02",Cadrage!$D$28,Cadrage!$E$28))) -> 0.005 | AB9: =IF($A9="","",IF($B9="V01",Cadrage!$C$42,IF($B9="V02",Cadrage!$D$42,Cadrage!$E$42))) -> 90 | AC9: =IF($A9="","",IF($F9="MBWAY",Cadrage!$K$34,IF($F9="ISCOM",Cadrage!$K$35,IF($F9="IPAC",Cadrage!$K$36,IF($F9="PIGIER",Cadrage!$K$37,Cadrage!$K$38))))) -> 1.2 | AD9: =IF($A9="","",($O9*(1+$W9)^$S9+$P9*_xlfn.IFERROR((($T9/$U9)*(1+$V9))^$R9,0))*_xlfn.IFERROR($G9/$Q9,0)*($J9+$Y9)*$K9*($L9+$Z9)) -> 0 | AE9: =IF($A9="","",IF($N9=1,$AD9,0)) -> 0 | AF9: =IF($A9="","",IF($N9=1,$AD9,$H9*($M9+$AA9))) -> 63.32 | AG9: =IF($A9="","",$I9*(1+$X9*$AC9)) -> 7375.578 | AH9: =IF($A9="","",$AF9*$AG9+$AE9*$AB9) -> 467021.6
A10: =IF(Moteur!D10="","",Moteur!D10) -> MBWAY_LYO | B10: =IF(Moteur!B10="","",Moteur!B10) -> V01 | C10: =IF(Moteur!F10="","",Moteur!F10) -> MAS_MGT | D10: =IF(Moteur!G10="","",Moteur!G10) -> M1 | E10: =IF(Moteur!H10="","",Moteur!H10) -> ALT | F10: =IF(Moteur!E10="","",Moteur!E10) -> MBWAY | G10: =IF($A10="","",_xlfn.SUMIFS(Socle!$H$1:$H$658,Socle!$C$1:$C$658,$A10,Socle!$D$1:$D$658,$C10,Socle!$E$1:$E$658,$D10,Socle!$F$1:$F$658,$E10,Socle!$G$1:$G$658,"2026")) -> 1120 | H10: =IF($A10="","",_xlfn.SUMIFS(Socle!$N$1:$N$658,Socle!$C$1:$C$658,$A10,Socle!$D$1:$D$658,$C10,Socle!$E$1:$E$658,$D10,Socle!$F$1:$F$658,$E10,Socle!$G$1:$G$658,"2026")) -> 0 | I10: =IF($A10="","",_xlfn.SUMIFS(Socle!$P$1:$P$658,Socle!$C$1:$C$658,$A10,Socle!$D$1:$D$658,$C10,Socle!$E$1:$E$658,$D10,Socle!$F$1:$F$658,$E10,Socle!$G$1:$G$658,"2026")) -> 7875 | J10: =IF($A10="","",_xlfn.SUMIFS(Socle!$W$1:$W$658,Socle!$C$1:$C$658,$A10,Socle!$D$1:$D$658,$C10,Socle!$E$1:$E$658,$D10,Socle!$F$1:$F$658,$E10,Socle!$G$1:$G$658,"2026")) -> 0.2 | K10: =IF($A10="","",_xlfn.SUMIFS(Socle!$X$1:$X$658,Socle!$C$1:$C$658,$A10,Socle!$D$1:$D$658,$C10,Socle!$E$1:$E$658,$D10,Socle!$F$1:$F$658,$E10,Socle!$G$1:$G$658,"2026")) -> 0.70089286 | L10: =IF($A10="","",_xlfn.SUMIFS(Socle!$Y$1:$Y$658,Socle!$C$1:$C$658,$A10,Socle!$D$1:$D$658,$C10,Socle!$E$1:$E$658,$D10,Socle!$F$1:$F$658,$E10,Socle!$G$1:$G$658,"2026")) -> 0.42038217 | M10: =IF($A10="","",_xlfn.SUMIFS(Socle!$V$1:$V$658,Socle!$C$1:$C$658,$A10,Socle!$D$1:$D$658,$C10,Socle!$E$1:$E$658,$D10,Socle!$F$1:$F$658,$E10,Socle!$G$1:$G$658,"2026")) -> 0 | N10: =IF($A10="","",IF(OR($D10="B1",$D10="M1",$D10="BTS1"),1,0)) -> 1 | O10: =IF($A10="","",_xlfn.SUMIFS(Campagne!$D$1:$D$141,Campagne!$C$1:$C$141,$A10)) -> 716 | P10: =IF($A10="","",_xlfn.SUMIFS(Campagne!$E$1:$E$141,Campagne!$C$1:$C$141,$A10)) -> 950 | Q10: =IF($A10="","",_xlfn.SUMIFS(Campagne!$F$1:$F$141,Campagne!$C$1:$C$141,$A10)) -> 1666 | R10: =IF($A10="","",_xlfn.SUMIFS(Campagne!$K$1:$K$141,Campagne!$C$1:$C$141,$A10)) -> 0.50391241 | S10: =IF($A10="","",_xlfn.SUMIFS(Campagne!$M$1:$M$141,Campagne!$C$1:$C$141,$A10)) -> 0.32659376 | T10: =IF($A10="","",_xlfn.SUMIFS(Pilotage!$K$19:$K$32,Pilotage!$A$19:$A$32,$A10)*_xlfn.SUMIFS(Pilotage!$J$19:$J$32,Pilotage!$A$19:$A$32,$A10)*(SUM(Pilotage!$K$19:$K$32)/SUMPRODUCT(Pilotage!$K$19:$K$32,Pilotage!$J$19:$J$32))) -> 41783 | U10: =IF($A10="","",_xlfn.SUMIFS(Pilotage!$K$19:$K$32,Pilotage!$A$19:$A$32,$A10)) -> 41783 | V10: =IF($A10="","",IF($B10="V01",Cadrage!$C$23,IF($B10="V02",Cadrage!$D$23,Cadrage!$E$23))) -> 0.08 | W10: =IF($A10="","",IF($B10="V01",Cadrage!$C$24,IF($B10="V02",Cadrage!$D$24,Cadrage!$E$24))) -> 0.1 | X10: =IF($A10="","",IF($B10="V01",Cadrage!$C$25,IF($B10="V02",Cadrage!$D$25,Cadrage!$E$25))) -> 0.0029 | Y10: =IF($A10="","",IF($B10="V01",Cadrage!$C$26,IF($B10="V02",Cadrage!$D$26,Cadrage!$E$26))) -> 0.01 | Z10: =IF($A10="","",IF($B10="V01",Cadrage!$C$27,IF($B10="V02",Cadrage!$D$27,Cadrage!$E$27))) -> 0.01 | AA10: =IF($A10="","",IF($B10="V01",Cadrage!$C$28,IF($B10="V02",Cadrage!$D$28,Cadrage!$E$28))) -> 0.005 | AB10: =IF($A10="","",IF($B10="V01",Cadrage!$C$42,IF($B10="V02",Cadrage!$D$42,Cadrage!$E$42))) -> 90 | AC10: =IF($A10="","",IF($F10="MBWAY",Cadrage!$K$34,IF($F10="ISCOM",Cadrage!$K$35,IF($F10="IPAC",Cadrage!$K$36,IF($F10="PIGIER",Cadrage!$K$37,Cadrage!$K$38))))) -> 1.2 | AD10: =IF($A10="","",($O10*(1+$W10)^$S10+$P10*_xlfn.IFERROR((($T10/$U10)*(1+$V10))^$R10,0))*_xlfn.IFERROR($G10/$Q10,0)*($J10+$Y10)*$K10*($L10+$Z10)) -> 73.512365 | AE10: =IF($A10="","",IF($N10=1,$AD10,0)) -> 73.512365 | AF10: =IF($A10="","",IF($N10=1,$AD10,$H10*($M10+$AA10))) -> 73.512365 | AG10: =IF($A10="","",$I10*(1+$X10*$AC10)) -> 7902.405 | AH10: =IF($A10="","",$AF10*$AG10+$AE10*$AB10) -> 587540.59
A11: =IF(Moteur!D11="","",Moteur!D11) -> MBWAY_LYO | B11: =IF(Moteur!B11="","",Moteur!B11) -> V01 | C11: =IF(Moteur!F11="","",Moteur!F11) -> MAS_MGT | D11: =IF(Moteur!G11="","",Moteur!G11) -> M2 | E11: =IF(Moteur!H11="","",Moteur!H11) -> ALT | F11: =IF(Moteur!E11="","",Moteur!E11) -> MBWAY | G11: =IF($A11="","",_xlfn.SUMIFS(Socle!$H$1:$H$658,Socle!$C$1:$C$658,$A11,Socle!$D$1:$D$658,$C11,Socle!$E$1:$E$658,$D11,Socle!$F$1:$F$658,$E11,Socle!$G$1:$G$658,"2026")) -> 0 | H11: =IF($A11="","",_xlfn.SUMIFS(Socle!$N$1:$N$658,Socle!$C$1:$C$658,$A11,Socle!$D$1:$D$658,$C11,Socle!$E$1:$E$658,$D11,Socle!$F$1:$F$658,$E11,Socle!$G$1:$G$658,"2026")) -> 66 | I11: =IF($A11="","",_xlfn.SUMIFS(Socle!$P$1:$P$658,Socle!$C$1:$C$658,$A11,Socle!$D$1:$D$658,$C11,Socle!$E$1:$E$658,$D11,Socle!$F$1:$F$658,$E11,Socle!$G$1:$G$658,"2026")) -> 7875 | J11: =IF($A11="","",_xlfn.SUMIFS(Socle!$W$1:$W$658,Socle!$C$1:$C$658,$A11,Socle!$D$1:$D$658,$C11,Socle!$E$1:$E$658,$D11,Socle!$F$1:$F$658,$E11,Socle!$G$1:$G$658,"2026")) -> 0 | K11: =IF($A11="","",_xlfn.SUMIFS(Socle!$X$1:$X$658,Socle!$C$1:$C$658,$A11,Socle!$D$1:$D$658,$C11,Socle!$E$1:$E$658,$D11,Socle!$F$1:$F$658,$E11,Socle!$G$1:$G$658,"2026")) -> 0 | L11: =IF($A11="","",_xlfn.SUMIFS(Socle!$Y$1:$Y$658,Socle!$C$1:$C$658,$A11,Socle!$D$1:$D$658,$C11,Socle!$E$1:$E$658,$D11,Socle!$F$1:$F$658,$E11,Socle!$G$1:$G$658,"2026")) -> 0 | M11: =IF($A11="","",_xlfn.SUMIFS(Socle!$V$1:$V$658,Socle!$C$1:$C$658,$A11,Socle!$D$1:$D$658,$C11,Socle!$E$1:$E$658,$D11,Socle!$F$1:$F$658,$E11,Socle!$G$1:$G$658,"2026")) -> 0.98484848 | N11: =IF($A11="","",IF(OR($D11="B1",$D11="M1",$D11="BTS1"),1,0)) -> 0 | O11: =IF($A11="","",_xlfn.SUMIFS(Campagne!$D$1:$D$141,Campagne!$C$1:$C$141,$A11)) -> 716 | P11: =IF($A11="","",_xlfn.SUMIFS(Campagne!$E$1:$E$141,Campagne!$C$1:$C$141,$A11)) -> 950 | Q11: =IF($A11="","",_xlfn.SUMIFS(Campagne!$F$1:$F$141,Campagne!$C$1:$C$141,$A11)) -> 1666 | R11: =IF($A11="","",_xlfn.SUMIFS(Campagne!$K$1:$K$141,Campagne!$C$1:$C$141,$A11)) -> 0.50391241 | S11: =IF($A11="","",_xlfn.SUMIFS(Campagne!$M$1:$M$141,Campagne!$C$1:$C$141,$A11)) -> 0.32659376 | T11: =IF($A11="","",_xlfn.SUMIFS(Pilotage!$K$19:$K$32,Pilotage!$A$19:$A$32,$A11)*_xlfn.SUMIFS(Pilotage!$J$19:$J$32,Pilotage!$A$19:$A$32,$A11)*(SUM(Pilotage!$K$19:$K$32)/SUMPRODUCT(Pilotage!$K$19:$K$32,Pilotage!$J$19:$J$32))) -> 41783 | U11: =IF($A11="","",_xlfn.SUMIFS(Pilotage!$K$19:$K$32,Pilotage!$A$19:$A$32,$A11)) -> 41783 | V11: =IF($A11="","",IF($B11="V01",Cadrage!$C$23,IF($B11="V02",Cadrage!$D$23,Cadrage!$E$23))) -> 0.08 | W11: =IF($A11="","",IF($B11="V01",Cadrage!$C$24,IF($B11="V02",Cadrage!$D$24,Cadrage!$E$24))) -> 0.1 | X11: =IF($A11="","",IF($B11="V01",Cadrage!$C$25,IF($B11="V02",Cadrage!$D$25,Cadrage!$E$25))) -> 0.0029 | Y11: =IF($A11="","",IF($B11="V01",Cadrage!$C$26,IF($B11="V02",Cadrage!$D$26,Cadrage!$E$26))) -> 0.01 | Z11: =IF($A11="","",IF($B11="V01",Cadrage!$C$27,IF($B11="V02",Cadrage!$D$27,Cadrage!$E$27))) -> 0.01 | AA11: =IF($A11="","",IF($B11="V01",Cadrage!$C$28,IF($B11="V02",Cadrage!$D$28,Cadrage!$E$28))) -> 0.005 | AB11: =IF($A11="","",IF($B11="V01",Cadrage!$C$42,IF($B11="V02",Cadrage!$D$42,Cadrage!$E$42))) -> 90 | AC11: =IF($A11="","",IF($F11="MBWAY",Cadrage!$K$34,IF($F11="ISCOM",Cadrage!$K$35,IF($F11="IPAC",Cadrage!$K$36,IF($F11="PIGIER",Cadrage!$K$37,Cadrage!$K$38))))) -> 1.2 | AD11: =IF($A11="","",($O11*(1+$W11)^$S11+$P11*_xlfn.IFERROR((($T11/$U11)*(1+$V11))^$R11,0))*_xlfn.IFERROR($G11/$Q11,0)*($J11+$Y11)*$K11*($L11+$Z11)) -> 0 | AE11: =IF($A11="","",IF($N11=1,$AD11,0)) -> 0 | AF11: =IF($A11="","",IF($N11=1,$AD11,$H11*($M11+$AA11))) -> 65.33 | AG11: =IF($A11="","",$I11*(1+$X11*$AC11)) -> 7902.405 | AH11: =IF($A11="","",$AF11*$AG11+$AE11*$AB11) -> 516264.12
A12: =IF(Moteur!D12="","",Moteur!D12) -> MBWAY_NAN | B12: =IF(Moteur!B12="","",Moteur!B12) -> V01 | C12: =IF(Moteur!F12="","",Moteur!F12) -> BAC_MGT | D12: =IF(Moteur!G12="","",Moteur!G12) -> B1 | E12: =IF(Moteur!H12="","",Moteur!H12) -> INIT | F12: =IF(Moteur!E12="","",Moteur!E12) -> MBWAY | G12: =IF($A12="","",_xlfn.SUMIFS(Socle!$H$1:$H$658,Socle!$C$1:$C$658,$A12,Socle!$D$1:$D$658,$C12,Socle!$E$1:$E$658,$D12,Socle!$F$1:$F$658,$E12,Socle!$G$1:$G$658,"2026")) -> 496 | H12: =IF($A12="","",_xlfn.SUMIFS(Socle!$N$1:$N$658,Socle!$C$1:$C$658,$A12,Socle!$D$1:$D$658,$C12,Socle!$E$1:$E$658,$D12,Socle!$F$1:$F$658,$E12,Socle!$G$1:$G$658,"2026")) -> 0 | I12: =IF($A12="","",_xlfn.SUMIFS(Socle!$P$1:$P$658,Socle!$C$1:$C$658,$A12,Socle!$D$1:$D$658,$C12,Socle!$E$1:$E$658,$D12,Socle!$F$1:$F$658,$E12,Socle!$G$1:$G$658,"2026")) -> 7500 | J12: =IF($A12="","",_xlfn.SUMIFS(Socle!$W$1:$W$658,Socle!$C$1:$C$658,$A12,Socle!$D$1:$D$658,$C12,Socle!$E$1:$E$658,$D12,Socle!$F$1:$F$658,$E12,Socle!$G$1:$G$658,"2026")) -> 0.28024193 | K12: =IF($A12="","",_xlfn.SUMIFS(Socle!$X$1:$X$658,Socle!$C$1:$C$658,$A12,Socle!$D$1:$D$658,$C12,Socle!$E$1:$E$658,$D12,Socle!$F$1:$F$658,$E12,Socle!$G$1:$G$658,"2026")) -> 0.71942446 | L12: =IF($A12="","",_xlfn.SUMIFS(Socle!$Y$1:$Y$658,Socle!$C$1:$C$658,$A12,Socle!$D$1:$D$658,$C12,Socle!$E$1:$E$658,$D12,Socle!$F$1:$F$658,$E12,Socle!$G$1:$G$658,"2026")) -> 0.6 | M12: =IF($A12="","",_xlfn.SUMIFS(Socle!$V$1:$V$658,Socle!$C$1:$C$658,$A12,Socle!$D$1:$D$658,$C12,Socle!$E$1:$E$658,$D12,Socle!$F$1:$F$658,$E12,Socle!$G$1:$G$658,"2026")) -> 0 | N12: =IF($A12="","",IF(OR($D12="B1",$D12="M1",$D12="BTS1"),1,0)) -> 1 | O12: =IF($A12="","",_xlfn.SUMIFS(Campagne!$D$1:$D$141,Campagne!$C$1:$C$141,$A12)) -> 728 | P12: =IF($A12="","",_xlfn.SUMIFS(Campagne!$E$1:$E$141,Campagne!$C$1:$C$141,$A12)) -> 788 | Q12: =IF($A12="","",_xlfn.SUMIFS(Campagne!$F$1:$F$141,Campagne!$C$1:$C$141,$A12)) -> 1516 | R12: =IF($A12="","",_xlfn.SUMIFS(Campagne!$K$1:$K$141,Campagne!$C$1:$C$141,$A12)) -> 0.52465564 | S12: =IF($A12="","",_xlfn.SUMIFS(Campagne!$M$1:$M$141,Campagne!$C$1:$C$141,$A12)) -> 0.34345059 | T12: =IF($A12="","",_xlfn.SUMIFS(Pilotage!$K$19:$K$32,Pilotage!$A$19:$A$32,$A12)*_xlfn.SUMIFS(Pilotage!$J$19:$J$32,Pilotage!$A$19:$A$32,$A12)*(SUM(Pilotage!$K$19:$K$32)/SUMPRODUCT(Pilotage!$K$19:$K$32,Pilotage!$J$19:$J$32))) -> 31533 | U12: =IF($A12="","",_xlfn.SUMIFS(Pilotage!$K$19:$K$32,Pilotage!$A$19:$A$32,$A12)) -> 31533 | V12: =IF($A12="","",IF($B12="V01",Cadrage!$C$23,IF($B12="V02",Cadrage!$D$23,Cadrage!$E$23))) -> 0.08 | W12: =IF($A12="","",IF($B12="V01",Cadrage!$C$24,IF($B12="V02",Cadrage!$D$24,Cadrage!$E$24))) -> 0.1 | X12: =IF($A12="","",IF($B12="V01",Cadrage!$C$25,IF($B12="V02",Cadrage!$D$25,Cadrage!$E$25))) -> 0.0029 | Y12: =IF($A12="","",IF($B12="V01",Cadrage!$C$26,IF($B12="V02",Cadrage!$D$26,Cadrage!$E$26))) -> 0.01 | Z12: =IF($A12="","",IF($B12="V01",Cadrage!$C$27,IF($B12="V02",Cadrage!$D$27,Cadrage!$E$27))) -> 0.01 | AA12: =IF($A12="","",IF($B12="V01",Cadrage!$C$28,IF($B12="V02",Cadrage!$D$28,Cadrage!$E$28))) -> 0.005 | AB12: =IF($A12="","",IF($B12="V01",Cadrage!$C$42,IF($B12="V02",Cadrage!$D$42,Cadrage!$E$42))) -> 90 | AC12: =IF($A12="","",IF($F12="MBWAY",Cadrage!$K$34,IF($F12="ISCOM",Cadrage!$K$35,IF($F12="IPAC",Cadrage!$K$36,IF($F12="PIGIER",Cadrage!$K$37,Cadrage!$K$38))))) -> 1.2 | AD12: =IF($A12="","",($O12*(1+$W12)^$S12+$P12*_xlfn.IFERROR((($T12/$U12)*(1+$V12))^$R12,0))*_xlfn.IFERROR($G12/$Q12,0)*($J12+$Y12)*$K12*($L12+$Z12)) -> 65.539313 | AE12: =IF($A12="","",IF($N12=1,$AD12,0)) -> 65.539313 | AF12: =IF($A12="","",IF($N12=1,$AD12,$H12*($M12+$AA12))) -> 65.539313 | AG12: =IF($A12="","",$I12*(1+$X12*$AC12)) -> 7526.1 | AH12: =IF($A12="","",$AF12*$AG12+$AE12*$AB12) -> 499153.96
A13: =IF(Moteur!D13="","",Moteur!D13) -> MBWAY_NAN | B13: =IF(Moteur!B13="","",Moteur!B13) -> V01 | C13: =IF(Moteur!F13="","",Moteur!F13) -> BAC_MGT | D13: =IF(Moteur!G13="","",Moteur!G13) -> B2 | E13: =IF(Moteur!H13="","",Moteur!H13) -> ALT | F13: =IF(Moteur!E13="","",Moteur!E13) -> MBWAY | G13: =IF($A13="","",_xlfn.SUMIFS(Socle!$H$1:$H$658,Socle!$C$1:$C$658,$A13,Socle!$D$1:$D$658,$C13,Socle!$E$1:$E$658,$D13,Socle!$F$1:$F$658,$E13,Socle!$G$1:$G$658,"2026")) -> 0 | H13: =IF($A13="","",_xlfn.SUMIFS(Socle!$N$1:$N$658,Socle!$C$1:$C$658,$A13,Socle!$D$1:$D$658,$C13,Socle!$E$1:$E$658,$D13,Socle!$F$1:$F$658,$E13,Socle!$G$1:$G$658,"2026")) -> 60 | I13: =IF($A13="","",_xlfn.SUMIFS(Socle!$P$1:$P$658,Socle!$C$1:$C$658,$A13,Socle!$D$1:$D$658,$C13,Socle!$E$1:$E$658,$D13,Socle!$F$1:$F$658,$E13,Socle!$G$1:$G$658,"2026")) -> 7000 | J13: =IF($A13="","",_xlfn.SUMIFS(Socle!$W$1:$W$658,Socle!$C$1:$C$658,$A13,Socle!$D$1:$D$658,$C13,Socle!$E$1:$E$658,$D13,Socle!$F$1:$F$658,$E13,Socle!$G$1:$G$658,"2026")) -> 0 | K13: =IF($A13="","",_xlfn.SUMIFS(Socle!$X$1:$X$658,Socle!$C$1:$C$658,$A13,Socle!$D$1:$D$658,$C13,Socle!$E$1:$E$658,$D13,Socle!$F$1:$F$658,$E13,Socle!$G$1:$G$658,"2026")) -> 0 | L13: =IF($A13="","",_xlfn.SUMIFS(Socle!$Y$1:$Y$658,Socle!$C$1:$C$658,$A13,Socle!$D$1:$D$658,$C13,Socle!$E$1:$E$658,$D13,Socle!$F$1:$F$658,$E13,Socle!$G$1:$G$658,"2026")) -> 0 | M13: =IF($A13="","",_xlfn.SUMIFS(Socle!$V$1:$V$658,Socle!$C$1:$C$658,$A13,Socle!$D$1:$D$658,$C13,Socle!$E$1:$E$658,$D13,Socle!$F$1:$F$658,$E13,Socle!$G$1:$G$658,"2026")) -> 0.96666667 | N13: =IF($A13="","",IF(OR($D13="B1",$D13="M1",$D13="BTS1"),1,0)) -> 0 | O13: =IF($A13="","",_xlfn.SUMIFS(Campagne!$D$1:$D$141,Campagne!$C$1:$C$141,$A13)) -> 728 | P13: =IF($A13="","",_xlfn.SUMIFS(Campagne!$E$1:$E$141,Campagne!$C$1:$C$141,$A13)) -> 788 | Q13: =IF($A13="","",_xlfn.SUMIFS(Campagne!$F$1:$F$141,Campagne!$C$1:$C$141,$A13)) -> 1516 | R13: =IF($A13="","",_xlfn.SUMIFS(Campagne!$K$1:$K$141,Campagne!$C$1:$C$141,$A13)) -> 0.52465564 | S13: =IF($A13="","",_xlfn.SUMIFS(Campagne!$M$1:$M$141,Campagne!$C$1:$C$141,$A13)) -> 0.34345059 | T13: =IF($A13="","",_xlfn.SUMIFS(Pilotage!$K$19:$K$32,Pilotage!$A$19:$A$32,$A13)*_xlfn.SUMIFS(Pilotage!$J$19:$J$32,Pilotage!$A$19:$A$32,$A13)*(SUM(Pilotage!$K$19:$K$32)/SUMPRODUCT(Pilotage!$K$19:$K$32,Pilotage!$J$19:$J$32))) -> 31533 | U13: =IF($A13="","",_xlfn.SUMIFS(Pilotage!$K$19:$K$32,Pilotage!$A$19:$A$32,$A13)) -> 31533 | V13: =IF($A13="","",IF($B13="V01",Cadrage!$C$23,IF($B13="V02",Cadrage!$D$23,Cadrage!$E$23))) -> 0.08 | W13: =IF($A13="","",IF($B13="V01",Cadrage!$C$24,IF($B13="V02",Cadrage!$D$24,Cadrage!$E$24))) -> 0.1 | X13: =IF($A13="","",IF($B13="V01",Cadrage!$C$25,IF($B13="V02",Cadrage!$D$25,Cadrage!$E$25))) -> 0.0029 | Y13: =IF($A13="","",IF($B13="V01",Cadrage!$C$26,IF($B13="V02",Cadrage!$D$26,Cadrage!$E$26))) -> 0.01 | Z13: =IF($A13="","",IF($B13="V01",Cadrage!$C$27,IF($B13="V02",Cadrage!$D$27,Cadrage!$E$27))) -> 0.01 | AA13: =IF($A13="","",IF($B13="V01",Cadrage!$C$28,IF($B13="V02",Cadrage!$D$28,Cadrage!$E$28))) -> 0.005 | AB13: =IF($A13="","",IF($B13="V01",Cadrage!$C$42,IF($B13="V02",Cadrage!$D$42,Cadrage!$E$42))) -> 90 | AC13: =IF($A13="","",IF($F13="MBWAY",Cadrage!$K$34,IF($F13="ISCOM",Cadrage!$K$35,IF($F13="IPAC",Cadrage!$K$36,IF($F13="PIGIER",Cadrage!$K$37,Cadrage!$K$38))))) -> 1.2 | AD13: =IF($A13="","",($O13*(1+$W13)^$S13+$P13*_xlfn.IFERROR((($T13/$U13)*(1+$V13))^$R13,0))*_xlfn.IFERROR($G13/$Q13,0)*($J13+$Y13)*$K13*($L13+$Z13)) -> 0 | AE13: =IF($A13="","",IF($N13=1,$AD13,0)) -> 0 | AF13: =IF($A13="","",IF($N13=1,$AD13,$H13*($M13+$AA13))) -> 58.3 | AG13: =IF($A13="","",$I13*(1+$X13*$AC13)) -> 7024.36 | AH13: =IF($A13="","",$AF13*$AG13+$AE13*$AB13) -> 409520.19
... A190: =IF(Moteur!D190="","",Moteur!D190) | B190: =IF(Moteur!B190="","",Moteur!B190) | C190: =IF(Moteur!F190="","",Moteur!F190) | D190: =IF(Moteur!G190="","",Moteur!G190) | E190: =IF(Moteur!H190="","",Moteur!H190) | F190: =IF(Moteur!E190="","",Moteur!E190) | G190: =IF($A190="","",_xlfn.SUMIFS(Socle!$H$1:$H$658,Socle!$C$1:$C$658,$A190,Socle!$D$1:$D$658,$C190,Socle!$E$1:$E$658,$D190,Socle!$F$1:$F$658,$E190,Socle!$G$1:$G$658,"2026")) | H190: =IF($A190="","",_xlfn.SUMIFS(Socle!$N$1:$N$658,Socle!$C$1:$C$658,$A190,Socle!$D$1:$D$658,$C190,Socle!$E$1:$E$658,$D190,Socle!$F$1:$F$658,$E190,Socle!$G$1:$G$658,"2026")) | I190: =IF($A190="","",_xlfn.SUMIFS(Socle!$P$1:$P$658,Socle!$C$1:$C$658,$A190,Socle!$D$1:$D$658,$C190,Socle!$E$1:$E$658,$D190,Socle!$F$1:$F$658,$E190,Socle!$G$1:$G$658,"2026")) | J190: =IF($A190="","",_xlfn.SUMIFS(Socle!$W$1:$W$658,Socle!$C$1:$C$658,$A190,Socle!$D$1:$D$658,$C190,Socle!$E$1:$E$658,$D190,Socle!$F$1:$F$658,$E190,Socle!$G$1:$G$658,"2026")) | K190: =IF($A190="","",_xlfn.SUMIFS(Socle!$X$1:$X$658,Socle!$C$1:$C$658,$A190,Socle!$D$1:$D$658,$C190,Socle!$E$1:$E$658,$D190,Socle!$F$1:$F$658,$E190,Socle!$G$1:$G$658,"2026")) | L190: =IF($A190="","",_xlfn.SUMIFS(Socle!$Y$1:$Y$658,Socle!$C$1:$C$658,$A190,Socle!$D$1:$D$658,$C190,Socle!$E$1:$E$658,$D190,Socle!$F$1:$F$658,$E190,Socle!$G$1:$G$658,"2026")) | M190: =IF($A190="","",_xlfn.SUMIFS(Socle!$V$1:$V$658,Socle!$C$1:$C$658,$A190,Socle!$D$1:$D$658,$C190,Socle!$E$1:$E$658,$D190,Socle!$F$1:$F$658,$E190,Socle!$G$1:$G$658,"2026")) | N190: =IF($A190="","",IF(OR($D190="B1",$D190="M1",$D190="BTS1"),1,0)) | O190: =IF($A190="","",_xlfn.SUMIFS(Campagne!$D$1:$D$141,Campagne!$C$1:$C$141,$A190)) | P190: =IF($A190="","",_xlfn.SUMIFS(Campagne!$E$1:$E$141,Campagne!$C$1:$C$141,$A190)) | Q190: =IF($A190="","",_xlfn.SUMIFS(Campagne!$F$1:$F$141,Campagne!$C$1:$C$141,$A190)) | R190: =IF($A190="","",_xlfn.SUMIFS(Campagne!$K$1:$K$141,Campagne!$C$1:$C$141,$A190)) | S190: =IF($A190="","",_xlfn.SUMIFS(Campagne!$M$1:$M$141,Campagne!$C$1:$C$141,$A190)) | T190: =IF($A190="","",_xlfn.SUMIFS(Pilotage!$K$19:$K$32,Pilotage!$A$19:$A$32,$A190)*_xlfn.SUMIFS(Pilotage!$J$19:$J$32,Pilotage!$A$19:$A$32,$A190)*(SUM(Pilotage!$K$19:$K$32)/SUMPRODUCT(Pilotage!$K$19:$K$32,Pilotage!$J$19:$J$32))) | U190: =IF($A190="","",_xlfn.SUMIFS(Pilotage!$K$19:$K$32,Pilotage!$A$19:$A$32,$A190)) | V190: =IF($A190="","",IF($B190="V01",Cadrage!$C$23,IF($B190="V02",Cadrage!$D$23,Cadrage!$E$23))) | W190: =IF($A190="","",IF($B190="V01",Cadrage!$C$24,IF($B190="V02",Cadrage!$D$24,Cadrage!$E$24))) | X190: =IF($A190="","",IF($B190="V01",Cadrage!$C$25,IF($B190="V02",Cadrage!$D$25,Cadrage!$E$25))) | Y190: =IF($A190="","",IF($B190="V01",Cadrage!$C$26,IF($B190="V02",Cadrage!$D$26,Cadrage!$E$26))) | Z190: =IF($A190="","",IF($B190="V01",Cadrage!$C$27,IF($B190="V02",Cadrage!$D$27,Cadrage!$E$27))) | AA190: =IF($A190="","",IF($B190="V01",Cadrage!$C$28,IF($B190="V02",Cadrage!$D$28,Cadrage!$E$28))) | AB190: =IF($A190="","",IF($B190="V01",Cadrage!$C$42,IF($B190="V02",Cadrage!$D$42,Cadrage!$E$42))) | AC190: =IF($A190="","",IF($F190="MBWAY",Cadrage!$K$34,IF($F190="ISCOM",Cadrage!$K$35,IF($F190="IPAC",Cadrage!$K$36,IF($F190="PIGIER",Cadrage!$K$37,Cadrage!$K$38))))) | AD190: =IF($A190="","",($O190*(1+$W190)^$S190+$P190*_xlfn.IFERROR((($T190/$U190)*(1+$V190))^$R190,0))*_xlfn.IFERROR($G190/$Q190,0)*($J190+$Y190)*$K190*($L190+$Z190)) | AE190: =IF($A190="","",IF($N190=1,$AD190,0)) | AF190: =IF($A190="","",IF($N190=1,$AD190,$H190*($M190+$AA190))) | AG190: =IF($A190="","",$I190*(1+$X190*$AC190)) | AH190: =IF($A190="","",$AF190*$AG190+$AE190*$AB190)

Sheet _CALC_PNL
A1: ENT | B1: ACC | C1: EX | D1: VER | E1: ISBUD | F1: CPT26 | G1: ACQ | H1: BRAND | I1: INFL | J1: SAL | K1: FTE | L1: PROD | M1: STRUCT | N1: CAF | O1: FAC | P1: AMT_LIVE | R1: =_xlfn.SUMIFS(Comptabilité!$F$1:$F$1446,Comptabilité!$B$1:$B$1446,"7062",Comptabilité!$C$1:$C$1446,"2026")+_xlfn.SUMIFS(Comptabilité!$F$1:$F$1446,Comptabilité!$B$1:$B$1446,"706",Comptabilité!$C$1:$C$1446,"2026")+_xlfn.SUMIFS(Comptabilité!$F$1:$F$1446,Comptabilité!$B$1:$B$1446,"708",Comptabilité!$C$1:$C$1446,"2026") -> 23098985 | T1: EBITDA_SIGNED | V1: ■ VIOLET = colonne branchee sur une saisie (cad / Pilotage / 3_Allocation) -> a recabler cote Tagetik
A2: =IF(PNL!A2="","",PNL!A2) -> MBWAY_PAR | B2: =IF(PNL!B2="","",PNL!B2) -> 7062 | C2: =IF(PNL!C2="","",PNL!C2) -> 2024 | D2: =IF(PNL!D2="","",PNL!D2) -> ACT | E2: =IF($A2="","",IF(AND($C2="2027",OR($D2="V01",$D2="V02",$D2="V03")),1,0)) -> 0 | F2: =IF($A2="","",IF($E2=1,_xlfn.SUMIFS(Comptabilité!$F$1:$F$1446,Comptabilité!$A$1:$A$1446,$A2,Comptabilité!$B$1:$B$1446,$B2,Comptabilité!$C$1:$C$1446,"2026"),0)) -> 0 | G2: =IF($A2="","",IF($D2="V01",Cadrage!$C$23,IF($D2="V02",Cadrage!$D$23,Cadrage!$E$23))) -> -0.05 | H2: =IF($A2="","",IF($D2="V01",Cadrage!$C$24,IF($D2="V02",Cadrage!$D$24,Cadrage!$E$24))) -> -0.05 | I2: =IF($A2="","",IF($D2="V01",Cadrage!$C$34,IF($D2="V02",Cadrage!$D$34,Cadrage!$E$34))) -> 0.03 | J2: =IF($A2="","",IF($D2="V01",Cadrage!$C$35,IF($D2="V02",Cadrage!$D$35,Cadrage!$E$35))) -> 0.03 | K2: =IF($A2="","",IF($D2="V01",Cadrage!$C$36,IF($D2="V02",Cadrage!$D$36,Cadrage!$E$36))) -> 0.05 | L2: =IF($A2="","",IF($D2="V01",Cadrage!$C$37,IF($D2="V02",Cadrage!$D$37,Cadrage!$E$37))) -> 0 | M2: =IF($A2="","",IF($D2="V01",Cadrage!$C$38,IF($D2="V02",Cadrage!$D$38,Cadrage!$E$38))) -> 0.04 | N2: =IF($A2="","",IF($D2="V01",$R$2,IF($D2="V02",$R$3,$R$4))) -> 0.98062208 | O2: =IF($A2="","",IF(OR($B2="7062",$B2="706",$B2="708"),$N2,IF($B2="6231",1+$G2,IF($B2="6236",1+$H2,IF(OR($B2="621",$B2="604",$B2="6063"),$N2*(1-$L2),IF(OR($B2="6411",$B2="6413",$B2="6414",$B2="645"),(1+$J2)*(1+$K2),IF(OR($B2="613",$B2="615",$B2="616",$B2="6226",$B2="625",$B2="626",$B2="6281"),(1+$I2)*(1-$L2)*(1+$M2),IF(OR($B2="6331",$B2="63511",$B2="6333"),(1+$I2)*(1-$L2),IF($B2="6811",1+$I2,1))))))))) -> 0.98062208 | P2: =IF($A2="","",IF($E2=1,$F2*$O2,PNL!G2)) -> 2201360 | R2: =_xlfn.SUMIFS(Moteur!$R$1:$R$200,Moteur!$B$1:$B$200,"V01")/$R$1 -> 1.0490376 | T2: =IF($A2="","",IF($E2=1,IF(OR($B2="7062",$B2="706",$B2="708"),$P2,IF(AND(LEFT($B2,1)="6",$B2<>"6811"),-$P2,0)),0)) -> 0
A3: =IF(PNL!A3="","",PNL!A3) -> MBWAY_LYO | B3: =IF(PNL!B3="","",PNL!B3) -> 7062 | C3: =IF(PNL!C3="","",PNL!C3) -> 2024 | D3: =IF(PNL!D3="","",PNL!D3) -> ACT | E3: =IF($A3="","",IF(AND($C3="2027",OR($D3="V01",$D3="V02",$D3="V03")),1,0)) -> 0 | F3: =IF($A3="","",IF($E3=1,_xlfn.SUMIFS(Comptabilité!$F$1:$F$1446,Comptabilité!$A$1:$A$1446,$A3,Comptabilité!$B$1:$B$1446,$B3,Comptabilité!$C$1:$C$1446,"2026"),0)) -> 0 | G3: =IF($A3="","",IF($D3="V01",Cadrage!$C$23,IF($D3="V02",Cadrage!$D$23,Cadrage!$E$23))) -> -0.05 | H3: =IF($A3="","",IF($D3="V01",Cadrage!$C$24,IF($D3="V02",Cadrage!$D$24,Cadrage!$E$24))) -> -0.05 | I3: =IF($A3="","",IF($D3="V01",Cadrage!$C$34,IF($D3="V02",Cadrage!$D$34,Cadrage!$E$34))) -> 0.03 | J3: =IF($A3="","",IF($D3="V01",Cadrage!$C$35,IF($D3="V02",Cadrage!$D$35,Cadrage!$E$35))) -> 0.03 | K3: =IF($A3="","",IF($D3="V01",Cadrage!$C$36,IF($D3="V02",Cadrage!$D$36,Cadrage!$E$36))) -> 0.05 | L3: =IF($A3="","",IF($D3="V01",Cadrage!$C$37,IF($D3="V02",Cadrage!$D$37,Cadrage!$E$37))) -> 0 | M3: =IF($A3="","",IF($D3="V01",Cadrage!$C$38,IF($D3="V02",Cadrage!$D$38,Cadrage!$E$38))) -> 0.04 | N3: =IF($A3="","",IF($D3="V01",$R$2,IF($D3="V02",$R$3,$R$4))) -> 0.98062208 | O3: =IF($A3="","",IF(OR($B3="7062",$B3="706",$B3="708"),$N3,IF($B3="6231",1+$G3,IF($B3="6236",1+$H3,IF(OR($B3="621",$B3="604",$B3="6063"),$N3*(1-$L3),IF(OR($B3="6411",$B3="6413",$B3="6414",$B3="645"),(1+$J3)*(1+$K3),IF(OR($B3="613",$B3="615",$B3="616",$B3="6226",$B3="625",$B3="626",$B3="6281"),(1+$I3)*(1-$L3)*(1+$M3),IF(OR($B3="6331",$B3="63511",$B3="6333"),(1+$I3)*(1-$L3),IF($B3="6811",1+$I3,1))))))))) -> 0.98062208 | P3: =IF($A3="","",IF($E3=1,$F3*$O3,PNL!G3)) -> 1751925 | R3: =_xlfn.SUMIFS(Moteur!$R$1:$R$200,Moteur!$B$1:$B$200,"V02")/$R$1 -> 1.1608375 | T3: =IF($A3="","",IF($E3=1,IF(OR($B3="7062",$B3="706",$B3="708"),$P3,IF(AND(LEFT($B3,1)="6",$B3<>"6811"),-$P3,0)),0)) -> 0
A4: =IF(PNL!A4="","",PNL!A4) -> MBWAY_NAN | B4: =IF(PNL!B4="","",PNL!B4) -> 7062 | C4: =IF(PNL!C4="","",PNL!C4) -> 2024 | D4: =IF(PNL!D4="","",PNL!D4) -> ACT | E4: =IF($A4="","",IF(AND($C4="2027",OR($D4="V01",$D4="V02",$D4="V03")),1,0)) -> 0 | F4: =IF($A4="","",IF($E4=1,_xlfn.SUMIFS(Comptabilité!$F$1:$F$1446,Comptabilité!$A$1:$A$1446,$A4,Comptabilité!$B$1:$B$1446,$B4,Comptabilité!$C$1:$C$1446,"2026"),0)) -> 0 | G4: =IF($A4="","",IF($D4="V01",Cadrage!$C$23,IF($D4="V02",Cadrage!$D$23,Cadrage!$E$23))) -> -0.05 | H4: =IF($A4="","",IF($D4="V01",Cadrage!$C$24,IF($D4="V02",Cadrage!$D$24,Cadrage!$E$24))) -> -0.05 | I4: =IF($A4="","",IF($D4="V01",Cadrage!$C$34,IF($D4="V02",Cadrage!$D$34,Cadrage!$E$34))) -> 0.03 | J4: =IF($A4="","",IF($D4="V01",Cadrage!$C$35,IF($D4="V02",Cadrage!$D$35,Cadrage!$E$35))) -> 0.03 | K4: =IF($A4="","",IF($D4="V01",Cadrage!$C$36,IF($D4="V02",Cadrage!$D$36,Cadrage!$E$36))) -> 0.05 | L4: =IF($A4="","",IF($D4="V01",Cadrage!$C$37,IF($D4="V02",Cadrage!$D$37,Cadrage!$E$37))) -> 0 | M4: =IF($A4="","",IF($D4="V01",Cadrage!$C$38,IF($D4="V02",Cadrage!$D$38,Cadrage!$E$38))) -> 0.04 | N4: =IF($A4="","",IF($D4="V01",$R$2,IF($D4="V02",$R$3,$R$4))) -> 0.98062208 | O4: =IF($A4="","",IF(OR($B4="7062",$B4="706",$B4="708"),$N4,IF($B4="6231",1+$G4,IF($B4="6236",1+$H4,IF(OR($B4="621",$B4="604",$B4="6063"),$N4*(1-$L4),IF(OR($B4="6411",$B4="6413",$B4="6414",$B4="645"),(1+$J4)*(1+$K4),IF(OR($B4="613",$B4="615",$B4="616",$B4="6226",$B4="625",$B4="626",$B4="6281"),(1+$I4)*(1-$L4)*(1+$M4),IF(OR($B4="6331",$B4="63511",$B4="6333"),(1+$I4)*(1-$L4),IF($B4="6811",1+$I4,1))))))))) -> 0.98062208 | P4: =IF($A4="","",IF($E4=1,$F4*$O4,PNL!G4)) -> 1516000 | R4: =_xlfn.SUMIFS(Moteur!$R$1:$R$200,Moteur!$B$1:$B$200,"V03")/$R$1 -> 0.98062208 | T4: =IF($A4="","",IF($E4=1,IF(OR($B4="7062",$B4="706",$B4="708"),$P4,IF(AND(LEFT($B4,1)="6",$B4<>"6811"),-$P4,0)),0)) -> 0
A5: =IF(PNL!A5="","",PNL!A5) -> MBWAY_BOR | B5: =IF(PNL!B5="","",PNL!B5) -> 7062 | C5: =IF(PNL!C5="","",PNL!C5) -> 2024 | D5: =IF(PNL!D5="","",PNL!D5) -> ACT | E5: =IF($A5="","",IF(AND($C5="2027",OR($D5="V01",$D5="V02",$D5="V03")),1,0)) -> 0 | F5: =IF($A5="","",IF($E5=1,_xlfn.SUMIFS(Comptabilité!$F$1:$F$1446,Comptabilité!$A$1:$A$1446,$A5,Comptabilité!$B$1:$B$1446,$B5,Comptabilité!$C$1:$C$1446,"2026"),0)) -> 0 | G5: =IF($A5="","",IF($D5="V01",Cadrage!$C$23,IF($D5="V02",Cadrage!$D$23,Cadrage!$E$23))) -> -0.05 | H5: =IF($A5="","",IF($D5="V01",Cadrage!$C$24,IF($D5="V02",Cadrage!$D$24,Cadrage!$E$24))) -> -0.05 | I5: =IF($A5="","",IF($D5="V01",Cadrage!$C$34,IF($D5="V02",Cadrage!$D$34,Cadrage!$E$34))) -> 0.03 | J5: =IF($A5="","",IF($D5="V01",Cadrage!$C$35,IF($D5="V02",Cadrage!$D$35,Cadrage!$E$35))) -> 0.03 | K5: =IF($A5="","",IF($D5="V01",Cadrage!$C$36,IF($D5="V02",Cadrage!$D$36,Cadrage!$E$36))) -> 0.05 | L5: =IF($A5="","",IF($D5="V01",Cadrage!$C$37,IF($D5="V02",Cadrage!$D$37,Cadrage!$E$37))) -> 0 | M5: =IF($A5="","",IF($D5="V01",Cadrage!$C$38,IF($D5="V02",Cadrage!$D$38,Cadrage!$E$38))) -> 0.04 | N5: =IF($A5="","",IF($D5="V01",$R$2,IF($D5="V02",$R$3,$R$4))) -> 0.98062208 | O5: =IF($A5="","",IF(OR($B5="7062",$B5="706",$B5="708"),$N5,IF($B5="6231",1+$G5,IF($B5="6236",1+$H5,IF(OR($B5="621",$B5="604",$B5="6063"),$N5*(1-$L5),IF(OR($B5="6411",$B5="6413",$B5="6414",$B5="645"),(1+$J5)*(1+$K5),IF(OR($B5="613",$B5="615",$B5="616",$B5="6226",$B5="625",$B5="626",$B5="6281"),(1+$I5)*(1-$L5)*(1+$M5),IF(OR($B5="6331",$B5="63511",$B5="6333"),(1+$I5)*(1-$L5),IF($B5="6811",1+$I5,1))))))))) -> 0.98062208 | P5: =IF($A5="","",IF($E5=1,$F5*$O5,PNL!G5)) -> 1238205 | T5: =IF($A5="","",IF($E5=1,IF(OR($B5="7062",$B5="706",$B5="708"),$P5,IF(AND(LEFT($B5,1)="6",$B5<>"6811"),-$P5,0)),0)) -> 0
A6: =IF(PNL!A6="","",PNL!A6) -> ISCOM_PAR | B6: =IF(PNL!B6="","",PNL!B6) -> 7062 | C6: =IF(PNL!C6="","",PNL!C6) -> 2024 | D6: =IF(PNL!D6="","",PNL!D6) -> ACT | E6: =IF($A6="","",IF(AND($C6="2027",OR($D6="V01",$D6="V02",$D6="V03")),1,0)) -> 0 | F6: =IF($A6="","",IF($E6=1,_xlfn.SUMIFS(Comptabilité!$F$1:$F$1446,Comptabilité!$A$1:$A$1446,$A6,Comptabilité!$B$1:$B$1446,$B6,Comptabilité!$C$1:$C$1446,"2026"),0)) -> 0 | G6: =IF($A6="","",IF($D6="V01",Cadrage!$C$23,IF($D6="V02",Cadrage!$D$23,Cadrage!$E$23))) -> -0.05 | H6: =IF($A6="","",IF($D6="V01",Cadrage!$C$24,IF($D6="V02",Cadrage!$D$24,Cadrage!$E$24))) -> -0.05 | I6: =IF($A6="","",IF($D6="V01",Cadrage!$C$34,IF($D6="V02",Cadrage!$D$34,Cadrage!$E$34))) -> 0.03 | J6: =IF($A6="","",IF($D6="V01",Cadrage!$C$35,IF($D6="V02",Cadrage!$D$35,Cadrage!$E$35))) -> 0.03 | K6: =IF($A6="","",IF($D6="V01",Cadrage!$C$36,IF($D6="V02",Cadrage!$D$36,Cadrage!$E$36))) -> 0.05 | L6: =IF($A6="","",IF($D6="V01",Cadrage!$C$37,IF($D6="V02",Cadrage!$D$37,Cadrage!$E$37))) -> 0 | M6: =IF($A6="","",IF($D6="V01",Cadrage!$C$38,IF($D6="V02",Cadrage!$D$38,Cadrage!$E$38))) -> 0.04 | N6: =IF($A6="","",IF($D6="V01",$R$2,IF($D6="V02",$R$3,$R$4))) -> 0.98062208 | O6: =IF($A6="","",IF(OR($B6="7062",$B6="706",$B6="708"),$N6,IF($B6="6231",1+$G6,IF($B6="6236",1+$H6,IF(OR($B6="621",$B6="604",$B6="6063"),$N6*(1-$L6),IF(OR($B6="6411",$B6="6413",$B6="6414",$B6="645"),(1+$J6)*(1+$K6),IF(OR($B6="613",$B6="615",$B6="616",$B6="6226",$B6="625",$B6="626",$B6="6281"),(1+$I6)*(1-$L6)*(1+$M6),IF(OR($B6="6331",$B6="63511",$B6="6333"),(1+$I6)*(1-$L6),IF($B6="6811",1+$I6,1))))))))) -> 0.98062208 | P6: =IF($A6="","",IF($E6=1,$F6*$O6,PNL!G6)) -> 2031120 | T6: =IF($A6="","",IF($E6=1,IF(OR($B6="7062",$B6="706",$B6="708"),$P6,IF(AND(LEFT($B6,1)="6",$B6<>"6811"),-$P6,0)),0)) -> 0
A7: =IF(PNL!A7="","",PNL!A7) -> ISCOM_LIL | B7: =IF(PNL!B7="","",PNL!B7) -> 7062 | C7: =IF(PNL!C7="","",PNL!C7) -> 2024 | D7: =IF(PNL!D7="","",PNL!D7) -> ACT | E7: =IF($A7="","",IF(AND($C7="2027",OR($D7="V01",$D7="V02",$D7="V03")),1,0)) -> 0 | F7: =IF($A7="","",IF($E7=1,_xlfn.SUMIFS(Comptabilité!$F$1:$F$1446,Comptabilité!$A$1:$A$1446,$A7,Comptabilité!$B$1:$B$1446,$B7,Comptabilité!$C$1:$C$1446,"2026"),0)) -> 0 | G7: =IF($A7="","",IF($D7="V01",Cadrage!$C$23,IF($D7="V02",Cadrage!$D$23,Cadrage!$E$23))) -> -0.05 | H7: =IF($A7="","",IF($D7="V01",Cadrage!$C$24,IF($D7="V02",Cadrage!$D$24,Cadrage!$E$24))) -> -0.05 | I7: =IF($A7="","",IF($D7="V01",Cadrage!$C$34,IF($D7="V02",Cadrage!$D$34,Cadrage!$E$34))) -> 0.03 | J7: =IF($A7="","",IF($D7="V01",Cadrage!$C$35,IF($D7="V02",Cadrage!$D$35,Cadrage!$E$35))) -> 0.03 | K7: =IF($A7="","",IF($D7="V01",Cadrage!$C$36,IF($D7="V02",Cadrage!$D$36,Cadrage!$E$36))) -> 0.05 | L7: =IF($A7="","",IF($D7="V01",Cadrage!$C$37,IF($D7="V02",Cadrage!$D$37,Cadrage!$E$37))) -> 0 | M7: =IF($A7="","",IF($D7="V01",Cadrage!$C$38,IF($D7="V02",Cadrage!$D$38,Cadrage!$E$38))) -> 0.04 | N7: =IF($A7="","",IF($D7="V01",$R$2,IF($D7="V02",$R$3,$R$4))) -> 0.98062208 | O7: =IF($A7="","",IF(OR($B7="7062",$B7="706",$B7="708"),$N7,IF($B7="6231",1+$G7,IF($B7="6236",1+$H7,IF(OR($B7="621",$B7="604",$B7="6063"),$N7*(1-$L7),IF(OR($B7="6411",$B7="6413",$B7="6414",$B7="645"),(1+$J7)*(1+$K7),IF(OR($B7="613",$B7="615",$B7="616",$B7="6226",$B7="625",$B7="626",$B7="6281"),(1+$I7)*(1-$L7)*(1+$M7),IF(OR($B7="6331",$B7="63511",$B7="6333"),(1+$I7)*(1-$L7),IF($B7="6811",1+$I7,1))))))))) -> 0.98062208 | P7: =IF($A7="","",IF($E7=1,$F7*$O7,PNL!G7)) -> 1229900 | T7: =IF($A7="","",IF($E7=1,IF(OR($B7="7062",$B7="706",$B7="708"),$P7,IF(AND(LEFT($B7,1)="6",$B7<>"6811"),-$P7,0)),0)) -> 0
A8: =IF(PNL!A8="","",PNL!A8) -> ISCOM_TLS | B8: =IF(PNL!B8="","",PNL!B8) -> 7062 | C8: =IF(PNL!C8="","",PNL!C8) -> 2024 | D8: =IF(PNL!D8="","",PNL!D8) -> ACT | E8: =IF($A8="","",IF(AND($C8="2027",OR($D8="V01",$D8="V02",$D8="V03")),1,0)) -> 0 | F8: =IF($A8="","",IF($E8=1,_xlfn.SUMIFS(Comptabilité!$F$1:$F$1446,Comptabilité!$A$1:$A$1446,$A8,Comptabilité!$B$1:$B$1446,$B8,Comptabilité!$C$1:$C$1446,"2026"),0)) -> 0 | G8: =IF($A8="","",IF($D8="V01",Cadrage!$C$23,IF($D8="V02",Cadrage!$D$23,Cadrage!$E$23))) -> -0.05 | H8: =IF($A8="","",IF($D8="V01",Cadrage!$C$24,IF($D8="V02",Cadrage!$D$24,Cadrage!$E$24))) -> -0.05 | I8: =IF($A8="","",IF($D8="V01",Cadrage!$C$34,IF($D8="V02",Cadrage!$D$34,Cadrage!$E$34))) -> 0.03 | J8: =IF($A8="","",IF($D8="V01",Cadrage!$C$35,IF($D8="V02",Cadrage!$D$35,Cadrage!$E$35))) -> 0.03 | K8: =IF($A8="","",IF($D8="V01",Cadrage!$C$36,IF($D8="V02",Cadrage!$D$36,Cadrage!$E$36))) -> 0.05 | L8: =IF($A8="","",IF($D8="V01",Cadrage!$C$37,IF($D8="V02",Cadrage!$D$37,Cadrage!$E$37))) -> 0 | M8: =IF($A8="","",IF($D8="V01",Cadrage!$C$38,IF($D8="V02",Cadrage!$D$38,Cadrage!$E$38))) -> 0.04 | N8: =IF($A8="","",IF($D8="V01",$R$2,IF($D8="V02",$R$3,$R$4))) -> 0.98062208 | O8: =IF($A8="","",IF(OR($B8="7062",$B8="706",$B8="708"),$N8,IF($B8="6231",1+$G8,IF($B8="6236",1+$H8,IF(OR($B8="621",$B8="604",$B8="6063"),$N8*(1-$L8),IF(OR($B8="6411",$B8="6413",$B8="6414",$B8="645"),(1+$J8)*(1+$K8),IF(OR($B8="613",$B8="615",$B8="616",$B8="6226",$B8="625",$B8="626",$B8="6281"),(1+$I8)*(1-$L8)*(1+$M8),IF(OR($B8="6331",$B8="63511",$B8="6333"),(1+$I8)*(1-$L8),IF($B8="6811",1+$I8,1))))))))) -> 0.98062208 | P8: =IF($A8="","",IF($E8=1,$F8*$O8,PNL!G8)) -> 1141920 | T8: =IF($A8="","",IF($E8=1,IF(OR($B8="7062",$B8="706",$B8="708"),$P8,IF(AND(LEFT($B8,1)="6",$B8<>"6811"),-$P8,0)),0)) -> 0
A9: =IF(PNL!A9="","",PNL!A9) -> IPAC_NAN | B9: =IF(PNL!B9="","",PNL!B9) -> 7062 | C9: =IF(PNL!C9="","",PNL!C9) -> 2024 | D9: =IF(PNL!D9="","",PNL!D9) -> ACT | E9: =IF($A9="","",IF(AND($C9="2027",OR($D9="V01",$D9="V02",$D9="V03")),1,0)) -> 0 | F9: =IF($A9="","",IF($E9=1,_xlfn.SUMIFS(Comptabilité!$F$1:$F$1446,Comptabilité!$A$1:$A$1446,$A9,Comptabilité!$B$1:$B$1446,$B9,Comptabilité!$C$1:$C$1446,"2026"),0)) -> 0 | G9: =IF($A9="","",IF($D9="V01",Cadrage!$C$23,IF($D9="V02",Cadrage!$D$23,Cadrage!$E$23))) -> -0.05 | H9: =IF($A9="","",IF($D9="V01",Cadrage!$C$24,IF($D9="V02",Cadrage!$D$24,Cadrage!$E$24))) -> -0.05 | I9: =IF($A9="","",IF($D9="V01",Cadrage!$C$34,IF($D9="V02",Cadrage!$D$34,Cadrage!$E$34))) -> 0.03 | J9: =IF($A9="","",IF($D9="V01",Cadrage!$C$35,IF($D9="V02",Cadrage!$D$35,Cadrage!$E$35))) -> 0.03 | K9: =IF($A9="","",IF($D9="V01",Cadrage!$C$36,IF($D9="V02",Cadrage!$D$36,Cadrage!$E$36))) -> 0.05 | L9: =IF($A9="","",IF($D9="V01",Cadrage!$C$37,IF($D9="V02",Cadrage!$D$37,Cadrage!$E$37))) -> 0 | M9: =IF($A9="","",IF($D9="V01",Cadrage!$C$38,IF($D9="V02",Cadrage!$D$38,Cadrage!$E$38))) -> 0.04 | N9: =IF($A9="","",IF($D9="V01",$R$2,IF($D9="V02",$R$3,$R$4))) -> 0.98062208 | O9: =IF($A9="","",IF(OR($B9="7062",$B9="706",$B9="708"),$N9,IF($B9="6231",1+$G9,IF($B9="6236",1+$H9,IF(OR($B9="621",$B9="604",$B9="6063"),$N9*(1-$L9),IF(OR($B9="6411",$B9="6413",$B9="6414",$B9="645"),(1+$J9)*(1+$K9),IF(OR($B9="613",$B9="615",$B9="616",$B9="6226",$B9="625",$B9="626",$B9="6281"),(1+$I9)*(1-$L9)*(1+$M9),IF(OR($B9="6331",$B9="63511",$B9="6333"),(1+$I9)*(1-$L9),IF($B9="6811",1+$I9,1))))))))) -> 0.98062208 | P9: =IF($A9="","",IF($E9=1,$F9*$O9,PNL!G9)) -> 903000 | T9: =IF($A9="","",IF($E9=1,IF(OR($B9="7062",$B9="706",$B9="708"),$P9,IF(AND(LEFT($B9,1)="6",$B9<>"6811"),-$P9,0)),0)) -> 0
A10: =IF(PNL!A10="","",PNL!A10) -> IPAC_REN | B10: =IF(PNL!B10="","",PNL!B10) -> 7062 | C10: =IF(PNL!C10="","",PNL!C10) -> 2024 | D10: =IF(PNL!D10="","",PNL!D10) -> ACT | E10: =IF($A10="","",IF(AND($C10="2027",OR($D10="V01",$D10="V02",$D10="V03")),1,0)) -> 0 | F10: =IF($A10="","",IF($E10=1,_xlfn.SUMIFS(Comptabilité!$F$1:$F$1446,Comptabilité!$A$1:$A$1446,$A10,Comptabilité!$B$1:$B$1446,$B10,Comptabilité!$C$1:$C$1446,"2026"),0)) -> 0 | G10: =IF($A10="","",IF($D10="V01",Cadrage!$C$23,IF($D10="V02",Cadrage!$D$23,Cadrage!$E$23))) -> -0.05 | H10: =IF($A10="","",IF($D10="V01",Cadrage!$C$24,IF($D10="V02",Cadrage!$D$24,Cadrage!$E$24))) -> -0.05 | I10: =IF($A10="","",IF($D10="V01",Cadrage!$C$34,IF($D10="V02",Cadrage!$D$34,Cadrage!$E$34))) -> 0.03 | J10: =IF($A10="","",IF($D10="V01",Cadrage!$C$35,IF($D10="V02",Cadrage!$D$35,Cadrage!$E$35))) -> 0.03 | K10: =IF($A10="","",IF($D10="V01",Cadrage!$C$36,IF($D10="V02",Cadrage!$D$36,Cadrage!$E$36))) -> 0.05 | L10: =IF($A10="","",IF($D10="V01",Cadrage!$C$37,IF($D10="V02",Cadrage!$D$37,Cadrage!$E$37))) -> 0 | M10: =IF($A10="","",IF($D10="V01",Cadrage!$C$38,IF($D10="V02",Cadrage!$D$38,Cadrage!$E$38))) -> 0.04 | N10: =IF($A10="","",IF($D10="V01",$R$2,IF($D10="V02",$R$3,$R$4))) -> 0.98062208 | O10: =IF($A10="","",IF(OR($B10="7062",$B10="706",$B10="708"),$N10,IF($B10="6231",1+$G10,IF($B10="6236",1+$H10,IF(OR($B10="621",$B10="604",$B10="6063"),$N10*(1-$L10),IF(OR($B10="6411",$B10="6413",$B10="6414",$B10="645"),(1+$J10)*(1+$K10),IF(OR($B10="613",$B10="615",$B10="616",$B10="6226",$B10="625",$B10="626",$B10="6281"),(1+$I10)*(1-$L10)*(1+$M10),IF(OR($B10="6331",$B10="63511",$B10="6333"),(1+$I10)*(1-$L10),IF($B10="6811",1+$I10,1))))))))) -> 0.98062208 | P10: =IF($A10="","",IF($E10=1,$F10*$O10,PNL!G10)) -> 698250 | T10: =IF($A10="","",IF($E10=1,IF(OR($B10="7062",$B10="706",$B10="708"),$P10,IF(AND(LEFT($B10,1)="6",$B10<>"6811"),-$P10,0)),0)) -> 0
A11: =IF(PNL!A11="","",PNL!A11) -> IPAC_MTP | B11: =IF(PNL!B11="","",PNL!B11) -> 7062 | C11: =IF(PNL!C11="","",PNL!C11) -> 2024 | D11: =IF(PNL!D11="","",PNL!D11) -> ACT | E11: =IF($A11="","",IF(AND($C11="2027",OR($D11="V01",$D11="V02",$D11="V03")),1,0)) -> 0 | F11: =IF($A11="","",IF($E11=1,_xlfn.SUMIFS(Comptabilité!$F$1:$F$1446,Comptabilité!$A$1:$A$1446,$A11,Comptabilité!$B$1:$B$1446,$B11,Comptabilité!$C$1:$C$1446,"2026"),0)) -> 0 | G11: =IF($A11="","",IF($D11="V01",Cadrage!$C$23,IF($D11="V02",Cadrage!$D$23,Cadrage!$E$23))) -> -0.05 | H11: =IF($A11="","",IF($D11="V01",Cadrage!$C$24,IF($D11="V02",Cadrage!$D$24,Cadrage!$E$24))) -> -0.05 | I11: =IF($A11="","",IF($D11="V01",Cadrage!$C$34,IF($D11="V02",Cadrage!$D$34,Cadrage!$E$34))) -> 0.03 | J11: =IF($A11="","",IF($D11="V01",Cadrage!$C$35,IF($D11="V02",Cadrage!$D$35,Cadrage!$E$35))) -> 0.03 | K11: =IF($A11="","",IF($D11="V01",Cadrage!$C$36,IF($D11="V02",Cadrage!$D$36,Cadrage!$E$36))) -> 0.05 | L11: =IF($A11="","",IF($D11="V01",Cadrage!$C$37,IF($D11="V02",Cadrage!$D$37,Cadrage!$E$37))) -> 0 | M11: =IF($A11="","",IF($D11="V01",Cadrage!$C$38,IF($D11="V02",Cadrage!$D$38,Cadrage!$E$38))) -> 0.04 | N11: =IF($A11="","",IF($D11="V01",$R$2,IF($D11="V02",$R$3,$R$4))) -> 0.98062208 | O11: =IF($A11="","",IF(OR($B11="7062",$B11="706",$B11="708"),$N11,IF($B11="6231",1+$G11,IF($B11="6236",1+$H11,IF(OR($B11="621",$B11="604",$B11="6063"),$N11*(1-$L11),IF(OR($B11="6411",$B11="6413",$B11="6414",$B11="645"),(1+$J11)*(1+$K11),IF(OR($B11="613",$B11="615",$B11="616",$B11="6226",$B11="625",$B11="626",$B11="6281"),(1+$I11)*(1-$L11)*(1+$M11),IF(OR($B11="6331",$B11="63511",$B11="6333"),(1+$I11)*(1-$L11),IF($B11="6811",1+$I11,1))))))))) -> 0.98062208 | P11: =IF($A11="","",IF($E11=1,$F11*$O11,PNL!G11)) -> 698250 | T11: =IF($A11="","",IF($E11=1,IF(OR($B11="7062",$B11="706",$B11="708"),$P11,IF(AND(LEFT($B11,1)="6",$B11<>"6811"),-$P11,0)),0)) -> 0
A12: =IF(PNL!A12="","",PNL!A12) -> TUNON_PAR | B12: =IF(PNL!B12="","",PNL!B12) -> 7062 | C12: =IF(PNL!C12="","",PNL!C12) -> 2024 | D12: =IF(PNL!D12="","",PNL!D12) -> ACT | E12: =IF($A12="","",IF(AND($C12="2027",OR($D12="V01",$D12="V02",$D12="V03")),1,0)) -> 0 | F12: =IF($A12="","",IF($E12=1,_xlfn.SUMIFS(Comptabilité!$F$1:$F$1446,Comptabilité!$A$1:$A$1446,$A12,Comptabilité!$B$1:$B$1446,$B12,Comptabilité!$C$1:$C$1446,"2026"),0)) -> 0 | G12: =IF($A12="","",IF($D12="V01",Cadrage!$C$23,IF($D12="V02",Cadrage!$D$23,Cadrage!$E$23))) -> -0.05 | H12: =IF($A12="","",IF($D12="V01",Cadrage!$C$24,IF($D12="V02",Cadrage!$D$24,Cadrage!$E$24))) -> -0.05 | I12: =IF($A12="","",IF($D12="V01",Cadrage!$C$34,IF($D12="V02",Cadrage!$D$34,Cadrage!$E$34))) -> 0.03 | J12: =IF($A12="","",IF($D12="V01",Cadrage!$C$35,IF($D12="V02",Cadrage!$D$35,Cadrage!$E$35))) -> 0.03 | K12: =IF($A12="","",IF($D12="V01",Cadrage!$C$36,IF($D12="V02",Cadrage!$D$36,Cadrage!$E$36))) -> 0.05 | L12: =IF($A12="","",IF($D12="V01",Cadrage!$C$37,IF($D12="V02",Cadrage!$D$37,Cadrage!$E$37))) -> 0 | M12: =IF($A12="","",IF($D12="V01",Cadrage!$C$38,IF($D12="V02",Cadrage!$D$38,Cadrage!$E$38))) -> 0.04 | N12: =IF($A12="","",IF($D12="V01",$R$2,IF($D12="V02",$R$3,$R$4))) -> 0.98062208 | O12: =IF($A12="","",IF(OR($B12="7062",$B12="706",$B12="708"),$N12,IF($B12="6231",1+$G12,IF($B12="6236",1+$H12,IF(OR($B12="621",$B12="604",$B12="6063"),$N12*(1-$L12),IF(OR($B12="6411",$B12="6413",$B12="6414",$B12="645"),(1+$J12)*(1+$K12),IF(OR($B12="613",$B12="615",$B12="616",$B12="6226",$B12="625",$B12="626",$B12="6281"),(1+$I12)*(1-$L12)*(1+$M12),IF(OR($B12="6331",$B12="63511",$B12="6333"),(1+$I12)*(1-$L12),IF($B12="6811",1+$I12,1))))))))) -> 0.98062208 | P12: =IF($A12="","",IF($E12=1,$F12*$O12,PNL!G12)) -> 964320 | T12: =IF($A12="","",IF($E12=1,IF(OR($B12="7062",$B12="706",$B12="708"),$P12,IF(AND(LEFT($B12,1)="6",$B12<>"6811"),-$P12,0)),0)) -> 0
A13: =IF(PNL!A13="","",PNL!A13) -> TUNON_LYO | B13: =IF(PNL!B13="","",PNL!B13) -> 7062 | C13: =IF(PNL!C13="","",PNL!C13) -> 2024 | D13: =IF(PNL!D13="","",PNL!D13) -> ACT | E13: =IF($A13="","",IF(AND($C13="2027",OR($D13="V01",$D13="V02",$D13="V03")),1,0)) -> 0 | F13: =IF($A13="","",IF($E13=1,_xlfn.SUMIFS(Comptabilité!$F$1:$F$1446,Comptabilité!$A$1:$A$1446,$A13,Comptabilité!$B$1:$B$1446,$B13,Comptabilité!$C$1:$C$1446,"2026"),0)) -> 0 | G13: =IF($A13="","",IF($D13="V01",Cadrage!$C$23,IF($D13="V02",Cadrage!$D$23,Cadrage!$E$23))) -> -0.05 | H13: =IF($A13="","",IF($D13="V01",Cadrage!$C$24,IF($D13="V02",Cadrage!$D$24,Cadrage!$E$24))) -> -0.05 | I13: =IF($A13="","",IF($D13="V01",Cadrage!$C$34,IF($D13="V02",Cadrage!$D$34,Cadrage!$E$34))) -> 0.03 | J13: =IF($A13="","",IF($D13="V01",Cadrage!$C$35,IF($D13="V02",Cadrage!$D$35,Cadrage!$E$35))) -> 0.03 | K13: =IF($A13="","",IF($D13="V01",Cadrage!$C$36,IF($D13="V02",Cadrage!$D$36,Cadrage!$E$36))) -> 0.05 | L13: =IF($A13="","",IF($D13="V01",Cadrage!$C$37,IF($D13="V02",Cadrage!$D$37,Cadrage!$E$37))) -> 0 | M13: =IF($A13="","",IF($D13="V01",Cadrage!$C$38,IF($D13="V02",Cadrage!$D$38,Cadrage!$E$38))) -> 0.04 | N13: =IF($A13="","",IF($D13="V01",$R$2,IF($D13="V02",$R$3,$R$4))) -> 0.98062208 | O13: =IF($A13="","",IF(OR($B13="7062",$B13="706",$B13="708"),$N13,IF($B13="6231",1+$G13,IF($B13="6236",1+$H13,IF(OR($B13="621",$B13="604",$B13="6063"),$N13*(1-$L13),IF(OR($B13="6411",$B13="6413",$B13="6414",$B13="645"),(1+$J13)*(1+$K13),IF(OR($B13="613",$B13="615",$B13="616",$B13="6226",$B13="625",$B13="626",$B13="6281"),(1+$I13)*(1-$L13)*(1+$M13),IF(OR($B13="6331",$B13="63511",$B13="6333"),(1+$I13)*(1-$L13),IF($B13="6811",1+$I13,1))))))))) -> 0.98062208 | P13: =IF($A13="","",IF($E13=1,$F13*$O13,PNL!G13)) -> 771750 | T13: =IF($A13="","",IF($E13=1,IF(OR($B13="7062",$B13="706",$B13="708"),$P13,IF(AND(LEFT($B13,1)="6",$B13<>"6811"),-$P13,0)),0)) -> 0
A14: =IF(PNL!A14="","",PNL!A14) -> MBWAY_PAR | B14: =IF(PNL!B14="","",PNL!B14) -> 7062 | C14: =IF(PNL!C14="","",PNL!C14) -> 2025 | D14: =IF(PNL!D14="","",PNL!D14) -> ACT | E14: =IF($A14="","",IF(AND($C14="2027",OR($D14="V01",$D14="V02",$D14="V03")),1,0)) -> 0 | F14: =IF($A14="","",IF($E14=1,_xlfn.SUMIFS(Comptabilité!$F$1:$F$1446,Comptabilité!$A$1:$A$1446,$A14,Comptabilité!$B$1:$B$1446,$B14,Comptabilité!$C$1:$C$1446,"2026"),0)) -> 0 | G14: =IF($A14="","",IF($D14="V01",Cadrage!$C$23,IF($D14="V02",Cadrage!$D$23,Cadrage!$E$23))) -> -0.05 | H14: =IF($A14="","",IF($D14="V01",Cadrage!$C$24,IF($D14="V02",Cadrage!$D$24,Cadrage!$E$24))) -> -0.05 | I14: =IF($A14="","",IF($D14="V01",Cadrage!$C$34,IF($D14="V02",Cadrage!$D$34,Cadrage!$E$34))) -> 0.03 | J14: =IF($A14="","",IF($D14="V01",Cadrage!$C$35,IF($D14="V02",Cadrage!$D$35,Cadrage!$E$35))) -> 0.03 | K14: =IF($A14="","",IF($D14="V01",Cadrage!$C$36,IF($D14="V02",Cadrage!$D$36,Cadrage!$E$36))) -> 0.05 | L14: =IF($A14="","",IF($D14="V01",Cadrage!$C$37,IF($D14="V02",Cadrage!$D$37,Cadrage!$E$37))) -> 0 | M14: =IF($A14="","",IF($D14="V01",Cadrage!$C$38,IF($D14="V02",Cadrage!$D$38,Cadrage!$E$38))) -> 0.04 | N14: =IF($A14="","",IF($D14="V01",$R$2,IF($D14="V02",$R$3,$R$4))) -> 0.98062208 | O14: =IF($A14="","",IF(OR($B14="7062",$B14="706",$B14="708"),$N14,IF($B14="6231",1+$G14,IF($B14="6236",1+$H14,IF(OR($B14="621",$B14="604",$B14="6063"),$N14*(1-$L14),IF(OR($B14="6411",$B14="6413",$B14="6414",$B14="645"),(1+$J14)*(1+$K14),IF(OR($B14="613",$B14="615",$B14="616",$B14="6226",$B14="625",$B14="626",$B14="6281"),(1+$I14)*(1-$L14)*(1+$M14),IF(OR($B14="6331",$B14="63511",$B14="6333"),(1+$I14)*(1-$L14),IF($B14="6811",1+$I14,1))))))))) -> 0.98062208 | P14: =IF($A14="","",IF($E14=1,$F14*$O14,PNL!G14)) -> 2339680 | T14: =IF($A14="","",IF($E14=1,IF(OR($B14="7062",$B14="706",$B14="708"),$P14,IF(AND(LEFT($B14,1)="6",$B14<>"6811"),-$P14,0)),0)) -> 0
A15: =IF(PNL!A15="","",PNL!A15) -> MBWAY_LYO | B15: =IF(PNL!B15="","",PNL!B15) -> 7062 | C15: =IF(PNL!C15="","",PNL!C15) -> 2025 | D15: =IF(PNL!D15="","",PNL!D15) -> ACT | E15: =IF($A15="","",IF(AND($C15="2027",OR($D15="V01",$D15="V02",$D15="V03")),1,0)) -> 0 | F15: =IF($A15="","",IF($E15=1,_xlfn.SUMIFS(Comptabilité!$F$1:$F$1446,Comptabilité!$A$1:$A$1446,$A15,Comptabilité!$B$1:$B$1446,$B15,Comptabilité!$C$1:$C$1446,"2026"),0)) -> 0 | G15: =IF($A15="","",IF($D15="V01",Cadrage!$C$23,IF($D15="V02",Cadrage!$D$23,Cadrage!$E$23))) -> -0.05 | H15: =IF($A15="","",IF($D15="V01",Cadrage!$C$24,IF($D15="V02",Cadrage!$D$24,Cadrage!$E$24))) -> -0.05 | I15: =IF($A15="","",IF($D15="V01",Cadrage!$C$34,IF($D15="V02",Cadrage!$D$34,Cadrage!$E$34))) -> 0.03 | J15: =IF($A15="","",IF($D15="V01",Cadrage!$C$35,IF($D15="V02",Cadrage!$D$35,Cadrage!$E$35))) -> 0.03 | K15: =IF($A15="","",IF($D15="V01",Cadrage!$C$36,IF($D15="V02",Cadrage!$D$36,Cadrage!$E$36))) -> 0.05 | L15: =IF($A15="","",IF($D15="V01",Cadrage!$C$37,IF($D15="V02",Cadrage!$D$37,Cadrage!$E$37))) -> 0 | M15: =IF($A15="","",IF($D15="V01",Cadrage!$C$38,IF($D15="V02",Cadrage!$D$38,Cadrage!$E$38))) -> 0.04 | N15: =IF($A15="","",IF($D15="V01",$R$2,IF($D15="V02",$R$3,$R$4))) -> 0.98062208 | O15: =IF($A15="","",IF(OR($B15="7062",$B15="706",$B15="708"),$N15,IF($B15="6231",1+$G15,IF($B15="6236",1+$H15,IF(OR($B15="621",$B15="604",$B15="6063"),$N15*(1-$L15),IF(OR($B15="6411",$B15="6413",$B15="6414",$B15="645"),(1+$J15)*(1+$K15),IF(OR($B15="613",$B15="615",$B15="616",$B15="6226",$B15="625",$B15="626",$B15="6281"),(1+$I15)*(1-$L15)*(1+$M15),IF(OR($B15="6331",$B15="63511",$B15="6333"),(1+$I15)*(1-$L15),IF($B15="6811",1+$I15,1))))))))) -> 0.98062208 | P15: =IF($A15="","",IF($E15=1,$F15*$O15,PNL!G15)) -> 1843275 | T15: =IF($A15="","",IF($E15=1,IF(OR($B15="7062",$B15="706",$B15="708"),$P15,IF(AND(LEFT($B15,1)="6",$B15<>"6811"),-$P15,0)),0)) -> 0
A16: =IF(PNL!A16="","",PNL!A16) -> MBWAY_NAN | B16: =IF(PNL!B16="","",PNL!B16) -> 7062 | C16: =IF(PNL!C16="","",PNL!C16) -> 2025 | D16: =IF(PNL!D16="","",PNL!D16) -> ACT | E16: =IF($A16="","",IF(AND($C16="2027",OR($D16="V01",$D16="V02",$D16="V03")),1,0)) -> 0 | F16: =IF($A16="","",IF($E16=1,_xlfn.SUMIFS(Comptabilité!$F$1:$F$1446,Comptabilité!$A$1:$A$1446,$A16,Comptabilité!$B$1:$B$1446,$B16,Comptabilité!$C$1:$C$1446,"2026"),0)) -> 0 | G16: =IF($A16="","",IF($D16="V01",Cadrage!$C$23,IF($D16="V02",Cadrage!$D$23,Cadrage!$E$23))) -> -0.05 | H16: =IF($A16="","",IF($D16="V01",Cadrage!$C$24,IF($D16="V02",Cadrage!$D$24,Cadrage!$E$24))) -> -0.05 | I16: =IF($A16="","",IF($D16="V01",Cadrage!$C$34,IF($D16="V02",Cadrage!$D$34,Cadrage!$E$34))) -> 0.03 | J16: =IF($A16="","",IF($D16="V01",Cadrage!$C$35,IF($D16="V02",Cadrage!$D$35,Cadrage!$E$35))) -> 0.03 | K16: =IF($A16="","",IF($D16="V01",Cadrage!$C$36,IF($D16="V02",Cadrage!$D$36,Cadrage!$E$36))) -> 0.05 | L16: =IF($A16="","",IF($D16="V01",Cadrage!$C$37,IF($D16="V02",Cadrage!$D$37,Cadrage!$E$37))) -> 0 | M16: =IF($A16="","",IF($D16="V01",Cadrage!$C$38,IF($D16="V02",Cadrage!$D$38,Cadrage!$E$38))) -> 0.04 | N16: =IF($A16="","",IF($D16="V01",$R$2,IF($D16="V02",$R$3,$R$4))) -> 0.98062208 | O16: =IF($A16="","",IF(OR($B16="7062",$B16="706",$B16="708"),$N16,IF($B16="6231",1+$G16,IF($B16="6236",1+$H16,IF(OR($B16="621",$B16="604",$B16="6063"),$N16*(1-$L16),IF(OR($B16="6411",$B16="6413",$B16="6414",$B16="645"),(1+$J16)*(1+$K16),IF(OR($B16="613",$B16="615",$B16="616",$B16="6226",$B16="625",$B16="626",$B16="6281"),(1+$I16)*(1-$L16)*(1+$M16),IF(OR($B16="6331",$B16="63511",$B16="6333"),(1+$I16)*(1-$L16),IF($B16="6811",1+$I16,1))))))))) -> 0.98062208 | P16: =IF($A16="","",IF($E16=1,$F16*$O16,PNL!G16)) -> 1610500 | T16: =IF($A16="","",IF($E16=1,IF(OR($B16="7062",$B16="706",$B16="708"),$P16,IF(AND(LEFT($B16,1)="6",$B16<>"6811"),-$P16,0)),0)) -> 0
... A1347: =IF(PNL!A1347="","",PNL!A1347) | B1347: =IF(PNL!B1347="","",PNL!B1347) | C1347: =IF(PNL!C1347="","",PNL!C1347) | D1347: =IF(PNL!D1347="","",PNL!D1347) | E1347: =IF($A1347="","",IF(AND($C1347="2027",OR($D1347="V01",$D1347="V02",$D1347="V03")),1,0)) | F1347: =IF($A1347="","",IF($E1347=1,_xlfn.SUMIFS(Comptabilité!$F$1:$F$1446,Comptabilité!$A$1:$A$1446,$A1347,Comptabilité!$B$1:$B$1446,$B1347,Comptabilité!$C$1:$C$1446,"2026"),0)) | G1347: =IF($A1347="","",IF($D1347="V01",Cadrage!$C$23,IF($D1347="V02",Cadrage!$D$23,Cadrage!$E$23))) | H1347: =IF($A1347="","",IF($D1347="V01",Cadrage!$C$24,IF($D1347="V02",Cadrage!$D$24,Cadrage!$E$24))) | I1347: =IF($A1347="","",IF($D1347="V01",Cadrage!$C$34,IF($D1347="V02",Cadrage!$D$34,Cadrage!$E$34))) | J1347: =IF($A1347="","",IF($D1347="V01",Cadrage!$C$35,IF($D1347="V02",Cadrage!$D$35,Cadrage!$E$35))) | K1347: =IF($A1347="","",IF($D1347="V01",Cadrage!$C$36,IF($D1347="V02",Cadrage!$D$36,Cadrage!$E$36))) | L1347: =IF($A1347="","",IF($D1347="V01",Cadrage!$C$37,IF($D1347="V02",Cadrage!$D$37,Cadrage!$E$37))) | M1347: =IF($A1347="","",IF($D1347="V01",Cadrage!$C$38,IF($D1347="V02",Cadrage!$D$38,Cadrage!$E$38))) | N1347: =IF($A1347="","",IF($D1347="V01",$R$2,IF($D1347="V02",$R$3,$R$4))) | O1347: =IF($A1347="","",IF(OR($B1347="7062",$B1347="706",$B1347="708"),$N1347,IF($B1347="6231",1+$G1347,IF($B1347="6236",1+$H1347,IF(OR($B1347="621",$B1347="604",$B1347="6063"),$N1347*(1-$L1347),IF(OR($B1347="6411",$B1347="6413",$B1347="6414",$B1347="645"),(1+$J1347)*(1+$K1347),IF(OR($B1347="613",$B1347="615",$B1347="616",$B1347="6226",$B1347="625",$B1347="626",$B1347="6281"),(1+$I1347)*(1-$L1347)*(1+$M1347),IF(OR($B1347="6331",$B1347="63511",$B1347="6333"),(1+$I1347)*(1-$L1347),IF($B1347="6811",1+$I1347,1))))))))) | P1347: =IF($A1347="","",IF($E1347=1,$F1347*$O1347,PNL!G1347)) | T1347: =IF($A1347="","",IF($E1347=1,IF(OR($B1347="7062",$B1347="706",$B1347="708"),$P1347,IF(AND(LEFT($B1347,1)="6",$B1347<>"6811"),-$P1347,0)),0))
A1348: =IF(PNL!A1348="","",PNL!A1348) | B1348: =IF(PNL!B1348="","",PNL!B1348) | C1348: =IF(PNL!C1348="","",PNL!C1348) | D1348: =IF(PNL!D1348="","",PNL!D1348) | E1348: =IF($A1348="","",IF(AND($C1348="2027",OR($D1348="V01",$D1348="V02",$D1348="V03")),1,0)) | F1348: =IF($A1348="","",IF($E1348=1,_xlfn.SUMIFS(Comptabilité!$F$1:$F$1446,Comptabilité!$A$1:$A$1446,$A1348,Comptabilité!$B$1:$B$1446,$B1348,Comptabilité!$C$1:$C$1446,"2026"),0)) | G1348: =IF($A1348="","",IF($D1348="V01",Cadrage!$C$23,IF($D1348="V02",Cadrage!$D$23,Cadrage!$E$23))) | H1348: =IF($A1348="","",IF($D1348="V01",Cadrage!$C$24,IF($D1348="V02",Cadrage!$D$24,Cadrage!$E$24))) | I1348: =IF($A1348="","",IF($D1348="V01",Cadrage!$C$34,IF($D1348="V02",Cadrage!$D$34,Cadrage!$E$34))) | J1348: =IF($A1348="","",IF($D1348="V01",Cadrage!$C$35,IF($D1348="V02",Cadrage!$D$35,Cadrage!$E$35))) | K1348: =IF($A1348="","",IF($D1348="V01",Cadrage!$C$36,IF($D1348="V02",Cadrage!$D$36,Cadrage!$E$36))) | L1348: =IF($A1348="","",IF($D1348="V01",Cadrage!$C$37,IF($D1348="V02",Cadrage!$D$37,Cadrage!$E$37))) | M1348: =IF($A1348="","",IF($D1348="V01",Cadrage!$C$38,IF($D1348="V02",Cadrage!$D$38,Cadrage!$E$38))) | N1348: =IF($A1348="","",IF($D1348="V01",$R$2,IF($D1348="V02",$R$3,$R$4))) | O1348: =IF($A1348="","",IF(OR($B1348="7062",$B1348="706",$B1348="708"),$N1348,IF($B1348="6231",1+$G1348,IF($B1348="6236",1+$H1348,IF(OR($B1348="621",$B1348="604",$B1348="6063"),$N1348*(1-$L1348),IF(OR($B1348="6411",$B1348="6413",$B1348="6414",$B1348="645"),(1+$J1348)*(1+$K1348),IF(OR($B1348="613",$B1348="615",$B1348="616",$B1348="6226",$B1348="625",$B1348="626",$B1348="6281"),(1+$I1348)*(1-$L1348)*(1+$M1348),IF(OR($B1348="6331",$B1348="63511",$B1348="6333"),(1+$I1348)*(1-$L1348),IF($B1348="6811",1+$I1348,1))))))))) | P1348: =IF($A1348="","",IF($E1348=1,$F1348*$O1348,PNL!G1348))
A1349: =IF(PNL!A1349="","",PNL!A1349) | B1349: =IF(PNL!B1349="","",PNL!B1349) | C1349: =IF(PNL!C1349="","",PNL!C1349) | D1349: =IF(PNL!D1349="","",PNL!D1349) | E1349: =IF($A1349="","",IF(AND($C1349="2027",OR($D1349="V01",$D1349="V02",$D1349="V03")),1,0)) | F1349: =IF($A1349="","",IF($E1349=1,_xlfn.SUMIFS(Comptabilité!$F$1:$F$1446,Comptabilité!$A$1:$A$1446,$A1349,Comptabilité!$B$1:$B$1446,$B1349,Comptabilité!$C$1:$C$1446,"2026"),0)) | G1349: =IF($A1349="","",IF($D1349="V01",Cadrage!$C$23,IF($D1349="V02",Cadrage!$D$23,Cadrage!$E$23))) | H1349: =IF($A1349="","",IF($D1349="V01",Cadrage!$C$24,IF($D1349="V02",Cadrage!$D$24,Cadrage!$E$24))) | I1349: =IF($A1349="","",IF($D1349="V01",Cadrage!$C$34,IF($D1349="V02",Cadrage!$D$34,Cadrage!$E$34))) | J1349: =IF($A1349="","",IF($D1349="V01",Cadrage!$C$35,IF($D1349="V02",Cadrage!$D$35,Cadrage!$E$35))) | K1349: =IF($A1349="","",IF($D1349="V01",Cadrage!$C$36,IF($D1349="V02",Cadrage!$D$36,Cadrage!$E$36))) | L1349: =IF($A1349="","",IF($D1349="V01",Cadrage!$C$37,IF($D1349="V02",Cadrage!$D$37,Cadrage!$E$37))) | M1349: =IF($A1349="","",IF($D1349="V01",Cadrage!$C$38,IF($D1349="V02",Cadrage!$D$38,Cadrage!$E$38))) | N1349: =IF($A1349="","",IF($D1349="V01",$R$2,IF($D1349="V02",$R$3,$R$4))) | O1349: =IF($A1349="","",IF(OR($B1349="7062",$B1349="706",$B1349="708"),$N1349,IF($B1349="6231",1+$G1349,IF($B1349="6236",1+$H1349,IF(OR($B1349="621",$B1349="604",$B1349="6063"),$N1349*(1-$L1349),IF(OR($B1349="6411",$B1349="6413",$B1349="6414",$B1349="645"),(1+$J1349)*(1+$K1349),IF(OR($B1349="613",$B1349="615",$B1349="616",$B1349="6226",$B1349="625",$B1349="626",$B1349="6281"),(1+$I1349)*(1-$L1349)*(1+$M1349),IF(OR($B1349="6331",$B1349="63511",$B1349="6333"),(1+$I1349)*(1-$L1349),IF($B1349="6811",1+$I1349,1))))))))) | P1349: =IF($A1349="","",IF($E1349=1,$F1349*$O1349,PNL!G1349))
A1350: =IF(PNL!A1350="","",PNL!A1350) | B1350: =IF(PNL!B1350="","",PNL!B1350) | C1350: =IF(PNL!C1350="","",PNL!C1350) | D1350: =IF(PNL!D1350="","",PNL!D1350) | E1350: =IF($A1350="","",IF(AND($C1350="2027",OR($D1350="V01",$D1350="V02",$D1350="V03")),1,0)) | F1350: =IF($A1350="","",IF($E1350=1,_xlfn.SUMIFS(Comptabilité!$F$1:$F$1446,Comptabilité!$A$1:$A$1446,$A1350,Comptabilité!$B$1:$B$1446,$B1350,Comptabilité!$C$1:$C$1446,"2026"),0)) | G1350: =IF($A1350="","",IF($D1350="V01",Cadrage!$C$23,IF($D1350="V02",Cadrage!$D$23,Cadrage!$E$23))) | H1350: =IF($A1350="","",IF($D1350="V01",Cadrage!$C$24,IF($D1350="V02",Cadrage!$D$24,Cadrage!$E$24))) | I1350: =IF($A1350="","",IF($D1350="V01",Cadrage!$C$34,IF($D1350="V02",Cadrage!$D$34,Cadrage!$E$34))) | J1350: =IF($A1350="","",IF($D1350="V01",Cadrage!$C$35,IF($D1350="V02",Cadrage!$D$35,Cadrage!$E$35))) | K1350: =IF($A1350="","",IF($D1350="V01",Cadrage!$C$36,IF($D1350="V02",Cadrage!$D$36,Cadrage!$E$36))) | L1350: =IF($A1350="","",IF($D1350="V01",Cadrage!$C$37,IF($D1350="V02",Cadrage!$D$37,Cadrage!$E$37))) | M1350: =IF($A1350="","",IF($D1350="V01",Cadrage!$C$38,IF($D1350="V02",Cadrage!$D$38,Cadrage!$E$38))) | N1350: =IF($A1350="","",IF($D1350="V01",$R$2,IF($D1350="V02",$R$3,$R$4))) | O1350: =IF($A1350="","",IF(OR($B1350="7062",$B1350="706",$B1350="708"),$N1350,IF($B1350="6231",1+$G1350,IF($B1350="6236",1+$H1350,IF(OR($B1350="621",$B1350="604",$B1350="6063"),$N1350*(1-$L1350),IF(OR($B1350="6411",$B1350="6413",$B1350="6414",$B1350="645"),(1+$J1350)*(1+$K1350),IF(OR($B1350="613",$B1350="615",$B1350="616",$B1350="6226",$B1350="625",$B1350="626",$B1350="6281"),(1+$I1350)*(1-$L1350)*(1+$M1350),IF(OR($B1350="6331",$B1350="63511",$B1350="6333"),(1+$I1350)*(1-$L1350),IF($B1350="6811",1+$I1350,1))))))))) | P1350: =IF($A1350="","",IF($E1350=1,$F1350*$O1350,PNL!G1350))
A1351: =IF(PNL!A1351="","",PNL!A1351) | B1351: =IF(PNL!B1351="","",PNL!B1351) | C1351: =IF(PNL!C1351="","",PNL!C1351) | D1351: =IF(PNL!D1351="","",PNL!D1351) | E1351: =IF($A1351="","",IF(AND($C1351="2027",OR($D1351="V01",$D1351="V02",$D1351="V03")),1,0)) | F1351: =IF($A1351="","",IF($E1351=1,_xlfn.SUMIFS(Comptabilité!$F$1:$F$1446,Comptabilité!$A$1:$A$1446,$A1351,Comptabilité!$B$1:$B$1446,$B1351,Comptabilité!$C$1:$C$1446,"2026"),0)) | G1351: =IF($A1351="","",IF($D1351="V01",Cadrage!$C$23,IF($D1351="V02",Cadrage!$D$23,Cadrage!$E$23))) | H1351: =IF($A1351="","",IF($D1351="V01",Cadrage!$C$24,IF($D1351="V02",Cadrage!$D$24,Cadrage!$E$24))) | I1351: =IF($A1351="","",IF($D1351="V01",Cadrage!$C$34,IF($D1351="V02",Cadrage!$D$34,Cadrage!$E$34))) | J1351: =IF($A1351="","",IF($D1351="V01",Cadrage!$C$35,IF($D1351="V02",Cadrage!$D$35,Cadrage!$E$35))) | K1351: =IF($A1351="","",IF($D1351="V01",Cadrage!$C$36,IF($D1351="V02",Cadrage!$D$36,Cadrage!$E$36))) | L1351: =IF($A1351="","",IF($D1351="V01",Cadrage!$C$37,IF($D1351="V02",Cadrage!$D$37,Cadrage!$E$37))) | M1351: =IF($A1351="","",IF($D1351="V01",Cadrage!$C$38,IF($D1351="V02",Cadrage!$D$38,Cadrage!$E$38))) | N1351: =IF($A1351="","",IF($D1351="V01",$R$2,IF($D1351="V02",$R$3,$R$4))) | O1351: =IF($A1351="","",IF(OR($B1351="7062",$B1351="706",$B1351="708"),$N1351,IF($B1351="6231",1+$G1351,IF($B1351="6236",1+$H1351,IF(OR($B1351="621",$B1351="604",$B1351="6063"),$N1351*(1-$L1351),IF(OR($B1351="6411",$B1351="6413",$B1351="6414",$B1351="645"),(1+$J1351)*(1+$K1351),IF(OR($B1351="613",$B1351="615",$B1351="616",$B1351="6226",$B1351="625",$B1351="626",$B1351="6281"),(1+$I1351)*(1-$L1351)*(1+$M1351),IF(OR($B1351="6331",$B1351="63511",$B1351="6333"),(1+$I1351)*(1-$L1351),IF($B1351="6811",1+$I1351,1))))))))) | P1351: =IF($A1351="","",IF($E1351=1,$F1351*$O1351,PNL!G1351))
A1352: =IF(PNL!A1352="","",PNL!A1352) | B1352: =IF(PNL!B1352="","",PNL!B1352) | C1352: =IF(PNL!C1352="","",PNL!C1352) | D1352: =IF(PNL!D1352="","",PNL!D1352) | E1352: =IF($A1352="","",IF(AND($C1352="2027",OR($D1352="V01",$D1352="V02",$D1352="V03")),1,0)) | F1352: =IF($A1352="","",IF($E1352=1,_xlfn.SUMIFS(Comptabilité!$F$1:$F$1446,Comptabilité!$A$1:$A$1446,$A1352,Comptabilité!$B$1:$B$1446,$B1352,Comptabilité!$C$1:$C$1446,"2026"),0)) | G1352: =IF($A1352="","",IF($D1352="V01",Cadrage!$C$23,IF($D1352="V02",Cadrage!$D$23,Cadrage!$E$23))) | H1352: =IF($A1352="","",IF($D1352="V01",Cadrage!$C$24,IF($D1352="V02",Cadrage!$D$24,Cadrage!$E$24))) | I1352: =IF($A1352="","",IF($D1352="V01",Cadrage!$C$34,IF($D1352="V02",Cadrage!$D$34,Cadrage!$E$34))) | J1352: =IF($A1352="","",IF($D1352="V01",Cadrage!$C$35,IF($D1352="V02",Cadrage!$D$35,Cadrage!$E$35))) | K1352: =IF($A1352="","",IF($D1352="V01",Cadrage!$C$36,IF($D1352="V02",Cadrage!$D$36,Cadrage!$E$36))) | L1352: =IF($A1352="","",IF($D1352="V01",Cadrage!$C$37,IF($D1352="V02",Cadrage!$D$37,Cadrage!$E$37))) | M1352: =IF($A1352="","",IF($D1352="V01",Cadrage!$C$38,IF($D1352="V02",Cadrage!$D$38,Cadrage!$E$38))) | N1352: =IF($A1352="","",IF($D1352="V01",$R$2,IF($D1352="V02",$R$3,$R$4))) | O1352: =IF($A1352="","",IF(OR($B1352="7062",$B1352="706",$B1352="708"),$N1352,IF($B1352="6231",1+$G1352,IF($B1352="6236",1+$H1352,IF(OR($B1352="621",$B1352="604",$B1352="6063"),$N1352*(1-$L1352),IF(OR($B1352="6411",$B1352="6413",$B1352="6414",$B1352="645"),(1+$J1352)*(1+$K1352),IF(OR($B1352="613",$B1352="615",$B1352="616",$B1352="6226",$B1352="625",$B1352="626",$B1352="6281"),(1+$I1352)*(1-$L1352)*(1+$M1352),IF(OR($B1352="6331",$B1352="63511",$B1352="6333"),(1+$I1352)*(1-$L1352),IF($B1352="6811",1+$I1352,1))))))))) | P1352: =IF($A1352="","",IF($E1352=1,$F1352*$O1352,PNL!G1352))
A1353: =IF(PNL!A1353="","",PNL!A1353) | B1353: =IF(PNL!B1353="","",PNL!B1353) | C1353: =IF(PNL!C1353="","",PNL!C1353) | D1353: =IF(PNL!D1353="","",PNL!D1353) | E1353: =IF($A1353="","",IF(AND($C1353="2027",OR($D1353="V01",$D1353="V02",$D1353="V03")),1,0)) | F1353: =IF($A1353="","",IF($E1353=1,_xlfn.SUMIFS(Comptabilité!$F$1:$F$1446,Comptabilité!$A$1:$A$1446,$A1353,Comptabilité!$B$1:$B$1446,$B1353,Comptabilité!$C$1:$C$1446,"2026"),0)) | G1353: =IF($A1353="","",IF($D1353="V01",Cadrage!$C$23,IF($D1353="V02",Cadrage!$D$23,Cadrage!$E$23))) | H1353: =IF($A1353="","",IF($D1353="V01",Cadrage!$C$24,IF($D1353="V02",Cadrage!$D$24,Cadrage!$E$24))) | I1353: =IF($A1353="","",IF($D1353="V01",Cadrage!$C$34,IF($D1353="V02",Cadrage!$D$34,Cadrage!$E$34))) | J1353: =IF($A1353="","",IF($D1353="V01",Cadrage!$C$35,IF($D1353="V02",Cadrage!$D$35,Cadrage!$E$35))) | K1353: =IF($A1353="","",IF($D1353="V01",Cadrage!$C$36,IF($D1353="V02",Cadrage!$D$36,Cadrage!$E$36))) | L1353: =IF($A1353="","",IF($D1353="V01",Cadrage!$C$37,IF($D1353="V02",Cadrage!$D$37,Cadrage!$E$37))) | M1353: =IF($A1353="","",IF($D1353="V01",Cadrage!$C$38,IF($D1353="V02",Cadrage!$D$38,Cadrage!$E$38))) | N1353: =IF($A1353="","",IF($D1353="V01",$R$2,IF($D1353="V02",$R$3,$R$4))) | O1353: =IF($A1353="","",IF(OR($B1353="7062",$B1353="706",$B1353="708"),$N1353,IF($B1353="6231",1+$G1353,IF($B1353="6236",1+$H1353,IF(OR($B1353="621",$B1353="604",$B1353="6063"),$N1353*(1-$L1353),IF(OR($B1353="6411",$B1353="6413",$B1353="6414",$B1353="645"),(1+$J1353)*(1+$K1353),IF(OR($B1353="613",$B1353="615",$B1353="616",$B1353="6226",$B1353="625",$B1353="626",$B1353="6281"),(1+$I1353)*(1-$L1353)*(1+$M1353),IF(OR($B1353="6331",$B1353="63511",$B1353="6333"),(1+$I1353)*(1-$L1353),IF($B1353="6811",1+$I1353,1))))))))) | P1353: =IF($A1353="","",IF($E1353=1,$F1353*$O1353,PNL!G1353))
A1354: =IF(PNL!A1354="","",PNL!A1354) | B1354: =IF(PNL!B1354="","",PNL!B1354) | C1354: =IF(PNL!C1354="","",PNL!C1354) | D1354: =IF(PNL!D1354="","",PNL!D1354) | E1354: =IF($A1354="","",IF(AND($C1354="2027",OR($D1354="V01",$D1354="V02",$D1354="V03")),1,0)) | F1354: =IF($A1354="","",IF($E1354=1,_xlfn.SUMIFS(Comptabilité!$F$1:$F$1446,Comptabilité!$A$1:$A$1446,$A1354,Comptabilité!$B$1:$B$1446,$B1354,Comptabilité!$C$1:$C$1446,"2026"),0)) | G1354: =IF($A1354="","",IF($D1354="V01",Cadrage!$C$23,IF($D1354="V02",Cadrage!$D$23,Cadrage!$E$23))) | H1354: =IF($A1354="","",IF($D1354="V01",Cadrage!$C$24,IF($D1354="V02",Cadrage!$D$24,Cadrage!$E$24))) | I1354: =IF($A1354="","",IF($D1354="V01",Cadrage!$C$34,IF($D1354="V02",Cadrage!$D$34,Cadrage!$E$34))) | J1354: =IF($A1354="","",IF($D1354="V01",Cadrage!$C$35,IF($D1354="V02",Cadrage!$D$35,Cadrage!$E$35))) | K1354: =IF($A1354="","",IF($D1354="V01",Cadrage!$C$36,IF($D1354="V02",Cadrage!$D$36,Cadrage!$E$36))) | L1354: =IF($A1354="","",IF($D1354="V01",Cadrage!$C$37,IF($D1354="V02",Cadrage!$D$37,Cadrage!$E$37))) | M1354: =IF($A1354="","",IF($D1354="V01",Cadrage!$C$38,IF($D1354="V02",Cadrage!$D$38,Cadrage!$E$38))) | N1354: =IF($A1354="","",IF($D1354="V01",$R$2,IF($D1354="V02",$R$3,$R$4))) | O1354: =IF($A1354="","",IF(OR($B1354="7062",$B1354="706",$B1354="708"),$N1354,IF($B1354="6231",1+$G1354,IF($B1354="6236",1+$H1354,IF(OR($B1354="621",$B1354="604",$B1354="6063"),$N1354*(1-$L1354),IF(OR($B1354="6411",$B1354="6413",$B1354="6414",$B1354="645"),(1+$J1354)*(1+$K1354),IF(OR($B1354="613",$B1354="615",$B1354="616",$B1354="6226",$B1354="625",$B1354="626",$B1354="6281"),(1+$I1354)*(1-$L1354)*(1+$M1354),IF(OR($B1354="6331",$B1354="63511",$B1354="6333"),(1+$I1354)*(1-$L1354),IF($B1354="6811",1+$I1354,1))))))))) | P1354: =IF($A1354="","",IF($E1354=1,$F1354*$O1354,PNL!G1354))
A1355: =IF(PNL!A1355="","",PNL!A1355) | B1355: =IF(PNL!B1355="","",PNL!B1355) | C1355: =IF(PNL!C1355="","",PNL!C1355) | D1355: =IF(PNL!D1355="","",PNL!D1355) | E1355: =IF($A1355="","",IF(AND($C1355="2027",OR($D1355="V01",$D1355="V02",$D1355="V03")),1,0)) | F1355: =IF($A1355="","",IF($E1355=1,_xlfn.SUMIFS(Comptabilité!$F$1:$F$1446,Comptabilité!$A$1:$A$1446,$A1355,Comptabilité!$B$1:$B$1446,$B1355,Comptabilité!$C$1:$C$1446,"2026"),0)) | G1355: =IF($A1355="","",IF($D1355="V01",Cadrage!$C$23,IF($D1355="V02",Cadrage!$D$23,Cadrage!$E$23))) | H1355: =IF($A1355="","",IF($D1355="V01",Cadrage!$C$24,IF($D1355="V02",Cadrage!$D$24,Cadrage!$E$24))) | I1355: =IF($A1355="","",IF($D1355="V01",Cadrage!$C$34,IF($D1355="V02",Cadrage!$D$34,Cadrage!$E$34))) | J1355: =IF($A1355="","",IF($D1355="V01",Cadrage!$C$35,IF($D1355="V02",Cadrage!$D$35,Cadrage!$E$35))) | K1355: =IF($A1355="","",IF($D1355="V01",Cadrage!$C$36,IF($D1355="V02",Cadrage!$D$36,Cadrage!$E$36))) | L1355: =IF($A1355="","",IF($D1355="V01",Cadrage!$C$37,IF($D1355="V02",Cadrage!$D$37,Cadrage!$E$37))) | M1355: =IF($A1355="","",IF($D1355="V01",Cadrage!$C$38,IF($D1355="V02",Cadrage!$D$38,Cadrage!$E$38))) | N1355: =IF($A1355="","",IF($D1355="V01",$R$2,IF($D1355="V02",$R$3,$R$4))) | O1355: =IF($A1355="","",IF(OR($B1355="7062",$B1355="706",$B1355="708"),$N1355,IF($B1355="6231",1+$G1355,IF($B1355="6236",1+$H1355,IF(OR($B1355="621",$B1355="604",$B1355="6063"),$N1355*(1-$L1355),IF(OR($B1355="6411",$B1355="6413",$B1355="6414",$B1355="645"),(1+$J1355)*(1+$K1355),IF(OR($B1355="613",$B1355="615",$B1355="616",$B1355="6226",$B1355="625",$B1355="626",$B1355="6281"),(1+$I1355)*(1-$L1355)*(1+$M1355),IF(OR($B1355="6331",$B1355="63511",$B1355="6333"),(1+$I1355)*(1-$L1355),IF($B1355="6811",1+$I1355,1))))))))) | P1355: =IF($A1355="","",IF($E1355=1,$F1355*$O1355,PNL!G1355))
A1356: =IF(PNL!A1356="","",PNL!A1356) | B1356: =IF(PNL!B1356="","",PNL!B1356) | C1356: =IF(PNL!C1356="","",PNL!C1356) | D1356: =IF(PNL!D1356="","",PNL!D1356) | E1356: =IF($A1356="","",IF(AND($C1356="2027",OR($D1356="V01",$D1356="V02",$D1356="V03")),1,0)) | F1356: =IF($A1356="","",IF($E1356=1,_xlfn.SUMIFS(Comptabilité!$F$1:$F$1446,Comptabilité!$A$1:$A$1446,$A1356,Comptabilité!$B$1:$B$1446,$B1356,Comptabilité!$C$1:$C$1446,"2026"),0)) | G1356: =IF($A1356="","",IF($D1356="V01",Cadrage!$C$23,IF($D1356="V02",Cadrage!$D$23,Cadrage!$E$23))) | H1356: =IF($A1356="","",IF($D1356="V01",Cadrage!$C$24,IF($D1356="V02",Cadrage!$D$24,Cadrage!$E$24))) | I1356: =IF($A1356="","",IF($D1356="V01",Cadrage!$C$34,IF($D1356="V02",Cadrage!$D$34,Cadrage!$E$34))) | J1356: =IF($A1356="","",IF($D1356="V01",Cadrage!$C$35,IF($D1356="V02",Cadrage!$D$35,Cadrage!$E$35))) | K1356: =IF($A1356="","",IF($D1356="V01",Cadrage!$C$36,IF($D1356="V02",Cadrage!$D$36,Cadrage!$E$36))) | L1356: =IF($A1356="","",IF($D1356="V01",Cadrage!$C$37,IF($D1356="V02",Cadrage!$D$37,Cadrage!$E$37))) | M1356: =IF($A1356="","",IF($D1356="V01",Cadrage!$C$38,IF($D1356="V02",Cadrage!$D$38,Cadrage!$E$38))) | N1356: =IF($A1356="","",IF($D1356="V01",$R$2,IF($D1356="V02",$R$3,$R$4))) | O1356: =IF($A1356="","",IF(OR($B1356="7062",$B1356="706",$B1356="708"),$N1356,IF($B1356="6231",1+$G1356,IF($B1356="6236",1+$H1356,IF(OR($B1356="621",$B1356="604",$B1356="6063"),$N1356*(1-$L1356),IF(OR($B1356="6411",$B1356="6413",$B1356="6414",$B1356="645"),(1+$J1356)*(1+$K1356),IF(OR($B1356="613",$B1356="615",$B1356="616",$B1356="6226",$B1356="625",$B1356="626",$B1356="6281"),(1+$I1356)*(1-$L1356)*(1+$M1356),IF(OR($B1356="6331",$B1356="63511",$B1356="6333"),(1+$I1356)*(1-$L1356),IF($B1356="6811",1+$I1356,1))))))))) | P1356: =IF($A1356="","",IF($E1356=1,$F1356*$O1356,PNL!G1356))
A1357: =IF(PNL!A1357="","",PNL!A1357) | B1357: =IF(PNL!B1357="","",PNL!B1357) | C1357: =IF(PNL!C1357="","",PNL!C1357) | D1357: =IF(PNL!D1357="","",PNL!D1357) | E1357: =IF($A1357="","",IF(AND($C1357="2027",OR($D1357="V01",$D1357="V02",$D1357="V03")),1,0)) | F1357: =IF($A1357="","",IF($E1357=1,_xlfn.SUMIFS(Comptabilité!$F$1:$F$1446,Comptabilité!$A$1:$A$1446,$A1357,Comptabilité!$B$1:$B$1446,$B1357,Comptabilité!$C$1:$C$1446,"2026"),0)) | G1357: =IF($A1357="","",IF($D1357="V01",Cadrage!$C$23,IF($D1357="V02",Cadrage!$D$23,Cadrage!$E$23))) | H1357: =IF($A1357="","",IF($D1357="V01",Cadrage!$C$24,IF($D1357="V02",Cadrage!$D$24,Cadrage!$E$24))) | I1357: =IF($A1357="","",IF($D1357="V01",Cadrage!$C$34,IF($D1357="V02",Cadrage!$D$34,Cadrage!$E$34))) | J1357: =IF($A1357="","",IF($D1357="V01",Cadrage!$C$35,IF($D1357="V02",Cadrage!$D$35,Cadrage!$E$35))) | K1357: =IF($A1357="","",IF($D1357="V01",Cadrage!$C$36,IF($D1357="V02",Cadrage!$D$36,Cadrage!$E$36))) | L1357: =IF($A1357="","",IF($D1357="V01",Cadrage!$C$37,IF($D1357="V02",Cadrage!$D$37,Cadrage!$E$37))) | M1357: =IF($A1357="","",IF($D1357="V01",Cadrage!$C$38,IF($D1357="V02",Cadrage!$D$38,Cadrage!$E$38))) | N1357: =IF($A1357="","",IF($D1357="V01",$R$2,IF($D1357="V02",$R$3,$R$4))) | O1357: =IF($A1357="","",IF(OR($B1357="7062",$B1357="706",$B1357="708"),$N1357,IF($B1357="6231",1+$G1357,IF($B1357="6236",1+$H1357,IF(OR($B1357="621",$B1357="604",$B1357="6063"),$N1357*(1-$L1357),IF(OR($B1357="6411",$B1357="6413",$B1357="6414",$B1357="645"),(1+$J1357)*(1+$K1357),IF(OR($B1357="613",$B1357="615",$B1357="616",$B1357="6226",$B1357="625",$B1357="626",$B1357="6281"),(1+$I1357)*(1-$L1357)*(1+$M1357),IF(OR($B1357="6331",$B1357="63511",$B1357="6333"),(1+$I1357)*(1-$L1357),IF($B1357="6811",1+$I1357,1))))))))) | P1357: =IF($A1357="","",IF($E1357=1,$F1357*$O1357,PNL!G1357))
A1358: =IF(PNL!A1358="","",PNL!A1358) | B1358: =IF(PNL!B1358="","",PNL!B1358) | C1358: =IF(PNL!C1358="","",PNL!C1358) | D1358: =IF(PNL!D1358="","",PNL!D1358) | E1358: =IF($A1358="","",IF(AND($C1358="2027",OR($D1358="V01",$D1358="V02",$D1358="V03")),1,0)) | F1358: =IF($A1358="","",IF($E1358=1,_xlfn.SUMIFS(Comptabilité!$F$1:$F$1446,Comptabilité!$A$1:$A$1446,$A1358,Comptabilité!$B$1:$B$1446,$B1358,Comptabilité!$C$1:$C$1446,"2026"),0)) | G1358: =IF($A1358="","",IF($D1358="V01",Cadrage!$C$23,IF($D1358="V02",Cadrage!$D$23,Cadrage!$E$23))) | H1358: =IF($A1358="","",IF($D1358="V01",Cadrage!$C$24,IF($D1358="V02",Cadrage!$D$24,Cadrage!$E$24))) | I1358: =IF($A1358="","",IF($D1358="V01",Cadrage!$C$34,IF($D1358="V02",Cadrage!$D$34,Cadrage!$E$34))) | J1358: =IF($A1358="","",IF($D1358="V01",Cadrage!$C$35,IF($D1358="V02",Cadrage!$D$35,Cadrage!$E$35))) | K1358: =IF($A1358="","",IF($D1358="V01",Cadrage!$C$36,IF($D1358="V02",Cadrage!$D$36,Cadrage!$E$36))) | L1358: =IF($A1358="","",IF($D1358="V01",Cadrage!$C$37,IF($D1358="V02",Cadrage!$D$37,Cadrage!$E$37))) | M1358: =IF($A1358="","",IF($D1358="V01",Cadrage!$C$38,IF($D1358="V02",Cadrage!$D$38,Cadrage!$E$38))) | N1358: =IF($A1358="","",IF($D1358="V01",$R$2,IF($D1358="V02",$R$3,$R$4))) | O1358: =IF($A1358="","",IF(OR($B1358="7062",$B1358="706",$B1358="708"),$N1358,IF($B1358="6231",1+$G1358,IF($B1358="6236",1+$H1358,IF(OR($B1358="621",$B1358="604",$B1358="6063"),$N1358*(1-$L1358),IF(OR($B1358="6411",$B1358="6413",$B1358="6414",$B1358="645"),(1+$J1358)*(1+$K1358),IF(OR($B1358="613",$B1358="615",$B1358="616",$B1358="6226",$B1358="625",$B1358="626",$B1358="6281"),(1+$I1358)*(1-$L1358)*(1+$M1358),IF(OR($B1358="6331",$B1358="63511",$B1358="6333"),(1+$I1358)*(1-$L1358),IF($B1358="6811",1+$I1358,1))))))))) | P1358: =IF($A1358="","",IF($E1358=1,$F1358*$O1358,PNL!G1358))
A1359: =IF(PNL!A1359="","",PNL!A1359) | B1359: =IF(PNL!B1359="","",PNL!B1359) | C1359: =IF(PNL!C1359="","",PNL!C1359) | D1359: =IF(PNL!D1359="","",PNL!D1359) | E1359: =IF($A1359="","",IF(AND($C1359="2027",OR($D1359="V01",$D1359="V02",$D1359="V03")),1,0)) | F1359: =IF($A1359="","",IF($E1359=1,_xlfn.SUMIFS(Comptabilité!$F$1:$F$1446,Comptabilité!$A$1:$A$1446,$A1359,Comptabilité!$B$1:$B$1446,$B1359,Comptabilité!$C$1:$C$1446,"2026"),0)) | G1359: =IF($A1359="","",IF($D1359="V01",Cadrage!$C$23,IF($D1359="V02",Cadrage!$D$23,Cadrage!$E$23))) | H1359: =IF($A1359="","",IF($D1359="V01",Cadrage!$C$24,IF($D1359="V02",Cadrage!$D$24,Cadrage!$E$24))) | I1359: =IF($A1359="","",IF($D1359="V01",Cadrage!$C$34,IF($D1359="V02",Cadrage!$D$34,Cadrage!$E$34))) | J1359: =IF($A1359="","",IF($D1359="V01",Cadrage!$C$35,IF($D1359="V02",Cadrage!$D$35,Cadrage!$E$35))) | K1359: =IF($A1359="","",IF($D1359="V01",Cadrage!$C$36,IF($D1359="V02",Cadrage!$D$36,Cadrage!$E$36))) | L1359: =IF($A1359="","",IF($D1359="V01",Cadrage!$C$37,IF($D1359="V02",Cadrage!$D$37,Cadrage!$E$37))) | M1359: =IF($A1359="","",IF($D1359="V01",Cadrage!$C$38,IF($D1359="V02",Cadrage!$D$38,Cadrage!$E$38))) | N1359: =IF($A1359="","",IF($D1359="V01",$R$2,IF($D1359="V02",$R$3,$R$4))) | O1359: =IF($A1359="","",IF(OR($B1359="7062",$B1359="706",$B1359="708"),$N1359,IF($B1359="6231",1+$G1359,IF($B1359="6236",1+$H1359,IF(OR($B1359="621",$B1359="604",$B1359="6063"),$N1359*(1-$L1359),IF(OR($B1359="6411",$B1359="6413",$B1359="6414",$B1359="645"),(1+$J1359)*(1+$K1359),IF(OR($B1359="613",$B1359="615",$B1359="616",$B1359="6226",$B1359="625",$B1359="626",$B1359="6281"),(1+$I1359)*(1-$L1359)*(1+$M1359),IF(OR($B1359="6331",$B1359="63511",$B1359="6333"),(1+$I1359)*(1-$L1359),IF($B1359="6811",1+$I1359,1))))))))) | P1359: =IF($A1359="","",IF($E1359=1,$F1359*$O1359,PNL!G1359))
... A1435: =IF(PNL!A1435="","",PNL!A1435) | B1435: =IF(PNL!B1435="","",PNL!B1435) | C1435: =IF(PNL!C1435="","",PNL!C1435) | D1435: =IF(PNL!D1435="","",PNL!D1435) | E1435: =IF($A1435="","",IF(AND($C1435="2027",OR($D1435="V01",$D1435="V02",$D1435="V03")),1,0)) | F1435: =IF($A1435="","",IF($E1435=1,_xlfn.SUMIFS(Comptabilité!$F$1:$F$1446,Comptabilité!$A$1:$A$1446,$A1435,Comptabilité!$B$1:$B$1446,$B1435,Comptabilité!$C$1:$C$1446,"2026"),0)) | G1435: =IF($A1435="","",IF($D1435="V01",Cadrage!$C$23,IF($D1435="V02",Cadrage!$D$23,Cadrage!$E$23))) | H1435: =IF($A1435="","",IF($D1435="V01",Cadrage!$C$24,IF($D1435="V02",Cadrage!$D$24,Cadrage!$E$24))) | I1435: =IF($A1435="","",IF($D1435="V01",Cadrage!$C$34,IF($D1435="V02",Cadrage!$D$34,Cadrage!$E$34))) | J1435: =IF($A1435="","",IF($D1435="V01",Cadrage!$C$35,IF($D1435="V02",Cadrage!$D$35,Cadrage!$E$35))) | K1435: =IF($A1435="","",IF($D1435="V01",Cadrage!$C$36,IF($D1435="V02",Cadrage!$D$36,Cadrage!$E$36))) | L1435: =IF($A1435="","",IF($D1435="V01",Cadrage!$C$37,IF($D1435="V02",Cadrage!$D$37,Cadrage!$E$37))) | M1435: =IF($A1435="","",IF($D1435="V01",Cadrage!$C$38,IF($D1435="V02",Cadrage!$D$38,Cadrage!$E$38))) | N1435: =IF($A1435="","",IF($D1435="V01",$R$2,IF($D1435="V02",$R$3,$R$4))) | O1435: =IF($A1435="","",IF(OR($B1435="7062",$B1435="706",$B1435="708"),$N1435,IF($B1435="6231",1+$G1435,IF($B1435="6236",1+$H1435,IF(OR($B1435="621",$B1435="604",$B1435="6063"),$N1435*(1-$L1435),IF(OR($B1435="6411",$B1435="6413",$B1435="6414",$B1435="645"),(1+$J1435)*(1+$K1435),IF(OR($B1435="613",$B1435="615",$B1435="616",$B1435="6226",$B1435="625",$B1435="626",$B1435="6281"),(1+$I1435)*(1-$L1435)*(1+$M1435),IF(OR($B1435="6331",$B1435="63511",$B1435="6333"),(1+$I1435)*(1-$L1435),IF($B1435="6811",1+$I1435,1))))))))) | P1435: =IF($A1435="","",IF($E1435=1,$F1435*$O1435,PNL!G1435))
