Workbook

Sheet Données
A1: ① SOCLE DE DONNÉES — 14 campus × 5 marques · la seule saisie du classeur
A3: ① PÉRIMÈTRE (les filtres du cockpit)
A4: Filtre | B4: Valeur
A5: Scénario | B5: REEL
A6: Version | B6: V_FINAL
A7: Exercice | B7: 2026
A8: Période | B8: 12 — Cumul
A9: Marque | B9: Toutes
A10: Campus | B10: Tous
A11: Modalité | B11: Toutes
A13: ② SOCLE CAMPUS (source : V_COCKPIT / V_ALLOCATION, grain campus × exercice)
A14: Entity | B14: Marque | C14: CA 2024 | D14: CA 2025 | E14: CA 2026 | F14: EBITDA 2024 | G14: EBITDA 2025 | H14: EBITDA 2026 | I14: Inscrits 26 | J14: Effectifs 26 | K14: Places 26 | L14: Mix alt. 26
A15: MBWAY_BOR | B15: MBway | C15: 1537990 | D15: 1656282 | E15: 1784942 | F15: 237542 | G15: 268273 | H15: 307544 | I15: 102 | J15: 251 | K15: 296 | L15: 0.7959
A16: MBWAY_LYO | B16: MBway | C16: 2154491 | D16: 2320201 | E16: 2500434 | F16: 354945 | G16: 399596 | H16: 456436 | I16: 132 | J16: 324 | K16: 412 | L16: 0.7959
A17: MBWAY_NAN | B17: MBway | C17: 1865360 | D17: 2008832 | E17: 2164878 | F17: 299628 | G17: 337733 | H17: 386312 | I17: 120 | J17: 295 | K17: 348 | L17: 0.7959
A18: MBWAY_PAR | B18: MBway | C18: 2715965 | D18: 2924860 | E18: 3152062 | F18: 469817 | G18: 527720 | H18: 601217 | I18: 157 | J18: 383 | K18: 470 | L18: 0.7959
A19: ISCOM_LIL | B19: ISCOM | C19: 1627556 | D19: 1687214 | E19: 1750304 | F19: 246201 | G19: 272204 | H19: 288015 | I19: 99 | J19: 243 | K19: 296 | L19: 0.7959
A20: ISCOM_PAR | B20: ISCOM | C20: 2686759 | D20: 2785243 | E20: 2889390 | F20: 450936 | G20: 495292 | H20: 523028 | I20: 143 | J20: 352 | K20: 444 | L20: 0.7959
A21: ISCOM_TLS | B21: ISCOM | C21: 1505766 | D21: 1560960 | E21: 1619329 | F21: 224660 | G21: 248616 | H21: 263130 | I21: 94 | J21: 230 | K21: 296 | L21: 0.7959
A22: IPAC_MTP | B22: Ipac | C22: 650230 | D22: 713330 | E22: 783111 | F22: 74568 | G22: 90342 | H22: 108000 | I22: 40 | J22: 117 | K22: 192 | L22: 1
A23: IPAC_NAN | B23: Ipac | C23: 855566 | D23: 938593 | E23: 1030409 | F23: 105663 | G23: 127069 | H23: 151056 | I23: 50 | J23: 147 | K23: 192 | L23: 1
A24: IPAC_REN | B24: Ipac | C24: 650230 | D24: 713330 | E24: 783111 | F24: 74568 | G24: 90342 | H24: 108000 | I24: 40 | J24: 117 | K24: 192 | L24: 1
A25: PIGIER_BOR | B25: Pigier | C25: 1027213 | D25: 1075204 | E25: 1126238 | F25: 196141 | G25: 212061 | H25: 231329 | I25: 72 | J25: 175 | K25: 312 | L25: 1
A26: PIGIER_LYO | B26: Pigier | C26: 1438970 | D26: 1506199 | E26: 1577690 | F26: 289961 | G26: 312883 | H26: 340591 | I26: 93 | J26: 227 | K26: 312 | L26: 1
... A28: TUNON_PAR | B28: Tunon | C28: 1024236 | D28: 1051471 | E28: 1080198 | F28: 65804 | G28: 60619 | H28: 48547 | I28: 47 | J28: 137 | K28: 192 | L28: 1
A29: TOTAL GROUPE | C29: =SUM(C15:C28) | D29: =SUM(D15:D28) | E29: =SUM(E15:E28) | F29: =SUM(F15:F28) | G29: =SUM(G15:G28) | H29: =SUM(H15:H28) | I29: =SUM(I15:I28) | J29: =SUM(J15:J28) | K29: =SUM(K15:K28)
A30: ③ ACQUISITION (groupe)
A31: Mesure | B31: 2024 | C31: 2025 | D31: 2026
A32: Dépenses d'acquisition (€) | B32: 358170 | C32: 394702 | D32: 434174
A33: Inscrits (nouveaux) | B33: 1092 | C33: 1159 | D33: 1229
A34: ④ BRIDGE EBITDA GROUPE 2025 → 2026 (l'effet coûts est le résidu : le pont boucle toujours)
A35: Étape | B35: Montant (€)
A37: EBITDA 2025 | B37: =SUM($G$15:$G$28)
A38: Effet activité | B38: 211706
A39: Effet prix / mix | B39: 289000
A40: Effet coûts (résidu) | B40: =B41-B37-B38-B39
A41: EBITDA 2026 | B41: =SUM($H$15:$H$28)
A43: ⑤ AGRÉGATS PAR MARQUE — 100 % calculés depuis ②
A44: Marque | B44: CA 2024 | C44: CA 2025 | D44: CA 2026 | E44: EBITDA 2024 | F44: EBITDA 2025 | G44: EBITDA 2026 | H44: Marge 2024 | I44: Marge 2025 | J44: Marge 2026
A46: MBway | B46: =SUMIF(Données!$B$15:$B$28,$A46,Données!$C$15:$C$28) | C46: =SUMIF(Données!$B$15:$B$28,$A46,Données!$D$15:$D$28) | D46: =SUMIF(Données!$B$15:$B$28,$A46,Données!$E$15:$E$28) | E46: =SUMIF(Données!$B$15:$B$28,$A46,Données!$F$15:$F$28) | F46: =SUMIF(Données!$B$15:$B$28,$A46,Données!$G$15:$G$28) | G46: =SUMIF(Données!$B$15:$B$28,$A46,Données!$H$15:$H$28) | H46: =E46/B46 | I46: =F46/C46 | J46: =G46/D46
A47: ISCOM | B47: =SUMIF(Données!$B$15:$B$28,$A47,Données!$C$15:$C$28) | C47: =SUMIF(Données!$B$15:$B$28,$A47,Données!$D$15:$D$28) | D47: =SUMIF(Données!$B$15:$B$28,$A47,Données!$E$15:$E$28) | E47: =SUMIF(Données!$B$15:$B$28,$A47,Données!$F$15:$F$28) | F47: =SUMIF(Données!$B$15:$B$28,$A47,Données!$G$15:$G$28) | G47: =SUMIF(Données!$B$15:$B$28,$A47,Données!$H$15:$H$28) | H47: =E47/B47 | I47: =F47/C47 | J47: =G47/D47
A48: Ipac | B48: =SUMIF(Données!$B$15:$B$28,$A48,Données!$C$15:$C$28) | C48: =SUMIF(Données!$B$15:$B$28,$A48,Données!$D$15:$D$28) | D48: =SUMIF(Données!$B$15:$B$28,$A48,Données!$E$15:$E$28) | E48: =SUMIF(Données!$B$15:$B$28,$A48,Données!$F$15:$F$28) | F48: =SUMIF(Données!$B$15:$B$28,$A48,Données!$G$15:$G$28) | G48: =SUMIF(Données!$B$15:$B$28,$A48,Données!$H$15:$H$28) | H48: =E48/B48 | I48: =F48/C48 | J48: =G48/D48
A49: Pigier | B49: =SUMIF(Données!$B$15:$B$28,$A49,Données!$C$15:$C$28) | C49: =SUMIF(Données!$B$15:$B$28,$A49,Données!$D$15:$D$28) | D49: =SUMIF(Données!$B$15:$B$28,$A49,Données!$E$15:$E$28) | E49: =SUMIF(Données!$B$15:$B$28,$A49,Données!$F$15:$F$28) | F49: =SUMIF(Données!$B$15:$B$28,$A49,Données!$G$15:$G$28) | G49: =SUMIF(Données!$B$15:$B$28,$A49,Données!$H$15:$H$28) | H49: =E49/B49 | I49: =F49/C49 | J49: =G49/D49
A50: Tunon | B50: =SUMIF(Données!$B$15:$B$28,$A50,Données!$C$15:$C$28) | C50: =SUMIF(Données!$B$15:$B$28,$A50,Données!$D$15:$D$28) | D50: =SUMIF(Données!$B$15:$B$28,$A50,Données!$E$15:$E$28) | E50: =SUMIF(Données!$B$15:$B$28,$A50,Données!$F$15:$F$28) | F50: =SUMIF(Données!$B$15:$B$28,$A50,Données!$G$15:$G$28) | G50: =SUMIF(Données!$B$15:$B$28,$A50,Données!$H$15:$H$28) | H50: =E50/B50 | I50: =F50/C50 | J50: =G50/D50
A52: ⑥ ZONE TECHNIQUE — séries des graphes (ne pas saisir)
A53: Étape (waterfall) | B53: Socle | C53: Ancre | D53: Hausse | E53: Baisse
A54: EBITDA 2025 | B54: 0 | C54: =B37 | D54: 0 | E54: 0
A55: Activité | B55: =B37 | C55: 0 | D55: =B38 | E55: 0
A56: Prix / mix | B56: =B37+B38 | C56: 0 | D56: =B39 | E56: 0
A57: Coûts | B57: =B41 | C57: 0 | D57: 0 | E57: =B37+B38+B39-B41
A58: EBITDA 2026 | B58: 0 | C58: =B41 | D58: 0 | E58: 0
A61: Exercice | B61: Dépenses (base 100) | C61: Inscrits (base 100)
A62: 2024 | B62: =B32/$B$32*100 | C62: =B33/$B$33*100
A63: 2025 | B63: =C32/$B$32*100 | C63: =C33/$B$33*100
A64: 2026 | B64: =D32/$B$32*100 | C64: =D33/$B$33*100

Sheet Données drill
A1: ② DONNÉES DU DRILL — grain COHORTE-CLASSE (V_ALLOCATION / V_CAMPUS_CLASSE)
A3: Une ligne = une cohorte-classe. Tout remonte exactement au socle campus de l'onglet ①.
A4: Marque | B4: Campus | C4: Programme | D4: Année | E4: Modalité | F4: Nb cl. | G4: Capa. | H4: Places | I4: Effectif 26 | J4: Effectif 25 | K4: CA 2025 | L4: CA 2026 | M4: Coût var. 25 | N4: Coût var. 26 | O4: Coût dir. 25 | P4: Coût dir. 26 | Q4: Coût siège | R4: EBITDA 2025 | S4: EBITDA 2026 | T4: Contribution | U4: Coût complet | V4: Marge complète | W4: Inclus | X4: Rang | Z4: — membres — | AH4: Marque | AI4: Campus | AJ4: Programme | AK4: Année d'étude | AL4: Modalité
A5: MBway | B5: MBWAY_BOR | C5: BAC_MGT | D5: B1 | E5: INIT | F5: 2 | G5: 32 | H5: =F5*G5 | I5: 51 | J5: 48 | K5: 347043 | L5: 374001 | M5: 16961 | N5: 18571 | O5: 275831 | P5: 293058 | Q5: 20536 | R5: =K5-M5-O5 | S5: =L5-N5-P5 | T5: =L5-N5 | U5: =N5+P5+Q5 | V5: =L5-U5 | W5: =IF(AND(OR(Drill!$C$6="(Tous)",$A5=Drill!$C$6),OR(Drill!$D$6="(Tous)",$B5=Drill!$D$6),OR(Drill!$E$6="(Tous)",$C5=Drill!$E$6),OR(Drill!$F$6="(Tous)",$D5=Drill!$F$6),OR(Drill!$G$6="(Tous)",$E5=Drill!$G$6)),1,0) | X5: =IF(W5=1,SUM($W$5:W5),"") | Z5: MBway | AA5: MBWAY_BOR | AB5: BAC_CCE | AC5: 1 | AD5: ALT | AF5: Marque | AH5: (Tous) | AI5: (Tous) | AJ5: (Tous) | AK5: (Tous) | AL5: (Tous)
A6: MBway | B6: MBWAY_BOR | C6: BAC_MGT | D6: B2 | E6: ALT | F6: 2 | G6: 32 | H6: =F6*G6 | I6: 50 | J6: 47 | K6: 314189 | L6: 338596 | M6: 16452 | N6: 18014 | O6: 275831 | P6: 293058 | Q6: 19920 | R6: =K6-M6-O6 | S6: =L6-N6-P6 | T6: =L6-N6 | U6: =N6+P6+Q6 | V6: =L6-U6 | W6: =IF(AND(OR(Drill!$C$6="(Tous)",$A6=Drill!$C$6),OR(Drill!$D$6="(Tous)",$B6=Drill!$D$6),OR(Drill!$E$6="(Tous)",$C6=Drill!$E$6),OR(Drill!$F$6="(Tous)",$D6=Drill!$F$6),OR(Drill!$G$6="(Tous)",$E6=Drill!$G$6)),1,0) | X6: =IF(W6=1,SUM($W$5:W6),"") | Z6: ISCOM | AA6: MBWAY_LYO | AB6: BAC_COM | AC6: 2 | AD6: INIT | AF6: Campus | AH6: MBway | AI6: MBWAY_BOR | AJ6: BAC_CCE | AK6: 1 | AL6: ALT
A7: MBway | B7: MBWAY_BOR | C7: BAC_MGT | D7: B3 | E7: ALT | F7: 2 | G7: 32 | H7: =F7*G7 | I7: 49 | J7: 46 | K7: 307906 | L7: 331824 | M7: 16123 | N7: 17654 | O7: 275831 | P7: 293058 | Q7: 19522 | R7: =K7-M7-O7 | S7: =L7-N7-P7 | T7: =L7-N7 | U7: =N7+P7+Q7 | V7: =L7-U7 | W7: =IF(AND(OR(Drill!$C$6="(Tous)",$A7=Drill!$C$6),OR(Drill!$D$6="(Tous)",$B7=Drill!$D$6),OR(Drill!$E$6="(Tous)",$C7=Drill!$E$6),OR(Drill!$F$6="(Tous)",$D7=Drill!$F$6),OR(Drill!$G$6="(Tous)",$E7=Drill!$G$6)),1,0) | X7: =IF(W7=1,SUM($W$5:W7),"") | Z7: Ipac | AA7: MBWAY_NAN | AB7: BAC_MGT | AC7: B1 | AF7: Programme | AH7: ISCOM | AI7: MBWAY_LYO | AJ7: BAC_COM | AK7: 2 | AL7: INIT
A8: MBway | B8: MBWAY_BOR | C8: MAS_MGT | D8: M1 | E8: ALT | F8: 2 | G8: 26 | H8: =F8*G8 | I8: 51 | J8: 48 | K8: 347043 | L8: 374001 | M8: 16961 | N8: 18571 | O8: 238700 | P8: 253608 | Q8: 20536 | R8: =K8-M8-O8 | S8: =L8-N8-P8 | T8: =L8-N8 | U8: =N8+P8+Q8 | V8: =L8-U8 | W8: =IF(AND(OR(Drill!$C$6="(Tous)",$A8=Drill!$C$6),OR(Drill!$D$6="(Tous)",$B8=Drill!$D$6),OR(Drill!$E$6="(Tous)",$C8=Drill!$E$6),OR(Drill!$F$6="(Tous)",$D8=Drill!$F$6),OR(Drill!$G$6="(Tous)",$E8=Drill!$G$6)),1,0) | X8: =IF(W8=1,SUM($W$5:W8),"") | Z8: Pigier | AA8: MBWAY_PAR | AB8: BAC_RH | AC8: B2 | AF8: Année d'étude | AH8: Ipac | AI8: MBWAY_NAN | AJ8: BAC_MGT | AK8: B1
A9: MBway | B9: MBWAY_BOR | C9: MAS_MGT | D9: M2 | E9: ALT | F9: 2 | G9: 26 | H9: =F9*G9 | I9: 50 | J9: 47 | K9: 340102 | L9: 366521 | M9: 16622 | N9: 18200 | O9: 238700 | P9: 253608 | Q9: 20125 | R9: =K9-M9-O9 | S9: =L9-N9-P9 | T9: =L9-N9 | U9: =N9+P9+Q9 | V9: =L9-U9 | W9: =IF(AND(OR(Drill!$C$6="(Tous)",$A9=Drill!$C$6),OR(Drill!$D$6="(Tous)",$B9=Drill!$D$6),OR(Drill!$E$6="(Tous)",$C9=Drill!$E$6),OR(Drill!$F$6="(Tous)",$D9=Drill!$F$6),OR(Drill!$G$6="(Tous)",$E9=Drill!$G$6)),1,0) | X9: =IF(W9=1,SUM($W$5:W9),"") | Z9: Tunon | AA9: ISCOM_LIL | AB9: BAC_TOU | AC9: B3 | AF9: Modalité | AH9: Pigier | AI9: MBWAY_PAR | AJ9: BAC_RH | AK9: B2
A10: MBway | B10: MBWAY_LYO | C10: BAC_MGT | D10: B1 | E10: INIT | F10: 3 | G10: 32 | H10: =F10*G10 | I10: 66 | J10: 62 | K10: 486154 | L10: 523919 | M10: 21949 | N10: 24033 | O10: 412295 | P10: 438033 | Q10: 26576 | R10: =K10-M10-O10 | S10: =L10-N10-P10 | T10: =L10-N10 | U10: =N10+P10+Q10 | V10: =L10-U10 | W10: =IF(AND(OR(Drill!$C$6="(Tous)",$A10=Drill!$C$6),OR(Drill!$D$6="(Tous)",$B10=Drill!$D$6),OR(Drill!$E$6="(Tous)",$C10=Drill!$E$6),OR(Drill!$F$6="(Tous)",$D10=Drill!$F$6),OR(Drill!$G$6="(Tous)",$E10=Drill!$G$6)),1,0) | X10: =IF(W10=1,SUM($W$5:W10),"") | AA10: ISCOM_PAR | AB10: BTS_GES | AC10: M1 | AH10: Tunon | AI10: ISCOM_LIL | AJ10: BAC_TOU | AK10: B3
A11: MBway | B11: MBWAY_LYO | C11: BAC_MGT | D11: B2 | E11: ALT | F11: 3 | G11: 32 | H11: =F11*G11 | I11: 64 | J11: 60 | K11: 440132 | L11: 474321 | M11: 21291 | N11: 23312 | O11: 412295 | P11: 438033 | Q11: 25779 | R11: =K11-M11-O11 | S11: =L11-N11-P11 | T11: =L11-N11 | U11: =N11+P11+Q11 | V11: =L11-U11 | W11: =IF(AND(OR(Drill!$C$6="(Tous)",$A11=Drill!$C$6),OR(Drill!$D$6="(Tous)",$B11=Drill!$D$6),OR(Drill!$E$6="(Tous)",$C11=Drill!$E$6),OR(Drill!$F$6="(Tous)",$D11=Drill!$F$6),OR(Drill!$G$6="(Tous)",$E11=Drill!$G$6)),1,0) | X11: =IF(W11=1,SUM($W$5:W11),"") | AA11: ISCOM_TLS | AB11: MAS_COM | AC11: M2 | AI11: ISCOM_PAR | AJ11: BTS_GES | AK11: M1
A12: MBway | B12: MBWAY_LYO | C12: BAC_MGT | D12: B3 | E12: ALT | F12: 2 | G12: 32 | H12: =F12*G12 | I12: 63 | J12: 59 | K12: 431329 | L12: 464835 | M12: 20865 | N12: 22846 | O12: 274863 | P12: 292022 | Q12: 25263 | R12: =K12-M12-O12 | S12: =L12-N12-P12 | T12: =L12-N12 | U12: =N12+P12+Q12 | V12: =L12-U12 | W12: =IF(AND(OR(Drill!$C$6="(Tous)",$A12=Drill!$C$6),OR(Drill!$D$6="(Tous)",$B12=Drill!$D$6),OR(Drill!$E$6="(Tous)",$C12=Drill!$E$6),OR(Drill!$F$6="(Tous)",$D12=Drill!$F$6),OR(Drill!$G$6="(Tous)",$E12=Drill!$G$6)),1,0) | X12: =IF(W12=1,SUM($W$5:W12),"") | AA12: IPAC_MTP | AB12: MAS_MGT | AI12: ISCOM_TLS | AJ12: MAS_COM | AK12: M2
A13: MBway | B13: MBWAY_LYO | C13: MAS_MGT | D13: M1 | E13: ALT | F13: 3 | G13: 26 | H13: =F13*G13 | I13: 66 | J13: 62 | K13: 486154 | L13: 523919 | M13: 21949 | N13: 24033 | O13: 356794 | P13: 379067 | Q13: 26576 | R13: =K13-M13-O13 | S13: =L13-N13-P13 | T13: =L13-N13 | U13: =N13+P13+Q13 | V13: =L13-U13 | W13: =IF(AND(OR(Drill!$C$6="(Tous)",$A13=Drill!$C$6),OR(Drill!$D$6="(Tous)",$B13=Drill!$D$6),OR(Drill!$E$6="(Tous)",$C13=Drill!$E$6),OR(Drill!$F$6="(Tous)",$D13=Drill!$F$6),OR(Drill!$G$6="(Tous)",$E13=Drill!$G$6)),1,0) | X13: =IF(W13=1,SUM($W$5:W13),"") | AA13: IPAC_NAN | AI13: IPAC_MTP | AJ13: MAS_MGT
A14: MBway | B14: MBWAY_LYO | C14: MAS_MGT | D14: M2 | E14: ALT | F14: 3 | G14: 26 | H14: =F14*G14 | I14: 65 | J14: 61 | K14: 476431 | L14: 513440 | M14: 21510 | N14: 23552 | O14: 356794 | P14: 379067 | Q14: 26045 | R14: =K14-M14-O14 | S14: =L14-N14-P14 | T14: =L14-N14 | U14: =N14+P14+Q14 | V14: =L14-U14 | W14: =IF(AND(OR(Drill!$C$6="(Tous)",$A14=Drill!$C$6),OR(Drill!$D$6="(Tous)",$B14=Drill!$D$6),OR(Drill!$E$6="(Tous)",$C14=Drill!$E$6),OR(Drill!$F$6="(Tous)",$D14=Drill!$F$6),OR(Drill!$G$6="(Tous)",$E14=Drill!$G$6)),1,0) | X14: =IF(W14=1,SUM($W$5:W14),"") | AA14: IPAC_REN | AI14: IPAC_NAN
A15: MBway | B15: MBWAY_NAN | C15: BAC_MGT | D15: B1 | E15: INIT | F15: 2 | G15: 32 | H15: =F15*G15 | I15: 60 | J15: 57 | K15: 420913 | L15: 453609 | M15: 19954 | N15: 21848 | O15: 281142 | P15: 298687 | Q15: 24160 | R15: =K15-M15-O15 | S15: =L15-N15-P15 | T15: =L15-N15 | U15: =N15+P15+Q15 | V15: =L15-U15 | W15: =IF(AND(OR(Drill!$C$6="(Tous)",$A15=Drill!$C$6),OR(Drill!$D$6="(Tous)",$B15=Drill!$D$6),OR(Drill!$E$6="(Tous)",$C15=Drill!$E$6),OR(Drill!$F$6="(Tous)",$D15=Drill!$F$6),OR(Drill!$G$6="(Tous)",$E15=Drill!$G$6)),1,0) | X15: =IF(W15=1,SUM($W$5:W15),"") | AA15: PIGIER_BOR | AI15: IPAC_REN
A16: MBway | B16: MBWAY_NAN | C16: BAC_MGT | D16: B2 | E16: ALT | F16: 2 | G16: 32 | H16: =F16*G16 | I16: 59 | J16: 55 | K16: 381067 | L16: 410668 | M16: 19355 | N16: 21193 | O16: 281142 | P16: 298687 | Q16: 23435 | R16: =K16-M16-O16 | S16: =L16-N16-P16 | T16: =L16-N16 | U16: =N16+P16+Q16 | V16: =L16-U16 | W16: =IF(AND(OR(Drill!$C$6="(Tous)",$A16=Drill!$C$6),OR(Drill!$D$6="(Tous)",$B16=Drill!$D$6),OR(Drill!$E$6="(Tous)",$C16=Drill!$E$6),OR(Drill!$F$6="(Tous)",$D16=Drill!$F$6),OR(Drill!$G$6="(Tous)",$E16=Drill!$G$6)),1,0) | X16: =IF(W16=1,SUM($W$5:W16),"") | AA16: PIGIER_LYO | AI16: PIGIER_BOR
A17: MBway | B17: MBWAY_NAN | C17: BAC_MGT | D17: B3 | E17: ALT | F17: 2 | G17: 32 | H17: =F17*G17 | I17: 57 | J17: 54 | K17: 373445 | L17: 402454 | M17: 18968 | N17: 20769 | O17: 281142 | P17: 298687 | Q17: 22967 | R17: =K17-M17-O17 | S17: =L17-N17-P17 | T17: =L17-N17 | U17: =N17+P17+Q17 | V17: =L17-U17 | W17: =IF(AND(OR(Drill!$C$6="(Tous)",$A17=Drill!$C$6),OR(Drill!$D$6="(Tous)",$B17=Drill!$D$6),OR(Drill!$E$6="(Tous)",$C17=Drill!$E$6),OR(Drill!$F$6="(Tous)",$D17=Drill!$F$6),OR(Drill!$G$6="(Tous)",$E17=Drill!$G$6)),1,0) | X17: =IF(W17=1,SUM($W$5:W17),"") | AA17: TUNON_LYO | AI17: PIGIER_LYO
A18: MBway | B18: MBWAY_NAN | C18: MAS_MGT | D18: M1 | E18: ALT | F18: 3 | G18: 26 | H18: =F18*G18 | I18: 60 | J18: 57 | K18: 420913 | L18: 453609 | M18: 19954 | N18: 21848 | O18: 364944 | P18: 387718 | Q18: 24160 | R18: =K18-M18-O18 | S18: =L18-N18-P18 | T18: =L18-N18 | U18: =N18+P18+Q18 | V18: =L18-U18 | W18: =IF(AND(OR(Drill!$C$6="(Tous)",$A18=Drill!$C$6),OR(Drill!$D$6="(Tous)",$B18=Drill!$D$6),OR(Drill!$E$6="(Tous)",$C18=Drill!$E$6),OR(Drill!$F$6="(Tous)",$D18=Drill!$F$6),OR(Drill!$G$6="(Tous)",$E18=Drill!$G$6)),1,0) | X18: =IF(W18=1,SUM($W$5:W18),"") | AA18: TUNON_PAR | AI18: TUNON_LYO
A19: MBway | B19: MBWAY_NAN | C19: MAS_MGT | D19: M2 | E19: ALT | F19: 3 | G19: 26 | H19: =F19*G19 | I19: 59 | J19: 56 | K19: 412495 | L19: 444537 | M19: 19555 | N19: 21411 | O19: 364944 | P19: 387718 | Q19: 23677 | R19: =K19-M19-O19 | S19: =L19-N19-P19 | T19: =L19-N19 | U19: =N19+P19+Q19 | V19: =L19-U19 | W19: =IF(AND(OR(Drill!$C$6="(Tous)",$A19=Drill!$C$6),OR(Drill!$D$6="(Tous)",$B19=Drill!$D$6),OR(Drill!$E$6="(Tous)",$C19=Drill!$E$6),OR(Drill!$F$6="(Tous)",$D19=Drill!$F$6),OR(Drill!$G$6="(Tous)",$E19=Drill!$G$6)),1,0) | X19: =IF(W19=1,SUM($W$5:W19),"") | AI19: TUNON_PAR
A20: MBway | B20: MBWAY_PAR | C20: BAC_MGT | D20: B1 | E20: INIT | F20: 3 | G20: 32 | H20: =F20*G20 | I20: 78 | J20: 74 | K20: 612849 | L20: 660455 | M20: 25940 | N20: 28403 | O20: 452264 | P20: 480483 | Q20: 31408 | R20: =K20-M20-O20 | S20: =L20-N20-P20 | T20: =L20-N20 | U20: =N20+P20+Q20 | V20: =L20-U20 | W20: =IF(AND(OR(Drill!$C$6="(Tous)",$A20=Drill!$C$6),OR(Drill!$D$6="(Tous)",$B20=Drill!$D$6),OR(Drill!$E$6="(Tous)",$C20=Drill!$E$6),OR(Drill!$F$6="(Tous)",$D20=Drill!$F$6),OR(Drill!$G$6="(Tous)",$E20=Drill!$G$6)),1,0) | X20: =IF(W20=1,SUM($W$5:W20),"")
A21: MBway | B21: MBWAY_PAR | C21: BAC_MGT | D21: B2 | E21: ALT | F21: 3 | G21: 32 | H21: =F21*G21 | I21: 76 | J21: 71 | K21: 554833 | L21: 597932 | M21: 25162 | N21: 27551 | O21: 452264 | P21: 480483 | Q21: 30466 | R21: =K21-M21-O21 | S21: =L21-N21-P21 | T21: =L21-N21 | U21: =N21+P21+Q21 | V21: =L21-U21 | W21: =IF(AND(OR(Drill!$C$6="(Tous)",$A21=Drill!$C$6),OR(Drill!$D$6="(Tous)",$B21=Drill!$D$6),OR(Drill!$E$6="(Tous)",$C21=Drill!$E$6),OR(Drill!$F$6="(Tous)",$D21=Drill!$F$6),OR(Drill!$G$6="(Tous)",$E21=Drill!$G$6)),1,0) | X21: =IF(W21=1,SUM($W$5:W21),"")
A22: MBway | B22: MBWAY_PAR | C22: BAC_MGT | D22: B3 | E22: ALT | F22: 3 | G22: 32 | H22: =F22*G22 | I22: 74 | J22: 70 | K22: 543736 | L22: 585974 | M22: 24659 | N22: 27000 | O22: 452264 | P22: 480483 | Q22: 29857 | R22: =K22-M22-O22 | S22: =L22-N22-P22 | T22: =L22-N22 | U22: =N22+P22+Q22 | V22: =L22-U22 | W22: =IF(AND(OR(Drill!$C$6="(Tous)",$A22=Drill!$C$6),OR(Drill!$D$6="(Tous)",$B22=Drill!$D$6),OR(Drill!$E$6="(Tous)",$C22=Drill!$E$6),OR(Drill!$F$6="(Tous)",$D22=Drill!$F$6),OR(Drill!$G$6="(Tous)",$E22=Drill!$G$6)),1,0) | X22: =IF(W22=1,SUM($W$5:W22),"")
A23: MBway | B23: MBWAY_PAR | C23: MAS_MGT | D23: M1 | E23: ALT | F23: 4 | G23: 26 | H23: =F23*G23 | I23: 78 | J23: 74 | K23: 612849 | L23: 660455 | M23: 25940 | N23: 28403 | O23: 521843 | P23: 554404 | Q23: 31408 | R23: =K23-M23-O23 | S23: =L23-N23-P23 | T23: =L23-N23 | U23: =N23+P23+Q23 | V23: =L23-U23 | W23: =IF(AND(OR(Drill!$C$6="(Tous)",$A23=Drill!$C$6),OR(Drill!$D$6="(Tous)",$B23=Drill!$D$6),OR(Drill!$E$6="(Tous)",$C23=Drill!$E$6),OR(Drill!$F$6="(Tous)",$D23=Drill!$F$6),OR(Drill!$G$6="(Tous)",$E23=Drill!$G$6)),1,0) | X23: =IF(W23=1,SUM($W$5:W23),"")
A24: MBway | B24: MBWAY_PAR | C24: MAS_MGT | D24: M2 | E24: ALT | F24: 3 | G24: 26 | H24: =F24*G24 | I24: 77 | J24: 72 | K24: 600592 | L24: 647246 | M24: 25421 | N24: 27835 | O24: 391382 | P24: 415803 | Q24: 30780 | R24: =K24-M24-O24 | S24: =L24-N24-P24 | T24: =L24-N24 | U24: =N24+P24+Q24 | V24: =L24-U24 | W24: =IF(AND(OR(Drill!$C$6="(Tous)",$A24=Drill!$C$6),OR(Drill!$D$6="(Tous)",$B24=Drill!$D$6),OR(Drill!$E$6="(Tous)",$C24=Drill!$E$6),OR(Drill!$F$6="(Tous)",$D24=Drill!$F$6),OR(Drill!$G$6="(Tous)",$E24=Drill!$G$6)),1,0) | X24: =IF(W24=1,SUM($W$5:W24),"")
A25: ISCOM | B25: ISCOM_LIL | C25: BAC_COM | D25: B1 | E25: INIT | F25: 2 | G25: 32 | H25: =F25*G25 | I25: 50 | J25: 49 | K25: 353524 | L25: 366743 | M25: 17101 | N25: 18025 | O25: 281393 | P25: 290430 | Q25: 19932 | R25: =K25-M25-O25 | S25: =L25-N25-P25 | T25: =L25-N25 | U25: =N25+P25+Q25 | V25: =L25-U25 | W25: =IF(AND(OR(Drill!$C$6="(Tous)",$A25=Drill!$C$6),OR(Drill!$D$6="(Tous)",$B25=Drill!$D$6),OR(Drill!$E$6="(Tous)",$C25=Drill!$E$6),OR(Drill!$F$6="(Tous)",$D25=Drill!$F$6),OR(Drill!$G$6="(Tous)",$E25=Drill!$G$6)),1,0) | X25: =IF(W25=1,SUM($W$5:W25),"")
A26: ISCOM | B26: ISCOM_LIL | C26: BAC_COM | D26: B2 | E26: ALT | F26: 2 | G26: 32 | H26: =F26*G26 | I26: 48 | J26: 47 | K26: 320057 | L26: 332025 | M26: 16588 | N26: 17484 | O26: 281393 | P26: 290430 | Q26: 19334 | R26: =K26-M26-O26 | S26: =L26-N26-P26 | T26: =L26-N26 | U26: =N26+P26+Q26 | V26: =L26-U26 | W26: =IF(AND(OR(Drill!$C$6="(Tous)",$A26=Drill!$C$6),OR(Drill!$D$6="(Tous)",$B26=Drill!$D$6),OR(Drill!$E$6="(Tous)",$C26=Drill!$E$6),OR(Drill!$F$6="(Tous)",$D26=Drill!$F$6),OR(Drill!$G$6="(Tous)",$E26=Drill!$G$6)),1,0) | X26: =IF(W26=1,SUM($W$5:W26),"")
A27: ISCOM | B27: ISCOM_LIL | C27: BAC_COM | D27: B3 | E27: ALT | F27: 2 | G27: 32 | H27: =F27*G27 | I27: 47 | J27: 46 | K27: 313656 | L27: 325384 | M27: 16256 | N27: 17134 | O27: 281393 | P27: 290430 | Q27: 18947 | R27: =K27-M27-O27 | S27: =L27-N27-P27 | T27: =L27-N27 | U27: =N27+P27+Q27 | V27: =L27-U27 | W27: =IF(AND(OR(Drill!$C$6="(Tous)",$A27=Drill!$C$6),OR(Drill!$D$6="(Tous)",$B27=Drill!$D$6),OR(Drill!$E$6="(Tous)",$C27=Drill!$E$6),OR(Drill!$F$6="(Tous)",$D27=Drill!$F$6),OR(Drill!$G$6="(Tous)",$E27=Drill!$G$6)),1,0) | X27: =IF(W27=1,SUM($W$5:W27),"")
A28: ISCOM | B28: ISCOM_LIL | C28: MAS_COM | D28: M1 | E28: ALT | F28: 2 | G28: 26 | H28: =F28*G28 | I28: 49 | J28: 49 | K28: 353524 | L28: 366743 | M28: 17101 | N28: 18025 | O28: 243513 | P28: 251334 | Q28: 19932 | R28: =K28-M28-O28 | S28: =L28-N28-P28 | T28: =L28-N28 | U28: =N28+P28+Q28 | V28: =L28-U28 | W28: =IF(AND(OR(Drill!$C$6="(Tous)",$A28=Drill!$C$6),OR(Drill!$D$6="(Tous)",$B28=Drill!$D$6),OR(Drill!$E$6="(Tous)",$C28=Drill!$E$6),OR(Drill!$F$6="(Tous)",$D28=Drill!$F$6),OR(Drill!$G$6="(Tous)",$E28=Drill!$G$6)),1,0) | X28: =IF(W28=1,SUM($W$5:W28),"")
A29: ISCOM | B29: ISCOM_LIL | C29: MAS_COM | D29: M2 | E29: ALT | F29: 2 | G29: 26 | H29: =F29*G29 | I29: 49 | J29: 48 | K29: 346453 | L29: 359408 | M29: 16759 | N29: 17664 | O29: 243513 | P29: 251334 | Q29: 19533 | R29: =K29-M29-O29 | S29: =L29-N29-P29 | T29: =L29-N29 | U29: =N29+P29+Q29 | V29: =L29-U29 | W29: =IF(AND(OR(Drill!$C$6="(Tous)",$A29=Drill!$C$6),OR(Drill!$D$6="(Tous)",$B29=Drill!$D$6),OR(Drill!$E$6="(Tous)",$C29=Drill!$E$6),OR(Drill!$F$6="(Tous)",$D29=Drill!$F$6),OR(Drill!$G$6="(Tous)",$E29=Drill!$G$6)),1,0) | X29: =IF(W29=1,SUM($W$5:W29),"")
A30: ISCOM | B30: ISCOM_PAR | C30: BAC_COM | D30: B1 | E30: INIT | F30: 3 | G30: 32 | H30: =F30*G30 | I30: 72 | J30: 70 | K30: 583595 | L30: 605417 | M30: 24702 | N30: 26036 | O30: 458466 | P30: 473236 | Q30: 28791 | R30: =K30-M30-O30 | S30: =L30-N30-P30 | T30: =L30-N30 | U30: =N30+P30+Q30 | V30: =L30-U30 | W30: =IF(AND(OR(Drill!$C$6="(Tous)",$A30=Drill!$C$6),OR(Drill!$D$6="(Tous)",$B30=Drill!$D$6),OR(Drill!$E$6="(Tous)",$C30=Drill!$E$6),OR(Drill!$F$6="(Tous)",$D30=Drill!$F$6),OR(Drill!$G$6="(Tous)",$E30=Drill!$G$6)),1,0) | X30: =IF(W30=1,SUM($W$5:W30),"")
A31: ISCOM | B31: ISCOM_PAR | C31: BAC_COM | D31: B2 | E31: ALT | F31: 3 | G31: 32 | H31: =F31*G31 | I31: 70 | J31: 68 | K31: 528348 | L31: 548104 | M31: 23961 | N31: 25255 | O31: 458466 | P31: 473236 | Q31: 27927 | R31: =K31-M31-O31 | S31: =L31-N31-P31 | T31: =L31-N31 | U31: =N31+P31+Q31 | V31: =L31-U31 | W31: =IF(AND(OR(Drill!$C$6="(Tous)",$A31=Drill!$C$6),OR(Drill!$D$6="(Tous)",$B31=Drill!$D$6),OR(Drill!$E$6="(Tous)",$C31=Drill!$E$6),OR(Drill!$F$6="(Tous)",$D31=Drill!$F$6),OR(Drill!$G$6="(Tous)",$E31=Drill!$G$6)),1,0) | X31: =IF(W31=1,SUM($W$5:W31),"")
... A64: Tunon | B64: TUNON_PAR | C64: BAC_TOU | D64: B3 | E64: ALT | F64: 2 | G64: 32 | H64: =F64*G64 | I64: 45 | J64: 44 | K64: 342234 | L64: 351584 | M64: 15520 | N64: 16200 | O64: 314389 | P64: 327293 | Q64: 17914 | R64: =K64-M64-O64 | S64: =L64-N64-P64 | T64: =L64-N64 | U64: =N64+P64+Q64 | V64: =L64-U64 | W64: =IF(AND(OR(Drill!$C$6="(Tous)",$A64=Drill!$C$6),OR(Drill!$D$6="(Tous)",$B64=Drill!$D$6),OR(Drill!$E$6="(Tous)",$C64=Drill!$E$6),OR(Drill!$F$6="(Tous)",$D64=Drill!$F$6),OR(Drill!$G$6="(Tous)",$E64=Drill!$G$6)),1,0) | X64: =IF(W64=1,SUM($W$5:W64),"")
A65: TOTAL | F65: =SUM(F5:F64) | G65: =SUM(G5:G64) | H65: =SUM(H5:H64) | I65: =SUM(I5:I64) | J65: =SUM(J5:J64) | K65: =SUM(K5:K64) | L65: =SUM(L5:L64) | M65: =SUM(M5:M64) | ... V65: =SUM(V5:V64)
A67: Clés de ventilation comptable (onglet ⑥) — les postes du coût direct n'évoluent pas au même rythme
A68: Compte | B68: Libellé | C68: Assiette | D68: Part 2025 | E68: Part 2026
A69: 706 | B69: Scolarité initiale | C69: CA × 0,97 × (1−mix alt.)
A70: 7062 | B70: Scolarité alternance | C70: CA × 0,97 × mix alt.
A71: 708 | B71: Produits annexes | C71: CA | D71: 0.03 | E71: 0.03
A72: 621 | B72: Vacataires | C72: Coût variable | D72: 0.85 | E72: 0.85
A73: 604 | B73: Achats de prestations | C73: Coût variable | D73: 0.15 | E73: 0.15
A74: 641 | B74: Masse salariale permanente | C74: Coût direct | D74: 0.64 | E74: 0.6465593
A75: 613 | B75: Loyers & charges locatives | C75: Coût direct | D75: 0.22 | E75: 0.22010737
A76: 6236 | B76: Quote-part marque | C76: Coût direct | D76: 0.1 | E76: 0.09272816
A77: 6063 | B77: Fournitures & petits équipements | C77: Coût direct | D77: 0.04 | E77: 0.040605173

Sheet Cockpit
B2: ③ Cockpit de performance — EDUSERVICES GROUP | M2: RÉEL · CLÔTURE 2026
B3: Constat 2024 → 2026 · 14 campus · 5 marques · socle CRM & comptabilité rapprochés
B5: Scénario | C5: =Données!B5 | D5: Version | E5: =Données!B6 | F5: Exercice | G5: =Données!B7 | H5: Période | I5: =Données!B8 | J5: Marque | K5: =Données!B9 | L5: Campus | M5: =Données!B10
B7: CHIFFRE D'AFFAIRES | D7: EBITDA | F7: MARGE EBITDA | H7: INSCRITS (NOUVEAUX) | J7: COÛT D'ACQUISITION | L7: REMPLISSAGE MOYEN
B8: =C35 | D8: =E35 | F8: =H35 | H8: =J35 | J8: =Données!D32/Données!D33 | L8: =K35
B9: =D35 | D9: =F35 | F9: =I35 | H9: =J35/Données!C33-1 | J9: =(Données!D32/Données!D33)/(Données!C32/Données!C33)-1 | L9: =SUM(Données!$K$15:$K$28)-SUM(Données!$J$15:$J$28)
B11: Bridge EBITDA 2025 → 2026 | E11: M€ · axe tronqué à 3,2 | F11: Marge EBITDA par marque | I11: 2024 · 2025 · 2026 | J11: Tension acquisition | M11: base 100 = 2024
B33: Portefeuille — marque & campus | M33: exercice 2026 · variation vs 2025
B34: Marque / campus | C34: CA 2026 | D34: Δ CA | E34: EBITDA | F34: Δ EBITDA | G34: Part EBITDA | H34: Marge EBITDA | I34: Δ marge | J34: Inscrits | K34: Rempl. | L34: Mix alt. | M34: Alerte
B35: GROUPE | C35: =SUM(Données!$E$15:$E$28) | D35: =C35/SUM(Données!$D$15:$D$28)-1 | E35: =SUM(Données!$H$15:$H$28) | F35: =E35/SUM(Données!$G$15:$G$28)-1 | G35: =E35/$E$35 | H35: =E35/C35 | I35: =(H35-SUM(Données!$G$15:$G$28)/SUM(Données!$D$15:$D$28))*100 | J35: =SUM(Données!$I$15:$I$28) | K35: =SUM(Données!$J$15:$J$28)/SUM(Données!$K$15:$K$28) | L35: =SUMPRODUCT(Données!$J$15:$J$28,Données!$L$15:$L$28)/SUM(Données!$J$15:$J$28) | M35: =IF(H35<0.08,"FRAGILE","")
B36: MBway | C36: =SUMIF(Données!$B$15:$B$28,$B36,Données!$E$15:$E$28) | D36: =C36/SUMIF(Données!$B$15:$B$28,$B36,Données!$D$15:$D$28)-1 | E36: =SUMIF(Données!$B$15:$B$28,$B36,Données!$H$15:$H$28) | F36: =E36/SUMIF(Données!$B$15:$B$28,$B36,Données!$G$15:$G$28)-1 | G36: =E36/$E$35 | H36: =E36/C36 | I36: =(H36-SUMIF(Données!$B$15:$B$28,$B36,Données!$G$15:$G$28)/SUMIF(Données!$B$15:$B$28,$B36,Données!$D$15:$D$28))*100 | J36: =SUMIF(Données!$B$15:$B$28,$B36,Données!$I$15:$I$28) | K36: =SUMIF(Données!$B$15:$B$28,$B36,Données!$J$15:$J$28)/SUMIF(Données!$B$15:$B$28,$B36,Données!$K$15:$K$28) | L36: =SUMPRODUCT((Données!$B$15:$B$28=$B36)*Données!$J$15:$J$28*Données!$L$15:$L$28)/SUMIF(Données!$B$15:$B$28,$B36,Données!$J$15:$J$28) | M36: =IF(H36<0.08,"FRAGILE","")
B37: MBWAY_BOR | C37: =VLOOKUP($B37,Données!$A$15:$L$28,5,0) | D37: =C37/VLOOKUP($B37,Données!$A$15:$L$28,4,0)-1 | E37: =VLOOKUP($B37,Données!$A$15:$L$28,8,0) | F37: =IF(VLOOKUP($B37,Données!$A$15:$L$28,7,0)<=0,"n/s",E37/VLOOKUP($B37,Données!$A$15:$L$28,7,0)-1) | G37: =E37/$E$35 | H37: =E37/C37 | I37: =(H37-VLOOKUP($B37,Données!$A$15:$L$28,7,0)/VLOOKUP($B37,Données!$A$15:$L$28,4,0))*100 | J37: =VLOOKUP($B37,Données!$A$15:$L$28,9,0) | K37: =VLOOKUP($B37,Données!$A$15:$L$28,10,0)/VLOOKUP($B37,Données!$A$15:$L$28,11,0) | L37: =VLOOKUP($B37,Données!$A$15:$L$28,12,0) | M37: =IF(H37<0.08,"FRAGILE","")
B38: MBWAY_LYO | C38: =VLOOKUP($B38,Données!$A$15:$L$28,5,0) | D38: =C38/VLOOKUP($B38,Données!$A$15:$L$28,4,0)-1 | E38: =VLOOKUP($B38,Données!$A$15:$L$28,8,0) | F38: =IF(VLOOKUP($B38,Données!$A$15:$L$28,7,0)<=0,"n/s",E38/VLOOKUP($B38,Données!$A$15:$L$28,7,0)-1) | G38: =E38/$E$35 | H38: =E38/C38 | I38: =(H38-VLOOKUP($B38,Données!$A$15:$L$28,7,0)/VLOOKUP($B38,Données!$A$15:$L$28,4,0))*100 | J38: =VLOOKUP($B38,Données!$A$15:$L$28,9,0) | K38: =VLOOKUP($B38,Données!$A$15:$L$28,10,0)/VLOOKUP($B38,Données!$A$15:$L$28,11,0) | L38: =VLOOKUP($B38,Données!$A$15:$L$28,12,0) | M38: =IF(H38<0.08,"FRAGILE","")
B39: MBWAY_NAN | C39: =VLOOKUP($B39,Données!$A$15:$L$28,5,0) | D39: =C39/VLOOKUP($B39,Données!$A$15:$L$28,4,0)-1 | E39: =VLOOKUP($B39,Données!$A$15:$L$28,8,0) | F39: =IF(VLOOKUP($B39,Données!$A$15:$L$28,7,0)<=0,"n/s",E39/VLOOKUP($B39,Données!$A$15:$L$28,7,0)-1) | G39: =E39/$E$35 | H39: =E39/C39 | I39: =(H39-VLOOKUP($B39,Données!$A$15:$L$28,7,0)/VLOOKUP($B39,Données!$A$15:$L$28,4,0))*100 | J39: =VLOOKUP($B39,Données!$A$15:$L$28,9,0) | K39: =VLOOKUP($B39,Données!$A$15:$L$28,10,0)/VLOOKUP($B39,Données!$A$15:$L$28,11,0) | L39: =VLOOKUP($B39,Données!$A$15:$L$28,12,0) | M39: =IF(H39<0.08,"FRAGILE","")
B40: MBWAY_PAR | C40: =VLOOKUP($B40,Données!$A$15:$L$28,5,0) | D40: =C40/VLOOKUP($B40,Données!$A$15:$L$28,4,0)-1 | E40: =VLOOKUP($B40,Données!$A$15:$L$28,8,0) | F40: =IF(VLOOKUP($B40,Données!$A$15:$L$28,7,0)<=0,"n/s",E40/VLOOKUP($B40,Données!$A$15:$L$28,7,0)-1) | G40: =E40/$E$35 | H40: =E40/C40 | I40: =(H40-VLOOKUP($B40,Données!$A$15:$L$28,7,0)/VLOOKUP($B40,Données!$A$15:$L$28,4,0))*100 | J40: =VLOOKUP($B40,Données!$A$15:$L$28,9,0) | K40: =VLOOKUP($B40,Données!$A$15:$L$28,10,0)/VLOOKUP($B40,Données!$A$15:$L$28,11,0) | L40: =VLOOKUP($B40,Données!$A$15:$L$28,12,0) | M40: =IF(H40<0.08,"FRAGILE","")
B41: ISCOM | C41: =SUMIF(Données!$B$15:$B$28,$B41,Données!$E$15:$E$28) | D41: =C41/SUMIF(Données!$B$15:$B$28,$B41,Données!$D$15:$D$28)-1 | E41: =SUMIF(Données!$B$15:$B$28,$B41,Données!$H$15:$H$28) | F41: =E41/SUMIF(Données!$B$15:$B$28,$B41,Données!$G$15:$G$28)-1 | G41: =E41/$E$35 | H41: =E41/C41 | I41: =(H41-SUMIF(Données!$B$15:$B$28,$B41,Données!$G$15:$G$28)/SUMIF(Données!$B$15:$B$28,$B41,Données!$D$15:$D$28))*100 | J41: =SUMIF(Données!$B$15:$B$28,$B41,Données!$I$15:$I$28) | K41: =SUMIF(Données!$B$15:$B$28,$B41,Données!$J$15:$J$28)/SUMIF(Données!$B$15:$B$28,$B41,Données!$K$15:$K$28) | L41: =SUMPRODUCT((Données!$B$15:$B$28=$B41)*Données!$J$15:$J$28*Données!$L$15:$L$28)/SUMIF(Données!$B$15:$B$28,$B41,Données!$J$15:$J$28) | M41: =IF(H41<0.08,"FRAGILE","")
B42: ISCOM_LIL | C42: =VLOOKUP($B42,Données!$A$15:$L$28,5,0) | D42: =C42/VLOOKUP($B42,Données!$A$15:$L$28,4,0)-1 | E42: =VLOOKUP($B42,Données!$A$15:$L$28,8,0) | F42: =IF(VLOOKUP($B42,Données!$A$15:$L$28,7,0)<=0,"n/s",E42/VLOOKUP($B42,Données!$A$15:$L$28,7,0)-1) | G42: =E42/$E$35 | H42: =E42/C42 | I42: =(H42-VLOOKUP($B42,Données!$A$15:$L$28,7,0)/VLOOKUP($B42,Données!$A$15:$L$28,4,0))*100 | J42: =VLOOKUP($B42,Données!$A$15:$L$28,9,0) | K42: =VLOOKUP($B42,Données!$A$15:$L$28,10,0)/VLOOKUP($B42,Données!$A$15:$L$28,11,0) | L42: =VLOOKUP($B42,Données!$A$15:$L$28,12,0) | M42: =IF(H42<0.08,"FRAGILE","")
B43: ISCOM_PAR | C43: =VLOOKUP($B43,Données!$A$15:$L$28,5,0) | D43: =C43/VLOOKUP($B43,Données!$A$15:$L$28,4,0)-1 | E43: =VLOOKUP($B43,Données!$A$15:$L$28,8,0) | F43: =IF(VLOOKUP($B43,Données!$A$15:$L$28,7,0)<=0,"n/s",E43/VLOOKUP($B43,Données!$A$15:$L$28,7,0)-1) | G43: =E43/$E$35 | H43: =E43/C43 | I43: =(H43-VLOOKUP($B43,Données!$A$15:$L$28,7,0)/VLOOKUP($B43,Données!$A$15:$L$28,4,0))*100 | J43: =VLOOKUP($B43,Données!$A$15:$L$28,9,0) | K43: =VLOOKUP($B43,Données!$A$15:$L$28,10,0)/VLOOKUP($B43,Données!$A$15:$L$28,11,0) | L43: =VLOOKUP($B43,Données!$A$15:$L$28,12,0) | M43: =IF(H43<0.08,"FRAGILE","")
B44: ISCOM_TLS | C44: =VLOOKUP($B44,Données!$A$15:$L$28,5,0) | D44: =C44/VLOOKUP($B44,Données!$A$15:$L$28,4,0)-1 | E44: =VLOOKUP($B44,Données!$A$15:$L$28,8,0) | F44: =IF(VLOOKUP($B44,Données!$A$15:$L$28,7,0)<=0,"n/s",E44/VLOOKUP($B44,Données!$A$15:$L$28,7,0)-1) | G44: =E44/$E$35 | H44: =E44/C44 | I44: =(H44-VLOOKUP($B44,Données!$A$15:$L$28,7,0)/VLOOKUP($B44,Données!$A$15:$L$28,4,0))*100 | J44: =VLOOKUP($B44,Données!$A$15:$L$28,9,0) | K44: =VLOOKUP($B44,Données!$A$15:$L$28,10,0)/VLOOKUP($B44,Données!$A$15:$L$28,11,0) | L44: =VLOOKUP($B44,Données!$A$15:$L$28,12,0) | M44: =IF(H44<0.08,"FRAGILE","")
B45: Ipac | C45: =SUMIF(Données!$B$15:$B$28,$B45,Données!$E$15:$E$28) | D45: =C45/SUMIF(Données!$B$15:$B$28,$B45,Données!$D$15:$D$28)-1 | E45: =SUMIF(Données!$B$15:$B$28,$B45,Données!$H$15:$H$28) | F45: =E45/SUMIF(Données!$B$15:$B$28,$B45,Données!$G$15:$G$28)-1 | G45: =E45/$E$35 | H45: =E45/C45 | I45: =(H45-SUMIF(Données!$B$15:$B$28,$B45,Données!$G$15:$G$28)/SUMIF(Données!$B$15:$B$28,$B45,Données!$D$15:$D$28))*100 | J45: =SUMIF(Données!$B$15:$B$28,$B45,Données!$I$15:$I$28) | K45: =SUMIF(Données!$B$15:$B$28,$B45,Données!$J$15:$J$28)/SUMIF(Données!$B$15:$B$28,$B45,Données!$K$15:$K$28) | L45: =SUMPRODUCT((Données!$B$15:$B$28=$B45)*Données!$J$15:$J$28*Données!$L$15:$L$28)/SUMIF(Données!$B$15:$B$28,$B45,Données!$J$15:$J$28) | M45: =IF(H45<0.08,"FRAGILE","")
B46: IPAC_MTP | C46: =VLOOKUP($B46,Données!$A$15:$L$28,5,0) | D46: =C46/VLOOKUP($B46,Données!$A$15:$L$28,4,0)-1 | E46: =VLOOKUP($B46,Données!$A$15:$L$28,8,0) | F46: =IF(VLOOKUP($B46,Données!$A$15:$L$28,7,0)<=0,"n/s",E46/VLOOKUP($B46,Données!$A$15:$L$28,7,0)-1) | G46: =E46/$E$35 | H46: =E46/C46 | I46: =(H46-VLOOKUP($B46,Données!$A$15:$L$28,7,0)/VLOOKUP($B46,Données!$A$15:$L$28,4,0))*100 | J46: =VLOOKUP($B46,Données!$A$15:$L$28,9,0) | K46: =VLOOKUP($B46,Données!$A$15:$L$28,10,0)/VLOOKUP($B46,Données!$A$15:$L$28,11,0) | L46: =VLOOKUP($B46,Données!$A$15:$L$28,12,0) | M46: =IF(H46<0.08,"FRAGILE","")
B47: IPAC_NAN | C47: =VLOOKUP($B47,Données!$A$15:$L$28,5,0) | D47: =C47/VLOOKUP($B47,Données!$A$15:$L$28,4,0)-1 | E47: =VLOOKUP($B47,Données!$A$15:$L$28,8,0) | F47: =IF(VLOOKUP($B47,Données!$A$15:$L$28,7,0)<=0,"n/s",E47/VLOOKUP($B47,Données!$A$15:$L$28,7,0)-1) | G47: =E47/$E$35 | H47: =E47/C47 | I47: =(H47-VLOOKUP($B47,Données!$A$15:$L$28,7,0)/VLOOKUP($B47,Données!$A$15:$L$28,4,0))*100 | J47: =VLOOKUP($B47,Données!$A$15:$L$28,9,0) | K47: =VLOOKUP($B47,Données!$A$15:$L$28,10,0)/VLOOKUP($B47,Données!$A$15:$L$28,11,0) | L47: =VLOOKUP($B47,Données!$A$15:$L$28,12,0) | M47: =IF(H47<0.08,"FRAGILE","")
B48: IPAC_REN | C48: =VLOOKUP($B48,Données!$A$15:$L$28,5,0) | D48: =C48/VLOOKUP($B48,Données!$A$15:$L$28,4,0)-1 | E48: =VLOOKUP($B48,Données!$A$15:$L$28,8,0) | F48: =IF(VLOOKUP($B48,Données!$A$15:$L$28,7,0)<=0,"n/s",E48/VLOOKUP($B48,Données!$A$15:$L$28,7,0)-1) | G48: =E48/$E$35 | H48: =E48/C48 | I48: =(H48-VLOOKUP($B48,Données!$A$15:$L$28,7,0)/VLOOKUP($B48,Données!$A$15:$L$28,4,0))*100 | J48: =VLOOKUP($B48,Données!$A$15:$L$28,9,0) | K48: =VLOOKUP($B48,Données!$A$15:$L$28,10,0)/VLOOKUP($B48,Données!$A$15:$L$28,11,0) | L48: =VLOOKUP($B48,Données!$A$15:$L$28,12,0) | M48: =IF(H48<0.08,"FRAGILE","")
B49: Pigier | C49: =SUMIF(Données!$B$15:$B$28,$B49,Données!$E$15:$E$28) | D49: =C49/SUMIF(Données!$B$15:$B$28,$B49,Données!$D$15:$D$28)-1 | E49: =SUMIF(Données!$B$15:$B$28,$B49,Données!$H$15:$H$28) | F49: =E49/SUMIF(Données!$B$15:$B$28,$B49,Données!$G$15:$G$28)-1 | G49: =E49/$E$35 | H49: =E49/C49 | I49: =(H49-SUMIF(Données!$B$15:$B$28,$B49,Données!$G$15:$G$28)/SUMIF(Données!$B$15:$B$28,$B49,Données!$D$15:$D$28))*100 | J49: =SUMIF(Données!$B$15:$B$28,$B49,Données!$I$15:$I$28) | K49: =SUMIF(Données!$B$15:$B$28,$B49,Données!$J$15:$J$28)/SUMIF(Données!$B$15:$B$28,$B49,Données!$K$15:$K$28) | L49: =SUMPRODUCT((Données!$B$15:$B$28=$B49)*Données!$J$15:$J$28*Données!$L$15:$L$28)/SUMIF(Données!$B$15:$B$28,$B49,Données!$J$15:$J$28) | M49: =IF(H49<0.08,"FRAGILE","")
B50: PIGIER_BOR | C50: =VLOOKUP($B50,Données!$A$15:$L$28,5,0) | D50: =C50/VLOOKUP($B50,Données!$A$15:$L$28,4,0)-1 | E50: =VLOOKUP($B50,Données!$A$15:$L$28,8,0) | F50: =IF(VLOOKUP($B50,Données!$A$15:$L$28,7,0)<=0,"n/s",E50/VLOOKUP($B50,Données!$A$15:$L$28,7,0)-1) | G50: =E50/$E$35 | H50: =E50/C50 | I50: =(H50-VLOOKUP($B50,Données!$A$15:$L$28,7,0)/VLOOKUP($B50,Données!$A$15:$L$28,4,0))*100 | J50: =VLOOKUP($B50,Données!$A$15:$L$28,9,0) | K50: =VLOOKUP($B50,Données!$A$15:$L$28,10,0)/VLOOKUP($B50,Données!$A$15:$L$28,11,0) | L50: =VLOOKUP($B50,Données!$A$15:$L$28,12,0) | M50: =IF(H50<0.08,"FRAGILE","")
B51: PIGIER_LYO | C51: =VLOOKUP($B51,Données!$A$15:$L$28,5,0) | D51: =C51/VLOOKUP($B51,Données!$A$15:$L$28,4,0)-1 | E51: =VLOOKUP($B51,Données!$A$15:$L$28,8,0) | F51: =IF(VLOOKUP($B51,Données!$A$15:$L$28,7,0)<=0,"n/s",E51/VLOOKUP($B51,Données!$A$15:$L$28,7,0)-1) | G51: =E51/$E$35 | H51: =E51/C51 | I51: =(H51-VLOOKUP($B51,Données!$A$15:$L$28,7,0)/VLOOKUP($B51,Données!$A$15:$L$28,4,0))*100 | J51: =VLOOKUP($B51,Données!$A$15:$L$28,9,0) | K51: =VLOOKUP($B51,Données!$A$15:$L$28,10,0)/VLOOKUP($B51,Données!$A$15:$L$28,11,0) | L51: =VLOOKUP($B51,Données!$A$15:$L$28,12,0) | M51: =IF(H51<0.08,"FRAGILE","")
B52: Tunon | C52: =SUMIF(Données!$B$15:$B$28,$B52,Données!$E$15:$E$28) | D52: =C52/SUMIF(Données!$B$15:$B$28,$B52,Données!$D$15:$D$28)-1 | E52: =SUMIF(Données!$B$15:$B$28,$B52,Données!$H$15:$H$28) | F52: =E52/SUMIF(Données!$B$15:$B$28,$B52,Données!$G$15:$G$28)-1 | G52: =E52/$E$35 | H52: =E52/C52 | I52: =(H52-SUMIF(Données!$B$15:$B$28,$B52,Données!$G$15:$G$28)/SUMIF(Données!$B$15:$B$28,$B52,Données!$D$15:$D$28))*100 | J52: =SUMIF(Données!$B$15:$B$28,$B52,Données!$I$15:$I$28) | K52: =SUMIF(Données!$B$15:$B$28,$B52,Données!$J$15:$J$28)/SUMIF(Données!$B$15:$B$28,$B52,Données!$K$15:$K$28) | L52: =SUMPRODUCT((Données!$B$15:$B$28=$B52)*Données!$J$15:$J$28*Données!$L$15:$L$28)/SUMIF(Données!$B$15:$B$28,$B52,Données!$J$15:$J$28) | M52: =IF(H52<0.08,"FRAGILE","")
B53: TUNON_LYO | C53: =VLOOKUP($B53,Données!$A$15:$L$28,5,0) | D53: =C53/VLOOKUP($B53,Données!$A$15:$L$28,4,0)-1 | E53: =VLOOKUP($B53,Données!$A$15:$L$28,8,0) | F53: =IF(VLOOKUP($B53,Données!$A$15:$L$28,7,0)<=0,"n/s",E53/VLOOKUP($B53,Données!$A$15:$L$28,7,0)-1) | G53: =E53/$E$35 | H53: =E53/C53 | I53: =(H53-VLOOKUP($B53,Données!$A$15:$L$28,7,0)/VLOOKUP($B53,Données!$A$15:$L$28,4,0))*100 | J53: =VLOOKUP($B53,Données!$A$15:$L$28,9,0) | K53: =VLOOKUP($B53,Données!$A$15:$L$28,10,0)/VLOOKUP($B53,Données!$A$15:$L$28,11,0) | L53: =VLOOKUP($B53,Données!$A$15:$L$28,12,0) | M53: =IF(H53<0.08,"FRAGILE","")
B54: TUNON_PAR | C54: =VLOOKUP($B54,Données!$A$15:$L$28,5,0) | D54: =C54/VLOOKUP($B54,Données!$A$15:$L$28,4,0)-1 | E54: =VLOOKUP($B54,Données!$A$15:$L$28,8,0) | F54: =IF(VLOOKUP($B54,Données!$A$15:$L$28,7,0)<=0,"n/s",E54/VLOOKUP($B54,Données!$A$15:$L$28,7,0)-1) | G54: =E54/$E$35 | H54: =E54/C54 | I54: =(H54-VLOOKUP($B54,Données!$A$15:$L$28,7,0)/VLOOKUP($B54,Données!$A$15:$L$28,4,0))*100 | J54: =VLOOKUP($B54,Données!$A$15:$L$28,9,0) | K54: =VLOOKUP($B54,Données!$A$15:$L$28,10,0)/VLOOKUP($B54,Données!$A$15:$L$28,11,0) | L54: =VLOOKUP($B54,Données!$A$15:$L$28,12,0) | M54: =IF(H54<0.08,"FRAGILE","")
B56: Le signal du cockpit. Tunon pèse 8,4 % du CA mais 2,1 % de l'EBITDA. Ipac, le réseau le plus jeune, pèse 11,2 % du CA pour 9,5 % de l'EBITDA — il monte en charge, Rennes et Montpellier encore à 61 % de remplissage. À l'inverse Pigier, la plus petite des cinq, est la plus rentable (21,2 %). Et le groupe n'occupe que 75 % de ses places : plus de 1 000 places ouvertes et vides. Le cadrage 2027 ne peut pas être un « + x % » uniforme — c'est ici que le drill prend le relais.
B60: Source : socle CRM et comptabilité rapprochés · les marges se lisent en POINTS. Tout le cockpit est en formules : seuls les onglets ① et ② se saisissent.

Sheet Drill
B2: ④ Drill EBITDA — du groupe à la classe | M2: CONTRIBUTION vs COÛT COMPLET
B3: Marque → Campus → Programme → Année d'étude → Modalité · exercice 2026
B5: ① CHEMIN DE DRILL | C5: Marque | D5: Campus | E5: Programme | F5: Année d'étude | G5: Modalité
B6: remets « (Tous) » pour remonter d'un niveau | C6: (Tous) | D6: (Tous) | E6: (Tous) | F6: (Tous) | G6: (Tous) | O6: =5-COUNTIF($C$6:$G$6,"(Tous)")+1
B8: ="② Vous regardez : "&IF($O$6=1,"le GROUPE (tous périmètres)",IF($C$6="(Tous)","",$C$6)&IF($D$6="(Tous)",""," › "&$D$6)&IF($E$6="(Tous)",""," › "&$E$6)&IF($F$6="(Tous)",""," › "&$F$6)&IF($G$6="(Tous)",""," › "&$G$6))
B10: ② NIVEAU COURANT
B11: Agrégat de la sélection | C11: CA 2026 | D11: Δ CA | E11: EBITDA | F11: Marge EBITDA | G11: Contribution | H11: Coût complet | I11: Marge complète | J11: Effectifs | K11: Places | L11: Remplissage | M11: Statut
B12: =IF($O$6=1,"GROUPE",INDEX($C$6:$G$6,$O$6-1)) | C12: =SUMPRODUCT('Données drill'!$W$5:$W$64,'Données drill'!$L$5:$L$64) | D12: =C12/SUMPRODUCT('Données drill'!$W$5:$W$64,'Données drill'!$K$5:$K$64)-1 | E12: =SUMPRODUCT('Données drill'!$W$5:$W$64,'Données drill'!$S$5:$S$64) | F12: =IFERROR(E12/C12,0) | G12: =SUMPRODUCT('Données drill'!$W$5:$W$64,'Données drill'!$T$5:$T$64) | H12: =SUMPRODUCT('Données drill'!$W$5:$W$64,'Données drill'!$U$5:$U$64) | I12: =SUMPRODUCT('Données drill'!$W$5:$W$64,'Données drill'!$V$5:$V$64) | J12: =SUMPRODUCT('Données drill'!$W$5:$W$64,'Données drill'!$I$5:$I$64) | K12: =SUMPRODUCT('Données drill'!$W$5:$W$64,'Données drill'!$H$5:$H$64) | L12: =IFERROR(J12/K12,0) | M12: =IF(E12<0,"DÉFICITAIRE",IF(I12<0,"PIÈGE",IF(L12<0.7,"SOUS-REMPLI","SAIN")))
B14: =" ③ NIVEAU SUIVANT — "&IF($O$6>5,"grain classe atteint, voir le détail ci-dessous",UPPER(INDEX('Données drill'!$AF$5:$AF$9,$O$6)))
B15: Membre | C15: CA 2026 | D15: Δ CA | E15: EBITDA | F15: Marge EBITDA | G15: Contribution | H15: Coût complet | I15: Marge complète | J15: Effectifs | K15: Places | L15: Remplissage | M15: Statut
B16: =IF($O$6>5,"",IFERROR(INDEX('Données drill'!$Z$5:$AD$18,1,$O$6),"")) | C16: =IF($B16="","",SUMPRODUCT('Données drill'!$W$5:$W$64*(INDEX('Données drill'!$A$5:$E$64,0,$O$6)=$B16)*'Données drill'!$L$5:$L$64)) | D16: =IF(OR($C16="",$C16=0),"",C16/SUMPRODUCT('Données drill'!$W$5:$W$64*(INDEX('Données drill'!$A$5:$E$64,0,$O$6)=$B16)*'Données drill'!$K$5:$K$64)-1) | E16: =IF(OR($C16="",$C16=0),"",SUMPRODUCT('Données drill'!$W$5:$W$64*(INDEX('Données drill'!$A$5:$E$64,0,$O$6)=$B16)*'Données drill'!$S$5:$S$64)) | F16: =IF(OR($C16="",$C16=0),"",E16/C16) | G16: =IF(OR($C16="",$C16=0),"",SUMPRODUCT('Données drill'!$W$5:$W$64*(INDEX('Données drill'!$A$5:$E$64,0,$O$6)=$B16)*'Données drill'!$T$5:$T$64)) | H16: =IF(OR($C16="",$C16=0),"",SUMPRODUCT('Données drill'!$W$5:$W$64*(INDEX('Données drill'!$A$5:$E$64,0,$O$6)=$B16)*'Données drill'!$U$5:$U$64)) | I16: =IF(OR($C16="",$C16=0),"",SUMPRODUCT('Données drill'!$W$5:$W$64*(INDEX('Données drill'!$A$5:$E$64,0,$O$6)=$B16)*'Données drill'!$V$5:$V$64)) | J16: =IF(OR($C16="",$C16=0),"",SUMPRODUCT('Données drill'!$W$5:$W$64*(INDEX('Données drill'!$A$5:$E$64,0,$O$6)=$B16)*'Données drill'!$I$5:$I$64)) | K16: =IF(OR($C16="",$C16=0),"",SUMPRODUCT('Données drill'!$W$5:$W$64*(INDEX('Données drill'!$A$5:$E$64,0,$O$6)=$B16)*'Données drill'!$H$5:$H$64)) | L16: =IF(OR($C16="",$C16=0),"",J16/K16) | M16: =IF(OR($C16="",$C16=0),"",IF(E16<0,"DÉFICITAIRE",IF(I16<0,"PIÈGE",IF(L16<0.7,"SOUS-REMPLI",""))))
B17: =IF($O$6>5,"",IFERROR(INDEX('Données drill'!$Z$5:$AD$18,2,$O$6),"")) | C17: =IF($B17="","",SUMPRODUCT('Données drill'!$W$5:$W$64*(INDEX('Données drill'!$A$5:$E$64,0,$O$6)=$B17)*'Données drill'!$L$5:$L$64)) | D17: =IF(OR($C17="",$C17=0),"",C17/SUMPRODUCT('Données drill'!$W$5:$W$64*(INDEX('Données drill'!$A$5:$E$64,0,$O$6)=$B17)*'Données drill'!$K$5:$K$64)-1) | E17: =IF(OR($C17="",$C17=0),"",SUMPRODUCT('Données drill'!$W$5:$W$64*(INDEX('Données drill'!$A$5:$E$64,0,$O$6)=$B17)*'Données drill'!$S$5:$S$64)) | F17: =IF(OR($C17="",$C17=0),"",E17/C17) | G17: =IF(OR($C17="",$C17=0),"",SUMPRODUCT('Données drill'!$W$5:$W$64*(INDEX('Données drill'!$A$5:$E$64,0,$O$6)=$B17)*'Données drill'!$T$5:$T$64)) | H17: =IF(OR($C17="",$C17=0),"",SUMPRODUCT('Données drill'!$W$5:$W$64*(INDEX('Données drill'!$A$5:$E$64,0,$O$6)=$B17)*'Données drill'!$U$5:$U$64)) | I17: =IF(OR($C17="",$C17=0),"",SUMPRODUCT('Données drill'!$W$5:$W$64*(INDEX('Données drill'!$A$5:$E$64,0,$O$6)=$B17)*'Données drill'!$V$5:$V$64)) | J17: =IF(OR($C17="",$C17=0),"",SUMPRODUCT('Données drill'!$W$5:$W$64*(INDEX('Données drill'!$A$5:$E$64,0,$O$6)=$B17)*'Données drill'!$I$5:$I$64)) | K17: =IF(OR($C17="",$C17=0),"",SUMPRODUCT('Données drill'!$W$5:$W$64*(INDEX('Données drill'!$A$5:$E$64,0,$O$6)=$B17)*'Données drill'!$H$5:$H$64)) | L17: =IF(OR($C17="",$C17=0),"",J17/K17) | M17: =IF(OR($C17="",$C17=0),"",IF(E17<0,"DÉFICITAIRE",IF(I17<0,"PIÈGE",IF(L17<0.7,"SOUS-REMPLI",""))))
B18: =IF($O$6>5,"",IFERROR(INDEX('Données drill'!$Z$5:$AD$18,3,$O$6),"")) | C18: =IF($B18="","",SUMPRODUCT('Données drill'!$W$5:$W$64*(INDEX('Données drill'!$A$5:$E$64,0,$O$6)=$B18)*'Données drill'!$L$5:$L$64)) | D18: =IF(OR($C18="",$C18=0),"",C18/SUMPRODUCT('Données drill'!$W$5:$W$64*(INDEX('Données drill'!$A$5:$E$64,0,$O$6)=$B18)*'Données drill'!$K$5:$K$64)-1) | E18: =IF(OR($C18="",$C18=0),"",SUMPRODUCT('Données drill'!$W$5:$W$64*(INDEX('Données drill'!$A$5:$E$64,0,$O$6)=$B18)*'Données drill'!$S$5:$S$64)) | F18: =IF(OR($C18="",$C18=0),"",E18/C18) | G18: =IF(OR($C18="",$C18=0),"",SUMPRODUCT('Données drill'!$W$5:$W$64*(INDEX('Données drill'!$A$5:$E$64,0,$O$6)=$B18)*'Données drill'!$T$5:$T$64)) | H18: =IF(OR($C18="",$C18=0),"",SUMPRODUCT('Données drill'!$W$5:$W$64*(INDEX('Données drill'!$A$5:$E$64,0,$O$6)=$B18)*'Données drill'!$U$5:$U$64)) | I18: =IF(OR($C18="",$C18=0),"",SUMPRODUCT('Données drill'!$W$5:$W$64*(INDEX('Données drill'!$A$5:$E$64,0,$O$6)=$B18)*'Données drill'!$V$5:$V$64)) | J18: =IF(OR($C18="",$C18=0),"",SUMPRODUCT('Données drill'!$W$5:$W$64*(INDEX('Données drill'!$A$5:$E$64,0,$O$6)=$B18)*'Données drill'!$I$5:$I$64)) | K18: =IF(OR($C18="",$C18=0),"",SUMPRODUCT('Données drill'!$W$5:$W$64*(INDEX('Données drill'!$A$5:$E$64,0,$O$6)=$B18)*'Données drill'!$H$5:$H$64)) | L18: =IF(OR($C18="",$C18=0),"",J18/K18) | M18: =IF(OR($C18="",$C18=0),"",IF(E18<0,"DÉFICITAIRE",IF(I18<0,"PIÈGE",IF(L18<0.7,"SOUS-REMPLI",""))))
B19: =IF($O$6>5,"",IFERROR(INDEX('Données drill'!$Z$5:$AD$18,4,$O$6),"")) | C19: =IF($B19="","",SUMPRODUCT('Données drill'!$W$5:$W$64*(INDEX('Données drill'!$A$5:$E$64,0,$O$6)=$B19)*'Données drill'!$L$5:$L$64)) | D19: =IF(OR($C19="",$C19=0),"",C19/SUMPRODUCT('Données drill'!$W$5:$W$64*(INDEX('Données drill'!$A$5:$E$64,0,$O$6)=$B19)*'Données drill'!$K$5:$K$64)-1) | E19: =IF(OR($C19="",$C19=0),"",SUMPRODUCT('Données drill'!$W$5:$W$64*(INDEX('Données drill'!$A$5:$E$64,0,$O$6)=$B19)*'Données drill'!$S$5:$S$64)) | F19: =IF(OR($C19="",$C19=0),"",E19/C19) | G19: =IF(OR($C19="",$C19=0),"",SUMPRODUCT('Données drill'!$W$5:$W$64*(INDEX('Données drill'!$A$5:$E$64,0,$O$6)=$B19)*'Données drill'!$T$5:$T$64)) | H19: =IF(OR($C19="",$C19=0),"",SUMPRODUCT('Données drill'!$W$5:$W$64*(INDEX('Données drill'!$A$5:$E$64,0,$O$6)=$B19)*'Données drill'!$U$5:$U$64)) | I19: =IF(OR($C19="",$C19=0),"",SUMPRODUCT('Données drill'!$W$5:$W$64*(INDEX('Données drill'!$A$5:$E$64,0,$O$6)=$B19)*'Données drill'!$V$5:$V$64)) | J19: =IF(OR($C19="",$C19=0),"",SUMPRODUCT('Données drill'!$W$5:$W$64*(INDEX('Données drill'!$A$5:$E$64,0,$O$6)=$B19)*'Données drill'!$I$5:$I$64)) | K19: =IF(OR($C19="",$C19=0),"",SUMPRODUCT('Données drill'!$W$5:$W$64*(INDEX('Données drill'!$A$5:$E$64,0,$O$6)=$B19)*'Données drill'!$H$5:$H$64)) | L19: =IF(OR($C19="",$C19=0),"",J19/K19) | M19: =IF(OR($C19="",$C19=0),"",IF(E19<0,"DÉFICITAIRE",IF(I19<0,"PIÈGE",IF(L19<0.7,"SOUS-REMPLI",""))))
B20: =IF($O$6>5,"",IFERROR(INDEX('Données drill'!$Z$5:$AD$18,5,$O$6),"")) | C20: =IF($B20="","",SUMPRODUCT('Données drill'!$W$5:$W$64*(INDEX('Données drill'!$A$5:$E$64,0,$O$6)=$B20)*'Données drill'!$L$5:$L$64)) | D20: =IF(OR($C20="",$C20=0),"",C20/SUMPRODUCT('Données drill'!$W$5:$W$64*(INDEX('Données drill'!$A$5:$E$64,0,$O$6)=$B20)*'Données drill'!$K$5:$K$64)-1) | E20: =IF(OR($C20="",$C20=0),"",SUMPRODUCT('Données drill'!$W$5:$W$64*(INDEX('Données drill'!$A$5:$E$64,0,$O$6)=$B20)*'Données drill'!$S$5:$S$64)) | F20: =IF(OR($C20="",$C20=0),"",E20/C20) | G20: =IF(OR($C20="",$C20=0),"",SUMPRODUCT('Données drill'!$W$5:$W$64*(INDEX('Données drill'!$A$5:$E$64,0,$O$6)=$B20)*'Données drill'!$T$5:$T$64)) | H20: =IF(OR($C20="",$C20=0),"",SUMPRODUCT('Données drill'!$W$5:$W$64*(INDEX('Données drill'!$A$5:$E$64,0,$O$6)=$B20)*'Données drill'!$U$5:$U$64)) | I20: =IF(OR($C20="",$C20=0),"",SUMPRODUCT('Données drill'!$W$5:$W$64*(INDEX('Données drill'!$A$5:$E$64,0,$O$6)=$B20)*'Données drill'!$V$5:$V$64)) | J20: =IF(OR($C20="",$C20=0),"",SUMPRODUCT('Données drill'!$W$5:$W$64*(INDEX('Données drill'!$A$5:$E$64,0,$O$6)=$B20)*'Données drill'!$I$5:$I$64)) | K20: =IF(OR($C20="",$C20=0),"",SUMPRODUCT('Données drill'!$W$5:$W$64*(INDEX('Données drill'!$A$5:$E$64,0,$O$6)=$B20)*'Données drill'!$H$5:$H$64)) | L20: =IF(OR($C20="",$C20=0),"",J20/K20) | M20: =IF(OR($C20="",$C20=0),"",IF(E20<0,"DÉFICITAIRE",IF(I20<0,"PIÈGE",IF(L20<0.7,"SOUS-REMPLI",""))))
B21: =IF($O$6>5,"",IFERROR(INDEX('Données drill'!$Z$5:$AD$18,6,$O$6),"")) | C21: =IF($B21="","",SUMPRODUCT('Données drill'!$W$5:$W$64*(INDEX('Données drill'!$A$5:$E$64,0,$O$6)=$B21)*'Données drill'!$L$5:$L$64)) | D21: =IF(OR($C21="",$C21=0),"",C21/SUMPRODUCT('Données drill'!$W$5:$W$64*(INDEX('Données drill'!$A$5:$E$64,0,$O$6)=$B21)*'Données drill'!$K$5:$K$64)-1) | E21: =IF(OR($C21="",$C21=0),"",SUMPRODUCT('Données drill'!$W$5:$W$64*(INDEX('Données drill'!$A$5:$E$64,0,$O$6)=$B21)*'Données drill'!$S$5:$S$64)) | F21: =IF(OR($C21="",$C21=0),"",E21/C21) | G21: =IF(OR($C21="",$C21=0),"",SUMPRODUCT('Données drill'!$W$5:$W$64*(INDEX('Données drill'!$A$5:$E$64,0,$O$6)=$B21)*'Données drill'!$T$5:$T$64)) | H21: =IF(OR($C21="",$C21=0),"",SUMPRODUCT('Données drill'!$W$5:$W$64*(INDEX('Données drill'!$A$5:$E$64,0,$O$6)=$B21)*'Données drill'!$U$5:$U$64)) | I21: =IF(OR($C21="",$C21=0),"",SUMPRODUCT('Données drill'!$W$5:$W$64*(INDEX('Données drill'!$A$5:$E$64,0,$O$6)=$B21)*'Données drill'!$V$5:$V$64)) | J21: =IF(OR($C21="",$C21=0),"",SUMPRODUCT('Données drill'!$W$5:$W$64*(INDEX('Données drill'!$A$5:$E$64,0,$O$6)=$B21)*'Données drill'!$I$5:$I$64)) | K21: =IF(OR($C21="",$C21=0),"",SUMPRODUCT('Données drill'!$W$5:$W$64*(INDEX('Données drill'!$A$5:$E$64,0,$O$6)=$B21)*'Données drill'!$H$5:$H$64)) | L21: =IF(OR($C21="",$C21=0),"",J21/K21) | M21: =IF(OR($C21="",$C21=0),"",IF(E21<0,"DÉFICITAIRE",IF(I21<0,"PIÈGE",IF(L21<0.7,"SOUS-REMPLI",""))))
B22: =IF($O$6>5,"",IFERROR(INDEX('Données drill'!$Z$5:$AD$18,7,$O$6),"")) | C22: =IF($B22="","",SUMPRODUCT('Données drill'!$W$5:$W$64*(INDEX('Données drill'!$A$5:$E$64,0,$O$6)=$B22)*'Données drill'!$L$5:$L$64)) | D22: =IF(OR($C22="",$C22=0),"",C22/SUMPRODUCT('Données drill'!$W$5:$W$64*(INDEX('Données drill'!$A$5:$E$64,0,$O$6)=$B22)*'Données drill'!$K$5:$K$64)-1) | E22: =IF(OR($C22="",$C22=0),"",SUMPRODUCT('Données drill'!$W$5:$W$64*(INDEX('Données drill'!$A$5:$E$64,0,$O$6)=$B22)*'Données drill'!$S$5:$S$64)) | F22: =IF(OR($C22="",$C22=0),"",E22/C22) | G22: =IF(OR($C22="",$C22=0),"",SUMPRODUCT('Données drill'!$W$5:$W$64*(INDEX('Données drill'!$A$5:$E$64,0,$O$6)=$B22)*'Données drill'!$T$5:$T$64)) | H22: =IF(OR($C22="",$C22=0),"",SUMPRODUCT('Données drill'!$W$5:$W$64*(INDEX('Données drill'!$A$5:$E$64,0,$O$6)=$B22)*'Données drill'!$U$5:$U$64)) | I22: =IF(OR($C22="",$C22=0),"",SUMPRODUCT('Données drill'!$W$5:$W$64*(INDEX('Données drill'!$A$5:$E$64,0,$O$6)=$B22)*'Données drill'!$V$5:$V$64)) | J22: =IF(OR($C22="",$C22=0),"",SUMPRODUCT('Données drill'!$W$5:$W$64*(INDEX('Données drill'!$A$5:$E$64,0,$O$6)=$B22)*'Données drill'!$I$5:$I$64)) | K22: =IF(OR($C22="",$C22=0),"",SUMPRODUCT('Données drill'!$W$5:$W$64*(INDEX('Données drill'!$A$5:$E$64,0,$O$6)=$B22)*'Données drill'!$H$5:$H$64)) | L22: =IF(OR($C22="",$C22=0),"",J22/K22) | M22: =IF(OR($C22="",$C22=0),"",IF(E22<0,"DÉFICITAIRE",IF(I22<0,"PIÈGE",IF(L22<0.7,"SOUS-REMPLI",""))))
B23: =IF($O$6>5,"",IFERROR(INDEX('Données drill'!$Z$5:$AD$18,8,$O$6),"")) | C23: =IF($B23="","",SUMPRODUCT('Données drill'!$W$5:$W$64*(INDEX('Données drill'!$A$5:$E$64,0,$O$6)=$B23)*'Données drill'!$L$5:$L$64)) | D23: =IF(OR($C23="",$C23=0),"",C23/SUMPRODUCT('Données drill'!$W$5:$W$64*(INDEX('Données drill'!$A$5:$E$64,0,$O$6)=$B23)*'Données drill'!$K$5:$K$64)-1) | E23: =IF(OR($C23="",$C23=0),"",SUMPRODUCT('Données drill'!$W$5:$W$64*(INDEX('Données drill'!$A$5:$E$64,0,$O$6)=$B23)*'Données drill'!$S$5:$S$64)) | F23: =IF(OR($C23="",$C23=0),"",E23/C23) | G23: =IF(OR($C23="",$C23=0),"",SUMPRODUCT('Données drill'!$W$5:$W$64*(INDEX('Données drill'!$A$5:$E$64,0,$O$6)=$B23)*'Données drill'!$T$5:$T$64)) | H23: =IF(OR($C23="",$C23=0),"",SUMPRODUCT('Données drill'!$W$5:$W$64*(INDEX('Données drill'!$A$5:$E$64,0,$O$6)=$B23)*'Données drill'!$U$5:$U$64)) | I23: =IF(OR($C23="",$C23=0),"",SUMPRODUCT('Données drill'!$W$5:$W$64*(INDEX('Données drill'!$A$5:$E$64,0,$O$6)=$B23)*'Données drill'!$V$5:$V$64)) | J23: =IF(OR($C23="",$C23=0),"",SUMPRODUCT('Données drill'!$W$5:$W$64*(INDEX('Données drill'!$A$5:$E$64,0,$O$6)=$B23)*'Données drill'!$I$5:$I$64)) | K23: =IF(OR($C23="",$C23=0),"",SUMPRODUCT('Données drill'!$W$5:$W$64*(INDEX('Données drill'!$A$5:$E$64,0,$O$6)=$B23)*'Données drill'!$H$5:$H$64)) | L23: =IF(OR($C23="",$C23=0),"",J23/K23) | M23: =IF(OR($C23="",$C23=0),"",IF(E23<0,"DÉFICITAIRE",IF(I23<0,"PIÈGE",IF(L23<0.7,"SOUS-REMPLI",""))))
B24: =IF($O$6>5,"",IFERROR(INDEX('Données drill'!$Z$5:$AD$18,9,$O$6),"")) | C24: =IF($B24="","",SUMPRODUCT('Données drill'!$W$5:$W$64*(INDEX('Données drill'!$A$5:$E$64,0,$O$6)=$B24)*'Données drill'!$L$5:$L$64)) | D24: =IF(OR($C24="",$C24=0),"",C24/SUMPRODUCT('Données drill'!$W$5:$W$64*(INDEX('Données drill'!$A$5:$E$64,0,$O$6)=$B24)*'Données drill'!$K$5:$K$64)-1) | E24: =IF(OR($C24="",$C24=0),"",SUMPRODUCT('Données drill'!$W$5:$W$64*(INDEX('Données drill'!$A$5:$E$64,0,$O$6)=$B24)*'Données drill'!$S$5:$S$64)) | F24: =IF(OR($C24="",$C24=0),"",E24/C24) | G24: =IF(OR($C24="",$C24=0),"",SUMPRODUCT('Données drill'!$W$5:$W$64*(INDEX('Données drill'!$A$5:$E$64,0,$O$6)=$B24)*'Données drill'!$T$5:$T$64)) | H24: =IF(OR($C24="",$C24=0),"",SUMPRODUCT('Données drill'!$W$5:$W$64*(INDEX('Données drill'!$A$5:$E$64,0,$O$6)=$B24)*'Données drill'!$U$5:$U$64)) | I24: =IF(OR($C24="",$C24=0),"",SUMPRODUCT('Données drill'!$W$5:$W$64*(INDEX('Données drill'!$A$5:$E$64,0,$O$6)=$B24)*'Données drill'!$V$5:$V$64)) | J24: =IF(OR($C24="",$C24=0),"",SUMPRODUCT('Données drill'!$W$5:$W$64*(INDEX('Données drill'!$A$5:$E$64,0,$O$6)=$B24)*'Données drill'!$I$5:$I$64)) | K24: =IF(OR($C24="",$C24=0),"",SUMPRODUCT('Données drill'!$W$5:$W$64*(INDEX('Données drill'!$A$5:$E$64,0,$O$6)=$B24)*'Données drill'!$H$5:$H$64)) | L24: =IF(OR($C24="",$C24=0),"",J24/K24) | M24: =IF(OR($C24="",$C24=0),"",IF(E24<0,"DÉFICITAIRE",IF(I24<0,"PIÈGE",IF(L24<0.7,"SOUS-REMPLI",""))))
B25: =IF($O$6>5,"",IFERROR(INDEX('Données drill'!$Z$5:$AD$18,10,$O$6),"")) | C25: =IF($B25="","",SUMPRODUCT('Données drill'!$W$5:$W$64*(INDEX('Données drill'!$A$5:$E$64,0,$O$6)=$B25)*'Données drill'!$L$5:$L$64)) | D25: =IF(OR($C25="",$C25=0),"",C25/SUMPRODUCT('Données drill'!$W$5:$W$64*(INDEX('Données drill'!$A$5:$E$64,0,$O$6)=$B25)*'Données drill'!$K$5:$K$64)-1) | E25: =IF(OR($C25="",$C25=0),"",SUMPRODUCT('Données drill'!$W$5:$W$64*(INDEX('Données drill'!$A$5:$E$64,0,$O$6)=$B25)*'Données drill'!$S$5:$S$64)) | F25: =IF(OR($C25="",$C25=0),"",E25/C25) | G25: =IF(OR($C25="",$C25=0),"",SUMPRODUCT('Données drill'!$W$5:$W$64*(INDEX('Données drill'!$A$5:$E$64,0,$O$6)=$B25)*'Données drill'!$T$5:$T$64)) | H25: =IF(OR($C25="",$C25=0),"",SUMPRODUCT('Données drill'!$W$5:$W$64*(INDEX('Données drill'!$A$5:$E$64,0,$O$6)=$B25)*'Données drill'!$U$5:$U$64)) | I25: =IF(OR($C25="",$C25=0),"",SUMPRODUCT('Données drill'!$W$5:$W$64*(INDEX('Données drill'!$A$5:$E$64,0,$O$6)=$B25)*'Données drill'!$V$5:$V$64)) | J25: =IF(OR($C25="",$C25=0),"",SUMPRODUCT('Données drill'!$W$5:$W$64*(INDEX('Données drill'!$A$5:$E$64,0,$O$6)=$B25)*'Données drill'!$I$5:$I$64)) | K25: =IF(OR($C25="",$C25=0),"",SUMPRODUCT('Données drill'!$W$5:$W$64*(INDEX('Données drill'!$A$5:$E$64,0,$O$6)=$B25)*'Données drill'!$H$5:$H$64)) | L25: =IF(OR($C25="",$C25=0),"",J25/K25) | M25: =IF(OR($C25="",$C25=0),"",IF(E25<0,"DÉFICITAIRE",IF(I25<0,"PIÈGE",IF(L25<0.7,"SOUS-REMPLI",""))))
B26: =IF($O$6>5,"",IFERROR(INDEX('Données drill'!$Z$5:$AD$18,11,$O$6),"")) | C26: =IF($B26="","",SUMPRODUCT('Données drill'!$W$5:$W$64*(INDEX('Données drill'!$A$5:$E$64,0,$O$6)=$B26)*'Données drill'!$L$5:$L$64)) | D26: =IF(OR($C26="",$C26=0),"",C26/SUMPRODUCT('Données drill'!$W$5:$W$64*(INDEX('Données drill'!$A$5:$E$64,0,$O$6)=$B26)*'Données drill'!$K$5:$K$64)-1) | E26: =IF(OR($C26="",$C26=0),"",SUMPRODUCT('Données drill'!$W$5:$W$64*(INDEX('Données drill'!$A$5:$E$64,0,$O$6)=$B26)*'Données drill'!$S$5:$S$64)) | F26: =IF(OR($C26="",$C26=0),"",E26/C26) | G26: =IF(OR($C26="",$C26=0),"",SUMPRODUCT('Données drill'!$W$5:$W$64*(INDEX('Données drill'!$A$5:$E$64,0,$O$6)=$B26)*'Données drill'!$T$5:$T$64)) | H26: =IF(OR($C26="",$C26=0),"",SUMPRODUCT('Données drill'!$W$5:$W$64*(INDEX('Données drill'!$A$5:$E$64,0,$O$6)=$B26)*'Données drill'!$U$5:$U$64)) | I26: =IF(OR($C26="",$C26=0),"",SUMPRODUCT('Données drill'!$W$5:$W$64*(INDEX('Données drill'!$A$5:$E$64,0,$O$6)=$B26)*'Données drill'!$V$5:$V$64)) | J26: =IF(OR($C26="",$C26=0),"",SUMPRODUCT('Données drill'!$W$5:$W$64*(INDEX('Données drill'!$A$5:$E$64,0,$O$6)=$B26)*'Données drill'!$I$5:$I$64)) | K26: =IF(OR($C26="",$C26=0),"",SUMPRODUCT('Données drill'!$W$5:$W$64*(INDEX('Données drill'!$A$5:$E$64,0,$O$6)=$B26)*'Données drill'!$H$5:$H$64)) | L26: =IF(OR($C26="",$C26=0),"",J26/K26) | M26: =IF(OR($C26="",$C26=0),"",IF(E26<0,"DÉFICITAIRE",IF(I26<0,"PIÈGE",IF(L26<0.7,"SOUS-REMPLI",""))))
B27: =IF($O$6>5,"",IFERROR(INDEX('Données drill'!$Z$5:$AD$18,12,$O$6),"")) | C27: =IF($B27="","",SUMPRODUCT('Données drill'!$W$5:$W$64*(INDEX('Données drill'!$A$5:$E$64,0,$O$6)=$B27)*'Données drill'!$L$5:$L$64)) | D27: =IF(OR($C27="",$C27=0),"",C27/SUMPRODUCT('Données drill'!$W$5:$W$64*(INDEX('Données drill'!$A$5:$E$64,0,$O$6)=$B27)*'Données drill'!$K$5:$K$64)-1) | E27: =IF(OR($C27="",$C27=0),"",SUMPRODUCT('Données drill'!$W$5:$W$64*(INDEX('Données drill'!$A$5:$E$64,0,$O$6)=$B27)*'Données drill'!$S$5:$S$64)) | F27: =IF(OR($C27="",$C27=0),"",E27/C27) | G27: =IF(OR($C27="",$C27=0),"",SUMPRODUCT('Données drill'!$W$5:$W$64*(INDEX('Données drill'!$A$5:$E$64,0,$O$6)=$B27)*'Données drill'!$T$5:$T$64)) | H27: =IF(OR($C27="",$C27=0),"",SUMPRODUCT('Données drill'!$W$5:$W$64*(INDEX('Données drill'!$A$5:$E$64,0,$O$6)=$B27)*'Données drill'!$U$5:$U$64)) | I27: =IF(OR($C27="",$C27=0),"",SUMPRODUCT('Données drill'!$W$5:$W$64*(INDEX('Données drill'!$A$5:$E$64,0,$O$6)=$B27)*'Données drill'!$V$5:$V$64)) | J27: =IF(OR($C27="",$C27=0),"",SUMPRODUCT('Données drill'!$W$5:$W$64*(INDEX('Données drill'!$A$5:$E$64,0,$O$6)=$B27)*'Données drill'!$I$5:$I$64)) | K27: =IF(OR($C27="",$C27=0),"",SUMPRODUCT('Données drill'!$W$5:$W$64*(INDEX('Données drill'!$A$5:$E$64,0,$O$6)=$B27)*'Données drill'!$H$5:$H$64)) | L27: =IF(OR($C27="",$C27=0),"",J27/K27) | M27: =IF(OR($C27="",$C27=0),"",IF(E27<0,"DÉFICITAIRE",IF(I27<0,"PIÈGE",IF(L27<0.7,"SOUS-REMPLI",""))))
B28: =IF($O$6>5,"",IFERROR(INDEX('Données drill'!$Z$5:$AD$18,13,$O$6),"")) | C28: =IF($B28="","",SUMPRODUCT('Données drill'!$W$5:$W$64*(INDEX('Données drill'!$A$5:$E$64,0,$O$6)=$B28)*'Données drill'!$L$5:$L$64)) | D28: =IF(OR($C28="",$C28=0),"",C28/SUMPRODUCT('Données drill'!$W$5:$W$64*(INDEX('Données drill'!$A$5:$E$64,0,$O$6)=$B28)*'Données drill'!$K$5:$K$64)-1) | E28: =IF(OR($C28="",$C28=0),"",SUMPRODUCT('Données drill'!$W$5:$W$64*(INDEX('Données drill'!$A$5:$E$64,0,$O$6)=$B28)*'Données drill'!$S$5:$S$64)) | F28: =IF(OR($C28="",$C28=0),"",E28/C28) | G28: =IF(OR($C28="",$C28=0),"",SUMPRODUCT('Données drill'!$W$5:$W$64*(INDEX('Données drill'!$A$5:$E$64,0,$O$6)=$B28)*'Données drill'!$T$5:$T$64)) | H28: =IF(OR($C28="",$C28=0),"",SUMPRODUCT('Données drill'!$W$5:$W$64*(INDEX('Données drill'!$A$5:$E$64,0,$O$6)=$B28)*'Données drill'!$U$5:$U$64)) | I28: =IF(OR($C28="",$C28=0),"",SUMPRODUCT('Données drill'!$W$5:$W$64*(INDEX('Données drill'!$A$5:$E$64,0,$O$6)=$B28)*'Données drill'!$V$5:$V$64)) | J28: =IF(OR($C28="",$C28=0),"",SUMPRODUCT('Données drill'!$W$5:$W$64*(INDEX('Données drill'!$A$5:$E$64,0,$O$6)=$B28)*'Données drill'!$I$5:$I$64)) | K28: =IF(OR($C28="",$C28=0),"",SUMPRODUCT('Données drill'!$W$5:$W$64*(INDEX('Données drill'!$A$5:$E$64,0,$O$6)=$B28)*'Données drill'!$H$5:$H$64)) | L28: =IF(OR($C28="",$C28=0),"",J28/K28) | M28: =IF(OR($C28="",$C28=0),"",IF(E28<0,"DÉFICITAIRE",IF(I28<0,"PIÈGE",IF(L28<0.7,"SOUS-REMPLI",""))))
B29: =IF($O$6>5,"",IFERROR(INDEX('Données drill'!$Z$5:$AD$18,14,$O$6),"")) | C29: =IF($B29="","",SUMPRODUCT('Données drill'!$W$5:$W$64*(INDEX('Données drill'!$A$5:$E$64,0,$O$6)=$B29)*'Données drill'!$L$5:$L$64)) | D29: =IF(OR($C29="",$C29=0),"",C29/SUMPRODUCT('Données drill'!$W$5:$W$64*(INDEX('Données drill'!$A$5:$E$64,0,$O$6)=$B29)*'Données drill'!$K$5:$K$64)-1) | E29: =IF(OR($C29="",$C29=0),"",SUMPRODUCT('Données drill'!$W$5:$W$64*(INDEX('Données drill'!$A$5:$E$64,0,$O$6)=$B29)*'Données drill'!$S$5:$S$64)) | F29: =IF(OR($C29="",$C29=0),"",E29/C29) | G29: =IF(OR($C29="",$C29=0),"",SUMPRODUCT('Données drill'!$W$5:$W$64*(INDEX('Données drill'!$A$5:$E$64,0,$O$6)=$B29)*'Données drill'!$T$5:$T$64)) | H29: =IF(OR($C29="",$C29=0),"",SUMPRODUCT('Données drill'!$W$5:$W$64*(INDEX('Données drill'!$A$5:$E$64,0,$O$6)=$B29)*'Données drill'!$U$5:$U$64)) | I29: =IF(OR($C29="",$C29=0),"",SUMPRODUCT('Données drill'!$W$5:$W$64*(INDEX('Données drill'!$A$5:$E$64,0,$O$6)=$B29)*'Données drill'!$V$5:$V$64)) | J29: =IF(OR($C29="",$C29=0),"",SUMPRODUCT('Données drill'!$W$5:$W$64*(INDEX('Données drill'!$A$5:$E$64,0,$O$6)=$B29)*'Données drill'!$I$5:$I$64)) | K29: =IF(OR($C29="",$C29=0),"",SUMPRODUCT('Données drill'!$W$5:$W$64*(INDEX('Données drill'!$A$5:$E$64,0,$O$6)=$B29)*'Données drill'!$H$5:$H$64)) | L29: =IF(OR($C29="",$C29=0),"",J29/K29) | M29: =IF(OR($C29="",$C29=0),"",IF(E29<0,"DÉFICITAIRE",IF(I29<0,"PIÈGE",IF(L29<0.7,"SOUS-REMPLI",""))))
B30: ④ DÉTAIL AU GRAIN CLASSE — le fond du drill
B31: Campus · Programme · Année · Modalité | C31: CA 2026 | D31: Δ CA | E31: EBITDA | F31: Marge EBITDA | G31: Contribution | H31: Coût complet | I31: Marge complète | J31: Effectifs | K31: Places | L31: Remplissage | M31: Statut
B32: =IF($N32="","",INDEX('Données drill'!$B$5:$B$64,$N32)&" · "&INDEX('Données drill'!$C$5:$C$64,$N32)&" · "&INDEX('Données drill'!$D$5:$D$64,$N32)&" · "&INDEX('Données drill'!$E$5:$E$64,$N32)) | C32: =IF($N32="","",INDEX('Données drill'!$L$5:$L$64,$N32)) | D32: =IF($N32="","",C32/INDEX('Données drill'!$K$5:$K$64,$N32)-1) | E32: =IF($N32="","",INDEX('Données drill'!$S$5:$S$64,$N32)) | F32: =IF($N32="","",E32/C32) | G32: =IF($N32="","",INDEX('Données drill'!$T$5:$T$64,$N32)) | H32: =IF($N32="","",INDEX('Données drill'!$U$5:$U$64,$N32)) | I32: =IF($N32="","",INDEX('Données drill'!$V$5:$V$64,$N32)) | J32: =IF($N32="","",INDEX('Données drill'!$I$5:$I$64,$N32)) | K32: =IF($N32="","",INDEX('Données drill'!$H$5:$H$64,$N32)) | L32: =IF($N32="","",J32/K32) | M32: =IF($N32="","",IF(E32<0,"DÉFICITAIRE",IF(I32<0,"PIÈGE",IF(L32<0.7,"SOUS-REMPLI","")))) | N32: =IFERROR(MATCH(1,'Données drill'!$X$5:$X$64,0),"")
B33: =IF($N33="","",INDEX('Données drill'!$B$5:$B$64,$N33)&" · "&INDEX('Données drill'!$C$5:$C$64,$N33)&" · "&INDEX('Données drill'!$D$5:$D$64,$N33)&" · "&INDEX('Données drill'!$E$5:$E$64,$N33)) | C33: =IF($N33="","",INDEX('Données drill'!$L$5:$L$64,$N33)) | D33: =IF($N33="","",C33/INDEX('Données drill'!$K$5:$K$64,$N33)-1) | E33: =IF($N33="","",INDEX('Données drill'!$S$5:$S$64,$N33)) | F33: =IF($N33="","",E33/C33) | G33: =IF($N33="","",INDEX('Données drill'!$T$5:$T$64,$N33)) | H33: =IF($N33="","",INDEX('Données drill'!$U$5:$U$64,$N33)) | I33: =IF($N33="","",INDEX('Données drill'!$V$5:$V$64,$N33)) | J33: =IF($N33="","",INDEX('Données drill'!$I$5:$I$64,$N33)) | K33: =IF($N33="","",INDEX('Données drill'!$H$5:$H$64,$N33)) | L33: =IF($N33="","",J33/K33) | M33: =IF($N33="","",IF(E33<0,"DÉFICITAIRE",IF(I33<0,"PIÈGE",IF(L33<0.7,"SOUS-REMPLI","")))) | N33: =IFERROR(MATCH(2,'Données drill'!$X$5:$X$64,0),"")
B34: =IF($N34="","",INDEX('Données drill'!$B$5:$B$64,$N34)&" · "&INDEX('Données drill'!$C$5:$C$64,$N34)&" · "&INDEX('Données drill'!$D$5:$D$64,$N34)&" · "&INDEX('Données drill'!$E$5:$E$64,$N34)) | C34: =IF($N34="","",INDEX('Données drill'!$L$5:$L$64,$N34)) | D34: =IF($N34="","",C34/INDEX('Données drill'!$K$5:$K$64,$N34)-1) | E34: =IF($N34="","",INDEX('Données drill'!$S$5:$S$64,$N34)) | F34: =IF($N34="","",E34/C34) | G34: =IF($N34="","",INDEX('Données drill'!$T$5:$T$64,$N34)) | H34: =IF($N34="","",INDEX('Données drill'!$U$5:$U$64,$N34)) | I34: =IF($N34="","",INDEX('Données drill'!$V$5:$V$64,$N34)) | J34: =IF($N34="","",INDEX('Données drill'!$I$5:$I$64,$N34)) | K34: =IF($N34="","",INDEX('Données drill'!$H$5:$H$64,$N34)) | L34: =IF($N34="","",J34/K34) | M34: =IF($N34="","",IF(E34<0,"DÉFICITAIRE",IF(I34<0,"PIÈGE",IF(L34<0.7,"SOUS-REMPLI","")))) | N34: =IFERROR(MATCH(3,'Données drill'!$X$5:$X$64,0),"")
B35: =IF($N35="","",INDEX('Données drill'!$B$5:$B$64,$N35)&" · "&INDEX('Données drill'!$C$5:$C$64,$N35)&" · "&INDEX('Données drill'!$D$5:$D$64,$N35)&" · "&INDEX('Données drill'!$E$5:$E$64,$N35)) | C35: =IF($N35="","",INDEX('Données drill'!$L$5:$L$64,$N35)) | D35: =IF($N35="","",C35/INDEX('Données drill'!$K$5:$K$64,$N35)-1) | E35: =IF($N35="","",INDEX('Données drill'!$S$5:$S$64,$N35)) | F35: =IF($N35="","",E35/C35) | G35: =IF($N35="","",INDEX('Données drill'!$T$5:$T$64,$N35)) | H35: =IF($N35="","",INDEX('Données drill'!$U$5:$U$64,$N35)) | I35: =IF($N35="","",INDEX('Données drill'!$V$5:$V$64,$N35)) | J35: =IF($N35="","",INDEX('Données drill'!$I$5:$I$64,$N35)) | K35: =IF($N35="","",INDEX('Données drill'!$H$5:$H$64,$N35)) | L35: =IF($N35="","",J35/K35) | M35: =IF($N35="","",IF(E35<0,"DÉFICITAIRE",IF(I35<0,"PIÈGE",IF(L35<0.7,"SOUS-REMPLI","")))) | N35: =IFERROR(MATCH(4,'Données drill'!$X$5:$X$64,0),"")
B36: =IF($N36="","",INDEX('Données drill'!$B$5:$B$64,$N36)&" · "&INDEX('Données drill'!$C$5:$C$64,$N36)&" · "&INDEX('Données drill'!$D$5:$D$64,$N36)&" · "&INDEX('Données drill'!$E$5:$E$64,$N36)) | C36: =IF($N36="","",INDEX('Données drill'!$L$5:$L$64,$N36)) | D36: =IF($N36="","",C36/INDEX('Données drill'!$K$5:$K$64,$N36)-1) | E36: =IF($N36="","",INDEX('Données drill'!$S$5:$S$64,$N36)) | F36: =IF($N36="","",E36/C36) | G36: =IF($N36="","",INDEX('Données drill'!$T$5:$T$64,$N36)) | H36: =IF($N36="","",INDEX('Données drill'!$U$5:$U$64,$N36)) | I36: =IF($N36="","",INDEX('Données drill'!$V$5:$V$64,$N36)) | J36: =IF($N36="","",INDEX('Données drill'!$I$5:$I$64,$N36)) | K36: =IF($N36="","",INDEX('Données drill'!$H$5:$H$64,$N36)) | L36: =IF($N36="","",J36/K36) | M36: =IF($N36="","",IF(E36<0,"DÉFICITAIRE",IF(I36<0,"PIÈGE",IF(L36<0.7,"SOUS-REMPLI","")))) | N36: =IFERROR(MATCH(5,'Données drill'!$X$5:$X$64,0),"")
B37: =IF($N37="","",INDEX('Données drill'!$B$5:$B$64,$N37)&" · "&INDEX('Données drill'!$C$5:$C$64,$N37)&" · "&INDEX('Données drill'!$D$5:$D$64,$N37)&" · "&INDEX('Données drill'!$E$5:$E$64,$N37)) | C37: =IF($N37="","",INDEX('Données drill'!$L$5:$L$64,$N37)) | D37: =IF($N37="","",C37/INDEX('Données drill'!$K$5:$K$64,$N37)-1) | E37: =IF($N37="","",INDEX('Données drill'!$S$5:$S$64,$N37)) | F37: =IF($N37="","",E37/C37) | G37: =IF($N37="","",INDEX('Données drill'!$T$5:$T$64,$N37)) | H37: =IF($N37="","",INDEX('Données drill'!$U$5:$U$64,$N37)) | I37: =IF($N37="","",INDEX('Données drill'!$V$5:$V$64,$N37)) | J37: =IF($N37="","",INDEX('Données drill'!$I$5:$I$64,$N37)) | K37: =IF($N37="","",INDEX('Données drill'!$H$5:$H$64,$N37)) | L37: =IF($N37="","",J37/K37) | M37: =IF($N37="","",IF(E37<0,"DÉFICITAIRE",IF(I37<0,"PIÈGE",IF(L37<0.7,"SOUS-REMPLI","")))) | N37: =IFERROR(MATCH(6,'Données drill'!$X$5:$X$64,0),"")
B38: =IF($N38="","",INDEX('Données drill'!$B$5:$B$64,$N38)&" · "&INDEX('Données drill'!$C$5:$C$64,$N38)&" · "&INDEX('Données drill'!$D$5:$D$64,$N38)&" · "&INDEX('Données drill'!$E$5:$E$64,$N38)) | C38: =IF($N38="","",INDEX('Données drill'!$L$5:$L$64,$N38)) | D38: =IF($N38="","",C38/INDEX('Données drill'!$K$5:$K$64,$N38)-1) | E38: =IF($N38="","",INDEX('Données drill'!$S$5:$S$64,$N38)) | F38: =IF($N38="","",E38/C38) | G38: =IF($N38="","",INDEX('Données drill'!$T$5:$T$64,$N38)) | H38: =IF($N38="","",INDEX('Données drill'!$U$5:$U$64,$N38)) | I38: =IF($N38="","",INDEX('Données drill'!$V$5:$V$64,$N38)) | J38: =IF($N38="","",INDEX('Données drill'!$I$5:$I$64,$N38)) | K38: =IF($N38="","",INDEX('Données drill'!$H$5:$H$64,$N38)) | L38: =IF($N38="","",J38/K38) | M38: =IF($N38="","",IF(E38<0,"DÉFICITAIRE",IF(I38<0,"PIÈGE",IF(L38<0.7,"SOUS-REMPLI","")))) | N38: =IFERROR(MATCH(7,'Données drill'!$X$5:$X$64,0),"")
B39: =IF($N39="","",INDEX('Données drill'!$B$5:$B$64,$N39)&" · "&INDEX('Données drill'!$C$5:$C$64,$N39)&" · "&INDEX('Données drill'!$D$5:$D$64,$N39)&" · "&INDEX('Données drill'!$E$5:$E$64,$N39)) | C39: =IF($N39="","",INDEX('Données drill'!$L$5:$L$64,$N39)) | D39: =IF($N39="","",C39/INDEX('Données drill'!$K$5:$K$64,$N39)-1) | E39: =IF($N39="","",INDEX('Données drill'!$S$5:$S$64,$N39)) | F39: =IF($N39="","",E39/C39) | G39: =IF($N39="","",INDEX('Données drill'!$T$5:$T$64,$N39)) | H39: =IF($N39="","",INDEX('Données drill'!$U$5:$U$64,$N39)) | I39: =IF($N39="","",INDEX('Données drill'!$V$5:$V$64,$N39)) | J39: =IF($N39="","",INDEX('Données drill'!$I$5:$I$64,$N39)) | K39: =IF($N39="","",INDEX('Données drill'!$H$5:$H$64,$N39)) | L39: =IF($N39="","",J39/K39) | M39: =IF($N39="","",IF(E39<0,"DÉFICITAIRE",IF(I39<0,"PIÈGE",IF(L39<0.7,"SOUS-REMPLI","")))) | N39: =IFERROR(MATCH(8,'Données drill'!$X$5:$X$64,0),"")
B40: =IF($N40="","",INDEX('Données drill'!$B$5:$B$64,$N40)&" · "&INDEX('Données drill'!$C$5:$C$64,$N40)&" · "&INDEX('Données drill'!$D$5:$D$64,$N40)&" · "&INDEX('Données drill'!$E$5:$E$64,$N40)) | C40: =IF($N40="","",INDEX('Données drill'!$L$5:$L$64,$N40)) | D40: =IF($N40="","",C40/INDEX('Données drill'!$K$5:$K$64,$N40)-1) | E40: =IF($N40="","",INDEX('Données drill'!$S$5:$S$64,$N40)) | F40: =IF($N40="","",E40/C40) | G40: =IF($N40="","",INDEX('Données drill'!$T$5:$T$64,$N40)) | H40: =IF($N40="","",INDEX('Données drill'!$U$5:$U$64,$N40)) | I40: =IF($N40="","",INDEX('Données drill'!$V$5:$V$64,$N40)) | J40: =IF($N40="","",INDEX('Données drill'!$I$5:$I$64,$N40)) | K40: =IF($N40="","",INDEX('Données drill'!$H$5:$H$64,$N40)) | L40: =IF($N40="","",J40/K40) | M40: =IF($N40="","",IF(E40<0,"DÉFICITAIRE",IF(I40<0,"PIÈGE",IF(L40<0.7,"SOUS-REMPLI","")))) | N40: =IFERROR(MATCH(9,'Données drill'!$X$5:$X$64,0),"")
B41: =IF($N41="","",INDEX('Données drill'!$B$5:$B$64,$N41)&" · "&INDEX('Données drill'!$C$5:$C$64,$N41)&" · "&INDEX('Données drill'!$D$5:$D$64,$N41)&" · "&INDEX('Données drill'!$E$5:$E$64,$N41)) | C41: =IF($N41="","",INDEX('Données drill'!$L$5:$L$64,$N41)) | D41: =IF($N41="","",C41/INDEX('Données drill'!$K$5:$K$64,$N41)-1) | E41: =IF($N41="","",INDEX('Données drill'!$S$5:$S$64,$N41)) | F41: =IF($N41="","",E41/C41) | G41: =IF($N41="","",INDEX('Données drill'!$T$5:$T$64,$N41)) | H41: =IF($N41="","",INDEX('Données drill'!$U$5:$U$64,$N41)) | I41: =IF($N41="","",INDEX('Données drill'!$V$5:$V$64,$N41)) | J41: =IF($N41="","",INDEX('Données drill'!$I$5:$I$64,$N41)) | K41: =IF($N41="","",INDEX('Données drill'!$H$5:$H$64,$N41)) | L41: =IF($N41="","",J41/K41) | M41: =IF($N41="","",IF(E41<0,"DÉFICITAIRE",IF(I41<0,"PIÈGE",IF(L41<0.7,"SOUS-REMPLI","")))) | N41: =IFERROR(MATCH(10,'Données drill'!$X$5:$X$64,0),"")
B42: =IF($N42="","",INDEX('Données drill'!$B$5:$B$64,$N42)&" · "&INDEX('Données drill'!$C$5:$C$64,$N42)&" · "&INDEX('Données drill'!$D$5:$D$64,$N42)&" · "&INDEX('Données drill'!$E$5:$E$64,$N42)) | C42: =IF($N42="","",INDEX('Données drill'!$L$5:$L$64,$N42)) | D42: =IF($N42="","",C42/INDEX('Données drill'!$K$5:$K$64,$N42)-1) | E42: =IF($N42="","",INDEX('Données drill'!$S$5:$S$64,$N42)) | F42: =IF($N42="","",E42/C42) | G42: =IF($N42="","",INDEX('Données drill'!$T$5:$T$64,$N42)) | H42: =IF($N42="","",INDEX('Données drill'!$U$5:$U$64,$N42)) | I42: =IF($N42="","",INDEX('Données drill'!$V$5:$V$64,$N42)) | J42: =IF($N42="","",INDEX('Données drill'!$I$5:$I$64,$N42)) | K42: =IF($N42="","",INDEX('Données drill'!$H$5:$H$64,$N42)) | L42: =IF($N42="","",J42/K42) | M42: =IF($N42="","",IF(E42<0,"DÉFICITAIRE",IF(I42<0,"PIÈGE",IF(L42<0.7,"SOUS-REMPLI","")))) | N42: =IFERROR(MATCH(11,'Données drill'!$X$5:$X$64,0),"")
B43: =IF($N43="","",INDEX('Données drill'!$B$5:$B$64,$N43)&" · "&INDEX('Données drill'!$C$5:$C$64,$N43)&" · "&INDEX('Données drill'!$D$5:$D$64,$N43)&" · "&INDEX('Données drill'!$E$5:$E$64,$N43)) | C43: =IF($N43="","",INDEX('Données drill'!$L$5:$L$64,$N43)) | D43: =IF($N43="","",C43/INDEX('Données drill'!$K$5:$K$64,$N43)-1) | E43: =IF($N43="","",INDEX('Données drill'!$S$5:$S$64,$N43)) | F43: =IF($N43="","",E43/C43) | G43: =IF($N43="","",INDEX('Données drill'!$T$5:$T$64,$N43)) | H43: =IF($N43="","",INDEX('Données drill'!$U$5:$U$64,$N43)) | I43: =IF($N43="","",INDEX('Données drill'!$V$5:$V$64,$N43)) | J43: =IF($N43="","",INDEX('Données drill'!$I$5:$I$64,$N43)) | K43: =IF($N43="","",INDEX('Données drill'!$H$5:$H$64,$N43)) | L43: =IF($N43="","",J43/K43) | M43: =IF($N43="","",IF(E43<0,"DÉFICITAIRE",IF(I43<0,"PIÈGE",IF(L43<0.7,"SOUS-REMPLI","")))) | N43: =IFERROR(MATCH(12,'Données drill'!$X$5:$X$64,0),"")
B44: =IF($N44="","",INDEX('Données drill'!$B$5:$B$64,$N44)&" · "&INDEX('Données drill'!$C$5:$C$64,$N44)&" · "&INDEX('Données drill'!$D$5:$D$64,$N44)&" · "&INDEX('Données drill'!$E$5:$E$64,$N44)) | C44: =IF($N44="","",INDEX('Données drill'!$L$5:$L$64,$N44)) | D44: =IF($N44="","",C44/INDEX('Données drill'!$K$5:$K$64,$N44)-1) | E44: =IF($N44="","",INDEX('Données drill'!$S$5:$S$64,$N44)) | F44: =IF($N44="","",E44/C44) | G44: =IF($N44="","",INDEX('Données drill'!$T$5:$T$64,$N44)) | H44: =IF($N44="","",INDEX('Données drill'!$U$5:$U$64,$N44)) | I44: =IF($N44="","",INDEX('Données drill'!$V$5:$V$64,$N44)) | J44: =IF($N44="","",INDEX('Données drill'!$I$5:$I$64,$N44)) | K44: =IF($N44="","",INDEX('Données drill'!$H$5:$H$64,$N44)) | L44: =IF($N44="","",J44/K44) | M44: =IF($N44="","",IF(E44<0,"DÉFICITAIRE",IF(I44<0,"PIÈGE",IF(L44<0.7,"SOUS-REMPLI","")))) | N44: =IFERROR(MATCH(13,'Données drill'!$X$5:$X$64,0),"")
B45: =IF($N45="","",INDEX('Données drill'!$B$5:$B$64,$N45)&" · "&INDEX('Données drill'!$C$5:$C$64,$N45)&" · "&INDEX('Données drill'!$D$5:$D$64,$N45)&" · "&INDEX('Données drill'!$E$5:$E$64,$N45)) | C45: =IF($N45="","",INDEX('Données drill'!$L$5:$L$64,$N45)) | D45: =IF($N45="","",C45/INDEX('Données drill'!$K$5:$K$64,$N45)-1) | E45: =IF($N45="","",INDEX('Données drill'!$S$5:$S$64,$N45)) | F45: =IF($N45="","",E45/C45) | G45: =IF($N45="","",INDEX('Données drill'!$T$5:$T$64,$N45)) | H45: =IF($N45="","",INDEX('Données drill'!$U$5:$U$64,$N45)) | I45: =IF($N45="","",INDEX('Données drill'!$V$5:$V$64,$N45)) | J45: =IF($N45="","",INDEX('Données drill'!$I$5:$I$64,$N45)) | K45: =IF($N45="","",INDEX('Données drill'!$H$5:$H$64,$N45)) | L45: =IF($N45="","",J45/K45) | M45: =IF($N45="","",IF(E45<0,"DÉFICITAIRE",IF(I45<0,"PIÈGE",IF(L45<0.7,"SOUS-REMPLI","")))) | N45: =IFERROR(MATCH(14,'Données drill'!$X$5:$X$64,0),"")
B46: =IF($N46="","",INDEX('Données drill'!$B$5:$B$64,$N46)&" · "&INDEX('Données drill'!$C$5:$C$64,$N46)&" · "&INDEX('Données drill'!$D$5:$D$64,$N46)&" · "&INDEX('Données drill'!$E$5:$E$64,$N46)) | C46: =IF($N46="","",INDEX('Données drill'!$L$5:$L$64,$N46)) | D46: =IF($N46="","",C46/INDEX('Données drill'!$K$5:$K$64,$N46)-1) | E46: =IF($N46="","",INDEX('Données drill'!$S$5:$S$64,$N46)) | F46: =IF($N46="","",E46/C46) | G46: =IF($N46="","",INDEX('Données drill'!$T$5:$T$64,$N46)) | H46: =IF($N46="","",INDEX('Données drill'!$U$5:$U$64,$N46)) | I46: =IF($N46="","",INDEX('Données drill'!$V$5:$V$64,$N46)) | J46: =IF($N46="","",INDEX('Données drill'!$I$5:$I$64,$N46)) | K46: =IF($N46="","",INDEX('Données drill'!$H$5:$H$64,$N46)) | L46: =IF($N46="","",J46/K46) | M46: =IF($N46="","",IF(E46<0,"DÉFICITAIRE",IF(I46<0,"PIÈGE",IF(L46<0.7,"SOUS-REMPLI","")))) | N46: =IFERROR(MATCH(15,'Données drill'!$X$5:$X$64,0),"")
B47: =IF($N47="","",INDEX('Données drill'!$B$5:$B$64,$N47)&" · "&INDEX('Données drill'!$C$5:$C$64,$N47)&" · "&INDEX('Données drill'!$D$5:$D$64,$N47)&" · "&INDEX('Données drill'!$E$5:$E$64,$N47)) | C47: =IF($N47="","",INDEX('Données drill'!$L$5:$L$64,$N47)) | D47: =IF($N47="","",C47/INDEX('Données drill'!$K$5:$K$64,$N47)-1) | E47: =IF($N47="","",INDEX('Données drill'!$S$5:$S$64,$N47)) | F47: =IF($N47="","",E47/C47) | G47: =IF($N47="","",INDEX('Données drill'!$T$5:$T$64,$N47)) | H47: =IF($N47="","",INDEX('Données drill'!$U$5:$U$64,$N47)) | I47: =IF($N47="","",INDEX('Données drill'!$V$5:$V$64,$N47)) | J47: =IF($N47="","",INDEX('Données drill'!$I$5:$I$64,$N47)) | K47: =IF($N47="","",INDEX('Données drill'!$H$5:$H$64,$N47)) | L47: =IF($N47="","",J47/K47) | M47: =IF($N47="","",IF(E47<0,"DÉFICITAIRE",IF(I47<0,"PIÈGE",IF(L47<0.7,"SOUS-REMPLI","")))) | N47: =IFERROR(MATCH(16,'Données drill'!$X$5:$X$64,0),"")
B48: =IF($N48="","",INDEX('Données drill'!$B$5:$B$64,$N48)&" · "&INDEX('Données drill'!$C$5:$C$64,$N48)&" · "&INDEX('Données drill'!$D$5:$D$64,$N48)&" · "&INDEX('Données drill'!$E$5:$E$64,$N48)) | C48: =IF($N48="","",INDEX('Données drill'!$L$5:$L$64,$N48)) | D48: =IF($N48="","",C48/INDEX('Données drill'!$K$5:$K$64,$N48)-1) | E48: =IF($N48="","",INDEX('Données drill'!$S$5:$S$64,$N48)) | F48: =IF($N48="","",E48/C48) | G48: =IF($N48="","",INDEX('Données drill'!$T$5:$T$64,$N48)) | H48: =IF($N48="","",INDEX('Données drill'!$U$5:$U$64,$N48)) | I48: =IF($N48="","",INDEX('Données drill'!$V$5:$V$64,$N48)) | J48: =IF($N48="","",INDEX('Données drill'!$I$5:$I$64,$N48)) | K48: =IF($N48="","",INDEX('Données drill'!$H$5:$H$64,$N48)) | L48: =IF($N48="","",J48/K48) | M48: =IF($N48="","",IF(E48<0,"DÉFICITAIRE",IF(I48<0,"PIÈGE",IF(L48<0.7,"SOUS-REMPLI","")))) | N48: =IFERROR(MATCH(17,'Données drill'!$X$5:$X$64,0),"")
B49: =IF($N49="","",INDEX('Données drill'!$B$5:$B$64,$N49)&" · "&INDEX('Données drill'!$C$5:$C$64,$N49)&" · "&INDEX('Données drill'!$D$5:$D$64,$N49)&" · "&INDEX('Données drill'!$E$5:$E$64,$N49)) | C49: =IF($N49="","",INDEX('Données drill'!$L$5:$L$64,$N49)) | D49: =IF($N49="","",C49/INDEX('Données drill'!$K$5:$K$64,$N49)-1) | E49: =IF($N49="","",INDEX('Données drill'!$S$5:$S$64,$N49)) | F49: =IF($N49="","",E49/C49) | G49: =IF($N49="","",INDEX('Données drill'!$T$5:$T$64,$N49)) | H49: =IF($N49="","",INDEX('Données drill'!$U$5:$U$64,$N49)) | I49: =IF($N49="","",INDEX('Données drill'!$V$5:$V$64,$N49)) | J49: =IF($N49="","",INDEX('Données drill'!$I$5:$I$64,$N49)) | K49: =IF($N49="","",INDEX('Données drill'!$H$5:$H$64,$N49)) | L49: =IF($N49="","",J49/K49) | M49: =IF($N49="","",IF(E49<0,"DÉFICITAIRE",IF(I49<0,"PIÈGE",IF(L49<0.7,"SOUS-REMPLI","")))) | N49: =IFERROR(MATCH(18,'Données drill'!$X$5:$X$64,0),"")
B50: =IF($N50="","",INDEX('Données drill'!$B$5:$B$64,$N50)&" · "&INDEX('Données drill'!$C$5:$C$64,$N50)&" · "&INDEX('Données drill'!$D$5:$D$64,$N50)&" · "&INDEX('Données drill'!$E$5:$E$64,$N50)) | C50: =IF($N50="","",INDEX('Données drill'!$L$5:$L$64,$N50)) | D50: =IF($N50="","",C50/INDEX('Données drill'!$K$5:$K$64,$N50)-1) | E50: =IF($N50="","",INDEX('Données drill'!$S$5:$S$64,$N50)) | F50: =IF($N50="","",E50/C50) | G50: =IF($N50="","",INDEX('Données drill'!$T$5:$T$64,$N50)) | H50: =IF($N50="","",INDEX('Données drill'!$U$5:$U$64,$N50)) | I50: =IF($N50="","",INDEX('Données drill'!$V$5:$V$64,$N50)) | J50: =IF($N50="","",INDEX('Données drill'!$I$5:$I$64,$N50)) | K50: =IF($N50="","",INDEX('Données drill'!$H$5:$H$64,$N50)) | L50: =IF($N50="","",J50/K50) | M50: =IF($N50="","",IF(E50<0,"DÉFICITAIRE",IF(I50<0,"PIÈGE",IF(L50<0.7,"SOUS-REMPLI","")))) | N50: =IFERROR(MATCH(19,'Données drill'!$X$5:$X$64,0),"")
B51: =IF($N51="","",INDEX('Données drill'!$B$5:$B$64,$N51)&" · "&INDEX('Données drill'!$C$5:$C$64,$N51)&" · "&INDEX('Données drill'!$D$5:$D$64,$N51)&" · "&INDEX('Données drill'!$E$5:$E$64,$N51)) | C51: =IF($N51="","",INDEX('Données drill'!$L$5:$L$64,$N51)) | D51: =IF($N51="","",C51/INDEX('Données drill'!$K$5:$K$64,$N51)-1) | E51: =IF($N51="","",INDEX('Données drill'!$S$5:$S$64,$N51)) | F51: =IF($N51="","",E51/C51) | G51: =IF($N51="","",INDEX('Données drill'!$T$5:$T$64,$N51)) | H51: =IF($N51="","",INDEX('Données drill'!$U$5:$U$64,$N51)) | I51: =IF($N51="","",INDEX('Données drill'!$V$5:$V$64,$N51)) | J51: =IF($N51="","",INDEX('Données drill'!$I$5:$I$64,$N51)) | K51: =IF($N51="","",INDEX('Données drill'!$H$5:$H$64,$N51)) | L51: =IF($N51="","",J51/K51) | M51: =IF($N51="","",IF(E51<0,"DÉFICITAIRE",IF(I51<0,"PIÈGE",IF(L51<0.7,"SOUS-REMPLI","")))) | N51: =IFERROR(MATCH(20,'Données drill'!$X$5:$X$64,0),"")
B53: Comment lire. La CONTRIBUTION (CA − coûts évitables) répond à « que perd-on si on ferme ? ». La MARGE COMPLÈTE (après permanents, structure et siège) répond à « cette classe paie-t-elle sa part ? ». Aux niveaux hauts elles disent la même chose ; au grain classe elles se contredisent. « PIÈGE » = marge complète négative mais EBITDA positif : la fermer coûterait plus cher que la garder. « DÉFICITAIRE » = EBITDA négatif, elle ne couvre pas ses coûts directs — là seulement l'arbitrage se pose.

Sheet Drill — Pourquoi
B2: ⑤ Drill through › Pourquoi l'EBITDA a-t-il varié ?
B3: requête exécutée sur la cellule EBITDA du cockpit — paramètres hérités de son contexte
B5: CONTEXTE HÉRITÉ DE LA CELLULE | C5: :SCENARIO | D5: :VERSION | E5: :PERIODE | F5: :EXERCICE | G5: :ENTITY
C6: =Données!B5 | D6: =Données!B6 | E6: 12 | F6: =Données!B7 | G6: TUNON_PAR
B8: ="Cellule d'origine : Cockpit › Portefeuille › "&$G$6&" › EBITDA "&Données!B7
B10: Étape | C10: Montant | D10: Détail | E10: Lecture | G10: Agrégats lus | H10: 2025 | I10: 2026 | K10: Étape | L10: Socle | M10: Ancre | N10: Hausse | O10: Baisse
B11: ="EBITDA "&(Données!B7-1) | C11: =H12-H13-H14 | E11: point de départ | G11: Effectifs | H11: =SUMIF('Données drill'!$B$5:$B$64,$G$6,'Données drill'!$J$5:$J$64) | I11: =SUMIF('Données drill'!$B$5:$B$64,$G$6,'Données drill'!$I$5:$I$64) | K11: EBITDA N-1 | L11: 0 | M11: =C11 | N11: 0 | O11: 0
B12: + Effet effectifs | C12: =(I11-H11)*(H15-H16) | D12: =H11&" → "&I11&" élèves" | E12: volume, valorisé à la marge variable de l'exercice précédent | G12: CA | H12: =SUMIF('Données drill'!$B$5:$B$64,$G$6,'Données drill'!$K$5:$K$64) | I12: =SUMIF('Données drill'!$B$5:$B$64,$G$6,'Données drill'!$L$5:$L$64) | K12: Effectifs | L12: =C11 | M12: 0 | N12: =C12 | O12: 0
B13: + Effet prix / mix | C13: =(I15-H15)*I11 | D13: =ROUND(H15,0)&" → "&ROUND(I15,0)&" € / élève" | E13: tarif, mix initiale/alternance, mix programmes | G13: Coût variable | H13: =SUMIF('Données drill'!$B$5:$B$64,$G$6,'Données drill'!$M$5:$M$64) | I13: =SUMIF('Données drill'!$B$5:$B$64,$G$6,'Données drill'!$N$5:$N$64) | K13: Prix / mix | L13: =C11+C12 | M13: 0 | N13: =C13 | O13: 0
B14: − Effet coût variable unitaire | C14: =-(I16-H16)*I11 | D14: =ROUND(H16,0)&" → "&ROUND(I16,0)&" € / élève" | E14: vacataires et achats directs, par élève | G14: Coûts directs | H14: =SUMIF('Données drill'!$B$5:$B$64,$G$6,'Données drill'!$O$5:$O$64) | I14: =SUMIF('Données drill'!$B$5:$B$64,$G$6,'Données drill'!$P$5:$P$64) | K14: Coût var. | L14: =C11+C12+C13+C14 | M14: 0 | N14: 0 | O14: =-C14
B15: − Effet coûts directs | C15: =-(I14-H14) | D15: =ROUND(H14/1000,0)&" → "&ROUND(I14/1000,0)&" k€" | E15: permanents et structure : ils ne suivent pas l'activité | G15: CA / élève | H15: =H12/H11 | I15: =I12/I11 | K15: Coûts directs | L15: =C16 | M15: 0 | N15: 0 | O15: =-C15
B16: ="EBITDA "&Données!B7 | C16: =I12-I13-I14 | D16: ="marge "&ROUND((I12-I13-I14)/I12*100,1)&" %" | E16: doit égaler la cellule cliquée | G16: Coût var. / élève | H16: =H13/H11 | I16: =I13/I11 | K16: EBITDA N | L16: 0 | M16: =C16 | N16: 0 | O16: 0
B17: Contrôle du pont | C17: =C11+C12+C13+C14+C15-C16 | E17: =" écart "&ROUND(C17,2)&" € — le pont retombe exactement sur la cellule cliquée"
B38: Ce que le drill fait dire au chiffre. Le pont sépare ce qui vient de l'activité (effectifs, prix, mix) de ce qui vient des coûts. Quand l'effet coûts directs dépasse à lui seul la croissance, le campus n'a pas un problème de marché mais un problème de structure de coûts — et la discussion change de nature. Change le campus en G6 : tout le pont se recalcule, et l'écart de contrôle reste nul.

Sheet Drill — Par compte
B2: ⑥ Drill through › Et dans la compta, quels comptes ont bougé ?
B3: même cellule, même contexte · trié par variation absolue décroissante
B5: CONTEXTE HÉRITÉ
B6: =Données!B5&" · "&Données!B6&" · 12 · "&Données!B7&" · "&'Drill — Pourquoi'!$G$6
B8: ="Rapprochement : Σ produits − Σ charges = EBITDA du campus = la cellule"
B10: Compte | C10: Libellé | D10: 2025 | E10: 2026 | F10: Variation | G10: Var. % | H10: Nature
B11: 706 | C11: Scolarité initiale | D11: ='Drill — Pourquoi'!$H$12*0.97*(1-SUMIFS('Données drill'!$I$5:$I$64,'Données drill'!$B$5:$B$64,'Drill — Pourquoi'!$G$6,'Données drill'!$E$5:$E$64,"ALT")/SUMIF('Données drill'!$B$5:$B$64,'Drill — Pourquoi'!$G$6,'Données drill'!$I$5:$I$64)) | E11: ='Drill — Pourquoi'!$I$12*0.97*(1-SUMIFS('Données drill'!$I$5:$I$64,'Données drill'!$B$5:$B$64,'Drill — Pourquoi'!$G$6,'Données drill'!$E$5:$E$64,"ALT")/SUMIF('Données drill'!$B$5:$B$64,'Drill — Pourquoi'!$G$6,'Données drill'!$I$5:$I$64)) | F11: =E11-D11 | G11: =IFERROR(F11/ABS(D11),0) | H11: produit
B12: 7062 | C12: Scolarité alternance | D12: ='Drill — Pourquoi'!$H$12*0.97*(SUMIFS('Données drill'!$I$5:$I$64,'Données drill'!$B$5:$B$64,'Drill — Pourquoi'!$G$6,'Données drill'!$E$5:$E$64,"ALT")/SUMIF('Données drill'!$B$5:$B$64,'Drill — Pourquoi'!$G$6,'Données drill'!$I$5:$I$64)) | E12: ='Drill — Pourquoi'!$I$12*0.97*(SUMIFS('Données drill'!$I$5:$I$64,'Données drill'!$B$5:$B$64,'Drill — Pourquoi'!$G$6,'Données drill'!$E$5:$E$64,"ALT")/SUMIF('Données drill'!$B$5:$B$64,'Drill — Pourquoi'!$G$6,'Données drill'!$I$5:$I$64)) | F12: =E12-D12 | G12: =IFERROR(F12/ABS(D12),0) | H12: produit
B13: 708 | C13: Produits annexes | D13: ='Drill — Pourquoi'!$H$12*0.03 | E13: ='Drill — Pourquoi'!$I$12*0.03 | F13: =E13-D13 | G13: =IFERROR(F13/ABS(D13),0) | H13: produit
B14: 621 | C14: Vacataires | D14: ='Drill — Pourquoi'!$H$13*0.85 | E14: ='Drill — Pourquoi'!$I$13*0.85 | F14: =E14-D14 | G14: =IFERROR(F14/ABS(D14),0) | H14: charge
B15: 604 | C15: Achats de prestations | D15: ='Drill — Pourquoi'!$H$13*0.15 | E15: ='Drill — Pourquoi'!$I$13*0.15 | F15: =E15-D15 | G15: =IFERROR(F15/ABS(D15),0) | H15: charge
B16: 641 | C16: Masse salariale permanente | D16: ='Drill — Pourquoi'!$H$14*'Données drill'!$D$74 | E16: ='Drill — Pourquoi'!$I$14*'Données drill'!$E$74 | F16: =E16-D16 | G16: =IFERROR(F16/ABS(D16),0) | H16: charge
B17: 613 | C17: Loyers & charges locatives | D17: ='Drill — Pourquoi'!$H$14*'Données drill'!$D$75 | E17: ='Drill — Pourquoi'!$I$14*'Données drill'!$E$75 | F17: =E17-D17 | G17: =IFERROR(F17/ABS(D17),0) | H17: charge
B18: 6236 | C18: Quote-part marque | D18: ='Drill — Pourquoi'!$H$14*'Données drill'!$D$76 | E18: ='Drill — Pourquoi'!$I$14*'Données drill'!$E$76 | F18: =E18-D18 | G18: =IFERROR(F18/ABS(D18),0) | H18: charge
B19: 6063 | C19: Fournitures & petits équipements | D19: ='Drill — Pourquoi'!$H$14*'Données drill'!$D$77 | E19: ='Drill — Pourquoi'!$I$14*'Données drill'!$E$77 | F19: =E19-D19 | G19: =IFERROR(F19/ABS(D19),0) | H19: charge
C20: EBITDA = Σ produits − Σ charges | D20: =SUMIF($H$11:$H$19,"produit",D11:D19)-SUMIF($H$11:$H$19,"charge",D11:D19) | E20: =SUMIF($H$11:$H$19,"produit",E11:E19)-SUMIF($H$11:$H$19,"charge",E11:E19) | F20: =E20-D20
B22: Les deux drills se répondent. L'onglet ⑤ donne la cause économique — « effet coûts directs » ; celui-ci dit quelle ligne comptable la porte. Les postes du coût direct n'évoluent pas au même rythme : la masse salariale permanente suit la politique salariale, les loyers l'indexation, la quote-part marque les arbitrages du siège. Les clés de ventilation sont en bas de l'onglet ② et se modifient.
