Workbook

Sheet 00_Notice
B2: EDUSERVICES GROUP — Modèle de Budget & Simulation
B3: Budget annuel N+1 · piloté par les inducteurs · pré-maquette avant implémentation CCH Tagetik
B5: 1. Objet du classeur
B6: Ce classeur prépare, sous Excel, l'intégralité d'un budget annuel N+1 pour EDUSERVICES GROUP,
B7: avant sa mise en place dans CCH Tagetik. Il est piloté par les inducteurs métier (effectifs
B8: étudiants, tarifs, ratio d'encadrement, CAC…) et intègre un moteur de simulation par scénario.
B10: Maille : Campus → Marque / École → Groupe. Le budget est reconstruit par campus puis
B11: consolidé automatiquement. Le réalisé N-1 sert de base de cadrage et de comparaison.
B13: 2. Comment utiliser le modèle
B14: Étape 1 | C14: Renseigner le réalisé (feuille 04_Historique) : effectifs, tarifs, loyers, D&A par campus.
B15: Étape 2 | C15: Fixer les hypothèses de la note de cadrage (feuille 02_Parametres) pour chaque scénario.
B16: Étape 3 | C16: Choisir le scénario actif dans la cellule jaune C3 de 02_Parametres (Cadrage / Optimiste / Prudent).
B17: Étape 4 | C17: Lire le budget consolidé (06_PnL) et le tableau de bord de simulation (07_Simulation).
B18: Étape 5 | C18: Basculer vers Tagetik en suivant la feuille 08_Mapping_Tagetik (dimensions & comptes).
B20: 3. Légende des couleurs (convention modélisation financière)
B21: Exemple | C21: Saisie / donnée en dur
B22: Exemple | C22: Formule / calcul
B23: Exemple | C23: Lien vers une autre feuille
B24: Exemple | C24: Hypothèse clé / cellule à remplir
B26: 4. Avertissement
B27: Les montants pré-remplis sont ILLUSTRATIFS (marques, campus, effectifs et euros) et destinés à faire tourner la démo. Ils doivent être remplacés par les données réelles d'EDUSERVICES GROUP avant toute exploitation. Sources à documenter dans 04_Historique.
B31: Date de préparation : 2026-08-11

Sheet 01_Note_cadrage
B2: Note de cadrage budgétaire — Budget N+1
B3: Hypothèses directrices retenues (scénario CADRAGE). Modifiables en 02_Parametres.
B5: 1. Objectifs du groupe
B6: Poursuivre la croissance des effectifs par le développement du recrutement et l'amélioration
B7: du taux de réinscription, tout en préservant la marge EBITDA.
B8: Maîtriser le coût d'acquisition étudiant (CAC) et la masse salariale via le ratio d'encadrement.
B10: 2. Hypothèses clés (valeur de cadrage)
B11: Inducteur | C11: Valeur | D11: Justification / commentaire
B12: Taux de réinscription (progression nette) | C12: ='02_Parametres'!D6 | D12: Part des étudiants poursuivant leur cursus (net des diplômés et abandons).
B13: Croissance des nouvelles inscriptions | C13: ='02_Parametres'!D7 | D13: Objectif de recrutement vs N-1, porté par le marketing et l'ouverture de programmes.
B14: Hausse tarifaire moyenne | C14: ='02_Parametres'!D8 | D14: Revalorisation des frais de scolarité, alignée sur le positionnement et l'inflation.
B15: Ratio d'encadrement (étudiants / ETP enseignant) | C15: ='02_Parametres'!D9 | D15: Pilote la masse salariale enseignante. Plus élevé = plus efficient.
B16: Politique salariale (augmentation) | C16: ='02_Parametres'!D10 | D16: Revalorisation moyenne des rémunérations chargées.
B17: Inflation des charges | C17: ='02_Parametres'!D11 | D17: Appliquée aux loyers et autres charges d'exploitation.
B18: Coût d'acquisition marketing (CAC) | C18: ='02_Parametres'!D12 | D18: Dépense marketing moyenne par nouvel inscrit.
B20: 3. Règles de gestion du modèle
B21: Effectif budgété = Effectif N-1 × taux de réinscription + Nouvelles inscriptions N-1 × (1 + croissance).
B22: Chiffre d'affaires = Effectif × tarif revalorisé + frais de dossier + autres produits par étudiant.
B23: Masse salariale = (Effectif / ratio d'encadrement) × coût enseignant chargé + ETP admin × coût admin,
B24: coûts revalorisés de la politique salariale.
B25: Marketing = Nouvelles inscriptions × CAC. Loyers & autres charges revalorisés de l'inflation.
B26: EBITDA = CA − Masse salariale − Loyers − Marketing − Autres charges. EBIT = EBITDA − D&A.

Sheet 02_Parametres
B2: Paramètres & Scénarios de simulation
B3: Scénario actif : | C3: Cadrage | E3: ◄ Choisir ici : le modèle entier bascule automatiquement.
B5: Levier de simulation | C5: Unité | D5: Cadrage | E5: Optimiste | F5: Prudent | G5: ACTIF
B6: Taux de réinscription (progression nette) | C6: % | D6: 0.62 | E6: 0.66 | F6: 0.58 | G6: =INDEX(D6:F6,MATCH($C$3,$D$5:$F$5,0))
B7: Croissance des nouvelles inscriptions | C7: % | D7: 0.06 | E7: 0.12 | F7: 0 | G7: =INDEX(D7:F7,MATCH($C$3,$D$5:$F$5,0))
B8: Hausse tarifaire moyenne | C8: % | D8: 0.03 | E8: 0.04 | F8: 0.02 | G8: =INDEX(D8:F8,MATCH($C$3,$D$5:$F$5,0))
B9: Ratio d'encadrement (étud./ETP ens.) | C9: nb | D9: 18 | E9: 19 | F9: 17 | G9: =INDEX(D9:F9,MATCH($C$3,$D$5:$F$5,0))
B10: Politique salariale (augmentation) | C10: % | D10: 0.025 | E10: 0.02 | F10: 0.03 | G10: =INDEX(D10:F10,MATCH($C$3,$D$5:$F$5,0))
B11: Inflation des charges | C11: % | D11: 0.02 | E11: 0.015 | F11: 0.03 | G11: =INDEX(D11:F11,MATCH($C$3,$D$5:$F$5,0))
B12: Coût d'acquisition marketing (CAC) | C12: € | D12: 900 | E12: 780 | F12: 1100 | G12: =INDEX(D12:F12,MATCH($C$3,$D$5:$F$5,0))
B13: Constantes de référence (communes aux scénarios)
B14: Coût chargé enseignant (€/ETP) | D14: 52000 | G14: =D14
B15: Coût chargé administratif (€/ETP) | D15: 42000 | G15: =D15
B16: Autres charges par étudiant (€) | D16: 600 | G16: =D16
B17: Autres produits par étudiant (€) | D17: 150 | G17: =D17
B18: Frais de dossier par nouvel inscrit (€) | D18: 90 | G18: =D18
B20: Bleu = saisie modifiable · Gris clair = valeur active utilisée par le moteur.

Sheet 03_Referentiel
B2: Référentiel — Dimensions (mapping Tagetik)
B4: Dimension ENTITÉ : Groupe → Marque → Campus
B5: Code entité | C5: Marque / École | D5: Campus (ville) | E5: Niveau | F5: Devise
B6: GRP-EDU | C6: EDUSERVICES GROUP | D6: — | E6: Groupe | F6: EUR
B7: MDS-NAN | C7: MyDigitalSchool | D7: Nantes | E7: Campus | F7: EUR
B8: MDS-PAR | C8: MyDigitalSchool | D8: Paris | E8: Campus | F8: EUR
B9: MDS-LYO | C9: MyDigitalSchool | D9: Lyon | E9: Campus | F9: EUR
B10: MDS-BOR | C10: MyDigitalSchool | D10: Bordeaux | E10: Campus | F10: EUR
B11: WSS-PAR | C11: Win Sport School | D11: Paris | E11: Campus | F11: EUR
B12: WSS-LYO | C12: Win Sport School | D12: Lyon | E12: Campus | F12: EUR
B13: IHE-NAN | C13: IHECF | D13: Nantes | E13: Campus | F13: EUR
B14: IHE-TLS | C14: IHECF | D14: Toulouse | E14: Campus | F14: EUR
B15: MOD-PAR | C15: MODART International | D15: Paris | E15: Campus | F15: EUR
B16: MOD-LYO | C16: MODART International | D16: Lyon | E16: Campus | F16: EUR
... B18: ESI-MTP | C18: ESIS | D18: Montpellier | E18: Campus | F18: EUR
B20: Dimension COMPTE (Account) — plan simplifié
B21: Compte | C21: Libellé | D21: Type | E21: Signe | F21: Rubrique P&L
B22: 70600 | C22: Scolarité | D22: Produit | E22: + | F22: Chiffre d'affaires
B23: 70800 | C23: Frais de dossier | D23: Produit | E23: + | F23: Chiffre d'affaires
B24: 70900 | C24: Autres produits | D24: Produit | E24: + | F24: Chiffre d'affaires
B25: 64000 | C25: Masse salariale | D25: Charge | E25: - | F25: Charges de personnel
B26: 61300 | C26: Loyers & charges locatives | D26: Charge | E26: - | F26: Charges externes
B27: 62300 | C27: Marketing & acquisition | D27: Charge | E27: - | F27: Charges externes
B28: 60000 | C28: Autres charges d'exploitation | D28: Charge | E28: - | F28: Charges externes
B29: 68000 | C29: Dotations amortissements (D&A) | D29: Charge | E29: - | F29: D&A

Sheet 04_Historique
A1: Réalisé N-1 par campus (base de cadrage)
A2: Cellules bleues = données réelles à saisir. Valeurs actuelles ILLUSTRATIVES.
A3: Code | B3: Marque / École | C3: Campus | D3: Effectif N-1 | E3: Nouv. inscrits N-1 | F3: Tarif moyen N-1 | G3: ETP admin | H3: Loyers N-1 | I3: D&A | J3: CA N-1 | K3: Masse sal. N-1 | L3: Marketing N-1 | M3: Autres ch. N-1 | N3: EBITDA N-1
A4: MDS-NAN | B4: MyDigitalSchool | C4: Nantes | D4: 620 | E4: 260 | F4: 7200 | G4: 9 | H4: 480000 | I4: 90000 | J4: 4580400 | K4: 2146000 | L4: 247000 | M4: 372000 | N4: 1335400
A5: MDS-PAR | B5: MyDigitalSchool | C5: Paris | D5: 880 | E5: 360 | F5: 7900 | G5: 12 | H5: 950000 | I5: 140000 | J5: 7116400 | K5: 3052000 | L5: 342000 | M5: 528000 | N5: 2244400
A6: MDS-LYO | B6: MyDigitalSchool | C6: Lyon | D6: 540 | E6: 230 | F6: 7400 | G6: 8 | H6: 520000 | I6: 80000 | J6: 4097700 | K6: 1896000 | L6: 218500 | M6: 324000 | N6: 1139200
A7: MDS-BOR | B7: MyDigitalSchool | C7: Bordeaux | D7: 360 | E7: 165 | F7: 7200 | G7: 6 | H7: 360000 | I7: 55000 | J7: 2660850 | K7: 1292000 | L7: 156750 | M7: 216000 | N7: 636100
A8: WSS-PAR | B8: Win Sport School | C8: Paris | D8: 430 | E8: 190 | F8: 8200 | G8: 7 | H8: 620000 | I8: 70000 | J8: 3607600 | K8: 1542000 | L8: 180500 | M8: 258000 | N8: 1007100
A9: WSS-LYO | B9: Win Sport School | C9: Lyon | D9: 300 | E9: 140 | F9: 7800 | G9: 5 | H9: 380000 | I9: 48000 | J9: 2397600 | K9: 1094000 | L9: 133000 | M9: 180000 | N9: 610600
A10: IHE-NAN | B10: IHECF | C10: Nantes | D10: 410 | E10: 150 | F10: 6900 | G10: 6 | H10: 300000 | I10: 40000 | J10: 2904000 | K10: 1448000 | L10: 142500 | M10: 246000 | N10: 767500
A11: IHE-TLS | B11: IHECF | C11: Toulouse | D11: 280 | E11: 120 | F11: 6700 | G11: 5 | H11: 260000 | I11: 35000 | J11: 1928800 | K11: 1042000 | L11: 114000 | M11: 168000 | N11: 344800
A12: MOD-PAR | B12: MODART International | C12: Paris | D12: 350 | E12: 150 | F12: 8600 | G12: 7 | H12: 700000 | I12: 95000 | J12: 3076000 | K12: 1282000 | L12: 142500 | M12: 210000 | N12: 741500
A13: MOD-LYO | B13: MODART International | C13: Lyon | D13: 230 | E13: 105 | F13: 8200 | G13: 4 | H13: 360000 | I13: 50000 | J13: 1929950 | K13: 844000 | L13: 99750 | M13: 138000 | N13: 488200
A14: ESI-LIL | B14: ESIS | C14: Lille | D14: 320 | E14: 150 | F14: 7000 | G14: 5 | H14: 300000 | I14: 42000 | J14: 2301500 | K14: 1146000 | L14: 142500 | M14: 192000 | N14: 521000
A15: ESI-MTP | B15: ESIS | C15: Montpellier | D15: 260 | E15: 125 | F15: 6800 | G15: 4 | H15: 250000 | I15: 33000 | J15: 1818250 | K15: 896000 | L15: 118750 | M15: 156000 | N15: 397500
A16: TOTAL GROUPE | D16: =SUM(D4:D15) | E16: =SUM(E4:E15) | G16: =SUM(G4:G15) | H16: =SUM(H4:H15) | I16: =SUM(I4:I15) | J16: =SUM(J4:J15) | K16: =SUM(K4:K15) | L16: =SUM(L4:L15) | M16: =SUM(M4:M15) | N16: =SUM(N4:N15)

Sheet 05_Moteur
A1: Moteur de budget N+1 par campus (calcul par inducteurs)
A2: 100% formules. Réagit aux leviers de 02_Parametres et au réalisé de 04_Historique.
A3: Code | B3: Marque / École | C3: Campus | D3: Réinscrits | E3: Nouv. inscrits | F3: Effectif budget | G3: Tarif moyen | H3: Scolarité | I3: Frais dossier | J3: Autres produits | K3: CA Budget | L3: ETP enseignants | M3: ETP admin | N3: MS enseignants | O3: MS admin | P3: Masse salariale | Q3: Loyers | R3: Marketing | S3: Autres charges | T3: EBITDA | U3: D&A | V3: EBIT | W3: Marge EBITDA % | X3: CA / étudiant
A4: ='04_Historique'!A4 | B4: ='04_Historique'!B4 | C4: ='04_Historique'!C4 | D4: ='04_Historique'!D4*'02_Parametres'!$G$6 | E4: ='04_Historique'!E4*(1+'02_Parametres'!$G$7) | F4: =D4+E4 | G4: ='04_Historique'!F4*(1+'02_Parametres'!$G$8) | H4: =F4*G4 | I4: =E4*'02_Parametres'!$D$18 | J4: =F4*'02_Parametres'!$D$17 | K4: =H4+I4+J4 | L4: =F4/'02_Parametres'!$G$9 | M4: ='04_Historique'!G4 | N4: =L4*'02_Parametres'!$D$14*(1+'02_Parametres'!$G$10) | O4: =M4*'02_Parametres'!$D$15*(1+'02_Parametres'!$G$10) | P4: =N4+O4 | Q4: ='04_Historique'!H4*(1+'02_Parametres'!$G$11) | R4: =E4*'02_Parametres'!$G$12 | S4: =F4*'02_Parametres'!$D$16*(1+'02_Parametres'!$G$11) | T4: =K4-P4-Q4-R4-S4 | U4: ='04_Historique'!I4 | V4: =T4-U4 | W4: =IFERROR(T4/K4,0) | X4: =IFERROR(K4/F4,0)
A5: ='04_Historique'!A5 | B5: ='04_Historique'!B5 | C5: ='04_Historique'!C5 | D5: ='04_Historique'!D5*'02_Parametres'!$G$6 | E5: ='04_Historique'!E5*(1+'02_Parametres'!$G$7) | F5: =D5+E5 | G5: ='04_Historique'!F5*(1+'02_Parametres'!$G$8) | H5: =F5*G5 | I5: =E5*'02_Parametres'!$D$18 | J5: =F5*'02_Parametres'!$D$17 | K5: =H5+I5+J5 | L5: =F5/'02_Parametres'!$G$9 | M5: ='04_Historique'!G5 | N5: =L5*'02_Parametres'!$D$14*(1+'02_Parametres'!$G$10) | O5: =M5*'02_Parametres'!$D$15*(1+'02_Parametres'!$G$10) | P5: =N5+O5 | Q5: ='04_Historique'!H5*(1+'02_Parametres'!$G$11) | R5: =E5*'02_Parametres'!$G$12 | S5: =F5*'02_Parametres'!$D$16*(1+'02_Parametres'!$G$11) | T5: =K5-P5-Q5-R5-S5 | U5: ='04_Historique'!I5 | V5: =T5-U5 | W5: =IFERROR(T5/K5,0) | X5: =IFERROR(K5/F5,0)
A6: ='04_Historique'!A6 | B6: ='04_Historique'!B6 | C6: ='04_Historique'!C6 | D6: ='04_Historique'!D6*'02_Parametres'!$G$6 | E6: ='04_Historique'!E6*(1+'02_Parametres'!$G$7) | F6: =D6+E6 | G6: ='04_Historique'!F6*(1+'02_Parametres'!$G$8) | H6: =F6*G6 | I6: =E6*'02_Parametres'!$D$18 | J6: =F6*'02_Parametres'!$D$17 | K6: =H6+I6+J6 | L6: =F6/'02_Parametres'!$G$9 | M6: ='04_Historique'!G6 | N6: =L6*'02_Parametres'!$D$14*(1+'02_Parametres'!$G$10) | O6: =M6*'02_Parametres'!$D$15*(1+'02_Parametres'!$G$10) | P6: =N6+O6 | Q6: ='04_Historique'!H6*(1+'02_Parametres'!$G$11) | R6: =E6*'02_Parametres'!$G$12 | S6: =F6*'02_Parametres'!$D$16*(1+'02_Parametres'!$G$11) | T6: =K6-P6-Q6-R6-S6 | U6: ='04_Historique'!I6 | V6: =T6-U6 | W6: =IFERROR(T6/K6,0) | X6: =IFERROR(K6/F6,0)
A7: ='04_Historique'!A7 | B7: ='04_Historique'!B7 | C7: ='04_Historique'!C7 | D7: ='04_Historique'!D7*'02_Parametres'!$G$6 | E7: ='04_Historique'!E7*(1+'02_Parametres'!$G$7) | F7: =D7+E7 | G7: ='04_Historique'!F7*(1+'02_Parametres'!$G$8) | H7: =F7*G7 | I7: =E7*'02_Parametres'!$D$18 | J7: =F7*'02_Parametres'!$D$17 | K7: =H7+I7+J7 | L7: =F7/'02_Parametres'!$G$9 | M7: ='04_Historique'!G7 | N7: =L7*'02_Parametres'!$D$14*(1+'02_Parametres'!$G$10) | O7: =M7*'02_Parametres'!$D$15*(1+'02_Parametres'!$G$10) | P7: =N7+O7 | Q7: ='04_Historique'!H7*(1+'02_Parametres'!$G$11) | R7: =E7*'02_Parametres'!$G$12 | S7: =F7*'02_Parametres'!$D$16*(1+'02_Parametres'!$G$11) | T7: =K7-P7-Q7-R7-S7 | U7: ='04_Historique'!I7 | V7: =T7-U7 | W7: =IFERROR(T7/K7,0) | X7: =IFERROR(K7/F7,0)
A8: ='04_Historique'!A8 | B8: ='04_Historique'!B8 | C8: ='04_Historique'!C8 | D8: ='04_Historique'!D8*'02_Parametres'!$G$6 | E8: ='04_Historique'!E8*(1+'02_Parametres'!$G$7) | F8: =D8+E8 | G8: ='04_Historique'!F8*(1+'02_Parametres'!$G$8) | H8: =F8*G8 | I8: =E8*'02_Parametres'!$D$18 | J8: =F8*'02_Parametres'!$D$17 | K8: =H8+I8+J8 | L8: =F8/'02_Parametres'!$G$9 | M8: ='04_Historique'!G8 | N8: =L8*'02_Parametres'!$D$14*(1+'02_Parametres'!$G$10) | O8: =M8*'02_Parametres'!$D$15*(1+'02_Parametres'!$G$10) | P8: =N8+O8 | Q8: ='04_Historique'!H8*(1+'02_Parametres'!$G$11) | R8: =E8*'02_Parametres'!$G$12 | S8: =F8*'02_Parametres'!$D$16*(1+'02_Parametres'!$G$11) | T8: =K8-P8-Q8-R8-S8 | U8: ='04_Historique'!I8 | V8: =T8-U8 | W8: =IFERROR(T8/K8,0) | X8: =IFERROR(K8/F8,0)
A9: ='04_Historique'!A9 | B9: ='04_Historique'!B9 | C9: ='04_Historique'!C9 | D9: ='04_Historique'!D9*'02_Parametres'!$G$6 | E9: ='04_Historique'!E9*(1+'02_Parametres'!$G$7) | F9: =D9+E9 | G9: ='04_Historique'!F9*(1+'02_Parametres'!$G$8) | H9: =F9*G9 | I9: =E9*'02_Parametres'!$D$18 | J9: =F9*'02_Parametres'!$D$17 | K9: =H9+I9+J9 | L9: =F9/'02_Parametres'!$G$9 | M9: ='04_Historique'!G9 | N9: =L9*'02_Parametres'!$D$14*(1+'02_Parametres'!$G$10) | O9: =M9*'02_Parametres'!$D$15*(1+'02_Parametres'!$G$10) | P9: =N9+O9 | Q9: ='04_Historique'!H9*(1+'02_Parametres'!$G$11) | R9: =E9*'02_Parametres'!$G$12 | S9: =F9*'02_Parametres'!$D$16*(1+'02_Parametres'!$G$11) | T9: =K9-P9-Q9-R9-S9 | U9: ='04_Historique'!I9 | V9: =T9-U9 | W9: =IFERROR(T9/K9,0) | X9: =IFERROR(K9/F9,0)
A10: ='04_Historique'!A10 | B10: ='04_Historique'!B10 | C10: ='04_Historique'!C10 | D10: ='04_Historique'!D10*'02_Parametres'!$G$6 | E10: ='04_Historique'!E10*(1+'02_Parametres'!$G$7) | F10: =D10+E10 | G10: ='04_Historique'!F10*(1+'02_Parametres'!$G$8) | H10: =F10*G10 | I10: =E10*'02_Parametres'!$D$18 | J10: =F10*'02_Parametres'!$D$17 | K10: =H10+I10+J10 | L10: =F10/'02_Parametres'!$G$9 | M10: ='04_Historique'!G10 | N10: =L10*'02_Parametres'!$D$14*(1+'02_Parametres'!$G$10) | O10: =M10*'02_Parametres'!$D$15*(1+'02_Parametres'!$G$10) | P10: =N10+O10 | Q10: ='04_Historique'!H10*(1+'02_Parametres'!$G$11) | R10: =E10*'02_Parametres'!$G$12 | S10: =F10*'02_Parametres'!$D$16*(1+'02_Parametres'!$G$11) | T10: =K10-P10-Q10-R10-S10 | U10: ='04_Historique'!I10 | V10: =T10-U10 | W10: =IFERROR(T10/K10,0) | X10: =IFERROR(K10/F10,0)
A11: ='04_Historique'!A11 | B11: ='04_Historique'!B11 | C11: ='04_Historique'!C11 | D11: ='04_Historique'!D11*'02_Parametres'!$G$6 | E11: ='04_Historique'!E11*(1+'02_Parametres'!$G$7) | F11: =D11+E11 | G11: ='04_Historique'!F11*(1+'02_Parametres'!$G$8) | H11: =F11*G11 | I11: =E11*'02_Parametres'!$D$18 | J11: =F11*'02_Parametres'!$D$17 | K11: =H11+I11+J11 | L11: =F11/'02_Parametres'!$G$9 | M11: ='04_Historique'!G11 | N11: =L11*'02_Parametres'!$D$14*(1+'02_Parametres'!$G$10) | O11: =M11*'02_Parametres'!$D$15*(1+'02_Parametres'!$G$10) | P11: =N11+O11 | Q11: ='04_Historique'!H11*(1+'02_Parametres'!$G$11) | R11: =E11*'02_Parametres'!$G$12 | S11: =F11*'02_Parametres'!$D$16*(1+'02_Parametres'!$G$11) | T11: =K11-P11-Q11-R11-S11 | U11: ='04_Historique'!I11 | V11: =T11-U11 | W11: =IFERROR(T11/K11,0) | X11: =IFERROR(K11/F11,0)
A12: ='04_Historique'!A12 | B12: ='04_Historique'!B12 | C12: ='04_Historique'!C12 | D12: ='04_Historique'!D12*'02_Parametres'!$G$6 | E12: ='04_Historique'!E12*(1+'02_Parametres'!$G$7) | F12: =D12+E12 | G12: ='04_Historique'!F12*(1+'02_Parametres'!$G$8) | H12: =F12*G12 | I12: =E12*'02_Parametres'!$D$18 | J12: =F12*'02_Parametres'!$D$17 | K12: =H12+I12+J12 | L12: =F12/'02_Parametres'!$G$9 | M12: ='04_Historique'!G12 | N12: =L12*'02_Parametres'!$D$14*(1+'02_Parametres'!$G$10) | O12: =M12*'02_Parametres'!$D$15*(1+'02_Parametres'!$G$10) | P12: =N12+O12 | Q12: ='04_Historique'!H12*(1+'02_Parametres'!$G$11) | R12: =E12*'02_Parametres'!$G$12 | S12: =F12*'02_Parametres'!$D$16*(1+'02_Parametres'!$G$11) | T12: =K12-P12-Q12-R12-S12 | U12: ='04_Historique'!I12 | V12: =T12-U12 | W12: =IFERROR(T12/K12,0) | X12: =IFERROR(K12/F12,0)
A13: ='04_Historique'!A13 | B13: ='04_Historique'!B13 | C13: ='04_Historique'!C13 | D13: ='04_Historique'!D13*'02_Parametres'!$G$6 | E13: ='04_Historique'!E13*(1+'02_Parametres'!$G$7) | F13: =D13+E13 | G13: ='04_Historique'!F13*(1+'02_Parametres'!$G$8) | H13: =F13*G13 | I13: =E13*'02_Parametres'!$D$18 | J13: =F13*'02_Parametres'!$D$17 | K13: =H13+I13+J13 | L13: =F13/'02_Parametres'!$G$9 | M13: ='04_Historique'!G13 | N13: =L13*'02_Parametres'!$D$14*(1+'02_Parametres'!$G$10) | O13: =M13*'02_Parametres'!$D$15*(1+'02_Parametres'!$G$10) | P13: =N13+O13 | Q13: ='04_Historique'!H13*(1+'02_Parametres'!$G$11) | R13: =E13*'02_Parametres'!$G$12 | S13: =F13*'02_Parametres'!$D$16*(1+'02_Parametres'!$G$11) | T13: =K13-P13-Q13-R13-S13 | U13: ='04_Historique'!I13 | V13: =T13-U13 | W13: =IFERROR(T13/K13,0) | X13: =IFERROR(K13/F13,0)
A14: ='04_Historique'!A14 | B14: ='04_Historique'!B14 | C14: ='04_Historique'!C14 | D14: ='04_Historique'!D14*'02_Parametres'!$G$6 | E14: ='04_Historique'!E14*(1+'02_Parametres'!$G$7) | F14: =D14+E14 | G14: ='04_Historique'!F14*(1+'02_Parametres'!$G$8) | H14: =F14*G14 | I14: =E14*'02_Parametres'!$D$18 | J14: =F14*'02_Parametres'!$D$17 | K14: =H14+I14+J14 | L14: =F14/'02_Parametres'!$G$9 | M14: ='04_Historique'!G14 | N14: =L14*'02_Parametres'!$D$14*(1+'02_Parametres'!$G$10) | O14: =M14*'02_Parametres'!$D$15*(1+'02_Parametres'!$G$10) | P14: =N14+O14 | Q14: ='04_Historique'!H14*(1+'02_Parametres'!$G$11) | R14: =E14*'02_Parametres'!$G$12 | S14: =F14*'02_Parametres'!$D$16*(1+'02_Parametres'!$G$11) | T14: =K14-P14-Q14-R14-S14 | U14: ='04_Historique'!I14 | V14: =T14-U14 | W14: =IFERROR(T14/K14,0) | X14: =IFERROR(K14/F14,0)
A15: ='04_Historique'!A15 | B15: ='04_Historique'!B15 | C15: ='04_Historique'!C15 | D15: ='04_Historique'!D15*'02_Parametres'!$G$6 | E15: ='04_Historique'!E15*(1+'02_Parametres'!$G$7) | F15: =D15+E15 | G15: ='04_Historique'!F15*(1+'02_Parametres'!$G$8) | H15: =F15*G15 | I15: =E15*'02_Parametres'!$D$18 | J15: =F15*'02_Parametres'!$D$17 | K15: =H15+I15+J15 | L15: =F15/'02_Parametres'!$G$9 | M15: ='04_Historique'!G15 | N15: =L15*'02_Parametres'!$D$14*(1+'02_Parametres'!$G$10) | O15: =M15*'02_Parametres'!$D$15*(1+'02_Parametres'!$G$10) | P15: =N15+O15 | Q15: ='04_Historique'!H15*(1+'02_Parametres'!$G$11) | R15: =E15*'02_Parametres'!$G$12 | S15: =F15*'02_Parametres'!$D$16*(1+'02_Parametres'!$G$11) | T15: =K15-P15-Q15-R15-S15 | U15: ='04_Historique'!I15 | V15: =T15-U15 | W15: =IFERROR(T15/K15,0) | X15: =IFERROR(K15/F15,0)
A16: TOTAL GROUPE | D16: =SUM(D4:D15) | E16: =SUM(E4:E15) | F16: =SUM(F4:F15) | H16: =SUM(H4:H15) | I16: =SUM(I4:I15) | J16: =SUM(J4:J15) | K16: =SUM(K4:K15) | L16: =SUM(L4:L15) | M16: =SUM(M4:M15) | N16: =SUM(N4:N15) | O16: =SUM(O4:O15) | ... V16: =SUM(V4:V15) | W16: =IFERROR(T16/K16,0) | X16: =IFERROR(K16/F16,0)

Sheet 06_PnL
B2: Compte de résultat — Groupe (Budget N+1 vs Réalisé N-1)
B3: Scénario actif : | C3: ='02_Parametres'!C3
B5: Rubrique | C5: Réalisé N-1 | D5: Budget N+1 | E5: Écart € | F5: Écart %
B6: Effectifs (nb) | C6: ='04_Historique'!D16 | D6: ='05_Moteur'!F16 | E6: =D6-C6 | F6: =IFERROR(D6/C6-1,0)
B7: Chiffre d'affaires | C7: ='04_Historique'!J16 | D7: ='05_Moteur'!K16 | E7: =D7-C7 | F7: =IFERROR(D7/C7-1,0)
B8: Masse salariale | C8: =-'04_Historique'!K16 | D8: =-'05_Moteur'!P16 | E8: =D8-C8 | F8: =IFERROR(D8/C8-1,0)
B9: Loyers | C9: =-'04_Historique'!H16 | D9: =-'05_Moteur'!Q16 | E9: =D9-C9 | F9: =IFERROR(D9/C9-1,0)
B10: Marketing | C10: =-'04_Historique'!L16 | D10: =-'05_Moteur'!R16 | E10: =D10-C10 | F10: =IFERROR(D10/C10-1,0)
B11: Autres charges | C11: =-'04_Historique'!M16 | D11: =-'05_Moteur'!S16 | E11: =D11-C11 | F11: =IFERROR(D11/C11-1,0)
B12: EBITDA | C12: ='04_Historique'!N16 | D12: ='05_Moteur'!T16 | E12: =D12-C12 | F12: =IFERROR(D12/C12-1,0)
B13: Marge EBITDA % | C13: =IFERROR('04_Historique'!N16/'04_Historique'!J16,0) | D13: =IFERROR('05_Moteur'!T16/'05_Moteur'!K16,0) | E13: =D13-C13
B14: D&A | C14: =-'04_Historique'!I16 | D14: =-'05_Moteur'!U16 | E14: =D14-C14 | F14: =IFERROR(D14/C14-1,0)
B15: EBIT | C15: ='04_Historique'!N16-'04_Historique'!I16 | D15: ='05_Moteur'!V16 | E15: =D15-C15 | F15: =IFERROR(D15/C15-1,0)
B17: Synthèse par marque / école
B18: Marque / École | C18: CA Budget | D18: EBITDA Budget | E18: Marge EBITDA % | F18: Δ CA vs N-1
B19: MyDigitalSchool | C19: =SUMIF('05_Moteur'!$B$4:$B$15,"MyDigitalSchool",'05_Moteur'!$K$4:$K$15) | D19: =SUMIF('05_Moteur'!$B$4:$B$15,"MyDigitalSchool",'05_Moteur'!$T$4:$T$15) | E19: =IFERROR(D19/C19,0) | F19: =IFERROR(C19/SUMIF('04_Historique'!$B$4:$B$15,"MyDigitalSchool",'04_Historique'!$J$4:$J$15)-1,0)
B20: Win Sport School | C20: =SUMIF('05_Moteur'!$B$4:$B$15,"Win Sport School",'05_Moteur'!$K$4:$K$15) | D20: =SUMIF('05_Moteur'!$B$4:$B$15,"Win Sport School",'05_Moteur'!$T$4:$T$15) | E20: =IFERROR(D20/C20,0) | F20: =IFERROR(C20/SUMIF('04_Historique'!$B$4:$B$15,"Win Sport School",'04_Historique'!$J$4:$J$15)-1,0)
B21: IHECF | C21: =SUMIF('05_Moteur'!$B$4:$B$15,"IHECF",'05_Moteur'!$K$4:$K$15) | D21: =SUMIF('05_Moteur'!$B$4:$B$15,"IHECF",'05_Moteur'!$T$4:$T$15) | E21: =IFERROR(D21/C21,0) | F21: =IFERROR(C21/SUMIF('04_Historique'!$B$4:$B$15,"IHECF",'04_Historique'!$J$4:$J$15)-1,0)
B22: MODART International | C22: =SUMIF('05_Moteur'!$B$4:$B$15,"MODART International",'05_Moteur'!$K$4:$K$15) | D22: =SUMIF('05_Moteur'!$B$4:$B$15,"MODART International",'05_Moteur'!$T$4:$T$15) | E22: =IFERROR(D22/C22,0) | F22: =IFERROR(C22/SUMIF('04_Historique'!$B$4:$B$15,"MODART International",'04_Historique'!$J$4:$J$15)-1,0)
B23: ESIS | C23: =SUMIF('05_Moteur'!$B$4:$B$15,"ESIS",'05_Moteur'!$K$4:$K$15) | D23: =SUMIF('05_Moteur'!$B$4:$B$15,"ESIS",'05_Moteur'!$T$4:$T$15) | E23: =IFERROR(D23/C23,0) | F23: =IFERROR(C23/SUMIF('04_Historique'!$B$4:$B$15,"ESIS",'04_Historique'!$J$4:$J$15)-1,0)
B24: TOTAL | C24: =SUM(C19:C23) | D24: =SUM(D19:D23) | E24: =IFERROR(D24/C24,0)

Sheet 07_Simulation
B2: Tableau de bord — Simulation budgétaire
B3: Change le scénario en 02_Parametres!C3 et tous les indicateurs ci-dessous se recalculent.
B4: Scénario actif : | C4: ='02_Parametres'!C3
B6: Indicateurs clés — Budget N+1
B7: Indicateur | C7: Budget N+1 | D7: Réalisé N-1 | E7: Évolution
B8: Effectif total (nb) | C8: ='05_Moteur'!F16 | D8: ='04_Historique'!D16 | E8: =IFERROR('05_Moteur'!F16/'04_Historique'!D16-1,0)
B9: Chiffre d'affaires | C9: ='05_Moteur'!K16 | D9: ='04_Historique'!J16 | E9: =IFERROR('05_Moteur'!K16/'04_Historique'!J16-1,0)
B10: EBITDA | C10: ='05_Moteur'!T16 | D10: ='04_Historique'!N16 | E10: =IFERROR('05_Moteur'!T16/'04_Historique'!N16-1,0)
B11: Marge EBITDA % | C11: =IFERROR('05_Moteur'!T16/'05_Moteur'!K16,0) | D11: =IFERROR('04_Historique'!N16/'04_Historique'!J16,0) | E11: =IFERROR(C11/D11-1,0)
B12: EBIT | C12: ='05_Moteur'!V16 | D12: ='04_Historique'!N16-'04_Historique'!I16 | E12: =IFERROR(C12/D12-1,0)
B13: CA / étudiant | C13: =IFERROR('05_Moteur'!K16/'05_Moteur'!F16,0) | D13: =IFERROR('04_Historique'!J16/'04_Historique'!D16,0) | E13: =IFERROR(C13/D13-1,0)
B15: Comparatif des scénarios (rappel des hypothèses)
B16: Levier | C16: Cadrage | D16: Optimiste | E16: Prudent | F16: Actif
B17: Réinscription | C17: ='02_Parametres'!D6 | D17: ='02_Parametres'!E6 | E17: ='02_Parametres'!F6 | F17: ='02_Parametres'!G6
B18: Croissance recrut. | C18: ='02_Parametres'!D7 | D18: ='02_Parametres'!E7 | E18: ='02_Parametres'!F7 | F18: ='02_Parametres'!G7
B19: Hausse tarifaire | C19: ='02_Parametres'!D8 | D19: ='02_Parametres'!E8 | E19: ='02_Parametres'!F8 | F19: ='02_Parametres'!G8
B20: Ratio encadrement | C20: ='02_Parametres'!D9 | D20: ='02_Parametres'!E9 | E20: ='02_Parametres'!F9 | F20: ='02_Parametres'!G9
B21: Politique salariale | C21: ='02_Parametres'!D10 | D21: ='02_Parametres'!E10 | E21: ='02_Parametres'!F10 | F21: ='02_Parametres'!G10
B22: Inflation charges | C22: ='02_Parametres'!D11 | D22: ='02_Parametres'!E11 | E22: ='02_Parametres'!F11 | F22: ='02_Parametres'!G11
B23: CAC (€) | C23: ='02_Parametres'!D12 | D23: ='02_Parametres'!E12 | E23: ='02_Parametres'!F12 | F23: ='02_Parametres'!G12

Sheet 08_Mapping_Tagetik
B2: Passerelle vers CCH Tagetik
B3: Correspondance entre le modèle Excel et les objets Tagetik pour l'implémentation.
B5: Dimensions
B6: Concept du modèle | C6: Dimension Tagetik | D6: Détail / valeurs
B7: Campus | C7: Entity | D7: GRP-EDU → marques → campus (voir 03_Referentiel). Hiérarchie de consolidation.
B8: Compte P&L | C8: Account | D8: Plan de comptes 03_Referentiel (70600, 64000…) rattaché à l'arbre Account.
B9: Budget N+1 / Réalisé N-1 | C9: Category | D9: Category = ACTUAL (N-1) et BUDGET (N+1). Scénarios = versions/Category dédiées.
B10: Année budgétaire | C10: Period / Year | D10: Budget annuel : Period = FY. Détail mensuel possible via allocation Tagetik.
B11: Scénario (Cadrage/Opt/Prudent) | C11: Category ou Custom dim. | D11: Un jeu de valeurs par scénario ; en Excel via le sélecteur 02_Parametres!C3.
B12: Effectifs, ETP, ratio, CAC | C12: Comptes techniques / drivers | D12: Stockés comme comptes non-financiers (statistiques) pour le calcul piloté par inducteurs.
B14: Étapes d'implémentation recommandées
B15: 1. Créer/valider les dimensions Entity (campus→marque→groupe) et Account.
B16: 2. Charger le réalisé N-1 (Category ACTUAL) depuis 04_Historique.
B17: 3. Traduire les inducteurs (02_Parametres) en formules de calcul / règles Tagetik.
B18: 4. Rejouer le budget par campus (logique de 05_Moteur) et vérifier vs 06_PnL.
B19: 5. Décliner les scénarios en versions et automatiser la simulation.
