Workbook

Sheet 00_Notice
B2: EDUSERVICES GROUP — Pilotage budgétaire (v2)
B3: Cohortes · marketing mesuré sur l'historique · maille programme×année · cadrage cible · simulateur de décisions
B5: Les feuilles
B6: 01_Cadrage | C6: POSTE DE COMMANDE CFO : cadrage top-down (N-2 · atterrissage · objectif · budget · écart) + leviers %/scénarios + coefficients + graphes
B7: DATA_Referentiel | C7: RÉFÉRENTIEL Tagetik : dimensions CODE · DESCRIPTION · hiérarchies (Entité, Compte, Version, Programme, Année, Modalité, Période)
B8: DATA_Chargement | C8: TABLE DE FAITS Tagetik (format long) : entité×programme×année×modalité × compte × version — structure allouée jusqu'à la classe
B9: 04_Referentiel | C9: Dimensions : entités, comptes (fixe/variable)
B10: 05_Param_Prog_Annee | C10: DONNÉES DE RÉFÉRENCE par programme×année (capacité, heures, taux, pédago, CAC variable, passage)
B11: 06_Historique | C11: Réalisé N-1 par cellule (funnel, cohorte) + historique marketing N-2/N-1 → élasticité mesurée
B12: 07_Structure | C12: Réalisé par campus (loyers, ETP, D&A, m²)
B13: 08_Moteur | C13: Moteur budget par cellule (cohortes, marketing→volume, seuil=point mort)
B14: 09_Allocation | C14: Frais de structure alloués par driver
B15: 10_PnL | C15: P&L consolidé N-1 vs Budget + pont à 4 effets
B16: 11_Simulateur | C16: Décisions ouvrir/fermer/redistribuer (maille PROMO) → EBITDA AVANT → APRÈS
B17: 11b_Mutualisation | C17: Mutualisation inter-sections (maille CAMPUS) : sections économisables & économie potentielle
... B21: 14_Mapping_Tagetik | C21: Passerelle Tagetik
B23: Légende
B24: exemple | C24: Saisie / donnée réelle
B25: exemple | C25: Formule
B26: exemple | C26: Lien inter-feuilles
B27: exemple | C27: Hypothèse à remplir
B29: Marques/campus réels EDUSERVICES ; montants ILLUSTRATIFS calibrés sur des ordres de grandeur sourcés (scolarité 8-11 k€, NPEC ~7-10 k€, marge EBITDA ~20 %, classe ~30). À remplacer par le réel.
B32: Mode d'emploi — par où commencer
B33: 1 | C33: 01_Cadrage : choisis le SCÉNARIO et règle les leviers (%) ; pose l'objectif ; lis l'écart et le reste à trouver. Tout le budget se recalcule.
B34: 2 | C34: 08_Moteur : le budget se construit cellule par cellule (cohortes → marketing→volume → tarif → financement).
B35: 3 | C35: 10_PnL & 13_Simulation : lis le compte de résultat consolidé et les KPIs (Budget vs N-1).
B36: 4 | C36: 01_Cadrage (haut) : l'objectif vs le budget construit donne l'écart ; 12_Sensibilite : quel levier actionner pour combler l'écart.
B37: 5 | C37: 11 / 11b / 11c : simule des décisions (ouvrir / fermer / regrouper / mutualiser) — BAC À SABLE, sans impact sur le budget officiel.
B39: 3 façons d'utiliser le modèle
B40: Construire (bottom-up) | C40: Le budget monte tout seul depuis les drivers et l'historique — aucune saisie de résultat.
B41: Challenger | C41: Un directeur de campus ajuste SES effectifs / curseurs → version bottom-up à confronter au cadrage.
B42: Simuler | C42: Tester une ouverture / fermeture / mutualisation et voir l'impact EBITDA avant de trancher.
B44: 💡 Astuce : survole le TITRE d'un onglet pour lire son OBJET, et une ENTÊTE de colonne pour son explication. 🔵 bleu = à saisir · 🟡 jaune = hypothèse à remplir.

Sheet 01_Cadrage
B2: EDUSERVICES — Cadrage & pilotage TOP-DOWN (poste de commande CFO)
B3: Scénario actif : | D3: Cadrage | E3: ◄ bascule tout le budget
B4: Base de projection : | D4: Atterrissage N | E4: → facteur base : | F4: =IF($D$4="Réalisé N-1",$D$7/$E$7,1) | G4: (le budget construit projette depuis la base retenue)
B5: ① Cadrage top-down — N-2 · réalisé N-1 · atterrissage N · budget construit (base retenue) · objectif · écart | J5: ③ Coefficients stratégiques (marque × campus) — intensité marketing / prix
B6: Indicateur | C6: N-2 (réel) | D6: Réalisé N-1 | E6: Atterrissage N | F6: Budget construit | G6: 🟡 Objectif | H6: Écart | J6: Marque | K6: Ville | L6: Marketing | M6: Prix | N6: Posture | O6: Clé
B7: Chiffre d'affaires | C7: 17957736 | D7: 19035200 | E7: 19986960 | F7: =SUM('08_Moteur'!$AH$3:$AH$60)*$F$4 | G7: 21186178 | H7: =F7-G7 | J7: MBway | K7: Paris | L7: 1.2 | M7: 1 | N7: =IF(L7>=1.15,"Pousser",IF(L7<=0.85,"Défendre","Maintenir")) | O7: =J7&"|"&K7
B8: EBITDA | C8: 2478869 | D8: 2776333 | E8: 2915150 | F8: ='09_Allocation'!J20*$F$4 | G8: 3389788 | H8: =F8-G8 | J8: MBway | K8: Lyon | L8: 1.2 | M8: 1 | N8: =IF(L8>=1.15,"Pousser",IF(L8<=0.85,"Défendre","Maintenir")) | O8: =J8&"|"&K8
B9: Marge EBITDA % | C9: =IFERROR(C8/C7,0) | D9: =IFERROR(D8/D7,0) | E9: =IFERROR(E8/E7,0) | F9: =IFERROR(F8/F7,0) | G9: =IFERROR(G8/G7,0) | H9: =F9-G9 | J9: MBway | K9: Nantes | L9: 1.2 | M9: 1 | N9: =IF(L9>=1.15,"Pousser",IF(L9<=0.85,"Défendre","Maintenir")) | O9: =J9&"|"&K9
J10: MBway | K10: Bordeaux | L10: 1.2 | M10: 1 | N10: =IF(L10>=1.15,"Pousser",IF(L10<=0.85,"Défendre","Maintenir")) | O10: =J10&"|"&K10
B11: RESTE À TROUVER (EBITDA vs objectif) : | F11: =IF(G8-F8>0,G8-F8,0) | G11: =IF(G8-F8>0,"à combler","atteint") | J11: ISCOM | K11: Paris | L11: 1 | M11: 1.2 | N11: =IF(L11>=1.15,"Pousser",IF(L11<=0.85,"Défendre","Maintenir")) | O11: =J11&"|"&K11
J12: ISCOM | K12: Lille | L12: 1 | M12: 1.2 | N12: =IF(L12>=1.15,"Pousser",IF(L12<=0.85,"Défendre","Maintenir")) | O12: =J12&"|"&K12
B13: ② Leviers & hypothèses — varie en % · bascule par scénario (colonne ACTIF = scénario choisi) | J13: ISCOM | K13: Toulouse | L13: 1 | M13: 1.2 | N13: =IF(L13>=1.15,"Pousser",IF(L13<=0.85,"Défendre","Maintenir")) | O13: =J13&"|"&K13
J14: Ipac Bachelor Factory | K14: Nantes | L14: 1.3 | M14: 0.8 | N14: =IF(L14>=1.15,"Pousser",IF(L14<=0.85,"Défendre","Maintenir")) | O14: =J14&"|"&K14
B15: Paramètre | C15: Unité | D15: Base (atterr.) | E15: Cadrage | F15: Optimiste | G15: Prudent | H15: ACTIF | J15: Ipac Bachelor Factory | K15: Rennes | L15: 1.3 | M15: 0.8 | N15: =IF(L15>=1.15,"Pousser",IF(L15<=0.85,"Défendre","Maintenir")) | O15: =J15&"|"&K15
B16: Variation du budget marketing (→ volume) | C16: % | D16: 0 | E16: 0.1 | F16: 0.2 | G16: -0.05 | H16: =INDEX(E16:G16,MATCH($D$3,$E$15:$G$15,0)) | J16: Ipac Bachelor Factory | K16: Montpellier | L16: 1.3 | M16: 0.8 | N16: =IF(L16>=1.15,"Pousser",IF(L16<=0.85,"Défendre","Maintenir")) | O16: =J16&"|"&K16
B17: Hausse tarifaire (prix) | C17: % | D17: 0 | E17: 0.03 | F17: 0.04 | G17: 0.02 | H17: =INDEX(E17:G17,MATCH($D$3,$E$15:$G$15,0)) | J17: Pigier | K17: Lyon | L17: 0.7 | M17: 1 | N17: =IF(L17>=1.15,"Pousser",IF(L17<=0.85,"Défendre","Maintenir")) | O17: =J17&"|"&K17
B18: Gain de conversion admissions | C18: pts | D18: 0 | E18: 0.015 | F18: 0.04 | G18: 0 | H18: =INDEX(E18:G18,MATCH($D$3,$E$15:$G$15,0)) | J18: Pigier | K18: Bordeaux | L18: 0.7 | M18: 1 | N18: =IF(L18>=1.15,"Pousser",IF(L18<=0.85,"Défendre","Maintenir")) | O18: =J18&"|"&K18
B19: Amélioration du taux de passage | C19: pts | D19: 0 | E19: 0.01 | F19: 0.03 | G19: -0.01 | H19: =INDEX(E19:G19,MATCH($D$3,$E$15:$G$15,0)) | J19: Tunon | K19: Paris | L19: 1 | M19: 1.1 | N19: =IF(L19>=1.15,"Pousser",IF(L19<=0.85,"Défendre","Maintenir")) | O19: =J19&"|"&K19
B20: Inflation des charges (groupe) | C20: % | D20: 0 | E20: 0.02 | F20: 0.015 | G20: 0.03 | H20: =INDEX(E20:G20,MATCH($D$3,$E$15:$G$15,0)) | J20: Tunon | K20: Lyon | L20: 1 | M20: 1.1 | N20: =IF(L20>=1.15,"Pousser",IF(L20<=0.85,"Défendre","Maintenir")) | O20: =J20&"|"&K20
B21: Politique salariale (groupe) | C21: % | D21: 0 | E21: 0.025 | F21: 0.02 | G21: 0.03 | H21: =INDEX(E21:G21,MATCH($D$3,$E$15:$G$15,0))
B22: Constantes de référence — base = atterrissage · les 3 scénarios sont SAISISSABLES (€ : variation en % · taux : valeur en %)
B23: Coût chargé / ETP permanent | C23: € | D23: 58000 | E23: 0 | F23: 0 | G23: 0 | H23: =D23*(1+INDEX(E23:G23,MATCH($D$3,$E$15:$G$15,0)))
B24: Frais de dossier / nouvel inscrit | C24: € | D24: 90 | E24: 0 | F24: 0 | G24: 0 | H24: =D24*(1+INDEX(E24:G24,MATCH($D$3,$E$15:$G$15,0)))
B25: Frais de structure & marketing groupe (FIXE) | C25: € | D25: 2000000 | E25: 0 | F25: 0 | G25: 0 | H25: =D25*(1+INDEX(E25:G25,MATCH($D$3,$E$15:$G$15,0)))
B26: Autres charges d'exploitation / étudiant | C26: € | D26: 934 | E26: 0 | F26: 0 | G26: 0 | H26: =D26*(1+INDEX(E26:G26,MATCH($D$3,$E$15:$G$15,0)))
B27: Élasticité marketing (défaut) | C27: x | D27: 0.5 | E27: 0.5 | F27: 0.5 | G27: 0.5 | H27: =INDEX(E27:G27,MATCH($D$3,$E$15:$G$15,0))
B28: Conversion cand.→inscrit (défaut) | C28: % | D28: 0.372 | E28: 0.372 | F28: 0.372 | G28: 0.372 | H28: =INDEX(E28:G28,MATCH($D$3,$E$15:$G$15,0))
B32: Drivers d'allocation de la structure — en cascade (un driver par niveau)
B33: Groupe → MARQUE (par) : | D33: Chiffre d'affaires | E33: ◄ pilote l'allocation par campus (feuille 09)
B34: Marque → CAMPUS (par) : | D34: Effectifs
B35: Campus → PROGRAMME (par) : | D35: Nombre de classes | E35: ◄ pour l'allocation fine à la classe (feuille 11c)

Sheet DATA_Referentiel
B2: RÉFÉRENTIEL DES DIMENSIONS (à charger dans Tagetik) — CODE · DESCRIPTION · HIÉRARCHIE
B4: 1) Dimension ENTITÉ — hiérarchie Groupe → Marque → Campus
B5: Code | C5: Description | D5: Parent | E5: Niveau
B6: EDU | C6: EDUSERVICES (Groupe) | E6: Groupe
B7: MBWAY | C7: MBway | D7: EDU | E7: Marque
B8: ISCOM | C8: ISCOM | D8: EDU | E8: Marque
B9: IPAC | C9: Ipac Bachelor Factory | D9: EDU | E9: Marque
B10: PIGIER | C10: Pigier | D10: EDU | E10: Marque
B11: TUNON | C11: Tunon | D11: EDU | E11: Marque
B12: MBWAY_PAR | C12: MBway Paris | D12: MBWAY | E12: Campus
B13: MBWAY_LYO | C13: MBway Lyon | D13: MBWAY | E13: Campus
B14: MBWAY_NAN | C14: MBway Nantes | D14: MBWAY | E14: Campus
B15: MBWAY_BOR | C15: MBway Bordeaux | D15: MBWAY | E15: Campus
B16: ISCOM_PAR | C16: ISCOM Paris | D16: ISCOM | E16: Campus
B17: ISCOM_LIL | C17: ISCOM Lille | D17: ISCOM | E17: Campus
B18: ISCOM_TLS | C18: ISCOM Toulouse | D18: ISCOM | E18: Campus
... B25: TUNON_LYO | C25: Tunon Lyon | D25: TUNON | E25: Campus
B27: 2) Dimension COMPTE — hiérarchie P&L + statistiques (comptes comptables réels · codes techniques)
B28: Code | C28: Description | D28: Parent | E28: Type | F28: Sens
B29: PL | C29: Compte de résultat | E29: Noeud
B30: CA | C30: Chiffre d'affaires | D30: PL | E30: Noeud | F30: Produit
B31: COUTS_DIR | C31: Coûts directs évitables | D31: PL | E31: Noeud | F31: Charge
B32: STRUCTURE | C32: Structure (non-évitable) | D32: PL | E32: Noeud | F32: Charge
B33: AMORT | C33: Amortissements | D33: PL | E33: Noeud | F33: Charge
B34: STATS | C34: Statistiques (effectifs/flux) | E34: Noeud | F34: Technique
B35: INDUCT | C35: Inducteurs & prix unitaires | E35: Noeud | F35: Technique
B36: 706100 | C36: Droits de scolarité | D36: CA | E36: COMPTABLE | F36: Produit
B37: 708500 | C37: Frais de dossier / inscription | D37: CA | E37: COMPTABLE | F37: Produit
B38: 604100 | C38: Vacations & sous-traitance pédagogique | D38: COUTS_DIR | E38: COMPTABLE | F38: Charge
B39: 606300 | C39: Fournitures & ressources pédagogiques | D39: COUTS_DIR | E39: COMPTABLE | F39: Charge
B40: 623000 | C40: Publicité & marketing (acquisition) | D40: COUTS_DIR | E40: COMPTABLE | F40: Charge
B41: 613200 | C41: Locations immobilières (loyers) | D41: STRUCTURE | E41: COMPTABLE | F41: Charge
B42: 641100 | C42: Rémunérations du personnel permanent | D42: STRUCTURE | E42: COMPTABLE | F42: Charge
B43: 622600 | C43: Honoraires & frais de siège (structure groupe) | D43: STRUCTURE | E43: COMPTABLE | F43: Charge
B44: 606800 | C44: Autres achats & charges externes | D44: COUTS_DIR | E44: COMPTABLE | F44: Charge
B45: 681100 | C45: Dotations aux amortissements | D45: AMORT | E45: COMPTABLE | F45: Charge
B46: STA_EFF | C46: Effectif inscrit | D46: STATS | E46: TECHNIQUE | F46: Technique
B47: STA_CAND | C47: Candidatures reçues | D47: STATS | E47: TECHNIQUE | F47: Technique
... B57: CAC_LEAD | C57: Coût d'acquisition par lead | D57: INDUCT | E57: TECHNIQUE | F57: Technique
B59: 3) Dimension VERSION / SCÉNARIO — code Tagetik (année + type + version)
B60: Code | C60: Description | D60: Type | E60: Année
B61: 2023ACT_VDEF | C61: Réalisé 2023 (N-2) — version définitive | D61: Actual | E61: 2023
B62: 2024ACT_VDEF | C62: Réalisé 2024 (N-1) — version définitive | D62: Actual | E62: 2024
B63: 2025FCST_V4 | C63: Atterrissage 2025 — Forecast V4 | D63: Forecast | E63: 2025
B64: 2026BUD_V1 | C64: Budget 2026 — version 1 (construit par le modèle) | D64: Budget | E64: 2026
B66: 4) Dimension PROGRAMME
B67: Code | C67: Description | D67: Cycle | E67: Domaine
B68: BAC_MGT | C68: Bachelor Management | D68: Bachelor | E68: Management
B69: MAS_MGT | C69: Mastère Management | D69: Mastère | E69: Management
B70: BAC_COM | C70: Bachelor Communication | D70: Bachelor | E70: Communication
B71: MAS_COM | C71: Mastère Communication | D71: Mastère | E71: Communication
B72: BAC_CCE | C72: Bachelor Commerce | D72: Bachelor | E72: Commerce
B73: BTS_GES | C73: BTS Gestion | D73: BTS | E73: Commerce/RH
B74: BAC_RH | C74: Bachelor RH | D74: Bachelor | E74: Commerce/RH
B75: BAC_TOU | C75: Bachelor Tourisme | D75: Bachelor | E75: Tourisme
B77: 5) Dimension ANNÉE D'ÉTUDES
B78: Code | C78: Description | D78: Cycle
B79: B1 | C79: Bachelor 1 | D79: Bachelor
B80: B2 | C80: Bachelor 2 | D80: Bachelor
B81: B3 | C81: Bachelor 3 | D81: Bachelor
B82: M1 | C82: Mastère 1 | D82: Mastère
B83: M2 | C83: Mastère 2 | D83: Mastère
B84: BTS1 | C84: BTS 1re année | D84: BTS
B85: BTS2 | C85: BTS 2e année | D85: BTS
B87: 6) Dimension MODALITÉ
B88: Code | C88: Description
B89: INIT | C89: Formation initiale
B90: ALT | C90: Alternance
B92: 7) Dimension PÉRIODE
B93: Code | C93: Description | D93: Type
B94: 2023 | C94: Exercice 2023 (clos 31/08) | D94: Annuel
B95: 2024 | C95: Exercice 2024 | D95: Annuel
B96: 2025 | C96: Exercice 2025 | D96: Annuel
B97: 2026 | C97: Exercice 2026 | D97: Annuel

Sheet DATA_Chargement
B1: TABLE DE FAITS À CHARGER DANS TAGETIK — format long (une ligne = un croisement dimension × compte × version)
B2: Codes issus de DATA_Referentiel. Comptable = vrai compte PCG ; technique = code STA_/DRV_/PRX_/CAC_. Structure (loyers, permanents, siège, D&A) DÉJÀ ALLOUÉE jusqu'à la classe (par nb de classes). 3 versions : Réalisé N-2 · Réalisé N-1 · Atterrissage (Forecast V4).
B4: Entité | C4: Programme | D4: Année | E4: Modalité | F4: Compte | G4: Libellé compte | H4: Type | I4: Version | J4: Période | K4: Unité | L4: Montant
B5: MBWAY_PAR | C5: BAC_MGT | D5: B1 | E5: INIT | F5: 706100 | G5: Droits de scolarité | H5: COMPTABLE | I5: 2023ACT_VDEF | J5: 2023 | K5: EUR | L5: 596700
B6: MBWAY_PAR | C6: BAC_MGT | D6: B1 | E6: INIT | F6: 706100 | G6: Droits de scolarité | H6: COMPTABLE | I6: 2024ACT_VDEF | J6: 2024 | K6: EUR | L6: 629850
B7: MBWAY_PAR | C7: BAC_MGT | D7: B1 | E7: INIT | F7: 706100 | G7: Droits de scolarité | H7: COMPTABLE | I7: 2025FCST_V4 | J7: 2025 | K7: EUR | L7: 663000
B8: MBWAY_PAR | C8: BAC_MGT | D8: B1 | E8: INIT | F8: 708500 | G8: Frais de dossier / inscription | H8: COMPTABLE | I8: 2023ACT_VDEF | J8: 2023 | K8: EUR | L8: 6318
B9: MBWAY_PAR | C9: BAC_MGT | D9: B1 | E9: INIT | F9: 708500 | G9: Frais de dossier / inscription | H9: COMPTABLE | I9: 2024ACT_VDEF | J9: 2024 | K9: EUR | L9: 6669
B10: MBWAY_PAR | C10: BAC_MGT | D10: B1 | E10: INIT | F10: 708500 | G10: Frais de dossier / inscription | H10: COMPTABLE | I10: 2025FCST_V4 | J10: 2025 | K10: EUR | L10: 7020
B11: MBWAY_PAR | C11: BAC_MGT | D11: B1 | E11: INIT | F11: 604100 | G11: Vacations & sous-traitance pédagogique | H11: COMPTABLE | I11: 2023ACT_VDEF | J11: 2023 | K11: EUR | L11: 93960
B12: MBWAY_PAR | C12: BAC_MGT | D12: B1 | E12: INIT | F12: 604100 | G12: Vacations & sous-traitance pédagogique | H12: COMPTABLE | I12: 2024ACT_VDEF | J12: 2024 | K12: EUR | L12: 99180
B13: MBWAY_PAR | C13: BAC_MGT | D13: B1 | E13: INIT | F13: 604100 | G13: Vacations & sous-traitance pédagogique | H13: COMPTABLE | I13: 2025FCST_V4 | J13: 2025 | K13: EUR | L13: 104400
B14: MBWAY_PAR | C14: BAC_MGT | D14: B1 | E14: INIT | F14: 606300 | G14: Fournitures & ressources pédagogiques | H14: COMPTABLE | I14: 2023ACT_VDEF | J14: 2023 | K14: EUR | L14: 28080
B15: MBWAY_PAR | C15: BAC_MGT | D15: B1 | E15: INIT | F15: 606300 | G15: Fournitures & ressources pédagogiques | H15: COMPTABLE | I15: 2024ACT_VDEF | J15: 2024 | K15: EUR | L15: 29640
B16: MBWAY_PAR | C16: BAC_MGT | D16: B1 | E16: INIT | F16: 606300 | G16: Fournitures & ressources pédagogiques | H16: COMPTABLE | I16: 2025FCST_V4 | J16: 2025 | K16: EUR | L16: 31200
... B2959: TUNON_LYO | C2959: BAC_TOU | D2959: B3 | E2959: ALT | F2959: PRX_TARIF | G2959: Tarif moyen scolarité | H2959: TECHNIQUE | I2959: 2025FCST_V4 | J2959: 2025 | K2959: EUR | L2959: 8000

Sheet 04_Referentiel
B2: Référentiel — dimensions
B4: Entités : Groupe → Marque → Campus
B5: Marque | C5: Ville | D5: Domaine | E5: Niveau | F5: Devise
B6: EDUSERVICES GROUP | C6: — | D6: Tous | E6: Groupe | F6: EUR
B7: MBway | C7: Paris | D7: Management | E7: Campus | F7: EUR
B8: MBway | C8: Lyon | D8: Management | E8: Campus | F8: EUR
B9: MBway | C9: Nantes | D9: Management | E9: Campus | F9: EUR
B10: MBway | C10: Bordeaux | D10: Management | E10: Campus | F10: EUR
B11: ISCOM | C11: Paris | D11: Communication | E11: Campus | F11: EUR
B12: ISCOM | C12: Lille | D12: Communication | E12: Campus | F12: EUR
B13: ISCOM | C13: Toulouse | D13: Communication | E13: Campus | F13: EUR
B14: Ipac Bachelor Factory | C14: Nantes | D14: Commerce | E14: Campus | F14: EUR
B15: Ipac Bachelor Factory | C15: Rennes | D15: Commerce | E15: Campus | F15: EUR
B16: Ipac Bachelor Factory | C16: Montpellier | D16: Commerce | E16: Campus | F16: EUR
... B20: Tunon | C20: Lyon | D20: Tourisme | E20: Campus | F20: EUR
B22: Comptes (nature fixe/variable)
B23: Compte | C23: Libellé | D23: Rubrique | E23: Nature | F23: Inducteur
B24: 70600 | C24: Scolarité | D24: CA | E24: — | F24: Effectif × tarif
B25: 70800 | C25: Frais de dossier | D25: CA | E25: — | F25: Nouveaux
B26: 64100 | C26: Enseignement | D26: Coût direct | E26: Semi-fixe/classe | F26: Classes × heures
B27: 60700 | C27: Pédagogie | D27: Coût direct | E27: Variable | F27: Effectif
B28: 62300 | C28: Marketing | D28: Coût direct | E28: Variable | F28: Nouveaux / budget
B29: 61300 | C29: Loyers | D29: Structure | E29: Fixe | F29: Campus
B30: 64000 | C30: Personnel permanent | D30: Structure | E30: Fixe | F30: ETP
B31: 65000 | C31: Structure groupe | D31: Structure | E31: Fixe (alloué) | F31: Driver
B32: 68000 | C32: D&A | D32: D&A | E32: Fixe | F32: Campus

Sheet 05_Param_Prog_Annee
A1: Données de référence par programme × année (issues du réalisé — à charger)
A2: Bleu = saisie. Capacité, heures, taux, pédago, CAC variable et taux de passage varient par programme ET par année.
A3: Clé (prog|année) | B3: Programme | C3: Année | D3: Mod. | E3: Capacité | F3: Heures/classe | G3: Taux horaire | H3: Coût pédago/étu | I3: CAC variable | J3: Taux de passage
A4: Bachelor Management|B1 | B4: Bachelor Management | C4: B1 | D4: INIT | E4: 32 | F4: 600 | G4: 58 | H4: 400 | I4: 320
A5: Bachelor Management|B2 | B5: Bachelor Management | C5: B2 | D5: ALT | E5: 32 | F5: 560 | G5: 58 | H5: 400 | I5: 0 | J5: 0.93
A6: Bachelor Management|B3 | B6: Bachelor Management | C6: B3 | D6: ALT | E6: 32 | F6: 520 | G6: 58 | H6: 400 | I6: 0 | J6: 0.95
A7: Mastère Management|M1 | B7: Mastère Management | C7: M1 | D7: ALT | E7: 26 | F7: 480 | G7: 70 | H7: 520 | I7: 600
A8: Mastère Management|M2 | B8: Mastère Management | C8: M2 | D8: ALT | E8: 26 | F8: 440 | G8: 70 | H8: 520 | I8: 0 | J8: 0.96
A9: Bachelor Communication|B1 | B9: Bachelor Communication | C9: B1 | D9: INIT | E9: 32 | F9: 600 | G9: 62 | H9: 550 | I9: 320
A10: Bachelor Communication|B2 | B10: Bachelor Communication | C10: B2 | D10: ALT | E10: 32 | F10: 560 | G10: 62 | H10: 550 | I10: 0 | J10: 0.93
A11: Bachelor Communication|B3 | B11: Bachelor Communication | C11: B3 | D11: ALT | E11: 32 | F11: 520 | G11: 62 | H11: 550 | I11: 0 | J11: 0.95
A12: Mastère Communication|M1 | B12: Mastère Communication | C12: M1 | D12: ALT | E12: 26 | F12: 480 | G12: 74 | H12: 670 | I12: 600
A13: Mastère Communication|M2 | B13: Mastère Communication | C13: M2 | D13: ALT | E13: 26 | F13: 440 | G13: 74 | H13: 670 | I13: 0 | J13: 0.96
A14: Bachelor Commerce|B1 | B14: Bachelor Commerce | C14: B1 | D14: ALT | E14: 32 | F14: 600 | G14: 58 | H14: 380 | I14: 320
A15: Bachelor Commerce|B2 | B15: Bachelor Commerce | C15: B2 | D15: ALT | E15: 32 | F15: 560 | G15: 58 | H15: 380 | I15: 0 | J15: 0.93
A16: Bachelor Commerce|B3 | B16: Bachelor Commerce | C16: B3 | D16: ALT | E16: 32 | F16: 520 | G16: 58 | H16: 380 | I16: 0 | J16: 0.95
A17: BTS Gestion|1 | B17: BTS Gestion | C17: 1 | D17: ALT | E17: 30 | F17: 720 | G17: 55 | H17: 350 | I17: 250
A18: BTS Gestion|2 | B18: BTS Gestion | C18: 2 | D18: ALT | E18: 30 | F18: 680 | G18: 55 | H18: 350 | I18: 0 | J18: 0.94
A19: Bachelor RH|B1 | B19: Bachelor RH | C19: B1 | D19: ALT | E19: 32 | F19: 600 | G19: 58 | H19: 380 | I19: 320
A20: Bachelor RH|B3 | B20: Bachelor RH | C20: B3 | D20: ALT | E20: 32 | F20: 520 | G20: 58 | H20: 380 | I20: 0 | J20: 0.95
A21: Bachelor Tourisme|B1 | B21: Bachelor Tourisme | C21: B1 | D21: ALT | E21: 32 | F21: 600 | G21: 56 | H21: 450 | I21: 320
A22: Bachelor Tourisme|B2 | B22: Bachelor Tourisme | C22: B2 | D22: ALT | E22: 32 | F22: 560 | G22: 56 | H22: 450 | I22: 0 | J22: 0.93
A23: Bachelor Tourisme|B3 | B23: Bachelor Tourisme | C23: B3 | D23: ALT | E23: 32 | F23: 520 | G23: 56 | H23: 450 | I23: 0 | J23: 0.95

Sheet 06_Historique
A1: Réalisé N-1 par cellule (funnel + cohorte)
A3: Marque | B3: Ville | C3: Programme | D3: Type | E3: Année | F3: Mod. | G3: Entrée | H3: Cand N-1 | I3: Nouv N-1 | J3: Réins N-1 | K3: Effectif N-1 | L3: Eff. année inf. N-1 | M3: Tarif N-1 | N3: Classes N-1
A4: MBway | B4: Paris | C4: Bachelor Management | D4: BAC | E4: B1 | F4: INIT | G4: 1 | H4: 210 | I4: 78 | J4: 0 | K4: 78 | L4: 0 | M4: 8500 | N4: 3
A5: MBway | B5: Paris | C5: Bachelor Management | D5: BAC | E5: B2 | F5: ALT | G5: 0 | H5: 0 | I5: 0 | J5: 66 | K5: 66 | L5: 78 | M5: 8000 | N5: 3
A6: MBway | B6: Paris | C6: Bachelor Management | D6: BAC | E6: B3 | F6: ALT | G6: 0 | H6: 0 | I6: 0 | J6: 58 | K6: 58 | L6: 66 | M6: 8000 | N6: 2
A7: MBway | B7: Paris | C7: Mastère Management | D7: MAST | E7: M1 | F7: ALT | G7: 1 | H7: 126 | I7: 47 | J7: 0 | K7: 47 | L7: 0 | M7: 9000 | N7: 2
A8: MBway | B8: Paris | C8: Mastère Management | D8: MAST | E8: M2 | F8: ALT | G8: 0 | H8: 0 | I8: 0 | J8: 42 | K8: 42 | L8: 47 | M8: 9000 | N8: 2
A9: MBway | B9: Lyon | C9: Bachelor Management | D9: BAC | E9: B1 | F9: INIT | G9: 1 | H9: 177 | I9: 66 | J9: 0 | K9: 66 | L9: 0 | M9: 8500 | N9: 3
A10: MBway | B10: Lyon | C10: Bachelor Management | D10: BAC | E10: B2 | F10: ALT | G10: 0 | H10: 0 | I10: 0 | J10: 56 | K10: 56 | L10: 66 | M10: 8000 | N10: 2
A11: MBway | B11: Lyon | C11: Bachelor Management | D11: BAC | E11: B3 | F11: ALT | G11: 0 | H11: 0 | I11: 0 | J11: 50 | K11: 50 | L11: 56 | M11: 8000 | N11: 2
A12: MBway | B12: Lyon | C12: Mastère Management | D12: MAST | E12: M1 | F12: ALT | G12: 1 | H12: 108 | I12: 40 | J12: 0 | K12: 40 | L12: 0 | M12: 9000 | N12: 2
A13: MBway | B13: Lyon | C13: Mastère Management | D13: MAST | E13: M2 | F13: ALT | G13: 0 | H13: 0 | I13: 0 | J13: 36 | K13: 36 | L13: 40 | M13: 9000 | N13: 2
A14: MBway | B14: Nantes | C14: Bachelor Management | D14: BAC | E14: B1 | F14: INIT | G14: 1 | H14: 161 | I14: 60 | J14: 0 | K14: 60 | L14: 0 | M14: 8500 | N14: 2
A15: MBway | B15: Nantes | C15: Bachelor Management | D15: BAC | E15: B2 | F15: ALT | G15: 0 | H15: 0 | I15: 0 | J15: 51 | K15: 51 | L15: 60 | M15: 8000 | N15: 2
... A61: Tunon | B61: Lyon | C61: Bachelor Tourisme | D61: BAC | E61: B3 | F61: ALT | G61: 0 | H61: 0 | I61: 0 | J61: 30 | K61: 30 | L61: 34 | M61: 8000 | N61: 1
A64: Historique marketing par programme (issu du réalisé) → élasticité mesurée
A65: Programme | B65: Cand N-2 | C65: Cand N-1 | D65: Marketing N-2 | E65: Marketing N-1 | F65: Élasticité mesurée
A66: Bachelor Management | B66: 652 | C66: 685 | D66: 74182 | E66: 81600 | F66: =IFERROR((C66/B66-1)/(E66/D66-1),'01_Cadrage'!$H$27)
A67: Mastère Management | B67: 394 | C67: 414 | D67: 84000 | E67: 92400 | F67: =IFERROR((C67/B67-1)/(E67/D67-1),'01_Cadrage'!$H$27)
A68: Bachelor Communication | B68: 432 | C68: 454 | D68: 49164 | E68: 54080 | F68: =IFERROR((C68/B68-1)/(E68/D68-1),'01_Cadrage'!$H$27)
A69: Mastère Communication | B69: 259 | C69: 272 | D69: 55091 | E69: 60600 | F69: =IFERROR((C69/B69-1)/(E69/D69-1),'01_Cadrage'!$H$27)
A70: Bachelor Commerce | B70: 333 | C70: 350 | D70: 37818 | E70: 41600 | F70: =IFERROR((C70/B70-1)/(E70/D70-1),'01_Cadrage'!$H$27)
A71: BTS Gestion | B71: 169 | C71: 177 | D71: 15000 | E71: 16500 | F71: =IFERROR((C71/B71-1)/(E71/D71-1),'01_Cadrage'!$H$27)
A72: Bachelor RH | B72: 210 | C72: 221 | D72: 23855 | E72: 26240 | F72: =IFERROR((C72/B72-1)/(E72/D72-1),'01_Cadrage'!$H$27)
A73: Bachelor Tourisme | B73: 223 | C73: 234 | D73: 25309 | E73: 27840 | F73: =IFERROR((C73/B73-1)/(E73/D73-1),'01_Cadrage'!$H$27)

Sheet 07_Structure
A1: Réalisé N-1 par campus (structure)
A3: Marque | B3: Ville | C3: Effectif N-1 | D3: CA N-1 | E3: Contribution N-1 | F3: Loyer N-1 | G3: ETP perm. | H3: Masse perm. N-1 | I3: D&A N-1 | J3: Surface m² | K3: EBITDA campus N-1
A4: MBway | B4: Paris | C4: 291 | D4: 2467250 | E4: 1624256 | F4: 271000 | G4: 11 | H4: =G4*'01_Cadrage'!$H$23 | I4: 148000 | J4: 2328 | K4: =E4-F4-H4
A5: MBway | B5: Lyon | C5: 248 | D5: 2102540 | E5: 1358988 | F5: 231000 | G5: 9 | H5: =G5*'01_Cadrage'!$H$23 | I5: 126000 | J5: 1984 | K5: =E5-F5-H5
A6: MBway | B6: Nantes | C6: 224 | D6: 1898640 | E6: 1227184 | F6: 209000 | G6: 8 | H6: =G6*'01_Cadrage'!$H$23 | I6: 114000 | J6: 1792 | K6: =E6-F6-H6
A7: MBway | B7: Bordeaux | C7: 191 | D7: 1619880 | E7: 999406 | F7: 178000 | G7: 7 | H7: =G7*'01_Cadrage'!$H$23 | I7: 97000 | J7: 1528 | K7: =E7-F7-H7
A8: ISCOM | B8: Paris | C8: 269 | D8: 2280350 | E8: 1440794 | F8: 251000 | G8: 10 | H8: =G8*'01_Cadrage'!$H$23 | I8: 137000 | J8: 2152 | K8: =E8-F8-H8
A9: ISCOM | B9: Lille | C9: 187 | D9: 1585200 | E9: 922372 | F9: 174000 | G9: 7 | H9: =G9*'01_Cadrage'!$H$23 | I9: 95000 | J9: 1496 | K9: =E9-F9-H9
A10: ISCOM | B10: Toulouse | C10: 175 | D10: 1483250 | E10: 873430 | F10: 163000 | G10: 7 | H10: =G10*'01_Cadrage'!$H$23 | I10: 89000 | J10: 1400 | K10: =E10-F10-H10
A11: Ipac Bachelor Factory | B11: Nantes | C11: 130 | D11: 1044500 | E11: 662800 | F11: 115000 | G11: 5 | H11: =G11*'01_Cadrage'!$H$23 | I11: 63000 | J11: 1040 | K11: =E11-F11-H11
A12: Ipac Bachelor Factory | B12: Rennes | C12: 104 | D12: 835600 | E12: 521424 | F12: 92000 | G12: 4 | H12: =G12*'01_Cadrage'!$H$23 | I12: 50000 | J12: 832 | K12: =E12-F12-H12
A13: Ipac Bachelor Factory | B13: Montpellier | C13: 104 | D13: 835600 | E13: 521424 | F13: 92000 | G13: 4 | H13: =G13*'01_Cadrage'!$H$23 | I13: 50000 | J13: 832 | K13: =E13-F13-H13
A14: Pigier | B14: Lyon | C14: 149 | D14: 1130470 | E14: 628864 | F14: 124000 | G14: 6 | H14: =G14*'01_Cadrage'!$H$23 | I14: 68000 | J14: 1192 | K14: =E14-F14-H14
A15: Pigier | B15: Bordeaux | C15: 117 | D15: 887850 | E15: 540202 | F15: 98000 | G15: 5 | H15: =G15*'01_Cadrage'!$H$23 | I15: 53000 | J15: 936 | K15: =E15-F15-H15
... A17: Tunon | B17: Lyon | C17: 104 | D17: 835600 | E17: 519824 | F17: 92000 | G17: 4 | H17: =G17*'01_Cadrage'!$H$23 | I17: 50000 | J17: 832 | K17: =E17-F17-H17
A18: TOTAL | C18: =SUM(C4:C17) | D18: =SUM(D4:D17) | E18: =SUM(E4:E17) | F18: =SUM(F4:F17) | G18: =SUM(G4:G17) | H18: =SUM(H4:H17) | I18: =SUM(I4:I17) | J18: =SUM(J4:J17) | K18: =SUM(K4:K17)

Sheet 08_Moteur
A1: Moteur de budget par cellule (cohortes · marketing→volume mesuré · seuil=point mort)
A2: Marque | B2: Ville | C2: Programme | D2: Année | E2: Mod | F2: Entrée | G2: Eff N-1 | H2: Nouv N-1 | I2: Réins N-1 | J2: Cand N-1 | K2: EffInf N-1 | L2: Tarif N-1 | M2: Cl N-1 | N2: clé | O2: Cap | P2: Heures | Q2: Taux | R2: Pédago | S2: CACvar | T2: Passage | U2: Coût/cl | V2: cMkt | W2: cPrix | X2: Élast | Y2: Effort | Z2: Cand Bud | AA2: Conv | AB2: Nouv Bud | AC2: Réins Bud | AD2: Effectif Bud | AE2: Tarif Bud | AF2: (réservé) | AG2: (réservé2) | AH2: CA Bud | AI2: Cl besoin | AJ2: Enseign | AK2: Pédago€ | AL2: Mktg | AM2: Contrib | AN2: Rempl | AO2: Contr/étu | AP2: Pt mort
A3: ='06_Historique'!A4 | B3: ='06_Historique'!B4 | C3: ='06_Historique'!C4 | D3: ='06_Historique'!E4 | E3: ='06_Historique'!F4 | F3: ='06_Historique'!G4 | G3: ='06_Historique'!K4 | H3: ='06_Historique'!I4 | I3: ='06_Historique'!J4 | J3: ='06_Historique'!H4 | K3: ='06_Historique'!L4 | L3: ='06_Historique'!M4 | M3: ='06_Historique'!N4 | N3: =C3&"|"&D3 | O3: =INDEX('05_Param_Prog_Annee'!$E$4:$E$23,MATCH(N3,'05_Param_Prog_Annee'!$A$4:$A$23,0)) | P3: =INDEX('05_Param_Prog_Annee'!$F$4:$F$23,MATCH(N3,'05_Param_Prog_Annee'!$A$4:$A$23,0)) | Q3: =INDEX('05_Param_Prog_Annee'!$G$4:$G$23,MATCH(N3,'05_Param_Prog_Annee'!$A$4:$A$23,0)) | R3: =INDEX('05_Param_Prog_Annee'!$H$4:$H$23,MATCH(N3,'05_Param_Prog_Annee'!$A$4:$A$23,0)) | S3: =INDEX('05_Param_Prog_Annee'!$I$4:$I$23,MATCH(N3,'05_Param_Prog_Annee'!$A$4:$A$23,0)) | T3: =IFERROR(INDEX('05_Param_Prog_Annee'!$J$4:$J$23,MATCH(N3,'05_Param_Prog_Annee'!$A$4:$A$23,0)),0) | U3: =P3*Q3*(1+'01_Cadrage'!$H$21) | V3: =INDEX('01_Cadrage'!$L$7:$L$20,MATCH(A3&"|"&B3,'01_Cadrage'!$O$7:$O$20,0)) | W3: =INDEX('01_Cadrage'!$M$7:$M$20,MATCH(A3&"|"&B3,'01_Cadrage'!$O$7:$O$20,0)) | X3: =IFERROR(INDEX('06_Historique'!$F$66:$F$73,MATCH(C3,'06_Historique'!$A$66:$A$73,0)),'01_Cadrage'!$H$27) | Y3: ='01_Cadrage'!$H$16*V3 | Z3: =IF(F3=1,J3*(1+X3*Y3),0) | AA3: =IF(F3=1,IFERROR(H3/J3,'01_Cadrage'!$H$28)+'01_Cadrage'!$H$18,0) | AB3: =Z3*AA3 | AC3: =IF(F3=1,0,K3*(T3+'01_Cadrage'!$H$19)) | AD3: =AB3+AC3 | AE3: =L3*(1+'01_Cadrage'!$H$17*W3) | AF3: =1 | AG3: =1 | AH3: =AD3*AE3*AF3+AB3*'01_Cadrage'!$H$24 | AI3: =IF(AD3<=0,0,MAX(1,ROUNDUP(AD3/O3,0))) | AJ3: =AI3*U3 | AK3: =AD3*R3*(1+'01_Cadrage'!$H$20) | AL3: =H3*S3*(1+Y3) | AM3: =AH3-AJ3-AK3-AL3-AD3*'01_Cadrage'!$H$26*(1+'01_Cadrage'!$H$20) | AN3: =IFERROR(AD3/(AI3*O3),0) | AO3: =IFERROR(AM3/AD3,0) | AP3: =IFERROR(AI3*U3/(AE3*AF3-R3*(1+'01_Cadrage'!$H$20)),0)
A4: ='06_Historique'!A5 | B4: ='06_Historique'!B5 | C4: ='06_Historique'!C5 | D4: ='06_Historique'!E5 | E4: ='06_Historique'!F5 | F4: ='06_Historique'!G5 | G4: ='06_Historique'!K5 | H4: ='06_Historique'!I5 | I4: ='06_Historique'!J5 | J4: ='06_Historique'!H5 | K4: ='06_Historique'!L5 | L4: ='06_Historique'!M5 | M4: ='06_Historique'!N5 | N4: =C4&"|"&D4 | O4: =INDEX('05_Param_Prog_Annee'!$E$4:$E$23,MATCH(N4,'05_Param_Prog_Annee'!$A$4:$A$23,0)) | P4: =INDEX('05_Param_Prog_Annee'!$F$4:$F$23,MATCH(N4,'05_Param_Prog_Annee'!$A$4:$A$23,0)) | Q4: =INDEX('05_Param_Prog_Annee'!$G$4:$G$23,MATCH(N4,'05_Param_Prog_Annee'!$A$4:$A$23,0)) | R4: =INDEX('05_Param_Prog_Annee'!$H$4:$H$23,MATCH(N4,'05_Param_Prog_Annee'!$A$4:$A$23,0)) | S4: =INDEX('05_Param_Prog_Annee'!$I$4:$I$23,MATCH(N4,'05_Param_Prog_Annee'!$A$4:$A$23,0)) | T4: =IFERROR(INDEX('05_Param_Prog_Annee'!$J$4:$J$23,MATCH(N4,'05_Param_Prog_Annee'!$A$4:$A$23,0)),0) | U4: =P4*Q4*(1+'01_Cadrage'!$H$21) | V4: =INDEX('01_Cadrage'!$L$7:$L$20,MATCH(A4&"|"&B4,'01_Cadrage'!$O$7:$O$20,0)) | W4: =INDEX('01_Cadrage'!$M$7:$M$20,MATCH(A4&"|"&B4,'01_Cadrage'!$O$7:$O$20,0)) | X4: =IFERROR(INDEX('06_Historique'!$F$66:$F$73,MATCH(C4,'06_Historique'!$A$66:$A$73,0)),'01_Cadrage'!$H$27) | Y4: ='01_Cadrage'!$H$16*V4 | Z4: =IF(F4=1,J4*(1+X4*Y4),0) | AA4: =IF(F4=1,IFERROR(H4/J4,'01_Cadrage'!$H$28)+'01_Cadrage'!$H$18,0) | AB4: =Z4*AA4 | AC4: =IF(F4=1,0,K4*(T4+'01_Cadrage'!$H$19)) | AD4: =AB4+AC4 | AE4: =L4*(1+'01_Cadrage'!$H$17*W4) | AF4: =1 | AG4: =1 | AH4: =AD4*AE4*AF4+AB4*'01_Cadrage'!$H$24 | AI4: =IF(AD4<=0,0,MAX(1,ROUNDUP(AD4/O4,0))) | AJ4: =AI4*U4 | AK4: =AD4*R4*(1+'01_Cadrage'!$H$20) | AL4: =H4*S4*(1+Y4) | AM4: =AH4-AJ4-AK4-AL4-AD4*'01_Cadrage'!$H$26*(1+'01_Cadrage'!$H$20) | AN4: =IFERROR(AD4/(AI4*O4),0) | AO4: =IFERROR(AM4/AD4,0) | AP4: =IFERROR(AI4*U4/(AE4*AF4-R4*(1+'01_Cadrage'!$H$20)),0)
A5: ='06_Historique'!A6 | B5: ='06_Historique'!B6 | C5: ='06_Historique'!C6 | D5: ='06_Historique'!E6 | E5: ='06_Historique'!F6 | F5: ='06_Historique'!G6 | G5: ='06_Historique'!K6 | H5: ='06_Historique'!I6 | I5: ='06_Historique'!J6 | J5: ='06_Historique'!H6 | K5: ='06_Historique'!L6 | L5: ='06_Historique'!M6 | M5: ='06_Historique'!N6 | N5: =C5&"|"&D5 | O5: =INDEX('05_Param_Prog_Annee'!$E$4:$E$23,MATCH(N5,'05_Param_Prog_Annee'!$A$4:$A$23,0)) | P5: =INDEX('05_Param_Prog_Annee'!$F$4:$F$23,MATCH(N5,'05_Param_Prog_Annee'!$A$4:$A$23,0)) | Q5: =INDEX('05_Param_Prog_Annee'!$G$4:$G$23,MATCH(N5,'05_Param_Prog_Annee'!$A$4:$A$23,0)) | R5: =INDEX('05_Param_Prog_Annee'!$H$4:$H$23,MATCH(N5,'05_Param_Prog_Annee'!$A$4:$A$23,0)) | S5: =INDEX('05_Param_Prog_Annee'!$I$4:$I$23,MATCH(N5,'05_Param_Prog_Annee'!$A$4:$A$23,0)) | T5: =IFERROR(INDEX('05_Param_Prog_Annee'!$J$4:$J$23,MATCH(N5,'05_Param_Prog_Annee'!$A$4:$A$23,0)),0) | U5: =P5*Q5*(1+'01_Cadrage'!$H$21) | V5: =INDEX('01_Cadrage'!$L$7:$L$20,MATCH(A5&"|"&B5,'01_Cadrage'!$O$7:$O$20,0)) | W5: =INDEX('01_Cadrage'!$M$7:$M$20,MATCH(A5&"|"&B5,'01_Cadrage'!$O$7:$O$20,0)) | X5: =IFERROR(INDEX('06_Historique'!$F$66:$F$73,MATCH(C5,'06_Historique'!$A$66:$A$73,0)),'01_Cadrage'!$H$27) | Y5: ='01_Cadrage'!$H$16*V5 | Z5: =IF(F5=1,J5*(1+X5*Y5),0) | AA5: =IF(F5=1,IFERROR(H5/J5,'01_Cadrage'!$H$28)+'01_Cadrage'!$H$18,0) | AB5: =Z5*AA5 | AC5: =IF(F5=1,0,K5*(T5+'01_Cadrage'!$H$19)) | AD5: =AB5+AC5 | AE5: =L5*(1+'01_Cadrage'!$H$17*W5) | AF5: =1 | AG5: =1 | AH5: =AD5*AE5*AF5+AB5*'01_Cadrage'!$H$24 | AI5: =IF(AD5<=0,0,MAX(1,ROUNDUP(AD5/O5,0))) | AJ5: =AI5*U5 | AK5: =AD5*R5*(1+'01_Cadrage'!$H$20) | AL5: =H5*S5*(1+Y5) | AM5: =AH5-AJ5-AK5-AL5-AD5*'01_Cadrage'!$H$26*(1+'01_Cadrage'!$H$20) | AN5: =IFERROR(AD5/(AI5*O5),0) | AO5: =IFERROR(AM5/AD5,0) | AP5: =IFERROR(AI5*U5/(AE5*AF5-R5*(1+'01_Cadrage'!$H$20)),0)
A6: ='06_Historique'!A7 | B6: ='06_Historique'!B7 | C6: ='06_Historique'!C7 | D6: ='06_Historique'!E7 | E6: ='06_Historique'!F7 | F6: ='06_Historique'!G7 | G6: ='06_Historique'!K7 | H6: ='06_Historique'!I7 | I6: ='06_Historique'!J7 | J6: ='06_Historique'!H7 | K6: ='06_Historique'!L7 | L6: ='06_Historique'!M7 | M6: ='06_Historique'!N7 | N6: =C6&"|"&D6 | O6: =INDEX('05_Param_Prog_Annee'!$E$4:$E$23,MATCH(N6,'05_Param_Prog_Annee'!$A$4:$A$23,0)) | P6: =INDEX('05_Param_Prog_Annee'!$F$4:$F$23,MATCH(N6,'05_Param_Prog_Annee'!$A$4:$A$23,0)) | Q6: =INDEX('05_Param_Prog_Annee'!$G$4:$G$23,MATCH(N6,'05_Param_Prog_Annee'!$A$4:$A$23,0)) | R6: =INDEX('05_Param_Prog_Annee'!$H$4:$H$23,MATCH(N6,'05_Param_Prog_Annee'!$A$4:$A$23,0)) | S6: =INDEX('05_Param_Prog_Annee'!$I$4:$I$23,MATCH(N6,'05_Param_Prog_Annee'!$A$4:$A$23,0)) | T6: =IFERROR(INDEX('05_Param_Prog_Annee'!$J$4:$J$23,MATCH(N6,'05_Param_Prog_Annee'!$A$4:$A$23,0)),0) | U6: =P6*Q6*(1+'01_Cadrage'!$H$21) | V6: =INDEX('01_Cadrage'!$L$7:$L$20,MATCH(A6&"|"&B6,'01_Cadrage'!$O$7:$O$20,0)) | W6: =INDEX('01_Cadrage'!$M$7:$M$20,MATCH(A6&"|"&B6,'01_Cadrage'!$O$7:$O$20,0)) | X6: =IFERROR(INDEX('06_Historique'!$F$66:$F$73,MATCH(C6,'06_Historique'!$A$66:$A$73,0)),'01_Cadrage'!$H$27) | Y6: ='01_Cadrage'!$H$16*V6 | Z6: =IF(F6=1,J6*(1+X6*Y6),0) | AA6: =IF(F6=1,IFERROR(H6/J6,'01_Cadrage'!$H$28)+'01_Cadrage'!$H$18,0) | AB6: =Z6*AA6 | AC6: =IF(F6=1,0,K6*(T6+'01_Cadrage'!$H$19)) | AD6: =AB6+AC6 | AE6: =L6*(1+'01_Cadrage'!$H$17*W6) | AF6: =1 | AG6: =1 | AH6: =AD6*AE6*AF6+AB6*'01_Cadrage'!$H$24 | AI6: =IF(AD6<=0,0,MAX(1,ROUNDUP(AD6/O6,0))) | AJ6: =AI6*U6 | AK6: =AD6*R6*(1+'01_Cadrage'!$H$20) | AL6: =H6*S6*(1+Y6) | AM6: =AH6-AJ6-AK6-AL6-AD6*'01_Cadrage'!$H$26*(1+'01_Cadrage'!$H$20) | AN6: =IFERROR(AD6/(AI6*O6),0) | AO6: =IFERROR(AM6/AD6,0) | AP6: =IFERROR(AI6*U6/(AE6*AF6-R6*(1+'01_Cadrage'!$H$20)),0)
A7: ='06_Historique'!A8 | B7: ='06_Historique'!B8 | C7: ='06_Historique'!C8 | D7: ='06_Historique'!E8 | E7: ='06_Historique'!F8 | F7: ='06_Historique'!G8 | G7: ='06_Historique'!K8 | H7: ='06_Historique'!I8 | I7: ='06_Historique'!J8 | J7: ='06_Historique'!H8 | K7: ='06_Historique'!L8 | L7: ='06_Historique'!M8 | M7: ='06_Historique'!N8 | N7: =C7&"|"&D7 | O7: =INDEX('05_Param_Prog_Annee'!$E$4:$E$23,MATCH(N7,'05_Param_Prog_Annee'!$A$4:$A$23,0)) | P7: =INDEX('05_Param_Prog_Annee'!$F$4:$F$23,MATCH(N7,'05_Param_Prog_Annee'!$A$4:$A$23,0)) | Q7: =INDEX('05_Param_Prog_Annee'!$G$4:$G$23,MATCH(N7,'05_Param_Prog_Annee'!$A$4:$A$23,0)) | R7: =INDEX('05_Param_Prog_Annee'!$H$4:$H$23,MATCH(N7,'05_Param_Prog_Annee'!$A$4:$A$23,0)) | S7: =INDEX('05_Param_Prog_Annee'!$I$4:$I$23,MATCH(N7,'05_Param_Prog_Annee'!$A$4:$A$23,0)) | T7: =IFERROR(INDEX('05_Param_Prog_Annee'!$J$4:$J$23,MATCH(N7,'05_Param_Prog_Annee'!$A$4:$A$23,0)),0) | U7: =P7*Q7*(1+'01_Cadrage'!$H$21) | V7: =INDEX('01_Cadrage'!$L$7:$L$20,MATCH(A7&"|"&B7,'01_Cadrage'!$O$7:$O$20,0)) | W7: =INDEX('01_Cadrage'!$M$7:$M$20,MATCH(A7&"|"&B7,'01_Cadrage'!$O$7:$O$20,0)) | X7: =IFERROR(INDEX('06_Historique'!$F$66:$F$73,MATCH(C7,'06_Historique'!$A$66:$A$73,0)),'01_Cadrage'!$H$27) | Y7: ='01_Cadrage'!$H$16*V7 | Z7: =IF(F7=1,J7*(1+X7*Y7),0) | AA7: =IF(F7=1,IFERROR(H7/J7,'01_Cadrage'!$H$28)+'01_Cadrage'!$H$18,0) | AB7: =Z7*AA7 | AC7: =IF(F7=1,0,K7*(T7+'01_Cadrage'!$H$19)) | AD7: =AB7+AC7 | AE7: =L7*(1+'01_Cadrage'!$H$17*W7) | AF7: =1 | AG7: =1 | AH7: =AD7*AE7*AF7+AB7*'01_Cadrage'!$H$24 | AI7: =IF(AD7<=0,0,MAX(1,ROUNDUP(AD7/O7,0))) | AJ7: =AI7*U7 | AK7: =AD7*R7*(1+'01_Cadrage'!$H$20) | AL7: =H7*S7*(1+Y7) | AM7: =AH7-AJ7-AK7-AL7-AD7*'01_Cadrage'!$H$26*(1+'01_Cadrage'!$H$20) | AN7: =IFERROR(AD7/(AI7*O7),0) | AO7: =IFERROR(AM7/AD7,0) | AP7: =IFERROR(AI7*U7/(AE7*AF7-R7*(1+'01_Cadrage'!$H$20)),0)
A8: ='06_Historique'!A9 | B8: ='06_Historique'!B9 | C8: ='06_Historique'!C9 | D8: ='06_Historique'!E9 | E8: ='06_Historique'!F9 | F8: ='06_Historique'!G9 | G8: ='06_Historique'!K9 | H8: ='06_Historique'!I9 | I8: ='06_Historique'!J9 | J8: ='06_Historique'!H9 | K8: ='06_Historique'!L9 | L8: ='06_Historique'!M9 | M8: ='06_Historique'!N9 | N8: =C8&"|"&D8 | O8: =INDEX('05_Param_Prog_Annee'!$E$4:$E$23,MATCH(N8,'05_Param_Prog_Annee'!$A$4:$A$23,0)) | P8: =INDEX('05_Param_Prog_Annee'!$F$4:$F$23,MATCH(N8,'05_Param_Prog_Annee'!$A$4:$A$23,0)) | Q8: =INDEX('05_Param_Prog_Annee'!$G$4:$G$23,MATCH(N8,'05_Param_Prog_Annee'!$A$4:$A$23,0)) | R8: =INDEX('05_Param_Prog_Annee'!$H$4:$H$23,MATCH(N8,'05_Param_Prog_Annee'!$A$4:$A$23,0)) | S8: =INDEX('05_Param_Prog_Annee'!$I$4:$I$23,MATCH(N8,'05_Param_Prog_Annee'!$A$4:$A$23,0)) | T8: =IFERROR(INDEX('05_Param_Prog_Annee'!$J$4:$J$23,MATCH(N8,'05_Param_Prog_Annee'!$A$4:$A$23,0)),0) | U8: =P8*Q8*(1+'01_Cadrage'!$H$21) | V8: =INDEX('01_Cadrage'!$L$7:$L$20,MATCH(A8&"|"&B8,'01_Cadrage'!$O$7:$O$20,0)) | W8: =INDEX('01_Cadrage'!$M$7:$M$20,MATCH(A8&"|"&B8,'01_Cadrage'!$O$7:$O$20,0)) | X8: =IFERROR(INDEX('06_Historique'!$F$66:$F$73,MATCH(C8,'06_Historique'!$A$66:$A$73,0)),'01_Cadrage'!$H$27) | Y8: ='01_Cadrage'!$H$16*V8 | Z8: =IF(F8=1,J8*(1+X8*Y8),0) | AA8: =IF(F8=1,IFERROR(H8/J8,'01_Cadrage'!$H$28)+'01_Cadrage'!$H$18,0) | AB8: =Z8*AA8 | AC8: =IF(F8=1,0,K8*(T8+'01_Cadrage'!$H$19)) | AD8: =AB8+AC8 | AE8: =L8*(1+'01_Cadrage'!$H$17*W8) | AF8: =1 | AG8: =1 | AH8: =AD8*AE8*AF8+AB8*'01_Cadrage'!$H$24 | AI8: =IF(AD8<=0,0,MAX(1,ROUNDUP(AD8/O8,0))) | AJ8: =AI8*U8 | AK8: =AD8*R8*(1+'01_Cadrage'!$H$20) | AL8: =H8*S8*(1+Y8) | AM8: =AH8-AJ8-AK8-AL8-AD8*'01_Cadrage'!$H$26*(1+'01_Cadrage'!$H$20) | AN8: =IFERROR(AD8/(AI8*O8),0) | AO8: =IFERROR(AM8/AD8,0) | AP8: =IFERROR(AI8*U8/(AE8*AF8-R8*(1+'01_Cadrage'!$H$20)),0)
A9: ='06_Historique'!A10 | B9: ='06_Historique'!B10 | C9: ='06_Historique'!C10 | D9: ='06_Historique'!E10 | E9: ='06_Historique'!F10 | F9: ='06_Historique'!G10 | G9: ='06_Historique'!K10 | H9: ='06_Historique'!I10 | I9: ='06_Historique'!J10 | J9: ='06_Historique'!H10 | K9: ='06_Historique'!L10 | L9: ='06_Historique'!M10 | M9: ='06_Historique'!N10 | N9: =C9&"|"&D9 | O9: =INDEX('05_Param_Prog_Annee'!$E$4:$E$23,MATCH(N9,'05_Param_Prog_Annee'!$A$4:$A$23,0)) | P9: =INDEX('05_Param_Prog_Annee'!$F$4:$F$23,MATCH(N9,'05_Param_Prog_Annee'!$A$4:$A$23,0)) | Q9: =INDEX('05_Param_Prog_Annee'!$G$4:$G$23,MATCH(N9,'05_Param_Prog_Annee'!$A$4:$A$23,0)) | R9: =INDEX('05_Param_Prog_Annee'!$H$4:$H$23,MATCH(N9,'05_Param_Prog_Annee'!$A$4:$A$23,0)) | S9: =INDEX('05_Param_Prog_Annee'!$I$4:$I$23,MATCH(N9,'05_Param_Prog_Annee'!$A$4:$A$23,0)) | T9: =IFERROR(INDEX('05_Param_Prog_Annee'!$J$4:$J$23,MATCH(N9,'05_Param_Prog_Annee'!$A$4:$A$23,0)),0) | U9: =P9*Q9*(1+'01_Cadrage'!$H$21) | V9: =INDEX('01_Cadrage'!$L$7:$L$20,MATCH(A9&"|"&B9,'01_Cadrage'!$O$7:$O$20,0)) | W9: =INDEX('01_Cadrage'!$M$7:$M$20,MATCH(A9&"|"&B9,'01_Cadrage'!$O$7:$O$20,0)) | X9: =IFERROR(INDEX('06_Historique'!$F$66:$F$73,MATCH(C9,'06_Historique'!$A$66:$A$73,0)),'01_Cadrage'!$H$27) | Y9: ='01_Cadrage'!$H$16*V9 | Z9: =IF(F9=1,J9*(1+X9*Y9),0) | AA9: =IF(F9=1,IFERROR(H9/J9,'01_Cadrage'!$H$28)+'01_Cadrage'!$H$18,0) | AB9: =Z9*AA9 | AC9: =IF(F9=1,0,K9*(T9+'01_Cadrage'!$H$19)) | AD9: =AB9+AC9 | AE9: =L9*(1+'01_Cadrage'!$H$17*W9) | AF9: =1 | AG9: =1 | AH9: =AD9*AE9*AF9+AB9*'01_Cadrage'!$H$24 | AI9: =IF(AD9<=0,0,MAX(1,ROUNDUP(AD9/O9,0))) | AJ9: =AI9*U9 | AK9: =AD9*R9*(1+'01_Cadrage'!$H$20) | AL9: =H9*S9*(1+Y9) | AM9: =AH9-AJ9-AK9-AL9-AD9*'01_Cadrage'!$H$26*(1+'01_Cadrage'!$H$20) | AN9: =IFERROR(AD9/(AI9*O9),0) | AO9: =IFERROR(AM9/AD9,0) | AP9: =IFERROR(AI9*U9/(AE9*AF9-R9*(1+'01_Cadrage'!$H$20)),0)
A10: ='06_Historique'!A11 | B10: ='06_Historique'!B11 | C10: ='06_Historique'!C11 | D10: ='06_Historique'!E11 | E10: ='06_Historique'!F11 | F10: ='06_Historique'!G11 | G10: ='06_Historique'!K11 | H10: ='06_Historique'!I11 | I10: ='06_Historique'!J11 | J10: ='06_Historique'!H11 | K10: ='06_Historique'!L11 | L10: ='06_Historique'!M11 | M10: ='06_Historique'!N11 | N10: =C10&"|"&D10 | O10: =INDEX('05_Param_Prog_Annee'!$E$4:$E$23,MATCH(N10,'05_Param_Prog_Annee'!$A$4:$A$23,0)) | P10: =INDEX('05_Param_Prog_Annee'!$F$4:$F$23,MATCH(N10,'05_Param_Prog_Annee'!$A$4:$A$23,0)) | Q10: =INDEX('05_Param_Prog_Annee'!$G$4:$G$23,MATCH(N10,'05_Param_Prog_Annee'!$A$4:$A$23,0)) | R10: =INDEX('05_Param_Prog_Annee'!$H$4:$H$23,MATCH(N10,'05_Param_Prog_Annee'!$A$4:$A$23,0)) | S10: =INDEX('05_Param_Prog_Annee'!$I$4:$I$23,MATCH(N10,'05_Param_Prog_Annee'!$A$4:$A$23,0)) | T10: =IFERROR(INDEX('05_Param_Prog_Annee'!$J$4:$J$23,MATCH(N10,'05_Param_Prog_Annee'!$A$4:$A$23,0)),0) | U10: =P10*Q10*(1+'01_Cadrage'!$H$21) | V10: =INDEX('01_Cadrage'!$L$7:$L$20,MATCH(A10&"|"&B10,'01_Cadrage'!$O$7:$O$20,0)) | W10: =INDEX('01_Cadrage'!$M$7:$M$20,MATCH(A10&"|"&B10,'01_Cadrage'!$O$7:$O$20,0)) | X10: =IFERROR(INDEX('06_Historique'!$F$66:$F$73,MATCH(C10,'06_Historique'!$A$66:$A$73,0)),'01_Cadrage'!$H$27) | Y10: ='01_Cadrage'!$H$16*V10 | Z10: =IF(F10=1,J10*(1+X10*Y10),0) | AA10: =IF(F10=1,IFERROR(H10/J10,'01_Cadrage'!$H$28)+'01_Cadrage'!$H$18,0) | AB10: =Z10*AA10 | AC10: =IF(F10=1,0,K10*(T10+'01_Cadrage'!$H$19)) | AD10: =AB10+AC10 | AE10: =L10*(1+'01_Cadrage'!$H$17*W10) | AF10: =1 | AG10: =1 | AH10: =AD10*AE10*AF10+AB10*'01_Cadrage'!$H$24 | AI10: =IF(AD10<=0,0,MAX(1,ROUNDUP(AD10/O10,0))) | AJ10: =AI10*U10 | AK10: =AD10*R10*(1+'01_Cadrage'!$H$20) | AL10: =H10*S10*(1+Y10) | AM10: =AH10-AJ10-AK10-AL10-AD10*'01_Cadrage'!$H$26*(1+'01_Cadrage'!$H$20) | AN10: =IFERROR(AD10/(AI10*O10),0) | AO10: =IFERROR(AM10/AD10,0) | AP10: =IFERROR(AI10*U10/(AE10*AF10-R10*(1+'01_Cadrage'!$H$20)),0)
A11: ='06_Historique'!A12 | B11: ='06_Historique'!B12 | C11: ='06_Historique'!C12 | D11: ='06_Historique'!E12 | E11: ='06_Historique'!F12 | F11: ='06_Historique'!G12 | G11: ='06_Historique'!K12 | H11: ='06_Historique'!I12 | I11: ='06_Historique'!J12 | J11: ='06_Historique'!H12 | K11: ='06_Historique'!L12 | L11: ='06_Historique'!M12 | M11: ='06_Historique'!N12 | N11: =C11&"|"&D11 | O11: =INDEX('05_Param_Prog_Annee'!$E$4:$E$23,MATCH(N11,'05_Param_Prog_Annee'!$A$4:$A$23,0)) | P11: =INDEX('05_Param_Prog_Annee'!$F$4:$F$23,MATCH(N11,'05_Param_Prog_Annee'!$A$4:$A$23,0)) | Q11: =INDEX('05_Param_Prog_Annee'!$G$4:$G$23,MATCH(N11,'05_Param_Prog_Annee'!$A$4:$A$23,0)) | R11: =INDEX('05_Param_Prog_Annee'!$H$4:$H$23,MATCH(N11,'05_Param_Prog_Annee'!$A$4:$A$23,0)) | S11: =INDEX('05_Param_Prog_Annee'!$I$4:$I$23,MATCH(N11,'05_Param_Prog_Annee'!$A$4:$A$23,0)) | T11: =IFERROR(INDEX('05_Param_Prog_Annee'!$J$4:$J$23,MATCH(N11,'05_Param_Prog_Annee'!$A$4:$A$23,0)),0) | U11: =P11*Q11*(1+'01_Cadrage'!$H$21) | V11: =INDEX('01_Cadrage'!$L$7:$L$20,MATCH(A11&"|"&B11,'01_Cadrage'!$O$7:$O$20,0)) | W11: =INDEX('01_Cadrage'!$M$7:$M$20,MATCH(A11&"|"&B11,'01_Cadrage'!$O$7:$O$20,0)) | X11: =IFERROR(INDEX('06_Historique'!$F$66:$F$73,MATCH(C11,'06_Historique'!$A$66:$A$73,0)),'01_Cadrage'!$H$27) | Y11: ='01_Cadrage'!$H$16*V11 | Z11: =IF(F11=1,J11*(1+X11*Y11),0) | AA11: =IF(F11=1,IFERROR(H11/J11,'01_Cadrage'!$H$28)+'01_Cadrage'!$H$18,0) | AB11: =Z11*AA11 | AC11: =IF(F11=1,0,K11*(T11+'01_Cadrage'!$H$19)) | AD11: =AB11+AC11 | AE11: =L11*(1+'01_Cadrage'!$H$17*W11) | AF11: =1 | AG11: =1 | AH11: =AD11*AE11*AF11+AB11*'01_Cadrage'!$H$24 | AI11: =IF(AD11<=0,0,MAX(1,ROUNDUP(AD11/O11,0))) | AJ11: =AI11*U11 | AK11: =AD11*R11*(1+'01_Cadrage'!$H$20) | AL11: =H11*S11*(1+Y11) | AM11: =AH11-AJ11-AK11-AL11-AD11*'01_Cadrage'!$H$26*(1+'01_Cadrage'!$H$20) | AN11: =IFERROR(AD11/(AI11*O11),0) | AO11: =IFERROR(AM11/AD11,0) | AP11: =IFERROR(AI11*U11/(AE11*AF11-R11*(1+'01_Cadrage'!$H$20)),0)
A12: ='06_Historique'!A13 | B12: ='06_Historique'!B13 | C12: ='06_Historique'!C13 | D12: ='06_Historique'!E13 | E12: ='06_Historique'!F13 | F12: ='06_Historique'!G13 | G12: ='06_Historique'!K13 | H12: ='06_Historique'!I13 | I12: ='06_Historique'!J13 | J12: ='06_Historique'!H13 | K12: ='06_Historique'!L13 | L12: ='06_Historique'!M13 | M12: ='06_Historique'!N13 | N12: =C12&"|"&D12 | O12: =INDEX('05_Param_Prog_Annee'!$E$4:$E$23,MATCH(N12,'05_Param_Prog_Annee'!$A$4:$A$23,0)) | P12: =INDEX('05_Param_Prog_Annee'!$F$4:$F$23,MATCH(N12,'05_Param_Prog_Annee'!$A$4:$A$23,0)) | Q12: =INDEX('05_Param_Prog_Annee'!$G$4:$G$23,MATCH(N12,'05_Param_Prog_Annee'!$A$4:$A$23,0)) | R12: =INDEX('05_Param_Prog_Annee'!$H$4:$H$23,MATCH(N12,'05_Param_Prog_Annee'!$A$4:$A$23,0)) | S12: =INDEX('05_Param_Prog_Annee'!$I$4:$I$23,MATCH(N12,'05_Param_Prog_Annee'!$A$4:$A$23,0)) | T12: =IFERROR(INDEX('05_Param_Prog_Annee'!$J$4:$J$23,MATCH(N12,'05_Param_Prog_Annee'!$A$4:$A$23,0)),0) | U12: =P12*Q12*(1+'01_Cadrage'!$H$21) | V12: =INDEX('01_Cadrage'!$L$7:$L$20,MATCH(A12&"|"&B12,'01_Cadrage'!$O$7:$O$20,0)) | W12: =INDEX('01_Cadrage'!$M$7:$M$20,MATCH(A12&"|"&B12,'01_Cadrage'!$O$7:$O$20,0)) | X12: =IFERROR(INDEX('06_Historique'!$F$66:$F$73,MATCH(C12,'06_Historique'!$A$66:$A$73,0)),'01_Cadrage'!$H$27) | Y12: ='01_Cadrage'!$H$16*V12 | Z12: =IF(F12=1,J12*(1+X12*Y12),0) | AA12: =IF(F12=1,IFERROR(H12/J12,'01_Cadrage'!$H$28)+'01_Cadrage'!$H$18,0) | AB12: =Z12*AA12 | AC12: =IF(F12=1,0,K12*(T12+'01_Cadrage'!$H$19)) | AD12: =AB12+AC12 | AE12: =L12*(1+'01_Cadrage'!$H$17*W12) | AF12: =1 | AG12: =1 | AH12: =AD12*AE12*AF12+AB12*'01_Cadrage'!$H$24 | AI12: =IF(AD12<=0,0,MAX(1,ROUNDUP(AD12/O12,0))) | AJ12: =AI12*U12 | AK12: =AD12*R12*(1+'01_Cadrage'!$H$20) | AL12: =H12*S12*(1+Y12) | AM12: =AH12-AJ12-AK12-AL12-AD12*'01_Cadrage'!$H$26*(1+'01_Cadrage'!$H$20) | AN12: =IFERROR(AD12/(AI12*O12),0) | AO12: =IFERROR(AM12/AD12,0) | AP12: =IFERROR(AI12*U12/(AE12*AF12-R12*(1+'01_Cadrage'!$H$20)),0)
A13: ='06_Historique'!A14 | B13: ='06_Historique'!B14 | C13: ='06_Historique'!C14 | D13: ='06_Historique'!E14 | E13: ='06_Historique'!F14 | F13: ='06_Historique'!G14 | G13: ='06_Historique'!K14 | H13: ='06_Historique'!I14 | I13: ='06_Historique'!J14 | J13: ='06_Historique'!H14 | K13: ='06_Historique'!L14 | L13: ='06_Historique'!M14 | M13: ='06_Historique'!N14 | N13: =C13&"|"&D13 | O13: =INDEX('05_Param_Prog_Annee'!$E$4:$E$23,MATCH(N13,'05_Param_Prog_Annee'!$A$4:$A$23,0)) | P13: =INDEX('05_Param_Prog_Annee'!$F$4:$F$23,MATCH(N13,'05_Param_Prog_Annee'!$A$4:$A$23,0)) | Q13: =INDEX('05_Param_Prog_Annee'!$G$4:$G$23,MATCH(N13,'05_Param_Prog_Annee'!$A$4:$A$23,0)) | R13: =INDEX('05_Param_Prog_Annee'!$H$4:$H$23,MATCH(N13,'05_Param_Prog_Annee'!$A$4:$A$23,0)) | S13: =INDEX('05_Param_Prog_Annee'!$I$4:$I$23,MATCH(N13,'05_Param_Prog_Annee'!$A$4:$A$23,0)) | T13: =IFERROR(INDEX('05_Param_Prog_Annee'!$J$4:$J$23,MATCH(N13,'05_Param_Prog_Annee'!$A$4:$A$23,0)),0) | U13: =P13*Q13*(1+'01_Cadrage'!$H$21) | V13: =INDEX('01_Cadrage'!$L$7:$L$20,MATCH(A13&"|"&B13,'01_Cadrage'!$O$7:$O$20,0)) | W13: =INDEX('01_Cadrage'!$M$7:$M$20,MATCH(A13&"|"&B13,'01_Cadrage'!$O$7:$O$20,0)) | X13: =IFERROR(INDEX('06_Historique'!$F$66:$F$73,MATCH(C13,'06_Historique'!$A$66:$A$73,0)),'01_Cadrage'!$H$27) | Y13: ='01_Cadrage'!$H$16*V13 | Z13: =IF(F13=1,J13*(1+X13*Y13),0) | AA13: =IF(F13=1,IFERROR(H13/J13,'01_Cadrage'!$H$28)+'01_Cadrage'!$H$18,0) | AB13: =Z13*AA13 | AC13: =IF(F13=1,0,K13*(T13+'01_Cadrage'!$H$19)) | AD13: =AB13+AC13 | AE13: =L13*(1+'01_Cadrage'!$H$17*W13) | AF13: =1 | AG13: =1 | AH13: =AD13*AE13*AF13+AB13*'01_Cadrage'!$H$24 | AI13: =IF(AD13<=0,0,MAX(1,ROUNDUP(AD13/O13,0))) | AJ13: =AI13*U13 | AK13: =AD13*R13*(1+'01_Cadrage'!$H$20) | AL13: =H13*S13*(1+Y13) | AM13: =AH13-AJ13-AK13-AL13-AD13*'01_Cadrage'!$H$26*(1+'01_Cadrage'!$H$20) | AN13: =IFERROR(AD13/(AI13*O13),0) | AO13: =IFERROR(AM13/AD13,0) | AP13: =IFERROR(AI13*U13/(AE13*AF13-R13*(1+'01_Cadrage'!$H$20)),0)
A14: ='06_Historique'!A15 | B14: ='06_Historique'!B15 | C14: ='06_Historique'!C15 | D14: ='06_Historique'!E15 | E14: ='06_Historique'!F15 | F14: ='06_Historique'!G15 | G14: ='06_Historique'!K15 | H14: ='06_Historique'!I15 | I14: ='06_Historique'!J15 | J14: ='06_Historique'!H15 | K14: ='06_Historique'!L15 | L14: ='06_Historique'!M15 | M14: ='06_Historique'!N15 | N14: =C14&"|"&D14 | O14: =INDEX('05_Param_Prog_Annee'!$E$4:$E$23,MATCH(N14,'05_Param_Prog_Annee'!$A$4:$A$23,0)) | P14: =INDEX('05_Param_Prog_Annee'!$F$4:$F$23,MATCH(N14,'05_Param_Prog_Annee'!$A$4:$A$23,0)) | Q14: =INDEX('05_Param_Prog_Annee'!$G$4:$G$23,MATCH(N14,'05_Param_Prog_Annee'!$A$4:$A$23,0)) | R14: =INDEX('05_Param_Prog_Annee'!$H$4:$H$23,MATCH(N14,'05_Param_Prog_Annee'!$A$4:$A$23,0)) | S14: =INDEX('05_Param_Prog_Annee'!$I$4:$I$23,MATCH(N14,'05_Param_Prog_Annee'!$A$4:$A$23,0)) | T14: =IFERROR(INDEX('05_Param_Prog_Annee'!$J$4:$J$23,MATCH(N14,'05_Param_Prog_Annee'!$A$4:$A$23,0)),0) | U14: =P14*Q14*(1+'01_Cadrage'!$H$21) | V14: =INDEX('01_Cadrage'!$L$7:$L$20,MATCH(A14&"|"&B14,'01_Cadrage'!$O$7:$O$20,0)) | W14: =INDEX('01_Cadrage'!$M$7:$M$20,MATCH(A14&"|"&B14,'01_Cadrage'!$O$7:$O$20,0)) | X14: =IFERROR(INDEX('06_Historique'!$F$66:$F$73,MATCH(C14,'06_Historique'!$A$66:$A$73,0)),'01_Cadrage'!$H$27) | Y14: ='01_Cadrage'!$H$16*V14 | Z14: =IF(F14=1,J14*(1+X14*Y14),0) | AA14: =IF(F14=1,IFERROR(H14/J14,'01_Cadrage'!$H$28)+'01_Cadrage'!$H$18,0) | AB14: =Z14*AA14 | AC14: =IF(F14=1,0,K14*(T14+'01_Cadrage'!$H$19)) | AD14: =AB14+AC14 | AE14: =L14*(1+'01_Cadrage'!$H$17*W14) | AF14: =1 | AG14: =1 | AH14: =AD14*AE14*AF14+AB14*'01_Cadrage'!$H$24 | AI14: =IF(AD14<=0,0,MAX(1,ROUNDUP(AD14/O14,0))) | AJ14: =AI14*U14 | AK14: =AD14*R14*(1+'01_Cadrage'!$H$20) | AL14: =H14*S14*(1+Y14) | AM14: =AH14-AJ14-AK14-AL14-AD14*'01_Cadrage'!$H$26*(1+'01_Cadrage'!$H$20) | AN14: =IFERROR(AD14/(AI14*O14),0) | AO14: =IFERROR(AM14/AD14,0) | AP14: =IFERROR(AI14*U14/(AE14*AF14-R14*(1+'01_Cadrage'!$H$20)),0)
... A60: ='06_Historique'!A61 | B60: ='06_Historique'!B61 | C60: ='06_Historique'!C61 | D60: ='06_Historique'!E61 | E60: ='06_Historique'!F61 | F60: ='06_Historique'!G61 | G60: ='06_Historique'!K61 | H60: ='06_Historique'!I61 | I60: ='06_Historique'!J61 | J60: ='06_Historique'!H61 | K60: ='06_Historique'!L61 | L60: ='06_Historique'!M61 | M60: ='06_Historique'!N61 | N60: =C60&"|"&D60 | O60: =INDEX('05_Param_Prog_Annee'!$E$4:$E$23,MATCH(N60,'05_Param_Prog_Annee'!$A$4:$A$23,0)) | P60: =INDEX('05_Param_Prog_Annee'!$F$4:$F$23,MATCH(N60,'05_Param_Prog_Annee'!$A$4:$A$23,0)) | Q60: =INDEX('05_Param_Prog_Annee'!$G$4:$G$23,MATCH(N60,'05_Param_Prog_Annee'!$A$4:$A$23,0)) | R60: =INDEX('05_Param_Prog_Annee'!$H$4:$H$23,MATCH(N60,'05_Param_Prog_Annee'!$A$4:$A$23,0)) | S60: =INDEX('05_Param_Prog_Annee'!$I$4:$I$23,MATCH(N60,'05_Param_Prog_Annee'!$A$4:$A$23,0)) | T60: =IFERROR(INDEX('05_Param_Prog_Annee'!$J$4:$J$23,MATCH(N60,'05_Param_Prog_Annee'!$A$4:$A$23,0)),0) | U60: =P60*Q60*(1+'01_Cadrage'!$H$21) | V60: =INDEX('01_Cadrage'!$L$7:$L$20,MATCH(A60&"|"&B60,'01_Cadrage'!$O$7:$O$20,0)) | W60: =INDEX('01_Cadrage'!$M$7:$M$20,MATCH(A60&"|"&B60,'01_Cadrage'!$O$7:$O$20,0)) | X60: =IFERROR(INDEX('06_Historique'!$F$66:$F$73,MATCH(C60,'06_Historique'!$A$66:$A$73,0)),'01_Cadrage'!$H$27) | Y60: ='01_Cadrage'!$H$16*V60 | Z60: =IF(F60=1,J60*(1+X60*Y60),0) | AA60: =IF(F60=1,IFERROR(H60/J60,'01_Cadrage'!$H$28)+'01_Cadrage'!$H$18,0) | AB60: =Z60*AA60 | AC60: =IF(F60=1,0,K60*(T60+'01_Cadrage'!$H$19)) | AD60: =AB60+AC60 | AE60: =L60*(1+'01_Cadrage'!$H$17*W60) | AF60: =1 | AG60: =1 | AH60: =AD60*AE60*AF60+AB60*'01_Cadrage'!$H$24 | AI60: =IF(AD60<=0,0,MAX(1,ROUNDUP(AD60/O60,0))) | AJ60: =AI60*U60 | AK60: =AD60*R60*(1+'01_Cadrage'!$H$20) | AL60: =H60*S60*(1+Y60) | AM60: =AH60-AJ60-AK60-AL60-AD60*'01_Cadrage'!$H$26*(1+'01_Cadrage'!$H$20) | AN60: =IFERROR(AD60/(AI60*O60),0) | AO60: =IFERROR(AM60/AD60,0) | AP60: =IFERROR(AI60*U60/(AE60*AF60-R60*(1+'01_Cadrage'!$H$20)),0)
A61: TOTAL | F61: =SUM(F3:F60) | G61: =SUM(G3:G60) | H61: =SUM(H3:H60) | AB61: =SUM(AB3:AB60) | AC61: =SUM(AC3:AC60) | AD61: =SUM(AD3:AD60) | AH61: =SUM(AH3:AH60) | AI61: =SUM(AI3:AI60) | AJ61: =SUM(AJ3:AJ60) | AK61: =SUM(AK3:AK60) | AL61: =SUM(AL3:AL60) | AM61: =SUM(AM3:AM60)
A63: Guide de lecture — de gauche à droite, chaque bloc construit le budget de la cellule :
A64: A–F | B64: Identité & type : marque, campus, programme, année, modalité, année d'entrée (1 = on recrute)
A65: G–M | B65: Réalisé N-1 repris : effectif, nouveaux, réinscrits, candidatures, effectif année inférieure, tarif, classes
A66: N–T | B66: Paramètres programme×année (feuille 05) : capacité, heures, taux, pédago, CAC variable, taux de passage
A67: U–Y | B67: Coûts unitaires & coefficients : coût/classe, coeff marketing, coeff prix, élasticité, effort
A68: Z–AD | B68: COHORTE → VOLUME : candidatures budget → conversion → nouveaux + réinscrits = EFFECTIF budget
A69: AE–AH | B69: Tarif & CA budget : tarif budget, CA budget
A70: AI–AL | B70: Coûts budget : classes nécessaires, enseignement, pédagogie, marketing
A71: AM–AP | B71: RÉSULTATS : marge de CONTRIBUTION, remplissage, contribution/étudiant, point mort (seuil d'ouverture)

Sheet 09_Allocation
B2: Allocation des frais de structure par driver
B3: Driver actif : | C3: ='01_Cadrage'!$D$34 | E3: Frais de structure (fixe) à allouer : | H3: ='01_Cadrage'!$H$25*(1+'01_Cadrage'!$H$20)
B5: Marque | C5: Ville | D5: Contribution | E5: Loyer | F5: Masse perm. | G5: Driver | H5: Part | I5: Alloué | J5: EBITDA campus | K5: D&A | L5: EBIT
B6: MBway | C6: Paris | D6: =SUMIFS('08_Moteur'!$AM$3:$AM$60,'08_Moteur'!$A$3:$A$60,"MBway",'08_Moteur'!$B$3:$B$60,"Paris") | E6: ='07_Structure'!F4*(1+'01_Cadrage'!$H$20) | F6: ='07_Structure'!G4*'01_Cadrage'!$H$23*(1+'01_Cadrage'!$H$21) | G6: =IF($C$3="Effectifs",SUMIFS('08_Moteur'!$AD$3:$AD$60,'08_Moteur'!$A$3:$A$60,"MBway",'08_Moteur'!$B$3:$B$60,"Paris"),IF($C$3="Chiffre d'affaires",SUMIFS('08_Moteur'!$AH$3:$AH$60,'08_Moteur'!$A$3:$A$60,"MBway",'08_Moteur'!$B$3:$B$60,"Paris"),'07_Structure'!J4)) | H6: =IFERROR(G6/SUM($G$6:$G$19),0) | I6: =H6*$H$3 | J6: =D6-E6-F6-I6 | K6: ='07_Structure'!I4 | L6: =J6-K6
B7: MBway | C7: Lyon | D7: =SUMIFS('08_Moteur'!$AM$3:$AM$60,'08_Moteur'!$A$3:$A$60,"MBway",'08_Moteur'!$B$3:$B$60,"Lyon") | E7: ='07_Structure'!F5*(1+'01_Cadrage'!$H$20) | F7: ='07_Structure'!G5*'01_Cadrage'!$H$23*(1+'01_Cadrage'!$H$21) | G7: =IF($C$3="Effectifs",SUMIFS('08_Moteur'!$AD$3:$AD$60,'08_Moteur'!$A$3:$A$60,"MBway",'08_Moteur'!$B$3:$B$60,"Lyon"),IF($C$3="Chiffre d'affaires",SUMIFS('08_Moteur'!$AH$3:$AH$60,'08_Moteur'!$A$3:$A$60,"MBway",'08_Moteur'!$B$3:$B$60,"Lyon"),'07_Structure'!J5)) | H7: =IFERROR(G7/SUM($G$6:$G$19),0) | I7: =H7*$H$3 | J7: =D7-E7-F7-I7 | K7: ='07_Structure'!I5 | L7: =J7-K7
B8: MBway | C8: Nantes | D8: =SUMIFS('08_Moteur'!$AM$3:$AM$60,'08_Moteur'!$A$3:$A$60,"MBway",'08_Moteur'!$B$3:$B$60,"Nantes") | E8: ='07_Structure'!F6*(1+'01_Cadrage'!$H$20) | F8: ='07_Structure'!G6*'01_Cadrage'!$H$23*(1+'01_Cadrage'!$H$21) | G8: =IF($C$3="Effectifs",SUMIFS('08_Moteur'!$AD$3:$AD$60,'08_Moteur'!$A$3:$A$60,"MBway",'08_Moteur'!$B$3:$B$60,"Nantes"),IF($C$3="Chiffre d'affaires",SUMIFS('08_Moteur'!$AH$3:$AH$60,'08_Moteur'!$A$3:$A$60,"MBway",'08_Moteur'!$B$3:$B$60,"Nantes"),'07_Structure'!J6)) | H8: =IFERROR(G8/SUM($G$6:$G$19),0) | I8: =H8*$H$3 | J8: =D8-E8-F8-I8 | K8: ='07_Structure'!I6 | L8: =J8-K8
B9: MBway | C9: Bordeaux | D9: =SUMIFS('08_Moteur'!$AM$3:$AM$60,'08_Moteur'!$A$3:$A$60,"MBway",'08_Moteur'!$B$3:$B$60,"Bordeaux") | E9: ='07_Structure'!F7*(1+'01_Cadrage'!$H$20) | F9: ='07_Structure'!G7*'01_Cadrage'!$H$23*(1+'01_Cadrage'!$H$21) | G9: =IF($C$3="Effectifs",SUMIFS('08_Moteur'!$AD$3:$AD$60,'08_Moteur'!$A$3:$A$60,"MBway",'08_Moteur'!$B$3:$B$60,"Bordeaux"),IF($C$3="Chiffre d'affaires",SUMIFS('08_Moteur'!$AH$3:$AH$60,'08_Moteur'!$A$3:$A$60,"MBway",'08_Moteur'!$B$3:$B$60,"Bordeaux"),'07_Structure'!J7)) | H9: =IFERROR(G9/SUM($G$6:$G$19),0) | I9: =H9*$H$3 | J9: =D9-E9-F9-I9 | K9: ='07_Structure'!I7 | L9: =J9-K9
B10: ISCOM | C10: Paris | D10: =SUMIFS('08_Moteur'!$AM$3:$AM$60,'08_Moteur'!$A$3:$A$60,"ISCOM",'08_Moteur'!$B$3:$B$60,"Paris") | E10: ='07_Structure'!F8*(1+'01_Cadrage'!$H$20) | F10: ='07_Structure'!G8*'01_Cadrage'!$H$23*(1+'01_Cadrage'!$H$21) | G10: =IF($C$3="Effectifs",SUMIFS('08_Moteur'!$AD$3:$AD$60,'08_Moteur'!$A$3:$A$60,"ISCOM",'08_Moteur'!$B$3:$B$60,"Paris"),IF($C$3="Chiffre d'affaires",SUMIFS('08_Moteur'!$AH$3:$AH$60,'08_Moteur'!$A$3:$A$60,"ISCOM",'08_Moteur'!$B$3:$B$60,"Paris"),'07_Structure'!J8)) | H10: =IFERROR(G10/SUM($G$6:$G$19),0) | I10: =H10*$H$3 | J10: =D10-E10-F10-I10 | K10: ='07_Structure'!I8 | L10: =J10-K10
B11: ISCOM | C11: Lille | D11: =SUMIFS('08_Moteur'!$AM$3:$AM$60,'08_Moteur'!$A$3:$A$60,"ISCOM",'08_Moteur'!$B$3:$B$60,"Lille") | E11: ='07_Structure'!F9*(1+'01_Cadrage'!$H$20) | F11: ='07_Structure'!G9*'01_Cadrage'!$H$23*(1+'01_Cadrage'!$H$21) | G11: =IF($C$3="Effectifs",SUMIFS('08_Moteur'!$AD$3:$AD$60,'08_Moteur'!$A$3:$A$60,"ISCOM",'08_Moteur'!$B$3:$B$60,"Lille"),IF($C$3="Chiffre d'affaires",SUMIFS('08_Moteur'!$AH$3:$AH$60,'08_Moteur'!$A$3:$A$60,"ISCOM",'08_Moteur'!$B$3:$B$60,"Lille"),'07_Structure'!J9)) | H11: =IFERROR(G11/SUM($G$6:$G$19),0) | I11: =H11*$H$3 | J11: =D11-E11-F11-I11 | K11: ='07_Structure'!I9 | L11: =J11-K11
B12: ISCOM | C12: Toulouse | D12: =SUMIFS('08_Moteur'!$AM$3:$AM$60,'08_Moteur'!$A$3:$A$60,"ISCOM",'08_Moteur'!$B$3:$B$60,"Toulouse") | E12: ='07_Structure'!F10*(1+'01_Cadrage'!$H$20) | F12: ='07_Structure'!G10*'01_Cadrage'!$H$23*(1+'01_Cadrage'!$H$21) | G12: =IF($C$3="Effectifs",SUMIFS('08_Moteur'!$AD$3:$AD$60,'08_Moteur'!$A$3:$A$60,"ISCOM",'08_Moteur'!$B$3:$B$60,"Toulouse"),IF($C$3="Chiffre d'affaires",SUMIFS('08_Moteur'!$AH$3:$AH$60,'08_Moteur'!$A$3:$A$60,"ISCOM",'08_Moteur'!$B$3:$B$60,"Toulouse"),'07_Structure'!J10)) | H12: =IFERROR(G12/SUM($G$6:$G$19),0) | I12: =H12*$H$3 | J12: =D12-E12-F12-I12 | K12: ='07_Structure'!I10 | L12: =J12-K12
B13: Ipac Bachelor Factory | C13: Nantes | D13: =SUMIFS('08_Moteur'!$AM$3:$AM$60,'08_Moteur'!$A$3:$A$60,"Ipac Bachelor Factory",'08_Moteur'!$B$3:$B$60,"Nantes") | E13: ='07_Structure'!F11*(1+'01_Cadrage'!$H$20) | F13: ='07_Structure'!G11*'01_Cadrage'!$H$23*(1+'01_Cadrage'!$H$21) | G13: =IF($C$3="Effectifs",SUMIFS('08_Moteur'!$AD$3:$AD$60,'08_Moteur'!$A$3:$A$60,"Ipac Bachelor Factory",'08_Moteur'!$B$3:$B$60,"Nantes"),IF($C$3="Chiffre d'affaires",SUMIFS('08_Moteur'!$AH$3:$AH$60,'08_Moteur'!$A$3:$A$60,"Ipac Bachelor Factory",'08_Moteur'!$B$3:$B$60,"Nantes"),'07_Structure'!J11)) | H13: =IFERROR(G13/SUM($G$6:$G$19),0) | I13: =H13*$H$3 | J13: =D13-E13-F13-I13 | K13: ='07_Structure'!I11 | L13: =J13-K13
B14: Ipac Bachelor Factory | C14: Rennes | D14: =SUMIFS('08_Moteur'!$AM$3:$AM$60,'08_Moteur'!$A$3:$A$60,"Ipac Bachelor Factory",'08_Moteur'!$B$3:$B$60,"Rennes") | E14: ='07_Structure'!F12*(1+'01_Cadrage'!$H$20) | F14: ='07_Structure'!G12*'01_Cadrage'!$H$23*(1+'01_Cadrage'!$H$21) | G14: =IF($C$3="Effectifs",SUMIFS('08_Moteur'!$AD$3:$AD$60,'08_Moteur'!$A$3:$A$60,"Ipac Bachelor Factory",'08_Moteur'!$B$3:$B$60,"Rennes"),IF($C$3="Chiffre d'affaires",SUMIFS('08_Moteur'!$AH$3:$AH$60,'08_Moteur'!$A$3:$A$60,"Ipac Bachelor Factory",'08_Moteur'!$B$3:$B$60,"Rennes"),'07_Structure'!J12)) | H14: =IFERROR(G14/SUM($G$6:$G$19),0) | I14: =H14*$H$3 | J14: =D14-E14-F14-I14 | K14: ='07_Structure'!I12 | L14: =J14-K14
B15: Ipac Bachelor Factory | C15: Montpellier | D15: =SUMIFS('08_Moteur'!$AM$3:$AM$60,'08_Moteur'!$A$3:$A$60,"Ipac Bachelor Factory",'08_Moteur'!$B$3:$B$60,"Montpellier") | E15: ='07_Structure'!F13*(1+'01_Cadrage'!$H$20) | F15: ='07_Structure'!G13*'01_Cadrage'!$H$23*(1+'01_Cadrage'!$H$21) | G15: =IF($C$3="Effectifs",SUMIFS('08_Moteur'!$AD$3:$AD$60,'08_Moteur'!$A$3:$A$60,"Ipac Bachelor Factory",'08_Moteur'!$B$3:$B$60,"Montpellier"),IF($C$3="Chiffre d'affaires",SUMIFS('08_Moteur'!$AH$3:$AH$60,'08_Moteur'!$A$3:$A$60,"Ipac Bachelor Factory",'08_Moteur'!$B$3:$B$60,"Montpellier"),'07_Structure'!J13)) | H15: =IFERROR(G15/SUM($G$6:$G$19),0) | I15: =H15*$H$3 | J15: =D15-E15-F15-I15 | K15: ='07_Structure'!I13 | L15: =J15-K15
B16: Pigier | C16: Lyon | D16: =SUMIFS('08_Moteur'!$AM$3:$AM$60,'08_Moteur'!$A$3:$A$60,"Pigier",'08_Moteur'!$B$3:$B$60,"Lyon") | E16: ='07_Structure'!F14*(1+'01_Cadrage'!$H$20) | F16: ='07_Structure'!G14*'01_Cadrage'!$H$23*(1+'01_Cadrage'!$H$21) | G16: =IF($C$3="Effectifs",SUMIFS('08_Moteur'!$AD$3:$AD$60,'08_Moteur'!$A$3:$A$60,"Pigier",'08_Moteur'!$B$3:$B$60,"Lyon"),IF($C$3="Chiffre d'affaires",SUMIFS('08_Moteur'!$AH$3:$AH$60,'08_Moteur'!$A$3:$A$60,"Pigier",'08_Moteur'!$B$3:$B$60,"Lyon"),'07_Structure'!J14)) | H16: =IFERROR(G16/SUM($G$6:$G$19),0) | I16: =H16*$H$3 | J16: =D16-E16-F16-I16 | K16: ='07_Structure'!I14 | L16: =J16-K16
B17: Pigier | C17: Bordeaux | D17: =SUMIFS('08_Moteur'!$AM$3:$AM$60,'08_Moteur'!$A$3:$A$60,"Pigier",'08_Moteur'!$B$3:$B$60,"Bordeaux") | E17: ='07_Structure'!F15*(1+'01_Cadrage'!$H$20) | F17: ='07_Structure'!G15*'01_Cadrage'!$H$23*(1+'01_Cadrage'!$H$21) | G17: =IF($C$3="Effectifs",SUMIFS('08_Moteur'!$AD$3:$AD$60,'08_Moteur'!$A$3:$A$60,"Pigier",'08_Moteur'!$B$3:$B$60,"Bordeaux"),IF($C$3="Chiffre d'affaires",SUMIFS('08_Moteur'!$AH$3:$AH$60,'08_Moteur'!$A$3:$A$60,"Pigier",'08_Moteur'!$B$3:$B$60,"Bordeaux"),'07_Structure'!J15)) | H17: =IFERROR(G17/SUM($G$6:$G$19),0) | I17: =H17*$H$3 | J17: =D17-E17-F17-I17 | K17: ='07_Structure'!I15 | L17: =J17-K17
B18: Tunon | C18: Paris | D18: =SUMIFS('08_Moteur'!$AM$3:$AM$60,'08_Moteur'!$A$3:$A$60,"Tunon",'08_Moteur'!$B$3:$B$60,"Paris") | E18: ='07_Structure'!F16*(1+'01_Cadrage'!$H$20) | F18: ='07_Structure'!G16*'01_Cadrage'!$H$23*(1+'01_Cadrage'!$H$21) | G18: =IF($C$3="Effectifs",SUMIFS('08_Moteur'!$AD$3:$AD$60,'08_Moteur'!$A$3:$A$60,"Tunon",'08_Moteur'!$B$3:$B$60,"Paris"),IF($C$3="Chiffre d'affaires",SUMIFS('08_Moteur'!$AH$3:$AH$60,'08_Moteur'!$A$3:$A$60,"Tunon",'08_Moteur'!$B$3:$B$60,"Paris"),'07_Structure'!J16)) | H18: =IFERROR(G18/SUM($G$6:$G$19),0) | I18: =H18*$H$3 | J18: =D18-E18-F18-I18 | K18: ='07_Structure'!I16 | L18: =J18-K18
B19: Tunon | C19: Lyon | D19: =SUMIFS('08_Moteur'!$AM$3:$AM$60,'08_Moteur'!$A$3:$A$60,"Tunon",'08_Moteur'!$B$3:$B$60,"Lyon") | E19: ='07_Structure'!F17*(1+'01_Cadrage'!$H$20) | F19: ='07_Structure'!G17*'01_Cadrage'!$H$23*(1+'01_Cadrage'!$H$21) | G19: =IF($C$3="Effectifs",SUMIFS('08_Moteur'!$AD$3:$AD$60,'08_Moteur'!$A$3:$A$60,"Tunon",'08_Moteur'!$B$3:$B$60,"Lyon"),IF($C$3="Chiffre d'affaires",SUMIFS('08_Moteur'!$AH$3:$AH$60,'08_Moteur'!$A$3:$A$60,"Tunon",'08_Moteur'!$B$3:$B$60,"Lyon"),'07_Structure'!J17)) | H19: =IFERROR(G19/SUM($G$6:$G$19),0) | I19: =H19*$H$3 | J19: =D19-E19-F19-I19 | K19: ='07_Structure'!I17 | L19: =J19-K19
B20: TOTAL | D20: =SUM(D6:D19) | E20: =SUM(E6:E19) | F20: =SUM(F6:F19) | G20: =SUM(G6:G19) | I20: =SUM(I6:I19) | J20: =SUM(J6:J19) | K20: =SUM(K6:K19) | L20: =SUM(L6:L19)

Sheet 10_PnL
B2: Compte de résultat consolidé — Budget vs N-1
B3: Scénario : | C3: ='01_Cadrage'!D3
B5: Rubrique | C5: Réalisé N-1 | D5: Budget N+1 | E5: Écart € | F5: Écart %
B6: Effectifs | C6: ='07_Structure'!C18 | D6: =SUM('08_Moteur'!$AD$3:$AD$60) | E6: =D6-C6 | F6: =IFERROR(D6/C6-1,0)
B7: Chiffre d'affaires | C7: ='07_Structure'!D18 | D7: =SUM('08_Moteur'!$AH$3:$AH$60) | E7: =D7-C7 | F7: =IFERROR(D7/C7-1,0)
B8: Coûts directs (ens.+pédago+mktg+autres) | C8: =-('07_Structure'!D18-'07_Structure'!E18) | D8: =-(SUM('08_Moteur'!$AJ$3:$AJ$60)+SUM('08_Moteur'!$AK$3:$AK$60)+SUM('08_Moteur'!$AL$3:$AL$60)+'01_Cadrage'!$H$26*(1+'01_Cadrage'!$H$20)*SUM('08_Moteur'!$AD$3:$AD$60)) | E8: =D8-C8 | F8: =IFERROR(D8/C8-1,0)
B9: Marge de contribution | C9: ='07_Structure'!E18 | D9: =SUM('08_Moteur'!$AM$3:$AM$60) | E9: =D9-C9 | F9: =IFERROR(D9/C9-1,0)
B10: Loyers | C10: =-'07_Structure'!F18 | D10: =-'09_Allocation'!E20 | E10: =D10-C10 | F10: =IFERROR(D10/C10-1,0)
B11: Personnel permanent | C11: =-'07_Structure'!H18 | D11: =-'09_Allocation'!F20 | E11: =D11-C11 | F11: =IFERROR(D11/C11-1,0)
B12: Frais de structure groupe | C12: =-2000000 | D12: =-'09_Allocation'!I20 | E12: =D12-C12 | F12: =IFERROR(D12/C12-1,0)
B13: EBITDA | C13: ='07_Structure'!E18-'07_Structure'!F18-'07_Structure'!H18-2000000 | D13: ='09_Allocation'!J20 | E13: =D13-C13 | F13: =IFERROR(D13/C13-1,0)
B14: Marge EBITDA % | C14: =IFERROR(('07_Structure'!E18-'07_Structure'!F18-'07_Structure'!H18-2000000)/'07_Structure'!D18,0) | D14: =IFERROR('09_Allocation'!J20/SUM('08_Moteur'!$AH$3:$AH$60),0) | E14: =D14-C14
B15: D&A | C15: =-'07_Structure'!I18 | D15: =-'09_Allocation'!K20 | E15: =D15-C15 | F15: =IFERROR(D15/C15-1,0)
B16: EBIT | C16: ='07_Structure'!E18-'07_Structure'!F18-'07_Structure'!H18-2000000-'07_Structure'!I18 | D16: ='09_Allocation'!L20 | E16: =D16-C16 | F16: =IFERROR(D16/C16-1,0)
B18: Pont Chiffre d'affaires (N-1 → Budget)
B19: Effet | C19: Montant
B20: CA Réalisé N-1 | C20: ='07_Structure'!D18
B21: + Effet Volume | C21: =SUMPRODUCT(('08_Moteur'!$AD$3:$AD$60-'08_Moteur'!$G$3:$G$60)*'08_Moteur'!$L$3:$L$60)
B22: + Effet Tarif | C22: =SUMPRODUCT('08_Moteur'!$AD$3:$AD$60*('08_Moteur'!$AE$3:$AE$60-'08_Moteur'!$L$3:$L$60))
B23: + Effet Frais | C23: =SUMPRODUCT('08_Moteur'!$AB$3:$AB$60)*'01_Cadrage'!$H$24-SUMPRODUCT('08_Moteur'!$H$3:$H$60)*'01_Cadrage'!$H$24
B24: CA Budget N+1 | C24: =SUM('08_Moteur'!$AH$3:$AH$60)

Sheet 11_Simulateur
A1: Simulateur & conseil de décisions — logique CFO 360° : décider sur la CONTRIBUTION ; ouvrir/fermer redilue la structure sur TOUS
A2: EBITDA groupe AVANT : | D2: ='09_Allocation'!J20 | E2: Σ Δ décisions : | G2: =SUM(Q6:Q63) | I2: EBITDA groupe APRÈS : | K2: =D2+G2
A3: Structure / étudiant — AVANT : | D3: =('09_Allocation'!E20+'09_Allocation'!F20+'09_Allocation'!I20)/SUM('08_Moteur'!$AD$3:$AD$60) | E3: APRÈS : | G3: =IFERROR(('09_Allocation'!E20+'09_Allocation'!F20+'09_Allocation'!I20)/SUM(M6:M63),0) | I3: Effectif total APRÈS : | K3: =SUM(M6:M63) | M3: ⚠ Fermer retire des étudiants → structure/étudiant ↑ (tous absorbent +). Ouvrir en capte → structure/étudiant ↓ (tous s'enrichissent). La structure totale ne bouge pas ; l'EBITDA groupe ne varie que des contributions.
A4: 🧪 BAC À SABLE : décisions à la maille d'UNE promo — impact SIMULÉ (encadré ci-dessus), sans effet sur le budget officiel (09/10/13), qui se pilote via les LEVIERS (02). « Regrouper » ici respecte la capacité de la promo ; pour mutualiser des sections parallèles d'un même CAMPUS, voir la feuille 11b_Mutualisation.
A5: Marque | B5: Ville | C5: Programme | D5: Année | E5: Effectif | F5: CA | G5: Coûts directs évitables | H5: MARGE DE CONTRIBUTION | I5: Rempl. | J5: 🤖 Reco | K5: Motif | L5: Décision | M5: Effectif après | N5: Contribution après | O5: Structure allouée (après, dilution) | P5: Résultat tout compris (après) | Q5: Δ EBITDA
A6: ='08_Moteur'!A3 | B6: ='08_Moteur'!B3 | C6: ='08_Moteur'!C3 | D6: ='08_Moteur'!D3 | E6: ='08_Moteur'!AD3 | F6: ='08_Moteur'!AH3 | G6: =F6-'08_Moteur'!AM3 | H6: ='08_Moteur'!AM3 | I6: ='08_Moteur'!AN3 | J6: =IF(H6<0,"🔴 Ne pas lancer",IF(I6>=0.95,"🟢 Ouvrir +1 (capter+diluer)",IF(I6<0.55,"🟡 Surveiller","🟢 Maintenir"))) | K6: =IF(H6<0,"Entrée à contribution négative → ne pas lancer cette cohorte",IF(I6>=0.95,"Saturé → ouvrir capte des étudiants ET dilue la structure pour tous",IF(I6<0.55,"Sous-rempli mais contribution positive → garder","Sain"))) | L6: Maintenir | M6: =IF(L6="Ne pas lancer",0,IF(L6="Ouvrir +1 classe",E6+'08_Moteur'!O3,E6)) | N6: =IF(L6="Ne pas lancer",0,IF(L6="Ouvrir +1 classe",H6+'08_Moteur'!O3*('08_Moteur'!AE3*'08_Moteur'!AF3-('08_Moteur'!R3+'01_Cadrage'!$H$26)*(1+'01_Cadrage'!$H$20)-'08_Moteur'!S3)-'08_Moteur'!U3,IF(L6="Regrouper (-1 classe)",IF(AND('08_Moteur'!AI3>=2,E6<=('08_Moteur'!AI3-1)*'08_Moteur'!O3*1.1),H6+'08_Moteur'!U3,H6),H6))) | O6: =M6*IFERROR(('09_Allocation'!E20+'09_Allocation'!F20+'09_Allocation'!I20)/SUM(M6:M63),0) | P6: =N6-O6 | Q6: =N6-H6
A7: ='08_Moteur'!A4 | B7: ='08_Moteur'!B4 | C7: ='08_Moteur'!C4 | D7: ='08_Moteur'!D4 | E7: ='08_Moteur'!AD4 | F7: ='08_Moteur'!AH4 | G7: =F7-'08_Moteur'!AM4 | H7: ='08_Moteur'!AM4 | I7: ='08_Moteur'!AN4 | J7: =IF(H7<0,"🔴 Restructurer (mutualiser)",IF(AND('08_Moteur'!AI4>=2,E7<=('08_Moteur'!AI4-1)*'08_Moteur'!O4*1.1),"🟡 Regroupable (−1 classe tient en capacité)",IF(I7<0.55,"🟠 Sous-rempli mais −1 classe déborderait","🟢 Maintenir"))) | K7: ="Poursuite : cohorte déjà inscrite → seul levier = regrouper. −1 classe créditée uniquement si l'effectif tient dans les classes restantes (capacité +10% tolérée). Remplissage si −1 classe : "&IF('08_Moteur'!AI4>=2,TEXT(IFERROR(E7/(('08_Moteur'!AI4-1)*'08_Moteur'!O4),0),"0%"),"n/a (1 seule classe)") | L7: Maintenir | M7: =IF(L7="Ne pas lancer",0,IF(L7="Ouvrir +1 classe",E7+'08_Moteur'!O4,E7)) | N7: =IF(L7="Ne pas lancer",0,IF(L7="Ouvrir +1 classe",H7+'08_Moteur'!O4*('08_Moteur'!AE4*'08_Moteur'!AF4-('08_Moteur'!R4+'01_Cadrage'!$H$26)*(1+'01_Cadrage'!$H$20)-'08_Moteur'!S4)-'08_Moteur'!U4,IF(L7="Regrouper (-1 classe)",IF(AND('08_Moteur'!AI4>=2,E7<=('08_Moteur'!AI4-1)*'08_Moteur'!O4*1.1),H7+'08_Moteur'!U4,H7),H7))) | O7: =M7*IFERROR(('09_Allocation'!E20+'09_Allocation'!F20+'09_Allocation'!I20)/SUM(M6:M63),0) | P7: =N7-O7 | Q7: =N7-H7
A8: ='08_Moteur'!A5 | B8: ='08_Moteur'!B5 | C8: ='08_Moteur'!C5 | D8: ='08_Moteur'!D5 | E8: ='08_Moteur'!AD5 | F8: ='08_Moteur'!AH5 | G8: =F8-'08_Moteur'!AM5 | H8: ='08_Moteur'!AM5 | I8: ='08_Moteur'!AN5 | J8: =IF(H8<0,"🔴 Restructurer (mutualiser)",IF(AND('08_Moteur'!AI5>=2,E8<=('08_Moteur'!AI5-1)*'08_Moteur'!O5*1.1),"🟡 Regroupable (−1 classe tient en capacité)",IF(I8<0.55,"🟠 Sous-rempli mais −1 classe déborderait","🟢 Maintenir"))) | K8: ="Poursuite : cohorte déjà inscrite → seul levier = regrouper. −1 classe créditée uniquement si l'effectif tient dans les classes restantes (capacité +10% tolérée). Remplissage si −1 classe : "&IF('08_Moteur'!AI5>=2,TEXT(IFERROR(E8/(('08_Moteur'!AI5-1)*'08_Moteur'!O5),0),"0%"),"n/a (1 seule classe)") | L8: Maintenir | M8: =IF(L8="Ne pas lancer",0,IF(L8="Ouvrir +1 classe",E8+'08_Moteur'!O5,E8)) | N8: =IF(L8="Ne pas lancer",0,IF(L8="Ouvrir +1 classe",H8+'08_Moteur'!O5*('08_Moteur'!AE5*'08_Moteur'!AF5-('08_Moteur'!R5+'01_Cadrage'!$H$26)*(1+'01_Cadrage'!$H$20)-'08_Moteur'!S5)-'08_Moteur'!U5,IF(L8="Regrouper (-1 classe)",IF(AND('08_Moteur'!AI5>=2,E8<=('08_Moteur'!AI5-1)*'08_Moteur'!O5*1.1),H8+'08_Moteur'!U5,H8),H8))) | O8: =M8*IFERROR(('09_Allocation'!E20+'09_Allocation'!F20+'09_Allocation'!I20)/SUM(M6:M63),0) | P8: =N8-O8 | Q8: =N8-H8
A9: ='08_Moteur'!A6 | B9: ='08_Moteur'!B6 | C9: ='08_Moteur'!C6 | D9: ='08_Moteur'!D6 | E9: ='08_Moteur'!AD6 | F9: ='08_Moteur'!AH6 | G9: =F9-'08_Moteur'!AM6 | H9: ='08_Moteur'!AM6 | I9: ='08_Moteur'!AN6 | J9: =IF(H9<0,"🔴 Ne pas lancer",IF(I9>=0.95,"🟢 Ouvrir +1 (capter+diluer)",IF(I9<0.55,"🟡 Surveiller","🟢 Maintenir"))) | K9: =IF(H9<0,"Entrée à contribution négative → ne pas lancer cette cohorte",IF(I9>=0.95,"Saturé → ouvrir capte des étudiants ET dilue la structure pour tous",IF(I9<0.55,"Sous-rempli mais contribution positive → garder","Sain"))) | L9: Maintenir | M9: =IF(L9="Ne pas lancer",0,IF(L9="Ouvrir +1 classe",E9+'08_Moteur'!O6,E9)) | N9: =IF(L9="Ne pas lancer",0,IF(L9="Ouvrir +1 classe",H9+'08_Moteur'!O6*('08_Moteur'!AE6*'08_Moteur'!AF6-('08_Moteur'!R6+'01_Cadrage'!$H$26)*(1+'01_Cadrage'!$H$20)-'08_Moteur'!S6)-'08_Moteur'!U6,IF(L9="Regrouper (-1 classe)",IF(AND('08_Moteur'!AI6>=2,E9<=('08_Moteur'!AI6-1)*'08_Moteur'!O6*1.1),H9+'08_Moteur'!U6,H9),H9))) | O9: =M9*IFERROR(('09_Allocation'!E20+'09_Allocation'!F20+'09_Allocation'!I20)/SUM(M6:M63),0) | P9: =N9-O9 | Q9: =N9-H9
A10: ='08_Moteur'!A7 | B10: ='08_Moteur'!B7 | C10: ='08_Moteur'!C7 | D10: ='08_Moteur'!D7 | E10: ='08_Moteur'!AD7 | F10: ='08_Moteur'!AH7 | G10: =F10-'08_Moteur'!AM7 | H10: ='08_Moteur'!AM7 | I10: ='08_Moteur'!AN7 | J10: =IF(H10<0,"🔴 Restructurer (mutualiser)",IF(AND('08_Moteur'!AI7>=2,E10<=('08_Moteur'!AI7-1)*'08_Moteur'!O7*1.1),"🟡 Regroupable (−1 classe tient en capacité)",IF(I10<0.55,"🟠 Sous-rempli mais −1 classe déborderait","🟢 Maintenir"))) | K10: ="Poursuite : cohorte déjà inscrite → seul levier = regrouper. −1 classe créditée uniquement si l'effectif tient dans les classes restantes (capacité +10% tolérée). Remplissage si −1 classe : "&IF('08_Moteur'!AI7>=2,TEXT(IFERROR(E10/(('08_Moteur'!AI7-1)*'08_Moteur'!O7),0),"0%"),"n/a (1 seule classe)") | L10: Maintenir | M10: =IF(L10="Ne pas lancer",0,IF(L10="Ouvrir +1 classe",E10+'08_Moteur'!O7,E10)) | N10: =IF(L10="Ne pas lancer",0,IF(L10="Ouvrir +1 classe",H10+'08_Moteur'!O7*('08_Moteur'!AE7*'08_Moteur'!AF7-('08_Moteur'!R7+'01_Cadrage'!$H$26)*(1+'01_Cadrage'!$H$20)-'08_Moteur'!S7)-'08_Moteur'!U7,IF(L10="Regrouper (-1 classe)",IF(AND('08_Moteur'!AI7>=2,E10<=('08_Moteur'!AI7-1)*'08_Moteur'!O7*1.1),H10+'08_Moteur'!U7,H10),H10))) | O10: =M10*IFERROR(('09_Allocation'!E20+'09_Allocation'!F20+'09_Allocation'!I20)/SUM(M6:M63),0) | P10: =N10-O10 | Q10: =N10-H10
A11: ='08_Moteur'!A8 | B11: ='08_Moteur'!B8 | C11: ='08_Moteur'!C8 | D11: ='08_Moteur'!D8 | E11: ='08_Moteur'!AD8 | F11: ='08_Moteur'!AH8 | G11: =F11-'08_Moteur'!AM8 | H11: ='08_Moteur'!AM8 | I11: ='08_Moteur'!AN8 | J11: =IF(H11<0,"🔴 Ne pas lancer",IF(I11>=0.95,"🟢 Ouvrir +1 (capter+diluer)",IF(I11<0.55,"🟡 Surveiller","🟢 Maintenir"))) | K11: =IF(H11<0,"Entrée à contribution négative → ne pas lancer cette cohorte",IF(I11>=0.95,"Saturé → ouvrir capte des étudiants ET dilue la structure pour tous",IF(I11<0.55,"Sous-rempli mais contribution positive → garder","Sain"))) | L11: Maintenir | M11: =IF(L11="Ne pas lancer",0,IF(L11="Ouvrir +1 classe",E11+'08_Moteur'!O8,E11)) | N11: =IF(L11="Ne pas lancer",0,IF(L11="Ouvrir +1 classe",H11+'08_Moteur'!O8*('08_Moteur'!AE8*'08_Moteur'!AF8-('08_Moteur'!R8+'01_Cadrage'!$H$26)*(1+'01_Cadrage'!$H$20)-'08_Moteur'!S8)-'08_Moteur'!U8,IF(L11="Regrouper (-1 classe)",IF(AND('08_Moteur'!AI8>=2,E11<=('08_Moteur'!AI8-1)*'08_Moteur'!O8*1.1),H11+'08_Moteur'!U8,H11),H11))) | O11: =M11*IFERROR(('09_Allocation'!E20+'09_Allocation'!F20+'09_Allocation'!I20)/SUM(M6:M63),0) | P11: =N11-O11 | Q11: =N11-H11
A12: ='08_Moteur'!A9 | B12: ='08_Moteur'!B9 | C12: ='08_Moteur'!C9 | D12: ='08_Moteur'!D9 | E12: ='08_Moteur'!AD9 | F12: ='08_Moteur'!AH9 | G12: =F12-'08_Moteur'!AM9 | H12: ='08_Moteur'!AM9 | I12: ='08_Moteur'!AN9 | J12: =IF(H12<0,"🔴 Restructurer (mutualiser)",IF(AND('08_Moteur'!AI9>=2,E12<=('08_Moteur'!AI9-1)*'08_Moteur'!O9*1.1),"🟡 Regroupable (−1 classe tient en capacité)",IF(I12<0.55,"🟠 Sous-rempli mais −1 classe déborderait","🟢 Maintenir"))) | K12: ="Poursuite : cohorte déjà inscrite → seul levier = regrouper. −1 classe créditée uniquement si l'effectif tient dans les classes restantes (capacité +10% tolérée). Remplissage si −1 classe : "&IF('08_Moteur'!AI9>=2,TEXT(IFERROR(E12/(('08_Moteur'!AI9-1)*'08_Moteur'!O9),0),"0%"),"n/a (1 seule classe)") | L12: Maintenir | M12: =IF(L12="Ne pas lancer",0,IF(L12="Ouvrir +1 classe",E12+'08_Moteur'!O9,E12)) | N12: =IF(L12="Ne pas lancer",0,IF(L12="Ouvrir +1 classe",H12+'08_Moteur'!O9*('08_Moteur'!AE9*'08_Moteur'!AF9-('08_Moteur'!R9+'01_Cadrage'!$H$26)*(1+'01_Cadrage'!$H$20)-'08_Moteur'!S9)-'08_Moteur'!U9,IF(L12="Regrouper (-1 classe)",IF(AND('08_Moteur'!AI9>=2,E12<=('08_Moteur'!AI9-1)*'08_Moteur'!O9*1.1),H12+'08_Moteur'!U9,H12),H12))) | O12: =M12*IFERROR(('09_Allocation'!E20+'09_Allocation'!F20+'09_Allocation'!I20)/SUM(M6:M63),0) | P12: =N12-O12 | Q12: =N12-H12
A13: ='08_Moteur'!A10 | B13: ='08_Moteur'!B10 | C13: ='08_Moteur'!C10 | D13: ='08_Moteur'!D10 | E13: ='08_Moteur'!AD10 | F13: ='08_Moteur'!AH10 | G13: =F13-'08_Moteur'!AM10 | H13: ='08_Moteur'!AM10 | I13: ='08_Moteur'!AN10 | J13: =IF(H13<0,"🔴 Restructurer (mutualiser)",IF(AND('08_Moteur'!AI10>=2,E13<=('08_Moteur'!AI10-1)*'08_Moteur'!O10*1.1),"🟡 Regroupable (−1 classe tient en capacité)",IF(I13<0.55,"🟠 Sous-rempli mais −1 classe déborderait","🟢 Maintenir"))) | K13: ="Poursuite : cohorte déjà inscrite → seul levier = regrouper. −1 classe créditée uniquement si l'effectif tient dans les classes restantes (capacité +10% tolérée). Remplissage si −1 classe : "&IF('08_Moteur'!AI10>=2,TEXT(IFERROR(E13/(('08_Moteur'!AI10-1)*'08_Moteur'!O10),0),"0%"),"n/a (1 seule classe)") | L13: Maintenir | M13: =IF(L13="Ne pas lancer",0,IF(L13="Ouvrir +1 classe",E13+'08_Moteur'!O10,E13)) | N13: =IF(L13="Ne pas lancer",0,IF(L13="Ouvrir +1 classe",H13+'08_Moteur'!O10*('08_Moteur'!AE10*'08_Moteur'!AF10-('08_Moteur'!R10+'01_Cadrage'!$H$26)*(1+'01_Cadrage'!$H$20)-'08_Moteur'!S10)-'08_Moteur'!U10,IF(L13="Regrouper (-1 classe)",IF(AND('08_Moteur'!AI10>=2,E13<=('08_Moteur'!AI10-1)*'08_Moteur'!O10*1.1),H13+'08_Moteur'!U10,H13),H13))) | O13: =M13*IFERROR(('09_Allocation'!E20+'09_Allocation'!F20+'09_Allocation'!I20)/SUM(M6:M63),0) | P13: =N13-O13 | Q13: =N13-H13
A14: ='08_Moteur'!A11 | B14: ='08_Moteur'!B11 | C14: ='08_Moteur'!C11 | D14: ='08_Moteur'!D11 | E14: ='08_Moteur'!AD11 | F14: ='08_Moteur'!AH11 | G14: =F14-'08_Moteur'!AM11 | H14: ='08_Moteur'!AM11 | I14: ='08_Moteur'!AN11 | J14: =IF(H14<0,"🔴 Ne pas lancer",IF(I14>=0.95,"🟢 Ouvrir +1 (capter+diluer)",IF(I14<0.55,"🟡 Surveiller","🟢 Maintenir"))) | K14: =IF(H14<0,"Entrée à contribution négative → ne pas lancer cette cohorte",IF(I14>=0.95,"Saturé → ouvrir capte des étudiants ET dilue la structure pour tous",IF(I14<0.55,"Sous-rempli mais contribution positive → garder","Sain"))) | L14: Maintenir | M14: =IF(L14="Ne pas lancer",0,IF(L14="Ouvrir +1 classe",E14+'08_Moteur'!O11,E14)) | N14: =IF(L14="Ne pas lancer",0,IF(L14="Ouvrir +1 classe",H14+'08_Moteur'!O11*('08_Moteur'!AE11*'08_Moteur'!AF11-('08_Moteur'!R11+'01_Cadrage'!$H$26)*(1+'01_Cadrage'!$H$20)-'08_Moteur'!S11)-'08_Moteur'!U11,IF(L14="Regrouper (-1 classe)",IF(AND('08_Moteur'!AI11>=2,E14<=('08_Moteur'!AI11-1)*'08_Moteur'!O11*1.1),H14+'08_Moteur'!U11,H14),H14))) | O14: =M14*IFERROR(('09_Allocation'!E20+'09_Allocation'!F20+'09_Allocation'!I20)/SUM(M6:M63),0) | P14: =N14-O14 | Q14: =N14-H14
A15: ='08_Moteur'!A12 | B15: ='08_Moteur'!B12 | C15: ='08_Moteur'!C12 | D15: ='08_Moteur'!D12 | E15: ='08_Moteur'!AD12 | F15: ='08_Moteur'!AH12 | G15: =F15-'08_Moteur'!AM12 | H15: ='08_Moteur'!AM12 | I15: ='08_Moteur'!AN12 | J15: =IF(H15<0,"🔴 Restructurer (mutualiser)",IF(AND('08_Moteur'!AI12>=2,E15<=('08_Moteur'!AI12-1)*'08_Moteur'!O12*1.1),"🟡 Regroupable (−1 classe tient en capacité)",IF(I15<0.55,"🟠 Sous-rempli mais −1 classe déborderait","🟢 Maintenir"))) | K15: ="Poursuite : cohorte déjà inscrite → seul levier = regrouper. −1 classe créditée uniquement si l'effectif tient dans les classes restantes (capacité +10% tolérée). Remplissage si −1 classe : "&IF('08_Moteur'!AI12>=2,TEXT(IFERROR(E15/(('08_Moteur'!AI12-1)*'08_Moteur'!O12),0),"0%"),"n/a (1 seule classe)") | L15: Maintenir | M15: =IF(L15="Ne pas lancer",0,IF(L15="Ouvrir +1 classe",E15+'08_Moteur'!O12,E15)) | N15: =IF(L15="Ne pas lancer",0,IF(L15="Ouvrir +1 classe",H15+'08_Moteur'!O12*('08_Moteur'!AE12*'08_Moteur'!AF12-('08_Moteur'!R12+'01_Cadrage'!$H$26)*(1+'01_Cadrage'!$H$20)-'08_Moteur'!S12)-'08_Moteur'!U12,IF(L15="Regrouper (-1 classe)",IF(AND('08_Moteur'!AI12>=2,E15<=('08_Moteur'!AI12-1)*'08_Moteur'!O12*1.1),H15+'08_Moteur'!U12,H15),H15))) | O15: =M15*IFERROR(('09_Allocation'!E20+'09_Allocation'!F20+'09_Allocation'!I20)/SUM(M6:M63),0) | P15: =N15-O15 | Q15: =N15-H15
A16: ='08_Moteur'!A13 | B16: ='08_Moteur'!B13 | C16: ='08_Moteur'!C13 | D16: ='08_Moteur'!D13 | E16: ='08_Moteur'!AD13 | F16: ='08_Moteur'!AH13 | G16: =F16-'08_Moteur'!AM13 | H16: ='08_Moteur'!AM13 | I16: ='08_Moteur'!AN13 | J16: =IF(H16<0,"🔴 Ne pas lancer",IF(I16>=0.95,"🟢 Ouvrir +1 (capter+diluer)",IF(I16<0.55,"🟡 Surveiller","🟢 Maintenir"))) | K16: =IF(H16<0,"Entrée à contribution négative → ne pas lancer cette cohorte",IF(I16>=0.95,"Saturé → ouvrir capte des étudiants ET dilue la structure pour tous",IF(I16<0.55,"Sous-rempli mais contribution positive → garder","Sain"))) | L16: Maintenir | M16: =IF(L16="Ne pas lancer",0,IF(L16="Ouvrir +1 classe",E16+'08_Moteur'!O13,E16)) | N16: =IF(L16="Ne pas lancer",0,IF(L16="Ouvrir +1 classe",H16+'08_Moteur'!O13*('08_Moteur'!AE13*'08_Moteur'!AF13-('08_Moteur'!R13+'01_Cadrage'!$H$26)*(1+'01_Cadrage'!$H$20)-'08_Moteur'!S13)-'08_Moteur'!U13,IF(L16="Regrouper (-1 classe)",IF(AND('08_Moteur'!AI13>=2,E16<=('08_Moteur'!AI13-1)*'08_Moteur'!O13*1.1),H16+'08_Moteur'!U13,H16),H16))) | O16: =M16*IFERROR(('09_Allocation'!E20+'09_Allocation'!F20+'09_Allocation'!I20)/SUM(M6:M63),0) | P16: =N16-O16 | Q16: =N16-H16
A17: ='08_Moteur'!A14 | B17: ='08_Moteur'!B14 | C17: ='08_Moteur'!C14 | D17: ='08_Moteur'!D14 | E17: ='08_Moteur'!AD14 | F17: ='08_Moteur'!AH14 | G17: =F17-'08_Moteur'!AM14 | H17: ='08_Moteur'!AM14 | I17: ='08_Moteur'!AN14 | J17: =IF(H17<0,"🔴 Restructurer (mutualiser)",IF(AND('08_Moteur'!AI14>=2,E17<=('08_Moteur'!AI14-1)*'08_Moteur'!O14*1.1),"🟡 Regroupable (−1 classe tient en capacité)",IF(I17<0.55,"🟠 Sous-rempli mais −1 classe déborderait","🟢 Maintenir"))) | K17: ="Poursuite : cohorte déjà inscrite → seul levier = regrouper. −1 classe créditée uniquement si l'effectif tient dans les classes restantes (capacité +10% tolérée). Remplissage si −1 classe : "&IF('08_Moteur'!AI14>=2,TEXT(IFERROR(E17/(('08_Moteur'!AI14-1)*'08_Moteur'!O14),0),"0%"),"n/a (1 seule classe)") | L17: Maintenir | M17: =IF(L17="Ne pas lancer",0,IF(L17="Ouvrir +1 classe",E17+'08_Moteur'!O14,E17)) | N17: =IF(L17="Ne pas lancer",0,IF(L17="Ouvrir +1 classe",H17+'08_Moteur'!O14*('08_Moteur'!AE14*'08_Moteur'!AF14-('08_Moteur'!R14+'01_Cadrage'!$H$26)*(1+'01_Cadrage'!$H$20)-'08_Moteur'!S14)-'08_Moteur'!U14,IF(L17="Regrouper (-1 classe)",IF(AND('08_Moteur'!AI14>=2,E17<=('08_Moteur'!AI14-1)*'08_Moteur'!O14*1.1),H17+'08_Moteur'!U14,H17),H17))) | O17: =M17*IFERROR(('09_Allocation'!E20+'09_Allocation'!F20+'09_Allocation'!I20)/SUM(M6:M63),0) | P17: =N17-O17 | Q17: =N17-H17
A18: ='08_Moteur'!A15 | B18: ='08_Moteur'!B15 | C18: ='08_Moteur'!C15 | D18: ='08_Moteur'!D15 | E18: ='08_Moteur'!AD15 | F18: ='08_Moteur'!AH15 | G18: =F18-'08_Moteur'!AM15 | H18: ='08_Moteur'!AM15 | I18: ='08_Moteur'!AN15 | J18: =IF(H18<0,"🔴 Restructurer (mutualiser)",IF(AND('08_Moteur'!AI15>=2,E18<=('08_Moteur'!AI15-1)*'08_Moteur'!O15*1.1),"🟡 Regroupable (−1 classe tient en capacité)",IF(I18<0.55,"🟠 Sous-rempli mais −1 classe déborderait","🟢 Maintenir"))) | K18: ="Poursuite : cohorte déjà inscrite → seul levier = regrouper. −1 classe créditée uniquement si l'effectif tient dans les classes restantes (capacité +10% tolérée). Remplissage si −1 classe : "&IF('08_Moteur'!AI15>=2,TEXT(IFERROR(E18/(('08_Moteur'!AI15-1)*'08_Moteur'!O15),0),"0%"),"n/a (1 seule classe)") | L18: Maintenir | M18: =IF(L18="Ne pas lancer",0,IF(L18="Ouvrir +1 classe",E18+'08_Moteur'!O15,E18)) | N18: =IF(L18="Ne pas lancer",0,IF(L18="Ouvrir +1 classe",H18+'08_Moteur'!O15*('08_Moteur'!AE15*'08_Moteur'!AF15-('08_Moteur'!R15+'01_Cadrage'!$H$26)*(1+'01_Cadrage'!$H$20)-'08_Moteur'!S15)-'08_Moteur'!U15,IF(L18="Regrouper (-1 classe)",IF(AND('08_Moteur'!AI15>=2,E18<=('08_Moteur'!AI15-1)*'08_Moteur'!O15*1.1),H18+'08_Moteur'!U15,H18),H18))) | O18: =M18*IFERROR(('09_Allocation'!E20+'09_Allocation'!F20+'09_Allocation'!I20)/SUM(M6:M63),0) | P18: =N18-O18 | Q18: =N18-H18
A19: ='08_Moteur'!A16 | B19: ='08_Moteur'!B16 | C19: ='08_Moteur'!C16 | D19: ='08_Moteur'!D16 | E19: ='08_Moteur'!AD16 | F19: ='08_Moteur'!AH16 | G19: =F19-'08_Moteur'!AM16 | H19: ='08_Moteur'!AM16 | I19: ='08_Moteur'!AN16 | J19: =IF(H19<0,"🔴 Ne pas lancer",IF(I19>=0.95,"🟢 Ouvrir +1 (capter+diluer)",IF(I19<0.55,"🟡 Surveiller","🟢 Maintenir"))) | K19: =IF(H19<0,"Entrée à contribution négative → ne pas lancer cette cohorte",IF(I19>=0.95,"Saturé → ouvrir capte des étudiants ET dilue la structure pour tous",IF(I19<0.55,"Sous-rempli mais contribution positive → garder","Sain"))) | L19: Maintenir | M19: =IF(L19="Ne pas lancer",0,IF(L19="Ouvrir +1 classe",E19+'08_Moteur'!O16,E19)) | N19: =IF(L19="Ne pas lancer",0,IF(L19="Ouvrir +1 classe",H19+'08_Moteur'!O16*('08_Moteur'!AE16*'08_Moteur'!AF16-('08_Moteur'!R16+'01_Cadrage'!$H$26)*(1+'01_Cadrage'!$H$20)-'08_Moteur'!S16)-'08_Moteur'!U16,IF(L19="Regrouper (-1 classe)",IF(AND('08_Moteur'!AI16>=2,E19<=('08_Moteur'!AI16-1)*'08_Moteur'!O16*1.1),H19+'08_Moteur'!U16,H19),H19))) | O19: =M19*IFERROR(('09_Allocation'!E20+'09_Allocation'!F20+'09_Allocation'!I20)/SUM(M6:M63),0) | P19: =N19-O19 | Q19: =N19-H19
A20: ='08_Moteur'!A17 | B20: ='08_Moteur'!B17 | C20: ='08_Moteur'!C17 | D20: ='08_Moteur'!D17 | E20: ='08_Moteur'!AD17 | F20: ='08_Moteur'!AH17 | G20: =F20-'08_Moteur'!AM17 | H20: ='08_Moteur'!AM17 | I20: ='08_Moteur'!AN17 | J20: =IF(H20<0,"🔴 Restructurer (mutualiser)",IF(AND('08_Moteur'!AI17>=2,E20<=('08_Moteur'!AI17-1)*'08_Moteur'!O17*1.1),"🟡 Regroupable (−1 classe tient en capacité)",IF(I20<0.55,"🟠 Sous-rempli mais −1 classe déborderait","🟢 Maintenir"))) | K20: ="Poursuite : cohorte déjà inscrite → seul levier = regrouper. −1 classe créditée uniquement si l'effectif tient dans les classes restantes (capacité +10% tolérée). Remplissage si −1 classe : "&IF('08_Moteur'!AI17>=2,TEXT(IFERROR(E20/(('08_Moteur'!AI17-1)*'08_Moteur'!O17),0),"0%"),"n/a (1 seule classe)") | L20: Maintenir | M20: =IF(L20="Ne pas lancer",0,IF(L20="Ouvrir +1 classe",E20+'08_Moteur'!O17,E20)) | N20: =IF(L20="Ne pas lancer",0,IF(L20="Ouvrir +1 classe",H20+'08_Moteur'!O17*('08_Moteur'!AE17*'08_Moteur'!AF17-('08_Moteur'!R17+'01_Cadrage'!$H$26)*(1+'01_Cadrage'!$H$20)-'08_Moteur'!S17)-'08_Moteur'!U17,IF(L20="Regrouper (-1 classe)",IF(AND('08_Moteur'!AI17>=2,E20<=('08_Moteur'!AI17-1)*'08_Moteur'!O17*1.1),H20+'08_Moteur'!U17,H20),H20))) | O20: =M20*IFERROR(('09_Allocation'!E20+'09_Allocation'!F20+'09_Allocation'!I20)/SUM(M6:M63),0) | P20: =N20-O20 | Q20: =N20-H20
A21: ='08_Moteur'!A18 | B21: ='08_Moteur'!B18 | C21: ='08_Moteur'!C18 | D21: ='08_Moteur'!D18 | E21: ='08_Moteur'!AD18 | F21: ='08_Moteur'!AH18 | G21: =F21-'08_Moteur'!AM18 | H21: ='08_Moteur'!AM18 | I21: ='08_Moteur'!AN18 | J21: =IF(H21<0,"🔴 Ne pas lancer",IF(I21>=0.95,"🟢 Ouvrir +1 (capter+diluer)",IF(I21<0.55,"🟡 Surveiller","🟢 Maintenir"))) | K21: =IF(H21<0,"Entrée à contribution négative → ne pas lancer cette cohorte",IF(I21>=0.95,"Saturé → ouvrir capte des étudiants ET dilue la structure pour tous",IF(I21<0.55,"Sous-rempli mais contribution positive → garder","Sain"))) | L21: Maintenir | M21: =IF(L21="Ne pas lancer",0,IF(L21="Ouvrir +1 classe",E21+'08_Moteur'!O18,E21)) | N21: =IF(L21="Ne pas lancer",0,IF(L21="Ouvrir +1 classe",H21+'08_Moteur'!O18*('08_Moteur'!AE18*'08_Moteur'!AF18-('08_Moteur'!R18+'01_Cadrage'!$H$26)*(1+'01_Cadrage'!$H$20)-'08_Moteur'!S18)-'08_Moteur'!U18,IF(L21="Regrouper (-1 classe)",IF(AND('08_Moteur'!AI18>=2,E21<=('08_Moteur'!AI18-1)*'08_Moteur'!O18*1.1),H21+'08_Moteur'!U18,H21),H21))) | O21: =M21*IFERROR(('09_Allocation'!E20+'09_Allocation'!F20+'09_Allocation'!I20)/SUM(M6:M63),0) | P21: =N21-O21 | Q21: =N21-H21
A22: ='08_Moteur'!A19 | B22: ='08_Moteur'!B19 | C22: ='08_Moteur'!C19 | D22: ='08_Moteur'!D19 | E22: ='08_Moteur'!AD19 | F22: ='08_Moteur'!AH19 | G22: =F22-'08_Moteur'!AM19 | H22: ='08_Moteur'!AM19 | I22: ='08_Moteur'!AN19 | J22: =IF(H22<0,"🔴 Restructurer (mutualiser)",IF(AND('08_Moteur'!AI19>=2,E22<=('08_Moteur'!AI19-1)*'08_Moteur'!O19*1.1),"🟡 Regroupable (−1 classe tient en capacité)",IF(I22<0.55,"🟠 Sous-rempli mais −1 classe déborderait","🟢 Maintenir"))) | K22: ="Poursuite : cohorte déjà inscrite → seul levier = regrouper. −1 classe créditée uniquement si l'effectif tient dans les classes restantes (capacité +10% tolérée). Remplissage si −1 classe : "&IF('08_Moteur'!AI19>=2,TEXT(IFERROR(E22/(('08_Moteur'!AI19-1)*'08_Moteur'!O19),0),"0%"),"n/a (1 seule classe)") | L22: Maintenir | M22: =IF(L22="Ne pas lancer",0,IF(L22="Ouvrir +1 classe",E22+'08_Moteur'!O19,E22)) | N22: =IF(L22="Ne pas lancer",0,IF(L22="Ouvrir +1 classe",H22+'08_Moteur'!O19*('08_Moteur'!AE19*'08_Moteur'!AF19-('08_Moteur'!R19+'01_Cadrage'!$H$26)*(1+'01_Cadrage'!$H$20)-'08_Moteur'!S19)-'08_Moteur'!U19,IF(L22="Regrouper (-1 classe)",IF(AND('08_Moteur'!AI19>=2,E22<=('08_Moteur'!AI19-1)*'08_Moteur'!O19*1.1),H22+'08_Moteur'!U19,H22),H22))) | O22: =M22*IFERROR(('09_Allocation'!E20+'09_Allocation'!F20+'09_Allocation'!I20)/SUM(M6:M63),0) | P22: =N22-O22 | Q22: =N22-H22
A23: ='08_Moteur'!A20 | B23: ='08_Moteur'!B20 | C23: ='08_Moteur'!C20 | D23: ='08_Moteur'!D20 | E23: ='08_Moteur'!AD20 | F23: ='08_Moteur'!AH20 | G23: =F23-'08_Moteur'!AM20 | H23: ='08_Moteur'!AM20 | I23: ='08_Moteur'!AN20 | J23: =IF(H23<0,"🔴 Restructurer (mutualiser)",IF(AND('08_Moteur'!AI20>=2,E23<=('08_Moteur'!AI20-1)*'08_Moteur'!O20*1.1),"🟡 Regroupable (−1 classe tient en capacité)",IF(I23<0.55,"🟠 Sous-rempli mais −1 classe déborderait","🟢 Maintenir"))) | K23: ="Poursuite : cohorte déjà inscrite → seul levier = regrouper. −1 classe créditée uniquement si l'effectif tient dans les classes restantes (capacité +10% tolérée). Remplissage si −1 classe : "&IF('08_Moteur'!AI20>=2,TEXT(IFERROR(E23/(('08_Moteur'!AI20-1)*'08_Moteur'!O20),0),"0%"),"n/a (1 seule classe)") | L23: Maintenir | M23: =IF(L23="Ne pas lancer",0,IF(L23="Ouvrir +1 classe",E23+'08_Moteur'!O20,E23)) | N23: =IF(L23="Ne pas lancer",0,IF(L23="Ouvrir +1 classe",H23+'08_Moteur'!O20*('08_Moteur'!AE20*'08_Moteur'!AF20-('08_Moteur'!R20+'01_Cadrage'!$H$26)*(1+'01_Cadrage'!$H$20)-'08_Moteur'!S20)-'08_Moteur'!U20,IF(L23="Regrouper (-1 classe)",IF(AND('08_Moteur'!AI20>=2,E23<=('08_Moteur'!AI20-1)*'08_Moteur'!O20*1.1),H23+'08_Moteur'!U20,H23),H23))) | O23: =M23*IFERROR(('09_Allocation'!E20+'09_Allocation'!F20+'09_Allocation'!I20)/SUM(M6:M63),0) | P23: =N23-O23 | Q23: =N23-H23
A24: ='08_Moteur'!A21 | B24: ='08_Moteur'!B21 | C24: ='08_Moteur'!C21 | D24: ='08_Moteur'!D21 | E24: ='08_Moteur'!AD21 | F24: ='08_Moteur'!AH21 | G24: =F24-'08_Moteur'!AM21 | H24: ='08_Moteur'!AM21 | I24: ='08_Moteur'!AN21 | J24: =IF(H24<0,"🔴 Ne pas lancer",IF(I24>=0.95,"🟢 Ouvrir +1 (capter+diluer)",IF(I24<0.55,"🟡 Surveiller","🟢 Maintenir"))) | K24: =IF(H24<0,"Entrée à contribution négative → ne pas lancer cette cohorte",IF(I24>=0.95,"Saturé → ouvrir capte des étudiants ET dilue la structure pour tous",IF(I24<0.55,"Sous-rempli mais contribution positive → garder","Sain"))) | L24: Maintenir | M24: =IF(L24="Ne pas lancer",0,IF(L24="Ouvrir +1 classe",E24+'08_Moteur'!O21,E24)) | N24: =IF(L24="Ne pas lancer",0,IF(L24="Ouvrir +1 classe",H24+'08_Moteur'!O21*('08_Moteur'!AE21*'08_Moteur'!AF21-('08_Moteur'!R21+'01_Cadrage'!$H$26)*(1+'01_Cadrage'!$H$20)-'08_Moteur'!S21)-'08_Moteur'!U21,IF(L24="Regrouper (-1 classe)",IF(AND('08_Moteur'!AI21>=2,E24<=('08_Moteur'!AI21-1)*'08_Moteur'!O21*1.1),H24+'08_Moteur'!U21,H24),H24))) | O24: =M24*IFERROR(('09_Allocation'!E20+'09_Allocation'!F20+'09_Allocation'!I20)/SUM(M6:M63),0) | P24: =N24-O24 | Q24: =N24-H24
A25: ='08_Moteur'!A22 | B25: ='08_Moteur'!B22 | C25: ='08_Moteur'!C22 | D25: ='08_Moteur'!D22 | E25: ='08_Moteur'!AD22 | F25: ='08_Moteur'!AH22 | G25: =F25-'08_Moteur'!AM22 | H25: ='08_Moteur'!AM22 | I25: ='08_Moteur'!AN22 | J25: =IF(H25<0,"🔴 Restructurer (mutualiser)",IF(AND('08_Moteur'!AI22>=2,E25<=('08_Moteur'!AI22-1)*'08_Moteur'!O22*1.1),"🟡 Regroupable (−1 classe tient en capacité)",IF(I25<0.55,"🟠 Sous-rempli mais −1 classe déborderait","🟢 Maintenir"))) | K25: ="Poursuite : cohorte déjà inscrite → seul levier = regrouper. −1 classe créditée uniquement si l'effectif tient dans les classes restantes (capacité +10% tolérée). Remplissage si −1 classe : "&IF('08_Moteur'!AI22>=2,TEXT(IFERROR(E25/(('08_Moteur'!AI22-1)*'08_Moteur'!O22),0),"0%"),"n/a (1 seule classe)") | L25: Maintenir | M25: =IF(L25="Ne pas lancer",0,IF(L25="Ouvrir +1 classe",E25+'08_Moteur'!O22,E25)) | N25: =IF(L25="Ne pas lancer",0,IF(L25="Ouvrir +1 classe",H25+'08_Moteur'!O22*('08_Moteur'!AE22*'08_Moteur'!AF22-('08_Moteur'!R22+'01_Cadrage'!$H$26)*(1+'01_Cadrage'!$H$20)-'08_Moteur'!S22)-'08_Moteur'!U22,IF(L25="Regrouper (-1 classe)",IF(AND('08_Moteur'!AI22>=2,E25<=('08_Moteur'!AI22-1)*'08_Moteur'!O22*1.1),H25+'08_Moteur'!U22,H25),H25))) | O25: =M25*IFERROR(('09_Allocation'!E20+'09_Allocation'!F20+'09_Allocation'!I20)/SUM(M6:M63),0) | P25: =N25-O25 | Q25: =N25-H25
A26: ='08_Moteur'!A23 | B26: ='08_Moteur'!B23 | C26: ='08_Moteur'!C23 | D26: ='08_Moteur'!D23 | E26: ='08_Moteur'!AD23 | F26: ='08_Moteur'!AH23 | G26: =F26-'08_Moteur'!AM23 | H26: ='08_Moteur'!AM23 | I26: ='08_Moteur'!AN23 | J26: =IF(H26<0,"🔴 Ne pas lancer",IF(I26>=0.95,"🟢 Ouvrir +1 (capter+diluer)",IF(I26<0.55,"🟡 Surveiller","🟢 Maintenir"))) | K26: =IF(H26<0,"Entrée à contribution négative → ne pas lancer cette cohorte",IF(I26>=0.95,"Saturé → ouvrir capte des étudiants ET dilue la structure pour tous",IF(I26<0.55,"Sous-rempli mais contribution positive → garder","Sain"))) | L26: Maintenir | M26: =IF(L26="Ne pas lancer",0,IF(L26="Ouvrir +1 classe",E26+'08_Moteur'!O23,E26)) | N26: =IF(L26="Ne pas lancer",0,IF(L26="Ouvrir +1 classe",H26+'08_Moteur'!O23*('08_Moteur'!AE23*'08_Moteur'!AF23-('08_Moteur'!R23+'01_Cadrage'!$H$26)*(1+'01_Cadrage'!$H$20)-'08_Moteur'!S23)-'08_Moteur'!U23,IF(L26="Regrouper (-1 classe)",IF(AND('08_Moteur'!AI23>=2,E26<=('08_Moteur'!AI23-1)*'08_Moteur'!O23*1.1),H26+'08_Moteur'!U23,H26),H26))) | O26: =M26*IFERROR(('09_Allocation'!E20+'09_Allocation'!F20+'09_Allocation'!I20)/SUM(M6:M63),0) | P26: =N26-O26 | Q26: =N26-H26
A27: ='08_Moteur'!A24 | B27: ='08_Moteur'!B24 | C27: ='08_Moteur'!C24 | D27: ='08_Moteur'!D24 | E27: ='08_Moteur'!AD24 | F27: ='08_Moteur'!AH24 | G27: =F27-'08_Moteur'!AM24 | H27: ='08_Moteur'!AM24 | I27: ='08_Moteur'!AN24 | J27: =IF(H27<0,"🔴 Restructurer (mutualiser)",IF(AND('08_Moteur'!AI24>=2,E27<=('08_Moteur'!AI24-1)*'08_Moteur'!O24*1.1),"🟡 Regroupable (−1 classe tient en capacité)",IF(I27<0.55,"🟠 Sous-rempli mais −1 classe déborderait","🟢 Maintenir"))) | K27: ="Poursuite : cohorte déjà inscrite → seul levier = regrouper. −1 classe créditée uniquement si l'effectif tient dans les classes restantes (capacité +10% tolérée). Remplissage si −1 classe : "&IF('08_Moteur'!AI24>=2,TEXT(IFERROR(E27/(('08_Moteur'!AI24-1)*'08_Moteur'!O24),0),"0%"),"n/a (1 seule classe)") | L27: Maintenir | M27: =IF(L27="Ne pas lancer",0,IF(L27="Ouvrir +1 classe",E27+'08_Moteur'!O24,E27)) | N27: =IF(L27="Ne pas lancer",0,IF(L27="Ouvrir +1 classe",H27+'08_Moteur'!O24*('08_Moteur'!AE24*'08_Moteur'!AF24-('08_Moteur'!R24+'01_Cadrage'!$H$26)*(1+'01_Cadrage'!$H$20)-'08_Moteur'!S24)-'08_Moteur'!U24,IF(L27="Regrouper (-1 classe)",IF(AND('08_Moteur'!AI24>=2,E27<=('08_Moteur'!AI24-1)*'08_Moteur'!O24*1.1),H27+'08_Moteur'!U24,H27),H27))) | O27: =M27*IFERROR(('09_Allocation'!E20+'09_Allocation'!F20+'09_Allocation'!I20)/SUM(M6:M63),0) | P27: =N27-O27 | Q27: =N27-H27
A28: ='08_Moteur'!A25 | B28: ='08_Moteur'!B25 | C28: ='08_Moteur'!C25 | D28: ='08_Moteur'!D25 | E28: ='08_Moteur'!AD25 | F28: ='08_Moteur'!AH25 | G28: =F28-'08_Moteur'!AM25 | H28: ='08_Moteur'!AM25 | I28: ='08_Moteur'!AN25 | J28: =IF(H28<0,"🔴 Restructurer (mutualiser)",IF(AND('08_Moteur'!AI25>=2,E28<=('08_Moteur'!AI25-1)*'08_Moteur'!O25*1.1),"🟡 Regroupable (−1 classe tient en capacité)",IF(I28<0.55,"🟠 Sous-rempli mais −1 classe déborderait","🟢 Maintenir"))) | K28: ="Poursuite : cohorte déjà inscrite → seul levier = regrouper. −1 classe créditée uniquement si l'effectif tient dans les classes restantes (capacité +10% tolérée). Remplissage si −1 classe : "&IF('08_Moteur'!AI25>=2,TEXT(IFERROR(E28/(('08_Moteur'!AI25-1)*'08_Moteur'!O25),0),"0%"),"n/a (1 seule classe)") | L28: Maintenir | M28: =IF(L28="Ne pas lancer",0,IF(L28="Ouvrir +1 classe",E28+'08_Moteur'!O25,E28)) | N28: =IF(L28="Ne pas lancer",0,IF(L28="Ouvrir +1 classe",H28+'08_Moteur'!O25*('08_Moteur'!AE25*'08_Moteur'!AF25-('08_Moteur'!R25+'01_Cadrage'!$H$26)*(1+'01_Cadrage'!$H$20)-'08_Moteur'!S25)-'08_Moteur'!U25,IF(L28="Regrouper (-1 classe)",IF(AND('08_Moteur'!AI25>=2,E28<=('08_Moteur'!AI25-1)*'08_Moteur'!O25*1.1),H28+'08_Moteur'!U25,H28),H28))) | O28: =M28*IFERROR(('09_Allocation'!E20+'09_Allocation'!F20+'09_Allocation'!I20)/SUM(M6:M63),0) | P28: =N28-O28 | Q28: =N28-H28
A29: ='08_Moteur'!A26 | B29: ='08_Moteur'!B26 | C29: ='08_Moteur'!C26 | D29: ='08_Moteur'!D26 | E29: ='08_Moteur'!AD26 | F29: ='08_Moteur'!AH26 | G29: =F29-'08_Moteur'!AM26 | H29: ='08_Moteur'!AM26 | I29: ='08_Moteur'!AN26 | J29: =IF(H29<0,"🔴 Ne pas lancer",IF(I29>=0.95,"🟢 Ouvrir +1 (capter+diluer)",IF(I29<0.55,"🟡 Surveiller","🟢 Maintenir"))) | K29: =IF(H29<0,"Entrée à contribution négative → ne pas lancer cette cohorte",IF(I29>=0.95,"Saturé → ouvrir capte des étudiants ET dilue la structure pour tous",IF(I29<0.55,"Sous-rempli mais contribution positive → garder","Sain"))) | L29: Maintenir | M29: =IF(L29="Ne pas lancer",0,IF(L29="Ouvrir +1 classe",E29+'08_Moteur'!O26,E29)) | N29: =IF(L29="Ne pas lancer",0,IF(L29="Ouvrir +1 classe",H29+'08_Moteur'!O26*('08_Moteur'!AE26*'08_Moteur'!AF26-('08_Moteur'!R26+'01_Cadrage'!$H$26)*(1+'01_Cadrage'!$H$20)-'08_Moteur'!S26)-'08_Moteur'!U26,IF(L29="Regrouper (-1 classe)",IF(AND('08_Moteur'!AI26>=2,E29<=('08_Moteur'!AI26-1)*'08_Moteur'!O26*1.1),H29+'08_Moteur'!U26,H29),H29))) | O29: =M29*IFERROR(('09_Allocation'!E20+'09_Allocation'!F20+'09_Allocation'!I20)/SUM(M6:M63),0) | P29: =N29-O29 | Q29: =N29-H29
A30: ='08_Moteur'!A27 | B30: ='08_Moteur'!B27 | C30: ='08_Moteur'!C27 | D30: ='08_Moteur'!D27 | E30: ='08_Moteur'!AD27 | F30: ='08_Moteur'!AH27 | G30: =F30-'08_Moteur'!AM27 | H30: ='08_Moteur'!AM27 | I30: ='08_Moteur'!AN27 | J30: =IF(H30<0,"🔴 Restructurer (mutualiser)",IF(AND('08_Moteur'!AI27>=2,E30<=('08_Moteur'!AI27-1)*'08_Moteur'!O27*1.1),"🟡 Regroupable (−1 classe tient en capacité)",IF(I30<0.55,"🟠 Sous-rempli mais −1 classe déborderait","🟢 Maintenir"))) | K30: ="Poursuite : cohorte déjà inscrite → seul levier = regrouper. −1 classe créditée uniquement si l'effectif tient dans les classes restantes (capacité +10% tolérée). Remplissage si −1 classe : "&IF('08_Moteur'!AI27>=2,TEXT(IFERROR(E30/(('08_Moteur'!AI27-1)*'08_Moteur'!O27),0),"0%"),"n/a (1 seule classe)") | L30: Maintenir | M30: =IF(L30="Ne pas lancer",0,IF(L30="Ouvrir +1 classe",E30+'08_Moteur'!O27,E30)) | N30: =IF(L30="Ne pas lancer",0,IF(L30="Ouvrir +1 classe",H30+'08_Moteur'!O27*('08_Moteur'!AE27*'08_Moteur'!AF27-('08_Moteur'!R27+'01_Cadrage'!$H$26)*(1+'01_Cadrage'!$H$20)-'08_Moteur'!S27)-'08_Moteur'!U27,IF(L30="Regrouper (-1 classe)",IF(AND('08_Moteur'!AI27>=2,E30<=('08_Moteur'!AI27-1)*'08_Moteur'!O27*1.1),H30+'08_Moteur'!U27,H30),H30))) | O30: =M30*IFERROR(('09_Allocation'!E20+'09_Allocation'!F20+'09_Allocation'!I20)/SUM(M6:M63),0) | P30: =N30-O30 | Q30: =N30-H30
A31: ='08_Moteur'!A28 | B31: ='08_Moteur'!B28 | C31: ='08_Moteur'!C28 | D31: ='08_Moteur'!D28 | E31: ='08_Moteur'!AD28 | F31: ='08_Moteur'!AH28 | G31: =F31-'08_Moteur'!AM28 | H31: ='08_Moteur'!AM28 | I31: ='08_Moteur'!AN28 | J31: =IF(H31<0,"🔴 Ne pas lancer",IF(I31>=0.95,"🟢 Ouvrir +1 (capter+diluer)",IF(I31<0.55,"🟡 Surveiller","🟢 Maintenir"))) | K31: =IF(H31<0,"Entrée à contribution négative → ne pas lancer cette cohorte",IF(I31>=0.95,"Saturé → ouvrir capte des étudiants ET dilue la structure pour tous",IF(I31<0.55,"Sous-rempli mais contribution positive → garder","Sain"))) | L31: Maintenir | M31: =IF(L31="Ne pas lancer",0,IF(L31="Ouvrir +1 classe",E31+'08_Moteur'!O28,E31)) | N31: =IF(L31="Ne pas lancer",0,IF(L31="Ouvrir +1 classe",H31+'08_Moteur'!O28*('08_Moteur'!AE28*'08_Moteur'!AF28-('08_Moteur'!R28+'01_Cadrage'!$H$26)*(1+'01_Cadrage'!$H$20)-'08_Moteur'!S28)-'08_Moteur'!U28,IF(L31="Regrouper (-1 classe)",IF(AND('08_Moteur'!AI28>=2,E31<=('08_Moteur'!AI28-1)*'08_Moteur'!O28*1.1),H31+'08_Moteur'!U28,H31),H31))) | O31: =M31*IFERROR(('09_Allocation'!E20+'09_Allocation'!F20+'09_Allocation'!I20)/SUM(M6:M63),0) | P31: =N31-O31 | Q31: =N31-H31
A32: ='08_Moteur'!A29 | B32: ='08_Moteur'!B29 | C32: ='08_Moteur'!C29 | D32: ='08_Moteur'!D29 | E32: ='08_Moteur'!AD29 | F32: ='08_Moteur'!AH29 | G32: =F32-'08_Moteur'!AM29 | H32: ='08_Moteur'!AM29 | I32: ='08_Moteur'!AN29 | J32: =IF(H32<0,"🔴 Restructurer (mutualiser)",IF(AND('08_Moteur'!AI29>=2,E32<=('08_Moteur'!AI29-1)*'08_Moteur'!O29*1.1),"🟡 Regroupable (−1 classe tient en capacité)",IF(I32<0.55,"🟠 Sous-rempli mais −1 classe déborderait","🟢 Maintenir"))) | K32: ="Poursuite : cohorte déjà inscrite → seul levier = regrouper. −1 classe créditée uniquement si l'effectif tient dans les classes restantes (capacité +10% tolérée). Remplissage si −1 classe : "&IF('08_Moteur'!AI29>=2,TEXT(IFERROR(E32/(('08_Moteur'!AI29-1)*'08_Moteur'!O29),0),"0%"),"n/a (1 seule classe)") | L32: Maintenir | M32: =IF(L32="Ne pas lancer",0,IF(L32="Ouvrir +1 classe",E32+'08_Moteur'!O29,E32)) | N32: =IF(L32="Ne pas lancer",0,IF(L32="Ouvrir +1 classe",H32+'08_Moteur'!O29*('08_Moteur'!AE29*'08_Moteur'!AF29-('08_Moteur'!R29+'01_Cadrage'!$H$26)*(1+'01_Cadrage'!$H$20)-'08_Moteur'!S29)-'08_Moteur'!U29,IF(L32="Regrouper (-1 classe)",IF(AND('08_Moteur'!AI29>=2,E32<=('08_Moteur'!AI29-1)*'08_Moteur'!O29*1.1),H32+'08_Moteur'!U29,H32),H32))) | O32: =M32*IFERROR(('09_Allocation'!E20+'09_Allocation'!F20+'09_Allocation'!I20)/SUM(M6:M63),0) | P32: =N32-O32 | Q32: =N32-H32
A33: ='08_Moteur'!A30 | B33: ='08_Moteur'!B30 | C33: ='08_Moteur'!C30 | D33: ='08_Moteur'!D30 | E33: ='08_Moteur'!AD30 | F33: ='08_Moteur'!AH30 | G33: =F33-'08_Moteur'!AM30 | H33: ='08_Moteur'!AM30 | I33: ='08_Moteur'!AN30 | J33: =IF(H33<0,"🔴 Restructurer (mutualiser)",IF(AND('08_Moteur'!AI30>=2,E33<=('08_Moteur'!AI30-1)*'08_Moteur'!O30*1.1),"🟡 Regroupable (−1 classe tient en capacité)",IF(I33<0.55,"🟠 Sous-rempli mais −1 classe déborderait","🟢 Maintenir"))) | K33: ="Poursuite : cohorte déjà inscrite → seul levier = regrouper. −1 classe créditée uniquement si l'effectif tient dans les classes restantes (capacité +10% tolérée). Remplissage si −1 classe : "&IF('08_Moteur'!AI30>=2,TEXT(IFERROR(E33/(('08_Moteur'!AI30-1)*'08_Moteur'!O30),0),"0%"),"n/a (1 seule classe)") | L33: Maintenir | M33: =IF(L33="Ne pas lancer",0,IF(L33="Ouvrir +1 classe",E33+'08_Moteur'!O30,E33)) | N33: =IF(L33="Ne pas lancer",0,IF(L33="Ouvrir +1 classe",H33+'08_Moteur'!O30*('08_Moteur'!AE30*'08_Moteur'!AF30-('08_Moteur'!R30+'01_Cadrage'!$H$26)*(1+'01_Cadrage'!$H$20)-'08_Moteur'!S30)-'08_Moteur'!U30,IF(L33="Regrouper (-1 classe)",IF(AND('08_Moteur'!AI30>=2,E33<=('08_Moteur'!AI30-1)*'08_Moteur'!O30*1.1),H33+'08_Moteur'!U30,H33),H33))) | O33: =M33*IFERROR(('09_Allocation'!E20+'09_Allocation'!F20+'09_Allocation'!I20)/SUM(M6:M63),0) | P33: =N33-O33 | Q33: =N33-H33
A34: ='08_Moteur'!A31 | B34: ='08_Moteur'!B31 | C34: ='08_Moteur'!C31 | D34: ='08_Moteur'!D31 | E34: ='08_Moteur'!AD31 | F34: ='08_Moteur'!AH31 | G34: =F34-'08_Moteur'!AM31 | H34: ='08_Moteur'!AM31 | I34: ='08_Moteur'!AN31 | J34: =IF(H34<0,"🔴 Ne pas lancer",IF(I34>=0.95,"🟢 Ouvrir +1 (capter+diluer)",IF(I34<0.55,"🟡 Surveiller","🟢 Maintenir"))) | K34: =IF(H34<0,"Entrée à contribution négative → ne pas lancer cette cohorte",IF(I34>=0.95,"Saturé → ouvrir capte des étudiants ET dilue la structure pour tous",IF(I34<0.55,"Sous-rempli mais contribution positive → garder","Sain"))) | L34: Maintenir | M34: =IF(L34="Ne pas lancer",0,IF(L34="Ouvrir +1 classe",E34+'08_Moteur'!O31,E34)) | N34: =IF(L34="Ne pas lancer",0,IF(L34="Ouvrir +1 classe",H34+'08_Moteur'!O31*('08_Moteur'!AE31*'08_Moteur'!AF31-('08_Moteur'!R31+'01_Cadrage'!$H$26)*(1+'01_Cadrage'!$H$20)-'08_Moteur'!S31)-'08_Moteur'!U31,IF(L34="Regrouper (-1 classe)",IF(AND('08_Moteur'!AI31>=2,E34<=('08_Moteur'!AI31-1)*'08_Moteur'!O31*1.1),H34+'08_Moteur'!U31,H34),H34))) | O34: =M34*IFERROR(('09_Allocation'!E20+'09_Allocation'!F20+'09_Allocation'!I20)/SUM(M6:M63),0) | P34: =N34-O34 | Q34: =N34-H34
A35: ='08_Moteur'!A32 | B35: ='08_Moteur'!B32 | C35: ='08_Moteur'!C32 | D35: ='08_Moteur'!D32 | E35: ='08_Moteur'!AD32 | F35: ='08_Moteur'!AH32 | G35: =F35-'08_Moteur'!AM32 | H35: ='08_Moteur'!AM32 | I35: ='08_Moteur'!AN32 | J35: =IF(H35<0,"🔴 Restructurer (mutualiser)",IF(AND('08_Moteur'!AI32>=2,E35<=('08_Moteur'!AI32-1)*'08_Moteur'!O32*1.1),"🟡 Regroupable (−1 classe tient en capacité)",IF(I35<0.55,"🟠 Sous-rempli mais −1 classe déborderait","🟢 Maintenir"))) | K35: ="Poursuite : cohorte déjà inscrite → seul levier = regrouper. −1 classe créditée uniquement si l'effectif tient dans les classes restantes (capacité +10% tolérée). Remplissage si −1 classe : "&IF('08_Moteur'!AI32>=2,TEXT(IFERROR(E35/(('08_Moteur'!AI32-1)*'08_Moteur'!O32),0),"0%"),"n/a (1 seule classe)") | L35: Maintenir | M35: =IF(L35="Ne pas lancer",0,IF(L35="Ouvrir +1 classe",E35+'08_Moteur'!O32,E35)) | N35: =IF(L35="Ne pas lancer",0,IF(L35="Ouvrir +1 classe",H35+'08_Moteur'!O32*('08_Moteur'!AE32*'08_Moteur'!AF32-('08_Moteur'!R32+'01_Cadrage'!$H$26)*(1+'01_Cadrage'!$H$20)-'08_Moteur'!S32)-'08_Moteur'!U32,IF(L35="Regrouper (-1 classe)",IF(AND('08_Moteur'!AI32>=2,E35<=('08_Moteur'!AI32-1)*'08_Moteur'!O32*1.1),H35+'08_Moteur'!U32,H35),H35))) | O35: =M35*IFERROR(('09_Allocation'!E20+'09_Allocation'!F20+'09_Allocation'!I20)/SUM(M6:M63),0) | P35: =N35-O35 | Q35: =N35-H35
A36: ='08_Moteur'!A33 | B36: ='08_Moteur'!B33 | C36: ='08_Moteur'!C33 | D36: ='08_Moteur'!D33 | E36: ='08_Moteur'!AD33 | F36: ='08_Moteur'!AH33 | G36: =F36-'08_Moteur'!AM33 | H36: ='08_Moteur'!AM33 | I36: ='08_Moteur'!AN33 | J36: =IF(H36<0,"🔴 Ne pas lancer",IF(I36>=0.95,"🟢 Ouvrir +1 (capter+diluer)",IF(I36<0.55,"🟡 Surveiller","🟢 Maintenir"))) | K36: =IF(H36<0,"Entrée à contribution négative → ne pas lancer cette cohorte",IF(I36>=0.95,"Saturé → ouvrir capte des étudiants ET dilue la structure pour tous",IF(I36<0.55,"Sous-rempli mais contribution positive → garder","Sain"))) | L36: Maintenir | M36: =IF(L36="Ne pas lancer",0,IF(L36="Ouvrir +1 classe",E36+'08_Moteur'!O33,E36)) | N36: =IF(L36="Ne pas lancer",0,IF(L36="Ouvrir +1 classe",H36+'08_Moteur'!O33*('08_Moteur'!AE33*'08_Moteur'!AF33-('08_Moteur'!R33+'01_Cadrage'!$H$26)*(1+'01_Cadrage'!$H$20)-'08_Moteur'!S33)-'08_Moteur'!U33,IF(L36="Regrouper (-1 classe)",IF(AND('08_Moteur'!AI33>=2,E36<=('08_Moteur'!AI33-1)*'08_Moteur'!O33*1.1),H36+'08_Moteur'!U33,H36),H36))) | O36: =M36*IFERROR(('09_Allocation'!E20+'09_Allocation'!F20+'09_Allocation'!I20)/SUM(M6:M63),0) | P36: =N36-O36 | Q36: =N36-H36
A37: ='08_Moteur'!A34 | B37: ='08_Moteur'!B34 | C37: ='08_Moteur'!C34 | D37: ='08_Moteur'!D34 | E37: ='08_Moteur'!AD34 | F37: ='08_Moteur'!AH34 | G37: =F37-'08_Moteur'!AM34 | H37: ='08_Moteur'!AM34 | I37: ='08_Moteur'!AN34 | J37: =IF(H37<0,"🔴 Restructurer (mutualiser)",IF(AND('08_Moteur'!AI34>=2,E37<=('08_Moteur'!AI34-1)*'08_Moteur'!O34*1.1),"🟡 Regroupable (−1 classe tient en capacité)",IF(I37<0.55,"🟠 Sous-rempli mais −1 classe déborderait","🟢 Maintenir"))) | K37: ="Poursuite : cohorte déjà inscrite → seul levier = regrouper. −1 classe créditée uniquement si l'effectif tient dans les classes restantes (capacité +10% tolérée). Remplissage si −1 classe : "&IF('08_Moteur'!AI34>=2,TEXT(IFERROR(E37/(('08_Moteur'!AI34-1)*'08_Moteur'!O34),0),"0%"),"n/a (1 seule classe)") | L37: Maintenir | M37: =IF(L37="Ne pas lancer",0,IF(L37="Ouvrir +1 classe",E37+'08_Moteur'!O34,E37)) | N37: =IF(L37="Ne pas lancer",0,IF(L37="Ouvrir +1 classe",H37+'08_Moteur'!O34*('08_Moteur'!AE34*'08_Moteur'!AF34-('08_Moteur'!R34+'01_Cadrage'!$H$26)*(1+'01_Cadrage'!$H$20)-'08_Moteur'!S34)-'08_Moteur'!U34,IF(L37="Regrouper (-1 classe)",IF(AND('08_Moteur'!AI34>=2,E37<=('08_Moteur'!AI34-1)*'08_Moteur'!O34*1.1),H37+'08_Moteur'!U34,H37),H37))) | O37: =M37*IFERROR(('09_Allocation'!E20+'09_Allocation'!F20+'09_Allocation'!I20)/SUM(M6:M63),0) | P37: =N37-O37 | Q37: =N37-H37
A38: ='08_Moteur'!A35 | B38: ='08_Moteur'!B35 | C38: ='08_Moteur'!C35 | D38: ='08_Moteur'!D35 | E38: ='08_Moteur'!AD35 | F38: ='08_Moteur'!AH35 | G38: =F38-'08_Moteur'!AM35 | H38: ='08_Moteur'!AM35 | I38: ='08_Moteur'!AN35 | J38: =IF(H38<0,"🔴 Restructurer (mutualiser)",IF(AND('08_Moteur'!AI35>=2,E38<=('08_Moteur'!AI35-1)*'08_Moteur'!O35*1.1),"🟡 Regroupable (−1 classe tient en capacité)",IF(I38<0.55,"🟠 Sous-rempli mais −1 classe déborderait","🟢 Maintenir"))) | K38: ="Poursuite : cohorte déjà inscrite → seul levier = regrouper. −1 classe créditée uniquement si l'effectif tient dans les classes restantes (capacité +10% tolérée). Remplissage si −1 classe : "&IF('08_Moteur'!AI35>=2,TEXT(IFERROR(E38/(('08_Moteur'!AI35-1)*'08_Moteur'!O35),0),"0%"),"n/a (1 seule classe)") | L38: Maintenir | M38: =IF(L38="Ne pas lancer",0,IF(L38="Ouvrir +1 classe",E38+'08_Moteur'!O35,E38)) | N38: =IF(L38="Ne pas lancer",0,IF(L38="Ouvrir +1 classe",H38+'08_Moteur'!O35*('08_Moteur'!AE35*'08_Moteur'!AF35-('08_Moteur'!R35+'01_Cadrage'!$H$26)*(1+'01_Cadrage'!$H$20)-'08_Moteur'!S35)-'08_Moteur'!U35,IF(L38="Regrouper (-1 classe)",IF(AND('08_Moteur'!AI35>=2,E38<=('08_Moteur'!AI35-1)*'08_Moteur'!O35*1.1),H38+'08_Moteur'!U35,H38),H38))) | O38: =M38*IFERROR(('09_Allocation'!E20+'09_Allocation'!F20+'09_Allocation'!I20)/SUM(M6:M63),0) | P38: =N38-O38 | Q38: =N38-H38
A39: ='08_Moteur'!A36 | B39: ='08_Moteur'!B36 | C39: ='08_Moteur'!C36 | D39: ='08_Moteur'!D36 | E39: ='08_Moteur'!AD36 | F39: ='08_Moteur'!AH36 | G39: =F39-'08_Moteur'!AM36 | H39: ='08_Moteur'!AM36 | I39: ='08_Moteur'!AN36 | J39: =IF(H39<0,"🔴 Ne pas lancer",IF(I39>=0.95,"🟢 Ouvrir +1 (capter+diluer)",IF(I39<0.55,"🟡 Surveiller","🟢 Maintenir"))) | K39: =IF(H39<0,"Entrée à contribution négative → ne pas lancer cette cohorte",IF(I39>=0.95,"Saturé → ouvrir capte des étudiants ET dilue la structure pour tous",IF(I39<0.55,"Sous-rempli mais contribution positive → garder","Sain"))) | L39: Maintenir | M39: =IF(L39="Ne pas lancer",0,IF(L39="Ouvrir +1 classe",E39+'08_Moteur'!O36,E39)) | N39: =IF(L39="Ne pas lancer",0,IF(L39="Ouvrir +1 classe",H39+'08_Moteur'!O36*('08_Moteur'!AE36*'08_Moteur'!AF36-('08_Moteur'!R36+'01_Cadrage'!$H$26)*(1+'01_Cadrage'!$H$20)-'08_Moteur'!S36)-'08_Moteur'!U36,IF(L39="Regrouper (-1 classe)",IF(AND('08_Moteur'!AI36>=2,E39<=('08_Moteur'!AI36-1)*'08_Moteur'!O36*1.1),H39+'08_Moteur'!U36,H39),H39))) | O39: =M39*IFERROR(('09_Allocation'!E20+'09_Allocation'!F20+'09_Allocation'!I20)/SUM(M6:M63),0) | P39: =N39-O39 | Q39: =N39-H39
A40: ='08_Moteur'!A37 | B40: ='08_Moteur'!B37 | C40: ='08_Moteur'!C37 | D40: ='08_Moteur'!D37 | E40: ='08_Moteur'!AD37 | F40: ='08_Moteur'!AH37 | G40: =F40-'08_Moteur'!AM37 | H40: ='08_Moteur'!AM37 | I40: ='08_Moteur'!AN37 | J40: =IF(H40<0,"🔴 Restructurer (mutualiser)",IF(AND('08_Moteur'!AI37>=2,E40<=('08_Moteur'!AI37-1)*'08_Moteur'!O37*1.1),"🟡 Regroupable (−1 classe tient en capacité)",IF(I40<0.55,"🟠 Sous-rempli mais −1 classe déborderait","🟢 Maintenir"))) | K40: ="Poursuite : cohorte déjà inscrite → seul levier = regrouper. −1 classe créditée uniquement si l'effectif tient dans les classes restantes (capacité +10% tolérée). Remplissage si −1 classe : "&IF('08_Moteur'!AI37>=2,TEXT(IFERROR(E40/(('08_Moteur'!AI37-1)*'08_Moteur'!O37),0),"0%"),"n/a (1 seule classe)") | L40: Maintenir | M40: =IF(L40="Ne pas lancer",0,IF(L40="Ouvrir +1 classe",E40+'08_Moteur'!O37,E40)) | N40: =IF(L40="Ne pas lancer",0,IF(L40="Ouvrir +1 classe",H40+'08_Moteur'!O37*('08_Moteur'!AE37*'08_Moteur'!AF37-('08_Moteur'!R37+'01_Cadrage'!$H$26)*(1+'01_Cadrage'!$H$20)-'08_Moteur'!S37)-'08_Moteur'!U37,IF(L40="Regrouper (-1 classe)",IF(AND('08_Moteur'!AI37>=2,E40<=('08_Moteur'!AI37-1)*'08_Moteur'!O37*1.1),H40+'08_Moteur'!U37,H40),H40))) | O40: =M40*IFERROR(('09_Allocation'!E20+'09_Allocation'!F20+'09_Allocation'!I20)/SUM(M6:M63),0) | P40: =N40-O40 | Q40: =N40-H40
A41: ='08_Moteur'!A38 | B41: ='08_Moteur'!B38 | C41: ='08_Moteur'!C38 | D41: ='08_Moteur'!D38 | E41: ='08_Moteur'!AD38 | F41: ='08_Moteur'!AH38 | G41: =F41-'08_Moteur'!AM38 | H41: ='08_Moteur'!AM38 | I41: ='08_Moteur'!AN38 | J41: =IF(H41<0,"🔴 Ne pas lancer",IF(I41>=0.95,"🟢 Ouvrir +1 (capter+diluer)",IF(I41<0.55,"🟡 Surveiller","🟢 Maintenir"))) | K41: =IF(H41<0,"Entrée à contribution négative → ne pas lancer cette cohorte",IF(I41>=0.95,"Saturé → ouvrir capte des étudiants ET dilue la structure pour tous",IF(I41<0.55,"Sous-rempli mais contribution positive → garder","Sain"))) | L41: Maintenir | M41: =IF(L41="Ne pas lancer",0,IF(L41="Ouvrir +1 classe",E41+'08_Moteur'!O38,E41)) | N41: =IF(L41="Ne pas lancer",0,IF(L41="Ouvrir +1 classe",H41+'08_Moteur'!O38*('08_Moteur'!AE38*'08_Moteur'!AF38-('08_Moteur'!R38+'01_Cadrage'!$H$26)*(1+'01_Cadrage'!$H$20)-'08_Moteur'!S38)-'08_Moteur'!U38,IF(L41="Regrouper (-1 classe)",IF(AND('08_Moteur'!AI38>=2,E41<=('08_Moteur'!AI38-1)*'08_Moteur'!O38*1.1),H41+'08_Moteur'!U38,H41),H41))) | O41: =M41*IFERROR(('09_Allocation'!E20+'09_Allocation'!F20+'09_Allocation'!I20)/SUM(M6:M63),0) | P41: =N41-O41 | Q41: =N41-H41
A42: ='08_Moteur'!A39 | B42: ='08_Moteur'!B39 | C42: ='08_Moteur'!C39 | D42: ='08_Moteur'!D39 | E42: ='08_Moteur'!AD39 | F42: ='08_Moteur'!AH39 | G42: =F42-'08_Moteur'!AM39 | H42: ='08_Moteur'!AM39 | I42: ='08_Moteur'!AN39 | J42: =IF(H42<0,"🔴 Restructurer (mutualiser)",IF(AND('08_Moteur'!AI39>=2,E42<=('08_Moteur'!AI39-1)*'08_Moteur'!O39*1.1),"🟡 Regroupable (−1 classe tient en capacité)",IF(I42<0.55,"🟠 Sous-rempli mais −1 classe déborderait","🟢 Maintenir"))) | K42: ="Poursuite : cohorte déjà inscrite → seul levier = regrouper. −1 classe créditée uniquement si l'effectif tient dans les classes restantes (capacité +10% tolérée). Remplissage si −1 classe : "&IF('08_Moteur'!AI39>=2,TEXT(IFERROR(E42/(('08_Moteur'!AI39-1)*'08_Moteur'!O39),0),"0%"),"n/a (1 seule classe)") | L42: Maintenir | M42: =IF(L42="Ne pas lancer",0,IF(L42="Ouvrir +1 classe",E42+'08_Moteur'!O39,E42)) | N42: =IF(L42="Ne pas lancer",0,IF(L42="Ouvrir +1 classe",H42+'08_Moteur'!O39*('08_Moteur'!AE39*'08_Moteur'!AF39-('08_Moteur'!R39+'01_Cadrage'!$H$26)*(1+'01_Cadrage'!$H$20)-'08_Moteur'!S39)-'08_Moteur'!U39,IF(L42="Regrouper (-1 classe)",IF(AND('08_Moteur'!AI39>=2,E42<=('08_Moteur'!AI39-1)*'08_Moteur'!O39*1.1),H42+'08_Moteur'!U39,H42),H42))) | O42: =M42*IFERROR(('09_Allocation'!E20+'09_Allocation'!F20+'09_Allocation'!I20)/SUM(M6:M63),0) | P42: =N42-O42 | Q42: =N42-H42
A43: ='08_Moteur'!A40 | B43: ='08_Moteur'!B40 | C43: ='08_Moteur'!C40 | D43: ='08_Moteur'!D40 | E43: ='08_Moteur'!AD40 | F43: ='08_Moteur'!AH40 | G43: =F43-'08_Moteur'!AM40 | H43: ='08_Moteur'!AM40 | I43: ='08_Moteur'!AN40 | J43: =IF(H43<0,"🔴 Restructurer (mutualiser)",IF(AND('08_Moteur'!AI40>=2,E43<=('08_Moteur'!AI40-1)*'08_Moteur'!O40*1.1),"🟡 Regroupable (−1 classe tient en capacité)",IF(I43<0.55,"🟠 Sous-rempli mais −1 classe déborderait","🟢 Maintenir"))) | K43: ="Poursuite : cohorte déjà inscrite → seul levier = regrouper. −1 classe créditée uniquement si l'effectif tient dans les classes restantes (capacité +10% tolérée). Remplissage si −1 classe : "&IF('08_Moteur'!AI40>=2,TEXT(IFERROR(E43/(('08_Moteur'!AI40-1)*'08_Moteur'!O40),0),"0%"),"n/a (1 seule classe)") | L43: Maintenir | M43: =IF(L43="Ne pas lancer",0,IF(L43="Ouvrir +1 classe",E43+'08_Moteur'!O40,E43)) | N43: =IF(L43="Ne pas lancer",0,IF(L43="Ouvrir +1 classe",H43+'08_Moteur'!O40*('08_Moteur'!AE40*'08_Moteur'!AF40-('08_Moteur'!R40+'01_Cadrage'!$H$26)*(1+'01_Cadrage'!$H$20)-'08_Moteur'!S40)-'08_Moteur'!U40,IF(L43="Regrouper (-1 classe)",IF(AND('08_Moteur'!AI40>=2,E43<=('08_Moteur'!AI40-1)*'08_Moteur'!O40*1.1),H43+'08_Moteur'!U40,H43),H43))) | O43: =M43*IFERROR(('09_Allocation'!E20+'09_Allocation'!F20+'09_Allocation'!I20)/SUM(M6:M63),0) | P43: =N43-O43 | Q43: =N43-H43
A44: ='08_Moteur'!A41 | B44: ='08_Moteur'!B41 | C44: ='08_Moteur'!C41 | D44: ='08_Moteur'!D41 | E44: ='08_Moteur'!AD41 | F44: ='08_Moteur'!AH41 | G44: =F44-'08_Moteur'!AM41 | H44: ='08_Moteur'!AM41 | I44: ='08_Moteur'!AN41 | J44: =IF(H44<0,"🔴 Ne pas lancer",IF(I44>=0.95,"🟢 Ouvrir +1 (capter+diluer)",IF(I44<0.55,"🟡 Surveiller","🟢 Maintenir"))) | K44: =IF(H44<0,"Entrée à contribution négative → ne pas lancer cette cohorte",IF(I44>=0.95,"Saturé → ouvrir capte des étudiants ET dilue la structure pour tous",IF(I44<0.55,"Sous-rempli mais contribution positive → garder","Sain"))) | L44: Maintenir | M44: =IF(L44="Ne pas lancer",0,IF(L44="Ouvrir +1 classe",E44+'08_Moteur'!O41,E44)) | N44: =IF(L44="Ne pas lancer",0,IF(L44="Ouvrir +1 classe",H44+'08_Moteur'!O41*('08_Moteur'!AE41*'08_Moteur'!AF41-('08_Moteur'!R41+'01_Cadrage'!$H$26)*(1+'01_Cadrage'!$H$20)-'08_Moteur'!S41)-'08_Moteur'!U41,IF(L44="Regrouper (-1 classe)",IF(AND('08_Moteur'!AI41>=2,E44<=('08_Moteur'!AI41-1)*'08_Moteur'!O41*1.1),H44+'08_Moteur'!U41,H44),H44))) | O44: =M44*IFERROR(('09_Allocation'!E20+'09_Allocation'!F20+'09_Allocation'!I20)/SUM(M6:M63),0) | P44: =N44-O44 | Q44: =N44-H44
A45: ='08_Moteur'!A42 | B45: ='08_Moteur'!B42 | C45: ='08_Moteur'!C42 | D45: ='08_Moteur'!D42 | E45: ='08_Moteur'!AD42 | F45: ='08_Moteur'!AH42 | G45: =F45-'08_Moteur'!AM42 | H45: ='08_Moteur'!AM42 | I45: ='08_Moteur'!AN42 | J45: =IF(H45<0,"🔴 Restructurer (mutualiser)",IF(AND('08_Moteur'!AI42>=2,E45<=('08_Moteur'!AI42-1)*'08_Moteur'!O42*1.1),"🟡 Regroupable (−1 classe tient en capacité)",IF(I45<0.55,"🟠 Sous-rempli mais −1 classe déborderait","🟢 Maintenir"))) | K45: ="Poursuite : cohorte déjà inscrite → seul levier = regrouper. −1 classe créditée uniquement si l'effectif tient dans les classes restantes (capacité +10% tolérée). Remplissage si −1 classe : "&IF('08_Moteur'!AI42>=2,TEXT(IFERROR(E45/(('08_Moteur'!AI42-1)*'08_Moteur'!O42),0),"0%"),"n/a (1 seule classe)") | L45: Maintenir | M45: =IF(L45="Ne pas lancer",0,IF(L45="Ouvrir +1 classe",E45+'08_Moteur'!O42,E45)) | N45: =IF(L45="Ne pas lancer",0,IF(L45="Ouvrir +1 classe",H45+'08_Moteur'!O42*('08_Moteur'!AE42*'08_Moteur'!AF42-('08_Moteur'!R42+'01_Cadrage'!$H$26)*(1+'01_Cadrage'!$H$20)-'08_Moteur'!S42)-'08_Moteur'!U42,IF(L45="Regrouper (-1 classe)",IF(AND('08_Moteur'!AI42>=2,E45<=('08_Moteur'!AI42-1)*'08_Moteur'!O42*1.1),H45+'08_Moteur'!U42,H45),H45))) | O45: =M45*IFERROR(('09_Allocation'!E20+'09_Allocation'!F20+'09_Allocation'!I20)/SUM(M6:M63),0) | P45: =N45-O45 | Q45: =N45-H45
A46: ='08_Moteur'!A43 | B46: ='08_Moteur'!B43 | C46: ='08_Moteur'!C43 | D46: ='08_Moteur'!D43 | E46: ='08_Moteur'!AD43 | F46: ='08_Moteur'!AH43 | G46: =F46-'08_Moteur'!AM43 | H46: ='08_Moteur'!AM43 | I46: ='08_Moteur'!AN43 | J46: =IF(H46<0,"🔴 Restructurer (mutualiser)",IF(AND('08_Moteur'!AI43>=2,E46<=('08_Moteur'!AI43-1)*'08_Moteur'!O43*1.1),"🟡 Regroupable (−1 classe tient en capacité)",IF(I46<0.55,"🟠 Sous-rempli mais −1 classe déborderait","🟢 Maintenir"))) | K46: ="Poursuite : cohorte déjà inscrite → seul levier = regrouper. −1 classe créditée uniquement si l'effectif tient dans les classes restantes (capacité +10% tolérée). Remplissage si −1 classe : "&IF('08_Moteur'!AI43>=2,TEXT(IFERROR(E46/(('08_Moteur'!AI43-1)*'08_Moteur'!O43),0),"0%"),"n/a (1 seule classe)") | L46: Maintenir | M46: =IF(L46="Ne pas lancer",0,IF(L46="Ouvrir +1 classe",E46+'08_Moteur'!O43,E46)) | N46: =IF(L46="Ne pas lancer",0,IF(L46="Ouvrir +1 classe",H46+'08_Moteur'!O43*('08_Moteur'!AE43*'08_Moteur'!AF43-('08_Moteur'!R43+'01_Cadrage'!$H$26)*(1+'01_Cadrage'!$H$20)-'08_Moteur'!S43)-'08_Moteur'!U43,IF(L46="Regrouper (-1 classe)",IF(AND('08_Moteur'!AI43>=2,E46<=('08_Moteur'!AI43-1)*'08_Moteur'!O43*1.1),H46+'08_Moteur'!U43,H46),H46))) | O46: =M46*IFERROR(('09_Allocation'!E20+'09_Allocation'!F20+'09_Allocation'!I20)/SUM(M6:M63),0) | P46: =N46-O46 | Q46: =N46-H46
A47: ='08_Moteur'!A44 | B47: ='08_Moteur'!B44 | C47: ='08_Moteur'!C44 | D47: ='08_Moteur'!D44 | E47: ='08_Moteur'!AD44 | F47: ='08_Moteur'!AH44 | G47: =F47-'08_Moteur'!AM44 | H47: ='08_Moteur'!AM44 | I47: ='08_Moteur'!AN44 | J47: =IF(H47<0,"🔴 Ne pas lancer",IF(I47>=0.95,"🟢 Ouvrir +1 (capter+diluer)",IF(I47<0.55,"🟡 Surveiller","🟢 Maintenir"))) | K47: =IF(H47<0,"Entrée à contribution négative → ne pas lancer cette cohorte",IF(I47>=0.95,"Saturé → ouvrir capte des étudiants ET dilue la structure pour tous",IF(I47<0.55,"Sous-rempli mais contribution positive → garder","Sain"))) | L47: Maintenir | M47: =IF(L47="Ne pas lancer",0,IF(L47="Ouvrir +1 classe",E47+'08_Moteur'!O44,E47)) | N47: =IF(L47="Ne pas lancer",0,IF(L47="Ouvrir +1 classe",H47+'08_Moteur'!O44*('08_Moteur'!AE44*'08_Moteur'!AF44-('08_Moteur'!R44+'01_Cadrage'!$H$26)*(1+'01_Cadrage'!$H$20)-'08_Moteur'!S44)-'08_Moteur'!U44,IF(L47="Regrouper (-1 classe)",IF(AND('08_Moteur'!AI44>=2,E47<=('08_Moteur'!AI44-1)*'08_Moteur'!O44*1.1),H47+'08_Moteur'!U44,H47),H47))) | O47: =M47*IFERROR(('09_Allocation'!E20+'09_Allocation'!F20+'09_Allocation'!I20)/SUM(M6:M63),0) | P47: =N47-O47 | Q47: =N47-H47
A48: ='08_Moteur'!A45 | B48: ='08_Moteur'!B45 | C48: ='08_Moteur'!C45 | D48: ='08_Moteur'!D45 | E48: ='08_Moteur'!AD45 | F48: ='08_Moteur'!AH45 | G48: =F48-'08_Moteur'!AM45 | H48: ='08_Moteur'!AM45 | I48: ='08_Moteur'!AN45 | J48: =IF(H48<0,"🔴 Restructurer (mutualiser)",IF(AND('08_Moteur'!AI45>=2,E48<=('08_Moteur'!AI45-1)*'08_Moteur'!O45*1.1),"🟡 Regroupable (−1 classe tient en capacité)",IF(I48<0.55,"🟠 Sous-rempli mais −1 classe déborderait","🟢 Maintenir"))) | K48: ="Poursuite : cohorte déjà inscrite → seul levier = regrouper. −1 classe créditée uniquement si l'effectif tient dans les classes restantes (capacité +10% tolérée). Remplissage si −1 classe : "&IF('08_Moteur'!AI45>=2,TEXT(IFERROR(E48/(('08_Moteur'!AI45-1)*'08_Moteur'!O45),0),"0%"),"n/a (1 seule classe)") | L48: Maintenir | M48: =IF(L48="Ne pas lancer",0,IF(L48="Ouvrir +1 classe",E48+'08_Moteur'!O45,E48)) | N48: =IF(L48="Ne pas lancer",0,IF(L48="Ouvrir +1 classe",H48+'08_Moteur'!O45*('08_Moteur'!AE45*'08_Moteur'!AF45-('08_Moteur'!R45+'01_Cadrage'!$H$26)*(1+'01_Cadrage'!$H$20)-'08_Moteur'!S45)-'08_Moteur'!U45,IF(L48="Regrouper (-1 classe)",IF(AND('08_Moteur'!AI45>=2,E48<=('08_Moteur'!AI45-1)*'08_Moteur'!O45*1.1),H48+'08_Moteur'!U45,H48),H48))) | O48: =M48*IFERROR(('09_Allocation'!E20+'09_Allocation'!F20+'09_Allocation'!I20)/SUM(M6:M63),0) | P48: =N48-O48 | Q48: =N48-H48
A49: ='08_Moteur'!A46 | B49: ='08_Moteur'!B46 | C49: ='08_Moteur'!C46 | D49: ='08_Moteur'!D46 | E49: ='08_Moteur'!AD46 | F49: ='08_Moteur'!AH46 | G49: =F49-'08_Moteur'!AM46 | H49: ='08_Moteur'!AM46 | I49: ='08_Moteur'!AN46 | J49: =IF(H49<0,"🔴 Restructurer (mutualiser)",IF(AND('08_Moteur'!AI46>=2,E49<=('08_Moteur'!AI46-1)*'08_Moteur'!O46*1.1),"🟡 Regroupable (−1 classe tient en capacité)",IF(I49<0.55,"🟠 Sous-rempli mais −1 classe déborderait","🟢 Maintenir"))) | K49: ="Poursuite : cohorte déjà inscrite → seul levier = regrouper. −1 classe créditée uniquement si l'effectif tient dans les classes restantes (capacité +10% tolérée). Remplissage si −1 classe : "&IF('08_Moteur'!AI46>=2,TEXT(IFERROR(E49/(('08_Moteur'!AI46-1)*'08_Moteur'!O46),0),"0%"),"n/a (1 seule classe)") | L49: Maintenir | M49: =IF(L49="Ne pas lancer",0,IF(L49="Ouvrir +1 classe",E49+'08_Moteur'!O46,E49)) | N49: =IF(L49="Ne pas lancer",0,IF(L49="Ouvrir +1 classe",H49+'08_Moteur'!O46*('08_Moteur'!AE46*'08_Moteur'!AF46-('08_Moteur'!R46+'01_Cadrage'!$H$26)*(1+'01_Cadrage'!$H$20)-'08_Moteur'!S46)-'08_Moteur'!U46,IF(L49="Regrouper (-1 classe)",IF(AND('08_Moteur'!AI46>=2,E49<=('08_Moteur'!AI46-1)*'08_Moteur'!O46*1.1),H49+'08_Moteur'!U46,H49),H49))) | O49: =M49*IFERROR(('09_Allocation'!E20+'09_Allocation'!F20+'09_Allocation'!I20)/SUM(M6:M63),0) | P49: =N49-O49 | Q49: =N49-H49
A50: ='08_Moteur'!A47 | B50: ='08_Moteur'!B47 | C50: ='08_Moteur'!C47 | D50: ='08_Moteur'!D47 | E50: ='08_Moteur'!AD47 | F50: ='08_Moteur'!AH47 | G50: =F50-'08_Moteur'!AM47 | H50: ='08_Moteur'!AM47 | I50: ='08_Moteur'!AN47 | J50: =IF(H50<0,"🔴 Ne pas lancer",IF(I50>=0.95,"🟢 Ouvrir +1 (capter+diluer)",IF(I50<0.55,"🟡 Surveiller","🟢 Maintenir"))) | K50: =IF(H50<0,"Entrée à contribution négative → ne pas lancer cette cohorte",IF(I50>=0.95,"Saturé → ouvrir capte des étudiants ET dilue la structure pour tous",IF(I50<0.55,"Sous-rempli mais contribution positive → garder","Sain"))) | L50: Maintenir | M50: =IF(L50="Ne pas lancer",0,IF(L50="Ouvrir +1 classe",E50+'08_Moteur'!O47,E50)) | N50: =IF(L50="Ne pas lancer",0,IF(L50="Ouvrir +1 classe",H50+'08_Moteur'!O47*('08_Moteur'!AE47*'08_Moteur'!AF47-('08_Moteur'!R47+'01_Cadrage'!$H$26)*(1+'01_Cadrage'!$H$20)-'08_Moteur'!S47)-'08_Moteur'!U47,IF(L50="Regrouper (-1 classe)",IF(AND('08_Moteur'!AI47>=2,E50<=('08_Moteur'!AI47-1)*'08_Moteur'!O47*1.1),H50+'08_Moteur'!U47,H50),H50))) | O50: =M50*IFERROR(('09_Allocation'!E20+'09_Allocation'!F20+'09_Allocation'!I20)/SUM(M6:M63),0) | P50: =N50-O50 | Q50: =N50-H50
A51: ='08_Moteur'!A48 | B51: ='08_Moteur'!B48 | C51: ='08_Moteur'!C48 | D51: ='08_Moteur'!D48 | E51: ='08_Moteur'!AD48 | F51: ='08_Moteur'!AH48 | G51: =F51-'08_Moteur'!AM48 | H51: ='08_Moteur'!AM48 | I51: ='08_Moteur'!AN48 | J51: =IF(H51<0,"🔴 Restructurer (mutualiser)",IF(AND('08_Moteur'!AI48>=2,E51<=('08_Moteur'!AI48-1)*'08_Moteur'!O48*1.1),"🟡 Regroupable (−1 classe tient en capacité)",IF(I51<0.55,"🟠 Sous-rempli mais −1 classe déborderait","🟢 Maintenir"))) | K51: ="Poursuite : cohorte déjà inscrite → seul levier = regrouper. −1 classe créditée uniquement si l'effectif tient dans les classes restantes (capacité +10% tolérée). Remplissage si −1 classe : "&IF('08_Moteur'!AI48>=2,TEXT(IFERROR(E51/(('08_Moteur'!AI48-1)*'08_Moteur'!O48),0),"0%"),"n/a (1 seule classe)") | L51: Maintenir | M51: =IF(L51="Ne pas lancer",0,IF(L51="Ouvrir +1 classe",E51+'08_Moteur'!O48,E51)) | N51: =IF(L51="Ne pas lancer",0,IF(L51="Ouvrir +1 classe",H51+'08_Moteur'!O48*('08_Moteur'!AE48*'08_Moteur'!AF48-('08_Moteur'!R48+'01_Cadrage'!$H$26)*(1+'01_Cadrage'!$H$20)-'08_Moteur'!S48)-'08_Moteur'!U48,IF(L51="Regrouper (-1 classe)",IF(AND('08_Moteur'!AI48>=2,E51<=('08_Moteur'!AI48-1)*'08_Moteur'!O48*1.1),H51+'08_Moteur'!U48,H51),H51))) | O51: =M51*IFERROR(('09_Allocation'!E20+'09_Allocation'!F20+'09_Allocation'!I20)/SUM(M6:M63),0) | P51: =N51-O51 | Q51: =N51-H51
A52: ='08_Moteur'!A49 | B52: ='08_Moteur'!B49 | C52: ='08_Moteur'!C49 | D52: ='08_Moteur'!D49 | E52: ='08_Moteur'!AD49 | F52: ='08_Moteur'!AH49 | G52: =F52-'08_Moteur'!AM49 | H52: ='08_Moteur'!AM49 | I52: ='08_Moteur'!AN49 | J52: =IF(H52<0,"🔴 Ne pas lancer",IF(I52>=0.95,"🟢 Ouvrir +1 (capter+diluer)",IF(I52<0.55,"🟡 Surveiller","🟢 Maintenir"))) | K52: =IF(H52<0,"Entrée à contribution négative → ne pas lancer cette cohorte",IF(I52>=0.95,"Saturé → ouvrir capte des étudiants ET dilue la structure pour tous",IF(I52<0.55,"Sous-rempli mais contribution positive → garder","Sain"))) | L52: Maintenir | M52: =IF(L52="Ne pas lancer",0,IF(L52="Ouvrir +1 classe",E52+'08_Moteur'!O49,E52)) | N52: =IF(L52="Ne pas lancer",0,IF(L52="Ouvrir +1 classe",H52+'08_Moteur'!O49*('08_Moteur'!AE49*'08_Moteur'!AF49-('08_Moteur'!R49+'01_Cadrage'!$H$26)*(1+'01_Cadrage'!$H$20)-'08_Moteur'!S49)-'08_Moteur'!U49,IF(L52="Regrouper (-1 classe)",IF(AND('08_Moteur'!AI49>=2,E52<=('08_Moteur'!AI49-1)*'08_Moteur'!O49*1.1),H52+'08_Moteur'!U49,H52),H52))) | O52: =M52*IFERROR(('09_Allocation'!E20+'09_Allocation'!F20+'09_Allocation'!I20)/SUM(M6:M63),0) | P52: =N52-O52 | Q52: =N52-H52
A53: ='08_Moteur'!A50 | B53: ='08_Moteur'!B50 | C53: ='08_Moteur'!C50 | D53: ='08_Moteur'!D50 | E53: ='08_Moteur'!AD50 | F53: ='08_Moteur'!AH50 | G53: =F53-'08_Moteur'!AM50 | H53: ='08_Moteur'!AM50 | I53: ='08_Moteur'!AN50 | J53: =IF(H53<0,"🔴 Restructurer (mutualiser)",IF(AND('08_Moteur'!AI50>=2,E53<=('08_Moteur'!AI50-1)*'08_Moteur'!O50*1.1),"🟡 Regroupable (−1 classe tient en capacité)",IF(I53<0.55,"🟠 Sous-rempli mais −1 classe déborderait","🟢 Maintenir"))) | K53: ="Poursuite : cohorte déjà inscrite → seul levier = regrouper. −1 classe créditée uniquement si l'effectif tient dans les classes restantes (capacité +10% tolérée). Remplissage si −1 classe : "&IF('08_Moteur'!AI50>=2,TEXT(IFERROR(E53/(('08_Moteur'!AI50-1)*'08_Moteur'!O50),0),"0%"),"n/a (1 seule classe)") | L53: Maintenir | M53: =IF(L53="Ne pas lancer",0,IF(L53="Ouvrir +1 classe",E53+'08_Moteur'!O50,E53)) | N53: =IF(L53="Ne pas lancer",0,IF(L53="Ouvrir +1 classe",H53+'08_Moteur'!O50*('08_Moteur'!AE50*'08_Moteur'!AF50-('08_Moteur'!R50+'01_Cadrage'!$H$26)*(1+'01_Cadrage'!$H$20)-'08_Moteur'!S50)-'08_Moteur'!U50,IF(L53="Regrouper (-1 classe)",IF(AND('08_Moteur'!AI50>=2,E53<=('08_Moteur'!AI50-1)*'08_Moteur'!O50*1.1),H53+'08_Moteur'!U50,H53),H53))) | O53: =M53*IFERROR(('09_Allocation'!E20+'09_Allocation'!F20+'09_Allocation'!I20)/SUM(M6:M63),0) | P53: =N53-O53 | Q53: =N53-H53
A54: ='08_Moteur'!A51 | B54: ='08_Moteur'!B51 | C54: ='08_Moteur'!C51 | D54: ='08_Moteur'!D51 | E54: ='08_Moteur'!AD51 | F54: ='08_Moteur'!AH51 | G54: =F54-'08_Moteur'!AM51 | H54: ='08_Moteur'!AM51 | I54: ='08_Moteur'!AN51 | J54: =IF(H54<0,"🔴 Ne pas lancer",IF(I54>=0.95,"🟢 Ouvrir +1 (capter+diluer)",IF(I54<0.55,"🟡 Surveiller","🟢 Maintenir"))) | K54: =IF(H54<0,"Entrée à contribution négative → ne pas lancer cette cohorte",IF(I54>=0.95,"Saturé → ouvrir capte des étudiants ET dilue la structure pour tous",IF(I54<0.55,"Sous-rempli mais contribution positive → garder","Sain"))) | L54: Maintenir | M54: =IF(L54="Ne pas lancer",0,IF(L54="Ouvrir +1 classe",E54+'08_Moteur'!O51,E54)) | N54: =IF(L54="Ne pas lancer",0,IF(L54="Ouvrir +1 classe",H54+'08_Moteur'!O51*('08_Moteur'!AE51*'08_Moteur'!AF51-('08_Moteur'!R51+'01_Cadrage'!$H$26)*(1+'01_Cadrage'!$H$20)-'08_Moteur'!S51)-'08_Moteur'!U51,IF(L54="Regrouper (-1 classe)",IF(AND('08_Moteur'!AI51>=2,E54<=('08_Moteur'!AI51-1)*'08_Moteur'!O51*1.1),H54+'08_Moteur'!U51,H54),H54))) | O54: =M54*IFERROR(('09_Allocation'!E20+'09_Allocation'!F20+'09_Allocation'!I20)/SUM(M6:M63),0) | P54: =N54-O54 | Q54: =N54-H54
A55: ='08_Moteur'!A52 | B55: ='08_Moteur'!B52 | C55: ='08_Moteur'!C52 | D55: ='08_Moteur'!D52 | E55: ='08_Moteur'!AD52 | F55: ='08_Moteur'!AH52 | G55: =F55-'08_Moteur'!AM52 | H55: ='08_Moteur'!AM52 | I55: ='08_Moteur'!AN52 | J55: =IF(H55<0,"🔴 Restructurer (mutualiser)",IF(AND('08_Moteur'!AI52>=2,E55<=('08_Moteur'!AI52-1)*'08_Moteur'!O52*1.1),"🟡 Regroupable (−1 classe tient en capacité)",IF(I55<0.55,"🟠 Sous-rempli mais −1 classe déborderait","🟢 Maintenir"))) | K55: ="Poursuite : cohorte déjà inscrite → seul levier = regrouper. −1 classe créditée uniquement si l'effectif tient dans les classes restantes (capacité +10% tolérée). Remplissage si −1 classe : "&IF('08_Moteur'!AI52>=2,TEXT(IFERROR(E55/(('08_Moteur'!AI52-1)*'08_Moteur'!O52),0),"0%"),"n/a (1 seule classe)") | L55: Maintenir | M55: =IF(L55="Ne pas lancer",0,IF(L55="Ouvrir +1 classe",E55+'08_Moteur'!O52,E55)) | N55: =IF(L55="Ne pas lancer",0,IF(L55="Ouvrir +1 classe",H55+'08_Moteur'!O52*('08_Moteur'!AE52*'08_Moteur'!AF52-('08_Moteur'!R52+'01_Cadrage'!$H$26)*(1+'01_Cadrage'!$H$20)-'08_Moteur'!S52)-'08_Moteur'!U52,IF(L55="Regrouper (-1 classe)",IF(AND('08_Moteur'!AI52>=2,E55<=('08_Moteur'!AI52-1)*'08_Moteur'!O52*1.1),H55+'08_Moteur'!U52,H55),H55))) | O55: =M55*IFERROR(('09_Allocation'!E20+'09_Allocation'!F20+'09_Allocation'!I20)/SUM(M6:M63),0) | P55: =N55-O55 | Q55: =N55-H55
A56: ='08_Moteur'!A53 | B56: ='08_Moteur'!B53 | C56: ='08_Moteur'!C53 | D56: ='08_Moteur'!D53 | E56: ='08_Moteur'!AD53 | F56: ='08_Moteur'!AH53 | G56: =F56-'08_Moteur'!AM53 | H56: ='08_Moteur'!AM53 | I56: ='08_Moteur'!AN53 | J56: =IF(H56<0,"🔴 Ne pas lancer",IF(I56>=0.95,"🟢 Ouvrir +1 (capter+diluer)",IF(I56<0.55,"🟡 Surveiller","🟢 Maintenir"))) | K56: =IF(H56<0,"Entrée à contribution négative → ne pas lancer cette cohorte",IF(I56>=0.95,"Saturé → ouvrir capte des étudiants ET dilue la structure pour tous",IF(I56<0.55,"Sous-rempli mais contribution positive → garder","Sain"))) | L56: Maintenir | M56: =IF(L56="Ne pas lancer",0,IF(L56="Ouvrir +1 classe",E56+'08_Moteur'!O53,E56)) | N56: =IF(L56="Ne pas lancer",0,IF(L56="Ouvrir +1 classe",H56+'08_Moteur'!O53*('08_Moteur'!AE53*'08_Moteur'!AF53-('08_Moteur'!R53+'01_Cadrage'!$H$26)*(1+'01_Cadrage'!$H$20)-'08_Moteur'!S53)-'08_Moteur'!U53,IF(L56="Regrouper (-1 classe)",IF(AND('08_Moteur'!AI53>=2,E56<=('08_Moteur'!AI53-1)*'08_Moteur'!O53*1.1),H56+'08_Moteur'!U53,H56),H56))) | O56: =M56*IFERROR(('09_Allocation'!E20+'09_Allocation'!F20+'09_Allocation'!I20)/SUM(M6:M63),0) | P56: =N56-O56 | Q56: =N56-H56
A57: ='08_Moteur'!A54 | B57: ='08_Moteur'!B54 | C57: ='08_Moteur'!C54 | D57: ='08_Moteur'!D54 | E57: ='08_Moteur'!AD54 | F57: ='08_Moteur'!AH54 | G57: =F57-'08_Moteur'!AM54 | H57: ='08_Moteur'!AM54 | I57: ='08_Moteur'!AN54 | J57: =IF(H57<0,"🔴 Restructurer (mutualiser)",IF(AND('08_Moteur'!AI54>=2,E57<=('08_Moteur'!AI54-1)*'08_Moteur'!O54*1.1),"🟡 Regroupable (−1 classe tient en capacité)",IF(I57<0.55,"🟠 Sous-rempli mais −1 classe déborderait","🟢 Maintenir"))) | K57: ="Poursuite : cohorte déjà inscrite → seul levier = regrouper. −1 classe créditée uniquement si l'effectif tient dans les classes restantes (capacité +10% tolérée). Remplissage si −1 classe : "&IF('08_Moteur'!AI54>=2,TEXT(IFERROR(E57/(('08_Moteur'!AI54-1)*'08_Moteur'!O54),0),"0%"),"n/a (1 seule classe)") | L57: Maintenir | M57: =IF(L57="Ne pas lancer",0,IF(L57="Ouvrir +1 classe",E57+'08_Moteur'!O54,E57)) | N57: =IF(L57="Ne pas lancer",0,IF(L57="Ouvrir +1 classe",H57+'08_Moteur'!O54*('08_Moteur'!AE54*'08_Moteur'!AF54-('08_Moteur'!R54+'01_Cadrage'!$H$26)*(1+'01_Cadrage'!$H$20)-'08_Moteur'!S54)-'08_Moteur'!U54,IF(L57="Regrouper (-1 classe)",IF(AND('08_Moteur'!AI54>=2,E57<=('08_Moteur'!AI54-1)*'08_Moteur'!O54*1.1),H57+'08_Moteur'!U54,H57),H57))) | O57: =M57*IFERROR(('09_Allocation'!E20+'09_Allocation'!F20+'09_Allocation'!I20)/SUM(M6:M63),0) | P57: =N57-O57 | Q57: =N57-H57
A58: ='08_Moteur'!A55 | B58: ='08_Moteur'!B55 | C58: ='08_Moteur'!C55 | D58: ='08_Moteur'!D55 | E58: ='08_Moteur'!AD55 | F58: ='08_Moteur'!AH55 | G58: =F58-'08_Moteur'!AM55 | H58: ='08_Moteur'!AM55 | I58: ='08_Moteur'!AN55 | J58: =IF(H58<0,"🔴 Ne pas lancer",IF(I58>=0.95,"🟢 Ouvrir +1 (capter+diluer)",IF(I58<0.55,"🟡 Surveiller","🟢 Maintenir"))) | K58: =IF(H58<0,"Entrée à contribution négative → ne pas lancer cette cohorte",IF(I58>=0.95,"Saturé → ouvrir capte des étudiants ET dilue la structure pour tous",IF(I58<0.55,"Sous-rempli mais contribution positive → garder","Sain"))) | L58: Maintenir | M58: =IF(L58="Ne pas lancer",0,IF(L58="Ouvrir +1 classe",E58+'08_Moteur'!O55,E58)) | N58: =IF(L58="Ne pas lancer",0,IF(L58="Ouvrir +1 classe",H58+'08_Moteur'!O55*('08_Moteur'!AE55*'08_Moteur'!AF55-('08_Moteur'!R55+'01_Cadrage'!$H$26)*(1+'01_Cadrage'!$H$20)-'08_Moteur'!S55)-'08_Moteur'!U55,IF(L58="Regrouper (-1 classe)",IF(AND('08_Moteur'!AI55>=2,E58<=('08_Moteur'!AI55-1)*'08_Moteur'!O55*1.1),H58+'08_Moteur'!U55,H58),H58))) | O58: =M58*IFERROR(('09_Allocation'!E20+'09_Allocation'!F20+'09_Allocation'!I20)/SUM(M6:M63),0) | P58: =N58-O58 | Q58: =N58-H58
A59: ='08_Moteur'!A56 | B59: ='08_Moteur'!B56 | C59: ='08_Moteur'!C56 | D59: ='08_Moteur'!D56 | E59: ='08_Moteur'!AD56 | F59: ='08_Moteur'!AH56 | G59: =F59-'08_Moteur'!AM56 | H59: ='08_Moteur'!AM56 | I59: ='08_Moteur'!AN56 | J59: =IF(H59<0,"🔴 Restructurer (mutualiser)",IF(AND('08_Moteur'!AI56>=2,E59<=('08_Moteur'!AI56-1)*'08_Moteur'!O56*1.1),"🟡 Regroupable (−1 classe tient en capacité)",IF(I59<0.55,"🟠 Sous-rempli mais −1 classe déborderait","🟢 Maintenir"))) | K59: ="Poursuite : cohorte déjà inscrite → seul levier = regrouper. −1 classe créditée uniquement si l'effectif tient dans les classes restantes (capacité +10% tolérée). Remplissage si −1 classe : "&IF('08_Moteur'!AI56>=2,TEXT(IFERROR(E59/(('08_Moteur'!AI56-1)*'08_Moteur'!O56),0),"0%"),"n/a (1 seule classe)") | L59: Maintenir | M59: =IF(L59="Ne pas lancer",0,IF(L59="Ouvrir +1 classe",E59+'08_Moteur'!O56,E59)) | N59: =IF(L59="Ne pas lancer",0,IF(L59="Ouvrir +1 classe",H59+'08_Moteur'!O56*('08_Moteur'!AE56*'08_Moteur'!AF56-('08_Moteur'!R56+'01_Cadrage'!$H$26)*(1+'01_Cadrage'!$H$20)-'08_Moteur'!S56)-'08_Moteur'!U56,IF(L59="Regrouper (-1 classe)",IF(AND('08_Moteur'!AI56>=2,E59<=('08_Moteur'!AI56-1)*'08_Moteur'!O56*1.1),H59+'08_Moteur'!U56,H59),H59))) | O59: =M59*IFERROR(('09_Allocation'!E20+'09_Allocation'!F20+'09_Allocation'!I20)/SUM(M6:M63),0) | P59: =N59-O59 | Q59: =N59-H59
A60: ='08_Moteur'!A57 | B60: ='08_Moteur'!B57 | C60: ='08_Moteur'!C57 | D60: ='08_Moteur'!D57 | E60: ='08_Moteur'!AD57 | F60: ='08_Moteur'!AH57 | G60: =F60-'08_Moteur'!AM57 | H60: ='08_Moteur'!AM57 | I60: ='08_Moteur'!AN57 | J60: =IF(H60<0,"🔴 Restructurer (mutualiser)",IF(AND('08_Moteur'!AI57>=2,E60<=('08_Moteur'!AI57-1)*'08_Moteur'!O57*1.1),"🟡 Regroupable (−1 classe tient en capacité)",IF(I60<0.55,"🟠 Sous-rempli mais −1 classe déborderait","🟢 Maintenir"))) | K60: ="Poursuite : cohorte déjà inscrite → seul levier = regrouper. −1 classe créditée uniquement si l'effectif tient dans les classes restantes (capacité +10% tolérée). Remplissage si −1 classe : "&IF('08_Moteur'!AI57>=2,TEXT(IFERROR(E60/(('08_Moteur'!AI57-1)*'08_Moteur'!O57),0),"0%"),"n/a (1 seule classe)") | L60: Maintenir | M60: =IF(L60="Ne pas lancer",0,IF(L60="Ouvrir +1 classe",E60+'08_Moteur'!O57,E60)) | N60: =IF(L60="Ne pas lancer",0,IF(L60="Ouvrir +1 classe",H60+'08_Moteur'!O57*('08_Moteur'!AE57*'08_Moteur'!AF57-('08_Moteur'!R57+'01_Cadrage'!$H$26)*(1+'01_Cadrage'!$H$20)-'08_Moteur'!S57)-'08_Moteur'!U57,IF(L60="Regrouper (-1 classe)",IF(AND('08_Moteur'!AI57>=2,E60<=('08_Moteur'!AI57-1)*'08_Moteur'!O57*1.1),H60+'08_Moteur'!U57,H60),H60))) | O60: =M60*IFERROR(('09_Allocation'!E20+'09_Allocation'!F20+'09_Allocation'!I20)/SUM(M6:M63),0) | P60: =N60-O60 | Q60: =N60-H60
A61: ='08_Moteur'!A58 | B61: ='08_Moteur'!B58 | C61: ='08_Moteur'!C58 | D61: ='08_Moteur'!D58 | E61: ='08_Moteur'!AD58 | F61: ='08_Moteur'!AH58 | G61: =F61-'08_Moteur'!AM58 | H61: ='08_Moteur'!AM58 | I61: ='08_Moteur'!AN58 | J61: =IF(H61<0,"🔴 Ne pas lancer",IF(I61>=0.95,"🟢 Ouvrir +1 (capter+diluer)",IF(I61<0.55,"🟡 Surveiller","🟢 Maintenir"))) | K61: =IF(H61<0,"Entrée à contribution négative → ne pas lancer cette cohorte",IF(I61>=0.95,"Saturé → ouvrir capte des étudiants ET dilue la structure pour tous",IF(I61<0.55,"Sous-rempli mais contribution positive → garder","Sain"))) | L61: Maintenir | M61: =IF(L61="Ne pas lancer",0,IF(L61="Ouvrir +1 classe",E61+'08_Moteur'!O58,E61)) | N61: =IF(L61="Ne pas lancer",0,IF(L61="Ouvrir +1 classe",H61+'08_Moteur'!O58*('08_Moteur'!AE58*'08_Moteur'!AF58-('08_Moteur'!R58+'01_Cadrage'!$H$26)*(1+'01_Cadrage'!$H$20)-'08_Moteur'!S58)-'08_Moteur'!U58,IF(L61="Regrouper (-1 classe)",IF(AND('08_Moteur'!AI58>=2,E61<=('08_Moteur'!AI58-1)*'08_Moteur'!O58*1.1),H61+'08_Moteur'!U58,H61),H61))) | O61: =M61*IFERROR(('09_Allocation'!E20+'09_Allocation'!F20+'09_Allocation'!I20)/SUM(M6:M63),0) | P61: =N61-O61 | Q61: =N61-H61
A62: ='08_Moteur'!A59 | B62: ='08_Moteur'!B59 | C62: ='08_Moteur'!C59 | D62: ='08_Moteur'!D59 | E62: ='08_Moteur'!AD59 | F62: ='08_Moteur'!AH59 | G62: =F62-'08_Moteur'!AM59 | H62: ='08_Moteur'!AM59 | I62: ='08_Moteur'!AN59 | J62: =IF(H62<0,"🔴 Restructurer (mutualiser)",IF(AND('08_Moteur'!AI59>=2,E62<=('08_Moteur'!AI59-1)*'08_Moteur'!O59*1.1),"🟡 Regroupable (−1 classe tient en capacité)",IF(I62<0.55,"🟠 Sous-rempli mais −1 classe déborderait","🟢 Maintenir"))) | K62: ="Poursuite : cohorte déjà inscrite → seul levier = regrouper. −1 classe créditée uniquement si l'effectif tient dans les classes restantes (capacité +10% tolérée). Remplissage si −1 classe : "&IF('08_Moteur'!AI59>=2,TEXT(IFERROR(E62/(('08_Moteur'!AI59-1)*'08_Moteur'!O59),0),"0%"),"n/a (1 seule classe)") | L62: Maintenir | M62: =IF(L62="Ne pas lancer",0,IF(L62="Ouvrir +1 classe",E62+'08_Moteur'!O59,E62)) | N62: =IF(L62="Ne pas lancer",0,IF(L62="Ouvrir +1 classe",H62+'08_Moteur'!O59*('08_Moteur'!AE59*'08_Moteur'!AF59-('08_Moteur'!R59+'01_Cadrage'!$H$26)*(1+'01_Cadrage'!$H$20)-'08_Moteur'!S59)-'08_Moteur'!U59,IF(L62="Regrouper (-1 classe)",IF(AND('08_Moteur'!AI59>=2,E62<=('08_Moteur'!AI59-1)*'08_Moteur'!O59*1.1),H62+'08_Moteur'!U59,H62),H62))) | O62: =M62*IFERROR(('09_Allocation'!E20+'09_Allocation'!F20+'09_Allocation'!I20)/SUM(M6:M63),0) | P62: =N62-O62 | Q62: =N62-H62
A63: ='08_Moteur'!A60 | B63: ='08_Moteur'!B60 | C63: ='08_Moteur'!C60 | D63: ='08_Moteur'!D60 | E63: ='08_Moteur'!AD60 | F63: ='08_Moteur'!AH60 | G63: =F63-'08_Moteur'!AM60 | H63: ='08_Moteur'!AM60 | I63: ='08_Moteur'!AN60 | J63: =IF(H63<0,"🔴 Restructurer (mutualiser)",IF(AND('08_Moteur'!AI60>=2,E63<=('08_Moteur'!AI60-1)*'08_Moteur'!O60*1.1),"🟡 Regroupable (−1 classe tient en capacité)",IF(I63<0.55,"🟠 Sous-rempli mais −1 classe déborderait","🟢 Maintenir"))) | K63: ="Poursuite : cohorte déjà inscrite → seul levier = regrouper. −1 classe créditée uniquement si l'effectif tient dans les classes restantes (capacité +10% tolérée). Remplissage si −1 classe : "&IF('08_Moteur'!AI60>=2,TEXT(IFERROR(E63/(('08_Moteur'!AI60-1)*'08_Moteur'!O60),0),"0%"),"n/a (1 seule classe)") | L63: Maintenir | M63: =IF(L63="Ne pas lancer",0,IF(L63="Ouvrir +1 classe",E63+'08_Moteur'!O60,E63)) | N63: =IF(L63="Ne pas lancer",0,IF(L63="Ouvrir +1 classe",H63+'08_Moteur'!O60*('08_Moteur'!AE60*'08_Moteur'!AF60-('08_Moteur'!R60+'01_Cadrage'!$H$26)*(1+'01_Cadrage'!$H$20)-'08_Moteur'!S60)-'08_Moteur'!U60,IF(L63="Regrouper (-1 classe)",IF(AND('08_Moteur'!AI60>=2,E63<=('08_Moteur'!AI60-1)*'08_Moteur'!O60*1.1),H63+'08_Moteur'!U60,H63),H63))) | O63: =M63*IFERROR(('09_Allocation'!E20+'09_Allocation'!F20+'09_Allocation'!I20)/SUM(M6:M63),0) | P63: =N63-O63 | Q63: =N63-H63

Sheet 11b_Mutualisation
B2: Mutualisation inter-sections — maille CAMPUS × CYCLE (un cran au-dessus du simulateur)
B3: Le simulateur (11) raisonne à la maille d'UNE promo. Ici on regroupe les promos d'un même CYCLE sur un campus (ex. Bachelor B1+B2+B3, qui partagent un tronc commun) : chacune arrondit au minimum de son côté → de la capacité se gaspille ; la mutualisation en récupère une partie.
B4: % d'heures mutualisables (tronc commun partagé) : | G4: 0.25 | H4: ← hypothèse : part des heures réellement partageable au sein d'un cycle (le reste reste spécifique à chaque année).
B5: Marque | C5: Ville | D5: Cycle | E5: Effectif | F5: Sections aujourd'hui | G5: Capacité moy. | H5: Sections si mutualisé | I5: Sections économisables | J5: Coût moyen / classe | K5: Économie potentielle €
B6: MBway | C6: Paris | D6: Bachelor | E6: =SUMPRODUCT(('08_Moteur'!$A$3:$A$60="MBway")*('08_Moteur'!$B$3:$B$60="Paris")*(('08_Moteur'!$D$3:$D$60="B1")+('08_Moteur'!$D$3:$D$60="B2")+('08_Moteur'!$D$3:$D$60="B3"))*'08_Moteur'!$AD$3:$AD$60) | F6: =SUMPRODUCT(('08_Moteur'!$A$3:$A$60="MBway")*('08_Moteur'!$B$3:$B$60="Paris")*(('08_Moteur'!$D$3:$D$60="B1")+('08_Moteur'!$D$3:$D$60="B2")+('08_Moteur'!$D$3:$D$60="B3"))*'08_Moteur'!$AI$3:$AI$60) | G6: =IFERROR(SUMPRODUCT(('08_Moteur'!$A$3:$A$60="MBway")*('08_Moteur'!$B$3:$B$60="Paris")*(('08_Moteur'!$D$3:$D$60="B1")+('08_Moteur'!$D$3:$D$60="B2")+('08_Moteur'!$D$3:$D$60="B3"))*'08_Moteur'!$AI$3:$AI$60*'08_Moteur'!$O$3:$O$60)/F6,0) | H6: =IF(E6<=0,0,MAX(1,ROUNDUP(E6/G6,0))) | I6: =MAX(0,F6-H6) | J6: =IFERROR(SUMPRODUCT(('08_Moteur'!$A$3:$A$60="MBway")*('08_Moteur'!$B$3:$B$60="Paris")*(('08_Moteur'!$D$3:$D$60="B1")+('08_Moteur'!$D$3:$D$60="B2")+('08_Moteur'!$D$3:$D$60="B3"))*'08_Moteur'!$AJ$3:$AJ$60)/F6,0) | K6: =I6*J6*$G$4
B7: MBway | C7: Paris | D7: Mastère | E7: =SUMPRODUCT(('08_Moteur'!$A$3:$A$60="MBway")*('08_Moteur'!$B$3:$B$60="Paris")*(('08_Moteur'!$D$3:$D$60="M1")+('08_Moteur'!$D$3:$D$60="M2"))*'08_Moteur'!$AD$3:$AD$60) | F7: =SUMPRODUCT(('08_Moteur'!$A$3:$A$60="MBway")*('08_Moteur'!$B$3:$B$60="Paris")*(('08_Moteur'!$D$3:$D$60="M1")+('08_Moteur'!$D$3:$D$60="M2"))*'08_Moteur'!$AI$3:$AI$60) | G7: =IFERROR(SUMPRODUCT(('08_Moteur'!$A$3:$A$60="MBway")*('08_Moteur'!$B$3:$B$60="Paris")*(('08_Moteur'!$D$3:$D$60="M1")+('08_Moteur'!$D$3:$D$60="M2"))*'08_Moteur'!$AI$3:$AI$60*'08_Moteur'!$O$3:$O$60)/F7,0) | H7: =IF(E7<=0,0,MAX(1,ROUNDUP(E7/G7,0))) | I7: =MAX(0,F7-H7) | J7: =IFERROR(SUMPRODUCT(('08_Moteur'!$A$3:$A$60="MBway")*('08_Moteur'!$B$3:$B$60="Paris")*(('08_Moteur'!$D$3:$D$60="M1")+('08_Moteur'!$D$3:$D$60="M2"))*'08_Moteur'!$AJ$3:$AJ$60)/F7,0) | K7: =I7*J7*$G$4
B8: MBway | C8: Lyon | D8: Bachelor | E8: =SUMPRODUCT(('08_Moteur'!$A$3:$A$60="MBway")*('08_Moteur'!$B$3:$B$60="Lyon")*(('08_Moteur'!$D$3:$D$60="B1")+('08_Moteur'!$D$3:$D$60="B2")+('08_Moteur'!$D$3:$D$60="B3"))*'08_Moteur'!$AD$3:$AD$60) | F8: =SUMPRODUCT(('08_Moteur'!$A$3:$A$60="MBway")*('08_Moteur'!$B$3:$B$60="Lyon")*(('08_Moteur'!$D$3:$D$60="B1")+('08_Moteur'!$D$3:$D$60="B2")+('08_Moteur'!$D$3:$D$60="B3"))*'08_Moteur'!$AI$3:$AI$60) | G8: =IFERROR(SUMPRODUCT(('08_Moteur'!$A$3:$A$60="MBway")*('08_Moteur'!$B$3:$B$60="Lyon")*(('08_Moteur'!$D$3:$D$60="B1")+('08_Moteur'!$D$3:$D$60="B2")+('08_Moteur'!$D$3:$D$60="B3"))*'08_Moteur'!$AI$3:$AI$60*'08_Moteur'!$O$3:$O$60)/F8,0) | H8: =IF(E8<=0,0,MAX(1,ROUNDUP(E8/G8,0))) | I8: =MAX(0,F8-H8) | J8: =IFERROR(SUMPRODUCT(('08_Moteur'!$A$3:$A$60="MBway")*('08_Moteur'!$B$3:$B$60="Lyon")*(('08_Moteur'!$D$3:$D$60="B1")+('08_Moteur'!$D$3:$D$60="B2")+('08_Moteur'!$D$3:$D$60="B3"))*'08_Moteur'!$AJ$3:$AJ$60)/F8,0) | K8: =I8*J8*$G$4
B9: MBway | C9: Lyon | D9: Mastère | E9: =SUMPRODUCT(('08_Moteur'!$A$3:$A$60="MBway")*('08_Moteur'!$B$3:$B$60="Lyon")*(('08_Moteur'!$D$3:$D$60="M1")+('08_Moteur'!$D$3:$D$60="M2"))*'08_Moteur'!$AD$3:$AD$60) | F9: =SUMPRODUCT(('08_Moteur'!$A$3:$A$60="MBway")*('08_Moteur'!$B$3:$B$60="Lyon")*(('08_Moteur'!$D$3:$D$60="M1")+('08_Moteur'!$D$3:$D$60="M2"))*'08_Moteur'!$AI$3:$AI$60) | G9: =IFERROR(SUMPRODUCT(('08_Moteur'!$A$3:$A$60="MBway")*('08_Moteur'!$B$3:$B$60="Lyon")*(('08_Moteur'!$D$3:$D$60="M1")+('08_Moteur'!$D$3:$D$60="M2"))*'08_Moteur'!$AI$3:$AI$60*'08_Moteur'!$O$3:$O$60)/F9,0) | H9: =IF(E9<=0,0,MAX(1,ROUNDUP(E9/G9,0))) | I9: =MAX(0,F9-H9) | J9: =IFERROR(SUMPRODUCT(('08_Moteur'!$A$3:$A$60="MBway")*('08_Moteur'!$B$3:$B$60="Lyon")*(('08_Moteur'!$D$3:$D$60="M1")+('08_Moteur'!$D$3:$D$60="M2"))*'08_Moteur'!$AJ$3:$AJ$60)/F9,0) | K9: =I9*J9*$G$4
B10: MBway | C10: Nantes | D10: Bachelor | E10: =SUMPRODUCT(('08_Moteur'!$A$3:$A$60="MBway")*('08_Moteur'!$B$3:$B$60="Nantes")*(('08_Moteur'!$D$3:$D$60="B1")+('08_Moteur'!$D$3:$D$60="B2")+('08_Moteur'!$D$3:$D$60="B3"))*'08_Moteur'!$AD$3:$AD$60) | F10: =SUMPRODUCT(('08_Moteur'!$A$3:$A$60="MBway")*('08_Moteur'!$B$3:$B$60="Nantes")*(('08_Moteur'!$D$3:$D$60="B1")+('08_Moteur'!$D$3:$D$60="B2")+('08_Moteur'!$D$3:$D$60="B3"))*'08_Moteur'!$AI$3:$AI$60) | G10: =IFERROR(SUMPRODUCT(('08_Moteur'!$A$3:$A$60="MBway")*('08_Moteur'!$B$3:$B$60="Nantes")*(('08_Moteur'!$D$3:$D$60="B1")+('08_Moteur'!$D$3:$D$60="B2")+('08_Moteur'!$D$3:$D$60="B3"))*'08_Moteur'!$AI$3:$AI$60*'08_Moteur'!$O$3:$O$60)/F10,0) | H10: =IF(E10<=0,0,MAX(1,ROUNDUP(E10/G10,0))) | I10: =MAX(0,F10-H10) | J10: =IFERROR(SUMPRODUCT(('08_Moteur'!$A$3:$A$60="MBway")*('08_Moteur'!$B$3:$B$60="Nantes")*(('08_Moteur'!$D$3:$D$60="B1")+('08_Moteur'!$D$3:$D$60="B2")+('08_Moteur'!$D$3:$D$60="B3"))*'08_Moteur'!$AJ$3:$AJ$60)/F10,0) | K10: =I10*J10*$G$4
B11: MBway | C11: Nantes | D11: Mastère | E11: =SUMPRODUCT(('08_Moteur'!$A$3:$A$60="MBway")*('08_Moteur'!$B$3:$B$60="Nantes")*(('08_Moteur'!$D$3:$D$60="M1")+('08_Moteur'!$D$3:$D$60="M2"))*'08_Moteur'!$AD$3:$AD$60) | F11: =SUMPRODUCT(('08_Moteur'!$A$3:$A$60="MBway")*('08_Moteur'!$B$3:$B$60="Nantes")*(('08_Moteur'!$D$3:$D$60="M1")+('08_Moteur'!$D$3:$D$60="M2"))*'08_Moteur'!$AI$3:$AI$60) | G11: =IFERROR(SUMPRODUCT(('08_Moteur'!$A$3:$A$60="MBway")*('08_Moteur'!$B$3:$B$60="Nantes")*(('08_Moteur'!$D$3:$D$60="M1")+('08_Moteur'!$D$3:$D$60="M2"))*'08_Moteur'!$AI$3:$AI$60*'08_Moteur'!$O$3:$O$60)/F11,0) | H11: =IF(E11<=0,0,MAX(1,ROUNDUP(E11/G11,0))) | I11: =MAX(0,F11-H11) | J11: =IFERROR(SUMPRODUCT(('08_Moteur'!$A$3:$A$60="MBway")*('08_Moteur'!$B$3:$B$60="Nantes")*(('08_Moteur'!$D$3:$D$60="M1")+('08_Moteur'!$D$3:$D$60="M2"))*'08_Moteur'!$AJ$3:$AJ$60)/F11,0) | K11: =I11*J11*$G$4
B12: MBway | C12: Bordeaux | D12: Bachelor | E12: =SUMPRODUCT(('08_Moteur'!$A$3:$A$60="MBway")*('08_Moteur'!$B$3:$B$60="Bordeaux")*(('08_Moteur'!$D$3:$D$60="B1")+('08_Moteur'!$D$3:$D$60="B2")+('08_Moteur'!$D$3:$D$60="B3"))*'08_Moteur'!$AD$3:$AD$60) | F12: =SUMPRODUCT(('08_Moteur'!$A$3:$A$60="MBway")*('08_Moteur'!$B$3:$B$60="Bordeaux")*(('08_Moteur'!$D$3:$D$60="B1")+('08_Moteur'!$D$3:$D$60="B2")+('08_Moteur'!$D$3:$D$60="B3"))*'08_Moteur'!$AI$3:$AI$60) | G12: =IFERROR(SUMPRODUCT(('08_Moteur'!$A$3:$A$60="MBway")*('08_Moteur'!$B$3:$B$60="Bordeaux")*(('08_Moteur'!$D$3:$D$60="B1")+('08_Moteur'!$D$3:$D$60="B2")+('08_Moteur'!$D$3:$D$60="B3"))*'08_Moteur'!$AI$3:$AI$60*'08_Moteur'!$O$3:$O$60)/F12,0) | H12: =IF(E12<=0,0,MAX(1,ROUNDUP(E12/G12,0))) | I12: =MAX(0,F12-H12) | J12: =IFERROR(SUMPRODUCT(('08_Moteur'!$A$3:$A$60="MBway")*('08_Moteur'!$B$3:$B$60="Bordeaux")*(('08_Moteur'!$D$3:$D$60="B1")+('08_Moteur'!$D$3:$D$60="B2")+('08_Moteur'!$D$3:$D$60="B3"))*'08_Moteur'!$AJ$3:$AJ$60)/F12,0) | K12: =I12*J12*$G$4
B13: MBway | C13: Bordeaux | D13: Mastère | E13: =SUMPRODUCT(('08_Moteur'!$A$3:$A$60="MBway")*('08_Moteur'!$B$3:$B$60="Bordeaux")*(('08_Moteur'!$D$3:$D$60="M1")+('08_Moteur'!$D$3:$D$60="M2"))*'08_Moteur'!$AD$3:$AD$60) | F13: =SUMPRODUCT(('08_Moteur'!$A$3:$A$60="MBway")*('08_Moteur'!$B$3:$B$60="Bordeaux")*(('08_Moteur'!$D$3:$D$60="M1")+('08_Moteur'!$D$3:$D$60="M2"))*'08_Moteur'!$AI$3:$AI$60) | G13: =IFERROR(SUMPRODUCT(('08_Moteur'!$A$3:$A$60="MBway")*('08_Moteur'!$B$3:$B$60="Bordeaux")*(('08_Moteur'!$D$3:$D$60="M1")+('08_Moteur'!$D$3:$D$60="M2"))*'08_Moteur'!$AI$3:$AI$60*'08_Moteur'!$O$3:$O$60)/F13,0) | H13: =IF(E13<=0,0,MAX(1,ROUNDUP(E13/G13,0))) | I13: =MAX(0,F13-H13) | J13: =IFERROR(SUMPRODUCT(('08_Moteur'!$A$3:$A$60="MBway")*('08_Moteur'!$B$3:$B$60="Bordeaux")*(('08_Moteur'!$D$3:$D$60="M1")+('08_Moteur'!$D$3:$D$60="M2"))*'08_Moteur'!$AJ$3:$AJ$60)/F13,0) | K13: =I13*J13*$G$4
B14: ISCOM | C14: Paris | D14: Bachelor | E14: =SUMPRODUCT(('08_Moteur'!$A$3:$A$60="ISCOM")*('08_Moteur'!$B$3:$B$60="Paris")*(('08_Moteur'!$D$3:$D$60="B1")+('08_Moteur'!$D$3:$D$60="B2")+('08_Moteur'!$D$3:$D$60="B3"))*'08_Moteur'!$AD$3:$AD$60) | F14: =SUMPRODUCT(('08_Moteur'!$A$3:$A$60="ISCOM")*('08_Moteur'!$B$3:$B$60="Paris")*(('08_Moteur'!$D$3:$D$60="B1")+('08_Moteur'!$D$3:$D$60="B2")+('08_Moteur'!$D$3:$D$60="B3"))*'08_Moteur'!$AI$3:$AI$60) | G14: =IFERROR(SUMPRODUCT(('08_Moteur'!$A$3:$A$60="ISCOM")*('08_Moteur'!$B$3:$B$60="Paris")*(('08_Moteur'!$D$3:$D$60="B1")+('08_Moteur'!$D$3:$D$60="B2")+('08_Moteur'!$D$3:$D$60="B3"))*'08_Moteur'!$AI$3:$AI$60*'08_Moteur'!$O$3:$O$60)/F14,0) | H14: =IF(E14<=0,0,MAX(1,ROUNDUP(E14/G14,0))) | I14: =MAX(0,F14-H14) | J14: =IFERROR(SUMPRODUCT(('08_Moteur'!$A$3:$A$60="ISCOM")*('08_Moteur'!$B$3:$B$60="Paris")*(('08_Moteur'!$D$3:$D$60="B1")+('08_Moteur'!$D$3:$D$60="B2")+('08_Moteur'!$D$3:$D$60="B3"))*'08_Moteur'!$AJ$3:$AJ$60)/F14,0) | K14: =I14*J14*$G$4
B15: ISCOM | C15: Paris | D15: Mastère | E15: =SUMPRODUCT(('08_Moteur'!$A$3:$A$60="ISCOM")*('08_Moteur'!$B$3:$B$60="Paris")*(('08_Moteur'!$D$3:$D$60="M1")+('08_Moteur'!$D$3:$D$60="M2"))*'08_Moteur'!$AD$3:$AD$60) | F15: =SUMPRODUCT(('08_Moteur'!$A$3:$A$60="ISCOM")*('08_Moteur'!$B$3:$B$60="Paris")*(('08_Moteur'!$D$3:$D$60="M1")+('08_Moteur'!$D$3:$D$60="M2"))*'08_Moteur'!$AI$3:$AI$60) | G15: =IFERROR(SUMPRODUCT(('08_Moteur'!$A$3:$A$60="ISCOM")*('08_Moteur'!$B$3:$B$60="Paris")*(('08_Moteur'!$D$3:$D$60="M1")+('08_Moteur'!$D$3:$D$60="M2"))*'08_Moteur'!$AI$3:$AI$60*'08_Moteur'!$O$3:$O$60)/F15,0) | H15: =IF(E15<=0,0,MAX(1,ROUNDUP(E15/G15,0))) | I15: =MAX(0,F15-H15) | J15: =IFERROR(SUMPRODUCT(('08_Moteur'!$A$3:$A$60="ISCOM")*('08_Moteur'!$B$3:$B$60="Paris")*(('08_Moteur'!$D$3:$D$60="M1")+('08_Moteur'!$D$3:$D$60="M2"))*'08_Moteur'!$AJ$3:$AJ$60)/F15,0) | K15: =I15*J15*$G$4
B16: ISCOM | C16: Lille | D16: Bachelor | E16: =SUMPRODUCT(('08_Moteur'!$A$3:$A$60="ISCOM")*('08_Moteur'!$B$3:$B$60="Lille")*(('08_Moteur'!$D$3:$D$60="B1")+('08_Moteur'!$D$3:$D$60="B2")+('08_Moteur'!$D$3:$D$60="B3"))*'08_Moteur'!$AD$3:$AD$60) | F16: =SUMPRODUCT(('08_Moteur'!$A$3:$A$60="ISCOM")*('08_Moteur'!$B$3:$B$60="Lille")*(('08_Moteur'!$D$3:$D$60="B1")+('08_Moteur'!$D$3:$D$60="B2")+('08_Moteur'!$D$3:$D$60="B3"))*'08_Moteur'!$AI$3:$AI$60) | G16: =IFERROR(SUMPRODUCT(('08_Moteur'!$A$3:$A$60="ISCOM")*('08_Moteur'!$B$3:$B$60="Lille")*(('08_Moteur'!$D$3:$D$60="B1")+('08_Moteur'!$D$3:$D$60="B2")+('08_Moteur'!$D$3:$D$60="B3"))*'08_Moteur'!$AI$3:$AI$60*'08_Moteur'!$O$3:$O$60)/F16,0) | H16: =IF(E16<=0,0,MAX(1,ROUNDUP(E16/G16,0))) | I16: =MAX(0,F16-H16) | J16: =IFERROR(SUMPRODUCT(('08_Moteur'!$A$3:$A$60="ISCOM")*('08_Moteur'!$B$3:$B$60="Lille")*(('08_Moteur'!$D$3:$D$60="B1")+('08_Moteur'!$D$3:$D$60="B2")+('08_Moteur'!$D$3:$D$60="B3"))*'08_Moteur'!$AJ$3:$AJ$60)/F16,0) | K16: =I16*J16*$G$4
B17: ISCOM | C17: Lille | D17: Mastère | E17: =SUMPRODUCT(('08_Moteur'!$A$3:$A$60="ISCOM")*('08_Moteur'!$B$3:$B$60="Lille")*(('08_Moteur'!$D$3:$D$60="M1")+('08_Moteur'!$D$3:$D$60="M2"))*'08_Moteur'!$AD$3:$AD$60) | F17: =SUMPRODUCT(('08_Moteur'!$A$3:$A$60="ISCOM")*('08_Moteur'!$B$3:$B$60="Lille")*(('08_Moteur'!$D$3:$D$60="M1")+('08_Moteur'!$D$3:$D$60="M2"))*'08_Moteur'!$AI$3:$AI$60) | G17: =IFERROR(SUMPRODUCT(('08_Moteur'!$A$3:$A$60="ISCOM")*('08_Moteur'!$B$3:$B$60="Lille")*(('08_Moteur'!$D$3:$D$60="M1")+('08_Moteur'!$D$3:$D$60="M2"))*'08_Moteur'!$AI$3:$AI$60*'08_Moteur'!$O$3:$O$60)/F17,0) | H17: =IF(E17<=0,0,MAX(1,ROUNDUP(E17/G17,0))) | I17: =MAX(0,F17-H17) | J17: =IFERROR(SUMPRODUCT(('08_Moteur'!$A$3:$A$60="ISCOM")*('08_Moteur'!$B$3:$B$60="Lille")*(('08_Moteur'!$D$3:$D$60="M1")+('08_Moteur'!$D$3:$D$60="M2"))*'08_Moteur'!$AJ$3:$AJ$60)/F17,0) | K17: =I17*J17*$G$4
B18: ISCOM | C18: Toulouse | D18: Bachelor | E18: =SUMPRODUCT(('08_Moteur'!$A$3:$A$60="ISCOM")*('08_Moteur'!$B$3:$B$60="Toulouse")*(('08_Moteur'!$D$3:$D$60="B1")+('08_Moteur'!$D$3:$D$60="B2")+('08_Moteur'!$D$3:$D$60="B3"))*'08_Moteur'!$AD$3:$AD$60) | F18: =SUMPRODUCT(('08_Moteur'!$A$3:$A$60="ISCOM")*('08_Moteur'!$B$3:$B$60="Toulouse")*(('08_Moteur'!$D$3:$D$60="B1")+('08_Moteur'!$D$3:$D$60="B2")+('08_Moteur'!$D$3:$D$60="B3"))*'08_Moteur'!$AI$3:$AI$60) | G18: =IFERROR(SUMPRODUCT(('08_Moteur'!$A$3:$A$60="ISCOM")*('08_Moteur'!$B$3:$B$60="Toulouse")*(('08_Moteur'!$D$3:$D$60="B1")+('08_Moteur'!$D$3:$D$60="B2")+('08_Moteur'!$D$3:$D$60="B3"))*'08_Moteur'!$AI$3:$AI$60*'08_Moteur'!$O$3:$O$60)/F18,0) | H18: =IF(E18<=0,0,MAX(1,ROUNDUP(E18/G18,0))) | I18: =MAX(0,F18-H18) | J18: =IFERROR(SUMPRODUCT(('08_Moteur'!$A$3:$A$60="ISCOM")*('08_Moteur'!$B$3:$B$60="Toulouse")*(('08_Moteur'!$D$3:$D$60="B1")+('08_Moteur'!$D$3:$D$60="B2")+('08_Moteur'!$D$3:$D$60="B3"))*'08_Moteur'!$AJ$3:$AJ$60)/F18,0) | K18: =I18*J18*$G$4
B19: ISCOM | C19: Toulouse | D19: Mastère | E19: =SUMPRODUCT(('08_Moteur'!$A$3:$A$60="ISCOM")*('08_Moteur'!$B$3:$B$60="Toulouse")*(('08_Moteur'!$D$3:$D$60="M1")+('08_Moteur'!$D$3:$D$60="M2"))*'08_Moteur'!$AD$3:$AD$60) | F19: =SUMPRODUCT(('08_Moteur'!$A$3:$A$60="ISCOM")*('08_Moteur'!$B$3:$B$60="Toulouse")*(('08_Moteur'!$D$3:$D$60="M1")+('08_Moteur'!$D$3:$D$60="M2"))*'08_Moteur'!$AI$3:$AI$60) | G19: =IFERROR(SUMPRODUCT(('08_Moteur'!$A$3:$A$60="ISCOM")*('08_Moteur'!$B$3:$B$60="Toulouse")*(('08_Moteur'!$D$3:$D$60="M1")+('08_Moteur'!$D$3:$D$60="M2"))*'08_Moteur'!$AI$3:$AI$60*'08_Moteur'!$O$3:$O$60)/F19,0) | H19: =IF(E19<=0,0,MAX(1,ROUNDUP(E19/G19,0))) | I19: =MAX(0,F19-H19) | J19: =IFERROR(SUMPRODUCT(('08_Moteur'!$A$3:$A$60="ISCOM")*('08_Moteur'!$B$3:$B$60="Toulouse")*(('08_Moteur'!$D$3:$D$60="M1")+('08_Moteur'!$D$3:$D$60="M2"))*'08_Moteur'!$AJ$3:$AJ$60)/F19,0) | K19: =I19*J19*$G$4
B20: Ipac Bachelor Factory | C20: Nantes | D20: Bachelor | E20: =SUMPRODUCT(('08_Moteur'!$A$3:$A$60="Ipac Bachelor Factory")*('08_Moteur'!$B$3:$B$60="Nantes")*(('08_Moteur'!$D$3:$D$60="B1")+('08_Moteur'!$D$3:$D$60="B2")+('08_Moteur'!$D$3:$D$60="B3"))*'08_Moteur'!$AD$3:$AD$60) | F20: =SUMPRODUCT(('08_Moteur'!$A$3:$A$60="Ipac Bachelor Factory")*('08_Moteur'!$B$3:$B$60="Nantes")*(('08_Moteur'!$D$3:$D$60="B1")+('08_Moteur'!$D$3:$D$60="B2")+('08_Moteur'!$D$3:$D$60="B3"))*'08_Moteur'!$AI$3:$AI$60) | G20: =IFERROR(SUMPRODUCT(('08_Moteur'!$A$3:$A$60="Ipac Bachelor Factory")*('08_Moteur'!$B$3:$B$60="Nantes")*(('08_Moteur'!$D$3:$D$60="B1")+('08_Moteur'!$D$3:$D$60="B2")+('08_Moteur'!$D$3:$D$60="B3"))*'08_Moteur'!$AI$3:$AI$60*'08_Moteur'!$O$3:$O$60)/F20,0) | H20: =IF(E20<=0,0,MAX(1,ROUNDUP(E20/G20,0))) | I20: =MAX(0,F20-H20) | J20: =IFERROR(SUMPRODUCT(('08_Moteur'!$A$3:$A$60="Ipac Bachelor Factory")*('08_Moteur'!$B$3:$B$60="Nantes")*(('08_Moteur'!$D$3:$D$60="B1")+('08_Moteur'!$D$3:$D$60="B2")+('08_Moteur'!$D$3:$D$60="B3"))*'08_Moteur'!$AJ$3:$AJ$60)/F20,0) | K20: =I20*J20*$G$4
B21: Ipac Bachelor Factory | C21: Rennes | D21: Bachelor | E21: =SUMPRODUCT(('08_Moteur'!$A$3:$A$60="Ipac Bachelor Factory")*('08_Moteur'!$B$3:$B$60="Rennes")*(('08_Moteur'!$D$3:$D$60="B1")+('08_Moteur'!$D$3:$D$60="B2")+('08_Moteur'!$D$3:$D$60="B3"))*'08_Moteur'!$AD$3:$AD$60) | F21: =SUMPRODUCT(('08_Moteur'!$A$3:$A$60="Ipac Bachelor Factory")*('08_Moteur'!$B$3:$B$60="Rennes")*(('08_Moteur'!$D$3:$D$60="B1")+('08_Moteur'!$D$3:$D$60="B2")+('08_Moteur'!$D$3:$D$60="B3"))*'08_Moteur'!$AI$3:$AI$60) | G21: =IFERROR(SUMPRODUCT(('08_Moteur'!$A$3:$A$60="Ipac Bachelor Factory")*('08_Moteur'!$B$3:$B$60="Rennes")*(('08_Moteur'!$D$3:$D$60="B1")+('08_Moteur'!$D$3:$D$60="B2")+('08_Moteur'!$D$3:$D$60="B3"))*'08_Moteur'!$AI$3:$AI$60*'08_Moteur'!$O$3:$O$60)/F21,0) | H21: =IF(E21<=0,0,MAX(1,ROUNDUP(E21/G21,0))) | I21: =MAX(0,F21-H21) | J21: =IFERROR(SUMPRODUCT(('08_Moteur'!$A$3:$A$60="Ipac Bachelor Factory")*('08_Moteur'!$B$3:$B$60="Rennes")*(('08_Moteur'!$D$3:$D$60="B1")+('08_Moteur'!$D$3:$D$60="B2")+('08_Moteur'!$D$3:$D$60="B3"))*'08_Moteur'!$AJ$3:$AJ$60)/F21,0) | K21: =I21*J21*$G$4
B22: Ipac Bachelor Factory | C22: Montpellier | D22: Bachelor | E22: =SUMPRODUCT(('08_Moteur'!$A$3:$A$60="Ipac Bachelor Factory")*('08_Moteur'!$B$3:$B$60="Montpellier")*(('08_Moteur'!$D$3:$D$60="B1")+('08_Moteur'!$D$3:$D$60="B2")+('08_Moteur'!$D$3:$D$60="B3"))*'08_Moteur'!$AD$3:$AD$60) | F22: =SUMPRODUCT(('08_Moteur'!$A$3:$A$60="Ipac Bachelor Factory")*('08_Moteur'!$B$3:$B$60="Montpellier")*(('08_Moteur'!$D$3:$D$60="B1")+('08_Moteur'!$D$3:$D$60="B2")+('08_Moteur'!$D$3:$D$60="B3"))*'08_Moteur'!$AI$3:$AI$60) | G22: =IFERROR(SUMPRODUCT(('08_Moteur'!$A$3:$A$60="Ipac Bachelor Factory")*('08_Moteur'!$B$3:$B$60="Montpellier")*(('08_Moteur'!$D$3:$D$60="B1")+('08_Moteur'!$D$3:$D$60="B2")+('08_Moteur'!$D$3:$D$60="B3"))*'08_Moteur'!$AI$3:$AI$60*'08_Moteur'!$O$3:$O$60)/F22,0) | H22: =IF(E22<=0,0,MAX(1,ROUNDUP(E22/G22,0))) | I22: =MAX(0,F22-H22) | J22: =IFERROR(SUMPRODUCT(('08_Moteur'!$A$3:$A$60="Ipac Bachelor Factory")*('08_Moteur'!$B$3:$B$60="Montpellier")*(('08_Moteur'!$D$3:$D$60="B1")+('08_Moteur'!$D$3:$D$60="B2")+('08_Moteur'!$D$3:$D$60="B3"))*'08_Moteur'!$AJ$3:$AJ$60)/F22,0) | K22: =I22*J22*$G$4
B23: Pigier | C23: Lyon | D23: BTS | E23: =SUMPRODUCT(('08_Moteur'!$A$3:$A$60="Pigier")*('08_Moteur'!$B$3:$B$60="Lyon")*(('08_Moteur'!$D$3:$D$60="1")+('08_Moteur'!$D$3:$D$60="2"))*'08_Moteur'!$AD$3:$AD$60) | F23: =SUMPRODUCT(('08_Moteur'!$A$3:$A$60="Pigier")*('08_Moteur'!$B$3:$B$60="Lyon")*(('08_Moteur'!$D$3:$D$60="1")+('08_Moteur'!$D$3:$D$60="2"))*'08_Moteur'!$AI$3:$AI$60) | G23: =IFERROR(SUMPRODUCT(('08_Moteur'!$A$3:$A$60="Pigier")*('08_Moteur'!$B$3:$B$60="Lyon")*(('08_Moteur'!$D$3:$D$60="1")+('08_Moteur'!$D$3:$D$60="2"))*'08_Moteur'!$AI$3:$AI$60*'08_Moteur'!$O$3:$O$60)/F23,0) | H23: =IF(E23<=0,0,MAX(1,ROUNDUP(E23/G23,0))) | I23: =MAX(0,F23-H23) | J23: =IFERROR(SUMPRODUCT(('08_Moteur'!$A$3:$A$60="Pigier")*('08_Moteur'!$B$3:$B$60="Lyon")*(('08_Moteur'!$D$3:$D$60="1")+('08_Moteur'!$D$3:$D$60="2"))*'08_Moteur'!$AJ$3:$AJ$60)/F23,0) | K23: =I23*J23*$G$4
B24: Pigier | C24: Lyon | D24: Bachelor | E24: =SUMPRODUCT(('08_Moteur'!$A$3:$A$60="Pigier")*('08_Moteur'!$B$3:$B$60="Lyon")*(('08_Moteur'!$D$3:$D$60="B1")+('08_Moteur'!$D$3:$D$60="B2")+('08_Moteur'!$D$3:$D$60="B3"))*'08_Moteur'!$AD$3:$AD$60) | F24: =SUMPRODUCT(('08_Moteur'!$A$3:$A$60="Pigier")*('08_Moteur'!$B$3:$B$60="Lyon")*(('08_Moteur'!$D$3:$D$60="B1")+('08_Moteur'!$D$3:$D$60="B2")+('08_Moteur'!$D$3:$D$60="B3"))*'08_Moteur'!$AI$3:$AI$60) | G24: =IFERROR(SUMPRODUCT(('08_Moteur'!$A$3:$A$60="Pigier")*('08_Moteur'!$B$3:$B$60="Lyon")*(('08_Moteur'!$D$3:$D$60="B1")+('08_Moteur'!$D$3:$D$60="B2")+('08_Moteur'!$D$3:$D$60="B3"))*'08_Moteur'!$AI$3:$AI$60*'08_Moteur'!$O$3:$O$60)/F24,0) | H24: =IF(E24<=0,0,MAX(1,ROUNDUP(E24/G24,0))) | I24: =MAX(0,F24-H24) | J24: =IFERROR(SUMPRODUCT(('08_Moteur'!$A$3:$A$60="Pigier")*('08_Moteur'!$B$3:$B$60="Lyon")*(('08_Moteur'!$D$3:$D$60="B1")+('08_Moteur'!$D$3:$D$60="B2")+('08_Moteur'!$D$3:$D$60="B3"))*'08_Moteur'!$AJ$3:$AJ$60)/F24,0) | K24: =I24*J24*$G$4
B25: Pigier | C25: Bordeaux | D25: BTS | E25: =SUMPRODUCT(('08_Moteur'!$A$3:$A$60="Pigier")*('08_Moteur'!$B$3:$B$60="Bordeaux")*(('08_Moteur'!$D$3:$D$60="1")+('08_Moteur'!$D$3:$D$60="2"))*'08_Moteur'!$AD$3:$AD$60) | F25: =SUMPRODUCT(('08_Moteur'!$A$3:$A$60="Pigier")*('08_Moteur'!$B$3:$B$60="Bordeaux")*(('08_Moteur'!$D$3:$D$60="1")+('08_Moteur'!$D$3:$D$60="2"))*'08_Moteur'!$AI$3:$AI$60) | G25: =IFERROR(SUMPRODUCT(('08_Moteur'!$A$3:$A$60="Pigier")*('08_Moteur'!$B$3:$B$60="Bordeaux")*(('08_Moteur'!$D$3:$D$60="1")+('08_Moteur'!$D$3:$D$60="2"))*'08_Moteur'!$AI$3:$AI$60*'08_Moteur'!$O$3:$O$60)/F25,0) | H25: =IF(E25<=0,0,MAX(1,ROUNDUP(E25/G25,0))) | I25: =MAX(0,F25-H25) | J25: =IFERROR(SUMPRODUCT(('08_Moteur'!$A$3:$A$60="Pigier")*('08_Moteur'!$B$3:$B$60="Bordeaux")*(('08_Moteur'!$D$3:$D$60="1")+('08_Moteur'!$D$3:$D$60="2"))*'08_Moteur'!$AJ$3:$AJ$60)/F25,0) | K25: =I25*J25*$G$4
B26: Pigier | C26: Bordeaux | D26: Bachelor | E26: =SUMPRODUCT(('08_Moteur'!$A$3:$A$60="Pigier")*('08_Moteur'!$B$3:$B$60="Bordeaux")*(('08_Moteur'!$D$3:$D$60="B1")+('08_Moteur'!$D$3:$D$60="B2")+('08_Moteur'!$D$3:$D$60="B3"))*'08_Moteur'!$AD$3:$AD$60) | F26: =SUMPRODUCT(('08_Moteur'!$A$3:$A$60="Pigier")*('08_Moteur'!$B$3:$B$60="Bordeaux")*(('08_Moteur'!$D$3:$D$60="B1")+('08_Moteur'!$D$3:$D$60="B2")+('08_Moteur'!$D$3:$D$60="B3"))*'08_Moteur'!$AI$3:$AI$60) | G26: =IFERROR(SUMPRODUCT(('08_Moteur'!$A$3:$A$60="Pigier")*('08_Moteur'!$B$3:$B$60="Bordeaux")*(('08_Moteur'!$D$3:$D$60="B1")+('08_Moteur'!$D$3:$D$60="B2")+('08_Moteur'!$D$3:$D$60="B3"))*'08_Moteur'!$AI$3:$AI$60*'08_Moteur'!$O$3:$O$60)/F26,0) | H26: =IF(E26<=0,0,MAX(1,ROUNDUP(E26/G26,0))) | I26: =MAX(0,F26-H26) | J26: =IFERROR(SUMPRODUCT(('08_Moteur'!$A$3:$A$60="Pigier")*('08_Moteur'!$B$3:$B$60="Bordeaux")*(('08_Moteur'!$D$3:$D$60="B1")+('08_Moteur'!$D$3:$D$60="B2")+('08_Moteur'!$D$3:$D$60="B3"))*'08_Moteur'!$AJ$3:$AJ$60)/F26,0) | K26: =I26*J26*$G$4
B27: Tunon | C27: Paris | D27: Bachelor | E27: =SUMPRODUCT(('08_Moteur'!$A$3:$A$60="Tunon")*('08_Moteur'!$B$3:$B$60="Paris")*(('08_Moteur'!$D$3:$D$60="B1")+('08_Moteur'!$D$3:$D$60="B2")+('08_Moteur'!$D$3:$D$60="B3"))*'08_Moteur'!$AD$3:$AD$60) | F27: =SUMPRODUCT(('08_Moteur'!$A$3:$A$60="Tunon")*('08_Moteur'!$B$3:$B$60="Paris")*(('08_Moteur'!$D$3:$D$60="B1")+('08_Moteur'!$D$3:$D$60="B2")+('08_Moteur'!$D$3:$D$60="B3"))*'08_Moteur'!$AI$3:$AI$60) | G27: =IFERROR(SUMPRODUCT(('08_Moteur'!$A$3:$A$60="Tunon")*('08_Moteur'!$B$3:$B$60="Paris")*(('08_Moteur'!$D$3:$D$60="B1")+('08_Moteur'!$D$3:$D$60="B2")+('08_Moteur'!$D$3:$D$60="B3"))*'08_Moteur'!$AI$3:$AI$60*'08_Moteur'!$O$3:$O$60)/F27,0) | H27: =IF(E27<=0,0,MAX(1,ROUNDUP(E27/G27,0))) | I27: =MAX(0,F27-H27) | J27: =IFERROR(SUMPRODUCT(('08_Moteur'!$A$3:$A$60="Tunon")*('08_Moteur'!$B$3:$B$60="Paris")*(('08_Moteur'!$D$3:$D$60="B1")+('08_Moteur'!$D$3:$D$60="B2")+('08_Moteur'!$D$3:$D$60="B3"))*'08_Moteur'!$AJ$3:$AJ$60)/F27,0) | K27: =I27*J27*$G$4
B28: Tunon | C28: Lyon | D28: Bachelor | E28: =SUMPRODUCT(('08_Moteur'!$A$3:$A$60="Tunon")*('08_Moteur'!$B$3:$B$60="Lyon")*(('08_Moteur'!$D$3:$D$60="B1")+('08_Moteur'!$D$3:$D$60="B2")+('08_Moteur'!$D$3:$D$60="B3"))*'08_Moteur'!$AD$3:$AD$60) | F28: =SUMPRODUCT(('08_Moteur'!$A$3:$A$60="Tunon")*('08_Moteur'!$B$3:$B$60="Lyon")*(('08_Moteur'!$D$3:$D$60="B1")+('08_Moteur'!$D$3:$D$60="B2")+('08_Moteur'!$D$3:$D$60="B3"))*'08_Moteur'!$AI$3:$AI$60) | G28: =IFERROR(SUMPRODUCT(('08_Moteur'!$A$3:$A$60="Tunon")*('08_Moteur'!$B$3:$B$60="Lyon")*(('08_Moteur'!$D$3:$D$60="B1")+('08_Moteur'!$D$3:$D$60="B2")+('08_Moteur'!$D$3:$D$60="B3"))*'08_Moteur'!$AI$3:$AI$60*'08_Moteur'!$O$3:$O$60)/F28,0) | H28: =IF(E28<=0,0,MAX(1,ROUNDUP(E28/G28,0))) | I28: =MAX(0,F28-H28) | J28: =IFERROR(SUMPRODUCT(('08_Moteur'!$A$3:$A$60="Tunon")*('08_Moteur'!$B$3:$B$60="Lyon")*(('08_Moteur'!$D$3:$D$60="B1")+('08_Moteur'!$D$3:$D$60="B2")+('08_Moteur'!$D$3:$D$60="B3"))*'08_Moteur'!$AJ$3:$AJ$60)/F28,0) | K28: =I28*J28*$G$4
B29: TOTAL | E29: =SUM(E6:E28) | F29: =SUM(F6:F28) | H29: =SUM(H6:H28) | I29: =SUM(I6:I28) | K29: =SUM(K6:K28)
B31: Économie potentielle totale de mutualisation : | G31: =K29
B33: 🧪 Indicateur de POTENTIEL (bac à sable), maille campus × cycle. « Sections économisables » = classes récupérables si l'on regroupe les étudiants d'un même cycle dans des classes pleines ; le plancher = ARRONDI.SUP(effectif du cycle / capacité) → la capacité n'est JAMAIS dépassée (même garde-fou que le simulateur, mais sur le cycle). On ne mélange PAS des cycles différents (un B1 et un M2 ne partagent pas de classe). L'économie ne porte que sur la part d'heures réellement mutualisable au sein du cycle (tronc commun) — le reste reste spécifique à chaque année. N'affecte PAS le P&L officiel ; à décliner dans Tagetik à la maille de consolidation.

Sheet 11c_Cascade
B2: Allocation EN CASCADE sur un VRAI campus (ISCOM Toulouse) & effet d'une fermeture
B3: OBJET DE L'ONGLET : montrer, sur un vrai campus, QUAND fermer une promo est bénéfique (ou pas). Chiffres RÉELS du moteur. La structure NON-ÉVITABLE descend en cascade : groupe → marque au CA → campus au nb d'étudiants → promo au NOMBRE DE CLASSES. On DÉCIDE sur la CONTRIBUTION (évitable) ; le « résultat tout compris » (après structure) n'est qu'informatif. Change l'effectif SCÉNARIO (bleu) : contribution et classes se recalculent.
B5: 1) Structure non-évitable de ISCOM Toulouse — siège groupe cascadé (CA marque → effectif campus) + loyer & permanents directs (réels, feuille 09)
B6: Siège / structure centrale GROUPE (réel) : | G6: ='01_Cadrage'!$H$25*(1+'01_Cadrage'!$H$20)
B7: × Part ISCOM au CA : | G7: =IFERROR(SUMIFS('08_Moteur'!$AH$3:$AH$60,'08_Moteur'!$A$3:$A$60,"ISCOM")/SUM('08_Moteur'!$AH$3:$AH$60),0) | H7: → Siège ISCOM : | I7: =G6*G7
B8: × Part Toulouse dans ISCOM (aux effectifs) : | G8: =IFERROR(SUMIFS('08_Moteur'!$AD$3:$AD$60,'08_Moteur'!$A$3:$A$60,"ISCOM",'08_Moteur'!$B$3:$B$60,"Toulouse")/SUMIFS('08_Moteur'!$AD$3:$AD$60,'08_Moteur'!$A$3:$A$60,"ISCOM"),0) | H8: → Siège Toulouse : | I8: =I7*G8
B9: Loyer Toulouse (réel, feuille 09) : | I9: ='09_Allocation'!E12
B10: Permanents Toulouse (réel, feuille 09) : | I10: ='09_Allocation'!F12
B11: ENVELOPE Toulouse = siège + loyer + permanents (NON-ÉVITABLE) : | I11: =I8+I9+I10
B13: 2) Répartition campus → promos AU NOMBRE DE CLASSES + décision (change l'effectif bleu ; le rouge = résultat tout compris < 0) | P13: Paramètres unitaires (issus du modèle, feuille 05)
B14: Promo (ISCOM Toulouse) | C14: Eff. réel (moteur) | D14: Eff. scénario | E14: Classes | F14: CA | G14: Contribution (évitable) | H14: Struct/classe | I14: Struct allouée | J14: Résultat t.c. (avant) | K14: Décision | L14: Cl. après | M14: Struct après | N14: Résultat t.c. (après) | P14: Capacité | Q14: Coût/classe | R14: Tarif | S14: Charge/étu | T14: CAC/étu
B15: Bachelor 1 (INIT) | C15: ='08_Moteur'!AD33 | D15: 51 | E15: =IF(D15<=0,0,MAX(1,ROUNDUP(D15/P15,0))) | F15: =D15*R15 | G15: =F15-E15*Q15-D15*S15-D15*T15 | H15: =IFERROR($I$11/SUM($E$15:$E$19),0) | I15: =E15*H15 | J15: =G15-I15 | K15: Maintenir | L15: =IF(K15="Fermer",0,E15) | M15: =IF(K15="Fermer",0,L15*IFERROR($I$11/SUM($L$15:$L$19),0)) | N15: =IF(K15="Fermer",0,G15-M15) | P15: 32 | Q15: 37200 | R15: 8500 | S15: 1484 | T15: 320
B16: Bachelor 2 (ALT) | C16: ='08_Moteur'!AD34 | D16: 44 | E16: =IF(D16<=0,0,MAX(1,ROUNDUP(D16/P16,0))) | F16: =D16*R16 | G16: =F16-E16*Q16-D16*S16-D16*T16 | H16: =IFERROR($I$11/SUM($E$15:$E$19),0) | I16: =E16*H16 | J16: =G16-I16 | K16: Maintenir | L16: =IF(K16="Fermer",0,E16) | M16: =IF(K16="Fermer",0,L16*IFERROR($I$11/SUM($L$15:$L$19),0)) | N16: =IF(K16="Fermer",0,G16-M16) | P16: 32 | Q16: 34720 | R16: 8000 | S16: 1484 | T16: 0
B17: Bachelor 3 (ALT) | C17: ='08_Moteur'!AD35 | D17: 38 | E17: =IF(D17<=0,0,MAX(1,ROUNDUP(D17/P17,0))) | F17: =D17*R17 | G17: =F17-E17*Q17-D17*S17-D17*T17 | H17: =IFERROR($I$11/SUM($E$15:$E$19),0) | I17: =E17*H17 | J17: =G17-I17 | K17: Maintenir | L17: =IF(K17="Fermer",0,E17) | M17: =IF(K17="Fermer",0,L17*IFERROR($I$11/SUM($L$15:$L$19),0)) | N17: =IF(K17="Fermer",0,G17-M17) | P17: 32 | Q17: 32240 | R17: 8000 | S17: 1484 | T17: 0
B18: Mastère 1 (ALT — piège) | C18: ='08_Moteur'!AD36 | D18: 31 | E18: =IF(D18<=0,0,MAX(1,ROUNDUP(D18/P18,0))) | F18: =D18*R18 | G18: =F18-E18*Q18-D18*S18-D18*T18 | H18: =IFERROR($I$11/SUM($E$15:$E$19),0) | I18: =E18*H18 | J18: =G18-I18 | K18: Maintenir | L18: =IF(K18="Fermer",0,E18) | M18: =IF(K18="Fermer",0,L18*IFERROR($I$11/SUM($L$15:$L$19),0)) | N18: =IF(K18="Fermer",0,G18-M18) | P18: 26 | Q18: 35520 | R18: 9000 | S18: 1604 | T18: 600
B19: Mastère 2 — extinction | C19: ='08_Moteur'!AD37 | D19: 4 | E19: =IF(D19<=0,0,MAX(1,ROUNDUP(D19/P19,0))) | F19: =D19*R19 | G19: =F19-E19*Q19-D19*S19-D19*T19 | H19: =IFERROR($I$11/SUM($E$15:$E$19),0) | I19: =E19*H19 | J19: =G19-I19 | K19: Fermer | L19: =IF(K19="Fermer",0,E19) | M19: =IF(K19="Fermer",0,L19*IFERROR($I$11/SUM($L$15:$L$19),0)) | N19: =IF(K19="Fermer",0,G19-M19) | P19: 26 | Q19: 32560 | R19: 9000 | S19: 1604 | T19: 0
B20: TOTAL | C20: =SUM(C15:C19) | D20: =SUM(D15:D19) | E20: =SUM(E15:E19) | F20: =SUM(F15:F19) | G20: =SUM(G15:G19) | I20: =SUM(I15:I19) | J20: =SUM(J15:J19) | L20: =SUM(L15:L19) | M20: =SUM(M15:M19) | N20: =SUM(N15:N19)
B22: EBITDA campus AVANT : | F22: =SUM(G15:G19)-$I$11 | H22: EBITDA campus APRÈS : | J22: =SUMIFS(G15:G19,K15:K19,"<>Fermer")-$I$11 | M22: Δ EBITDA : | N22: =J22-F22
B24: 🧪 LECTURE (vrai campus ISCOM Toulouse, bac à sable). On DÉCIDE sur la CONTRIBUTION (évitable), JAMAIS sur le résultat tout compris. Trois enseignements visibles ici : ① FERMER BÉNÉFIQUE — le Mastère 2 est en EXTINCTION (4 étudiants) : sa CONTRIBUTION est négative (une classe coûte plus qu'elle ne rapporte) → le fermer fait MONTER l'EBITDA campus (Δ = perte évitée). ② EFFET D'ENTRAÎNEMENT — en fermant, la structure non-évitable se redivise sur les classes restantes (÷ nb de classes) → le résultat tout compris du Bachelor 3 (déjà mince) bascule EN ROUGE, alors que l'EBITDA s'est amélioré : c'est un effet d'ALLOCATION comptable, pas une vraie perte. ③ LE PIÈGE — le Mastère 1 est EN ROUGE en résultat tout compris (il porte beaucoup de structure) MAIS sa CONTRIBUTION est POSITIVE (~+119 k€) → il NE FAUT PAS le fermer : le fermer FERAIT PERDRE cette contribution et alourdirait tout le monde. Essaie : mets le Mastère 1 sur « Fermer » → l'EBITDA CHUTE. N'affecte pas le P&L officiel.

Sheet 12_Sensibilite
B2: Sensibilité — impact € sur l'EBITDA par levier
B3: Sens unique : tes leviers → EBITDA. Approximations vivantes au point courant. Pour combler l'écart de cadrage, lis quel levier pèse le plus.
B5: Levier (pas) | C5: Impact EBITDA | D5: Lecture
B6: +1 % de hausse tarifaire | C6: =0.01*SUMPRODUCT('08_Moteur'!$AD$3:$AD$60*'08_Moteur'!$AE$3:$AE$60*'08_Moteur'!$AF$3:$AF$60) | D6: Tombe quasi intégralement en EBITDA.
B7: +1 % de budget marketing | C7: =0.01*'01_Cadrage'!$H$27*SUMPRODUCT(('08_Moteur'!$F$3:$F$60=1)*'08_Moteur'!$AM$3:$AM$60)-0.01*SUMPRODUCT(('08_Moteur'!$F$3:$F$60=1)*'08_Moteur'!$H$3:$H$60*'08_Moteur'!$S$3:$S$60*(1+'08_Moteur'!$Y$3:$Y$60)) | D7: Plus de leads → plus d'inscrits, net du coût.
B8: +1 point de taux de passage | C8: =0.01*SUMPRODUCT(('08_Moteur'!$F$3:$F$60=0)*'08_Moteur'!$K$3:$K$60)*IFERROR(SUM('08_Moteur'!$AM$3:$AM$60)/SUM('08_Moteur'!$AD$3:$AD$60),0) | D8: Rétention : + d'étudiants qui poursuivent.

Sheet 13_Simulation
B2: Tableau de bord — simulation
B3: Scénario : | C3: ='01_Cadrage'!D3
B5: Indicateur | C5: Budget | D5: N-1 | E5: Évolution
B6: Effectif total | C6: =SUM('08_Moteur'!$AD$3:$AD$60) | D6: ='07_Structure'!C18 | E6: =IFERROR(C6/D6-1,0)
B7: Chiffre d'affaires | C7: =SUM('08_Moteur'!$AH$3:$AH$60) | D7: ='07_Structure'!D18 | E7: =IFERROR(C7/D7-1,0)
B8: Marge de contribution | C8: =SUM('08_Moteur'!$AM$3:$AM$60) | D8: ='07_Structure'!E18 | E8: =IFERROR(C8/D8-1,0)
B9: EBITDA | C9: ='09_Allocation'!J20 | D9: ='07_Structure'!E18-'07_Structure'!F18-'07_Structure'!H18-2000000 | E9: =IFERROR(C9/D9-1,0)
B10: Marge EBITDA % | C10: =IFERROR('09_Allocation'!J20/SUM('08_Moteur'!$AH$3:$AH$60),0) | D10: =IFERROR(('07_Structure'!E18-'07_Structure'!F18-'07_Structure'!H18-2000000)/'07_Structure'!D18,0) | E10: =C10-D10
B11: Nombre de classes | C11: =SUM('08_Moteur'!$AI$3:$AI$60) | D11: =SUM('08_Moteur'!$M$3:$M$60) | E11: =IFERROR(C11/D11-1,0)
B12: Nouveaux inscrits | C12: =SUM('08_Moteur'!$AB$3:$AB$60) | D12: =SUM('08_Moteur'!$H$3:$H$60) | E12: =IFERROR(C12/D12-1,0)
B13: Taux d'alternance | C13: =IFERROR(SUMPRODUCT(('08_Moteur'!$E$3:$E$60="ALT")*'08_Moteur'!$AD$3:$AD$60)/SUM('08_Moteur'!$AD$3:$AD$60),0) | D13: =IFERROR(SUMPRODUCT(('08_Moteur'!$E$3:$E$60="ALT")*'08_Moteur'!$G$3:$G$60)/SUM('08_Moteur'!$G$3:$G$60),0) | E13: =C13-D13

Sheet 14_Mapping_Tagetik
B2: Passerelle vers CCH Tagetik
B4: Correspondance modèle → Tagetik
B5: Concept | C5: Objet Tagetik | D5: Détail
B6: Marque / Campus | C6: Entity | D6: Hiérarchie Groupe→Marque→Campus
B7: Programme × Année × Modalité | C7: Dimensions analytiques | D7: Maille fine, attributs initial/alternance
B8: Params (capacité, heures…) | C8: Attributs de dimension / driver | D8: Données de référence par programme×année (feuille 05)
B9: Historique N-2/N-1 | C9: Category ACTUAL (multi-années) | D9: Plus de profondeur = élasticité marketing robuste
B10: Cohortes / taux de passage | C10: Règle de calcul | D10: Progression B1→B2→B3
B11: Objectifs (cadrage) | C11: Version cible + écart | D11: Top-down vs bottom-up
B12: Décisions ouvrir/fermer | C12: Scénarios / versions | D12: Simulateur → snapshot
B13: Allocation structure | C13: Cost allocation (driver) | D13: Effectif/CA/m²
