Workbook

Sheet Données (V_CAMPUS_CLASSE)
A1: DONNÉES SOURCE — vue V_CAMPUS_CLASSE (wrapper sur V_ALLOCATION) · filtrer ENTITY = campos
A2: EXERCICE | B2: ENTITY | C2: MARQUE | D2: PROGRAMME | E2: AN_ETUDE | F2: MODALITE | G2: VOL_EFF | H2: VOL_CLASS | I2: VOL_NEW | J2: CA | K2: CAPACITE | L2: PLACES | M2: COST_VARIABLE | N2: CONTRIBUTION | O2: COST_COMPLET | P2: MARGE_COMPLETE | Q2: COST_SIEGE | R2: POINT_MORT
A3: 2024 | B3: ISCOM_PAR | C3: ISCOM | D3: BAC_COM | E3: B1 | F3: INIT | G3: 64 | H3: 3 | I3: 64 | J3: 543360 | K3: 32 | L3: 96 | M3: 90944 | N3: 452416 | O3: 564207 | P3: -20847 | Q3: 78447 | R3: 26.6
A4: 2024 | B4: ISCOM_PAR | C4: ISCOM | D4: BAC_COM | E4: B2 | F4: ALT | G4: 62 | H4: 3 | I4: 0 | J4: 486080 | K4: 32 | L4: 96 | M4: 56790 | N4: 429290 | O4: 491964 | P4: -5884 | Q4: 75996 | R4: 23.7
A5: 2024 | B5: ISCOM_PAR | C5: ISCOM | D5: BAC_COM | E5: B3 | F5: ALT | G5: 61 | H5: 3 | I5: 0 | J5: 478240 | K5: 32 | L5: 96 | M5: 56407 | N5: 421833 | O5: 486344 | P5: -8104 | Q5: 74770 | R5: 23.4
A6: 2024 | B6: ISCOM_PAR | C6: ISCOM | D6: MAS_COM | E6: M1 | F6: ALT | G6: 64 | H6: 3 | I6: 64 | J6: 543360 | K6: 26 | L6: 78 | M6: 78548 | N6: 464812 | O6: 510388 | P6: 32972 | Q6: 78447 | R6: 23.4
A7: 2024 | B7: ISCOM_PAR | C7: ISCOM | D7: MAS_COM | E7: M2 | F7: ALT | G7: 63 | H7: 3 | I7: 0 | J7: 529200 | K7: 26 | L7: 78 | M7: 53041 | N7: 476159 | O7: 479644 | P7: 49556 | Q7: 77222 | R7: 21.2
A8: 2025 | B8: ISCOM_PAR | C8: ISCOM | D8: BAC_COM | E8: B1 | F8: INIT | G8: 68 | H8: 3 | I8: 68 | J8: 577320 | K8: 32 | L8: 96 | M8: 96443 | N8: 480877 | O8: 592861 | P8: -15541 | Q8: 83812 | R8: 27.9
A9: 2025 | B9: ISCOM_PAR | C9: ISCOM | D9: BAC_COM | E9: B2 | F9: ALT | G9: 66 | H9: 3 | I9: 0 | J9: 517440 | K9: 32 | L9: 96 | M9: 59412 | N9: 458028 | O9: 516595 | P9: 845 | Q9: 81347 | R9: 24.8
A10: 2025 | B10: ISCOM_PAR | C10: ISCOM | D10: BAC_COM | E10: B3 | F10: ALT | G10: 65 | H10: 3 | I10: 0 | J10: 509600 | K10: 32 | L10: 96 | M10: 59035 | N10: 450565 | O10: 511042 | P10: -1442 | Q10: 80114 | R10: 24.6
A11: 2025 | B11: ISCOM_PAR | C11: ISCOM | D11: MAS_COM | E11: M1 | F11: ALT | G11: 68 | H11: 3 | I11: 68 | J11: 577320 | K11: 26 | L11: 78 | M11: 83479 | N11: 493841 | O11: 536575 | P11: 40745 | Q11: 83812 | R11: 24.6
A12: 2025 | B12: ISCOM_PAR | C12: ISCOM | D12: MAS_COM | E12: M2 | F12: ALT | G12: 67 | H12: 3 | I12: 0 | J12: 562800 | K12: 26 | L12: 78 | M12: 55467 | N12: 507333 | O12: 503386 | P12: 59414 | Q12: 82579 | R12: 22.2
A13: 2026 | B13: ISCOM_PAR | C13: ISCOM | D13: BAC_COM | E13: B1 | F13: INIT | G13: 72 | H13: 3 | I13: 72 | J13: 611280 | K13: 32 | L13: 96 | M13: 102464 | N13: 508816 | O13: 623796 | P13: -12516 | Q13: 89311 | R13: 29.4
A14: 2026 | B14: ISCOM_PAR | C14: ISCOM | D14: BAC_COM | E14: B2 | F14: ALT | G14: 70 | H14: 3 | I14: 0 | J14: 548800 | K14: 32 | L14: 96 | M14: 62266 | N14: 486534 | O14: 543059 | P14: 5741 | Q14: 86830 | R14: 26
... A17: 2026 | B17: ISCOM_PAR | C17: ISCOM | D17: MAS_COM | E17: M2 | F17: ALT | G17: 71 | H17: 3 | I17: 0 | J17: 596400 | K17: 26 | L17: 78 | M17: 58110 | N17: 538290 | O17: 528913 | P17: 67487 | Q17: 88071 | R17: 23.3

Sheet Masque
A1: COCKPIT DIRECTEUR — Iscom Paris · MASQUE (formules → onglet Données)
A2: Tout est en SUMIFS sur la vue V_CAMPUS_CLASSE. Change le filtre campus/exercice → tout se recalcule.
A4: ① Mes chiffres clés 2026
A5: Effectif | D5: Remplissage moyen | G5: Chiffre d'affaires
A6: =SUMIFS('Données (V_CAMPUS_CLASSE)'!$G$3:$G$17,'Données (V_CAMPUS_CLASSE)'!$A$3:$A$17,2026,'Données (V_CAMPUS_CLASSE)'!$B$3:$B$17,"ISCOM_PAR") | D6: =SUMIFS('Données (V_CAMPUS_CLASSE)'!$G$3:$G$17,'Données (V_CAMPUS_CLASSE)'!$A$3:$A$17,2026,'Données (V_CAMPUS_CLASSE)'!$B$3:$B$17,"ISCOM_PAR")/SUMIFS('Données (V_CAMPUS_CLASSE)'!$L$3:$L$17,'Données (V_CAMPUS_CLASSE)'!$A$3:$A$17,2026,'Données (V_CAMPUS_CLASSE)'!$B$3:$B$17,"ISCOM_PAR") | G6: =SUMIFS('Données (V_CAMPUS_CLASSE)'!$J$3:$J$17,'Données (V_CAMPUS_CLASSE)'!$A$3:$A$17,2026,'Données (V_CAMPUS_CLASSE)'!$B$3:$B$17,"ISCOM_PAR")
A7: Contribution | D7: Quote-part siège | G7: EBITDA net
A8: =SUMIFS('Données (V_CAMPUS_CLASSE)'!$N$3:$N$17,'Données (V_CAMPUS_CLASSE)'!$A$3:$A$17,2026,'Données (V_CAMPUS_CLASSE)'!$B$3:$B$17,"ISCOM_PAR") | D8: =-1*SUMIFS('Données (V_CAMPUS_CLASSE)'!$Q$3:$Q$17,'Données (V_CAMPUS_CLASSE)'!$A$3:$A$17,2026,'Données (V_CAMPUS_CLASSE)'!$B$3:$B$17,"ISCOM_PAR") | G8: =SUMIFS('Données (V_CAMPUS_CLASSE)'!$P$3:$P$17,'Données (V_CAMPUS_CLASSE)'!$A$3:$A$17,2026,'Données (V_CAMPUS_CLASSE)'!$B$3:$B$17,"ISCOM_PAR")
A10: ② Ma trajectoire 2024 → 2026
B11: 2024 | C11: 2025 | D11: 2026
A12: Chiffre d'affaires | B12: =SUMIFS('Données (V_CAMPUS_CLASSE)'!$J$3:$J$17,'Données (V_CAMPUS_CLASSE)'!$A$3:$A$17,2024,'Données (V_CAMPUS_CLASSE)'!$B$3:$B$17,"ISCOM_PAR") | C12: =SUMIFS('Données (V_CAMPUS_CLASSE)'!$J$3:$J$17,'Données (V_CAMPUS_CLASSE)'!$A$3:$A$17,2025,'Données (V_CAMPUS_CLASSE)'!$B$3:$B$17,"ISCOM_PAR") | D12: =SUMIFS('Données (V_CAMPUS_CLASSE)'!$J$3:$J$17,'Données (V_CAMPUS_CLASSE)'!$A$3:$A$17,2026,'Données (V_CAMPUS_CLASSE)'!$B$3:$B$17,"ISCOM_PAR")
A13: Effectif | B13: =SUMIFS('Données (V_CAMPUS_CLASSE)'!$G$3:$G$17,'Données (V_CAMPUS_CLASSE)'!$A$3:$A$17,2024,'Données (V_CAMPUS_CLASSE)'!$B$3:$B$17,"ISCOM_PAR") | C13: =SUMIFS('Données (V_CAMPUS_CLASSE)'!$G$3:$G$17,'Données (V_CAMPUS_CLASSE)'!$A$3:$A$17,2025,'Données (V_CAMPUS_CLASSE)'!$B$3:$B$17,"ISCOM_PAR") | D13: =SUMIFS('Données (V_CAMPUS_CLASSE)'!$G$3:$G$17,'Données (V_CAMPUS_CLASSE)'!$A$3:$A$17,2026,'Données (V_CAMPUS_CLASSE)'!$B$3:$B$17,"ISCOM_PAR")
A14: Contribution | B14: =SUMIFS('Données (V_CAMPUS_CLASSE)'!$N$3:$N$17,'Données (V_CAMPUS_CLASSE)'!$A$3:$A$17,2024,'Données (V_CAMPUS_CLASSE)'!$B$3:$B$17,"ISCOM_PAR") | C14: =SUMIFS('Données (V_CAMPUS_CLASSE)'!$N$3:$N$17,'Données (V_CAMPUS_CLASSE)'!$A$3:$A$17,2025,'Données (V_CAMPUS_CLASSE)'!$B$3:$B$17,"ISCOM_PAR") | D14: =SUMIFS('Données (V_CAMPUS_CLASSE)'!$N$3:$N$17,'Données (V_CAMPUS_CLASSE)'!$A$3:$A$17,2026,'Données (V_CAMPUS_CLASSE)'!$B$3:$B$17,"ISCOM_PAR")
A15: EBITDA net | B15: =SUMIFS('Données (V_CAMPUS_CLASSE)'!$P$3:$P$17,'Données (V_CAMPUS_CLASSE)'!$A$3:$A$17,2024,'Données (V_CAMPUS_CLASSE)'!$B$3:$B$17,"ISCOM_PAR") | C15: =SUMIFS('Données (V_CAMPUS_CLASSE)'!$P$3:$P$17,'Données (V_CAMPUS_CLASSE)'!$A$3:$A$17,2025,'Données (V_CAMPUS_CLASSE)'!$B$3:$B$17,"ISCOM_PAR") | D15: =SUMIFS('Données (V_CAMPUS_CLASSE)'!$P$3:$P$17,'Données (V_CAMPUS_CLASSE)'!$A$3:$A$17,2026,'Données (V_CAMPUS_CLASSE)'!$B$3:$B$17,"ISCOM_PAR")
A17: ③ Mon P&L par classe 2026 (SUMIFS par programme × année)
A18: Programme ▸ Année | B18: Rempl. | C18: Eff. | D18: CA | E18: Contribution | F18: Coût complet | G18: Marge complète | H18: Pt mort | I18: Signal
A19: BAC_COM B1 | B19: =SUMIFS('Données (V_CAMPUS_CLASSE)'!$G$3:$G$17,'Données (V_CAMPUS_CLASSE)'!$A$3:$A$17,2026,'Données (V_CAMPUS_CLASSE)'!$B$3:$B$17,"ISCOM_PAR",'Données (V_CAMPUS_CLASSE)'!$D$3:$D$17,"BAC_COM",'Données (V_CAMPUS_CLASSE)'!$E$3:$E$17,"B1")/SUMIFS('Données (V_CAMPUS_CLASSE)'!$L$3:$L$17,'Données (V_CAMPUS_CLASSE)'!$A$3:$A$17,2026,'Données (V_CAMPUS_CLASSE)'!$B$3:$B$17,"ISCOM_PAR",'Données (V_CAMPUS_CLASSE)'!$D$3:$D$17,"BAC_COM",'Données (V_CAMPUS_CLASSE)'!$E$3:$E$17,"B1") | C19: =SUMIFS('Données (V_CAMPUS_CLASSE)'!$G$3:$G$17,'Données (V_CAMPUS_CLASSE)'!$A$3:$A$17,2026,'Données (V_CAMPUS_CLASSE)'!$B$3:$B$17,"ISCOM_PAR",'Données (V_CAMPUS_CLASSE)'!$D$3:$D$17,"BAC_COM",'Données (V_CAMPUS_CLASSE)'!$E$3:$E$17,"B1") | D19: =SUMIFS('Données (V_CAMPUS_CLASSE)'!$J$3:$J$17,'Données (V_CAMPUS_CLASSE)'!$A$3:$A$17,2026,'Données (V_CAMPUS_CLASSE)'!$B$3:$B$17,"ISCOM_PAR",'Données (V_CAMPUS_CLASSE)'!$D$3:$D$17,"BAC_COM",'Données (V_CAMPUS_CLASSE)'!$E$3:$E$17,"B1") | E19: =SUMIFS('Données (V_CAMPUS_CLASSE)'!$N$3:$N$17,'Données (V_CAMPUS_CLASSE)'!$A$3:$A$17,2026,'Données (V_CAMPUS_CLASSE)'!$B$3:$B$17,"ISCOM_PAR",'Données (V_CAMPUS_CLASSE)'!$D$3:$D$17,"BAC_COM",'Données (V_CAMPUS_CLASSE)'!$E$3:$E$17,"B1") | F19: =SUMIFS('Données (V_CAMPUS_CLASSE)'!$O$3:$O$17,'Données (V_CAMPUS_CLASSE)'!$A$3:$A$17,2026,'Données (V_CAMPUS_CLASSE)'!$B$3:$B$17,"ISCOM_PAR",'Données (V_CAMPUS_CLASSE)'!$D$3:$D$17,"BAC_COM",'Données (V_CAMPUS_CLASSE)'!$E$3:$E$17,"B1") | G19: =SUMIFS('Données (V_CAMPUS_CLASSE)'!$P$3:$P$17,'Données (V_CAMPUS_CLASSE)'!$A$3:$A$17,2026,'Données (V_CAMPUS_CLASSE)'!$B$3:$B$17,"ISCOM_PAR",'Données (V_CAMPUS_CLASSE)'!$D$3:$D$17,"BAC_COM",'Données (V_CAMPUS_CLASSE)'!$E$3:$E$17,"B1") | H19: =SUMIFS('Données (V_CAMPUS_CLASSE)'!$R$3:$R$17,'Données (V_CAMPUS_CLASSE)'!$A$3:$A$17,2026,'Données (V_CAMPUS_CLASSE)'!$B$3:$B$17,"ISCOM_PAR",'Données (V_CAMPUS_CLASSE)'!$D$3:$D$17,"BAC_COM",'Données (V_CAMPUS_CLASSE)'!$E$3:$E$17,"B1") | I19: =IF(G19<0,"🔴 piège",IF(B19>0.9,"⚠️ saturé","🟢 sain"))
A20: BAC_COM B2 | B20: =SUMIFS('Données (V_CAMPUS_CLASSE)'!$G$3:$G$17,'Données (V_CAMPUS_CLASSE)'!$A$3:$A$17,2026,'Données (V_CAMPUS_CLASSE)'!$B$3:$B$17,"ISCOM_PAR",'Données (V_CAMPUS_CLASSE)'!$D$3:$D$17,"BAC_COM",'Données (V_CAMPUS_CLASSE)'!$E$3:$E$17,"B2")/SUMIFS('Données (V_CAMPUS_CLASSE)'!$L$3:$L$17,'Données (V_CAMPUS_CLASSE)'!$A$3:$A$17,2026,'Données (V_CAMPUS_CLASSE)'!$B$3:$B$17,"ISCOM_PAR",'Données (V_CAMPUS_CLASSE)'!$D$3:$D$17,"BAC_COM",'Données (V_CAMPUS_CLASSE)'!$E$3:$E$17,"B2") | C20: =SUMIFS('Données (V_CAMPUS_CLASSE)'!$G$3:$G$17,'Données (V_CAMPUS_CLASSE)'!$A$3:$A$17,2026,'Données (V_CAMPUS_CLASSE)'!$B$3:$B$17,"ISCOM_PAR",'Données (V_CAMPUS_CLASSE)'!$D$3:$D$17,"BAC_COM",'Données (V_CAMPUS_CLASSE)'!$E$3:$E$17,"B2") | D20: =SUMIFS('Données (V_CAMPUS_CLASSE)'!$J$3:$J$17,'Données (V_CAMPUS_CLASSE)'!$A$3:$A$17,2026,'Données (V_CAMPUS_CLASSE)'!$B$3:$B$17,"ISCOM_PAR",'Données (V_CAMPUS_CLASSE)'!$D$3:$D$17,"BAC_COM",'Données (V_CAMPUS_CLASSE)'!$E$3:$E$17,"B2") | E20: =SUMIFS('Données (V_CAMPUS_CLASSE)'!$N$3:$N$17,'Données (V_CAMPUS_CLASSE)'!$A$3:$A$17,2026,'Données (V_CAMPUS_CLASSE)'!$B$3:$B$17,"ISCOM_PAR",'Données (V_CAMPUS_CLASSE)'!$D$3:$D$17,"BAC_COM",'Données (V_CAMPUS_CLASSE)'!$E$3:$E$17,"B2") | F20: =SUMIFS('Données (V_CAMPUS_CLASSE)'!$O$3:$O$17,'Données (V_CAMPUS_CLASSE)'!$A$3:$A$17,2026,'Données (V_CAMPUS_CLASSE)'!$B$3:$B$17,"ISCOM_PAR",'Données (V_CAMPUS_CLASSE)'!$D$3:$D$17,"BAC_COM",'Données (V_CAMPUS_CLASSE)'!$E$3:$E$17,"B2") | G20: =SUMIFS('Données (V_CAMPUS_CLASSE)'!$P$3:$P$17,'Données (V_CAMPUS_CLASSE)'!$A$3:$A$17,2026,'Données (V_CAMPUS_CLASSE)'!$B$3:$B$17,"ISCOM_PAR",'Données (V_CAMPUS_CLASSE)'!$D$3:$D$17,"BAC_COM",'Données (V_CAMPUS_CLASSE)'!$E$3:$E$17,"B2") | H20: =SUMIFS('Données (V_CAMPUS_CLASSE)'!$R$3:$R$17,'Données (V_CAMPUS_CLASSE)'!$A$3:$A$17,2026,'Données (V_CAMPUS_CLASSE)'!$B$3:$B$17,"ISCOM_PAR",'Données (V_CAMPUS_CLASSE)'!$D$3:$D$17,"BAC_COM",'Données (V_CAMPUS_CLASSE)'!$E$3:$E$17,"B2") | I20: =IF(G20<0,"🔴 piège",IF(B20>0.9,"⚠️ saturé","🟢 sain"))
A21: BAC_COM B3 | B21: =SUMIFS('Données (V_CAMPUS_CLASSE)'!$G$3:$G$17,'Données (V_CAMPUS_CLASSE)'!$A$3:$A$17,2026,'Données (V_CAMPUS_CLASSE)'!$B$3:$B$17,"ISCOM_PAR",'Données (V_CAMPUS_CLASSE)'!$D$3:$D$17,"BAC_COM",'Données (V_CAMPUS_CLASSE)'!$E$3:$E$17,"B3")/SUMIFS('Données (V_CAMPUS_CLASSE)'!$L$3:$L$17,'Données (V_CAMPUS_CLASSE)'!$A$3:$A$17,2026,'Données (V_CAMPUS_CLASSE)'!$B$3:$B$17,"ISCOM_PAR",'Données (V_CAMPUS_CLASSE)'!$D$3:$D$17,"BAC_COM",'Données (V_CAMPUS_CLASSE)'!$E$3:$E$17,"B3") | C21: =SUMIFS('Données (V_CAMPUS_CLASSE)'!$G$3:$G$17,'Données (V_CAMPUS_CLASSE)'!$A$3:$A$17,2026,'Données (V_CAMPUS_CLASSE)'!$B$3:$B$17,"ISCOM_PAR",'Données (V_CAMPUS_CLASSE)'!$D$3:$D$17,"BAC_COM",'Données (V_CAMPUS_CLASSE)'!$E$3:$E$17,"B3") | D21: =SUMIFS('Données (V_CAMPUS_CLASSE)'!$J$3:$J$17,'Données (V_CAMPUS_CLASSE)'!$A$3:$A$17,2026,'Données (V_CAMPUS_CLASSE)'!$B$3:$B$17,"ISCOM_PAR",'Données (V_CAMPUS_CLASSE)'!$D$3:$D$17,"BAC_COM",'Données (V_CAMPUS_CLASSE)'!$E$3:$E$17,"B3") | E21: =SUMIFS('Données (V_CAMPUS_CLASSE)'!$N$3:$N$17,'Données (V_CAMPUS_CLASSE)'!$A$3:$A$17,2026,'Données (V_CAMPUS_CLASSE)'!$B$3:$B$17,"ISCOM_PAR",'Données (V_CAMPUS_CLASSE)'!$D$3:$D$17,"BAC_COM",'Données (V_CAMPUS_CLASSE)'!$E$3:$E$17,"B3") | F21: =SUMIFS('Données (V_CAMPUS_CLASSE)'!$O$3:$O$17,'Données (V_CAMPUS_CLASSE)'!$A$3:$A$17,2026,'Données (V_CAMPUS_CLASSE)'!$B$3:$B$17,"ISCOM_PAR",'Données (V_CAMPUS_CLASSE)'!$D$3:$D$17,"BAC_COM",'Données (V_CAMPUS_CLASSE)'!$E$3:$E$17,"B3") | G21: =SUMIFS('Données (V_CAMPUS_CLASSE)'!$P$3:$P$17,'Données (V_CAMPUS_CLASSE)'!$A$3:$A$17,2026,'Données (V_CAMPUS_CLASSE)'!$B$3:$B$17,"ISCOM_PAR",'Données (V_CAMPUS_CLASSE)'!$D$3:$D$17,"BAC_COM",'Données (V_CAMPUS_CLASSE)'!$E$3:$E$17,"B3") | H21: =SUMIFS('Données (V_CAMPUS_CLASSE)'!$R$3:$R$17,'Données (V_CAMPUS_CLASSE)'!$A$3:$A$17,2026,'Données (V_CAMPUS_CLASSE)'!$B$3:$B$17,"ISCOM_PAR",'Données (V_CAMPUS_CLASSE)'!$D$3:$D$17,"BAC_COM",'Données (V_CAMPUS_CLASSE)'!$E$3:$E$17,"B3") | I21: =IF(G21<0,"🔴 piège",IF(B21>0.9,"⚠️ saturé","🟢 sain"))
A22: MAS_COM M1 | B22: =SUMIFS('Données (V_CAMPUS_CLASSE)'!$G$3:$G$17,'Données (V_CAMPUS_CLASSE)'!$A$3:$A$17,2026,'Données (V_CAMPUS_CLASSE)'!$B$3:$B$17,"ISCOM_PAR",'Données (V_CAMPUS_CLASSE)'!$D$3:$D$17,"MAS_COM",'Données (V_CAMPUS_CLASSE)'!$E$3:$E$17,"M1")/SUMIFS('Données (V_CAMPUS_CLASSE)'!$L$3:$L$17,'Données (V_CAMPUS_CLASSE)'!$A$3:$A$17,2026,'Données (V_CAMPUS_CLASSE)'!$B$3:$B$17,"ISCOM_PAR",'Données (V_CAMPUS_CLASSE)'!$D$3:$D$17,"MAS_COM",'Données (V_CAMPUS_CLASSE)'!$E$3:$E$17,"M1") | C22: =SUMIFS('Données (V_CAMPUS_CLASSE)'!$G$3:$G$17,'Données (V_CAMPUS_CLASSE)'!$A$3:$A$17,2026,'Données (V_CAMPUS_CLASSE)'!$B$3:$B$17,"ISCOM_PAR",'Données (V_CAMPUS_CLASSE)'!$D$3:$D$17,"MAS_COM",'Données (V_CAMPUS_CLASSE)'!$E$3:$E$17,"M1") | D22: =SUMIFS('Données (V_CAMPUS_CLASSE)'!$J$3:$J$17,'Données (V_CAMPUS_CLASSE)'!$A$3:$A$17,2026,'Données (V_CAMPUS_CLASSE)'!$B$3:$B$17,"ISCOM_PAR",'Données (V_CAMPUS_CLASSE)'!$D$3:$D$17,"MAS_COM",'Données (V_CAMPUS_CLASSE)'!$E$3:$E$17,"M1") | E22: =SUMIFS('Données (V_CAMPUS_CLASSE)'!$N$3:$N$17,'Données (V_CAMPUS_CLASSE)'!$A$3:$A$17,2026,'Données (V_CAMPUS_CLASSE)'!$B$3:$B$17,"ISCOM_PAR",'Données (V_CAMPUS_CLASSE)'!$D$3:$D$17,"MAS_COM",'Données (V_CAMPUS_CLASSE)'!$E$3:$E$17,"M1") | F22: =SUMIFS('Données (V_CAMPUS_CLASSE)'!$O$3:$O$17,'Données (V_CAMPUS_CLASSE)'!$A$3:$A$17,2026,'Données (V_CAMPUS_CLASSE)'!$B$3:$B$17,"ISCOM_PAR",'Données (V_CAMPUS_CLASSE)'!$D$3:$D$17,"MAS_COM",'Données (V_CAMPUS_CLASSE)'!$E$3:$E$17,"M1") | G22: =SUMIFS('Données (V_CAMPUS_CLASSE)'!$P$3:$P$17,'Données (V_CAMPUS_CLASSE)'!$A$3:$A$17,2026,'Données (V_CAMPUS_CLASSE)'!$B$3:$B$17,"ISCOM_PAR",'Données (V_CAMPUS_CLASSE)'!$D$3:$D$17,"MAS_COM",'Données (V_CAMPUS_CLASSE)'!$E$3:$E$17,"M1") | H22: =SUMIFS('Données (V_CAMPUS_CLASSE)'!$R$3:$R$17,'Données (V_CAMPUS_CLASSE)'!$A$3:$A$17,2026,'Données (V_CAMPUS_CLASSE)'!$B$3:$B$17,"ISCOM_PAR",'Données (V_CAMPUS_CLASSE)'!$D$3:$D$17,"MAS_COM",'Données (V_CAMPUS_CLASSE)'!$E$3:$E$17,"M1") | I22: =IF(G22<0,"🔴 piège",IF(B22>0.9,"⚠️ saturé","🟢 sain"))
A23: MAS_COM M2 | B23: =SUMIFS('Données (V_CAMPUS_CLASSE)'!$G$3:$G$17,'Données (V_CAMPUS_CLASSE)'!$A$3:$A$17,2026,'Données (V_CAMPUS_CLASSE)'!$B$3:$B$17,"ISCOM_PAR",'Données (V_CAMPUS_CLASSE)'!$D$3:$D$17,"MAS_COM",'Données (V_CAMPUS_CLASSE)'!$E$3:$E$17,"M2")/SUMIFS('Données (V_CAMPUS_CLASSE)'!$L$3:$L$17,'Données (V_CAMPUS_CLASSE)'!$A$3:$A$17,2026,'Données (V_CAMPUS_CLASSE)'!$B$3:$B$17,"ISCOM_PAR",'Données (V_CAMPUS_CLASSE)'!$D$3:$D$17,"MAS_COM",'Données (V_CAMPUS_CLASSE)'!$E$3:$E$17,"M2") | C23: =SUMIFS('Données (V_CAMPUS_CLASSE)'!$G$3:$G$17,'Données (V_CAMPUS_CLASSE)'!$A$3:$A$17,2026,'Données (V_CAMPUS_CLASSE)'!$B$3:$B$17,"ISCOM_PAR",'Données (V_CAMPUS_CLASSE)'!$D$3:$D$17,"MAS_COM",'Données (V_CAMPUS_CLASSE)'!$E$3:$E$17,"M2") | D23: =SUMIFS('Données (V_CAMPUS_CLASSE)'!$J$3:$J$17,'Données (V_CAMPUS_CLASSE)'!$A$3:$A$17,2026,'Données (V_CAMPUS_CLASSE)'!$B$3:$B$17,"ISCOM_PAR",'Données (V_CAMPUS_CLASSE)'!$D$3:$D$17,"MAS_COM",'Données (V_CAMPUS_CLASSE)'!$E$3:$E$17,"M2") | E23: =SUMIFS('Données (V_CAMPUS_CLASSE)'!$N$3:$N$17,'Données (V_CAMPUS_CLASSE)'!$A$3:$A$17,2026,'Données (V_CAMPUS_CLASSE)'!$B$3:$B$17,"ISCOM_PAR",'Données (V_CAMPUS_CLASSE)'!$D$3:$D$17,"MAS_COM",'Données (V_CAMPUS_CLASSE)'!$E$3:$E$17,"M2") | F23: =SUMIFS('Données (V_CAMPUS_CLASSE)'!$O$3:$O$17,'Données (V_CAMPUS_CLASSE)'!$A$3:$A$17,2026,'Données (V_CAMPUS_CLASSE)'!$B$3:$B$17,"ISCOM_PAR",'Données (V_CAMPUS_CLASSE)'!$D$3:$D$17,"MAS_COM",'Données (V_CAMPUS_CLASSE)'!$E$3:$E$17,"M2") | G23: =SUMIFS('Données (V_CAMPUS_CLASSE)'!$P$3:$P$17,'Données (V_CAMPUS_CLASSE)'!$A$3:$A$17,2026,'Données (V_CAMPUS_CLASSE)'!$B$3:$B$17,"ISCOM_PAR",'Données (V_CAMPUS_CLASSE)'!$D$3:$D$17,"MAS_COM",'Données (V_CAMPUS_CLASSE)'!$E$3:$E$17,"M2") | H23: =SUMIFS('Données (V_CAMPUS_CLASSE)'!$R$3:$R$17,'Données (V_CAMPUS_CLASSE)'!$A$3:$A$17,2026,'Données (V_CAMPUS_CLASSE)'!$B$3:$B$17,"ISCOM_PAR",'Données (V_CAMPUS_CLASSE)'!$D$3:$D$17,"MAS_COM",'Données (V_CAMPUS_CLASSE)'!$E$3:$E$17,"M2") | I23: =IF(G23<0,"🔴 piège",IF(B23>0.9,"⚠️ saturé","🟢 sain"))
A25: Le masque ne contient AUCUNE valeur en dur : tout est SUMIFS sur la vue V_CAMPUS_CLASSE (onglet Données). Sous Tagetik : la matrice pointe la vue, mêmes axes (ENTITY, EXERCICE, PROGRAMME, AN_ETUDE), mêmes mesures.
