Workbook

Sheet Le moteur
B1: EDUSERVICES · le moteur d'acquisition
B2: CALIBRATION & EFFET D'UN +Δ% — campus groupé par marque
B4: LE GESTE · la seule cellule à saisir | D4: Δ budget d'acquisition | F4: 0.08
B6: ="Je dépense "&TEXT(H58,"#,##0 €")&". J'encaisse "&TEXT(J58,"#,##0 €")&". Les servir coûte "&TEXT(I58*K58,"#,##0 €")&". Il me reste "&TEXT(L58,"#,##0 €")&"."
B9: JE DÉPENSE | E9: J'ENCAISSE | H9: LES SERVIR COÛTE | K9: IL ME RESTE | N9: PAR EURO INVESTI
B10: =H58 | E10: =J58 | H10: =I58*K58 | K10: =L58 | N10: =IFERROR(L58/H58,0)
B11: le Δ appliqué au budget 2026 | E11: les inscrits gagnés × le CA par inscrit | H11: consommables, et vacataire si une classe doit ouvrir | K11: d'EBITDA en plus, première année | N11: d'EBITDA pour un euro d'acquisition
B13: ="JUSQU'OÙ ? Le geste gagne "&TEXT(I58,"#,##0")&" inscrits pour "&TEXT(G58,"#,##0")&" places libres dans le réseau, soit "&TEXT(I58/G58,"0.0%")&" de la capacité disponible."
B14: La limite n'est pas économique — l'euro d'acquisition reste rentable très loin — elle est PHYSIQUE. Le modèle ne compte que le vacataire d'une classe qui ouvre ; il ne dit rien du jour où il faudrait un campus de plus.
B17: ① CE QUE LA VUE RESTITUE · V_MOTEUR_CAL, une ligne par campus, aucun calcul
B18: Ces dix-neuf colonnes sortent de la base. Elles sont additives : on peut les sommer, les filtrer, les remonter à la marque — rien n'y est un ratio.
B19: Marque | C19: Campus | D19: Leads payants 2024 | E19: Leads payants 2025 | F19: Leads payants 2026 | G19: Budget acq. 2024 | H19: Budget acq. 2025 | I19: Budget acq. 2026 | J19: Élasticité | K19: Leads totaux 2026 | L19: Inscrits 2026 | M19: CA nouveaux 2026 | N19: Effectifs 2026 | O19: Places 2026 | P19: Classes 2026 | Q19: Heures d'enseignement 2026 | R19: Consommables 604+6063 | S19: Vacataires 621 | T19: Enseignants permanents 6411
B20: Ipac Bachelor Factory | C20: Montpellier | D20: 377 | E20: 399 | F20: 422 | G20: 12543 | H20: 13798 | I20: 15178 | J20: 0.59134489 | K20: 680 | L20: 40 | M20: 269600 | N20: 117 | O20: 192 | P20: 6 | Q20: 2880 | R20: 43535 | S20: 72438 | T20: 136087.43
C21: Nantes | D21: 489 | E21: 516 | F21: 544 | G21: 17983 | H21: 19782 | I21: 21760 | J21: 0.55908079 | K21: 850 | L21: 50 | M21: 354500 | N21: 145 | O21: 192 | P21: 6 | Q21: 2880 | R21: 53954 | S21: 72438 | T21: 168182.73
C22: Rennes | D22: 371 | E22: 392 | F22: 415 | G22: 12341 | H22: 13575 | I22: 14933 | J22: 0.58787656 | K22: 680 | L22: 40 | M22: 269600 | N22: 117 | O22: 192 | P22: 6 | Q22: 2880 | R22: 43535 | S22: 72438 | T22: 136168.63
B23: ISCOM | C23: Lille | D23: 571 | E23: 600 | F23: 630 | G23: 20843 | H23: 22927 | I23: 25220 | J23: 0.51584831 | K23: 1260 | L23: 100 | M23: 744000 | N23: 244 | O23: 296 | P23: 10 | Q23: 4800 | R23: 90791 | S23: 120729 | T23: 284669.17
C24: Paris | D24: 1035 | E24: 1080 | F24: 1126 | G24: 50248 | H24: 55272 | I24: 60800 | J24: 0.44208627 | K24: 1816 | L24: 144 | M24: 1222560 | N24: 354 | O24: 444 | P24: 15 | Q24: 7200 | R24: 131722 | S24: 181094 | T24: 488050.48
C25: Toulouse | D25: 526 | E25: 553 | F25: 581 | G25: 18251 | H25: 20076 | I25: 22083 | J25: 0.52180337 | K25: 1186 | L25: 94 | M25: 685260 | N25: 231 | O25: 296 | P25: 10 | Q25: 4800 | R25: 85954 | S25: 120729 | T25: 267683.87
B26: MBway | C26: Bordeaux | D26: 592 | E26: 623 | F26: 656 | G26: 20597 | H26: 22657 | I26: 24923 | J26: 0.53845529 | K26: 1286 | L26: 102 | M26: 751230 | N26: 249 | O26: 296 | P26: 10 | Q26: 4800 | R26: 92652 | S26: 120729 | T26: 280337.09
C27: Lyon | D27: 863 | E27: 905 | F27: 950 | G27: 34532 | H27: 37985 | I27: 41783 | J27: 0.50391241 | K27: 1666 | L27: 132 | M27: 1051380 | N27: 324 | O27: 380 | P27: 13 | Q27: 6240 | R27: 120559 | S27: 156948 | T27: 400192.8
C28: Nantes | D28: 713 | E28: 749 | F28: 788 | G28: 26060 | H28: 28666 | I28: 31533 | J28: 0.52465564 | K28: 1516 | L28: 120 | M28: 910800 | N28: 294 | O28: 348 | P28: 12 | Q28: 5640 | R28: 109396 | S28: 144875 | T28: 344252.4
C29: Paris | D29: 1158 | E29: 1210 | F29: 1265 | G29: 56438 | H29: 62082 | I29: 68291 | J29: 0.46359595 | K29: 1976 | L29: 156 | M29: 1324440 | N29: 382 | O29: 444 | P29: 15 | Q29: 7200 | R29: 142140 | S29: 181094 | T29: 502062.96
B30: Pigier | C30: Bordeaux | D30: 528 | E30: 552 | F30: 578 | G30: 18155 | H30: 19971 | I30: 21968 | J30: 0.47459663 | K30: 1230 | L30: 72 | M30: 460440 | N30: 176 | O30: 312 | P30: 10 | Q30: 5680 | R30: 52838 | S30: 96583 | T30: 182756.35
C31: Lyon | D31: 765 | E31: 798 | F31: 832 | G31: 30258 | H31: 33284 | I31: 36612 | J31: 0.44045026 | K31: 1570 | L31: 92 | M31: 636180 | N31: 226 | O31: 312 | P31: 10 | Q31: 5680 | R31: 67722 | S31: 96583 | T31: 241308.7
B32: Tunon | C32: Lyon | D32: 392 | E32: 410 | F32: 428 | G32: 15578 | H32: 17136 | I32: 18850 | J32: 0.46084356 | K32: 680 | L32: 40 | M32: 297600 | N32: 117 | O32: 192 | P32: 6 | Q32: 2880 | R32: 43535 | S32: 72438 | T32: 185947.72
C33: Paris | D33: 517 | E33: 538 | F33: 560 | G33: 24992 | H33: 27491 | I33: 30240 | J33: 0.41914907 | K33: 800 | L33: 47 | M33: 372710 | N33: 138 | O33: 192 | P33: 6 | Q33: 2880 | R33: 51349 | S33: 72438 | T33: 223369.51
B34: GROUPE | C34: 14 campus | D34: =SUM(D20:D33) | E34: =SUM(E20:E33) | F34: =SUM(F20:F33) | G34: =SUM(G20:G33) | H34: =SUM(H20:H33) | I34: =SUM(I20:I33) | J34: — | K34: =SUM(K20:K33) | L34: =SUM(L20:L33) | M34: =SUM(M20:M33) | N34: =SUM(N20:N33) | O34: =SUM(O20:O33) | P34: =SUM(P20:P33) | Q34: =SUM(Q20:Q33) | R34: =SUM(R20:R33) | ... T34: =SUM(T20:T33)
B41: ② CE QUE LE MASQUE CALCULE · chaque formule pointe une cellule du tableau ①
B42: Rien n'est stocké ici. Cliquez une cellule : la formule remonte au tableau du dessus, et la seule saisie du classeur est F4.
B43: Marque | C43: Campus | D43: Conversion lead → inscrit | E43: CA par inscrit | F43: Consommables / élève | G43: Places libres | H43: Δ budget | I43: Inscrits gagnés | J43: CA gagné | K43: Coût marginal / élève | L43: EBITDA gagné | M43: CAC marginal
B44: Ipac Bachelor Factory | C44: =C20 | D44: =IFERROR(L20/K20,0) | E44: =IFERROR(M20/L20,0) | F44: =IFERROR(R20/N20,0) | G44: =O20-N20 | H44: =I20*$F$4 | I44: =F20*((1+$F$4)^J20-1)*D44 | J44: =I44*E44 | K44: =IF(I44<=G44,F44,F44+S20/O20) | L44: =J44-H44-I44*K44 | M44: =IFERROR(H44/I44,0)
C45: =C21 | D45: =IFERROR(L21/K21,0) | E45: =IFERROR(M21/L21,0) | F45: =IFERROR(R21/N21,0) | G45: =O21-N21 | H45: =I21*$F$4 | I45: =F21*((1+$F$4)^J21-1)*D45 | J45: =I45*E45 | K45: =IF(I45<=G45,F45,F45+S21/O21) | L45: =J45-H45-I45*K45 | M45: =IFERROR(H45/I45,0)
C46: =C22 | D46: =IFERROR(L22/K22,0) | E46: =IFERROR(M22/L22,0) | F46: =IFERROR(R22/N22,0) | G46: =O22-N22 | H46: =I22*$F$4 | I46: =F22*((1+$F$4)^J22-1)*D46 | J46: =I46*E46 | K46: =IF(I46<=G46,F46,F46+S22/O22) | L46: =J46-H46-I46*K46 | M46: =IFERROR(H46/I46,0)
B47: ISCOM | C47: =C23 | D47: =IFERROR(L23/K23,0) | E47: =IFERROR(M23/L23,0) | F47: =IFERROR(R23/N23,0) | G47: =O23-N23 | H47: =I23*$F$4 | I47: =F23*((1+$F$4)^J23-1)*D47 | J47: =I47*E47 | K47: =IF(I47<=G47,F47,F47+S23/O23) | L47: =J47-H47-I47*K47 | M47: =IFERROR(H47/I47,0)
C48: =C24 | D48: =IFERROR(L24/K24,0) | E48: =IFERROR(M24/L24,0) | F48: =IFERROR(R24/N24,0) | G48: =O24-N24 | H48: =I24*$F$4 | I48: =F24*((1+$F$4)^J24-1)*D48 | J48: =I48*E48 | K48: =IF(I48<=G48,F48,F48+S24/O24) | L48: =J48-H48-I48*K48 | M48: =IFERROR(H48/I48,0)
C49: =C25 | D49: =IFERROR(L25/K25,0) | E49: =IFERROR(M25/L25,0) | F49: =IFERROR(R25/N25,0) | G49: =O25-N25 | H49: =I25*$F$4 | I49: =F25*((1+$F$4)^J25-1)*D49 | J49: =I49*E49 | K49: =IF(I49<=G49,F49,F49+S25/O25) | L49: =J49-H49-I49*K49 | M49: =IFERROR(H49/I49,0)
B50: MBway | C50: =C26 | D50: =IFERROR(L26/K26,0) | E50: =IFERROR(M26/L26,0) | F50: =IFERROR(R26/N26,0) | G50: =O26-N26 | H50: =I26*$F$4 | I50: =F26*((1+$F$4)^J26-1)*D50 | J50: =I50*E50 | K50: =IF(I50<=G50,F50,F50+S26/O26) | L50: =J50-H50-I50*K50 | M50: =IFERROR(H50/I50,0)
C51: =C27 | D51: =IFERROR(L27/K27,0) | E51: =IFERROR(M27/L27,0) | F51: =IFERROR(R27/N27,0) | G51: =O27-N27 | H51: =I27*$F$4 | I51: =F27*((1+$F$4)^J27-1)*D51 | J51: =I51*E51 | K51: =IF(I51<=G51,F51,F51+S27/O27) | L51: =J51-H51-I51*K51 | M51: =IFERROR(H51/I51,0)
C52: =C28 | D52: =IFERROR(L28/K28,0) | E52: =IFERROR(M28/L28,0) | F52: =IFERROR(R28/N28,0) | G52: =O28-N28 | H52: =I28*$F$4 | I52: =F28*((1+$F$4)^J28-1)*D52 | J52: =I52*E52 | K52: =IF(I52<=G52,F52,F52+S28/O28) | L52: =J52-H52-I52*K52 | M52: =IFERROR(H52/I52,0)
C53: =C29 | D53: =IFERROR(L29/K29,0) | E53: =IFERROR(M29/L29,0) | F53: =IFERROR(R29/N29,0) | G53: =O29-N29 | H53: =I29*$F$4 | I53: =F29*((1+$F$4)^J29-1)*D53 | J53: =I53*E53 | K53: =IF(I53<=G53,F53,F53+S29/O29) | L53: =J53-H53-I53*K53 | M53: =IFERROR(H53/I53,0)
B54: Pigier | C54: =C30 | D54: =IFERROR(L30/K30,0) | E54: =IFERROR(M30/L30,0) | F54: =IFERROR(R30/N30,0) | G54: =O30-N30 | H54: =I30*$F$4 | I54: =F30*((1+$F$4)^J30-1)*D54 | J54: =I54*E54 | K54: =IF(I54<=G54,F54,F54+S30/O30) | L54: =J54-H54-I54*K54 | M54: =IFERROR(H54/I54,0)
C55: =C31 | D55: =IFERROR(L31/K31,0) | E55: =IFERROR(M31/L31,0) | F55: =IFERROR(R31/N31,0) | G55: =O31-N31 | H55: =I31*$F$4 | I55: =F31*((1+$F$4)^J31-1)*D55 | J55: =I55*E55 | K55: =IF(I55<=G55,F55,F55+S31/O31) | L55: =J55-H55-I55*K55 | M55: =IFERROR(H55/I55,0)
B56: Tunon | C56: =C32 | D56: =IFERROR(L32/K32,0) | E56: =IFERROR(M32/L32,0) | F56: =IFERROR(R32/N32,0) | G56: =O32-N32 | H56: =I32*$F$4 | I56: =F32*((1+$F$4)^J32-1)*D56 | J56: =I56*E56 | K56: =IF(I56<=G56,F56,F56+S32/O32) | L56: =J56-H56-I56*K56 | M56: =IFERROR(H56/I56,0)
C57: =C33 | D57: =IFERROR(L33/K33,0) | E57: =IFERROR(M33/L33,0) | F57: =IFERROR(R33/N33,0) | G57: =O33-N33 | H57: =I33*$F$4 | I57: =F33*((1+$F$4)^J33-1)*D57 | J57: =I57*E57 | K57: =IF(I57<=G57,F57,F57+S33/O33) | L57: =J57-H57-I57*K57 | M57: =IFERROR(H57/I57,0)
B58: GROUPE | C58: 14 campus | D58: =IFERROR(L34/K34,0) | E58: =IFERROR(M34/L34,0) | F58: =IFERROR(R34/N34,0) | G58: =SUM(G44:G57) | H58: =SUM(H44:H57) | I58: =SUM(I44:I57) | J58: =SUM(J44:J57) | K58: =IFERROR(SUMPRODUCT(I44:I57,K44:K57)/I58,0) | L58: =SUM(L44:L57) | M58: =IFERROR(H58/I58,0)
B60: Lecture des fonds : bleu = restitué par la vue, ocre = calculé par le masque, sable = paramètre du modèle. Un coût marginal en rouge signale un campus où la classe doit ouvrir.

Sheet Le coût variable
B1: EDUSERVICES · le moteur d'acquisition
B2: LE COÛT VARIABLE — pourquoi il ne peut pas être un nombre
B5: La comptabilité ne connaît pas le programme.
B6: AW_002_000004_000001 est au grain CAMPUS × COMPTE. Un coût par élève et par programme ne se lit donc pas : il s'alloue. V_ALLOCATION le fait déjà, avec des clés différentes selon la nature de la charge — et c'est de là que vient tout le reste.
B8: ① Trois poches d'enseignement, trois comportements
B9: Le même euro de charge ne se répartit pas de la même façon, et surtout ne réagit pas de la même façon quand un élève de plus arrive.
B11: Poche | C11: Comptes | D11: Montant 2026 | E11: Clé d'allocation | F11: Varie avec | G11: Comportement | H11: Bouge si un élève de plus arrive ?
B12: Consommables | C12: 604 + 6063 | D12: ='Le moteur'!R34 | E12: EFFECTIFS | F12: le campus | G12: VARIABLE | H12: OUI — c'est le seul euro qui suit vraiment l'élève
B13: Vacataires | C13: 621 | D13: ='Le moteur'!S34 | E13: HEURES | F13: le programme | G13: SEMI-VARIABLE | H13: Seulement si la classe doit ouvrir
B14: Enseignants permanents | C14: 6411 | D14: ='Le moteur'!T34 | E14: HEURES | F14: le nombre de postes | G14: CAPACITÉ | H14: NON — payé pareil pour 24 ou 32 élèves dans la salle
B15: Les heures d'une classe dépendent du programme : un BTS en initial pèse 1 000 heures, un Mastère en alternance 420. La clé EFFECTIFS, elle, ne distingue rien à l'intérieur d'un campus — par construction.
B18: ② Le coût variable MOYEN, au grain cycle × modalité
B19: Ce que coûte un élève déjà inscrit, vacataire et consommables. Chaque ligne est une réalité du réseau ; la moyenne, elle, n'est nulle part. Le tarif horaire est déduit du réel : 621 ÷ heures.
B21: Cycle · modalité | C21: Effectifs 2026 | D21: Heures / élève | E21: Tarif horaire | F21: Vacataires / élève | G21: Consommables / élève | H21: Coût moyen / élève | I21: Écart à la moyenne
B22: Mastère · alternance | C22: 840 | D22: 18 | E22: =$E$26 | F22: =D22*E22 | G22: 372.09528 | H22: =F22+G22 | I22: =IFERROR(H22/$H$26-1,0)
B23: Bachelor · alternance | C23: 1688 | D23: 21.042654 | E23: =$E$26 | F23: =D23*E23 | G23: 361.83035 | H23: =F23+G23 | I23: =IFERROR(H23/$H$26-1,0)
B24: Bachelor · initial | C24: 424 | D24: 24.056604 | E24: =$E$26 | F24: =D24*E24 | G24: 372.09528 | H24: =F24+G24 | I24: =IFERROR(H24/$H$26-1,0)
B25: BTS · alternance | C25: 162 | D25: 34.567901 | E25: =$E$26 | F25: =D25*E25 | G25: 299.90076 | H25: =F25+G25 | I25: =IFERROR(H25/$H$26-1,0)
B26: MOYENNE PONDÉRÉE | C26: =SUM(C22:C25) | D26: =IFERROR('Le moteur'!Q34/C26,0) | E26: =IFERROR('Le moteur'!S34/'Le moteur'!Q34,0) | F26: =D26*E26 | G26: =IFERROR(SUMPRODUCT(C22:C25,G22:G25)/C26,0) | H26: =F26+G26 | I26: —
B28: ="Un facteur "&TEXT(MAX(H22:H25)/MIN(H22:H25),"0.00")&" entre les extrêmes. Le coût variable « moyen » du réseau — "&TEXT(H26,"#,##0 €")&" — ne décrit aucun élève réel : il cadre, il ne décide pas."
B30: ③ Le coût d'enseignement campus par campus · ce qui suit l'élève, ce qui suit la classe, ce qui ne bouge pas
B31: Aucun montant n'est saisi ici : chaque euro pointe le tableau ① de l'onglet « Le moteur ». La colonne « quote-part vacataire / place » est exactement le terme que le masque ajoute quand une classe doit ouvrir.
B33: Campus | C33: Effectifs 2026 | D33: Places libres | E33: Consommables 604+6063 | F33: Consommables / élève | G33: Heures d'enseignement | H33: Vacataires 621 | I33: Quote-part vacataire / place | J33: Permanents 6411 | K33: Permanents / élève
B34: Ipac Bachelor Factory Montpellier | C34: ='Le moteur'!N20 | D34: ='Le moteur'!G44 | E34: ='Le moteur'!R20 | F34: =IFERROR(E34/C34,0) | G34: ='Le moteur'!Q20 | H34: ='Le moteur'!S20 | I34: =IFERROR(H34/'Le moteur'!O20,0) | J34: ='Le moteur'!T20 | K34: =IFERROR(J34/C34,0)
B35: Ipac Bachelor Factory Nantes | C35: ='Le moteur'!N21 | D35: ='Le moteur'!G45 | E35: ='Le moteur'!R21 | F35: =IFERROR(E35/C35,0) | G35: ='Le moteur'!Q21 | H35: ='Le moteur'!S21 | I35: =IFERROR(H35/'Le moteur'!O21,0) | J35: ='Le moteur'!T21 | K35: =IFERROR(J35/C35,0)
B36: Ipac Bachelor Factory Rennes | C36: ='Le moteur'!N22 | D36: ='Le moteur'!G46 | E36: ='Le moteur'!R22 | F36: =IFERROR(E36/C36,0) | G36: ='Le moteur'!Q22 | H36: ='Le moteur'!S22 | I36: =IFERROR(H36/'Le moteur'!O22,0) | J36: ='Le moteur'!T22 | K36: =IFERROR(J36/C36,0)
B37: ISCOM Lille | C37: ='Le moteur'!N23 | D37: ='Le moteur'!G47 | E37: ='Le moteur'!R23 | F37: =IFERROR(E37/C37,0) | G37: ='Le moteur'!Q23 | H37: ='Le moteur'!S23 | I37: =IFERROR(H37/'Le moteur'!O23,0) | J37: ='Le moteur'!T23 | K37: =IFERROR(J37/C37,0)
B38: ISCOM Paris | C38: ='Le moteur'!N24 | D38: ='Le moteur'!G48 | E38: ='Le moteur'!R24 | F38: =IFERROR(E38/C38,0) | G38: ='Le moteur'!Q24 | H38: ='Le moteur'!S24 | I38: =IFERROR(H38/'Le moteur'!O24,0) | J38: ='Le moteur'!T24 | K38: =IFERROR(J38/C38,0)
B39: ISCOM Toulouse | C39: ='Le moteur'!N25 | D39: ='Le moteur'!G49 | E39: ='Le moteur'!R25 | F39: =IFERROR(E39/C39,0) | G39: ='Le moteur'!Q25 | H39: ='Le moteur'!S25 | I39: =IFERROR(H39/'Le moteur'!O25,0) | J39: ='Le moteur'!T25 | K39: =IFERROR(J39/C39,0)
B40: MBway Bordeaux | C40: ='Le moteur'!N26 | D40: ='Le moteur'!G50 | E40: ='Le moteur'!R26 | F40: =IFERROR(E40/C40,0) | G40: ='Le moteur'!Q26 | H40: ='Le moteur'!S26 | I40: =IFERROR(H40/'Le moteur'!O26,0) | J40: ='Le moteur'!T26 | K40: =IFERROR(J40/C40,0)
B41: MBway Lyon | C41: ='Le moteur'!N27 | D41: ='Le moteur'!G51 | E41: ='Le moteur'!R27 | F41: =IFERROR(E41/C41,0) | G41: ='Le moteur'!Q27 | H41: ='Le moteur'!S27 | I41: =IFERROR(H41/'Le moteur'!O27,0) | J41: ='Le moteur'!T27 | K41: =IFERROR(J41/C41,0)
B42: MBway Nantes | C42: ='Le moteur'!N28 | D42: ='Le moteur'!G52 | E42: ='Le moteur'!R28 | F42: =IFERROR(E42/C42,0) | G42: ='Le moteur'!Q28 | H42: ='Le moteur'!S28 | I42: =IFERROR(H42/'Le moteur'!O28,0) | J42: ='Le moteur'!T28 | K42: =IFERROR(J42/C42,0)
B43: MBway Paris | C43: ='Le moteur'!N29 | D43: ='Le moteur'!G53 | E43: ='Le moteur'!R29 | F43: =IFERROR(E43/C43,0) | G43: ='Le moteur'!Q29 | H43: ='Le moteur'!S29 | I43: =IFERROR(H43/'Le moteur'!O29,0) | J43: ='Le moteur'!T29 | K43: =IFERROR(J43/C43,0)
B44: Pigier Bordeaux | C44: ='Le moteur'!N30 | D44: ='Le moteur'!G54 | E44: ='Le moteur'!R30 | F44: =IFERROR(E44/C44,0) | G44: ='Le moteur'!Q30 | H44: ='Le moteur'!S30 | I44: =IFERROR(H44/'Le moteur'!O30,0) | J44: ='Le moteur'!T30 | K44: =IFERROR(J44/C44,0)
B45: Pigier Lyon | C45: ='Le moteur'!N31 | D45: ='Le moteur'!G55 | E45: ='Le moteur'!R31 | F45: =IFERROR(E45/C45,0) | G45: ='Le moteur'!Q31 | H45: ='Le moteur'!S31 | I45: =IFERROR(H45/'Le moteur'!O31,0) | J45: ='Le moteur'!T31 | K45: =IFERROR(J45/C45,0)
... B47: Tunon Paris | C47: ='Le moteur'!N33 | D47: ='Le moteur'!G57 | E47: ='Le moteur'!R33 | F47: =IFERROR(E47/C47,0) | G47: ='Le moteur'!Q33 | H47: ='Le moteur'!S33 | I47: =IFERROR(H47/'Le moteur'!O33,0) | J47: ='Le moteur'!T33 | K47: =IFERROR(J47/C47,0)
B48: GROUPE · 14 campus | C48: =SUM(C34:C47) | D48: =SUM(D34:D47) | E48: =SUM(E34:E47) | F48: =IFERROR(E48/C48,0) | G48: =SUM(G34:G47) | H48: =SUM(H34:H47) | I48: =IFERROR(H48/'Le moteur'!O34,0) | J48: =SUM(J34:J47) | K48: =IFERROR(J48/C48,0)
B50: ="Les permanents pèsent "&TEXT(J48/(E48+H48+J48),"0 %")&" du coût d'enseignement du réseau, et pas un euro d'entre eux ne bouge quand un élève de plus s'assoit."
B52: ④ Mais ce n'est pas ce coût-là que le masque soustrait
B53: Le geste ajoute des élèves dans des classes qui existent déjà. Leur vacataire est déjà payé, leur professeur permanent aussi : ils ne coûtent pas un euro de plus. Le coût MARGINAL n'est donc pas le coût moyen.
B55: TANT QU'IL RESTE UNE PLACE | D55: ="les consommables seuls — de "&TEXT(MIN(F34:F47),"#,##0 €")&" à "&TEXT(MAX(F34:F47),"#,##0 €")&" selon le campus"
B56: QUAND LA CLASSE EST PLEINE | D56: + la quote-part du vacataire d'une classe neuve — et là, le programme compte
D57: Le masque bascule seul : IF(inscrits gagnés <= places libres ; consommables ; consommables + vacataires du campus ÷ places du campus).
B60: Programme qui ouvre | C60: Heures / classe | D60: Tarif horaire | E60: Coût du vacataire | F60: Capacité de la classe | G60: Coût d'ouverture / place | H60: + consommables ⇒ coût marginal
B61: Bachelor · alternance | C61: ='Intégration & contrôles'!C9 | D61: =$E$26 | E61: =C61*D61 | F61: ='Intégration & contrôles'!D9 | G61: =E61/F61 | H61: ="de "&TEXT(G61+MIN($F$34:$F$47),"#,##0 €")&" à "&TEXT(G61+MAX($F$34:$F$47),"#,##0 €")&" selon le campus"
B62: Mastère · alternance | C62: ='Intégration & contrôles'!C13 | D62: =$E$26 | E62: =C62*D62 | F62: ='Intégration & contrôles'!D13 | G62: =E62/F62 | H62: ="de "&TEXT(G62+MIN($F$34:$F$47),"#,##0 €")&" à "&TEXT(G62+MAX($F$34:$F$47),"#,##0 €")&" selon le campus"
B63: Bachelor · initial | C63: ='Intégration & contrôles'!C10 | D63: =$E$26 | E63: =C63*D63 | F63: ='Intégration & contrôles'!D10 | G63: =E63/F63 | H63: ="de "&TEXT(G63+MIN($F$34:$F$47),"#,##0 €")&" à "&TEXT(G63+MAX($F$34:$F$47),"#,##0 €")&" selon le campus"
B64: BTS · alternance | C64: ='Intégration & contrôles'!C11 | D64: =$E$26 | E64: =C64*D64 | F64: ='Intégration & contrôles'!D11 | G64: =E64/F64 | H64: ="de "&TEXT(G64+MIN($F$34:$F$47),"#,##0 €")&" à "&TEXT(G64+MAX($F$34:$F$47),"#,##0 €")&" selon le campus"
B66: Heures et capacités viennent de l'onglet « Intégration & contrôles » ; le tarif horaire de la ligne MOYENNE PONDÉRÉE ci-dessus. Rien n'est saisi dans ce tableau.
B68: ⑤ Et les enseignants permanents, ils sont où ?
B69: Dans le modèle, et alloués à l'heure comme les vacataires — mais pas dans le coût variable. Voici les vingt comptes de charges du P&L et, pour chacun, la seule question qui compte.
B70: Un professeur permanent est un ENGAGEMENT DE CAPACITÉ, pas un coût à l'élève : il est payé pareil que la salle contienne 24 ou 32 étudiants. C'est pour cela qu'il pèse le plus lourd du coût d'enseignement et qu'il ne figure quand même pas dans le coût marginal. Le vacataire, lui, est la seule ressource enseignante que l'on achète à la classe — et le 621 est du personnel EXTÉRIEUR : une facture, donc sans charges sociales 645 en plus.
B72: Ces montants sont restitués par la COMPTABILITÉ (AW_002_000004_000001), et non repris du tableau ① : c'est ce qui permet de les réconcilier avec la vue — quatre contrôles, onglet « Intégration & contrôles ».
B73: Compte et libellé | D73: Montant 2026 | E73: Part des charges | F73: Poche du modèle | G73: Clé d'allocation | H73: Comportement | I73: Bouge si un élève de plus arrive ?
B74: 604 · Achats d'études et supports pédagogiques | D74: 677808 | E74: =IFERROR(D74/$D$94,0) | F74: COST_ODIR | G74: EFFECTIFS | H74: Variable | I74: OUI
B75: 6063 · Fournitures pédagogiques et administratives | D75: 451874 | E75: =IFERROR(D75/$D$94,0) | F75: COST_ODIR | G75: EFFECTIFS | H75: Variable | I75: OUI
B76: 621 · Personnel extérieur — enseignants vacataires | D76: 1581554 | E76: =IFERROR(D76/$D$94,0) | F76: COST_VAC | G76: HEURES | H76: Semi-variable | I76: Seulement si une classe doit ouvrir
B77: 6411 · Salaires — enseignants permanents | D77: 3841069.8 | E77: =IFERROR(D77/$D$94,0) | F77: COST_PERM | G77: HEURES | H77: Capacité | I77: NON — le poste est engagé à l'année, pas à l'élève
B78: 6231 · Annonces et insertions — budget d'acquisition | D78: 434174 | E78: =IFERROR(D78/$D$94,0) | F78: COST_ODIR | G78: ENTRANTS | H78: Levier | I78: C'EST LA SAISIE — déjà soustrait comme Δ budget
B79: 6413 · Salaires — personnel administratif des campus | D79: 2033330.6 | E79: =IFERROR(D79/$D$94,0) | F79: COST_STRUCT | G79: K3 | H79: Structure | I79: NON
B80: 645 · Charges sociales sur les salaires | D80: 3162957.9 | E80: =IFERROR(D80/$D$94,0) | F80: COST_STRUCT | G80: K3 | H80: Structure | I80: NON — et 621 n'en porte pas : c'est une facture, pas une paie
B81: 613 · Locations immobilières des campus | D81: 2372423.5 | E81: =IFERROR(D81/$D$94,0) | F81: COST_STRUCT | G81: K3 | H81: Structure | I81: NON — c'est le mur qui coûte, pas l'élève
B82: 615 · Entretien et réparations | D82: 338915.38 | E82: =IFERROR(D82/$D$94,0) | F82: COST_STRUCT | G82: K3 | H82: Structure | I82: NON
B83: 616 · Primes d'assurance | D83: 225926.43 | E83: =IFERROR(D83/$D$94,0) | F83: COST_STRUCT | G83: K3 | H83: Structure | I83: NON
B84: 625 · Déplacements, missions et réceptions | D84: 338890.38 | E84: =IFERROR(D84/$D$94,0) | F84: COST_STRUCT | G84: K3 | H84: Structure | I84: NON
B85: 63511 · Contribution économique territoriale | D85: 225943.95 | E85: =IFERROR(D85/$D$94,0) | F85: COST_STRUCT | G85: K3 | H85: Structure | I85: NON
... B93: 6811 · Dotations aux amortissements | D93: 1352683 | E93: =IFERROR(D93/$D$94,0) | F93: hors modèle | G93: — | H93: Hors EBITDA | I93: NON — sous la ligne d'EBITDA
B94: TOTAL DES CHARGES 2026 · dotations incluses | D94: =SUM(D74:D93) | E94: 1
B95: Chiffre d'affaires 2026 · 706 + 7062 + 708 | D95: 23098985
B96: EBITDA 2026 = CA − charges hors dotations | D96: =D95-D94+D93
B98: ="Sur "&TEXT(D94,"#,##0 €")&" de charges, "&TEXT(D74+D75,"#,##0 €")&" seulement bougent quand un élève de plus s'assoit — soit "&TEXT((D74+D75)/D94,"0.0 %")&". Tout le reste est de la capacité déjà engagée : c'est précisément ce qui rend le geste d'acquisition aussi rentable tant qu'il reste des places."

Sheet Intégration & contrôles
B1: EDUSERVICES · le moteur d'acquisition
B2: INTÉGRATION TAGETIK & CONTRÔLES
B5: ⓐ Les paramètres du modèle · les seules hypothèses du classeur
B6: Elles ne sortent d'aucune vue : elles décrivent la maquette pédagogique. Fond sable = hypothèse. Changer une cellule ici change tout l'onglet « Le coût variable ».
B8: Programme | C8: Heures / classe | D8: Capacité de la classe | E8: Origine
B9: Bachelor · alternance | C9: 480 | D9: 32 | E9: maquette pédagogique
B10: Bachelor · initial | C10: 600 | D10: 32 | E10: maquette pédagogique
B11: BTS · alternance | C11: 700 | D11: 30 | E11: maquette pédagogique
B12: BTS · initial | C12: 1000 | D12: 30 | E12: maquette pédagogique (programme absent du réseau en 2026)
B13: Mastère · alternance | C13: 420 | D13: 26 | E13: maquette pédagogique
B14: Mastère · initial | C14: 520 | D14: 26 | E14: maquette pédagogique (programme absent du réseau en 2026)
B16: Le tarif horaire, lui, n'est PAS un paramètre : il se déduit du réel, compte 621 ÷ heures d'enseignement. Il vit dans l'onglet « Le coût variable ».
B18: ⓑ Le mapping · colonne du classeur ↔ colonne de V_MOTEUR_CAL
B19: Le tableau ① de l'onglet « Le moteur » est la vue, colonne pour colonne. Deux colonnes sont à ajouter à la vue — elles sont signalées en rouge, et tagetik/V_MOTEUR_CAL.sql les porte déjà.
B21: Colonne du classeur | C21: Colonne de la vue | D21: Nature | E21: Commentaire
B22: B · Marque | C22: MARQUE | D22: dimension | E22: regroupement d'affichage
B23: C · Campus | C23: CAMPUS | D23: dimension | E23: libellé azienda
B24: D · Leads payants 2024 | C24: LEAD_PAY_2024 | D24: mesure
B25: E · Leads payants 2025 | C25: LEAD_PAY_2025 | D25: mesure
B26: F · Leads payants 2026 | C26: LEAD_PAY_2026 | D26: mesure | E26: base du geste
B27: G · Budget acq. 2024 | C27: SPEND_ACQ_2024 | D27: mesure
B28: H · Budget acq. 2025 | C28: SPEND_ACQ_2025 | D28: mesure
B29: I · Budget acq. 2026 | C29: SPEND_ACQ_2026 | D29: mesure | E29: =compte 6231
B30: J · Élasticité | C30: ELASTICITE | D30: NON additive | E30: régression log-log, reste au campus
B31: K · Leads totaux 2026 | C31: LEAD_TOT_N | D31: mesure | E31: dénominateur de la conversion
B32: L · Inscrits 2026 | C32: INSCRITS_N | D32: mesure | E32: numérateur de la conversion
B33: M · CA nouveaux 2026 | C33: CA_NEW_N | D33: mesure
B34: N · Effectifs 2026 | C34: EFFECTIFS_N | D34: mesure
B35: O · Places 2026 | C35: PLACES_N | D35: mesure | E35: classes × capacité
B36: P · Classes 2026 | C36: CLASSES_N | D36: mesure
B37: Q · Heures d'enseignement 2026 | C37: HEURES_N | D37: mesure | E37: À AJOUTER À LA VUE
B38: R · Consommables 604+6063 | C38: COUT_CONSO_N | D38: mesure
B39: S · Vacataires 621 | C39: COUT_VACAT_N | D39: mesure
B40: T · Enseignants permanents 6411 | C40: COUT_PERM_N | D40: mesure | E40: À AJOUTER À LA VUE
B43: ⓒ Les formules du masque · la ligne 44, campus Ipac Montpellier
B44: Toutes les autres lignes sont la même formule, décalée. Aucune n'utilise de constante : chacune pointe le tableau ① ou la saisie F4.
B46: Mesure | C46: Col. | D46: Formule du classeur | F46: Ce qu'elle dit
B47: Δ budget d'acquisition | C47: F4 | D47: SAISIE | F47: la seule cellule modifiable du classeur
B48: Conversion lead → inscrit | C48: D | D48: =IFERROR(L20/K20,0) | F48: INSCRITS_N ÷ LEAD_TOT_N — jamais pré-calculée, sinon la ligne groupe se trompe
B49: CA par inscrit | C49: E | D49: =IFERROR(M20/L20,0) | F49: CA_NEW_N ÷ INSCRITS_N
B50: Consommables / élève | C50: F | D50: =IFERROR(R20/N20,0) | F50: COUT_CONSO_N ÷ EFFECTIFS_N
B51: Places libres | C51: G | D51: =O20-N20 | F51: PLACES_N − EFFECTIFS_N : la borne physique du geste
B52: Δ budget | C52: H | D52: =I20*$F$4 | F52: le geste, appliqué au budget 2026
B53: Inscrits gagnés | C53: I | D53: =F20*((1+$F$4)^J20-1)*D44 | F53: leads payants × l'effet d'élasticité, converti au taux du campus
B54: CA gagné | C54: J | D54: =I44*E44 | F54: inscrits gagnés × CA par inscrit
B55: Coût marginal / élève | C55: K | D55: =IF(I44<=G44,F44,F44+S20/O20) | F55: consommables seuls, + quote-part vacataire si la classe doit ouvrir
B56: EBITDA gagné | C56: L | D56: =J44-H44-I44*K44 | F56: CA gagné − Δ budget − coût de service
B57: CAC marginal | C57: M | D57: =IFERROR(H44/I44,0) | F57: Δ budget ÷ inscrits gagnés
B60: ⓓ Les contrôles · ils doivent tous valoir zéro
B61: Chacun confronte deux sources indépendantes. Le dernier n'est pas un écart mais une marge : il dit combien de sièges restent avant que le coût marginal ne bascule.
B63: Contrôle | D63: Source A | E63: Source B | F63: Écart | G63: Statut | H63: Ce qui est comparé
B64: Budget d'acquisition : dépense CRM 2026 = compte 6231 | D64: ='Le moteur'!I34 | E64: ='Le coût variable'!D78 | F64: =D64-E64 | G64: =IF(ABS(F64)<1,"OK","À VÉRIFIER") | H64: socle CRM contre comptabilité
B65: Consommables : comptes 604 + 6063 = COUT_CONSO_N | D65: ='Le coût variable'!D74+'Le coût variable'!D75 | E65: ='Le moteur'!R34 | F65: =D65-E65 | G65: =IF(ABS(F65)<1,"OK","À VÉRIFIER") | H65: comptes contre agrégat de la vue
B66: Vacataires : compte 621 = COUT_VACAT_N | D66: ='Le coût variable'!D76 | E66: ='Le moteur'!S34 | F66: =D66-E66 | G66: =IF(ABS(F66)<1,"OK","À VÉRIFIER") | H66: comptes contre agrégat de la vue
B67: Permanents : compte 6411 = COUT_PERM_N | D67: ='Le coût variable'!D77 | E67: ='Le moteur'!T34 | F67: =D67-E67 | G67: =IF(ABS(F67)<1,"OK","À VÉRIFIER") | H67: comptes contre agrégat de la vue
B68: Effectifs : grain programme = grain campus | D68: ='Le coût variable'!C26 | E68: ='Le moteur'!N34 | F68: =D68-E68 | G68: =IF(ABS(F68)<1,"OK","À VÉRIFIER") | H68: cycle × modalité contre campus
B69: Allocation : consommables alloués aux programmes = total réseau | D69: =SUMPRODUCT('Le coût variable'!C22:C25,'Le coût variable'!G22:G25) | E69: ='Le moteur'!R34 | F69: =D69-E69 | G69: =IF(ABS(F69)<1,"OK","À VÉRIFIER") | H69: la clé EFFECTIFS ne perd rien
B70: EBITDA gagné : CA gagné − Δ budget − coût de service | D70: ='Le moteur'!J58-'Le moteur'!H58-'Le moteur'!I58*'Le moteur'!K58 | E70: ='Le moteur'!L58 | F70: =D70-E70 | G70: =IF(ABS(F70)<1,"OK","À VÉRIFIER") | H70: additivité de la ligne groupe
B71: Régime du coût marginal : inscrits gagnés ≤ places libres | D71: ='Le moteur'!I58 | E71: ='Le moteur'!G58 | F71: =E71-D71 | G71: =IF(F71>0,"OK · marge","BASCULE") | H71: si dépassé, une classe ouvre
B74: Ce qu'il reste à faire côté Tagetik
B75: ① ajouter HEURES_N et COUT_PERM_N à V_MOTEUR_CAL (le .sql du dépôt les porte). ② brancher le tableau ① sur la vue, une ligne par campus, hiérarchie MARQUE ▸ CAMPUS. ③ le tableau ② est un masque de saisie : seule F4 est ouverte. ④ l'onglet « Le coût variable » ne lit que le tableau ① et les paramètres ci-dessus.
