Workbook

Sheet La méthode
B1: COMMENT LA PROJECTION EST CONSTRUITE
B2: Une seule relation, mesurée sur trois exercices — et ce qu'elle permet de dire
B4: 1 | C4: On ne prévoit pas, on construit | D4: Personne ne devine le nombre d'inscrits de 2027. On part de 2026 et on applique ce que l'historique a mesuré. Deux entrées seulement : le budget marketing, décidé au siège, et les effectifs déjà inscrits, qui poursuivent leur cursus.
B5: 2 | C5: Ce que dit l'historique : une élasticité | D5: Sur 2024-2026, le budget marketing a crû de +13,7 % par an, les inscrits de +6,1 %. Le rapport de ces deux croissances, mesuré en logarithmes, vaut 0,46 sur les totaux du groupe. Autrement dit : +1 % de budget donne +0,46 % d'inscrits. Ce n'est pas une hypothèse posée, c'est une pente relevée sur les comptes — et elle est relevée séparément pour chacun des 14 campus, parce que c'est au campus que le budget se dépense.
B6: 3 | C6: Pourquoi ce rendement décroît | D6: Parce qu'on n'achète pas des inscrits : on achète de l'audience, sur un marché fini, par enchères. Les contacts les moins chers sont pris en premier ; l'euro suivant va chercher des audiences plus larges et plus disputées. Le volume continue de monter, moins vite que la dépense.
B7: 4 | C7: Ce qu'on n'a PAS eu à supposer | D7: Le taux de transformation d'un contact en inscrit est passé de 7,135 % à 7,147 % en trois ans. Sur les 137 inscrits gagnés, 98,5 % viennent du volume de contacts et 1,5 % de la transformation. Le tenir constant ne relève d'aucune hypothèse. Et c'est pour cela qu'il ne faut surtout pas le remultiplier : il est déjà contenu dans l'élasticité.
B8: 5 | C8: Le marketing n'agit que sur les entrants | D8: Les inscrits entrent en première année. Les autres années viennent des cohortes déjà là, qui ne doivent rien au budget de l'exercice. Les entrants pèsent 39,5 % de l'effectif : un moteur qui ferait bouger tout l'effectif avec le budget se tromperait d'un facteur deux et demi.
B9: 6 | C9: Puis le compte d'exploitation | D9: L'effectif rencontre le tarif et donne le chiffre d'affaires. Les charges variables — vacataires, achats d'études, fournitures — le suivent, à 11,74 %. Le reste est tenu constant. Et le budget marketing se retranche : c'est un levier, mais c'est aussi une charge.
B10: 7 | C10: Et la preuve | D10: On cale l'élasticité sur 2024 et 2025 uniquement. On lui donne le budget 2026, qu'elle n'a jamais vu. Elle rend 1 232 inscrits ; il y en a eu 1 229. Écart : +0,25 %. Par campus, écart moyen 1,06 %, maximum 2,28 %.
B12: LA RELATION, ÉCRITE EN ENTIER
C13: inscrits 2027 | D13: =" = inscrits 2026 × ( budget marketing 2027 ÷ budget marketing 2026 ) ^ "&TEXT(Historique!$M$25,"0.00")
D14: ="et rien d'autre : le taux de transformation est déjà dans l'exposant. L'élasticité est propre à chaque campus, de "&TEXT(MIN(Historique!$AB$6:$AB$24),"0.00")&" à "&TEXT(MAX(Historique!$AB$6:$AB$24),"0.00")&" ; elle vaut "&TEXT(Historique!$M$25,"0.00")&" sur les totaux du groupe."
B16: PUIS, JUSQU'À L'EBITDA
D17: chiffre d'affaires = effectif × tarif
D18: charges variables = chiffre d'affaires × 11,74 %
D19: EBITDA = chiffre d'affaires − variables − budget marketing − structure

Sheet Le moteur
B1: LE MOTEUR — DU BUDGET MARKETING À L'EBITDA
B2: Deux gestes, une élasticité mesurée, et la chaîne complète
B4: LE GESTE
B5: Δ budget marketing 2027 | D5: 0.137 | E5: ← la tendance des trois derniers exercices
B6: Δ tarif 2027 | D6: 0.0029 | E6: ← le levier prix du cadrage V01
B7: Sur chaque ligne campus : inscrits 2027 = inscrits 2026 × ( 1 + Δ budget marketing ) ^ élasticité du campus. Les lignes marque et la ligne groupe sont les sommes de leurs campus.
C8: CE QUE VOUS DÉCIDEZ | G8: CE QUE ÇA DONNE | M8: LE CHIFFRE D'AFFAIRES | P8: L'EBITDA
B9: Marque · Campus | C9: Budget marketing 2026 | D9: Budget marketing 2027 | E9: Élasti- cité | G9: Inscrits 2026 | H9: Inscrits 2027 | I9: Δ | K9: Effectif 2026 | L9: Effectif 2027 | M9: CA 2026 | N9: CA 2027 | P9: EBITDA 2026 | Q9: EBITDA 2027 | R9: Δ EBITDA
B10: Ipac Bachelor Factory | C10: =$C11+$C12+$C13 | D10: =$D11+$D12+$D13 | E10: =SUMPRODUCT($E$11:$E$13,$G$11:$G$13)/SUM($G$11:$G$13) | G10: =$G11+$G12+$G13 | H10: =$H11+$H12+$H13 | I10: =$I11+$I12+$I13 | K10: =$K11+$K12+$K13 | L10: =$L11+$L12+$L13 | M10: =$M11+$M12+$M13 | N10: =$N11+$N12+$N13 | P10: =$P11+$P12+$P13 | Q10: =$Q11+$Q12+$Q13 | R10: =$R11+$R12+$R13 | T10: MQ:Ipac Bachelor Factory | U10: =$U11+$U12+$U13 | V10: =$V11+$V12+$V13
B11: Montpellier | C11: =IF(LEFT($T11,3)="MQ:",SUMPRODUCT((Donnees!$B$4:$B$17=MID($T11,4,99))*1,Donnees!$F$4:$F$17),INDEX(Donnees!$F$4:$F$17,MATCH($T11,Donnees!$A$4:$A$17,0))) | D11: =$C11*(1+$D$5) | E11: =INDEX(Historique!$U$1:$U$200,MATCH($T11,Historique!$T$1:$T$200,0)) | G11: =IF(LEFT($T11,3)="MQ:",SUMPRODUCT((Donnees!$B$4:$B$17=MID($T11,4,99))*1,Donnees!$I$4:$I$17),INDEX(Donnees!$I$4:$I$17,MATCH($T11,Donnees!$A$4:$A$17,0))) | H11: =$G11*POWER(1+$D$5,$E11) | I11: =$H11-$G11 | K11: =IF(LEFT($T11,3)="MQ:",SUMPRODUCT((Donnees!$B$4:$B$17=MID($T11,4,99))*1,Donnees!$J$4:$J$17),INDEX(Donnees!$J$4:$J$17,MATCH($T11,Donnees!$A$4:$A$17,0))) | L11: =$K11+$I11 | M11: =IF(LEFT($T11,3)="MQ:",SUMPRODUCT((Donnees!$B$4:$B$17=MID($T11,4,99))*1,Donnees!$L$4:$L$17),INDEX(Donnees!$L$4:$L$17,MATCH($T11,Donnees!$A$4:$A$17,0))) | N11: =$L11*($M11/$K11)*(1+$D$6) | P11: =$M11-$U11-$C11-IF(LEFT($T11,3)="MQ:",SUMPRODUCT((Donnees!$B$4:$B$17=MID($T11,4,99))*1,Donnees!$N$4:$N$17),INDEX(Donnees!$N$4:$N$17,MATCH($T11,Donnees!$A$4:$A$17,0))) | Q11: =$N11-$V11-$D11-IF(LEFT($T11,3)="MQ:",SUMPRODUCT((Donnees!$B$4:$B$17=MID($T11,4,99))*1,Donnees!$N$4:$N$17),INDEX(Donnees!$N$4:$N$17,MATCH($T11,Donnees!$A$4:$A$17,0))) | R11: =$Q11-$P11 | T11: IPAC_MTP | U11: =IF(LEFT($T11,3)="MQ:",SUMPRODUCT((Donnees!$B$4:$B$17=MID($T11,4,99))*1,Donnees!$M$4:$M$17),INDEX(Donnees!$M$4:$M$17,MATCH($T11,Donnees!$A$4:$A$17,0))) | V11: =$U11*($N11/$M11)
B12: Nantes | C12: =IF(LEFT($T12,3)="MQ:",SUMPRODUCT((Donnees!$B$4:$B$17=MID($T12,4,99))*1,Donnees!$F$4:$F$17),INDEX(Donnees!$F$4:$F$17,MATCH($T12,Donnees!$A$4:$A$17,0))) | D12: =$C12*(1+$D$5) | E12: =INDEX(Historique!$U$1:$U$200,MATCH($T12,Historique!$T$1:$T$200,0)) | G12: =IF(LEFT($T12,3)="MQ:",SUMPRODUCT((Donnees!$B$4:$B$17=MID($T12,4,99))*1,Donnees!$I$4:$I$17),INDEX(Donnees!$I$4:$I$17,MATCH($T12,Donnees!$A$4:$A$17,0))) | H12: =$G12*POWER(1+$D$5,$E12) | I12: =$H12-$G12 | K12: =IF(LEFT($T12,3)="MQ:",SUMPRODUCT((Donnees!$B$4:$B$17=MID($T12,4,99))*1,Donnees!$J$4:$J$17),INDEX(Donnees!$J$4:$J$17,MATCH($T12,Donnees!$A$4:$A$17,0))) | L12: =$K12+$I12 | M12: =IF(LEFT($T12,3)="MQ:",SUMPRODUCT((Donnees!$B$4:$B$17=MID($T12,4,99))*1,Donnees!$L$4:$L$17),INDEX(Donnees!$L$4:$L$17,MATCH($T12,Donnees!$A$4:$A$17,0))) | N12: =$L12*($M12/$K12)*(1+$D$6) | P12: =$M12-$U12-$C12-IF(LEFT($T12,3)="MQ:",SUMPRODUCT((Donnees!$B$4:$B$17=MID($T12,4,99))*1,Donnees!$N$4:$N$17),INDEX(Donnees!$N$4:$N$17,MATCH($T12,Donnees!$A$4:$A$17,0))) | Q12: =$N12-$V12-$D12-IF(LEFT($T12,3)="MQ:",SUMPRODUCT((Donnees!$B$4:$B$17=MID($T12,4,99))*1,Donnees!$N$4:$N$17),INDEX(Donnees!$N$4:$N$17,MATCH($T12,Donnees!$A$4:$A$17,0))) | R12: =$Q12-$P12 | T12: IPAC_NAN | U12: =IF(LEFT($T12,3)="MQ:",SUMPRODUCT((Donnees!$B$4:$B$17=MID($T12,4,99))*1,Donnees!$M$4:$M$17),INDEX(Donnees!$M$4:$M$17,MATCH($T12,Donnees!$A$4:$A$17,0))) | V12: =$U12*($N12/$M12)
B13: Rennes | C13: =IF(LEFT($T13,3)="MQ:",SUMPRODUCT((Donnees!$B$4:$B$17=MID($T13,4,99))*1,Donnees!$F$4:$F$17),INDEX(Donnees!$F$4:$F$17,MATCH($T13,Donnees!$A$4:$A$17,0))) | D13: =$C13*(1+$D$5) | E13: =INDEX(Historique!$U$1:$U$200,MATCH($T13,Historique!$T$1:$T$200,0)) | G13: =IF(LEFT($T13,3)="MQ:",SUMPRODUCT((Donnees!$B$4:$B$17=MID($T13,4,99))*1,Donnees!$I$4:$I$17),INDEX(Donnees!$I$4:$I$17,MATCH($T13,Donnees!$A$4:$A$17,0))) | H13: =$G13*POWER(1+$D$5,$E13) | I13: =$H13-$G13 | K13: =IF(LEFT($T13,3)="MQ:",SUMPRODUCT((Donnees!$B$4:$B$17=MID($T13,4,99))*1,Donnees!$J$4:$J$17),INDEX(Donnees!$J$4:$J$17,MATCH($T13,Donnees!$A$4:$A$17,0))) | L13: =$K13+$I13 | M13: =IF(LEFT($T13,3)="MQ:",SUMPRODUCT((Donnees!$B$4:$B$17=MID($T13,4,99))*1,Donnees!$L$4:$L$17),INDEX(Donnees!$L$4:$L$17,MATCH($T13,Donnees!$A$4:$A$17,0))) | N13: =$L13*($M13/$K13)*(1+$D$6) | P13: =$M13-$U13-$C13-IF(LEFT($T13,3)="MQ:",SUMPRODUCT((Donnees!$B$4:$B$17=MID($T13,4,99))*1,Donnees!$N$4:$N$17),INDEX(Donnees!$N$4:$N$17,MATCH($T13,Donnees!$A$4:$A$17,0))) | Q13: =$N13-$V13-$D13-IF(LEFT($T13,3)="MQ:",SUMPRODUCT((Donnees!$B$4:$B$17=MID($T13,4,99))*1,Donnees!$N$4:$N$17),INDEX(Donnees!$N$4:$N$17,MATCH($T13,Donnees!$A$4:$A$17,0))) | R13: =$Q13-$P13 | T13: IPAC_REN | U13: =IF(LEFT($T13,3)="MQ:",SUMPRODUCT((Donnees!$B$4:$B$17=MID($T13,4,99))*1,Donnees!$M$4:$M$17),INDEX(Donnees!$M$4:$M$17,MATCH($T13,Donnees!$A$4:$A$17,0))) | V13: =$U13*($N13/$M13)
B14: ISCOM | C14: =$C15+$C16+$C17 | D14: =$D15+$D16+$D17 | E14: =SUMPRODUCT($E$15:$E$17,$G$15:$G$17)/SUM($G$15:$G$17) | G14: =$G15+$G16+$G17 | H14: =$H15+$H16+$H17 | I14: =$I15+$I16+$I17 | K14: =$K15+$K16+$K17 | L14: =$L15+$L16+$L17 | M14: =$M15+$M16+$M17 | N14: =$N15+$N16+$N17 | P14: =$P15+$P16+$P17 | Q14: =$Q15+$Q16+$Q17 | R14: =$R15+$R16+$R17 | T14: MQ:ISCOM | U14: =$U15+$U16+$U17 | V14: =$V15+$V16+$V17
B15: Lille | C15: =IF(LEFT($T15,3)="MQ:",SUMPRODUCT((Donnees!$B$4:$B$17=MID($T15,4,99))*1,Donnees!$F$4:$F$17),INDEX(Donnees!$F$4:$F$17,MATCH($T15,Donnees!$A$4:$A$17,0))) | D15: =$C15*(1+$D$5) | E15: =INDEX(Historique!$U$1:$U$200,MATCH($T15,Historique!$T$1:$T$200,0)) | G15: =IF(LEFT($T15,3)="MQ:",SUMPRODUCT((Donnees!$B$4:$B$17=MID($T15,4,99))*1,Donnees!$I$4:$I$17),INDEX(Donnees!$I$4:$I$17,MATCH($T15,Donnees!$A$4:$A$17,0))) | H15: =$G15*POWER(1+$D$5,$E15) | I15: =$H15-$G15 | K15: =IF(LEFT($T15,3)="MQ:",SUMPRODUCT((Donnees!$B$4:$B$17=MID($T15,4,99))*1,Donnees!$J$4:$J$17),INDEX(Donnees!$J$4:$J$17,MATCH($T15,Donnees!$A$4:$A$17,0))) | L15: =$K15+$I15 | M15: =IF(LEFT($T15,3)="MQ:",SUMPRODUCT((Donnees!$B$4:$B$17=MID($T15,4,99))*1,Donnees!$L$4:$L$17),INDEX(Donnees!$L$4:$L$17,MATCH($T15,Donnees!$A$4:$A$17,0))) | N15: =$L15*($M15/$K15)*(1+$D$6) | P15: =$M15-$U15-$C15-IF(LEFT($T15,3)="MQ:",SUMPRODUCT((Donnees!$B$4:$B$17=MID($T15,4,99))*1,Donnees!$N$4:$N$17),INDEX(Donnees!$N$4:$N$17,MATCH($T15,Donnees!$A$4:$A$17,0))) | Q15: =$N15-$V15-$D15-IF(LEFT($T15,3)="MQ:",SUMPRODUCT((Donnees!$B$4:$B$17=MID($T15,4,99))*1,Donnees!$N$4:$N$17),INDEX(Donnees!$N$4:$N$17,MATCH($T15,Donnees!$A$4:$A$17,0))) | R15: =$Q15-$P15 | T15: ISCOM_LIL | U15: =IF(LEFT($T15,3)="MQ:",SUMPRODUCT((Donnees!$B$4:$B$17=MID($T15,4,99))*1,Donnees!$M$4:$M$17),INDEX(Donnees!$M$4:$M$17,MATCH($T15,Donnees!$A$4:$A$17,0))) | V15: =$U15*($N15/$M15)
B16: Paris | C16: =IF(LEFT($T16,3)="MQ:",SUMPRODUCT((Donnees!$B$4:$B$17=MID($T16,4,99))*1,Donnees!$F$4:$F$17),INDEX(Donnees!$F$4:$F$17,MATCH($T16,Donnees!$A$4:$A$17,0))) | D16: =$C16*(1+$D$5) | E16: =INDEX(Historique!$U$1:$U$200,MATCH($T16,Historique!$T$1:$T$200,0)) | G16: =IF(LEFT($T16,3)="MQ:",SUMPRODUCT((Donnees!$B$4:$B$17=MID($T16,4,99))*1,Donnees!$I$4:$I$17),INDEX(Donnees!$I$4:$I$17,MATCH($T16,Donnees!$A$4:$A$17,0))) | H16: =$G16*POWER(1+$D$5,$E16) | I16: =$H16-$G16 | K16: =IF(LEFT($T16,3)="MQ:",SUMPRODUCT((Donnees!$B$4:$B$17=MID($T16,4,99))*1,Donnees!$J$4:$J$17),INDEX(Donnees!$J$4:$J$17,MATCH($T16,Donnees!$A$4:$A$17,0))) | L16: =$K16+$I16 | M16: =IF(LEFT($T16,3)="MQ:",SUMPRODUCT((Donnees!$B$4:$B$17=MID($T16,4,99))*1,Donnees!$L$4:$L$17),INDEX(Donnees!$L$4:$L$17,MATCH($T16,Donnees!$A$4:$A$17,0))) | N16: =$L16*($M16/$K16)*(1+$D$6) | P16: =$M16-$U16-$C16-IF(LEFT($T16,3)="MQ:",SUMPRODUCT((Donnees!$B$4:$B$17=MID($T16,4,99))*1,Donnees!$N$4:$N$17),INDEX(Donnees!$N$4:$N$17,MATCH($T16,Donnees!$A$4:$A$17,0))) | Q16: =$N16-$V16-$D16-IF(LEFT($T16,3)="MQ:",SUMPRODUCT((Donnees!$B$4:$B$17=MID($T16,4,99))*1,Donnees!$N$4:$N$17),INDEX(Donnees!$N$4:$N$17,MATCH($T16,Donnees!$A$4:$A$17,0))) | R16: =$Q16-$P16 | T16: ISCOM_PAR | U16: =IF(LEFT($T16,3)="MQ:",SUMPRODUCT((Donnees!$B$4:$B$17=MID($T16,4,99))*1,Donnees!$M$4:$M$17),INDEX(Donnees!$M$4:$M$17,MATCH($T16,Donnees!$A$4:$A$17,0))) | V16: =$U16*($N16/$M16)
B17: Toulouse | C17: =IF(LEFT($T17,3)="MQ:",SUMPRODUCT((Donnees!$B$4:$B$17=MID($T17,4,99))*1,Donnees!$F$4:$F$17),INDEX(Donnees!$F$4:$F$17,MATCH($T17,Donnees!$A$4:$A$17,0))) | D17: =$C17*(1+$D$5) | E17: =INDEX(Historique!$U$1:$U$200,MATCH($T17,Historique!$T$1:$T$200,0)) | G17: =IF(LEFT($T17,3)="MQ:",SUMPRODUCT((Donnees!$B$4:$B$17=MID($T17,4,99))*1,Donnees!$I$4:$I$17),INDEX(Donnees!$I$4:$I$17,MATCH($T17,Donnees!$A$4:$A$17,0))) | H17: =$G17*POWER(1+$D$5,$E17) | I17: =$H17-$G17 | K17: =IF(LEFT($T17,3)="MQ:",SUMPRODUCT((Donnees!$B$4:$B$17=MID($T17,4,99))*1,Donnees!$J$4:$J$17),INDEX(Donnees!$J$4:$J$17,MATCH($T17,Donnees!$A$4:$A$17,0))) | L17: =$K17+$I17 | M17: =IF(LEFT($T17,3)="MQ:",SUMPRODUCT((Donnees!$B$4:$B$17=MID($T17,4,99))*1,Donnees!$L$4:$L$17),INDEX(Donnees!$L$4:$L$17,MATCH($T17,Donnees!$A$4:$A$17,0))) | N17: =$L17*($M17/$K17)*(1+$D$6) | P17: =$M17-$U17-$C17-IF(LEFT($T17,3)="MQ:",SUMPRODUCT((Donnees!$B$4:$B$17=MID($T17,4,99))*1,Donnees!$N$4:$N$17),INDEX(Donnees!$N$4:$N$17,MATCH($T17,Donnees!$A$4:$A$17,0))) | Q17: =$N17-$V17-$D17-IF(LEFT($T17,3)="MQ:",SUMPRODUCT((Donnees!$B$4:$B$17=MID($T17,4,99))*1,Donnees!$N$4:$N$17),INDEX(Donnees!$N$4:$N$17,MATCH($T17,Donnees!$A$4:$A$17,0))) | R17: =$Q17-$P17 | T17: ISCOM_TLS | U17: =IF(LEFT($T17,3)="MQ:",SUMPRODUCT((Donnees!$B$4:$B$17=MID($T17,4,99))*1,Donnees!$M$4:$M$17),INDEX(Donnees!$M$4:$M$17,MATCH($T17,Donnees!$A$4:$A$17,0))) | V17: =$U17*($N17/$M17)
B18: MBway | C18: =$C19+$C20+$C21+$C22 | D18: =$D19+$D20+$D21+$D22 | E18: =SUMPRODUCT($E$19:$E$22,$G$19:$G$22)/SUM($G$19:$G$22) | G18: =$G19+$G20+$G21+$G22 | H18: =$H19+$H20+$H21+$H22 | I18: =$I19+$I20+$I21+$I22 | K18: =$K19+$K20+$K21+$K22 | L18: =$L19+$L20+$L21+$L22 | M18: =$M19+$M20+$M21+$M22 | N18: =$N19+$N20+$N21+$N22 | P18: =$P19+$P20+$P21+$P22 | Q18: =$Q19+$Q20+$Q21+$Q22 | R18: =$R19+$R20+$R21+$R22 | T18: MQ:MBway | U18: =$U19+$U20+$U21+$U22 | V18: =$V19+$V20+$V21+$V22
B19: Bordeaux | C19: =IF(LEFT($T19,3)="MQ:",SUMPRODUCT((Donnees!$B$4:$B$17=MID($T19,4,99))*1,Donnees!$F$4:$F$17),INDEX(Donnees!$F$4:$F$17,MATCH($T19,Donnees!$A$4:$A$17,0))) | D19: =$C19*(1+$D$5) | E19: =INDEX(Historique!$U$1:$U$200,MATCH($T19,Historique!$T$1:$T$200,0)) | G19: =IF(LEFT($T19,3)="MQ:",SUMPRODUCT((Donnees!$B$4:$B$17=MID($T19,4,99))*1,Donnees!$I$4:$I$17),INDEX(Donnees!$I$4:$I$17,MATCH($T19,Donnees!$A$4:$A$17,0))) | H19: =$G19*POWER(1+$D$5,$E19) | I19: =$H19-$G19 | K19: =IF(LEFT($T19,3)="MQ:",SUMPRODUCT((Donnees!$B$4:$B$17=MID($T19,4,99))*1,Donnees!$J$4:$J$17),INDEX(Donnees!$J$4:$J$17,MATCH($T19,Donnees!$A$4:$A$17,0))) | L19: =$K19+$I19 | M19: =IF(LEFT($T19,3)="MQ:",SUMPRODUCT((Donnees!$B$4:$B$17=MID($T19,4,99))*1,Donnees!$L$4:$L$17),INDEX(Donnees!$L$4:$L$17,MATCH($T19,Donnees!$A$4:$A$17,0))) | N19: =$L19*($M19/$K19)*(1+$D$6) | P19: =$M19-$U19-$C19-IF(LEFT($T19,3)="MQ:",SUMPRODUCT((Donnees!$B$4:$B$17=MID($T19,4,99))*1,Donnees!$N$4:$N$17),INDEX(Donnees!$N$4:$N$17,MATCH($T19,Donnees!$A$4:$A$17,0))) | Q19: =$N19-$V19-$D19-IF(LEFT($T19,3)="MQ:",SUMPRODUCT((Donnees!$B$4:$B$17=MID($T19,4,99))*1,Donnees!$N$4:$N$17),INDEX(Donnees!$N$4:$N$17,MATCH($T19,Donnees!$A$4:$A$17,0))) | R19: =$Q19-$P19 | T19: MBWAY_BOR | U19: =IF(LEFT($T19,3)="MQ:",SUMPRODUCT((Donnees!$B$4:$B$17=MID($T19,4,99))*1,Donnees!$M$4:$M$17),INDEX(Donnees!$M$4:$M$17,MATCH($T19,Donnees!$A$4:$A$17,0))) | V19: =$U19*($N19/$M19)
B20: Lyon | C20: =IF(LEFT($T20,3)="MQ:",SUMPRODUCT((Donnees!$B$4:$B$17=MID($T20,4,99))*1,Donnees!$F$4:$F$17),INDEX(Donnees!$F$4:$F$17,MATCH($T20,Donnees!$A$4:$A$17,0))) | D20: =$C20*(1+$D$5) | E20: =INDEX(Historique!$U$1:$U$200,MATCH($T20,Historique!$T$1:$T$200,0)) | G20: =IF(LEFT($T20,3)="MQ:",SUMPRODUCT((Donnees!$B$4:$B$17=MID($T20,4,99))*1,Donnees!$I$4:$I$17),INDEX(Donnees!$I$4:$I$17,MATCH($T20,Donnees!$A$4:$A$17,0))) | H20: =$G20*POWER(1+$D$5,$E20) | I20: =$H20-$G20 | K20: =IF(LEFT($T20,3)="MQ:",SUMPRODUCT((Donnees!$B$4:$B$17=MID($T20,4,99))*1,Donnees!$J$4:$J$17),INDEX(Donnees!$J$4:$J$17,MATCH($T20,Donnees!$A$4:$A$17,0))) | L20: =$K20+$I20 | M20: =IF(LEFT($T20,3)="MQ:",SUMPRODUCT((Donnees!$B$4:$B$17=MID($T20,4,99))*1,Donnees!$L$4:$L$17),INDEX(Donnees!$L$4:$L$17,MATCH($T20,Donnees!$A$4:$A$17,0))) | N20: =$L20*($M20/$K20)*(1+$D$6) | P20: =$M20-$U20-$C20-IF(LEFT($T20,3)="MQ:",SUMPRODUCT((Donnees!$B$4:$B$17=MID($T20,4,99))*1,Donnees!$N$4:$N$17),INDEX(Donnees!$N$4:$N$17,MATCH($T20,Donnees!$A$4:$A$17,0))) | Q20: =$N20-$V20-$D20-IF(LEFT($T20,3)="MQ:",SUMPRODUCT((Donnees!$B$4:$B$17=MID($T20,4,99))*1,Donnees!$N$4:$N$17),INDEX(Donnees!$N$4:$N$17,MATCH($T20,Donnees!$A$4:$A$17,0))) | R20: =$Q20-$P20 | T20: MBWAY_LYO | U20: =IF(LEFT($T20,3)="MQ:",SUMPRODUCT((Donnees!$B$4:$B$17=MID($T20,4,99))*1,Donnees!$M$4:$M$17),INDEX(Donnees!$M$4:$M$17,MATCH($T20,Donnees!$A$4:$A$17,0))) | V20: =$U20*($N20/$M20)
B21: Nantes | C21: =IF(LEFT($T21,3)="MQ:",SUMPRODUCT((Donnees!$B$4:$B$17=MID($T21,4,99))*1,Donnees!$F$4:$F$17),INDEX(Donnees!$F$4:$F$17,MATCH($T21,Donnees!$A$4:$A$17,0))) | D21: =$C21*(1+$D$5) | E21: =INDEX(Historique!$U$1:$U$200,MATCH($T21,Historique!$T$1:$T$200,0)) | G21: =IF(LEFT($T21,3)="MQ:",SUMPRODUCT((Donnees!$B$4:$B$17=MID($T21,4,99))*1,Donnees!$I$4:$I$17),INDEX(Donnees!$I$4:$I$17,MATCH($T21,Donnees!$A$4:$A$17,0))) | H21: =$G21*POWER(1+$D$5,$E21) | I21: =$H21-$G21 | K21: =IF(LEFT($T21,3)="MQ:",SUMPRODUCT((Donnees!$B$4:$B$17=MID($T21,4,99))*1,Donnees!$J$4:$J$17),INDEX(Donnees!$J$4:$J$17,MATCH($T21,Donnees!$A$4:$A$17,0))) | L21: =$K21+$I21 | M21: =IF(LEFT($T21,3)="MQ:",SUMPRODUCT((Donnees!$B$4:$B$17=MID($T21,4,99))*1,Donnees!$L$4:$L$17),INDEX(Donnees!$L$4:$L$17,MATCH($T21,Donnees!$A$4:$A$17,0))) | N21: =$L21*($M21/$K21)*(1+$D$6) | P21: =$M21-$U21-$C21-IF(LEFT($T21,3)="MQ:",SUMPRODUCT((Donnees!$B$4:$B$17=MID($T21,4,99))*1,Donnees!$N$4:$N$17),INDEX(Donnees!$N$4:$N$17,MATCH($T21,Donnees!$A$4:$A$17,0))) | Q21: =$N21-$V21-$D21-IF(LEFT($T21,3)="MQ:",SUMPRODUCT((Donnees!$B$4:$B$17=MID($T21,4,99))*1,Donnees!$N$4:$N$17),INDEX(Donnees!$N$4:$N$17,MATCH($T21,Donnees!$A$4:$A$17,0))) | R21: =$Q21-$P21 | T21: MBWAY_NAN | U21: =IF(LEFT($T21,3)="MQ:",SUMPRODUCT((Donnees!$B$4:$B$17=MID($T21,4,99))*1,Donnees!$M$4:$M$17),INDEX(Donnees!$M$4:$M$17,MATCH($T21,Donnees!$A$4:$A$17,0))) | V21: =$U21*($N21/$M21)
B22: Paris | C22: =IF(LEFT($T22,3)="MQ:",SUMPRODUCT((Donnees!$B$4:$B$17=MID($T22,4,99))*1,Donnees!$F$4:$F$17),INDEX(Donnees!$F$4:$F$17,MATCH($T22,Donnees!$A$4:$A$17,0))) | D22: =$C22*(1+$D$5) | E22: =INDEX(Historique!$U$1:$U$200,MATCH($T22,Historique!$T$1:$T$200,0)) | G22: =IF(LEFT($T22,3)="MQ:",SUMPRODUCT((Donnees!$B$4:$B$17=MID($T22,4,99))*1,Donnees!$I$4:$I$17),INDEX(Donnees!$I$4:$I$17,MATCH($T22,Donnees!$A$4:$A$17,0))) | H22: =$G22*POWER(1+$D$5,$E22) | I22: =$H22-$G22 | K22: =IF(LEFT($T22,3)="MQ:",SUMPRODUCT((Donnees!$B$4:$B$17=MID($T22,4,99))*1,Donnees!$J$4:$J$17),INDEX(Donnees!$J$4:$J$17,MATCH($T22,Donnees!$A$4:$A$17,0))) | L22: =$K22+$I22 | M22: =IF(LEFT($T22,3)="MQ:",SUMPRODUCT((Donnees!$B$4:$B$17=MID($T22,4,99))*1,Donnees!$L$4:$L$17),INDEX(Donnees!$L$4:$L$17,MATCH($T22,Donnees!$A$4:$A$17,0))) | N22: =$L22*($M22/$K22)*(1+$D$6) | P22: =$M22-$U22-$C22-IF(LEFT($T22,3)="MQ:",SUMPRODUCT((Donnees!$B$4:$B$17=MID($T22,4,99))*1,Donnees!$N$4:$N$17),INDEX(Donnees!$N$4:$N$17,MATCH($T22,Donnees!$A$4:$A$17,0))) | Q22: =$N22-$V22-$D22-IF(LEFT($T22,3)="MQ:",SUMPRODUCT((Donnees!$B$4:$B$17=MID($T22,4,99))*1,Donnees!$N$4:$N$17),INDEX(Donnees!$N$4:$N$17,MATCH($T22,Donnees!$A$4:$A$17,0))) | R22: =$Q22-$P22 | T22: MBWAY_PAR | U22: =IF(LEFT($T22,3)="MQ:",SUMPRODUCT((Donnees!$B$4:$B$17=MID($T22,4,99))*1,Donnees!$M$4:$M$17),INDEX(Donnees!$M$4:$M$17,MATCH($T22,Donnees!$A$4:$A$17,0))) | V22: =$U22*($N22/$M22)
B23: Pigier | C23: =$C24+$C25 | D23: =$D24+$D25 | E23: =SUMPRODUCT($E$24:$E$25,$G$24:$G$25)/SUM($G$24:$G$25) | G23: =$G24+$G25 | H23: =$H24+$H25 | I23: =$I24+$I25 | K23: =$K24+$K25 | L23: =$L24+$L25 | M23: =$M24+$M25 | N23: =$N24+$N25 | P23: =$P24+$P25 | Q23: =$Q24+$Q25 | R23: =$R24+$R25 | T23: MQ:Pigier | U23: =$U24+$U25 | V23: =$V24+$V25
B24: Bordeaux | C24: =IF(LEFT($T24,3)="MQ:",SUMPRODUCT((Donnees!$B$4:$B$17=MID($T24,4,99))*1,Donnees!$F$4:$F$17),INDEX(Donnees!$F$4:$F$17,MATCH($T24,Donnees!$A$4:$A$17,0))) | D24: =$C24*(1+$D$5) | E24: =INDEX(Historique!$U$1:$U$200,MATCH($T24,Historique!$T$1:$T$200,0)) | G24: =IF(LEFT($T24,3)="MQ:",SUMPRODUCT((Donnees!$B$4:$B$17=MID($T24,4,99))*1,Donnees!$I$4:$I$17),INDEX(Donnees!$I$4:$I$17,MATCH($T24,Donnees!$A$4:$A$17,0))) | H24: =$G24*POWER(1+$D$5,$E24) | I24: =$H24-$G24 | K24: =IF(LEFT($T24,3)="MQ:",SUMPRODUCT((Donnees!$B$4:$B$17=MID($T24,4,99))*1,Donnees!$J$4:$J$17),INDEX(Donnees!$J$4:$J$17,MATCH($T24,Donnees!$A$4:$A$17,0))) | L24: =$K24+$I24 | M24: =IF(LEFT($T24,3)="MQ:",SUMPRODUCT((Donnees!$B$4:$B$17=MID($T24,4,99))*1,Donnees!$L$4:$L$17),INDEX(Donnees!$L$4:$L$17,MATCH($T24,Donnees!$A$4:$A$17,0))) | N24: =$L24*($M24/$K24)*(1+$D$6) | P24: =$M24-$U24-$C24-IF(LEFT($T24,3)="MQ:",SUMPRODUCT((Donnees!$B$4:$B$17=MID($T24,4,99))*1,Donnees!$N$4:$N$17),INDEX(Donnees!$N$4:$N$17,MATCH($T24,Donnees!$A$4:$A$17,0))) | Q24: =$N24-$V24-$D24-IF(LEFT($T24,3)="MQ:",SUMPRODUCT((Donnees!$B$4:$B$17=MID($T24,4,99))*1,Donnees!$N$4:$N$17),INDEX(Donnees!$N$4:$N$17,MATCH($T24,Donnees!$A$4:$A$17,0))) | R24: =$Q24-$P24 | T24: PIGIER_BOR | U24: =IF(LEFT($T24,3)="MQ:",SUMPRODUCT((Donnees!$B$4:$B$17=MID($T24,4,99))*1,Donnees!$M$4:$M$17),INDEX(Donnees!$M$4:$M$17,MATCH($T24,Donnees!$A$4:$A$17,0))) | V24: =$U24*($N24/$M24)
B25: Lyon | C25: =IF(LEFT($T25,3)="MQ:",SUMPRODUCT((Donnees!$B$4:$B$17=MID($T25,4,99))*1,Donnees!$F$4:$F$17),INDEX(Donnees!$F$4:$F$17,MATCH($T25,Donnees!$A$4:$A$17,0))) | D25: =$C25*(1+$D$5) | E25: =INDEX(Historique!$U$1:$U$200,MATCH($T25,Historique!$T$1:$T$200,0)) | G25: =IF(LEFT($T25,3)="MQ:",SUMPRODUCT((Donnees!$B$4:$B$17=MID($T25,4,99))*1,Donnees!$I$4:$I$17),INDEX(Donnees!$I$4:$I$17,MATCH($T25,Donnees!$A$4:$A$17,0))) | H25: =$G25*POWER(1+$D$5,$E25) | I25: =$H25-$G25 | K25: =IF(LEFT($T25,3)="MQ:",SUMPRODUCT((Donnees!$B$4:$B$17=MID($T25,4,99))*1,Donnees!$J$4:$J$17),INDEX(Donnees!$J$4:$J$17,MATCH($T25,Donnees!$A$4:$A$17,0))) | L25: =$K25+$I25 | M25: =IF(LEFT($T25,3)="MQ:",SUMPRODUCT((Donnees!$B$4:$B$17=MID($T25,4,99))*1,Donnees!$L$4:$L$17),INDEX(Donnees!$L$4:$L$17,MATCH($T25,Donnees!$A$4:$A$17,0))) | N25: =$L25*($M25/$K25)*(1+$D$6) | P25: =$M25-$U25-$C25-IF(LEFT($T25,3)="MQ:",SUMPRODUCT((Donnees!$B$4:$B$17=MID($T25,4,99))*1,Donnees!$N$4:$N$17),INDEX(Donnees!$N$4:$N$17,MATCH($T25,Donnees!$A$4:$A$17,0))) | Q25: =$N25-$V25-$D25-IF(LEFT($T25,3)="MQ:",SUMPRODUCT((Donnees!$B$4:$B$17=MID($T25,4,99))*1,Donnees!$N$4:$N$17),INDEX(Donnees!$N$4:$N$17,MATCH($T25,Donnees!$A$4:$A$17,0))) | R25: =$Q25-$P25 | T25: PIGIER_LYO | U25: =IF(LEFT($T25,3)="MQ:",SUMPRODUCT((Donnees!$B$4:$B$17=MID($T25,4,99))*1,Donnees!$M$4:$M$17),INDEX(Donnees!$M$4:$M$17,MATCH($T25,Donnees!$A$4:$A$17,0))) | V25: =$U25*($N25/$M25)
B26: Tunon | C26: =$C27+$C28 | D26: =$D27+$D28 | E26: =SUMPRODUCT($E$27:$E$28,$G$27:$G$28)/SUM($G$27:$G$28) | G26: =$G27+$G28 | H26: =$H27+$H28 | I26: =$I27+$I28 | K26: =$K27+$K28 | L26: =$L27+$L28 | M26: =$M27+$M28 | N26: =$N27+$N28 | P26: =$P27+$P28 | Q26: =$Q27+$Q28 | R26: =$R27+$R28 | T26: MQ:Tunon | U26: =$U27+$U28 | V26: =$V27+$V28
B27: Lyon | C27: =IF(LEFT($T27,3)="MQ:",SUMPRODUCT((Donnees!$B$4:$B$17=MID($T27,4,99))*1,Donnees!$F$4:$F$17),INDEX(Donnees!$F$4:$F$17,MATCH($T27,Donnees!$A$4:$A$17,0))) | D27: =$C27*(1+$D$5) | E27: =INDEX(Historique!$U$1:$U$200,MATCH($T27,Historique!$T$1:$T$200,0)) | G27: =IF(LEFT($T27,3)="MQ:",SUMPRODUCT((Donnees!$B$4:$B$17=MID($T27,4,99))*1,Donnees!$I$4:$I$17),INDEX(Donnees!$I$4:$I$17,MATCH($T27,Donnees!$A$4:$A$17,0))) | H27: =$G27*POWER(1+$D$5,$E27) | I27: =$H27-$G27 | K27: =IF(LEFT($T27,3)="MQ:",SUMPRODUCT((Donnees!$B$4:$B$17=MID($T27,4,99))*1,Donnees!$J$4:$J$17),INDEX(Donnees!$J$4:$J$17,MATCH($T27,Donnees!$A$4:$A$17,0))) | L27: =$K27+$I27 | M27: =IF(LEFT($T27,3)="MQ:",SUMPRODUCT((Donnees!$B$4:$B$17=MID($T27,4,99))*1,Donnees!$L$4:$L$17),INDEX(Donnees!$L$4:$L$17,MATCH($T27,Donnees!$A$4:$A$17,0))) | N27: =$L27*($M27/$K27)*(1+$D$6) | P27: =$M27-$U27-$C27-IF(LEFT($T27,3)="MQ:",SUMPRODUCT((Donnees!$B$4:$B$17=MID($T27,4,99))*1,Donnees!$N$4:$N$17),INDEX(Donnees!$N$4:$N$17,MATCH($T27,Donnees!$A$4:$A$17,0))) | Q27: =$N27-$V27-$D27-IF(LEFT($T27,3)="MQ:",SUMPRODUCT((Donnees!$B$4:$B$17=MID($T27,4,99))*1,Donnees!$N$4:$N$17),INDEX(Donnees!$N$4:$N$17,MATCH($T27,Donnees!$A$4:$A$17,0))) | R27: =$Q27-$P27 | T27: TUNON_LYO | U27: =IF(LEFT($T27,3)="MQ:",SUMPRODUCT((Donnees!$B$4:$B$17=MID($T27,4,99))*1,Donnees!$M$4:$M$17),INDEX(Donnees!$M$4:$M$17,MATCH($T27,Donnees!$A$4:$A$17,0))) | V27: =$U27*($N27/$M27)
B28: Paris | C28: =IF(LEFT($T28,3)="MQ:",SUMPRODUCT((Donnees!$B$4:$B$17=MID($T28,4,99))*1,Donnees!$F$4:$F$17),INDEX(Donnees!$F$4:$F$17,MATCH($T28,Donnees!$A$4:$A$17,0))) | D28: =$C28*(1+$D$5) | E28: =INDEX(Historique!$U$1:$U$200,MATCH($T28,Historique!$T$1:$T$200,0)) | G28: =IF(LEFT($T28,3)="MQ:",SUMPRODUCT((Donnees!$B$4:$B$17=MID($T28,4,99))*1,Donnees!$I$4:$I$17),INDEX(Donnees!$I$4:$I$17,MATCH($T28,Donnees!$A$4:$A$17,0))) | H28: =$G28*POWER(1+$D$5,$E28) | I28: =$H28-$G28 | K28: =IF(LEFT($T28,3)="MQ:",SUMPRODUCT((Donnees!$B$4:$B$17=MID($T28,4,99))*1,Donnees!$J$4:$J$17),INDEX(Donnees!$J$4:$J$17,MATCH($T28,Donnees!$A$4:$A$17,0))) | L28: =$K28+$I28 | M28: =IF(LEFT($T28,3)="MQ:",SUMPRODUCT((Donnees!$B$4:$B$17=MID($T28,4,99))*1,Donnees!$L$4:$L$17),INDEX(Donnees!$L$4:$L$17,MATCH($T28,Donnees!$A$4:$A$17,0))) | N28: =$L28*($M28/$K28)*(1+$D$6) | P28: =$M28-$U28-$C28-IF(LEFT($T28,3)="MQ:",SUMPRODUCT((Donnees!$B$4:$B$17=MID($T28,4,99))*1,Donnees!$N$4:$N$17),INDEX(Donnees!$N$4:$N$17,MATCH($T28,Donnees!$A$4:$A$17,0))) | Q28: =$N28-$V28-$D28-IF(LEFT($T28,3)="MQ:",SUMPRODUCT((Donnees!$B$4:$B$17=MID($T28,4,99))*1,Donnees!$N$4:$N$17),INDEX(Donnees!$N$4:$N$17,MATCH($T28,Donnees!$A$4:$A$17,0))) | R28: =$Q28-$P28 | T28: TUNON_PAR | U28: =IF(LEFT($T28,3)="MQ:",SUMPRODUCT((Donnees!$B$4:$B$17=MID($T28,4,99))*1,Donnees!$M$4:$M$17),INDEX(Donnees!$M$4:$M$17,MATCH($T28,Donnees!$A$4:$A$17,0))) | V28: =$U28*($N28/$M28)
B29: GROUPE · avant siège | C29: =$C10+$C14+$C18+$C23+$C26 | D29: =$D10+$D14+$D18+$D23+$D26 | E29: =($E10*$G10+$E14*$G14+$E18*$G18+$E23*$G23+$E26*$G26)/($G10+$G14+$G18+$G23+$G26) | G29: =$G10+$G14+$G18+$G23+$G26 | H29: =$H10+$H14+$H18+$H23+$H26 | I29: =$I10+$I14+$I18+$I23+$I26 | K29: =$K10+$K14+$K18+$K23+$K26 | L29: =$L10+$L14+$L18+$L23+$L26 | M29: =$M10+$M14+$M18+$M23+$M26 | N29: =$N10+$N14+$N18+$N23+$N26 | P29: =$P10+$P14+$P18+$P23+$P26 | Q29: =$Q10+$Q14+$Q18+$Q23+$Q26 | R29: =$R10+$R14+$R18+$R23+$R26 | U29: =$U10+$U14+$U18+$U23+$U26 | V29: =$V10+$V14+$V18+$V23+$V26
B31: D'OÙ VIENT L'EFFET SUR L'EBITDA | K31: L'EBITDA DU RÉSEAU
B32: Chiffre d'affaires supplémentaire | H32: =$N29-$M29 | K32: EBITDA avant siège, 2026 | R32: =$P29
B33: dont les charges variables consomment | H33: =-($V29-$U29) | K33: Siège | R33: =-Donnees!$L$19
B34: Budget marketing supplémentaire | H34: =-($D29-$C29) | K34: = EBITDA réseau 2026 | R34: =$R32-Donnees!$L$19
B35: = EFFET SUR L'EBITDA | H35: =$R29 | K35: EBITDA réseau 2027 | R35: =$Q29-Donnees!$L$19
K36: écart | R36: =$R35-$R34
B38: Le marketing de 2027 n'agit que sur les ENTRANTS : les autres années viennent de cohortes déjà inscrites, qui ne doivent rien au budget de l'année. Les entrants pèsent 39,5 % de l'effectif.
B39: Les charges variables (621 vacataires, 604 achats d'études, 6063 fournitures) suivent le chiffre d'affaires — 11,74 % de celui-ci. Tout le reste est tenu constant : ce moteur porte sur le marketing et le tarif, pas sur les coûts.
B40: Le budget marketing est à la fois le levier et une charge. C'est pour cela que l'effet sur l'EBITDA n'est pas la marge sur le chiffre d'affaires supplémentaire, mais cette marge MOINS le budget engagé.
B41: L'élasticité vient de l'onglet « Historique », où elle est calculée par régression sur les trois exercices. Elle n'est recopiée nulle part.
B42: Le calcul se fait CAMPUS PAR CAMPUS : c'est là qu'une élasticité se mesure, et là que le budget se dépense. Les lignes marque et la ligne groupe sont des sommes — le masque s'additionne. L'élasticité qu'elles affichent n'est donc pas une pente mesurée : c'est la moyenne de leurs campus, pondérée par les inscrits.

Sheet Historique
B1: CE QUE DIT L'HISTORIQUE
B2: Trois exercices, deux colonnes, une pente — mesurée là où le budget se décide
B3: L'élasticité est la pente de ln(inscrits) sur ln(budget marketing), calculée par SLOPE sur les colonnes masquées V à AA. Rien n'est recopié.
B5: Marque · Campus | C5: Budget 2024 | D5: Budget 2025 | E5: Budget 2026 | G5: Inscrits 2024 | H5: Inscrits 2025 | I5: Inscrits 2026 | K5: Budget par an | L5: Inscrits par an | M5: ÉLASTICITÉ
B6: Ipac Bachelor Factory | C6: =IF(LEFT($T6,3)="MQ:",SUMPRODUCT((Donnees!$B$4:$B$17=MID($T6,4,99))*1,Donnees!$D$4:$D$17),INDEX(Donnees!$D$4:$D$17,MATCH($T6,Donnees!$A$4:$A$17,0))) | D6: =IF(LEFT($T6,3)="MQ:",SUMPRODUCT((Donnees!$B$4:$B$17=MID($T6,4,99))*1,Donnees!$E$4:$E$17),INDEX(Donnees!$E$4:$E$17,MATCH($T6,Donnees!$A$4:$A$17,0))) | E6: =IF(LEFT($T6,3)="MQ:",SUMPRODUCT((Donnees!$B$4:$B$17=MID($T6,4,99))*1,Donnees!$F$4:$F$17),INDEX(Donnees!$F$4:$F$17,MATCH($T6,Donnees!$A$4:$A$17,0))) | G6: =IF(LEFT($T6,3)="MQ:",SUMPRODUCT((Donnees!$B$4:$B$17=MID($T6,4,99))*1,Donnees!$G$4:$G$17),INDEX(Donnees!$G$4:$G$17,MATCH($T6,Donnees!$A$4:$A$17,0))) | H6: =IF(LEFT($T6,3)="MQ:",SUMPRODUCT((Donnees!$B$4:$B$17=MID($T6,4,99))*1,Donnees!$H$4:$H$17),INDEX(Donnees!$H$4:$H$17,MATCH($T6,Donnees!$A$4:$A$17,0))) | I6: =IF(LEFT($T6,3)="MQ:",SUMPRODUCT((Donnees!$B$4:$B$17=MID($T6,4,99))*1,Donnees!$I$4:$I$17),INDEX(Donnees!$I$4:$I$17,MATCH($T6,Donnees!$A$4:$A$17,0))) | K6: =POWER($E6/$C6,0.5)-1 | L6: =POWER($I6/$G6,0.5)-1 | M6: =$U6 | T6: MQ:Ipac Bachelor Factory | U6: =SLOPE($Y6:$AA6,$V6:$X6) | V6: =LN($C6) | W6: =LN($D6) | X6: =LN($E6) | Y6: =LN($G6) | Z6: =LN($H6) | AA6: =LN($I6) | AB6: =IF(LEFT($T6,3)="MQ:","",$U6)
B7: Montpellier | C7: =IF(LEFT($T7,3)="MQ:",SUMPRODUCT((Donnees!$B$4:$B$17=MID($T7,4,99))*1,Donnees!$D$4:$D$17),INDEX(Donnees!$D$4:$D$17,MATCH($T7,Donnees!$A$4:$A$17,0))) | D7: =IF(LEFT($T7,3)="MQ:",SUMPRODUCT((Donnees!$B$4:$B$17=MID($T7,4,99))*1,Donnees!$E$4:$E$17),INDEX(Donnees!$E$4:$E$17,MATCH($T7,Donnees!$A$4:$A$17,0))) | E7: =IF(LEFT($T7,3)="MQ:",SUMPRODUCT((Donnees!$B$4:$B$17=MID($T7,4,99))*1,Donnees!$F$4:$F$17),INDEX(Donnees!$F$4:$F$17,MATCH($T7,Donnees!$A$4:$A$17,0))) | G7: =IF(LEFT($T7,3)="MQ:",SUMPRODUCT((Donnees!$B$4:$B$17=MID($T7,4,99))*1,Donnees!$G$4:$G$17),INDEX(Donnees!$G$4:$G$17,MATCH($T7,Donnees!$A$4:$A$17,0))) | H7: =IF(LEFT($T7,3)="MQ:",SUMPRODUCT((Donnees!$B$4:$B$17=MID($T7,4,99))*1,Donnees!$H$4:$H$17),INDEX(Donnees!$H$4:$H$17,MATCH($T7,Donnees!$A$4:$A$17,0))) | I7: =IF(LEFT($T7,3)="MQ:",SUMPRODUCT((Donnees!$B$4:$B$17=MID($T7,4,99))*1,Donnees!$I$4:$I$17),INDEX(Donnees!$I$4:$I$17,MATCH($T7,Donnees!$A$4:$A$17,0))) | K7: =POWER($E7/$C7,0.5)-1 | L7: =POWER($I7/$G7,0.5)-1 | M7: =$U7 | T7: IPAC_MTP | U7: =SLOPE($Y7:$AA7,$V7:$X7) | V7: =LN($C7) | W7: =LN($D7) | X7: =LN($E7) | Y7: =LN($G7) | Z7: =LN($H7) | AA7: =LN($I7) | AB7: =IF(LEFT($T7,3)="MQ:","",$U7)
B8: Nantes | C8: =IF(LEFT($T8,3)="MQ:",SUMPRODUCT((Donnees!$B$4:$B$17=MID($T8,4,99))*1,Donnees!$D$4:$D$17),INDEX(Donnees!$D$4:$D$17,MATCH($T8,Donnees!$A$4:$A$17,0))) | D8: =IF(LEFT($T8,3)="MQ:",SUMPRODUCT((Donnees!$B$4:$B$17=MID($T8,4,99))*1,Donnees!$E$4:$E$17),INDEX(Donnees!$E$4:$E$17,MATCH($T8,Donnees!$A$4:$A$17,0))) | E8: =IF(LEFT($T8,3)="MQ:",SUMPRODUCT((Donnees!$B$4:$B$17=MID($T8,4,99))*1,Donnees!$F$4:$F$17),INDEX(Donnees!$F$4:$F$17,MATCH($T8,Donnees!$A$4:$A$17,0))) | G8: =IF(LEFT($T8,3)="MQ:",SUMPRODUCT((Donnees!$B$4:$B$17=MID($T8,4,99))*1,Donnees!$G$4:$G$17),INDEX(Donnees!$G$4:$G$17,MATCH($T8,Donnees!$A$4:$A$17,0))) | H8: =IF(LEFT($T8,3)="MQ:",SUMPRODUCT((Donnees!$B$4:$B$17=MID($T8,4,99))*1,Donnees!$H$4:$H$17),INDEX(Donnees!$H$4:$H$17,MATCH($T8,Donnees!$A$4:$A$17,0))) | I8: =IF(LEFT($T8,3)="MQ:",SUMPRODUCT((Donnees!$B$4:$B$17=MID($T8,4,99))*1,Donnees!$I$4:$I$17),INDEX(Donnees!$I$4:$I$17,MATCH($T8,Donnees!$A$4:$A$17,0))) | K8: =POWER($E8/$C8,0.5)-1 | L8: =POWER($I8/$G8,0.5)-1 | M8: =$U8 | T8: IPAC_NAN | U8: =SLOPE($Y8:$AA8,$V8:$X8) | V8: =LN($C8) | W8: =LN($D8) | X8: =LN($E8) | Y8: =LN($G8) | Z8: =LN($H8) | AA8: =LN($I8) | AB8: =IF(LEFT($T8,3)="MQ:","",$U8)
B9: Rennes | C9: =IF(LEFT($T9,3)="MQ:",SUMPRODUCT((Donnees!$B$4:$B$17=MID($T9,4,99))*1,Donnees!$D$4:$D$17),INDEX(Donnees!$D$4:$D$17,MATCH($T9,Donnees!$A$4:$A$17,0))) | D9: =IF(LEFT($T9,3)="MQ:",SUMPRODUCT((Donnees!$B$4:$B$17=MID($T9,4,99))*1,Donnees!$E$4:$E$17),INDEX(Donnees!$E$4:$E$17,MATCH($T9,Donnees!$A$4:$A$17,0))) | E9: =IF(LEFT($T9,3)="MQ:",SUMPRODUCT((Donnees!$B$4:$B$17=MID($T9,4,99))*1,Donnees!$F$4:$F$17),INDEX(Donnees!$F$4:$F$17,MATCH($T9,Donnees!$A$4:$A$17,0))) | G9: =IF(LEFT($T9,3)="MQ:",SUMPRODUCT((Donnees!$B$4:$B$17=MID($T9,4,99))*1,Donnees!$G$4:$G$17),INDEX(Donnees!$G$4:$G$17,MATCH($T9,Donnees!$A$4:$A$17,0))) | H9: =IF(LEFT($T9,3)="MQ:",SUMPRODUCT((Donnees!$B$4:$B$17=MID($T9,4,99))*1,Donnees!$H$4:$H$17),INDEX(Donnees!$H$4:$H$17,MATCH($T9,Donnees!$A$4:$A$17,0))) | I9: =IF(LEFT($T9,3)="MQ:",SUMPRODUCT((Donnees!$B$4:$B$17=MID($T9,4,99))*1,Donnees!$I$4:$I$17),INDEX(Donnees!$I$4:$I$17,MATCH($T9,Donnees!$A$4:$A$17,0))) | K9: =POWER($E9/$C9,0.5)-1 | L9: =POWER($I9/$G9,0.5)-1 | M9: =$U9 | T9: IPAC_REN | U9: =SLOPE($Y9:$AA9,$V9:$X9) | V9: =LN($C9) | W9: =LN($D9) | X9: =LN($E9) | Y9: =LN($G9) | Z9: =LN($H9) | AA9: =LN($I9) | AB9: =IF(LEFT($T9,3)="MQ:","",$U9)
B10: ISCOM | C10: =IF(LEFT($T10,3)="MQ:",SUMPRODUCT((Donnees!$B$4:$B$17=MID($T10,4,99))*1,Donnees!$D$4:$D$17),INDEX(Donnees!$D$4:$D$17,MATCH($T10,Donnees!$A$4:$A$17,0))) | D10: =IF(LEFT($T10,3)="MQ:",SUMPRODUCT((Donnees!$B$4:$B$17=MID($T10,4,99))*1,Donnees!$E$4:$E$17),INDEX(Donnees!$E$4:$E$17,MATCH($T10,Donnees!$A$4:$A$17,0))) | E10: =IF(LEFT($T10,3)="MQ:",SUMPRODUCT((Donnees!$B$4:$B$17=MID($T10,4,99))*1,Donnees!$F$4:$F$17),INDEX(Donnees!$F$4:$F$17,MATCH($T10,Donnees!$A$4:$A$17,0))) | G10: =IF(LEFT($T10,3)="MQ:",SUMPRODUCT((Donnees!$B$4:$B$17=MID($T10,4,99))*1,Donnees!$G$4:$G$17),INDEX(Donnees!$G$4:$G$17,MATCH($T10,Donnees!$A$4:$A$17,0))) | H10: =IF(LEFT($T10,3)="MQ:",SUMPRODUCT((Donnees!$B$4:$B$17=MID($T10,4,99))*1,Donnees!$H$4:$H$17),INDEX(Donnees!$H$4:$H$17,MATCH($T10,Donnees!$A$4:$A$17,0))) | I10: =IF(LEFT($T10,3)="MQ:",SUMPRODUCT((Donnees!$B$4:$B$17=MID($T10,4,99))*1,Donnees!$I$4:$I$17),INDEX(Donnees!$I$4:$I$17,MATCH($T10,Donnees!$A$4:$A$17,0))) | K10: =POWER($E10/$C10,0.5)-1 | L10: =POWER($I10/$G10,0.5)-1 | M10: =$U10 | T10: MQ:ISCOM | U10: =SLOPE($Y10:$AA10,$V10:$X10) | V10: =LN($C10) | W10: =LN($D10) | X10: =LN($E10) | Y10: =LN($G10) | Z10: =LN($H10) | AA10: =LN($I10) | AB10: =IF(LEFT($T10,3)="MQ:","",$U10)
B11: Lille | C11: =IF(LEFT($T11,3)="MQ:",SUMPRODUCT((Donnees!$B$4:$B$17=MID($T11,4,99))*1,Donnees!$D$4:$D$17),INDEX(Donnees!$D$4:$D$17,MATCH($T11,Donnees!$A$4:$A$17,0))) | D11: =IF(LEFT($T11,3)="MQ:",SUMPRODUCT((Donnees!$B$4:$B$17=MID($T11,4,99))*1,Donnees!$E$4:$E$17),INDEX(Donnees!$E$4:$E$17,MATCH($T11,Donnees!$A$4:$A$17,0))) | E11: =IF(LEFT($T11,3)="MQ:",SUMPRODUCT((Donnees!$B$4:$B$17=MID($T11,4,99))*1,Donnees!$F$4:$F$17),INDEX(Donnees!$F$4:$F$17,MATCH($T11,Donnees!$A$4:$A$17,0))) | G11: =IF(LEFT($T11,3)="MQ:",SUMPRODUCT((Donnees!$B$4:$B$17=MID($T11,4,99))*1,Donnees!$G$4:$G$17),INDEX(Donnees!$G$4:$G$17,MATCH($T11,Donnees!$A$4:$A$17,0))) | H11: =IF(LEFT($T11,3)="MQ:",SUMPRODUCT((Donnees!$B$4:$B$17=MID($T11,4,99))*1,Donnees!$H$4:$H$17),INDEX(Donnees!$H$4:$H$17,MATCH($T11,Donnees!$A$4:$A$17,0))) | I11: =IF(LEFT($T11,3)="MQ:",SUMPRODUCT((Donnees!$B$4:$B$17=MID($T11,4,99))*1,Donnees!$I$4:$I$17),INDEX(Donnees!$I$4:$I$17,MATCH($T11,Donnees!$A$4:$A$17,0))) | K11: =POWER($E11/$C11,0.5)-1 | L11: =POWER($I11/$G11,0.5)-1 | M11: =$U11 | T11: ISCOM_LIL | U11: =SLOPE($Y11:$AA11,$V11:$X11) | V11: =LN($C11) | W11: =LN($D11) | X11: =LN($E11) | Y11: =LN($G11) | Z11: =LN($H11) | AA11: =LN($I11) | AB11: =IF(LEFT($T11,3)="MQ:","",$U11)
B12: Paris | C12: =IF(LEFT($T12,3)="MQ:",SUMPRODUCT((Donnees!$B$4:$B$17=MID($T12,4,99))*1,Donnees!$D$4:$D$17),INDEX(Donnees!$D$4:$D$17,MATCH($T12,Donnees!$A$4:$A$17,0))) | D12: =IF(LEFT($T12,3)="MQ:",SUMPRODUCT((Donnees!$B$4:$B$17=MID($T12,4,99))*1,Donnees!$E$4:$E$17),INDEX(Donnees!$E$4:$E$17,MATCH($T12,Donnees!$A$4:$A$17,0))) | E12: =IF(LEFT($T12,3)="MQ:",SUMPRODUCT((Donnees!$B$4:$B$17=MID($T12,4,99))*1,Donnees!$F$4:$F$17),INDEX(Donnees!$F$4:$F$17,MATCH($T12,Donnees!$A$4:$A$17,0))) | G12: =IF(LEFT($T12,3)="MQ:",SUMPRODUCT((Donnees!$B$4:$B$17=MID($T12,4,99))*1,Donnees!$G$4:$G$17),INDEX(Donnees!$G$4:$G$17,MATCH($T12,Donnees!$A$4:$A$17,0))) | H12: =IF(LEFT($T12,3)="MQ:",SUMPRODUCT((Donnees!$B$4:$B$17=MID($T12,4,99))*1,Donnees!$H$4:$H$17),INDEX(Donnees!$H$4:$H$17,MATCH($T12,Donnees!$A$4:$A$17,0))) | I12: =IF(LEFT($T12,3)="MQ:",SUMPRODUCT((Donnees!$B$4:$B$17=MID($T12,4,99))*1,Donnees!$I$4:$I$17),INDEX(Donnees!$I$4:$I$17,MATCH($T12,Donnees!$A$4:$A$17,0))) | K12: =POWER($E12/$C12,0.5)-1 | L12: =POWER($I12/$G12,0.5)-1 | M12: =$U12 | T12: ISCOM_PAR | U12: =SLOPE($Y12:$AA12,$V12:$X12) | V12: =LN($C12) | W12: =LN($D12) | X12: =LN($E12) | Y12: =LN($G12) | Z12: =LN($H12) | AA12: =LN($I12) | AB12: =IF(LEFT($T12,3)="MQ:","",$U12)
B13: Toulouse | C13: =IF(LEFT($T13,3)="MQ:",SUMPRODUCT((Donnees!$B$4:$B$17=MID($T13,4,99))*1,Donnees!$D$4:$D$17),INDEX(Donnees!$D$4:$D$17,MATCH($T13,Donnees!$A$4:$A$17,0))) | D13: =IF(LEFT($T13,3)="MQ:",SUMPRODUCT((Donnees!$B$4:$B$17=MID($T13,4,99))*1,Donnees!$E$4:$E$17),INDEX(Donnees!$E$4:$E$17,MATCH($T13,Donnees!$A$4:$A$17,0))) | E13: =IF(LEFT($T13,3)="MQ:",SUMPRODUCT((Donnees!$B$4:$B$17=MID($T13,4,99))*1,Donnees!$F$4:$F$17),INDEX(Donnees!$F$4:$F$17,MATCH($T13,Donnees!$A$4:$A$17,0))) | G13: =IF(LEFT($T13,3)="MQ:",SUMPRODUCT((Donnees!$B$4:$B$17=MID($T13,4,99))*1,Donnees!$G$4:$G$17),INDEX(Donnees!$G$4:$G$17,MATCH($T13,Donnees!$A$4:$A$17,0))) | H13: =IF(LEFT($T13,3)="MQ:",SUMPRODUCT((Donnees!$B$4:$B$17=MID($T13,4,99))*1,Donnees!$H$4:$H$17),INDEX(Donnees!$H$4:$H$17,MATCH($T13,Donnees!$A$4:$A$17,0))) | I13: =IF(LEFT($T13,3)="MQ:",SUMPRODUCT((Donnees!$B$4:$B$17=MID($T13,4,99))*1,Donnees!$I$4:$I$17),INDEX(Donnees!$I$4:$I$17,MATCH($T13,Donnees!$A$4:$A$17,0))) | K13: =POWER($E13/$C13,0.5)-1 | L13: =POWER($I13/$G13,0.5)-1 | M13: =$U13 | T13: ISCOM_TLS | U13: =SLOPE($Y13:$AA13,$V13:$X13) | V13: =LN($C13) | W13: =LN($D13) | X13: =LN($E13) | Y13: =LN($G13) | Z13: =LN($H13) | AA13: =LN($I13) | AB13: =IF(LEFT($T13,3)="MQ:","",$U13)
B14: MBway | C14: =IF(LEFT($T14,3)="MQ:",SUMPRODUCT((Donnees!$B$4:$B$17=MID($T14,4,99))*1,Donnees!$D$4:$D$17),INDEX(Donnees!$D$4:$D$17,MATCH($T14,Donnees!$A$4:$A$17,0))) | D14: =IF(LEFT($T14,3)="MQ:",SUMPRODUCT((Donnees!$B$4:$B$17=MID($T14,4,99))*1,Donnees!$E$4:$E$17),INDEX(Donnees!$E$4:$E$17,MATCH($T14,Donnees!$A$4:$A$17,0))) | E14: =IF(LEFT($T14,3)="MQ:",SUMPRODUCT((Donnees!$B$4:$B$17=MID($T14,4,99))*1,Donnees!$F$4:$F$17),INDEX(Donnees!$F$4:$F$17,MATCH($T14,Donnees!$A$4:$A$17,0))) | G14: =IF(LEFT($T14,3)="MQ:",SUMPRODUCT((Donnees!$B$4:$B$17=MID($T14,4,99))*1,Donnees!$G$4:$G$17),INDEX(Donnees!$G$4:$G$17,MATCH($T14,Donnees!$A$4:$A$17,0))) | H14: =IF(LEFT($T14,3)="MQ:",SUMPRODUCT((Donnees!$B$4:$B$17=MID($T14,4,99))*1,Donnees!$H$4:$H$17),INDEX(Donnees!$H$4:$H$17,MATCH($T14,Donnees!$A$4:$A$17,0))) | I14: =IF(LEFT($T14,3)="MQ:",SUMPRODUCT((Donnees!$B$4:$B$17=MID($T14,4,99))*1,Donnees!$I$4:$I$17),INDEX(Donnees!$I$4:$I$17,MATCH($T14,Donnees!$A$4:$A$17,0))) | K14: =POWER($E14/$C14,0.5)-1 | L14: =POWER($I14/$G14,0.5)-1 | M14: =$U14 | T14: MQ:MBway | U14: =SLOPE($Y14:$AA14,$V14:$X14) | V14: =LN($C14) | W14: =LN($D14) | X14: =LN($E14) | Y14: =LN($G14) | Z14: =LN($H14) | AA14: =LN($I14) | AB14: =IF(LEFT($T14,3)="MQ:","",$U14)
B15: Bordeaux | C15: =IF(LEFT($T15,3)="MQ:",SUMPRODUCT((Donnees!$B$4:$B$17=MID($T15,4,99))*1,Donnees!$D$4:$D$17),INDEX(Donnees!$D$4:$D$17,MATCH($T15,Donnees!$A$4:$A$17,0))) | D15: =IF(LEFT($T15,3)="MQ:",SUMPRODUCT((Donnees!$B$4:$B$17=MID($T15,4,99))*1,Donnees!$E$4:$E$17),INDEX(Donnees!$E$4:$E$17,MATCH($T15,Donnees!$A$4:$A$17,0))) | E15: =IF(LEFT($T15,3)="MQ:",SUMPRODUCT((Donnees!$B$4:$B$17=MID($T15,4,99))*1,Donnees!$F$4:$F$17),INDEX(Donnees!$F$4:$F$17,MATCH($T15,Donnees!$A$4:$A$17,0))) | G15: =IF(LEFT($T15,3)="MQ:",SUMPRODUCT((Donnees!$B$4:$B$17=MID($T15,4,99))*1,Donnees!$G$4:$G$17),INDEX(Donnees!$G$4:$G$17,MATCH($T15,Donnees!$A$4:$A$17,0))) | H15: =IF(LEFT($T15,3)="MQ:",SUMPRODUCT((Donnees!$B$4:$B$17=MID($T15,4,99))*1,Donnees!$H$4:$H$17),INDEX(Donnees!$H$4:$H$17,MATCH($T15,Donnees!$A$4:$A$17,0))) | I15: =IF(LEFT($T15,3)="MQ:",SUMPRODUCT((Donnees!$B$4:$B$17=MID($T15,4,99))*1,Donnees!$I$4:$I$17),INDEX(Donnees!$I$4:$I$17,MATCH($T15,Donnees!$A$4:$A$17,0))) | K15: =POWER($E15/$C15,0.5)-1 | L15: =POWER($I15/$G15,0.5)-1 | M15: =$U15 | T15: MBWAY_BOR | U15: =SLOPE($Y15:$AA15,$V15:$X15) | V15: =LN($C15) | W15: =LN($D15) | X15: =LN($E15) | Y15: =LN($G15) | Z15: =LN($H15) | AA15: =LN($I15) | AB15: =IF(LEFT($T15,3)="MQ:","",$U15)
B16: Lyon | C16: =IF(LEFT($T16,3)="MQ:",SUMPRODUCT((Donnees!$B$4:$B$17=MID($T16,4,99))*1,Donnees!$D$4:$D$17),INDEX(Donnees!$D$4:$D$17,MATCH($T16,Donnees!$A$4:$A$17,0))) | D16: =IF(LEFT($T16,3)="MQ:",SUMPRODUCT((Donnees!$B$4:$B$17=MID($T16,4,99))*1,Donnees!$E$4:$E$17),INDEX(Donnees!$E$4:$E$17,MATCH($T16,Donnees!$A$4:$A$17,0))) | E16: =IF(LEFT($T16,3)="MQ:",SUMPRODUCT((Donnees!$B$4:$B$17=MID($T16,4,99))*1,Donnees!$F$4:$F$17),INDEX(Donnees!$F$4:$F$17,MATCH($T16,Donnees!$A$4:$A$17,0))) | G16: =IF(LEFT($T16,3)="MQ:",SUMPRODUCT((Donnees!$B$4:$B$17=MID($T16,4,99))*1,Donnees!$G$4:$G$17),INDEX(Donnees!$G$4:$G$17,MATCH($T16,Donnees!$A$4:$A$17,0))) | H16: =IF(LEFT($T16,3)="MQ:",SUMPRODUCT((Donnees!$B$4:$B$17=MID($T16,4,99))*1,Donnees!$H$4:$H$17),INDEX(Donnees!$H$4:$H$17,MATCH($T16,Donnees!$A$4:$A$17,0))) | I16: =IF(LEFT($T16,3)="MQ:",SUMPRODUCT((Donnees!$B$4:$B$17=MID($T16,4,99))*1,Donnees!$I$4:$I$17),INDEX(Donnees!$I$4:$I$17,MATCH($T16,Donnees!$A$4:$A$17,0))) | K16: =POWER($E16/$C16,0.5)-1 | L16: =POWER($I16/$G16,0.5)-1 | M16: =$U16 | T16: MBWAY_LYO | U16: =SLOPE($Y16:$AA16,$V16:$X16) | V16: =LN($C16) | W16: =LN($D16) | X16: =LN($E16) | Y16: =LN($G16) | Z16: =LN($H16) | AA16: =LN($I16) | AB16: =IF(LEFT($T16,3)="MQ:","",$U16)
B17: Nantes | C17: =IF(LEFT($T17,3)="MQ:",SUMPRODUCT((Donnees!$B$4:$B$17=MID($T17,4,99))*1,Donnees!$D$4:$D$17),INDEX(Donnees!$D$4:$D$17,MATCH($T17,Donnees!$A$4:$A$17,0))) | D17: =IF(LEFT($T17,3)="MQ:",SUMPRODUCT((Donnees!$B$4:$B$17=MID($T17,4,99))*1,Donnees!$E$4:$E$17),INDEX(Donnees!$E$4:$E$17,MATCH($T17,Donnees!$A$4:$A$17,0))) | E17: =IF(LEFT($T17,3)="MQ:",SUMPRODUCT((Donnees!$B$4:$B$17=MID($T17,4,99))*1,Donnees!$F$4:$F$17),INDEX(Donnees!$F$4:$F$17,MATCH($T17,Donnees!$A$4:$A$17,0))) | G17: =IF(LEFT($T17,3)="MQ:",SUMPRODUCT((Donnees!$B$4:$B$17=MID($T17,4,99))*1,Donnees!$G$4:$G$17),INDEX(Donnees!$G$4:$G$17,MATCH($T17,Donnees!$A$4:$A$17,0))) | H17: =IF(LEFT($T17,3)="MQ:",SUMPRODUCT((Donnees!$B$4:$B$17=MID($T17,4,99))*1,Donnees!$H$4:$H$17),INDEX(Donnees!$H$4:$H$17,MATCH($T17,Donnees!$A$4:$A$17,0))) | I17: =IF(LEFT($T17,3)="MQ:",SUMPRODUCT((Donnees!$B$4:$B$17=MID($T17,4,99))*1,Donnees!$I$4:$I$17),INDEX(Donnees!$I$4:$I$17,MATCH($T17,Donnees!$A$4:$A$17,0))) | K17: =POWER($E17/$C17,0.5)-1 | L17: =POWER($I17/$G17,0.5)-1 | M17: =$U17 | T17: MBWAY_NAN | U17: =SLOPE($Y17:$AA17,$V17:$X17) | V17: =LN($C17) | W17: =LN($D17) | X17: =LN($E17) | Y17: =LN($G17) | Z17: =LN($H17) | AA17: =LN($I17) | AB17: =IF(LEFT($T17,3)="MQ:","",$U17)
... B24: Paris | C24: =IF(LEFT($T24,3)="MQ:",SUMPRODUCT((Donnees!$B$4:$B$17=MID($T24,4,99))*1,Donnees!$D$4:$D$17),INDEX(Donnees!$D$4:$D$17,MATCH($T24,Donnees!$A$4:$A$17,0))) | D24: =IF(LEFT($T24,3)="MQ:",SUMPRODUCT((Donnees!$B$4:$B$17=MID($T24,4,99))*1,Donnees!$E$4:$E$17),INDEX(Donnees!$E$4:$E$17,MATCH($T24,Donnees!$A$4:$A$17,0))) | E24: =IF(LEFT($T24,3)="MQ:",SUMPRODUCT((Donnees!$B$4:$B$17=MID($T24,4,99))*1,Donnees!$F$4:$F$17),INDEX(Donnees!$F$4:$F$17,MATCH($T24,Donnees!$A$4:$A$17,0))) | G24: =IF(LEFT($T24,3)="MQ:",SUMPRODUCT((Donnees!$B$4:$B$17=MID($T24,4,99))*1,Donnees!$G$4:$G$17),INDEX(Donnees!$G$4:$G$17,MATCH($T24,Donnees!$A$4:$A$17,0))) | H24: =IF(LEFT($T24,3)="MQ:",SUMPRODUCT((Donnees!$B$4:$B$17=MID($T24,4,99))*1,Donnees!$H$4:$H$17),INDEX(Donnees!$H$4:$H$17,MATCH($T24,Donnees!$A$4:$A$17,0))) | I24: =IF(LEFT($T24,3)="MQ:",SUMPRODUCT((Donnees!$B$4:$B$17=MID($T24,4,99))*1,Donnees!$I$4:$I$17),INDEX(Donnees!$I$4:$I$17,MATCH($T24,Donnees!$A$4:$A$17,0))) | K24: =POWER($E24/$C24,0.5)-1 | L24: =POWER($I24/$G24,0.5)-1 | M24: =$U24 | T24: TUNON_PAR | U24: =SLOPE($Y24:$AA24,$V24:$X24) | V24: =LN($C24) | W24: =LN($D24) | X24: =LN($E24) | Y24: =LN($G24) | Z24: =LN($H24) | AA24: =LN($I24) | AB24: =IF(LEFT($T24,3)="MQ:","",$U24)
B25: GROUPE | C25: =$C6+$C10+$C14+$C19+$C22 | D25: =$D6+$D10+$D14+$D19+$D22 | E25: =$E6+$E10+$E14+$E19+$E22 | G25: =$G6+$G10+$G14+$G19+$G22 | H25: =$H6+$H10+$H14+$H19+$H22 | I25: =$I6+$I10+$I14+$I19+$I22 | K25: =POWER($E25/$C25,0.5)-1 | L25: =POWER($I25/$G25,0.5)-1 | M25: =$U25 | T25: GROUPE | U25: =SLOPE($Y25:$AA25,$V25:$X25) | V25: =LN($C25) | W25: =LN($D25) | X25: =LN($E25) | Y25: =LN($G25) | Z25: =LN($H25) | AA25: =LN($I25)
B27: COMMENT LA LIRE
B28: ="Une élasticité de "&TEXT($M25,"0.00")&" veut dire : +1 % de budget marketing donne +"&TEXT($M25,"0.00")&" % d'inscrits."
B29: Elle est inférieure à 1 partout : le volume monte toujours, mais moins vite que la dépense. C'est le rendement décroissant, et il se mesure au lieu de se supposer.
B30: ="Elle varie de "&TEXT(MIN($AB$6:$AB$24),"0.00")&" à "&TEXT(MAX($AB$6:$AB$24),"0.00")&" selon le campus : les marchés les plus disputés sont ceux où le prochain euro travaille le moins."
B31: Une élasticité ne se moyenne pas. Celle d'une marque, ici, est recalculée sur le budget et les inscrits de la marque entière, comme un indice base 100 — ce n'est pas la moyenne de ses campus.
B32: ="Deux mesures, deux niveaux : sur les totaux consolidés du groupe la pente vaut "&TEXT($M25,"0.00")&" ; le moteur, lui, calcule campus par campus et fait la somme, ce qui donne "&TEXT('Le moteur'!$E$29,"0.00")&". L'écart est un effet de composition : les campus les plus réactifs ne sont pas les plus gros. C'est le second chiffre qui pilote le masque, parce que c'est au campus que le budget se dépense."

Sheet Playback
B1: PLAYBACK — LA MÉTHODE MISE À L'ÉPREUVE
B2: Calée sur 2024-2025 seulement, à qui l'on donne le budget 2026 qu'elle n'a jamais vu
B3: Une méthode calée sur trois points et jugée sur ces trois points ne prouve rien. Ici elle n'en voit que deux, et on la juge sur le troisième.
B5: Marque · Campus | C5: Élasticité calée 24-25 | D5: Budget 2026 | E5: Inscrits prédits | G5: Inscrits constatés | H5: Écart | I5: en % | J5: Élasticité sur 3 ans
B6: Ipac Bachelor Factory | C6: =LN(INDEX(Historique!$H$1:$H$200,MATCH($T6,Historique!$T$1:$T$200,0))/INDEX(Historique!$G$1:$G$200,MATCH($T6,Historique!$T$1:$T$200,0)))/LN(INDEX(Historique!$D$1:$D$200,MATCH($T6,Historique!$T$1:$T$200,0))/INDEX(Historique!$C$1:$C$200,MATCH($T6,Historique!$T$1:$T$200,0))) | D6: =INDEX(Historique!$E$1:$E$200,MATCH($T6,Historique!$T$1:$T$200,0)) | E6: =INDEX(Historique!$H$1:$H$200,MATCH($T6,Historique!$T$1:$T$200,0))*POWER($D6/INDEX(Historique!$D$1:$D$200,MATCH($T6,Historique!$T$1:$T$200,0)),$C6) | G6: =INDEX(Historique!$I$1:$I$200,MATCH($T6,Historique!$T$1:$T$200,0)) | H6: =$E6-$G6 | I6: =$E6/$G6-1 | J6: =INDEX(Historique!$M$1:$M$200,MATCH($T6,Historique!$T$1:$T$200,0)) | T6: MQ:Ipac Bachelor Factory | U6: =IF(LEFT($T6,3)="MQ:","",ABS($I6))
B7: Montpellier | C7: =LN(INDEX(Historique!$H$1:$H$200,MATCH($T7,Historique!$T$1:$T$200,0))/INDEX(Historique!$G$1:$G$200,MATCH($T7,Historique!$T$1:$T$200,0)))/LN(INDEX(Historique!$D$1:$D$200,MATCH($T7,Historique!$T$1:$T$200,0))/INDEX(Historique!$C$1:$C$200,MATCH($T7,Historique!$T$1:$T$200,0))) | D7: =INDEX(Historique!$E$1:$E$200,MATCH($T7,Historique!$T$1:$T$200,0)) | E7: =INDEX(Historique!$H$1:$H$200,MATCH($T7,Historique!$T$1:$T$200,0))*POWER($D7/INDEX(Historique!$D$1:$D$200,MATCH($T7,Historique!$T$1:$T$200,0)),$C7) | G7: =INDEX(Historique!$I$1:$I$200,MATCH($T7,Historique!$T$1:$T$200,0)) | H7: =$E7-$G7 | I7: =$E7/$G7-1 | J7: =INDEX(Historique!$M$1:$M$200,MATCH($T7,Historique!$T$1:$T$200,0)) | T7: IPAC_MTP | U7: =IF(LEFT($T7,3)="MQ:","",ABS($I7))
B8: Nantes | C8: =LN(INDEX(Historique!$H$1:$H$200,MATCH($T8,Historique!$T$1:$T$200,0))/INDEX(Historique!$G$1:$G$200,MATCH($T8,Historique!$T$1:$T$200,0)))/LN(INDEX(Historique!$D$1:$D$200,MATCH($T8,Historique!$T$1:$T$200,0))/INDEX(Historique!$C$1:$C$200,MATCH($T8,Historique!$T$1:$T$200,0))) | D8: =INDEX(Historique!$E$1:$E$200,MATCH($T8,Historique!$T$1:$T$200,0)) | E8: =INDEX(Historique!$H$1:$H$200,MATCH($T8,Historique!$T$1:$T$200,0))*POWER($D8/INDEX(Historique!$D$1:$D$200,MATCH($T8,Historique!$T$1:$T$200,0)),$C8) | G8: =INDEX(Historique!$I$1:$I$200,MATCH($T8,Historique!$T$1:$T$200,0)) | H8: =$E8-$G8 | I8: =$E8/$G8-1 | J8: =INDEX(Historique!$M$1:$M$200,MATCH($T8,Historique!$T$1:$T$200,0)) | T8: IPAC_NAN | U8: =IF(LEFT($T8,3)="MQ:","",ABS($I8))
B9: Rennes | C9: =LN(INDEX(Historique!$H$1:$H$200,MATCH($T9,Historique!$T$1:$T$200,0))/INDEX(Historique!$G$1:$G$200,MATCH($T9,Historique!$T$1:$T$200,0)))/LN(INDEX(Historique!$D$1:$D$200,MATCH($T9,Historique!$T$1:$T$200,0))/INDEX(Historique!$C$1:$C$200,MATCH($T9,Historique!$T$1:$T$200,0))) | D9: =INDEX(Historique!$E$1:$E$200,MATCH($T9,Historique!$T$1:$T$200,0)) | E9: =INDEX(Historique!$H$1:$H$200,MATCH($T9,Historique!$T$1:$T$200,0))*POWER($D9/INDEX(Historique!$D$1:$D$200,MATCH($T9,Historique!$T$1:$T$200,0)),$C9) | G9: =INDEX(Historique!$I$1:$I$200,MATCH($T9,Historique!$T$1:$T$200,0)) | H9: =$E9-$G9 | I9: =$E9/$G9-1 | J9: =INDEX(Historique!$M$1:$M$200,MATCH($T9,Historique!$T$1:$T$200,0)) | T9: IPAC_REN | U9: =IF(LEFT($T9,3)="MQ:","",ABS($I9))
B10: ISCOM | C10: =LN(INDEX(Historique!$H$1:$H$200,MATCH($T10,Historique!$T$1:$T$200,0))/INDEX(Historique!$G$1:$G$200,MATCH($T10,Historique!$T$1:$T$200,0)))/LN(INDEX(Historique!$D$1:$D$200,MATCH($T10,Historique!$T$1:$T$200,0))/INDEX(Historique!$C$1:$C$200,MATCH($T10,Historique!$T$1:$T$200,0))) | D10: =INDEX(Historique!$E$1:$E$200,MATCH($T10,Historique!$T$1:$T$200,0)) | E10: =INDEX(Historique!$H$1:$H$200,MATCH($T10,Historique!$T$1:$T$200,0))*POWER($D10/INDEX(Historique!$D$1:$D$200,MATCH($T10,Historique!$T$1:$T$200,0)),$C10) | G10: =INDEX(Historique!$I$1:$I$200,MATCH($T10,Historique!$T$1:$T$200,0)) | H10: =$E10-$G10 | I10: =$E10/$G10-1 | J10: =INDEX(Historique!$M$1:$M$200,MATCH($T10,Historique!$T$1:$T$200,0)) | T10: MQ:ISCOM | U10: =IF(LEFT($T10,3)="MQ:","",ABS($I10))
B11: Lille | C11: =LN(INDEX(Historique!$H$1:$H$200,MATCH($T11,Historique!$T$1:$T$200,0))/INDEX(Historique!$G$1:$G$200,MATCH($T11,Historique!$T$1:$T$200,0)))/LN(INDEX(Historique!$D$1:$D$200,MATCH($T11,Historique!$T$1:$T$200,0))/INDEX(Historique!$C$1:$C$200,MATCH($T11,Historique!$T$1:$T$200,0))) | D11: =INDEX(Historique!$E$1:$E$200,MATCH($T11,Historique!$T$1:$T$200,0)) | E11: =INDEX(Historique!$H$1:$H$200,MATCH($T11,Historique!$T$1:$T$200,0))*POWER($D11/INDEX(Historique!$D$1:$D$200,MATCH($T11,Historique!$T$1:$T$200,0)),$C11) | G11: =INDEX(Historique!$I$1:$I$200,MATCH($T11,Historique!$T$1:$T$200,0)) | H11: =$E11-$G11 | I11: =$E11/$G11-1 | J11: =INDEX(Historique!$M$1:$M$200,MATCH($T11,Historique!$T$1:$T$200,0)) | T11: ISCOM_LIL | U11: =IF(LEFT($T11,3)="MQ:","",ABS($I11))
B12: Paris | C12: =LN(INDEX(Historique!$H$1:$H$200,MATCH($T12,Historique!$T$1:$T$200,0))/INDEX(Historique!$G$1:$G$200,MATCH($T12,Historique!$T$1:$T$200,0)))/LN(INDEX(Historique!$D$1:$D$200,MATCH($T12,Historique!$T$1:$T$200,0))/INDEX(Historique!$C$1:$C$200,MATCH($T12,Historique!$T$1:$T$200,0))) | D12: =INDEX(Historique!$E$1:$E$200,MATCH($T12,Historique!$T$1:$T$200,0)) | E12: =INDEX(Historique!$H$1:$H$200,MATCH($T12,Historique!$T$1:$T$200,0))*POWER($D12/INDEX(Historique!$D$1:$D$200,MATCH($T12,Historique!$T$1:$T$200,0)),$C12) | G12: =INDEX(Historique!$I$1:$I$200,MATCH($T12,Historique!$T$1:$T$200,0)) | H12: =$E12-$G12 | I12: =$E12/$G12-1 | J12: =INDEX(Historique!$M$1:$M$200,MATCH($T12,Historique!$T$1:$T$200,0)) | T12: ISCOM_PAR | U12: =IF(LEFT($T12,3)="MQ:","",ABS($I12))
B13: Toulouse | C13: =LN(INDEX(Historique!$H$1:$H$200,MATCH($T13,Historique!$T$1:$T$200,0))/INDEX(Historique!$G$1:$G$200,MATCH($T13,Historique!$T$1:$T$200,0)))/LN(INDEX(Historique!$D$1:$D$200,MATCH($T13,Historique!$T$1:$T$200,0))/INDEX(Historique!$C$1:$C$200,MATCH($T13,Historique!$T$1:$T$200,0))) | D13: =INDEX(Historique!$E$1:$E$200,MATCH($T13,Historique!$T$1:$T$200,0)) | E13: =INDEX(Historique!$H$1:$H$200,MATCH($T13,Historique!$T$1:$T$200,0))*POWER($D13/INDEX(Historique!$D$1:$D$200,MATCH($T13,Historique!$T$1:$T$200,0)),$C13) | G13: =INDEX(Historique!$I$1:$I$200,MATCH($T13,Historique!$T$1:$T$200,0)) | H13: =$E13-$G13 | I13: =$E13/$G13-1 | J13: =INDEX(Historique!$M$1:$M$200,MATCH($T13,Historique!$T$1:$T$200,0)) | T13: ISCOM_TLS | U13: =IF(LEFT($T13,3)="MQ:","",ABS($I13))
B14: MBway | C14: =LN(INDEX(Historique!$H$1:$H$200,MATCH($T14,Historique!$T$1:$T$200,0))/INDEX(Historique!$G$1:$G$200,MATCH($T14,Historique!$T$1:$T$200,0)))/LN(INDEX(Historique!$D$1:$D$200,MATCH($T14,Historique!$T$1:$T$200,0))/INDEX(Historique!$C$1:$C$200,MATCH($T14,Historique!$T$1:$T$200,0))) | D14: =INDEX(Historique!$E$1:$E$200,MATCH($T14,Historique!$T$1:$T$200,0)) | E14: =INDEX(Historique!$H$1:$H$200,MATCH($T14,Historique!$T$1:$T$200,0))*POWER($D14/INDEX(Historique!$D$1:$D$200,MATCH($T14,Historique!$T$1:$T$200,0)),$C14) | G14: =INDEX(Historique!$I$1:$I$200,MATCH($T14,Historique!$T$1:$T$200,0)) | H14: =$E14-$G14 | I14: =$E14/$G14-1 | J14: =INDEX(Historique!$M$1:$M$200,MATCH($T14,Historique!$T$1:$T$200,0)) | T14: MQ:MBway | U14: =IF(LEFT($T14,3)="MQ:","",ABS($I14))
B15: Bordeaux | C15: =LN(INDEX(Historique!$H$1:$H$200,MATCH($T15,Historique!$T$1:$T$200,0))/INDEX(Historique!$G$1:$G$200,MATCH($T15,Historique!$T$1:$T$200,0)))/LN(INDEX(Historique!$D$1:$D$200,MATCH($T15,Historique!$T$1:$T$200,0))/INDEX(Historique!$C$1:$C$200,MATCH($T15,Historique!$T$1:$T$200,0))) | D15: =INDEX(Historique!$E$1:$E$200,MATCH($T15,Historique!$T$1:$T$200,0)) | E15: =INDEX(Historique!$H$1:$H$200,MATCH($T15,Historique!$T$1:$T$200,0))*POWER($D15/INDEX(Historique!$D$1:$D$200,MATCH($T15,Historique!$T$1:$T$200,0)),$C15) | G15: =INDEX(Historique!$I$1:$I$200,MATCH($T15,Historique!$T$1:$T$200,0)) | H15: =$E15-$G15 | I15: =$E15/$G15-1 | J15: =INDEX(Historique!$M$1:$M$200,MATCH($T15,Historique!$T$1:$T$200,0)) | T15: MBWAY_BOR | U15: =IF(LEFT($T15,3)="MQ:","",ABS($I15))
B16: Lyon | C16: =LN(INDEX(Historique!$H$1:$H$200,MATCH($T16,Historique!$T$1:$T$200,0))/INDEX(Historique!$G$1:$G$200,MATCH($T16,Historique!$T$1:$T$200,0)))/LN(INDEX(Historique!$D$1:$D$200,MATCH($T16,Historique!$T$1:$T$200,0))/INDEX(Historique!$C$1:$C$200,MATCH($T16,Historique!$T$1:$T$200,0))) | D16: =INDEX(Historique!$E$1:$E$200,MATCH($T16,Historique!$T$1:$T$200,0)) | E16: =INDEX(Historique!$H$1:$H$200,MATCH($T16,Historique!$T$1:$T$200,0))*POWER($D16/INDEX(Historique!$D$1:$D$200,MATCH($T16,Historique!$T$1:$T$200,0)),$C16) | G16: =INDEX(Historique!$I$1:$I$200,MATCH($T16,Historique!$T$1:$T$200,0)) | H16: =$E16-$G16 | I16: =$E16/$G16-1 | J16: =INDEX(Historique!$M$1:$M$200,MATCH($T16,Historique!$T$1:$T$200,0)) | T16: MBWAY_LYO | U16: =IF(LEFT($T16,3)="MQ:","",ABS($I16))
B17: Nantes | C17: =LN(INDEX(Historique!$H$1:$H$200,MATCH($T17,Historique!$T$1:$T$200,0))/INDEX(Historique!$G$1:$G$200,MATCH($T17,Historique!$T$1:$T$200,0)))/LN(INDEX(Historique!$D$1:$D$200,MATCH($T17,Historique!$T$1:$T$200,0))/INDEX(Historique!$C$1:$C$200,MATCH($T17,Historique!$T$1:$T$200,0))) | D17: =INDEX(Historique!$E$1:$E$200,MATCH($T17,Historique!$T$1:$T$200,0)) | E17: =INDEX(Historique!$H$1:$H$200,MATCH($T17,Historique!$T$1:$T$200,0))*POWER($D17/INDEX(Historique!$D$1:$D$200,MATCH($T17,Historique!$T$1:$T$200,0)),$C17) | G17: =INDEX(Historique!$I$1:$I$200,MATCH($T17,Historique!$T$1:$T$200,0)) | H17: =$E17-$G17 | I17: =$E17/$G17-1 | J17: =INDEX(Historique!$M$1:$M$200,MATCH($T17,Historique!$T$1:$T$200,0)) | T17: MBWAY_NAN | U17: =IF(LEFT($T17,3)="MQ:","",ABS($I17))
... B24: Paris | C24: =LN(INDEX(Historique!$H$1:$H$200,MATCH($T24,Historique!$T$1:$T$200,0))/INDEX(Historique!$G$1:$G$200,MATCH($T24,Historique!$T$1:$T$200,0)))/LN(INDEX(Historique!$D$1:$D$200,MATCH($T24,Historique!$T$1:$T$200,0))/INDEX(Historique!$C$1:$C$200,MATCH($T24,Historique!$T$1:$T$200,0))) | D24: =INDEX(Historique!$E$1:$E$200,MATCH($T24,Historique!$T$1:$T$200,0)) | E24: =INDEX(Historique!$H$1:$H$200,MATCH($T24,Historique!$T$1:$T$200,0))*POWER($D24/INDEX(Historique!$D$1:$D$200,MATCH($T24,Historique!$T$1:$T$200,0)),$C24) | G24: =INDEX(Historique!$I$1:$I$200,MATCH($T24,Historique!$T$1:$T$200,0)) | H24: =$E24-$G24 | I24: =$E24/$G24-1 | J24: =INDEX(Historique!$M$1:$M$200,MATCH($T24,Historique!$T$1:$T$200,0)) | T24: TUNON_PAR | U24: =IF(LEFT($T24,3)="MQ:","",ABS($I24))
B25: GROUPE | C25: =LN(INDEX(Historique!$H$1:$H$200,MATCH("GROUPE",Historique!$T$1:$T$200,0))/INDEX(Historique!$G$1:$G$200,MATCH("GROUPE",Historique!$T$1:$T$200,0)))/LN(INDEX(Historique!$D$1:$D$200,MATCH("GROUPE",Historique!$T$1:$T$200,0))/INDEX(Historique!$C$1:$C$200,MATCH("GROUPE",Historique!$T$1:$T$200,0))) | D25: =INDEX(Historique!$E$1:$E$200,MATCH("GROUPE",Historique!$T$1:$T$200,0)) | E25: =INDEX(Historique!$H$1:$H$200,MATCH("GROUPE",Historique!$T$1:$T$200,0))*POWER($D25/INDEX(Historique!$D$1:$D$200,MATCH("GROUPE",Historique!$T$1:$T$200,0)),$C25) | G25: =INDEX(Historique!$I$1:$I$200,MATCH("GROUPE",Historique!$T$1:$T$200,0)) | H25: =$E25-$G25 | I25: =$E25/$G25-1 | J25: =INDEX(Historique!$M$1:$M$200,MATCH("GROUPE",Historique!$T$1:$T$200,0)) | T25: GROUPE
B27: CE QUE LE TEST ÉTABLIT
B28: ="Au niveau du groupe, la méthode rend "&TEXT($E25,"#,##0")&" inscrits pour "&TEXT($G25,"#,##0")&" constatés, soit "&TEXT($I25,"+0.00%;-0.00%")&"."
B29: ="Sur les "&TEXT(COUNT($U$6:$U$24),"0")&" campus, écart moyen "&TEXT(AVERAGE($U$6:$U$24),"0.00%")&", maximum "&TEXT(MAX($U$6:$U$24),"0.00%")&"."
B30: ="L'élasticité calée sur deux points ("&TEXT($C25,"0.000")&") et celle calée sur trois ("&TEXT($J25,"0.000")&") ne diffèrent que de "&TEXT(ABS($C25/$J25-1),"0.0%")&" : la pente ne dépend pas de l'année qu'on lui donne."
B31: Ce n'est pas un ajustement rétrospectif : le budget 2026 n'entre nulle part dans le calage.

Sheet Donnees
A1: Q_ELASTICITE · sortie de requête — budget marketing et inscrits par campus
A2: Le budget marketing est la somme de l'acquisition (6231) et des frais de marque (6236), ramenés au campus qui en bénéficie. Le total groupe est inchangé.
A3: CAMPUS | B3: MARQUE | C3: VILLE | D3: BUDGET 2024 | E3: BUDGET 2025 | F3: BUDGET 2026 | G3: INSCRITS 2024 | H3: INSCRITS 2025 | I3: INSCRITS 2026 | J3: EFFECTIF 2026 | K3: DONT ENTRANTS | L3: CA 2026 | M3: VARIABLES 2026 | N3: STRUCTURE 2026 | P3: ln bud 24 | Q3: ln bud 25 | R3: ln bud 26 | S3: ln ins 24 | T3: ln ins 25 | U3: ln ins 26 | V3: ELASTICITE 3 ANS | W3: ELASTICITE 24-25 | X3: INSCRITS PREDITS 26 | Y3: ECART
A4: IPAC_MTP | B4: Ipac Bachelor Factory | C4: Montpellier | D4: 26124 | E4: 31668 | F4: 38692 | G4: 36 | H4: 38 | I4: 40 | J4: 117 | K4: 40 | L4: 781650 | M4: 115973 | N4: 472560 | P4: =LN(D4) | Q4: =LN(E4) | R4: =LN(F4) | S4: =LN(G4) | T4: =LN(H4) | U4: =LN(I4) | V4: =SLOPE(S4:U4,P4:R4) | W4: =SLOPE(S4:T4,P4:Q4) | X4: =H4*POWER(F4/E4,W4) | Y4: =X4/I4-1
A5: IPAC_NAN | B5: Ipac Bachelor Factory | C5: Nantes | D5: 33920 | E5: 40864 | F5: 49649 | G5: 44 | H5: 47 | I5: 50 | J5: 145 | K5: 50 | L5: 1019500 | M5: 126392 | N5: 619811 | P5: =LN(D5) | Q5: =LN(E5) | R5: =LN(F5) | S5: =LN(G5) | T5: =LN(H5) | U5: =LN(I5) | V5: =SLOPE(S5:U5,P5:R5) | W5: =SLOPE(S5:T5,P5:Q5) | X5: =H5*POWER(F5/E5,W5) | Y5: =X5/I5-1
A6: IPAC_REN | B6: Ipac Bachelor Factory | C6: Rennes | D6: 26363 | E6: 31978 | F6: 39085 | G6: 36 | H6: 38 | I6: 40 | J6: 117 | K6: 40 | L6: 781650 | M6: 115973 | N6: 472805 | P6: =LN(D6) | Q6: =LN(E6) | R6: =LN(F6) | S6: =LN(G6) | T6: =LN(H6) | U6: =LN(I6) | V6: =SLOPE(S6:U6,P6:R6) | W6: =SLOPE(S6:T6,P6:Q6) | X6: =H6*POWER(F6/E6,W6) | Y6: =X6/I6-1
A7: ISCOM_LIL | B7: ISCOM | C7: Lille | D7: 69338 | E7: 75695 | F7: 82638 | G7: 88 | H7: 94 | I7: 100 | J7: 244 | K7: 100 | L7: 1755850 | M7: 211520 | N7: 1051764 | P7: =LN(D7) | Q7: =LN(E7) | R7: =LN(F7) | S7: =LN(G7) | T7: =LN(H7) | U7: =LN(I7) | V7: =SLOPE(S7:U7,P7:R7) | W7: =SLOPE(S7:T7,P7:Q7) | X7: =H7*POWER(F7/E7,W7) | Y7: =X7/I7-1
A8: ISCOM_PAR | B8: ISCOM | C8: Paris | D8: 102342 | E8: 112508 | F8: 123686 | G8: 128 | H8: 136 | I8: 144 | J8: 354 | K8: 144 | L8: 2908720 | M8: 312816 | N8: 1755973 | P8: =LN(D8) | Q8: =LN(E8) | R8: =LN(F8) | S8: =LN(G8) | T8: =LN(H8) | U8: =LN(I8) | V8: =SLOPE(S8:U8,P8:R8) | W8: =SLOPE(S8:T8,P8:Q8) | X8: =H8*POWER(F8/E8,W8) | Y8: =X8/I8-1
A9: ISCOM_TLS | B9: ISCOM | C9: Toulouse | D9: 64888 | E9: 70786 | F9: 77222 | G9: 84 | H9: 88 | I9: 94 | J9: 231 | K9: 94 | L9: 1627980 | M9: 206683 | N9: 972818 | P9: =LN(D9) | Q9: =LN(E9) | R9: =LN(F9) | S9: =LN(G9) | T9: =LN(H9) | U9: =LN(I9) | V9: =SLOPE(S9:U9,P9:R9) | W9: =SLOPE(S9:T9,P9:Q9) | X9: =H9*POWER(F9/E9,W9) | Y9: =X9/I9-1
A10: MBWAY_BOR | B10: MBway | C10: Bordeaux | D10: 59474 | E10: 69903 | F10: 82341 | G10: 90 | H10: 96 | I10: 102 | J10: 249 | K10: 102 | L10: 1773610 | M10: 213381 | N10: 1046334 | P10: =LN(D10) | Q10: =LN(E10) | R10: =LN(F10) | S10: =LN(G10) | T10: =LN(H10) | U10: =LN(I10) | V10: =SLOPE(S10:U10,P10:R10) | W10: =SLOPE(S10:T10,P10:Q10) | X10: =H10*POWER(F10/E10,W10) | Y10: =X10/I10-1
A11: MBWAY_LYO | B11: MBway | C11: Lyon | D11: 77782 | E11: 91110 | F11: 107038 | G11: 118 | H11: 124 | I11: 132 | J11: 324 | K11: 132 | L11: 2496705 | M11: 277507 | N11: 1481108 | P11: =LN(D11) | Q11: =LN(E11) | R11: =LN(F11) | S11: =LN(G11) | T11: =LN(H11) | U11: =LN(I11) | V11: =SLOPE(S11:U11,P11:R11) | W11: =SLOPE(S11:T11,P11:Q11) | X11: =H11*POWER(F11/E11,W11) | Y11: =X11/I11-1
A12: MBWAY_NAN | B12: MBway | C12: Nantes | D12: 70831 | E12: 83168 | F12: 97882 | G12: 106 | H12: 114 | I12: 120 | J12: 294 | K12: 120 | L12: 2158300 | M12: 254271 | N12: 1273157 | P12: =LN(D12) | Q12: =LN(E12) | R12: =LN(F12) | S12: =LN(G12) | T12: =LN(H12) | U12: =LN(I12) | V12: =SLOPE(S12:U12,P12:R12) | W12: =SLOPE(S12:T12,P12:Q12) | X12: =H12*POWER(F12/E12,W12) | Y12: =X12/I12-1
A13: MBWAY_PAR | B13: MBway | C13: Paris | D13: 98199 | E13: 114102 | F13: 133091 | G13: 138 | H13: 148 | I13: 156 | J13: 382 | K13: 156 | L13: 3138840 | M13: 323234 | N13: 1862138 | P13: =LN(D13) | Q13: =LN(E13) | R13: =LN(F13) | S13: =LN(G13) | T13: =LN(H13) | U13: =LN(I13) | V13: =SLOPE(S13:U13,P13:R13) | W13: =SLOPE(S13:T13,P13:Q13) | X13: =H13*POWER(F13/E13,W13) | Y13: =X13/I13-1
A14: PIGIER_BOR | B14: Pigier | C14: Bordeaux | D14: 65915 | E14: 73244 | F14: 81391 | G14: 64 | H14: 68 | I14: 72 | J14: 176 | K14: 72 | L14: 1132650 | M14: 149421 | N14: 613480 | P14: =LN(D14) | Q14: =LN(E14) | R14: =LN(F14) | S14: =LN(G14) | T14: =LN(H14) | U14: =LN(I14) | V14: =SLOPE(S14:U14,P14:R14) | W14: =SLOPE(S14:T14,P14:Q14) | X14: =H14*POWER(F14/E14,W14) | Y14: =X14/I14-1
A15: PIGIER_LYO | B15: Pigier | C15: Lyon | D15: 83697 | E15: 93237 | F15: 103873 | G15: 82 | H15: 86 | I15: 92 | J15: 226 | K15: 92 | L15: 1573830 | M15: 164305 | N15: 861064 | P15: =LN(D15) | Q15: =LN(E15) | R15: =LN(F15) | S15: =LN(G15) | T15: =LN(H15) | U15: =LN(I15) | V15: =SLOPE(S15:U15,P15:R15) | W15: =SLOPE(S15:T15,P15:Q15) | X15: =H15*POWER(F15/E15,W15) | Y15: =X15/I15-1
... A17: TUNON_PAR | B17: Tunon | C17: Paris | D17: 44073 | E17: 47920 | F17: 52113 | G17: 42 | H17: 44 | I17: 47 | J17: 138 | K17: 47 | L17: 1086150 | M17: 123787 | N17: 786127 | P17: =LN(D17) | Q17: =LN(E17) | R17: =LN(F17) | S17: =LN(G17) | T17: =LN(H17) | U17: =LN(I17) | V17: =SLOPE(S17:U17,P17:R17) | W17: =SLOPE(S17:T17,P17:Q17) | X17: =H17*POWER(F17/E17,W17) | Y17: =X17/I17-1
A19: SIÈGE 2026 (hors frais de marque) | L19: 2891983
