Workbook

Sheet Simulation
B1: SIMULATION D'OUVERTURE ET DE FERMETURE DE CLASSE
B2: Budget 2027 construit par le cadrage · version V01 — ce que valent vraiment un groupe de plus et un groupe de moins
B4: Campus | C4: MBway Paris | F4: capacité par groupe : Bachelor 32 · Mastère 26 · BTS 30 | L4: SI UN GROUPE FERME, QU'EST-CE QU'ON SUPPRIME VRAIMENT ? | AC4: =INDEX(Libelles!$B$1:$B$40,MATCH($C$4,Libelles!$C$1:$C$40,0))
L5: Part des enseignants permanents effectivement supprimée | S5: 0
L6: Part de la structure du campus effectivement supprimée | S6: 0
B8: ="Le cadrage a construit "&TEXT(SUMIFS(Donnees!$J$4:$J$400,Donnees!$A$4:$A$400,$AC$4),"#,##0")&" étudiants pour "&TEXT(SUMIFS(Donnees!$I$4:$I$400,Donnees!$A$4:$A$400,$AC$4),"#,##0")&" places ouvertes : "&IF($AC$8<0.5,"aucun sans place",TEXT($AC$8,"#,##0")&" sans place")&", et "&TEXT($AD$8,"#,##0")&" places vides." | AC8: =SUMPRODUCT((Donnees!$A$4:$A$400=$AC$4)*(Donnees!$J$4:$J$400>Donnees!$I$4:$I$400)*(Donnees!$J$4:$J$400-Donnees!$I$4:$I$400)) | AD8: =SUMPRODUCT((Donnees!$A$4:$A$400=$AC$4)*(Donnees!$I$4:$I$400>Donnees!$J$4:$J$400)*(Donnees!$I$4:$I$400-Donnees!$J$4:$J$400))
E10: CE QUE LE CADRAGE A CONSTRUIT | M10: VOTRE DÉCISION | O10: CE QUE ÇA DONNE | Q10: L'EFFET
B11: Programme | C11: Année | D11: Modalité | E11: Groupes | F11: Places | G11: Effectif construit | H11: Effectif plaçable | I11: Remplissage | J11: Chiffre d'affaires | K11: Contribution | L11: Marge complète | M11: Groupes + / − | N11: Étudiants recrutés | O11: Places après | P11: Effectif retenu | Q11: Δ chiffre d'affaires | R11: Δ coûts | S11: Δ EBITDA
B12: =IF($U12=0,"",INDEX(Libelles!$F$1:$F$40,MATCH(INDEX(Donnees!$C$1:$C$400,$U12),Libelles!$E$1:$E$40,0))) | C12: =IF($U12=0,"",INDEX(Libelles!$I$1:$I$40,MATCH(INDEX(Donnees!$D$1:$D$400,$U12),Libelles!$H$1:$H$40,0))) | D12: =IF($U12=0,"",INDEX(Libelles!$L$1:$L$40,MATCH(INDEX(Donnees!$E$1:$E$400,$U12),Libelles!$K$1:$K$40,0))) | E12: =IF($U12=0,"",INDEX(Donnees!$G$1:$G$400,$U12)) | F12: =IF($U12=0,"",INDEX(Donnees!$I$1:$I$400,$U12)) | G12: =IF($U12=0,"",INDEX(Donnees!$J$1:$J$400,$U12)) | H12: =IF($U12=0,"",MIN($G12,$F12)) | I12: =IF($U12=0,"",$G12/$F12) | J12: =IF($U12=0,"",INDEX(Donnees!$K$1:$K$400,$U12)) | K12: =IF($U12=0,"",INDEX(Donnees!$V$1:$V$400,$U12)) | L12: =IF($U12=0,"",INDEX(Donnees!$U$1:$U$400,$U12)) | M12: 0 | N12: 0 | O12: =IF($U12=0,"",($E12+$M12)*INDEX(Donnees!$H$1:$H$400,$U12)) | P12: =IF($U12=0,"",MIN($G12+$N12,$O12)) | Q12: =IF($U12=0,"",($P12-$H12)*$J12/$G12) | R12: =IF($U12=0,"",$V12+$W12+$X12-$Y12-$Z12) | S12: =IF($U12=0,"",$Q12-$R12) | U12: =IF(ISERROR(MATCH($AC$4&"#"&1,Donnees!$AB$1:$AB$400,0)),0,MATCH($AC$4&"#"&1,Donnees!$AB$1:$AB$400,0)) | V12: =IF($U12=0,0,$M12*INDEX(Donnees!$W$1:$W$400,$U12)) | W12: =IF($U12=0,0,($P12-$H12)*INDEX(Donnees!$Y$1:$Y$400,$U12)) | X12: =IF($U12=0,0,MAX(0,$P12-MIN($G12,$O12))*INDEX(Donnees!$S$1:$S$400,$U12)) | Y12: =IF($U12=0,0,MAX(0,-$M12)*INDEX(Donnees!$X$1:$X$400,$U12)*$S$5) | Z12: =IF($U12=0,0,MAX(0,-$M12)*INDEX(Donnees!$P$1:$P$400,$U12)/MAX($E12,1)*$S$6) | AA12: =IF($U12=0,0,($H12-$G12)*$J12/$G12) | AB12: =IF($U12=0,0,($H12-$G12)*INDEX(Donnees!$Y$1:$Y$400,$U12))
B13: =IF($U13=0,"",INDEX(Libelles!$F$1:$F$40,MATCH(INDEX(Donnees!$C$1:$C$400,$U13),Libelles!$E$1:$E$40,0))) | C13: =IF($U13=0,"",INDEX(Libelles!$I$1:$I$40,MATCH(INDEX(Donnees!$D$1:$D$400,$U13),Libelles!$H$1:$H$40,0))) | D13: =IF($U13=0,"",INDEX(Libelles!$L$1:$L$40,MATCH(INDEX(Donnees!$E$1:$E$400,$U13),Libelles!$K$1:$K$40,0))) | E13: =IF($U13=0,"",INDEX(Donnees!$G$1:$G$400,$U13)) | F13: =IF($U13=0,"",INDEX(Donnees!$I$1:$I$400,$U13)) | G13: =IF($U13=0,"",INDEX(Donnees!$J$1:$J$400,$U13)) | H13: =IF($U13=0,"",MIN($G13,$F13)) | I13: =IF($U13=0,"",$G13/$F13) | J13: =IF($U13=0,"",INDEX(Donnees!$K$1:$K$400,$U13)) | K13: =IF($U13=0,"",INDEX(Donnees!$V$1:$V$400,$U13)) | L13: =IF($U13=0,"",INDEX(Donnees!$U$1:$U$400,$U13)) | M13: 0 | N13: 0 | O13: =IF($U13=0,"",($E13+$M13)*INDEX(Donnees!$H$1:$H$400,$U13)) | P13: =IF($U13=0,"",MIN($G13+$N13,$O13)) | Q13: =IF($U13=0,"",($P13-$H13)*$J13/$G13) | R13: =IF($U13=0,"",$V13+$W13+$X13-$Y13-$Z13) | S13: =IF($U13=0,"",$Q13-$R13) | U13: =IF(ISERROR(MATCH($AC$4&"#"&2,Donnees!$AB$1:$AB$400,0)),0,MATCH($AC$4&"#"&2,Donnees!$AB$1:$AB$400,0)) | V13: =IF($U13=0,0,$M13*INDEX(Donnees!$W$1:$W$400,$U13)) | W13: =IF($U13=0,0,($P13-$H13)*INDEX(Donnees!$Y$1:$Y$400,$U13)) | X13: =IF($U13=0,0,MAX(0,$P13-MIN($G13,$O13))*INDEX(Donnees!$S$1:$S$400,$U13)) | Y13: =IF($U13=0,0,MAX(0,-$M13)*INDEX(Donnees!$X$1:$X$400,$U13)*$S$5) | Z13: =IF($U13=0,0,MAX(0,-$M13)*INDEX(Donnees!$P$1:$P$400,$U13)/MAX($E13,1)*$S$6) | AA13: =IF($U13=0,0,($H13-$G13)*$J13/$G13) | AB13: =IF($U13=0,0,($H13-$G13)*INDEX(Donnees!$Y$1:$Y$400,$U13))
B14: =IF($U14=0,"",INDEX(Libelles!$F$1:$F$40,MATCH(INDEX(Donnees!$C$1:$C$400,$U14),Libelles!$E$1:$E$40,0))) | C14: =IF($U14=0,"",INDEX(Libelles!$I$1:$I$40,MATCH(INDEX(Donnees!$D$1:$D$400,$U14),Libelles!$H$1:$H$40,0))) | D14: =IF($U14=0,"",INDEX(Libelles!$L$1:$L$40,MATCH(INDEX(Donnees!$E$1:$E$400,$U14),Libelles!$K$1:$K$40,0))) | E14: =IF($U14=0,"",INDEX(Donnees!$G$1:$G$400,$U14)) | F14: =IF($U14=0,"",INDEX(Donnees!$I$1:$I$400,$U14)) | G14: =IF($U14=0,"",INDEX(Donnees!$J$1:$J$400,$U14)) | H14: =IF($U14=0,"",MIN($G14,$F14)) | I14: =IF($U14=0,"",$G14/$F14) | J14: =IF($U14=0,"",INDEX(Donnees!$K$1:$K$400,$U14)) | K14: =IF($U14=0,"",INDEX(Donnees!$V$1:$V$400,$U14)) | L14: =IF($U14=0,"",INDEX(Donnees!$U$1:$U$400,$U14)) | M14: 0 | N14: 0 | O14: =IF($U14=0,"",($E14+$M14)*INDEX(Donnees!$H$1:$H$400,$U14)) | P14: =IF($U14=0,"",MIN($G14+$N14,$O14)) | Q14: =IF($U14=0,"",($P14-$H14)*$J14/$G14) | R14: =IF($U14=0,"",$V14+$W14+$X14-$Y14-$Z14) | S14: =IF($U14=0,"",$Q14-$R14) | U14: =IF(ISERROR(MATCH($AC$4&"#"&3,Donnees!$AB$1:$AB$400,0)),0,MATCH($AC$4&"#"&3,Donnees!$AB$1:$AB$400,0)) | V14: =IF($U14=0,0,$M14*INDEX(Donnees!$W$1:$W$400,$U14)) | W14: =IF($U14=0,0,($P14-$H14)*INDEX(Donnees!$Y$1:$Y$400,$U14)) | X14: =IF($U14=0,0,MAX(0,$P14-MIN($G14,$O14))*INDEX(Donnees!$S$1:$S$400,$U14)) | Y14: =IF($U14=0,0,MAX(0,-$M14)*INDEX(Donnees!$X$1:$X$400,$U14)*$S$5) | Z14: =IF($U14=0,0,MAX(0,-$M14)*INDEX(Donnees!$P$1:$P$400,$U14)/MAX($E14,1)*$S$6) | AA14: =IF($U14=0,0,($H14-$G14)*$J14/$G14) | AB14: =IF($U14=0,0,($H14-$G14)*INDEX(Donnees!$Y$1:$Y$400,$U14))
B15: =IF($U15=0,"",INDEX(Libelles!$F$1:$F$40,MATCH(INDEX(Donnees!$C$1:$C$400,$U15),Libelles!$E$1:$E$40,0))) | C15: =IF($U15=0,"",INDEX(Libelles!$I$1:$I$40,MATCH(INDEX(Donnees!$D$1:$D$400,$U15),Libelles!$H$1:$H$40,0))) | D15: =IF($U15=0,"",INDEX(Libelles!$L$1:$L$40,MATCH(INDEX(Donnees!$E$1:$E$400,$U15),Libelles!$K$1:$K$40,0))) | E15: =IF($U15=0,"",INDEX(Donnees!$G$1:$G$400,$U15)) | F15: =IF($U15=0,"",INDEX(Donnees!$I$1:$I$400,$U15)) | G15: =IF($U15=0,"",INDEX(Donnees!$J$1:$J$400,$U15)) | H15: =IF($U15=0,"",MIN($G15,$F15)) | I15: =IF($U15=0,"",$G15/$F15) | J15: =IF($U15=0,"",INDEX(Donnees!$K$1:$K$400,$U15)) | K15: =IF($U15=0,"",INDEX(Donnees!$V$1:$V$400,$U15)) | L15: =IF($U15=0,"",INDEX(Donnees!$U$1:$U$400,$U15)) | M15: 0 | N15: 0 | O15: =IF($U15=0,"",($E15+$M15)*INDEX(Donnees!$H$1:$H$400,$U15)) | P15: =IF($U15=0,"",MIN($G15+$N15,$O15)) | Q15: =IF($U15=0,"",($P15-$H15)*$J15/$G15) | R15: =IF($U15=0,"",$V15+$W15+$X15-$Y15-$Z15) | S15: =IF($U15=0,"",$Q15-$R15) | U15: =IF(ISERROR(MATCH($AC$4&"#"&4,Donnees!$AB$1:$AB$400,0)),0,MATCH($AC$4&"#"&4,Donnees!$AB$1:$AB$400,0)) | V15: =IF($U15=0,0,$M15*INDEX(Donnees!$W$1:$W$400,$U15)) | W15: =IF($U15=0,0,($P15-$H15)*INDEX(Donnees!$Y$1:$Y$400,$U15)) | X15: =IF($U15=0,0,MAX(0,$P15-MIN($G15,$O15))*INDEX(Donnees!$S$1:$S$400,$U15)) | Y15: =IF($U15=0,0,MAX(0,-$M15)*INDEX(Donnees!$X$1:$X$400,$U15)*$S$5) | Z15: =IF($U15=0,0,MAX(0,-$M15)*INDEX(Donnees!$P$1:$P$400,$U15)/MAX($E15,1)*$S$6) | AA15: =IF($U15=0,0,($H15-$G15)*$J15/$G15) | AB15: =IF($U15=0,0,($H15-$G15)*INDEX(Donnees!$Y$1:$Y$400,$U15))
B16: =IF($U16=0,"",INDEX(Libelles!$F$1:$F$40,MATCH(INDEX(Donnees!$C$1:$C$400,$U16),Libelles!$E$1:$E$40,0))) | C16: =IF($U16=0,"",INDEX(Libelles!$I$1:$I$40,MATCH(INDEX(Donnees!$D$1:$D$400,$U16),Libelles!$H$1:$H$40,0))) | D16: =IF($U16=0,"",INDEX(Libelles!$L$1:$L$40,MATCH(INDEX(Donnees!$E$1:$E$400,$U16),Libelles!$K$1:$K$40,0))) | E16: =IF($U16=0,"",INDEX(Donnees!$G$1:$G$400,$U16)) | F16: =IF($U16=0,"",INDEX(Donnees!$I$1:$I$400,$U16)) | G16: =IF($U16=0,"",INDEX(Donnees!$J$1:$J$400,$U16)) | H16: =IF($U16=0,"",MIN($G16,$F16)) | I16: =IF($U16=0,"",$G16/$F16) | J16: =IF($U16=0,"",INDEX(Donnees!$K$1:$K$400,$U16)) | K16: =IF($U16=0,"",INDEX(Donnees!$V$1:$V$400,$U16)) | L16: =IF($U16=0,"",INDEX(Donnees!$U$1:$U$400,$U16)) | M16: 0 | N16: 0 | O16: =IF($U16=0,"",($E16+$M16)*INDEX(Donnees!$H$1:$H$400,$U16)) | P16: =IF($U16=0,"",MIN($G16+$N16,$O16)) | Q16: =IF($U16=0,"",($P16-$H16)*$J16/$G16) | R16: =IF($U16=0,"",$V16+$W16+$X16-$Y16-$Z16) | S16: =IF($U16=0,"",$Q16-$R16) | U16: =IF(ISERROR(MATCH($AC$4&"#"&5,Donnees!$AB$1:$AB$400,0)),0,MATCH($AC$4&"#"&5,Donnees!$AB$1:$AB$400,0)) | V16: =IF($U16=0,0,$M16*INDEX(Donnees!$W$1:$W$400,$U16)) | W16: =IF($U16=0,0,($P16-$H16)*INDEX(Donnees!$Y$1:$Y$400,$U16)) | X16: =IF($U16=0,0,MAX(0,$P16-MIN($G16,$O16))*INDEX(Donnees!$S$1:$S$400,$U16)) | Y16: =IF($U16=0,0,MAX(0,-$M16)*INDEX(Donnees!$X$1:$X$400,$U16)*$S$5) | Z16: =IF($U16=0,0,MAX(0,-$M16)*INDEX(Donnees!$P$1:$P$400,$U16)/MAX($E16,1)*$S$6) | AA16: =IF($U16=0,0,($H16-$G16)*$J16/$G16) | AB16: =IF($U16=0,0,($H16-$G16)*INDEX(Donnees!$Y$1:$Y$400,$U16))
B17: Total du campus | E17: =SUM(E12:E16) | F17: =SUM(F12:F16) | G17: =SUM(G12:G16) | H17: =SUM(H12:H16) | I17: =$G17/$F17 | J17: =SUM(J12:J16) | K17: =SUM(K12:K16) | L17: =SUM(L12:L16) | O17: =SUM(O12:O16) | P17: =SUM(P12:P16) | Q17: =SUM(Q12:Q16) | R17: =SUM(R12:R16) | S17: =$Q17-$R17
B19: CE QUI PART AVEC LE GROUPE, CE QUI RESTE SUR LE CAMPUS | L19: L'EFFET DE VOTRE DÉCISION
B20: Poste | I20: Montant 2027 | J20: Comportement | S20: Montant
B21: Vacataires (621) | I21: =SUMIFS(Donnees!$L$4:$L$400,Donnees!$A$4:$A$400,$AC$4) | J21: part avec le groupe | L21: Chiffre d'affaires | S21: =$Q17
B22: Achats d'études et fournitures (604 · 6063) | I22: =SUMIFS(Donnees!$M$4:$M$400,Donnees!$A$4:$A$400,$AC$4) | J22: suivent l'élève | L22: Vacataires (621) | S22: =-SUM(V12:V16)
B23: Recrutement (6231) | I23: =SUMIFS(Donnees!$N$4:$N$400,Donnees!$A$4:$A$400,$AC$4) | J23: suit l'entrant | L23: Achats d'études et fournitures (604 · 6063) | S23: =-SUM(W12:W16)
B24: Enseignants permanents (6411) | I24: =SUMIFS(Donnees!$O$4:$O$400,Donnees!$A$4:$A$400,$AC$4) | J24: restent, sauf décision RH | L24: Acquisition des étudiants recrutés en plus | S24: =-SUM(X12:X16)
B25: Structure du campus (613 · 615 · 616 · 625 · 645 · 6413 · 63511) | I25: =SUMIFS(Donnees!$P$4:$P$400,Donnees!$A$4:$A$400,$AC$4) | J25: reste | L25: Permanents et structure effectivement supprimés | S25: =SUM(Y12:Y16)+SUM(Z12:Z16)
B26: Frais de marque (6236) | I26: =SUMIFS(Donnees!$Q$4:$Q$400,Donnees!$A$4:$A$400,$AC$4) | J26: reste, se réalloue
B27: Siège (6414 · 6226 · 626 · 6281 · 6331 · 6333) | I27: =SUMIFS(Donnees!$R$4:$R$400,Donnees!$A$4:$A$400,$AC$4) | J27: reste, se réalloue | L27: EFFET SUR L'EBITDA DU CAMPUS | S27: =SUM(S21:S25)
B28: Coût complet du campus | I28: =SUM(I21:I27)
B29: dont ne bouge pas si un groupe ferme | I29: =SUM(I24:I27) | J29: =TEXT(I29/I28,"0 %")&" du coût complet" | L29: EBITDA du campus construit par le cadrage | S29: =SUM(L12:L16)
L30: ce que les places d'aujourd'hui ne permettent pas de livrer | S30: =SUM(AA12:AA16)-SUM(AB12:AB16)
L31: EBITDA livrable sans rien changer | S31: =$S29+$S30
L32: effet de votre décision | S32: =$S27
L33: EBITDA du campus après décision | S33: =$S31+$S32
B36: Effectif plaçable = MIN(effectif construit ; places ouvertes). Le cadrage, lui, ne plafonne pas : c'est de cet écart que vient la ligne « ce que les places d'aujourd'hui ne permettent pas de livrer ».
B37: Effectif retenu = MIN(effectif construit + étudiants recrutés ; places après décision). Les colonnes Δ mesurent l'écart à l'effectif plaçable, c'est-à-dire ce que votre décision change vraiment.
B38: Un groupe qui s'ouvre ou qui se ferme emporte UN paquet d'heures de vacataires — c'est le seul coût qui suit la structure. Les achats et fournitures suivent l'élève.
B39: Les étudiants recrutés en plus sont valorisés au CAC marginal du campus, CPL ÷ (rendement × conversion), de 890 € à 2 193 € selon le campus. Le compte 6231 en est exclu pour ne pas compter l'acquisition deux fois.
B40: Les permanents et la structure ne sortent de l'EBITDA que dans la proportion saisie en haut à droite. À 0 %, ils restent et se réallouent sur les classes qui survivent.

Sheet Le piège du coût complet
B1: LE PIÈGE DU COÛT COMPLET
B2: Pourquoi une classe qui ne rapporte rien au coût complet coûte cher à fermer
B4: Campus | C4: =Simulation!$C$4 | L4: =IF($L11=0,"",INDEX(Donnees!$C$1:$C$400,$L11))
L5: =IF($L$7=0,"",IF(INDEX(Donnees!$C$1:$C$400,$L$7)=$L$4,"",INDEX(Donnees!$C$1:$C$400,$L$7)))
B6: L'allocation répartit sur chaque classe la totalité des charges du campus, de la marque et du siège. C'est juste pour mesurer une rentabilité, et faux pour décider d'une fermeture : la classe qui part n'emmène avec elle que ses vacataires et ses consommables. | L6: =COUNTIFS(Donnees!$A$4:$A$400,Simulation!$AC$4)
B7: Tout le reste — les enseignants permanents, les murs, la marque, le siège — reste à payer, et se réalloue simplement sur les classes qui survivent. La marge complète de la classe fermée disparaît donc du rapport, mais ses coûts, eux, réapparaissent ailleurs. | L7: =IF($L$6=0,0,MATCH(Simulation!$AC$4&"#"&$L$6,Donnees!$AB$1:$AB$400,0))
B9: CE QUE DIT LE COÛT COMPLET, ET CE QUE DIT LA CONTRIBUTION
B10: Programme | C10: Année | D10: Chiffre d'affaires | E10: Coûts qui partent avec la classe | F10: Contribution | G10: Coûts qui restent sur le campus | H10: Marge complète | I10: Contribution ÷ marge complète | J10: Effectif par groupe | K10: Point mort en élèves
B11: =IF($L11=0,"",INDEX(Libelles!$F$1:$F$40,MATCH(INDEX(Donnees!$C$1:$C$400,$L11),Libelles!$E$1:$E$40,0))) | C11: =IF($L11=0,"",INDEX(Libelles!$I$1:$I$40,MATCH(INDEX(Donnees!$D$1:$D$400,$L11),Libelles!$H$1:$H$40,0))) | D11: =IF($L11=0,"",INDEX(Donnees!$K$1:$K$400,$L11)) | E11: =IF($L11=0,"",INDEX(Donnees!$L$1:$L$400,$L11)+INDEX(Donnees!$M$1:$M$400,$L11)+INDEX(Donnees!$N$1:$N$400,$L11)) | F11: =IF($L11=0,"",$D11-$E11) | G11: =IF($L11=0,"",INDEX(Donnees!$O$1:$O$400,$L11)+INDEX(Donnees!$P$1:$P$400,$L11)+INDEX(Donnees!$Q$1:$Q$400,$L11)+INDEX(Donnees!$R$1:$R$400,$L11)) | H11: =IF($L11=0,"",$F11-$G11) | I11: =IF($L11=0,"",IF($H11<=0,"—",$F11/$H11)) | J11: =IF($L11=0,"",INDEX(Donnees!$AC$1:$AC$400,$L11)) | K11: =IF($L11=0,"",INDEX(Donnees!$AD$1:$AD$400,$L11)) | L11: =IF(ISERROR(MATCH(Simulation!$AC$4&"#"&1,Donnees!$AB$1:$AB$400,0)),0,MATCH(Simulation!$AC$4&"#"&1,Donnees!$AB$1:$AB$400,0))
B12: =IF($L12=0,"",INDEX(Libelles!$F$1:$F$40,MATCH(INDEX(Donnees!$C$1:$C$400,$L12),Libelles!$E$1:$E$40,0))) | C12: =IF($L12=0,"",INDEX(Libelles!$I$1:$I$40,MATCH(INDEX(Donnees!$D$1:$D$400,$L12),Libelles!$H$1:$H$40,0))) | D12: =IF($L12=0,"",INDEX(Donnees!$K$1:$K$400,$L12)) | E12: =IF($L12=0,"",INDEX(Donnees!$L$1:$L$400,$L12)+INDEX(Donnees!$M$1:$M$400,$L12)+INDEX(Donnees!$N$1:$N$400,$L12)) | F12: =IF($L12=0,"",$D12-$E12) | G12: =IF($L12=0,"",INDEX(Donnees!$O$1:$O$400,$L12)+INDEX(Donnees!$P$1:$P$400,$L12)+INDEX(Donnees!$Q$1:$Q$400,$L12)+INDEX(Donnees!$R$1:$R$400,$L12)) | H12: =IF($L12=0,"",$F12-$G12) | I12: =IF($L12=0,"",IF($H12<=0,"—",$F12/$H12)) | J12: =IF($L12=0,"",INDEX(Donnees!$AC$1:$AC$400,$L12)) | K12: =IF($L12=0,"",INDEX(Donnees!$AD$1:$AD$400,$L12)) | L12: =IF(ISERROR(MATCH(Simulation!$AC$4&"#"&2,Donnees!$AB$1:$AB$400,0)),0,MATCH(Simulation!$AC$4&"#"&2,Donnees!$AB$1:$AB$400,0))
B13: =IF($L13=0,"",INDEX(Libelles!$F$1:$F$40,MATCH(INDEX(Donnees!$C$1:$C$400,$L13),Libelles!$E$1:$E$40,0))) | C13: =IF($L13=0,"",INDEX(Libelles!$I$1:$I$40,MATCH(INDEX(Donnees!$D$1:$D$400,$L13),Libelles!$H$1:$H$40,0))) | D13: =IF($L13=0,"",INDEX(Donnees!$K$1:$K$400,$L13)) | E13: =IF($L13=0,"",INDEX(Donnees!$L$1:$L$400,$L13)+INDEX(Donnees!$M$1:$M$400,$L13)+INDEX(Donnees!$N$1:$N$400,$L13)) | F13: =IF($L13=0,"",$D13-$E13) | G13: =IF($L13=0,"",INDEX(Donnees!$O$1:$O$400,$L13)+INDEX(Donnees!$P$1:$P$400,$L13)+INDEX(Donnees!$Q$1:$Q$400,$L13)+INDEX(Donnees!$R$1:$R$400,$L13)) | H13: =IF($L13=0,"",$F13-$G13) | I13: =IF($L13=0,"",IF($H13<=0,"—",$F13/$H13)) | J13: =IF($L13=0,"",INDEX(Donnees!$AC$1:$AC$400,$L13)) | K13: =IF($L13=0,"",INDEX(Donnees!$AD$1:$AD$400,$L13)) | L13: =IF(ISERROR(MATCH(Simulation!$AC$4&"#"&3,Donnees!$AB$1:$AB$400,0)),0,MATCH(Simulation!$AC$4&"#"&3,Donnees!$AB$1:$AB$400,0))
B14: =IF($L14=0,"",INDEX(Libelles!$F$1:$F$40,MATCH(INDEX(Donnees!$C$1:$C$400,$L14),Libelles!$E$1:$E$40,0))) | C14: =IF($L14=0,"",INDEX(Libelles!$I$1:$I$40,MATCH(INDEX(Donnees!$D$1:$D$400,$L14),Libelles!$H$1:$H$40,0))) | D14: =IF($L14=0,"",INDEX(Donnees!$K$1:$K$400,$L14)) | E14: =IF($L14=0,"",INDEX(Donnees!$L$1:$L$400,$L14)+INDEX(Donnees!$M$1:$M$400,$L14)+INDEX(Donnees!$N$1:$N$400,$L14)) | F14: =IF($L14=0,"",$D14-$E14) | G14: =IF($L14=0,"",INDEX(Donnees!$O$1:$O$400,$L14)+INDEX(Donnees!$P$1:$P$400,$L14)+INDEX(Donnees!$Q$1:$Q$400,$L14)+INDEX(Donnees!$R$1:$R$400,$L14)) | H14: =IF($L14=0,"",$F14-$G14) | I14: =IF($L14=0,"",IF($H14<=0,"—",$F14/$H14)) | J14: =IF($L14=0,"",INDEX(Donnees!$AC$1:$AC$400,$L14)) | K14: =IF($L14=0,"",INDEX(Donnees!$AD$1:$AD$400,$L14)) | L14: =IF(ISERROR(MATCH(Simulation!$AC$4&"#"&4,Donnees!$AB$1:$AB$400,0)),0,MATCH(Simulation!$AC$4&"#"&4,Donnees!$AB$1:$AB$400,0))
B15: =IF($L15=0,"",INDEX(Libelles!$F$1:$F$40,MATCH(INDEX(Donnees!$C$1:$C$400,$L15),Libelles!$E$1:$E$40,0))) | C15: =IF($L15=0,"",INDEX(Libelles!$I$1:$I$40,MATCH(INDEX(Donnees!$D$1:$D$400,$L15),Libelles!$H$1:$H$40,0))) | D15: =IF($L15=0,"",INDEX(Donnees!$K$1:$K$400,$L15)) | E15: =IF($L15=0,"",INDEX(Donnees!$L$1:$L$400,$L15)+INDEX(Donnees!$M$1:$M$400,$L15)+INDEX(Donnees!$N$1:$N$400,$L15)) | F15: =IF($L15=0,"",$D15-$E15) | G15: =IF($L15=0,"",INDEX(Donnees!$O$1:$O$400,$L15)+INDEX(Donnees!$P$1:$P$400,$L15)+INDEX(Donnees!$Q$1:$Q$400,$L15)+INDEX(Donnees!$R$1:$R$400,$L15)) | H15: =IF($L15=0,"",$F15-$G15) | I15: =IF($L15=0,"",IF($H15<=0,"—",$F15/$H15)) | J15: =IF($L15=0,"",INDEX(Donnees!$AC$1:$AC$400,$L15)) | K15: =IF($L15=0,"",INDEX(Donnees!$AD$1:$AD$400,$L15)) | L15: =IF(ISERROR(MATCH(Simulation!$AC$4&"#"&5,Donnees!$AB$1:$AB$400,0)),0,MATCH(Simulation!$AC$4&"#"&5,Donnees!$AB$1:$AB$400,0))
B16: Total du campus | D16: =SUM(D11:D15) | E16: =SUM(E11:E15) | F16: =SUM(F11:F15) | G16: =SUM(G11:G15) | H16: =SUM(H11:H15) | I16: =IF($H16<=0,"—",$F16/$H16)
B18: ET SI ON FERMAIT UNE FILIÈRE ENTIÈRE ?
F19: =IF($L$4="","—",INDEX(Libelles!$F$1:$F$40,MATCH($L$4,Libelles!$E$1:$E$40,0))) | I19: =IF($L$5="","—",INDEX(Libelles!$F$1:$F$40,MATCH($L$5,Libelles!$E$1:$E$40,0)))
B20: Poste | F20: Montant 2027 | G20: Effet si on ferme | I20: Montant 2027 | J20: Effet si on ferme
B21: Chiffre d'affaires | F21: =IF($L$4="","",SUMIFS(Donnees!$K$4:$K$400,Donnees!$A$4:$A$400,Simulation!$AC$4,Donnees!$C$4:$C$400,$L$4)) | G21: =IF($L$4="","",-SUMIFS(Donnees!$K$4:$K$400,Donnees!$A$4:$A$400,Simulation!$AC$4,Donnees!$C$4:$C$400,$L$4)) | I21: =IF($L$5="","",SUMIFS(Donnees!$K$4:$K$400,Donnees!$A$4:$A$400,Simulation!$AC$4,Donnees!$C$4:$C$400,$L$5)) | J21: =IF($L$5="","",-SUMIFS(Donnees!$K$4:$K$400,Donnees!$A$4:$A$400,Simulation!$AC$4,Donnees!$C$4:$C$400,$L$5))
B22: Vacataires (621) | F22: =IF($L$4="","",SUMIFS(Donnees!$L$4:$L$400,Donnees!$A$4:$A$400,Simulation!$AC$4,Donnees!$C$4:$C$400,$L$4)) | G22: =IF($L$4="","",SUMIFS(Donnees!$L$4:$L$400,Donnees!$A$4:$A$400,Simulation!$AC$4,Donnees!$C$4:$C$400,$L$4)) | I22: =IF($L$5="","",SUMIFS(Donnees!$L$4:$L$400,Donnees!$A$4:$A$400,Simulation!$AC$4,Donnees!$C$4:$C$400,$L$5)) | J22: =IF($L$5="","",SUMIFS(Donnees!$L$4:$L$400,Donnees!$A$4:$A$400,Simulation!$AC$4,Donnees!$C$4:$C$400,$L$5))
B23: Achats d'études et fournitures (604 · 6063) | F23: =IF($L$4="","",SUMIFS(Donnees!$M$4:$M$400,Donnees!$A$4:$A$400,Simulation!$AC$4,Donnees!$C$4:$C$400,$L$4)) | G23: =IF($L$4="","",SUMIFS(Donnees!$M$4:$M$400,Donnees!$A$4:$A$400,Simulation!$AC$4,Donnees!$C$4:$C$400,$L$4)) | I23: =IF($L$5="","",SUMIFS(Donnees!$M$4:$M$400,Donnees!$A$4:$A$400,Simulation!$AC$4,Donnees!$C$4:$C$400,$L$5)) | J23: =IF($L$5="","",SUMIFS(Donnees!$M$4:$M$400,Donnees!$A$4:$A$400,Simulation!$AC$4,Donnees!$C$4:$C$400,$L$5))
B24: Recrutement (6231) | F24: =IF($L$4="","",SUMIFS(Donnees!$N$4:$N$400,Donnees!$A$4:$A$400,Simulation!$AC$4,Donnees!$C$4:$C$400,$L$4)) | G24: =IF($L$4="","",SUMIFS(Donnees!$N$4:$N$400,Donnees!$A$4:$A$400,Simulation!$AC$4,Donnees!$C$4:$C$400,$L$4)) | I24: =IF($L$5="","",SUMIFS(Donnees!$N$4:$N$400,Donnees!$A$4:$A$400,Simulation!$AC$4,Donnees!$C$4:$C$400,$L$5)) | J24: =IF($L$5="","",SUMIFS(Donnees!$N$4:$N$400,Donnees!$A$4:$A$400,Simulation!$AC$4,Donnees!$C$4:$C$400,$L$5))
B25: Enseignants permanents (6411) — restent | F25: =IF($L$4="","",SUMIFS(Donnees!$O$4:$O$400,Donnees!$A$4:$A$400,Simulation!$AC$4,Donnees!$C$4:$C$400,$L$4)) | G25: =IF($L$4="","",0) | I25: =IF($L$5="","",SUMIFS(Donnees!$O$4:$O$400,Donnees!$A$4:$A$400,Simulation!$AC$4,Donnees!$C$4:$C$400,$L$5)) | J25: =IF($L$5="","",0)
B26: Structure du campus (613 · 615 · 616 · 625 · 645 · 6413 · 63511) — reste | F26: =IF($L$4="","",SUMIFS(Donnees!$P$4:$P$400,Donnees!$A$4:$A$400,Simulation!$AC$4,Donnees!$C$4:$C$400,$L$4)) | G26: =IF($L$4="","",0) | I26: =IF($L$5="","",SUMIFS(Donnees!$P$4:$P$400,Donnees!$A$4:$A$400,Simulation!$AC$4,Donnees!$C$4:$C$400,$L$5)) | J26: =IF($L$5="","",0)
B27: Frais de marque et siège (6236 · holding) — restent | F27: =IF($L$4="","",SUMIFS(Donnees!$Q$4:$Q$400,Donnees!$A$4:$A$400,Simulation!$AC$4,Donnees!$C$4:$C$400,$L$4)+SUMIFS(Donnees!$R$4:$R$400,Donnees!$A$4:$A$400,Simulation!$AC$4,Donnees!$C$4:$C$400,$L$4)) | G27: =IF($L$4="","",0) | I27: =IF($L$5="","",SUMIFS(Donnees!$Q$4:$Q$400,Donnees!$A$4:$A$400,Simulation!$AC$4,Donnees!$C$4:$C$400,$L$5)+SUMIFS(Donnees!$R$4:$R$400,Donnees!$A$4:$A$400,Simulation!$AC$4,Donnees!$C$4:$C$400,$L$5)) | J27: =IF($L$5="","",0)
B28: Marge complète affichée par le rapport | F28: =F21-SUM(F22:F27) | I28: =I21-SUM(I22:I27)
B29: la fermeture semble donc rapporter cela en moins | G29: =-F28 | J29: =-I28
B30: EFFET RÉEL SUR L'EBITDA DU CAMPUS | G30: =SUM(G21:G27) | J30: =SUM(J21:J27)
B31: écart : les coûts qui restent et se réallouent sur les classes survivantes | G31: =G30-G29 | J31: =J30-J29
B33: Le rapport au coût complet annonce une marge quasi nulle sur ces filières. La fermer ne fait pourtant pas gagner cette marge : elle fait perdre sa contribution, parce que les permanents, les murs, la marque et le siège restent — et se réallouent sur les classes qui restent.

Sheet Donnees
A1: Q_SIMULATION_CLASSES · scénario 2027BUD_V1 · version V01
A3: CAMPUS | B3: MARQUE | C3: PROGRAMME | D3: ANNEE | E3: MODALITE | F3: ENTREE | G3: GROUPES | H3: CAPACITE | I3: PLACES | J3: EFFECTIF | K3: CA | L3: VACATAIRES | M3: CONSOMMABLES | N3: RECRUTEMENT | O3: PERMANENTS | P3: STRUCTURE | Q3: FRAIS DE MARQUE | R3: SIEGE | S3: COUT DU PROCHAIN INSCRIT | T3: COUT COMPLET | U3: MARGE COMPLETE | V3: CONTRIBUTION | W3: VACATAIRES PAR GROUPE | X3: PERMANENTS PAR GROUPE | Y3: CONSOMMABLES PAR ELEVE | Z3: REMPLISSAGE | AA3: RANG | AB3: CLE | AC3: EFFECTIF PAR GROUPE | AD3: POINT MORT
A4: IPAC_MTP | B4: IPAC | C4: BAC_CCE | D4: B1 | E4: ALT | F4: 1 | G4: 2 | H4: 32 | I4: 64 | J4: 44.7376 | K4: 302351.04 | L4: 24861.44 | M4: 16419.529 | N4: 16392.241 | O4: 48356.4 | P4: 94933.72 | Q4: 8544.09 | R4: 40834.86 | S4: 1033.98 | T4: =SUM(L4:R4) | U4: =K4-T4 | V4: =K4-(L4+M4+N4) | W4: =L4/G4 | X4: =O4/G4 | Y4: =M4/J4 | Z4: =J4/I4 | AA4: =COUNTIFS($A$4:$A4,$A4) | AB4: =$A4&"#"&$AA4 | AC4: =J4/G4 | AD4: =(T4/G4)/(V4/J4)
A5: IPAC_MTP | B5: IPAC | C5: BAC_CCE | D5: B2 | E5: ALT | F5: 0 | G5: 2 | H5: 32 | I5: 64 | J5: 39.2 | K5: 261398.17 | L5: 24861.44 | M5: 14387.127 | N5: 0 | O5: 48356.4 | P5: 94933.72 | Q5: 8544.09 | R5: 40834.86 | S5: 1033.98 | T5: =SUM(L5:R5) | U5: =K5-T5 | V5: =K5-(L5+M5+N5) | W5: =L5/G5 | X5: =O5/G5 | Y5: =M5/J5 | Z5: =J5/I5 | AA5: =COUNTIFS($A$4:$A5,$A5) | AB5: =$A5&"#"&$AA5 | AC5: =J5/G5 | AD5: =(T5/G5)/(V5/J5)
A6: IPAC_MTP | B6: IPAC | C6: BAC_CCE | D6: B3 | E6: ALT | F6: 0 | G6: 2 | H6: 32 | I6: 64 | J6: 38.195 | K6: 254696.51 | L6: 24861.44 | M6: 14018.273 | N6: 0 | O6: 48356.4 | P6: 94933.72 | Q6: 8544.09 | R6: 40834.86 | S6: 1033.98 | T6: =SUM(L6:R6) | U6: =K6-T6 | V6: =K6-(L6+M6+N6) | W6: =L6/G6 | X6: =O6/G6 | Y6: =M6/J6 | Z6: =J6/I6 | AA6: =COUNTIFS($A$4:$A6,$A6) | AB6: =$A6&"#"&$AA6 | AC6: =J6/G6 | AD6: =(T6/G6)/(V6/J6)
A7: IPAC_NAN | B7: IPAC | C7: BAC_CCE | D7: B1 | E7: ALT | F7: 1 | G7: 2 | H7: 32 | I7: 64 | J7: 55.8325 | K7: 396929.38 | L7: 24861.44 | M7: 20496.901 | N7: 23500.809 | O7: 59760.93 | P7: 135129.56 | Q7: 10586.14 | R7: 50594.47 | S7: 1216.28 | T7: =SUM(L7:R7) | U7: =K7-T7 | V7: =K7-(L7+M7+N7) | W7: =L7/G7 | X7: =O7/G7 | Y7: =M7/J7 | Z7: =J7/I7 | AA7: =COUNTIFS($A$4:$A7,$A7) | AB7: =$A7&"#"&$AA7 | AC7: =J7/G7 | AD7: =(T7/G7)/(V7/J7)
A8: IPAC_NAN | B8: IPAC | C8: BAC_CCE | D8: B2 | E8: ALT | F8: 0 | G8: 2 | H8: 32 | I8: 64 | J8: 48.25 | K8: 338680.5 | L8: 24861.44 | M8: 17713.258 | N8: 0 | O8: 59760.93 | P8: 135129.56 | Q8: 10586.14 | R8: 50594.47 | S8: 1216.28 | T8: =SUM(L8:R8) | U8: =K8-T8 | V8: =K8-(L8+M8+N8) | W8: =L8/G8 | X8: =O8/G8 | Y8: =M8/J8 | Z8: =J8/I8 | AA8: =COUNTIFS($A$4:$A8,$A8) | AB8: =$A8&"#"&$AA8 | AC8: =J8/G8 | AD8: =(T8/G8)/(V8/J8)
A9: IPAC_NAN | B9: IPAC | C9: BAC_CCE | D9: B3 | E9: ALT | F9: 0 | G9: 2 | H9: 32 | I9: 64 | J9: 47.24 | K9: 331591.02 | L9: 24861.44 | M9: 17342.472 | N9: 0 | O9: 59760.93 | P9: 135129.56 | Q9: 10586.14 | R9: 50594.47 | S9: 1216.28 | T9: =SUM(L9:R9) | U9: =K9-T9 | V9: =K9-(L9+M9+N9) | W9: =L9/G9 | X9: =O9/G9 | Y9: =M9/J9 | Z9: =J9/I9 | AA9: =COUNTIFS($A$4:$A9,$A9) | AB9: =$A9&"#"&$AA9 | AC9: =J9/G9 | AD9: =(T9/G9)/(V9/J9)
A10: IPAC_REN | B10: IPAC | C10: BAC_CCE | D10: B1 | E10: ALT | F10: 1 | G10: 2 | H10: 32 | I10: 64 | J10: 44.7266 | K10: 302276.65 | L10: 24861.44 | M10: 16416.977 | N10: 16127.633 | O10: 48385.25 | P10: 94990.37 | Q10: 8543.32 | R10: 40831.18 | S10: 1040.55 | T10: =SUM(L10:R10) | U10: =K10-T10 | V10: =K10-(L10+M10+N10) | W10: =L10/G10 | X10: =O10/G10 | Y10: =M10/J10 | Z10: =J10/I10 | AA10: =COUNTIFS($A$4:$A10,$A10) | AB10: =$A10&"#"&$AA10 | AC10: =J10/G10 | AD10: =(T10/G10)/(V10/J10)
A11: IPAC_REN | B11: IPAC | C11: BAC_CCE | D11: B2 | E11: ALT | F11: 0 | G11: 2 | H11: 32 | I11: 64 | J11: 39.2 | K11: 261398.17 | L11: 24861.44 | M11: 14388.428 | N11: 0 | O11: 48385.25 | P11: 94990.37 | Q11: 8543.32 | R11: 40831.18 | S11: 1040.55 | T11: =SUM(L11:R11) | U11: =K11-T11 | V11: =K11-(L11+M11+N11) | W11: =L11/G11 | X11: =O11/G11 | Y11: =M11/J11 | Z11: =J11/I11 | AA11: =COUNTIFS($A$4:$A11,$A11) | AB11: =$A11&"#"&$AA11 | AC11: =J11/G11 | AD11: =(T11/G11)/(V11/J11)
A12: IPAC_REN | B12: IPAC | C12: BAC_CCE | D12: B3 | E12: ALT | F12: 0 | G12: 2 | H12: 32 | I12: 64 | J12: 38.195 | K12: 254696.51 | L12: 24861.44 | M12: 14019.541 | N12: 0 | O12: 48385.25 | P12: 94990.37 | Q12: 8543.32 | R12: 40831.18 | S12: 1040.55 | T12: =SUM(L12:R12) | U12: =K12-T12 | V12: =K12-(L12+M12+N12) | W12: =L12/G12 | X12: =O12/G12 | Y12: =M12/J12 | Z12: =J12/I12 | AA12: =COUNTIFS($A$4:$A12,$A12) | AB12: =$A12&"#"&$AA12 | AC12: =J12/G12 | AD12: =(T12/G12)/(V12/J12)
A13: ISCOM_LIL | B13: ISCOM | C13: BAC_COM | D13: B1 | E13: INIT | F13: 1 | G13: 2 | H13: 32 | I13: 64 | J13: 54.6014 | K13: 407572.86 | L13: 31076.54 | M13: 20009.67 | N13: 13477.63 | O13: 75864.33 | P13: 138138.31 | Q13: 11943.37 | R13: 45455.53 | S13: 978.58 | T13: =SUM(L13:R13) | U13: =K13-T13 | V13: =K13-(L13+M13+N13) | W13: =L13/G13 | X13: =O13/G13 | Y13: =M13/J13 | Z13: =J13/I13 | AA13: =COUNTIFS($A$4:$A13,$A13) | AB13: =$A13&"#"&$AA13 | AC13: =J13/G13 | AD13: =(T13/G13)/(V13/J13)
A14: ISCOM_LIL | B14: ISCOM | C14: BAC_COM | D14: B2 | E14: ALT | F14: 0 | G14: 2 | H14: 32 | I14: 64 | J14: 48.25 | K14: 332098.87 | L14: 24861.24 | M14: 17682.085 | N14: 0 | O14: 60691.47 | P14: 138138.31 | Q14: 11943.37 | R14: 45455.53 | S14: 978.58 | T14: =SUM(L14:R14) | U14: =K14-T14 | V14: =K14-(L14+M14+N14) | W14: =L14/G14 | X14: =O14/G14 | Y14: =M14/J14 | Z14: =J14/I14 | AA14: =COUNTIFS($A$4:$A14,$A14) | AB14: =$A14&"#"&$AA14 | AC14: =J14/G14 | AD14: =(T14/G14)/(V14/J14)
A15: ISCOM_LIL | B15: ISCOM | C15: BAC_COM | D15: B3 | E15: ALT | F15: 0 | G15: 2 | H15: 32 | I15: 64 | J15: 47.24 | K15: 325147.16 | L15: 24861.24 | M15: 17311.952 | N15: 0 | O15: 60691.47 | P15: 138138.31 | Q15: 11943.37 | R15: 45455.53 | S15: 978.58 | T15: =SUM(L15:R15) | U15: =K15-T15 | V15: =K15-(L15+M15+N15) | W15: =L15/G15 | X15: =O15/G15 | Y15: =M15/J15 | Z15: =J15/I15 | AA15: =COUNTIFS($A$4:$A15,$A15) | AB15: =$A15&"#"&$AA15 | AC15: =J15/G15 | AD15: =(T15/G15)/(V15/J15)
... A63: TUNON_PAR | B63: TUNON | C63: BAC_TOU | D63: B3 | E63: ALT | F63: 0 | G63: 2 | H63: 32 | I63: 64 | J63: 45.23 | K63: 355682.97 | L63: 24861.44 | M63: 16657.329 | N63: 0 | O63: 79370.63 | P63: 173558.65 | Q63: 11270.4 | R63: 47691.32 | S63: 2192.89 | T63: =SUM(L63:R63) | U63: =K63-T63 | V63: =K63-(L63+M63+N63) | W63: =L63/G63 | X63: =O63/G63 | Y63: =M63/J63 | Z63: =J63/I63 | AA63: =COUNTIFS($A$4:$A63,$A63) | AB63: =$A63&"#"&$AA63 | AC63: =J63/G63 | AD63: =(T63/G63)/(V63/J63)

Sheet Libelles
B1: TABLE DE CORRESPONDANCE
B2: Le code est la clé technique lue par le masque ; le libellé est ce que voit le lecteur.
B4: code | C4: Campus | E4: code | F4: Programme | H4: code | I4: Année | K4: code | L4: Modalité
B5: IPAC_MTP | C5: Ipac Montpellier | E5: BAC_CCE | F5: Bachelor Commerce | H5: B1 | I5: 1re année | K5: ALT | L5: alternance
B6: IPAC_NAN | C6: Ipac Nantes | E6: BAC_COM | F6: Bachelor Communication | H6: B2 | I6: 2e année | K6: INIT | L6: initial
B7: IPAC_REN | C7: Ipac Rennes | E7: BAC_MGT | F7: Bachelor Management | H7: B3 | I7: 3e année
B8: ISCOM_LIL | C8: ISCOM Lille | E8: BAC_RH | F8: Bachelor Ressources humaines | H8: BTS1 | I8: 1re année
B9: ISCOM_PAR | C9: ISCOM Paris | E9: BAC_TOU | F9: Bachelor Tourisme | H9: BTS2 | I9: 2e année
B10: ISCOM_TLS | C10: ISCOM Toulouse | E10: BTS_GES | F10: BTS Gestion | H10: M1 | I10: M1
B11: MBWAY_BOR | C11: MBway Bordeaux | E11: MAS_COM | F11: Mastère Communication | H11: M2 | I11: M2
B12: MBWAY_LYO | C12: MBway Lyon | E12: MAS_MGT | F12: Mastère Management
B13: MBWAY_NAN | C13: MBway Nantes
B14: MBWAY_PAR | C14: MBway Paris
B15: PIGIER_BOR | C15: Pigier Bordeaux
B16: PIGIER_LYO | C16: Pigier Lyon
B17: TUNON_LYO | C17: Tunon Lyon
B18: TUNON_PAR | C18: Tunon Paris
