Workbook
Name ALLOC_BRAND_CAMP: ALLOC!$C$8
Name ALLOC_CAMP_CLASS: ALLOC!$C$9
Name ALLOC_GRP_BRAND: ALLOC!$C$6
Name ALLOC_GRP_MARQUE: ALLOC!$C$7
Name BUD_REF_CAP: PIL!$K$15:$K$28
Name HYP_ACQ_BUD_V01: cad!$C$23
Name HYP_ACQ_BUD_V02: cad!$D$23
Name HYP_ACQ_BUD_V03: cad!$E$23
Name HYP_BRAND_BUD_V01: cad!$C$24
Name HYP_BRAND_BUD_V02: cad!$D$24
Name HYP_BRAND_BUD_V03: cad!$E$24
Name HYP_CAP_RETENU: PIL!$J$15:$J$28
Name HYP_CONV_ADM_V01: cad!$C$27
Name HYP_CONV_ADM_V02: cad!$D$27
Name HYP_CONV_ADM_V03: cad!$E$27
Name HYP_CONV_LEAD_V01: cad!$C$26
Name HYP_CONV_LEAD_V02: cad!$D$26
Name HYP_CONV_LEAD_V03: cad!$E$26
Name HYP_FEE_V01: cad!$C$39
Name HYP_FEE_V02: cad!$D$39
Name HYP_FEE_V03: cad!$E$39
Name HYP_FTE_PERM_V01: cad!$C$34
Name HYP_FTE_PERM_V02: cad!$D$34
Name HYP_FTE_PERM_V03: cad!$E$34
Name HYP_INFL_EXT_V01: cad!$C$32
Name HYP_INFL_EXT_V02: cad!$D$32
Name HYP_INFL_EXT_V03: cad!$E$32
Name HYP_PASSAGE_V01: cad!$C$28
Name HYP_PASSAGE_V02: cad!$D$28
Name HYP_PASSAGE_V03: cad!$E$28
Name HYP_PRICE_COEF_IPAC: cad!$J$14
Name HYP_PRICE_COEF_ISCOM: cad!$J$13
Name HYP_PRICE_COEF_MBWAY: cad!$J$12
Name HYP_PRICE_COEF_PIGIER: cad!$J$15
Name HYP_PRICE_COEF_TUNON: cad!$J$16
Name HYP_PRICE_V01: cad!$C$25
Name HYP_PRICE_V02: cad!$D$25
Name HYP_PRICE_V03: cad!$E$25
Name HYP_PRODUCTIVITY_V01: cad!$C$35
Name HYP_PRODUCTIVITY_V02: cad!$D$35
Name HYP_PRODUCTIVITY_V03: cad!$E$35
Name HYP_SALARY_V01: cad!$C$33
Name HYP_SALARY_V02: cad!$D$33
Name HYP_SALARY_V03: cad!$E$33
Name HYP_STRUCT_COST_V01: cad!$C$36
Name HYP_STRUCT_COST_V02: cad!$D$36
Name HYP_STRUCT_COST_V03: cad!$E$36
Name SCENARIO_ACTIF: cad!$C$5
Name SCENARIO_CODE: cad!$P$1
Name TEC_EBITDA: cad!$F$6
Name TEC_PL: cad!$F$5

Sheet _TGK_HIDDEN
A1: Template00 | B1: =cad!A65546 -> 0
A2: Template01 | B2: =Socle!A65536 -> 0
A3: Template02 | B3: =Campagne!A65536 -> 0
A4: Template03 | B4: =Moteur!A65536 -> 0
A5: Template04 | B5: =Compta!A65536 -> 0
A6: Template05 | B6: =PNL!A65536 -> 0
A7: Template06 | B7: =PIL!A65538 -> 0
A9: Template08 | B9: =Allocation!A65536 -> 0
A10: Template09 | B10: =ALLOC!B65537 -> 0

Sheet cad
P1: =IF(cad!$C$5="Optimiste","V02",IF(cad!$C$5="Prudent","V03","V01")) -> V02
B2: POSTE DE COMMANDE CFO — Cadrage CA & EBITDA 2027
B5: Scenario actif : | C5: Optimiste | E5: Croissance CA cible : | F5: 0.05
E6: Marge EBITDA cible : | F6: 0.15
B8: Reconciliation — Reference · Cible · Construit (scenario actif) | I8: Coeff prix par marque (decision)
B10: Indicateur | C10: Reference | D10: Cible | E10: Construit | F10: Ecart | G10: Ecart % | I10: Marque | J10: Coeff prix
C11: 2026
B12: Chiffre d'affaires | C12: 22544725 | D12: =C12*(1+cad!$F$5) -> 23671961 | E12: =_xlfn.SUMIFS(Moteur!$R$1:$R$175,Moteur!$B$1:$B$175,cad!$P$1) -> #VALUE! | F12: =E12-D12 -> #VALUE! | G12: =_xlfn.IFERROR(E12/D12-1,0) -> 0 | I12: MBway | J12: 1.2
B13: EBITDA | C13: 3291530 | D13: =D12*cad!$F$6 -> 3550794.2 | E13: =_xlfn.SUMIFS(_CALC_PNL!$T$1:$T$1347,_CALC_PNL!$D$1:$D$1347,cad!$P$1,_CALC_PNL!$C$1:$C$1347,"2027") -> #VALUE! | F13: =E13-D13 -> #VALUE! | G13: =_xlfn.IFERROR(E13/D13-1,0) -> 0 | I13: ISCOM | J13: 1.15
B14: Marge EBITDA % | C14: =_xlfn.IFERROR(C13/C12,0) -> 0.14600001 | D14: =cad!$F$6 -> 0.15 | E14: =_xlfn.IFERROR(E13/E12,0) -> 0 | F14: =E14-D14 -> -0.15 | I14: Ipac Bachelor Factory | J14: 0.95
B15: Effectif | C15: 3036 | E15: =_xlfn.SUMIFS(Moteur!$P$1:$P$175,Moteur!$B$1:$B$175,cad!$P$1) -> #VALUE! | F15: =E15-#REF! -> #VALUE! | G15: =_xlfn.IFERROR(E15/#REF!-1,0) -> 0 | I15: Pigier | J15: 0.9
I16: Tunon | J16: 1.05
B19: Leviers de CROISSANCE / REVENUS
B21: Paramètre | C21: =C22 -> Cadrage | D21: =D22 -> Optimiste | E21: =E22 -> Prudent | F21: ACTIF (scenario)
C22: Cadrage | D22: Optimiste | E22: Prudent
B23: Variation du budget d'acquisition → leads payants | C23: 0.08 | D23: 0.15 | E23: -0.05 | F23: #N/A
B24: Variation du budget de marque → socle organique | C24: 0.1 | D24: 0.2 | E24: -0.05 | F24: #N/A
B25: Hausse tarifaire (prix) | C25: 0.02 | D25: 0.035 | E25: 0.02 | F25: #N/A
B26: Gain du taux de conversion Lead → Candidature | C26: 0.01 | D26: 0.03 | E26: -0.01 | F26: #N/A
B27: Gain du taux de conversion Admis → Inscrit | C27: 0.01 | D27: 0.025 | E27: -0.01 | F27: #N/A
B28: Amélioration du taux de passage | C28: 0.005 | D28: 0.015 | E28: -0.01 | F28: #N/A
B30: Leviers de COUTS
B32: Inflation des charges externes | C32: 0.02 | D32: 0.015 | E32: 0.03 | F32: =INDEX(C32:E32,MATCH(cad!$C$5,$C$22:$E$22,0)) -> 0.015
B33: Politique salariale sur la masse permanente | C33: 0.025 | D33: 0.02 | E33: 0.03 | F33: =INDEX(C33:E33,MATCH(cad!$C$5,$C$22:$E$22,0)) -> 0.02
B34: Variation des effectifs permanents | C34: 0.04 | D34: 0.03 | E34: 0.05 | F34: =INDEX(C34:E34,MATCH(cad!$C$5,$C$22:$E$22,0)) -> 0.03
B35: Effort de productivité sur les achats et la structure | C35: 0.01 | D35: 0.03 | F35: =INDEX(C35:E35,MATCH(cad!$C$5,$C$22:$E$22,0)) -> 0.03
B36: Variation des coûts de structure (loyers, IT, siège…) | D36: -0.03 | E36: 0.04 | F36: =INDEX(C36:E36,MATCH(cad!$C$5,$C$22:$E$22,0)) -> -0.03
B38: Constante — frais de dossier (decision)
B39: Frais de dossier par nouvel inscrit | C39: 90 | D39: 90 | E39: 90 | F39: =INDEX(C39:E39,MATCH(cad!$C$5,$C$22:$E$22,0)) -> 90

Sheet PIL
B2: PILOTAGE · Cockpit de decision CFO — Budget 2027
B6: CA 2027 | D6: EBITDA (après siège) | F6: Marge EBITDA | H6: Effectif | J6: Croissance CA vs 2026
B7: =E49 -> #VALUE! | D7: =H49 -> #VALUE! | F7: =I49 -> 0 | H7: =D49 -> #VALUE! | J7: =_xlfn.IFERROR(E49/cad!$C$12-1,0) -> 0
B12: 1 · Cap strategique par campus (marque x ville) — arbitrage du budget d'acquisition
U13: à masquer | V13: à masquer | W13: à masquer
A14: Campus | B14: Marque | C14: Ville | D14: CAC marginal | E14: Croiss. leads | F14: Intensité mkt | G14: Cap Eff | H14: Cap mom. | I14: Cap pot. | J14: Cap retenu | K14: Budget acq réf. | L14: Entity | U14: CAP_EFF (live) | V14: CAP_MOM (live) | W14: CAP_POT (live)
A15: MBWAY_PAR | B15: MBway | C15: Paris | D15: 1475.0125 | E15: 0.11073637 | F15: 0.021756763 | G15: 0.8149808 | H15: 1.0597054 | I15: 0.86473065 | J15: 1 | K15: 68291 | L15: MBWAY_PAR
A16: MBWAY_LYO | B16: MBway | C16: Lyon | D16: 1101.595 | E16: 0.11887172 | F16: 0.016735257 | G16: 1.0912421 | H16: 1.1375577 | I16: 1.1241979 | J16: 1 | K16: 41783 | L16: MBWAY_LYO
A17: MBWAY_NAN | B17: MBway | C17: Nantes | D17: 963.56901 | E17: 0.1237954 | F17: 0.014610109 | G17: 1.2475566 | H17: 1.1846754 | I17: 1.2877207 | J17: 1 | K17: 31533 | L17: MBWAY_NAN
A18: MBWAY_BOR | B18: MBway | C18: Bordeaux | D18: 889.58534 | E18: 0.12609457 | F18: 0.01405213 | G18: 1.3513114 | H18: 1.2066776 | I18: 1.3388532 | J18: 1 | K18: 24923 | L18: MBWAY_BOR
A19: ISCOM_PAR | B19: ISCOM | C19: Paris | D19: 1540.3212 | E19: 0.077744807 | F19: 0.020902665 | G19: 0.78042607 | H19: 0.74398855 | I19: 0.90006419 | J19: 1 | K19: 60800 | L19: ISCOM_PAR
A20: ISCOM_LIL | B20: ISCOM | C20: Lille | D20: 978.58254 | E20: 0.081545064 | F20: 0.014363413 | G20: 1.2284164 | H20: 0.78035559 | I20: 1.3098377 | J20: 1 | K20: 25220 | L20: ISCOM_LIL
A21: ISCOM_TLS | B21: ISCOM | C21: Toulouse | D21: 919.03491 | E21: 0.082116788 | F21: 0.013564662 | G21: 1.30801 | H21: 0.78582677 | I21: 1.386967 | J21: 1 | K21: 22083 | L21: ISCOM_TLS
A22: IPAC_NAN | B22: Ipac | C22: Nantes | D22: 1216.283 | E22: 0.13788487 | F22: 0.021343795 | G22: 0.98834472 | H22: 1.3195064 | I22: 0.88146178 | J22: 1 | K22: 21760 | L22: IPAC_NAN
A23: IPAC_REN | B23: Ipac | C23: Rennes | D23: 1040.5484 | E23: 0.14478114 | F23: 0.019104458 | G23: 1.1552628 | H23: 1.3855011 | I23: 0.98478271 | J23: 1 | K23: 14933 | L23: IPAC_REN
A24: IPAC_MTP | B24: Ipac | C24: Montpellier | D24: 1033.9757 | E24: 0.14478114 | F24: 0.019417898 | G24: 1.1626065 | H24: 1.3855011 | I24: 0.96888656 | J24: 1 | K24: 15178 | L24: IPAC_MTP
A25: PIGIER_LYO | B25: Pigier | C25: Lyon | D25: 1704.9638 | E25: 0.085003455 | F25: 0.029279527 | G25: 0.70506298 | H25: 0.81345109 | I25: 0.64255614 | J25: 1 | K25: 36612 | L25: PIGIER_LYO
A26: PIGIER_BOR | B26: Pigier | C26: Bordeaux | D26: 1368.0761 | E26: 0.087533156 | F26: 0.024360438 | G26: 0.87868421 | H26: 0.83765937 | I26: 0.77230713 | J26: 1 | K26: 21968 | L26: PIGIER_BOR
... A28: TUNON_LYO | B28: Tunon | C28: Lyon | D28: 1624.6613 | E28: 0.072555205 | F28: 0.021828498 | G28: 0.7399123 | H28: 0.69432601 | I28: 0.86188889 | J28: 1 | K28: 18850 | L28: TUNON_LYO
B30: 2 · Synthese par campus (resultats budget, live)
A32: Campus | B32: Marque | C32: Ville | D32: Effectif | E32: CA 2027 | F32: Prix moy. | G32: Part CA | H32: EBITDA campus | I32: Mrg EBITDA | J32: EBITDA/etud. | K32: Rejoue | L32: CAC marg.
A33: MBWAY_PAR | B33: MBway | C33: Paris | D33: =_xlfn.SUMIFS(Moteur!$P$1:$P$175,Moteur!$D$1:$D$175,$A33,Moteur!$B$1:$B$175,cad!$P$1) -> #VALUE! | E33: =_xlfn.SUMIFS(Moteur!$R$1:$R$175,Moteur!$D$1:$D$175,$A33,Moteur!$B$1:$B$175,cad!$P$1) -> #VALUE! | F33: =_xlfn.IFERROR(E33/D33,0) -> 0 | G33: =_xlfn.IFERROR(E33/SUM($E$33:$E$46),0) -> 0 | H33: =_xlfn.SUMIFS(_CALC_PNL!$T$1:$T$1347,_CALC_PNL!$A$1:$A$1347,$A33,_CALC_PNL!$D$1:$D$1347,cad!$P$1,_CALC_PNL!$C$1:$C$1347,"2027") -> #VALUE! | I33: =_xlfn.IFERROR(H33/E33,0) -> 0 | J33: =_xlfn.IFERROR(H33/D33,0) -> 0 | K33: =_xlfn.SUMIFS(PIL!$K$15:$K$28,PIL!$A$15:$A$28,$A33)*_xlfn.SUMIFS(PIL!$J$15:$J$28,PIL!$A$15:$A$28,$A33)*(SUM(PIL!$K$15:$K$28)/SUMPRODUCT(PIL!$K$15:$K$28,PIL!$J$15:$J$28)) -> 68291 | L33: =_xlfn.SUMIFS(PIL!$D$15:$D$28,PIL!$A$15:$A$28,$A33) -> 1475.0125
A34: MBWAY_LYO | B34: MBway | C34: Lyon | D34: =_xlfn.SUMIFS(Moteur!$P$1:$P$175,Moteur!$D$1:$D$175,$A34,Moteur!$B$1:$B$175,cad!$P$1) -> #VALUE! | E34: =_xlfn.SUMIFS(Moteur!$R$1:$R$175,Moteur!$D$1:$D$175,$A34,Moteur!$B$1:$B$175,cad!$P$1) -> #VALUE! | F34: =_xlfn.IFERROR(E34/D34,0) -> 0 | G34: =_xlfn.IFERROR(E34/SUM($E$33:$E$46),0) -> 0 | H34: =_xlfn.SUMIFS(_CALC_PNL!$T$1:$T$1347,_CALC_PNL!$A$1:$A$1347,$A34,_CALC_PNL!$D$1:$D$1347,cad!$P$1,_CALC_PNL!$C$1:$C$1347,"2027") -> #VALUE! | I34: =_xlfn.IFERROR(H34/E34,0) -> 0 | J34: =_xlfn.IFERROR(H34/D34,0) -> 0 | K34: =_xlfn.SUMIFS(PIL!$K$15:$K$28,PIL!$A$15:$A$28,$A34)*_xlfn.SUMIFS(PIL!$J$15:$J$28,PIL!$A$15:$A$28,$A34)*(SUM(PIL!$K$15:$K$28)/SUMPRODUCT(PIL!$K$15:$K$28,PIL!$J$15:$J$28)) -> 41783 | L34: =_xlfn.SUMIFS(PIL!$D$15:$D$28,PIL!$A$15:$A$28,$A34) -> 1101.595
A35: MBWAY_NAN | B35: MBway | C35: Nantes | D35: =_xlfn.SUMIFS(Moteur!$P$1:$P$175,Moteur!$D$1:$D$175,$A35,Moteur!$B$1:$B$175,cad!$P$1) -> #VALUE! | E35: =_xlfn.SUMIFS(Moteur!$R$1:$R$175,Moteur!$D$1:$D$175,$A35,Moteur!$B$1:$B$175,cad!$P$1) -> #VALUE! | F35: =_xlfn.IFERROR(E35/D35,0) -> 0 | G35: =_xlfn.IFERROR(E35/SUM($E$33:$E$46),0) -> 0 | H35: =_xlfn.SUMIFS(_CALC_PNL!$T$1:$T$1347,_CALC_PNL!$A$1:$A$1347,$A35,_CALC_PNL!$D$1:$D$1347,cad!$P$1,_CALC_PNL!$C$1:$C$1347,"2027") -> #VALUE! | I35: =_xlfn.IFERROR(H35/E35,0) -> 0 | J35: =_xlfn.IFERROR(H35/D35,0) -> 0 | K35: =_xlfn.SUMIFS(PIL!$K$15:$K$28,PIL!$A$15:$A$28,$A35)*_xlfn.SUMIFS(PIL!$J$15:$J$28,PIL!$A$15:$A$28,$A35)*(SUM(PIL!$K$15:$K$28)/SUMPRODUCT(PIL!$K$15:$K$28,PIL!$J$15:$J$28)) -> 31533 | L35: =_xlfn.SUMIFS(PIL!$D$15:$D$28,PIL!$A$15:$A$28,$A35) -> 963.56901
A36: MBWAY_BOR | B36: MBway | C36: Bordeaux | D36: =_xlfn.SUMIFS(Moteur!$P$1:$P$175,Moteur!$D$1:$D$175,$A36,Moteur!$B$1:$B$175,cad!$P$1) -> #VALUE! | E36: =_xlfn.SUMIFS(Moteur!$R$1:$R$175,Moteur!$D$1:$D$175,$A36,Moteur!$B$1:$B$175,cad!$P$1) -> #VALUE! | F36: =_xlfn.IFERROR(E36/D36,0) -> 0 | G36: =_xlfn.IFERROR(E36/SUM($E$33:$E$46),0) -> 0 | H36: =_xlfn.SUMIFS(_CALC_PNL!$T$1:$T$1347,_CALC_PNL!$A$1:$A$1347,$A36,_CALC_PNL!$D$1:$D$1347,cad!$P$1,_CALC_PNL!$C$1:$C$1347,"2027") -> #VALUE! | I36: =_xlfn.IFERROR(H36/E36,0) -> 0 | J36: =_xlfn.IFERROR(H36/D36,0) -> 0 | K36: =_xlfn.SUMIFS(PIL!$K$15:$K$28,PIL!$A$15:$A$28,$A36)*_xlfn.SUMIFS(PIL!$J$15:$J$28,PIL!$A$15:$A$28,$A36)*(SUM(PIL!$K$15:$K$28)/SUMPRODUCT(PIL!$K$15:$K$28,PIL!$J$15:$J$28)) -> 24923 | L36: =_xlfn.SUMIFS(PIL!$D$15:$D$28,PIL!$A$15:$A$28,$A36) -> 889.58534
A37: ISCOM_PAR | B37: ISCOM | C37: Paris | D37: =_xlfn.SUMIFS(Moteur!$P$1:$P$175,Moteur!$D$1:$D$175,$A37,Moteur!$B$1:$B$175,cad!$P$1) -> #VALUE! | E37: =_xlfn.SUMIFS(Moteur!$R$1:$R$175,Moteur!$D$1:$D$175,$A37,Moteur!$B$1:$B$175,cad!$P$1) -> #VALUE! | F37: =_xlfn.IFERROR(E37/D37,0) -> 0 | G37: =_xlfn.IFERROR(E37/SUM($E$33:$E$46),0) -> 0 | H37: =_xlfn.SUMIFS(_CALC_PNL!$T$1:$T$1347,_CALC_PNL!$A$1:$A$1347,$A37,_CALC_PNL!$D$1:$D$1347,cad!$P$1,_CALC_PNL!$C$1:$C$1347,"2027") -> #VALUE! | I37: =_xlfn.IFERROR(H37/E37,0) -> 0 | J37: =_xlfn.IFERROR(H37/D37,0) -> 0 | K37: =_xlfn.SUMIFS(PIL!$K$15:$K$28,PIL!$A$15:$A$28,$A37)*_xlfn.SUMIFS(PIL!$J$15:$J$28,PIL!$A$15:$A$28,$A37)*(SUM(PIL!$K$15:$K$28)/SUMPRODUCT(PIL!$K$15:$K$28,PIL!$J$15:$J$28)) -> 60800 | L37: =_xlfn.SUMIFS(PIL!$D$15:$D$28,PIL!$A$15:$A$28,$A37) -> 1540.3212
A38: ISCOM_LIL | B38: ISCOM | C38: Lille | D38: =_xlfn.SUMIFS(Moteur!$P$1:$P$175,Moteur!$D$1:$D$175,$A38,Moteur!$B$1:$B$175,cad!$P$1) -> #VALUE! | E38: =_xlfn.SUMIFS(Moteur!$R$1:$R$175,Moteur!$D$1:$D$175,$A38,Moteur!$B$1:$B$175,cad!$P$1) -> #VALUE! | F38: =_xlfn.IFERROR(E38/D38,0) -> 0 | G38: =_xlfn.IFERROR(E38/SUM($E$33:$E$46),0) -> 0 | H38: =_xlfn.SUMIFS(_CALC_PNL!$T$1:$T$1347,_CALC_PNL!$A$1:$A$1347,$A38,_CALC_PNL!$D$1:$D$1347,cad!$P$1,_CALC_PNL!$C$1:$C$1347,"2027") -> #VALUE! | I38: =_xlfn.IFERROR(H38/E38,0) -> 0 | J38: =_xlfn.IFERROR(H38/D38,0) -> 0 | K38: =_xlfn.SUMIFS(PIL!$K$15:$K$28,PIL!$A$15:$A$28,$A38)*_xlfn.SUMIFS(PIL!$J$15:$J$28,PIL!$A$15:$A$28,$A38)*(SUM(PIL!$K$15:$K$28)/SUMPRODUCT(PIL!$K$15:$K$28,PIL!$J$15:$J$28)) -> 25220 | L38: =_xlfn.SUMIFS(PIL!$D$15:$D$28,PIL!$A$15:$A$28,$A38) -> 978.58254
A39: ISCOM_TLS | B39: ISCOM | C39: Toulouse | D39: =_xlfn.SUMIFS(Moteur!$P$1:$P$175,Moteur!$D$1:$D$175,$A39,Moteur!$B$1:$B$175,cad!$P$1) -> #VALUE! | E39: =_xlfn.SUMIFS(Moteur!$R$1:$R$175,Moteur!$D$1:$D$175,$A39,Moteur!$B$1:$B$175,cad!$P$1) -> #VALUE! | F39: =_xlfn.IFERROR(E39/D39,0) -> 0 | G39: =_xlfn.IFERROR(E39/SUM($E$33:$E$46),0) -> 0 | H39: =_xlfn.SUMIFS(_CALC_PNL!$T$1:$T$1347,_CALC_PNL!$A$1:$A$1347,$A39,_CALC_PNL!$D$1:$D$1347,cad!$P$1,_CALC_PNL!$C$1:$C$1347,"2027") -> #VALUE! | I39: =_xlfn.IFERROR(H39/E39,0) -> 0 | J39: =_xlfn.IFERROR(H39/D39,0) -> 0 | K39: =_xlfn.SUMIFS(PIL!$K$15:$K$28,PIL!$A$15:$A$28,$A39)*_xlfn.SUMIFS(PIL!$J$15:$J$28,PIL!$A$15:$A$28,$A39)*(SUM(PIL!$K$15:$K$28)/SUMPRODUCT(PIL!$K$15:$K$28,PIL!$J$15:$J$28)) -> 22083 | L39: =_xlfn.SUMIFS(PIL!$D$15:$D$28,PIL!$A$15:$A$28,$A39) -> 919.03491
A40: IPAC_NAN | B40: Ipac | C40: Nantes | D40: =_xlfn.SUMIFS(Moteur!$P$1:$P$175,Moteur!$D$1:$D$175,$A40,Moteur!$B$1:$B$175,cad!$P$1) -> #VALUE! | E40: =_xlfn.SUMIFS(Moteur!$R$1:$R$175,Moteur!$D$1:$D$175,$A40,Moteur!$B$1:$B$175,cad!$P$1) -> #VALUE! | F40: =_xlfn.IFERROR(E40/D40,0) -> 0 | G40: =_xlfn.IFERROR(E40/SUM($E$33:$E$46),0) -> 0 | H40: =_xlfn.SUMIFS(_CALC_PNL!$T$1:$T$1347,_CALC_PNL!$A$1:$A$1347,$A40,_CALC_PNL!$D$1:$D$1347,cad!$P$1,_CALC_PNL!$C$1:$C$1347,"2027") -> #VALUE! | I40: =_xlfn.IFERROR(H40/E40,0) -> 0 | J40: =_xlfn.IFERROR(H40/D40,0) -> 0 | K40: =_xlfn.SUMIFS(PIL!$K$15:$K$28,PIL!$A$15:$A$28,$A40)*_xlfn.SUMIFS(PIL!$J$15:$J$28,PIL!$A$15:$A$28,$A40)*(SUM(PIL!$K$15:$K$28)/SUMPRODUCT(PIL!$K$15:$K$28,PIL!$J$15:$J$28)) -> 21760 | L40: =_xlfn.SUMIFS(PIL!$D$15:$D$28,PIL!$A$15:$A$28,$A40) -> 1216.283
A41: IPAC_REN | B41: Ipac | C41: Rennes | D41: =_xlfn.SUMIFS(Moteur!$P$1:$P$175,Moteur!$D$1:$D$175,$A41,Moteur!$B$1:$B$175,cad!$P$1) -> #VALUE! | E41: =_xlfn.SUMIFS(Moteur!$R$1:$R$175,Moteur!$D$1:$D$175,$A41,Moteur!$B$1:$B$175,cad!$P$1) -> #VALUE! | F41: =_xlfn.IFERROR(E41/D41,0) -> 0 | G41: =_xlfn.IFERROR(E41/SUM($E$33:$E$46),0) -> 0 | H41: =_xlfn.SUMIFS(_CALC_PNL!$T$1:$T$1347,_CALC_PNL!$A$1:$A$1347,$A41,_CALC_PNL!$D$1:$D$1347,cad!$P$1,_CALC_PNL!$C$1:$C$1347,"2027") -> #VALUE! | I41: =_xlfn.IFERROR(H41/E41,0) -> 0 | J41: =_xlfn.IFERROR(H41/D41,0) -> 0 | K41: =_xlfn.SUMIFS(PIL!$K$15:$K$28,PIL!$A$15:$A$28,$A41)*_xlfn.SUMIFS(PIL!$J$15:$J$28,PIL!$A$15:$A$28,$A41)*(SUM(PIL!$K$15:$K$28)/SUMPRODUCT(PIL!$K$15:$K$28,PIL!$J$15:$J$28)) -> 14933 | L41: =_xlfn.SUMIFS(PIL!$D$15:$D$28,PIL!$A$15:$A$28,$A41) -> 1040.5484
A42: IPAC_MTP | B42: Ipac | C42: Montpellier | D42: =_xlfn.SUMIFS(Moteur!$P$1:$P$175,Moteur!$D$1:$D$175,$A42,Moteur!$B$1:$B$175,cad!$P$1) -> #VALUE! | E42: =_xlfn.SUMIFS(Moteur!$R$1:$R$175,Moteur!$D$1:$D$175,$A42,Moteur!$B$1:$B$175,cad!$P$1) -> #VALUE! | F42: =_xlfn.IFERROR(E42/D42,0) -> 0 | G42: =_xlfn.IFERROR(E42/SUM($E$33:$E$46),0) -> 0 | H42: =_xlfn.SUMIFS(_CALC_PNL!$T$1:$T$1347,_CALC_PNL!$A$1:$A$1347,$A42,_CALC_PNL!$D$1:$D$1347,cad!$P$1,_CALC_PNL!$C$1:$C$1347,"2027") -> #VALUE! | I42: =_xlfn.IFERROR(H42/E42,0) -> 0 | J42: =_xlfn.IFERROR(H42/D42,0) -> 0 | K42: =_xlfn.SUMIFS(PIL!$K$15:$K$28,PIL!$A$15:$A$28,$A42)*_xlfn.SUMIFS(PIL!$J$15:$J$28,PIL!$A$15:$A$28,$A42)*(SUM(PIL!$K$15:$K$28)/SUMPRODUCT(PIL!$K$15:$K$28,PIL!$J$15:$J$28)) -> 15178 | L42: =_xlfn.SUMIFS(PIL!$D$15:$D$28,PIL!$A$15:$A$28,$A42) -> 1033.9757
A43: PIGIER_LYO | B43: Pigier | C43: Lyon | D43: =_xlfn.SUMIFS(Moteur!$P$1:$P$175,Moteur!$D$1:$D$175,$A43,Moteur!$B$1:$B$175,cad!$P$1) -> #VALUE! | E43: =_xlfn.SUMIFS(Moteur!$R$1:$R$175,Moteur!$D$1:$D$175,$A43,Moteur!$B$1:$B$175,cad!$P$1) -> #VALUE! | F43: =_xlfn.IFERROR(E43/D43,0) -> 0 | G43: =_xlfn.IFERROR(E43/SUM($E$33:$E$46),0) -> 0 | H43: =_xlfn.SUMIFS(_CALC_PNL!$T$1:$T$1347,_CALC_PNL!$A$1:$A$1347,$A43,_CALC_PNL!$D$1:$D$1347,cad!$P$1,_CALC_PNL!$C$1:$C$1347,"2027") -> #VALUE! | I43: =_xlfn.IFERROR(H43/E43,0) -> 0 | J43: =_xlfn.IFERROR(H43/D43,0) -> 0 | K43: =_xlfn.SUMIFS(PIL!$K$15:$K$28,PIL!$A$15:$A$28,$A43)*_xlfn.SUMIFS(PIL!$J$15:$J$28,PIL!$A$15:$A$28,$A43)*(SUM(PIL!$K$15:$K$28)/SUMPRODUCT(PIL!$K$15:$K$28,PIL!$J$15:$J$28)) -> 36612 | L43: =_xlfn.SUMIFS(PIL!$D$15:$D$28,PIL!$A$15:$A$28,$A43) -> 1704.9638
A44: PIGIER_BOR | B44: Pigier | C44: Bordeaux | D44: =_xlfn.SUMIFS(Moteur!$P$1:$P$175,Moteur!$D$1:$D$175,$A44,Moteur!$B$1:$B$175,cad!$P$1) -> #VALUE! | E44: =_xlfn.SUMIFS(Moteur!$R$1:$R$175,Moteur!$D$1:$D$175,$A44,Moteur!$B$1:$B$175,cad!$P$1) -> #VALUE! | F44: =_xlfn.IFERROR(E44/D44,0) -> 0 | G44: =_xlfn.IFERROR(E44/SUM($E$33:$E$46),0) -> 0 | H44: =_xlfn.SUMIFS(_CALC_PNL!$T$1:$T$1347,_CALC_PNL!$A$1:$A$1347,$A44,_CALC_PNL!$D$1:$D$1347,cad!$P$1,_CALC_PNL!$C$1:$C$1347,"2027") -> #VALUE! | I44: =_xlfn.IFERROR(H44/E44,0) -> 0 | J44: =_xlfn.IFERROR(H44/D44,0) -> 0 | K44: =_xlfn.SUMIFS(PIL!$K$15:$K$28,PIL!$A$15:$A$28,$A44)*_xlfn.SUMIFS(PIL!$J$15:$J$28,PIL!$A$15:$A$28,$A44)*(SUM(PIL!$K$15:$K$28)/SUMPRODUCT(PIL!$K$15:$K$28,PIL!$J$15:$J$28)) -> 21968 | L44: =_xlfn.SUMIFS(PIL!$D$15:$D$28,PIL!$A$15:$A$28,$A44) -> 1368.0761
... A46: TUNON_LYO | B46: Tunon | C46: Lyon | D46: =_xlfn.SUMIFS(Moteur!$P$1:$P$175,Moteur!$D$1:$D$175,$A46,Moteur!$B$1:$B$175,cad!$P$1) -> #VALUE! | E46: =_xlfn.SUMIFS(Moteur!$R$1:$R$175,Moteur!$D$1:$D$175,$A46,Moteur!$B$1:$B$175,cad!$P$1) -> #VALUE! | F46: =_xlfn.IFERROR(E46/D46,0) -> 0 | G46: =_xlfn.IFERROR(E46/SUM($E$33:$E$46),0) -> 0 | H46: =_xlfn.SUMIFS(_CALC_PNL!$T$1:$T$1347,_CALC_PNL!$A$1:$A$1347,$A46,_CALC_PNL!$D$1:$D$1347,cad!$P$1,_CALC_PNL!$C$1:$C$1347,"2027") -> #VALUE! | I46: =_xlfn.IFERROR(H46/E46,0) -> 0 | J46: =_xlfn.IFERROR(H46/D46,0) -> 0 | K46: =_xlfn.SUMIFS(PIL!$K$15:$K$28,PIL!$A$15:$A$28,$A46)*_xlfn.SUMIFS(PIL!$J$15:$J$28,PIL!$A$15:$A$28,$A46)*(SUM(PIL!$K$15:$K$28)/SUMPRODUCT(PIL!$K$15:$K$28,PIL!$J$15:$J$28)) -> 18850 | L46: =_xlfn.SUMIFS(PIL!$D$15:$D$28,PIL!$A$15:$A$28,$A46) -> 1624.6613
A47: Sous-total campus | D47: =SUM(D33:D46) -> #VALUE! | E47: =SUM(E33:E46) -> #VALUE! | F47: =_xlfn.IFERROR(E47/D47,0) -> 0 | G47: =SUM(G33:G46) -> 0 | H47: =SUM(H33:H46) -> #VALUE! | I47: =_xlfn.IFERROR(H47/E47,0) -> 0 | J47: =_xlfn.IFERROR(H47/D47,0) -> 0 | K47: =SUM(K33:K46) -> 434174
A48: Siege / holding (GRP) | H48: =_xlfn.SUMIFS(_CALC_PNL!$T$1:$T$1347,_CALC_PNL!$A$1:$A$1347,"GRP",_CALC_PNL!$D$1:$D$1347,cad!$P$1,_CALC_PNL!$C$1:$C$1347,"2027") -> #VALUE!
A49: GROUPE 2027 V01 | D49: =D47 -> #VALUE! | E49: =E47 -> #VALUE! | F49: =_xlfn.IFERROR(E49/D49,0) -> 0 | G49: =SUM(G33:G46) -> 0 | H49: =H47+H48 -> #VALUE! | I49: =_xlfn.IFERROR(H49/E49,0) -> 0 | J49: =_xlfn.IFERROR(H49/D49,0) -> 0 | K49: =SUM(K33:K46) -> 434174

Sheet ALLOC
N1: =IF($C$6="Chiffre d'affaires","REV_CA",IF($C$6="Nombre de classes","VOL_CLASS","VOL_EFF")) -> VOL_EFF
B2: 3 · ALLOCATION & RENTABILITE — cout complet du groupe a la classe | N2: =IF($C$7="Chiffre d'affaires","REV_CA",IF($C$7="Nombre de classes","VOL_CLASS","VOL_EFF")) -> VOL_EFF
N3: =IF($C$8="Chiffre d'affaires","REV_CA",IF($C$8="Nombre de classes","VOL_CLASS","VOL_EFF")) -> REV_CA
N4: =IF($C$9="Chiffre d'affaires","REV_CA",IF($C$9="Nombre de classes","VOL_CLASS","VOL_EFF")) -> REV_CA
B5: Cles d'allocation (saisie)
B6: Clé d’allocation siège administratif → marque | C6: Effectif
B7: Clé d’allocation Campus → Classe | C7: Effectif
B8: Clé d’allocation Marque → Campus | C8: Chiffre d'affaires
B9: Clé d’allocation Pub de marque → marque | C9: Chiffre d'affaires
B14: Maille fine — deplie campus/classe avec les [+]
B17: Marque ▸ Campus ▸ Classe | C17: Effectif | D17: CA | E17: VAC | F17: PERM | G17: ODIR | H17: STRUCT | I17: Frais marque | J17: Holding | K17: Cout complet | L17: Marge complete | M17: Marge %
B18: MBway | C18: =_xlfn.SUMIFS(Allocation!$I$1:$I$175,Allocation!$C$1:$C$175,"2026",Allocation!$E$1:$E$175,"MBWAY") -> 1249 | D18: =_xlfn.SUMIFS(Allocation!$K$1:$K$175,Allocation!$C$1:$C$175,"2026",Allocation!$E$1:$E$175,"MBWAY") -> 9567455 | E18: =_xlfn.SUMIFS(Allocation!$V$1:$V$175,Allocation!$C$1:$C$175,"2026",Allocation!$E$1:$E$175,"MBWAY") -> 603646 | F18: =_xlfn.SUMIFS(Allocation!$W$1:$W$175,Allocation!$C$1:$C$175,"2026",Allocation!$E$1:$E$175,"MBWAY") -> 1528197 | G18: =_xlfn.SUMIFS(Allocation!$X$1:$X$175,Allocation!$C$1:$C$175,"2026",Allocation!$E$1:$E$175,"MBWAY") -> 631277 | H18: =_xlfn.SUMIFS(Allocation!$Y$1:$Y$175,Allocation!$C$1:$C$175,"2026",Allocation!$E$1:$E$175,"MBWAY") -> 1452771 | I18: =_xlfn.SUMIFS(Allocation!$AC$1:$AC$175,Allocation!$C$1:$C$175,"2026",Allocation!$E$1:$E$175,"MBWAY") -> 676344 | J18: =_xlfn.SUMIFS(Allocation!$Z$1:$Z$175,Allocation!$C$1:$C$175,"2026",Allocation!$E$1:$E$175,"MBWAY") -> 2891983 | K18: =E18+F18+G18+H18+I18+J18 -> 7784218 | L18: =_xlfn.SUMIFS(Allocation!$AA$1:$AA$175,Allocation!$C$1:$C$175,"2026",Allocation!$E$1:$E$175,"MBWAY") -> 1783237 | M18: =_xlfn.IFERROR(L18/D18,0) -> 0.18638572
B19: Paris (MBWAY_PAR) | C19: =_xlfn.SUMIFS(Allocation!$I$1:$I$175,Allocation!$C$1:$C$175,"2026",Allocation!$D$1:$D$175,"MBWAY_PAR") -> 382 | D19: =_xlfn.SUMIFS(Allocation!$K$1:$K$175,Allocation!$C$1:$C$175,"2026",Allocation!$D$1:$D$175,"MBWAY_PAR") -> 3138840 | E19: =_xlfn.SUMIFS(Allocation!$V$1:$V$175,Allocation!$C$1:$C$175,"2026",Allocation!$D$1:$D$175,"MBWAY_PAR") -> 181094 | F19: =_xlfn.SUMIFS(Allocation!$W$1:$W$175,Allocation!$C$1:$C$175,"2026",Allocation!$D$1:$D$175,"MBWAY_PAR") -> 605202 | G19: =_xlfn.SUMIFS(Allocation!$X$1:$X$175,Allocation!$C$1:$C$175,"2026",Allocation!$D$1:$D$175,"MBWAY_PAR") -> 210431 | H19: =_xlfn.SUMIFS(Allocation!$Y$1:$Y$175,Allocation!$C$1:$C$175,"2026",Allocation!$D$1:$D$175,"MBWAY_PAR") -> 1452771 | I19: =_xlfn.SUMIFS(Allocation!$AC$1:$AC$175,Allocation!$C$1:$C$175,"2026",Allocation!$D$1:$D$175,"MBWAY_PAR") -> 676344 | J19: =_xlfn.SUMIFS(Allocation!$Z$1:$Z$175,Allocation!$C$1:$C$175,"2026",Allocation!$D$1:$D$175,"MBWAY_PAR") -> 2891983 | K19: =E19+F19+G19+H19+I19+J19 -> 6017825 | L19: =_xlfn.SUMIFS(Allocation!$AA$1:$AA$175,Allocation!$C$1:$C$175,"2026",Allocation!$D$1:$D$175,"MBWAY_PAR") -> -2878985 | M19: =_xlfn.IFERROR(L19/D19,0) -> -0.91721305
B20: BAC_MGT B1 INIT | C20: =_xlfn.SUMIFS(Allocation!$I$1:$I$175,Allocation!$C$1:$C$175,"2026",Allocation!$D$1:$D$175,"MBWAY_PAR",Allocation!$F$1:$F$175,"BAC_MGT",Allocation!$G$1:$G$175,"B1",Allocation!$H$1:$H$175,"INIT") -> 78 | D20: =_xlfn.SUMIFS(Allocation!$K$1:$K$175,Allocation!$C$1:$C$175,"2026",Allocation!$D$1:$D$175,"MBWAY_PAR",Allocation!$F$1:$F$175,"BAC_MGT",Allocation!$G$1:$G$175,"B1",Allocation!$H$1:$H$175,"INIT") -> 662220 | E20: =_xlfn.SUMIFS(Allocation!$V$1:$V$175,Allocation!$C$1:$C$175,"2026",Allocation!$D$1:$D$175,"MBWAY_PAR",Allocation!$F$1:$F$175,"BAC_MGT",Allocation!$G$1:$G$175,"B1",Allocation!$H$1:$H$175,"INIT") -> 45273.5 | F20: =_xlfn.SUMIFS(Allocation!$W$1:$W$175,Allocation!$C$1:$C$175,"2026",Allocation!$D$1:$D$175,"MBWAY_PAR",Allocation!$F$1:$F$175,"BAC_MGT",Allocation!$G$1:$G$175,"B1",Allocation!$H$1:$H$175,"INIT") -> 151300.5 | G20: =_xlfn.SUMIFS(Allocation!$X$1:$X$175,Allocation!$C$1:$C$175,"2026",Allocation!$D$1:$D$175,"MBWAY_PAR",Allocation!$F$1:$F$175,"BAC_MGT",Allocation!$G$1:$G$175,"B1",Allocation!$H$1:$H$175,"INIT") -> 51787.017 | H20: =_xlfn.SUMIFS(Allocation!$Y$1:$Y$175,Allocation!$C$1:$C$175,"2026",Allocation!$D$1:$D$175,"MBWAY_PAR",Allocation!$F$1:$F$175,"BAC_MGT",Allocation!$G$1:$G$175,"B1",Allocation!$H$1:$H$175,"INIT") -> 1452771 | I20: =_xlfn.SUMIFS(Allocation!$AC$1:$AC$175,Allocation!$C$1:$C$175,"2026",Allocation!$D$1:$D$175,"MBWAY_PAR",Allocation!$F$1:$F$175,"BAC_MGT",Allocation!$G$1:$G$175,"B1",Allocation!$H$1:$H$175,"INIT") -> 676344 | J20: =_xlfn.SUMIFS(Allocation!$Z$1:$Z$175,Allocation!$C$1:$C$175,"2026",Allocation!$D$1:$D$175,"MBWAY_PAR",Allocation!$F$1:$F$175,"BAC_MGT",Allocation!$G$1:$G$175,"B1",Allocation!$H$1:$H$175,"INIT") -> 2891983 | K20: =E20+F20+G20+H20+I20+J20 -> 5269459 | L20: =_xlfn.SUMIFS(Allocation!$AA$1:$AA$175,Allocation!$C$1:$C$175,"2026",Allocation!$D$1:$D$175,"MBWAY_PAR",Allocation!$F$1:$F$175,"BAC_MGT",Allocation!$G$1:$G$175,"B1",Allocation!$H$1:$H$175,"INIT") -> -4607239 | M20: =_xlfn.IFERROR(L20/D20,0) -> -6.9572635
B21: BAC_MGT B2 ALT | C21: =_xlfn.SUMIFS(Allocation!$I$1:$I$175,Allocation!$C$1:$C$175,"2026",Allocation!$D$1:$D$175,"MBWAY_PAR",Allocation!$F$1:$F$175,"BAC_MGT",Allocation!$G$1:$G$175,"B2",Allocation!$H$1:$H$175,"ALT") -> 76 | D21: =_xlfn.SUMIFS(Allocation!$K$1:$K$175,Allocation!$C$1:$C$175,"2026",Allocation!$D$1:$D$175,"MBWAY_PAR",Allocation!$F$1:$F$175,"BAC_MGT",Allocation!$G$1:$G$175,"B2",Allocation!$H$1:$H$175,"ALT") -> 595840 | E21: =_xlfn.SUMIFS(Allocation!$V$1:$V$175,Allocation!$C$1:$C$175,"2026",Allocation!$D$1:$D$175,"MBWAY_PAR",Allocation!$F$1:$F$175,"BAC_MGT",Allocation!$G$1:$G$175,"B2",Allocation!$H$1:$H$175,"ALT") -> 36218.8 | F21: =_xlfn.SUMIFS(Allocation!$W$1:$W$175,Allocation!$C$1:$C$175,"2026",Allocation!$D$1:$D$175,"MBWAY_PAR",Allocation!$F$1:$F$175,"BAC_MGT",Allocation!$G$1:$G$175,"B2",Allocation!$H$1:$H$175,"ALT") -> 121040.4 | G21: =_xlfn.SUMIFS(Allocation!$X$1:$X$175,Allocation!$C$1:$C$175,"2026",Allocation!$D$1:$D$175,"MBWAY_PAR",Allocation!$F$1:$F$175,"BAC_MGT",Allocation!$G$1:$G$175,"B2",Allocation!$H$1:$H$175,"ALT") -> 28279.162 | H21: =_xlfn.SUMIFS(Allocation!$Y$1:$Y$175,Allocation!$C$1:$C$175,"2026",Allocation!$D$1:$D$175,"MBWAY_PAR",Allocation!$F$1:$F$175,"BAC_MGT",Allocation!$G$1:$G$175,"B2",Allocation!$H$1:$H$175,"ALT") -> 0 | I21: =_xlfn.SUMIFS(Allocation!$AC$1:$AC$175,Allocation!$C$1:$C$175,"2026",Allocation!$D$1:$D$175,"MBWAY_PAR",Allocation!$F$1:$F$175,"BAC_MGT",Allocation!$G$1:$G$175,"B2",Allocation!$H$1:$H$175,"ALT") -> 0 | J21: =_xlfn.SUMIFS(Allocation!$Z$1:$Z$175,Allocation!$C$1:$C$175,"2026",Allocation!$D$1:$D$175,"MBWAY_PAR",Allocation!$F$1:$F$175,"BAC_MGT",Allocation!$G$1:$G$175,"B2",Allocation!$H$1:$H$175,"ALT") -> 0 | K21: =E21+F21+G21+H21+I21+J21 -> 185538.36 | L21: =_xlfn.SUMIFS(Allocation!$AA$1:$AA$175,Allocation!$C$1:$C$175,"2026",Allocation!$D$1:$D$175,"MBWAY_PAR",Allocation!$F$1:$F$175,"BAC_MGT",Allocation!$G$1:$G$175,"B2",Allocation!$H$1:$H$175,"ALT") -> 410301.64 | M21: =_xlfn.IFERROR(L21/D21,0) -> 0.68861043
B22: BAC_MGT B3 ALT | C22: =_xlfn.SUMIFS(Allocation!$I$1:$I$175,Allocation!$C$1:$C$175,"2026",Allocation!$D$1:$D$175,"MBWAY_PAR",Allocation!$F$1:$F$175,"BAC_MGT",Allocation!$G$1:$G$175,"B3",Allocation!$H$1:$H$175,"ALT") -> 74 | D22: =_xlfn.SUMIFS(Allocation!$K$1:$K$175,Allocation!$C$1:$C$175,"2026",Allocation!$D$1:$D$175,"MBWAY_PAR",Allocation!$F$1:$F$175,"BAC_MGT",Allocation!$G$1:$G$175,"B3",Allocation!$H$1:$H$175,"ALT") -> 580160 | E22: =_xlfn.SUMIFS(Allocation!$V$1:$V$175,Allocation!$C$1:$C$175,"2026",Allocation!$D$1:$D$175,"MBWAY_PAR",Allocation!$F$1:$F$175,"BAC_MGT",Allocation!$G$1:$G$175,"B3",Allocation!$H$1:$H$175,"ALT") -> 36218.8 | F22: =_xlfn.SUMIFS(Allocation!$W$1:$W$175,Allocation!$C$1:$C$175,"2026",Allocation!$D$1:$D$175,"MBWAY_PAR",Allocation!$F$1:$F$175,"BAC_MGT",Allocation!$G$1:$G$175,"B3",Allocation!$H$1:$H$175,"ALT") -> 121040.4 | G22: =_xlfn.SUMIFS(Allocation!$X$1:$X$175,Allocation!$C$1:$C$175,"2026",Allocation!$D$1:$D$175,"MBWAY_PAR",Allocation!$F$1:$F$175,"BAC_MGT",Allocation!$G$1:$G$175,"B3",Allocation!$H$1:$H$175,"ALT") -> 27534.974 | H22: =_xlfn.SUMIFS(Allocation!$Y$1:$Y$175,Allocation!$C$1:$C$175,"2026",Allocation!$D$1:$D$175,"MBWAY_PAR",Allocation!$F$1:$F$175,"BAC_MGT",Allocation!$G$1:$G$175,"B3",Allocation!$H$1:$H$175,"ALT") -> 0 | I22: =_xlfn.SUMIFS(Allocation!$AC$1:$AC$175,Allocation!$C$1:$C$175,"2026",Allocation!$D$1:$D$175,"MBWAY_PAR",Allocation!$F$1:$F$175,"BAC_MGT",Allocation!$G$1:$G$175,"B3",Allocation!$H$1:$H$175,"ALT") -> 0 | J22: =_xlfn.SUMIFS(Allocation!$Z$1:$Z$175,Allocation!$C$1:$C$175,"2026",Allocation!$D$1:$D$175,"MBWAY_PAR",Allocation!$F$1:$F$175,"BAC_MGT",Allocation!$G$1:$G$175,"B3",Allocation!$H$1:$H$175,"ALT") -> 0 | K22: =E22+F22+G22+H22+I22+J22 -> 184794.17 | L22: =_xlfn.SUMIFS(Allocation!$AA$1:$AA$175,Allocation!$C$1:$C$175,"2026",Allocation!$D$1:$D$175,"MBWAY_PAR",Allocation!$F$1:$F$175,"BAC_MGT",Allocation!$G$1:$G$175,"B3",Allocation!$H$1:$H$175,"ALT") -> 395365.83 | M22: =_xlfn.IFERROR(L22/D22,0) -> 0.68147722
B23: MAS_MGT M1 ALT | C23: =_xlfn.SUMIFS(Allocation!$I$1:$I$175,Allocation!$C$1:$C$175,"2026",Allocation!$D$1:$D$175,"MBWAY_PAR",Allocation!$F$1:$F$175,"MAS_MGT",Allocation!$G$1:$G$175,"M1",Allocation!$H$1:$H$175,"ALT") -> 78 | D23: =_xlfn.SUMIFS(Allocation!$K$1:$K$175,Allocation!$C$1:$C$175,"2026",Allocation!$D$1:$D$175,"MBWAY_PAR",Allocation!$F$1:$F$175,"MAS_MGT",Allocation!$G$1:$G$175,"M1",Allocation!$H$1:$H$175,"ALT") -> 662220 | E23: =_xlfn.SUMIFS(Allocation!$V$1:$V$175,Allocation!$C$1:$C$175,"2026",Allocation!$D$1:$D$175,"MBWAY_PAR",Allocation!$F$1:$F$175,"MAS_MGT",Allocation!$G$1:$G$175,"M1",Allocation!$H$1:$H$175,"ALT") -> 31691.45 | F23: =_xlfn.SUMIFS(Allocation!$W$1:$W$175,Allocation!$C$1:$C$175,"2026",Allocation!$D$1:$D$175,"MBWAY_PAR",Allocation!$F$1:$F$175,"MAS_MGT",Allocation!$G$1:$G$175,"M1",Allocation!$H$1:$H$175,"ALT") -> 105910.35 | G23: =_xlfn.SUMIFS(Allocation!$X$1:$X$175,Allocation!$C$1:$C$175,"2026",Allocation!$D$1:$D$175,"MBWAY_PAR",Allocation!$F$1:$F$175,"MAS_MGT",Allocation!$G$1:$G$175,"M1",Allocation!$H$1:$H$175,"ALT") -> 74550.684 | H23: =_xlfn.SUMIFS(Allocation!$Y$1:$Y$175,Allocation!$C$1:$C$175,"2026",Allocation!$D$1:$D$175,"MBWAY_PAR",Allocation!$F$1:$F$175,"MAS_MGT",Allocation!$G$1:$G$175,"M1",Allocation!$H$1:$H$175,"ALT") -> 0 | I23: =_xlfn.SUMIFS(Allocation!$AC$1:$AC$175,Allocation!$C$1:$C$175,"2026",Allocation!$D$1:$D$175,"MBWAY_PAR",Allocation!$F$1:$F$175,"MAS_MGT",Allocation!$G$1:$G$175,"M1",Allocation!$H$1:$H$175,"ALT") -> 0 | J23: =_xlfn.SUMIFS(Allocation!$Z$1:$Z$175,Allocation!$C$1:$C$175,"2026",Allocation!$D$1:$D$175,"MBWAY_PAR",Allocation!$F$1:$F$175,"MAS_MGT",Allocation!$G$1:$G$175,"M1",Allocation!$H$1:$H$175,"ALT") -> 0 | K23: =E23+F23+G23+H23+I23+J23 -> 212152.48 | L23: =_xlfn.SUMIFS(Allocation!$AA$1:$AA$175,Allocation!$C$1:$C$175,"2026",Allocation!$D$1:$D$175,"MBWAY_PAR",Allocation!$F$1:$F$175,"MAS_MGT",Allocation!$G$1:$G$175,"M1",Allocation!$H$1:$H$175,"ALT") -> 450067.52 | M23: =_xlfn.IFERROR(L23/D23,0) -> 0.67963444
B24: MAS_MGT M2 ALT | C24: =_xlfn.SUMIFS(Allocation!$I$1:$I$175,Allocation!$C$1:$C$175,"2026",Allocation!$D$1:$D$175,"MBWAY_PAR",Allocation!$F$1:$F$175,"MAS_MGT",Allocation!$G$1:$G$175,"M2",Allocation!$H$1:$H$175,"ALT") -> 76 | D24: =_xlfn.SUMIFS(Allocation!$K$1:$K$175,Allocation!$C$1:$C$175,"2026",Allocation!$D$1:$D$175,"MBWAY_PAR",Allocation!$F$1:$F$175,"MAS_MGT",Allocation!$G$1:$G$175,"M2",Allocation!$H$1:$H$175,"ALT") -> 638400 | E24: =_xlfn.SUMIFS(Allocation!$V$1:$V$175,Allocation!$C$1:$C$175,"2026",Allocation!$D$1:$D$175,"MBWAY_PAR",Allocation!$F$1:$F$175,"MAS_MGT",Allocation!$G$1:$G$175,"M2",Allocation!$H$1:$H$175,"ALT") -> 31691.45 | F24: =_xlfn.SUMIFS(Allocation!$W$1:$W$175,Allocation!$C$1:$C$175,"2026",Allocation!$D$1:$D$175,"MBWAY_PAR",Allocation!$F$1:$F$175,"MAS_MGT",Allocation!$G$1:$G$175,"M2",Allocation!$H$1:$H$175,"ALT") -> 105910.35 | G24: =_xlfn.SUMIFS(Allocation!$X$1:$X$175,Allocation!$C$1:$C$175,"2026",Allocation!$D$1:$D$175,"MBWAY_PAR",Allocation!$F$1:$F$175,"MAS_MGT",Allocation!$G$1:$G$175,"M2",Allocation!$H$1:$H$175,"ALT") -> 28279.162 | H24: =_xlfn.SUMIFS(Allocation!$Y$1:$Y$175,Allocation!$C$1:$C$175,"2026",Allocation!$D$1:$D$175,"MBWAY_PAR",Allocation!$F$1:$F$175,"MAS_MGT",Allocation!$G$1:$G$175,"M2",Allocation!$H$1:$H$175,"ALT") -> 0 | I24: =_xlfn.SUMIFS(Allocation!$AC$1:$AC$175,Allocation!$C$1:$C$175,"2026",Allocation!$D$1:$D$175,"MBWAY_PAR",Allocation!$F$1:$F$175,"MAS_MGT",Allocation!$G$1:$G$175,"M2",Allocation!$H$1:$H$175,"ALT") -> 0 | J24: =_xlfn.SUMIFS(Allocation!$Z$1:$Z$175,Allocation!$C$1:$C$175,"2026",Allocation!$D$1:$D$175,"MBWAY_PAR",Allocation!$F$1:$F$175,"MAS_MGT",Allocation!$G$1:$G$175,"M2",Allocation!$H$1:$H$175,"ALT") -> 0 | K24: =E24+F24+G24+H24+I24+J24 -> 165880.96 | L24: =_xlfn.SUMIFS(Allocation!$AA$1:$AA$175,Allocation!$C$1:$C$175,"2026",Allocation!$D$1:$D$175,"MBWAY_PAR",Allocation!$F$1:$F$175,"MAS_MGT",Allocation!$G$1:$G$175,"M2",Allocation!$H$1:$H$175,"ALT") -> 472519.04 | M24: =_xlfn.IFERROR(L24/D24,0) -> 0.7401614
B25: Lyon (MBWAY_LYO) | C25: =_xlfn.SUMIFS(Allocation!$I$1:$I$175,Allocation!$C$1:$C$175,"2026",Allocation!$D$1:$D$175,"MBWAY_LYO") -> 324 | D25: =_xlfn.SUMIFS(Allocation!$K$1:$K$175,Allocation!$C$1:$C$175,"2026",Allocation!$D$1:$D$175,"MBWAY_LYO") -> 2496705 | E25: =_xlfn.SUMIFS(Allocation!$V$1:$V$175,Allocation!$C$1:$C$175,"2026",Allocation!$D$1:$D$175,"MBWAY_LYO") -> 156948 | F25: =_xlfn.SUMIFS(Allocation!$W$1:$W$175,Allocation!$C$1:$C$175,"2026",Allocation!$D$1:$D$175,"MBWAY_LYO") -> 362623 | G25: =_xlfn.SUMIFS(Allocation!$X$1:$X$175,Allocation!$C$1:$C$175,"2026",Allocation!$D$1:$D$175,"MBWAY_LYO") -> 162342 | H25: =_xlfn.SUMIFS(Allocation!$Y$1:$Y$175,Allocation!$C$1:$C$175,"2026",Allocation!$D$1:$D$175,"MBWAY_LYO") -> 0 | I25: =_xlfn.SUMIFS(Allocation!$AC$1:$AC$175,Allocation!$C$1:$C$175,"2026",Allocation!$D$1:$D$175,"MBWAY_LYO") -> 0 | J25: =_xlfn.SUMIFS(Allocation!$Z$1:$Z$175,Allocation!$C$1:$C$175,"2026",Allocation!$D$1:$D$175,"MBWAY_LYO") -> 0 | K25: =E25+F25+G25+H25+I25+J25 -> 681913 | L25: =_xlfn.SUMIFS(Allocation!$AA$1:$AA$175,Allocation!$C$1:$C$175,"2026",Allocation!$D$1:$D$175,"MBWAY_LYO") -> 1814792 | M25: =_xlfn.IFERROR(L25/D25,0) -> 0.72687482
B26: BAC_MGT B1 INIT | C26: =_xlfn.SUMIFS(Allocation!$I$1:$I$175,Allocation!$C$1:$C$175,"2026",Allocation!$D$1:$D$175,"MBWAY_LYO",Allocation!$F$1:$F$175,"BAC_MGT",Allocation!$G$1:$G$175,"B1",Allocation!$H$1:$H$175,"INIT") -> 66 | D26: =_xlfn.SUMIFS(Allocation!$K$1:$K$175,Allocation!$C$1:$C$175,"2026",Allocation!$D$1:$D$175,"MBWAY_LYO",Allocation!$F$1:$F$175,"BAC_MGT",Allocation!$G$1:$G$175,"B1",Allocation!$H$1:$H$175,"INIT") -> 525690 | E26: =_xlfn.SUMIFS(Allocation!$V$1:$V$175,Allocation!$C$1:$C$175,"2026",Allocation!$D$1:$D$175,"MBWAY_LYO",Allocation!$F$1:$F$175,"BAC_MGT",Allocation!$G$1:$G$175,"B1",Allocation!$H$1:$H$175,"INIT") -> 45273.462 | F26: =_xlfn.SUMIFS(Allocation!$W$1:$W$175,Allocation!$C$1:$C$175,"2026",Allocation!$D$1:$D$175,"MBWAY_LYO",Allocation!$F$1:$F$175,"BAC_MGT",Allocation!$G$1:$G$175,"B1",Allocation!$H$1:$H$175,"INIT") -> 104602.79 | G26: =_xlfn.SUMIFS(Allocation!$X$1:$X$175,Allocation!$C$1:$C$175,"2026",Allocation!$D$1:$D$175,"MBWAY_LYO",Allocation!$F$1:$F$175,"BAC_MGT",Allocation!$G$1:$G$175,"B1",Allocation!$H$1:$H$175,"INIT") -> 45449.815 | H26: =_xlfn.SUMIFS(Allocation!$Y$1:$Y$175,Allocation!$C$1:$C$175,"2026",Allocation!$D$1:$D$175,"MBWAY_LYO",Allocation!$F$1:$F$175,"BAC_MGT",Allocation!$G$1:$G$175,"B1",Allocation!$H$1:$H$175,"INIT") -> 0 | I26: =_xlfn.SUMIFS(Allocation!$AC$1:$AC$175,Allocation!$C$1:$C$175,"2026",Allocation!$D$1:$D$175,"MBWAY_LYO",Allocation!$F$1:$F$175,"BAC_MGT",Allocation!$G$1:$G$175,"B1",Allocation!$H$1:$H$175,"INIT") -> 0 | J26: =_xlfn.SUMIFS(Allocation!$Z$1:$Z$175,Allocation!$C$1:$C$175,"2026",Allocation!$D$1:$D$175,"MBWAY_LYO",Allocation!$F$1:$F$175,"BAC_MGT",Allocation!$G$1:$G$175,"B1",Allocation!$H$1:$H$175,"INIT") -> 0 | K26: =E26+F26+G26+H26+I26+J26 -> 195326.06 | L26: =_xlfn.SUMIFS(Allocation!$AA$1:$AA$175,Allocation!$C$1:$C$175,"2026",Allocation!$D$1:$D$175,"MBWAY_LYO",Allocation!$F$1:$F$175,"BAC_MGT",Allocation!$G$1:$G$175,"B1",Allocation!$H$1:$H$175,"INIT") -> 330363.94 | M26: =_xlfn.IFERROR(L26/D26,0) -> 0.62843869
B27: BAC_MGT B2 ALT | C27: =_xlfn.SUMIFS(Allocation!$I$1:$I$175,Allocation!$C$1:$C$175,"2026",Allocation!$D$1:$D$175,"MBWAY_LYO",Allocation!$F$1:$F$175,"BAC_MGT",Allocation!$G$1:$G$175,"B2",Allocation!$H$1:$H$175,"ALT") -> 64 | D27: =_xlfn.SUMIFS(Allocation!$K$1:$K$175,Allocation!$C$1:$C$175,"2026",Allocation!$D$1:$D$175,"MBWAY_LYO",Allocation!$F$1:$F$175,"BAC_MGT",Allocation!$G$1:$G$175,"B2",Allocation!$H$1:$H$175,"ALT") -> 470400 | E27: =_xlfn.SUMIFS(Allocation!$V$1:$V$175,Allocation!$C$1:$C$175,"2026",Allocation!$D$1:$D$175,"MBWAY_LYO",Allocation!$F$1:$F$175,"BAC_MGT",Allocation!$G$1:$G$175,"B2",Allocation!$H$1:$H$175,"ALT") -> 24145.846 | F27: =_xlfn.SUMIFS(Allocation!$W$1:$W$175,Allocation!$C$1:$C$175,"2026",Allocation!$D$1:$D$175,"MBWAY_LYO",Allocation!$F$1:$F$175,"BAC_MGT",Allocation!$G$1:$G$175,"B2",Allocation!$H$1:$H$175,"ALT") -> 55788.154 | G27: =_xlfn.SUMIFS(Allocation!$X$1:$X$175,Allocation!$C$1:$C$175,"2026",Allocation!$D$1:$D$175,"MBWAY_LYO",Allocation!$F$1:$F$175,"BAC_MGT",Allocation!$G$1:$G$175,"B2",Allocation!$H$1:$H$175,"ALT") -> 23814.123 | H27: =_xlfn.SUMIFS(Allocation!$Y$1:$Y$175,Allocation!$C$1:$C$175,"2026",Allocation!$D$1:$D$175,"MBWAY_LYO",Allocation!$F$1:$F$175,"BAC_MGT",Allocation!$G$1:$G$175,"B2",Allocation!$H$1:$H$175,"ALT") -> 0 | I27: =_xlfn.SUMIFS(Allocation!$AC$1:$AC$175,Allocation!$C$1:$C$175,"2026",Allocation!$D$1:$D$175,"MBWAY_LYO",Allocation!$F$1:$F$175,"BAC_MGT",Allocation!$G$1:$G$175,"B2",Allocation!$H$1:$H$175,"ALT") -> 0 | J27: =_xlfn.SUMIFS(Allocation!$Z$1:$Z$175,Allocation!$C$1:$C$175,"2026",Allocation!$D$1:$D$175,"MBWAY_LYO",Allocation!$F$1:$F$175,"BAC_MGT",Allocation!$G$1:$G$175,"B2",Allocation!$H$1:$H$175,"ALT") -> 0 | K27: =E27+F27+G27+H27+I27+J27 -> 103748.12 | L27: =_xlfn.SUMIFS(Allocation!$AA$1:$AA$175,Allocation!$C$1:$C$175,"2026",Allocation!$D$1:$D$175,"MBWAY_LYO",Allocation!$F$1:$F$175,"BAC_MGT",Allocation!$G$1:$G$175,"B2",Allocation!$H$1:$H$175,"ALT") -> 366651.88 | M27: =_xlfn.IFERROR(L27/D27,0) -> 0.77944702
B28: BAC_MGT B3 ALT | C28: =_xlfn.SUMIFS(Allocation!$I$1:$I$175,Allocation!$C$1:$C$175,"2026",Allocation!$D$1:$D$175,"MBWAY_LYO",Allocation!$F$1:$F$175,"BAC_MGT",Allocation!$G$1:$G$175,"B3",Allocation!$H$1:$H$175,"ALT") -> 63 | D28: =_xlfn.SUMIFS(Allocation!$K$1:$K$175,Allocation!$C$1:$C$175,"2026",Allocation!$D$1:$D$175,"MBWAY_LYO",Allocation!$F$1:$F$175,"BAC_MGT",Allocation!$G$1:$G$175,"B3",Allocation!$H$1:$H$175,"ALT") -> 463050 | E28: =_xlfn.SUMIFS(Allocation!$V$1:$V$175,Allocation!$C$1:$C$175,"2026",Allocation!$D$1:$D$175,"MBWAY_LYO",Allocation!$F$1:$F$175,"BAC_MGT",Allocation!$G$1:$G$175,"B3",Allocation!$H$1:$H$175,"ALT") -> 24145.846 | F28: =_xlfn.SUMIFS(Allocation!$W$1:$W$175,Allocation!$C$1:$C$175,"2026",Allocation!$D$1:$D$175,"MBWAY_LYO",Allocation!$F$1:$F$175,"BAC_MGT",Allocation!$G$1:$G$175,"B3",Allocation!$H$1:$H$175,"ALT") -> 55788.154 | G28: =_xlfn.SUMIFS(Allocation!$X$1:$X$175,Allocation!$C$1:$C$175,"2026",Allocation!$D$1:$D$175,"MBWAY_LYO",Allocation!$F$1:$F$175,"BAC_MGT",Allocation!$G$1:$G$175,"B3",Allocation!$H$1:$H$175,"ALT") -> 23442.028 | H28: =_xlfn.SUMIFS(Allocation!$Y$1:$Y$175,Allocation!$C$1:$C$175,"2026",Allocation!$D$1:$D$175,"MBWAY_LYO",Allocation!$F$1:$F$175,"BAC_MGT",Allocation!$G$1:$G$175,"B3",Allocation!$H$1:$H$175,"ALT") -> 0 | I28: =_xlfn.SUMIFS(Allocation!$AC$1:$AC$175,Allocation!$C$1:$C$175,"2026",Allocation!$D$1:$D$175,"MBWAY_LYO",Allocation!$F$1:$F$175,"BAC_MGT",Allocation!$G$1:$G$175,"B3",Allocation!$H$1:$H$175,"ALT") -> 0 | J28: =_xlfn.SUMIFS(Allocation!$Z$1:$Z$175,Allocation!$C$1:$C$175,"2026",Allocation!$D$1:$D$175,"MBWAY_LYO",Allocation!$F$1:$F$175,"BAC_MGT",Allocation!$G$1:$G$175,"B3",Allocation!$H$1:$H$175,"ALT") -> 0 | K28: =E28+F28+G28+H28+I28+J28 -> 103376.03 | L28: =_xlfn.SUMIFS(Allocation!$AA$1:$AA$175,Allocation!$C$1:$C$175,"2026",Allocation!$D$1:$D$175,"MBWAY_LYO",Allocation!$F$1:$F$175,"BAC_MGT",Allocation!$G$1:$G$175,"B3",Allocation!$H$1:$H$175,"ALT") -> 359673.97 | M28: =_xlfn.IFERROR(L28/D28,0) -> 0.77674975
B29: MAS_MGT M1 ALT | C29: =_xlfn.SUMIFS(Allocation!$I$1:$I$175,Allocation!$C$1:$C$175,"2026",Allocation!$D$1:$D$175,"MBWAY_LYO",Allocation!$F$1:$F$175,"MAS_MGT",Allocation!$G$1:$G$175,"M1",Allocation!$H$1:$H$175,"ALT") -> 66 | D29: =_xlfn.SUMIFS(Allocation!$K$1:$K$175,Allocation!$C$1:$C$175,"2026",Allocation!$D$1:$D$175,"MBWAY_LYO",Allocation!$F$1:$F$175,"MAS_MGT",Allocation!$G$1:$G$175,"M1",Allocation!$H$1:$H$175,"ALT") -> 525690 | E29: =_xlfn.SUMIFS(Allocation!$V$1:$V$175,Allocation!$C$1:$C$175,"2026",Allocation!$D$1:$D$175,"MBWAY_LYO",Allocation!$F$1:$F$175,"MAS_MGT",Allocation!$G$1:$G$175,"M1",Allocation!$H$1:$H$175,"ALT") -> 31691.423 | F29: =_xlfn.SUMIFS(Allocation!$W$1:$W$175,Allocation!$C$1:$C$175,"2026",Allocation!$D$1:$D$175,"MBWAY_LYO",Allocation!$F$1:$F$175,"MAS_MGT",Allocation!$G$1:$G$175,"M1",Allocation!$H$1:$H$175,"ALT") -> 73221.952 | G29: =_xlfn.SUMIFS(Allocation!$X$1:$X$175,Allocation!$C$1:$C$175,"2026",Allocation!$D$1:$D$175,"MBWAY_LYO",Allocation!$F$1:$F$175,"MAS_MGT",Allocation!$G$1:$G$175,"M1",Allocation!$H$1:$H$175,"ALT") -> 45449.815 | H29: =_xlfn.SUMIFS(Allocation!$Y$1:$Y$175,Allocation!$C$1:$C$175,"2026",Allocation!$D$1:$D$175,"MBWAY_LYO",Allocation!$F$1:$F$175,"MAS_MGT",Allocation!$G$1:$G$175,"M1",Allocation!$H$1:$H$175,"ALT") -> 0 | I29: =_xlfn.SUMIFS(Allocation!$AC$1:$AC$175,Allocation!$C$1:$C$175,"2026",Allocation!$D$1:$D$175,"MBWAY_LYO",Allocation!$F$1:$F$175,"MAS_MGT",Allocation!$G$1:$G$175,"M1",Allocation!$H$1:$H$175,"ALT") -> 0 | J29: =_xlfn.SUMIFS(Allocation!$Z$1:$Z$175,Allocation!$C$1:$C$175,"2026",Allocation!$D$1:$D$175,"MBWAY_LYO",Allocation!$F$1:$F$175,"MAS_MGT",Allocation!$G$1:$G$175,"M1",Allocation!$H$1:$H$175,"ALT") -> 0 | K29: =E29+F29+G29+H29+I29+J29 -> 150363.19 | L29: =_xlfn.SUMIFS(Allocation!$AA$1:$AA$175,Allocation!$C$1:$C$175,"2026",Allocation!$D$1:$D$175,"MBWAY_LYO",Allocation!$F$1:$F$175,"MAS_MGT",Allocation!$G$1:$G$175,"M1",Allocation!$H$1:$H$175,"ALT") -> 375326.81 | M29: =_xlfn.IFERROR(L29/D29,0) -> 0.71396985
B30: MAS_MGT M2 ALT | C30: =_xlfn.SUMIFS(Allocation!$I$1:$I$175,Allocation!$C$1:$C$175,"2026",Allocation!$D$1:$D$175,"MBWAY_LYO",Allocation!$F$1:$F$175,"MAS_MGT",Allocation!$G$1:$G$175,"M2",Allocation!$H$1:$H$175,"ALT") -> 65 | D30: =_xlfn.SUMIFS(Allocation!$K$1:$K$175,Allocation!$C$1:$C$175,"2026",Allocation!$D$1:$D$175,"MBWAY_LYO",Allocation!$F$1:$F$175,"MAS_MGT",Allocation!$G$1:$G$175,"M2",Allocation!$H$1:$H$175,"ALT") -> 511875 | E30: =_xlfn.SUMIFS(Allocation!$V$1:$V$175,Allocation!$C$1:$C$175,"2026",Allocation!$D$1:$D$175,"MBWAY_LYO",Allocation!$F$1:$F$175,"MAS_MGT",Allocation!$G$1:$G$175,"M2",Allocation!$H$1:$H$175,"ALT") -> 31691.423 | F30: =_xlfn.SUMIFS(Allocation!$W$1:$W$175,Allocation!$C$1:$C$175,"2026",Allocation!$D$1:$D$175,"MBWAY_LYO",Allocation!$F$1:$F$175,"MAS_MGT",Allocation!$G$1:$G$175,"M2",Allocation!$H$1:$H$175,"ALT") -> 73221.952 | G30: =_xlfn.SUMIFS(Allocation!$X$1:$X$175,Allocation!$C$1:$C$175,"2026",Allocation!$D$1:$D$175,"MBWAY_LYO",Allocation!$F$1:$F$175,"MAS_MGT",Allocation!$G$1:$G$175,"M2",Allocation!$H$1:$H$175,"ALT") -> 24186.219 | H30: =_xlfn.SUMIFS(Allocation!$Y$1:$Y$175,Allocation!$C$1:$C$175,"2026",Allocation!$D$1:$D$175,"MBWAY_LYO",Allocation!$F$1:$F$175,"MAS_MGT",Allocation!$G$1:$G$175,"M2",Allocation!$H$1:$H$175,"ALT") -> 0 | I30: =_xlfn.SUMIFS(Allocation!$AC$1:$AC$175,Allocation!$C$1:$C$175,"2026",Allocation!$D$1:$D$175,"MBWAY_LYO",Allocation!$F$1:$F$175,"MAS_MGT",Allocation!$G$1:$G$175,"M2",Allocation!$H$1:$H$175,"ALT") -> 0 | J30: =_xlfn.SUMIFS(Allocation!$Z$1:$Z$175,Allocation!$C$1:$C$175,"2026",Allocation!$D$1:$D$175,"MBWAY_LYO",Allocation!$F$1:$F$175,"MAS_MGT",Allocation!$G$1:$G$175,"M2",Allocation!$H$1:$H$175,"ALT") -> 0 | K30: =E30+F30+G30+H30+I30+J30 -> 129099.59 | L30: =_xlfn.SUMIFS(Allocation!$AA$1:$AA$175,Allocation!$C$1:$C$175,"2026",Allocation!$D$1:$D$175,"MBWAY_LYO",Allocation!$F$1:$F$175,"MAS_MGT",Allocation!$G$1:$G$175,"M2",Allocation!$H$1:$H$175,"ALT") -> 382775.41 | M30: =_xlfn.IFERROR(L30/D30,0) -> 0.74779078
B31: Nantes (MBWAY_NAN) | C31: =_xlfn.SUMIFS(Allocation!$I$1:$I$175,Allocation!$C$1:$C$175,"2026",Allocation!$D$1:$D$175,"MBWAY_NAN") -> 294 | D31: =_xlfn.SUMIFS(Allocation!$K$1:$K$175,Allocation!$C$1:$C$175,"2026",Allocation!$D$1:$D$175,"MBWAY_NAN") -> 2158300 | E31: =_xlfn.SUMIFS(Allocation!$V$1:$V$175,Allocation!$C$1:$C$175,"2026",Allocation!$D$1:$D$175,"MBWAY_NAN") -> 144875 | F31: =_xlfn.SUMIFS(Allocation!$W$1:$W$175,Allocation!$C$1:$C$175,"2026",Allocation!$D$1:$D$175,"MBWAY_NAN") -> 298865 | G31: =_xlfn.SUMIFS(Allocation!$X$1:$X$175,Allocation!$C$1:$C$175,"2026",Allocation!$D$1:$D$175,"MBWAY_NAN") -> 140929 | H31: =_xlfn.SUMIFS(Allocation!$Y$1:$Y$175,Allocation!$C$1:$C$175,"2026",Allocation!$D$1:$D$175,"MBWAY_NAN") -> 0 | I31: =_xlfn.SUMIFS(Allocation!$AC$1:$AC$175,Allocation!$C$1:$C$175,"2026",Allocation!$D$1:$D$175,"MBWAY_NAN") -> 0 | J31: =_xlfn.SUMIFS(Allocation!$Z$1:$Z$175,Allocation!$C$1:$C$175,"2026",Allocation!$D$1:$D$175,"MBWAY_NAN") -> 0 | K31: =E31+F31+G31+H31+I31+J31 -> 584669 | L31: =_xlfn.SUMIFS(Allocation!$AA$1:$AA$175,Allocation!$C$1:$C$175,"2026",Allocation!$D$1:$D$175,"MBWAY_NAN") -> 1573631 | M31: =_xlfn.IFERROR(L31/D31,0) -> 0.7291067
B32: BAC_MGT B1 INIT | C32: =_xlfn.SUMIFS(Allocation!$I$1:$I$175,Allocation!$C$1:$C$175,"2026",Allocation!$D$1:$D$175,"MBWAY_NAN",Allocation!$F$1:$F$175,"BAC_MGT",Allocation!$G$1:$G$175,"B1",Allocation!$H$1:$H$175,"INIT") -> 60 | D32: =_xlfn.SUMIFS(Allocation!$K$1:$K$175,Allocation!$C$1:$C$175,"2026",Allocation!$D$1:$D$175,"MBWAY_NAN",Allocation!$F$1:$F$175,"BAC_MGT",Allocation!$G$1:$G$175,"B1",Allocation!$H$1:$H$175,"INIT") -> 455400 | E32: =_xlfn.SUMIFS(Allocation!$V$1:$V$175,Allocation!$C$1:$C$175,"2026",Allocation!$D$1:$D$175,"MBWAY_NAN",Allocation!$F$1:$F$175,"BAC_MGT",Allocation!$G$1:$G$175,"B1",Allocation!$H$1:$H$175,"INIT") -> 30824.468 | F32: =_xlfn.SUMIFS(Allocation!$W$1:$W$175,Allocation!$C$1:$C$175,"2026",Allocation!$D$1:$D$175,"MBWAY_NAN",Allocation!$F$1:$F$175,"BAC_MGT",Allocation!$G$1:$G$175,"B1",Allocation!$H$1:$H$175,"INIT") -> 63588.298 | G32: =_xlfn.SUMIFS(Allocation!$X$1:$X$175,Allocation!$C$1:$C$175,"2026",Allocation!$D$1:$D$175,"MBWAY_NAN",Allocation!$F$1:$F$175,"BAC_MGT",Allocation!$G$1:$G$175,"B1",Allocation!$H$1:$H$175,"INIT") -> 38092.214 | H32: =_xlfn.SUMIFS(Allocation!$Y$1:$Y$175,Allocation!$C$1:$C$175,"2026",Allocation!$D$1:$D$175,"MBWAY_NAN",Allocation!$F$1:$F$175,"BAC_MGT",Allocation!$G$1:$G$175,"B1",Allocation!$H$1:$H$175,"INIT") -> 0 | I32: =_xlfn.SUMIFS(Allocation!$AC$1:$AC$175,Allocation!$C$1:$C$175,"2026",Allocation!$D$1:$D$175,"MBWAY_NAN",Allocation!$F$1:$F$175,"BAC_MGT",Allocation!$G$1:$G$175,"B1",Allocation!$H$1:$H$175,"INIT") -> 0 | J32: =_xlfn.SUMIFS(Allocation!$Z$1:$Z$175,Allocation!$C$1:$C$175,"2026",Allocation!$D$1:$D$175,"MBWAY_NAN",Allocation!$F$1:$F$175,"BAC_MGT",Allocation!$G$1:$G$175,"B1",Allocation!$H$1:$H$175,"INIT") -> 0 | K32: =E32+F32+G32+H32+I32+J32 -> 132504.98 | L32: =_xlfn.SUMIFS(Allocation!$AA$1:$AA$175,Allocation!$C$1:$C$175,"2026",Allocation!$D$1:$D$175,"MBWAY_NAN",Allocation!$F$1:$F$175,"BAC_MGT",Allocation!$G$1:$G$175,"B1",Allocation!$H$1:$H$175,"INIT") -> 322895.02 | M32: =_xlfn.IFERROR(L32/D32,0) -> 0.70903606
B33: BAC_MGT B2 ALT | C33: =_xlfn.SUMIFS(Allocation!$I$1:$I$175,Allocation!$C$1:$C$175,"2026",Allocation!$D$1:$D$175,"MBWAY_NAN",Allocation!$F$1:$F$175,"BAC_MGT",Allocation!$G$1:$G$175,"B2",Allocation!$H$1:$H$175,"ALT") -> 58 | D33: =_xlfn.SUMIFS(Allocation!$K$1:$K$175,Allocation!$C$1:$C$175,"2026",Allocation!$D$1:$D$175,"MBWAY_NAN",Allocation!$F$1:$F$175,"BAC_MGT",Allocation!$G$1:$G$175,"B2",Allocation!$H$1:$H$175,"ALT") -> 406000 | E33: =_xlfn.SUMIFS(Allocation!$V$1:$V$175,Allocation!$C$1:$C$175,"2026",Allocation!$D$1:$D$175,"MBWAY_NAN",Allocation!$F$1:$F$175,"BAC_MGT",Allocation!$G$1:$G$175,"B2",Allocation!$H$1:$H$175,"ALT") -> 24659.574 | F33: =_xlfn.SUMIFS(Allocation!$W$1:$W$175,Allocation!$C$1:$C$175,"2026",Allocation!$D$1:$D$175,"MBWAY_NAN",Allocation!$F$1:$F$175,"BAC_MGT",Allocation!$G$1:$G$175,"B2",Allocation!$H$1:$H$175,"ALT") -> 50870.638 | G33: =_xlfn.SUMIFS(Allocation!$X$1:$X$175,Allocation!$C$1:$C$175,"2026",Allocation!$D$1:$D$175,"MBWAY_NAN",Allocation!$F$1:$F$175,"BAC_MGT",Allocation!$G$1:$G$175,"B2",Allocation!$H$1:$H$175,"ALT") -> 21581.524 | H33: =_xlfn.SUMIFS(Allocation!$Y$1:$Y$175,Allocation!$C$1:$C$175,"2026",Allocation!$D$1:$D$175,"MBWAY_NAN",Allocation!$F$1:$F$175,"BAC_MGT",Allocation!$G$1:$G$175,"B2",Allocation!$H$1:$H$175,"ALT") -> 0 | I33: =_xlfn.SUMIFS(Allocation!$AC$1:$AC$175,Allocation!$C$1:$C$175,"2026",Allocation!$D$1:$D$175,"MBWAY_NAN",Allocation!$F$1:$F$175,"BAC_MGT",Allocation!$G$1:$G$175,"B2",Allocation!$H$1:$H$175,"ALT") -> 0 | J33: =_xlfn.SUMIFS(Allocation!$Z$1:$Z$175,Allocation!$C$1:$C$175,"2026",Allocation!$D$1:$D$175,"MBWAY_NAN",Allocation!$F$1:$F$175,"BAC_MGT",Allocation!$G$1:$G$175,"B2",Allocation!$H$1:$H$175,"ALT") -> 0 | K33: =E33+F33+G33+H33+I33+J33 -> 97111.737 | L33: =_xlfn.SUMIFS(Allocation!$AA$1:$AA$175,Allocation!$C$1:$C$175,"2026",Allocation!$D$1:$D$175,"MBWAY_NAN",Allocation!$F$1:$F$175,"BAC_MGT",Allocation!$G$1:$G$175,"B2",Allocation!$H$1:$H$175,"ALT") -> 308888.26 | M33: =_xlfn.IFERROR(L33/D33,0) -> 0.76080853
B34: BAC_MGT B3 ALT | C34: =_xlfn.SUMIFS(Allocation!$I$1:$I$175,Allocation!$C$1:$C$175,"2026",Allocation!$D$1:$D$175,"MBWAY_NAN",Allocation!$F$1:$F$175,"BAC_MGT",Allocation!$G$1:$G$175,"B3",Allocation!$H$1:$H$175,"ALT") -> 57 | D34: =_xlfn.SUMIFS(Allocation!$K$1:$K$175,Allocation!$C$1:$C$175,"2026",Allocation!$D$1:$D$175,"MBWAY_NAN",Allocation!$F$1:$F$175,"BAC_MGT",Allocation!$G$1:$G$175,"B3",Allocation!$H$1:$H$175,"ALT") -> 399000 | E34: =_xlfn.SUMIFS(Allocation!$V$1:$V$175,Allocation!$C$1:$C$175,"2026",Allocation!$D$1:$D$175,"MBWAY_NAN",Allocation!$F$1:$F$175,"BAC_MGT",Allocation!$G$1:$G$175,"B3",Allocation!$H$1:$H$175,"ALT") -> 24659.574 | F34: =_xlfn.SUMIFS(Allocation!$W$1:$W$175,Allocation!$C$1:$C$175,"2026",Allocation!$D$1:$D$175,"MBWAY_NAN",Allocation!$F$1:$F$175,"BAC_MGT",Allocation!$G$1:$G$175,"B3",Allocation!$H$1:$H$175,"ALT") -> 50870.638 | G34: =_xlfn.SUMIFS(Allocation!$X$1:$X$175,Allocation!$C$1:$C$175,"2026",Allocation!$D$1:$D$175,"MBWAY_NAN",Allocation!$F$1:$F$175,"BAC_MGT",Allocation!$G$1:$G$175,"B3",Allocation!$H$1:$H$175,"ALT") -> 21209.429 | H34: =_xlfn.SUMIFS(Allocation!$Y$1:$Y$175,Allocation!$C$1:$C$175,"2026",Allocation!$D$1:$D$175,"MBWAY_NAN",Allocation!$F$1:$F$175,"BAC_MGT",Allocation!$G$1:$G$175,"B3",Allocation!$H$1:$H$175,"ALT") -> 0 | I34: =_xlfn.SUMIFS(Allocation!$AC$1:$AC$175,Allocation!$C$1:$C$175,"2026",Allocation!$D$1:$D$175,"MBWAY_NAN",Allocation!$F$1:$F$175,"BAC_MGT",Allocation!$G$1:$G$175,"B3",Allocation!$H$1:$H$175,"ALT") -> 0 | J34: =_xlfn.SUMIFS(Allocation!$Z$1:$Z$175,Allocation!$C$1:$C$175,"2026",Allocation!$D$1:$D$175,"MBWAY_NAN",Allocation!$F$1:$F$175,"BAC_MGT",Allocation!$G$1:$G$175,"B3",Allocation!$H$1:$H$175,"ALT") -> 0 | K34: =E34+F34+G34+H34+I34+J34 -> 96739.641 | L34: =_xlfn.SUMIFS(Allocation!$AA$1:$AA$175,Allocation!$C$1:$C$175,"2026",Allocation!$D$1:$D$175,"MBWAY_NAN",Allocation!$F$1:$F$175,"BAC_MGT",Allocation!$G$1:$G$175,"B3",Allocation!$H$1:$H$175,"ALT") -> 302260.36 | M34: =_xlfn.IFERROR(L34/D34,0) -> 0.75754476
B35: MAS_MGT M1 ALT | C35: =_xlfn.SUMIFS(Allocation!$I$1:$I$175,Allocation!$C$1:$C$175,"2026",Allocation!$D$1:$D$175,"MBWAY_NAN",Allocation!$F$1:$F$175,"MAS_MGT",Allocation!$G$1:$G$175,"M1",Allocation!$H$1:$H$175,"ALT") -> 60 | D35: =_xlfn.SUMIFS(Allocation!$K$1:$K$175,Allocation!$C$1:$C$175,"2026",Allocation!$D$1:$D$175,"MBWAY_NAN",Allocation!$F$1:$F$175,"MAS_MGT",Allocation!$G$1:$G$175,"M1",Allocation!$H$1:$H$175,"ALT") -> 455400 | E35: =_xlfn.SUMIFS(Allocation!$V$1:$V$175,Allocation!$C$1:$C$175,"2026",Allocation!$D$1:$D$175,"MBWAY_NAN",Allocation!$F$1:$F$175,"MAS_MGT",Allocation!$G$1:$G$175,"M1",Allocation!$H$1:$H$175,"ALT") -> 32365.691 | F35: =_xlfn.SUMIFS(Allocation!$W$1:$W$175,Allocation!$C$1:$C$175,"2026",Allocation!$D$1:$D$175,"MBWAY_NAN",Allocation!$F$1:$F$175,"MAS_MGT",Allocation!$G$1:$G$175,"M1",Allocation!$H$1:$H$175,"ALT") -> 66767.713 | G35: =_xlfn.SUMIFS(Allocation!$X$1:$X$175,Allocation!$C$1:$C$175,"2026",Allocation!$D$1:$D$175,"MBWAY_NAN",Allocation!$F$1:$F$175,"MAS_MGT",Allocation!$G$1:$G$175,"M1",Allocation!$H$1:$H$175,"ALT") -> 38092.214 | H35: =_xlfn.SUMIFS(Allocation!$Y$1:$Y$175,Allocation!$C$1:$C$175,"2026",Allocation!$D$1:$D$175,"MBWAY_NAN",Allocation!$F$1:$F$175,"MAS_MGT",Allocation!$G$1:$G$175,"M1",Allocation!$H$1:$H$175,"ALT") -> 0 | I35: =_xlfn.SUMIFS(Allocation!$AC$1:$AC$175,Allocation!$C$1:$C$175,"2026",Allocation!$D$1:$D$175,"MBWAY_NAN",Allocation!$F$1:$F$175,"MAS_MGT",Allocation!$G$1:$G$175,"M1",Allocation!$H$1:$H$175,"ALT") -> 0 | J35: =_xlfn.SUMIFS(Allocation!$Z$1:$Z$175,Allocation!$C$1:$C$175,"2026",Allocation!$D$1:$D$175,"MBWAY_NAN",Allocation!$F$1:$F$175,"MAS_MGT",Allocation!$G$1:$G$175,"M1",Allocation!$H$1:$H$175,"ALT") -> 0 | K35: =E35+F35+G35+H35+I35+J35 -> 137225.62 | L35: =_xlfn.SUMIFS(Allocation!$AA$1:$AA$175,Allocation!$C$1:$C$175,"2026",Allocation!$D$1:$D$175,"MBWAY_NAN",Allocation!$F$1:$F$175,"MAS_MGT",Allocation!$G$1:$G$175,"M1",Allocation!$H$1:$H$175,"ALT") -> 318174.38 | M35: =_xlfn.IFERROR(L35/D35,0) -> 0.69867014
B36: MAS_MGT M2 ALT | C36: =_xlfn.SUMIFS(Allocation!$I$1:$I$175,Allocation!$C$1:$C$175,"2026",Allocation!$D$1:$D$175,"MBWAY_NAN",Allocation!$F$1:$F$175,"MAS_MGT",Allocation!$G$1:$G$175,"M2",Allocation!$H$1:$H$175,"ALT") -> 59 | D36: =_xlfn.SUMIFS(Allocation!$K$1:$K$175,Allocation!$C$1:$C$175,"2026",Allocation!$D$1:$D$175,"MBWAY_NAN",Allocation!$F$1:$F$175,"MAS_MGT",Allocation!$G$1:$G$175,"M2",Allocation!$H$1:$H$175,"ALT") -> 442500 | E36: =_xlfn.SUMIFS(Allocation!$V$1:$V$175,Allocation!$C$1:$C$175,"2026",Allocation!$D$1:$D$175,"MBWAY_NAN",Allocation!$F$1:$F$175,"MAS_MGT",Allocation!$G$1:$G$175,"M2",Allocation!$H$1:$H$175,"ALT") -> 32365.691 | F36: =_xlfn.SUMIFS(Allocation!$W$1:$W$175,Allocation!$C$1:$C$175,"2026",Allocation!$D$1:$D$175,"MBWAY_NAN",Allocation!$F$1:$F$175,"MAS_MGT",Allocation!$G$1:$G$175,"M2",Allocation!$H$1:$H$175,"ALT") -> 66767.713 | G36: =_xlfn.SUMIFS(Allocation!$X$1:$X$175,Allocation!$C$1:$C$175,"2026",Allocation!$D$1:$D$175,"MBWAY_NAN",Allocation!$F$1:$F$175,"MAS_MGT",Allocation!$G$1:$G$175,"M2",Allocation!$H$1:$H$175,"ALT") -> 21953.619 | H36: =_xlfn.SUMIFS(Allocation!$Y$1:$Y$175,Allocation!$C$1:$C$175,"2026",Allocation!$D$1:$D$175,"MBWAY_NAN",Allocation!$F$1:$F$175,"MAS_MGT",Allocation!$G$1:$G$175,"M2",Allocation!$H$1:$H$175,"ALT") -> 0 | I36: =_xlfn.SUMIFS(Allocation!$AC$1:$AC$175,Allocation!$C$1:$C$175,"2026",Allocation!$D$1:$D$175,"MBWAY_NAN",Allocation!$F$1:$F$175,"MAS_MGT",Allocation!$G$1:$G$175,"M2",Allocation!$H$1:$H$175,"ALT") -> 0 | J36: =_xlfn.SUMIFS(Allocation!$Z$1:$Z$175,Allocation!$C$1:$C$175,"2026",Allocation!$D$1:$D$175,"MBWAY_NAN",Allocation!$F$1:$F$175,"MAS_MGT",Allocation!$G$1:$G$175,"M2",Allocation!$H$1:$H$175,"ALT") -> 0 | K36: =E36+F36+G36+H36+I36+J36 -> 121087.02 | L36: =_xlfn.SUMIFS(Allocation!$AA$1:$AA$175,Allocation!$C$1:$C$175,"2026",Allocation!$D$1:$D$175,"MBWAY_NAN",Allocation!$F$1:$F$175,"MAS_MGT",Allocation!$G$1:$G$175,"M2",Allocation!$H$1:$H$175,"ALT") -> 321412.98 | M36: =_xlfn.IFERROR(L36/D36,0) -> 0.72635701
B37: Bordeaux (MBWAY_BOR) | C37: =_xlfn.SUMIFS(Allocation!$I$1:$I$175,Allocation!$C$1:$C$175,"2026",Allocation!$D$1:$D$175,"MBWAY_BOR") -> 249 | D37: =_xlfn.SUMIFS(Allocation!$K$1:$K$175,Allocation!$C$1:$C$175,"2026",Allocation!$D$1:$D$175,"MBWAY_BOR") -> 1773610 | E37: =_xlfn.SUMIFS(Allocation!$V$1:$V$175,Allocation!$C$1:$C$175,"2026",Allocation!$D$1:$D$175,"MBWAY_BOR") -> 120729 | F37: =_xlfn.SUMIFS(Allocation!$W$1:$W$175,Allocation!$C$1:$C$175,"2026",Allocation!$D$1:$D$175,"MBWAY_BOR") -> 261507 | G37: =_xlfn.SUMIFS(Allocation!$X$1:$X$175,Allocation!$C$1:$C$175,"2026",Allocation!$D$1:$D$175,"MBWAY_BOR") -> 117575 | H37: =_xlfn.SUMIFS(Allocation!$Y$1:$Y$175,Allocation!$C$1:$C$175,"2026",Allocation!$D$1:$D$175,"MBWAY_BOR") -> 0 | I37: =_xlfn.SUMIFS(Allocation!$AC$1:$AC$175,Allocation!$C$1:$C$175,"2026",Allocation!$D$1:$D$175,"MBWAY_BOR") -> 0 | J37: =_xlfn.SUMIFS(Allocation!$Z$1:$Z$175,Allocation!$C$1:$C$175,"2026",Allocation!$D$1:$D$175,"MBWAY_BOR") -> 0 | K37: =E37+F37+G37+H37+I37+J37 -> 499811 | L37: =_xlfn.SUMIFS(Allocation!$AA$1:$AA$175,Allocation!$C$1:$C$175,"2026",Allocation!$D$1:$D$175,"MBWAY_BOR") -> 1273799 | M37: =_xlfn.IFERROR(L37/D37,0) -> 0.71819566
B38: BAC_MGT B1 INIT | C38: =_xlfn.SUMIFS(Allocation!$I$1:$I$175,Allocation!$C$1:$C$175,"2026",Allocation!$D$1:$D$175,"MBWAY_BOR",Allocation!$F$1:$F$175,"BAC_MGT",Allocation!$G$1:$G$175,"B1",Allocation!$H$1:$H$175,"INIT") -> 51 | D38: =_xlfn.SUMIFS(Allocation!$K$1:$K$175,Allocation!$C$1:$C$175,"2026",Allocation!$D$1:$D$175,"MBWAY_BOR",Allocation!$F$1:$F$175,"BAC_MGT",Allocation!$G$1:$G$175,"B1",Allocation!$H$1:$H$175,"INIT") -> 375615 | E38: =_xlfn.SUMIFS(Allocation!$V$1:$V$175,Allocation!$C$1:$C$175,"2026",Allocation!$D$1:$D$175,"MBWAY_BOR",Allocation!$F$1:$F$175,"BAC_MGT",Allocation!$G$1:$G$175,"B1",Allocation!$H$1:$H$175,"INIT") -> 30182.25 | F38: =_xlfn.SUMIFS(Allocation!$W$1:$W$175,Allocation!$C$1:$C$175,"2026",Allocation!$D$1:$D$175,"MBWAY_BOR",Allocation!$F$1:$F$175,"BAC_MGT",Allocation!$G$1:$G$175,"B1",Allocation!$H$1:$H$175,"INIT") -> 65376.75 | G38: =_xlfn.SUMIFS(Allocation!$X$1:$X$175,Allocation!$C$1:$C$175,"2026",Allocation!$D$1:$D$175,"MBWAY_BOR",Allocation!$F$1:$F$175,"BAC_MGT",Allocation!$G$1:$G$175,"B1",Allocation!$H$1:$H$175,"INIT") -> 31438.416 | H38: =_xlfn.SUMIFS(Allocation!$Y$1:$Y$175,Allocation!$C$1:$C$175,"2026",Allocation!$D$1:$D$175,"MBWAY_BOR",Allocation!$F$1:$F$175,"BAC_MGT",Allocation!$G$1:$G$175,"B1",Allocation!$H$1:$H$175,"INIT") -> 0 | I38: =_xlfn.SUMIFS(Allocation!$AC$1:$AC$175,Allocation!$C$1:$C$175,"2026",Allocation!$D$1:$D$175,"MBWAY_BOR",Allocation!$F$1:$F$175,"BAC_MGT",Allocation!$G$1:$G$175,"B1",Allocation!$H$1:$H$175,"INIT") -> 0 | J38: =_xlfn.SUMIFS(Allocation!$Z$1:$Z$175,Allocation!$C$1:$C$175,"2026",Allocation!$D$1:$D$175,"MBWAY_BOR",Allocation!$F$1:$F$175,"BAC_MGT",Allocation!$G$1:$G$175,"B1",Allocation!$H$1:$H$175,"INIT") -> 0 | K38: =E38+F38+G38+H38+I38+J38 -> 126997.42 | L38: =_xlfn.SUMIFS(Allocation!$AA$1:$AA$175,Allocation!$C$1:$C$175,"2026",Allocation!$D$1:$D$175,"MBWAY_BOR",Allocation!$F$1:$F$175,"BAC_MGT",Allocation!$G$1:$G$175,"B1",Allocation!$H$1:$H$175,"INIT") -> 248617.58 | M38: =_xlfn.IFERROR(L38/D38,0) -> 0.66189472
B39: BAC_MGT B2 ALT | C39: =_xlfn.SUMIFS(Allocation!$I$1:$I$175,Allocation!$C$1:$C$175,"2026",Allocation!$D$1:$D$175,"MBWAY_BOR",Allocation!$F$1:$F$175,"BAC_MGT",Allocation!$G$1:$G$175,"B2",Allocation!$H$1:$H$175,"ALT") -> 49 | D39: =_xlfn.SUMIFS(Allocation!$K$1:$K$175,Allocation!$C$1:$C$175,"2026",Allocation!$D$1:$D$175,"MBWAY_BOR",Allocation!$F$1:$F$175,"BAC_MGT",Allocation!$G$1:$G$175,"B2",Allocation!$H$1:$H$175,"ALT") -> 332710 | E39: =_xlfn.SUMIFS(Allocation!$V$1:$V$175,Allocation!$C$1:$C$175,"2026",Allocation!$D$1:$D$175,"MBWAY_BOR",Allocation!$F$1:$F$175,"BAC_MGT",Allocation!$G$1:$G$175,"B2",Allocation!$H$1:$H$175,"ALT") -> 24145.8 | F39: =_xlfn.SUMIFS(Allocation!$W$1:$W$175,Allocation!$C$1:$C$175,"2026",Allocation!$D$1:$D$175,"MBWAY_BOR",Allocation!$F$1:$F$175,"BAC_MGT",Allocation!$G$1:$G$175,"B2",Allocation!$H$1:$H$175,"ALT") -> 52301.4 | G39: =_xlfn.SUMIFS(Allocation!$X$1:$X$175,Allocation!$C$1:$C$175,"2026",Allocation!$D$1:$D$175,"MBWAY_BOR",Allocation!$F$1:$F$175,"BAC_MGT",Allocation!$G$1:$G$175,"B2",Allocation!$H$1:$H$175,"ALT") -> 18232.723 | H39: =_xlfn.SUMIFS(Allocation!$Y$1:$Y$175,Allocation!$C$1:$C$175,"2026",Allocation!$D$1:$D$175,"MBWAY_BOR",Allocation!$F$1:$F$175,"BAC_MGT",Allocation!$G$1:$G$175,"B2",Allocation!$H$1:$H$175,"ALT") -> 0 | I39: =_xlfn.SUMIFS(Allocation!$AC$1:$AC$175,Allocation!$C$1:$C$175,"2026",Allocation!$D$1:$D$175,"MBWAY_BOR",Allocation!$F$1:$F$175,"BAC_MGT",Allocation!$G$1:$G$175,"B2",Allocation!$H$1:$H$175,"ALT") -> 0 | J39: =_xlfn.SUMIFS(Allocation!$Z$1:$Z$175,Allocation!$C$1:$C$175,"2026",Allocation!$D$1:$D$175,"MBWAY_BOR",Allocation!$F$1:$F$175,"BAC_MGT",Allocation!$G$1:$G$175,"B2",Allocation!$H$1:$H$175,"ALT") -> 0 | K39: =E39+F39+G39+H39+I39+J39 -> 94679.923 | L39: =_xlfn.SUMIFS(Allocation!$AA$1:$AA$175,Allocation!$C$1:$C$175,"2026",Allocation!$D$1:$D$175,"MBWAY_BOR",Allocation!$F$1:$F$175,"BAC_MGT",Allocation!$G$1:$G$175,"B2",Allocation!$H$1:$H$175,"ALT") -> 238030.08 | M39: =_xlfn.IFERROR(L39/D39,0) -> 0.71542808
B40: BAC_MGT B3 ALT | C40: =_xlfn.SUMIFS(Allocation!$I$1:$I$175,Allocation!$C$1:$C$175,"2026",Allocation!$D$1:$D$175,"MBWAY_BOR",Allocation!$F$1:$F$175,"BAC_MGT",Allocation!$G$1:$G$175,"B3",Allocation!$H$1:$H$175,"ALT") -> 48 | D40: =_xlfn.SUMIFS(Allocation!$K$1:$K$175,Allocation!$C$1:$C$175,"2026",Allocation!$D$1:$D$175,"MBWAY_BOR",Allocation!$F$1:$F$175,"BAC_MGT",Allocation!$G$1:$G$175,"B3",Allocation!$H$1:$H$175,"ALT") -> 325920 | E40: =_xlfn.SUMIFS(Allocation!$V$1:$V$175,Allocation!$C$1:$C$175,"2026",Allocation!$D$1:$D$175,"MBWAY_BOR",Allocation!$F$1:$F$175,"BAC_MGT",Allocation!$G$1:$G$175,"B3",Allocation!$H$1:$H$175,"ALT") -> 24145.8 | F40: =_xlfn.SUMIFS(Allocation!$W$1:$W$175,Allocation!$C$1:$C$175,"2026",Allocation!$D$1:$D$175,"MBWAY_BOR",Allocation!$F$1:$F$175,"BAC_MGT",Allocation!$G$1:$G$175,"B3",Allocation!$H$1:$H$175,"ALT") -> 52301.4 | G40: =_xlfn.SUMIFS(Allocation!$X$1:$X$175,Allocation!$C$1:$C$175,"2026",Allocation!$D$1:$D$175,"MBWAY_BOR",Allocation!$F$1:$F$175,"BAC_MGT",Allocation!$G$1:$G$175,"B3",Allocation!$H$1:$H$175,"ALT") -> 17860.627 | H40: =_xlfn.SUMIFS(Allocation!$Y$1:$Y$175,Allocation!$C$1:$C$175,"2026",Allocation!$D$1:$D$175,"MBWAY_BOR",Allocation!$F$1:$F$175,"BAC_MGT",Allocation!$G$1:$G$175,"B3",Allocation!$H$1:$H$175,"ALT") -> 0 | I40: =_xlfn.SUMIFS(Allocation!$AC$1:$AC$175,Allocation!$C$1:$C$175,"2026",Allocation!$D$1:$D$175,"MBWAY_BOR",Allocation!$F$1:$F$175,"BAC_MGT",Allocation!$G$1:$G$175,"B3",Allocation!$H$1:$H$175,"ALT") -> 0 | J40: =_xlfn.SUMIFS(Allocation!$Z$1:$Z$175,Allocation!$C$1:$C$175,"2026",Allocation!$D$1:$D$175,"MBWAY_BOR",Allocation!$F$1:$F$175,"BAC_MGT",Allocation!$G$1:$G$175,"B3",Allocation!$H$1:$H$175,"ALT") -> 0 | K40: =E40+F40+G40+H40+I40+J40 -> 94307.827 | L40: =_xlfn.SUMIFS(Allocation!$AA$1:$AA$175,Allocation!$C$1:$C$175,"2026",Allocation!$D$1:$D$175,"MBWAY_BOR",Allocation!$F$1:$F$175,"BAC_MGT",Allocation!$G$1:$G$175,"B3",Allocation!$H$1:$H$175,"ALT") -> 231612.17 | M40: =_xlfn.IFERROR(L40/D40,0) -> 0.71064118
B41: MAS_MGT M1 ALT | C41: =_xlfn.SUMIFS(Allocation!$I$1:$I$175,Allocation!$C$1:$C$175,"2026",Allocation!$D$1:$D$175,"MBWAY_BOR",Allocation!$F$1:$F$175,"MAS_MGT",Allocation!$G$1:$G$175,"M1",Allocation!$H$1:$H$175,"ALT") -> 51 | D41: =_xlfn.SUMIFS(Allocation!$K$1:$K$175,Allocation!$C$1:$C$175,"2026",Allocation!$D$1:$D$175,"MBWAY_BOR",Allocation!$F$1:$F$175,"MAS_MGT",Allocation!$G$1:$G$175,"M1",Allocation!$H$1:$H$175,"ALT") -> 375615 | E41: =_xlfn.SUMIFS(Allocation!$V$1:$V$175,Allocation!$C$1:$C$175,"2026",Allocation!$D$1:$D$175,"MBWAY_BOR",Allocation!$F$1:$F$175,"MAS_MGT",Allocation!$G$1:$G$175,"M1",Allocation!$H$1:$H$175,"ALT") -> 21127.575 | F41: =_xlfn.SUMIFS(Allocation!$W$1:$W$175,Allocation!$C$1:$C$175,"2026",Allocation!$D$1:$D$175,"MBWAY_BOR",Allocation!$F$1:$F$175,"MAS_MGT",Allocation!$G$1:$G$175,"M1",Allocation!$H$1:$H$175,"ALT") -> 45763.725 | G41: =_xlfn.SUMIFS(Allocation!$X$1:$X$175,Allocation!$C$1:$C$175,"2026",Allocation!$D$1:$D$175,"MBWAY_BOR",Allocation!$F$1:$F$175,"MAS_MGT",Allocation!$G$1:$G$175,"M1",Allocation!$H$1:$H$175,"ALT") -> 31438.416 | H41: =_xlfn.SUMIFS(Allocation!$Y$1:$Y$175,Allocation!$C$1:$C$175,"2026",Allocation!$D$1:$D$175,"MBWAY_BOR",Allocation!$F$1:$F$175,"MAS_MGT",Allocation!$G$1:$G$175,"M1",Allocation!$H$1:$H$175,"ALT") -> 0 | I41: =_xlfn.SUMIFS(Allocation!$AC$1:$AC$175,Allocation!$C$1:$C$175,"2026",Allocation!$D$1:$D$175,"MBWAY_BOR",Allocation!$F$1:$F$175,"MAS_MGT",Allocation!$G$1:$G$175,"M1",Allocation!$H$1:$H$175,"ALT") -> 0 | J41: =_xlfn.SUMIFS(Allocation!$Z$1:$Z$175,Allocation!$C$1:$C$175,"2026",Allocation!$D$1:$D$175,"MBWAY_BOR",Allocation!$F$1:$F$175,"MAS_MGT",Allocation!$G$1:$G$175,"M1",Allocation!$H$1:$H$175,"ALT") -> 0 | K41: =E41+F41+G41+H41+I41+J41 -> 98329.716 | L41: =_xlfn.SUMIFS(Allocation!$AA$1:$AA$175,Allocation!$C$1:$C$175,"2026",Allocation!$D$1:$D$175,"MBWAY_BOR",Allocation!$F$1:$F$175,"MAS_MGT",Allocation!$G$1:$G$175,"M1",Allocation!$H$1:$H$175,"ALT") -> 277285.28 | M41: =_xlfn.IFERROR(L41/D41,0) -> 0.73821675
B42: MAS_MGT M2 ALT | C42: =_xlfn.SUMIFS(Allocation!$I$1:$I$175,Allocation!$C$1:$C$175,"2026",Allocation!$D$1:$D$175,"MBWAY_BOR",Allocation!$F$1:$F$175,"MAS_MGT",Allocation!$G$1:$G$175,"M2",Allocation!$H$1:$H$175,"ALT") -> 50 | D42: =_xlfn.SUMIFS(Allocation!$K$1:$K$175,Allocation!$C$1:$C$175,"2026",Allocation!$D$1:$D$175,"MBWAY_BOR",Allocation!$F$1:$F$175,"MAS_MGT",Allocation!$G$1:$G$175,"M2",Allocation!$H$1:$H$175,"ALT") -> 363750 | E42: =_xlfn.SUMIFS(Allocation!$V$1:$V$175,Allocation!$C$1:$C$175,"2026",Allocation!$D$1:$D$175,"MBWAY_BOR",Allocation!$F$1:$F$175,"MAS_MGT",Allocation!$G$1:$G$175,"M2",Allocation!$H$1:$H$175,"ALT") -> 21127.575 | F42: =_xlfn.SUMIFS(Allocation!$W$1:$W$175,Allocation!$C$1:$C$175,"2026",Allocation!$D$1:$D$175,"MBWAY_BOR",Allocation!$F$1:$F$175,"MAS_MGT",Allocation!$G$1:$G$175,"M2",Allocation!$H$1:$H$175,"ALT") -> 45763.725 | G42: =_xlfn.SUMIFS(Allocation!$X$1:$X$175,Allocation!$C$1:$C$175,"2026",Allocation!$D$1:$D$175,"MBWAY_BOR",Allocation!$F$1:$F$175,"MAS_MGT",Allocation!$G$1:$G$175,"M2",Allocation!$H$1:$H$175,"ALT") -> 18604.819 | H42: =_xlfn.SUMIFS(Allocation!$Y$1:$Y$175,Allocation!$C$1:$C$175,"2026",Allocation!$D$1:$D$175,"MBWAY_BOR",Allocation!$F$1:$F$175,"MAS_MGT",Allocation!$G$1:$G$175,"M2",Allocation!$H$1:$H$175,"ALT") -> 0 | I42: =_xlfn.SUMIFS(Allocation!$AC$1:$AC$175,Allocation!$C$1:$C$175,"2026",Allocation!$D$1:$D$175,"MBWAY_BOR",Allocation!$F$1:$F$175,"MAS_MGT",Allocation!$G$1:$G$175,"M2",Allocation!$H$1:$H$175,"ALT") -> 0 | J42: =_xlfn.SUMIFS(Allocation!$Z$1:$Z$175,Allocation!$C$1:$C$175,"2026",Allocation!$D$1:$D$175,"MBWAY_BOR",Allocation!$F$1:$F$175,"MAS_MGT",Allocation!$G$1:$G$175,"M2",Allocation!$H$1:$H$175,"ALT") -> 0 | K42: =E42+F42+G42+H42+I42+J42 -> 85496.119 | L42: =_xlfn.SUMIFS(Allocation!$AA$1:$AA$175,Allocation!$C$1:$C$175,"2026",Allocation!$D$1:$D$175,"MBWAY_BOR",Allocation!$F$1:$F$175,"MAS_MGT",Allocation!$G$1:$G$175,"M2",Allocation!$H$1:$H$175,"ALT") -> 278253.88 | M42: =_xlfn.IFERROR(L42/D42,0) -> 0.76495912
B43: ISCOM | C43: =_xlfn.SUMIFS(Allocation!$I$1:$I$175,Allocation!$C$1:$C$175,"2026",Allocation!$E$1:$E$175,"ISCOM") -> 829 | D43: =_xlfn.SUMIFS(Allocation!$K$1:$K$175,Allocation!$C$1:$C$175,"2026",Allocation!$E$1:$E$175,"ISCOM") -> 6292550 | E43: =_xlfn.SUMIFS(Allocation!$V$1:$V$175,Allocation!$C$1:$C$175,"2026",Allocation!$E$1:$E$175,"ISCOM") -> 422552 | F43: =_xlfn.SUMIFS(Allocation!$W$1:$W$175,Allocation!$C$1:$C$175,"2026",Allocation!$E$1:$E$175,"ISCOM") -> 1058481 | G43: =_xlfn.SUMIFS(Allocation!$X$1:$X$175,Allocation!$C$1:$C$175,"2026",Allocation!$E$1:$E$175,"ISCOM") -> 416570 | H43: =_xlfn.SUMIFS(Allocation!$Y$1:$Y$175,Allocation!$C$1:$C$175,"2026",Allocation!$E$1:$E$175,"ISCOM") -> 0 | I43: =_xlfn.SUMIFS(Allocation!$AC$1:$AC$175,Allocation!$C$1:$C$175,"2026",Allocation!$E$1:$E$175,"ISCOM") -> 0 | J43: =_xlfn.SUMIFS(Allocation!$Z$1:$Z$175,Allocation!$C$1:$C$175,"2026",Allocation!$E$1:$E$175,"ISCOM") -> 0 | K43: =E43+F43+G43+H43+I43+J43 -> 1897603 | L43: =_xlfn.SUMIFS(Allocation!$AA$1:$AA$175,Allocation!$C$1:$C$175,"2026",Allocation!$E$1:$E$175,"ISCOM") -> 4394947 | M43: =_xlfn.IFERROR(L43/D43,0) -> 0.69843656
B44: Paris (ISCOM_PAR) | C44: =_xlfn.SUMIFS(Allocation!$I$1:$I$175,Allocation!$C$1:$C$175,"2026",Allocation!$D$1:$D$175,"ISCOM_PAR") -> 354 | D44: =_xlfn.SUMIFS(Allocation!$K$1:$K$175,Allocation!$C$1:$C$175,"2026",Allocation!$D$1:$D$175,"ISCOM_PAR") -> 2908720 | E44: =_xlfn.SUMIFS(Allocation!$V$1:$V$175,Allocation!$C$1:$C$175,"2026",Allocation!$D$1:$D$175,"ISCOM_PAR") -> 181094 | F44: =_xlfn.SUMIFS(Allocation!$W$1:$W$175,Allocation!$C$1:$C$175,"2026",Allocation!$D$1:$D$175,"ISCOM_PAR") -> 605202 | G44: =_xlfn.SUMIFS(Allocation!$X$1:$X$175,Allocation!$C$1:$C$175,"2026",Allocation!$D$1:$D$175,"ISCOM_PAR") -> 192522 | H44: =_xlfn.SUMIFS(Allocation!$Y$1:$Y$175,Allocation!$C$1:$C$175,"2026",Allocation!$D$1:$D$175,"ISCOM_PAR") -> 0 | I44: =_xlfn.SUMIFS(Allocation!$AC$1:$AC$175,Allocation!$C$1:$C$175,"2026",Allocation!$D$1:$D$175,"ISCOM_PAR") -> 0 | J44: =_xlfn.SUMIFS(Allocation!$Z$1:$Z$175,Allocation!$C$1:$C$175,"2026",Allocation!$D$1:$D$175,"ISCOM_PAR") -> 0 | K44: =E44+F44+G44+H44+I44+J44 -> 978818 | L44: =_xlfn.SUMIFS(Allocation!$AA$1:$AA$175,Allocation!$C$1:$C$175,"2026",Allocation!$D$1:$D$175,"ISCOM_PAR") -> 1929902 | M44: =_xlfn.IFERROR(L44/D44,0) -> 0.66348841
B45: BAC_COM B1 INIT | C45: =_xlfn.SUMIFS(Allocation!$I$1:$I$175,Allocation!$C$1:$C$175,"2026",Allocation!$D$1:$D$175,"ISCOM_PAR",Allocation!$F$1:$F$175,"BAC_COM",Allocation!$G$1:$G$175,"B1",Allocation!$H$1:$H$175,"INIT") -> 72 | D45: =_xlfn.SUMIFS(Allocation!$K$1:$K$175,Allocation!$C$1:$C$175,"2026",Allocation!$D$1:$D$175,"ISCOM_PAR",Allocation!$F$1:$F$175,"BAC_COM",Allocation!$G$1:$G$175,"B1",Allocation!$H$1:$H$175,"INIT") -> 611280 | E45: =_xlfn.SUMIFS(Allocation!$V$1:$V$175,Allocation!$C$1:$C$175,"2026",Allocation!$D$1:$D$175,"ISCOM_PAR",Allocation!$F$1:$F$175,"BAC_COM",Allocation!$G$1:$G$175,"B1",Allocation!$H$1:$H$175,"INIT") -> 45273.5 | F45: =_xlfn.SUMIFS(Allocation!$W$1:$W$175,Allocation!$C$1:$C$175,"2026",Allocation!$D$1:$D$175,"ISCOM_PAR",Allocation!$F$1:$F$175,"BAC_COM",Allocation!$G$1:$G$175,"B1",Allocation!$H$1:$H$175,"INIT") -> 151300.5 | G45: =_xlfn.SUMIFS(Allocation!$X$1:$X$175,Allocation!$C$1:$C$175,"2026",Allocation!$D$1:$D$175,"ISCOM_PAR",Allocation!$F$1:$F$175,"BAC_COM",Allocation!$G$1:$G$175,"B1",Allocation!$H$1:$H$175,"INIT") -> 57190.915 | H45: =_xlfn.SUMIFS(Allocation!$Y$1:$Y$175,Allocation!$C$1:$C$175,"2026",Allocation!$D$1:$D$175,"ISCOM_PAR",Allocation!$F$1:$F$175,"BAC_COM",Allocation!$G$1:$G$175,"B1",Allocation!$H$1:$H$175,"INIT") -> 0 | I45: =_xlfn.SUMIFS(Allocation!$AC$1:$AC$175,Allocation!$C$1:$C$175,"2026",Allocation!$D$1:$D$175,"ISCOM_PAR",Allocation!$F$1:$F$175,"BAC_COM",Allocation!$G$1:$G$175,"B1",Allocation!$H$1:$H$175,"INIT") -> 0 | J45: =_xlfn.SUMIFS(Allocation!$Z$1:$Z$175,Allocation!$C$1:$C$175,"2026",Allocation!$D$1:$D$175,"ISCOM_PAR",Allocation!$F$1:$F$175,"BAC_COM",Allocation!$G$1:$G$175,"B1",Allocation!$H$1:$H$175,"INIT") -> 0 | K45: =E45+F45+G45+H45+I45+J45 -> 253764.92 | L45: =_xlfn.SUMIFS(Allocation!$AA$1:$AA$175,Allocation!$C$1:$C$175,"2026",Allocation!$D$1:$D$175,"ISCOM_PAR",Allocation!$F$1:$F$175,"BAC_COM",Allocation!$G$1:$G$175,"B1",Allocation!$H$1:$H$175,"INIT") -> 357515.08 | M45: =_xlfn.IFERROR(L45/D45,0) -> 0.58486305
B46: BAC_COM B2 ALT | C46: =_xlfn.SUMIFS(Allocation!$I$1:$I$175,Allocation!$C$1:$C$175,"2026",Allocation!$D$1:$D$175,"ISCOM_PAR",Allocation!$F$1:$F$175,"BAC_COM",Allocation!$G$1:$G$175,"B2",Allocation!$H$1:$H$175,"ALT") -> 70 | D46: =_xlfn.SUMIFS(Allocation!$K$1:$K$175,Allocation!$C$1:$C$175,"2026",Allocation!$D$1:$D$175,"ISCOM_PAR",Allocation!$F$1:$F$175,"BAC_COM",Allocation!$G$1:$G$175,"B2",Allocation!$H$1:$H$175,"ALT") -> 548800 | E46: =_xlfn.SUMIFS(Allocation!$V$1:$V$175,Allocation!$C$1:$C$175,"2026",Allocation!$D$1:$D$175,"ISCOM_PAR",Allocation!$F$1:$F$175,"BAC_COM",Allocation!$G$1:$G$175,"B2",Allocation!$H$1:$H$175,"ALT") -> 36218.8 | F46: =_xlfn.SUMIFS(Allocation!$W$1:$W$175,Allocation!$C$1:$C$175,"2026",Allocation!$D$1:$D$175,"ISCOM_PAR",Allocation!$F$1:$F$175,"BAC_COM",Allocation!$G$1:$G$175,"B2",Allocation!$H$1:$H$175,"ALT") -> 121040.4 | G46: =_xlfn.SUMIFS(Allocation!$X$1:$X$175,Allocation!$C$1:$C$175,"2026",Allocation!$D$1:$D$175,"ISCOM_PAR",Allocation!$F$1:$F$175,"BAC_COM",Allocation!$G$1:$G$175,"B2",Allocation!$H$1:$H$175,"ALT") -> 26046.723 | H46: =_xlfn.SUMIFS(Allocation!$Y$1:$Y$175,Allocation!$C$1:$C$175,"2026",Allocation!$D$1:$D$175,"ISCOM_PAR",Allocation!$F$1:$F$175,"BAC_COM",Allocation!$G$1:$G$175,"B2",Allocation!$H$1:$H$175,"ALT") -> 0 | I46: =_xlfn.SUMIFS(Allocation!$AC$1:$AC$175,Allocation!$C$1:$C$175,"2026",Allocation!$D$1:$D$175,"ISCOM_PAR",Allocation!$F$1:$F$175,"BAC_COM",Allocation!$G$1:$G$175,"B2",Allocation!$H$1:$H$175,"ALT") -> 0 | J46: =_xlfn.SUMIFS(Allocation!$Z$1:$Z$175,Allocation!$C$1:$C$175,"2026",Allocation!$D$1:$D$175,"ISCOM_PAR",Allocation!$F$1:$F$175,"BAC_COM",Allocation!$G$1:$G$175,"B2",Allocation!$H$1:$H$175,"ALT") -> 0 | K46: =E46+F46+G46+H46+I46+J46 -> 183305.92 | L46: =_xlfn.SUMIFS(Allocation!$AA$1:$AA$175,Allocation!$C$1:$C$175,"2026",Allocation!$D$1:$D$175,"ISCOM_PAR",Allocation!$F$1:$F$175,"BAC_COM",Allocation!$G$1:$G$175,"B2",Allocation!$H$1:$H$175,"ALT") -> 365494.08 | M46: =_xlfn.IFERROR(L46/D46,0) -> 0.66598775
B47: BAC_COM B3 ALT | C47: =_xlfn.SUMIFS(Allocation!$I$1:$I$175,Allocation!$C$1:$C$175,"2026",Allocation!$D$1:$D$175,"ISCOM_PAR",Allocation!$F$1:$F$175,"BAC_COM",Allocation!$G$1:$G$175,"B3",Allocation!$H$1:$H$175,"ALT") -> 69 | D47: =_xlfn.SUMIFS(Allocation!$K$1:$K$175,Allocation!$C$1:$C$175,"2026",Allocation!$D$1:$D$175,"ISCOM_PAR",Allocation!$F$1:$F$175,"BAC_COM",Allocation!$G$1:$G$175,"B3",Allocation!$H$1:$H$175,"ALT") -> 540960 | E47: =_xlfn.SUMIFS(Allocation!$V$1:$V$175,Allocation!$C$1:$C$175,"2026",Allocation!$D$1:$D$175,"ISCOM_PAR",Allocation!$F$1:$F$175,"BAC_COM",Allocation!$G$1:$G$175,"B3",Allocation!$H$1:$H$175,"ALT") -> 36218.8 | F47: =_xlfn.SUMIFS(Allocation!$W$1:$W$175,Allocation!$C$1:$C$175,"2026",Allocation!$D$1:$D$175,"ISCOM_PAR",Allocation!$F$1:$F$175,"BAC_COM",Allocation!$G$1:$G$175,"B3",Allocation!$H$1:$H$175,"ALT") -> 121040.4 | G47: =_xlfn.SUMIFS(Allocation!$X$1:$X$175,Allocation!$C$1:$C$175,"2026",Allocation!$D$1:$D$175,"ISCOM_PAR",Allocation!$F$1:$F$175,"BAC_COM",Allocation!$G$1:$G$175,"B3",Allocation!$H$1:$H$175,"ALT") -> 25674.627 | H47: =_xlfn.SUMIFS(Allocation!$Y$1:$Y$175,Allocation!$C$1:$C$175,"2026",Allocation!$D$1:$D$175,"ISCOM_PAR",Allocation!$F$1:$F$175,"BAC_COM",Allocation!$G$1:$G$175,"B3",Allocation!$H$1:$H$175,"ALT") -> 0 | I47: =_xlfn.SUMIFS(Allocation!$AC$1:$AC$175,Allocation!$C$1:$C$175,"2026",Allocation!$D$1:$D$175,"ISCOM_PAR",Allocation!$F$1:$F$175,"BAC_COM",Allocation!$G$1:$G$175,"B3",Allocation!$H$1:$H$175,"ALT") -> 0 | J47: =_xlfn.SUMIFS(Allocation!$Z$1:$Z$175,Allocation!$C$1:$C$175,"2026",Allocation!$D$1:$D$175,"ISCOM_PAR",Allocation!$F$1:$F$175,"BAC_COM",Allocation!$G$1:$G$175,"B3",Allocation!$H$1:$H$175,"ALT") -> 0 | K47: =E47+F47+G47+H47+I47+J47 -> 182933.83 | L47: =_xlfn.SUMIFS(Allocation!$AA$1:$AA$175,Allocation!$C$1:$C$175,"2026",Allocation!$D$1:$D$175,"ISCOM_PAR",Allocation!$F$1:$F$175,"BAC_COM",Allocation!$G$1:$G$175,"B3",Allocation!$H$1:$H$175,"ALT") -> 358026.17 | M47: =_xlfn.IFERROR(L47/D47,0) -> 0.66183484
B48: MAS_COM M1 ALT | C48: =_xlfn.SUMIFS(Allocation!$I$1:$I$175,Allocation!$C$1:$C$175,"2026",Allocation!$D$1:$D$175,"ISCOM_PAR",Allocation!$F$1:$F$175,"MAS_COM",Allocation!$G$1:$G$175,"M1",Allocation!$H$1:$H$175,"ALT") -> 72 | D48: =_xlfn.SUMIFS(Allocation!$K$1:$K$175,Allocation!$C$1:$C$175,"2026",Allocation!$D$1:$D$175,"ISCOM_PAR",Allocation!$F$1:$F$175,"MAS_COM",Allocation!$G$1:$G$175,"M1",Allocation!$H$1:$H$175,"ALT") -> 611280 | E48: =_xlfn.SUMIFS(Allocation!$V$1:$V$175,Allocation!$C$1:$C$175,"2026",Allocation!$D$1:$D$175,"ISCOM_PAR",Allocation!$F$1:$F$175,"MAS_COM",Allocation!$G$1:$G$175,"M1",Allocation!$H$1:$H$175,"ALT") -> 31691.45 | F48: =_xlfn.SUMIFS(Allocation!$W$1:$W$175,Allocation!$C$1:$C$175,"2026",Allocation!$D$1:$D$175,"ISCOM_PAR",Allocation!$F$1:$F$175,"MAS_COM",Allocation!$G$1:$G$175,"M1",Allocation!$H$1:$H$175,"ALT") -> 105910.35 | G48: =_xlfn.SUMIFS(Allocation!$X$1:$X$175,Allocation!$C$1:$C$175,"2026",Allocation!$D$1:$D$175,"ISCOM_PAR",Allocation!$F$1:$F$175,"MAS_COM",Allocation!$G$1:$G$175,"M1",Allocation!$H$1:$H$175,"ALT") -> 57190.915 | H48: =_xlfn.SUMIFS(Allocation!$Y$1:$Y$175,Allocation!$C$1:$C$175,"2026",Allocation!$D$1:$D$175,"ISCOM_PAR",Allocation!$F$1:$F$175,"MAS_COM",Allocation!$G$1:$G$175,"M1",Allocation!$H$1:$H$175,"ALT") -> 0 | I48: =_xlfn.SUMIFS(Allocation!$AC$1:$AC$175,Allocation!$C$1:$C$175,"2026",Allocation!$D$1:$D$175,"ISCOM_PAR",Allocation!$F$1:$F$175,"MAS_COM",Allocation!$G$1:$G$175,"M1",Allocation!$H$1:$H$175,"ALT") -> 0 | J48: =_xlfn.SUMIFS(Allocation!$Z$1:$Z$175,Allocation!$C$1:$C$175,"2026",Allocation!$D$1:$D$175,"ISCOM_PAR",Allocation!$F$1:$F$175,"MAS_COM",Allocation!$G$1:$G$175,"M1",Allocation!$H$1:$H$175,"ALT") -> 0 | K48: =E48+F48+G48+H48+I48+J48 -> 194792.72 | L48: =_xlfn.SUMIFS(Allocation!$AA$1:$AA$175,Allocation!$C$1:$C$175,"2026",Allocation!$D$1:$D$175,"ISCOM_PAR",Allocation!$F$1:$F$175,"MAS_COM",Allocation!$G$1:$G$175,"M1",Allocation!$H$1:$H$175,"ALT") -> 416487.28 | M48: =_xlfn.IFERROR(L48/D48,0) -> 0.68133635
B49: MAS_COM M2 ALT | C49: =_xlfn.SUMIFS(Allocation!$I$1:$I$175,Allocation!$C$1:$C$175,"2026",Allocation!$D$1:$D$175,"ISCOM_PAR",Allocation!$F$1:$F$175,"MAS_COM",Allocation!$G$1:$G$175,"M2",Allocation!$H$1:$H$175,"ALT") -> 71 | D49: =_xlfn.SUMIFS(Allocation!$K$1:$K$175,Allocation!$C$1:$C$175,"2026",Allocation!$D$1:$D$175,"ISCOM_PAR",Allocation!$F$1:$F$175,"MAS_COM",Allocation!$G$1:$G$175,"M2",Allocation!$H$1:$H$175,"ALT") -> 596400 | E49: =_xlfn.SUMIFS(Allocation!$V$1:$V$175,Allocation!$C$1:$C$175,"2026",Allocation!$D$1:$D$175,"ISCOM_PAR",Allocation!$F$1:$F$175,"MAS_COM",Allocation!$G$1:$G$175,"M2",Allocation!$H$1:$H$175,"ALT") -> 31691.45 | F49: =_xlfn.SUMIFS(Allocation!$W$1:$W$175,Allocation!$C$1:$C$175,"2026",Allocation!$D$1:$D$175,"ISCOM_PAR",Allocation!$F$1:$F$175,"MAS_COM",Allocation!$G$1:$G$175,"M2",Allocation!$H$1:$H$175,"ALT") -> 105910.35 | G49: =_xlfn.SUMIFS(Allocation!$X$1:$X$175,Allocation!$C$1:$C$175,"2026",Allocation!$D$1:$D$175,"ISCOM_PAR",Allocation!$F$1:$F$175,"MAS_COM",Allocation!$G$1:$G$175,"M2",Allocation!$H$1:$H$175,"ALT") -> 26418.819 | H49: =_xlfn.SUMIFS(Allocation!$Y$1:$Y$175,Allocation!$C$1:$C$175,"2026",Allocation!$D$1:$D$175,"ISCOM_PAR",Allocation!$F$1:$F$175,"MAS_COM",Allocation!$G$1:$G$175,"M2",Allocation!$H$1:$H$175,"ALT") -> 0 | I49: =_xlfn.SUMIFS(Allocation!$AC$1:$AC$175,Allocation!$C$1:$C$175,"2026",Allocation!$D$1:$D$175,"ISCOM_PAR",Allocation!$F$1:$F$175,"MAS_COM",Allocation!$G$1:$G$175,"M2",Allocation!$H$1:$H$175,"ALT") -> 0 | J49: =_xlfn.SUMIFS(Allocation!$Z$1:$Z$175,Allocation!$C$1:$C$175,"2026",Allocation!$D$1:$D$175,"ISCOM_PAR",Allocation!$F$1:$F$175,"MAS_COM",Allocation!$G$1:$G$175,"M2",Allocation!$H$1:$H$175,"ALT") -> 0 | K49: =E49+F49+G49+H49+I49+J49 -> 164020.62 | L49: =_xlfn.SUMIFS(Allocation!$AA$1:$AA$175,Allocation!$C$1:$C$175,"2026",Allocation!$D$1:$D$175,"ISCOM_PAR",Allocation!$F$1:$F$175,"MAS_COM",Allocation!$G$1:$G$175,"M2",Allocation!$H$1:$H$175,"ALT") -> 432379.38 | M49: =_xlfn.IFERROR(L49/D49,0) -> 0.72498219
B50: Lille (ISCOM_LIL) | C50: =_xlfn.SUMIFS(Allocation!$I$1:$I$175,Allocation!$C$1:$C$175,"2026",Allocation!$D$1:$D$175,"ISCOM_LIL") -> 244 | D50: =_xlfn.SUMIFS(Allocation!$K$1:$K$175,Allocation!$C$1:$C$175,"2026",Allocation!$D$1:$D$175,"ISCOM_LIL") -> 1755850 | E50: =_xlfn.SUMIFS(Allocation!$V$1:$V$175,Allocation!$C$1:$C$175,"2026",Allocation!$D$1:$D$175,"ISCOM_LIL") -> 120729 | F50: =_xlfn.SUMIFS(Allocation!$W$1:$W$175,Allocation!$C$1:$C$175,"2026",Allocation!$D$1:$D$175,"ISCOM_LIL") -> 229130 | G50: =_xlfn.SUMIFS(Allocation!$X$1:$X$175,Allocation!$C$1:$C$175,"2026",Allocation!$D$1:$D$175,"ISCOM_LIL") -> 116011 | H50: =_xlfn.SUMIFS(Allocation!$Y$1:$Y$175,Allocation!$C$1:$C$175,"2026",Allocation!$D$1:$D$175,"ISCOM_LIL") -> 0 | I50: =_xlfn.SUMIFS(Allocation!$AC$1:$AC$175,Allocation!$C$1:$C$175,"2026",Allocation!$D$1:$D$175,"ISCOM_LIL") -> 0 | J50: =_xlfn.SUMIFS(Allocation!$Z$1:$Z$175,Allocation!$C$1:$C$175,"2026",Allocation!$D$1:$D$175,"ISCOM_LIL") -> 0 | K50: =E50+F50+G50+H50+I50+J50 -> 465870 | L50: =_xlfn.SUMIFS(Allocation!$AA$1:$AA$175,Allocation!$C$1:$C$175,"2026",Allocation!$D$1:$D$175,"ISCOM_LIL") -> 1289980 | M50: =_xlfn.IFERROR(L50/D50,0) -> 0.73467551
B51: BAC_COM B1 INIT | C51: =_xlfn.SUMIFS(Allocation!$I$1:$I$175,Allocation!$C$1:$C$175,"2026",Allocation!$D$1:$D$175,"ISCOM_LIL",Allocation!$F$1:$F$175,"BAC_COM",Allocation!$G$1:$G$175,"B1",Allocation!$H$1:$H$175,"INIT") -> 50 | D51: =_xlfn.SUMIFS(Allocation!$K$1:$K$175,Allocation!$C$1:$C$175,"2026",Allocation!$D$1:$D$175,"ISCOM_LIL",Allocation!$F$1:$F$175,"BAC_COM",Allocation!$G$1:$G$175,"B1",Allocation!$H$1:$H$175,"INIT") -> 372000 | E51: =_xlfn.SUMIFS(Allocation!$V$1:$V$175,Allocation!$C$1:$C$175,"2026",Allocation!$D$1:$D$175,"ISCOM_LIL",Allocation!$F$1:$F$175,"BAC_COM",Allocation!$G$1:$G$175,"B1",Allocation!$H$1:$H$175,"INIT") -> 30182.25 | F51: =_xlfn.SUMIFS(Allocation!$W$1:$W$175,Allocation!$C$1:$C$175,"2026",Allocation!$D$1:$D$175,"ISCOM_LIL",Allocation!$F$1:$F$175,"BAC_COM",Allocation!$G$1:$G$175,"B1",Allocation!$H$1:$H$175,"INIT") -> 57282.5 | G51: =_xlfn.SUMIFS(Allocation!$X$1:$X$175,Allocation!$C$1:$C$175,"2026",Allocation!$D$1:$D$175,"ISCOM_LIL",Allocation!$F$1:$F$175,"BAC_COM",Allocation!$G$1:$G$175,"B1",Allocation!$H$1:$H$175,"INIT") -> 31214.713 | H51: =_xlfn.SUMIFS(Allocation!$Y$1:$Y$175,Allocation!$C$1:$C$175,"2026",Allocation!$D$1:$D$175,"ISCOM_LIL",Allocation!$F$1:$F$175,"BAC_COM",Allocation!$G$1:$G$175,"B1",Allocation!$H$1:$H$175,"INIT") -> 0 | I51: =_xlfn.SUMIFS(Allocation!$AC$1:$AC$175,Allocation!$C$1:$C$175,"2026",Allocation!$D$1:$D$175,"ISCOM_LIL",Allocation!$F$1:$F$175,"BAC_COM",Allocation!$G$1:$G$175,"B1",Allocation!$H$1:$H$175,"INIT") -> 0 | J51: =_xlfn.SUMIFS(Allocation!$Z$1:$Z$175,Allocation!$C$1:$C$175,"2026",Allocation!$D$1:$D$175,"ISCOM_LIL",Allocation!$F$1:$F$175,"BAC_COM",Allocation!$G$1:$G$175,"B1",Allocation!$H$1:$H$175,"INIT") -> 0 | K51: =E51+F51+G51+H51+I51+J51 -> 118679.46 | L51: =_xlfn.SUMIFS(Allocation!$AA$1:$AA$175,Allocation!$C$1:$C$175,"2026",Allocation!$D$1:$D$175,"ISCOM_LIL",Allocation!$F$1:$F$175,"BAC_COM",Allocation!$G$1:$G$175,"B1",Allocation!$H$1:$H$175,"INIT") -> 253320.54 | M51: =_xlfn.IFERROR(L51/D51,0) -> 0.68096919
B52: BAC_COM B2 ALT | C52: =_xlfn.SUMIFS(Allocation!$I$1:$I$175,Allocation!$C$1:$C$175,"2026",Allocation!$D$1:$D$175,"ISCOM_LIL",Allocation!$F$1:$F$175,"BAC_COM",Allocation!$G$1:$G$175,"B2",Allocation!$H$1:$H$175,"ALT") -> 48 | D52: =_xlfn.SUMIFS(Allocation!$K$1:$K$175,Allocation!$C$1:$C$175,"2026",Allocation!$D$1:$D$175,"ISCOM_LIL",Allocation!$F$1:$F$175,"BAC_COM",Allocation!$G$1:$G$175,"B2",Allocation!$H$1:$H$175,"ALT") -> 329280 | E52: =_xlfn.SUMIFS(Allocation!$V$1:$V$175,Allocation!$C$1:$C$175,"2026",Allocation!$D$1:$D$175,"ISCOM_LIL",Allocation!$F$1:$F$175,"BAC_COM",Allocation!$G$1:$G$175,"B2",Allocation!$H$1:$H$175,"ALT") -> 24145.8 | F52: =_xlfn.SUMIFS(Allocation!$W$1:$W$175,Allocation!$C$1:$C$175,"2026",Allocation!$D$1:$D$175,"ISCOM_LIL",Allocation!$F$1:$F$175,"BAC_COM",Allocation!$G$1:$G$175,"B2",Allocation!$H$1:$H$175,"ALT") -> 45826 | G52: =_xlfn.SUMIFS(Allocation!$X$1:$X$175,Allocation!$C$1:$C$175,"2026",Allocation!$D$1:$D$175,"ISCOM_LIL",Allocation!$F$1:$F$175,"BAC_COM",Allocation!$G$1:$G$175,"B2",Allocation!$H$1:$H$175,"ALT") -> 17860.525 | H52: =_xlfn.SUMIFS(Allocation!$Y$1:$Y$175,Allocation!$C$1:$C$175,"2026",Allocation!$D$1:$D$175,"ISCOM_LIL",Allocation!$F$1:$F$175,"BAC_COM",Allocation!$G$1:$G$175,"B2",Allocation!$H$1:$H$175,"ALT") -> 0 | I52: =_xlfn.SUMIFS(Allocation!$AC$1:$AC$175,Allocation!$C$1:$C$175,"2026",Allocation!$D$1:$D$175,"ISCOM_LIL",Allocation!$F$1:$F$175,"BAC_COM",Allocation!$G$1:$G$175,"B2",Allocation!$H$1:$H$175,"ALT") -> 0 | J52: =_xlfn.SUMIFS(Allocation!$Z$1:$Z$175,Allocation!$C$1:$C$175,"2026",Allocation!$D$1:$D$175,"ISCOM_LIL",Allocation!$F$1:$F$175,"BAC_COM",Allocation!$G$1:$G$175,"B2",Allocation!$H$1:$H$175,"ALT") -> 0 | K52: =E52+F52+G52+H52+I52+J52 -> 87832.325 | L52: =_xlfn.SUMIFS(Allocation!$AA$1:$AA$175,Allocation!$C$1:$C$175,"2026",Allocation!$D$1:$D$175,"ISCOM_LIL",Allocation!$F$1:$F$175,"BAC_COM",Allocation!$G$1:$G$175,"B2",Allocation!$H$1:$H$175,"ALT") -> 241447.68 | M52: =_xlfn.IFERROR(L52/D52,0) -> 0.73325946
B53: BAC_COM B3 ALT | C53: =_xlfn.SUMIFS(Allocation!$I$1:$I$175,Allocation!$C$1:$C$175,"2026",Allocation!$D$1:$D$175,"ISCOM_LIL",Allocation!$F$1:$F$175,"BAC_COM",Allocation!$G$1:$G$175,"B3",Allocation!$H$1:$H$175,"ALT") -> 47 | D53: =_xlfn.SUMIFS(Allocation!$K$1:$K$175,Allocation!$C$1:$C$175,"2026",Allocation!$D$1:$D$175,"ISCOM_LIL",Allocation!$F$1:$F$175,"BAC_COM",Allocation!$G$1:$G$175,"B3",Allocation!$H$1:$H$175,"ALT") -> 322420 | E53: =_xlfn.SUMIFS(Allocation!$V$1:$V$175,Allocation!$C$1:$C$175,"2026",Allocation!$D$1:$D$175,"ISCOM_LIL",Allocation!$F$1:$F$175,"BAC_COM",Allocation!$G$1:$G$175,"B3",Allocation!$H$1:$H$175,"ALT") -> 24145.8 | F53: =_xlfn.SUMIFS(Allocation!$W$1:$W$175,Allocation!$C$1:$C$175,"2026",Allocation!$D$1:$D$175,"ISCOM_LIL",Allocation!$F$1:$F$175,"BAC_COM",Allocation!$G$1:$G$175,"B3",Allocation!$H$1:$H$175,"ALT") -> 45826 | G53: =_xlfn.SUMIFS(Allocation!$X$1:$X$175,Allocation!$C$1:$C$175,"2026",Allocation!$D$1:$D$175,"ISCOM_LIL",Allocation!$F$1:$F$175,"BAC_COM",Allocation!$G$1:$G$175,"B3",Allocation!$H$1:$H$175,"ALT") -> 17488.43 | H53: =_xlfn.SUMIFS(Allocation!$Y$1:$Y$175,Allocation!$C$1:$C$175,"2026",Allocation!$D$1:$D$175,"ISCOM_LIL",Allocation!$F$1:$F$175,"BAC_COM",Allocation!$G$1:$G$175,"B3",Allocation!$H$1:$H$175,"ALT") -> 0 | I53: =_xlfn.SUMIFS(Allocation!$AC$1:$AC$175,Allocation!$C$1:$C$175,"2026",Allocation!$D$1:$D$175,"ISCOM_LIL",Allocation!$F$1:$F$175,"BAC_COM",Allocation!$G$1:$G$175,"B3",Allocation!$H$1:$H$175,"ALT") -> 0 | J53: =_xlfn.SUMIFS(Allocation!$Z$1:$Z$175,Allocation!$C$1:$C$175,"2026",Allocation!$D$1:$D$175,"ISCOM_LIL",Allocation!$F$1:$F$175,"BAC_COM",Allocation!$G$1:$G$175,"B3",Allocation!$H$1:$H$175,"ALT") -> 0 | K53: =E53+F53+G53+H53+I53+J53 -> 87460.23 | L53: =_xlfn.SUMIFS(Allocation!$AA$1:$AA$175,Allocation!$C$1:$C$175,"2026",Allocation!$D$1:$D$175,"ISCOM_LIL",Allocation!$F$1:$F$175,"BAC_COM",Allocation!$G$1:$G$175,"B3",Allocation!$H$1:$H$175,"ALT") -> 234959.77 | M53: =_xlfn.IFERROR(L53/D53,0) -> 0.7287382
B54: MAS_COM M1 ALT | C54: =_xlfn.SUMIFS(Allocation!$I$1:$I$175,Allocation!$C$1:$C$175,"2026",Allocation!$D$1:$D$175,"ISCOM_LIL",Allocation!$F$1:$F$175,"MAS_COM",Allocation!$G$1:$G$175,"M1",Allocation!$H$1:$H$175,"ALT") -> 50 | D54: =_xlfn.SUMIFS(Allocation!$K$1:$K$175,Allocation!$C$1:$C$175,"2026",Allocation!$D$1:$D$175,"ISCOM_LIL",Allocation!$F$1:$F$175,"MAS_COM",Allocation!$G$1:$G$175,"M1",Allocation!$H$1:$H$175,"ALT") -> 372000 | E54: =_xlfn.SUMIFS(Allocation!$V$1:$V$175,Allocation!$C$1:$C$175,"2026",Allocation!$D$1:$D$175,"ISCOM_LIL",Allocation!$F$1:$F$175,"MAS_COM",Allocation!$G$1:$G$175,"M1",Allocation!$H$1:$H$175,"ALT") -> 21127.575 | F54: =_xlfn.SUMIFS(Allocation!$W$1:$W$175,Allocation!$C$1:$C$175,"2026",Allocation!$D$1:$D$175,"ISCOM_LIL",Allocation!$F$1:$F$175,"MAS_COM",Allocation!$G$1:$G$175,"M1",Allocation!$H$1:$H$175,"ALT") -> 40097.75 | G54: =_xlfn.SUMIFS(Allocation!$X$1:$X$175,Allocation!$C$1:$C$175,"2026",Allocation!$D$1:$D$175,"ISCOM_LIL",Allocation!$F$1:$F$175,"MAS_COM",Allocation!$G$1:$G$175,"M1",Allocation!$H$1:$H$175,"ALT") -> 31214.713 | H54: =_xlfn.SUMIFS(Allocation!$Y$1:$Y$175,Allocation!$C$1:$C$175,"2026",Allocation!$D$1:$D$175,"ISCOM_LIL",Allocation!$F$1:$F$175,"MAS_COM",Allocation!$G$1:$G$175,"M1",Allocation!$H$1:$H$175,"ALT") -> 0 | I54: =_xlfn.SUMIFS(Allocation!$AC$1:$AC$175,Allocation!$C$1:$C$175,"2026",Allocation!$D$1:$D$175,"ISCOM_LIL",Allocation!$F$1:$F$175,"MAS_COM",Allocation!$G$1:$G$175,"M1",Allocation!$H$1:$H$175,"ALT") -> 0 | J54: =_xlfn.SUMIFS(Allocation!$Z$1:$Z$175,Allocation!$C$1:$C$175,"2026",Allocation!$D$1:$D$175,"ISCOM_LIL",Allocation!$F$1:$F$175,"MAS_COM",Allocation!$G$1:$G$175,"M1",Allocation!$H$1:$H$175,"ALT") -> 0 | K54: =E54+F54+G54+H54+I54+J54 -> 92440.038 | L54: =_xlfn.SUMIFS(Allocation!$AA$1:$AA$175,Allocation!$C$1:$C$175,"2026",Allocation!$D$1:$D$175,"ISCOM_LIL",Allocation!$F$1:$F$175,"MAS_COM",Allocation!$G$1:$G$175,"M1",Allocation!$H$1:$H$175,"ALT") -> 279559.96 | M54: =_xlfn.IFERROR(L54/D54,0) -> 0.75150527
B55: MAS_COM M2 ALT | C55: =_xlfn.SUMIFS(Allocation!$I$1:$I$175,Allocation!$C$1:$C$175,"2026",Allocation!$D$1:$D$175,"ISCOM_LIL",Allocation!$F$1:$F$175,"MAS_COM",Allocation!$G$1:$G$175,"M2",Allocation!$H$1:$H$175,"ALT") -> 49 | D55: =_xlfn.SUMIFS(Allocation!$K$1:$K$175,Allocation!$C$1:$C$175,"2026",Allocation!$D$1:$D$175,"ISCOM_LIL",Allocation!$F$1:$F$175,"MAS_COM",Allocation!$G$1:$G$175,"M2",Allocation!$H$1:$H$175,"ALT") -> 360150 | E55: =_xlfn.SUMIFS(Allocation!$V$1:$V$175,Allocation!$C$1:$C$175,"2026",Allocation!$D$1:$D$175,"ISCOM_LIL",Allocation!$F$1:$F$175,"MAS_COM",Allocation!$G$1:$G$175,"M2",Allocation!$H$1:$H$175,"ALT") -> 21127.575 | F55: =_xlfn.SUMIFS(Allocation!$W$1:$W$175,Allocation!$C$1:$C$175,"2026",Allocation!$D$1:$D$175,"ISCOM_LIL",Allocation!$F$1:$F$175,"MAS_COM",Allocation!$G$1:$G$175,"M2",Allocation!$H$1:$H$175,"ALT") -> 40097.75 | G55: =_xlfn.SUMIFS(Allocation!$X$1:$X$175,Allocation!$C$1:$C$175,"2026",Allocation!$D$1:$D$175,"ISCOM_LIL",Allocation!$F$1:$F$175,"MAS_COM",Allocation!$G$1:$G$175,"M2",Allocation!$H$1:$H$175,"ALT") -> 18232.619 | H55: =_xlfn.SUMIFS(Allocation!$Y$1:$Y$175,Allocation!$C$1:$C$175,"2026",Allocation!$D$1:$D$175,"ISCOM_LIL",Allocation!$F$1:$F$175,"MAS_COM",Allocation!$G$1:$G$175,"M2",Allocation!$H$1:$H$175,"ALT") -> 0 | I55: =_xlfn.SUMIFS(Allocation!$AC$1:$AC$175,Allocation!$C$1:$C$175,"2026",Allocation!$D$1:$D$175,"ISCOM_LIL",Allocation!$F$1:$F$175,"MAS_COM",Allocation!$G$1:$G$175,"M2",Allocation!$H$1:$H$175,"ALT") -> 0 | J55: =_xlfn.SUMIFS(Allocation!$Z$1:$Z$175,Allocation!$C$1:$C$175,"2026",Allocation!$D$1:$D$175,"ISCOM_LIL",Allocation!$F$1:$F$175,"MAS_COM",Allocation!$G$1:$G$175,"M2",Allocation!$H$1:$H$175,"ALT") -> 0 | K55: =E55+F55+G55+H55+I55+J55 -> 79457.944 | L55: =_xlfn.SUMIFS(Allocation!$AA$1:$AA$175,Allocation!$C$1:$C$175,"2026",Allocation!$D$1:$D$175,"ISCOM_LIL",Allocation!$F$1:$F$175,"MAS_COM",Allocation!$G$1:$G$175,"M2",Allocation!$H$1:$H$175,"ALT") -> 280692.06 | M55: =_xlfn.IFERROR(L55/D55,0) -> 0.77937542
B56: Toulouse (ISCOM_TLS) | C56: =_xlfn.SUMIFS(Allocation!$I$1:$I$175,Allocation!$C$1:$C$175,"2026",Allocation!$D$1:$D$175,"ISCOM_TLS") -> 231 | D56: =_xlfn.SUMIFS(Allocation!$K$1:$K$175,Allocation!$C$1:$C$175,"2026",Allocation!$D$1:$D$175,"ISCOM_TLS") -> 1627980 | E56: =_xlfn.SUMIFS(Allocation!$V$1:$V$175,Allocation!$C$1:$C$175,"2026",Allocation!$D$1:$D$175,"ISCOM_TLS") -> 120729 | F56: =_xlfn.SUMIFS(Allocation!$W$1:$W$175,Allocation!$C$1:$C$175,"2026",Allocation!$D$1:$D$175,"ISCOM_TLS") -> 224149 | G56: =_xlfn.SUMIFS(Allocation!$X$1:$X$175,Allocation!$C$1:$C$175,"2026",Allocation!$D$1:$D$175,"ISCOM_TLS") -> 108037 | H56: =_xlfn.SUMIFS(Allocation!$Y$1:$Y$175,Allocation!$C$1:$C$175,"2026",Allocation!$D$1:$D$175,"ISCOM_TLS") -> 0 | I56: =_xlfn.SUMIFS(Allocation!$AC$1:$AC$175,Allocation!$C$1:$C$175,"2026",Allocation!$D$1:$D$175,"ISCOM_TLS") -> 0 | J56: =_xlfn.SUMIFS(Allocation!$Z$1:$Z$175,Allocation!$C$1:$C$175,"2026",Allocation!$D$1:$D$175,"ISCOM_TLS") -> 0 | K56: =E56+F56+G56+H56+I56+J56 -> 452915 | L56: =_xlfn.SUMIFS(Allocation!$AA$1:$AA$175,Allocation!$C$1:$C$175,"2026",Allocation!$D$1:$D$175,"ISCOM_TLS") -> 1175065 | M56: =_xlfn.IFERROR(L56/D56,0) -> 0.72179327
B57: BAC_COM B1 INIT | C57: =_xlfn.SUMIFS(Allocation!$I$1:$I$175,Allocation!$C$1:$C$175,"2026",Allocation!$D$1:$D$175,"ISCOM_TLS",Allocation!$F$1:$F$175,"BAC_COM",Allocation!$G$1:$G$175,"B1",Allocation!$H$1:$H$175,"INIT") -> 47 | D57: =_xlfn.SUMIFS(Allocation!$K$1:$K$175,Allocation!$C$1:$C$175,"2026",Allocation!$D$1:$D$175,"ISCOM_TLS",Allocation!$F$1:$F$175,"BAC_COM",Allocation!$G$1:$G$175,"B1",Allocation!$H$1:$H$175,"INIT") -> 342630 | E57: =_xlfn.SUMIFS(Allocation!$V$1:$V$175,Allocation!$C$1:$C$175,"2026",Allocation!$D$1:$D$175,"ISCOM_TLS",Allocation!$F$1:$F$175,"BAC_COM",Allocation!$G$1:$G$175,"B1",Allocation!$H$1:$H$175,"INIT") -> 30182.25 | F57: =_xlfn.SUMIFS(Allocation!$W$1:$W$175,Allocation!$C$1:$C$175,"2026",Allocation!$D$1:$D$175,"ISCOM_TLS",Allocation!$F$1:$F$175,"BAC_COM",Allocation!$G$1:$G$175,"B1",Allocation!$H$1:$H$175,"INIT") -> 56037.25 | G57: =_xlfn.SUMIFS(Allocation!$X$1:$X$175,Allocation!$C$1:$C$175,"2026",Allocation!$D$1:$D$175,"ISCOM_TLS",Allocation!$F$1:$F$175,"BAC_COM",Allocation!$G$1:$G$175,"B1",Allocation!$H$1:$H$175,"INIT") -> 28529.976 | H57: =_xlfn.SUMIFS(Allocation!$Y$1:$Y$175,Allocation!$C$1:$C$175,"2026",Allocation!$D$1:$D$175,"ISCOM_TLS",Allocation!$F$1:$F$175,"BAC_COM",Allocation!$G$1:$G$175,"B1",Allocation!$H$1:$H$175,"INIT") -> 0 | I57: =_xlfn.SUMIFS(Allocation!$AC$1:$AC$175,Allocation!$C$1:$C$175,"2026",Allocation!$D$1:$D$175,"ISCOM_TLS",Allocation!$F$1:$F$175,"BAC_COM",Allocation!$G$1:$G$175,"B1",Allocation!$H$1:$H$175,"INIT") -> 0 | J57: =_xlfn.SUMIFS(Allocation!$Z$1:$Z$175,Allocation!$C$1:$C$175,"2026",Allocation!$D$1:$D$175,"ISCOM_TLS",Allocation!$F$1:$F$175,"BAC_COM",Allocation!$G$1:$G$175,"B1",Allocation!$H$1:$H$175,"INIT") -> 0 | K57: =E57+F57+G57+H57+I57+J57 -> 114749.48 | L57: =_xlfn.SUMIFS(Allocation!$AA$1:$AA$175,Allocation!$C$1:$C$175,"2026",Allocation!$D$1:$D$175,"ISCOM_TLS",Allocation!$F$1:$F$175,"BAC_COM",Allocation!$G$1:$G$175,"B1",Allocation!$H$1:$H$175,"INIT") -> 227880.52 | M57: =_xlfn.IFERROR(L57/D57,0) -> 0.66509215
B58: BAC_COM B2 ALT | C58: =_xlfn.SUMIFS(Allocation!$I$1:$I$175,Allocation!$C$1:$C$175,"2026",Allocation!$D$1:$D$175,"ISCOM_TLS",Allocation!$F$1:$F$175,"BAC_COM",Allocation!$G$1:$G$175,"B2",Allocation!$H$1:$H$175,"ALT") -> 46 | D58: =_xlfn.SUMIFS(Allocation!$K$1:$K$175,Allocation!$C$1:$C$175,"2026",Allocation!$D$1:$D$175,"ISCOM_TLS",Allocation!$F$1:$F$175,"BAC_COM",Allocation!$G$1:$G$175,"B2",Allocation!$H$1:$H$175,"ALT") -> 309120 | E58: =_xlfn.SUMIFS(Allocation!$V$1:$V$175,Allocation!$C$1:$C$175,"2026",Allocation!$D$1:$D$175,"ISCOM_TLS",Allocation!$F$1:$F$175,"BAC_COM",Allocation!$G$1:$G$175,"B2",Allocation!$H$1:$H$175,"ALT") -> 24145.8 | F58: =_xlfn.SUMIFS(Allocation!$W$1:$W$175,Allocation!$C$1:$C$175,"2026",Allocation!$D$1:$D$175,"ISCOM_TLS",Allocation!$F$1:$F$175,"BAC_COM",Allocation!$G$1:$G$175,"B2",Allocation!$H$1:$H$175,"ALT") -> 44829.8 | G58: =_xlfn.SUMIFS(Allocation!$X$1:$X$175,Allocation!$C$1:$C$175,"2026",Allocation!$D$1:$D$175,"ISCOM_TLS",Allocation!$F$1:$F$175,"BAC_COM",Allocation!$G$1:$G$175,"B2",Allocation!$H$1:$H$175,"ALT") -> 17116.381 | H58: =_xlfn.SUMIFS(Allocation!$Y$1:$Y$175,Allocation!$C$1:$C$175,"2026",Allocation!$D$1:$D$175,"ISCOM_TLS",Allocation!$F$1:$F$175,"BAC_COM",Allocation!$G$1:$G$175,"B2",Allocation!$H$1:$H$175,"ALT") -> 0 | I58: =_xlfn.SUMIFS(Allocation!$AC$1:$AC$175,Allocation!$C$1:$C$175,"2026",Allocation!$D$1:$D$175,"ISCOM_TLS",Allocation!$F$1:$F$175,"BAC_COM",Allocation!$G$1:$G$175,"B2",Allocation!$H$1:$H$175,"ALT") -> 0 | J58: =_xlfn.SUMIFS(Allocation!$Z$1:$Z$175,Allocation!$C$1:$C$175,"2026",Allocation!$D$1:$D$175,"ISCOM_TLS",Allocation!$F$1:$F$175,"BAC_COM",Allocation!$G$1:$G$175,"B2",Allocation!$H$1:$H$175,"ALT") -> 0 | K58: =E58+F58+G58+H58+I58+J58 -> 86091.981 | L58: =_xlfn.SUMIFS(Allocation!$AA$1:$AA$175,Allocation!$C$1:$C$175,"2026",Allocation!$D$1:$D$175,"ISCOM_TLS",Allocation!$F$1:$F$175,"BAC_COM",Allocation!$G$1:$G$175,"B2",Allocation!$H$1:$H$175,"ALT") -> 223028.02 | M58: =_xlfn.IFERROR(L58/D58,0) -> 0.72149333
B59: BAC_COM B3 ALT | C59: =_xlfn.SUMIFS(Allocation!$I$1:$I$175,Allocation!$C$1:$C$175,"2026",Allocation!$D$1:$D$175,"ISCOM_TLS",Allocation!$F$1:$F$175,"BAC_COM",Allocation!$G$1:$G$175,"B3",Allocation!$H$1:$H$175,"ALT") -> 45 | D59: =_xlfn.SUMIFS(Allocation!$K$1:$K$175,Allocation!$C$1:$C$175,"2026",Allocation!$D$1:$D$175,"ISCOM_TLS",Allocation!$F$1:$F$175,"BAC_COM",Allocation!$G$1:$G$175,"B3",Allocation!$H$1:$H$175,"ALT") -> 302400 | E59: =_xlfn.SUMIFS(Allocation!$V$1:$V$175,Allocation!$C$1:$C$175,"2026",Allocation!$D$1:$D$175,"ISCOM_TLS",Allocation!$F$1:$F$175,"BAC_COM",Allocation!$G$1:$G$175,"B3",Allocation!$H$1:$H$175,"ALT") -> 24145.8 | F59: =_xlfn.SUMIFS(Allocation!$W$1:$W$175,Allocation!$C$1:$C$175,"2026",Allocation!$D$1:$D$175,"ISCOM_TLS",Allocation!$F$1:$F$175,"BAC_COM",Allocation!$G$1:$G$175,"B3",Allocation!$H$1:$H$175,"ALT") -> 44829.8 | G59: =_xlfn.SUMIFS(Allocation!$X$1:$X$175,Allocation!$C$1:$C$175,"2026",Allocation!$D$1:$D$175,"ISCOM_TLS",Allocation!$F$1:$F$175,"BAC_COM",Allocation!$G$1:$G$175,"B3",Allocation!$H$1:$H$175,"ALT") -> 16744.286 | H59: =_xlfn.SUMIFS(Allocation!$Y$1:$Y$175,Allocation!$C$1:$C$175,"2026",Allocation!$D$1:$D$175,"ISCOM_TLS",Allocation!$F$1:$F$175,"BAC_COM",Allocation!$G$1:$G$175,"B3",Allocation!$H$1:$H$175,"ALT") -> 0 | I59: =_xlfn.SUMIFS(Allocation!$AC$1:$AC$175,Allocation!$C$1:$C$175,"2026",Allocation!$D$1:$D$175,"ISCOM_TLS",Allocation!$F$1:$F$175,"BAC_COM",Allocation!$G$1:$G$175,"B3",Allocation!$H$1:$H$175,"ALT") -> 0 | J59: =_xlfn.SUMIFS(Allocation!$Z$1:$Z$175,Allocation!$C$1:$C$175,"2026",Allocation!$D$1:$D$175,"ISCOM_TLS",Allocation!$F$1:$F$175,"BAC_COM",Allocation!$G$1:$G$175,"B3",Allocation!$H$1:$H$175,"ALT") -> 0 | K59: =E59+F59+G59+H59+I59+J59 -> 85719.886 | L59: =_xlfn.SUMIFS(Allocation!$AA$1:$AA$175,Allocation!$C$1:$C$175,"2026",Allocation!$D$1:$D$175,"ISCOM_TLS",Allocation!$F$1:$F$175,"BAC_COM",Allocation!$G$1:$G$175,"B3",Allocation!$H$1:$H$175,"ALT") -> 216680.11 | M59: =_xlfn.IFERROR(L59/D59,0) -> 0.71653477
B60: MAS_COM M1 ALT | C60: =_xlfn.SUMIFS(Allocation!$I$1:$I$175,Allocation!$C$1:$C$175,"2026",Allocation!$D$1:$D$175,"ISCOM_TLS",Allocation!$F$1:$F$175,"MAS_COM",Allocation!$G$1:$G$175,"M1",Allocation!$H$1:$H$175,"ALT") -> 47 | D60: =_xlfn.SUMIFS(Allocation!$K$1:$K$175,Allocation!$C$1:$C$175,"2026",Allocation!$D$1:$D$175,"ISCOM_TLS",Allocation!$F$1:$F$175,"MAS_COM",Allocation!$G$1:$G$175,"M1",Allocation!$H$1:$H$175,"ALT") -> 342630 | E60: =_xlfn.SUMIFS(Allocation!$V$1:$V$175,Allocation!$C$1:$C$175,"2026",Allocation!$D$1:$D$175,"ISCOM_TLS",Allocation!$F$1:$F$175,"MAS_COM",Allocation!$G$1:$G$175,"M1",Allocation!$H$1:$H$175,"ALT") -> 21127.575 | F60: =_xlfn.SUMIFS(Allocation!$W$1:$W$175,Allocation!$C$1:$C$175,"2026",Allocation!$D$1:$D$175,"ISCOM_TLS",Allocation!$F$1:$F$175,"MAS_COM",Allocation!$G$1:$G$175,"M1",Allocation!$H$1:$H$175,"ALT") -> 39226.075 | G60: =_xlfn.SUMIFS(Allocation!$X$1:$X$175,Allocation!$C$1:$C$175,"2026",Allocation!$D$1:$D$175,"ISCOM_TLS",Allocation!$F$1:$F$175,"MAS_COM",Allocation!$G$1:$G$175,"M1",Allocation!$H$1:$H$175,"ALT") -> 28529.976 | H60: =_xlfn.SUMIFS(Allocation!$Y$1:$Y$175,Allocation!$C$1:$C$175,"2026",Allocation!$D$1:$D$175,"ISCOM_TLS",Allocation!$F$1:$F$175,"MAS_COM",Allocation!$G$1:$G$175,"M1",Allocation!$H$1:$H$175,"ALT") -> 0 | I60: =_xlfn.SUMIFS(Allocation!$AC$1:$AC$175,Allocation!$C$1:$C$175,"2026",Allocation!$D$1:$D$175,"ISCOM_TLS",Allocation!$F$1:$F$175,"MAS_COM",Allocation!$G$1:$G$175,"M1",Allocation!$H$1:$H$175,"ALT") -> 0 | J60: =_xlfn.SUMIFS(Allocation!$Z$1:$Z$175,Allocation!$C$1:$C$175,"2026",Allocation!$D$1:$D$175,"ISCOM_TLS",Allocation!$F$1:$F$175,"MAS_COM",Allocation!$G$1:$G$175,"M1",Allocation!$H$1:$H$175,"ALT") -> 0 | K60: =E60+F60+G60+H60+I60+J60 -> 88883.626 | L60: =_xlfn.SUMIFS(Allocation!$AA$1:$AA$175,Allocation!$C$1:$C$175,"2026",Allocation!$D$1:$D$175,"ISCOM_TLS",Allocation!$F$1:$F$175,"MAS_COM",Allocation!$G$1:$G$175,"M1",Allocation!$H$1:$H$175,"ALT") -> 253746.37 | M60: =_xlfn.IFERROR(L60/D60,0) -> 0.74058423
B61: MAS_COM M2 ALT | C61: =_xlfn.SUMIFS(Allocation!$I$1:$I$175,Allocation!$C$1:$C$175,"2026",Allocation!$D$1:$D$175,"ISCOM_TLS",Allocation!$F$1:$F$175,"MAS_COM",Allocation!$G$1:$G$175,"M2",Allocation!$H$1:$H$175,"ALT") -> 46 | D61: =_xlfn.SUMIFS(Allocation!$K$1:$K$175,Allocation!$C$1:$C$175,"2026",Allocation!$D$1:$D$175,"ISCOM_TLS",Allocation!$F$1:$F$175,"MAS_COM",Allocation!$G$1:$G$175,"M2",Allocation!$H$1:$H$175,"ALT") -> 331200 | E61: =_xlfn.SUMIFS(Allocation!$V$1:$V$175,Allocation!$C$1:$C$175,"2026",Allocation!$D$1:$D$175,"ISCOM_TLS",Allocation!$F$1:$F$175,"MAS_COM",Allocation!$G$1:$G$175,"M2",Allocation!$H$1:$H$175,"ALT") -> 21127.575 | F61: =_xlfn.SUMIFS(Allocation!$W$1:$W$175,Allocation!$C$1:$C$175,"2026",Allocation!$D$1:$D$175,"ISCOM_TLS",Allocation!$F$1:$F$175,"MAS_COM",Allocation!$G$1:$G$175,"M2",Allocation!$H$1:$H$175,"ALT") -> 39226.075 | G61: =_xlfn.SUMIFS(Allocation!$X$1:$X$175,Allocation!$C$1:$C$175,"2026",Allocation!$D$1:$D$175,"ISCOM_TLS",Allocation!$F$1:$F$175,"MAS_COM",Allocation!$G$1:$G$175,"M2",Allocation!$H$1:$H$175,"ALT") -> 17116.381 | H61: =_xlfn.SUMIFS(Allocation!$Y$1:$Y$175,Allocation!$C$1:$C$175,"2026",Allocation!$D$1:$D$175,"ISCOM_TLS",Allocation!$F$1:$F$175,"MAS_COM",Allocation!$G$1:$G$175,"M2",Allocation!$H$1:$H$175,"ALT") -> 0 | I61: =_xlfn.SUMIFS(Allocation!$AC$1:$AC$175,Allocation!$C$1:$C$175,"2026",Allocation!$D$1:$D$175,"ISCOM_TLS",Allocation!$F$1:$F$175,"MAS_COM",Allocation!$G$1:$G$175,"M2",Allocation!$H$1:$H$175,"ALT") -> 0 | J61: =_xlfn.SUMIFS(Allocation!$Z$1:$Z$175,Allocation!$C$1:$C$175,"2026",Allocation!$D$1:$D$175,"ISCOM_TLS",Allocation!$F$1:$F$175,"MAS_COM",Allocation!$G$1:$G$175,"M2",Allocation!$H$1:$H$175,"ALT") -> 0 | K61: =E61+F61+G61+H61+I61+J61 -> 77470.031 | L61: =_xlfn.SUMIFS(Allocation!$AA$1:$AA$175,Allocation!$C$1:$C$175,"2026",Allocation!$D$1:$D$175,"ISCOM_TLS",Allocation!$F$1:$F$175,"MAS_COM",Allocation!$G$1:$G$175,"M2",Allocation!$H$1:$H$175,"ALT") -> 253729.97 | M61: =_xlfn.IFERROR(L61/D61,0) -> 0.7660929
B62: Ipac | C62: =_xlfn.SUMIFS(Allocation!$I$1:$I$175,Allocation!$C$1:$C$175,"2026",Allocation!$E$1:$E$175,"IPAC") -> 379 | D62: =_xlfn.SUMIFS(Allocation!$K$1:$K$175,Allocation!$C$1:$C$175,"2026",Allocation!$E$1:$E$175,"IPAC") -> 2582800 | E62: =_xlfn.SUMIFS(Allocation!$V$1:$V$175,Allocation!$C$1:$C$175,"2026",Allocation!$E$1:$E$175,"IPAC") -> 217314 | F62: =_xlfn.SUMIFS(Allocation!$W$1:$W$175,Allocation!$C$1:$C$175,"2026",Allocation!$E$1:$E$175,"IPAC") -> 412435 | G62: =_xlfn.SUMIFS(Allocation!$X$1:$X$175,Allocation!$C$1:$C$175,"2026",Allocation!$E$1:$E$175,"IPAC") -> 192895 | H62: =_xlfn.SUMIFS(Allocation!$Y$1:$Y$175,Allocation!$C$1:$C$175,"2026",Allocation!$E$1:$E$175,"IPAC") -> 0 | I62: =_xlfn.SUMIFS(Allocation!$AC$1:$AC$175,Allocation!$C$1:$C$175,"2026",Allocation!$E$1:$E$175,"IPAC") -> 0 | J62: =_xlfn.SUMIFS(Allocation!$Z$1:$Z$175,Allocation!$C$1:$C$175,"2026",Allocation!$E$1:$E$175,"IPAC") -> 0 | K62: =E62+F62+G62+H62+I62+J62 -> 822644 | L62: =_xlfn.SUMIFS(Allocation!$AA$1:$AA$175,Allocation!$C$1:$C$175,"2026",Allocation!$E$1:$E$175,"IPAC") -> 1760156 | M62: =_xlfn.IFERROR(L62/D62,0) -> 0.6814914
B63: Nantes (IPAC_NAN) | C63: =_xlfn.SUMIFS(Allocation!$I$1:$I$175,Allocation!$C$1:$C$175,"2026",Allocation!$D$1:$D$175,"IPAC_NAN") -> 145 | D63: =_xlfn.SUMIFS(Allocation!$K$1:$K$175,Allocation!$C$1:$C$175,"2026",Allocation!$D$1:$D$175,"IPAC_NAN") -> 1019500 | E63: =_xlfn.SUMIFS(Allocation!$V$1:$V$175,Allocation!$C$1:$C$175,"2026",Allocation!$D$1:$D$175,"IPAC_NAN") -> 72438 | F63: =_xlfn.SUMIFS(Allocation!$W$1:$W$175,Allocation!$C$1:$C$175,"2026",Allocation!$D$1:$D$175,"IPAC_NAN") -> 149433 | G63: =_xlfn.SUMIFS(Allocation!$X$1:$X$175,Allocation!$C$1:$C$175,"2026",Allocation!$D$1:$D$175,"IPAC_NAN") -> 75714 | H63: =_xlfn.SUMIFS(Allocation!$Y$1:$Y$175,Allocation!$C$1:$C$175,"2026",Allocation!$D$1:$D$175,"IPAC_NAN") -> 0 | I63: =_xlfn.SUMIFS(Allocation!$AC$1:$AC$175,Allocation!$C$1:$C$175,"2026",Allocation!$D$1:$D$175,"IPAC_NAN") -> 0 | J63: =_xlfn.SUMIFS(Allocation!$Z$1:$Z$175,Allocation!$C$1:$C$175,"2026",Allocation!$D$1:$D$175,"IPAC_NAN") -> 0 | K63: =E63+F63+G63+H63+I63+J63 -> 297585 | L63: =_xlfn.SUMIFS(Allocation!$AA$1:$AA$175,Allocation!$C$1:$C$175,"2026",Allocation!$D$1:$D$175,"IPAC_NAN") -> 721915 | M63: =_xlfn.IFERROR(L63/D63,0) -> 0.70810692
B64: BAC_CCE B1 ALT | C64: =_xlfn.SUMIFS(Allocation!$I$1:$I$175,Allocation!$C$1:$C$175,"2026",Allocation!$D$1:$D$175,"IPAC_NAN",Allocation!$F$1:$F$175,"BAC_CCE",Allocation!$G$1:$G$175,"B1",Allocation!$H$1:$H$175,"ALT") -> 50 | D64: =_xlfn.SUMIFS(Allocation!$K$1:$K$175,Allocation!$C$1:$C$175,"2026",Allocation!$D$1:$D$175,"IPAC_NAN",Allocation!$F$1:$F$175,"BAC_CCE",Allocation!$G$1:$G$175,"B1",Allocation!$H$1:$H$175,"ALT") -> 354500 | E64: =_xlfn.SUMIFS(Allocation!$V$1:$V$175,Allocation!$C$1:$C$175,"2026",Allocation!$D$1:$D$175,"IPAC_NAN",Allocation!$F$1:$F$175,"BAC_CCE",Allocation!$G$1:$G$175,"B1",Allocation!$H$1:$H$175,"ALT") -> 24146 | F64: =_xlfn.SUMIFS(Allocation!$W$1:$W$175,Allocation!$C$1:$C$175,"2026",Allocation!$D$1:$D$175,"IPAC_NAN",Allocation!$F$1:$F$175,"BAC_CCE",Allocation!$G$1:$G$175,"B1",Allocation!$H$1:$H$175,"ALT") -> 49811 | G64: =_xlfn.SUMIFS(Allocation!$X$1:$X$175,Allocation!$C$1:$C$175,"2026",Allocation!$D$1:$D$175,"IPAC_NAN",Allocation!$F$1:$F$175,"BAC_CCE",Allocation!$G$1:$G$175,"B1",Allocation!$H$1:$H$175,"ALT") -> 40364.828 | H64: =_xlfn.SUMIFS(Allocation!$Y$1:$Y$175,Allocation!$C$1:$C$175,"2026",Allocation!$D$1:$D$175,"IPAC_NAN",Allocation!$F$1:$F$175,"BAC_CCE",Allocation!$G$1:$G$175,"B1",Allocation!$H$1:$H$175,"ALT") -> 0 | I64: =_xlfn.SUMIFS(Allocation!$AC$1:$AC$175,Allocation!$C$1:$C$175,"2026",Allocation!$D$1:$D$175,"IPAC_NAN",Allocation!$F$1:$F$175,"BAC_CCE",Allocation!$G$1:$G$175,"B1",Allocation!$H$1:$H$175,"ALT") -> 0 | J64: =_xlfn.SUMIFS(Allocation!$Z$1:$Z$175,Allocation!$C$1:$C$175,"2026",Allocation!$D$1:$D$175,"IPAC_NAN",Allocation!$F$1:$F$175,"BAC_CCE",Allocation!$G$1:$G$175,"B1",Allocation!$H$1:$H$175,"ALT") -> 0 | K64: =E64+F64+G64+H64+I64+J64 -> 114321.83 | L64: =_xlfn.SUMIFS(Allocation!$AA$1:$AA$175,Allocation!$C$1:$C$175,"2026",Allocation!$D$1:$D$175,"IPAC_NAN",Allocation!$F$1:$F$175,"BAC_CCE",Allocation!$G$1:$G$175,"B1",Allocation!$H$1:$H$175,"ALT") -> 240178.17 | M64: =_xlfn.IFERROR(L64/D64,0) -> 0.67751248
B65: BAC_CCE B2 ALT | C65: =_xlfn.SUMIFS(Allocation!$I$1:$I$175,Allocation!$C$1:$C$175,"2026",Allocation!$D$1:$D$175,"IPAC_NAN",Allocation!$F$1:$F$175,"BAC_CCE",Allocation!$G$1:$G$175,"B2",Allocation!$H$1:$H$175,"ALT") -> 48 | D65: =_xlfn.SUMIFS(Allocation!$K$1:$K$175,Allocation!$C$1:$C$175,"2026",Allocation!$D$1:$D$175,"IPAC_NAN",Allocation!$F$1:$F$175,"BAC_CCE",Allocation!$G$1:$G$175,"B2",Allocation!$H$1:$H$175,"ALT") -> 336000 | E65: =_xlfn.SUMIFS(Allocation!$V$1:$V$175,Allocation!$C$1:$C$175,"2026",Allocation!$D$1:$D$175,"IPAC_NAN",Allocation!$F$1:$F$175,"BAC_CCE",Allocation!$G$1:$G$175,"B2",Allocation!$H$1:$H$175,"ALT") -> 24146 | F65: =_xlfn.SUMIFS(Allocation!$W$1:$W$175,Allocation!$C$1:$C$175,"2026",Allocation!$D$1:$D$175,"IPAC_NAN",Allocation!$F$1:$F$175,"BAC_CCE",Allocation!$G$1:$G$175,"B2",Allocation!$H$1:$H$175,"ALT") -> 49811 | G65: =_xlfn.SUMIFS(Allocation!$X$1:$X$175,Allocation!$C$1:$C$175,"2026",Allocation!$D$1:$D$175,"IPAC_NAN",Allocation!$F$1:$F$175,"BAC_CCE",Allocation!$G$1:$G$175,"B2",Allocation!$H$1:$H$175,"ALT") -> 17860.634 | H65: =_xlfn.SUMIFS(Allocation!$Y$1:$Y$175,Allocation!$C$1:$C$175,"2026",Allocation!$D$1:$D$175,"IPAC_NAN",Allocation!$F$1:$F$175,"BAC_CCE",Allocation!$G$1:$G$175,"B2",Allocation!$H$1:$H$175,"ALT") -> 0 | I65: =_xlfn.SUMIFS(Allocation!$AC$1:$AC$175,Allocation!$C$1:$C$175,"2026",Allocation!$D$1:$D$175,"IPAC_NAN",Allocation!$F$1:$F$175,"BAC_CCE",Allocation!$G$1:$G$175,"B2",Allocation!$H$1:$H$175,"ALT") -> 0 | J65: =_xlfn.SUMIFS(Allocation!$Z$1:$Z$175,Allocation!$C$1:$C$175,"2026",Allocation!$D$1:$D$175,"IPAC_NAN",Allocation!$F$1:$F$175,"BAC_CCE",Allocation!$G$1:$G$175,"B2",Allocation!$H$1:$H$175,"ALT") -> 0 | K65: =E65+F65+G65+H65+I65+J65 -> 91817.634 | L65: =_xlfn.SUMIFS(Allocation!$AA$1:$AA$175,Allocation!$C$1:$C$175,"2026",Allocation!$D$1:$D$175,"IPAC_NAN",Allocation!$F$1:$F$175,"BAC_CCE",Allocation!$G$1:$G$175,"B2",Allocation!$H$1:$H$175,"ALT") -> 244182.37 | M65: =_xlfn.IFERROR(L65/D65,0) -> 0.72673323
B66: BAC_CCE B3 ALT | C66: =_xlfn.SUMIFS(Allocation!$I$1:$I$175,Allocation!$C$1:$C$175,"2026",Allocation!$D$1:$D$175,"IPAC_NAN",Allocation!$F$1:$F$175,"BAC_CCE",Allocation!$G$1:$G$175,"B3",Allocation!$H$1:$H$175,"ALT") -> 47 | D66: =_xlfn.SUMIFS(Allocation!$K$1:$K$175,Allocation!$C$1:$C$175,"2026",Allocation!$D$1:$D$175,"IPAC_NAN",Allocation!$F$1:$F$175,"BAC_CCE",Allocation!$G$1:$G$175,"B3",Allocation!$H$1:$H$175,"ALT") -> 329000 | E66: =_xlfn.SUMIFS(Allocation!$V$1:$V$175,Allocation!$C$1:$C$175,"2026",Allocation!$D$1:$D$175,"IPAC_NAN",Allocation!$F$1:$F$175,"BAC_CCE",Allocation!$G$1:$G$175,"B3",Allocation!$H$1:$H$175,"ALT") -> 24146 | F66: =_xlfn.SUMIFS(Allocation!$W$1:$W$175,Allocation!$C$1:$C$175,"2026",Allocation!$D$1:$D$175,"IPAC_NAN",Allocation!$F$1:$F$175,"BAC_CCE",Allocation!$G$1:$G$175,"B3",Allocation!$H$1:$H$175,"ALT") -> 49811 | G66: =_xlfn.SUMIFS(Allocation!$X$1:$X$175,Allocation!$C$1:$C$175,"2026",Allocation!$D$1:$D$175,"IPAC_NAN",Allocation!$F$1:$F$175,"BAC_CCE",Allocation!$G$1:$G$175,"B3",Allocation!$H$1:$H$175,"ALT") -> 17488.538 | H66: =_xlfn.SUMIFS(Allocation!$Y$1:$Y$175,Allocation!$C$1:$C$175,"2026",Allocation!$D$1:$D$175,"IPAC_NAN",Allocation!$F$1:$F$175,"BAC_CCE",Allocation!$G$1:$G$175,"B3",Allocation!$H$1:$H$175,"ALT") -> 0 | I66: =_xlfn.SUMIFS(Allocation!$AC$1:$AC$175,Allocation!$C$1:$C$175,"2026",Allocation!$D$1:$D$175,"IPAC_NAN",Allocation!$F$1:$F$175,"BAC_CCE",Allocation!$G$1:$G$175,"B3",Allocation!$H$1:$H$175,"ALT") -> 0 | J66: =_xlfn.SUMIFS(Allocation!$Z$1:$Z$175,Allocation!$C$1:$C$175,"2026",Allocation!$D$1:$D$175,"IPAC_NAN",Allocation!$F$1:$F$175,"BAC_CCE",Allocation!$G$1:$G$175,"B3",Allocation!$H$1:$H$175,"ALT") -> 0 | K66: =E66+F66+G66+H66+I66+J66 -> 91445.538 | L66: =_xlfn.SUMIFS(Allocation!$AA$1:$AA$175,Allocation!$C$1:$C$175,"2026",Allocation!$D$1:$D$175,"IPAC_NAN",Allocation!$F$1:$F$175,"BAC_CCE",Allocation!$G$1:$G$175,"B3",Allocation!$H$1:$H$175,"ALT") -> 237554.46 | M66: =_xlfn.IFERROR(L66/D66,0) -> 0.72205004
B67: Rennes (IPAC_REN) | C67: =_xlfn.SUMIFS(Allocation!$I$1:$I$175,Allocation!$C$1:$C$175,"2026",Allocation!$D$1:$D$175,"IPAC_REN") -> 117 | D67: =_xlfn.SUMIFS(Allocation!$K$1:$K$175,Allocation!$C$1:$C$175,"2026",Allocation!$D$1:$D$175,"IPAC_REN") -> 781650 | E67: =_xlfn.SUMIFS(Allocation!$V$1:$V$175,Allocation!$C$1:$C$175,"2026",Allocation!$D$1:$D$175,"IPAC_REN") -> 72438 | F67: =_xlfn.SUMIFS(Allocation!$W$1:$W$175,Allocation!$C$1:$C$175,"2026",Allocation!$D$1:$D$175,"IPAC_REN") -> 131501 | G67: =_xlfn.SUMIFS(Allocation!$X$1:$X$175,Allocation!$C$1:$C$175,"2026",Allocation!$D$1:$D$175,"IPAC_REN") -> 58468 | H67: =_xlfn.SUMIFS(Allocation!$Y$1:$Y$175,Allocation!$C$1:$C$175,"2026",Allocation!$D$1:$D$175,"IPAC_REN") -> 0 | I67: =_xlfn.SUMIFS(Allocation!$AC$1:$AC$175,Allocation!$C$1:$C$175,"2026",Allocation!$D$1:$D$175,"IPAC_REN") -> 0 | J67: =_xlfn.SUMIFS(Allocation!$Z$1:$Z$175,Allocation!$C$1:$C$175,"2026",Allocation!$D$1:$D$175,"IPAC_REN") -> 0 | K67: =E67+F67+G67+H67+I67+J67 -> 262407 | L67: =_xlfn.SUMIFS(Allocation!$AA$1:$AA$175,Allocation!$C$1:$C$175,"2026",Allocation!$D$1:$D$175,"IPAC_REN") -> 519243 | M67: =_xlfn.IFERROR(L67/D67,0) -> 0.66429092
B68: BAC_CCE B1 ALT | C68: =_xlfn.SUMIFS(Allocation!$I$1:$I$175,Allocation!$C$1:$C$175,"2026",Allocation!$D$1:$D$175,"IPAC_REN",Allocation!$F$1:$F$175,"BAC_CCE",Allocation!$G$1:$G$175,"B1",Allocation!$H$1:$H$175,"ALT") -> 40 | D68: =_xlfn.SUMIFS(Allocation!$K$1:$K$175,Allocation!$C$1:$C$175,"2026",Allocation!$D$1:$D$175,"IPAC_REN",Allocation!$F$1:$F$175,"BAC_CCE",Allocation!$G$1:$G$175,"B1",Allocation!$H$1:$H$175,"ALT") -> 269600 | E68: =_xlfn.SUMIFS(Allocation!$V$1:$V$175,Allocation!$C$1:$C$175,"2026",Allocation!$D$1:$D$175,"IPAC_REN",Allocation!$F$1:$F$175,"BAC_CCE",Allocation!$G$1:$G$175,"B1",Allocation!$H$1:$H$175,"ALT") -> 24146 | F68: =_xlfn.SUMIFS(Allocation!$W$1:$W$175,Allocation!$C$1:$C$175,"2026",Allocation!$D$1:$D$175,"IPAC_REN",Allocation!$F$1:$F$175,"BAC_CCE",Allocation!$G$1:$G$175,"B1",Allocation!$H$1:$H$175,"ALT") -> 43833.667 | G68: =_xlfn.SUMIFS(Allocation!$X$1:$X$175,Allocation!$C$1:$C$175,"2026",Allocation!$D$1:$D$175,"IPAC_REN",Allocation!$F$1:$F$175,"BAC_CCE",Allocation!$G$1:$G$175,"B1",Allocation!$H$1:$H$175,"ALT") -> 29816.761 | H68: =_xlfn.SUMIFS(Allocation!$Y$1:$Y$175,Allocation!$C$1:$C$175,"2026",Allocation!$D$1:$D$175,"IPAC_REN",Allocation!$F$1:$F$175,"BAC_CCE",Allocation!$G$1:$G$175,"B1",Allocation!$H$1:$H$175,"ALT") -> 0 | I68: =_xlfn.SUMIFS(Allocation!$AC$1:$AC$175,Allocation!$C$1:$C$175,"2026",Allocation!$D$1:$D$175,"IPAC_REN",Allocation!$F$1:$F$175,"BAC_CCE",Allocation!$G$1:$G$175,"B1",Allocation!$H$1:$H$175,"ALT") -> 0 | J68: =_xlfn.SUMIFS(Allocation!$Z$1:$Z$175,Allocation!$C$1:$C$175,"2026",Allocation!$D$1:$D$175,"IPAC_REN",Allocation!$F$1:$F$175,"BAC_CCE",Allocation!$G$1:$G$175,"B1",Allocation!$H$1:$H$175,"ALT") -> 0 | K68: =E68+F68+G68+H68+I68+J68 -> 97796.427 | L68: =_xlfn.SUMIFS(Allocation!$AA$1:$AA$175,Allocation!$C$1:$C$175,"2026",Allocation!$D$1:$D$175,"IPAC_REN",Allocation!$F$1:$F$175,"BAC_CCE",Allocation!$G$1:$G$175,"B1",Allocation!$H$1:$H$175,"ALT") -> 171803.57 | M68: =_xlfn.IFERROR(L68/D68,0) -> 0.63725361
B69: BAC_CCE B2 ALT | C69: =_xlfn.SUMIFS(Allocation!$I$1:$I$175,Allocation!$C$1:$C$175,"2026",Allocation!$D$1:$D$175,"IPAC_REN",Allocation!$F$1:$F$175,"BAC_CCE",Allocation!$G$1:$G$175,"B2",Allocation!$H$1:$H$175,"ALT") -> 39 | D69: =_xlfn.SUMIFS(Allocation!$K$1:$K$175,Allocation!$C$1:$C$175,"2026",Allocation!$D$1:$D$175,"IPAC_REN",Allocation!$F$1:$F$175,"BAC_CCE",Allocation!$G$1:$G$175,"B2",Allocation!$H$1:$H$175,"ALT") -> 259350 | E69: =_xlfn.SUMIFS(Allocation!$V$1:$V$175,Allocation!$C$1:$C$175,"2026",Allocation!$D$1:$D$175,"IPAC_REN",Allocation!$F$1:$F$175,"BAC_CCE",Allocation!$G$1:$G$175,"B2",Allocation!$H$1:$H$175,"ALT") -> 24146 | F69: =_xlfn.SUMIFS(Allocation!$W$1:$W$175,Allocation!$C$1:$C$175,"2026",Allocation!$D$1:$D$175,"IPAC_REN",Allocation!$F$1:$F$175,"BAC_CCE",Allocation!$G$1:$G$175,"B2",Allocation!$H$1:$H$175,"ALT") -> 43833.667 | G69: =_xlfn.SUMIFS(Allocation!$X$1:$X$175,Allocation!$C$1:$C$175,"2026",Allocation!$D$1:$D$175,"IPAC_REN",Allocation!$F$1:$F$175,"BAC_CCE",Allocation!$G$1:$G$175,"B2",Allocation!$H$1:$H$175,"ALT") -> 14511.667 | H69: =_xlfn.SUMIFS(Allocation!$Y$1:$Y$175,Allocation!$C$1:$C$175,"2026",Allocation!$D$1:$D$175,"IPAC_REN",Allocation!$F$1:$F$175,"BAC_CCE",Allocation!$G$1:$G$175,"B2",Allocation!$H$1:$H$175,"ALT") -> 0 | I69: =_xlfn.SUMIFS(Allocation!$AC$1:$AC$175,Allocation!$C$1:$C$175,"2026",Allocation!$D$1:$D$175,"IPAC_REN",Allocation!$F$1:$F$175,"BAC_CCE",Allocation!$G$1:$G$175,"B2",Allocation!$H$1:$H$175,"ALT") -> 0 | J69: =_xlfn.SUMIFS(Allocation!$Z$1:$Z$175,Allocation!$C$1:$C$175,"2026",Allocation!$D$1:$D$175,"IPAC_REN",Allocation!$F$1:$F$175,"BAC_CCE",Allocation!$G$1:$G$175,"B2",Allocation!$H$1:$H$175,"ALT") -> 0 | K69: =E69+F69+G69+H69+I69+J69 -> 82491.333 | L69: =_xlfn.SUMIFS(Allocation!$AA$1:$AA$175,Allocation!$C$1:$C$175,"2026",Allocation!$D$1:$D$175,"IPAC_REN",Allocation!$F$1:$F$175,"BAC_CCE",Allocation!$G$1:$G$175,"B2",Allocation!$H$1:$H$175,"ALT") -> 176858.67 | M69: =_xlfn.IFERROR(L69/D69,0) -> 0.68193047
B70: BAC_CCE B3 ALT | C70: =_xlfn.SUMIFS(Allocation!$I$1:$I$175,Allocation!$C$1:$C$175,"2026",Allocation!$D$1:$D$175,"IPAC_REN",Allocation!$F$1:$F$175,"BAC_CCE",Allocation!$G$1:$G$175,"B3",Allocation!$H$1:$H$175,"ALT") -> 38 | D70: =_xlfn.SUMIFS(Allocation!$K$1:$K$175,Allocation!$C$1:$C$175,"2026",Allocation!$D$1:$D$175,"IPAC_REN",Allocation!$F$1:$F$175,"BAC_CCE",Allocation!$G$1:$G$175,"B3",Allocation!$H$1:$H$175,"ALT") -> 252700 | E70: =_xlfn.SUMIFS(Allocation!$V$1:$V$175,Allocation!$C$1:$C$175,"2026",Allocation!$D$1:$D$175,"IPAC_REN",Allocation!$F$1:$F$175,"BAC_CCE",Allocation!$G$1:$G$175,"B3",Allocation!$H$1:$H$175,"ALT") -> 24146 | F70: =_xlfn.SUMIFS(Allocation!$W$1:$W$175,Allocation!$C$1:$C$175,"2026",Allocation!$D$1:$D$175,"IPAC_REN",Allocation!$F$1:$F$175,"BAC_CCE",Allocation!$G$1:$G$175,"B3",Allocation!$H$1:$H$175,"ALT") -> 43833.667 | G70: =_xlfn.SUMIFS(Allocation!$X$1:$X$175,Allocation!$C$1:$C$175,"2026",Allocation!$D$1:$D$175,"IPAC_REN",Allocation!$F$1:$F$175,"BAC_CCE",Allocation!$G$1:$G$175,"B3",Allocation!$H$1:$H$175,"ALT") -> 14139.573 | H70: =_xlfn.SUMIFS(Allocation!$Y$1:$Y$175,Allocation!$C$1:$C$175,"2026",Allocation!$D$1:$D$175,"IPAC_REN",Allocation!$F$1:$F$175,"BAC_CCE",Allocation!$G$1:$G$175,"B3",Allocation!$H$1:$H$175,"ALT") -> 0 | I70: =_xlfn.SUMIFS(Allocation!$AC$1:$AC$175,Allocation!$C$1:$C$175,"2026",Allocation!$D$1:$D$175,"IPAC_REN",Allocation!$F$1:$F$175,"BAC_CCE",Allocation!$G$1:$G$175,"B3",Allocation!$H$1:$H$175,"ALT") -> 0 | J70: =_xlfn.SUMIFS(Allocation!$Z$1:$Z$175,Allocation!$C$1:$C$175,"2026",Allocation!$D$1:$D$175,"IPAC_REN",Allocation!$F$1:$F$175,"BAC_CCE",Allocation!$G$1:$G$175,"B3",Allocation!$H$1:$H$175,"ALT") -> 0 | K70: =E70+F70+G70+H70+I70+J70 -> 82119.239 | L70: =_xlfn.SUMIFS(Allocation!$AA$1:$AA$175,Allocation!$C$1:$C$175,"2026",Allocation!$D$1:$D$175,"IPAC_REN",Allocation!$F$1:$F$175,"BAC_CCE",Allocation!$G$1:$G$175,"B3",Allocation!$H$1:$H$175,"ALT") -> 170580.76 | M70: =_xlfn.IFERROR(L70/D70,0) -> 0.67503269
B71: Montpellier (IPAC_MTP) | C71: =_xlfn.SUMIFS(Allocation!$I$1:$I$175,Allocation!$C$1:$C$175,"2026",Allocation!$D$1:$D$175,"IPAC_MTP") -> 117 | D71: =_xlfn.SUMIFS(Allocation!$K$1:$K$175,Allocation!$C$1:$C$175,"2026",Allocation!$D$1:$D$175,"IPAC_MTP") -> 781650 | E71: =_xlfn.SUMIFS(Allocation!$V$1:$V$175,Allocation!$C$1:$C$175,"2026",Allocation!$D$1:$D$175,"IPAC_MTP") -> 72438 | F71: =_xlfn.SUMIFS(Allocation!$W$1:$W$175,Allocation!$C$1:$C$175,"2026",Allocation!$D$1:$D$175,"IPAC_MTP") -> 131501 | G71: =_xlfn.SUMIFS(Allocation!$X$1:$X$175,Allocation!$C$1:$C$175,"2026",Allocation!$D$1:$D$175,"IPAC_MTP") -> 58713 | H71: =_xlfn.SUMIFS(Allocation!$Y$1:$Y$175,Allocation!$C$1:$C$175,"2026",Allocation!$D$1:$D$175,"IPAC_MTP") -> 0 | I71: =_xlfn.SUMIFS(Allocation!$AC$1:$AC$175,Allocation!$C$1:$C$175,"2026",Allocation!$D$1:$D$175,"IPAC_MTP") -> 0 | J71: =_xlfn.SUMIFS(Allocation!$Z$1:$Z$175,Allocation!$C$1:$C$175,"2026",Allocation!$D$1:$D$175,"IPAC_MTP") -> 0 | K71: =E71+F71+G71+H71+I71+J71 -> 262652 | L71: =_xlfn.SUMIFS(Allocation!$AA$1:$AA$175,Allocation!$C$1:$C$175,"2026",Allocation!$D$1:$D$175,"IPAC_MTP") -> 518998 | M71: =_xlfn.IFERROR(L71/D71,0) -> 0.66397748
B72: BAC_CCE B1 ALT | C72: =_xlfn.SUMIFS(Allocation!$I$1:$I$175,Allocation!$C$1:$C$175,"2026",Allocation!$D$1:$D$175,"IPAC_MTP",Allocation!$F$1:$F$175,"BAC_CCE",Allocation!$G$1:$G$175,"B1",Allocation!$H$1:$H$175,"ALT") -> 40 | D72: =_xlfn.SUMIFS(Allocation!$K$1:$K$175,Allocation!$C$1:$C$175,"2026",Allocation!$D$1:$D$175,"IPAC_MTP",Allocation!$F$1:$F$175,"BAC_CCE",Allocation!$G$1:$G$175,"B1",Allocation!$H$1:$H$175,"ALT") -> 269600 | E72: =_xlfn.SUMIFS(Allocation!$V$1:$V$175,Allocation!$C$1:$C$175,"2026",Allocation!$D$1:$D$175,"IPAC_MTP",Allocation!$F$1:$F$175,"BAC_CCE",Allocation!$G$1:$G$175,"B1",Allocation!$H$1:$H$175,"ALT") -> 24146 | F72: =_xlfn.SUMIFS(Allocation!$W$1:$W$175,Allocation!$C$1:$C$175,"2026",Allocation!$D$1:$D$175,"IPAC_MTP",Allocation!$F$1:$F$175,"BAC_CCE",Allocation!$G$1:$G$175,"B1",Allocation!$H$1:$H$175,"ALT") -> 43833.667 | G72: =_xlfn.SUMIFS(Allocation!$X$1:$X$175,Allocation!$C$1:$C$175,"2026",Allocation!$D$1:$D$175,"IPAC_MTP",Allocation!$F$1:$F$175,"BAC_CCE",Allocation!$G$1:$G$175,"B1",Allocation!$H$1:$H$175,"ALT") -> 30061.761 | H72: =_xlfn.SUMIFS(Allocation!$Y$1:$Y$175,Allocation!$C$1:$C$175,"2026",Allocation!$D$1:$D$175,"IPAC_MTP",Allocation!$F$1:$F$175,"BAC_CCE",Allocation!$G$1:$G$175,"B1",Allocation!$H$1:$H$175,"ALT") -> 0 | I72: =_xlfn.SUMIFS(Allocation!$AC$1:$AC$175,Allocation!$C$1:$C$175,"2026",Allocation!$D$1:$D$175,"IPAC_MTP",Allocation!$F$1:$F$175,"BAC_CCE",Allocation!$G$1:$G$175,"B1",Allocation!$H$1:$H$175,"ALT") -> 0 | J72: =_xlfn.SUMIFS(Allocation!$Z$1:$Z$175,Allocation!$C$1:$C$175,"2026",Allocation!$D$1:$D$175,"IPAC_MTP",Allocation!$F$1:$F$175,"BAC_CCE",Allocation!$G$1:$G$175,"B1",Allocation!$H$1:$H$175,"ALT") -> 0 | K72: =E72+F72+G72+H72+I72+J72 -> 98041.427 | L72: =_xlfn.SUMIFS(Allocation!$AA$1:$AA$175,Allocation!$C$1:$C$175,"2026",Allocation!$D$1:$D$175,"IPAC_MTP",Allocation!$F$1:$F$175,"BAC_CCE",Allocation!$G$1:$G$175,"B1",Allocation!$H$1:$H$175,"ALT") -> 171558.57 | M72: =_xlfn.IFERROR(L72/D72,0) -> 0.63634485
B73: BAC_CCE B2 ALT | C73: =_xlfn.SUMIFS(Allocation!$I$1:$I$175,Allocation!$C$1:$C$175,"2026",Allocation!$D$1:$D$175,"IPAC_MTP",Allocation!$F$1:$F$175,"BAC_CCE",Allocation!$G$1:$G$175,"B2",Allocation!$H$1:$H$175,"ALT") -> 39 | D73: =_xlfn.SUMIFS(Allocation!$K$1:$K$175,Allocation!$C$1:$C$175,"2026",Allocation!$D$1:$D$175,"IPAC_MTP",Allocation!$F$1:$F$175,"BAC_CCE",Allocation!$G$1:$G$175,"B2",Allocation!$H$1:$H$175,"ALT") -> 259350 | E73: =_xlfn.SUMIFS(Allocation!$V$1:$V$175,Allocation!$C$1:$C$175,"2026",Allocation!$D$1:$D$175,"IPAC_MTP",Allocation!$F$1:$F$175,"BAC_CCE",Allocation!$G$1:$G$175,"B2",Allocation!$H$1:$H$175,"ALT") -> 24146 | F73: =_xlfn.SUMIFS(Allocation!$W$1:$W$175,Allocation!$C$1:$C$175,"2026",Allocation!$D$1:$D$175,"IPAC_MTP",Allocation!$F$1:$F$175,"BAC_CCE",Allocation!$G$1:$G$175,"B2",Allocation!$H$1:$H$175,"ALT") -> 43833.667 | G73: =_xlfn.SUMIFS(Allocation!$X$1:$X$175,Allocation!$C$1:$C$175,"2026",Allocation!$D$1:$D$175,"IPAC_MTP",Allocation!$F$1:$F$175,"BAC_CCE",Allocation!$G$1:$G$175,"B2",Allocation!$H$1:$H$175,"ALT") -> 14511.667 | H73: =_xlfn.SUMIFS(Allocation!$Y$1:$Y$175,Allocation!$C$1:$C$175,"2026",Allocation!$D$1:$D$175,"IPAC_MTP",Allocation!$F$1:$F$175,"BAC_CCE",Allocation!$G$1:$G$175,"B2",Allocation!$H$1:$H$175,"ALT") -> 0 | I73: =_xlfn.SUMIFS(Allocation!$AC$1:$AC$175,Allocation!$C$1:$C$175,"2026",Allocation!$D$1:$D$175,"IPAC_MTP",Allocation!$F$1:$F$175,"BAC_CCE",Allocation!$G$1:$G$175,"B2",Allocation!$H$1:$H$175,"ALT") -> 0 | J73: =_xlfn.SUMIFS(Allocation!$Z$1:$Z$175,Allocation!$C$1:$C$175,"2026",Allocation!$D$1:$D$175,"IPAC_MTP",Allocation!$F$1:$F$175,"BAC_CCE",Allocation!$G$1:$G$175,"B2",Allocation!$H$1:$H$175,"ALT") -> 0 | K73: =E73+F73+G73+H73+I73+J73 -> 82491.333 | L73: =_xlfn.SUMIFS(Allocation!$AA$1:$AA$175,Allocation!$C$1:$C$175,"2026",Allocation!$D$1:$D$175,"IPAC_MTP",Allocation!$F$1:$F$175,"BAC_CCE",Allocation!$G$1:$G$175,"B2",Allocation!$H$1:$H$175,"ALT") -> 176858.67 | M73: =_xlfn.IFERROR(L73/D73,0) -> 0.68193047
B74: BAC_CCE B3 ALT | C74: =_xlfn.SUMIFS(Allocation!$I$1:$I$175,Allocation!$C$1:$C$175,"2026",Allocation!$D$1:$D$175,"IPAC_MTP",Allocation!$F$1:$F$175,"BAC_CCE",Allocation!$G$1:$G$175,"B3",Allocation!$H$1:$H$175,"ALT") -> 38 | D74: =_xlfn.SUMIFS(Allocation!$K$1:$K$175,Allocation!$C$1:$C$175,"2026",Allocation!$D$1:$D$175,"IPAC_MTP",Allocation!$F$1:$F$175,"BAC_CCE",Allocation!$G$1:$G$175,"B3",Allocation!$H$1:$H$175,"ALT") -> 252700 | E74: =_xlfn.SUMIFS(Allocation!$V$1:$V$175,Allocation!$C$1:$C$175,"2026",Allocation!$D$1:$D$175,"IPAC_MTP",Allocation!$F$1:$F$175,"BAC_CCE",Allocation!$G$1:$G$175,"B3",Allocation!$H$1:$H$175,"ALT") -> 24146 | F74: =_xlfn.SUMIFS(Allocation!$W$1:$W$175,Allocation!$C$1:$C$175,"2026",Allocation!$D$1:$D$175,"IPAC_MTP",Allocation!$F$1:$F$175,"BAC_CCE",Allocation!$G$1:$G$175,"B3",Allocation!$H$1:$H$175,"ALT") -> 43833.667 | G74: =_xlfn.SUMIFS(Allocation!$X$1:$X$175,Allocation!$C$1:$C$175,"2026",Allocation!$D$1:$D$175,"IPAC_MTP",Allocation!$F$1:$F$175,"BAC_CCE",Allocation!$G$1:$G$175,"B3",Allocation!$H$1:$H$175,"ALT") -> 14139.573 | H74: =_xlfn.SUMIFS(Allocation!$Y$1:$Y$175,Allocation!$C$1:$C$175,"2026",Allocation!$D$1:$D$175,"IPAC_MTP",Allocation!$F$1:$F$175,"BAC_CCE",Allocation!$G$1:$G$175,"B3",Allocation!$H$1:$H$175,"ALT") -> 0 | I74: =_xlfn.SUMIFS(Allocation!$AC$1:$AC$175,Allocation!$C$1:$C$175,"2026",Allocation!$D$1:$D$175,"IPAC_MTP",Allocation!$F$1:$F$175,"BAC_CCE",Allocation!$G$1:$G$175,"B3",Allocation!$H$1:$H$175,"ALT") -> 0 | J74: =_xlfn.SUMIFS(Allocation!$Z$1:$Z$175,Allocation!$C$1:$C$175,"2026",Allocation!$D$1:$D$175,"IPAC_MTP",Allocation!$F$1:$F$175,"BAC_CCE",Allocation!$G$1:$G$175,"B3",Allocation!$H$1:$H$175,"ALT") -> 0 | K74: =E74+F74+G74+H74+I74+J74 -> 82119.239 | L74: =_xlfn.SUMIFS(Allocation!$AA$1:$AA$175,Allocation!$C$1:$C$175,"2026",Allocation!$D$1:$D$175,"IPAC_MTP",Allocation!$F$1:$F$175,"BAC_CCE",Allocation!$G$1:$G$175,"B3",Allocation!$H$1:$H$175,"ALT") -> 170580.76 | M74: =_xlfn.IFERROR(L74/D74,0) -> 0.67503269
B75: Pigier | C75: =_xlfn.SUMIFS(Allocation!$I$1:$I$175,Allocation!$C$1:$C$175,"2026",Allocation!$E$1:$E$175,"PIGIER") -> 324 | D75: =_xlfn.SUMIFS(Allocation!$K$1:$K$175,Allocation!$C$1:$C$175,"2026",Allocation!$E$1:$E$175,"PIGIER") -> 2152220 | E75: =_xlfn.SUMIFS(Allocation!$V$1:$V$175,Allocation!$C$1:$C$175,"2026",Allocation!$E$1:$E$175,"PIGIER") -> 193166 | F75: =_xlfn.SUMIFS(Allocation!$W$1:$W$175,Allocation!$C$1:$C$175,"2026",Allocation!$E$1:$E$175,"PIGIER") -> 432359 | G75: =_xlfn.SUMIFS(Allocation!$X$1:$X$175,Allocation!$C$1:$C$175,"2026",Allocation!$E$1:$E$175,"PIGIER") -> 179140 | H75: =_xlfn.SUMIFS(Allocation!$Y$1:$Y$175,Allocation!$C$1:$C$175,"2026",Allocation!$E$1:$E$175,"PIGIER") -> 0 | I75: =_xlfn.SUMIFS(Allocation!$AC$1:$AC$175,Allocation!$C$1:$C$175,"2026",Allocation!$E$1:$E$175,"PIGIER") -> 0 | J75: =_xlfn.SUMIFS(Allocation!$Z$1:$Z$175,Allocation!$C$1:$C$175,"2026",Allocation!$E$1:$E$175,"PIGIER") -> 0 | K75: =E75+F75+G75+H75+I75+J75 -> 804665 | L75: =_xlfn.SUMIFS(Allocation!$AA$1:$AA$175,Allocation!$C$1:$C$175,"2026",Allocation!$E$1:$E$175,"PIGIER") -> 1347555 | M75: =_xlfn.IFERROR(L75/D75,0) -> 0.62612326
B76: Lyon (PIGIER_LYO) | C76: =_xlfn.SUMIFS(Allocation!$I$1:$I$175,Allocation!$C$1:$C$175,"2026",Allocation!$D$1:$D$175,"PIGIER_LYO") -> 182 | D76: =_xlfn.SUMIFS(Allocation!$K$1:$K$175,Allocation!$C$1:$C$175,"2026",Allocation!$D$1:$D$175,"PIGIER_LYO") -> 1250430 | E76: =_xlfn.SUMIFS(Allocation!$V$1:$V$175,Allocation!$C$1:$C$175,"2026",Allocation!$D$1:$D$175,"PIGIER_LYO") -> 96583 | F76: =_xlfn.SUMIFS(Allocation!$W$1:$W$175,Allocation!$C$1:$C$175,"2026",Allocation!$D$1:$D$175,"PIGIER_LYO") -> 223153 | G76: =_xlfn.SUMIFS(Allocation!$X$1:$X$175,Allocation!$C$1:$C$175,"2026",Allocation!$D$1:$D$175,"PIGIER_LYO") -> 104334 | H76: =_xlfn.SUMIFS(Allocation!$Y$1:$Y$175,Allocation!$C$1:$C$175,"2026",Allocation!$D$1:$D$175,"PIGIER_LYO") -> 0 | I76: =_xlfn.SUMIFS(Allocation!$AC$1:$AC$175,Allocation!$C$1:$C$175,"2026",Allocation!$D$1:$D$175,"PIGIER_LYO") -> 0 | J76: =_xlfn.SUMIFS(Allocation!$Z$1:$Z$175,Allocation!$C$1:$C$175,"2026",Allocation!$D$1:$D$175,"PIGIER_LYO") -> 0 | K76: =E76+F76+G76+H76+I76+J76 -> 424070 | L76: =_xlfn.SUMIFS(Allocation!$AA$1:$AA$175,Allocation!$C$1:$C$175,"2026",Allocation!$D$1:$D$175,"PIGIER_LYO") -> 826360 | M76: =_xlfn.IFERROR(L76/D76,0) -> 0.66086066
B77: BTS_GES BTS1 ALT | C77: =_xlfn.SUMIFS(Allocation!$I$1:$I$175,Allocation!$C$1:$C$175,"2026",Allocation!$D$1:$D$175,"PIGIER_LYO",Allocation!$F$1:$F$175,"BTS_GES",Allocation!$G$1:$G$175,"BTS1",Allocation!$H$1:$H$175,"ALT") -> 46 | D77: =_xlfn.SUMIFS(Allocation!$K$1:$K$175,Allocation!$C$1:$C$175,"2026",Allocation!$D$1:$D$175,"PIGIER_LYO",Allocation!$F$1:$F$175,"BTS_GES",Allocation!$G$1:$G$175,"BTS1",Allocation!$H$1:$H$175,"ALT") -> 293940 | E77: =_xlfn.SUMIFS(Allocation!$V$1:$V$175,Allocation!$C$1:$C$175,"2026",Allocation!$D$1:$D$175,"PIGIER_LYO",Allocation!$F$1:$F$175,"BTS_GES",Allocation!$G$1:$G$175,"BTS1",Allocation!$H$1:$H$175,"ALT") -> 28647.5 | F77: =_xlfn.SUMIFS(Allocation!$W$1:$W$175,Allocation!$C$1:$C$175,"2026",Allocation!$D$1:$D$175,"PIGIER_LYO",Allocation!$F$1:$F$175,"BTS_GES",Allocation!$G$1:$G$175,"BTS1",Allocation!$H$1:$H$175,"ALT") -> 66189.449 | G77: =_xlfn.SUMIFS(Allocation!$X$1:$X$175,Allocation!$C$1:$C$175,"2026",Allocation!$D$1:$D$175,"PIGIER_LYO",Allocation!$F$1:$F$175,"BTS_GES",Allocation!$G$1:$G$175,"BTS1",Allocation!$H$1:$H$175,"ALT") -> 35422.549 | H77: =_xlfn.SUMIFS(Allocation!$Y$1:$Y$175,Allocation!$C$1:$C$175,"2026",Allocation!$D$1:$D$175,"PIGIER_LYO",Allocation!$F$1:$F$175,"BTS_GES",Allocation!$G$1:$G$175,"BTS1",Allocation!$H$1:$H$175,"ALT") -> 0 | I77: =_xlfn.SUMIFS(Allocation!$AC$1:$AC$175,Allocation!$C$1:$C$175,"2026",Allocation!$D$1:$D$175,"PIGIER_LYO",Allocation!$F$1:$F$175,"BTS_GES",Allocation!$G$1:$G$175,"BTS1",Allocation!$H$1:$H$175,"ALT") -> 0 | J77: =_xlfn.SUMIFS(Allocation!$Z$1:$Z$175,Allocation!$C$1:$C$175,"2026",Allocation!$D$1:$D$175,"PIGIER_LYO",Allocation!$F$1:$F$175,"BTS_GES",Allocation!$G$1:$G$175,"BTS1",Allocation!$H$1:$H$175,"ALT") -> 0 | K77: =E77+F77+G77+H77+I77+J77 -> 130259.5 | L77: =_xlfn.SUMIFS(Allocation!$AA$1:$AA$175,Allocation!$C$1:$C$175,"2026",Allocation!$D$1:$D$175,"PIGIER_LYO",Allocation!$F$1:$F$175,"BTS_GES",Allocation!$G$1:$G$175,"BTS1",Allocation!$H$1:$H$175,"ALT") -> 163680.5 | M77: =_xlfn.IFERROR(L77/D77,0) -> 0.55685004
B78: BTS_GES BTS2 ALT | C78: =_xlfn.SUMIFS(Allocation!$I$1:$I$175,Allocation!$C$1:$C$175,"2026",Allocation!$D$1:$D$175,"PIGIER_LYO",Allocation!$F$1:$F$175,"BTS_GES",Allocation!$G$1:$G$175,"BTS2",Allocation!$H$1:$H$175,"ALT") -> 45 | D78: =_xlfn.SUMIFS(Allocation!$K$1:$K$175,Allocation!$C$1:$C$175,"2026",Allocation!$D$1:$D$175,"PIGIER_LYO",Allocation!$F$1:$F$175,"BTS_GES",Allocation!$G$1:$G$175,"BTS2",Allocation!$H$1:$H$175,"ALT") -> 283500 | E78: =_xlfn.SUMIFS(Allocation!$V$1:$V$175,Allocation!$C$1:$C$175,"2026",Allocation!$D$1:$D$175,"PIGIER_LYO",Allocation!$F$1:$F$175,"BTS_GES",Allocation!$G$1:$G$175,"BTS2",Allocation!$H$1:$H$175,"ALT") -> 28647.5 | F78: =_xlfn.SUMIFS(Allocation!$W$1:$W$175,Allocation!$C$1:$C$175,"2026",Allocation!$D$1:$D$175,"PIGIER_LYO",Allocation!$F$1:$F$175,"BTS_GES",Allocation!$G$1:$G$175,"BTS2",Allocation!$H$1:$H$175,"ALT") -> 66189.449 | G78: =_xlfn.SUMIFS(Allocation!$X$1:$X$175,Allocation!$C$1:$C$175,"2026",Allocation!$D$1:$D$175,"PIGIER_LYO",Allocation!$F$1:$F$175,"BTS_GES",Allocation!$G$1:$G$175,"BTS2",Allocation!$H$1:$H$175,"ALT") -> 16744.451 | H78: =_xlfn.SUMIFS(Allocation!$Y$1:$Y$175,Allocation!$C$1:$C$175,"2026",Allocation!$D$1:$D$175,"PIGIER_LYO",Allocation!$F$1:$F$175,"BTS_GES",Allocation!$G$1:$G$175,"BTS2",Allocation!$H$1:$H$175,"ALT") -> 0 | I78: =_xlfn.SUMIFS(Allocation!$AC$1:$AC$175,Allocation!$C$1:$C$175,"2026",Allocation!$D$1:$D$175,"PIGIER_LYO",Allocation!$F$1:$F$175,"BTS_GES",Allocation!$G$1:$G$175,"BTS2",Allocation!$H$1:$H$175,"ALT") -> 0 | J78: =_xlfn.SUMIFS(Allocation!$Z$1:$Z$175,Allocation!$C$1:$C$175,"2026",Allocation!$D$1:$D$175,"PIGIER_LYO",Allocation!$F$1:$F$175,"BTS_GES",Allocation!$G$1:$G$175,"BTS2",Allocation!$H$1:$H$175,"ALT") -> 0 | K78: =E78+F78+G78+H78+I78+J78 -> 111581.4 | L78: =_xlfn.SUMIFS(Allocation!$AA$1:$AA$175,Allocation!$C$1:$C$175,"2026",Allocation!$D$1:$D$175,"PIGIER_LYO",Allocation!$F$1:$F$175,"BTS_GES",Allocation!$G$1:$G$175,"BTS2",Allocation!$H$1:$H$175,"ALT") -> 171918.6 | M78: =_xlfn.IFERROR(L78/D78,0) -> 0.60641482
B79: BAC_RH B1 ALT | C79: =_xlfn.SUMIFS(Allocation!$I$1:$I$175,Allocation!$C$1:$C$175,"2026",Allocation!$D$1:$D$175,"PIGIER_LYO",Allocation!$F$1:$F$175,"BAC_RH",Allocation!$G$1:$G$175,"B1",Allocation!$H$1:$H$175,"ALT") -> 46 | D79: =_xlfn.SUMIFS(Allocation!$K$1:$K$175,Allocation!$C$1:$C$175,"2026",Allocation!$D$1:$D$175,"PIGIER_LYO",Allocation!$F$1:$F$175,"BAC_RH",Allocation!$G$1:$G$175,"B1",Allocation!$H$1:$H$175,"ALT") -> 342240 | E79: =_xlfn.SUMIFS(Allocation!$V$1:$V$175,Allocation!$C$1:$C$175,"2026",Allocation!$D$1:$D$175,"PIGIER_LYO",Allocation!$F$1:$F$175,"BAC_RH",Allocation!$G$1:$G$175,"B1",Allocation!$H$1:$H$175,"ALT") -> 19644 | F79: =_xlfn.SUMIFS(Allocation!$W$1:$W$175,Allocation!$C$1:$C$175,"2026",Allocation!$D$1:$D$175,"PIGIER_LYO",Allocation!$F$1:$F$175,"BAC_RH",Allocation!$G$1:$G$175,"B1",Allocation!$H$1:$H$175,"ALT") -> 45387.051 | G79: =_xlfn.SUMIFS(Allocation!$X$1:$X$175,Allocation!$C$1:$C$175,"2026",Allocation!$D$1:$D$175,"PIGIER_LYO",Allocation!$F$1:$F$175,"BAC_RH",Allocation!$G$1:$G$175,"B1",Allocation!$H$1:$H$175,"ALT") -> 35422.549 | H79: =_xlfn.SUMIFS(Allocation!$Y$1:$Y$175,Allocation!$C$1:$C$175,"2026",Allocation!$D$1:$D$175,"PIGIER_LYO",Allocation!$F$1:$F$175,"BAC_RH",Allocation!$G$1:$G$175,"B1",Allocation!$H$1:$H$175,"ALT") -> 0 | I79: =_xlfn.SUMIFS(Allocation!$AC$1:$AC$175,Allocation!$C$1:$C$175,"2026",Allocation!$D$1:$D$175,"PIGIER_LYO",Allocation!$F$1:$F$175,"BAC_RH",Allocation!$G$1:$G$175,"B1",Allocation!$H$1:$H$175,"ALT") -> 0 | J79: =_xlfn.SUMIFS(Allocation!$Z$1:$Z$175,Allocation!$C$1:$C$175,"2026",Allocation!$D$1:$D$175,"PIGIER_LYO",Allocation!$F$1:$F$175,"BAC_RH",Allocation!$G$1:$G$175,"B1",Allocation!$H$1:$H$175,"ALT") -> 0 | K79: =E79+F79+G79+H79+I79+J79 -> 100453.6 | L79: =_xlfn.SUMIFS(Allocation!$AA$1:$AA$175,Allocation!$C$1:$C$175,"2026",Allocation!$D$1:$D$175,"PIGIER_LYO",Allocation!$F$1:$F$175,"BAC_RH",Allocation!$G$1:$G$175,"B1",Allocation!$H$1:$H$175,"ALT") -> 241786.4 | M79: =_xlfn.IFERROR(L79/D79,0) -> 0.706482
B80: BAC_RH B3 ALT | C80: =_xlfn.SUMIFS(Allocation!$I$1:$I$175,Allocation!$C$1:$C$175,"2026",Allocation!$D$1:$D$175,"PIGIER_LYO",Allocation!$F$1:$F$175,"BAC_RH",Allocation!$G$1:$G$175,"B3",Allocation!$H$1:$H$175,"ALT") -> 45 | D80: =_xlfn.SUMIFS(Allocation!$K$1:$K$175,Allocation!$C$1:$C$175,"2026",Allocation!$D$1:$D$175,"PIGIER_LYO",Allocation!$F$1:$F$175,"BAC_RH",Allocation!$G$1:$G$175,"B3",Allocation!$H$1:$H$175,"ALT") -> 330750 | E80: =_xlfn.SUMIFS(Allocation!$V$1:$V$175,Allocation!$C$1:$C$175,"2026",Allocation!$D$1:$D$175,"PIGIER_LYO",Allocation!$F$1:$F$175,"BAC_RH",Allocation!$G$1:$G$175,"B3",Allocation!$H$1:$H$175,"ALT") -> 19644 | F80: =_xlfn.SUMIFS(Allocation!$W$1:$W$175,Allocation!$C$1:$C$175,"2026",Allocation!$D$1:$D$175,"PIGIER_LYO",Allocation!$F$1:$F$175,"BAC_RH",Allocation!$G$1:$G$175,"B3",Allocation!$H$1:$H$175,"ALT") -> 45387.051 | G80: =_xlfn.SUMIFS(Allocation!$X$1:$X$175,Allocation!$C$1:$C$175,"2026",Allocation!$D$1:$D$175,"PIGIER_LYO",Allocation!$F$1:$F$175,"BAC_RH",Allocation!$G$1:$G$175,"B3",Allocation!$H$1:$H$175,"ALT") -> 16744.451 | H80: =_xlfn.SUMIFS(Allocation!$Y$1:$Y$175,Allocation!$C$1:$C$175,"2026",Allocation!$D$1:$D$175,"PIGIER_LYO",Allocation!$F$1:$F$175,"BAC_RH",Allocation!$G$1:$G$175,"B3",Allocation!$H$1:$H$175,"ALT") -> 0 | I80: =_xlfn.SUMIFS(Allocation!$AC$1:$AC$175,Allocation!$C$1:$C$175,"2026",Allocation!$D$1:$D$175,"PIGIER_LYO",Allocation!$F$1:$F$175,"BAC_RH",Allocation!$G$1:$G$175,"B3",Allocation!$H$1:$H$175,"ALT") -> 0 | J80: =_xlfn.SUMIFS(Allocation!$Z$1:$Z$175,Allocation!$C$1:$C$175,"2026",Allocation!$D$1:$D$175,"PIGIER_LYO",Allocation!$F$1:$F$175,"BAC_RH",Allocation!$G$1:$G$175,"B3",Allocation!$H$1:$H$175,"ALT") -> 0 | K80: =E80+F80+G80+H80+I80+J80 -> 81775.501 | L80: =_xlfn.SUMIFS(Allocation!$AA$1:$AA$175,Allocation!$C$1:$C$175,"2026",Allocation!$D$1:$D$175,"PIGIER_LYO",Allocation!$F$1:$F$175,"BAC_RH",Allocation!$G$1:$G$175,"B3",Allocation!$H$1:$H$175,"ALT") -> 248974.5 | M80: =_xlfn.IFERROR(L80/D80,0) -> 0.75275737
B81: Bordeaux (PIGIER_BOR) | C81: =_xlfn.SUMIFS(Allocation!$I$1:$I$175,Allocation!$C$1:$C$175,"2026",Allocation!$D$1:$D$175,"PIGIER_BOR") -> 142 | D81: =_xlfn.SUMIFS(Allocation!$K$1:$K$175,Allocation!$C$1:$C$175,"2026",Allocation!$D$1:$D$175,"PIGIER_BOR") -> 901790 | E81: =_xlfn.SUMIFS(Allocation!$V$1:$V$175,Allocation!$C$1:$C$175,"2026",Allocation!$D$1:$D$175,"PIGIER_BOR") -> 96583 | F81: =_xlfn.SUMIFS(Allocation!$W$1:$W$175,Allocation!$C$1:$C$175,"2026",Allocation!$D$1:$D$175,"PIGIER_BOR") -> 209206 | G81: =_xlfn.SUMIFS(Allocation!$X$1:$X$175,Allocation!$C$1:$C$175,"2026",Allocation!$D$1:$D$175,"PIGIER_BOR") -> 74806 | H81: =_xlfn.SUMIFS(Allocation!$Y$1:$Y$175,Allocation!$C$1:$C$175,"2026",Allocation!$D$1:$D$175,"PIGIER_BOR") -> 0 | I81: =_xlfn.SUMIFS(Allocation!$AC$1:$AC$175,Allocation!$C$1:$C$175,"2026",Allocation!$D$1:$D$175,"PIGIER_BOR") -> 0 | J81: =_xlfn.SUMIFS(Allocation!$Z$1:$Z$175,Allocation!$C$1:$C$175,"2026",Allocation!$D$1:$D$175,"PIGIER_BOR") -> 0 | K81: =E81+F81+G81+H81+I81+J81 -> 380595 | L81: =_xlfn.SUMIFS(Allocation!$AA$1:$AA$175,Allocation!$C$1:$C$175,"2026",Allocation!$D$1:$D$175,"PIGIER_BOR") -> 521195 | M81: =_xlfn.IFERROR(L81/D81,0) -> 0.57795607
B82: BTS_GES BTS1 ALT | C82: =_xlfn.SUMIFS(Allocation!$I$1:$I$175,Allocation!$C$1:$C$175,"2026",Allocation!$D$1:$D$175,"PIGIER_BOR",Allocation!$F$1:$F$175,"BTS_GES",Allocation!$G$1:$G$175,"BTS1",Allocation!$H$1:$H$175,"ALT") -> 36 | D82: =_xlfn.SUMIFS(Allocation!$K$1:$K$175,Allocation!$C$1:$C$175,"2026",Allocation!$D$1:$D$175,"PIGIER_BOR",Allocation!$F$1:$F$175,"BTS_GES",Allocation!$G$1:$G$175,"BTS1",Allocation!$H$1:$H$175,"ALT") -> 212760 | E82: =_xlfn.SUMIFS(Allocation!$V$1:$V$175,Allocation!$C$1:$C$175,"2026",Allocation!$D$1:$D$175,"PIGIER_BOR",Allocation!$F$1:$F$175,"BTS_GES",Allocation!$G$1:$G$175,"BTS1",Allocation!$H$1:$H$175,"ALT") -> 28647.5 | F82: =_xlfn.SUMIFS(Allocation!$W$1:$W$175,Allocation!$C$1:$C$175,"2026",Allocation!$D$1:$D$175,"PIGIER_BOR",Allocation!$F$1:$F$175,"BTS_GES",Allocation!$G$1:$G$175,"BTS1",Allocation!$H$1:$H$175,"ALT") -> 62052.627 | G82: =_xlfn.SUMIFS(Allocation!$X$1:$X$175,Allocation!$C$1:$C$175,"2026",Allocation!$D$1:$D$175,"PIGIER_BOR",Allocation!$F$1:$F$175,"BTS_GES",Allocation!$G$1:$G$175,"BTS1",Allocation!$H$1:$H$175,"ALT") -> 24379.549 | H82: =_xlfn.SUMIFS(Allocation!$Y$1:$Y$175,Allocation!$C$1:$C$175,"2026",Allocation!$D$1:$D$175,"PIGIER_BOR",Allocation!$F$1:$F$175,"BTS_GES",Allocation!$G$1:$G$175,"BTS1",Allocation!$H$1:$H$175,"ALT") -> 0 | I82: =_xlfn.SUMIFS(Allocation!$AC$1:$AC$175,Allocation!$C$1:$C$175,"2026",Allocation!$D$1:$D$175,"PIGIER_BOR",Allocation!$F$1:$F$175,"BTS_GES",Allocation!$G$1:$G$175,"BTS1",Allocation!$H$1:$H$175,"ALT") -> 0 | J82: =_xlfn.SUMIFS(Allocation!$Z$1:$Z$175,Allocation!$C$1:$C$175,"2026",Allocation!$D$1:$D$175,"PIGIER_BOR",Allocation!$F$1:$F$175,"BTS_GES",Allocation!$G$1:$G$175,"BTS1",Allocation!$H$1:$H$175,"ALT") -> 0 | K82: =E82+F82+G82+H82+I82+J82 -> 115079.68 | L82: =_xlfn.SUMIFS(Allocation!$AA$1:$AA$175,Allocation!$C$1:$C$175,"2026",Allocation!$D$1:$D$175,"PIGIER_BOR",Allocation!$F$1:$F$175,"BTS_GES",Allocation!$G$1:$G$175,"BTS1",Allocation!$H$1:$H$175,"ALT") -> 97680.324 | M82: =_xlfn.IFERROR(L82/D82,0) -> 0.45911038
B83: BTS_GES BTS2 ALT | C83: =_xlfn.SUMIFS(Allocation!$I$1:$I$175,Allocation!$C$1:$C$175,"2026",Allocation!$D$1:$D$175,"PIGIER_BOR",Allocation!$F$1:$F$175,"BTS_GES",Allocation!$G$1:$G$175,"BTS2",Allocation!$H$1:$H$175,"ALT") -> 35 | D83: =_xlfn.SUMIFS(Allocation!$K$1:$K$175,Allocation!$C$1:$C$175,"2026",Allocation!$D$1:$D$175,"PIGIER_BOR",Allocation!$F$1:$F$175,"BTS_GES",Allocation!$G$1:$G$175,"BTS2",Allocation!$H$1:$H$175,"ALT") -> 203700 | E83: =_xlfn.SUMIFS(Allocation!$V$1:$V$175,Allocation!$C$1:$C$175,"2026",Allocation!$D$1:$D$175,"PIGIER_BOR",Allocation!$F$1:$F$175,"BTS_GES",Allocation!$G$1:$G$175,"BTS2",Allocation!$H$1:$H$175,"ALT") -> 28647.5 | F83: =_xlfn.SUMIFS(Allocation!$W$1:$W$175,Allocation!$C$1:$C$175,"2026",Allocation!$D$1:$D$175,"PIGIER_BOR",Allocation!$F$1:$F$175,"BTS_GES",Allocation!$G$1:$G$175,"BTS2",Allocation!$H$1:$H$175,"ALT") -> 62052.627 | G83: =_xlfn.SUMIFS(Allocation!$X$1:$X$175,Allocation!$C$1:$C$175,"2026",Allocation!$D$1:$D$175,"PIGIER_BOR",Allocation!$F$1:$F$175,"BTS_GES",Allocation!$G$1:$G$175,"BTS2",Allocation!$H$1:$H$175,"ALT") -> 13023.451 | H83: =_xlfn.SUMIFS(Allocation!$Y$1:$Y$175,Allocation!$C$1:$C$175,"2026",Allocation!$D$1:$D$175,"PIGIER_BOR",Allocation!$F$1:$F$175,"BTS_GES",Allocation!$G$1:$G$175,"BTS2",Allocation!$H$1:$H$175,"ALT") -> 0 | I83: =_xlfn.SUMIFS(Allocation!$AC$1:$AC$175,Allocation!$C$1:$C$175,"2026",Allocation!$D$1:$D$175,"PIGIER_BOR",Allocation!$F$1:$F$175,"BTS_GES",Allocation!$G$1:$G$175,"BTS2",Allocation!$H$1:$H$175,"ALT") -> 0 | J83: =_xlfn.SUMIFS(Allocation!$Z$1:$Z$175,Allocation!$C$1:$C$175,"2026",Allocation!$D$1:$D$175,"PIGIER_BOR",Allocation!$F$1:$F$175,"BTS_GES",Allocation!$G$1:$G$175,"BTS2",Allocation!$H$1:$H$175,"ALT") -> 0 | K83: =E83+F83+G83+H83+I83+J83 -> 103723.58 | L83: =_xlfn.SUMIFS(Allocation!$AA$1:$AA$175,Allocation!$C$1:$C$175,"2026",Allocation!$D$1:$D$175,"PIGIER_BOR",Allocation!$F$1:$F$175,"BTS_GES",Allocation!$G$1:$G$175,"BTS2",Allocation!$H$1:$H$175,"ALT") -> 99976.422 | M83: =_xlfn.IFERROR(L83/D83,0) -> 0.49080227
B84: BAC_RH B1 ALT | C84: =_xlfn.SUMIFS(Allocation!$I$1:$I$175,Allocation!$C$1:$C$175,"2026",Allocation!$D$1:$D$175,"PIGIER_BOR",Allocation!$F$1:$F$175,"BAC_RH",Allocation!$G$1:$G$175,"B1",Allocation!$H$1:$H$175,"ALT") -> 36 | D84: =_xlfn.SUMIFS(Allocation!$K$1:$K$175,Allocation!$C$1:$C$175,"2026",Allocation!$D$1:$D$175,"PIGIER_BOR",Allocation!$F$1:$F$175,"BAC_RH",Allocation!$G$1:$G$175,"B1",Allocation!$H$1:$H$175,"ALT") -> 247680 | E84: =_xlfn.SUMIFS(Allocation!$V$1:$V$175,Allocation!$C$1:$C$175,"2026",Allocation!$D$1:$D$175,"PIGIER_BOR",Allocation!$F$1:$F$175,"BAC_RH",Allocation!$G$1:$G$175,"B1",Allocation!$H$1:$H$175,"ALT") -> 19644 | F84: =_xlfn.SUMIFS(Allocation!$W$1:$W$175,Allocation!$C$1:$C$175,"2026",Allocation!$D$1:$D$175,"PIGIER_BOR",Allocation!$F$1:$F$175,"BAC_RH",Allocation!$G$1:$G$175,"B1",Allocation!$H$1:$H$175,"ALT") -> 42550.373 | G84: =_xlfn.SUMIFS(Allocation!$X$1:$X$175,Allocation!$C$1:$C$175,"2026",Allocation!$D$1:$D$175,"PIGIER_BOR",Allocation!$F$1:$F$175,"BAC_RH",Allocation!$G$1:$G$175,"B1",Allocation!$H$1:$H$175,"ALT") -> 24379.549 | H84: =_xlfn.SUMIFS(Allocation!$Y$1:$Y$175,Allocation!$C$1:$C$175,"2026",Allocation!$D$1:$D$175,"PIGIER_BOR",Allocation!$F$1:$F$175,"BAC_RH",Allocation!$G$1:$G$175,"B1",Allocation!$H$1:$H$175,"ALT") -> 0 | I84: =_xlfn.SUMIFS(Allocation!$AC$1:$AC$175,Allocation!$C$1:$C$175,"2026",Allocation!$D$1:$D$175,"PIGIER_BOR",Allocation!$F$1:$F$175,"BAC_RH",Allocation!$G$1:$G$175,"B1",Allocation!$H$1:$H$175,"ALT") -> 0 | J84: =_xlfn.SUMIFS(Allocation!$Z$1:$Z$175,Allocation!$C$1:$C$175,"2026",Allocation!$D$1:$D$175,"PIGIER_BOR",Allocation!$F$1:$F$175,"BAC_RH",Allocation!$G$1:$G$175,"B1",Allocation!$H$1:$H$175,"ALT") -> 0 | K84: =E84+F84+G84+H84+I84+J84 -> 86573.922 | L84: =_xlfn.SUMIFS(Allocation!$AA$1:$AA$175,Allocation!$C$1:$C$175,"2026",Allocation!$D$1:$D$175,"PIGIER_BOR",Allocation!$F$1:$F$175,"BAC_RH",Allocation!$G$1:$G$175,"B1",Allocation!$H$1:$H$175,"ALT") -> 161106.08 | M84: =_xlfn.IFERROR(L84/D84,0) -> 0.65046059
B85: BAC_RH B3 ALT | C85: =_xlfn.SUMIFS(Allocation!$I$1:$I$175,Allocation!$C$1:$C$175,"2026",Allocation!$D$1:$D$175,"PIGIER_BOR",Allocation!$F$1:$F$175,"BAC_RH",Allocation!$G$1:$G$175,"B3",Allocation!$H$1:$H$175,"ALT") -> 35 | D85: =_xlfn.SUMIFS(Allocation!$K$1:$K$175,Allocation!$C$1:$C$175,"2026",Allocation!$D$1:$D$175,"PIGIER_BOR",Allocation!$F$1:$F$175,"BAC_RH",Allocation!$G$1:$G$175,"B3",Allocation!$H$1:$H$175,"ALT") -> 237650 | E85: =_xlfn.SUMIFS(Allocation!$V$1:$V$175,Allocation!$C$1:$C$175,"2026",Allocation!$D$1:$D$175,"PIGIER_BOR",Allocation!$F$1:$F$175,"BAC_RH",Allocation!$G$1:$G$175,"B3",Allocation!$H$1:$H$175,"ALT") -> 19644 | F85: =_xlfn.SUMIFS(Allocation!$W$1:$W$175,Allocation!$C$1:$C$175,"2026",Allocation!$D$1:$D$175,"PIGIER_BOR",Allocation!$F$1:$F$175,"BAC_RH",Allocation!$G$1:$G$175,"B3",Allocation!$H$1:$H$175,"ALT") -> 42550.373 | G85: =_xlfn.SUMIFS(Allocation!$X$1:$X$175,Allocation!$C$1:$C$175,"2026",Allocation!$D$1:$D$175,"PIGIER_BOR",Allocation!$F$1:$F$175,"BAC_RH",Allocation!$G$1:$G$175,"B3",Allocation!$H$1:$H$175,"ALT") -> 13023.451 | H85: =_xlfn.SUMIFS(Allocation!$Y$1:$Y$175,Allocation!$C$1:$C$175,"2026",Allocation!$D$1:$D$175,"PIGIER_BOR",Allocation!$F$1:$F$175,"BAC_RH",Allocation!$G$1:$G$175,"B3",Allocation!$H$1:$H$175,"ALT") -> 0 | I85: =_xlfn.SUMIFS(Allocation!$AC$1:$AC$175,Allocation!$C$1:$C$175,"2026",Allocation!$D$1:$D$175,"PIGIER_BOR",Allocation!$F$1:$F$175,"BAC_RH",Allocation!$G$1:$G$175,"B3",Allocation!$H$1:$H$175,"ALT") -> 0 | J85: =_xlfn.SUMIFS(Allocation!$Z$1:$Z$175,Allocation!$C$1:$C$175,"2026",Allocation!$D$1:$D$175,"PIGIER_BOR",Allocation!$F$1:$F$175,"BAC_RH",Allocation!$G$1:$G$175,"B3",Allocation!$H$1:$H$175,"ALT") -> 0 | K85: =E85+F85+G85+H85+I85+J85 -> 75217.824 | L85: =_xlfn.SUMIFS(Allocation!$AA$1:$AA$175,Allocation!$C$1:$C$175,"2026",Allocation!$D$1:$D$175,"PIGIER_BOR",Allocation!$F$1:$F$175,"BAC_RH",Allocation!$G$1:$G$175,"B3",Allocation!$H$1:$H$175,"ALT") -> 162432.18 | M85: =_xlfn.IFERROR(L85/D85,0) -> 0.68349327
B86: Tunon | C86: =_xlfn.SUMIFS(Allocation!$I$1:$I$175,Allocation!$C$1:$C$175,"2026",Allocation!$E$1:$E$175,"TUNON") -> 255 | D86: =_xlfn.SUMIFS(Allocation!$K$1:$K$175,Allocation!$C$1:$C$175,"2026",Allocation!$E$1:$E$175,"TUNON") -> 1949700 | E86: =_xlfn.SUMIFS(Allocation!$V$1:$V$175,Allocation!$C$1:$C$175,"2026",Allocation!$E$1:$E$175,"TUNON") -> 144876 | F86: =_xlfn.SUMIFS(Allocation!$W$1:$W$175,Allocation!$C$1:$C$175,"2026",Allocation!$E$1:$E$175,"TUNON") -> 409445 | G86: =_xlfn.SUMIFS(Allocation!$X$1:$X$175,Allocation!$C$1:$C$175,"2026",Allocation!$E$1:$E$175,"TUNON") -> 143974 | H86: =_xlfn.SUMIFS(Allocation!$Y$1:$Y$175,Allocation!$C$1:$C$175,"2026",Allocation!$E$1:$E$175,"TUNON") -> 0 | I86: =_xlfn.SUMIFS(Allocation!$AC$1:$AC$175,Allocation!$C$1:$C$175,"2026",Allocation!$E$1:$E$175,"TUNON") -> 0 | J86: =_xlfn.SUMIFS(Allocation!$Z$1:$Z$175,Allocation!$C$1:$C$175,"2026",Allocation!$E$1:$E$175,"TUNON") -> 0 | K86: =E86+F86+G86+H86+I86+J86 -> 698295 | L86: =_xlfn.SUMIFS(Allocation!$AA$1:$AA$175,Allocation!$C$1:$C$175,"2026",Allocation!$E$1:$E$175,"TUNON") -> 1251405 | M86: =_xlfn.IFERROR(L86/D86,0) -> 0.6418449
B87: Paris (TUNON_PAR) | C87: =_xlfn.SUMIFS(Allocation!$I$1:$I$175,Allocation!$C$1:$C$175,"2026",Allocation!$D$1:$D$175,"TUNON_PAR") -> 138 | D87: =_xlfn.SUMIFS(Allocation!$K$1:$K$175,Allocation!$C$1:$C$175,"2026",Allocation!$D$1:$D$175,"TUNON_PAR") -> 1086150 | E87: =_xlfn.SUMIFS(Allocation!$V$1:$V$175,Allocation!$C$1:$C$175,"2026",Allocation!$D$1:$D$175,"TUNON_PAR") -> 72438 | F87: =_xlfn.SUMIFS(Allocation!$W$1:$W$175,Allocation!$C$1:$C$175,"2026",Allocation!$D$1:$D$175,"TUNON_PAR") -> 242081 | G87: =_xlfn.SUMIFS(Allocation!$X$1:$X$175,Allocation!$C$1:$C$175,"2026",Allocation!$D$1:$D$175,"TUNON_PAR") -> 81589 | H87: =_xlfn.SUMIFS(Allocation!$Y$1:$Y$175,Allocation!$C$1:$C$175,"2026",Allocation!$D$1:$D$175,"TUNON_PAR") -> 0 | I87: =_xlfn.SUMIFS(Allocation!$AC$1:$AC$175,Allocation!$C$1:$C$175,"2026",Allocation!$D$1:$D$175,"TUNON_PAR") -> 0 | J87: =_xlfn.SUMIFS(Allocation!$Z$1:$Z$175,Allocation!$C$1:$C$175,"2026",Allocation!$D$1:$D$175,"TUNON_PAR") -> 0 | K87: =E87+F87+G87+H87+I87+J87 -> 396108 | L87: =_xlfn.SUMIFS(Allocation!$AA$1:$AA$175,Allocation!$C$1:$C$175,"2026",Allocation!$D$1:$D$175,"TUNON_PAR") -> 690042 | M87: =_xlfn.IFERROR(L87/D87,0) -> 0.63531004
B88: BAC_TOU B1 ALT | C88: =_xlfn.SUMIFS(Allocation!$I$1:$I$175,Allocation!$C$1:$C$175,"2026",Allocation!$D$1:$D$175,"TUNON_PAR",Allocation!$F$1:$F$175,"BAC_TOU",Allocation!$G$1:$G$175,"B1",Allocation!$H$1:$H$175,"ALT") -> 47 | D88: =_xlfn.SUMIFS(Allocation!$K$1:$K$175,Allocation!$C$1:$C$175,"2026",Allocation!$D$1:$D$175,"TUNON_PAR",Allocation!$F$1:$F$175,"BAC_TOU",Allocation!$G$1:$G$175,"B1",Allocation!$H$1:$H$175,"ALT") -> 372710 | E88: =_xlfn.SUMIFS(Allocation!$V$1:$V$175,Allocation!$C$1:$C$175,"2026",Allocation!$D$1:$D$175,"TUNON_PAR",Allocation!$F$1:$F$175,"BAC_TOU",Allocation!$G$1:$G$175,"B1",Allocation!$H$1:$H$175,"ALT") -> 24146 | F88: =_xlfn.SUMIFS(Allocation!$W$1:$W$175,Allocation!$C$1:$C$175,"2026",Allocation!$D$1:$D$175,"TUNON_PAR",Allocation!$F$1:$F$175,"BAC_TOU",Allocation!$G$1:$G$175,"B1",Allocation!$H$1:$H$175,"ALT") -> 80693.667 | G88: =_xlfn.SUMIFS(Allocation!$X$1:$X$175,Allocation!$C$1:$C$175,"2026",Allocation!$D$1:$D$175,"TUNON_PAR",Allocation!$F$1:$F$175,"BAC_TOU",Allocation!$G$1:$G$175,"B1",Allocation!$H$1:$H$175,"ALT") -> 47728.428 | H88: =_xlfn.SUMIFS(Allocation!$Y$1:$Y$175,Allocation!$C$1:$C$175,"2026",Allocation!$D$1:$D$175,"TUNON_PAR",Allocation!$F$1:$F$175,"BAC_TOU",Allocation!$G$1:$G$175,"B1",Allocation!$H$1:$H$175,"ALT") -> 0 | I88: =_xlfn.SUMIFS(Allocation!$AC$1:$AC$175,Allocation!$C$1:$C$175,"2026",Allocation!$D$1:$D$175,"TUNON_PAR",Allocation!$F$1:$F$175,"BAC_TOU",Allocation!$G$1:$G$175,"B1",Allocation!$H$1:$H$175,"ALT") -> 0 | J88: =_xlfn.SUMIFS(Allocation!$Z$1:$Z$175,Allocation!$C$1:$C$175,"2026",Allocation!$D$1:$D$175,"TUNON_PAR",Allocation!$F$1:$F$175,"BAC_TOU",Allocation!$G$1:$G$175,"B1",Allocation!$H$1:$H$175,"ALT") -> 0 | K88: =E88+F88+G88+H88+I88+J88 -> 152568.09 | L88: =_xlfn.SUMIFS(Allocation!$AA$1:$AA$175,Allocation!$C$1:$C$175,"2026",Allocation!$D$1:$D$175,"TUNON_PAR",Allocation!$F$1:$F$175,"BAC_TOU",Allocation!$G$1:$G$175,"B1",Allocation!$H$1:$H$175,"ALT") -> 220141.91 | M88: =_xlfn.IFERROR(L88/D88,0) -> 0.590652
B89: BAC_TOU B2 ALT | C89: =_xlfn.SUMIFS(Allocation!$I$1:$I$175,Allocation!$C$1:$C$175,"2026",Allocation!$D$1:$D$175,"TUNON_PAR",Allocation!$F$1:$F$175,"BAC_TOU",Allocation!$G$1:$G$175,"B2",Allocation!$H$1:$H$175,"ALT") -> 46 | D89: =_xlfn.SUMIFS(Allocation!$K$1:$K$175,Allocation!$C$1:$C$175,"2026",Allocation!$D$1:$D$175,"TUNON_PAR",Allocation!$F$1:$F$175,"BAC_TOU",Allocation!$G$1:$G$175,"B2",Allocation!$H$1:$H$175,"ALT") -> 360640 | E89: =_xlfn.SUMIFS(Allocation!$V$1:$V$175,Allocation!$C$1:$C$175,"2026",Allocation!$D$1:$D$175,"TUNON_PAR",Allocation!$F$1:$F$175,"BAC_TOU",Allocation!$G$1:$G$175,"B2",Allocation!$H$1:$H$175,"ALT") -> 24146 | F89: =_xlfn.SUMIFS(Allocation!$W$1:$W$175,Allocation!$C$1:$C$175,"2026",Allocation!$D$1:$D$175,"TUNON_PAR",Allocation!$F$1:$F$175,"BAC_TOU",Allocation!$G$1:$G$175,"B2",Allocation!$H$1:$H$175,"ALT") -> 80693.667 | G89: =_xlfn.SUMIFS(Allocation!$X$1:$X$175,Allocation!$C$1:$C$175,"2026",Allocation!$D$1:$D$175,"TUNON_PAR",Allocation!$F$1:$F$175,"BAC_TOU",Allocation!$G$1:$G$175,"B2",Allocation!$H$1:$H$175,"ALT") -> 17116.333 | H89: =_xlfn.SUMIFS(Allocation!$Y$1:$Y$175,Allocation!$C$1:$C$175,"2026",Allocation!$D$1:$D$175,"TUNON_PAR",Allocation!$F$1:$F$175,"BAC_TOU",Allocation!$G$1:$G$175,"B2",Allocation!$H$1:$H$175,"ALT") -> 0 | I89: =_xlfn.SUMIFS(Allocation!$AC$1:$AC$175,Allocation!$C$1:$C$175,"2026",Allocation!$D$1:$D$175,"TUNON_PAR",Allocation!$F$1:$F$175,"BAC_TOU",Allocation!$G$1:$G$175,"B2",Allocation!$H$1:$H$175,"ALT") -> 0 | J89: =_xlfn.SUMIFS(Allocation!$Z$1:$Z$175,Allocation!$C$1:$C$175,"2026",Allocation!$D$1:$D$175,"TUNON_PAR",Allocation!$F$1:$F$175,"BAC_TOU",Allocation!$G$1:$G$175,"B2",Allocation!$H$1:$H$175,"ALT") -> 0 | K89: =E89+F89+G89+H89+I89+J89 -> 121956 | L89: =_xlfn.SUMIFS(Allocation!$AA$1:$AA$175,Allocation!$C$1:$C$175,"2026",Allocation!$D$1:$D$175,"TUNON_PAR",Allocation!$F$1:$F$175,"BAC_TOU",Allocation!$G$1:$G$175,"B2",Allocation!$H$1:$H$175,"ALT") -> 238684 | M89: =_xlfn.IFERROR(L89/D89,0) -> 0.66183452
B90: BAC_TOU B3 ALT | C90: =_xlfn.SUMIFS(Allocation!$I$1:$I$175,Allocation!$C$1:$C$175,"2026",Allocation!$D$1:$D$175,"TUNON_PAR",Allocation!$F$1:$F$175,"BAC_TOU",Allocation!$G$1:$G$175,"B3",Allocation!$H$1:$H$175,"ALT") -> 45 | D90: =_xlfn.SUMIFS(Allocation!$K$1:$K$175,Allocation!$C$1:$C$175,"2026",Allocation!$D$1:$D$175,"TUNON_PAR",Allocation!$F$1:$F$175,"BAC_TOU",Allocation!$G$1:$G$175,"B3",Allocation!$H$1:$H$175,"ALT") -> 352800 | E90: =_xlfn.SUMIFS(Allocation!$V$1:$V$175,Allocation!$C$1:$C$175,"2026",Allocation!$D$1:$D$175,"TUNON_PAR",Allocation!$F$1:$F$175,"BAC_TOU",Allocation!$G$1:$G$175,"B3",Allocation!$H$1:$H$175,"ALT") -> 24146 | F90: =_xlfn.SUMIFS(Allocation!$W$1:$W$175,Allocation!$C$1:$C$175,"2026",Allocation!$D$1:$D$175,"TUNON_PAR",Allocation!$F$1:$F$175,"BAC_TOU",Allocation!$G$1:$G$175,"B3",Allocation!$H$1:$H$175,"ALT") -> 80693.667 | G90: =_xlfn.SUMIFS(Allocation!$X$1:$X$175,Allocation!$C$1:$C$175,"2026",Allocation!$D$1:$D$175,"TUNON_PAR",Allocation!$F$1:$F$175,"BAC_TOU",Allocation!$G$1:$G$175,"B3",Allocation!$H$1:$H$175,"ALT") -> 16744.239 | H90: =_xlfn.SUMIFS(Allocation!$Y$1:$Y$175,Allocation!$C$1:$C$175,"2026",Allocation!$D$1:$D$175,"TUNON_PAR",Allocation!$F$1:$F$175,"BAC_TOU",Allocation!$G$1:$G$175,"B3",Allocation!$H$1:$H$175,"ALT") -> 0 | I90: =_xlfn.SUMIFS(Allocation!$AC$1:$AC$175,Allocation!$C$1:$C$175,"2026",Allocation!$D$1:$D$175,"TUNON_PAR",Allocation!$F$1:$F$175,"BAC_TOU",Allocation!$G$1:$G$175,"B3",Allocation!$H$1:$H$175,"ALT") -> 0 | J90: =_xlfn.SUMIFS(Allocation!$Z$1:$Z$175,Allocation!$C$1:$C$175,"2026",Allocation!$D$1:$D$175,"TUNON_PAR",Allocation!$F$1:$F$175,"BAC_TOU",Allocation!$G$1:$G$175,"B3",Allocation!$H$1:$H$175,"ALT") -> 0 | K90: =E90+F90+G90+H90+I90+J90 -> 121583.91 | L90: =_xlfn.SUMIFS(Allocation!$AA$1:$AA$175,Allocation!$C$1:$C$175,"2026",Allocation!$D$1:$D$175,"TUNON_PAR",Allocation!$F$1:$F$175,"BAC_TOU",Allocation!$G$1:$G$175,"B3",Allocation!$H$1:$H$175,"ALT") -> 231216.09 | M90: =_xlfn.IFERROR(L90/D90,0) -> 0.65537442
B91: Lyon (TUNON_LYO) | C91: =_xlfn.SUMIFS(Allocation!$I$1:$I$175,Allocation!$C$1:$C$175,"2026",Allocation!$D$1:$D$175,"TUNON_LYO") -> 117 | D91: =_xlfn.SUMIFS(Allocation!$K$1:$K$175,Allocation!$C$1:$C$175,"2026",Allocation!$D$1:$D$175,"TUNON_LYO") -> 863550 | E91: =_xlfn.SUMIFS(Allocation!$V$1:$V$175,Allocation!$C$1:$C$175,"2026",Allocation!$D$1:$D$175,"TUNON_LYO") -> 72438 | F91: =_xlfn.SUMIFS(Allocation!$W$1:$W$175,Allocation!$C$1:$C$175,"2026",Allocation!$D$1:$D$175,"TUNON_LYO") -> 167364 | G91: =_xlfn.SUMIFS(Allocation!$X$1:$X$175,Allocation!$C$1:$C$175,"2026",Allocation!$D$1:$D$175,"TUNON_LYO") -> 62385 | H91: =_xlfn.SUMIFS(Allocation!$Y$1:$Y$175,Allocation!$C$1:$C$175,"2026",Allocation!$D$1:$D$175,"TUNON_LYO") -> 0 | I91: =_xlfn.SUMIFS(Allocation!$AC$1:$AC$175,Allocation!$C$1:$C$175,"2026",Allocation!$D$1:$D$175,"TUNON_LYO") -> 0 | J91: =_xlfn.SUMIFS(Allocation!$Z$1:$Z$175,Allocation!$C$1:$C$175,"2026",Allocation!$D$1:$D$175,"TUNON_LYO") -> 0 | K91: =E91+F91+G91+H91+I91+J91 -> 302187 | L91: =_xlfn.SUMIFS(Allocation!$AA$1:$AA$175,Allocation!$C$1:$C$175,"2026",Allocation!$D$1:$D$175,"TUNON_LYO") -> 561363 | M91: =_xlfn.IFERROR(L91/D91,0) -> 0.65006427
B92: BAC_TOU B1 ALT | C92: =_xlfn.SUMIFS(Allocation!$I$1:$I$175,Allocation!$C$1:$C$175,"2026",Allocation!$D$1:$D$175,"TUNON_LYO",Allocation!$F$1:$F$175,"BAC_TOU",Allocation!$G$1:$G$175,"B1",Allocation!$H$1:$H$175,"ALT") -> 40 | D92: =_xlfn.SUMIFS(Allocation!$K$1:$K$175,Allocation!$C$1:$C$175,"2026",Allocation!$D$1:$D$175,"TUNON_LYO",Allocation!$F$1:$F$175,"BAC_TOU",Allocation!$G$1:$G$175,"B1",Allocation!$H$1:$H$175,"ALT") -> 297600 | E92: =_xlfn.SUMIFS(Allocation!$V$1:$V$175,Allocation!$C$1:$C$175,"2026",Allocation!$D$1:$D$175,"TUNON_LYO",Allocation!$F$1:$F$175,"BAC_TOU",Allocation!$G$1:$G$175,"B1",Allocation!$H$1:$H$175,"ALT") -> 24146 | F92: =_xlfn.SUMIFS(Allocation!$W$1:$W$175,Allocation!$C$1:$C$175,"2026",Allocation!$D$1:$D$175,"TUNON_LYO",Allocation!$F$1:$F$175,"BAC_TOU",Allocation!$G$1:$G$175,"B1",Allocation!$H$1:$H$175,"ALT") -> 55788 | G92: =_xlfn.SUMIFS(Allocation!$X$1:$X$175,Allocation!$C$1:$C$175,"2026",Allocation!$D$1:$D$175,"TUNON_LYO",Allocation!$F$1:$F$175,"BAC_TOU",Allocation!$G$1:$G$175,"B1",Allocation!$H$1:$H$175,"ALT") -> 33733.761 | H92: =_xlfn.SUMIFS(Allocation!$Y$1:$Y$175,Allocation!$C$1:$C$175,"2026",Allocation!$D$1:$D$175,"TUNON_LYO",Allocation!$F$1:$F$175,"BAC_TOU",Allocation!$G$1:$G$175,"B1",Allocation!$H$1:$H$175,"ALT") -> 0 | I92: =_xlfn.SUMIFS(Allocation!$AC$1:$AC$175,Allocation!$C$1:$C$175,"2026",Allocation!$D$1:$D$175,"TUNON_LYO",Allocation!$F$1:$F$175,"BAC_TOU",Allocation!$G$1:$G$175,"B1",Allocation!$H$1:$H$175,"ALT") -> 0 | J92: =_xlfn.SUMIFS(Allocation!$Z$1:$Z$175,Allocation!$C$1:$C$175,"2026",Allocation!$D$1:$D$175,"TUNON_LYO",Allocation!$F$1:$F$175,"BAC_TOU",Allocation!$G$1:$G$175,"B1",Allocation!$H$1:$H$175,"ALT") -> 0 | K92: =E92+F92+G92+H92+I92+J92 -> 113667.76 | L92: =_xlfn.SUMIFS(Allocation!$AA$1:$AA$175,Allocation!$C$1:$C$175,"2026",Allocation!$D$1:$D$175,"TUNON_LYO",Allocation!$F$1:$F$175,"BAC_TOU",Allocation!$G$1:$G$175,"B1",Allocation!$H$1:$H$175,"ALT") -> 183932.24 | M92: =_xlfn.IFERROR(L92/D92,0) -> 0.61805188
B93: BAC_TOU B2 ALT | C93: =_xlfn.SUMIFS(Allocation!$I$1:$I$175,Allocation!$C$1:$C$175,"2026",Allocation!$D$1:$D$175,"TUNON_LYO",Allocation!$F$1:$F$175,"BAC_TOU",Allocation!$G$1:$G$175,"B2",Allocation!$H$1:$H$175,"ALT") -> 39 | D93: =_xlfn.SUMIFS(Allocation!$K$1:$K$175,Allocation!$C$1:$C$175,"2026",Allocation!$D$1:$D$175,"TUNON_LYO",Allocation!$F$1:$F$175,"BAC_TOU",Allocation!$G$1:$G$175,"B2",Allocation!$H$1:$H$175,"ALT") -> 286650 | E93: =_xlfn.SUMIFS(Allocation!$V$1:$V$175,Allocation!$C$1:$C$175,"2026",Allocation!$D$1:$D$175,"TUNON_LYO",Allocation!$F$1:$F$175,"BAC_TOU",Allocation!$G$1:$G$175,"B2",Allocation!$H$1:$H$175,"ALT") -> 24146 | F93: =_xlfn.SUMIFS(Allocation!$W$1:$W$175,Allocation!$C$1:$C$175,"2026",Allocation!$D$1:$D$175,"TUNON_LYO",Allocation!$F$1:$F$175,"BAC_TOU",Allocation!$G$1:$G$175,"B2",Allocation!$H$1:$H$175,"ALT") -> 55788 | G93: =_xlfn.SUMIFS(Allocation!$X$1:$X$175,Allocation!$C$1:$C$175,"2026",Allocation!$D$1:$D$175,"TUNON_LYO",Allocation!$F$1:$F$175,"BAC_TOU",Allocation!$G$1:$G$175,"B2",Allocation!$H$1:$H$175,"ALT") -> 14511.667 | H93: =_xlfn.SUMIFS(Allocation!$Y$1:$Y$175,Allocation!$C$1:$C$175,"2026",Allocation!$D$1:$D$175,"TUNON_LYO",Allocation!$F$1:$F$175,"BAC_TOU",Allocation!$G$1:$G$175,"B2",Allocation!$H$1:$H$175,"ALT") -> 0 | I93: =_xlfn.SUMIFS(Allocation!$AC$1:$AC$175,Allocation!$C$1:$C$175,"2026",Allocation!$D$1:$D$175,"TUNON_LYO",Allocation!$F$1:$F$175,"BAC_TOU",Allocation!$G$1:$G$175,"B2",Allocation!$H$1:$H$175,"ALT") -> 0 | J93: =_xlfn.SUMIFS(Allocation!$Z$1:$Z$175,Allocation!$C$1:$C$175,"2026",Allocation!$D$1:$D$175,"TUNON_LYO",Allocation!$F$1:$F$175,"BAC_TOU",Allocation!$G$1:$G$175,"B2",Allocation!$H$1:$H$175,"ALT") -> 0 | K93: =E93+F93+G93+H93+I93+J93 -> 94445.667 | L93: =_xlfn.SUMIFS(Allocation!$AA$1:$AA$175,Allocation!$C$1:$C$175,"2026",Allocation!$D$1:$D$175,"TUNON_LYO",Allocation!$F$1:$F$175,"BAC_TOU",Allocation!$G$1:$G$175,"B2",Allocation!$H$1:$H$175,"ALT") -> 192204.33 | M93: =_xlfn.IFERROR(L93/D93,0) -> 0.67051922
B94: BAC_TOU B3 ALT | C94: =_xlfn.SUMIFS(Allocation!$I$1:$I$175,Allocation!$C$1:$C$175,"2026",Allocation!$D$1:$D$175,"TUNON_LYO",Allocation!$F$1:$F$175,"BAC_TOU",Allocation!$G$1:$G$175,"B3",Allocation!$H$1:$H$175,"ALT") -> 38 | D94: =_xlfn.SUMIFS(Allocation!$K$1:$K$175,Allocation!$C$1:$C$175,"2026",Allocation!$D$1:$D$175,"TUNON_LYO",Allocation!$F$1:$F$175,"BAC_TOU",Allocation!$G$1:$G$175,"B3",Allocation!$H$1:$H$175,"ALT") -> 279300 | E94: =_xlfn.SUMIFS(Allocation!$V$1:$V$175,Allocation!$C$1:$C$175,"2026",Allocation!$D$1:$D$175,"TUNON_LYO",Allocation!$F$1:$F$175,"BAC_TOU",Allocation!$G$1:$G$175,"B3",Allocation!$H$1:$H$175,"ALT") -> 24146 | F94: =_xlfn.SUMIFS(Allocation!$W$1:$W$175,Allocation!$C$1:$C$175,"2026",Allocation!$D$1:$D$175,"TUNON_LYO",Allocation!$F$1:$F$175,"BAC_TOU",Allocation!$G$1:$G$175,"B3",Allocation!$H$1:$H$175,"ALT") -> 55788 | G94: =_xlfn.SUMIFS(Allocation!$X$1:$X$175,Allocation!$C$1:$C$175,"2026",Allocation!$D$1:$D$175,"TUNON_LYO",Allocation!$F$1:$F$175,"BAC_TOU",Allocation!$G$1:$G$175,"B3",Allocation!$H$1:$H$175,"ALT") -> 14139.573 | H94: =_xlfn.SUMIFS(Allocation!$Y$1:$Y$175,Allocation!$C$1:$C$175,"2026",Allocation!$D$1:$D$175,"TUNON_LYO",Allocation!$F$1:$F$175,"BAC_TOU",Allocation!$G$1:$G$175,"B3",Allocation!$H$1:$H$175,"ALT") -> 0 | I94: =_xlfn.SUMIFS(Allocation!$AC$1:$AC$175,Allocation!$C$1:$C$175,"2026",Allocation!$D$1:$D$175,"TUNON_LYO",Allocation!$F$1:$F$175,"BAC_TOU",Allocation!$G$1:$G$175,"B3",Allocation!$H$1:$H$175,"ALT") -> 0 | J94: =_xlfn.SUMIFS(Allocation!$Z$1:$Z$175,Allocation!$C$1:$C$175,"2026",Allocation!$D$1:$D$175,"TUNON_LYO",Allocation!$F$1:$F$175,"BAC_TOU",Allocation!$G$1:$G$175,"B3",Allocation!$H$1:$H$175,"ALT") -> 0 | K94: =E94+F94+G94+H94+I94+J94 -> 94073.573 | L94: =_xlfn.SUMIFS(Allocation!$AA$1:$AA$175,Allocation!$C$1:$C$175,"2026",Allocation!$D$1:$D$175,"TUNON_LYO",Allocation!$F$1:$F$175,"BAC_TOU",Allocation!$G$1:$G$175,"B3",Allocation!$H$1:$H$175,"ALT") -> 185226.43 | M94: =_xlfn.IFERROR(L94/D94,0) -> 0.66318091
B95: GROUPE | C95: =_xlfn.SUMIFS(Allocation!$I$1:$I$175,Allocation!$C$1:$C$175,"2026") -> 3036 | D95: =_xlfn.SUMIFS(Allocation!$K$1:$K$175,Allocation!$C$1:$C$175,"2026") -> 22544725 | E95: =_xlfn.SUMIFS(Allocation!$V$1:$V$175,Allocation!$C$1:$C$175,"2026") -> 1581554 | F95: =_xlfn.SUMIFS(Allocation!$W$1:$W$175,Allocation!$C$1:$C$175,"2026") -> 3840917 | G95: =_xlfn.SUMIFS(Allocation!$X$1:$X$175,Allocation!$C$1:$C$175,"2026") -> 1563856 | H95: =_xlfn.SUMIFS(Allocation!$Y$1:$Y$175,Allocation!$C$1:$C$175,"2026") -> 1452771 | I95: =_xlfn.SUMIFS(Allocation!$AC$1:$AC$175,Allocation!$C$1:$C$175,"2026") -> 676344 | J95: =_xlfn.SUMIFS(Allocation!$Z$1:$Z$175,Allocation!$C$1:$C$175,"2026") -> 2891983 | K95: =E95+F95+G95+H95+I95+J95 -> 12007425 | L95: =_xlfn.SUMIFS(Allocation!$AA$1:$AA$175,Allocation!$C$1:$C$175,"2026") -> 10537300 | M95: =_xlfn.IFERROR(L95/D95,0) -> 0.46739537

Sheet Socle
A1: SCENARIO | B1: PERIODE | C1: ENTITY | D1: PROGRAMME | E1: AN_ETUDE | F1: MODALITE | G1: EXERCICE | H1: VOL_LEAD | I1: VOL_CAND | J1: VOL_ADMIS | K1: VOL_NEW | L1: VOL_REINS | M1: VOL_EFF | N1: VOL_EFF_INF | O1: VOL_CLASS | P1: REV_STUD | Q1: REV_FRAIS_INS | R1: VOL_LEAD_ORG | S1: VOL_LEAD_PAY | T1: DEPENSE_ACQ | U1: DEPENSE_MARQUE | V1: TX_PASSAGE | W1: TX_LEAD_CAND | X1: TX_CAND_ADMIS | Y1: TX_YIELD_ADMIS_INSC | Z1: VOL_LEAD_TOTAL | AA1: PART_ORG | AB1: CPL | AC1: CA
A2: 2027BUD_V1 | B2: 12 | C2: MBWAY_PAR | D2: BAC_MGT | E2: B1 | F2: INIT | G2: 2026 | H2: 646 | I2: 181 | J2: 130 | K2: 78 | L2: 0 | M2: 78 | N2: 0 | O2: 3 | P2: 8400 | Q2: 90 | R2: 232 | S2: 414 | T2: 22326 | U2: 21185 | V2: 0 | W2: 0.28018576 | X2: 0.71823204 | Y2: 0.6 | Z2: 646 | AA2: 0.35913313 | AB2: 53.927536 | AC2: 662220
A3: 2027BUD_V1 | B3: 12 | C3: MBWAY_PAR | D3: BAC_MGT | E3: B2 | F3: ALT | G3: 2026 | H3: 0 | I3: 0 | J3: 0 | K3: 0 | L3: 76 | M3: 76 | N3: 78 | O3: 3 | P3: 7840 | Q3: 90 | R3: 0 | S3: 0 | T3: 0 | U3: 0 | V3: 0.97435897 | W3: 0 | X3: 0 | Y3: 0 | Z3: 0 | AA3: 0 | AB3: 0 | AC3: 595840
A4: 2027BUD_V1 | B4: 12 | C4: MBWAY_PAR | D4: BAC_MGT | E4: B3 | F4: ALT | G4: 2026 | H4: 0 | I4: 0 | J4: 0 | K4: 0 | L4: 74 | M4: 74 | N4: 76 | O4: 3 | P4: 7840 | Q4: 90 | R4: 0 | S4: 0 | T4: 0 | U4: 0 | V4: 0.97368421 | W4: 0 | X4: 0 | Y4: 0 | Z4: 0 | AA4: 0 | AB4: 0 | AC4: 580160
A5: 2027BUD_V1 | B5: 12 | C5: MBWAY_PAR | D5: MAS_MGT | E5: M1 | F5: ALT | G5: 2026 | H5: 1330 | I5: 266 | J5: 186 | K5: 78 | L5: 0 | M5: 78 | N5: 0 | O5: 3 | P5: 8400 | Q5: 90 | R5: 479 | S5: 851 | T5: 45965 | U5: 43615 | V5: 0 | W5: 0.2 | X5: 0.69924812 | Y5: 0.41935484 | Z5: 1330 | AA5: 0.36015038 | AB5: 54.012926 | AC5: 662220
A6: 2027BUD_V1 | B6: 12 | C6: MBWAY_PAR | D6: MAS_MGT | E6: M2 | F6: ALT | G6: 2026 | H6: 0 | I6: 0 | J6: 0 | K6: 0 | L6: 76 | M6: 76 | N6: 78 | O6: 3 | P6: 8400 | Q6: 90 | R6: 0 | S6: 0 | T6: 0 | U6: 0 | V6: 0.97435897 | W6: 0 | X6: 0 | Y6: 0 | Z6: 0 | AA6: 0 | AB6: 0 | AC6: 638400
A7: 2027BUD_V1 | B7: 12 | C7: MBWAY_LYO | D7: BAC_MGT | E7: B1 | F7: INIT | G7: 2026 | H7: 546 | I7: 153 | J7: 110 | K7: 66 | L7: 0 | M7: 66 | N7: 0 | O7: 3 | P7: 7875 | Q7: 90 | R7: 235 | S7: 311 | T7: 13694 | U7: 21386 | V7: 0 | W7: 0.28021978 | X7: 0.71895425 | Y7: 0.6 | Z7: 546 | AA7: 0.43040293 | AB7: 44.032154 | AC7: 525690
A8: 2027BUD_V1 | B8: 12 | C8: MBWAY_LYO | D8: BAC_MGT | E8: B2 | F8: ALT | G8: 2026 | H8: 0 | I8: 0 | J8: 0 | K8: 0 | L8: 64 | M8: 64 | N8: 66 | O8: 2 | P8: 7350 | Q8: 90 | R8: 0 | S8: 0 | T8: 0 | U8: 0 | V8: 0.96969697 | W8: 0 | X8: 0 | Y8: 0 | Z8: 0 | AA8: 0 | AB8: 0 | AC8: 470400
A9: 2027BUD_V1 | B9: 12 | C9: MBWAY_LYO | D9: BAC_MGT | E9: B3 | F9: ALT | G9: 2026 | H9: 0 | I9: 0 | J9: 0 | K9: 0 | L9: 63 | M9: 63 | N9: 64 | O9: 2 | P9: 7350 | Q9: 90 | R9: 0 | S9: 0 | T9: 0 | U9: 0 | V9: 0.984375 | W9: 0 | X9: 0 | Y9: 0 | Z9: 0 | AA9: 0 | AB9: 0 | AC9: 463050
A10: 2027BUD_V1 | B10: 12 | C10: MBWAY_LYO | D10: MAS_MGT | E10: M1 | F10: ALT | G10: 2026 | H10: 1120 | I10: 224 | J10: 157 | K10: 66 | L10: 0 | M10: 66 | N10: 0 | O10: 3 | P10: 7875 | Q10: 90 | R10: 481 | S10: 639 | T10: 28089 | U10: 43869 | V10: 0 | W10: 0.2 | X10: 0.70089286 | Y10: 0.42038217 | Z10: 1120 | AA10: 0.42946429 | AB10: 43.957746 | AC10: 525690
A11: 2027BUD_V1 | B11: 12 | C11: MBWAY_LYO | D11: MAS_MGT | E11: M2 | F11: ALT | G11: 2026 | H11: 0 | I11: 0 | J11: 0 | K11: 0 | L11: 65 | M11: 65 | N11: 66 | O11: 3 | P11: 7875 | Q11: 90 | R11: 0 | S11: 0 | T11: 0 | U11: 0 | V11: 0.98484848 | W11: 0 | X11: 0 | Y11: 0 | Z11: 0 | AA11: 0 | AB11: 0 | AC11: 511875
A12: 2027BUD_V1 | B12: 12 | C12: MBWAY_NAN | D12: BAC_MGT | E12: B1 | F12: INIT | G12: 2026 | H12: 496 | I12: 139 | J12: 100 | K12: 60 | L12: 0 | M12: 60 | N12: 0 | O12: 2 | P12: 7500 | Q12: 90 | R12: 238 | S12: 258 | T12: 10317 | U12: 21708 | V12: 0 | W12: 0.28024193 | X12: 0.71942446 | Y12: 0.6 | Z12: 496 | AA12: 0.47983871 | AB12: 39.988372 | AC12: 455400
A13: 2027BUD_V1 | B13: 12 | C13: MBWAY_NAN | D13: BAC_MGT | E13: B2 | F13: ALT | G13: 2026 | H13: 0 | I13: 0 | J13: 0 | K13: 0 | L13: 58 | M13: 58 | N13: 60 | O13: 2 | P13: 7000 | Q13: 90 | R13: 0 | S13: 0 | T13: 0 | U13: 0 | V13: 0.96666667 | W13: 0 | X13: 0 | Y13: 0 | Z13: 0 | AA13: 0 | AB13: 0 | AC13: 406000
... A448: 2027BUD_V1 | B448: 12 | C448: TUNON_LYO | D448: BAC_TOU | E448: B3 | F448: ALT | G448: 2024 | H448: 0 | I448: 0 | J448: 0 | K448: 0 | L448: 34 | M448: 34 | N448: 35 | O448: 2 | P448: 7350 | Q448: 90 | R448: 0 | S448: 0 | T448: 0 | U448: 0 | V448: 0.97142857 | W448: 0 | X448: 0 | Y448: 0 | Z448: 0 | AA448: 0 | AB448: 0 | AC448: 249900

Sheet Campagne
A1: SCENARIO | B1: PERIODE | C1: ENTITY | D1: ORG_REF | E1: PAID_REF | F1: LEAD_REF | G1: SPEND_ACQ_REF | H1: SPEND_BRAND_REF | I1: PART_ORG | J1: CPL | K1: REND_ACQ | L1: CONVERSION | M1: REND_BRAND | N1: CAC_MARGINAL
A2: 2027BUD_V1 | B2: 12 | C2: MBWAY_PAR | D2: 711 | E2: 1265 | F2: 1976 | G2: 68291 | H2: 64800 | I2: 0.35981781 | J2: 53.98498 | K2: 0.46359591 | L2: 0.078947368 | M2: 0.30805415 | N2: 1475.0125
A3: 2027BUD_V1 | B3: 12 | C3: MBWAY_LYO | D3: 716 | E3: 950 | F3: 1666 | G3: 41783 | H3: 65255 | I3: 0.42977191 | J3: 43.982105 | K3: 0.50391247 | L3: 0.079231693 | M3: 0.32659377 | N3: 1101.595
A4: 2027BUD_V1 | B4: 12 | C4: MBWAY_NAN | D4: 728 | E4: 788 | F4: 1516 | G4: 31533 | H4: 66349 | I4: 0.48021108 | J4: 40.016497 | K4: 0.52465547 | L4: 0.079155673 | M4: 0.34345055 | N4: 963.56901
A5: 2027BUD_V1 | B5: 12 | C5: MBWAY_BOR | D5: 630 | E5: 656 | F5: 1286 | G5: 24923 | H5: 57418 | I5: 0.48989113 | J5: 37.992378 | K5: 0.5384553 | L5: 0.079315708 | M5: 0.34824924 | N5: 889.58534
A6: 2027BUD_V1 | B6: 12 | C6: ISCOM_PAR | D6: 690 | E6: 1126 | F6: 1816 | G6: 60800 | H6: 62886 | I6: 0.37995595 | J6: 53.996448 | K6: 0.44208648 | L6: 0.079295154 | M6: 0.31719358 | N6: 1540.3212
A7: 2027BUD_V1 | B7: 12 | C7: ISCOM_LIL | D7: 630 | E7: 630 | F7: 1260 | G7: 25220 | H7: 57418 | I7: 0.5 | J7: 40.031746 | K7: 0.51584848 | L7: 0.079302141 | M7: 0.34838067 | N7: 978.58254
A8: 2027BUD_V1 | B8: 12 | C8: ISCOM_TLS | D8: 605 | E8: 581 | F8: 1186 | G8: 22083 | H8: 55139 | I8: 0.51011804 | J8: 38.008606 | K8: 0.52180324 | L8: 0.07925801 | M8: 0.35585221 | N8: 919.03491
A9: 2027BUD_V1 | B9: 12 | C9: IPAC_NAN | D9: 306 | E9: 544 | F9: 850 | G9: 21760 | H9: 27889 | I9: 0.36 | J9: 40 | K9: 0.55908043 | L9: 0.058823529 | M9: 0.30491226 | N9: 1216.283
A10: 2027BUD_V1 | B10: 12 | C10: IPAC_REN | D10: 265 | E10: 415 | F10: 680 | G10: 14933 | H10: 24152 | I10: 0.38970588 | J10: 35.983133 | K10: 0.58787584 | L10: 0.058823529 | M10: 0.31735418 | N10: 1040.5484
A11: 2027BUD_V1 | B11: 12 | C11: IPAC_MTP | D11: 258 | E11: 422 | F11: 680 | G11: 15178 | H11: 23514 | I11: 0.37941177 | J11: 35.966825 | K11: 0.59134467 | L11: 0.058823529 | M11: 0.31527526 | N11: 1033.9757
A12: 2027BUD_V1 | B12: 12 | C12: PIGIER_LYO | D12: 738 | E12: 832 | F12: 1570 | G12: 36612 | H12: 67261 | I12: 0.47006369 | J12: 44.004808 | K12: 0.44045018 | L12: 0.058598726 | M12: 0.34304577 | N12: 1704.9638
A13: 2027BUD_V1 | B13: 12 | C13: PIGIER_BOR | D13: 652 | E13: 578 | F13: 1230 | G13: 21968 | H13: 59423 | I13: 0.5300813 | J13: 38.00692 | K13: 0.47459706 | L13: 0.058536585 | M13: 0.35757395 | N13: 1368.0761
... A15: 2027BUD_V1 | B15: 12 | C15: TUNON_LYO | D15: 252 | E15: 428 | F15: 680 | G15: 18850 | H15: 22967 | I15: 0.37058823 | J15: 44.042056 | K15: 0.46084373 | L15: 0.058823529 | M15: 0.31798649 | N15: 1624.6613

Sheet Moteur
A1: SCENARIO | B1: VERSION | C1: PERIODE | D1: ENTITY | E1: MARQUE | F1: PROGRAMME | G1: AN_ETUDE | H1: MODALITE | I1: EXERCICE | J1: NOUVEAUX | K1: EFFECTIF | L1: PRIX | M1: CA | O1: NOUVEAUX (live) | P1: EFFECTIF (live) | Q1: PRIX (live) | R1: 🟢 CA (live) | S1: Δ CA vs Tagetik
A2: 2027BUD_V1 | B2: V01 | C2: 12 | D2: MBWAY_PAR | E2: MBWAY | F2: BAC_MGT | G2: B1 | H2: INIT | I2: 2027 | J2: 84.920594 | K2: 84.920594 | L2: 8601.6 | M2: 738095.83 | O2: =IF(D2="","",_CALC_MOTEUR!AE2) -> 8.7179354e+09 | P2: =IF(D2="","",_CALC_MOTEUR!AF2) -> 8.7179354e+09 | Q2: =IF(D2="","",_CALC_MOTEUR!AG2) -> 8400008400 | R2: =IF(D2="","",_CALC_MOTEUR!AH2) -> 7.3230732e+19 | S2: =IF(D2="","",R2-M2) -> 7.3230732e+19
A3: 2027BUD_V1 | B3: V02 | C3: 12 | D3: MBWAY_PAR | E3: MBWAY | F3: BAC_MGT | G3: B1 | H3: INIT | I3: 2027 | J3: 95.673985 | K3: 95.673985 | L3: 8752.8 | M3: 846025.91 | O3: =IF(D3="","",_CALC_MOTEUR!AE3) -> #VALUE! | P3: =IF(D3="","",_CALC_MOTEUR!AF3) -> #VALUE! | Q3: =IF(D3="","",_CALC_MOTEUR!AG3) -> #VALUE! | R3: =IF(D3="","",_CALC_MOTEUR!AH3) -> #VALUE! | S3: =IF(D3="","",R3-M3) -> #VALUE!
A4: 2027BUD_V1 | B4: V03 | C4: 12 | D4: MBWAY_PAR | E4: MBWAY | F4: BAC_MGT | G4: B1 | H4: INIT | I4: 2027 | J4: 72.432661 | K4: 72.432661 | L4: 8601.6 | M4: 629555.71 | O4: =IF(D4="","",_CALC_MOTEUR!AE4) -> #VALUE! | P4: =IF(D4="","",_CALC_MOTEUR!AF4) -> #VALUE! | Q4: =IF(D4="","",_CALC_MOTEUR!AG4) -> #VALUE! | R4: =IF(D4="","",_CALC_MOTEUR!AH4) -> #VALUE! | S4: =IF(D4="","",R4-M4) -> #VALUE!
A5: 2027BUD_V1 | B5: V01 | C5: 12 | D5: MBWAY_PAR | E5: MBWAY | F5: BAC_MGT | G5: B2 | H5: ALT | I5: 2027 | J5: 0 | K5: 76.39 | L5: 8028.16 | M5: 613271.14 | O5: =IF(D5="","",_CALC_MOTEUR!AE5) -> 0 | P5: =IF(D5="","",_CALC_MOTEUR!AF5) -> #VALUE! | Q5: =IF(D5="","",_CALC_MOTEUR!AG5) -> #VALUE! | R5: =IF(D5="","",_CALC_MOTEUR!AH5) -> #VALUE! | S5: =IF(D5="","",R5-M5) -> #VALUE!
A6: 2027BUD_V1 | B6: V02 | C6: 12 | D6: MBWAY_PAR | E6: MBWAY | F6: BAC_MGT | G6: B2 | H6: ALT | I6: 2027 | J6: 0 | K6: 77.17 | L6: 8169.28 | M6: 630423.34 | O6: =IF(D6="","",_CALC_MOTEUR!AE6) -> 0 | P6: =IF(D6="","",_CALC_MOTEUR!AF6) -> #VALUE! | Q6: =IF(D6="","",_CALC_MOTEUR!AG6) -> #VALUE! | R6: =IF(D6="","",_CALC_MOTEUR!AH6) -> #VALUE! | S6: =IF(D6="","",R6-M6) -> #VALUE!
A7: 2027BUD_V1 | B7: V03 | C7: 12 | D7: MBWAY_PAR | E7: MBWAY | F7: BAC_MGT | G7: B2 | H7: ALT | I7: 2027 | J7: 0 | K7: 75.22 | L7: 8028.16 | M7: 603878.2 | O7: =IF(D7="","",_CALC_MOTEUR!AE7) -> 0 | P7: =IF(D7="","",_CALC_MOTEUR!AF7) -> #VALUE! | Q7: =IF(D7="","",_CALC_MOTEUR!AG7) -> #VALUE! | R7: =IF(D7="","",_CALC_MOTEUR!AH7) -> #VALUE! | S7: =IF(D7="","",R7-M7) -> #VALUE!
A8: 2027BUD_V1 | B8: V01 | C8: 12 | D8: MBWAY_PAR | E8: MBWAY | F8: BAC_MGT | G8: B3 | H8: ALT | I8: 2027 | J8: 0 | K8: 74.38 | L8: 8028.16 | M8: 597134.54 | O8: =IF(D8="","",_CALC_MOTEUR!AE8) -> 0 | P8: =IF(D8="","",_CALC_MOTEUR!AF8) -> #VALUE! | Q8: =IF(D8="","",_CALC_MOTEUR!AG8) -> #VALUE! | R8: =IF(D8="","",_CALC_MOTEUR!AH8) -> #VALUE! | S8: =IF(D8="","",R8-M8) -> #VALUE!
A9: 2027BUD_V1 | B9: V02 | C9: 12 | D9: MBWAY_PAR | E9: MBWAY | F9: BAC_MGT | G9: B3 | H9: ALT | I9: 2027 | J9: 0 | K9: 75.14 | L9: 8169.28 | M9: 613839.7 | O9: =IF(D9="","",_CALC_MOTEUR!AE9) -> 0 | P9: =IF(D9="","",_CALC_MOTEUR!AF9) -> #VALUE! | Q9: =IF(D9="","",_CALC_MOTEUR!AG9) -> #VALUE! | R9: =IF(D9="","",_CALC_MOTEUR!AH9) -> #VALUE! | S9: =IF(D9="","",R9-M9) -> #VALUE!
A10: 2027BUD_V1 | B10: V03 | C10: 12 | D10: MBWAY_PAR | E10: MBWAY | F10: BAC_MGT | G10: B3 | H10: ALT | I10: 2027 | J10: 0 | K10: 73.24 | L10: 8028.16 | M10: 587982.44 | O10: =IF(D10="","",_CALC_MOTEUR!AE10) -> 0 | P10: =IF(D10="","",_CALC_MOTEUR!AF10) -> #VALUE! | Q10: =IF(D10="","",_CALC_MOTEUR!AG10) -> #VALUE! | R10: =IF(D10="","",_CALC_MOTEUR!AH10) -> #VALUE! | S10: =IF(D10="","",R10-M10) -> #VALUE!
A11: 2027BUD_V1 | B11: V01 | C11: 12 | D11: MBWAY_PAR | E11: MBWAY | F11: MAS_MGT | G11: M1 | H11: ALT | I11: 2027 | J11: 86.701858 | K11: 86.701858 | L11: 8601.6 | M11: 753577.87 | O11: =IF(D11="","",_CALC_MOTEUR!AE11) -> #VALUE! | P11: =IF(D11="","",_CALC_MOTEUR!AF11) -> #VALUE! | Q11: =IF(D11="","",_CALC_MOTEUR!AG11) -> #VALUE! | R11: =IF(D11="","",_CALC_MOTEUR!AH11) -> #VALUE! | S11: =IF(D11="","",R11-M11) -> #VALUE!
A12: 2027BUD_V1 | B12: V02 | C12: 12 | D12: MBWAY_PAR | E12: MBWAY | F12: MAS_MGT | G12: M1 | H12: ALT | I12: 2027 | J12: 101.09633 | K12: 101.09633 | L12: 8752.8 | M12: 893974.64 | O12: =IF(D12="","",_CALC_MOTEUR!AE12) -> #VALUE! | P12: =IF(D12="","",_CALC_MOTEUR!AF12) -> #VALUE! | Q12: =IF(D12="","",_CALC_MOTEUR!AG12) -> #VALUE! | R12: =IF(D12="","",_CALC_MOTEUR!AH12) -> #VALUE! | S12: =IF(D12="","",R12-M12) -> #VALUE!
A13: 2027BUD_V1 | B13: V03 | C13: 12 | D13: MBWAY_PAR | E13: MBWAY | F13: MAS_MGT | G13: M1 | H13: ALT | I13: 2027 | J13: 70.836836 | K13: 70.836836 | L13: 8601.6 | M13: 615685.44 | O13: =IF(D13="","",_CALC_MOTEUR!AE13) -> #VALUE! | P13: =IF(D13="","",_CALC_MOTEUR!AF13) -> #VALUE! | Q13: =IF(D13="","",_CALC_MOTEUR!AG13) -> #VALUE! | R13: =IF(D13="","",_CALC_MOTEUR!AH13) -> #VALUE! | S13: =IF(D13="","",R13-M13) -> #VALUE!
... A175: 2027BUD_V1 | B175: V03 | C175: 12 | D175: TUNON_LYO | E175: TUNON | F175: BAC_TOU | G175: B3 | H175: ALT | I175: 2027 | J175: 0 | K175: 37.61 | L175: 7504.35 | M175: 282238.6 | O175: =IF(D175="","",_CALC_MOTEUR!AE175) -> 0 | P175: =IF(D175="","",_CALC_MOTEUR!AF175) -> #VALUE! | Q175: =IF(D175="","",_CALC_MOTEUR!AG175) -> #VALUE! | R175: =IF(D175="","",_CALC_MOTEUR!AH175) -> #VALUE! | S175: =IF(D175="","",R175-M175) -> #VALUE!

Sheet Compta
A1: Entity | B1: Account | C1: EXERCICE | D1: Scenario | E1: Period | F1: Amount
A2: MBWAY_PAR | B2: 7062 | C2: 2024 | D2: 2027BUD_V1 | E2: 12 | F2: 2197935
A3: MBWAY_LYO | B3: 7062 | C3: 2024 | D3: 2027BUD_V1 | E3: 12 | F3: 1748910
A4: MBWAY_NAN | B4: 7062 | C4: 2024 | D4: 2027BUD_V1 | E4: 12 | F4: 1510769
A5: MBWAY_BOR | B5: 7062 | C5: 2024 | D5: 2027BUD_V1 | E5: 12 | F5: 1240125
A6: ISCOM_PAR | B6: 7062 | C6: 2024 | D6: 2027BUD_V1 | E6: 12 | F6: 2038946
A7: ISCOM_LIL | B7: 7062 | C7: 2024 | D7: 2027BUD_V1 | E7: 12 | F7: 1227617
A8: ISCOM_TLS | B8: 7062 | C8: 2024 | D8: 2027BUD_V1 | E8: 12 | F8: 1140192
A9: IPAC_NAN | B9: 7062 | C9: 2024 | D9: 2027BUD_V1 | E9: 12 | F9: 903346
A10: IPAC_REN | B10: 7062 | C10: 2024 | D10: 2027BUD_V1 | E10: 12 | F10: 692462
A11: IPAC_MTP | B11: 7062 | C11: 2024 | D11: 2027BUD_V1 | E11: 12 | F11: 692462
A12: PIGIER_LYO | B12: 7062 | C12: 2024 | D12: 2027BUD_V1 | E12: 12 | F12: 1105509
A13: PIGIER_BOR | B13: 7062 | C13: 2024 | D13: 2027BUD_V1 | E13: 12 | F13: 796823
... A675: GRP | B675: TEC_EBITDA | C675: 2027 | D675: 2027BUD_V1 | E675: 12 | F675: 0.15

Sheet PNL
A1: ENTITY | B1: ACCOUNT | C1: EXERCICE | D1: VERSION | E1: SCENARIO | F1: PERIOD | G1: AMOUNT | H1: 🟢 AMOUNT (live) | I1: Δ vs Tagetik
A2: MBWAY_PAR | B2: 7062 | C2: 2024 | D2: ACT | E2: 2027BUD_V1 | F2: 12 | G2: 2197935 | H2: =IF(PNL!A2="","",_CALC_PNL!P2) -> 2197935 | I2: =IF(PNL!A2="","",IF(_CALC_PNL!E2=1,H2-G2,""))
A3: MBWAY_LYO | B3: 7062 | C3: 2024 | D3: ACT | E3: 2027BUD_V1 | F3: 12 | G3: 1748910 | H3: =IF(PNL!A3="","",_CALC_PNL!P3) -> 1748910 | I3: =IF(PNL!A3="","",IF(_CALC_PNL!E3=1,H3-G3,""))
A4: MBWAY_NAN | B4: 7062 | C4: 2024 | D4: ACT | E4: 2027BUD_V1 | F4: 12 | G4: 1510769 | H4: =IF(PNL!A4="","",_CALC_PNL!P4) -> 1510769 | I4: =IF(PNL!A4="","",IF(_CALC_PNL!E4=1,H4-G4,""))
A5: MBWAY_BOR | B5: 7062 | C5: 2024 | D5: ACT | E5: 2027BUD_V1 | F5: 12 | G5: 1240125 | H5: =IF(PNL!A5="","",_CALC_PNL!P5) -> 1240125 | I5: =IF(PNL!A5="","",IF(_CALC_PNL!E5=1,H5-G5,""))
A6: ISCOM_PAR | B6: 7062 | C6: 2024 | D6: ACT | E6: 2027BUD_V1 | F6: 12 | G6: 2038946 | H6: =IF(PNL!A6="","",_CALC_PNL!P6) -> 2038946 | I6: =IF(PNL!A6="","",IF(_CALC_PNL!E6=1,H6-G6,""))
A7: ISCOM_LIL | B7: 7062 | C7: 2024 | D7: ACT | E7: 2027BUD_V1 | F7: 12 | G7: 1227617 | H7: =IF(PNL!A7="","",_CALC_PNL!P7) -> 1227617 | I7: =IF(PNL!A7="","",IF(_CALC_PNL!E7=1,H7-G7,""))
A8: ISCOM_TLS | B8: 7062 | C8: 2024 | D8: ACT | E8: 2027BUD_V1 | F8: 12 | G8: 1140192 | H8: =IF(PNL!A8="","",_CALC_PNL!P8) -> 1140192 | I8: =IF(PNL!A8="","",IF(_CALC_PNL!E8=1,H8-G8,""))
A9: IPAC_NAN | B9: 7062 | C9: 2024 | D9: ACT | E9: 2027BUD_V1 | F9: 12 | G9: 903346 | H9: =IF(PNL!A9="","",_CALC_PNL!P9) -> 903346 | I9: =IF(PNL!A9="","",IF(_CALC_PNL!E9=1,H9-G9,""))
A10: IPAC_REN | B10: 7062 | C10: 2024 | D10: ACT | E10: 2027BUD_V1 | F10: 12 | G10: 692462 | H10: =IF(PNL!A10="","",_CALC_PNL!P10) -> 692462 | I10: =IF(PNL!A10="","",IF(_CALC_PNL!E10=1,H10-G10,""))
A11: IPAC_MTP | B11: 7062 | C11: 2024 | D11: ACT | E11: 2027BUD_V1 | F11: 12 | G11: 692462 | H11: =IF(PNL!A11="","",_CALC_PNL!P11) -> 692462 | I11: =IF(PNL!A11="","",IF(_CALC_PNL!E11=1,H11-G11,""))
A12: PIGIER_LYO | B12: 7062 | C12: 2024 | D12: ACT | E12: 2027BUD_V1 | F12: 12 | G12: 1105509 | H12: =IF(PNL!A12="","",_CALC_PNL!P12) -> 1105509 | I12: =IF(PNL!A12="","",IF(_CALC_PNL!E12=1,H12-G12,""))
A13: PIGIER_BOR | B13: 7062 | C13: 2024 | D13: ACT | E13: 2027BUD_V1 | F13: 12 | G13: 796823 | H13: =IF(PNL!A13="","",_CALC_PNL!P13) -> 796823 | I13: =IF(PNL!A13="","",IF(_CALC_PNL!E13=1,H13-G13,""))
... A1347: ISCOM_TLS | B1347: 6413 | C1347: 2027 | D1347: V03 | E1347: 2027BUD_V1 | F1347: 12 | G1347: 126948.63 | H1347: =IF(PNL!A1347="","",_CALC_PNL!P1347) -> #VALUE! | I1347: =IF(PNL!A1347="","",IF(_CALC_PNL!E1347=1,H1347-G1347,"")) -> #VALUE!

Sheet Allocation
A1: SCENARIO | B1: PERIODE | C1: EXERCICE | D1: ENTITY | E1: MARQUE | F1: PROGRAMME | G1: AN_ETUDE | H1: MODALITE | I1: VOL_EFF | J1: VOL_CLASS | K1: CA | L1: COST_VAC | M1: COST_PERM | N1: COST_ODIR | O1: COST_STRUCT | P1: COST_SIEGE | Q1: COST_VARIABLE | R1: COST_STRUCTURE | S1: COST_COMPLET | T1: MARGE_COMPLETE | V1: COST_VAC (live) | W1: COST_PERM | X1: COST_ODIR | Y1: COST_STRUCT | Z1: COST_HOLDING (live) | AA1: 🟢 MARGE (live) | AB1: Δ vs Tagetik | AC1: COST_MARQUE (live)
A2: 2027BUD_V1 | B2: 12 | C2: 2026 | D2: MBWAY_PAR | E2: MBWAY | F2: BAC_MGT | G2: B1 | H2: INIT | I2: 78 | J2: 3 | K2: 662220 | L2: 45273.5 | M2: 151300.5 | N2: 63168.851 | O2: 296639.1 | P2: 91236.233 | Q2: 108442.35 | R2: 539175.84 | S2: 647618.19 | T2: 14601.812 | V2: =IF(Allocation!D2="","",_CALC_ALLOC!AI2) -> 45273.5 | W2: =IF(Allocation!D2="","",_CALC_ALLOC!AJ2) -> 151300.5 | X2: =IF(Allocation!D2="","",_CALC_ALLOC!AK2) -> 51787.017 | Y2: =IF(Allocation!D2="","",_CALC_ALLOC!AL2) -> 1452771 | Z2: =IF(Allocation!D2="","",_CALC_ALLOC!AM2) -> 2891983 | AA2: =IF(Allocation!D2="","",_CALC_ALLOC!AN2) -> -4607239 | AB2: =IF(Allocation!D2="","",AA2-T2) -> -4621840.8 | AC2: =IF(Allocation!D2="","",_CALC_ALLOC!AR2) -> 676344
A3: 2027BUD_V1 | B3: 12 | C3: 2026 | D3: MBWAY_PAR | E3: MBWAY | F3: BAC_MGT | G3: B2 | H3: ALT | I3: 76 | J3: 3 | K3: 595840 | L3: 36218.8 | M3: 121040.4 | N3: 28279.162 | O3: 289032.97 | P3: 88896.842 | Q3: 64497.962 | R3: 498970.22 | S3: 563468.18 | T3: 32371.822 | V3: =IF(Allocation!D3="","",_CALC_ALLOC!AI3) -> 36218.8 | W3: =IF(Allocation!D3="","",_CALC_ALLOC!AJ3) -> 121040.4 | X3: =IF(Allocation!D3="","",_CALC_ALLOC!AK3) -> 28279.162 | Y3: =IF(Allocation!D3="","",_CALC_ALLOC!AL3) -> 0 | Z3: =IF(Allocation!D3="","",_CALC_ALLOC!AM3) -> 0 | AA3: =IF(Allocation!D3="","",_CALC_ALLOC!AN3) -> 410301.64 | AB3: =IF(Allocation!D3="","",AA3-T3) -> 377929.82 | AC3: =IF(Allocation!D3="","",_CALC_ALLOC!AR3) -> 0
A4: 2027BUD_V1 | B4: 12 | C4: 2026 | D4: MBWAY_PAR | E4: MBWAY | F4: BAC_MGT | G4: B3 | H4: ALT | I4: 74 | J4: 3 | K4: 580160 | L4: 36218.8 | M4: 121040.4 | N4: 27534.974 | O4: 281426.84 | P4: 86557.452 | Q4: 63753.774 | R4: 489024.69 | S4: 552778.47 | T4: 27381.532 | V4: =IF(Allocation!D4="","",_CALC_ALLOC!AI4) -> 36218.8 | W4: =IF(Allocation!D4="","",_CALC_ALLOC!AJ4) -> 121040.4 | X4: =IF(Allocation!D4="","",_CALC_ALLOC!AK4) -> 27534.974 | Y4: =IF(Allocation!D4="","",_CALC_ALLOC!AL4) -> 0 | Z4: =IF(Allocation!D4="","",_CALC_ALLOC!AM4) -> 0 | AA4: =IF(Allocation!D4="","",_CALC_ALLOC!AN4) -> 395365.83 | AB4: =IF(Allocation!D4="","",AA4-T4) -> 367984.29 | AC4: =IF(Allocation!D4="","",_CALC_ALLOC!AR4) -> 0
A5: 2027BUD_V1 | B5: 12 | C5: 2026 | D5: MBWAY_PAR | E5: MBWAY | F5: MAS_MGT | G5: M1 | H5: ALT | I5: 78 | J5: 3 | K5: 662220 | L5: 31691.45 | M5: 105910.35 | N5: 63168.851 | O5: 296639.1 | P5: 91236.233 | Q5: 94860.301 | R5: 493785.69 | S5: 588645.99 | T5: 73574.012 | V5: =IF(Allocation!D5="","",_CALC_ALLOC!AI5) -> 31691.45 | W5: =IF(Allocation!D5="","",_CALC_ALLOC!AJ5) -> 105910.35 | X5: =IF(Allocation!D5="","",_CALC_ALLOC!AK5) -> 74550.684 | Y5: =IF(Allocation!D5="","",_CALC_ALLOC!AL5) -> 0 | Z5: =IF(Allocation!D5="","",_CALC_ALLOC!AM5) -> 0 | AA5: =IF(Allocation!D5="","",_CALC_ALLOC!AN5) -> 450067.52 | AB5: =IF(Allocation!D5="","",AA5-T5) -> 376493.5 | AC5: =IF(Allocation!D5="","",_CALC_ALLOC!AR5) -> 0
A6: 2027BUD_V1 | B6: 12 | C6: 2026 | D6: MBWAY_PAR | E6: MBWAY | F6: MAS_MGT | G6: M2 | H6: ALT | I6: 76 | J6: 3 | K6: 638400 | L6: 31691.45 | M6: 105910.35 | N6: 28279.162 | O6: 289032.97 | P6: 88896.842 | Q6: 59970.612 | R6: 483840.17 | S6: 543810.78 | T6: 94589.222 | V6: =IF(Allocation!D6="","",_CALC_ALLOC!AI6) -> 31691.45 | W6: =IF(Allocation!D6="","",_CALC_ALLOC!AJ6) -> 105910.35 | X6: =IF(Allocation!D6="","",_CALC_ALLOC!AK6) -> 28279.162 | Y6: =IF(Allocation!D6="","",_CALC_ALLOC!AL6) -> 0 | Z6: =IF(Allocation!D6="","",_CALC_ALLOC!AM6) -> 0 | AA6: =IF(Allocation!D6="","",_CALC_ALLOC!AN6) -> 472519.04 | AB6: =IF(Allocation!D6="","",AA6-T6) -> 377929.82 | AC6: =IF(Allocation!D6="","",_CALC_ALLOC!AR6) -> 0
A7: 2027BUD_V1 | B7: 12 | C7: 2025 | D7: MBWAY_PAR | E7: MBWAY | F7: BAC_MGT | G7: B1 | H7: INIT | I7: 74 | J7: 3 | K7: 628260 | L7: 43211 | M7: 144407.5 | N7: 58773.624 | O7: 283445.96 | P7: 85831.285 | Q7: 101984.62 | R7: 513684.75 | S7: 615669.37 | T7: 12590.629 | V7: =IF(Allocation!D7="","",_CALC_ALLOC!AI7) -> 43211 | W7: =IF(Allocation!D7="","",_CALC_ALLOC!AJ7) -> 144407.5 | X7: =IF(Allocation!D7="","",_CALC_ALLOC!AK7) -> 58773.624 | Y7: =IF(Allocation!D7="","",_CALC_ALLOC!AL7) -> 0 | Z7: =IF(Allocation!D7="","",_CALC_ALLOC!AM7) -> 0 | AA7: =IF(Allocation!D7="","",_CALC_ALLOC!AN7) -> 381867.88 | AB7: =IF(Allocation!D7="","",AA7-T7) -> 369277.25 | AC7: =IF(Allocation!D7="","",_CALC_ALLOC!AR7) -> 0
A8: 2027BUD_V1 | B8: 12 | C8: 2025 | D8: MBWAY_PAR | E8: MBWAY | F8: BAC_MGT | G8: B2 | H8: ALT | I8: 72 | J8: 3 | K8: 564480 | L8: 34568.8 | M8: 115526 | N8: 26983.094 | O8: 275785.26 | P8: 83511.521 | Q8: 61551.894 | R8: 474822.78 | S8: 536374.67 | T8: 28105.326 | V8: =IF(Allocation!D8="","",_CALC_ALLOC!AI8) -> 34568.8 | W8: =IF(Allocation!D8="","",_CALC_ALLOC!AJ8) -> 115526 | X8: =IF(Allocation!D8="","",_CALC_ALLOC!AK8) -> 26983.094 | Y8: =IF(Allocation!D8="","",_CALC_ALLOC!AL8) -> 0 | Z8: =IF(Allocation!D8="","",_CALC_ALLOC!AM8) -> 0 | AA8: =IF(Allocation!D8="","",_CALC_ALLOC!AN8) -> 387402.11 | AB8: =IF(Allocation!D8="","",AA8-T8) -> 359296.78 | AC8: =IF(Allocation!D8="","",_CALC_ALLOC!AR8) -> 0
A9: 2027BUD_V1 | B9: 12 | C9: 2025 | D9: MBWAY_PAR | E9: MBWAY | F9: BAC_MGT | G9: B3 | H9: ALT | I9: 70 | J9: 3 | K9: 548800 | L9: 34568.8 | M9: 115526 | N9: 26233.564 | O9: 268124.56 | P9: 81191.756 | Q9: 60802.364 | R9: 464842.31 | S9: 525644.68 | T9: 23155.322 | V9: =IF(Allocation!D9="","",_CALC_ALLOC!AI9) -> 34568.8 | W9: =IF(Allocation!D9="","",_CALC_ALLOC!AJ9) -> 115526 | X9: =IF(Allocation!D9="","",_CALC_ALLOC!AK9) -> 26233.564 | Y9: =IF(Allocation!D9="","",_CALC_ALLOC!AL9) -> 0 | Z9: =IF(Allocation!D9="","",_CALC_ALLOC!AM9) -> 0 | AA9: =IF(Allocation!D9="","",_CALC_ALLOC!AN9) -> 372471.64 | AB9: =IF(Allocation!D9="","",AA9-T9) -> 349316.31 | AC9: =IF(Allocation!D9="","",_CALC_ALLOC!AR9) -> 0
A10: 2027BUD_V1 | B10: 12 | C10: 2025 | D10: MBWAY_PAR | E10: MBWAY | F10: MAS_MGT | G10: M1 | H10: ALT | I10: 74 | J10: 3 | K10: 628260 | L10: 30247.7 | M10: 101085.25 | N10: 58773.624 | O10: 283445.96 | P10: 85831.285 | Q10: 89021.324 | R10: 470362.5 | S10: 559383.82 | T10: 68876.179 | V10: =IF(Allocation!D10="","",_CALC_ALLOC!AI10) -> 30247.7 | W10: =IF(Allocation!D10="","",_CALC_ALLOC!AJ10) -> 101085.25 | X10: =IF(Allocation!D10="","",_CALC_ALLOC!AK10) -> 58773.624 | Y10: =IF(Allocation!D10="","",_CALC_ALLOC!AL10) -> 0 | Z10: =IF(Allocation!D10="","",_CALC_ALLOC!AM10) -> 0 | AA10: =IF(Allocation!D10="","",_CALC_ALLOC!AN10) -> 438153.43 | AB10: =IF(Allocation!D10="","",AA10-T10) -> 369277.25 | AC10: =IF(Allocation!D10="","",_CALC_ALLOC!AR10) -> 0
A11: 2027BUD_V1 | B11: 12 | C11: 2025 | D11: MBWAY_PAR | E11: MBWAY | F11: MAS_MGT | G11: M2 | H11: ALT | I11: 72 | J11: 3 | K11: 604800 | L11: 30247.7 | M11: 101085.25 | N11: 26983.094 | O11: 275785.26 | P11: 83511.521 | Q11: 57230.794 | R11: 460382.03 | S11: 517612.82 | T11: 87187.176 | V11: =IF(Allocation!D11="","",_CALC_ALLOC!AI11) -> 30247.7 | W11: =IF(Allocation!D11="","",_CALC_ALLOC!AJ11) -> 101085.25 | X11: =IF(Allocation!D11="","",_CALC_ALLOC!AK11) -> 26983.094 | Y11: =IF(Allocation!D11="","",_CALC_ALLOC!AL11) -> 0 | Z11: =IF(Allocation!D11="","",_CALC_ALLOC!AM11) -> 0 | AA11: =IF(Allocation!D11="","",_CALC_ALLOC!AN11) -> 446483.96 | AB11: =IF(Allocation!D11="","",AA11-T11) -> 359296.78 | AC11: =IF(Allocation!D11="","",_CALC_ALLOC!AR11) -> 0
A12: 2027BUD_V1 | B12: 12 | C12: 2024 | D12: MBWAY_PAR | E12: MBWAY | F12: BAC_MGT | G12: B1 | H12: INIT | I12: 69 | J12: 3 | K12: 585810 | L12: 41317.75 | M12: 138080.5 | N12: 54544.529 | O12: 269066.31 | P12: 79748.03 | Q12: 95862.279 | R12: 486894.84 | S12: 582757.12 | T12: 3052.8789 | V12: =IF(Allocation!D12="","",_CALC_ALLOC!AI12) -> 41317.75 | W12: =IF(Allocation!D12="","",_CALC_ALLOC!AJ12) -> 138080.5 | X12: =IF(Allocation!D12="","",_CALC_ALLOC!AK12) -> 54544.529 | Y12: =IF(Allocation!D12="","",_CALC_ALLOC!AL12) -> 0 | Z12: =IF(Allocation!D12="","",_CALC_ALLOC!AM12) -> 0 | AA12: =IF(Allocation!D12="","",_CALC_ALLOC!AN12) -> 351867.22 | AB12: =IF(Allocation!D12="","",AA12-T12) -> 348814.34 | AC12: =IF(Allocation!D12="","",_CALC_ALLOC!AR12) -> 0
A13: 2027BUD_V1 | B13: 12 | C13: 2024 | D13: MBWAY_PAR | E13: MBWAY | F13: BAC_MGT | G13: B2 | H13: ALT | I13: 68 | J13: 3 | K13: 533120 | L13: 33054.2 | M13: 110464.4 | N13: 25944 | O13: 265166.8 | P13: 78592.261 | Q13: 58998.2 | R13: 454223.46 | S13: 513221.66 | T13: 19898.339 | V13: =IF(Allocation!D13="","",_CALC_ALLOC!AI13) -> 33054.2 | W13: =IF(Allocation!D13="","",_CALC_ALLOC!AJ13) -> 110464.4 | X13: =IF(Allocation!D13="","",_CALC_ALLOC!AK13) -> 25944 | Y13: =IF(Allocation!D13="","",_CALC_ALLOC!AL13) -> 0 | Z13: =IF(Allocation!D13="","",_CALC_ALLOC!AM13) -> 0 | AA13: =IF(Allocation!D13="","",_CALC_ALLOC!AN13) -> 363657.4 | AB13: =IF(Allocation!D13="","",AA13-T13) -> 343759.06 | AC13: =IF(Allocation!D13="","",_CALC_ALLOC!AR13) -> 0
... A175: 2027BUD_V1 | B175: 12 | C175: 2024 | D175: TUNON_LYO | E175: TUNON | F175: BAC_TOU | G175: B3 | H175: ALT | I175: 34 | J175: 2 | K175: 249900 | L175: 22036 | M175: 50913.667 | N175: 12865.276 | O175: 99769.6 | P175: 41399.713 | Q175: 34901.276 | R175: 192082.98 | S175: 226984.26 | T175: 22915.744 | V175: =IF(Allocation!D175="","",_CALC_ALLOC!AI175) -> 22036 | W175: =IF(Allocation!D175="","",_CALC_ALLOC!AJ175) -> 50913.667 | X175: =IF(Allocation!D175="","",_CALC_ALLOC!AK175) -> 12865.276 | Y175: =IF(Allocation!D175="","",_CALC_ALLOC!AL175) -> 0 | Z175: =IF(Allocation!D175="","",_CALC_ALLOC!AM175) -> 0 | AA175: =IF(Allocation!D175="","",_CALC_ALLOC!AN175) -> 164085.06 | AB175: =IF(Allocation!D175="","",AA175-T175) -> 141169.31 | AC175: =IF(Allocation!D175="","",_CALC_ALLOC!AR175) -> 0

Sheet _CALC_MOTEUR
A1: KENT | B1: KVER | C1: KPROG | D1: KAN | E1: KMOD | F1: KMARQ | G1: VOL_LEAD | H1: VOL_EFF_INF | I1: REV_STUD | J1: RLC | K1: RCA | L1: YLD | M1: PASSAGE | N1: IS_ENTRY | O1: ORG_REF | P1: PAID_REF | Q1: LEAD_REF | R1: REND_ACQ | S1: REND_BRAND | T1: REJOUE | U1: BUD_REF | V1: ACQ | W1: BRAND | X1: PRICE | Y1: GLC | Z1: GCV | AA1: PASS | AB1: FEE | AC1: PRICE_COEF | AD1: NOUV_CALC | AE1: NOUVEAUX | AF1: EFFECTIF | AG1: PRIX | AH1: CA | AJ1: ■ VIOLET = colonne branchee sur une saisie (cad / Pilotage / 3_Allocation) -> a recabler cote Tagetik
A2: =IF(Moteur!D2="","",Moteur!D2) -> MBWAY_PAR | B2: =IF(Moteur!B2="","",Moteur!B2) -> V01 | C2: =IF(Moteur!F2="","",Moteur!F2) -> BAC_MGT | D2: =IF(Moteur!G2="","",Moteur!G2) -> B1 | E2: =IF(Moteur!H2="","",Moteur!H2) -> INIT | F2: =IF(Moteur!E2="","",Moteur!E2) -> MBWAY | G2: =IF($A2="","",_xlfn.SUMIFS(Socle!$H$1:$H$448,Socle!$C$1:$C$448,$A2,Socle!$D$1:$D$448,$C2,Socle!$E$1:$E$448,$D2,Socle!$F$1:$F$448,$E2,Socle!$G$1:$G$448,"2026")) -> 646 | H2: =IF($A2="","",_xlfn.SUMIFS(Socle!$N$1:$N$448,Socle!$C$1:$C$448,$A2,Socle!$D$1:$D$448,$C2,Socle!$E$1:$E$448,$D2,Socle!$F$1:$F$448,$E2,Socle!$G$1:$G$448,"2026")) -> 0 | I2: =IF($A2="","",_xlfn.SUMIFS(Socle!$P$1:$P$448,Socle!$C$1:$C$448,$A2,Socle!$D$1:$D$448,$C2,Socle!$E$1:$E$448,$D2,Socle!$F$1:$F$448,$E2,Socle!$G$1:$G$448,"2026")) -> 8400 | J2: =IF($A2="","",_xlfn.SUMIFS(Socle!$W$1:$W$448,Socle!$C$1:$C$448,$A2,Socle!$D$1:$D$448,$C2,Socle!$E$1:$E$448,$D2,Socle!$F$1:$F$448,$E2,Socle!$G$1:$G$448,"2026")) -> 0.28018576 | K2: =IF($A2="","",_xlfn.SUMIFS(Socle!$X$1:$X$448,Socle!$C$1:$C$448,$A2,Socle!$D$1:$D$448,$C2,Socle!$E$1:$E$448,$D2,Socle!$F$1:$F$448,$E2,Socle!$G$1:$G$448,"2026")) -> 0.71823204 | L2: =IF($A2="","",_xlfn.SUMIFS(Socle!$Y$1:$Y$448,Socle!$C$1:$C$448,$A2,Socle!$D$1:$D$448,$C2,Socle!$E$1:$E$448,$D2,Socle!$F$1:$F$448,$E2,Socle!$G$1:$G$448,"2026")) -> 0.6 | M2: =IF($A2="","",_xlfn.SUMIFS(Socle!$V$1:$V$448,Socle!$C$1:$C$448,$A2,Socle!$D$1:$D$448,$C2,Socle!$E$1:$E$448,$D2,Socle!$F$1:$F$448,$E2,Socle!$G$1:$G$448,"2026")) -> 0 | N2: =IF($A2="","",IF(OR($D2="B1",$D2="M1",$D2="BTS1"),1,0)) -> 1 | O2: =IF($A2="","",_xlfn.SUMIFS(Campagne!$D$1:$D$128,Campagne!$C$1:$C$128,$A2)) -> 711 | P2: =IF($A2="","",_xlfn.SUMIFS(Campagne!$E$1:$E$128,Campagne!$C$1:$C$128,$A2)) -> 1265 | Q2: =IF($A2="","",_xlfn.SUMIFS(Campagne!$F$1:$F$128,Campagne!$C$1:$C$128,$A2)) -> 1976 | R2: =IF($A2="","",_xlfn.SUMIFS(Campagne!$K$1:$K$128,Campagne!$C$1:$C$128,$A2)) -> 0.46359591 | S2: =IF($A2="","",_xlfn.SUMIFS(Campagne!$M$1:$M$128,Campagne!$C$1:$C$128,$A2)) -> 0.30805415 | T2: =IF($A2="","",_xlfn.SUMIFS(PIL!$K$15:$K$28,PIL!$A$15:$A$28,$A2)*_xlfn.SUMIFS(PIL!$J$15:$J$28,PIL!$A$15:$A$28,$A2)*(SUM(PIL!$K$15:$K$28)/SUMPRODUCT(PIL!$K$15:$K$28,PIL!$J$15:$J$28))) -> 68291 | U2: =IF($A2="","",_xlfn.SUMIFS(PIL!$K$15:$K$28,PIL!$A$15:$A$28,$A2)) -> 68291 | V2: 1000 | W2: 1000 | X2: 1000 | Y2: 1000 | Z2: 1000 | AA2: 1000 | AB2: 90 | AC2: 1000 | AD2: =IF($A2="","",($O2*(1+$W2)^$S2+$P2*_xlfn.IFERROR((($T2/$U2)*(1+$V2))^$R2,0))*_xlfn.IFERROR($G2/$Q2,0)*($J2+$Y2)*$K2*($L2+$Z2)) -> 8.7179354e+09 | AE2: =IF($A2="","",IF($N2=1,$AD2,0)) -> 8.7179354e+09 | AF2: =IF($A2="","",IF($N2=1,$AD2,$H2*($M2+$AA2))) -> 8.7179354e+09 | AG2: =IF($A2="","",$I2*(1+$X2*$AC2)) -> 8400008400 | AH2: =IF($A2="","",$AF2*$AG2+$AE2*$AB2) -> 7.3230732e+19
A3: =IF(Moteur!D3="","",Moteur!D3) -> MBWAY_PAR | B3: =IF(Moteur!B3="","",Moteur!B3) -> V02 | C3: =IF(Moteur!F3="","",Moteur!F3) -> BAC_MGT | D3: =IF(Moteur!G3="","",Moteur!G3) -> B1 | E3: =IF(Moteur!H3="","",Moteur!H3) -> INIT | F3: =IF(Moteur!E3="","",Moteur!E3) -> MBWAY | G3: =IF($A3="","",_xlfn.SUMIFS(Socle!$H$1:$H$448,Socle!$C$1:$C$448,$A3,Socle!$D$1:$D$448,$C3,Socle!$E$1:$E$448,$D3,Socle!$F$1:$F$448,$E3,Socle!$G$1:$G$448,"2026")) -> 646 | H3: =IF($A3="","",_xlfn.SUMIFS(Socle!$N$1:$N$448,Socle!$C$1:$C$448,$A3,Socle!$D$1:$D$448,$C3,Socle!$E$1:$E$448,$D3,Socle!$F$1:$F$448,$E3,Socle!$G$1:$G$448,"2026")) -> 0 | I3: =IF($A3="","",_xlfn.SUMIFS(Socle!$P$1:$P$448,Socle!$C$1:$C$448,$A3,Socle!$D$1:$D$448,$C3,Socle!$E$1:$E$448,$D3,Socle!$F$1:$F$448,$E3,Socle!$G$1:$G$448,"2026")) -> 8400 | J3: =IF($A3="","",_xlfn.SUMIFS(Socle!$W$1:$W$448,Socle!$C$1:$C$448,$A3,Socle!$D$1:$D$448,$C3,Socle!$E$1:$E$448,$D3,Socle!$F$1:$F$448,$E3,Socle!$G$1:$G$448,"2026")) -> 0.28018576 | K3: =IF($A3="","",_xlfn.SUMIFS(Socle!$X$1:$X$448,Socle!$C$1:$C$448,$A3,Socle!$D$1:$D$448,$C3,Socle!$E$1:$E$448,$D3,Socle!$F$1:$F$448,$E3,Socle!$G$1:$G$448,"2026")) -> 0.71823204 | L3: =IF($A3="","",_xlfn.SUMIFS(Socle!$Y$1:$Y$448,Socle!$C$1:$C$448,$A3,Socle!$D$1:$D$448,$C3,Socle!$E$1:$E$448,$D3,Socle!$F$1:$F$448,$E3,Socle!$G$1:$G$448,"2026")) -> 0.6 | M3: =IF($A3="","",_xlfn.SUMIFS(Socle!$V$1:$V$448,Socle!$C$1:$C$448,$A3,Socle!$D$1:$D$448,$C3,Socle!$E$1:$E$448,$D3,Socle!$F$1:$F$448,$E3,Socle!$G$1:$G$448,"2026")) -> 0 | N3: =IF($A3="","",IF(OR($D3="B1",$D3="M1",$D3="BTS1"),1,0)) -> 1 | O3: =IF($A3="","",_xlfn.SUMIFS(Campagne!$D$1:$D$128,Campagne!$C$1:$C$128,$A3)) -> 711 | P3: =IF($A3="","",_xlfn.SUMIFS(Campagne!$E$1:$E$128,Campagne!$C$1:$C$128,$A3)) -> 1265 | Q3: =IF($A3="","",_xlfn.SUMIFS(Campagne!$F$1:$F$128,Campagne!$C$1:$C$128,$A3)) -> 1976 | R3: =IF($A3="","",_xlfn.SUMIFS(Campagne!$K$1:$K$128,Campagne!$C$1:$C$128,$A3)) -> 0.46359591 | S3: =IF($A3="","",_xlfn.SUMIFS(Campagne!$M$1:$M$128,Campagne!$C$1:$C$128,$A3)) -> 0.30805415 | T3: =IF($A3="","",_xlfn.SUMIFS(PIL!$K$15:$K$28,PIL!$A$15:$A$28,$A3)*_xlfn.SUMIFS(PIL!$J$15:$J$28,PIL!$A$15:$A$28,$A3)*(SUM(PIL!$K$15:$K$28)/SUMPRODUCT(PIL!$K$15:$K$28,PIL!$J$15:$J$28))) -> 68291 | U3: =IF($A3="","",_xlfn.SUMIFS(PIL!$K$15:$K$28,PIL!$A$15:$A$28,$A3)) -> 68291 | AD3: =IF($A3="","",($O3*(1+$W3)^$S3+$P3*_xlfn.IFERROR((($T3/$U3)*(1+$V3))^$R3,0))*_xlfn.IFERROR($G3/$Q3,0)*($J3+$Y3)*$K3*($L3+$Z3)) -> #VALUE! | AE3: =IF($A3="","",IF($N3=1,$AD3,0)) -> #VALUE! | AF3: =IF($A3="","",IF($N3=1,$AD3,$H3*($M3+$AA3))) -> #VALUE! | AG3: =IF($A3="","",$I3*(1+$X3*$AC3)) -> #VALUE! | AH3: =IF($A3="","",$AF3*$AG3+$AE3*$AB3) -> #VALUE!
A4: =IF(Moteur!D4="","",Moteur!D4) -> MBWAY_PAR | B4: =IF(Moteur!B4="","",Moteur!B4) -> V03 | C4: =IF(Moteur!F4="","",Moteur!F4) -> BAC_MGT | D4: =IF(Moteur!G4="","",Moteur!G4) -> B1 | E4: =IF(Moteur!H4="","",Moteur!H4) -> INIT | F4: =IF(Moteur!E4="","",Moteur!E4) -> MBWAY | G4: =IF($A4="","",_xlfn.SUMIFS(Socle!$H$1:$H$448,Socle!$C$1:$C$448,$A4,Socle!$D$1:$D$448,$C4,Socle!$E$1:$E$448,$D4,Socle!$F$1:$F$448,$E4,Socle!$G$1:$G$448,"2026")) -> 646 | H4: =IF($A4="","",_xlfn.SUMIFS(Socle!$N$1:$N$448,Socle!$C$1:$C$448,$A4,Socle!$D$1:$D$448,$C4,Socle!$E$1:$E$448,$D4,Socle!$F$1:$F$448,$E4,Socle!$G$1:$G$448,"2026")) -> 0 | I4: =IF($A4="","",_xlfn.SUMIFS(Socle!$P$1:$P$448,Socle!$C$1:$C$448,$A4,Socle!$D$1:$D$448,$C4,Socle!$E$1:$E$448,$D4,Socle!$F$1:$F$448,$E4,Socle!$G$1:$G$448,"2026")) -> 8400 | J4: =IF($A4="","",_xlfn.SUMIFS(Socle!$W$1:$W$448,Socle!$C$1:$C$448,$A4,Socle!$D$1:$D$448,$C4,Socle!$E$1:$E$448,$D4,Socle!$F$1:$F$448,$E4,Socle!$G$1:$G$448,"2026")) -> 0.28018576 | K4: =IF($A4="","",_xlfn.SUMIFS(Socle!$X$1:$X$448,Socle!$C$1:$C$448,$A4,Socle!$D$1:$D$448,$C4,Socle!$E$1:$E$448,$D4,Socle!$F$1:$F$448,$E4,Socle!$G$1:$G$448,"2026")) -> 0.71823204 | L4: =IF($A4="","",_xlfn.SUMIFS(Socle!$Y$1:$Y$448,Socle!$C$1:$C$448,$A4,Socle!$D$1:$D$448,$C4,Socle!$E$1:$E$448,$D4,Socle!$F$1:$F$448,$E4,Socle!$G$1:$G$448,"2026")) -> 0.6 | M4: =IF($A4="","",_xlfn.SUMIFS(Socle!$V$1:$V$448,Socle!$C$1:$C$448,$A4,Socle!$D$1:$D$448,$C4,Socle!$E$1:$E$448,$D4,Socle!$F$1:$F$448,$E4,Socle!$G$1:$G$448,"2026")) -> 0 | N4: =IF($A4="","",IF(OR($D4="B1",$D4="M1",$D4="BTS1"),1,0)) -> 1 | O4: =IF($A4="","",_xlfn.SUMIFS(Campagne!$D$1:$D$128,Campagne!$C$1:$C$128,$A4)) -> 711 | P4: =IF($A4="","",_xlfn.SUMIFS(Campagne!$E$1:$E$128,Campagne!$C$1:$C$128,$A4)) -> 1265 | Q4: =IF($A4="","",_xlfn.SUMIFS(Campagne!$F$1:$F$128,Campagne!$C$1:$C$128,$A4)) -> 1976 | R4: =IF($A4="","",_xlfn.SUMIFS(Campagne!$K$1:$K$128,Campagne!$C$1:$C$128,$A4)) -> 0.46359591 | S4: =IF($A4="","",_xlfn.SUMIFS(Campagne!$M$1:$M$128,Campagne!$C$1:$C$128,$A4)) -> 0.30805415 | T4: =IF($A4="","",_xlfn.SUMIFS(PIL!$K$15:$K$28,PIL!$A$15:$A$28,$A4)*_xlfn.SUMIFS(PIL!$J$15:$J$28,PIL!$A$15:$A$28,$A4)*(SUM(PIL!$K$15:$K$28)/SUMPRODUCT(PIL!$K$15:$K$28,PIL!$J$15:$J$28))) -> 68291 | U4: =IF($A4="","",_xlfn.SUMIFS(PIL!$K$15:$K$28,PIL!$A$15:$A$28,$A4)) -> 68291 | AD4: =IF($A4="","",($O4*(1+$W4)^$S4+$P4*_xlfn.IFERROR((($T4/$U4)*(1+$V4))^$R4,0))*_xlfn.IFERROR($G4/$Q4,0)*($J4+$Y4)*$K4*($L4+$Z4)) -> #VALUE! | AE4: =IF($A4="","",IF($N4=1,$AD4,0)) -> #VALUE! | AF4: =IF($A4="","",IF($N4=1,$AD4,$H4*($M4+$AA4))) -> #VALUE! | AG4: =IF($A4="","",$I4*(1+$X4*$AC4)) -> #VALUE! | AH4: =IF($A4="","",$AF4*$AG4+$AE4*$AB4) -> #VALUE!
A5: =IF(Moteur!D5="","",Moteur!D5) -> MBWAY_PAR | B5: =IF(Moteur!B5="","",Moteur!B5) -> V01 | C5: =IF(Moteur!F5="","",Moteur!F5) -> BAC_MGT | D5: =IF(Moteur!G5="","",Moteur!G5) -> B2 | E5: =IF(Moteur!H5="","",Moteur!H5) -> ALT | F5: =IF(Moteur!E5="","",Moteur!E5) -> MBWAY | G5: =IF($A5="","",_xlfn.SUMIFS(Socle!$H$1:$H$448,Socle!$C$1:$C$448,$A5,Socle!$D$1:$D$448,$C5,Socle!$E$1:$E$448,$D5,Socle!$F$1:$F$448,$E5,Socle!$G$1:$G$448,"2026")) -> 0 | H5: =IF($A5="","",_xlfn.SUMIFS(Socle!$N$1:$N$448,Socle!$C$1:$C$448,$A5,Socle!$D$1:$D$448,$C5,Socle!$E$1:$E$448,$D5,Socle!$F$1:$F$448,$E5,Socle!$G$1:$G$448,"2026")) -> 156 | I5: =IF($A5="","",_xlfn.SUMIFS(Socle!$P$1:$P$448,Socle!$C$1:$C$448,$A5,Socle!$D$1:$D$448,$C5,Socle!$E$1:$E$448,$D5,Socle!$F$1:$F$448,$E5,Socle!$G$1:$G$448,"2026")) -> 15680 | J5: =IF($A5="","",_xlfn.SUMIFS(Socle!$W$1:$W$448,Socle!$C$1:$C$448,$A5,Socle!$D$1:$D$448,$C5,Socle!$E$1:$E$448,$D5,Socle!$F$1:$F$448,$E5,Socle!$G$1:$G$448,"2026")) -> 0 | K5: =IF($A5="","",_xlfn.SUMIFS(Socle!$X$1:$X$448,Socle!$C$1:$C$448,$A5,Socle!$D$1:$D$448,$C5,Socle!$E$1:$E$448,$D5,Socle!$F$1:$F$448,$E5,Socle!$G$1:$G$448,"2026")) -> 0 | L5: =IF($A5="","",_xlfn.SUMIFS(Socle!$Y$1:$Y$448,Socle!$C$1:$C$448,$A5,Socle!$D$1:$D$448,$C5,Socle!$E$1:$E$448,$D5,Socle!$F$1:$F$448,$E5,Socle!$G$1:$G$448,"2026")) -> 0 | M5: =IF($A5="","",_xlfn.SUMIFS(Socle!$V$1:$V$448,Socle!$C$1:$C$448,$A5,Socle!$D$1:$D$448,$C5,Socle!$E$1:$E$448,$D5,Socle!$F$1:$F$448,$E5,Socle!$G$1:$G$448,"2026")) -> 1.9487179 | N5: =IF($A5="","",IF(OR($D5="B1",$D5="M1",$D5="BTS1"),1,0)) -> 0 | O5: =IF($A5="","",_xlfn.SUMIFS(Campagne!$D$1:$D$128,Campagne!$C$1:$C$128,$A5)) -> 711 | P5: =IF($A5="","",_xlfn.SUMIFS(Campagne!$E$1:$E$128,Campagne!$C$1:$C$128,$A5)) -> 1265 | Q5: =IF($A5="","",_xlfn.SUMIFS(Campagne!$F$1:$F$128,Campagne!$C$1:$C$128,$A5)) -> 1976 | R5: =IF($A5="","",_xlfn.SUMIFS(Campagne!$K$1:$K$128,Campagne!$C$1:$C$128,$A5)) -> 0.46359591 | S5: =IF($A5="","",_xlfn.SUMIFS(Campagne!$M$1:$M$128,Campagne!$C$1:$C$128,$A5)) -> 0.30805415 | T5: =IF($A5="","",_xlfn.SUMIFS(PIL!$K$15:$K$28,PIL!$A$15:$A$28,$A5)*_xlfn.SUMIFS(PIL!$J$15:$J$28,PIL!$A$15:$A$28,$A5)*(SUM(PIL!$K$15:$K$28)/SUMPRODUCT(PIL!$K$15:$K$28,PIL!$J$15:$J$28))) -> 68291 | U5: =IF($A5="","",_xlfn.SUMIFS(PIL!$K$15:$K$28,PIL!$A$15:$A$28,$A5)) -> 68291 | AD5: =IF($A5="","",($O5*(1+$W5)^$S5+$P5*_xlfn.IFERROR((($T5/$U5)*(1+$V5))^$R5,0))*_xlfn.IFERROR($G5/$Q5,0)*($J5+$Y5)*$K5*($L5+$Z5)) -> #VALUE! | AE5: =IF($A5="","",IF($N5=1,$AD5,0)) -> 0 | AF5: =IF($A5="","",IF($N5=1,$AD5,$H5*($M5+$AA5))) -> #VALUE! | AG5: =IF($A5="","",$I5*(1+$X5*$AC5)) -> #VALUE! | AH5: =IF($A5="","",$AF5*$AG5+$AE5*$AB5) -> #VALUE!
